{"id":1310671745,"type":"Feature","properties":{"edtf:cessation":"uuuu","edtf:inception":"uuuu","geom:area":0,"geom:area_square_m":0,"geom:bbox":"22.12444,58.05889,22.12444,58.05889","geom:latitude":58.05889,"geom:longitude":22.12444,"gn:admin1_code":"14.0","gn:admin2_code":"714.0","gn:admin3_code":"9627.0","gn:asciiname":"Ula","gn:country_code":"EE","gn:dem":13,"gn:feature_class":"P","gn:feature_code":"PPL","gn:geonameid":8619953,"gn:latitude":58.05889,"gn:longitude":22.12444,"gn:modification_date":"2017-11-25","gn:name":"Ula","gn:population":0,"gn:timezone":"Europe/Tallinn","iso:country":"EE","lbl:bbox":"22.10444,58.03889,22.14444,58.07889","lbl:max_zoom":18,"lbl:min_zoom":13.5,"mz:hierarchy_label":1,"mz:is_current":1,"mz:min_zoom":12,"name:ara_x_preferred":["أولا"],"name:bel_x_preferred":["Ула"],"name:ben_x_preferred":["উলা"],"name:deu_x_preferred":["Ūla"],"name:ell_x_preferred":["Ούλα"],"name:est_x_preferred":["Ula"],"name:fas_x_preferred":["اولا"],"name:fra_x_preferred":["Oulla"],"name:fra_x_variant":["Ula"],"name:heb_x_preferred":["אוּלה"],"name:hin_x_preferred":["उला"],"name:hun_x_preferred":["Ula"],"name:ind_x_preferred":["Ula"],"name:ita_x_preferred":["Ula"],"name:jpn_x_preferred":["エーラ川"],"name:kor_x_preferred":["울라"],"name:nld_x_preferred":["Ūla"],"name:nld_x_variant":["Ula"],"name:nno_x_preferred":["Ula"],"name:nor_x_preferred":["Ula"],"name:pol_x_preferred":["Ula"],"name:por_x_preferred":["Ūla"],"name:rus_x_preferred":["Ула"],"name:spa_x_preferred":["Ula"],"name:swe_x_preferred":["Ula"],"name:tur_x_preferred":["Ula"],"name:ukr_x_preferred":["Ула"],"name:urd_x_preferred":["اولا"],"name:vie_x_preferred":["Sông Ula"],"name:vol_x_preferred":["Ula"],"name:zho_cn_x_preferred":["乌拉河"],"name:zho_tw_x_preferred":["烏拉河"],"src:geom":"geonames","wof:belongsto":[85682947,102191581,1713308667,85633135,1713305627],"wof:breaches":[],"wof:concordances":{"gn:id":8619953},"wof:country":"EE","wof:geomhash":"1ac55aa3170e689f41af3ac117487e65","wof:hierarchy":[{"continent_id":102191581,"country_id":85633135,"county_id":1713305627,"localadmin_id":1713308667,"locality_id":1310671745,"region_id":85682947}],"wof:id":1310671745,"wof:lang_x_official":["est"],"wof:lang_x_spoken":["est"],"wof:lastmodified":1636502242,"wof:name":"Ula","wof:parent_id":1713308667,"wof:placetype":"locality","wof:repo":"whosonfirst-data-admin-ee","wof:superseded_by":[],"wof:supersedes":[],"wof:tags":[]},"bbox":[22.12444,58.05889,22.12444,58.05889],"geometry":{"coordinates":[22.12444,58.05889],"type":"Point"}}