{"id":1243278103,"type":"Feature","properties":{"edtf:cessation":"uuuu","edtf:inception":"uuuu","geom:area":0,"geom:area_square_m":0,"geom:bbox":"24.24778,59.16389,24.24778,59.16389","geom:latitude":59.16389,"geom:longitude":24.24778,"gn:admin1_code":"1.0","gn:admin2_code":"726.0","gn:admin3_code":"1449.0","gn:asciiname":"Aude","gn:country_code":"EE","gn:dem":34,"gn:feature_class":"P","gn:feature_code":"PPL","gn:geonameid":592354,"gn:latitude":59.16389,"gn:longitude":24.24778,"gn:modification_date":"2017-11-25","gn:name":"Aude","gn:population":0,"gn:timezone":"Europe/Tallinn","iso:country":"EE","lbl:bbox":"24.22778,59.14389,24.26778,59.18389","lbl:max_zoom":18,"lbl:min_zoom":13.5,"mz:hierarchy_label":1,"mz:is_current":1,"mz:min_zoom":12,"name:est_x_preferred":["Aude"],"name:fra_x_preferred":["Aude"],"name:hye_x_preferred":["Աուդե"],"name:pol_x_preferred":["Aude"],"name:spa_x_preferred":["Aude"],"name:ukr_x_preferred":["Ауде"],"name:vol_x_preferred":["Aude"],"src:geom":"geonames","wof:belongsto":[85683055,102191581,1713312825,85633135,1713305739],"wof:breaches":[],"wof:concordances":{"gn:id":592354,"wk:page":"Aude%2C_Estonia"},"wof:coterminous":[1713312825],"wof:country":"EE","wof:geomhash":"abf69d923c87254017f1ea996c6581c9","wof:hierarchy":[{"continent_id":102191581,"country_id":85633135,"county_id":1713305739,"localadmin_id":1713312825,"locality_id":1243278103,"region_id":85683055}],"wof:id":1243278103,"wof:lang_x_official":["est"],"wof:lang_x_spoken":["est"],"wof:lastmodified":1596663248,"wof:name":"Aude","wof:parent_id":1713312825,"wof:placetype":"locality","wof:repo":"whosonfirst-data-admin-ee","wof:superseded_by":[],"wof:supersedes":[],"wof:tags":[]},"bbox":[24.24778,59.16389,24.24778,59.16389],"geometry":{"coordinates":[24.24778,59.16389],"type":"Point"}}