{"id":1343728419,"type":"Feature","properties":{"edtf:cessation":"uuuu","edtf:inception":"uuuu","geom:area":0,"geom:area_square_m":0,"geom:bbox":"26.60139,58.25944,26.60139,58.25944","geom:latitude":58.25944,"geom:longitude":26.60139,"gn:admin1_code":"18.0","gn:admin2_code":"528.0","gn:admin3_code":"8698.0","gn:asciiname":"Unipiha","gn:cc2":"EE","gn:country_code":"EE","gn:dem":69,"gn:feature_class":"P","gn:feature_code":"PPL","gn:geonameid":588056,"gn:latitude":58.25944,"gn:longitude":26.60139,"gn:modification_date":"2017-11-25","gn:name":"Unipiha","gn:population":0,"gn:timezone":"Europe/Tallinn","iso:country":"EE","lbl:bbox":"26.58139,58.23944,26.62139,58.27944","lbl:max_zoom":18,"lbl:min_zoom":13.5,"mz:hierarchy_label":1,"mz:is_current":1,"mz:min_zoom":12,"name:est_x_preferred":["Unipiha"],"name:fra_x_preferred":["Unipiha"],"name:hye_x_preferred":["Ունիպիհա"],"name:nld_x_preferred":["Unipiha"],"name:pol_x_preferred":["Unipiha"],"name:spa_x_preferred":["Unipiha"],"name:ukr_x_preferred":["Уніпіга"],"name:und_x_variant":["Myza Unipikha"],"name:vol_x_preferred":["Unipiha"],"src:geom":"geonames","wof:belongsto":[85682995,102191581,1713315201,85633135,1713305715],"wof:breaches":[],"wof:concordances":{"gn:id":588056,"wk:page":"Unipiha"},"wof:coterminous":[1713315201],"wof:country":"EE","wof:geomhash":"31a74474780594867ada5968ca77a2dc","wof:hierarchy":[{"continent_id":102191581,"country_id":85633135,"county_id":1713305715,"localadmin_id":1713315201,"locality_id":1343728419,"region_id":85682995}],"wof:id":1343728419,"wof:lang_x_official":["est"],"wof:lang_x_spoken":["est"],"wof:lastmodified":1596676767,"wof:name":"Unipiha","wof:parent_id":1713315201,"wof:placetype":"locality","wof:repo":"whosonfirst-data-admin-ee","wof:superseded_by":[],"wof:supersedes":[],"wof:tags":[]},"bbox":[26.60139,58.25944,26.60139,58.25944],"geometry":{"coordinates":[26.60139,58.25944],"type":"Point"}}