{"id":1260262295,"type":"Feature","properties":{"edtf:cessation":"uuuu","edtf:inception":"uuuu","geom:area":0,"geom:area_square_m":0,"geom:bbox":"24.46528,58.97861,24.46528,58.97861","geom:latitude":58.97861,"geom:longitude":24.46528,"gn:admin1_code":"13.0","gn:admin2_code":"503.0","gn:admin3_code":"8882.0","gn:asciiname":"Vaimoisa","gn:cc2":"EE","gn:country_code":"EE","gn:dem":48,"gn:feature_class":"P","gn:feature_code":"PPL","gn:geonameid":587899,"gn:latitude":58.97861,"gn:longitude":24.46528,"gn:modification_date":"2017-11-25","gn:name":"Vaimõisa","gn:population":0,"gn:timezone":"Europe/Tallinn","iso:country":"EE","lbl:bbox":"24.44528,58.95861,24.48528,58.99861","lbl:max_zoom":18,"lbl:min_zoom":13.5,"mz:hierarchy_label":1,"mz:is_current":1,"mz:min_zoom":12,"name:deu_x_preferred":["Vaimõisa"],"name:est_x_preferred":["Vaimõisa"],"name:fra_x_preferred":["Vaimõisa"],"name:hye_x_preferred":["Վաիմիիսա"],"name:pol_x_preferred":["Vaimõisa"],"name:sco_x_preferred":["Vaimõisa"],"name:spa_x_preferred":["Vaimõisa"],"name:und_x_variant":["Vaymyyza","Vanamõisa"],"name:vol_x_preferred":["Vaimõisa"],"src:geom":"geonames","wof:belongsto":[85683013,102191581,1713311153,85633135,1713305747],"wof:breaches":[],"wof:concordances":{"gn:id":587899,"wk:page":"Vaim%C3%B5isa"},"wof:coterminous":[1713311153],"wof:country":"EE","wof:geomhash":"84f8eaf7dd19bfa97bf0cae983678663","wof:hierarchy":[{"continent_id":102191581,"country_id":85633135,"county_id":1713305747,"localadmin_id":1713311153,"locality_id":1260262295,"region_id":85683013}],"wof:id":1260262295,"wof:lang_x_official":["est"],"wof:lang_x_spoken":["est"],"wof:lastmodified":1596662839,"wof:name":"Vaimoisa","wof:parent_id":1713311153,"wof:placetype":"locality","wof:repo":"whosonfirst-data-admin-ee","wof:superseded_by":[],"wof:supersedes":[],"wof:tags":[]},"bbox":[24.46528,58.97861,24.46528,58.97861],"geometry":{"coordinates":[24.46528,58.97861],"type":"Point"}}