{"id":1327239083,"type":"Feature","properties":{"edtf:cessation":"uuuu","edtf:inception":"uuuu","geom:area":0,"geom:area_square_m":0,"geom:bbox":"27.41639,59.40917,27.41639,59.40917","geom:latitude":59.40917,"geom:longitude":27.41639,"gn:admin1_code":"3.0","gn:admin2_code":"803.0","gn:admin3_code":"8647.0","gn:asciiname":"Uikala","gn:country_code":"EE","gn:dem":63,"gn:feature_class":"P","gn:feature_code":"PPL","gn:geonameid":588102,"gn:latitude":59.40917,"gn:longitude":27.41639,"gn:modification_date":"2017-11-25","gn:name":"Uikala","gn:population":0,"gn:timezone":"Europe/Tallinn","iso:country":"EE","lbl:bbox":"27.39639,59.38917,27.43639,59.42917","lbl:max_zoom":18,"lbl:min_zoom":13.5,"mz:hierarchy_label":1,"mz:is_current":1,"mz:min_zoom":12,"name:deu_x_preferred":["Uikala"],"name:est_x_preferred":["Uikala"],"name:hye_x_preferred":["Ուիկալա"],"name:pol_x_preferred":["Uikala"],"name:rus_x_preferred":["Уйкала"],"name:spa_x_preferred":["Uikala"],"name:vol_x_preferred":["Uikala"],"src:geom":"geonames","wof:belongsto":[85683059,102191581,1713306705,85633135,1713305783],"wof:breaches":[],"wof:concordances":{"gn:id":588102,"wk:page":"Uikala"},"wof:coterminous":[1713306705],"wof:country":"EE","wof:geomhash":"41dd35b724f3a3950deb5bddb84ad016","wof:hierarchy":[{"continent_id":102191581,"country_id":85633135,"county_id":1713305783,"localadmin_id":1713306705,"locality_id":1327239083,"region_id":85683059}],"wof:id":1327239083,"wof:lang_x_official":["est"],"wof:lang_x_spoken":["est"],"wof:lastmodified":1596676912,"wof:name":"Uikala","wof:parent_id":1713306705,"wof:placetype":"locality","wof:repo":"whosonfirst-data-admin-ee","wof:superseded_by":[],"wof:supersedes":[],"wof:tags":[]},"bbox":[27.41639,59.40917,27.41639,59.40917],"geometry":{"coordinates":[27.41639,59.40917],"type":"Point"}}