{"id":1242978401,"type":"Feature","properties":{"edtf:cessation":"uuuu","edtf:inception":"uuuu","geom:area":0,"geom:area_square_m":0,"geom:bbox":"27.47083,59.09889,27.47083,59.09889","geom:latitude":59.09889,"geom:longitude":27.47083,"gn:admin1_code":"3.0","gn:admin2_code":"130.0","gn:admin3_code":"2071.0","gn:asciiname":"Imatu","gn:cc2":"EE","gn:country_code":"EE","gn:dem":48,"gn:feature_class":"P","gn:feature_code":"PPL","gn:geonameid":592038,"gn:latitude":59.09889,"gn:longitude":27.47083,"gn:modification_date":"2017-11-25","gn:name":"Imatu","gn:population":0,"gn:timezone":"Europe/Tallinn","iso:country":"EE","lbl:bbox":"27.45083,59.07889,27.49083,59.11889","lbl:max_zoom":18,"lbl:min_zoom":13.5,"mz:hierarchy_label":1,"mz:is_current":1,"mz:min_zoom":12,"name:deu_x_preferred":["Imatu"],"name:est_x_preferred":["Imatu"],"name:fra_x_preferred":["Imatu"],"name:hye_x_preferred":["Իմատու"],"name:pol_x_preferred":["Imatu"],"name:spa_x_preferred":["Imatu"],"name:swe_x_preferred":["Imatu"],"name:und_x_variant":["Imatu Asundus"],"name:vol_x_preferred":["Imatu"],"src:geom":"geonames","wof:belongsto":[85683059,102191581,1713311819,85633135,1713305693],"wof:breaches":[],"wof:concordances":{"gn:id":592038,"wk:page":"Imatu"},"wof:coterminous":[1713311819],"wof:country":"EE","wof:geomhash":"4b54ec25bc7befa765523d8092ea0f50","wof:hierarchy":[{"continent_id":102191581,"country_id":85633135,"county_id":1713305693,"localadmin_id":1713311819,"locality_id":1242978401,"region_id":85683059}],"wof:id":1242978401,"wof:lang_x_official":["est"],"wof:lang_x_spoken":["est"],"wof:lastmodified":1596660758,"wof:name":"Imatu","wof:parent_id":1713311819,"wof:placetype":"locality","wof:repo":"whosonfirst-data-admin-ee","wof:superseded_by":[],"wof:supersedes":[],"wof:tags":[]},"bbox":[27.47083,59.09889,27.47083,59.09889],"geometry":{"coordinates":[27.47083,59.09889],"type":"Point"}}