{"id":1209879329,"type":"Feature","properties":{"edtf:cessation":"uuuu","edtf:inception":"uuuu","geom:area":0,"geom:area_square_m":0,"geom:bbox":"27.08556,58.63944,27.08556,58.63944","geom:latitude":58.63944,"geom:longitude":27.08556,"gn:admin1_code":"18.0","gn:admin2_code":"586.0","gn:admin3_code":"7043.0","gn:asciiname":"Ronisoo","gn:country_code":"EE","gn:dem":91,"gn:feature_class":"P","gn:feature_code":"PPL","gn:geonameid":8618100,"gn:latitude":58.63944,"gn:longitude":27.08556,"gn:modification_date":"2017-11-25","gn:name":"Ronisoo","gn:population":0,"gn:timezone":"Europe/Tallinn","iso:country":"EE","lbl:bbox":"27.06556,58.61944,27.10556,58.65944","lbl:max_zoom":18,"lbl:min_zoom":13.5,"mz:hierarchy_label":1,"mz:is_current":1,"mz:min_zoom":12,"name:est_x_preferred":["Ronisoo"],"name:fra_x_preferred":["Ronisoo"],"name:hye_x_preferred":["Ռոնիսոո"],"name:pol_x_preferred":["Ronisoo"],"name:spa_x_preferred":["Ronisoo"],"name:ukr_x_preferred":["Ронісоо"],"name:und_x_variant":["Ranna"],"name:vol_x_preferred":["Ronisoo"],"src:geom":"geonames","wof:belongsto":[85682995,102191581,1713309157,85633135,1713305679],"wof:breaches":[],"wof:concordances":{"gn:id":8618100,"wk:page":"Ronisoo"},"wof:coterminous":[1713309157],"wof:country":"EE","wof:geomhash":"a3901ea2bd4a74da9fa12905c3b9b79a","wof:hierarchy":[{"continent_id":102191581,"country_id":85633135,"county_id":1713305679,"localadmin_id":1713309157,"locality_id":1209879329,"region_id":85682995}],"wof:id":1209879329,"wof:lang_x_official":["est"],"wof:lang_x_spoken":["est"],"wof:lastmodified":1596660918,"wof:name":"Ronisoo","wof:parent_id":1713309157,"wof:placetype":"locality","wof:repo":"whosonfirst-data-admin-ee","wof:superseded_by":[],"wof:supersedes":[],"wof:tags":[]},"bbox":[27.08556,58.63944,27.08556,58.63944],"geometry":{"coordinates":[27.08556,58.63944],"type":"Point"}}