{"id":1343681861,"type":"Feature","properties":{"edtf:cessation":"uuuu","edtf:inception":"uuuu","geom:area":0,"geom:area_square_m":0,"geom:bbox":"26.18333,59.31667,26.18333,59.31667","geom:latitude":59.31667,"geom:longitude":26.18333,"gn:admin1_code":"8.0","gn:admin2_code":"272.0","gn:admin3_code":"2253.0","gn:asciiname":"Venehoone","gn:country_code":"EE","gn:dem":96,"gn:feature_class":"P","gn:feature_code":"PPL","gn:geonameid":587679,"gn:latitude":59.31667,"gn:longitude":26.18333,"gn:modification_date":"2017-11-25","gn:name":"Venehoone","gn:population":0,"gn:timezone":"Europe/Tallinn","iso:country":"EE","lbl:bbox":"26.16333,59.29667,26.20333,59.33667","lbl:max_zoom":18,"lbl:min_zoom":13.5,"mz:hierarchy_label":1,"mz:is_current":1,"mz:min_zoom":12,"src:geom":"geonames","wof:belongsto":[85683049,102191581,1713314589,85633135,1713305723],"wof:breaches":[],"wof:concordances":{"gn:id":587679},"wof:country":"EE","wof:geomhash":"9d2a9a9682f0f147fb2e64a6ac5b3ebe","wof:hierarchy":[{"continent_id":102191581,"country_id":85633135,"county_id":1713305723,"localadmin_id":1713314589,"locality_id":1343681861,"region_id":85683049}],"wof:id":1343681861,"wof:lang_x_official":["est"],"wof:lang_x_spoken":["est"],"wof:lastmodified":1596661734,"wof:name":"Venehoone","wof:parent_id":1713314589,"wof:placetype":"locality","wof:repo":"whosonfirst-data-admin-ee","wof:superseded_by":[],"wof:supersedes":[],"wof:tags":[]},"bbox":[26.18333,59.31667,26.18333,59.31667],"geometry":{"coordinates":[26.18333,59.31667],"type":"Point"}}