{"id":1243476709,"type":"Feature","properties":{"edtf:cessation":"uuuu","edtf:inception":"uuuu","geom:area":0,"geom:area_square_m":0,"geom:bbox":"25.81556,59.25694,25.81556,59.25694","geom:latitude":59.25694,"geom:longitude":25.81556,"gn:admin1_code":"8.0","gn:admin2_code":"792.0","gn:admin3_code":"4644.0","gn:asciiname":"Laeste","gn:country_code":"EE","gn:dem":89,"gn:feature_class":"P","gn:feature_code":"PPL","gn:geonameid":590771,"gn:latitude":59.25694,"gn:longitude":25.81556,"gn:modification_date":"2017-11-25","gn:name":"Läste","gn:population":0,"gn:timezone":"Europe/Tallinn","iso:country":"EE","lbl:bbox":"25.79556,59.23694,25.83556,59.27694","lbl:max_zoom":18,"lbl:min_zoom":13.5,"mz:hierarchy_label":1,"mz:is_current":1,"mz:min_zoom":12,"name:est_x_preferred":["Läste"],"name:hye_x_preferred":["Լեստե"],"name:ukr_x_preferred":["Лясте"],"name:urd_x_preferred":["لاسٹی"],"name:vol_x_preferred":["Läste"],"src:geom":"geonames","wof:belongsto":[85683049,102191581,1713314201,85633135,1713305761],"wof:breaches":[],"wof:concordances":{"gn:id":590771,"wk:page":"L%C3%A4ste"},"wof:coterminous":[1713314201],"wof:country":"EE","wof:geomhash":"d701d199f005637ced13b9357e20e60f","wof:hierarchy":[{"continent_id":102191581,"country_id":85633135,"county_id":1713305761,"localadmin_id":1713314201,"locality_id":1243476709,"region_id":85683049}],"wof:id":1243476709,"wof:lang_x_official":["est"],"wof:lang_x_spoken":["est"],"wof:lastmodified":1596676607,"wof:name":"Laeste","wof:parent_id":1713314201,"wof:placetype":"locality","wof:repo":"whosonfirst-data-admin-ee","wof:superseded_by":[],"wof:supersedes":[],"wof:tags":[]},"bbox":[25.81556,59.25694,25.81556,59.25694],"geometry":{"coordinates":[25.81556,59.25694],"type":"Point"}}