{"id":1126008391,"type":"Feature","properties":{"edtf:cessation":"uuuu","edtf:inception":"uuuu","geom:area":0,"geom:area_square_m":0,"geom:bbox":"26.18,58.13472,26.18,58.13472","geom:latitude":58.13472,"geom:longitude":26.18,"gn:country":"EE","gn:fcode":"PPL","gn:population":151,"iso:country":"EE","lbl:bbox":"26.16,58.11472,26.2,58.15472","lbl:latitude":58.13472,"lbl:longitude":26.18,"lbl:max_zoom":18,"lbl:min_zoom":13,"mz:hierarchy_label":1,"mz:is_current":1,"mz:min_zoom":11,"mz:note":"Quattroshapes Point Gazetteer import 20170519","name:ceb_x_preferred":["Koruste"],"name:eng_x_preferred":["Koruste"],"name:est_x_preferred":["Koruste"],"name:fra_x_preferred":["Koruste"],"name:hye_x_preferred":["Կոռուստե"],"name:nld_x_preferred":["Koruste"],"name:pol_x_preferred":["Koruste"],"name:spa_x_preferred":["Koruste"],"name:swe_x_preferred":["Koruste"],"name:ukr_x_preferred":["Корусте"],"name:vol_x_preferred":["Koruste"],"qs_pg:aaroncc":"EE","qs_pg:gn_country":"EE","qs_pg:gn_fcode":"PPL","qs_pg:gn_id":591090,"qs_pg:gn_pop":151,"qs_pg:name":"Koruste","qs_pg:name_adm0":"Eesti","qs_pg:name_adm1":"Tartumaa","qs_pg:photos_9k":1,"qs_pg:photos_9r":1,"qs_pg:photos_all":1,"qs_pg:photos_sr":0,"qs_pg:pop_sr":1,"qs_pg:qs_id":111032,"qs_pg:qs_pg_placetype":"locality","qs_pg:qs_pg_placetype_gp":"Town","qs_pg:woe_adm0":23424805,"qs_pg:woe_id":843237,"src:geom":"qs_pg","src:lbl_centroid":"qs_pg","src:population":"geonames","woe:adm0_id":23424805,"woe:name_adm0":"Eesti","woe:name_adm1":"Tartumaa","woe:placetype":"Town","wof:belongsto":[85682995,102191581,1713310139,85633135,1713305757],"wof:breaches":[],"wof:concordances":{"gn:id":591090,"gp:id":843237,"qs_pg:id":111032,"wd:id":"Q3468300"},"wof:coterminous":[1713310139],"wof:country":"EE","wof:created":1497300119,"wof:geomhash":"efb33e5e51883dfa3f5478582e973728","wof:hierarchy":[{"continent_id":102191581,"country_id":85633135,"county_id":1713305757,"localadmin_id":1713310139,"locality_id":1126008391,"region_id":85682995}],"wof:id":1126008391,"wof:lang_x_official":["est"],"wof:lang_x_spoken":["est"],"wof:lastmodified":1596661922,"wof:name":"Koruste","wof:parent_id":1713310139,"wof:placetype":"locality","wof:population":151,"wof:population_rank":1,"wof:repo":"whosonfirst-data-admin-ee","wof:superseded_by":[],"wof:supersedes":[],"wof:tags":[]},"bbox":[26.18,58.13472,26.18,58.13472],"geometry":{"coordinates":[26.18,58.13472],"type":"Point"}}