{"id":1293863207,"type":"Feature","properties":{"edtf:cessation":"uuuu","edtf:inception":"uuuu","geom:area":0,"geom:area_square_m":0,"geom:bbox":"25.02722,58.77917,25.02722,58.77917","geom:latitude":58.77917,"geom:longitude":25.02722,"gn:admin1_code":"13.0","gn:admin2_code":"293.0","gn:admin3_code":"3785.0","gn:asciiname":"Koogiste","gn:cc2":"EE","gn:country_code":"EE","gn:dem":56,"gn:feature_class":"P","gn:feature_code":"PPL","gn:geonameid":591163,"gn:latitude":58.77917,"gn:longitude":25.02722,"gn:modification_date":"2017-11-25","gn:name":"Koogiste","gn:population":0,"gn:timezone":"Europe/Tallinn","iso:country":"EE","lbl:bbox":"25.00722,58.75917,25.04722,58.79917","lbl:max_zoom":18,"lbl:min_zoom":13.5,"mz:hierarchy_label":1,"mz:is_current":1,"mz:min_zoom":12,"name:est_x_preferred":["Koogiste"],"name:hye_x_preferred":["Կոոգիստե"],"name:pol_x_preferred":["Koogiste"],"name:sco_x_preferred":["Koogiste"],"name:spa_x_preferred":["Koogiste"],"name:und_x_variant":["Kogiste"],"name:vol_x_preferred":["Koogiste"],"src:geom":"geonames","wof:belongsto":[85683013,102191581,1713310121,85633135,1713305713],"wof:breaches":[],"wof:concordances":{"gn:id":591163,"wk:page":"Koogiste"},"wof:coterminous":[1713309721],"wof:country":"EE","wof:geomhash":"54b50249476ae6e0e0897ec4f97716f3","wof:hierarchy":[{"continent_id":102191581,"country_id":85633135,"county_id":1713305713,"localadmin_id":1713310121,"locality_id":1293863207,"region_id":85683013}],"wof:id":1293863207,"wof:lang_x_official":["est"],"wof:lang_x_spoken":["est"],"wof:lastmodified":1596676748,"wof:name":"Koogiste","wof:parent_id":1713310121,"wof:placetype":"locality","wof:repo":"whosonfirst-data-admin-ee","wof:superseded_by":[],"wof:supersedes":[],"wof:tags":[]},"bbox":[25.02722,58.77917,25.02722,58.77917],"geometry":{"coordinates":[25.02722,58.77917],"type":"Point"}}