{"id":1293874357,"type":"Feature","properties":{"edtf:cessation":"uuuu","edtf:inception":"uuuu","geom:area":0,"geom:area_square_m":0,"geom:bbox":"26.0225,59.32944,26.0225,59.32944","geom:latitude":59.32944,"geom:longitude":26.0225,"gn:admin1_code":"8.0","gn:admin2_code":"272.0","gn:admin3_code":"6507.0","gn:asciiname":"Kaeaebaste","gn:country_code":"EE","gn:dem":94,"gn:feature_class":"P","gn:feature_code":"PPL","gn:geonameid":8618712,"gn:latitude":59.32944,"gn:longitude":26.0225,"gn:modification_date":"2017-11-25","gn:name":"Kääbaste","gn:population":0,"gn:timezone":"Europe/Tallinn","iso:country":"EE","lbl:bbox":"26.0025,59.30944,26.0425,59.34944","lbl:max_zoom":18,"lbl:min_zoom":13.5,"mz:hierarchy_label":1,"mz:is_current":1,"mz:min_zoom":12,"src:geom":"geonames","wof:belongsto":[85683049,102191581,1713312523,85633135,1713305723],"wof:breaches":[],"wof:concordances":{"gn:id":8618712},"wof:country":"EE","wof:geomhash":"0a2f0a9896347dafe4cb1ec95cf3a480","wof:hierarchy":[{"continent_id":102191581,"country_id":85633135,"county_id":1713305723,"localadmin_id":1713312523,"locality_id":1293874357,"region_id":85683049}],"wof:id":1293874357,"wof:lang_x_official":["est"],"wof:lang_x_spoken":["est"],"wof:lastmodified":1596661737,"wof:name":"Kaeaebaste","wof:parent_id":1713312523,"wof:placetype":"locality","wof:repo":"whosonfirst-data-admin-ee","wof:superseded_by":[],"wof:supersedes":[],"wof:tags":[]},"bbox":[26.0225,59.32944,26.0225,59.32944],"geometry":{"coordinates":[26.0225,59.32944],"type":"Point"}}