{"id":1276636843,"type":"Feature","properties":{"edtf:cessation":"uuuu","edtf:inception":"uuuu","geom:area":0,"geom:area_square_m":0,"geom:bbox":"24.29611,58.48056,24.29611,58.48056","geom:latitude":58.48056,"geom:longitude":24.29611,"gn:admin1_code":"11.0","gn:admin2_code":"624.0","gn:admin3_code":"5578.0","gn:asciiname":"Moisakuela","gn:country_code":"EE","gn:dem":12,"gn:feature_class":"P","gn:feature_code":"PPL","gn:geonameid":590181,"gn:latitude":58.48056,"gn:longitude":24.29611,"gn:modification_date":"2017-11-25","gn:name":"Mõisaküla","gn:population":0,"gn:timezone":"Europe/Tallinn","iso:country":"EE","lbl:bbox":"24.27611,58.46056,24.31611,58.50056","lbl:max_zoom":18,"lbl:min_zoom":13.5,"mz:hierarchy_label":1,"mz:is_current":1,"mz:min_zoom":12,"name:und_x_variant":["Mõisa","Myyzakyula","Mõisaküla"],"src:geom":"geonames","wof:belongsto":[85682981,102191581,1713314465,85633135,1713305703],"wof:breaches":[],"wof:concordances":{"gn:id":590181},"wof:country":"EE","wof:geomhash":"bd538b275cd11a2097405603f360804f","wof:hierarchy":[{"continent_id":102191581,"country_id":85633135,"county_id":1713305703,"localadmin_id":1713314465,"locality_id":1276636843,"region_id":85682981}],"wof:id":1276636843,"wof:lang_x_official":["est"],"wof:lang_x_spoken":["est"],"wof:lastmodified":1596677709,"wof:name":"Moisakuela","wof:parent_id":1713314465,"wof:placetype":"locality","wof:repo":"whosonfirst-data-admin-ee","wof:superseded_by":[],"wof:supersedes":[],"wof:tags":[]},"bbox":[24.29611,58.48056,24.29611,58.48056],"geometry":{"coordinates":[24.29611,58.48056],"type":"Point"}}