{"id":1310659627,"type":"Feature","properties":{"edtf:cessation":"uuuu","edtf:inception":"uuuu","geom:area":0,"geom:area_square_m":0,"geom:bbox":"26.68889,57.71667,26.68889,57.71667","geom:latitude":57.71667,"geom:longitude":26.68889,"gn:admin1_code":"21.0","gn:admin2_code":"142.0","gn:admin3_code":"3069.0","gn:asciiname":"Kikkaoja","gn:country_code":"EE","gn:dem":84,"gn:feature_class":"P","gn:feature_code":"PPL","gn:geonameid":794400,"gn:latitude":57.71667,"gn:longitude":26.68889,"gn:modification_date":"2017-11-25","gn:name":"Kikkaoja","gn:population":0,"gn:timezone":"Europe/Tallinn","iso:country":"EE","lbl:bbox":"26.66889,57.69667,26.70889,57.73667","lbl:max_zoom":18,"lbl:min_zoom":13.5,"mz:hierarchy_label":1,"mz:is_current":1,"mz:min_zoom":12,"name:est_x_preferred":["Kikkaoja"],"name:hye_x_preferred":["Կիկաոյա"],"name:pol_x_preferred":["Kikkaoja"],"name:sco_x_preferred":["Kikkaoja"],"name:spa_x_preferred":["Kikkaoja"],"name:ukr_x_preferred":["Кіккаоя"],"name:vol_x_preferred":["Kikkaoja"],"src:geom":"geonames","wof:belongsto":[85682937,102191581,1713312761,85633135,1713305795],"wof:breaches":[],"wof:concordances":{"gn:id":794400,"wk:page":"Kikkaoja"},"wof:coterminous":[1713312761],"wof:country":"EE","wof:geomhash":"4ab5dc81e4cfdc5915be3f5a7eb3a3dc","wof:hierarchy":[{"continent_id":102191581,"country_id":85633135,"county_id":1713305795,"localadmin_id":1713312761,"locality_id":1310659627,"region_id":85682937}],"wof:id":1310659627,"wof:lang_x_official":["est"],"wof:lang_x_spoken":["est"],"wof:lastmodified":1596677022,"wof:name":"Kikkaoja","wof:parent_id":1713312761,"wof:placetype":"locality","wof:repo":"whosonfirst-data-admin-ee","wof:superseded_by":[],"wof:supersedes":[],"wof:tags":[]},"bbox":[26.68889,57.71667,26.68889,57.71667],"geometry":{"coordinates":[26.68889,57.71667],"type":"Point"}}