{"id":1343481019,"type":"Feature","properties":{"edtf:cessation":"uuuu","edtf:inception":"uuuu","geom:area":0,"geom:area_square_m":0,"geom:bbox":"25.86667,59.51667,25.86667,59.51667","geom:latitude":59.51667,"geom:longitude":25.86667,"gn:admin1_code":"8.0","gn:admin2_code":"191.0","gn:admin3_code":"8787.0","gn:asciiname":"Uuekuela","gn:country_code":"EE","gn:dem":64,"gn:feature_class":"P","gn:feature_code":"PPL","gn:geonameid":588017,"gn:latitude":59.51667,"gn:longitude":25.86667,"gn:modification_date":"2017-11-25","gn:name":"Uueküla","gn:population":0,"gn:timezone":"Europe/Tallinn","iso:country":"EE","lbl:bbox":"25.84667,59.49667,25.88667,59.53667","lbl:max_zoom":18,"lbl:min_zoom":13.5,"mz:hierarchy_label":1,"mz:is_current":1,"mz:min_zoom":12,"name:und_x_variant":["Uekyula","Uzekyulya","Uueküla"],"src:geom":"geonames","wof:belongsto":[85683049,102191581,1713308269,85633135,1713305775],"wof:breaches":[],"wof:concordances":{"gn:id":588017},"wof:coterminous":[1713308269],"wof:country":"EE","wof:geomhash":"3d0a72c4cea803ad9fb5edf2770162fe","wof:hierarchy":[{"continent_id":102191581,"country_id":85633135,"county_id":1713305775,"localadmin_id":1713308269,"locality_id":1343481019,"region_id":85683049}],"wof:id":1343481019,"wof:lang_x_official":["est"],"wof:lang_x_spoken":["est"],"wof:lastmodified":1596678041,"wof:name":"Uuekuela","wof:parent_id":1713308269,"wof:placetype":"locality","wof:repo":"whosonfirst-data-admin-ee","wof:superseded_by":[],"wof:supersedes":[],"wof:tags":[]},"bbox":[25.86667,59.51667,25.86667,59.51667],"geometry":{"coordinates":[25.86667,59.51667],"type":"Point"}}