{"id":1242584999,"type":"Feature","properties":{"edtf:cessation":"uuuu","edtf:inception":"uuuu","geom:area":0,"geom:area_square_m":0,"geom:bbox":"26.90889,59.13056,26.90889,59.13056","geom:latitude":59.13056,"geom:longitude":26.90889,"gn:admin1_code":"3.0","gn:admin2_code":"130.0","gn:admin3_code":"5695.0","gn:asciiname":"Moisakuela","gn:country_code":"EE","gn:dem":68,"gn:feature_class":"P","gn:feature_code":"PPL","gn:geonameid":8618850,"gn:latitude":59.13056,"gn:longitude":26.90889,"gn:modification_date":"2017-11-25","gn:name":"Mõisaküla","gn:population":0,"gn:timezone":"Europe/Tallinn","iso:country":"EE","lbl:bbox":"26.88889,59.11056,26.92889,59.15056","lbl:max_zoom":18,"lbl:min_zoom":13.5,"mz:hierarchy_label":1,"mz:is_current":1,"mz:min_zoom":12,"src:geom":"geonames","wof:belongsto":[85683059,102191581,1713314433,85633135,1713305693],"wof:breaches":[],"wof:concordances":{"gn:id":8618850},"wof:country":"EE","wof:geomhash":"f1a5c8bc5ce2307eb79605dc584271db","wof:hierarchy":[{"continent_id":102191581,"country_id":85633135,"county_id":1713305693,"localadmin_id":1713314433,"locality_id":1242584999,"region_id":85683059}],"wof:id":1242584999,"wof:lang_x_official":["est"],"wof:lang_x_spoken":["est"],"wof:lastmodified":1596660737,"wof:name":"Moisakuela","wof:parent_id":1713314433,"wof:placetype":"locality","wof:repo":"whosonfirst-data-admin-ee","wof:superseded_by":[],"wof:supersedes":[],"wof:tags":[]},"bbox":[26.90889,59.13056,26.90889,59.13056],"geometry":{"coordinates":[26.90889,59.13056],"type":"Point"}}