{"id":1326789469,"type":"Feature","properties":{"edtf:cessation":"uuuu","edtf:inception":"uuuu","geom:area":0,"geom:area_square_m":0,"geom:bbox":"27.25861,57.69861,27.25861,57.69861","geom:latitude":57.69861,"geom:longitude":27.25861,"gn:admin1_code":"21.0","gn:admin2_code":"917.0","gn:admin3_code":"6112.0","gn:asciiname":"Keldo","gn:country_code":"EE","gn:dem":184,"gn:feature_class":"P","gn:feature_code":"PPL","gn:geonameid":8619893,"gn:latitude":57.69861,"gn:longitude":27.25861,"gn:modification_date":"2017-11-25","gn:name":"Keldo","gn:population":0,"gn:timezone":"Europe/Tallinn","iso:country":"EE","lbl:bbox":"27.23861,57.67861,27.27861,57.71861","lbl:max_zoom":18,"lbl:min_zoom":13.5,"mz:hierarchy_label":1,"mz:is_current":1,"mz:min_zoom":12,"name:und_x_variant":["Kelde"],"src:geom":"geonames","wof:belongsto":[85682937,102191581,1713316341,85633135,1713305633],"wof:breaches":[],"wof:concordances":{"gn:id":8619893},"wof:country":"EE","wof:geomhash":"b2fb57d496ea6dc2f7df9df1c070d96e","wof:hierarchy":[{"continent_id":102191581,"country_id":85633135,"county_id":1713305633,"localadmin_id":1713316341,"locality_id":1326789469,"region_id":85682937}],"wof:id":1326789469,"wof:lang_x_official":["est"],"wof:lang_x_spoken":["est"],"wof:lastmodified":1596660408,"wof:name":"Keldo","wof:parent_id":1713316341,"wof:placetype":"locality","wof:repo":"whosonfirst-data-admin-ee","wof:superseded_by":[],"wof:supersedes":[],"wof:tags":[]},"bbox":[27.25861,57.69861,27.25861,57.69861],"geometry":{"coordinates":[27.25861,57.69861],"type":"Point"}}