{"id":1259369221,"type":"Feature","properties":{"edtf:cessation":"uuuu","edtf:inception":"uuuu","geom:area":0,"geom:area_square_m":0,"geom:bbox":"24.28333,58.84417,24.28333,58.84417","geom:latitude":58.84417,"geom:longitude":24.28333,"gn:admin1_code":"13.0","gn:admin2_code":"503.0","gn:admin3_code":"8717.0","gn:asciiname":"Ketu","gn:country_code":"EE","gn:dem":24,"gn:feature_class":"P","gn:feature_code":"PPL","gn:geonameid":8618091,"gn:latitude":58.84417,"gn:longitude":24.28333,"gn:modification_date":"2017-11-25","gn:name":"Ketu","gn:population":0,"gn:timezone":"Europe/Tallinn","iso:country":"EE","lbl:bbox":"24.26333,58.82417,24.30333,58.86417","lbl:max_zoom":18,"lbl:min_zoom":13.5,"mz:hierarchy_label":1,"mz:is_current":1,"mz:min_zoom":12,"name:ben_x_preferred":["কেতু"],"name:cat_x_preferred":["Ketu"],"name:ceb_x_preferred":["Ketu"],"name:est_x_preferred":["Ketu"],"name:fra_x_preferred":["Ketu"],"name:por_x_preferred":["Ketu"],"name:san_x_preferred":["केतुः"],"name:swe_x_preferred":["Ketu"],"name:und_x_variant":["Tolli"],"src:geom":"geonames","wof:belongsto":[85683013,102191581,1713315149,85633135,1713305747],"wof:breaches":[],"wof:concordances":{"gn:id":8618091},"wof:country":"EE","wof:geomhash":"676c106edbe9fef269ce588b2ee91b8a","wof:hierarchy":[{"continent_id":102191581,"country_id":85633135,"county_id":1713305747,"localadmin_id":1713315149,"locality_id":1259369221,"region_id":85683013}],"wof:id":1259369221,"wof:lang_x_official":["est"],"wof:lang_x_spoken":["est"],"wof:lastmodified":1596662839,"wof:name":"Ketu","wof:parent_id":1713315149,"wof:placetype":"locality","wof:repo":"whosonfirst-data-admin-ee","wof:superseded_by":[],"wof:supersedes":[],"wof:tags":[]},"bbox":[24.28333,58.84417,24.28333,58.84417],"geometry":{"coordinates":[24.28333,58.84417],"type":"Point"}}