{"id":1327004355,"type":"Feature","properties":{"edtf:cessation":"uuuu","edtf:inception":"uuuu","geom:area":0,"geom:area_square_m":0,"geom:bbox":"25.66222,58.59306,25.66222,58.59306","geom:latitude":58.59306,"geom:longitude":25.66222,"gn:admin1_code":"20.0","gn:admin2_code":"615.0","gn:admin3_code":"4699.0","gn:asciiname":"Maalasti","gn:cc2":"EE","gn:country_code":"EE","gn:dem":44,"gn:feature_class":"P","gn:feature_code":"PPL","gn:geonameid":590460,"gn:latitude":58.59306,"gn:longitude":25.66222,"gn:modification_date":"2017-11-25","gn:name":"Maalasti","gn:population":0,"gn:timezone":"Europe/Tallinn","iso:country":"EE","lbl:bbox":"25.64222,58.57306,25.68222,58.61306","lbl:max_zoom":18,"lbl:min_zoom":13.5,"mz:hierarchy_label":1,"mz:is_current":1,"mz:min_zoom":12,"name:est_x_preferred":["Maalasti"],"name:hye_x_preferred":["Մաալաստի"],"name:nld_x_preferred":["Maalasti"],"name:pol_x_preferred":["Maalasti"],"name:spa_x_preferred":["Maalasti"],"name:ukr_x_preferred":["Мааласті"],"name:und_x_variant":["Malasti"],"name:urd_x_preferred":["مالاسٹی"],"name:vol_x_preferred":["Maalasti"],"src:geom":"geonames","wof:belongsto":[85682985,102191581,1713311641,85633135,1713305735],"wof:breaches":[],"wof:concordances":{"gn:id":590460,"wk:page":"Maalasti"},"wof:coterminous":[1713311641],"wof:country":"EE","wof:geomhash":"328e02e6214b46ffa64a505cea7ef7ad","wof:hierarchy":[{"continent_id":102191581,"country_id":85633135,"county_id":1713305735,"localadmin_id":1713311641,"locality_id":1327004355,"region_id":85682985}],"wof:id":1327004355,"wof:lang_x_official":["est"],"wof:lang_x_spoken":["est"],"wof:lastmodified":1596663461,"wof:name":"Maalasti","wof:parent_id":1713311641,"wof:placetype":"locality","wof:repo":"whosonfirst-data-admin-ee","wof:superseded_by":[],"wof:supersedes":[],"wof:tags":[]},"bbox":[25.66222,58.59306,25.66222,58.59306],"geometry":{"coordinates":[25.66222,58.59306],"type":"Point"}}