{"id":1226408611,"type":"Feature","properties":{"edtf:cessation":"uuuu","edtf:inception":"uuuu","geom:area":0,"geom:area_square_m":0,"geom:bbox":"26.59167,58.20806,26.59167,58.20806","geom:latitude":58.20806,"geom:longitude":26.59167,"gn:admin1_code":"18.0","gn:admin2_code":"283.0","gn:admin3_code":"3585.0","gn:asciiname":"Hallivariku","gn:country_code":"EE","gn:dem":143,"gn:feature_class":"P","gn:feature_code":"PPL","gn:geonameid":8620803,"gn:latitude":58.20806,"gn:longitude":26.59167,"gn:modification_date":"2017-11-25","gn:name":"Hallivariku","gn:population":0,"gn:timezone":"Europe/Tallinn","iso:country":"EE","lbl:bbox":"26.57167,58.18806,26.61167,58.22806","lbl:max_zoom":18,"lbl:min_zoom":13.5,"mz:hierarchy_label":1,"mz:is_current":1,"mz:min_zoom":12,"name:und_x_variant":["Kitse"],"src:geom":"geonames","wof:belongsto":[85682995,102191581,1713308755,85633135,1713305717],"wof:breaches":[],"wof:concordances":{"gn:id":8620803},"wof:country":"EE","wof:geomhash":"67d22046c4319f0e1618fb0b6e94f8ed","wof:hierarchy":[{"continent_id":102191581,"country_id":85633135,"county_id":1713305717,"localadmin_id":1713308755,"locality_id":1226408611,"region_id":85682995}],"wof:id":1226408611,"wof:lang_x_official":["est"],"wof:lang_x_spoken":["est"],"wof:lastmodified":1596676689,"wof:name":"Hallivariku","wof:parent_id":1713308755,"wof:placetype":"locality","wof:repo":"whosonfirst-data-admin-ee","wof:superseded_by":[],"wof:supersedes":[],"wof:tags":[]},"bbox":[26.59167,58.20806,26.59167,58.20806],"geometry":{"coordinates":[26.59167,58.20806],"type":"Point"}}