{"id":1242736899,"type":"Feature","properties":{"edtf:cessation":"uuuu","edtf:inception":"uuuu","geom:area":0,"geom:area_square_m":0,"geom:bbox":"27.14083,57.75444,27.14083,57.75444","geom:latitude":57.75444,"geom:longitude":27.14083,"gn:admin1_code":"21.0","gn:admin2_code":"917.0","gn:admin3_code":"9458.0","gn:asciiname":"Kruuda","gn:country_code":"EE","gn:dem":184,"gn:feature_class":"P","gn:feature_code":"PPL","gn:geonameid":8619193,"gn:latitude":57.75444,"gn:longitude":27.14083,"gn:modification_date":"2017-11-25","gn:name":"Kruuda","gn:population":0,"gn:timezone":"Europe/Tallinn","iso:country":"EE","lbl:bbox":"27.12083,57.73444,27.16083,57.77444","lbl:max_zoom":18,"lbl:min_zoom":13.5,"mz:hierarchy_label":1,"mz:is_current":1,"mz:min_zoom":12,"src:geom":"geonames","wof:belongsto":[85682937,102191581,1713315783,85633135,1713305633],"wof:breaches":[],"wof:concordances":{"gn:id":8619193},"wof:country":"EE","wof:geomhash":"1a328e80b43f88d256eb77d30cd251a6","wof:hierarchy":[{"continent_id":102191581,"country_id":85633135,"county_id":1713305633,"localadmin_id":1713315783,"locality_id":1242736899,"region_id":85682937}],"wof:id":1242736899,"wof:lang_x_official":["est"],"wof:lang_x_spoken":["est"],"wof:lastmodified":1596660389,"wof:name":"Kruuda","wof:parent_id":1713315783,"wof:placetype":"locality","wof:repo":"whosonfirst-data-admin-ee","wof:superseded_by":[],"wof:supersedes":[],"wof:tags":[]},"bbox":[27.14083,57.75444,27.14083,57.75444],"geometry":{"coordinates":[27.14083,57.75444],"type":"Point"}}