{"id":1344070825,"type":"Feature","properties":{"edtf:cessation":"uuuu","edtf:inception":"uuuu","geom:area":0,"geom:area_square_m":0,"geom:bbox":"25.72667,59.32444,25.72667,59.32444","geom:latitude":59.32444,"geom:longitude":25.72667,"gn:admin1_code":"1.0","gn:admin2_code":"141.0","gn:admin3_code":"6254.0","gn:asciiname":"Nahe","gn:cc2":"EE","gn:country_code":"EE","gn:dem":84,"gn:feature_class":"P","gn:feature_code":"PPL","gn:geonameid":590044,"gn:latitude":59.32444,"gn:longitude":25.72667,"gn:modification_date":"2017-11-25","gn:name":"Nahe","gn:population":0,"gn:timezone":"Europe/Tallinn","iso:country":"EE","lbl:bbox":"25.70667,59.30444,25.74667,59.34444","lbl:max_zoom":18,"lbl:min_zoom":13.5,"mz:hierarchy_label":1,"mz:is_current":1,"mz:min_zoom":12,"name:ceb_x_preferred":["Nahe"],"name:dan_x_preferred":["Nahe"],"name:deu_x_preferred":["Nahe"],"name:epo_x_preferred":["Nahe"],"name:fra_x_preferred":["Nahe"],"name:ita_x_preferred":["Nahe"],"name:ltz_x_preferred":["Nahe"],"name:mkd_x_preferred":["Нае"],"name:nld_x_preferred":["Nahe"],"name:pol_x_preferred":["Nahe"],"name:ron_x_preferred":["Nahe"],"name:rus_x_preferred":["Наэ"],"name:swe_x_preferred":["Nahe"],"name:und_x_variant":["Nakhe"],"src:geom":"geonames","wof:belongsto":[85683055,102191581,1713314585,85633135,1713305749],"wof:breaches":[],"wof:concordances":{"gn:id":590044},"wof:country":"EE","wof:geomhash":"3e00ca513829606024a302bad944107d","wof:hierarchy":[{"continent_id":102191581,"country_id":85633135,"county_id":1713305749,"localadmin_id":1713314585,"locality_id":1344070825,"region_id":85683055}],"wof:id":1344070825,"wof:lang_x_official":["est"],"wof:lang_x_spoken":["est"],"wof:lastmodified":1596662803,"wof:name":"Nahe","wof:parent_id":1713314585,"wof:placetype":"locality","wof:repo":"whosonfirst-data-admin-ee","wof:superseded_by":[],"wof:supersedes":[],"wof:tags":[]},"bbox":[25.72667,59.32444,25.72667,59.32444],"geometry":{"coordinates":[25.72667,59.32444],"type":"Point"}}