{"id":1276741401,"type":"Feature","properties":{"edtf:cessation":"uuuu","edtf:inception":"uuuu","geom:area":0,"geom:area_square_m":0,"geom:bbox":"24.44528,57.88667,24.44528,57.88667","geom:latitude":57.88667,"geom:longitude":24.44528,"gn:admin1_code":"11.0","gn:admin2_code":"214.0","gn:admin3_code":"2029.0","gn:asciiname":"Piiri","gn:country_code":"EE","gn:dem":17,"gn:feature_class":"P","gn:feature_code":"PPL","gn:geonameid":8619989,"gn:latitude":57.88667,"gn:longitude":24.44528,"gn:modification_date":"2017-11-25","gn:name":"Piiri","gn:population":0,"gn:timezone":"Europe/Tallinn","iso:country":"EE","lbl:bbox":"24.42528,57.86667,24.46528,57.90667","lbl:max_zoom":18,"lbl:min_zoom":13.5,"mz:hierarchy_label":1,"mz:is_current":1,"mz:min_zoom":12,"name:deu_x_preferred":["Piiri"],"name:est_x_preferred":["Piiri"],"name:fin_x_preferred":["Piiri"],"name:nld_x_preferred":["Piiri"],"name:pol_x_preferred":["Piiri"],"name:ukr_x_preferred":["Пійрі"],"name:und_x_variant":["Veneküla"],"name:vol_x_preferred":["Piiri"],"src:geom":"geonames","wof:belongsto":[85682981,102191581,1713309221,85633135,1713305741],"wof:breaches":[],"wof:concordances":{"gn:id":8619989},"wof:country":"EE","wof:geomhash":"738621a77140fd73d11934462049d1ec","wof:hierarchy":[{"continent_id":102191581,"country_id":85633135,"county_id":1713305741,"localadmin_id":1713309221,"locality_id":1276741401,"region_id":85682981}],"wof:id":1276741401,"wof:lang_x_official":["est"],"wof:lang_x_spoken":["est"],"wof:lastmodified":1596663209,"wof:name":"Piiri","wof:parent_id":1713309221,"wof:placetype":"locality","wof:repo":"whosonfirst-data-admin-ee","wof:superseded_by":[],"wof:supersedes":[],"wof:tags":[]},"bbox":[24.44528,57.88667,24.44528,57.88667],"geometry":{"coordinates":[24.44528,57.88667],"type":"Point"}}