{"id":1310205481,"type":"Feature","properties":{"edtf:cessation":"uuuu","edtf:inception":"uuuu","geom:area":0,"geom:area_square_m":0,"geom:bbox":"25.41667,58.85,25.41667,58.85","geom:latitude":58.85,"geom:longitude":25.41667,"gn:admin1_code":"4.0","gn:admin2_code":"834.0","gn:admin3_code":"5906.0","gn:asciiname":"Ees-Pala","gn:country_code":"EE","gn:dem":66,"gn:feature_class":"P","gn:feature_code":"PPL","gn:geonameid":592309,"gn:latitude":58.85,"gn:longitude":25.41667,"gn:modification_date":"2017-11-25","gn:name":"Ees-Pala","gn:population":0,"gn:timezone":"Europe/Tallinn","iso:country":"EE","lbl:bbox":"25.39667,58.83,25.43667,58.87","lbl:max_zoom":18,"lbl:min_zoom":13.5,"mz:hierarchy_label":1,"mz:is_current":1,"mz:min_zoom":12,"src:geom":"geonames","wof:belongsto":[85683031,102191581,1713306695,85633135,1713305773],"wof:breaches":[],"wof:concordances":{"gn:id":592309},"wof:country":"EE","wof:geomhash":"7e335763a29cfb08fa6b5945067e1a16","wof:hierarchy":[{"continent_id":102191581,"country_id":85633135,"county_id":1713305773,"localadmin_id":1713306695,"locality_id":1310205481,"region_id":85683031}],"wof:id":1310205481,"wof:lang_x_official":["est"],"wof:lang_x_spoken":["est"],"wof:lastmodified":1596677990,"wof:name":"Ees-Pala","wof:parent_id":1713306695,"wof:placetype":"locality","wof:repo":"whosonfirst-data-admin-ee","wof:superseded_by":[],"wof:supersedes":[],"wof:tags":[]},"bbox":[25.41667,58.85,25.41667,58.85],"geometry":{"coordinates":[25.41667,58.85],"type":"Point"}}