{"id":1327146109,"type":"Feature","properties":{"edtf:cessation":"uuuu","edtf:inception":"uuuu","geom:area":0,"geom:area_square_m":0,"geom:bbox":"27.42222,59.38194,27.42222,59.38194","geom:latitude":59.38194,"geom:longitude":27.42222,"gn:admin1_code":"3.0","gn:admin2_code":"251.0","gn:admin3_code":"3477.0","gn:asciiname":"Kotinuka","gn:country_code":"EE","gn:dem":58,"gn:feature_class":"P","gn:feature_code":"PPL","gn:geonameid":793486,"gn:latitude":59.38194,"gn:longitude":27.42222,"gn:modification_date":"2017-11-25","gn:name":"Kotinuka","gn:population":0,"gn:timezone":"Europe/Tallinn","iso:country":"EE","lbl:bbox":"27.40222,59.36194,27.44222,59.40194","lbl:max_zoom":18,"lbl:min_zoom":13.5,"mz:hierarchy_label":1,"mz:is_current":1,"mz:min_zoom":12,"name:deu_x_preferred":["Kotinuka"],"name:est_x_preferred":["Kotinuka"],"name:fra_x_preferred":["Kotinuka"],"name:hye_x_preferred":["Կոտինուկա"],"name:nld_x_preferred":["Kotinuka"],"name:pol_x_preferred":["Kotinuka"],"name:spa_x_preferred":["Kotinuka"],"name:vol_x_preferred":["Kotinuka"],"src:geom":"geonames","wof:belongsto":[85683059,102191581,1713313335,85633135,1713305651],"wof:breaches":[],"wof:concordances":{"gn:id":793486,"wk:page":"Kotinuka"},"wof:coterminous":[1713313335],"wof:country":"EE","wof:geomhash":"5391a62245fddc989be8c1c9fab0ba3a","wof:hierarchy":[{"continent_id":102191581,"country_id":85633135,"county_id":1713305651,"localadmin_id":1713313335,"locality_id":1327146109,"region_id":85683059}],"wof:id":1327146109,"wof:lang_x_official":["est"],"wof:lang_x_spoken":["est"],"wof:lastmodified":1596676515,"wof:name":"Kotinuka","wof:parent_id":1713313335,"wof:placetype":"locality","wof:repo":"whosonfirst-data-admin-ee","wof:superseded_by":[],"wof:supersedes":[],"wof:tags":[]},"bbox":[27.42222,59.38194,27.42222,59.38194],"geometry":{"coordinates":[27.42222,59.38194],"type":"Point"}}