{
  "type": "Feature",
  "properties": {
    "iso:country":"FI",
    "name:fi_x_preferred_x_variant":[
        "Tuomarinkyl\u00e4"
    ],
    "wof:name":"Tuomarinkyla",
    "wof:placetype":"neighbourhood"
},
  "geometry": {"coordinates":[24.93331741038279,60.26226810639557],"type":"Point"}
}