{"id":1125837995,"type":"Feature","properties":{"edtf:cessation":"uuuu","edtf:inception":"uuuu","geom:area":0,"geom:area_square_m":0,"geom:bbox":"26.53667,58.24028,26.53667,58.24028","geom:latitude":58.24028,"geom:longitude":26.53667,"gn:country":"EE","gn:fcode":"PPL","gn:population":335,"iso:country":"EE","lbl:bbox":"26.51667,58.22028,26.55667,58.26028","lbl:latitude":58.24028,"lbl:longitude":26.53667,"lbl:max_zoom":17,"lbl:min_zoom":12.5,"mz:hierarchy_label":1,"mz:is_current":1,"mz:min_zoom":11,"mz:note":"Quattroshapes Point Gazetteer import 20170519","name:ceb_x_preferred":["Luke"],"name:eng_x_preferred":["Luke"],"name:est_x_preferred":["Luke"],"name:hye_x_preferred":["Լուկե"],"name:nld_x_preferred":["Luke"],"name:pol_x_preferred":["Luke"],"name:spa_x_preferred":["Luke"],"name:ukr_x_preferred":["Луке"],"name:vol_x_preferred":["Luke"],"qs_pg:aaroncc":"EE","qs_pg:gn_country":"EE","qs_pg:gn_fcode":"PPL","qs_pg:gn_id":590486,"qs_pg:gn_pop":335,"qs_pg:name":"Luke","qs_pg:name_adm0":"Eesti","qs_pg:name_adm1":"Tartumaa","qs_pg:photos_9k":1,"qs_pg:photos_9r":1,"qs_pg:photos_all":3,"qs_pg:photos_sr":0,"qs_pg:pop_sr":2,"qs_pg:qs_id":915821,"qs_pg:qs_pg_placetype":"locality","qs_pg:qs_pg_placetype_gp":"Town","qs_pg:woe_adm0":23424805,"qs_pg:woe_id":843792,"src:geom":"qs_pg","src:lbl_centroid":"qs_pg","src:population":"geonames","woe:adm0_id":23424805,"woe:name_adm0":"Eesti","woe:name_adm1":"Tartumaa","woe:placetype":"Town","wof:belongsto":[85682995,102191581,1713314857,85633135,1713305715],"wof:breaches":[],"wof:concordances":{"gn:id":590486,"gp:id":843792,"qs_pg:id":915821,"wd:id":"Q3455299"},"wof:coterminous":[1713314857],"wof:country":"EE","wof:created":1497292797,"wof:geomhash":"11aaa5ece7b2f1b4204dd2133dc1cfb2","wof:hierarchy":[{"continent_id":102191581,"country_id":85633135,"county_id":1713305715,"localadmin_id":1713314857,"locality_id":1125837995,"region_id":85682995}],"wof:id":1125837995,"wof:lang_x_official":["est"],"wof:lang_x_spoken":["est"],"wof:lastmodified":1596676767,"wof:name":"Luke","wof:parent_id":1713314857,"wof:placetype":"locality","wof:population":335,"wof:population_rank":2,"wof:repo":"whosonfirst-data-admin-ee","wof:superseded_by":[],"wof:supersedes":[],"wof:tags":[]},"bbox":[26.53667,58.24028,26.53667,58.24028],"geometry":{"coordinates":[26.53667,58.24028],"type":"Point"}}