{"id":1293464235,"type":"Feature","properties":{"edtf:cessation":"uuuu","edtf:inception":"uuuu","geom:area":0,"geom:area_square_m":0,"geom:bbox":"25.76667,58.13333,25.76667,58.13333","geom:latitude":58.13333,"geom:longitude":25.76667,"gn:admin1_code":"20.0","gn:admin2_code":"899.0","gn:admin3_code":"2685.0","gn:asciiname":"Kannu","gn:country_code":"EE","gn:dem":114,"gn:feature_class":"P","gn:feature_code":"PPL","gn:geonameid":591662,"gn:latitude":58.13333,"gn:longitude":25.76667,"gn:modification_date":"2017-11-25","gn:name":"Kannu","gn:population":0,"gn:timezone":"Europe/Tallinn","iso:country":"EE","lbl:bbox":"25.74667,58.11333,25.78667,58.15333","lbl:max_zoom":18,"lbl:min_zoom":13.5,"mz:hierarchy_label":1,"mz:is_current":1,"mz:min_zoom":12,"name:est_x_preferred":["Kannu"],"name:fin_x_preferred":["Kannu"],"name:vol_x_preferred":["Kannu"],"src:geom":"geonames","wof:belongsto":[85682985,102191581,1713314459,85633135,1713305669],"wof:breaches":[],"wof:concordances":{"gn:id":591662},"wof:country":"EE","wof:geomhash":"6075644208c4b793f309f463630fb9c7","wof:hierarchy":[{"continent_id":102191581,"country_id":85633135,"county_id":1713305669,"localadmin_id":1713314459,"locality_id":1293464235,"region_id":85682985}],"wof:id":1293464235,"wof:lang_x_official":["est"],"wof:lang_x_spoken":["est"],"wof:lastmodified":1596661264,"wof:name":"Kannu","wof:parent_id":1713314459,"wof:placetype":"locality","wof:repo":"whosonfirst-data-admin-ee","wof:superseded_by":[],"wof:supersedes":[],"wof:tags":[]},"bbox":[25.76667,58.13333,25.76667,58.13333],"geometry":{"coordinates":[25.76667,58.13333],"type":"Point"}}