{"id":1209696973,"type":"Feature","properties":{"edtf:cessation":"uuuu","edtf:inception":"uuuu","geom:area":0,"geom:area_square_m":0,"geom:bbox":"25.15,58.63333,25.15,58.63333","geom:latitude":58.63333,"geom:longitude":25.15,"gn:admin1_code":"11.0","gn:admin2_code":"638.0","gn:admin3_code":"4696.0","gn:asciiname":"Lyuyste","gn:country_code":"EE","gn:dem":47,"gn:feature_class":"P","gn:feature_code":"PPL","gn:geonameid":590463,"gn:latitude":58.63333,"gn:longitude":25.15,"gn:modification_date":"2017-11-25","gn:name":"Lyuyste","gn:population":0,"gn:timezone":"Europe/Tallinn","iso:country":"EE","lbl:bbox":"25.13,58.61333,25.17,58.65333","lbl:max_zoom":18,"lbl:min_zoom":13.5,"mz:hierarchy_label":1,"mz:is_current":1,"mz:min_zoom":12,"name:est_x_preferred":["Lüüste"],"name:hye_x_preferred":["Լյուուստե"],"name:pol_x_preferred":["Lüüste"],"name:spa_x_preferred":["Lüüste"],"name:vol_x_preferred":["Lüüste"],"src:geom":"geonames","wof:belongsto":[85682981,102191581,1713309423,85633135,1713305733],"wof:breaches":[],"wof:concordances":{"gn:id":590463,"wk:page":"L%C3%BC%C3%BCste"},"wof:coterminous":[1713309423],"wof:country":"EE","wof:geomhash":"b5c9e4001915e6ba61fe4604261cafc4","wof:hierarchy":[{"continent_id":102191581,"country_id":85633135,"county_id":1713305733,"localadmin_id":1713309423,"locality_id":1209696973,"region_id":85682981}],"wof:id":1209696973,"wof:lang_x_official":["est"],"wof:lang_x_spoken":["est"],"wof:lastmodified":1596663427,"wof:name":"Lyuyste","wof:parent_id":1713309423,"wof:placetype":"locality","wof:repo":"whosonfirst-data-admin-ee","wof:superseded_by":[],"wof:supersedes":[],"wof:tags":[]},"bbox":[25.15,58.63333,25.15,58.63333],"geometry":{"coordinates":[25.15,58.63333],"type":"Point"}}