{"id":1125809009,"type":"Feature","properties":{"edtf:cessation":"uuuu","edtf:inception":"uuuu","geom:area":0,"geom:area_square_m":0,"geom:bbox":"25.74056,58.14917,25.74056,58.14917","geom:latitude":58.14917,"geom:longitude":25.74056,"gn:country":"EE","gn:fcode":"PPL","gn:population":147,"iso:country":"EE","lbl:bbox":"25.72056,58.12917,25.76056,58.16917","lbl:latitude":58.14917,"lbl:longitude":25.74056,"lbl:max_zoom":18,"lbl:min_zoom":13,"mz:hierarchy_label":1,"mz:is_current":1,"mz:min_zoom":11,"mz:note":"Quattroshapes Point Gazetteer import 20170519","name:bul_x_preferred":["Аникаци"],"name:ceb_x_preferred":["Anikatsi"],"name:ces_x_preferred":["Anikatsi"],"name:deu_x_preferred":["Anikatsi"],"name:eng_x_preferred":["Anikatsi"],"name:est_x_preferred":["Anikatsi"],"name:fra_x_preferred":["Anikatsi"],"name:hye_x_preferred":["Անիկացի"],"name:nld_x_preferred":["Anikatsi"],"name:pol_x_preferred":["Anikatsi"],"name:spa_x_preferred":["Anikatsi"],"name:swe_x_preferred":["Anikatsi"],"name:ukr_x_preferred":["Анікатсі"],"name:vol_x_preferred":["Anikatsi"],"qs_pg:aaroncc":"EE","qs_pg:gn_country":"EE","qs_pg:gn_fcode":"PPL","qs_pg:gn_id":592475,"qs_pg:gn_pop":147,"qs_pg:name":"Anikatsi","qs_pg:name_adm0":"Eesti","qs_pg:name_adm1":"Viljandimaa","qs_pg:photos_9r":0,"qs_pg:photos_sr":0,"qs_pg:pop_sr":1,"qs_pg:qs_id":1273583,"qs_pg:qs_pg_placetype":"locality","qs_pg:qs_pg_placetype_gp":"Town","qs_pg:woe_adm0":23424805,"qs_pg:woe_id":841952,"src:geom":"qs_pg","src:lbl_centroid":"qs_pg","src:population":"geonames","woe:adm0_id":23424805,"woe:name_adm0":"Eesti","woe:name_adm1":"Viljandimaa","woe:placetype":"Town","wof:belongsto":[85682985,102191581,1713313961,85633135,1713305669],"wof:breaches":[],"wof:concordances":{"gn:id":592475,"gp:id":841952,"qs_pg:id":1273583,"wd:id":"Q3477418"},"wof:coterminous":[1713313961],"wof:country":"EE","wof:created":1497291580,"wof:geomhash":"1a376698422876bb2513b8b571cfc9c2","wof:hierarchy":[{"continent_id":102191581,"country_id":85633135,"county_id":1713305669,"localadmin_id":1713313961,"locality_id":1125809009,"region_id":85682985}],"wof:id":1125809009,"wof:lang_x_official":["est"],"wof:lang_x_spoken":["est"],"wof:lastmodified":1596661248,"wof:name":"Anikatsi","wof:parent_id":1713313961,"wof:placetype":"locality","wof:population":147,"wof:population_rank":1,"wof:repo":"whosonfirst-data-admin-ee","wof:superseded_by":[],"wof:supersedes":[],"wof:tags":[]},"bbox":[25.74056,58.14917,25.74056,58.14917],"geometry":{"coordinates":[25.74056,58.14917],"type":"Point"}}