{"id":1310386675,"type":"Feature","properties":{"edtf:cessation":"uuuu","edtf:inception":"uuuu","geom:area":0,"geom:area_square_m":0,"geom:bbox":"24.25194,58.65667,24.25194,58.65667","geom:latitude":58.65667,"geom:longitude":24.25194,"gn:admin1_code":"11.0","gn:admin2_code":"430.0","gn:admin3_code":"5990.0","gn:asciiname":"Parasmaa","gn:country_code":"EE","gn:dem":21,"gn:feature_class":"P","gn:feature_code":"PPL","gn:geonameid":589607,"gn:latitude":58.65667,"gn:longitude":24.25194,"gn:modification_date":"2017-11-25","gn:name":"Parasmaa","gn:population":0,"gn:timezone":"Europe/Tallinn","iso:country":"EE","lbl:bbox":"24.23194,58.63667,24.27194,58.67667","lbl:max_zoom":18,"lbl:min_zoom":13.5,"mz:hierarchy_label":1,"mz:is_current":1,"mz:min_zoom":12,"name:est_x_preferred":["Parasmaa"],"name:hye_x_preferred":["Պառասմաա"],"name:pol_x_preferred":["Parasmaa"],"name:spa_x_preferred":["Parasmaa"],"name:und_x_variant":["Parasma"],"name:vol_x_preferred":["Parasmaa"],"src:geom":"geonames","wof:belongsto":[85683001,102191581,1713313847,85633135,1713305721],"wof:breaches":[],"wof:concordances":{"gn:id":589607,"wk:page":"Parasmaa"},"wof:coterminous":[1713313847],"wof:country":"EE","wof:geomhash":"b3a5006dd874dd435a11198222c93839","wof:hierarchy":[{"continent_id":102191581,"country_id":85633135,"county_id":1713305721,"localadmin_id":1713313847,"locality_id":1310386675,"region_id":85683001}],"wof:id":1310386675,"wof:lang_x_official":["est"],"wof:lang_x_spoken":["est"],"wof:lastmodified":1596661690,"wof:name":"Parasmaa","wof:parent_id":1713313847,"wof:placetype":"locality","wof:repo":"whosonfirst-data-admin-ee","wof:superseded_by":[],"wof:supersedes":[],"wof:tags":[]},"bbox":[24.25194,58.65667,24.25194,58.65667],"geometry":{"coordinates":[24.25194,58.65667],"type":"Point"}}