{"id":1225922327,"type":"Feature","properties":{"edtf:cessation":"uuuu","edtf:inception":"uuuu","geom:area":0,"geom:area_square_m":0,"geom:bbox":"25.11417,58.55194,25.11417,58.55194","geom:latitude":58.55194,"geom:longitude":25.11417,"gn:admin1_code":"11.0","gn:admin2_code":"638.0","gn:admin3_code":"4190.0","gn:asciiname":"Veneoja","gn:country_code":"EE","gn:dem":30,"gn:feature_class":"P","gn:feature_code":"PPL","gn:geonameid":8618324,"gn:latitude":58.55194,"gn:longitude":25.11417,"gn:modification_date":"2017-11-25","gn:name":"Veneoja","gn:population":0,"gn:timezone":"Europe/Tallinn","iso:country":"EE","lbl:bbox":"25.09417,58.53194,25.13417,58.57194","lbl:max_zoom":18,"lbl:min_zoom":13.5,"mz:hierarchy_label":1,"mz:is_current":1,"mz:min_zoom":12,"name:deu_x_preferred":["Veneoja"],"name:est_x_preferred":["Veneoja"],"name:fas_x_preferred":["ونئوجا"],"name:hye_x_preferred":["Վենեոյա"],"name:pol_x_preferred":["Veneoja"],"name:spa_x_preferred":["Veneoja"],"name:und_x_variant":["Vene-Kuusiku"],"name:vol_x_preferred":["Veneoja"],"src:geom":"geonames","wof:belongsto":[85682981,102191581,1713314987,85633135,1713305733],"wof:breaches":[],"wof:concordances":{"gn:id":8618324},"wof:country":"EE","wof:geomhash":"8c0df974aa107c0d7d8db6a9f50c8ecf","wof:hierarchy":[{"continent_id":102191581,"country_id":85633135,"county_id":1713305733,"localadmin_id":1713314987,"locality_id":1225922327,"region_id":85682981}],"wof:id":1225922327,"wof:lang_x_official":["est"],"wof:lang_x_spoken":["est"],"wof:lastmodified":1596663420,"wof:name":"Veneoja","wof:parent_id":1713314987,"wof:placetype":"locality","wof:repo":"whosonfirst-data-admin-ee","wof:superseded_by":[],"wof:supersedes":[],"wof:tags":[]},"bbox":[25.11417,58.55194,25.11417,58.55194],"geometry":{"coordinates":[25.11417,58.55194],"type":"Point"}}