{"id":1125956551,"type":"Feature","properties":{"edtf:cessation":"uuuu","edtf:inception":"uuuu","geom:area":0,"geom:area_square_m":0,"geom:bbox":"26.26,58.65333,26.26,58.65333","geom:latitude":58.65333,"geom:longitude":26.26,"gn:country":"EE","gn:fcode":"PPL","gn:population":102,"iso:country":"EE","lbl:bbox":"26.24,58.63333,26.28,58.67333","lbl:latitude":58.65333,"lbl:longitude":26.26,"lbl:max_zoom":18,"lbl:min_zoom":13,"mz:hierarchy_label":1,"mz:is_current":1,"mz:min_zoom":11,"mz:note":"Quattroshapes Point Gazetteer import 20170519","name:ceb_x_preferred":["Pööra"],"name:eng_x_preferred":["Pööra"],"name:est_x_preferred":["Pööra"],"name:hye_x_preferred":["Պոոռա"],"name:nld_x_preferred":["Pööra"],"name:pol_x_preferred":["Pööra"],"name:spa_x_preferred":["Pööra"],"name:swe_x_preferred":["Pööra"],"name:ukr_x_preferred":["Пєера"],"name:vol_x_preferred":["Pööra"],"qs_pg:aaroncc":"EE","qs_pg:gn_country":"EE","qs_pg:gn_fcode":"PPL","qs_pg:gn_id":794623,"qs_pg:gn_pop":102,"qs_pg:name":"Pööra","qs_pg:name_adm0":"Eesti","qs_pg:name_adm1":"Jõgevamaa","qs_pg:photos_9r":0,"qs_pg:photos_sr":0,"qs_pg:pop_sr":1,"qs_pg:qs_id":406177,"qs_pg:qs_pg_placetype":"locality","qs_pg:qs_pg_placetype_gp":"Town","qs_pg:woe_adm0":23424805,"qs_pg:woe_id":844835,"src:geom":"qs_pg","src:lbl_centroid":"qs_pg","src:population":"geonames","woe:adm0_id":23424805,"woe:name_adm0":"Eesti","woe:name_adm1":"Jõgevamaa","woe:placetype":"Town","wof:belongsto":[85683009,102191581,1713314329,85633135,1713305767],"wof:breaches":[],"wof:concordances":{"gn:id":794623,"gp:id":844835,"qs_pg:id":406177,"wd:id":"Q11187350"},"wof:coterminous":[1713314329],"wof:country":"EE","wof:created":1497297637,"wof:geomhash":"8810d63e665a6fc91f07cf28c44863f8","wof:hierarchy":[{"continent_id":102191581,"country_id":85633135,"county_id":1713305767,"localadmin_id":1713314329,"locality_id":1125956551,"region_id":85683009}],"wof:id":1125956551,"wof:lang_x_official":["est"],"wof:lang_x_spoken":["est"],"wof:lastmodified":1596676581,"wof:name":"Pööra","wof:parent_id":1713314329,"wof:placetype":"locality","wof:population":102,"wof:population_rank":1,"wof:repo":"whosonfirst-data-admin-ee","wof:superseded_by":[],"wof:supersedes":[],"wof:tags":[]},"bbox":[26.26,58.65333,26.26,58.65333],"geometry":{"coordinates":[26.26,58.65333],"type":"Point"}}