{"id":1260269297,"type":"Feature","properties":{"edtf:cessation":"uuuu","edtf:inception":"uuuu","geom:area":0,"geom:area_square_m":0,"geom:bbox":"24.72944,58.87667,24.72944,58.87667","geom:latitude":58.87667,"geom:longitude":24.72944,"gn:admin1_code":"13.0","gn:admin2_code":"668.0","gn:admin3_code":"2955.0","gn:asciiname":"Valli","gn:country_code":"EE","gn:dem":61,"gn:feature_class":"P","gn:feature_code":"PPL","gn:geonameid":587834,"gn:latitude":58.87667,"gn:longitude":24.72944,"gn:modification_date":"2017-11-25","gn:name":"Valli","gn:population":0,"gn:timezone":"Europe/Tallinn","iso:country":"EE","lbl:bbox":"24.70944,58.85667,24.74944,58.89667","lbl:max_zoom":18,"lbl:min_zoom":13.5,"mz:hierarchy_label":1,"mz:is_current":1,"mz:min_zoom":12,"name:ara_x_preferred":["فالي"],"name:est_x_preferred":["Valli"],"name:hye_x_preferred":["Վալլի"],"name:pol_x_preferred":["Valli"],"name:rus_x_preferred":["Валли"],"name:sco_x_preferred":["Valli"],"name:spa_x_preferred":["Valli"],"name:vol_x_preferred":["Valli"],"src:geom":"geonames","wof:belongsto":[85683013,102191581,1713311381,85633135,1713305711],"wof:breaches":[],"wof:concordances":{"gn:id":587834,"wk:page":"Valli%2C_Estonia"},"wof:coterminous":[1713311113],"wof:country":"EE","wof:geomhash":"77a5739646d1f77c25eddb7e08903c61","wof:hierarchy":[{"continent_id":102191581,"country_id":85633135,"county_id":1713305711,"localadmin_id":1713311381,"locality_id":1260269297,"region_id":85683013}],"wof:id":1260269297,"wof:lang_x_official":["est"],"wof:lang_x_spoken":["est"],"wof:lastmodified":1596676719,"wof:name":"Valli","wof:parent_id":1713311381,"wof:placetype":"locality","wof:repo":"whosonfirst-data-admin-ee","wof:superseded_by":[],"wof:supersedes":[],"wof:tags":[]},"bbox":[24.72944,58.87667,24.72944,58.87667],"geometry":{"coordinates":[24.72944,58.87667],"type":"Point"}}