{
  "type": "Feature",
  "properties": {
    "iso:country":"FI",
    "wof:name":"Kaivopuisto",
    "wof:placetype":"neighbourhood"
},
  "geometry": {"coordinates":[24.95853734036959,60.15825653687023],"type":"Point"}
}