{"id":1226725055,"type":"Feature","properties":{"edtf:cessation":"uuuu","edtf:inception":"uuuu","geom:area":0,"geom:area_square_m":0,"geom:bbox":"26.21694,58.03722,26.21694,58.03722","geom:latitude":58.03722,"geom:longitude":26.21694,"gn:admin1_code":"19.0","gn:admin2_code":"557.0","gn:admin3_code":"6352.0","gn:asciiname":"Ruuna","gn:country_code":"EE","gn:dem":98,"gn:feature_class":"P","gn:feature_code":"PPL","gn:geonameid":588910,"gn:latitude":58.03722,"gn:longitude":26.21694,"gn:modification_date":"2017-11-25","gn:name":"Ruuna","gn:population":0,"gn:timezone":"Europe/Tallinn","iso:country":"EE","lbl:bbox":"26.19694,58.01722,26.23694,58.05722","lbl:max_zoom":18,"lbl:min_zoom":13.5,"mz:hierarchy_label":1,"mz:is_current":1,"mz:min_zoom":12,"src:geom":"geonames","wof:belongsto":[85682941,102191581,1713307231,85633135,1713305759],"wof:breaches":[],"wof:concordances":{"gn:id":588910},"wof:coterminous":[1713309755],"wof:country":"EE","wof:geomhash":"fd8954fbf8f39e55dba9ac3ebd538b83","wof:hierarchy":[{"continent_id":102191581,"country_id":85633135,"county_id":1713305759,"localadmin_id":1713307231,"locality_id":1226725055,"region_id":85682941}],"wof:id":1226725055,"wof:lang_x_official":["est"],"wof:lang_x_spoken":["est"],"wof:lastmodified":1596661874,"wof:name":"Ruuna","wof:parent_id":1713307231,"wof:placetype":"locality","wof:repo":"whosonfirst-data-admin-ee","wof:superseded_by":[],"wof:supersedes":[],"wof:tags":[]},"bbox":[26.21694,58.03722,26.21694,58.03722],"geometry":{"coordinates":[26.21694,58.03722],"type":"Point"}}