{"id":1259944325,"type":"Feature","properties":{"edtf:cessation":"uuuu","edtf:inception":"uuuu","geom:area":0,"geom:area_square_m":0,"geom:bbox":"27.49611,57.79694,27.49611,57.79694","geom:latitude":57.79694,"geom:longitude":27.49611,"gn:admin1_code":"21.0","gn:admin2_code":"732.0","gn:admin3_code":"9208.0","gn:asciiname":"Veretina","gn:country_code":"EE","gn:dem":112,"gn:feature_class":"P","gn:feature_code":"PPL","gn:geonameid":794231,"gn:latitude":57.79694,"gn:longitude":27.49611,"gn:modification_date":"2017-11-25","gn:name":"Veretina","gn:population":0,"gn:timezone":"Europe/Tallinn","iso:country":"EE","lbl:bbox":"27.47611,57.77694,27.51611,57.81694","lbl:max_zoom":18,"lbl:min_zoom":13.5,"mz:hierarchy_label":1,"mz:is_current":1,"mz:min_zoom":12,"src:geom":"geonames","wof:belongsto":[85682955,102191581,1713316409,85633135,1713305631],"wof:breaches":[],"wof:concordances":{"gn:id":794231},"wof:coterminous":[1713316409],"wof:country":"EE","wof:geomhash":"8b4acf4053fa74ea68f33f83a2a85c8e","wof:hierarchy":[{"continent_id":102191581,"country_id":85633135,"county_id":1713305631,"localadmin_id":1713316409,"locality_id":1259944325,"region_id":85682955}],"wof:id":1259944325,"wof:lang_x_official":["est"],"wof:lang_x_spoken":["est"],"wof:lastmodified":1596663705,"wof:name":"Veretina","wof:parent_id":1713316409,"wof:placetype":"locality","wof:repo":"whosonfirst-data-admin-ee","wof:superseded_by":[],"wof:supersedes":[],"wof:tags":[]},"bbox":[27.49611,57.79694,27.49611,57.79694],"geometry":{"coordinates":[27.49611,57.79694],"type":"Point"}}