{"id":1293551891,"type":"Feature","properties":{"edtf:cessation":"uuuu","edtf:inception":"uuuu","geom:area":0,"geom:area_square_m":0,"geom:bbox":"25.87028,58.0625,25.87028,58.0625","geom:latitude":58.0625,"geom:longitude":25.87028,"gn:admin1_code":"19.0","gn:admin2_code":"824.0","gn:admin3_code":"4620.0","gn:asciiname":"Love","gn:cc2":"EE","gn:country_code":"EE","gn:dem":82,"gn:feature_class":"P","gn:feature_code":"PPL","gn:geonameid":590500,"gn:latitude":58.0625,"gn:longitude":25.87028,"gn:modification_date":"2017-11-25","gn:name":"Lõve","gn:population":0,"gn:timezone":"Europe/Tallinn","iso:country":"EE","lbl:bbox":"25.85028,58.0425,25.89028,58.0825","lbl:max_zoom":18,"lbl:min_zoom":13.5,"mz:hierarchy_label":1,"mz:is_current":1,"mz:min_zoom":12,"name:est_x_preferred":["Lõve"],"name:hye_x_preferred":["Լիվե"],"name:pol_x_preferred":["Lõve"],"name:spa_x_preferred":["Lõve"],"name:ukr_x_preferred":["Ливе"],"name:und_x_variant":["Lyve","Myza Lyve","Lõve Asundus"],"name:vol_x_preferred":["Lõve"],"src:geom":"geonames","wof:belongsto":[85682941,102191581,1713310475,85633135,1713305687],"wof:breaches":[],"wof:concordances":{"gn:id":590500,"wk:page":"L%C3%B5ve"},"wof:coterminous":[1713310475],"wof:country":"EE","wof:geomhash":"70d01d759f50328e0628a82d98be8b24","wof:hierarchy":[{"continent_id":102191581,"country_id":85633135,"county_id":1713305687,"localadmin_id":1713310475,"locality_id":1293551891,"region_id":85682941}],"wof:id":1293551891,"wof:lang_x_official":["est"],"wof:lang_x_spoken":["est"],"wof:lastmodified":1596661438,"wof:name":"Love","wof:parent_id":1713310475,"wof:placetype":"locality","wof:repo":"whosonfirst-data-admin-ee","wof:superseded_by":[],"wof:supersedes":[],"wof:tags":[]},"bbox":[25.87028,58.0625,25.87028,58.0625],"geometry":{"coordinates":[25.87028,58.0625],"type":"Point"}}