{"id":1310013355,"type":"Feature","properties":{"edtf:cessation":"uuuu","edtf:inception":"uuuu","geom:area":0,"geom:area_square_m":0,"geom:bbox":"26.92167,59.11361,26.92167,59.11361","geom:latitude":59.11361,"geom:longitude":26.92167,"gn:admin1_code":"3.0","gn:admin2_code":"130.0","gn:admin3_code":"5695.0","gn:asciiname":"Oonurme","gn:cc2":"EE","gn:country_code":"EE","gn:dem":77,"gn:feature_class":"P","gn:feature_code":"PPL","gn:geonameid":589823,"gn:latitude":59.11361,"gn:longitude":26.92167,"gn:modification_date":"2017-11-25","gn:name":"Oonurme","gn:population":0,"gn:timezone":"Europe/Tallinn","iso:country":"EE","lbl:bbox":"26.90167,59.09361,26.94167,59.13361","lbl:max_zoom":18,"lbl:min_zoom":13.5,"mz:hierarchy_label":1,"mz:is_current":1,"mz:min_zoom":12,"name:deu_x_preferred":["Oonurme"],"name:eng_x_preferred":["Oonurme"],"name:est_x_preferred":["Oonurme"],"name:hye_x_preferred":["Օոնուռմե"],"name:nld_x_preferred":["Oonurme"],"name:pol_x_preferred":["Oonurme"],"name:rus_x_preferred":["Оонурме"],"name:spa_x_preferred":["Oonurme"],"name:und_x_variant":["Onurme"],"name:vol_x_preferred":["Oonurme"],"src:geom":"geonames","wof:belongsto":[85683059,102191581,1713314433,85633135,1713305693],"wof:breaches":[],"wof:concordances":{"gn:id":589823,"wk:page":"Oonurme"},"wof:coterminous":[1713314433],"wof:country":"EE","wof:geomhash":"b3fc585bc74488556b9dd0ac4aae85f5","wof:hierarchy":[{"continent_id":102191581,"country_id":85633135,"county_id":1713305693,"localadmin_id":1713314433,"locality_id":1310013355,"region_id":85683059}],"wof:id":1310013355,"wof:lang_x_official":["est"],"wof:lang_x_spoken":["est"],"wof:lastmodified":1596660745,"wof:name":"Oonurme","wof:parent_id":1713314433,"wof:placetype":"locality","wof:repo":"whosonfirst-data-admin-ee","wof:superseded_by":[],"wof:supersedes":[],"wof:tags":[]},"bbox":[26.92167,59.11361,26.92167,59.11361],"geometry":{"coordinates":[26.92167,59.11361],"type":"Point"}}