{"id":1226712571,"type":"Feature","properties":{"edtf:cessation":"uuuu","edtf:inception":"uuuu","geom:area":0,"geom:area_square_m":0,"geom:bbox":"26.39083,58.10417,26.39083,58.10417","geom:latitude":58.10417,"geom:longitude":26.39083,"gn:admin1_code":"19.0","gn:admin2_code":"557.0","gn:admin3_code":"4959.0","gn:asciiname":"Miti","gn:country_code":"EE","gn:dem":88,"gn:feature_class":"P","gn:feature_code":"PPL","gn:geonameid":794573,"gn:latitude":58.10417,"gn:longitude":26.39083,"gn:modification_date":"2017-11-25","gn:name":"Miti","gn:population":0,"gn:timezone":"Europe/Tallinn","iso:country":"EE","lbl:bbox":"26.37083,58.08417,26.41083,58.12417","lbl:max_zoom":18,"lbl:min_zoom":13.5,"mz:hierarchy_label":1,"mz:is_current":1,"mz:min_zoom":12,"name:est_x_preferred":["Miti"],"name:hye_x_preferred":["Միտի"],"name:spa_x_preferred":["Miti"],"name:ukr_x_preferred":["Міті"],"name:vol_x_preferred":["Miti"],"src:geom":"geonames","wof:belongsto":[85682941,102191581,1713313493,85633135,1713305759],"wof:breaches":[],"wof:concordances":{"gn:id":794573,"wk:page":"Miti%2C_Estonia"},"wof:coterminous":[1713313493],"wof:country":"EE","wof:geomhash":"270194d056149078162875237088fd5b","wof:hierarchy":[{"continent_id":102191581,"country_id":85633135,"county_id":1713305759,"localadmin_id":1713313493,"locality_id":1226712571,"region_id":85682941}],"wof:id":1226712571,"wof:lang_x_official":["est"],"wof:lang_x_spoken":["est"],"wof:lastmodified":1596661871,"wof:name":"Miti","wof:parent_id":1713313493,"wof:placetype":"locality","wof:repo":"whosonfirst-data-admin-ee","wof:superseded_by":[],"wof:supersedes":[],"wof:tags":[]},"bbox":[26.39083,58.10417,26.39083,58.10417],"geometry":{"coordinates":[26.39083,58.10417],"type":"Point"}}