{"id":1125871591,"type":"Feature","properties":{"edtf:cessation":"uuuu","edtf:inception":"uuuu","geom:area":0,"geom:area_square_m":0,"geom:bbox":"24.23917,58.3975,24.23917,58.3975","geom:latitude":58.3975,"geom:longitude":24.23917,"gn:country":"EE","gn:fcode":"PPL","gn:population":168,"iso:country":"EE","lbl:bbox":"24.21917,58.3775,24.25917,58.4175","lbl:latitude":58.3975,"lbl:longitude":24.23917,"lbl:max_zoom":18,"lbl:min_zoom":13,"mz:hierarchy_label":1,"mz:is_current":1,"mz:min_zoom":11,"mz:note":"Quattroshapes Point Gazetteer import 20170519","name:bul_x_preferred":["Кихлепа"],"name:ceb_x_preferred":["Kihlepa"],"name:ces_x_preferred":["Kihlepa"],"name:eng_x_preferred":["Kihlepa"],"name:est_x_preferred":["Kihlepa"],"name:hye_x_preferred":["Կիհլեպա"],"name:nld_x_preferred":["Kihlepa"],"name:pol_x_preferred":["Kihlepa"],"name:rus_x_preferred":["Кихлепа"],"name:swe_x_preferred":["Kihlepa"],"name:und_x_variant":["Kikhlepa"],"name:vol_x_preferred":["Kihlepa"],"qs_pg:aaroncc":"EE","qs_pg:gn_country":"EE","qs_pg:gn_fcode":"PPL","qs_pg:gn_id":591419,"qs_pg:gn_pop":168,"qs_pg:name":"Kihlepa","qs_pg:name_adm0":"Eesti","qs_pg:name_adm1":"Pärnumaa","qs_pg:photos_9k":1,"qs_pg:photos_9r":1,"qs_pg:photos_all":1,"qs_pg:photos_sr":0,"qs_pg:pop_sr":1,"qs_pg:qs_id":889919,"qs_pg:qs_pg_placetype":"locality","qs_pg:qs_pg_placetype_gp":"Town","qs_pg:woe_adm0":23424805,"qs_pg:woe_id":842920,"src:geom":"qs_pg","src:lbl_centroid":"qs_pg","src:population":"geonames","woe:adm0_id":23424805,"woe:name_adm0":"Eesti","woe:name_adm1":"Pärnumaa","woe:placetype":"Town","wof:belongsto":[85682981,102191581,1713310095,85633135,1713305703],"wof:breaches":[],"wof:concordances":{"gn:id":591419,"gp:id":842920,"qs_pg:id":889919,"wd:id":"Q1954323"},"wof:coterminous":[1713310095],"wof:country":"EE","wof:created":1497294330,"wof:geomhash":"6ab2e6a6f31ae725a029aa772c71aab5","wof:hierarchy":[{"continent_id":102191581,"country_id":85633135,"county_id":1713305703,"localadmin_id":1713310095,"locality_id":1125871591,"region_id":85682981}],"wof:id":1125871591,"wof:lang_x_official":["est"],"wof:lang_x_spoken":["est"],"wof:lastmodified":1596677702,"wof:name":"Kihlepa","wof:parent_id":1713310095,"wof:placetype":"locality","wof:population":168,"wof:population_rank":1,"wof:repo":"whosonfirst-data-admin-ee","wof:superseded_by":[],"wof:supersedes":[],"wof:tags":[]},"bbox":[24.23917,58.3975,24.23917,58.3975],"geometry":{"coordinates":[24.23917,58.3975],"type":"Point"}}