{"id":1209781975,"type":"Feature","properties":{"edtf:cessation":"uuuu","edtf:inception":"uuuu","geom:area":0,"geom:area_square_m":0,"geom:bbox":"26.94222,58.28889,26.94222,58.28889","geom:latitude":58.28889,"geom:longitude":26.94222,"gn:admin1_code":"18.0","gn:admin2_code":"291.0","gn:admin3_code":"3500.0","gn:asciiname":"Kriimani","gn:country_code":"EE","gn:dem":60,"gn:feature_class":"P","gn:feature_code":"PPL","gn:geonameid":591053,"gn:latitude":58.28889,"gn:longitude":26.94222,"gn:modification_date":"2017-11-25","gn:name":"Kriimani","gn:population":0,"gn:timezone":"Europe/Tallinn","iso:country":"EE","lbl:bbox":"26.92222,58.26889,26.96222,58.30889","lbl:max_zoom":18,"lbl:min_zoom":13.5,"mz:hierarchy_label":1,"mz:is_current":1,"mz:min_zoom":12,"name:est_x_preferred":["Kriimani"],"name:fra_x_preferred":["Kriimani"],"name:hye_x_preferred":["Կռիիմանի"],"name:pol_x_preferred":["Kriimani"],"name:spa_x_preferred":["Kriimani"],"name:ukr_x_preferred":["Кріймані"],"name:vol_x_preferred":["Kriimani"],"src:geom":"geonames","wof:belongsto":[85682995,102191581,1713311321,85633135,1713305699],"wof:breaches":[],"wof:concordances":{"gn:id":591053,"wk:page":"Kriimani"},"wof:coterminous":[1713311321],"wof:country":"EE","wof:geomhash":"2e00388918e9188a305bfeef9318f435","wof:hierarchy":[{"continent_id":102191581,"country_id":85633135,"county_id":1713305699,"localadmin_id":1713311321,"locality_id":1209781975,"region_id":85682995}],"wof:id":1209781975,"wof:lang_x_official":["est"],"wof:lang_x_spoken":["est"],"wof:lastmodified":1596660662,"wof:name":"Kriimani","wof:parent_id":1713311321,"wof:placetype":"locality","wof:repo":"whosonfirst-data-admin-ee","wof:superseded_by":[],"wof:supersedes":[],"wof:tags":[]},"bbox":[26.94222,58.28889,26.94222,58.28889],"geometry":{"coordinates":[26.94222,58.28889],"type":"Point"}}