{"id":1126087287,"type":"Feature","properties":{"edtf:cessation":"uuuu","edtf:inception":"uuuu","geom:area":0,"geom:area_square_m":0,"geom:bbox":"24.86017,59.4336,24.86017,59.4336","geom:latitude":59.4336,"geom:longitude":24.86017,"gn:country":"EE","gn:fcode":"PPLX","gn:population":0,"iso:country":"EE","lbl:bbox":"24.85517,59.4286,24.86517,59.4386","lbl:latitude":59.4336,"lbl:longitude":24.86017,"lbl:max_zoom":18,"mz:hierarchy_label":1,"mz:is_current":1,"mz:min_zoom":15,"mz:note":"Quattroshapes Point Gazetteer import 20170519","name:ces_x_preferred":["Lasnamäe"],"name:deu_x_preferred":["Lasnamäe"],"name:est_x_preferred":["Lasnamäe linnaosa"],"name:fas_x_preferred":["لاسنامه"],"name:fin_x_preferred":["Lasnamäe"],"name:jpn_x_preferred":["ラスナマエ"],"name:lav_x_preferred":["Lasnamē"],"name:nld_x_preferred":["Lasnamäe"],"name:pol_x_preferred":["Lasnamäe"],"name:rus_x_preferred":["Ласнамяэ"],"name:spa_x_preferred":["Lasnamäe"],"name:swe_x_preferred":["Lasnamäe"],"name:udm_x_preferred":["Ласнамяэ"],"name:ukr_x_preferred":["Ласнамяє"],"name:urd_x_preferred":["لاسنامای"],"name:vie_x_preferred":["Lasnamäe"],"name:zho_x_preferred":["拉斯納麥埃區"],"qs_pg:aaroncc":"EE","qs_pg:gn_country":"EE","qs_pg:gn_fcode":"PPLX","qs_pg:gn_id":590775,"qs_pg:gn_pop":0,"qs_pg:name":"Lasnamäe","qs_pg:name_adm0":"Eesti","qs_pg:name_adm1":"Harjumaa","qs_pg:photos":370,"qs_pg:photos_1k":75,"qs_pg:photos_9k":2,"qs_pg:photos_9r":5,"qs_pg:photos_all":370,"qs_pg:photos_sr":6,"qs_pg:pop_sr":0,"qs_pg:qs_id":313633,"qs_pg:qs_pg_placetype":"neighbourhood","qs_pg:qs_pg_placetype_gp":"Suburb","qs_pg:woe_adm0":23424805,"qs_pg:woe_id":843526,"src:geom":"qs_pg","src:lbl_centroid":"qs_pg","woe:adm0_id":23424805,"woe:name_adm0":"Eesti","woe:name_adm1":"Harjumaa","woe:placetype":"Suburb","wof:belongsto":[85683055,102191581,1713305847,85633135,101748153,1713348895,1713305645],"wof:breaches":[],"wof:concordances":{"gn:id":590775,"gp:id":843526,"qs_pg:id":313633},"wof:country":"EE","wof:created":1497313012,"wof:geomhash":"f1118698cece9d020d6ee042f52c56bd","wof:hierarchy":[{"borough_id":1713348895,"continent_id":102191581,"country_id":85633135,"county_id":1713305645,"localadmin_id":1713305847,"locality_id":101748153,"neighbourhood_id":1126087287,"region_id":85683055}],"wof:id":1126087287,"wof:lastmodified":1596663550,"wof:name":"Lasnamäe","wof:parent_id":1713348895,"wof:placetype":"neighbourhood","wof:repo":"whosonfirst-data-admin-ee","wof:superseded_by":[],"wof:supersedes":[],"wof:tags":[]},"bbox":[24.86017,59.4336,24.86017,59.4336],"geometry":{"coordinates":[24.86017,59.4336],"type":"Point"}}