{"id":1309883999,"type":"Feature","properties":{"edtf:cessation":"uuuu","edtf:inception":"uuuu","geom:area":0,"geom:area_square_m":0,"geom:bbox":"24.81611,58.26222,24.81611,58.26222","geom:latitude":58.26222,"geom:longitude":24.81611,"gn:admin1_code":"11.0","gn:admin2_code":"712.0","gn:admin3_code":"4628.0","gn:asciiname":"Laehkma","gn:country_code":"EE","gn:dem":24,"gn:feature_class":"P","gn:feature_code":"PPL","gn:geonameid":590822,"gn:latitude":58.26222,"gn:longitude":24.81611,"gn:modification_date":"2017-11-25","gn:name":"Lähkma","gn:population":0,"gn:timezone":"Europe/Tallinn","iso:country":"EE","lbl:bbox":"24.79611,58.24222,24.83611,58.28222","lbl:max_zoom":18,"lbl:min_zoom":13.5,"mz:hierarchy_label":1,"mz:is_current":1,"mz:min_zoom":12,"name:est_x_preferred":["Lähkma"],"name:hye_x_preferred":["Լեհկմա"],"name:pol_x_preferred":["Lähkma"],"name:spa_x_preferred":["Lähkma"],"name:und_x_variant":["Lyakhkma"],"name:urd_x_preferred":["لاہکما"],"name:vol_x_preferred":["Lähkma"],"src:geom":"geonames","wof:belongsto":[85682981,102191581,1713309583,85633135,1713305705],"wof:breaches":[],"wof:concordances":{"gn:id":590822,"wk:page":"L%C3%A4hkma"},"wof:coterminous":[1713309583],"wof:country":"EE","wof:geomhash":"4b1b00c9ea404b53afb4bd99deb718bb","wof:hierarchy":[{"continent_id":102191581,"country_id":85633135,"county_id":1713305705,"localadmin_id":1713309583,"locality_id":1309883999,"region_id":85682981}],"wof:id":1309883999,"wof:lang_x_official":["est"],"wof:lang_x_spoken":["est"],"wof:lastmodified":1596677732,"wof:name":"Laehkma","wof:parent_id":1713309583,"wof:placetype":"locality","wof:repo":"whosonfirst-data-admin-ee","wof:superseded_by":[],"wof:supersedes":[],"wof:tags":[]},"bbox":[24.81611,58.26222,24.81611,58.26222],"geometry":{"coordinates":[24.81611,58.26222],"type":"Point"}}