{"id":1125788281,"type":"Feature","properties":{"edtf:cessation":"uuuu","edtf:inception":"uuuu","geom:area":0,"geom:area_square_m":0,"geom:bbox":"24.35139,59.17778,24.35139,59.17778","geom:latitude":59.17778,"geom:longitude":24.35139,"gn:country":"EE","gn:fcode":"PPL","gn:population":0,"iso:country":"EE","lbl:bbox":"24.33139,59.15778,24.37139,59.19778","lbl:latitude":59.17778,"lbl:longitude":24.35139,"lbl:max_zoom":18,"lbl:min_zoom":13.5,"mz:hierarchy_label":1,"mz:is_current":1,"mz:min_zoom":12,"mz:note":"Quattroshapes Point Gazetteer import 20170519","name:eng_x_preferred":["Hingu"],"name:est_x_preferred":["Hingu"],"name:fra_x_preferred":["Hingu"],"name:hye_x_preferred":["Հինգու"],"name:nld_x_preferred":["Hingu"],"name:pol_x_preferred":["Hingu"],"name:sco_x_preferred":["Hingu"],"name:spa_x_preferred":["Hingu"],"name:ukr_x_preferred":["Гінґу"],"name:vol_x_preferred":["Hingu"],"qs_pg:aaroncc":"EE","qs_pg:gn_country":"EE","qs_pg:gn_fcode":"PPL","qs_pg:gn_id":592120,"qs_pg:gn_pop":0,"qs_pg:name":"Hingu","qs_pg:name_adm0":"Eesti","qs_pg:name_adm1":"Harjumaa","qs_pg:photos":63,"qs_pg:photos_1k":13,"qs_pg:photos_9k":1,"qs_pg:photos_9r":2,"qs_pg:photos_all":63,"qs_pg:photos_sr":2,"qs_pg:pop_sr":0,"qs_pg:qs_id":478041,"qs_pg:qs_pg_placetype":"locality","qs_pg:qs_pg_placetype_gp":"Town","qs_pg:woe_adm0":23424805,"qs_pg:woe_id":842257,"src:geom":"qs_pg","src:lbl_centroid":"qs_pg","woe:adm0_id":23424805,"woe:name_adm0":"Eesti","woe:name_adm1":"Harjumaa","woe:placetype":"Town","wof:belongsto":[85683055,102191581,1713307889,85633135,1713305739],"wof:breaches":[],"wof:concordances":{"gn:id":592120,"gp:id":842257,"qs_pg:id":478041,"wd:id":"Q1856899"},"wof:coterminous":[1713307889],"wof:country":"EE","wof:created":1497290763,"wof:geomhash":"0ea138a8117b1c809442a51e28fc2766","wof:hierarchy":[{"continent_id":102191581,"country_id":85633135,"county_id":1713305739,"localadmin_id":1713307889,"locality_id":1125788281,"region_id":85683055}],"wof:id":1125788281,"wof:lang_x_official":["est"],"wof:lang_x_spoken":["est"],"wof:lastmodified":1596663243,"wof:name":"Hingu","wof:parent_id":1713307889,"wof:placetype":"locality","wof:repo":"whosonfirst-data-admin-ee","wof:superseded_by":[],"wof:supersedes":[],"wof:tags":[]},"bbox":[24.35139,59.17778,24.35139,59.17778],"geometry":{"coordinates":[24.35139,59.17778],"type":"Point"}}