{"id":1193101549,"type":"Feature","properties":{"edtf:cessation":"uuuu","edtf:inception":"uuuu","geom:area":0,"geom:area_square_m":0,"geom:bbox":"27.29306,57.65194,27.29306,57.65194","geom:latitude":57.65194,"geom:longitude":27.29306,"gn:admin1_code":"21.0","gn:admin2_code":"698.0","gn:admin3_code":"6592.0","gn:asciiname":"Paeltre","gn:country_code":"EE","gn:dem":198,"gn:feature_class":"P","gn:feature_code":"PPL","gn:geonameid":589570,"gn:latitude":57.65194,"gn:longitude":27.29306,"gn:modification_date":"2017-11-25","gn:name":"Pältre","gn:population":0,"gn:timezone":"Europe/Tallinn","iso:country":"EE","lbl:bbox":"27.27306,57.63194,27.31306,57.67194","lbl:max_zoom":18,"lbl:min_zoom":13.5,"mz:hierarchy_label":1,"mz:is_current":1,"mz:min_zoom":12,"name:est_x_preferred":["Pältre"],"name:hye_x_preferred":["Պելտռե"],"name:pol_x_preferred":["Pältre"],"name:spa_x_preferred":["Pältre"],"name:ukr_x_preferred":["Пялтре"],"name:und_x_variant":["Pärtli","Pältri","Pyartli"],"name:vol_x_preferred":["Pältre"],"src:geom":"geonames","wof:belongsto":[85682937,102191581,1713315809,85633135,1713305787],"wof:breaches":[],"wof:concordances":{"gn:id":589570,"wk:page":"P%C3%A4ltre"},"wof:coterminous":[1713315809],"wof:country":"EE","wof:geomhash":"3e5a505cb7c219838eb2687e63f03555","wof:hierarchy":[{"continent_id":102191581,"country_id":85633135,"county_id":1713305787,"localadmin_id":1713315809,"locality_id":1193101549,"region_id":85682937}],"wof:id":1193101549,"wof:lang_x_official":["est"],"wof:lang_x_spoken":["est"],"wof:lastmodified":1596676884,"wof:name":"Paeltre","wof:parent_id":1713315809,"wof:placetype":"locality","wof:repo":"whosonfirst-data-admin-ee","wof:superseded_by":[],"wof:supersedes":[],"wof:tags":[]},"bbox":[27.29306,57.65194,27.29306,57.65194],"geometry":{"coordinates":[27.29306,57.65194],"type":"Point"}}