{"id":1259604515,"type":"Feature","properties":{"edtf:cessation":"uuuu","edtf:inception":"uuuu","geom:area":0,"geom:area_square_m":0,"geom:bbox":"23.61889,58.91306,23.61889,58.91306","geom:latitude":58.91306,"geom:longitude":23.61889,"gn:admin1_code":"7.0","gn:admin2_code":"184.0","gn:admin3_code":"1658.0","gn:asciiname":"Espre","gn:country_code":"EE","gn:dem":15,"gn:feature_class":"P","gn:feature_code":"PPL","gn:geonameid":592241,"gn:latitude":58.91306,"gn:longitude":23.61889,"gn:modification_date":"2017-11-25","gn:name":"Espre","gn:population":0,"gn:timezone":"Europe/Tallinn","iso:country":"EE","lbl:bbox":"23.59889,58.89306,23.63889,58.93306","lbl:max_zoom":18,"lbl:min_zoom":13.5,"mz:hierarchy_label":1,"mz:is_current":1,"mz:min_zoom":12,"name:deu_x_preferred":["Espre"],"name:est_x_preferred":["Espre"],"name:hye_x_preferred":["Էսպռե"],"name:pol_x_preferred":["Espre"],"name:ukr_x_preferred":["Еспре"],"name:vol_x_preferred":["Espre"],"src:geom":"geonames","wof:belongsto":[85683001,102191581,1713308501,85633135,1713305755],"wof:breaches":[],"wof:concordances":{"gn:id":592241,"wk:page":"Espre"},"wof:coterminous":[1713308501],"wof:country":"EE","wof:geomhash":"f7c7a457b6fde28426189201f615ac2d","wof:hierarchy":[{"continent_id":102191581,"country_id":85633135,"county_id":1713305755,"localadmin_id":1713308501,"locality_id":1259604515,"region_id":85683001}],"wof:id":1259604515,"wof:lang_x_official":["est"],"wof:lang_x_spoken":["est"],"wof:lastmodified":1596662768,"wof:name":"Espre","wof:parent_id":1713308501,"wof:placetype":"locality","wof:repo":"whosonfirst-data-admin-ee","wof:superseded_by":[],"wof:supersedes":[],"wof:tags":[]},"bbox":[23.61889,58.91306,23.61889,58.91306],"geometry":{"coordinates":[23.61889,58.91306],"type":"Point"}}