{"id":1276213839,"type":"Feature","properties":{"edtf:cessation":"uuuu","edtf:inception":"uuuu","geom:area":0,"geom:area_square_m":0,"geom:bbox":"27.10806,58.23722,27.10806,58.23722","geom:latitude":58.23722,"geom:longitude":27.10806,"gn:admin1_code":"12.0","gn:admin2_code":"622.0","gn:admin3_code":"1980.0","gn:asciiname":"Ibaste","gn:country_code":"EE","gn:dem":42,"gn:feature_class":"P","gn:feature_code":"PPL","gn:geonameid":794141,"gn:latitude":58.23722,"gn:longitude":27.10806,"gn:modification_date":"2017-11-25","gn:name":"Ibaste","gn:population":0,"gn:timezone":"Europe/Tallinn","iso:country":"EE","lbl:bbox":"27.08806,58.21722,27.12806,58.25722","lbl:max_zoom":18,"lbl:min_zoom":13.5,"mz:hierarchy_label":1,"mz:is_current":1,"mz:min_zoom":12,"name:deu_x_preferred":["Ibaste"],"name:est_x_preferred":["Ibaste"],"name:hye_x_preferred":["Իբաստե"],"name:pol_x_preferred":["Ibaste"],"name:spa_x_preferred":["Ibaste"],"name:ukr_x_preferred":["Ібасте"],"name:vol_x_preferred":["Ibaste"],"src:geom":"geonames","wof:belongsto":[85682955,102191581,1713314013,85633135,1713305791],"wof:breaches":[],"wof:concordances":{"gn:id":794141,"wk:page":"Ibaste"},"wof:coterminous":[1713314013],"wof:country":"EE","wof:geomhash":"18605f83130698de9000fc3b7ca668cc","wof:hierarchy":[{"continent_id":102191581,"country_id":85633135,"county_id":1713305791,"localadmin_id":1713314013,"locality_id":1276213839,"region_id":85682955}],"wof:id":1276213839,"wof:lang_x_official":["est"],"wof:lang_x_spoken":["est"],"wof:lastmodified":1596676966,"wof:name":"Ibaste","wof:parent_id":1713314013,"wof:placetype":"locality","wof:repo":"whosonfirst-data-admin-ee","wof:superseded_by":[],"wof:supersedes":[],"wof:tags":[]},"bbox":[27.10806,58.23722,27.10806,58.23722],"geometry":{"coordinates":[27.10806,58.23722],"type":"Point"}}