{"id":1243145885,"type":"Feature","properties":{"edtf:cessation":"uuuu","edtf:inception":"uuuu","geom:area":0,"geom:area_square_m":0,"geom:bbox":"22.07083,58.27639,22.07083,58.27639","geom:latitude":58.27639,"geom:longitude":22.07083,"gn:admin1_code":"14.0","gn:admin2_code":"714.0","gn:admin3_code":"9093.0","gn:asciiname":"Kaerdu","gn:country_code":"EE","gn:dem":28,"gn:feature_class":"P","gn:feature_code":"PPL","gn:geonameid":591630,"gn:latitude":58.27639,"gn:longitude":22.07083,"gn:modification_date":"2017-11-25","gn:name":"Kärdu","gn:population":0,"gn:timezone":"Europe/Tallinn","iso:country":"EE","lbl:bbox":"22.05083,58.25639,22.09083,58.29639","lbl:max_zoom":18,"lbl:min_zoom":13.5,"mz:hierarchy_label":1,"mz:is_current":1,"mz:min_zoom":12,"name:est_x_preferred":["Kärdu"],"name:fra_x_preferred":["Kärdu"],"name:hye_x_preferred":["Կեռդու"],"name:pol_x_preferred":["Kärdu"],"name:ukr_x_preferred":["Кярду"],"name:und_x_variant":["Kyardu"],"name:vol_x_preferred":["Kärdu"],"src:geom":"geonames","wof:belongsto":[85682947,102191581,1713308525,85633135,1713305627],"wof:breaches":[],"wof:concordances":{"gn:id":591630,"wk:page":"K%C3%A4rdu%2C_L%C3%BCmanda_Parish"},"wof:country":"EE","wof:geomhash":"67d25692dd986a427f10e9432f0bee24","wof:hierarchy":[{"continent_id":102191581,"country_id":85633135,"county_id":1713305627,"localadmin_id":1713308525,"locality_id":1243145885,"region_id":85682947}],"wof:id":1243145885,"wof:lang_x_official":["est"],"wof:lang_x_spoken":["est"],"wof:lastmodified":1596674957,"wof:name":"Kaerdu","wof:parent_id":1713308525,"wof:placetype":"locality","wof:repo":"whosonfirst-data-admin-ee","wof:superseded_by":[],"wof:supersedes":[],"wof:tags":[]},"bbox":[22.07083,58.27639,22.07083,58.27639],"geometry":{"coordinates":[22.07083,58.27639],"type":"Point"}}