{"id":1327357685,"type":"Feature","properties":{"edtf:cessation":"uuuu","edtf:inception":"uuuu","geom:area":0,"geom:area_square_m":0,"geom:bbox":"25.45472,58.90556,25.45472,58.90556","geom:latitude":58.90556,"geom:longitude":25.45472,"gn:admin1_code":"4.0","gn:admin2_code":"834.0","gn:admin3_code":"9656.0","gn:asciiname":"Vaeljataguse","gn:country_code":"EE","gn:dem":67,"gn:feature_class":"P","gn:feature_code":"PPL","gn:geonameid":793310,"gn:latitude":58.90556,"gn:longitude":25.45472,"gn:modification_date":"2017-11-25","gn:name":"Väljataguse","gn:population":0,"gn:timezone":"Europe/Tallinn","iso:country":"EE","lbl:bbox":"25.43472,58.88556,25.47472,58.92556","lbl:max_zoom":18,"lbl:min_zoom":13.5,"mz:hierarchy_label":1,"mz:is_current":1,"mz:min_zoom":12,"src:geom":"geonames","wof:belongsto":[85683031,102191581,1713315893,85633135,1713305773],"wof:breaches":[],"wof:concordances":{"gn:id":793310},"wof:coterminous":[1713315893],"wof:country":"EE","wof:geomhash":"2b12689e21b8b67366c235dc0b929459","wof:hierarchy":[{"continent_id":102191581,"country_id":85633135,"county_id":1713305773,"localadmin_id":1713315893,"locality_id":1327357685,"region_id":85683031}],"wof:id":1327357685,"wof:lang_x_official":["est"],"wof:lang_x_spoken":["est"],"wof:lastmodified":1596677997,"wof:name":"Vaeljataguse","wof:parent_id":1713315893,"wof:placetype":"locality","wof:repo":"whosonfirst-data-admin-ee","wof:superseded_by":[],"wof:supersedes":[],"wof:tags":[]},"bbox":[25.45472,58.90556,25.45472,58.90556],"geometry":{"coordinates":[25.45472,58.90556],"type":"Point"}}