{"id":1310125901,"type":"Feature","properties":{"edtf:cessation":"uuuu","edtf:inception":"uuuu","geom:area":0,"geom:area_square_m":0,"geom:bbox":"26.59278,59.30278,26.59278,59.30278","geom:latitude":59.30278,"geom:longitude":26.59278,"gn:admin1_code":"8.0","gn:admin2_code":"901.0","gn:admin3_code":"5465.0","gn:asciiname":"Kaasiksoo","gn:country_code":"EE","gn:dem":86,"gn:feature_class":"P","gn:feature_code":"PPL","gn:geonameid":591837,"gn:latitude":59.30278,"gn:longitude":26.59278,"gn:modification_date":"2017-11-25","gn:name":"Kaasiksoo","gn:population":0,"gn:timezone":"Europe/Tallinn","iso:country":"EE","lbl:bbox":"26.57278,59.28278,26.61278,59.32278","lbl:max_zoom":18,"lbl:min_zoom":13.5,"mz:hierarchy_label":1,"mz:is_current":1,"mz:min_zoom":12,"name:und_x_variant":["Kasikso","Kaasiksoo"],"src:geom":"geonames","wof:belongsto":[85683049,102191581,1713308061,85633135,1713305771],"wof:breaches":[],"wof:concordances":{"gn:id":591837},"wof:country":"EE","wof:geomhash":"24724b548985d241af6911c4e0b3e8f9","wof:hierarchy":[{"continent_id":102191581,"country_id":85633135,"county_id":1713305771,"localadmin_id":1713308061,"locality_id":1310125901,"region_id":85683049}],"wof:id":1310125901,"wof:lang_x_official":["est"],"wof:lang_x_spoken":["est"],"wof:lastmodified":1596677963,"wof:name":"Kaasiksoo","wof:parent_id":1713308061,"wof:placetype":"locality","wof:repo":"whosonfirst-data-admin-ee","wof:superseded_by":[],"wof:supersedes":[],"wof:tags":[]},"bbox":[26.59278,59.30278,26.59278,59.30278],"geometry":{"coordinates":[26.59278,59.30278],"type":"Point"}}