{"id":1125950965,"type":"Feature","properties":{"edtf:cessation":"uuuu","edtf:inception":"uuuu","geom:area":0,"geom:area_square_m":0,"geom:bbox":"24.18139,59.33111,24.18139,59.33111","geom:latitude":59.33111,"geom:longitude":24.18139,"gn:country":"EE","gn:fcode":"PPL","gn:population":0,"iso:country":"EE","lbl:bbox":"24.16139,59.31111,24.20139,59.35111","lbl:latitude":59.33111,"lbl:longitude":24.18139,"lbl:max_zoom":18,"lbl:min_zoom":13.5,"mz:hierarchy_label":1,"mz:is_current":1,"mz:min_zoom":12,"mz:note":"Quattroshapes Point Gazetteer import 20170519","name:eng_x_preferred":["Põllküla"],"name:est_x_preferred":["Põllküla"],"name:fin_x_preferred":["Põllküla"],"name:fra_x_preferred":["Põllküla"],"name:hye_x_preferred":["Պիլլկյուլա"],"name:nld_x_preferred":["Põllküla"],"name:pol_x_preferred":["Põllküla"],"name:spa_x_preferred":["Põllküla"],"name:swe_x_preferred":["Põllküla"],"name:ukr_x_preferred":["Пиллкюла"],"name:vol_x_preferred":["Põllküla"],"qs_pg:aaroncc":"EE","qs_pg:gn_country":"EE","qs_pg:gn_fcode":"PPL","qs_pg:gn_id":794934,"qs_pg:gn_pop":0,"qs_pg:name":"Põllküla","qs_pg:name_adm0":"Eesti","qs_pg:name_adm1":"Harjumaa","qs_pg:photos":14,"qs_pg:photos_1k":3,"qs_pg:photos_9k":1,"qs_pg:photos_9r":1,"qs_pg:photos_all":14,"qs_pg:photos_sr":1,"qs_pg:pop_sr":0,"qs_pg:qs_id":57565,"qs_pg:qs_pg_placetype":"locality","qs_pg:qs_pg_placetype_gp":"Town","qs_pg:woe_adm0":23424805,"qs_pg:woe_id":844823,"src:geom":"qs_pg","src:lbl_centroid":"qs_pg","woe:adm0_id":23424805,"woe:name_adm0":"Eesti","woe:name_adm1":"Harjumaa","woe:placetype":"Town","wof:belongsto":[85683055,102191581,1713307717,85633135,1713305737],"wof:breaches":[],"wof:concordances":{"gn:id":794934,"gp:id":844823,"qs_pg:id":57565,"wd:id":"Q3470794"},"wof:coterminous":[1713307921],"wof:country":"EE","wof:created":1497297454,"wof:geomhash":"422646532442032dab656425c99e9c5b","wof:hierarchy":[{"continent_id":102191581,"country_id":85633135,"county_id":1713305737,"localadmin_id":1713307717,"locality_id":1125950965,"region_id":85683055}],"wof:id":1125950965,"wof:lang_x_official":["est"],"wof:lang_x_spoken":["est"],"wof:lastmodified":1596663325,"wof:name":"Põllküla","wof:parent_id":1713307717,"wof:placetype":"locality","wof:repo":"whosonfirst-data-admin-ee","wof:superseded_by":[],"wof:supersedes":[],"wof:tags":[]},"bbox":[24.18139,59.33111,24.18139,59.33111],"geometry":{"coordinates":[24.18139,59.33111],"type":"Point"}}