{"id":1276848969,"type":"Feature","properties":{"edtf:cessation":"uuuu","edtf:inception":"uuuu","geom:area":0,"geom:area_square_m":0,"geom:bbox":"24.73417,58.42056,24.73417,58.42056","geom:latitude":58.42056,"geom:longitude":24.73417,"gn:admin1_code":"11.0","gn:admin2_code":"809.0","gn:admin3_code":"8730.0","gn:asciiname":"Veski","gn:country_code":"EE","gn:dem":15,"gn:feature_class":"P","gn:feature_code":"PPL","gn:geonameid":8620350,"gn:latitude":58.42056,"gn:longitude":24.73417,"gn:modification_date":"2017-11-25","gn:name":"Veski","gn:population":0,"gn:timezone":"Europe/Tallinn","iso:country":"EE","lbl:bbox":"24.71417,58.40056,24.75417,58.44056","lbl:max_zoom":18,"lbl:min_zoom":13.5,"mz:hierarchy_label":1,"mz:is_current":1,"mz:min_zoom":12,"name:deu_x_preferred":["Veski"],"name:est_x_preferred":["Veski"],"name:pol_x_preferred":["Veski"],"name:rus_x_preferred":["Вески"],"name:sco_x_preferred":["Veski"],"name:und_x_variant":["Veske"],"src:geom":"geonames","wof:belongsto":[85682981,102191581,1713312377,85633135,1713305731],"wof:breaches":[],"wof:concordances":{"gn:id":8620350},"wof:country":"EE","wof:geomhash":"abd356102f6122f70ffcef9093f98ce9","wof:hierarchy":[{"continent_id":102191581,"country_id":85633135,"county_id":1713305731,"localadmin_id":1713312377,"locality_id":1276848969,"region_id":85682981}],"wof:id":1276848969,"wof:lang_x_official":["est"],"wof:lang_x_spoken":["est"],"wof:lastmodified":1596663391,"wof:name":"Veski","wof:parent_id":1713312377,"wof:placetype":"locality","wof:repo":"whosonfirst-data-admin-ee","wof:superseded_by":[],"wof:supersedes":[],"wof:tags":[]},"bbox":[24.73417,58.42056,24.73417,58.42056],"geometry":{"coordinates":[24.73417,58.42056],"type":"Point"}}