{"id":85901483,"type":"Feature","properties":{"edtf:cessation":"uuuu","edtf:inception":"uuuu","geom:area":0,"geom:area_square_m":0,"geom:bbox":"26.352503,59.35124,26.352503,59.35124","geom:latitude":59.35124,"geom:longitude":26.352503,"gn:latitude":59.36667,"gn:longitude":26.35,"iso:country":"EE","lbl:bbox":"26.347503,59.34624,26.357503,59.35624","lbl:latitude":59.35124,"lbl:longitude":26.352503,"lbl:max_zoom":18,"mps:latitude":59.354195,"mps:longitude":26.357696,"mz:hierarchy_label":0,"mz:is_current":1,"mz:is_funky":0,"mz:is_hard_boundary":0,"mz:is_landuse_aoi":0,"mz:is_official":0,"mz:max_zoom":18,"mz:min_zoom":14,"mz:tier_locality":1,"name:est_x_preferred":["Papiaru"],"name:pol_x_preferred":["Papiaru"],"name:vol_x_preferred":["Papiaru"],"qs:gn_adm0_cc":"EE","qs:gn_fcode":"PPLX","qs:gn_local":589165,"qs:gn_nam_loc":"Rakvere, Rakvere, L채채ne-Virumaa, EE","qs:gn_namadm1":"08","qs:gn_name":"Papiaru","qs:local_max":127,"qs:local_sum":127,"qs:localhoods":1,"qs:name":"Papiaru","qs:name_adm0":"Eesti","qs:name_adm1":"L채채ne-Virumaa","qs:name_adm2":"Rakvere Vald","qs:name_local":"Rakvere","qs:photo_max":22,"qs:photo_sum":127,"qs:placetype":"Suburb","qs:quad_count":23,"qs:woe_adm0":23424805,"qs:woe_adm1":2345282,"qs:woe_adm2":29389765,"qs:woe_lau":0,"qs:woe_local":845029,"qs:woe_ver":"7.10.0","src:geom":"mz","src:geom_alt":["quattroshapes_pg","quattroshapes"],"src:lbl_centroid":"yerbashapes","wd:wordcount":28,"wof:belongsto":[85683049,102191581,1713314069,85633135,101839837,1713305667],"wof:breaches":[],"wof:concordances":{"gn:id":589619,"gp:id":844599,"qs_pg:id":894610},"wof:country":"EE","wof:geom_alt":["quattroshapes_pg","quattroshapes"],"wof:geomhash":"31edf4fb67461aad8ff18441fedc1030","wof:hierarchy":[{"continent_id":102191581,"country_id":85633135,"county_id":1713305667,"localadmin_id":1713314069,"locality_id":101839837,"neighbourhood_id":85901483,"region_id":85683049}],"wof:id":85901483,"wof:lang":["unk"],"wof:lastmodified":1596661278,"wof:name":"Papiaru","wof:parent_id":101839837,"wof:placetype":"neighbourhood","wof:repo":"whosonfirst-data-admin-ee","wof:superseded_by":[],"wof:supersedes":[],"wof:tags":[]},"bbox":[26.352503,59.35124,26.352503,59.35124],"geometry":{"coordinates":[26.352503,59.35124],"type":"Point"}}