{"id":1344268733,"type":"Feature","properties":{"edtf:cessation":"uuuu","edtf:inception":"uuuu","geom:area":0,"geom:area_square_m":0,"geom:bbox":"26.88361,58.94972,26.88361,58.94972","geom:latitude":58.94972,"geom:longitude":26.88361,"gn:admin1_code":"5.0","gn:admin2_code":"486.0","gn:admin3_code":"3819.0","gn:asciiname":"Korve","gn:country_code":"EE","gn:dem":52,"gn:feature_class":"P","gn:feature_code":"PPL","gn:geonameid":793398,"gn:latitude":58.94972,"gn:longitude":26.88361,"gn:modification_date":"2017-11-25","gn:name":"Kõrve","gn:population":0,"gn:timezone":"Europe/Tallinn","iso:country":"EE","lbl:bbox":"26.86361,58.92972,26.90361,58.96972","lbl:max_zoom":18,"lbl:min_zoom":13.5,"mz:hierarchy_label":1,"mz:is_current":1,"mz:min_zoom":12,"name:und_x_variant":["Kõrve"],"src:geom":"geonames","wof:belongsto":[85683059,102191581,1713312061,85633135,1713305677],"wof:breaches":[],"wof:concordances":{"gn:id":793398,"wk:page":"K%C3%B5rve%2C_Ida-Viru_County"},"wof:coterminous":[1713312061],"wof:country":"EE","wof:geomhash":"3418954f046e22076412c26d02d1adde","wof:hierarchy":[{"continent_id":102191581,"country_id":85633135,"county_id":1713305677,"localadmin_id":1713312061,"locality_id":1344268733,"region_id":85683059}],"wof:id":1344268733,"wof:lang_x_official":["est"],"wof:lang_x_spoken":["est"],"wof:lastmodified":1596661036,"wof:name":"Korve","wof:parent_id":1713312061,"wof:placetype":"locality","wof:repo":"whosonfirst-data-admin-ee","wof:superseded_by":[],"wof:supersedes":[],"wof:tags":[]},"bbox":[26.88361,58.94972,26.88361,58.94972],"geometry":{"coordinates":[26.88361,58.94972],"type":"Point"}}