{"id":1125788251,"type":"Feature","properties":{"edtf:cessation":"uuuu","edtf:inception":"uuuu","geom:area":0,"geom:area_square_m":0,"geom:bbox":"25.17813,59.45365,25.17813,59.45365","geom:latitude":59.45365,"geom:longitude":25.17813,"gn:country":"EE","gn:fcode":"PPL","gn:population":0,"iso:country":"EE","lbl:bbox":"25.15813,59.43365,25.19813,59.47365","lbl:latitude":59.45365,"lbl:longitude":25.17813,"lbl:max_zoom":18,"lbl:min_zoom":13.5,"mz:hierarchy_label":1,"mz:is_current":1,"mz:min_zoom":12,"mz:note":"Quattroshapes Point Gazetteer import 20170519","name:est_x_preferred":["Jägala-Joa"],"name:fra_x_preferred":["Jägala-Joa"],"name:hye_x_preferred":["Եգալա-Յոա"],"name:nld_x_preferred":["Jägala-Joa"],"name:pol_x_preferred":["Jägala-Joa"],"name:spa_x_preferred":["Jägala-Joa"],"name:und_x_variant":["Maardu"],"name:urd_x_preferred":["جاگلہ-جوا"],"name:vol_x_preferred":["Jägala-Joa"],"qs_pg:aaroncc":"EE","qs_pg:gn_country":"EE","qs_pg:gn_fcode":"PPL","qs_pg:gn_id":591938,"qs_pg:gn_pop":0,"qs_pg:name":"Jägala-Joa","qs_pg:name_adm0":"Eesti","qs_pg:name_adm1":"Harjumaa","qs_pg:photos":223,"qs_pg:photos_1k":45,"qs_pg:photos_9k":1,"qs_pg:photos_9r":4,"qs_pg:photos_all":223,"qs_pg:photos_sr":4,"qs_pg:pop_sr":0,"qs_pg:qs_id":478039,"qs_pg:qs_pg_placetype":"locality","qs_pg:qs_pg_placetype_gp":"Town","qs_pg:woe_adm0":23424805,"qs_pg:woe_id":842384,"src:geom":"qs_pg","src:lbl_centroid":"qs_pg","woe:adm0_id":23424805,"woe:name_adm0":"Eesti","woe:name_adm1":"Harjumaa","woe:placetype":"Town","wof:belongsto":[85683055,102191581,1713305987,85633135,1713305689],"wof:breaches":[],"wof:concordances":{"gn:id":591938,"gp:id":842384,"qs_pg:id":478039},"wof:coterminous":[1713305987],"wof:country":"EE","wof:created":1497290761,"wof:geomhash":"edc1c193b3279ff9bc7276c16a1539f9","wof:hierarchy":[{"continent_id":102191581,"country_id":85633135,"county_id":1713305689,"localadmin_id":1713305987,"locality_id":1125788251,"region_id":85683055}],"wof:id":1125788251,"wof:lang_x_official":["est"],"wof:lang_x_spoken":["est"],"wof:lastmodified":1596661391,"wof:name":"Jägala-Joa","wof:parent_id":1713305987,"wof:placetype":"locality","wof:repo":"whosonfirst-data-admin-ee","wof:superseded_by":[],"wof:supersedes":[],"wof:tags":[]},"bbox":[25.17813,59.45365,25.17813,59.45365],"geometry":{"coordinates":[25.17813,59.45365],"type":"Point"}}