{"id":1310659639,"type":"Feature","properties":{"edtf:cessation":"uuuu","edtf:inception":"uuuu","geom:area":0,"geom:area_square_m":0,"geom:bbox":"26.58667,57.8525,26.58667,57.8525","geom:latitude":57.8525,"geom:longitude":26.58667,"gn:admin1_code":"21.0","gn:admin2_code":"142.0","gn:admin3_code":"8801.0","gn:asciiname":"Puustuso","gn:country_code":"EE","gn:dem":95,"gn:feature_class":"P","gn:feature_code":"PPL","gn:geonameid":8619769,"gn:latitude":57.8525,"gn:longitude":26.58667,"gn:modification_date":"2017-11-25","gn:name":"Puustusõ","gn:population":0,"gn:timezone":"Europe/Tallinn","iso:country":"EE","lbl:bbox":"26.56667,57.8325,26.60667,57.8725","lbl:max_zoom":18,"lbl:min_zoom":13.5,"mz:hierarchy_label":1,"mz:is_current":1,"mz:min_zoom":12,"name:und_x_variant":["Puustusõ","Puustuse"],"src:geom":"geonames","wof:belongsto":[85682937,102191581,1713313087,85633135,1713305795],"wof:breaches":[],"wof:concordances":{"gn:id":8619769},"wof:country":"EE","wof:geomhash":"b9b8dcd2462c3c496071dc9ee902cf60","wof:hierarchy":[{"continent_id":102191581,"country_id":85633135,"county_id":1713305795,"localadmin_id":1713313087,"locality_id":1310659639,"region_id":85682937}],"wof:id":1310659639,"wof:lang_x_official":["est"],"wof:lang_x_spoken":["est"],"wof:lastmodified":1596677024,"wof:name":"Puustuso","wof:parent_id":1713313087,"wof:placetype":"locality","wof:repo":"whosonfirst-data-admin-ee","wof:superseded_by":[],"wof:supersedes":[],"wof:tags":[]},"bbox":[26.58667,57.8525,26.58667,57.8525],"geometry":{"coordinates":[26.58667,57.8525],"type":"Point"}}