{"id":1192980297,"type":"Feature","properties":{"edtf:cessation":"uuuu","edtf:inception":"uuuu","geom:area":0,"geom:area_square_m":0,"geom:bbox":"25.89667,58.24528,25.89667,58.24528","geom:latitude":58.24528,"geom:longitude":25.89667,"gn:admin1_code":"20.0","gn:admin2_code":"899.0","gn:admin3_code":"7750.0","gn:asciiname":"Sooviku","gn:country_code":"EE","gn:dem":51,"gn:feature_class":"P","gn:feature_code":"PPL","gn:geonameid":793941,"gn:latitude":58.24528,"gn:longitude":25.89667,"gn:modification_date":"2017-11-25","gn:name":"Sooviku","gn:population":0,"gn:timezone":"Europe/Tallinn","iso:country":"EE","lbl:bbox":"25.87667,58.22528,25.91667,58.26528","lbl:max_zoom":18,"lbl:min_zoom":13.5,"mz:hierarchy_label":1,"mz:is_current":1,"mz:min_zoom":12,"name:ces_x_preferred":["Sooviku"],"name:est_x_preferred":["Sooviku"],"name:hye_x_preferred":["Սոովիկու"],"name:pol_x_preferred":["Sooviku"],"name:spa_x_preferred":["Sooviku"],"name:ukr_x_preferred":["Соовіку"],"name:vol_x_preferred":["Sooviku"],"src:geom":"geonames","wof:belongsto":[85682985,102191581,1713309819,85633135,1713305669],"wof:breaches":[],"wof:concordances":{"gn:id":793941},"wof:coterminous":[1713309819],"wof:country":"EE","wof:geomhash":"842253bfde71d01449dcce5afc02b53f","wof:hierarchy":[{"continent_id":102191581,"country_id":85633135,"county_id":1713305669,"localadmin_id":1713309819,"locality_id":1192980297,"region_id":85682985}],"wof:id":1192980297,"wof:lang_x_official":["est"],"wof:lang_x_spoken":["est"],"wof:lastmodified":1596661256,"wof:name":"Sooviku","wof:parent_id":1713309819,"wof:placetype":"locality","wof:repo":"whosonfirst-data-admin-ee","wof:superseded_by":[],"wof:supersedes":[],"wof:tags":[]},"bbox":[25.89667,58.24528,25.89667,58.24528],"geometry":{"coordinates":[25.89667,58.24528],"type":"Point"}}