{"id":1243243709,"type":"Feature","properties":{"edtf:cessation":"uuuu","edtf:inception":"uuuu","geom:area":0,"geom:area_square_m":0,"geom:bbox":"27.48861,58.06778,27.48861,58.06778","geom:latitude":58.06778,"geom:longitude":27.48861,"gn:admin1_code":"12.0","gn:admin2_code":"708.0","gn:admin3_code":"7975.0","gn:asciiname":"Suelgoja","gn:country_code":"EE","gn:dem":50,"gn:feature_class":"P","gn:feature_code":"PPL","gn:geonameid":794157,"gn:latitude":58.06778,"gn:longitude":27.48861,"gn:modification_date":"2017-11-25","gn:name":"Sülgoja","gn:population":0,"gn:timezone":"Europe/Tallinn","iso:country":"EE","lbl:bbox":"27.46861,58.04778,27.50861,58.08778","lbl:max_zoom":18,"lbl:min_zoom":13.5,"mz:hierarchy_label":1,"mz:is_current":1,"mz:min_zoom":12,"name:est_x_preferred":["Sülgoja"],"name:hye_x_preferred":["Սյուլգոյա"],"name:spa_x_preferred":["Sülgoja"],"name:ukr_x_preferred":["Сюлгоя"],"name:vol_x_preferred":["Sülgoja"],"src:geom":"geonames","wof:belongsto":[85682955,102191581,1713315947,85633135,1713305793],"wof:breaches":[],"wof:concordances":{"gn:id":794157,"wk:page":"S%C3%BClgoja"},"wof:coterminous":[1713315947],"wof:country":"EE","wof:geomhash":"beb7f555a570b14534db427ef9193766","wof:hierarchy":[{"continent_id":102191581,"country_id":85633135,"county_id":1713305793,"localadmin_id":1713315947,"locality_id":1243243709,"region_id":85682955}],"wof:id":1243243709,"wof:lang_x_official":["est"],"wof:lang_x_spoken":["est"],"wof:lastmodified":1596677001,"wof:name":"Suelgoja","wof:parent_id":1713315947,"wof:placetype":"locality","wof:repo":"whosonfirst-data-admin-ee","wof:superseded_by":[],"wof:supersedes":[],"wof:tags":[]},"bbox":[27.48861,58.06778,27.48861,58.06778],"geometry":{"coordinates":[27.48861,58.06778],"type":"Point"}}