{"id":1293464915,"type":"Feature","properties":{"edtf:cessation":"uuuu","edtf:inception":"uuuu","geom:area":0,"geom:area_square_m":0,"geom:bbox":"26.11917,57.97583,26.11917,57.97583","geom:latitude":57.97583,"geom:longitude":26.11917,"gn:admin1_code":"19.0","gn:admin2_code":"855.0","gn:admin3_code":"5096.0","gn:asciiname":"Mustumetsa","gn:country_code":"EE","gn:dem":73,"gn:feature_class":"P","gn:feature_code":"PPL","gn:geonameid":794542,"gn:latitude":57.97583,"gn:longitude":26.11917,"gn:modification_date":"2017-11-25","gn:name":"Mustumetsa","gn:population":0,"gn:timezone":"Europe/Tallinn","iso:country":"EE","lbl:bbox":"26.09917,57.95583,26.13917,57.99583","lbl:max_zoom":18,"lbl:min_zoom":13.5,"mz:hierarchy_label":1,"mz:is_current":1,"mz:min_zoom":12,"src:geom":"geonames","wof:belongsto":[85682941,102191581,1713310583,85633135,1713305753],"wof:breaches":[],"wof:concordances":{"gn:id":794542},"wof:coterminous":[1713310583],"wof:country":"EE","wof:geomhash":"6124f08b4aea5169e6b1200d156dbfda","wof:hierarchy":[{"continent_id":102191581,"country_id":85633135,"county_id":1713305753,"localadmin_id":1713310583,"locality_id":1293464915,"region_id":85682941}],"wof:id":1293464915,"wof:lang_x_official":["est"],"wof:lang_x_spoken":["est"],"wof:lastmodified":1596661954,"wof:name":"Mustumetsa","wof:parent_id":1713310583,"wof:placetype":"locality","wof:repo":"whosonfirst-data-admin-ee","wof:superseded_by":[],"wof:supersedes":[],"wof:tags":[]},"bbox":[26.11917,57.97583,26.11917,57.97583],"geometry":{"coordinates":[26.11917,57.97583],"type":"Point"}}