{"id":1259404995,"type":"Feature","properties":{"edtf:cessation":"uuuu","edtf:inception":"uuuu","geom:area":0,"geom:area_square_m":0,"geom:bbox":"25.97944,59.61222,25.97944,59.61222","geom:latitude":59.61222,"geom:longitude":25.97944,"gn:admin1_code":"8.0","gn:admin2_code":"191.0","gn:admin3_code":"4437.0","gn:asciiname":"Lobi","gn:country_code":"EE","gn:dem":29,"gn:feature_class":"P","gn:feature_code":"PPL","gn:geonameid":590579,"gn:latitude":59.61222,"gn:longitude":25.97944,"gn:modification_date":"2017-11-25","gn:name":"Lobi","gn:population":0,"gn:timezone":"Europe/Tallinn","iso:country":"EE","lbl:bbox":"25.95944,59.59222,25.99944,59.63222","lbl:max_zoom":18,"lbl:min_zoom":13.5,"mz:hierarchy_label":1,"mz:is_current":1,"mz:min_zoom":12,"name:ceb_x_preferred":["Lobi"],"name:fra_x_preferred":["Lobi"],"name:hye_x_preferred":["Լոբի"],"name:nld_x_preferred":["Lobi"],"name:rus_x_preferred":["Лоби"],"name:swe_x_preferred":["Lobi"],"src:geom":"geonames","wof:belongsto":[85683049,102191581,1713308519,85633135,1713305775],"wof:breaches":[],"wof:concordances":{"gn:id":590579},"wof:coterminous":[1713308519],"wof:country":"EE","wof:geomhash":"16041c1592083b848196849d25a16e78","wof:hierarchy":[{"continent_id":102191581,"country_id":85633135,"county_id":1713305775,"localadmin_id":1713308519,"locality_id":1259404995,"region_id":85683049}],"wof:id":1259404995,"wof:lang_x_official":["est"],"wof:lang_x_spoken":["est"],"wof:lastmodified":1596678038,"wof:name":"Lobi","wof:parent_id":1713308519,"wof:placetype":"locality","wof:repo":"whosonfirst-data-admin-ee","wof:superseded_by":[],"wof:supersedes":[],"wof:tags":[]},"bbox":[25.97944,59.61222,25.97944,59.61222],"geometry":{"coordinates":[25.97944,59.61222],"type":"Point"}}