{"id":1259748701,"type":"Feature","properties":{"edtf:cessation":"uuuu","edtf:inception":"uuuu","geom:area":0,"geom:area_square_m":0,"geom:bbox":"26.34694,57.75778,26.34694,57.75778","geom:latitude":57.75778,"geom:longitude":26.34694,"gn:admin1_code":"19.0","gn:admin2_code":"855.0","gn:admin3_code":"3951.0","gn:asciiname":"Kaeaerikmaee","gn:country_code":"EE","gn:dem":105,"gn:feature_class":"P","gn:feature_code":"PPL","gn:geonameid":794498,"gn:latitude":57.75778,"gn:longitude":26.34694,"gn:modification_date":"2017-11-25","gn:name":"Käärikmäe","gn:population":0,"gn:timezone":"Europe/Tallinn","iso:country":"EE","lbl:bbox":"26.32694,57.73778,26.36694,57.77778","lbl:max_zoom":18,"lbl:min_zoom":13.5,"mz:hierarchy_label":1,"mz:is_current":1,"mz:min_zoom":12,"name:est_x_preferred":["Käärikmäe"],"name:hye_x_preferred":["Կեեռիկմյաե"],"name:pol_x_preferred":["Käärikmäe"],"name:spa_x_preferred":["Käärikmäe"],"name:ukr_x_preferred":["Кяерікмяе"],"name:vol_x_preferred":["Käärikmäe"],"src:geom":"geonames","wof:belongsto":[85682941,102191581,1713310817,85633135,1713305753],"wof:breaches":[],"wof:concordances":{"gn:id":794498,"wk:page":"K%C3%A4%C3%A4rikm%C3%A4e"},"wof:country":"EE","wof:geomhash":"aed87e06d827eadf69a02042fa1dd8d4","wof:hierarchy":[{"continent_id":102191581,"country_id":85633135,"county_id":1713305753,"localadmin_id":1713310817,"locality_id":1259748701,"region_id":85682941}],"wof:id":1259748701,"wof:lang_x_official":["est"],"wof:lang_x_spoken":["est"],"wof:lastmodified":1596661951,"wof:name":"Kaeaerikmaee","wof:parent_id":1713310817,"wof:placetype":"locality","wof:repo":"whosonfirst-data-admin-ee","wof:superseded_by":[],"wof:supersedes":[],"wof:tags":[]},"bbox":[26.34694,57.75778,26.34694,57.75778],"geometry":{"coordinates":[26.34694,57.75778],"type":"Point"}}