{"id":1259999557,"type":"Feature","properties":{"edtf:cessation":"uuuu","edtf:inception":"uuuu","geom:area":0,"geom:area_square_m":0,"geom:bbox":"26.73528,59.51083,26.73528,59.51083","geom:latitude":59.51083,"geom:longitude":26.73528,"gn:admin1_code":"8.0","gn:admin2_code":"903.0","gn:admin3_code":"4736.0","gn:asciiname":"Lahe","gn:country_code":"EE","gn:dem":15,"gn:feature_class":"P","gn:feature_code":"PPL","gn:geonameid":590830,"gn:latitude":59.51083,"gn:longitude":26.73528,"gn:modification_date":"2017-11-25","gn:name":"Lahe","gn:population":0,"gn:timezone":"Europe/Tallinn","iso:country":"EE","lbl:bbox":"26.71528,59.49083,26.75528,59.53083","lbl:max_zoom":18,"lbl:min_zoom":13.5,"mz:hierarchy_label":1,"mz:is_current":1,"mz:min_zoom":12,"name:deu_x_preferred":["Lahe"],"name:est_x_preferred":["Lahe"],"name:hye_x_preferred":["Լահե"],"name:sco_x_preferred":["Lahe"],"name:ukr_x_preferred":["Лаге"],"name:und_x_variant":["Lakhekyula","Laheküla"],"name:vol_x_preferred":["Lahe"],"src:geom":"geonames","wof:belongsto":[85683049,102191581,1713307667,85633135,1713305777],"wof:breaches":[],"wof:concordances":{"gn:id":590830},"wof:country":"EE","wof:geomhash":"98cdaeb927d946a3dedd04c8df4f751d","wof:hierarchy":[{"continent_id":102191581,"country_id":85633135,"county_id":1713305777,"localadmin_id":1713307667,"locality_id":1259999557,"region_id":85683049}],"wof:id":1259999557,"wof:lang_x_official":["est"],"wof:lang_x_spoken":["est"],"wof:lastmodified":1596677938,"wof:name":"Lahe","wof:parent_id":1713307667,"wof:placetype":"locality","wof:repo":"whosonfirst-data-admin-ee","wof:superseded_by":[],"wof:supersedes":[],"wof:tags":[]},"bbox":[26.73528,59.51083,26.73528,59.51083],"geometry":{"coordinates":[26.73528,59.51083],"type":"Point"}}