{"id":1327109063,"type":"Feature","properties":{"edtf:cessation":"uuuu","edtf:inception":"uuuu","geom:area":0,"geom:area_square_m":0,"geom:bbox":"25.47556,58.49694,25.47556,58.49694","geom:latitude":58.49694,"geom:longitude":25.47556,"gn:admin1_code":"20.0","gn:admin2_code":"615.0","gn:admin3_code":"5031.0","gn:asciiname":"Munsi","gn:country_code":"EE","gn:dem":88,"gn:feature_class":"P","gn:feature_code":"PPL","gn:geonameid":590118,"gn:latitude":58.49694,"gn:longitude":25.47556,"gn:modification_date":"2017-11-25","gn:name":"Munsi","gn:population":0,"gn:timezone":"Europe/Tallinn","iso:country":"EE","lbl:bbox":"25.45556,58.47694,25.49556,58.51694","lbl:max_zoom":18,"lbl:min_zoom":13.5,"mz:hierarchy_label":1,"mz:is_current":1,"mz:min_zoom":12,"src:geom":"geonames","wof:belongsto":[85682985,102191581,1713311645,85633135,1713305735],"wof:breaches":[],"wof:concordances":{"gn:id":590118},"wof:coterminous":[1713311645],"wof:country":"EE","wof:geomhash":"1411941aa747f864d8c1874c7dcd6b82","wof:hierarchy":[{"continent_id":102191581,"country_id":85633135,"county_id":1713305735,"localadmin_id":1713311645,"locality_id":1327109063,"region_id":85682985}],"wof:id":1327109063,"wof:lang_x_official":["est"],"wof:lang_x_spoken":["est"],"wof:lastmodified":1596663464,"wof:name":"Munsi","wof:parent_id":1713311645,"wof:placetype":"locality","wof:repo":"whosonfirst-data-admin-ee","wof:superseded_by":[],"wof:supersedes":[],"wof:tags":[]},"bbox":[25.47556,58.49694,25.47556,58.49694],"geometry":{"coordinates":[25.47556,58.49694],"type":"Point"}}