{"id":1343541401,"type":"Feature","properties":{"edtf:cessation":"uuuu","edtf:inception":"uuuu","geom:area":0,"geom:area_square_m":0,"geom:bbox":"26.83722,58.00917,26.83722,58.00917","geom:latitude":58.00917,"geom:longitude":26.83722,"gn:admin1_code":"12.0","gn:admin2_code":"284.0","gn:admin3_code":"2387.0","gn:asciiname":"Kaagna","gn:country_code":"EE","gn:dem":132,"gn:feature_class":"P","gn:feature_code":"PPL","gn:geonameid":794182,"gn:latitude":58.00917,"gn:longitude":26.83722,"gn:modification_date":"2017-11-25","gn:name":"Kaagna","gn:population":0,"gn:timezone":"Europe/Tallinn","iso:country":"EE","lbl:bbox":"26.81722,57.98917,26.85722,58.02917","lbl:max_zoom":18,"lbl:min_zoom":13.5,"mz:hierarchy_label":1,"mz:is_current":1,"mz:min_zoom":12,"name:est_x_preferred":["Kaagna"],"name:hye_x_preferred":["Կաագնա"],"name:pol_x_preferred":["Kaagna"],"name:spa_x_preferred":["Kaagna"],"name:ukr_x_preferred":["Каагна"],"name:vol_x_preferred":["Kaagna"],"src:geom":"geonames","wof:belongsto":[85682955,102191581,1713309823,85633135,1713305789],"wof:breaches":[],"wof:concordances":{"gn:id":794182,"wk:page":"Kaagna"},"wof:coterminous":[1713309823],"wof:country":"EE","wof:geomhash":"7a82499a4731ced48c0d42547d59eaa7","wof:hierarchy":[{"continent_id":102191581,"country_id":85633135,"county_id":1713305789,"localadmin_id":1713309823,"locality_id":1343541401,"region_id":85682955}],"wof:id":1343541401,"wof:lang_x_official":["est"],"wof:lang_x_spoken":["est"],"wof:lastmodified":1596676788,"wof:name":"Kaagna","wof:parent_id":1713309823,"wof:placetype":"locality","wof:repo":"whosonfirst-data-admin-ee","wof:superseded_by":[],"wof:supersedes":[],"wof:tags":[]},"bbox":[26.83722,58.00917,26.83722,58.00917],"geometry":{"coordinates":[26.83722,58.00917],"type":"Point"}}