{"id":1326908523,"type":"Feature","properties":{"edtf:cessation":"uuuu","edtf:inception":"uuuu","geom:area":0,"geom:area_square_m":0,"geom:bbox":"24.63694,58.41,24.63694,58.41","geom:latitude":58.41,"geom:longitude":24.63694,"gn:admin1_code":"11.0","gn:admin2_code":"809.0","gn:admin3_code":"8885.0","gn:asciiname":"Vainu","gn:country_code":"EE","gn:dem":14,"gn:feature_class":"P","gn:feature_code":"PPL","gn:geonameid":794813,"gn:latitude":58.41,"gn:longitude":24.63694,"gn:modification_date":"2017-11-25","gn:name":"Vainu","gn:population":0,"gn:timezone":"Europe/Tallinn","iso:country":"EE","lbl:bbox":"24.61694,58.39,24.65694,58.43","lbl:max_zoom":18,"lbl:min_zoom":13.5,"mz:hierarchy_label":1,"mz:is_current":1,"mz:min_zoom":12,"name:est_x_preferred":["Vainu"],"name:pol_x_preferred":["Vainu"],"src:geom":"geonames","wof:belongsto":[85682981,102191581,1713312413,85633135,1713305731],"wof:breaches":[],"wof:concordances":{"gn:id":794813},"wof:coterminous":[1713312413],"wof:country":"EE","wof:geomhash":"bfbd38c489e80c8aa4f2b3498d89884a","wof:hierarchy":[{"continent_id":102191581,"country_id":85633135,"county_id":1713305731,"localadmin_id":1713312413,"locality_id":1326908523,"region_id":85682981}],"wof:id":1326908523,"wof:lang_x_official":["est"],"wof:lang_x_spoken":["est"],"wof:lastmodified":1596663392,"wof:name":"Vainu","wof:parent_id":1713312413,"wof:placetype":"locality","wof:repo":"whosonfirst-data-admin-ee","wof:superseded_by":[],"wof:supersedes":[],"wof:tags":[]},"bbox":[24.63694,58.41,24.63694,58.41],"geometry":{"coordinates":[24.63694,58.41],"type":"Point"}}