{"id":1242869767,"type":"Feature","properties":{"edtf:cessation":"uuuu","edtf:inception":"uuuu","geom:area":0,"geom:area_square_m":0,"geom:bbox":"26.525,59.16667,26.525,59.16667","geom:latitude":59.16667,"geom:longitude":26.525,"gn:admin1_code":"8.0","gn:admin2_code":"901.0","gn:admin3_code":"7262.0","gn:asciiname":"Metsavahi","gn:country_code":"EE","gn:dem":118,"gn:feature_class":"P","gn:feature_code":"PPL","gn:geonameid":8618677,"gn:latitude":59.16667,"gn:longitude":26.525,"gn:modification_date":"2017-11-25","gn:name":"Metsavahi","gn:population":0,"gn:timezone":"Europe/Tallinn","iso:country":"EE","lbl:bbox":"26.505,59.14667,26.545,59.18667","lbl:max_zoom":18,"lbl:min_zoom":13.5,"mz:hierarchy_label":1,"mz:is_current":1,"mz:min_zoom":12,"name:und_x_variant":["Metsawahhi"],"src:geom":"geonames","wof:belongsto":[85683049,102191581,1713307735,85633135,1713305771],"wof:breaches":[],"wof:concordances":{"gn:id":8618677},"wof:country":"EE","wof:geomhash":"359465bd68b0a8b1981bcc74c76143d1","wof:hierarchy":[{"continent_id":102191581,"country_id":85633135,"county_id":1713305771,"localadmin_id":1713307735,"locality_id":1242869767,"region_id":85683049}],"wof:id":1242869767,"wof:lang_x_official":["est"],"wof:lang_x_spoken":["est"],"wof:lastmodified":1596677964,"wof:name":"Metsavahi","wof:parent_id":1713307735,"wof:placetype":"locality","wof:repo":"whosonfirst-data-admin-ee","wof:superseded_by":[],"wof:supersedes":[],"wof:tags":[]},"bbox":[26.525,59.16667,26.525,59.16667],"geometry":{"coordinates":[26.525,59.16667],"type":"Point"}}