{"id":1344231501,"type":"Feature","properties":{"edtf:cessation":"uuuu","edtf:inception":"uuuu","geom:area":0,"geom:area_square_m":0,"geom:bbox":"25.63222,58.12083,25.63222,58.12083","geom:latitude":58.12083,"geom:longitude":25.63222,"gn:admin1_code":"20.0","gn:admin2_code":"480.0","gn:admin3_code":"1868.0","gn:asciiname":"Kolda","gn:country_code":"EE","gn:dem":99,"gn:feature_class":"P","gn:feature_code":"PPL","gn:geonameid":8620344,"gn:latitude":58.12083,"gn:longitude":25.63222,"gn:modification_date":"2017-11-25","gn:name":"Kolda","gn:population":0,"gn:timezone":"Europe/Tallinn","iso:country":"EE","lbl:bbox":"25.61222,58.10083,25.65222,58.14083","lbl:max_zoom":18,"lbl:min_zoom":13.5,"mz:hierarchy_label":1,"mz:is_current":1,"mz:min_zoom":12,"name:ben_x_preferred":["কোলদা"],"name:ceb_x_preferred":["Kolda"],"name:dan_x_preferred":["Kolda"],"name:deu_x_preferred":["Kolda"],"name:ell_x_preferred":["Κόλντα"],"name:eus_x_preferred":["Kolda"],"name:fas_x_preferred":["کولدا"],"name:fra_x_preferred":["Kolda"],"name:frr_x_preferred":["Kolda"],"name:hin_x_preferred":["कोल्डा"],"name:hun_x_preferred":["Kolda"],"name:ind_x_preferred":["Kolda"],"name:ita_x_preferred":["Kolda"],"name:lit_x_preferred":["Kolda"],"name:nld_x_preferred":["Kolda"],"name:pol_x_preferred":["Kolda"],"name:por_x_preferred":["Kolda"],"name:ron_x_preferred":["Kolda"],"name:rus_x_preferred":["Колда"],"name:spa_x_preferred":["Kolda"],"name:swe_x_preferred":["Kolda"],"name:tur_x_preferred":["Kolda"],"name:und_x_variant":["Saviaru"],"name:urd_x_preferred":["کولدا"],"name:vie_x_preferred":["Kolda"],"name:zho_x_preferred":["科尔达"],"src:geom":"geonames","wof:belongsto":[85682985,102191581,1713311511,85633135,1713305661],"wof:breaches":[],"wof:concordances":{"gn:id":8620344},"wof:country":"EE","wof:geomhash":"1835afc5398080f6b1b21b1b5abb5baa","wof:hierarchy":[{"continent_id":102191581,"country_id":85633135,"county_id":1713305661,"localadmin_id":1713311511,"locality_id":1344231501,"region_id":85682985}],"wof:id":1344231501,"wof:lang_x_official":["est"],"wof:lang_x_spoken":["est"],"wof:lastmodified":1636502237,"wof:name":"Kolda","wof:parent_id":1713311511,"wof:placetype":"locality","wof:repo":"whosonfirst-data-admin-ee","wof:superseded_by":[],"wof:supersedes":[],"wof:tags":[]},"bbox":[25.63222,58.12083,25.63222,58.12083],"geometry":{"coordinates":[25.63222,58.12083],"type":"Point"}}