{"id":1343423487,"type":"Feature","properties":{"edtf:cessation":"uuuu","edtf:inception":"uuuu","geom:area":0,"geom:area_square_m":0,"geom:bbox":"26.23444,57.83722,26.23444,57.83722","geom:latitude":57.83722,"geom:longitude":26.23444,"gn:admin1_code":"19.0","gn:admin2_code":"855.0","gn:admin3_code":"9326.0","gn:asciiname":"Vilaski","gn:country_code":"EE","gn:dem":43,"gn:feature_class":"P","gn:feature_code":"PPL","gn:geonameid":8619189,"gn:latitude":57.83722,"gn:longitude":26.23444,"gn:modification_date":"2017-11-25","gn:name":"Vilaski","gn:population":0,"gn:timezone":"Europe/Tallinn","iso:country":"EE","lbl:bbox":"26.21444,57.81722,26.25444,57.85722","lbl:max_zoom":18,"lbl:min_zoom":13.5,"mz:hierarchy_label":1,"mz:is_current":1,"mz:min_zoom":12,"name:und_x_variant":["Karula"],"src:geom":"geonames","wof:belongsto":[85682941,102191581,1713310309,85633135,1713305753],"wof:breaches":[],"wof:concordances":{"gn:id":8619189},"wof:coterminous":[1713310309],"wof:country":"EE","wof:geomhash":"8b0ecba3877aa3894e57de58980e9d5b","wof:hierarchy":[{"continent_id":102191581,"country_id":85633135,"county_id":1713305753,"localadmin_id":1713310309,"locality_id":1343423487,"region_id":85682941}],"wof:id":1343423487,"wof:lang_x_official":["est"],"wof:lang_x_spoken":["est"],"wof:lastmodified":1596661949,"wof:name":"Vilaski","wof:parent_id":1713310309,"wof:placetype":"locality","wof:repo":"whosonfirst-data-admin-ee","wof:superseded_by":[],"wof:supersedes":[],"wof:tags":[]},"bbox":[26.23444,57.83722,26.23444,57.83722],"geometry":{"coordinates":[26.23444,57.83722],"type":"Point"}}