{"id":1293091873,"type":"Feature","properties":{"edtf:cessation":"uuuu","edtf:inception":"uuuu","geom:area":0,"geom:area_square_m":0,"geom:bbox":"26.26917,59.15278,26.26917,59.15278","geom:latitude":59.15278,"geom:longitude":26.26917,"gn:admin1_code":"8.0","gn:admin2_code":"928.0","gn:admin3_code":"3410.0","gn:asciiname":"Koonu","gn:cc2":"EE","gn:country_code":"EE","gn:dem":123,"gn:feature_class":"P","gn:feature_code":"PPL","gn:geonameid":591153,"gn:latitude":59.15278,"gn:longitude":26.26917,"gn:modification_date":"2017-11-25","gn:name":"Koonu","gn:population":0,"gn:timezone":"Europe/Tallinn","iso:country":"EE","lbl:bbox":"26.24917,59.13278,26.28917,59.17278","lbl:max_zoom":18,"lbl:min_zoom":13.5,"mz:hierarchy_label":1,"mz:is_current":1,"mz:min_zoom":12,"name:est_x_preferred":["Koonu"],"name:hye_x_preferred":["Կոոնու"],"name:pol_x_preferred":["Koonu"],"name:und_x_variant":["Konu","Koo"],"name:vol_x_preferred":["Koonu"],"src:geom":"geonames","wof:belongsto":[85683049,102191581,1713311823,85633135,1713305769],"wof:breaches":[],"wof:concordances":{"gn:id":591153,"wk:page":"Koonu"},"wof:coterminous":[1713311823],"wof:country":"EE","wof:geomhash":"a211267dac48e502dbbf5ff915087030","wof:hierarchy":[{"continent_id":102191581,"country_id":85633135,"county_id":1713305769,"localadmin_id":1713311823,"locality_id":1293091873,"region_id":85683049}],"wof:id":1293091873,"wof:lang_x_official":["est"],"wof:lang_x_spoken":["est"],"wof:lastmodified":1596676541,"wof:name":"Koonu","wof:parent_id":1713311823,"wof:placetype":"locality","wof:repo":"whosonfirst-data-admin-ee","wof:superseded_by":[],"wof:supersedes":[],"wof:tags":[]},"bbox":[26.26917,59.15278,26.26917,59.15278],"geometry":{"coordinates":[26.26917,59.15278],"type":"Point"}}