{"id":1293192383,"type":"Feature","properties":{"edtf:cessation":"uuuu","edtf:inception":"uuuu","geom:area":0,"geom:area_square_m":0,"geom:bbox":"23.875,58.70722,23.875,58.70722","geom:latitude":58.70722,"geom:longitude":23.875,"gn:admin1_code":"11.0","gn:admin2_code":"430.0","gn:admin3_code":"1936.0","gn:asciiname":"Haelvati","gn:country_code":"EE","gn:dem":13,"gn:feature_class":"P","gn:feature_code":"PPL","gn:geonameid":592194,"gn:latitude":58.70722,"gn:longitude":23.875,"gn:modification_date":"2017-11-25","gn:name":"Hälvati","gn:population":0,"gn:timezone":"Europe/Tallinn","iso:country":"EE","lbl:bbox":"23.855,58.68722,23.895,58.72722","lbl:max_zoom":18,"lbl:min_zoom":13.5,"mz:hierarchy_label":1,"mz:is_current":1,"mz:min_zoom":12,"name:deu_x_preferred":["Hälvati"],"name:est_x_preferred":["Hälvati"],"name:hye_x_preferred":["Հելվատի"],"name:nld_x_preferred":["Hälvati"],"name:pol_x_preferred":["Hälvati"],"name:spa_x_preferred":["Hälvati"],"name:und_x_variant":["Khyal’vati"],"name:vol_x_preferred":["Hälvati"],"src:geom":"geonames","wof:belongsto":[85683001,102191581,1713309479,85633135,1713305721],"wof:breaches":[],"wof:concordances":{"gn:id":592194,"wk:page":"H%C3%A4lvati"},"wof:coterminous":[1713309479],"wof:country":"EE","wof:geomhash":"86b87d06be4e3ff012cbde5406cdca84","wof:hierarchy":[{"continent_id":102191581,"country_id":85633135,"county_id":1713305721,"localadmin_id":1713309479,"locality_id":1293192383,"region_id":85683001}],"wof:id":1293192383,"wof:lang_x_official":["est"],"wof:lang_x_spoken":["est"],"wof:lastmodified":1596661685,"wof:name":"Haelvati","wof:parent_id":1713309479,"wof:placetype":"locality","wof:repo":"whosonfirst-data-admin-ee","wof:superseded_by":[],"wof:supersedes":[],"wof:tags":[]},"bbox":[23.875,58.70722,23.875,58.70722],"geometry":{"coordinates":[23.875,58.70722],"type":"Point"}}