{"id":1276843899,"type":"Feature","properties":{"edtf:cessation":"uuuu","edtf:inception":"uuuu","geom:area":0,"geom:area_square_m":0,"geom:bbox":"22.69861,58.35194,22.69861,58.35194","geom:latitude":58.35194,"geom:longitude":22.69861,"gn:admin1_code":"14.0","gn:admin2_code":"714.0","gn:admin3_code":"4803.0","gn:asciiname":"Masa","gn:country_code":"EE","gn:dem":21,"gn:feature_class":"P","gn:feature_code":"PPL","gn:geonameid":8620659,"gn:latitude":58.35194,"gn:longitude":22.69861,"gn:modification_date":"2017-11-25","gn:name":"Masa","gn:population":0,"gn:timezone":"Europe/Tallinn","iso:country":"EE","lbl:bbox":"22.67861,58.33194,22.71861,58.37194","lbl:max_zoom":18,"lbl:min_zoom":13.5,"mz:hierarchy_label":1,"mz:is_current":1,"mz:min_zoom":12,"name:fra_x_preferred":["Masa"],"name:kor_x_preferred":["마사"],"name:msa_x_preferred":["Masa"],"name:ukr_x_preferred":["Маса"],"name:und_x_variant":["Lõõne"],"name:zho_x_preferred":["马萨"],"src:geom":"geonames","wof:belongsto":[85682947,102191581,1713306577,85633135,1713305627],"wof:breaches":[],"wof:concordances":{"gn:id":8620659},"wof:coterminous":[1713306577],"wof:country":"EE","wof:geomhash":"5540af27f3d86302584148592cf1a168","wof:hierarchy":[{"continent_id":102191581,"country_id":85633135,"county_id":1713305627,"localadmin_id":1713306577,"locality_id":1276843899,"region_id":85682947}],"wof:id":1276843899,"wof:lang_x_official":["est"],"wof:lang_x_spoken":["est"],"wof:lastmodified":1596674965,"wof:name":"Masa","wof:parent_id":1713306577,"wof:placetype":"locality","wof:repo":"whosonfirst-data-admin-ee","wof:superseded_by":[],"wof:supersedes":[],"wof:tags":[]},"bbox":[22.69861,58.35194,22.69861,58.35194],"geometry":{"coordinates":[22.69861,58.35194],"type":"Point"}}