{"id":1125846281,"type":"Feature","properties":{"edtf:cessation":"uuuu","edtf:inception":"uuuu","geom:area":0,"geom:area_square_m":0,"geom:bbox":"25.02278,59.62139,25.02278,59.62139","geom:latitude":59.62139,"geom:longitude":25.02278,"gn:country":"EE","gn:fcode":"PPL","gn:population":0,"iso:country":"EE","lbl:bbox":"25.00278,59.60139,25.04278,59.64139","lbl:latitude":59.62139,"lbl:longitude":25.02278,"lbl:max_zoom":18,"lbl:min_zoom":13.5,"mz:hierarchy_label":1,"mz:is_current":1,"mz:min_zoom":12,"mz:note":"Quattroshapes Point Gazetteer import 20170519","name:eng_x_preferred":["Idaotsa"],"name:est_x_preferred":["Idaotsa"],"name:fra_x_preferred":["Idaotsa"],"name:hye_x_preferred":["Իդաոցա"],"name:nld_x_preferred":["Idaotsa"],"name:pol_x_preferred":["Idaotsa"],"name:rus_x_preferred":["Идаотса"],"name:spa_x_preferred":["Idaotsa"],"name:vol_x_preferred":["Idaotsa"],"qs_pg:aaroncc":"EE","qs_pg:gn_country":"EE","qs_pg:gn_fcode":"PPL","qs_pg:gn_id":592076,"qs_pg:gn_pop":0,"qs_pg:name":"Idaotsa","qs_pg:name_adm0":"Eesti","qs_pg:name_adm1":"Harjumaa","qs_pg:photos":56,"qs_pg:photos_1k":11,"qs_pg:photos_9k":1,"qs_pg:photos_9r":2,"qs_pg:photos_all":56,"qs_pg:photos_sr":2,"qs_pg:pop_sr":0,"qs_pg:qs_id":1325004,"qs_pg:qs_pg_placetype":"locality","qs_pg:qs_pg_placetype_gp":"Town","qs_pg:woe_adm0":23424805,"qs_pg:woe_id":842299,"src:geom":"qs_pg","src:lbl_centroid":"qs_pg","woe:adm0_id":23424805,"woe:name_adm0":"Eesti","woe:name_adm1":"Harjumaa","woe:placetype":"Town","wof:belongsto":[85683055,102191581,1713306037,85633135,1713305625],"wof:breaches":[],"wof:concordances":{"gn:id":592076,"gp:id":842299,"qs_pg:id":1325004,"wd:id":"Q3459133"},"wof:coterminous":[1713306037],"wof:country":"EE","wof:created":1497293170,"wof:geomhash":"bb3f063a85a9019c28606ddb2b3c58b2","wof:hierarchy":[{"continent_id":102191581,"country_id":85633135,"county_id":1713305625,"localadmin_id":1713306037,"locality_id":1125846281,"region_id":85683055}],"wof:id":1125846281,"wof:lang_x_official":["est"],"wof:lang_x_spoken":["est"],"wof:lastmodified":1596676119,"wof:name":"Idaotsa","wof:parent_id":1713306037,"wof:placetype":"locality","wof:repo":"whosonfirst-data-admin-ee","wof:superseded_by":[],"wof:supersedes":[],"wof:tags":[]},"bbox":[25.02278,59.62139,25.02278,59.62139],"geometry":{"coordinates":[25.02278,59.62139],"type":"Point"}}