{"id":1326462059,"type":"Feature","properties":{"edtf:cessation":"uuuu","edtf:inception":"uuuu","geom:area":0,"geom:area_square_m":0,"geom:bbox":"26.21528,58.80028,26.21528,58.80028","geom:latitude":58.80028,"geom:longitude":26.21528,"gn:admin1_code":"5.0","gn:admin2_code":"247.0","gn:admin3_code":"1598.0","gn:asciiname":"Tirma","gn:country_code":"EE","gn:dem":84,"gn:feature_class":"P","gn:feature_code":"PPL","gn:geonameid":588277,"gn:latitude":58.80028,"gn:longitude":26.21528,"gn:modification_date":"2017-11-25","gn:name":"Tirma","gn:population":0,"gn:timezone":"Europe/Tallinn","iso:country":"EE","lbl:bbox":"26.19528,58.78028,26.23528,58.82028","lbl:max_zoom":18,"lbl:min_zoom":13.5,"mz:hierarchy_label":1,"mz:is_current":1,"mz:min_zoom":12,"src:geom":"geonames","wof:belongsto":[85683009,102191581,1713314357,85633135,1713305767],"wof:breaches":[],"wof:concordances":{"gn:id":588277},"wof:country":"EE","wof:geomhash":"c9aa9ab9e3210bd5febe0cad8ab2321f","wof:hierarchy":[{"continent_id":102191581,"country_id":85633135,"county_id":1713305767,"localadmin_id":1713314357,"locality_id":1326462059,"region_id":85683009}],"wof:id":1326462059,"wof:lang_x_official":["est"],"wof:lang_x_spoken":["est"],"wof:lastmodified":1596676573,"wof:name":"Tirma","wof:parent_id":1713314357,"wof:placetype":"locality","wof:repo":"whosonfirst-data-admin-ee","wof:superseded_by":[],"wof:supersedes":[],"wof:tags":[]},"bbox":[26.21528,58.80028,26.21528,58.80028],"geometry":{"coordinates":[26.21528,58.80028],"type":"Point"}}