{"id":1259657785,"type":"Feature","properties":{"edtf:cessation":"uuuu","edtf:inception":"uuuu","geom:area":0,"geom:area_square_m":0,"geom:bbox":"26.92972,57.67389,26.92972,57.67389","geom:latitude":57.67389,"geom:longitude":26.92972,"gn:admin1_code":"21.0","gn:admin2_code":"698.0","gn:admin3_code":"7656.0","gn:asciiname":"Kaveldi","gn:country_code":"EE","gn:dem":153,"gn:feature_class":"P","gn:feature_code":"PPL","gn:geonameid":794367,"gn:latitude":57.67389,"gn:longitude":26.92972,"gn:modification_date":"2017-11-25","gn:name":"Kaveldi","gn:population":0,"gn:timezone":"Europe/Tallinn","iso:country":"EE","lbl:bbox":"26.90972,57.65389,26.94972,57.69389","lbl:max_zoom":18,"lbl:min_zoom":13.5,"mz:hierarchy_label":1,"mz:is_current":1,"mz:min_zoom":12,"src:geom":"geonames","wof:belongsto":[85682937,102191581,1713315395,85633135,1713305787],"wof:breaches":[],"wof:concordances":{"gn:id":794367},"wof:coterminous":[1713315767],"wof:country":"EE","wof:geomhash":"44d09471f9e5a8236f4322db075ccf10","wof:hierarchy":[{"continent_id":102191581,"country_id":85633135,"county_id":1713305787,"localadmin_id":1713315395,"locality_id":1259657785,"region_id":85682937}],"wof:id":1259657785,"wof:lang_x_official":["est"],"wof:lang_x_spoken":["est"],"wof:lastmodified":1596676872,"wof:name":"Kaveldi","wof:parent_id":1713315395,"wof:placetype":"locality","wof:repo":"whosonfirst-data-admin-ee","wof:superseded_by":[],"wof:supersedes":[],"wof:tags":[]},"bbox":[26.92972,57.67389,26.92972,57.67389],"geometry":{"coordinates":[26.92972,57.67389],"type":"Point"}}