{"id":1293256571,"type":"Feature","properties":{"edtf:cessation":"uuuu","edtf:inception":"uuuu","geom:area":0,"geom:area_square_m":0,"geom:bbox":"27.04,57.63861,27.04,57.63861","geom:latitude":57.63861,"geom:longitude":27.04,"gn:admin1_code":"21.0","gn:admin2_code":"698.0","gn:admin3_code":"9488.0","gn:asciiname":"Vungi","gn:country_code":"EE","gn:dem":228,"gn:feature_class":"P","gn:feature_code":"PPL","gn:geonameid":8619877,"gn:latitude":57.63861,"gn:longitude":27.04,"gn:modification_date":"2017-11-25","gn:name":"Vungi","gn:population":0,"gn:timezone":"Europe/Tallinn","iso:country":"EE","lbl:bbox":"27.02,57.61861,27.06,57.65861","lbl:max_zoom":18,"lbl:min_zoom":13.5,"mz:hierarchy_label":1,"mz:is_current":1,"mz:min_zoom":12,"name:und_x_variant":["Vorsti"],"src:geom":"geonames","wof:belongsto":[85682937,102191581,1713315079,85633135,1713305787],"wof:breaches":[],"wof:concordances":{"gn:id":8619877},"wof:coterminous":[1713315079],"wof:country":"EE","wof:geomhash":"3911387c80f0dbcea397ac7646af736c","wof:hierarchy":[{"continent_id":102191581,"country_id":85633135,"county_id":1713305787,"localadmin_id":1713315079,"locality_id":1293256571,"region_id":85682937}],"wof:id":1293256571,"wof:lang_x_official":["est"],"wof:lang_x_spoken":["est"],"wof:lastmodified":1596676880,"wof:name":"Vungi","wof:parent_id":1713315079,"wof:placetype":"locality","wof:repo":"whosonfirst-data-admin-ee","wof:superseded_by":[],"wof:supersedes":[],"wof:tags":[]},"bbox":[27.04,57.63861,27.04,57.63861],"geometry":{"coordinates":[27.04,57.63861],"type":"Point"}}