{"id":1125890057,"type":"Feature","properties":{"edtf:cessation":"uuuu","edtf:inception":"uuuu","geom:area":0,"geom:area_square_m":0,"geom:bbox":"25.01083,59.27222,25.01083,59.27222","geom:latitude":59.27222,"geom:longitude":25.01083,"gn:country":"EE","gn:fcode":"PPL","gn:population":108,"iso:country":"EE","lbl:bbox":"24.99083,59.25222,25.03083,59.29222","lbl:latitude":59.27222,"lbl:longitude":25.01083,"lbl:max_zoom":18,"lbl:min_zoom":13,"mz:hierarchy_label":1,"mz:is_current":1,"mz:min_zoom":11,"mz:note":"Quattroshapes Point Gazetteer import 20170519","name:bul_x_preferred":["Ваидасо"],"name:ceb_x_preferred":["Vaidasoo"],"name:eng_x_preferred":["Vaidasoo"],"name:est_x_preferred":["Vaidasoo"],"name:fra_x_preferred":["Vaidasoo"],"name:hye_x_preferred":["Վաիդասոո"],"name:nld_x_preferred":["Vaidasoo"],"name:pol_x_preferred":["Vaidasoo"],"name:spa_x_preferred":["Vaidasoo"],"name:swe_x_preferred":["Vaidasoo"],"name:vol_x_preferred":["Vaidasoo"],"qs_pg:aaroncc":"EE","qs_pg:gn_country":"EE","qs_pg:gn_fcode":"PPL","qs_pg:gn_id":793232,"qs_pg:gn_pop":108,"qs_pg:name":"Vaidasoo","qs_pg:name_adm0":"Eesti","qs_pg:name_adm1":"Harjumaa","qs_pg:photos_9k":1,"qs_pg:photos_9r":1,"qs_pg:photos_all":2,"qs_pg:photos_sr":0,"qs_pg:pop_sr":1,"qs_pg:qs_id":916004,"qs_pg:qs_pg_placetype":"locality","qs_pg:qs_pg_placetype_gp":"Town","qs_pg:woe_adm0":23424805,"qs_pg:woe_id":846177,"src:geom":"qs_pg","src:lbl_centroid":"qs_pg","src:population":"geonames","woe:adm0_id":23424805,"woe:name_adm0":"Eesti","woe:name_adm1":"Harjumaa","woe:placetype":"Town","wof:belongsto":[85683055,102191581,1713313571,85633135,1713305683],"wof:breaches":[],"wof:concordances":{"gn:id":793232,"gp:id":846177,"qs_pg:id":916004,"wd:id":"Q2422980"},"wof:coterminous":[1713313571],"wof:country":"EE","wof:created":1497295273,"wof:geomhash":"8da9cf98c789a6a977b281af5b841406","wof:hierarchy":[{"continent_id":102191581,"country_id":85633135,"county_id":1713305683,"localadmin_id":1713313571,"locality_id":1125890057,"region_id":85683055}],"wof:id":1125890057,"wof:lang_x_official":["est"],"wof:lang_x_spoken":["est"],"wof:lastmodified":1596661481,"wof:name":"Vaidasoo","wof:parent_id":1713313571,"wof:placetype":"locality","wof:population":108,"wof:population_rank":1,"wof:repo":"whosonfirst-data-admin-ee","wof:superseded_by":[],"wof:supersedes":[],"wof:tags":[]},"bbox":[25.01083,59.27222,25.01083,59.27222],"geometry":{"coordinates":[25.01083,59.27222],"type":"Point"}}