{"id":1226216921,"type":"Feature","properties":{"edtf:cessation":"uuuu","edtf:inception":"uuuu","geom:area":0,"geom:area_square_m":0,"geom:bbox":"25.4825,58.10444,25.4825,58.10444","geom:latitude":58.10444,"geom:longitude":25.4825,"gn:admin1_code":"20.0","gn:admin2_code":"480.0","gn:admin3_code":"4183.0","gn:asciiname":"Leeli","gn:country_code":"EE","gn:dem":72,"gn:feature_class":"P","gn:feature_code":"PPL","gn:geonameid":793896,"gn:latitude":58.10444,"gn:longitude":25.4825,"gn:modification_date":"2017-11-25","gn:name":"Leeli","gn:population":0,"gn:timezone":"Europe/Tallinn","iso:country":"EE","lbl:bbox":"25.4625,58.08444,25.5025,58.12444","lbl:max_zoom":18,"lbl:min_zoom":13.5,"mz:hierarchy_label":1,"mz:is_current":1,"mz:min_zoom":12,"name:est_x_preferred":["Leeli"],"name:hye_x_preferred":["Լեելի"],"name:pol_x_preferred":["Leeli"],"name:spa_x_preferred":["Leeli"],"name:ukr_x_preferred":["Леелі"],"name:vol_x_preferred":["Leeli"],"src:geom":"geonames","wof:belongsto":[85682985,102191581,1713311665,85633135,1713305661],"wof:breaches":[],"wof:concordances":{"gn:id":793896,"wk:page":"Leeli"},"wof:coterminous":[1713311665],"wof:country":"EE","wof:geomhash":"377d1be80ea607c6d24053f08e9dc49c","wof:hierarchy":[{"continent_id":102191581,"country_id":85633135,"county_id":1713305661,"localadmin_id":1713311665,"locality_id":1226216921,"region_id":85682985}],"wof:id":1226216921,"wof:lang_x_official":["est"],"wof:lang_x_spoken":["est"],"wof:lastmodified":1596661303,"wof:name":"Leeli","wof:parent_id":1713311665,"wof:placetype":"locality","wof:repo":"whosonfirst-data-admin-ee","wof:superseded_by":[],"wof:supersedes":[],"wof:tags":[]},"bbox":[25.4825,58.10444,25.4825,58.10444],"geometry":{"coordinates":[25.4825,58.10444],"type":"Point"}}