{"id":1360049889,"type":"Feature","properties":{"edtf:cessation":"uuuu","edtf:inception":"uuuu","geom:area":0,"geom:area_square_m":0,"geom:bbox":"26.82778,57.665,26.82778,57.665","geom:latitude":57.665,"geom:longitude":26.82778,"gn:admin1_code":"21.0","gn:admin2_code":"698.0","gn:admin3_code":"6485.0","gn:asciiname":"Podra","gn:country_code":"EE","gn:dem":136,"gn:feature_class":"P","gn:feature_code":"PPL","gn:geonameid":8619110,"gn:latitude":57.665,"gn:longitude":26.82778,"gn:modification_date":"2017-11-25","gn:name":"Põdra","gn:population":0,"gn:timezone":"Europe/Tallinn","iso:country":"EE","lbl:bbox":"26.80778,57.645,26.84778,57.685","lbl:max_zoom":18,"lbl:min_zoom":13.5,"mz:hierarchy_label":1,"mz:is_current":1,"mz:min_zoom":12,"name:und_x_variant":["Põdra","Puustuse"],"src:geom":"geonames","wof:belongsto":[85682937,102191581,1713314731,85633135,1713305787],"wof:breaches":[],"wof:concordances":{"gn:id":8619110},"wof:coterminous":[1713314731],"wof:country":"EE","wof:geomhash":"005d36b778245650a4306cbe244332f6","wof:hierarchy":[{"continent_id":102191581,"country_id":85633135,"county_id":1713305787,"localadmin_id":1713314731,"locality_id":1360049889,"region_id":85682937}],"wof:id":1360049889,"wof:lang_x_official":["est"],"wof:lang_x_spoken":["est"],"wof:lastmodified":1596676883,"wof:name":"Podra","wof:parent_id":1713314731,"wof:placetype":"locality","wof:repo":"whosonfirst-data-admin-ee","wof:superseded_by":[],"wof:supersedes":[],"wof:tags":[]},"bbox":[26.82778,57.665,26.82778,57.665],"geometry":{"coordinates":[26.82778,57.665],"type":"Point"}}