{"id":1226218349,"type":"Feature","properties":{"edtf:cessation":"uuuu","edtf:inception":"uuuu","geom:area":0,"geom:area_square_m":0,"geom:bbox":"26.90667,58.42139,26.90667,58.42139","geom:latitude":58.42139,"geom:longitude":26.90667,"gn:admin1_code":"18.0","gn:admin2_code":"796.0","gn:admin3_code":"3970.0","gn:asciiname":"Kuekitaja","gn:country_code":"EE","gn:dem":54,"gn:feature_class":"P","gn:feature_code":"PPL","gn:geonameid":794098,"gn:latitude":58.42139,"gn:longitude":26.90667,"gn:modification_date":"2017-11-25","gn:name":"Kükitaja","gn:population":0,"gn:timezone":"Europe/Tallinn","iso:country":"EE","lbl:bbox":"26.88667,58.40139,26.92667,58.44139","lbl:max_zoom":18,"lbl:min_zoom":13.5,"mz:hierarchy_label":1,"mz:is_current":1,"mz:min_zoom":12,"src:geom":"geonames","wof:belongsto":[85683009,102191581,1713314643,85633135,1713305659],"wof:breaches":[],"wof:concordances":{"gn:id":794098},"wof:coterminous":[1713314643],"wof:country":"EE","wof:geomhash":"30a759a7bf61b7c11162e2178e4048a3","wof:hierarchy":[{"continent_id":102191581,"country_id":85633135,"county_id":1713305659,"localadmin_id":1713314643,"locality_id":1226218349,"region_id":85683009}],"wof:id":1226218349,"wof:lang_x_official":["est"],"wof:lang_x_spoken":["est"],"wof:lastmodified":1596676472,"wof:name":"Kuekitaja","wof:parent_id":1713314643,"wof:placetype":"locality","wof:repo":"whosonfirst-data-admin-ee","wof:superseded_by":[],"wof:supersedes":[],"wof:tags":[]},"bbox":[26.90667,58.42139,26.90667,58.42139],"geometry":{"coordinates":[26.90667,58.42139],"type":"Point"}}