{"id":1360059429,"type":"Feature","properties":{"edtf:cessation":"uuuu","edtf:inception":"uuuu","geom:area":0,"geom:area_square_m":0,"geom:bbox":"26.96611,57.76167,26.96611,57.76167","geom:latitude":57.76167,"geom:longitude":26.96611,"gn:admin1_code":"21.0","gn:admin2_code":"698.0","gn:admin3_code":"4358.0","gn:asciiname":"Liivakupalu","gn:country_code":"EE","gn:dem":161,"gn:feature_class":"P","gn:feature_code":"PPL","gn:geonameid":8620271,"gn:latitude":57.76167,"gn:longitude":26.96611,"gn:modification_date":"2017-11-25","gn:name":"Liivakupalu","gn:population":0,"gn:timezone":"Europe/Tallinn","iso:country":"EE","lbl:bbox":"26.94611,57.74167,26.98611,57.78167","lbl:max_zoom":18,"lbl:min_zoom":13.5,"mz:hierarchy_label":1,"mz:is_current":1,"mz:min_zoom":12,"name:und_x_variant":["Linnamäe"],"src:geom":"geonames","wof:belongsto":[85682937,102191581,1713315265,85633135,1713305787],"wof:breaches":[],"wof:concordances":{"gn:id":8620271},"wof:coterminous":[1713315265],"wof:country":"EE","wof:geomhash":"f0f261be852532deb53dc06eca332ab4","wof:hierarchy":[{"continent_id":102191581,"country_id":85633135,"county_id":1713305787,"localadmin_id":1713315265,"locality_id":1360059429,"region_id":85682937}],"wof:id":1360059429,"wof:lang_x_official":["est"],"wof:lang_x_spoken":["est"],"wof:lastmodified":1596676883,"wof:name":"Liivakupalu","wof:parent_id":1713315265,"wof:placetype":"locality","wof:repo":"whosonfirst-data-admin-ee","wof:superseded_by":[],"wof:supersedes":[],"wof:tags":[]},"bbox":[26.96611,57.76167,26.96611,57.76167],"geometry":{"coordinates":[26.96611,57.76167],"type":"Point"}}