{"id":1243575555,"type":"Feature","properties":{"edtf:cessation":"uuuu","edtf:inception":"uuuu","geom:area":0,"geom:area_square_m":0,"geom:bbox":"23.89306,58.7925,23.89306,58.7925","geom:latitude":58.7925,"geom:longitude":23.89306,"gn:admin1_code":"7.0","gn:admin2_code":"441.0","gn:admin3_code":"5259.0","gn:asciiname":"Tammiku","gn:country_code":"EE","gn:dem":12,"gn:feature_class":"P","gn:feature_code":"PPL","gn:geonameid":588388,"gn:latitude":58.7925,"gn:longitude":23.89306,"gn:modification_date":"2017-11-25","gn:name":"Tammiku","gn:population":0,"gn:timezone":"Europe/Tallinn","iso:country":"EE","lbl:bbox":"23.87306,58.7725,23.91306,58.8125","lbl:max_zoom":18,"lbl:min_zoom":13.5,"mz:hierarchy_label":1,"mz:is_current":1,"mz:min_zoom":12,"name:und_x_variant":["Nurme","Tammikääre","Tammiku"],"src:geom":"geonames","wof:belongsto":[85683001,102191581,1713315463,85633135,1713305701],"wof:breaches":[],"wof:concordances":{"gn:id":588388,"wk:page":"Tammiku%2C_Martna_Parish"},"wof:coterminous":[1713312471],"wof:country":"EE","wof:geomhash":"cfa5bea62c65ed00bd90d892cb018718","wof:hierarchy":[{"continent_id":102191581,"country_id":85633135,"county_id":1713305701,"localadmin_id":1713315463,"locality_id":1243575555,"region_id":85683001}],"wof:id":1243575555,"wof:lang_x_official":["est"],"wof:lang_x_spoken":["est"],"wof:lastmodified":1596677441,"wof:name":"Tammiku","wof:parent_id":1713315463,"wof:placetype":"locality","wof:repo":"whosonfirst-data-admin-ee","wof:superseded_by":[],"wof:supersedes":[],"wof:tags":[]},"bbox":[23.89306,58.7925,23.89306,58.7925],"geometry":{"coordinates":[23.89306,58.7925],"type":"Point"}}