{"id":1277064559,"type":"Feature","properties":{"edtf:cessation":"uuuu","edtf:inception":"uuuu","geom:area":0,"geom:area_square_m":0,"geom:bbox":"24.22139,58.27889,24.22139,58.27889","geom:latitude":58.27889,"geom:longitude":24.22139,"gn:admin1_code":"11.0","gn:admin2_code":"624.0","gn:admin3_code":"2893.0","gn:asciiname":"Lembra","gn:country_code":"EE","gn:dem":3,"gn:feature_class":"P","gn:feature_code":"PPL","gn:geonameid":590697,"gn:latitude":58.27889,"gn:longitude":24.22139,"gn:modification_date":"2017-11-25","gn:name":"Lembra","gn:population":0,"gn:timezone":"Europe/Tallinn","iso:country":"EE","lbl:bbox":"24.20139,58.25889,24.24139,58.29889","lbl:max_zoom":18,"lbl:min_zoom":13.5,"mz:hierarchy_label":1,"mz:is_current":1,"mz:min_zoom":12,"src:geom":"geonames","wof:belongsto":[85682981,102191581,1713310093,85633135,1713305703],"wof:breaches":[],"wof:concordances":{"gn:id":590697},"wof:country":"EE","wof:geomhash":"eb270b5849353753b495536c9d777a14","wof:hierarchy":[{"continent_id":102191581,"country_id":85633135,"county_id":1713305703,"localadmin_id":1713310093,"locality_id":1277064559,"region_id":85682981}],"wof:id":1277064559,"wof:lang_x_official":["est"],"wof:lang_x_spoken":["est"],"wof:lastmodified":1596677707,"wof:name":"Lembra","wof:parent_id":1713310093,"wof:placetype":"locality","wof:repo":"whosonfirst-data-admin-ee","wof:superseded_by":[],"wof:supersedes":[],"wof:tags":[]},"bbox":[24.22139,58.27889,24.22139,58.27889],"geometry":{"coordinates":[24.22139,58.27889],"type":"Point"}}