{"id":1125954965,"type":"Feature","properties":{"edtf:cessation":"uuuu","edtf:inception":"uuuu","geom:area":0,"geom:area_square_m":0,"geom:bbox":"25.43417,58.52778,25.43417,58.52778","geom:latitude":58.52778,"geom:longitude":25.43417,"gn:country":"EE","gn:fcode":"PPL","gn:population":95,"iso:country":"EE","lbl:bbox":"25.41417,58.50778,25.45417,58.54778","lbl:latitude":58.52778,"lbl:longitude":25.43417,"lbl:max_zoom":18,"lbl:min_zoom":13,"mz:hierarchy_label":1,"mz:is_current":1,"mz:min_zoom":11,"mz:note":"Quattroshapes Point Gazetteer import 20170519","name:und_x_variant":["Enge"],"qs_pg:aaroncc":"EE","qs_pg:gn_country":"EE","qs_pg:gn_fcode":"PPL","qs_pg:gn_id":592483,"qs_pg:gn_pop":95,"qs_pg:name":"Ängi","qs_pg:name_adm0":"Eesti","qs_pg:name_adm1":"Viljandimaa","qs_pg:photos_9r":0,"qs_pg:photos_sr":0,"qs_pg:pop_sr":1,"qs_pg:qs_id":405672,"qs_pg:qs_pg_placetype":"locality","qs_pg:qs_pg_placetype_gp":"Town","qs_pg:woe_adm0":23424805,"qs_pg:woe_id":841945,"src:geom":"qs_pg","src:lbl_centroid":"qs_pg","src:population":"geonames","woe:adm0_id":23424805,"woe:name_adm0":"Eesti","woe:name_adm1":"Viljandimaa","woe:placetype":"Town","wof:belongsto":[85682985,102191581,1713311725,85633135,1713305735],"wof:breaches":[],"wof:concordances":{"gn:id":592483,"gp:id":841945,"qs_pg:id":405672},"wof:coterminous":[1713311725],"wof:country":"EE","wof:created":1497297591,"wof:geomhash":"2762b1a38833f98184f3c72356d4f425","wof:hierarchy":[{"continent_id":102191581,"country_id":85633135,"county_id":1713305735,"localadmin_id":1713311725,"locality_id":1125954965,"region_id":85682985}],"wof:id":1125954965,"wof:lang_x_official":["est"],"wof:lang_x_spoken":["est"],"wof:lastmodified":1596663454,"wof:name":"Ängi","wof:parent_id":1713311725,"wof:placetype":"locality","wof:population":95,"wof:population_rank":1,"wof:repo":"whosonfirst-data-admin-ee","wof:superseded_by":[],"wof:supersedes":[],"wof:tags":[]},"bbox":[25.43417,58.52778,25.43417,58.52778],"geometry":{"coordinates":[25.43417,58.52778],"type":"Point"}}