{"id":1326600865,"type":"Feature","properties":{"edtf:cessation":"uuuu","edtf:inception":"uuuu","geom:area":0,"geom:area_square_m":0,"geom:bbox":"22.82167,58.26639,22.82167,58.26639","geom:latitude":58.26639,"geom:longitude":22.82167,"gn:admin1_code":"14.0","gn:admin2_code":"714.0","gn:admin3_code":"6818.0","gn:asciiname":"Ranna","gn:country_code":"EE","gn:dem":2,"gn:feature_class":"P","gn:feature_code":"PPL","gn:geonameid":589142,"gn:latitude":58.26639,"gn:longitude":22.82167,"gn:modification_date":"2017-11-25","gn:name":"Ranna","gn:population":0,"gn:timezone":"Europe/Tallinn","iso:country":"EE","lbl:bbox":"22.80167,58.24639,22.84167,58.28639","lbl:max_zoom":18,"lbl:min_zoom":13.5,"mz:hierarchy_label":1,"mz:is_current":1,"mz:min_zoom":12,"name:ceb_x_preferred":["Ranna"],"name:deu_x_preferred":["Ranna"],"name:pol_x_preferred":["Ranna"],"name:swe_x_preferred":["Ranna"],"name:und_x_variant":["Ranna Asundus"],"src:geom":"geonames","wof:belongsto":[85682947,102191581,1713306953,85633135,1713305627],"wof:breaches":[],"wof:concordances":{"gn:id":589142},"wof:coterminous":[1713306953],"wof:country":"EE","wof:geomhash":"da83e067676b630f6d1e87119875ebac","wof:hierarchy":[{"continent_id":102191581,"country_id":85633135,"county_id":1713305627,"localadmin_id":1713306953,"locality_id":1326600865,"region_id":85682947}],"wof:id":1326600865,"wof:lang_x_official":["est"],"wof:lang_x_spoken":["est"],"wof:lastmodified":1596674948,"wof:name":"Ranna","wof:parent_id":1713306953,"wof:placetype":"locality","wof:repo":"whosonfirst-data-admin-ee","wof:superseded_by":[],"wof:supersedes":[],"wof:tags":[]},"bbox":[22.82167,58.26639,22.82167,58.26639],"geometry":{"coordinates":[22.82167,58.26639],"type":"Point"}}