{"id":1125936773,"type":"Feature","properties":{"edtf:cessation":"uuuu","edtf:inception":"uuuu","geom:area":0,"geom:area_square_m":0,"geom:bbox":"26.13194,59.17361,26.13194,59.17361","geom:latitude":59.17361,"geom:longitude":26.13194,"gn:country":"EE","gn:fcode":"PPL","gn:population":99,"iso:country":"EE","lbl:bbox":"26.11194,59.15361,26.15194,59.19361","lbl:latitude":59.17361,"lbl:longitude":26.13194,"lbl:max_zoom":18,"lbl:min_zoom":13,"mz:hierarchy_label":1,"mz:is_current":1,"mz:min_zoom":11,"mz:note":"Quattroshapes Point Gazetteer import 20170519","name:eng_x_preferred":["Uudeküla"],"name:est_x_preferred":["Uudeküla"],"name:hye_x_preferred":["Ուուդեկյուլա"],"name:nld_x_preferred":["Uudeküla"],"name:ukr_x_preferred":["Уудекюла"],"name:und_x_variant":["Udenkul’"],"name:vol_x_preferred":["Uudeküla"],"qs_pg:aaroncc":"EE","qs_pg:gn_country":"EE","qs_pg:gn_fcode":"PPL","qs_pg:gn_id":588028,"qs_pg:gn_pop":99,"qs_pg:name":"Uudeküla","qs_pg:name_adm0":"Eesti","qs_pg:name_adm1":"Lääne-Virumaa","qs_pg:photos_9r":0,"qs_pg:photos_sr":0,"qs_pg:pop_sr":1,"qs_pg:qs_id":1274684,"qs_pg:qs_pg_placetype":"locality","qs_pg:qs_pg_placetype_gp":"Town","qs_pg:woe_adm0":23424805,"qs_pg:woe_id":846101,"src:geom":"qs_pg","src:lbl_centroid":"qs_pg","src:population":"geonames","woe:adm0_id":23424805,"woe:name_adm0":"Eesti","woe:name_adm1":"Lääne-Virumaa","woe:placetype":"Town","wof:belongsto":[85683049,102191581,1713308303,85633135,1713305761],"wof:breaches":[],"wof:concordances":{"gn:id":588028,"gp:id":846101,"qs_pg:id":1274684,"wd:id":"Q3463761"},"wof:coterminous":[1713308303],"wof:country":"EE","wof:created":1497296991,"wof:geomhash":"cb970a2c995594d0ff97a4438f738b2e","wof:hierarchy":[{"continent_id":102191581,"country_id":85633135,"county_id":1713305761,"localadmin_id":1713308303,"locality_id":1125936773,"region_id":85683049}],"wof:id":1125936773,"wof:lang_x_official":["est"],"wof:lang_x_spoken":["est"],"wof:lastmodified":1596676608,"wof:name":"Uudeküla","wof:parent_id":1713308303,"wof:placetype":"locality","wof:population":99,"wof:population_rank":1,"wof:repo":"whosonfirst-data-admin-ee","wof:superseded_by":[],"wof:supersedes":[],"wof:tags":[]},"bbox":[26.13194,59.17361,26.13194,59.17361],"geometry":{"coordinates":[26.13194,59.17361],"type":"Point"}}