{"id":1226308603,"type":"Feature","properties":{"edtf:cessation":"uuuu","edtf:inception":"uuuu","geom:area":0,"geom:area_square_m":0,"geom:bbox":"26.44278,58.12,26.44278,58.12","geom:latitude":58.12,"geom:longitude":26.44278,"gn:admin1_code":"19.0","gn:admin2_code":"557.0","gn:admin3_code":"7195.0","gn:asciiname":"Raebi","gn:country_code":"EE","gn:dem":113,"gn:feature_class":"P","gn:feature_code":"PPL","gn:geonameid":794570,"gn:latitude":58.12,"gn:longitude":26.44278,"gn:modification_date":"2017-11-25","gn:name":"Räbi","gn:population":0,"gn:timezone":"Europe/Tallinn","iso:country":"EE","lbl:bbox":"26.42278,58.1,26.46278,58.14","lbl:max_zoom":18,"lbl:min_zoom":13.5,"mz:hierarchy_label":1,"mz:is_current":1,"mz:min_zoom":12,"name:est_x_preferred":["Räbi"],"name:hye_x_preferred":["Ռեբի"],"name:spa_x_preferred":["Räbi"],"name:ukr_x_preferred":["Рябі"],"name:vol_x_preferred":["Räbi"],"src:geom":"geonames","wof:belongsto":[85682941,102191581,1713315455,85633135,1713305759],"wof:breaches":[],"wof:concordances":{"gn:id":794570,"wk:page":"R%C3%A4bi"},"wof:coterminous":[1713315455],"wof:country":"EE","wof:geomhash":"7000abfa7bbb1453f20a44eea0f432a3","wof:hierarchy":[{"continent_id":102191581,"country_id":85633135,"county_id":1713305759,"localadmin_id":1713315455,"locality_id":1226308603,"region_id":85682941}],"wof:id":1226308603,"wof:lang_x_official":["est"],"wof:lang_x_spoken":["est"],"wof:lastmodified":1596661874,"wof:name":"Raebi","wof:parent_id":1713315455,"wof:placetype":"locality","wof:repo":"whosonfirst-data-admin-ee","wof:superseded_by":[],"wof:supersedes":[],"wof:tags":[]},"bbox":[26.44278,58.12,26.44278,58.12],"geometry":{"coordinates":[26.44278,58.12],"type":"Point"}}