{"id":1126065659,"type":"Feature","properties":{"edtf:cessation":"uuuu","edtf:inception":"uuuu","geom:area":0,"geom:area_square_m":0,"geom:bbox":"25.91639,59.60306,25.91639,59.60306","geom:latitude":59.60306,"geom:longitude":25.91639,"gn:country":"EE","gn:fcode":"PPLX","gn:population":112,"iso:country":"EE","lbl:bbox":"25.91139,59.59806,25.92139,59.60806","lbl:latitude":59.60306,"lbl:longitude":25.91639,"lbl:max_zoom":18,"mz:hierarchy_label":1,"mz:is_current":1,"mz:min_zoom":15,"mz:note":"Quattroshapes Point Gazetteer import 20170519","name:ceb_x_preferred":["Käsmu"],"name:deu_x_preferred":["Käsmu"],"name:eng_x_preferred":["Käsmu"],"name:est_x_preferred":["Käsmu"],"name:fra_x_preferred":["Käsmu"],"name:hye_x_preferred":["Կեսմու"],"name:kor_x_preferred":["캐스무"],"name:nld_x_preferred":["Käsmu"],"name:pol_x_preferred":["Käsmu"],"name:rus_x_preferred":["Кясму"],"name:swe_x_preferred":["Käsmu"],"name:und_x_variant":["Kyasmu"],"name:vol_x_preferred":["Käsmu"],"name:zho_x_preferred":["卡斯姆"],"qs_pg:aaroncc":"EE","qs_pg:gn_country":"EE","qs_pg:gn_fcode":"PPLX","qs_pg:gn_id":591538,"qs_pg:gn_pop":112,"qs_pg:name":"Käsmu","qs_pg:photos_9r":0,"qs_pg:photos_sr":0,"qs_pg:pop_sr":1,"qs_pg:qs_id":125907,"qs_pg:qs_pg_placetype":"neighbourhood","src:geom":"qs_pg","src:lbl_centroid":"qs_pg","src:population":"geonames","wof:belongsto":[102191581,1713308389,85633135,1713305775,85683049],"wof:breaches":[],"wof:concordances":{"gn:id":591538,"qs_pg:id":125907},"wof:country":"EE","wof:created":1497308846,"wof:geomhash":"e3e23b7e3585d97f43c876f1840d6ad3","wof:hierarchy":[{"continent_id":102191581,"country_id":85633135,"county_id":1713305775,"localadmin_id":1713308389,"locality_id":-1,"neighbourhood_id":1126065659,"region_id":85683049}],"wof:id":1126065659,"wof:lastmodified":1596678050,"wof:name":"Käsmu","wof:parent_id":-1,"wof:placetype":"neighbourhood","wof:population":112,"wof:population_rank":1,"wof:repo":"whosonfirst-data-admin-ee","wof:superseded_by":[],"wof:supersedes":[],"wof:tags":[]},"bbox":[25.91639,59.60306,25.91639,59.60306],"geometry":{"coordinates":[25.91639,59.60306],"type":"Point"}}