{"id":1243431545,"type":"Feature","properties":{"edtf:cessation":"uuuu","edtf:inception":"uuuu","geom:area":0,"geom:area_square_m":0,"geom:bbox":"26.33333,58.13333,26.33333,58.13333","geom:latitude":58.13333,"geom:longitude":26.33333,"gn:admin1_code":"18.0","gn:admin2_code":"171.0","gn:admin3_code":"8727.0","gn:asciiname":"Pritsu","gn:cc2":"EE","gn:country_code":"EE","gn:dem":97,"gn:feature_class":"P","gn:feature_code":"PPL","gn:geonameid":589335,"gn:latitude":58.13333,"gn:longitude":26.33333,"gn:modification_date":"2017-11-25","gn:name":"Pritsu","gn:population":0,"gn:timezone":"Europe/Tallinn","iso:country":"EE","lbl:bbox":"26.31333,58.11333,26.35333,58.15333","lbl:max_zoom":18,"lbl:min_zoom":13.5,"mz:hierarchy_label":1,"mz:is_current":1,"mz:min_zoom":12,"name:und_x_variant":["Middendorf","Pritsu"],"src:geom":"geonames","wof:belongsto":[85682995,102191581,1713310595,85633135,1713305757],"wof:breaches":[],"wof:concordances":{"gn:id":589335},"wof:country":"EE","wof:geomhash":"844177e66fcdefc5f2cc9db81fe0b23d","wof:hierarchy":[{"continent_id":102191581,"country_id":85633135,"county_id":1713305757,"localadmin_id":1713310595,"locality_id":1243431545,"region_id":85682995}],"wof:id":1243431545,"wof:lang_x_official":["est"],"wof:lang_x_spoken":["est"],"wof:lastmodified":1596661916,"wof:name":"Pritsu","wof:parent_id":1713310595,"wof:placetype":"locality","wof:repo":"whosonfirst-data-admin-ee","wof:superseded_by":[],"wof:supersedes":[],"wof:tags":[]},"bbox":[26.33333,58.13333,26.33333,58.13333],"geometry":{"coordinates":[26.33333,58.13333],"type":"Point"}}