{"id":1260363703,"type":"Feature","properties":{"edtf:cessation":"uuuu","edtf:inception":"uuuu","geom:area":0,"geom:area_square_m":0,"geom:bbox":"26.73806,57.78556,26.73806,57.78556","geom:latitude":57.78556,"geom:longitude":26.73806,"gn:admin1_code":"21.0","gn:admin2_code":"142.0","gn:admin3_code":"4543.0","gn:asciiname":"Piisi","gn:country_code":"EE","gn:dem":81,"gn:feature_class":"P","gn:feature_code":"PPL","gn:geonameid":795590,"gn:latitude":57.78556,"gn:longitude":26.73806,"gn:modification_date":"2017-11-25","gn:name":"Piisi","gn:population":0,"gn:timezone":"Europe/Tallinn","iso:country":"EE","lbl:bbox":"26.71806,57.76556,26.75806,57.80556","lbl:max_zoom":18,"lbl:min_zoom":13.5,"mz:hierarchy_label":1,"mz:is_current":1,"mz:min_zoom":12,"name:est_x_preferred":["Piisi"],"name:hye_x_preferred":["Պիիսի"],"name:pol_x_preferred":["Piisi"],"name:rus_x_preferred":["Пийси"],"name:sco_x_preferred":["Piisi"],"name:spa_x_preferred":["Piisi"],"name:ukr_x_preferred":["Піїсі"],"name:vol_x_preferred":["Piisi"],"src:geom":"geonames","wof:belongsto":[85682937,102191581,1713315857,85633135,1713305795],"wof:breaches":[],"wof:concordances":{"gn:id":795590,"wk:page":"Piisi"},"wof:coterminous":[1713315439],"wof:country":"EE","wof:geomhash":"b824fc51a28c395282890406f695c303","wof:hierarchy":[{"continent_id":102191581,"country_id":85633135,"county_id":1713305795,"localadmin_id":1713315857,"locality_id":1260363703,"region_id":85682937}],"wof:id":1260363703,"wof:lang_x_official":["est"],"wof:lang_x_spoken":["est"],"wof:lastmodified":1596677020,"wof:name":"Piisi","wof:parent_id":1713315857,"wof:placetype":"locality","wof:repo":"whosonfirst-data-admin-ee","wof:superseded_by":[],"wof:supersedes":[],"wof:tags":[]},"bbox":[26.73806,57.78556,26.73806,57.78556],"geometry":{"coordinates":[26.73806,57.78556],"type":"Point"}}