{"id":1277135933,"type":"Feature","properties":{"edtf:cessation":"uuuu","edtf:inception":"uuuu","geom:area":0,"geom:area_square_m":0,"geom:bbox":"27.45528,57.80944,27.45528,57.80944","geom:latitude":57.80944,"geom:longitude":27.45528,"gn:admin1_code":"21.0","gn:admin2_code":"732.0","gn:admin3_code":"2703.0","gn:asciiname":"Karamsina","gn:country_code":"EE","gn:dem":98,"gn:feature_class":"P","gn:feature_code":"PPL","gn:geonameid":8619927,"gn:latitude":57.80944,"gn:longitude":27.45528,"gn:modification_date":"2017-11-25","gn:name":"Karamsina","gn:population":0,"gn:timezone":"Europe/Tallinn","iso:country":"EE","lbl:bbox":"27.43528,57.78944,27.47528,57.82944","lbl:max_zoom":18,"lbl:min_zoom":13.5,"mz:hierarchy_label":1,"mz:is_current":1,"mz:min_zoom":12,"name:und_x_variant":["Karamsinna"],"src:geom":"geonames","wof:belongsto":[85682955,102191581,1713315849,85633135,1713305631],"wof:breaches":[],"wof:concordances":{"gn:id":8619927},"wof:coterminous":[1713315849],"wof:country":"EE","wof:geomhash":"32ee69fc633974036431d5c4fcaa458a","wof:hierarchy":[{"continent_id":102191581,"country_id":85633135,"county_id":1713305631,"localadmin_id":1713315849,"locality_id":1277135933,"region_id":85682955}],"wof:id":1277135933,"wof:lang_x_official":["est"],"wof:lang_x_spoken":["est"],"wof:lastmodified":1596663707,"wof:name":"Karamsina","wof:parent_id":1713315849,"wof:placetype":"locality","wof:repo":"whosonfirst-data-admin-ee","wof:superseded_by":[],"wof:supersedes":[],"wof:tags":[]},"bbox":[27.45528,57.80944,27.45528,57.80944],"geometry":{"coordinates":[27.45528,57.80944],"type":"Point"}}