{"id":1209780151,"type":"Feature","properties":{"edtf:cessation":"uuuu","edtf:inception":"uuuu","geom:area":0,"geom:area_square_m":0,"geom:bbox":"26.62056,57.82139,26.62056,57.82139","geom:latitude":57.82139,"geom:longitude":26.62056,"gn:admin1_code":"21.0","gn:admin2_code":"142.0","gn:admin3_code":"7933.0","gn:asciiname":"Saere","gn:country_code":"EE","gn:dem":108,"gn:feature_class":"P","gn:feature_code":"PPL","gn:geonameid":794438,"gn:latitude":57.82139,"gn:longitude":26.62056,"gn:modification_date":"2017-11-25","gn:name":"Säre","gn:population":0,"gn:timezone":"Europe/Tallinn","iso:country":"EE","lbl:bbox":"26.60056,57.80139,26.64056,57.84139","lbl:max_zoom":18,"lbl:min_zoom":13.5,"mz:hierarchy_label":1,"mz:is_current":1,"mz:min_zoom":12,"name:est_x_preferred":["Säre"],"name:hye_x_preferred":["Սեռե"],"name:pol_x_preferred":["Säre"],"name:sco_x_preferred":["Säre"],"name:spa_x_preferred":["Säre"],"name:ukr_x_preferred":["Сяре"],"name:vol_x_preferred":["Säre"],"src:geom":"geonames","wof:belongsto":[85682937,102191581,1713315855,85633135,1713305795],"wof:breaches":[],"wof:concordances":{"gn:id":794438,"wk:page":"S%C3%A4re"},"wof:coterminous":[1713315855],"wof:country":"EE","wof:geomhash":"8ba4aecb3b489129f37ce20887af7864","wof:hierarchy":[{"continent_id":102191581,"country_id":85633135,"county_id":1713305795,"localadmin_id":1713315855,"locality_id":1209780151,"region_id":85682937}],"wof:id":1209780151,"wof:lang_x_official":["est"],"wof:lang_x_spoken":["est"],"wof:lastmodified":1596677022,"wof:name":"Saere","wof:parent_id":1713315855,"wof:placetype":"locality","wof:repo":"whosonfirst-data-admin-ee","wof:superseded_by":[],"wof:supersedes":[],"wof:tags":[]},"bbox":[26.62056,57.82139,26.62056,57.82139],"geometry":{"coordinates":[26.62056,57.82139],"type":"Point"}}