{"id":1310693043,"type":"Feature","properties":{"edtf:cessation":"uuuu","edtf:inception":"uuuu","geom:area":0,"geom:area_square_m":0,"geom:bbox":"23.75,58.6725,23.75,58.6725","geom:latitude":58.6725,"geom:longitude":23.75,"gn:admin1_code":"11.0","gn:admin2_code":"430.0","gn:admin3_code":"6055.0","gn:asciiname":"Peanse","gn:country_code":"EE","gn:dem":13,"gn:feature_class":"P","gn:feature_code":"PPL","gn:geonameid":589550,"gn:latitude":58.6725,"gn:longitude":23.75,"gn:modification_date":"2017-11-25","gn:name":"Peanse","gn:population":0,"gn:timezone":"Europe/Tallinn","iso:country":"EE","lbl:bbox":"23.73,58.6525,23.77,58.6925","lbl:max_zoom":18,"lbl:min_zoom":13.5,"mz:hierarchy_label":1,"mz:is_current":1,"mz:min_zoom":12,"name:und_x_variant":["Peanze","Peanse"],"src:geom":"geonames","wof:belongsto":[85683001,102191581,1713309277,85633135,1713305721],"wof:breaches":[],"wof:concordances":{"gn:id":589550},"wof:coterminous":[1713309277],"wof:country":"EE","wof:geomhash":"7e76d6ce3f81a2e90bbfe9948c745676","wof:hierarchy":[{"continent_id":102191581,"country_id":85633135,"county_id":1713305721,"localadmin_id":1713309277,"locality_id":1310693043,"region_id":85683001}],"wof:id":1310693043,"wof:lang_x_official":["est"],"wof:lang_x_spoken":["est"],"wof:lastmodified":1596661687,"wof:name":"Peanse","wof:parent_id":1713309277,"wof:placetype":"locality","wof:repo":"whosonfirst-data-admin-ee","wof:superseded_by":[],"wof:supersedes":[],"wof:tags":[]},"bbox":[23.75,58.6725,23.75,58.6725],"geometry":{"coordinates":[23.75,58.6725],"type":"Point"}}