{"id":1260203401,"type":"Feature","properties":{"edtf:cessation":"uuuu","edtf:inception":"uuuu","geom:area":0,"geom:area_square_m":0,"geom:bbox":"25.86,59.27278,25.86,59.27278","geom:latitude":59.27278,"geom:longitude":25.86,"gn:admin1_code":"8.0","gn:admin2_code":"792.0","gn:admin3_code":"8549.0","gn:asciiname":"Toorakorve","gn:country_code":"EE","gn:dem":103,"gn:feature_class":"P","gn:feature_code":"PPL","gn:geonameid":588274,"gn:latitude":59.27278,"gn:longitude":25.86,"gn:modification_date":"2017-11-25","gn:name":"Tõõrakõrve","gn:population":0,"gn:timezone":"Europe/Tallinn","iso:country":"EE","lbl:bbox":"25.84,59.25278,25.88,59.29278","lbl:max_zoom":18,"lbl:min_zoom":13.5,"mz:hierarchy_label":1,"mz:is_current":1,"mz:min_zoom":12,"name:est_x_preferred":["Tõõrakõrve"],"name:fas_x_preferred":["توراکورو"],"name:hye_x_preferred":["Տիիռակիռվե"],"name:ukr_x_preferred":["Тииракирве"],"name:und_x_variant":["Tõerakõrve","Toerakyrve","Tõerakõrve Asundus"],"name:vol_x_preferred":["Tõõrakõrve"],"src:geom":"geonames","wof:belongsto":[85683049,102191581,1713315331,85633135,1713305761],"wof:breaches":[],"wof:concordances":{"gn:id":588274,"wk:page":"T%C3%B5%C3%B5rak%C3%B5rve"},"wof:coterminous":[1713315331],"wof:country":"EE","wof:geomhash":"956e6901d68fa17338a8bfaffd9cbcc3","wof:hierarchy":[{"continent_id":102191581,"country_id":85633135,"county_id":1713305761,"localadmin_id":1713315331,"locality_id":1260203401,"region_id":85683049}],"wof:id":1260203401,"wof:lang_x_official":["est"],"wof:lang_x_spoken":["est"],"wof:lastmodified":1596676599,"wof:name":"Toorakorve","wof:parent_id":1713315331,"wof:placetype":"locality","wof:repo":"whosonfirst-data-admin-ee","wof:superseded_by":[],"wof:supersedes":[],"wof:tags":[]},"bbox":[25.86,59.27278,25.86,59.27278],"geometry":{"coordinates":[25.86,59.27278],"type":"Point"}}