{"id":1327131249,"type":"Feature","properties":{"edtf:cessation":"uuuu","edtf:inception":"uuuu","geom:area":0,"geom:area_square_m":0,"geom:bbox":"23.63667,59.01389,23.63667,59.01389","geom:latitude":59.01389,"geom:longitude":23.63667,"gn:admin1_code":"7.0","gn:admin2_code":"441.0","gn:admin3_code":"7465.0","gn:asciiname":"Salajoe","gn:country_code":"EE","gn:dem":13,"gn:feature_class":"P","gn:feature_code":"PPL","gn:geonameid":794871,"gn:latitude":59.01389,"gn:longitude":23.63667,"gn:modification_date":"2017-11-25","gn:name":"Salajõe","gn:population":0,"gn:timezone":"Europe/Tallinn","iso:country":"EE","lbl:bbox":"23.61667,58.99389,23.65667,59.03389","lbl:max_zoom":18,"lbl:min_zoom":13.5,"mz:hierarchy_label":1,"mz:is_current":1,"mz:min_zoom":12,"name:est_x_preferred":["Salajõe"],"name:fra_x_preferred":["Salajõe"],"name:hye_x_preferred":["Սալայիե"],"name:nld_x_preferred":["Salajõe"],"name:pol_x_preferred":["Salajõe"],"name:rus_x_preferred":["Салайые"],"name:spa_x_preferred":["Salajõe"],"name:swe_x_preferred":["Salk"],"name:ukr_x_preferred":["Салайие"],"name:vol_x_preferred":["Salajõe"],"src:geom":"geonames","wof:belongsto":[85683001,102191581,1713308855,85633135,1713305701],"wof:breaches":[],"wof:concordances":{"gn:id":794871,"wk:page":"Salaj%C3%B5e"},"wof:coterminous":[1713309123],"wof:country":"EE","wof:geomhash":"5d2e8511547f420ecfbac0cdb2c0fec5","wof:hierarchy":[{"continent_id":102191581,"country_id":85633135,"county_id":1713305701,"localadmin_id":1713308855,"locality_id":1327131249,"region_id":85683001}],"wof:id":1327131249,"wof:lang_x_official":["est"],"wof:lang_x_spoken":["est"],"wof:lastmodified":1596677439,"wof:name":"Salajoe","wof:parent_id":1713308855,"wof:placetype":"locality","wof:repo":"whosonfirst-data-admin-ee","wof:superseded_by":[],"wof:supersedes":[],"wof:tags":[]},"bbox":[23.63667,59.01389,23.63667,59.01389],"geometry":{"coordinates":[23.63667,59.01389],"type":"Point"}}