{"id":1310460963,"type":"Feature","properties":{"edtf:cessation":"uuuu","edtf:inception":"uuuu","geom:area":0,"geom:area_square_m":0,"geom:bbox":"26.60028,57.59778,26.60028,57.59778","geom:latitude":57.59778,"geom:longitude":26.60028,"gn:admin1_code":"21.0","gn:admin2_code":"698.0","gn:admin3_code":"1972.0","gn:asciiname":"Andsi","gn:country_code":"EE","gn:dem":82,"gn:feature_class":"P","gn:feature_code":"PPL","gn:geonameid":8619064,"gn:latitude":57.59778,"gn:longitude":26.60028,"gn:modification_date":"2017-11-25","gn:name":"Andsi","gn:population":0,"gn:timezone":"Europe/Tallinn","iso:country":"EE","lbl:bbox":"26.58028,57.57778,26.62028,57.61778","lbl:max_zoom":18,"lbl:min_zoom":13.5,"mz:hierarchy_label":1,"mz:is_current":1,"mz:min_zoom":12,"name:und_x_variant":["Antsi"],"src:geom":"geonames","wof:belongsto":[85682937,102191581,1713314963,85633135,1713305787],"wof:breaches":[],"wof:concordances":{"gn:id":8619064},"wof:country":"EE","wof:geomhash":"5b416f766bba970d6fced646d7e5cda7","wof:hierarchy":[{"continent_id":102191581,"country_id":85633135,"county_id":1713305787,"localadmin_id":1713314963,"locality_id":1310460963,"region_id":85682937}],"wof:id":1310460963,"wof:lang_x_official":["est"],"wof:lang_x_spoken":["est"],"wof:lastmodified":1596676878,"wof:name":"Andsi","wof:parent_id":1713314963,"wof:placetype":"locality","wof:repo":"whosonfirst-data-admin-ee","wof:superseded_by":[],"wof:supersedes":[],"wof:tags":[]},"bbox":[26.60028,57.59778,26.60028,57.59778],"geometry":{"coordinates":[26.60028,57.59778],"type":"Point"}}