{"id":1242854537,"type":"Feature","properties":{"edtf:cessation":"uuuu","edtf:inception":"uuuu","geom:area":0,"geom:area_square_m":0,"geom:bbox":"27.27417,57.98917,27.27417,57.98917","geom:latitude":57.98917,"geom:longitude":27.27417,"gn:admin1_code":"12.0","gn:admin2_code":"708.0","gn:admin3_code":"1706.0","gn:asciiname":"Vinso","gn:country_code":"EE","gn:dem":59,"gn:feature_class":"P","gn:feature_code":"PPL","gn:geonameid":794208,"gn:latitude":57.98917,"gn:longitude":27.27417,"gn:modification_date":"2017-11-25","gn:name":"Vinso","gn:population":0,"gn:timezone":"Europe/Tallinn","iso:country":"EE","lbl:bbox":"27.25417,57.96917,27.29417,58.00917","lbl:max_zoom":18,"lbl:min_zoom":13.5,"mz:hierarchy_label":1,"mz:is_current":1,"mz:min_zoom":12,"name:est_x_preferred":["Vinso"],"name:hye_x_preferred":["Վինսո"],"name:pol_x_preferred":["Vinso"],"name:spa_x_preferred":["Vinso"],"name:ukr_x_preferred":["Вінсо"],"name:vol_x_preferred":["Vinso"],"src:geom":"geonames","wof:belongsto":[85682955,102191581,1713310905,85633135,1713305793],"wof:breaches":[],"wof:concordances":{"gn:id":794208,"wk:page":"Vinso"},"wof:coterminous":[1713310969],"wof:country":"EE","wof:geomhash":"8f1b5d97a721ae0b2080d97e9c59d01e","wof:hierarchy":[{"continent_id":102191581,"country_id":85633135,"county_id":1713305793,"localadmin_id":1713310905,"locality_id":1242854537,"region_id":85682955}],"wof:id":1242854537,"wof:lang_x_official":["est"],"wof:lang_x_spoken":["est"],"wof:lastmodified":1596677000,"wof:name":"Vinso","wof:parent_id":1713310905,"wof:placetype":"locality","wof:repo":"whosonfirst-data-admin-ee","wof:superseded_by":[],"wof:supersedes":[],"wof:tags":[]},"bbox":[27.27417,57.98917,27.27417,57.98917],"geometry":{"coordinates":[27.27417,57.98917],"type":"Point"}}