{"id":1293464947,"type":"Feature","properties":{"edtf:cessation":"uuuu","edtf:inception":"uuuu","geom:area":0,"geom:area_square_m":0,"geom:bbox":"25.85111,58.04611,25.85111,58.04611","geom:latitude":58.04611,"geom:longitude":25.85111,"gn:admin1_code":"19.0","gn:admin2_code":"824.0","gn:admin3_code":"4390.0","gn:asciiname":"Voorbahi","gn:country_code":"EE","gn:dem":84,"gn:feature_class":"P","gn:feature_code":"PPL","gn:geonameid":793930,"gn:latitude":58.04611,"gn:longitude":25.85111,"gn:modification_date":"2017-11-25","gn:name":"Voorbahi","gn:population":0,"gn:timezone":"Europe/Tallinn","iso:country":"EE","lbl:bbox":"25.83111,58.02611,25.87111,58.06611","lbl:max_zoom":18,"lbl:min_zoom":13.5,"mz:hierarchy_label":1,"mz:is_current":1,"mz:min_zoom":12,"name:est_x_preferred":["Voorbahi"],"name:hye_x_preferred":["Վոոռբահի"],"name:pol_x_preferred":["Voorbahi"],"name:spa_x_preferred":["Voorbahi"],"name:ukr_x_preferred":["Воорбагі"],"name:vol_x_preferred":["Voorbahi"],"src:geom":"geonames","wof:belongsto":[85682941,102191581,1713315083,85633135,1713305687],"wof:breaches":[],"wof:concordances":{"gn:id":793930,"wk:page":"Voorbahi"},"wof:coterminous":[1713314041],"wof:country":"EE","wof:geomhash":"4bc03a0d7560e74e9b5037d2733abf4c","wof:hierarchy":[{"continent_id":102191581,"country_id":85633135,"county_id":1713305687,"localadmin_id":1713315083,"locality_id":1293464947,"region_id":85682941}],"wof:id":1293464947,"wof:lang_x_official":["est"],"wof:lang_x_spoken":["est"],"wof:lastmodified":1596661437,"wof:name":"Voorbahi","wof:parent_id":1713315083,"wof:placetype":"locality","wof:repo":"whosonfirst-data-admin-ee","wof:superseded_by":[],"wof:supersedes":[],"wof:tags":[]},"bbox":[25.85111,58.04611,25.85111,58.04611],"geometry":{"coordinates":[25.85111,58.04611],"type":"Point"}}