{"id":1126025101,"type":"Feature","properties":{"edtf:cessation":"uuuu","edtf:inception":"uuuu","geom:area":0,"geom:area_square_m":0,"geom:bbox":"26.0375,57.98583,26.0375,57.98583","geom:latitude":57.98583,"geom:longitude":26.0375,"gn:country":"EE","gn:fcode":"PPL","gn:population":153,"iso:country":"EE","lbl:bbox":"26.0175,57.96583,26.0575,58.00583","lbl:latitude":57.98583,"lbl:longitude":26.0375,"lbl:max_zoom":18,"lbl:min_zoom":13,"mz:hierarchy_label":1,"mz:is_current":1,"mz:min_zoom":11,"mz:note":"Quattroshapes Point Gazetteer import 20170519","name:eng_x_preferred":["Jõgeveste"],"name:rus_x_preferred":["Йыгевесте"],"name:und_x_variant":["Myza Iygeveste"],"qs_pg:aaroncc":"EE","qs_pg:gn_country":"EE","qs_pg:gn_fcode":"PPL","qs_pg:gn_id":591900,"qs_pg:gn_pop":153,"qs_pg:name":"Jõgeveste","qs_pg:photos_9r":0,"qs_pg:photos_sr":0,"qs_pg:pop_sr":1,"qs_pg:qs_id":550158,"qs_pg:qs_pg_placetype":"locality","src:geom":"qs_pg","src:lbl_centroid":"qs_pg","src:population":"geonames","wof:belongsto":[85682941,102191581,1713310345,85633135,1713305687],"wof:breaches":[],"wof:concordances":{"gn:id":591900,"qs_pg:id":550158},"wof:coterminous":[1713310345],"wof:country":"EE","wof:created":1497301090,"wof:geomhash":"c3dbf8dede7d2e7708f00af36f8c0a3e","wof:hierarchy":[{"continent_id":102191581,"country_id":85633135,"county_id":1713305687,"localadmin_id":1713310345,"locality_id":1126025101,"region_id":85682941}],"wof:id":1126025101,"wof:lang_x_official":["est"],"wof:lang_x_spoken":["est"],"wof:lastmodified":1596661440,"wof:name":"Jõgeveste","wof:parent_id":1713310345,"wof:placetype":"locality","wof:population":153,"wof:population_rank":1,"wof:repo":"whosonfirst-data-admin-ee","wof:superseded_by":[],"wof:supersedes":[],"wof:tags":[]},"bbox":[26.0375,57.98583,26.0375,57.98583],"geometry":{"coordinates":[26.0375,57.98583],"type":"Point"}}