{"id":1226407853,"type":"Feature","properties":{"edtf:cessation":"uuuu","edtf:inception":"uuuu","geom:area":0,"geom:area_square_m":0,"geom:bbox":"25.93556,58.03472,25.93556,58.03472","geom:latitude":58.03472,"geom:longitude":25.93556,"gn:admin1_code":"19.0","gn:admin2_code":"824.0","gn:admin3_code":"5304.0","gn:asciiname":"Iltsmu","gn:country_code":"EE","gn:dem":69,"gn:feature_class":"P","gn:feature_code":"PPL","gn:geonameid":592044,"gn:latitude":58.03472,"gn:longitude":25.93556,"gn:modification_date":"2017-11-25","gn:name":"Iltsmu","gn:population":0,"gn:timezone":"Europe/Tallinn","iso:country":"EE","lbl:bbox":"25.91556,58.01472,25.95556,58.05472","lbl:max_zoom":18,"lbl:min_zoom":13.5,"mz:hierarchy_label":1,"mz:is_current":1,"mz:min_zoom":12,"name:und_x_variant":["Mangle","Iltsmo","Iltsma","Iltsmu"],"src:geom":"geonames","wof:belongsto":[85682941,102191581,1713315251,85633135,1713305687],"wof:breaches":[],"wof:concordances":{"gn:id":592044},"wof:country":"EE","wof:geomhash":"83f62752273fde726f9fe7143f70265e","wof:hierarchy":[{"continent_id":102191581,"country_id":85633135,"county_id":1713305687,"localadmin_id":1713315251,"locality_id":1226407853,"region_id":85682941}],"wof:id":1226407853,"wof:lang_x_official":["est"],"wof:lang_x_spoken":["est"],"wof:lastmodified":1596661436,"wof:name":"Iltsmu","wof:parent_id":1713315251,"wof:placetype":"locality","wof:repo":"whosonfirst-data-admin-ee","wof:superseded_by":[],"wof:supersedes":[],"wof:tags":[]},"bbox":[25.93556,58.03472,25.93556,58.03472],"geometry":{"coordinates":[25.93556,58.03472],"type":"Point"}}