{"id":1126008697,"type":"Feature","properties":{"edtf:cessation":"uuuu","edtf:inception":"uuuu","geom:area":0,"geom:area_square_m":0,"geom:bbox":"26.545,57.87722,26.545,57.87722","geom:latitude":57.87722,"geom:longitude":26.545,"gn:country":"EE","gn:fcode":"PPL","gn:population":243,"iso:country":"EE","lbl:bbox":"26.525,57.85722,26.565,57.89722","lbl:latitude":57.87722,"lbl:longitude":26.545,"lbl:max_zoom":17,"lbl:min_zoom":12.5,"mz:hierarchy_label":1,"mz:is_current":1,"mz:min_zoom":11,"mz:note":"Quattroshapes Point Gazetteer import 20170519","qs_pg:aaroncc":"EE","qs_pg:gn_country":"EE","qs_pg:gn_fcode":"PPL","qs_pg:gn_id":794449,"qs_pg:gn_pop":243,"qs_pg:name":"Uue-Antsla","qs_pg:name_adm0":"Eesti","qs_pg:name_adm1":"Võrumaa","qs_pg:photos_9k":1,"qs_pg:photos_9r":1,"qs_pg:photos_all":4,"qs_pg:photos_sr":0,"qs_pg:pop_sr":2,"qs_pg:qs_id":111204,"qs_pg:qs_pg_placetype":"locality","qs_pg:qs_pg_placetype_gp":"Town","qs_pg:woe_adm0":23424805,"qs_pg:woe_id":846103,"src:geom":"qs_pg","src:lbl_centroid":"qs_pg","src:population":"geonames","woe:adm0_id":23424805,"woe:name_adm0":"Eesti","woe:name_adm1":"Võrumaa","woe:placetype":"Town","wof:belongsto":[85682937,102191581,1713311053,85633135,1713305795],"wof:breaches":[],"wof:concordances":{"gn:id":794449,"gp:id":846103,"qs_pg:id":111204},"wof:coterminous":[1713311053],"wof:country":"EE","wof:created":1497300136,"wof:geomhash":"24e69ccf886393b76b318e24a182f4e2","wof:hierarchy":[{"continent_id":102191581,"country_id":85633135,"county_id":1713305795,"localadmin_id":1713311053,"locality_id":1126008697,"region_id":85682937}],"wof:id":1126008697,"wof:lang_x_official":["est"],"wof:lang_x_spoken":["est"],"wof:lastmodified":1596677026,"wof:name":"Uue-Antsla","wof:parent_id":1713311053,"wof:placetype":"locality","wof:population":243,"wof:population_rank":2,"wof:repo":"whosonfirst-data-admin-ee","wof:superseded_by":[],"wof:supersedes":[],"wof:tags":[]},"bbox":[26.545,57.87722,26.545,57.87722],"geometry":{"coordinates":[26.545,57.87722],"type":"Point"}}