{"id":1193023549,"type":"Feature","properties":{"edtf:cessation":"uuuu","edtf:inception":"uuuu","geom:area":0,"geom:area_square_m":0,"geom:bbox":"27.71194,59.04167,27.71194,59.04167","geom:latitude":59.04167,"geom:longitude":27.71194,"gn:admin1_code":"3.0","gn:admin2_code":"130.0","gn:admin3_code":"2130.0","gn:asciiname":"Jaama","gn:cc2":"EE","gn:country_code":"EE","gn:dem":35,"gn:feature_class":"P","gn:feature_code":"PPL","gn:geonameid":587637,"gn:latitude":59.04167,"gn:longitude":27.71194,"gn:modification_date":"2017-11-25","gn:name":"Jaama","gn:population":0,"gn:timezone":"Europe/Tallinn","iso:country":"EE","lbl:bbox":"27.69194,59.02167,27.73194,59.06167","lbl:max_zoom":18,"lbl:min_zoom":13.5,"mz:hierarchy_label":1,"mz:is_current":1,"mz:min_zoom":12,"name:deu_x_preferred":["Jaama"],"name:eng_x_preferred":["Jaama"],"name:est_x_preferred":["Jaama"],"name:fra_x_preferred":["Jaama"],"name:hye_x_preferred":["Յաամա"],"name:nld_x_preferred":["Jaama"],"name:pol_x_preferred":["Jaama"],"name:rus_x_preferred":["Яама"],"name:spa_x_preferred":["Jaama"],"name:und_x_variant":["Yama","Vikhtse","Vihtse"],"name:urd_x_preferred":["جامہ"],"name:vol_x_preferred":["Jaama"],"src:geom":"geonames","wof:belongsto":[85683059,102191581,1713311563,85633135,1713305693],"wof:breaches":[],"wof:concordances":{"gn:id":587637,"wk:page":"Jaama%2C_Ida-Viru_County"},"wof:coterminous":[1713311563],"wof:country":"EE","wof:geomhash":"58984639c0a8f8c58653fefa271df132","wof:hierarchy":[{"continent_id":102191581,"country_id":85633135,"county_id":1713305693,"localadmin_id":1713311563,"locality_id":1193023549,"region_id":85683059}],"wof:id":1193023549,"wof:lang_x_official":["est"],"wof:lang_x_spoken":["est"],"wof:lastmodified":1596660735,"wof:name":"Jaama","wof:parent_id":1713311563,"wof:placetype":"locality","wof:repo":"whosonfirst-data-admin-ee","wof:superseded_by":[],"wof:supersedes":[],"wof:tags":[]},"bbox":[27.71194,59.04167,27.71194,59.04167],"geometry":{"coordinates":[27.71194,59.04167],"type":"Point"}}