{"id":1125821679,"type":"Feature","properties":{"edtf:cessation":"uuuu","edtf:inception":"uuuu","geom:area":0,"geom:area_square_m":0,"geom:bbox":"21.86923,58.486717,21.86923,58.486717","geom:latitude":58.486717,"geom:longitude":21.86923,"gn:country":"EE","iso:country":"EE","lbl:bbox":"21.84923,58.4667175,21.88923,58.5067175","lbl:latitude":58.486717,"lbl:longitude":21.86923,"lbl:max_zoom":18,"lbl:min_zoom":13.5,"mz:hierarchy_label":1,"mz:is_current":1,"mz:min_zoom":12,"mz:note":"Quattroshapes Point Gazetteer import 20170519","name:deu_x_preferred":["Neeme"],"name:eng_x_preferred":["Neeme"],"name:est_x_preferred":["Neeme"],"name:hye_x_preferred":["Նեեմե"],"name:nld_x_preferred":["Neeme"],"name:pol_x_preferred":["Neeme"],"name:spa_x_preferred":["Neeme"],"name:vol_x_preferred":["Neeme"],"qs_pg:aaroncc":"EE","qs_pg:gn_country":"EE","qs_pg:name":"Neeme","qs_pg:name_adm0":"Eesti","qs_pg:name_adm1":"Saaremaa","qs_pg:photos":56,"qs_pg:photos_1k":11,"qs_pg:photos_9k":1,"qs_pg:photos_9r":2,"qs_pg:photos_all":56,"qs_pg:photos_sr":2,"qs_pg:pop_sr":0,"qs_pg:qs_id":1086556,"qs_pg:qs_pg_placetype":"locality","qs_pg:qs_pg_placetype_gp":"Town","qs_pg:woe_adm0":23424805,"qs_pg:woe_id":844229,"src:geom":"qs_pg","src:lbl_centroid":"qs_pg","woe:adm0_id":23424805,"woe:name_adm0":"Eesti","woe:name_adm1":"Saaremaa","woe:placetype":"Town","wof:belongsto":[],"wof:breaches":[],"wof:concordances":{"gp:id":844229,"qs_pg:id":1086556,"wd:id":"Q3465993"},"wof:coterminous":[1713307073],"wof:country":"EE","wof:created":1497292098,"wof:geomhash":"a3d2484b977ae4675f2740be65595693","wof:hierarchy":[{"continent_id":-1,"country_id":-1,"locality_id":1125821679,"region_id":-1}],"wof:id":1125821679,"wof:lang_x_official":["est"],"wof:lang_x_spoken":["est"],"wof:lastmodified":1596130294,"wof:name":"Neeme","wof:parent_id":-1,"wof:placetype":"locality","wof:repo":"whosonfirst-data-admin-ee","wof:superseded_by":[],"wof:supersedes":[],"wof:tags":[]},"bbox":[21.86923,58.486717,21.86923,58.486717],"geometry":{"coordinates":[21.86923,58.486717],"type":"Point"}}