{"id":1326804527,"type":"Feature","properties":{"edtf:cessation":"uuuu","edtf:inception":"uuuu","geom:area":0,"geom:area_square_m":0,"geom:bbox":"27.16778,57.68472,27.16778,57.68472","geom:latitude":57.68472,"geom:longitude":27.16778,"gn:admin1_code":"21.0","gn:admin2_code":"917.0","gn:admin3_code":"4544.0","gn:asciiname":"Luhte","gn:country_code":"EE","gn:dem":203,"gn:feature_class":"P","gn:feature_code":"PPL","gn:geonameid":8619986,"gn:latitude":57.68472,"gn:longitude":27.16778,"gn:modification_date":"2017-11-25","gn:name":"Luhte","gn:population":0,"gn:timezone":"Europe/Tallinn","iso:country":"EE","lbl:bbox":"27.14778,57.66472,27.18778,57.70472","lbl:max_zoom":18,"lbl:min_zoom":13.5,"mz:hierarchy_label":1,"mz:is_current":1,"mz:min_zoom":12,"name:est_x_preferred":["Luhte"],"name:hye_x_preferred":["Լուհտե"],"name:nld_x_preferred":["Luhte"],"name:pol_x_preferred":["Luhte"],"name:spa_x_preferred":["Luhte"],"name:ukr_x_preferred":["Лухте"],"name:und_x_variant":["Luhtõ"],"name:vol_x_preferred":["Luhte"],"src:geom":"geonames","wof:belongsto":[85682937,102191581,1713316327,85633135,1713305633],"wof:breaches":[],"wof:concordances":{"gn:id":8619986,"wk:page":"Luhte"},"wof:coterminous":[1713316327],"wof:country":"EE","wof:geomhash":"1f378caebfe20fd6369550e4826167bf","wof:hierarchy":[{"continent_id":102191581,"country_id":85633135,"county_id":1713305633,"localadmin_id":1713316327,"locality_id":1326804527,"region_id":85682937}],"wof:id":1326804527,"wof:lang_x_official":["est"],"wof:lang_x_spoken":["est"],"wof:lastmodified":1596660403,"wof:name":"Luhte","wof:parent_id":1713316327,"wof:placetype":"locality","wof:repo":"whosonfirst-data-admin-ee","wof:superseded_by":[],"wof:supersedes":[],"wof:tags":[]},"bbox":[27.16778,57.68472,27.16778,57.68472],"geometry":{"coordinates":[27.16778,57.68472],"type":"Point"}}