{"id":1210003849,"type":"Feature","properties":{"edtf:cessation":"uuuu","edtf:inception":"uuuu","geom:area":0,"geom:area_square_m":0,"geom:bbox":"26.59833,58.06694,26.59833,58.06694","geom:latitude":58.06694,"geom:longitude":26.59833,"gn:admin1_code":"12.0","gn:admin2_code":"284.0","gn:admin3_code":"6209.0","gn:asciiname":"Kitse","gn:country_code":"EE","gn:dem":178,"gn:feature_class":"P","gn:feature_code":"PPL","gn:geonameid":591331,"gn:latitude":58.06694,"gn:longitude":26.59833,"gn:modification_date":"2017-11-25","gn:name":"Kitse","gn:population":0,"gn:timezone":"Europe/Tallinn","iso:country":"EE","lbl:bbox":"26.57833,58.04694,26.61833,58.08694","lbl:max_zoom":18,"lbl:min_zoom":13.5,"mz:hierarchy_label":1,"mz:is_current":1,"mz:min_zoom":12,"name:est_x_preferred":["Kitse"],"src:geom":"geonames","wof:belongsto":[85682955,102191581,1713314321,85633135,1713305789],"wof:breaches":[],"wof:concordances":{"gn:id":591331},"wof:country":"EE","wof:geomhash":"48d2b87c748fd80a59b84206e0c027bc","wof:hierarchy":[{"continent_id":102191581,"country_id":85633135,"county_id":1713305789,"localadmin_id":1713314321,"locality_id":1210003849,"region_id":85682955}],"wof:id":1210003849,"wof:lang_x_official":["est"],"wof:lang_x_spoken":["est"],"wof:lastmodified":1596676785,"wof:name":"Kitse","wof:parent_id":1713314321,"wof:placetype":"locality","wof:repo":"whosonfirst-data-admin-ee","wof:superseded_by":[],"wof:supersedes":[],"wof:tags":[]},"bbox":[26.59833,58.06694,26.59833,58.06694],"geometry":{"coordinates":[26.59833,58.06694],"type":"Point"}}