{"id":1326617303,"type":"Feature","properties":{"edtf:cessation":"uuuu","edtf:inception":"uuuu","geom:area":0,"geom:area_square_m":0,"geom:bbox":"26.86889,58.06111,26.86889,58.06111","geom:latitude":58.06111,"geom:longitude":26.86889,"gn:admin1_code":"12.0","gn:admin2_code":"284.0","gn:admin3_code":"2007.0","gn:asciiname":"Hilba","gn:country_code":"EE","gn:dem":116,"gn:feature_class":"P","gn:feature_code":"PPL","gn:geonameid":8620700,"gn:latitude":58.06111,"gn:longitude":26.86889,"gn:modification_date":"2017-11-25","gn:name":"Hilba","gn:population":0,"gn:timezone":"Europe/Tallinn","iso:country":"EE","lbl:bbox":"26.84889,58.04111,26.88889,58.08111","lbl:max_zoom":18,"lbl:min_zoom":13.5,"mz:hierarchy_label":1,"mz:is_current":1,"mz:min_zoom":12,"name:deu_x_preferred":["Hilba järv"],"name:est_x_preferred":["Hilba järv"],"name:und_x_variant":["Täikülä","Hilba"],"src:geom":"geonames","wof:belongsto":[85682955,102191581,1713313141,85633135,1713305789],"wof:breaches":[],"wof:concordances":{"gn:id":8620700,"wk:page":"Hilba"},"wof:country":"EE","wof:geomhash":"e2807b6228751fd30c05691aca48a6e6","wof:hierarchy":[{"continent_id":102191581,"country_id":85633135,"county_id":1713305789,"localadmin_id":1713313141,"locality_id":1326617303,"region_id":85682955}],"wof:id":1326617303,"wof:lang_x_official":["est"],"wof:lang_x_spoken":["est"],"wof:lastmodified":1596676792,"wof:name":"Hilba","wof:parent_id":1713313141,"wof:placetype":"locality","wof:repo":"whosonfirst-data-admin-ee","wof:superseded_by":[],"wof:supersedes":[],"wof:tags":[]},"bbox":[26.86889,58.06111,26.86889,58.06111],"geometry":{"coordinates":[26.86889,58.06111],"type":"Point"}}