{"id":1226518231,"type":"Feature","properties":{"edtf:cessation":"uuuu","edtf:inception":"uuuu","geom:area":0,"geom:area_square_m":0,"geom:bbox":"26.43333,58.43722,26.43333,58.43722","geom:latitude":58.43722,"geom:longitude":26.43333,"gn:admin1_code":"18.0","gn:admin2_code":"796.0","gn:admin3_code":"3900.0","gn:asciiname":"Koosa","gn:country_code":"EE","gn:dem":45,"gn:feature_class":"P","gn:feature_code":"PPL","gn:geonameid":8619429,"gn:latitude":58.43722,"gn:longitude":26.43333,"gn:modification_date":"2017-11-25","gn:name":"Koosa","gn:population":0,"gn:timezone":"Europe/Tallinn","iso:country":"EE","lbl:bbox":"26.41333,58.41722,26.45333,58.45722","lbl:max_zoom":18,"lbl:min_zoom":13.5,"mz:hierarchy_label":1,"mz:is_current":1,"mz:min_zoom":12,"name:ceb_x_preferred":["Koosa"],"name:est_x_preferred":["Koosa"],"name:hye_x_preferred":["Կոոսա"],"name:pol_x_preferred":["Koosa"],"name:spa_x_preferred":["Koosa"],"name:swe_x_preferred":["Koosa"],"name:ukr_x_preferred":["Кооза"],"name:und_x_variant":["Д-ры Кооза"],"name:vol_x_preferred":["Koosa"],"src:geom":"geonames","wof:belongsto":[85683009,102191581,1713309087,85633135,1713305659],"wof:breaches":[],"wof:concordances":{"gn:id":8619429},"wof:country":"EE","wof:geomhash":"471d1a26fe5b8c1efa54d2c72e52ef4b","wof:hierarchy":[{"continent_id":102191581,"country_id":85633135,"county_id":1713305659,"localadmin_id":1713309087,"locality_id":1226518231,"region_id":85683009}],"wof:id":1226518231,"wof:lang_x_official":["est"],"wof:lang_x_spoken":["est"],"wof:lastmodified":1596676472,"wof:name":"Koosa","wof:parent_id":1713309087,"wof:placetype":"locality","wof:repo":"whosonfirst-data-admin-ee","wof:superseded_by":[],"wof:supersedes":[],"wof:tags":[]},"bbox":[26.43333,58.43722,26.43333,58.43722],"geometry":{"coordinates":[26.43333,58.43722],"type":"Point"}}