{"id":1343444557,"type":"Feature","properties":{"edtf:cessation":"uuuu","edtf:inception":"uuuu","geom:area":0,"geom:area_square_m":0,"geom:bbox":"22.43278,58.3025,22.43278,58.3025","geom:latitude":58.3025,"geom:longitude":22.43278,"gn:admin1_code":"14.0","gn:admin2_code":"714.0","gn:admin3_code":"2935.0","gn:asciiname":"Pollu","gn:country_code":"EE","gn:dem":18,"gn:feature_class":"P","gn:feature_code":"PPL","gn:geonameid":589381,"gn:latitude":58.3025,"gn:longitude":22.43278,"gn:modification_date":"2017-11-25","gn:name":"Põllu","gn:population":0,"gn:timezone":"Europe/Tallinn","iso:country":"EE","lbl:bbox":"22.41278,58.2825,22.45278,58.3225","lbl:max_zoom":18,"lbl:min_zoom":13.5,"mz:hierarchy_label":1,"mz:is_current":1,"mz:min_zoom":12,"src:geom":"geonames","wof:belongsto":[85682947,102191581,1713308197,85633135,1713305627],"wof:breaches":[],"wof:concordances":{"gn:id":589381},"wof:country":"EE","wof:geomhash":"00a8266c73ec29f634890f130e55aaca","wof:hierarchy":[{"continent_id":102191581,"country_id":85633135,"county_id":1713305627,"localadmin_id":1713308197,"locality_id":1343444557,"region_id":85682947}],"wof:id":1343444557,"wof:lang_x_official":["est"],"wof:lang_x_spoken":["est"],"wof:lastmodified":1596674935,"wof:name":"Pollu","wof:parent_id":1713308197,"wof:placetype":"locality","wof:repo":"whosonfirst-data-admin-ee","wof:superseded_by":[],"wof:supersedes":[],"wof:tags":[]},"bbox":[22.43278,58.3025,22.43278,58.3025],"geometry":{"coordinates":[22.43278,58.3025],"type":"Point"}}