{"id":1226753717,"type":"Feature","properties":{"edtf:cessation":"uuuu","edtf:inception":"uuuu","geom:area":0,"geom:area_square_m":0,"geom:bbox":"25.68333,58.96667,25.68333,58.96667","geom:latitude":58.96667,"geom:longitude":25.68333,"gn:admin1_code":"4.0","gn:admin2_code":"567.0","gn:admin3_code":"3137.0","gn:asciiname":"Ollikuela","gn:country_code":"EE","gn:dem":79,"gn:feature_class":"P","gn:feature_code":"PPL","gn:geonameid":589835,"gn:latitude":58.96667,"gn:longitude":25.68333,"gn:modification_date":"2017-11-25","gn:name":"Olliküla","gn:population":0,"gn:timezone":"Europe/Tallinn","iso:country":"EE","lbl:bbox":"25.66333,58.94667,25.70333,58.98667","lbl:max_zoom":18,"lbl:min_zoom":13.5,"mz:hierarchy_label":1,"mz:is_current":1,"mz:min_zoom":12,"name:und_x_variant":["Ollikyula","Olliküla"],"src:geom":"geonames","wof:belongsto":[85683031,102191581,1713308111,85633135,1713305663],"wof:breaches":[],"wof:concordances":{"gn:id":589835},"wof:country":"EE","wof:geomhash":"ed599da2ff8c5a0d1d3d197084acd0b7","wof:hierarchy":[{"continent_id":102191581,"country_id":85633135,"county_id":1713305663,"localadmin_id":1713308111,"locality_id":1226753717,"region_id":85683031}],"wof:id":1226753717,"wof:lang_x_official":["est"],"wof:lang_x_spoken":["est"],"wof:lastmodified":1596661329,"wof:name":"Ollikuela","wof:parent_id":1713308111,"wof:placetype":"locality","wof:repo":"whosonfirst-data-admin-ee","wof:superseded_by":[],"wof:supersedes":[],"wof:tags":[]},"bbox":[25.68333,58.96667,25.68333,58.96667],"geometry":{"coordinates":[25.68333,58.96667],"type":"Point"}}