{"id":1259946165,"type":"Feature","properties":{"edtf:cessation":"uuuu","edtf:inception":"uuuu","geom:area":0,"geom:area_square_m":0,"geom:bbox":"27.06694,58.60917,27.06694,58.60917","geom:latitude":58.60917,"geom:longitude":27.06694,"gn:admin1_code":"18.0","gn:admin2_code":"586.0","gn:admin3_code":"7484.0","gn:asciiname":"Savastvere","gn:cc2":"EE","gn:country_code":"EE","gn:dem":64,"gn:feature_class":"P","gn:feature_code":"PPL","gn:geonameid":588755,"gn:latitude":58.60917,"gn:longitude":27.06694,"gn:modification_date":"2017-11-25","gn:name":"Savastvere","gn:population":0,"gn:timezone":"Europe/Tallinn","iso:country":"EE","lbl:bbox":"27.04694,58.58917,27.08694,58.62917","lbl:max_zoom":18,"lbl:min_zoom":13.5,"mz:hierarchy_label":1,"mz:is_current":1,"mz:min_zoom":12,"name:est_x_preferred":["Savastvere"],"name:fra_x_preferred":["Savastvere"],"name:hye_x_preferred":["Սավաստվեռե"],"name:pol_x_preferred":["Savastvere"],"name:spa_x_preferred":["Savastvere"],"name:ukr_x_preferred":["Саваствере"],"name:und_x_variant":["Savastere"],"name:vol_x_preferred":["Savastvere"],"src:geom":"geonames","wof:belongsto":[85682995,102191581,1713309601,85633135,1713305679],"wof:breaches":[],"wof:concordances":{"gn:id":588755,"wk:page":"Savastvere"},"wof:coterminous":[1713309601],"wof:country":"EE","wof:geomhash":"ed370a95a06bd9a2800dcd8bbf828910","wof:hierarchy":[{"continent_id":102191581,"country_id":85633135,"county_id":1713305679,"localadmin_id":1713309601,"locality_id":1259946165,"region_id":85682995}],"wof:id":1259946165,"wof:lang_x_official":["est"],"wof:lang_x_spoken":["est"],"wof:lastmodified":1596660935,"wof:name":"Savastvere","wof:parent_id":1713309601,"wof:placetype":"locality","wof:repo":"whosonfirst-data-admin-ee","wof:superseded_by":[],"wof:supersedes":[],"wof:tags":[]},"bbox":[27.06694,58.60917,27.06694,58.60917],"geometry":{"coordinates":[27.06694,58.60917],"type":"Point"}}