{"id":1293204535,"type":"Feature","properties":{"edtf:cessation":"uuuu","edtf:inception":"uuuu","geom:area":0,"geom:area_square_m":0,"geom:bbox":"24.37908,59.4482,24.37908,59.4482","geom:latitude":59.4482,"geom:longitude":24.37908,"gn:admin1_code":"1.0","gn:admin2_code":"198.0","gn:admin3_code":"7870.0","gn:asciiname":"Orava","gn:country_code":"EE","gn:dem":36,"gn:feature_class":"P","gn:feature_code":"PPL","gn:geonameid":589808,"gn:latitude":59.4482,"gn:longitude":24.37908,"gn:modification_date":"2018-05-02","gn:name":"Orava","gn:population":0,"gn:timezone":"Europe/Tallinn","iso:country":"EE","lbl:bbox":"24.35908,59.4282,24.39908,59.4682","lbl:max_zoom":18,"lbl:min_zoom":13.5,"mz:hierarchy_label":1,"mz:is_current":1,"mz:min_zoom":12,"name:ceb_x_preferred":["Orava"],"name:ces_x_preferred":["Orava"],"name:deu_x_preferred":["Orava"],"name:epo_x_preferred":["Oravo"],"name:est_x_preferred":["Orava"],"name:fin_x_preferred":["Orava"],"name:fra_x_preferred":["Orava"],"name:nld_x_preferred":["Orava"],"name:pol_x_preferred":["Orawa"],"name:ron_x_preferred":["Orava"],"name:slk_x_preferred":["Orava"],"name:spa_x_preferred":["Orava"],"name:swe_x_preferred":["Orava"],"src:geom":"geonames","wof:belongsto":[85683055,102191581,1713312491,85633135,1713305681],"wof:breaches":[],"wof:concordances":{"gn:id":589808},"wof:country":"EE","wof:geomhash":"17c774f5a1a9293df86c5d9a40684b3e","wof:hierarchy":[{"continent_id":102191581,"country_id":85633135,"county_id":1713305681,"localadmin_id":1713312491,"locality_id":1293204535,"region_id":85683055}],"wof:id":1293204535,"wof:lang_x_official":["est"],"wof:lang_x_spoken":["est"],"wof:lastmodified":1596661456,"wof:name":"Orava","wof:parent_id":1713312491,"wof:placetype":"locality","wof:repo":"whosonfirst-data-admin-ee","wof:superseded_by":[],"wof:supersedes":[],"wof:tags":[]},"bbox":[24.37908,59.4482,24.37908,59.4482],"geometry":{"coordinates":[24.37908,59.4482],"type":"Point"}}