{"id":1293088193,"type":"Feature","properties":{"edtf:cessation":"uuuu","edtf:inception":"uuuu","geom:area":0,"geom:area_square_m":0,"geom:bbox":"27.01222,57.98611,27.01222,57.98611","geom:latitude":57.98611,"geom:longitude":27.01222,"gn:admin1_code":"12.0","gn:admin2_code":"622.0","gn:admin3_code":"6347.0","gn:asciiname":"Vedo","gn:country_code":"EE","gn:dem":86,"gn:feature_class":"P","gn:feature_code":"PPL","gn:geonameid":8619793,"gn:latitude":57.98611,"gn:longitude":27.01222,"gn:modification_date":"2017-11-25","gn:name":"Vedo","gn:population":0,"gn:timezone":"Europe/Tallinn","iso:country":"EE","lbl:bbox":"26.99222,57.96611,27.03222,58.00611","lbl:max_zoom":18,"lbl:min_zoom":13.5,"mz:hierarchy_label":1,"mz:is_current":1,"mz:min_zoom":12,"name:und_x_variant":["Vedu"],"src:geom":"geonames","wof:belongsto":[85682955,102191581,1713310879,85633135,1713305791],"wof:breaches":[],"wof:concordances":{"gn:id":8619793},"wof:country":"EE","wof:geomhash":"a04c4176c4ea3e7c7bcbf08cb1a349fc","wof:hierarchy":[{"continent_id":102191581,"country_id":85633135,"county_id":1713305791,"localadmin_id":1713310879,"locality_id":1293088193,"region_id":85682955}],"wof:id":1293088193,"wof:lang_x_official":["est"],"wof:lang_x_spoken":["est"],"wof:lastmodified":1596676966,"wof:name":"Vedo","wof:parent_id":1713310879,"wof:placetype":"locality","wof:repo":"whosonfirst-data-admin-ee","wof:superseded_by":[],"wof:supersedes":[],"wof:tags":[]},"bbox":[27.01222,57.98611,27.01222,57.98611],"geometry":{"coordinates":[27.01222,57.98611],"type":"Point"}}