{"id":1276754761,"type":"Feature","properties":{"edtf:cessation":"uuuu","edtf:inception":"uuuu","geom:area":0,"geom:area_square_m":0,"geom:bbox":"26.08222,59.38361,26.08222,59.38361","geom:latitude":59.38361,"geom:longitude":26.08222,"gn:admin1_code":"8.0","gn:admin2_code":"272.0","gn:admin3_code":"1924.0","gn:asciiname":"Hobeda","gn:country_code":"EE","gn:dem":101,"gn:feature_class":"P","gn:feature_code":"PPL","gn:geonameid":592110,"gn:latitude":59.38361,"gn:longitude":26.08222,"gn:modification_date":"2017-11-25","gn:name":"Hõbeda","gn:population":0,"gn:timezone":"Europe/Tallinn","iso:country":"EE","lbl:bbox":"26.06222,59.36361,26.10222,59.40361","lbl:max_zoom":18,"lbl:min_zoom":13.5,"mz:hierarchy_label":1,"mz:is_current":1,"mz:min_zoom":12,"name:deu_x_preferred":["Hõbeda"],"name:est_x_preferred":["Hõbeda"],"name:hye_x_preferred":["Հիբեդա"],"name:pol_x_preferred":["Hõbeda"],"name:vol_x_preferred":["Hõbeda"],"src:geom":"geonames","wof:belongsto":[85683049,102191581,1713306103,85633135,1713305723],"wof:breaches":[],"wof:concordances":{"gn:id":592110,"wk:page":"H%C3%B5beda%2C_L%C3%A4%C3%A4ne-Viru_County"},"wof:coterminous":[1713306103],"wof:country":"EE","wof:geomhash":"0c9cdeea27170ee75db2c1d5e48774ea","wof:hierarchy":[{"continent_id":102191581,"country_id":85633135,"county_id":1713305723,"localadmin_id":1713306103,"locality_id":1276754761,"region_id":85683049}],"wof:id":1276754761,"wof:lang_x_official":["est"],"wof:lang_x_spoken":["est"],"wof:lastmodified":1596661736,"wof:name":"Hobeda","wof:parent_id":1713306103,"wof:placetype":"locality","wof:repo":"whosonfirst-data-admin-ee","wof:superseded_by":[],"wof:supersedes":[],"wof:tags":[]},"bbox":[26.08222,59.38361,26.08222,59.38361],"geometry":{"coordinates":[26.08222,59.38361],"type":"Point"}}