{"id":1209724431,"type":"Feature","properties":{"edtf:cessation":"uuuu","edtf:inception":"uuuu","geom:area":0,"geom:area_square_m":0,"geom:bbox":"22.21025,58.92133,22.21025,58.92133","geom:latitude":58.92133,"geom:longitude":22.21025,"gn:admin1_code":"2.0","gn:admin2_code":"205.0","gn:admin3_code":"5224.0","gn:asciiname":"Maegipe","gn:country_code":"EE","gn:dem":53,"gn:feature_class":"P","gn:feature_code":"PPL","gn:geonameid":590386,"gn:latitude":58.92133,"gn:longitude":22.21025,"gn:modification_date":"2017-11-25","gn:name":"Mägipe","gn:population":0,"gn:timezone":"Europe/Tallinn","iso:country":"EE","lbl:bbox":"22.19025,58.90133,22.23025,58.94133","lbl:max_zoom":18,"lbl:min_zoom":13.5,"mz:hierarchy_label":1,"mz:is_current":1,"mz:min_zoom":12,"name:deu_x_preferred":["Mägipe"],"name:est_x_preferred":["Mägipe"],"name:hye_x_preferred":["Մեգիպե"],"name:nld_x_preferred":["Mägipe"],"name:pol_x_preferred":["Mägipe"],"name:spa_x_preferred":["Mägipe"],"name:und_x_variant":["Myagipya","Mägipää"],"name:vol_x_preferred":["Mägipe"],"src:geom":"geonames","wof:belongsto":[85682989,102191581,1713310147,85633135,1713305629],"wof:breaches":[],"wof:concordances":{"gn:id":590386,"wk:page":"M%C3%A4gipe"},"wof:coterminous":[1713310147],"wof:country":"EE","wof:geomhash":"940d27c4283fec7e014b0800c6a595d4","wof:hierarchy":[{"continent_id":102191581,"country_id":85633135,"county_id":1713305629,"localadmin_id":1713310147,"locality_id":1209724431,"region_id":85682989}],"wof:id":1209724431,"wof:lang_x_official":["est"],"wof:lang_x_spoken":["est"],"wof:lastmodified":1596670012,"wof:name":"Maegipe","wof:parent_id":1713310147,"wof:placetype":"locality","wof:repo":"whosonfirst-data-admin-ee","wof:superseded_by":[],"wof:supersedes":[],"wof:tags":[]},"bbox":[22.21025,58.92133,22.21025,58.92133],"geometry":{"coordinates":[22.21025,58.92133],"type":"Point"}}