{"id":1209774635,"type":"Feature","properties":{"edtf:cessation":"uuuu","edtf:inception":"uuuu","geom:area":0,"geom:area_square_m":0,"geom:bbox":"27.015,57.72222,27.015,57.72222","geom:latitude":57.72222,"geom:longitude":27.015,"gn:admin1_code":"21.0","gn:admin2_code":"698.0","gn:admin3_code":"3664.0","gn:asciiname":"Kurgjaerve","gn:country_code":"EE","gn:dem":242,"gn:feature_class":"P","gn:feature_code":"PPL","gn:geonameid":8620258,"gn:latitude":57.72222,"gn:longitude":27.015,"gn:modification_date":"2017-11-25","gn:name":"Kurgjärve","gn:population":0,"gn:timezone":"Europe/Tallinn","iso:country":"EE","lbl:bbox":"26.995,57.70222,27.035,57.74222","lbl:max_zoom":18,"lbl:min_zoom":13.5,"mz:hierarchy_label":1,"mz:is_current":1,"mz:min_zoom":12,"name:und_x_variant":["Kurgjärve","Кургъярве"],"src:geom":"geonames","wof:belongsto":[85682937,102191581,1713315311,85633135,1713305787],"wof:breaches":[],"wof:concordances":{"gn:id":8620258},"wof:coterminous":[1713315311],"wof:country":"EE","wof:geomhash":"5df651c4c9f7e97a06c715f94ce87b6f","wof:hierarchy":[{"continent_id":102191581,"country_id":85633135,"county_id":1713305787,"localadmin_id":1713315311,"locality_id":1209774635,"region_id":85682937}],"wof:id":1209774635,"wof:lang_x_official":["est"],"wof:lang_x_spoken":["est"],"wof:lastmodified":1596676881,"wof:name":"Kurgjaerve","wof:parent_id":1713315311,"wof:placetype":"locality","wof:repo":"whosonfirst-data-admin-ee","wof:superseded_by":[],"wof:supersedes":[],"wof:tags":[]},"bbox":[27.015,57.72222,27.015,57.72222],"geometry":{"coordinates":[27.015,57.72222],"type":"Point"}}