{"id":1310503497,"type":"Feature","properties":{"edtf:cessation":"uuuu","edtf:inception":"uuuu","geom:area":0,"geom:area_square_m":0,"geom:bbox":"27.26139,59.34806,27.26139,59.34806","geom:latitude":59.34806,"geom:longitude":27.26139,"gn:admin1_code":"3.0","gn:admin2_code":"803.0","gn:admin3_code":"7551.0","gn:asciiname":"Servaaeaere","gn:country_code":"EE","gn:dem":64,"gn:feature_class":"P","gn:feature_code":"PPL","gn:geonameid":8619827,"gn:latitude":59.34806,"gn:longitude":27.26139,"gn:modification_date":"2017-11-25","gn:name":"Servaääre","gn:population":0,"gn:timezone":"Europe/Tallinn","iso:country":"EE","lbl:bbox":"27.24139,59.32806,27.28139,59.36806","lbl:max_zoom":18,"lbl:min_zoom":13.5,"mz:hierarchy_label":1,"mz:is_current":1,"mz:min_zoom":12,"name:deu_x_preferred":["Servaääre"],"name:est_x_preferred":["Servaääre"],"name:hye_x_preferred":["Սեռվաեեռե"],"name:nld_x_preferred":["Servaääre"],"name:pol_x_preferred":["Servaääre"],"name:spa_x_preferred":["Servaääre"],"name:vol_x_preferred":["Servaääre"],"src:geom":"geonames","wof:belongsto":[85683059,102191581,1713313463,85633135,1713305783],"wof:breaches":[],"wof:concordances":{"gn:id":8619827,"wk:page":"Serva%C3%A4%C3%A4re"},"wof:coterminous":[1713313463],"wof:country":"EE","wof:geomhash":"2d31fae9aa21426ef5a45d690331b2f6","wof:hierarchy":[{"continent_id":102191581,"country_id":85633135,"county_id":1713305783,"localadmin_id":1713313463,"locality_id":1310503497,"region_id":85683059}],"wof:id":1310503497,"wof:lang_x_official":["est"],"wof:lang_x_spoken":["est"],"wof:lastmodified":1596676910,"wof:name":"Servaaeaere","wof:parent_id":1713313463,"wof:placetype":"locality","wof:repo":"whosonfirst-data-admin-ee","wof:superseded_by":[],"wof:supersedes":[],"wof:tags":[]},"bbox":[27.26139,59.34806,27.26139,59.34806],"geometry":{"coordinates":[27.26139,59.34806],"type":"Point"}}