{"id":1193049671,"type":"Feature","properties":{"edtf:cessation":"uuuu","edtf:inception":"uuuu","geom:area":0,"geom:area_square_m":0,"geom:bbox":"26.95083,58.62889,26.95083,58.62889","geom:latitude":58.62889,"geom:longitude":26.95083,"gn:admin1_code":"18.0","gn:admin2_code":"586.0","gn:admin3_code":"9150.0","gn:asciiname":"Kogri","gn:country_code":"EE","gn:dem":84,"gn:feature_class":"P","gn:feature_code":"PPL","gn:geonameid":8618409,"gn:latitude":58.62889,"gn:longitude":26.95083,"gn:modification_date":"2017-11-25","gn:name":"Kogri","gn:population":0,"gn:timezone":"Europe/Tallinn","iso:country":"EE","lbl:bbox":"26.93083,58.60889,26.97083,58.64889","lbl:max_zoom":18,"lbl:min_zoom":13.5,"mz:hierarchy_label":1,"mz:is_current":1,"mz:min_zoom":12,"name:deu_x_preferred":["Kogri"],"name:est_x_preferred":["Kogri"],"name:hye_x_preferred":["Կոգռի"],"name:pol_x_preferred":["Kogri"],"name:spa_x_preferred":["Kogri"],"name:und_x_variant":["Konsa"],"name:vol_x_preferred":["Kogri"],"src:geom":"geonames","wof:belongsto":[85682995,102191581,1713309707,85633135,1713305679],"wof:breaches":[],"wof:concordances":{"gn:id":8618409},"wof:country":"EE","wof:geomhash":"940dc2a27fffe8c0608c79f7d84f8573","wof:hierarchy":[{"continent_id":102191581,"country_id":85633135,"county_id":1713305679,"localadmin_id":1713309707,"locality_id":1193049671,"region_id":85682995}],"wof:id":1193049671,"wof:lang_x_official":["est"],"wof:lang_x_spoken":["est"],"wof:lastmodified":1596660901,"wof:name":"Kogri","wof:parent_id":1713309707,"wof:placetype":"locality","wof:repo":"whosonfirst-data-admin-ee","wof:superseded_by":[],"wof:supersedes":[],"wof:tags":[]},"bbox":[26.95083,58.62889,26.95083,58.62889],"geometry":{"coordinates":[26.95083,58.62889],"type":"Point"}}