{"id":1326904417,"type":"Feature","properties":{"edtf:cessation":"uuuu","edtf:inception":"uuuu","geom:area":0,"geom:area_square_m":0,"geom:bbox":"27.11361,57.89333,27.11361,57.89333","geom:latitude":57.89333,"geom:longitude":27.11361,"gn:admin1_code":"21.0","gn:admin2_code":"917.0","gn:admin3_code":"3944.0","gn:asciiname":"Punsaku","gn:country_code":"EE","gn:dem":79,"gn:feature_class":"P","gn:feature_code":"PPL","gn:geonameid":8620235,"gn:latitude":57.89333,"gn:longitude":27.11361,"gn:modification_date":"2017-11-25","gn:name":"Punsaku","gn:population":0,"gn:timezone":"Europe/Tallinn","iso:country":"EE","lbl:bbox":"27.09361,57.87333,27.13361,57.91333","lbl:max_zoom":18,"lbl:min_zoom":13.5,"mz:hierarchy_label":1,"mz:is_current":1,"mz:min_zoom":12,"name:und_x_variant":["Pundsaku"],"src:geom":"geonames","wof:belongsto":[85682937,102191581,1713315581,85633135,1713305633],"wof:breaches":[],"wof:concordances":{"gn:id":8620235},"wof:country":"EE","wof:geomhash":"4445952d90ea68e7af73fa07199ea40c","wof:hierarchy":[{"continent_id":102191581,"country_id":85633135,"county_id":1713305633,"localadmin_id":1713315581,"locality_id":1326904417,"region_id":85682937}],"wof:id":1326904417,"wof:lang_x_official":["est"],"wof:lang_x_spoken":["est"],"wof:lastmodified":1596660418,"wof:name":"Punsaku","wof:parent_id":1713315581,"wof:placetype":"locality","wof:repo":"whosonfirst-data-admin-ee","wof:superseded_by":[],"wof:supersedes":[],"wof:tags":[]},"bbox":[27.11361,57.89333,27.11361,57.89333],"geometry":{"coordinates":[27.11361,57.89333],"type":"Point"}}