{"id":1242669287,"type":"Feature","properties":{"edtf:cessation":"uuuu","edtf:inception":"uuuu","geom:area":0,"geom:area_square_m":0,"geom:bbox":"23.81111,58.56611,23.81111,58.56611","geom:latitude":58.56611,"geom:longitude":23.81111,"gn:admin1_code":"11.0","gn:admin2_code":"430.0","gn:admin3_code":"3159.0","gn:asciiname":"Torgu","gn:country_code":"EE","gn:dem":23,"gn:feature_class":"P","gn:feature_code":"PPL","gn:geonameid":588216,"gn:latitude":58.56611,"gn:longitude":23.81111,"gn:modification_date":"2017-11-25","gn:name":"Torgu","gn:population":0,"gn:timezone":"Europe/Tallinn","iso:country":"EE","lbl:bbox":"23.79111,58.54611,23.83111,58.58611","lbl:max_zoom":18,"lbl:min_zoom":13.5,"mz:hierarchy_label":1,"mz:is_current":1,"mz:min_zoom":12,"src:geom":"geonames","wof:belongsto":[85683001,102191581,1713309577,85633135,1713305721],"wof:breaches":[],"wof:concordances":{"gn:id":588216},"wof:country":"EE","wof:geomhash":"80d4572185641a7c33f06d20be05a6fe","wof:hierarchy":[{"continent_id":102191581,"country_id":85633135,"county_id":1713305721,"localadmin_id":1713309577,"locality_id":1242669287,"region_id":85683001}],"wof:id":1242669287,"wof:lang_x_official":["est"],"wof:lang_x_spoken":["est"],"wof:lastmodified":1596661679,"wof:name":"Torgu","wof:parent_id":1713309577,"wof:placetype":"locality","wof:repo":"whosonfirst-data-admin-ee","wof:superseded_by":[],"wof:supersedes":[],"wof:tags":[]},"bbox":[23.81111,58.56611,23.81111,58.56611],"geometry":{"coordinates":[23.81111,58.56611],"type":"Point"}}