{"id":1125935967,"type":"Feature","properties":{"edtf:cessation":"uuuu","edtf:inception":"uuuu","geom:area":0,"geom:area_square_m":0,"geom:bbox":"25.93111,59.12778,25.93111,59.12778","geom:latitude":59.12778,"geom:longitude":25.93111,"gn:country":"EE","gn:fcode":"PPL","gn:population":126,"iso:country":"EE","lbl:bbox":"25.91111,59.10778,25.95111,59.14778","lbl:latitude":59.12778,"lbl:longitude":25.93111,"lbl:max_zoom":18,"lbl:min_zoom":13,"mz:hierarchy_label":1,"mz:is_current":1,"mz:min_zoom":11,"mz:note":"Quattroshapes Point Gazetteer import 20170519","name:bul_x_preferred":["Росна"],"name:ceb_x_preferred":["Roosna"],"name:eng_x_preferred":["Roosna"],"name:est_x_preferred":["Roosna"],"name:fra_x_preferred":["Roosna"],"name:hye_x_preferred":["Ռոոսնա"],"name:nld_x_preferred":["Roosna"],"name:pol_x_preferred":["Roosna"],"name:spa_x_preferred":["Roosna"],"name:swe_x_preferred":["Roosna"],"name:ukr_x_preferred":["Роосна"],"name:vol_x_preferred":["Roosna"],"qs_pg:aaroncc":"EE","qs_pg:gn_country":"EE","qs_pg:gn_fcode":"PPL","qs_pg:gn_id":588964,"qs_pg:gn_pop":126,"qs_pg:name":"Roosna","qs_pg:name_adm0":"Eesti","qs_pg:name_adm1":"Järvamaa","qs_pg:photos_9r":0,"qs_pg:photos_sr":0,"qs_pg:pop_sr":1,"qs_pg:qs_id":1274449,"qs_pg:qs_pg_placetype":"locality","qs_pg:qs_pg_placetype_gp":"Town","qs_pg:woe_adm0":23424805,"qs_pg:woe_id":845228,"src:geom":"qs_pg","src:lbl_centroid":"qs_pg","src:population":"geonames","woe:adm0_id":23424805,"woe:name_adm0":"Eesti","woe:name_adm1":"Järvamaa","woe:placetype":"Town","wof:belongsto":[85683031,102191581,1713306841,85633135,1713305765],"wof:breaches":[],"wof:concordances":{"gn:id":588964,"gp:id":845228,"qs_pg:id":1274449,"wd:id":"Q3086324"},"wof:coterminous":[1713306841],"wof:country":"EE","wof:created":1497296969,"wof:geomhash":"46e28446915a18068cc58f1d172b667c","wof:hierarchy":[{"continent_id":102191581,"country_id":85633135,"county_id":1713305765,"localadmin_id":1713306841,"locality_id":1125935967,"region_id":85683031}],"wof:id":1125935967,"wof:lang_x_official":["est"],"wof:lang_x_spoken":["est"],"wof:lastmodified":1596676652,"wof:name":"Roosna","wof:parent_id":1713306841,"wof:placetype":"locality","wof:population":126,"wof:population_rank":1,"wof:repo":"whosonfirst-data-admin-ee","wof:superseded_by":[],"wof:supersedes":[],"wof:tags":[]},"bbox":[25.93111,59.12778,25.93111,59.12778],"geometry":{"coordinates":[25.93111,59.12778],"type":"Point"}}