{"id":1243369815,"type":"Feature","properties":{"edtf:cessation":"uuuu","edtf:inception":"uuuu","geom:area":0,"geom:area_square_m":0,"geom:bbox":"25.68944,58.67611,25.68944,58.67611","geom:latitude":58.67611,"geom:longitude":25.68944,"gn:admin1_code":"4.0","gn:admin2_code":"834.0","gn:admin3_code":"3684.0","gn:asciiname":"Kurla","gn:country_code":"EE","gn:dem":62,"gn:feature_class":"P","gn:feature_code":"PPL","gn:geonameid":590919,"gn:latitude":58.67611,"gn:longitude":25.68944,"gn:modification_date":"2017-11-25","gn:name":"Kurla","gn:population":0,"gn:timezone":"Europe/Tallinn","iso:country":"EE","lbl:bbox":"25.66944,58.65611,25.70944,58.69611","lbl:max_zoom":18,"lbl:min_zoom":13.5,"mz:hierarchy_label":1,"mz:is_current":1,"mz:min_zoom":12,"name:est_x_preferred":["Kurla"],"name:fra_x_preferred":["Kurla"],"name:hye_x_preferred":["Կուռլա"],"name:pol_x_preferred":["Kurla"],"name:spa_x_preferred":["Kurla"],"name:ukr_x_preferred":["Курла"],"name:vol_x_preferred":["Kurla"],"src:geom":"geonames","wof:belongsto":[85683031,102191581,1713306595,85633135,1713305773],"wof:breaches":[],"wof:concordances":{"gn:id":590919,"wk:page":"Kurla%2C_Estonia"},"wof:coterminous":[1713306595],"wof:country":"EE","wof:geomhash":"8bf4d80ce23b9b5c332d63213d81fd65","wof:hierarchy":[{"continent_id":102191581,"country_id":85633135,"county_id":1713305773,"localadmin_id":1713306595,"locality_id":1243369815,"region_id":85683031}],"wof:id":1243369815,"wof:lang_x_official":["est"],"wof:lang_x_spoken":["est"],"wof:lastmodified":1596677995,"wof:name":"Kurla","wof:parent_id":1713306595,"wof:placetype":"locality","wof:repo":"whosonfirst-data-admin-ee","wof:superseded_by":[],"wof:supersedes":[],"wof:tags":[]},"bbox":[25.68944,58.67611,25.68944,58.67611],"geometry":{"coordinates":[25.68944,58.67611],"type":"Point"}}