{"id":1243534573,"type":"Feature","properties":{"edtf:cessation":"uuuu","edtf:inception":"uuuu","geom:area":0,"geom:area_square_m":0,"geom:bbox":"26.75667,58.08194,26.75667,58.08194","geom:latitude":58.08194,"geom:longitude":26.75667,"gn:admin1_code":"12.0","gn:admin2_code":"284.0","gn:admin3_code":"5959.0","gn:asciiname":"Palutaja","gn:country_code":"EE","gn:dem":142,"gn:feature_class":"P","gn:feature_code":"PPL","gn:geonameid":794178,"gn:latitude":58.08194,"gn:longitude":26.75667,"gn:modification_date":"2017-11-25","gn:name":"Palutaja","gn:population":0,"gn:timezone":"Europe/Tallinn","iso:country":"EE","lbl:bbox":"26.73667,58.06194,26.77667,58.10194","lbl:max_zoom":18,"lbl:min_zoom":13.5,"mz:hierarchy_label":1,"mz:is_current":1,"mz:min_zoom":12,"name:deu_x_preferred":["Palutaja"],"name:est_x_preferred":["Palutaja"],"name:hye_x_preferred":["Պալուտայա"],"name:pol_x_preferred":["Palutaja"],"name:sco_x_preferred":["Palutaja"],"name:spa_x_preferred":["Palutaja"],"name:ukr_x_preferred":["Палутая"],"name:vol_x_preferred":["Palutaja"],"src:geom":"geonames","wof:belongsto":[85682955,102191581,1713309749,85633135,1713305789],"wof:breaches":[],"wof:concordances":{"gn:id":794178,"wk:page":"Palutaja"},"wof:coterminous":[1713309749],"wof:country":"EE","wof:geomhash":"cd08920a86c9bc9cfb3680b0df7230dc","wof:hierarchy":[{"continent_id":102191581,"country_id":85633135,"county_id":1713305789,"localadmin_id":1713309749,"locality_id":1243534573,"region_id":85682955}],"wof:id":1243534573,"wof:lang_x_official":["est"],"wof:lang_x_spoken":["est"],"wof:lastmodified":1596676796,"wof:name":"Palutaja","wof:parent_id":1713309749,"wof:placetype":"locality","wof:repo":"whosonfirst-data-admin-ee","wof:superseded_by":[],"wof:supersedes":[],"wof:tags":[]},"bbox":[26.75667,58.08194,26.75667,58.08194],"geometry":{"coordinates":[26.75667,58.08194],"type":"Point"}}