{"id":1293293201,"type":"Feature","properties":{"edtf:cessation":"uuuu","edtf:inception":"uuuu","geom:area":0,"geom:area_square_m":0,"geom:bbox":"25.74917,58.94194,25.74917,58.94194","geom:latitude":58.94194,"geom:longitude":25.74917,"gn:admin1_code":"4.0","gn:admin2_code":"255.0","gn:admin3_code":"9807.0","gn:asciiname":"Oytla","gn:country_code":"EE","gn:dem":75,"gn:feature_class":"P","gn:feature_code":"PPL","gn:geonameid":589815,"gn:latitude":58.94194,"gn:longitude":25.74917,"gn:modification_date":"2017-11-25","gn:name":"Oytla","gn:population":0,"gn:timezone":"Europe/Tallinn","iso:country":"EE","lbl:bbox":"25.72917,58.92194,25.76917,58.96194","lbl:max_zoom":18,"lbl:min_zoom":13.5,"mz:hierarchy_label":1,"mz:is_current":1,"mz:min_zoom":12,"name:est_x_preferred":["Öötla"],"name:hye_x_preferred":["Օոտլա"],"name:pol_x_preferred":["Öötla"],"name:spa_x_preferred":["Öötla"],"name:ukr_x_preferred":["Єетла"],"name:und_x_variant":["Öötla Asundus","Oytla"],"name:vol_x_preferred":["Öötla"],"src:geom":"geonames","wof:belongsto":[85683031,102191581,1713307037,85633135,1713305765],"wof:breaches":[],"wof:concordances":{"gn:id":589815,"wk:page":"%C3%96%C3%B6tla"},"wof:coterminous":[1713307037],"wof:country":"EE","wof:geomhash":"55efc1fa814b519620f54ba63f392c55","wof:hierarchy":[{"continent_id":102191581,"country_id":85633135,"county_id":1713305765,"localadmin_id":1713307037,"locality_id":1293293201,"region_id":85683031}],"wof:id":1293293201,"wof:lang_x_official":["est"],"wof:lang_x_spoken":["est"],"wof:lastmodified":1596676645,"wof:name":"Oytla","wof:parent_id":1713307037,"wof:placetype":"locality","wof:repo":"whosonfirst-data-admin-ee","wof:superseded_by":[],"wof:supersedes":[],"wof:tags":[]},"bbox":[25.74917,58.94194,25.74917,58.94194],"geometry":{"coordinates":[25.74917,58.94194],"type":"Point"}}