{"id":1225835695,"type":"Feature","properties":{"edtf:cessation":"uuuu","edtf:inception":"uuuu","geom:area":0,"geom:area_square_m":0,"geom:bbox":"26.65472,59.33083,26.65472,59.33083","geom:latitude":59.33083,"geom:longitude":26.65472,"gn:admin1_code":"8.0","gn:admin2_code":"901.0","gn:admin3_code":"8665.0","gn:asciiname":"Miila","gn:cc2":"EE","gn:country_code":"EE","gn:dem":82,"gn:feature_class":"P","gn:feature_code":"PPL","gn:geonameid":590206,"gn:latitude":59.33083,"gn:longitude":26.65472,"gn:modification_date":"2017-11-25","gn:name":"Miila","gn:population":0,"gn:timezone":"Europe/Tallinn","iso:country":"EE","lbl:bbox":"26.63472,59.31083,26.67472,59.35083","lbl:max_zoom":18,"lbl:min_zoom":13.5,"mz:hierarchy_label":1,"mz:is_current":1,"mz:min_zoom":12,"name:est_x_preferred":["Miila"],"name:hye_x_preferred":["Միիլա"],"name:pol_x_preferred":["Miila"],"name:und_x_variant":["Miyla"],"name:vol_x_preferred":["Miila"],"src:geom":"geonames","wof:belongsto":[85683049,102191581,1713307681,85633135,1713305771],"wof:breaches":[],"wof:concordances":{"gn:id":590206,"wk:page":"Miila"},"wof:coterminous":[1713307931],"wof:country":"EE","wof:geomhash":"69140478fe0b71c14c781c72fa9c6fe9","wof:hierarchy":[{"continent_id":102191581,"country_id":85633135,"county_id":1713305771,"localadmin_id":1713307681,"locality_id":1225835695,"region_id":85683049}],"wof:id":1225835695,"wof:lang_x_official":["est"],"wof:lang_x_spoken":["est"],"wof:lastmodified":1596677957,"wof:name":"Miila","wof:parent_id":1713307681,"wof:placetype":"locality","wof:repo":"whosonfirst-data-admin-ee","wof:superseded_by":[],"wof:supersedes":[],"wof:tags":[]},"bbox":[26.65472,59.33083,26.65472,59.33083],"geometry":{"coordinates":[26.65472,59.33083],"type":"Point"}}