{"id":1242949547,"type":"Feature","properties":{"edtf:cessation":"uuuu","edtf:inception":"uuuu","geom:area":0,"geom:area_square_m":0,"geom:bbox":"25.19889,58.78056,25.19889,58.78056","geom:latitude":58.78056,"geom:longitude":25.19889,"gn:admin1_code":"4.0","gn:admin2_code":"834.0","gn:admin3_code":"2228.0","gn:asciiname":"Lommelu","gn:country_code":"EE","gn:dem":64,"gn:feature_class":"P","gn:feature_code":"PPL","gn:geonameid":590542,"gn:latitude":58.78056,"gn:longitude":25.19889,"gn:modification_date":"2017-11-25","gn:name":"Lõmmelu","gn:population":0,"gn:timezone":"Europe/Tallinn","iso:country":"EE","lbl:bbox":"25.17889,58.76056,25.21889,58.80056","lbl:max_zoom":18,"lbl:min_zoom":13.5,"mz:hierarchy_label":1,"mz:is_current":1,"mz:min_zoom":12,"name:und_x_variant":["Lymmelu","Lõmmelu"],"src:geom":"geonames","wof:belongsto":[85683031,102191581,1713306485,85633135,1713305773],"wof:breaches":[],"wof:concordances":{"gn:id":590542},"wof:country":"EE","wof:geomhash":"1d2dc7eda7961af89e6536dcfba235fc","wof:hierarchy":[{"continent_id":102191581,"country_id":85633135,"county_id":1713305773,"localadmin_id":1713306485,"locality_id":1242949547,"region_id":85683031}],"wof:id":1242949547,"wof:lang_x_official":["est"],"wof:lang_x_spoken":["est"],"wof:lastmodified":1596677991,"wof:name":"Lommelu","wof:parent_id":1713306485,"wof:placetype":"locality","wof:repo":"whosonfirst-data-admin-ee","wof:superseded_by":[],"wof:supersedes":[],"wof:tags":[]},"bbox":[25.19889,58.78056,25.19889,58.78056],"geometry":{"coordinates":[25.19889,58.78056],"type":"Point"}}