{"id":1125936631,"type":"Feature","properties":{"edtf:cessation":"uuuu","edtf:inception":"uuuu","geom:area":0,"geom:area_square_m":0,"geom:bbox":"25.655,58.17611,25.655,58.17611","geom:latitude":58.17611,"geom:longitude":25.655,"gn:country":"EE","gn:fcode":"PPL","gn:population":133,"iso:country":"EE","lbl:bbox":"25.635,58.15611,25.675,58.19611","lbl:latitude":58.17611,"lbl:longitude":25.655,"lbl:max_zoom":18,"lbl:min_zoom":13,"mz:hierarchy_label":1,"mz:is_current":1,"mz:min_zoom":11,"mz:note":"Quattroshapes Point Gazetteer import 20170519","name:bul_x_preferred":["Тухалане"],"name:ceb_x_preferred":["Tuhalaane"],"name:deu_x_preferred":["Tuhalaane"],"name:eng_x_preferred":["Tuhalaane"],"name:est_x_preferred":["Tuhalaane"],"name:hye_x_preferred":["Տուհալաանե"],"name:nld_x_preferred":["Tuhalaane"],"name:pol_x_preferred":["Tuhalaane"],"name:rus_x_preferred":["Тухалаане"],"name:spa_x_preferred":["Tuhalaane"],"name:swe_x_preferred":["Tuhalaane"],"name:ukr_x_preferred":["Тугалаане"],"name:und_x_variant":["Willust"],"name:vol_x_preferred":["Tuhalaane"],"qs_pg:aaroncc":"EE","qs_pg:gn_country":"EE","qs_pg:gn_fcode":"PPL","qs_pg:gn_id":588171,"qs_pg:gn_pop":133,"qs_pg:name":"Tuhalaane","qs_pg:name_adm0":"Eesti","qs_pg:name_adm1":"Viljandimaa","qs_pg:photos_9r":0,"qs_pg:photos_sr":0,"qs_pg:pop_sr":1,"qs_pg:qs_id":1274633,"qs_pg:qs_pg_placetype":"locality","qs_pg:qs_pg_placetype_gp":"Town","qs_pg:woe_adm0":23424805,"qs_pg:woe_id":845970,"src:geom":"qs_pg","src:lbl_centroid":"qs_pg","src:population":"geonames","woe:adm0_id":23424805,"woe:name_adm0":"Eesti","woe:name_adm1":"Viljandimaa","woe:placetype":"Town","wof:belongsto":[85682985,102191581,1713313477,85633135,1713305661],"wof:breaches":[],"wof:concordances":{"gn:id":588171,"gp:id":845970,"qs_pg:id":1274633,"wd:id":"Q7851688"},"wof:coterminous":[1713313477],"wof:country":"EE","wof:created":1497296987,"wof:geomhash":"4bc446d935086bc373d199cb96d1414d","wof:hierarchy":[{"continent_id":102191581,"country_id":85633135,"county_id":1713305661,"localadmin_id":1713313477,"locality_id":1125936631,"region_id":85682985}],"wof:id":1125936631,"wof:lang_x_official":["est"],"wof:lang_x_spoken":["est"],"wof:lastmodified":1596661310,"wof:name":"Tuhalaane","wof:parent_id":1713313477,"wof:placetype":"locality","wof:population":133,"wof:population_rank":1,"wof:repo":"whosonfirst-data-admin-ee","wof:superseded_by":[],"wof:supersedes":[],"wof:tags":[]},"bbox":[25.655,58.17611,25.655,58.17611],"geometry":{"coordinates":[25.655,58.17611],"type":"Point"}}