{"id":1125890463,"type":"Feature","properties":{"edtf:cessation":"uuuu","edtf:inception":"uuuu","geom:area":0,"geom:area_square_m":0,"geom:bbox":"25.815,58.26167,25.815,58.26167","geom:latitude":58.26167,"geom:longitude":25.815,"gn:country":"EE","gn:fcode":"PPL","gn:population":113,"iso:country":"EE","lbl:bbox":"25.795,58.24167,25.835,58.28167","lbl:latitude":58.26167,"lbl:longitude":25.815,"lbl:max_zoom":18,"lbl:min_zoom":13,"mz:hierarchy_label":1,"mz:is_current":1,"mz:min_zoom":11,"mz:note":"Quattroshapes Point Gazetteer import 20170519","name:ceb_x_preferred":["Ülensi"],"name:eng_x_preferred":["Ülensi"],"name:est_x_preferred":["Ülensi"],"name:hye_x_preferred":["Յուլենսի"],"name:nld_x_preferred":["Ülensi"],"name:pol_x_preferred":["Ülensi"],"name:spa_x_preferred":["Ülensi"],"name:swe_x_preferred":["Ülensi"],"name:ukr_x_preferred":["Юленсі"],"name:und_x_variant":["Shenze"],"name:vol_x_preferred":["Ülensi"],"qs_pg:aaroncc":"EE","qs_pg:gn_country":"EE","qs_pg:gn_fcode":"PPL","qs_pg:gn_id":588093,"qs_pg:gn_pop":113,"qs_pg:name":"Ülensi","qs_pg:name_adm0":"Eesti","qs_pg:name_adm1":"Viljandimaa","qs_pg:photos_9k":1,"qs_pg:photos_9r":1,"qs_pg:photos_all":3,"qs_pg:photos_sr":0,"qs_pg:pop_sr":1,"qs_pg:qs_id":915997,"qs_pg:qs_pg_placetype":"locality","qs_pg:qs_pg_placetype_gp":"Town","qs_pg:woe_adm0":23424805,"qs_pg:woe_id":846043,"src:geom":"qs_pg","src:lbl_centroid":"qs_pg","src:population":"geonames","woe:adm0_id":23424805,"woe:name_adm0":"Eesti","woe:name_adm1":"Viljandimaa","woe:placetype":"Town","wof:belongsto":[85682985,102191581,1713310077,85633135,1713305669],"wof:breaches":[],"wof:concordances":{"gn:id":588093,"gp:id":846043,"qs_pg:id":915997,"wd:id":"Q10955330"},"wof:coterminous":[1713310077],"wof:country":"EE","wof:created":1497295292,"wof:geomhash":"32b3a7debe482de1d6517436425e024c","wof:hierarchy":[{"continent_id":102191581,"country_id":85633135,"county_id":1713305669,"localadmin_id":1713310077,"locality_id":1125890463,"region_id":85682985}],"wof:id":1125890463,"wof:lang_x_official":["est"],"wof:lang_x_spoken":["est"],"wof:lastmodified":1596661258,"wof:name":"Ülensi","wof:parent_id":1713310077,"wof:placetype":"locality","wof:population":113,"wof:population_rank":1,"wof:repo":"whosonfirst-data-admin-ee","wof:superseded_by":[],"wof:supersedes":[],"wof:tags":[]},"bbox":[25.815,58.26167,25.815,58.26167],"geometry":{"coordinates":[25.815,58.26167],"type":"Point"}}