{"id":1292979227,"type":"Feature","properties":{"edtf:cessation":"uuuu","edtf:inception":"uuuu","geom:area":0,"geom:area_square_m":0,"geom:bbox":"24.71833,58.07417,24.71833,58.07417","geom:latitude":58.07417,"geom:longitude":24.71833,"gn:admin1_code":"11.0","gn:admin2_code":"712.0","gn:admin3_code":"6143.0","gn:asciiname":"Pihke","gn:cc2":"EE","gn:country_code":"EE","gn:dem":51,"gn:feature_class":"P","gn:feature_code":"PPL","gn:geonameid":589498,"gn:latitude":58.07417,"gn:longitude":24.71833,"gn:modification_date":"2017-11-25","gn:name":"Pihke","gn:population":0,"gn:timezone":"Europe/Tallinn","iso:country":"EE","lbl:bbox":"24.69833,58.05417,24.73833,58.09417","lbl:max_zoom":18,"lbl:min_zoom":13.5,"mz:hierarchy_label":1,"mz:is_current":1,"mz:min_zoom":12,"name:est_x_preferred":["Pihke"],"name:fra_x_preferred":["Pihke"],"name:hye_x_preferred":["Պիհկե"],"name:spa_x_preferred":["Pihke"],"name:und_x_variant":["Pikhke"],"name:vol_x_preferred":["Pihke"],"src:geom":"geonames","wof:belongsto":[85682981,102191581,1713314031,85633135,1713305705],"wof:breaches":[],"wof:concordances":{"gn:id":589498,"wk:page":"Pihke"},"wof:coterminous":[1713314031],"wof:country":"EE","wof:geomhash":"30abbc336b3c16f5a6e4be61c7959401","wof:hierarchy":[{"continent_id":102191581,"country_id":85633135,"county_id":1713305705,"localadmin_id":1713314031,"locality_id":1292979227,"region_id":85682981}],"wof:id":1292979227,"wof:lang_x_official":["est"],"wof:lang_x_spoken":["est"],"wof:lastmodified":1596677732,"wof:name":"Pihke","wof:parent_id":1713314031,"wof:placetype":"locality","wof:repo":"whosonfirst-data-admin-ee","wof:superseded_by":[],"wof:supersedes":[],"wof:tags":[]},"bbox":[24.71833,58.07417,24.71833,58.07417],"geometry":{"coordinates":[24.71833,58.07417],"type":"Point"}}