{"id":1260144745,"type":"Feature","properties":{"edtf:cessation":"uuuu","edtf:inception":"uuuu","geom:area":0,"geom:area_square_m":0,"geom:bbox":"27.09417,57.61917,27.09417,57.61917","geom:latitude":57.61917,"geom:longitude":27.09417,"gn:admin1_code":"21.0","gn:admin2_code":"698.0","gn:admin3_code":"4372.0","gn:asciiname":"Lillimoisa","gn:country_code":"EE","gn:dem":225,"gn:feature_class":"P","gn:feature_code":"PPL","gn:geonameid":8619273,"gn:latitude":57.61917,"gn:longitude":27.09417,"gn:modification_date":"2017-11-25","gn:name":"Lillimõisa","gn:population":0,"gn:timezone":"Europe/Tallinn","iso:country":"EE","lbl:bbox":"27.07417,57.59917,27.11417,57.63917","lbl:max_zoom":18,"lbl:min_zoom":13.5,"mz:hierarchy_label":1,"mz:is_current":1,"mz:min_zoom":12,"name:und_x_variant":["Lillimõisa","Lilli"],"src:geom":"geonames","wof:belongsto":[85682937,102191581,1713315619,85633135,1713305787],"wof:breaches":[],"wof:concordances":{"gn:id":8619273},"wof:coterminous":[1713315619],"wof:country":"EE","wof:geomhash":"3473c6872ed8938965712fa5ffc6bd36","wof:hierarchy":[{"continent_id":102191581,"country_id":85633135,"county_id":1713305787,"localadmin_id":1713315619,"locality_id":1260144745,"region_id":85682937}],"wof:id":1260144745,"wof:lang_x_official":["est"],"wof:lang_x_spoken":["est"],"wof:lastmodified":1596676868,"wof:name":"Lillimoisa","wof:parent_id":1713315619,"wof:placetype":"locality","wof:repo":"whosonfirst-data-admin-ee","wof:superseded_by":[],"wof:supersedes":[],"wof:tags":[]},"bbox":[27.09417,57.61917,27.09417,57.61917],"geometry":{"coordinates":[27.09417,57.61917],"type":"Point"}}