{"id":1343527637,"type":"Feature","properties":{"edtf:cessation":"uuuu","edtf:inception":"uuuu","geom:area":0,"geom:area_square_m":0,"geom:bbox":"27.4425,58.255,27.4425,58.255","geom:latitude":58.255,"geom:longitude":27.4425,"gn:admin1_code":"12.0","gn:admin2_code":"708.0","gn:admin3_code":"2241.0","gn:asciiname":"Vastso-Pihosto","gn:country_code":"EE","gn:dem":34,"gn:feature_class":"P","gn:feature_code":"PPL","gn:geonameid":8618242,"gn:latitude":58.255,"gn:longitude":27.4425,"gn:modification_date":"2017-11-25","gn:name":"Vasts천-Pihost천","gn:population":0,"gn:timezone":"Europe/Tallinn","iso:country":"EE","lbl:bbox":"27.4225,58.235,27.4625,58.275","lbl:max_zoom":18,"lbl:min_zoom":13.5,"mz:hierarchy_label":1,"mz:is_current":1,"mz:min_zoom":12,"name:und_x_variant":["Vasts천-Pihost천","Uue"],"src:geom":"geonames","wof:belongsto":[85682955,102191581,1713314183,85633135,1713305793],"wof:breaches":[],"wof:concordances":{"gn:id":8618242},"wof:country":"EE","wof:geomhash":"c2ccee61f5f553df6daf95d352c6921b","wof:hierarchy":[{"continent_id":102191581,"country_id":85633135,"county_id":1713305793,"localadmin_id":1713314183,"locality_id":1343527637,"region_id":85682955}],"wof:id":1343527637,"wof:lang_x_official":["est"],"wof:lang_x_spoken":["est"],"wof:lastmodified":1596676998,"wof:name":"Vastso-Pihosto","wof:parent_id":1713314183,"wof:placetype":"locality","wof:repo":"whosonfirst-data-admin-ee","wof:superseded_by":[],"wof:supersedes":[],"wof:tags":[]},"bbox":[27.4425,58.255,27.4425,58.255],"geometry":{"coordinates":[27.4425,58.255],"type":"Point"}}