{"id":1126037775,"type":"Feature","properties":{"edtf:cessation":"uuuu","edtf:inception":"uuuu","geom:area":0,"geom:area_square_m":0,"geom:bbox":"25.54556,58.12444,25.54556,58.12444","geom:latitude":58.12444,"geom:longitude":25.54556,"gn:country":"EE","gn:fcode":"PPL","gn:population":268,"iso:country":"EE","lbl:bbox":"25.52556,58.10444,25.56556,58.14444","lbl:latitude":58.12444,"lbl:longitude":25.54556,"lbl:max_zoom":17,"lbl:min_zoom":12.5,"mz:hierarchy_label":1,"mz:is_current":1,"mz:min_zoom":11,"mz:note":"Quattroshapes Point Gazetteer import 20170519","name:ceb_x_preferred":["Polli"],"name:deu_x_preferred":["Polli"],"name:eng_x_preferred":["Polli"],"name:est_x_preferred":["Polli"],"name:fra_x_preferred":["Polli"],"name:hye_x_preferred":["Պոլլի"],"name:ita_x_preferred":["Polli"],"name:nld_x_preferred":["Polli"],"name:pol_x_preferred":["Polli"],"name:spa_x_preferred":["Polli"],"name:swe_x_preferred":["Polli"],"name:ukr_x_preferred":["Поллі"],"name:vol_x_preferred":["Polli"],"qs_pg:aaroncc":"EE","qs_pg:gn_country":"EE","qs_pg:gn_fcode":"PPL","qs_pg:gn_id":589387,"qs_pg:gn_pop":268,"qs_pg:name":"Polli","qs_pg:name_adm0":"Eesti","qs_pg:name_adm1":"Viljandimaa","qs_pg:photos_9k":1,"qs_pg:photos_9r":1,"qs_pg:photos_all":1,"qs_pg:photos_sr":0,"qs_pg:pop_sr":2,"qs_pg:qs_id":966869,"qs_pg:qs_pg_placetype":"locality","qs_pg:qs_pg_placetype_gp":"Town","qs_pg:woe_adm0":23424805,"qs_pg:woe_id":844820,"src:geom":"qs_pg","src:lbl_centroid":"qs_pg","src:population":"geonames","woe:adm0_id":23424805,"woe:name_adm0":"Eesti","woe:name_adm1":"Viljandimaa","woe:placetype":"Town","wof:belongsto":[85682985,102191581,1713311633,85633135,1713305661],"wof:breaches":[],"wof:concordances":{"gn:id":589387,"gp:id":844820,"qs_pg:id":966869,"wd:id":"Q2364508"},"wof:coterminous":[1713311633],"wof:country":"EE","wof:created":1497301906,"wof:geomhash":"39f07384c3aefa0738e723e118d7de7a","wof:hierarchy":[{"continent_id":102191581,"country_id":85633135,"county_id":1713305661,"localadmin_id":1713311633,"locality_id":1126037775,"region_id":85682985}],"wof:id":1126037775,"wof:lang_x_official":["est"],"wof:lang_x_spoken":["est"],"wof:lastmodified":1596661311,"wof:name":"Polli","wof:parent_id":1713311633,"wof:placetype":"locality","wof:population":268,"wof:population_rank":2,"wof:repo":"whosonfirst-data-admin-ee","wof:superseded_by":[],"wof:supersedes":[],"wof:tags":[]},"bbox":[25.54556,58.12444,25.54556,58.12444],"geometry":{"coordinates":[25.54556,58.12444],"type":"Point"}}