{"id":1293889733,"type":"Feature","properties":{"edtf:cessation":"uuuu","edtf:inception":"uuuu","geom:area":0,"geom:area_square_m":0,"geom:bbox":"25.26306,58.74861,25.26306,58.74861","geom:latitude":58.74861,"geom:longitude":25.26306,"gn:admin1_code":"4.0","gn:admin2_code":"834.0","gn:admin3_code":"5144.0","gn:asciiname":"Mola","gn:country_code":"EE","gn:dem":57,"gn:feature_class":"P","gn:feature_code":"PPL","gn:geonameid":793282,"gn:latitude":58.74861,"gn:longitude":25.26306,"gn:modification_date":"2017-11-25","gn:name":"Mõla","gn:population":0,"gn:timezone":"Europe/Tallinn","iso:country":"EE","lbl:bbox":"25.24306,58.72861,25.28306,58.76861","lbl:max_zoom":18,"lbl:min_zoom":13.5,"mz:hierarchy_label":1,"mz:is_current":1,"mz:min_zoom":12,"name:cat_x_preferred":["Mola"],"name:ceb_x_preferred":["Mola"],"name:deu_x_preferred":["Mola"],"name:eus_x_preferred":["Mola"],"name:fra_x_preferred":["Mola"],"name:glg_x_preferred":["Mola"],"name:heb_x_preferred":["מולה"],"name:hun_x_preferred":["Mola"],"name:ita_x_preferred":["Mola"],"name:lat_x_preferred":["Mola"],"name:nld_x_preferred":["Mola"],"name:pol_x_preferred":["Mola"],"name:por_x_preferred":["Mola"],"name:rus_x_preferred":["Мола"],"name:spa_x_preferred":["Mola"],"name:srp_x_preferred":["Mola"],"name:swe_x_preferred":["Mola"],"src:geom":"geonames","wof:belongsto":[85683031,102191581,1713312807,85633135,1713305773],"wof:breaches":[],"wof:concordances":{"gn:id":793282},"wof:country":"EE","wof:geomhash":"037ab5be04179f57badab5125e41f828","wof:hierarchy":[{"continent_id":102191581,"country_id":85633135,"county_id":1713305773,"localadmin_id":1713312807,"locality_id":1293889733,"region_id":85683031}],"wof:id":1293889733,"wof:lang_x_official":["est"],"wof:lang_x_spoken":["est"],"wof:lastmodified":1596677997,"wof:name":"Mola","wof:parent_id":1713312807,"wof:placetype":"locality","wof:repo":"whosonfirst-data-admin-ee","wof:superseded_by":[],"wof:supersedes":[],"wof:tags":[]},"bbox":[25.26306,58.74861,25.26306,58.74861],"geometry":{"coordinates":[25.26306,58.74861],"type":"Point"}}