{"id":1276404335,"type":"Feature","properties":{"edtf:cessation":"uuuu","edtf:inception":"uuuu","geom:area":0,"geom:area_square_m":0,"geom:bbox":"25.67556,58.29944,25.67556,58.29944","geom:latitude":58.29944,"geom:longitude":25.67556,"gn:admin1_code":"20.0","gn:admin2_code":"899.0","gn:admin3_code":"4484.0","gn:asciiname":"Vasila","gn:country_code":"EE","gn:dem":83,"gn:feature_class":"P","gn:feature_code":"PPL","gn:geonameid":8620391,"gn:latitude":58.29944,"gn:longitude":25.67556,"gn:modification_date":"2017-11-25","gn:name":"Vasila","gn:population":0,"gn:timezone":"Europe/Tallinn","iso:country":"EE","lbl:bbox":"25.65556,58.27944,25.69556,58.31944","lbl:max_zoom":18,"lbl:min_zoom":13.5,"mz:hierarchy_label":1,"mz:is_current":1,"mz:min_zoom":12,"src:geom":"geonames","wof:belongsto":[85682985,102191581,1713309963,85633135,1713305669],"wof:breaches":[],"wof:concordances":{"gn:id":8620391},"wof:country":"EE","wof:geomhash":"0fc05e3d7289d09e70d1c5bfa721fb64","wof:hierarchy":[{"continent_id":102191581,"country_id":85633135,"county_id":1713305669,"localadmin_id":1713309963,"locality_id":1276404335,"region_id":85682985}],"wof:id":1276404335,"wof:lang_x_official":["est"],"wof:lang_x_spoken":["est"],"wof:lastmodified":1596661254,"wof:name":"Vasila","wof:parent_id":1713309963,"wof:placetype":"locality","wof:repo":"whosonfirst-data-admin-ee","wof:superseded_by":[],"wof:supersedes":[],"wof:tags":[]},"bbox":[25.67556,58.29944,25.67556,58.29944],"geometry":{"coordinates":[25.67556,58.29944],"type":"Point"}}