{"id":1209082047,"type":"Feature","properties":{"edtf:cessation":"uuuu","edtf:inception":"uuuu","geom:area":0,"geom:area_square_m":0,"geom:bbox":"26.89139,58.5125,26.89139,58.5125","geom:latitude":58.5125,"geom:longitude":26.89139,"gn:admin1_code":"18.0","gn:admin2_code":"586.0","gn:admin3_code":"9053.0","gn:asciiname":"Kaarli","gn:country_code":"EE","gn:dem":63,"gn:feature_class":"P","gn:feature_code":"PPL","gn:geonameid":591846,"gn:latitude":58.5125,"gn:longitude":26.89139,"gn:modification_date":"2017-11-25","gn:name":"Kaarli","gn:population":0,"gn:timezone":"Europe/Tallinn","iso:country":"EE","lbl:bbox":"26.87139,58.4925,26.91139,58.5325","lbl:max_zoom":18,"lbl:min_zoom":13.5,"mz:hierarchy_label":1,"mz:is_current":1,"mz:min_zoom":12,"name:und_x_variant":["Karli","Kaarli"],"src:geom":"geonames","wof:belongsto":[85682995,102191581,1713309681,85633135,1713305679],"wof:breaches":[],"wof:concordances":{"gn:id":591846},"wof:country":"EE","wof:geomhash":"ffdf50709ce41fd5602154a8a15617e5","wof:hierarchy":[{"continent_id":102191581,"country_id":85633135,"county_id":1713305679,"localadmin_id":1713309681,"locality_id":1209082047,"region_id":85682995}],"wof:id":1209082047,"wof:lang_x_official":["est"],"wof:lang_x_spoken":["est"],"wof:lastmodified":1596660912,"wof:name":"Kaarli","wof:parent_id":1713309681,"wof:placetype":"locality","wof:repo":"whosonfirst-data-admin-ee","wof:superseded_by":[],"wof:supersedes":[],"wof:tags":[]},"bbox":[26.89139,58.5125,26.89139,58.5125],"geometry":{"coordinates":[26.89139,58.5125],"type":"Point"}}