{"id":1293077417,"type":"Feature","properties":{"edtf:cessation":"uuuu","edtf:inception":"uuuu","geom:area":0,"geom:area_square_m":0,"geom:bbox":"24.51111,58.86472,24.51111,58.86472","geom:latitude":58.86472,"geom:longitude":24.51111,"gn:admin1_code":"13.0","gn:admin2_code":"503.0","gn:admin3_code":"4479.0","gn:asciiname":"Lokuta","gn:country_code":"EE","gn:dem":37,"gn:feature_class":"P","gn:feature_code":"PPL","gn:geonameid":8619573,"gn:latitude":58.86472,"gn:longitude":24.51111,"gn:modification_date":"2017-11-25","gn:name":"Lokuta","gn:population":0,"gn:timezone":"Europe/Tallinn","iso:country":"EE","lbl:bbox":"24.49111,58.84472,24.53111,58.88472","lbl:max_zoom":18,"lbl:min_zoom":13.5,"mz:hierarchy_label":1,"mz:is_current":1,"mz:min_zoom":12,"name:ceb_x_preferred":["Lokuta"],"name:est_x_preferred":["Lokuta"],"name:fra_x_preferred":["Lokuta"],"name:hye_x_preferred":["Լոկուտա"],"name:pol_x_preferred":["Lokuta"],"name:sco_x_preferred":["Lokuta"],"name:swe_x_preferred":["Lokuta"],"name:ukr_x_preferred":["Локута"],"name:vol_x_preferred":["Lokuta"],"src:geom":"geonames","wof:belongsto":[85683013,102191581,1713311141,85633135,1713305747],"wof:breaches":[],"wof:concordances":{"gn:id":8619573},"wof:country":"EE","wof:geomhash":"5e1a40272c74be82c7d2e71cc069a438","wof:hierarchy":[{"continent_id":102191581,"country_id":85633135,"county_id":1713305747,"localadmin_id":1713311141,"locality_id":1293077417,"region_id":85683013}],"wof:id":1293077417,"wof:lang_x_official":["est"],"wof:lang_x_spoken":["est"],"wof:lastmodified":1596662844,"wof:name":"Lokuta","wof:parent_id":1713311141,"wof:placetype":"locality","wof:repo":"whosonfirst-data-admin-ee","wof:superseded_by":[],"wof:supersedes":[],"wof:tags":[]},"bbox":[24.51111,58.86472,24.51111,58.86472],"geometry":{"coordinates":[24.51111,58.86472],"type":"Point"}}