{"id":1327220147,"type":"Feature","properties":{"edtf:cessation":"uuuu","edtf:inception":"uuuu","geom:area":0,"geom:area_square_m":0,"geom:bbox":"24.95,59.05,24.95,59.05","geom:latitude":59.05,"geom:longitude":24.95,"gn:admin1_code":"13.0","gn:admin2_code":"668.0","gn:admin3_code":"5717.0","gn:asciiname":"Orguse-Saunakuela","gn:country_code":"EE","gn:dem":77,"gn:feature_class":"P","gn:feature_code":"PPL","gn:geonameid":589800,"gn:latitude":59.05,"gn:longitude":24.95,"gn:modification_date":"2017-11-25","gn:name":"Orguse-Saunaküla","gn:population":0,"gn:timezone":"Europe/Tallinn","iso:country":"EE","lbl:bbox":"24.93,59.03,24.97,59.07","lbl:max_zoom":18,"lbl:min_zoom":13.5,"mz:hierarchy_label":1,"mz:is_current":1,"mz:min_zoom":12,"name:und_x_variant":["Orguse-Saunakyula","Orguse-Saunaküla"],"src:geom":"geonames","wof:belongsto":[85683013,102191581,1713311441,85633135,1713305711],"wof:breaches":[],"wof:concordances":{"gn:id":589800},"wof:country":"EE","wof:geomhash":"05f6b3d43000d86cc480fece801dea0e","wof:hierarchy":[{"continent_id":102191581,"country_id":85633135,"county_id":1713305711,"localadmin_id":1713311441,"locality_id":1327220147,"region_id":85683013}],"wof:id":1327220147,"wof:lang_x_official":["est"],"wof:lang_x_spoken":["est"],"wof:lastmodified":1596676729,"wof:name":"Orguse-Saunakuela","wof:parent_id":1713311441,"wof:placetype":"locality","wof:repo":"whosonfirst-data-admin-ee","wof:superseded_by":[],"wof:supersedes":[],"wof:tags":[]},"bbox":[24.95,59.05,24.95,59.05],"geometry":{"coordinates":[24.95,59.05],"type":"Point"}}