{"id":1209603279,"type":"Feature","properties":{"edtf:cessation":"uuuu","edtf:inception":"uuuu","geom:area":0,"geom:area_square_m":0,"geom:bbox":"23.70361,58.53306,23.70361,58.53306","geom:latitude":58.53306,"geom:longitude":23.70361,"gn:admin1_code":"11.0","gn:admin2_code":"430.0","gn:admin3_code":"5801.0","gn:asciiname":"Illuste","gn:country_code":"EE","gn:dem":8,"gn:feature_class":"P","gn:feature_code":"PPL","gn:geonameid":592053,"gn:latitude":58.53306,"gn:longitude":23.70361,"gn:modification_date":"2017-11-25","gn:name":"Illuste","gn:population":0,"gn:timezone":"Europe/Tallinn","iso:country":"EE","lbl:bbox":"23.68361,58.51306,23.72361,58.55306","lbl:max_zoom":18,"lbl:min_zoom":13.5,"mz:hierarchy_label":1,"mz:is_current":1,"mz:min_zoom":12,"name:und_x_variant":["Myza Illuste","Illuste"],"src:geom":"geonames","wof:belongsto":[85683001,102191581,1713309239,85633135,1713305721],"wof:breaches":[],"wof:concordances":{"gn:id":592053},"wof:country":"EE","wof:geomhash":"1b242df4deb0febd48622e766cb10d7e","wof:hierarchy":[{"continent_id":102191581,"country_id":85633135,"county_id":1713305721,"localadmin_id":1713309239,"locality_id":1209603279,"region_id":85683001}],"wof:id":1209603279,"wof:lang_x_official":["est"],"wof:lang_x_spoken":["est"],"wof:lastmodified":1596661683,"wof:name":"Illuste","wof:parent_id":1713309239,"wof:placetype":"locality","wof:repo":"whosonfirst-data-admin-ee","wof:superseded_by":[],"wof:supersedes":[],"wof:tags":[]},"bbox":[23.70361,58.53306,23.70361,58.53306],"geometry":{"coordinates":[23.70361,58.53306],"type":"Point"}}