{"id":1276983359,"type":"Feature","properties":{"edtf:cessation":"uuuu","edtf:inception":"uuuu","geom:area":0,"geom:area_square_m":0,"geom:bbox":"22.60668,58.80972,22.60668,58.80972","geom:latitude":58.80972,"geom:longitude":22.60668,"gn:admin1_code":"2.0","gn:admin2_code":"205.0","gn:admin3_code":"4253.0","gn:asciiname":"Lelu","gn:country_code":"EE","gn:dem":16,"gn:feature_class":"P","gn:feature_code":"PPL","gn:geonameid":590699,"gn:latitude":58.80972,"gn:longitude":22.60668,"gn:modification_date":"2017-11-25","gn:name":"Lelu","gn:population":0,"gn:timezone":"Europe/Tallinn","iso:country":"EE","lbl:bbox":"22.58668,58.78972,22.62668,58.82972","lbl:max_zoom":18,"lbl:min_zoom":13.5,"mz:hierarchy_label":1,"mz:is_current":1,"mz:min_zoom":12,"name:deu_x_preferred":["Lelu"],"name:est_x_preferred":["Lelu"],"name:hye_x_preferred":["Լելու"],"name:pol_x_preferred":["Lelu"],"name:spa_x_preferred":["Lelu"],"name:vol_x_preferred":["Lelu"],"src:geom":"geonames","wof:belongsto":[85682989,102191581,1713310273,85633135,1713305629],"wof:breaches":[],"wof:concordances":{"gn:id":590699,"wk:page":"Lelu%2C_Estonia"},"wof:coterminous":[1713310273],"wof:country":"EE","wof:geomhash":"b36fec97fbe628df96b072458a09baec","wof:hierarchy":[{"continent_id":102191581,"country_id":85633135,"county_id":1713305629,"localadmin_id":1713310273,"locality_id":1276983359,"region_id":85682989}],"wof:id":1276983359,"wof:lang_x_official":["est"],"wof:lang_x_spoken":["est"],"wof:lastmodified":1596670020,"wof:name":"Lelu","wof:parent_id":1713310273,"wof:placetype":"locality","wof:repo":"whosonfirst-data-admin-ee","wof:superseded_by":[],"wof:supersedes":[],"wof:tags":[]},"bbox":[22.60668,58.80972,22.60668,58.80972],"geometry":{"coordinates":[22.60668,58.80972],"type":"Point"}}