{"id":1260273841,"type":"Feature","properties":{"edtf:cessation":"uuuu","edtf:inception":"uuuu","geom:area":0,"geom:area_square_m":0,"geom:bbox":"26.16806,59.47556,26.16806,59.47556","geom:latitude":59.47556,"geom:longitude":26.16806,"gn:admin1_code":"8.0","gn:admin2_code":"191.0","gn:admin3_code":"7374.0","gn:asciiname":"Salatse","gn:country_code":"EE","gn:dem":81,"gn:feature_class":"P","gn:feature_code":"PPL","gn:geonameid":588828,"gn:latitude":59.47556,"gn:longitude":26.16806,"gn:modification_date":"2017-11-25","gn:name":"Salatse","gn:population":0,"gn:timezone":"Europe/Tallinn","iso:country":"EE","lbl:bbox":"26.14806,59.45556,26.18806,59.49556","lbl:max_zoom":18,"lbl:min_zoom":13.5,"mz:hierarchy_label":1,"mz:is_current":1,"mz:min_zoom":12,"name:est_x_preferred":["Salatse"],"name:fra_x_preferred":["Salatse"],"name:hye_x_preferred":["Սալացե"],"name:vol_x_preferred":["Salatse"],"src:geom":"geonames","wof:belongsto":[85683049,102191581,1713308201,85633135,1713305775],"wof:breaches":[],"wof:concordances":{"gn:id":588828,"wk:page":"Salatse"},"wof:coterminous":[1713308201],"wof:country":"EE","wof:geomhash":"5db17b64b301194cf8d3c297a2be47c5","wof:hierarchy":[{"continent_id":102191581,"country_id":85633135,"county_id":1713305775,"localadmin_id":1713308201,"locality_id":1260273841,"region_id":85683049}],"wof:id":1260273841,"wof:lang_x_official":["est"],"wof:lang_x_spoken":["est"],"wof:lastmodified":1596678041,"wof:name":"Salatse","wof:parent_id":1713308201,"wof:placetype":"locality","wof:repo":"whosonfirst-data-admin-ee","wof:superseded_by":[],"wof:supersedes":[],"wof:tags":[]},"bbox":[26.16806,59.47556,26.16806,59.47556],"geometry":{"coordinates":[26.16806,59.47556],"type":"Point"}}