{"id":1293492435,"type":"Feature","properties":{"edtf:cessation":"uuuu","edtf:inception":"uuuu","geom:area":0,"geom:area_square_m":0,"geom:bbox":"26.61833,58.86972,26.61833,58.86972","geom:latitude":58.86972,"geom:longitude":26.61833,"gn:admin1_code":"5.0","gn:admin2_code":"247.0","gn:admin3_code":"8558.0","gn:asciiname":"Venekuela","gn:country_code":"EE","gn:dem":106,"gn:feature_class":"P","gn:feature_code":"PPL","gn:geonameid":8619544,"gn:latitude":58.86972,"gn:longitude":26.61833,"gn:modification_date":"2017-11-25","gn:name":"Veneküla","gn:population":0,"gn:timezone":"Europe/Tallinn","iso:country":"EE","lbl:bbox":"26.59833,58.84972,26.63833,58.88972","lbl:max_zoom":18,"lbl:min_zoom":13.5,"mz:hierarchy_label":1,"mz:is_current":1,"mz:min_zoom":12,"name:und_x_variant":["Veneküla","Sadala-Veneküla"],"src:geom":"geonames","wof:belongsto":[85683009,102191581,1713312223,85633135,1713305767],"wof:breaches":[],"wof:concordances":{"gn:id":8619544},"wof:country":"EE","wof:geomhash":"7a0569e0b5b9e8660aebaf9be4f7b7db","wof:hierarchy":[{"continent_id":102191581,"country_id":85633135,"county_id":1713305767,"localadmin_id":1713312223,"locality_id":1293492435,"region_id":85683009}],"wof:id":1293492435,"wof:lang_x_official":["est"],"wof:lang_x_spoken":["est"],"wof:lastmodified":1596676583,"wof:name":"Venekuela","wof:parent_id":1713312223,"wof:placetype":"locality","wof:repo":"whosonfirst-data-admin-ee","wof:superseded_by":[],"wof:supersedes":[],"wof:tags":[]},"bbox":[26.61833,58.86972,26.61833,58.86972],"geometry":{"coordinates":[26.61833,58.86972],"type":"Point"}}