{"id":1209380383,"type":"Feature","properties":{"edtf:cessation":"uuuu","edtf:inception":"uuuu","geom:area":0,"geom:area_square_m":0,"geom:bbox":"25.80361,57.97194,25.80361,57.97194","geom:latitude":57.97194,"geom:longitude":25.80361,"gn:admin1_code":"19.0","gn:admin2_code":"824.0","gn:admin3_code":"3420.0","gn:asciiname":"Kannu","gn:country_code":"EE","gn:dem":104,"gn:feature_class":"P","gn:feature_code":"PPL","gn:geonameid":8619150,"gn:latitude":57.97194,"gn:longitude":25.80361,"gn:modification_date":"2017-11-25","gn:name":"Kannu","gn:population":0,"gn:timezone":"Europe/Tallinn","iso:country":"EE","lbl:bbox":"25.78361,57.95194,25.82361,57.99194","lbl:max_zoom":18,"lbl:min_zoom":13.5,"mz:hierarchy_label":1,"mz:is_current":1,"mz:min_zoom":12,"name:est_x_preferred":["Kannu"],"name:fin_x_preferred":["Kannu"],"name:und_x_variant":["Katai"],"name:vol_x_preferred":["Kannu"],"src:geom":"geonames","wof:belongsto":[85682941,102191581,1713310401,85633135,1713305687],"wof:breaches":[],"wof:concordances":{"gn:id":8619150},"wof:country":"EE","wof:geomhash":"a9599f2dcb15979e24897d9a1e26eeae","wof:hierarchy":[{"continent_id":102191581,"country_id":85633135,"county_id":1713305687,"localadmin_id":1713310401,"locality_id":1209380383,"region_id":85682941}],"wof:id":1209380383,"wof:lang_x_official":["est"],"wof:lang_x_spoken":["est"],"wof:lastmodified":1596661433,"wof:name":"Kannu","wof:parent_id":1713310401,"wof:placetype":"locality","wof:repo":"whosonfirst-data-admin-ee","wof:superseded_by":[],"wof:supersedes":[],"wof:tags":[]},"bbox":[25.80361,57.97194,25.80361,57.97194],"geometry":{"coordinates":[25.80361,57.97194],"type":"Point"}}