{"id":1226327969,"type":"Feature","properties":{"edtf:cessation":"uuuu","edtf:inception":"uuuu","geom:area":0,"geom:area_square_m":0,"geom:bbox":"26.73083,59.48472,26.73083,59.48472","geom:latitude":59.48472,"geom:longitude":26.73083,"gn:admin1_code":"8.0","gn:admin2_code":"903.0","gn:admin3_code":"8704.0","gn:asciiname":"Adrika","gn:country_code":"EE","gn:dem":35,"gn:feature_class":"P","gn:feature_code":"PPL","gn:geonameid":592613,"gn:latitude":59.48472,"gn:longitude":26.73083,"gn:modification_date":"2017-11-25","gn:name":"Adrika","gn:population":0,"gn:timezone":"Europe/Tallinn","iso:country":"EE","lbl:bbox":"26.71083,59.46472,26.75083,59.50472","lbl:max_zoom":18,"lbl:min_zoom":13.5,"mz:hierarchy_label":1,"mz:is_current":1,"mz:min_zoom":12,"name:und_x_variant":["Adriku","Adrika"],"src:geom":"geonames","wof:belongsto":[85683049,102191581,1713307699,85633135,1713305777],"wof:breaches":[],"wof:concordances":{"gn:id":592613},"wof:country":"EE","wof:geomhash":"f6b36fde76aead4b432bbf020b641cdd","wof:hierarchy":[{"continent_id":102191581,"country_id":85633135,"county_id":1713305777,"localadmin_id":1713307699,"locality_id":1226327969,"region_id":85683049}],"wof:id":1226327969,"wof:lang_x_official":["est"],"wof:lang_x_spoken":["est"],"wof:lastmodified":1596677934,"wof:name":"Adrika","wof:parent_id":1713307699,"wof:placetype":"locality","wof:repo":"whosonfirst-data-admin-ee","wof:superseded_by":[],"wof:supersedes":[],"wof:tags":[]},"bbox":[26.73083,59.48472,26.73083,59.48472],"geometry":{"coordinates":[26.73083,59.48472],"type":"Point"}}