{"id":1125893001,"type":"Feature","properties":{"edtf:cessation":"uuuu","edtf:inception":"uuuu","geom:area":0,"geom:area_square_m":0,"geom:bbox":"25.7225,58.88944,25.7225,58.88944","geom:latitude":58.88944,"geom:longitude":25.7225,"gn:country":"EE","gn:fcode":"PPL","gn:population":238,"iso:country":"EE","lbl:bbox":"25.7025,58.86944,25.7425,58.90944","lbl:latitude":58.88944,"lbl:longitude":25.7225,"lbl:max_zoom":17,"lbl:min_zoom":12.5,"mz:hierarchy_label":1,"mz:is_current":1,"mz:min_zoom":11,"mz:note":"Quattroshapes Point Gazetteer import 20170519","name:bul_x_preferred":["Саргвере"],"name:ceb_x_preferred":["Sargvere"],"name:eng_x_preferred":["Sargvere"],"name:est_x_preferred":["Sargvere"],"name:fra_x_preferred":["Sargvere"],"name:hye_x_preferred":["Սառգվեռե"],"name:nld_x_preferred":["Sargvere"],"name:pol_x_preferred":["Sargvere"],"name:swe_x_preferred":["Sargvere"],"name:ukr_x_preferred":["Сарґвере"],"name:und_x_variant":["Myza Syargvere"],"name:vol_x_preferred":["Sargvere"],"qs_pg:aaroncc":"EE","qs_pg:gn_country":"EE","qs_pg:gn_fcode":"PPL","qs_pg:gn_id":588791,"qs_pg:gn_pop":238,"qs_pg:name":"Sargvere","qs_pg:name_adm0":"Eesti","qs_pg:name_adm1":"Järvamaa","qs_pg:photos_9k":1,"qs_pg:photos_9r":1,"qs_pg:photos_all":6,"qs_pg:photos_sr":0,"qs_pg:pop_sr":2,"qs_pg:qs_id":918028,"qs_pg:qs_pg_placetype":"locality","qs_pg:qs_pg_placetype_gp":"Town","qs_pg:woe_adm0":23424805,"qs_pg:woe_id":845389,"src:geom":"qs_pg","src:lbl_centroid":"qs_pg","src:population":"geonames","woe:adm0_id":23424805,"woe:name_adm0":"Eesti","woe:name_adm1":"Järvamaa","woe:placetype":"Town","wof:belongsto":[85683031,102191581,1713312755,85633135,1713305663],"wof:breaches":[],"wof:concordances":{"gn:id":588791,"gp:id":845389,"qs_pg:id":918028,"wd:id":"Q3466436"},"wof:coterminous":[1713312755],"wof:country":"EE","wof:created":1497295409,"wof:geomhash":"dca2c7a0b265a2643f12c169c97f5b2f","wof:hierarchy":[{"continent_id":102191581,"country_id":85633135,"county_id":1713305663,"localadmin_id":1713312755,"locality_id":1125893001,"region_id":85683031}],"wof:id":1125893001,"wof:lang_x_official":["est"],"wof:lang_x_spoken":["est"],"wof:lastmodified":1596661330,"wof:name":"Sargvere","wof:parent_id":1713312755,"wof:placetype":"locality","wof:population":238,"wof:population_rank":2,"wof:repo":"whosonfirst-data-admin-ee","wof:superseded_by":[],"wof:supersedes":[],"wof:tags":[]},"bbox":[25.7225,58.88944,25.7225,58.88944],"geometry":{"coordinates":[25.7225,58.88944],"type":"Point"}}