{"id":1259770331,"type":"Feature","properties":{"edtf:cessation":"uuuu","edtf:inception":"uuuu","geom:area":0,"geom:area_square_m":0,"geom:bbox":"27.59056,58.08278,27.59056,58.08278","geom:latitude":58.08278,"geom:longitude":27.59056,"gn:admin1_code":"21.0","gn:asciiname":"Beresje","gn:country_code":"EE","gn:dem":30,"gn:feature_class":"P","gn:feature_code":"PPL","gn:geonameid":592330,"gn:latitude":58.08278,"gn:longitude":27.59056,"gn:modification_date":"2018-04-06","gn:name":"Beresje","gn:population":0,"gn:timezone":"Europe/Tallinn","iso:country":"EE","lbl:bbox":"27.57056,58.06278,27.61056,58.10278","lbl:max_zoom":18,"lbl:min_zoom":13.5,"mz:hierarchy_label":1,"mz:is_current":1,"mz:min_zoom":12,"name:deu_x_preferred":["Beresje"],"name:est_x_preferred":["Beresje"],"name:fra_x_preferred":["Beresje"],"name:hye_x_preferred":["Բեռեսե"],"name:nld_x_preferred":["Beresje"],"name:pol_x_preferred":["Beresje"],"name:rus_x_preferred":["Бересье"],"name:sco_x_preferred":["Beresje"],"name:spa_x_preferred":["Beresje"],"name:ukr_x_preferred":["Бересьє"],"name:und_x_variant":["Berez’ye"],"name:vol_x_preferred":["Beresje"],"src:geom":"geonames","wof:belongsto":[102191581,85633135,85682955],"wof:breaches":[],"wof:concordances":{"gn:id":592330,"wk:page":"Beresje"},"wof:coterminous":[1713316459],"wof:country":"EE","wof:geomhash":"8d1355f927b9ae6175da6cdd472c6cad","wof:hierarchy":[{"continent_id":102191581,"country_id":85633135,"locality_id":1259770331,"region_id":85682955}],"wof:id":1259770331,"wof:lang_x_official":["est"],"wof:lang_x_spoken":["est"],"wof:lastmodified":1596485156,"wof:name":"Beresje","wof:parent_id":85682955,"wof:placetype":"locality","wof:repo":"whosonfirst-data-admin-ee","wof:superseded_by":[],"wof:supersedes":[],"wof:tags":[]},"bbox":[27.59056,58.08278,27.59056,58.08278],"geometry":{"coordinates":[27.59056,58.08278],"type":"Point"}}