{"id":1293848277,"type":"Feature","properties":{"edtf:cessation":"uuuu","edtf:inception":"uuuu","geom:area":0,"geom:area_square_m":0,"geom:bbox":"26.64556,57.67111,26.64556,57.67111","geom:latitude":57.67111,"geom:longitude":26.64556,"gn:admin1_code":"21.0","gn:admin2_code":"698.0","gn:admin3_code":"9002.0","gn:asciiname":"Sulomoisa","gn:country_code":"EE","gn:dem":85,"gn:feature_class":"P","gn:feature_code":"PPL","gn:geonameid":8619613,"gn:latitude":57.67111,"gn:longitude":26.64556,"gn:modification_date":"2017-11-25","gn:name":"Sulõmõisa","gn:population":0,"gn:timezone":"Europe/Tallinn","iso:country":"EE","lbl:bbox":"26.62556,57.65111,26.66556,57.69111","lbl:max_zoom":18,"lbl:min_zoom":13.5,"mz:hierarchy_label":1,"mz:is_current":1,"mz:min_zoom":12,"name:und_x_variant":["Sulõmõisa","Sulemõisa"],"src:geom":"geonames","wof:belongsto":[85682937,102191581,1713315129,85633135,1713305787],"wof:breaches":[],"wof:concordances":{"gn:id":8619613},"wof:country":"EE","wof:geomhash":"81a5a87dadfd0df5364724433666bd5e","wof:hierarchy":[{"continent_id":102191581,"country_id":85633135,"county_id":1713305787,"localadmin_id":1713315129,"locality_id":1293848277,"region_id":85682937}],"wof:id":1293848277,"wof:lang_x_official":["est"],"wof:lang_x_spoken":["est"],"wof:lastmodified":1596676899,"wof:name":"Sulomoisa","wof:parent_id":1713315129,"wof:placetype":"locality","wof:repo":"whosonfirst-data-admin-ee","wof:superseded_by":[],"wof:supersedes":[],"wof:tags":[]},"bbox":[26.64556,57.67111,26.64556,57.67111],"geometry":{"coordinates":[26.64556,57.67111],"type":"Point"}}