{"id":1125850371,"type":"Feature","properties":{"edtf:cessation":"uuuu","edtf:inception":"uuuu","geom:area":0,"geom:area_square_m":0,"geom:bbox":"23.98,58.11722,23.98,58.11722","geom:latitude":58.11722,"geom:longitude":23.98,"gn:country":"EE","gn:fcode":"PPL","gn:population":104,"iso:country":"EE","lbl:bbox":"23.96,58.09722,24.0,58.13722","lbl:latitude":58.11722,"lbl:longitude":23.98,"lbl:max_zoom":18,"lbl:min_zoom":13,"mz:hierarchy_label":1,"mz:is_current":1,"mz:min_zoom":11,"mz:note":"Quattroshapes Point Gazetteer import 20170519","name:ceb_x_preferred":["Rootsiküla"],"name:eng_x_preferred":["Rootsiküla"],"name:est_x_preferred":["Rootsiküla"],"name:hye_x_preferred":["Ռոոցիկյուլա"],"name:nld_x_preferred":["Rootsiküla"],"name:pol_x_preferred":["Rootsiküla"],"name:spa_x_preferred":["Rootsiküla"],"name:swe_x_preferred":["Rootsiküla"],"name:und_x_variant":["Rotsikyula"],"name:vol_x_preferred":["Rootsiküla"],"qs_pg:aaroncc":"EE","qs_pg:gn_country":"EE","qs_pg:gn_fcode":"PPL","qs_pg:gn_id":588961,"qs_pg:gn_pop":104,"qs_pg:name":"Rootsiküla","qs_pg:name_adm0":"Eesti","qs_pg:name_adm1":"Pärnumaa","qs_pg:photos":11,"qs_pg:photos_1k":2,"qs_pg:photos_9k":1,"qs_pg:photos_9r":1,"qs_pg:photos_all":11,"qs_pg:photos_sr":1,"qs_pg:pop_sr":1,"qs_pg:qs_id":1096319,"qs_pg:qs_pg_placetype":"locality","qs_pg:qs_pg_placetype_gp":"Town","qs_pg:woe_adm0":23424805,"qs_pg:woe_id":845236,"src:geom":"qs_pg","src:lbl_centroid":"qs_pg","src:population":"geonames","woe:adm0_id":23424805,"woe:name_adm0":"Eesti","woe:name_adm1":"Pärnumaa","woe:placetype":"Town","wof:belongsto":[85682981,102191581,1713306139,85633135,1713305635],"wof:breaches":[],"wof:concordances":{"gn:id":588961,"gp:id":845236,"qs_pg:id":1096319,"wd:id":"Q3454333"},"wof:coterminous":[1713306139],"wof:country":"EE","wof:created":1497293374,"wof:geomhash":"0d5edf2f9998335d48453a1aa301ab20","wof:hierarchy":[{"continent_id":102191581,"country_id":85633135,"county_id":1713305635,"localadmin_id":1713306139,"locality_id":1125850371,"region_id":85682981}],"wof:id":1125850371,"wof:lang_x_official":["est"],"wof:lang_x_spoken":["est"],"wof:lastmodified":1596663957,"wof:name":"Rootsiküla","wof:parent_id":1713306139,"wof:placetype":"locality","wof:population":104,"wof:population_rank":1,"wof:repo":"whosonfirst-data-admin-ee","wof:superseded_by":[],"wof:supersedes":[],"wof:tags":[]},"bbox":[23.98,58.11722,23.98,58.11722],"geometry":{"coordinates":[23.98,58.11722],"type":"Point"}}