{"id":1293676225,"type":"Feature","properties":{"edtf:cessation":"uuuu","edtf:inception":"uuuu","geom:area":0,"geom:area_square_m":0,"geom:bbox":"27.42278,58.05,27.42278,58.05","geom:latitude":58.05,"geom:longitude":27.42278,"gn:admin1_code":"12.0","gn:admin2_code":"708.0","gn:admin3_code":"6743.0","gn:asciiname":"Palo","gn:country_code":"EE","gn:dem":43,"gn:feature_class":"P","gn:feature_code":"PPL","gn:geonameid":8620515,"gn:latitude":58.05,"gn:longitude":27.42278,"gn:modification_date":"2017-11-25","gn:name":"Palo","gn:population":0,"gn:timezone":"Europe/Tallinn","iso:country":"EE","lbl:bbox":"27.40278,58.03,27.44278,58.07","lbl:max_zoom":18,"lbl:min_zoom":13.5,"mz:hierarchy_label":1,"mz:is_current":1,"mz:min_zoom":12,"name:ceb_x_preferred":["Palo"],"name:deu_x_preferred":["Palo"],"name:fin_x_preferred":["Palo"],"name:ita_x_preferred":["Palo"],"name:nld_x_preferred":["Palo"],"name:pol_x_preferred":["Palo"],"name:slk_x_preferred":["Palo"],"name:spa_x_preferred":["Palo"],"name:swe_x_preferred":["Palo"],"name:tgl_x_preferred":["Palo"],"name:und_x_variant":["Palokülä"],"name:vol_x_preferred":["Palo"],"name:war_x_preferred":["Palo"],"src:geom":"geonames","wof:belongsto":[85682955,102191581,1713311043,85633135,1713305793],"wof:breaches":[],"wof:concordances":{"gn:id":8620515},"wof:country":"EE","wof:geomhash":"6a31378fedfd45e9f499f694f958adaf","wof:hierarchy":[{"continent_id":102191581,"country_id":85633135,"county_id":1713305793,"localadmin_id":1713311043,"locality_id":1293676225,"region_id":85682955}],"wof:id":1293676225,"wof:lang_x_official":["est"],"wof:lang_x_spoken":["est"],"wof:lastmodified":1596677002,"wof:name":"Palo","wof:parent_id":1713311043,"wof:placetype":"locality","wof:repo":"whosonfirst-data-admin-ee","wof:superseded_by":[],"wof:supersedes":[],"wof:tags":[]},"bbox":[27.42278,58.05,27.42278,58.05],"geometry":{"coordinates":[27.42278,58.05],"type":"Point"}}