{"id":1226629699,"type":"Feature","properties":{"edtf:cessation":"uuuu","edtf:inception":"uuuu","geom:area":0,"geom:area_square_m":0,"geom:bbox":"22.24167,58.09611,22.24167,58.09611","geom:latitude":58.09611,"geom:longitude":22.24167,"gn:admin1_code":"14.0","gn:admin2_code":"714.0","gn:admin3_code":"1297.0","gn:asciiname":"Ansekuela","gn:country_code":"EE","gn:dem":9,"gn:feature_class":"P","gn:feature_code":"PPL","gn:geonameid":592461,"gn:latitude":58.09611,"gn:longitude":22.24167,"gn:modification_date":"2017-11-25","gn:name":"Anseküla","gn:population":0,"gn:timezone":"Europe/Tallinn","iso:country":"EE","lbl:bbox":"22.22167,58.07611,22.26167,58.11611","lbl:max_zoom":18,"lbl:min_zoom":13.5,"mz:hierarchy_label":1,"mz:is_current":1,"mz:min_zoom":12,"name:deu_x_preferred":["Anseküla"],"name:est_x_preferred":["Anseküla"],"name:hye_x_preferred":["Անսեկյուլա"],"name:nld_x_preferred":["Anseküla"],"name:pol_x_preferred":["Anseküla"],"name:spa_x_preferred":["Anseküla"],"name:swe_x_preferred":["Anseküla"],"name:ukr_x_preferred":["Ансекюла"],"name:und_x_variant":["Ansekil","Asuküla","Anzekyul’","Anzekyula","Ansekyula"],"name:vol_x_preferred":["Anseküla"],"src:geom":"geonames","wof:belongsto":[85682947,102191581,1713307499,85633135,1713305627],"wof:breaches":[],"wof:concordances":{"gn:id":592461,"wk:page":"Ansek%C3%BCla"},"wof:coterminous":[1713307499],"wof:country":"EE","wof:geomhash":"7f954a10305e74e3d6aa319b6f5d6ca3","wof:hierarchy":[{"continent_id":102191581,"country_id":85633135,"county_id":1713305627,"localadmin_id":1713307499,"locality_id":1226629699,"region_id":85682947}],"wof:id":1226629699,"wof:lang_x_official":["est"],"wof:lang_x_spoken":["est"],"wof:lastmodified":1596674948,"wof:name":"Ansekuela","wof:parent_id":1713307499,"wof:placetype":"locality","wof:repo":"whosonfirst-data-admin-ee","wof:superseded_by":[],"wof:supersedes":[],"wof:tags":[]},"bbox":[22.24167,58.09611,22.24167,58.09611],"geometry":{"coordinates":[22.24167,58.09611],"type":"Point"}}