{"id":1259460111,"type":"Feature","properties":{"edtf:cessation":"uuuu","edtf:inception":"uuuu","geom:area":0,"geom:area_square_m":0,"geom:bbox":"26.91222,58.01167,26.91222,58.01167","geom:latitude":58.01167,"geom:longitude":26.91222,"gn:admin1_code":"12.0","gn:admin2_code":"284.0","gn:admin3_code":"9066.0","gn:asciiname":"Tille","gn:country_code":"EE","gn:dem":110,"gn:feature_class":"P","gn:feature_code":"PPL","gn:geonameid":8620028,"gn:latitude":58.01167,"gn:longitude":26.91222,"gn:modification_date":"2017-11-25","gn:name":"Tille","gn:population":0,"gn:timezone":"Europe/Tallinn","iso:country":"EE","lbl:bbox":"26.89222,57.99167,26.93222,58.03167","lbl:max_zoom":18,"lbl:min_zoom":13.5,"mz:hierarchy_label":1,"mz:is_current":1,"mz:min_zoom":12,"name:ceb_x_preferred":["Tille"],"name:ces_x_preferred":["Tille"],"name:deu_x_preferred":["Tille"],"name:nld_x_preferred":["Tille"],"name:srp_x_preferred":["Тиј"],"name:swe_x_preferred":["Tille"],"src:geom":"geonames","wof:belongsto":[85682955,102191581,1713313837,85633135,1713305789],"wof:breaches":[],"wof:concordances":{"gn:id":8620028},"wof:country":"EE","wof:geomhash":"b616ac8bad17f35d07e343f5b1e8ab30","wof:hierarchy":[{"continent_id":102191581,"country_id":85633135,"county_id":1713305789,"localadmin_id":1713313837,"locality_id":1259460111,"region_id":85682955}],"wof:id":1259460111,"wof:lang_x_official":["est"],"wof:lang_x_spoken":["est"],"wof:lastmodified":1596676786,"wof:name":"Tille","wof:parent_id":1713313837,"wof:placetype":"locality","wof:repo":"whosonfirst-data-admin-ee","wof:superseded_by":[],"wof:supersedes":[],"wof:tags":[]},"bbox":[26.91222,58.01167,26.91222,58.01167],"geometry":{"coordinates":[26.91222,58.01167],"type":"Point"}}