{"id":1360171767,"type":"Feature","properties":{"edtf:cessation":"uuuu","edtf:inception":"uuuu","geom:area":0,"geom:area_square_m":0,"geom:bbox":"27.47444,58.02111,27.47444,58.02111","geom:latitude":58.02111,"geom:longitude":27.47444,"gn:admin1_code":"21.0","gn:admin2_code":"732.0","gn:admin3_code":"2512.0","gn:asciiname":"Lepiku","gn:country_code":"EE","gn:dem":39,"gn:feature_class":"P","gn:feature_code":"PPL","gn:geonameid":8619293,"gn:latitude":58.02111,"gn:longitude":27.47444,"gn:modification_date":"2017-11-25","gn:name":"Lepiku","gn:population":0,"gn:timezone":"Europe/Tallinn","iso:country":"EE","lbl:bbox":"27.45444,58.00111,27.49444,58.04111","lbl:max_zoom":18,"lbl:min_zoom":13.5,"mz:hierarchy_label":1,"mz:is_current":1,"mz:min_zoom":12,"name:deu_x_preferred":["Lepiku"],"name:est_x_preferred":["Lepiku"],"name:pol_x_preferred":["Lepiku"],"name:swe_x_preferred":["Lepiku"],"name:ukr_x_preferred":["Лепіку"],"name:vol_x_preferred":["Lepiku"],"src:geom":"geonames","wof:belongsto":[85682955,102191581,1713315961,85633135,1713305631],"wof:breaches":[],"wof:concordances":{"gn:id":8619293},"wof:country":"EE","wof:geomhash":"faced885308fa5d5606fe2421bb836fe","wof:hierarchy":[{"continent_id":102191581,"country_id":85633135,"county_id":1713305631,"localadmin_id":1713315961,"locality_id":1360171767,"region_id":85682955}],"wof:id":1360171767,"wof:lang_x_official":["est"],"wof:lang_x_spoken":["est"],"wof:lastmodified":1596663694,"wof:name":"Lepiku","wof:parent_id":1713315961,"wof:placetype":"locality","wof:repo":"whosonfirst-data-admin-ee","wof:superseded_by":[],"wof:supersedes":[],"wof:tags":[]},"bbox":[27.47444,58.02111,27.47444,58.02111],"geometry":{"coordinates":[27.47444,58.02111],"type":"Point"}}