{"id":1343467579,"type":"Feature","properties":{"edtf:cessation":"uuuu","edtf:inception":"uuuu","geom:area":0,"geom:area_square_m":0,"geom:bbox":"22.5561,58.96746,22.5561,58.96746","geom:latitude":58.96746,"geom:longitude":22.5561,"gn:admin1_code":"2.0","gn:admin2_code":"205.0","gn:admin3_code":"1788.0","gn:asciiname":"Heigi","gn:country_code":"EE","gn:dem":12,"gn:feature_class":"P","gn:feature_code":"PPL","gn:geonameid":592158,"gn:latitude":58.96746,"gn:longitude":22.5561,"gn:modification_date":"2017-11-25","gn:name":"Heigi","gn:population":0,"gn:timezone":"Europe/Tallinn","iso:country":"EE","lbl:bbox":"22.5361,58.94746,22.5761,58.98746","lbl:max_zoom":18,"lbl:min_zoom":13.5,"mz:hierarchy_label":1,"mz:is_current":1,"mz:min_zoom":12,"name:deu_x_preferred":["Heigi"],"name:est_x_preferred":["Heigi"],"name:hye_x_preferred":["Հեիգի"],"name:nld_x_preferred":["Heigi"],"name:pol_x_preferred":["Heigi"],"name:spa_x_preferred":["Heigi"],"name:und_x_variant":["Kheygi"],"name:vol_x_preferred":["Heigi"],"src:geom":"geonames","wof:belongsto":[85682989,102191581,1713310639,85633135,1713305629],"wof:breaches":[],"wof:concordances":{"gn:id":592158,"wk:page":"Heigi"},"wof:coterminous":[1713310639],"wof:country":"EE","wof:geomhash":"7d279e21a88b0192e6c8d4c02cfd3942","wof:hierarchy":[{"continent_id":102191581,"country_id":85633135,"county_id":1713305629,"localadmin_id":1713310639,"locality_id":1343467579,"region_id":85682989}],"wof:id":1343467579,"wof:lang_x_official":["est"],"wof:lang_x_spoken":["est"],"wof:lastmodified":1596670010,"wof:name":"Heigi","wof:parent_id":1713310639,"wof:placetype":"locality","wof:repo":"whosonfirst-data-admin-ee","wof:superseded_by":[],"wof:supersedes":[],"wof:tags":[]},"bbox":[22.5561,58.96746,22.5561,58.96746],"geometry":{"coordinates":[22.5561,58.96746],"type":"Point"}}