{"id":1276525999,"type":"Feature","properties":{"edtf:cessation":"uuuu","edtf:inception":"uuuu","geom:area":0,"geom:area_square_m":0,"geom:bbox":"23.72028,58.475,23.72028,58.475","geom:latitude":58.475,"geom:longitude":23.72028,"gn:admin1_code":"11.0","gn:admin2_code":"430.0","gn:admin3_code":"5530.0","gn:asciiname":"Nomme","gn:country_code":"EE","gn:dem":31,"gn:feature_class":"P","gn:feature_code":"PPL","gn:geonameid":589966,"gn:latitude":58.475,"gn:longitude":23.72028,"gn:modification_date":"2017-11-25","gn:name":"Nõmme","gn:population":0,"gn:timezone":"Europe/Tallinn","iso:country":"EE","lbl:bbox":"23.70028,58.455,23.74028,58.495","lbl:max_zoom":18,"lbl:min_zoom":13.5,"mz:hierarchy_label":1,"mz:is_current":1,"mz:min_zoom":12,"name:est_x_preferred":["Nõmme"],"name:hye_x_preferred":["Նիմե"],"name:pol_x_preferred":["Nõmme"],"name:spa_x_preferred":["Nõmme"],"name:und_x_variant":["Nymme"],"name:vol_x_preferred":["Nõmme"],"src:geom":"geonames","wof:belongsto":[85683001,102191581,1713309027,85633135,1713305721],"wof:breaches":[],"wof:concordances":{"gn:id":589966,"wk:page":"N%C3%B5mme%2C_P%C3%A4rnu_County"},"wof:coterminous":[1713309027],"wof:country":"EE","wof:geomhash":"bcd2145b9635eae76de34808271bfee9","wof:hierarchy":[{"continent_id":102191581,"country_id":85633135,"county_id":1713305721,"localadmin_id":1713309027,"locality_id":1276525999,"region_id":85683001}],"wof:id":1276525999,"wof:lang_x_official":["est"],"wof:lang_x_spoken":["est"],"wof:lastmodified":1596661694,"wof:name":"Nomme","wof:parent_id":1713309027,"wof:placetype":"locality","wof:repo":"whosonfirst-data-admin-ee","wof:superseded_by":[],"wof:supersedes":[],"wof:tags":[]},"bbox":[23.72028,58.475,23.72028,58.475],"geometry":{"coordinates":[23.72028,58.475],"type":"Point"}}