{"id":1242673095,"type":"Feature","properties":{"edtf:cessation":"uuuu","edtf:inception":"uuuu","geom:area":0,"geom:area_square_m":0,"geom:bbox":"26.26944,59.28361,26.26944,59.28361","geom:latitude":59.28361,"geom:longitude":26.26944,"gn:admin1_code":"8.0","gn:admin2_code":"661.0","gn:admin3_code":"2332.0","gn:asciiname":"Jaerni","gn:country_code":"EE","gn:dem":123,"gn:feature_class":"P","gn:feature_code":"PPL","gn:geonameid":591971,"gn:latitude":59.28361,"gn:longitude":26.26944,"gn:modification_date":"2017-11-25","gn:name":"Järni","gn:population":0,"gn:timezone":"Europe/Tallinn","iso:country":"EE","lbl:bbox":"26.24944,59.26361,26.28944,59.30361","lbl:max_zoom":18,"lbl:min_zoom":13.5,"mz:hierarchy_label":1,"mz:is_current":1,"mz:min_zoom":12,"name:est_x_preferred":["Järni"],"name:fra_x_preferred":["Järni"],"name:hye_x_preferred":["Եռնի"],"name:und_x_variant":["Yarni"],"name:urd_x_preferred":["جارنی"],"name:vol_x_preferred":["Järni"],"src:geom":"geonames","wof:belongsto":[85683049,102191581,1713314591,85633135,1713305719],"wof:breaches":[],"wof:concordances":{"gn:id":591971,"wk:page":"J%C3%A4rni"},"wof:coterminous":[1713314591],"wof:country":"EE","wof:geomhash":"621f2e6b45f2972c14016f8b3bab399a","wof:hierarchy":[{"continent_id":102191581,"country_id":85633135,"county_id":1713305719,"localadmin_id":1713314591,"locality_id":1242673095,"region_id":85683049}],"wof:id":1242673095,"wof:lang_x_official":["est"],"wof:lang_x_spoken":["est"],"wof:lastmodified":1596676669,"wof:name":"Jaerni","wof:parent_id":1713314591,"wof:placetype":"locality","wof:repo":"whosonfirst-data-admin-ee","wof:superseded_by":[],"wof:supersedes":[],"wof:tags":[]},"bbox":[26.26944,59.28361,26.26944,59.28361],"geometry":{"coordinates":[26.26944,59.28361],"type":"Point"}}