{"id":1126003931,"type":"Feature","properties":{"edtf:cessation":"uuuu","edtf:inception":"uuuu","geom:area":0,"geom:area_square_m":0,"geom:bbox":"24.76139,58.93861,24.76139,58.93861","geom:latitude":58.93861,"geom:longitude":24.76139,"gn:country":"EE","gn:fcode":"PPL","gn:population":301,"iso:country":"EE","lbl:bbox":"24.74139,58.91861,24.78139,58.95861","lbl:latitude":58.93861,"lbl:longitude":24.76139,"lbl:max_zoom":17,"lbl:min_zoom":12.5,"mz:hierarchy_label":1,"mz:is_current":1,"mz:min_zoom":11,"mz:note":"Quattroshapes Point Gazetteer import 20170519","name:ceb_x_preferred":["Raikküla vald"],"name:ceb_x_variant":["Raikküla"],"name:ces_x_preferred":["Raikküla"],"name:eng_x_preferred":["Raikküla Parish"],"name:est_x_preferred":["Raikküla vald"],"name:est_x_variant":["Raikküla"],"name:fas_x_preferred":["دهستان رایکولا"],"name:fra_x_preferred":["Commune de Raikküla"],"name:fra_x_variant":["Raikküla"],"name:hye_x_preferred":["Ռաիկյուլա"],"name:kat_x_preferred":["რაიკიულის მუნიციპალიტეტი"],"name:nor_x_preferred":["Raikküla kommune"],"name:pol_x_preferred":["Gmina Raikküla"],"name:pol_x_variant":["Raikküla"],"name:ron_x_preferred":["Comuna Raikküla"],"name:rus_x_preferred":["Райккюла"],"name:sco_x_preferred":["Raikküla Pairish"],"name:sco_x_variant":["Raikküla"],"name:spa_x_preferred":["Raikküla"],"name:swe_x_preferred":["Raikküla"],"name:ukr_x_preferred":["Райккюла"],"name:und_x_variant":["Myza Raykkyula"],"name:vol_x_preferred":["Raikküla"],"qs_pg:aaroncc":"EE","qs_pg:gn_country":"EE","qs_pg:gn_fcode":"PPL","qs_pg:gn_id":589179,"qs_pg:gn_pop":301,"qs_pg:name":"Raikküla","qs_pg:name_adm0":"Eesti","qs_pg:name_adm1":"Raplamaa","qs_pg:photos_9k":1,"qs_pg:photos_9r":1,"qs_pg:photos_all":4,"qs_pg:photos_sr":0,"qs_pg:pop_sr":2,"qs_pg:qs_id":915935,"qs_pg:qs_pg_placetype":"locality","qs_pg:qs_pg_placetype_gp":"Town","qs_pg:woe_adm0":23424805,"qs_pg:woe_id":845014,"src:geom":"qs_pg","src:lbl_centroid":"qs_pg","src:population":"geonames","woe:adm0_id":23424805,"woe:name_adm0":"Eesti","woe:name_adm1":"Raplamaa","woe:placetype":"Town","wof:belongsto":[85683013,102191581,1713311473,85633135,1713305711],"wof:breaches":[],"wof:concordances":{"gn:id":589179,"gp:id":845014,"qs_pg:id":915935},"wof:coterminous":[1713311473],"wof:country":"EE","wof:created":1497299818,"wof:geomhash":"8d9948f7ad7cd97ad581f3e1e3abf2ee","wof:hierarchy":[{"continent_id":102191581,"country_id":85633135,"county_id":1713305711,"localadmin_id":1713311473,"locality_id":1126003931,"region_id":85683013}],"wof:id":1126003931,"wof:lang_x_official":["est"],"wof:lang_x_spoken":["est"],"wof:lastmodified":1596676731,"wof:name":"Raikküla","wof:parent_id":1713311473,"wof:placetype":"locality","wof:population":301,"wof:population_rank":2,"wof:repo":"whosonfirst-data-admin-ee","wof:superseded_by":[],"wof:supersedes":[],"wof:tags":[]},"bbox":[24.76139,58.93861,24.76139,58.93861],"geometry":{"coordinates":[24.76139,58.93861],"type":"Point"}}