{"id":1327152187,"type":"Feature","properties":{"edtf:cessation":"uuuu","edtf:inception":"uuuu","geom:area":0,"geom:area_square_m":0,"geom:bbox":"24.37083,59.16444,24.37083,59.16444","geom:latitude":59.16444,"geom:longitude":24.37083,"gn:admin1_code":"1.0","gn:admin2_code":"726.0","gn:admin3_code":"6308.0","gn:asciiname":"Pohla","gn:cc2":"EE","gn:country_code":"EE","gn:dem":53,"gn:feature_class":"P","gn:feature_code":"PPL","gn:geonameid":589401,"gn:latitude":59.16444,"gn:longitude":24.37083,"gn:modification_date":"2017-11-25","gn:name":"Pohla","gn:population":0,"gn:timezone":"Europe/Tallinn","iso:country":"EE","lbl:bbox":"24.35083,59.14444,24.39083,59.18444","lbl:max_zoom":18,"lbl:min_zoom":13.5,"mz:hierarchy_label":1,"mz:is_current":1,"mz:min_zoom":12,"name:est_x_preferred":["Pohla"],"name:fra_x_preferred":["Pohla"],"name:hye_x_preferred":["Պոհլա"],"name:pol_x_preferred":["Pohla"],"name:sco_x_preferred":["Pohla"],"name:spa_x_preferred":["Pohla"],"name:ukr_x_preferred":["Погла"],"name:und_x_variant":["Pokhla"],"name:vol_x_preferred":["Pohla"],"src:geom":"geonames","wof:belongsto":[85683055,102191581,1713307817,85633135,1713305739],"wof:breaches":[],"wof:concordances":{"gn:id":589401,"wk:page":"Pohla%2C_Estonia"},"wof:coterminous":[1713307817],"wof:country":"EE","wof:geomhash":"d09dd36dd6735430675d804fda1b792d","wof:hierarchy":[{"continent_id":102191581,"country_id":85633135,"county_id":1713305739,"localadmin_id":1713307817,"locality_id":1327152187,"region_id":85683055}],"wof:id":1327152187,"wof:lang_x_official":["est"],"wof:lang_x_spoken":["est"],"wof:lastmodified":1596663248,"wof:name":"Pohla","wof:parent_id":1713307817,"wof:placetype":"locality","wof:repo":"whosonfirst-data-admin-ee","wof:superseded_by":[],"wof:supersedes":[],"wof:tags":[]},"bbox":[24.37083,59.16444,24.37083,59.16444],"geometry":{"coordinates":[24.37083,59.16444],"type":"Point"}}