{"id":1209494557,"type":"Feature","properties":{"edtf:cessation":"uuuu","edtf:inception":"uuuu","geom:area":0,"geom:area_square_m":0,"geom:bbox":"24.91417,59.17,24.91417,59.17","geom:latitude":59.17,"geom:longitude":24.91417,"gn:admin1_code":"13.0","gn:admin2_code":"317.0","gn:admin3_code":"5854.0","gn:asciiname":"Dzungli","gn:country_code":"EE","gn:dem":72,"gn:feature_class":"P","gn:feature_code":"PPL","gn:geonameid":8619040,"gn:latitude":59.17,"gn:longitude":24.91417,"gn:modification_date":"2017-11-25","gn:name":"Džungli","gn:population":0,"gn:timezone":"Europe/Tallinn","iso:country":"EE","lbl:bbox":"24.89417,59.15,24.93417,59.19","lbl:max_zoom":18,"lbl:min_zoom":13.5,"mz:hierarchy_label":1,"mz:is_current":1,"mz:min_zoom":12,"name:und_x_variant":["Džungli","Сундла"],"src:geom":"geonames","wof:belongsto":[85683013,102191581,1713314405,85633135,1713305707],"wof:breaches":[],"wof:concordances":{"gn:id":8619040},"wof:country":"EE","wof:geomhash":"0a7f21369f9c470ec93d6cfdd7e8d34a","wof:hierarchy":[{"continent_id":102191581,"country_id":85633135,"county_id":1713305707,"localadmin_id":1713314405,"locality_id":1209494557,"region_id":85683013}],"wof:id":1209494557,"wof:lang_x_official":["est"],"wof:lang_x_spoken":["est"],"wof:lastmodified":1596677035,"wof:name":"Dzungli","wof:parent_id":1713314405,"wof:placetype":"locality","wof:repo":"whosonfirst-data-admin-ee","wof:superseded_by":[],"wof:supersedes":[],"wof:tags":[]},"bbox":[24.91417,59.17,24.91417,59.17],"geometry":{"coordinates":[24.91417,59.17],"type":"Point"}}