{"id":1360175461,"type":"Feature","properties":{"edtf:cessation":"uuuu","edtf:inception":"uuuu","geom:area":0,"geom:area_square_m":0,"geom:bbox":"26.56056,59.29306,26.56056,59.29306","geom:latitude":59.29306,"geom:longitude":26.56056,"gn:admin1_code":"8.0","gn:admin2_code":"901.0","gn:admin3_code":"5465.0","gn:asciiname":"Valgesoo","gn:country_code":"EE","gn:dem":93,"gn:feature_class":"P","gn:feature_code":"PPL","gn:geonameid":587866,"gn:latitude":59.29306,"gn:longitude":26.56056,"gn:modification_date":"2017-11-25","gn:name":"Valgesoo","gn:population":0,"gn:timezone":"Europe/Tallinn","iso:country":"EE","lbl:bbox":"26.54056,59.27306,26.58056,59.31306","lbl:max_zoom":18,"lbl:min_zoom":13.5,"mz:hierarchy_label":1,"mz:is_current":1,"mz:min_zoom":12,"name:est_x_preferred":["Valgesoo küla"],"name:hye_x_preferred":["Վալգեսոո"],"name:nld_x_preferred":["Valgesoo"],"name:spa_x_preferred":["Valgesoo"],"name:ukr_x_preferred":["Валгесоо"],"name:und_x_variant":["Valageso"],"name:vol_x_preferred":["Valgesoo küla"],"src:geom":"geonames","wof:belongsto":[85683049,102191581,1713308061,85633135,1713305771],"wof:breaches":[],"wof:concordances":{"gn:id":587866},"wof:country":"EE","wof:geomhash":"df282b1a74fef75ac55eda1220ca7ace","wof:hierarchy":[{"continent_id":102191581,"country_id":85633135,"county_id":1713305771,"localadmin_id":1713308061,"locality_id":1360175461,"region_id":85683049}],"wof:id":1360175461,"wof:lang_x_official":["est"],"wof:lang_x_spoken":["est"],"wof:lastmodified":1596677958,"wof:name":"Valgesoo","wof:parent_id":1713308061,"wof:placetype":"locality","wof:repo":"whosonfirst-data-admin-ee","wof:superseded_by":[],"wof:supersedes":[],"wof:tags":[]},"bbox":[26.56056,59.29306,26.56056,59.29306],"geometry":{"coordinates":[26.56056,59.29306],"type":"Point"}}