{"id":1327133629,"type":"Feature","properties":{"edtf:cessation":"uuuu","edtf:inception":"uuuu","geom:area":0,"geom:area_square_m":0,"geom:bbox":"26.72556,58.84556,26.72556,58.84556","geom:latitude":58.84556,"geom:longitude":26.72556,"gn:admin1_code":"5.0","gn:admin2_code":"247.0","gn:admin3_code":"5548.0","gn:asciiname":"Naeduvere","gn:country_code":"EE","gn:dem":80,"gn:feature_class":"P","gn:feature_code":"PPL","gn:geonameid":793375,"gn:latitude":58.84556,"gn:longitude":26.72556,"gn:modification_date":"2017-11-25","gn:name":"Näduvere","gn:population":0,"gn:timezone":"Europe/Tallinn","iso:country":"EE","lbl:bbox":"26.70556,58.82556,26.74556,58.86556","lbl:max_zoom":18,"lbl:min_zoom":13.5,"mz:hierarchy_label":1,"mz:is_current":1,"mz:min_zoom":12,"src:geom":"geonames","wof:belongsto":[85683009,102191581,1713312273,85633135,1713305767],"wof:breaches":[],"wof:concordances":{"gn:id":793375},"wof:coterminous":[1713312273],"wof:country":"EE","wof:geomhash":"94e2019d37fc0782a068615d527f4707","wof:hierarchy":[{"continent_id":102191581,"country_id":85633135,"county_id":1713305767,"localadmin_id":1713312273,"locality_id":1327133629,"region_id":85683009}],"wof:id":1327133629,"wof:lang_x_official":["est"],"wof:lang_x_spoken":["est"],"wof:lastmodified":1596676583,"wof:name":"Naeduvere","wof:parent_id":1713312273,"wof:placetype":"locality","wof:repo":"whosonfirst-data-admin-ee","wof:superseded_by":[],"wof:supersedes":[],"wof:tags":[]},"bbox":[26.72556,58.84556,26.72556,58.84556],"geometry":{"coordinates":[26.72556,58.84556],"type":"Point"}}