{"id":1192982993,"type":"Feature","properties":{"edtf:cessation":"uuuu","edtf:inception":"uuuu","geom:area":0,"geom:area_square_m":0,"geom:bbox":"26.6275,57.75833,26.6275,57.75833","geom:latitude":57.75833,"geom:longitude":26.6275,"gn:admin1_code":"21.0","gn:admin2_code":"142.0","gn:admin3_code":"4427.0","gn:asciiname":"Litsmetsa","gn:country_code":"EE","gn:dem":80,"gn:feature_class":"P","gn:feature_code":"PPL","gn:geonameid":590589,"gn:latitude":57.75833,"gn:longitude":26.6275,"gn:modification_date":"2017-11-25","gn:name":"Litsmetsa","gn:population":0,"gn:timezone":"Europe/Tallinn","iso:country":"EE","lbl:bbox":"26.6075,57.73833,26.6475,57.77833","lbl:max_zoom":18,"lbl:min_zoom":13.5,"mz:hierarchy_label":1,"mz:is_current":1,"mz:min_zoom":12,"name:est_x_preferred":["Litsmetsa"],"name:hye_x_preferred":["Լիցմեցա"],"name:pol_x_preferred":["Litsmetsa"],"name:sco_x_preferred":["Litsmetsa"],"name:spa_x_preferred":["Litsmetsa"],"name:ukr_x_preferred":["Літсметса"],"name:vol_x_preferred":["Litsmetsa"],"src:geom":"geonames","wof:belongsto":[85682937,102191581,1713311065,85633135,1713305795],"wof:breaches":[],"wof:concordances":{"gn:id":590589,"wk:page":"Litsmetsa"},"wof:coterminous":[1713311065],"wof:country":"EE","wof:geomhash":"aa21d097689954d4a034f2ffd8d66f66","wof:hierarchy":[{"continent_id":102191581,"country_id":85633135,"county_id":1713305795,"localadmin_id":1713311065,"locality_id":1192982993,"region_id":85682937}],"wof:id":1192982993,"wof:lang_x_official":["est"],"wof:lang_x_spoken":["est"],"wof:lastmodified":1596677019,"wof:name":"Litsmetsa","wof:parent_id":1713311065,"wof:placetype":"locality","wof:repo":"whosonfirst-data-admin-ee","wof:superseded_by":[],"wof:supersedes":[],"wof:tags":[]},"bbox":[26.6275,57.75833,26.6275,57.75833],"geometry":{"coordinates":[26.6275,57.75833],"type":"Point"}}