{"id":1125987821,"type":"Feature","properties":{"edtf:cessation":"uuuu","edtf:inception":"uuuu","geom:area":0,"geom:area_square_m":0,"geom:bbox":"25.03333,58.43333,25.03333,58.43333","geom:latitude":58.43333,"geom:longitude":25.03333,"gn:country":"EE","gn:fcode":"PPL","gn:population":0,"iso:country":"EE","lbl:bbox":"25.01333,58.41333,25.05333,58.45333","lbl:latitude":58.43333,"lbl:longitude":25.03333,"lbl:max_zoom":18,"lbl:min_zoom":13.5,"mz:hierarchy_label":1,"mz:is_current":1,"mz:min_zoom":12,"mz:note":"Quattroshapes Point Gazetteer import 20170519","name:und_x_variant":["Kyrtsi-Tyrama"],"qs_pg:aaroncc":"EE","qs_pg:gn_country":"EE","qs_pg:gn_fcode":"PPL","qs_pg:gn_id":591093,"qs_pg:gn_pop":0,"qs_pg:name":"Tõramaa","qs_pg:name_adm0":"Eesti","qs_pg:name_adm1":"Viljandimaa","qs_pg:photos":305,"qs_pg:photos_1k":62,"qs_pg:photos_9k":1,"qs_pg:photos_9r":5,"qs_pg:photos_all":305,"qs_pg:photos_sr":5,"qs_pg:pop_sr":0,"qs_pg:qs_id":278229,"qs_pg:qs_pg_placetype":"locality","qs_pg:qs_pg_placetype_gp":"Town","qs_pg:woe_adm0":23424805,"qs_pg:woe_id":845916,"src:geom":"qs_pg","src:lbl_centroid":"qs_pg","woe:adm0_id":23424805,"woe:name_adm0":"Eesti","woe:name_adm1":"Viljandimaa","woe:placetype":"Town","wof:belongsto":[85682985,102191581,1713314847,85633135,1713305735],"wof:breaches":[],"wof:concordances":{"gn:id":591093,"gp:id":845916,"qs_pg:id":278229},"wof:country":"EE","wof:created":1497298898,"wof:geomhash":"a5e80bbd6f941791832e94c647bc5223","wof:hierarchy":[{"continent_id":102191581,"country_id":85633135,"county_id":1713305735,"localadmin_id":1713314847,"locality_id":1125987821,"region_id":85682985}],"wof:id":1125987821,"wof:lang_x_official":["est"],"wof:lang_x_spoken":["est"],"wof:lastmodified":1596663464,"wof:name":"Tõramaa","wof:parent_id":1713314847,"wof:placetype":"locality","wof:repo":"whosonfirst-data-admin-ee","wof:superseded_by":[],"wof:supersedes":[],"wof:tags":[]},"bbox":[25.03333,58.43333,25.03333,58.43333],"geometry":{"coordinates":[25.03333,58.43333],"type":"Point"}}