{"id":1259370931,"type":"Feature","properties":{"edtf:cessation":"uuuu","edtf:inception":"uuuu","geom:area":0,"geom:area_square_m":0,"geom:bbox":"25.04722,58.17444,25.04722,58.17444","geom:latitude":58.17444,"geom:longitude":25.04722,"gn:admin1_code":"11.0","gn:admin2_code":"712.0","gn:admin3_code":"9652.0","gn:asciiname":"Vaeljakuela","gn:country_code":"EE","gn:dem":68,"gn:feature_class":"P","gn:feature_code":"PPL","gn:geonameid":587843,"gn:latitude":58.17444,"gn:longitude":25.04722,"gn:modification_date":"2017-11-25","gn:name":"Väljaküla","gn:population":0,"gn:timezone":"Europe/Tallinn","iso:country":"EE","lbl:bbox":"25.02722,58.15444,25.06722,58.19444","lbl:max_zoom":18,"lbl:min_zoom":13.5,"mz:hierarchy_label":1,"mz:is_current":1,"mz:min_zoom":12,"name:und_x_variant":["Vyal’yakyula","Väljaküla"],"src:geom":"geonames","wof:belongsto":[85682981,102191581,1713309531,85633135,1713305705],"wof:breaches":[],"wof:concordances":{"gn:id":587843},"wof:coterminous":[1713309531],"wof:country":"EE","wof:geomhash":"1db9eef8c8de3c664f6871ac6cf98080","wof:hierarchy":[{"continent_id":102191581,"country_id":85633135,"county_id":1713305705,"localadmin_id":1713309531,"locality_id":1259370931,"region_id":85682981}],"wof:id":1259370931,"wof:lang_x_official":["est"],"wof:lang_x_spoken":["est"],"wof:lastmodified":1596677733,"wof:name":"Vaeljakuela","wof:parent_id":1713309531,"wof:placetype":"locality","wof:repo":"whosonfirst-data-admin-ee","wof:superseded_by":[],"wof:supersedes":[],"wof:tags":[]},"bbox":[25.04722,58.17444,25.04722,58.17444],"geometry":{"coordinates":[25.04722,58.17444],"type":"Point"}}