{"id":1259674423,"type":"Feature","properties":{"edtf:cessation":"uuuu","edtf:inception":"uuuu","geom:area":0,"geom:area_square_m":0,"geom:bbox":"26.6275,58.98611,26.6275,58.98611","geom:latitude":58.98611,"geom:longitude":26.6275,"gn:admin1_code":"8.0","gn:admin2_code":"901.0","gn:admin3_code":"4589.0","gn:asciiname":"Luusika","gn:cc2":"EE","gn:country_code":"EE","gn:dem":101,"gn:feature_class":"P","gn:feature_code":"PPL","gn:geonameid":590465,"gn:latitude":58.98611,"gn:longitude":26.6275,"gn:modification_date":"2017-11-25","gn:name":"Luusika","gn:population":0,"gn:timezone":"Europe/Tallinn","iso:country":"EE","lbl:bbox":"26.6075,58.96611,26.6475,59.00611","lbl:max_zoom":18,"lbl:min_zoom":13.5,"mz:hierarchy_label":1,"mz:is_current":1,"mz:min_zoom":12,"name:est_x_preferred":["Luusika"],"name:hye_x_preferred":["Լուուսիկա"],"name:pol_x_preferred":["Luusika"],"name:und_x_variant":["Luziku","Luusiku"],"name:vol_x_preferred":["Luusika"],"src:geom":"geonames","wof:belongsto":[85683049,102191581,1713315199,85633135,1713305771],"wof:breaches":[],"wof:concordances":{"gn:id":590465,"wk:page":"Luusika"},"wof:coterminous":[1713315199],"wof:country":"EE","wof:geomhash":"61ddd45846bc8e2da8cca93d0b7ef9bb","wof:hierarchy":[{"continent_id":102191581,"country_id":85633135,"county_id":1713305771,"localadmin_id":1713315199,"locality_id":1259674423,"region_id":85683049}],"wof:id":1259674423,"wof:lang_x_official":["est"],"wof:lang_x_spoken":["est"],"wof:lastmodified":1596677959,"wof:name":"Luusika","wof:parent_id":1713315199,"wof:placetype":"locality","wof:repo":"whosonfirst-data-admin-ee","wof:superseded_by":[],"wof:supersedes":[],"wof:tags":[]},"bbox":[26.6275,58.98611,26.6275,58.98611],"geometry":{"coordinates":[26.6275,58.98611],"type":"Point"}}