{"id":1260079457,"type":"Feature","properties":{"edtf:cessation":"uuuu","edtf:inception":"uuuu","geom:area":0,"geom:area_square_m":0,"geom:bbox":"25.9125,58.75917,25.9125,58.75917","geom:latitude":58.75917,"geom:longitude":25.9125,"gn:admin1_code":"5.0","gn:admin2_code":"618.0","gn:admin3_code":"6404.0","gn:asciiname":"Metsakuela","gn:country_code":"EE","gn:dem":71,"gn:feature_class":"P","gn:feature_code":"PPL","gn:geonameid":8618487,"gn:latitude":58.75917,"gn:longitude":25.9125,"gn:modification_date":"2017-11-25","gn:name":"Metsaküla","gn:population":0,"gn:timezone":"Europe/Tallinn","iso:country":"EE","lbl:bbox":"25.8925,58.73917,25.9325,58.77917","lbl:max_zoom":18,"lbl:min_zoom":13.5,"mz:hierarchy_label":1,"mz:is_current":1,"mz:min_zoom":12,"name:und_x_variant":["Metsaküla","Lõo"],"src:geom":"geonames","wof:belongsto":[85683009,102191581,1713314409,85633135,1713305657],"wof:breaches":[],"wof:concordances":{"gn:id":8618487},"wof:country":"EE","wof:geomhash":"9e07309f0298a65b96cec7c1e63c26a7","wof:hierarchy":[{"continent_id":102191581,"country_id":85633135,"county_id":1713305657,"localadmin_id":1713314409,"locality_id":1260079457,"region_id":85683009}],"wof:id":1260079457,"wof:lang_x_official":["est"],"wof:lang_x_spoken":["est"],"wof:lastmodified":1596676500,"wof:name":"Metsakuela","wof:parent_id":1713314409,"wof:placetype":"locality","wof:repo":"whosonfirst-data-admin-ee","wof:superseded_by":[],"wof:supersedes":[],"wof:tags":[]},"bbox":[25.9125,58.75917,25.9125,58.75917],"geometry":{"coordinates":[25.9125,58.75917],"type":"Point"}}