{"id":1125909695,"type":"Feature","properties":{"edtf:cessation":"uuuu","edtf:inception":"uuuu","geom:area":0,"geom:area_square_m":0,"geom:bbox":"23.24333,58.99806,23.24333,58.99806","geom:latitude":58.99806,"geom:longitude":23.24333,"gn:country":"EE","gn:fcode":"PPL","gn:population":104,"iso:country":"EE","lbl:bbox":"23.22333,58.97806,23.26333,59.01806","lbl:latitude":58.99806,"lbl:longitude":23.24333,"lbl:max_zoom":18,"lbl:min_zoom":13,"mz:hierarchy_label":1,"mz:is_current":1,"mz:min_zoom":11,"mz:note":"Quattroshapes Point Gazetteer import 20170519","name:afr_x_preferred":["Hullo"],"name:arg_x_preferred":["Hullo"],"name:ast_x_preferred":["Hullo"],"name:bar_x_preferred":["Hullo"],"name:bos_x_preferred":["Hullo"],"name:bul_x_preferred":["Хуло"],"name:cat_x_preferred":["Hullo"],"name:ceb_x_preferred":["Hullo"],"name:ces_x_preferred":["Hullo"],"name:cym_x_preferred":["Hullo"],"name:dan_x_preferred":["Hullo"],"name:deu_x_preferred":["Hullo"],"name:eml_x_preferred":["Hullo"],"name:eng_x_preferred":["Hullo"],"name:epo_x_preferred":["Hullo"],"name:est_x_preferred":["Hullo"],"name:eus_x_preferred":["Hullo"],"name:fao_x_preferred":["Hullo"],"name:fin_x_preferred":["Hullo"],"name:fra_x_preferred":["Hullo"],"name:frr_x_preferred":["Hullo"],"name:glg_x_preferred":["Hullo"],"name:gsw_x_preferred":["Hullo"],"name:hrv_x_preferred":["Hullo"],"name:hun_x_preferred":["Hullo"],"name:hye_x_preferred":["Հուլլո"],"name:ind_x_preferred":["Hullo"],"name:isl_x_preferred":["Hullo"],"name:ita_x_preferred":["Hullo"],"name:lav_x_preferred":["Hullo"],"name:lit_x_preferred":["Hullo"],"name:ltz_x_preferred":["Hullo"],"name:min_x_preferred":["Hullo"],"name:nds_x_preferred":["Hullo"],"name:nld_x_preferred":["Hullo"],"name:nno_x_preferred":["Hullo"],"name:nob_x_preferred":["Hullo"],"name:pol_x_preferred":["Hullo"],"name:por_x_preferred":["Hullo"],"name:roh_x_preferred":["Hullo"],"name:ron_x_preferred":["Hullo"],"name:sco_x_preferred":["Hullo"],"name:slk_x_preferred":["Hullo"],"name:slv_x_preferred":["Hullo"],"name:spa_x_preferred":["Hullo"],"name:sqi_x_preferred":["Hullo"],"name:srp_x_preferred":["Хуло"],"name:swe_x_preferred":["Hullo"],"name:tur_x_preferred":["Hullo"],"name:ukr_x_preferred":["Гулло"],"name:und_x_variant":["Khullo"],"name:vol_x_preferred":["Hullo"],"name:zho_x_preferred":["胡洛"],"qs_pg:aaroncc":"EE","qs_pg:gn_country":"EE","qs_pg:gn_fcode":"PPL","qs_pg:gn_id":592091,"qs_pg:gn_pop":104,"qs_pg:name":"Hullo","qs_pg:name_adm0":"Eesti","qs_pg:name_adm1":"Läänemaa","qs_pg:photos_9k":1,"qs_pg:photos_9r":2,"qs_pg:photos_all":36,"qs_pg:photos_sr":0,"qs_pg:pop_sr":1,"qs_pg:qs_id":1284455,"qs_pg:qs_pg_placetype":"locality","qs_pg:qs_pg_placetype_gp":"Town","qs_pg:woe_adm0":23424805,"qs_pg:woe_id":842285,"src:geom":"qs_pg","src:lbl_centroid":"qs_pg","src:population":"geonames","woe:adm0_id":23424805,"woe:name_adm0":"Eesti","woe:name_adm1":"Läänemaa","woe:placetype":"Town","wof:belongsto":[85683001,102191581,1713307217,85633135,1713305639],"wof:breaches":[],"wof:concordances":{"gn:id":592091,"gp:id":842285,"qs_pg:id":1284455,"wd:id":"Q3451126"},"wof:coterminous":[1713307217],"wof:country":"EE","wof:created":1497296100,"wof:geomhash":"acf179f5c3c1e3386d591faa7bc18b5b","wof:hierarchy":[{"continent_id":102191581,"country_id":85633135,"county_id":1713305639,"localadmin_id":1713307217,"locality_id":1125909695,"region_id":85683001}],"wof:id":1125909695,"wof:lang_x_official":["est"],"wof:lang_x_spoken":["est"],"wof:lastmodified":1596663600,"wof:name":"Hullo","wof:parent_id":1713307217,"wof:placetype":"locality","wof:population":104,"wof:population_rank":1,"wof:repo":"whosonfirst-data-admin-ee","wof:superseded_by":[],"wof:supersedes":[],"wof:tags":[]},"bbox":[23.24333,58.99806,23.24333,58.99806],"geometry":{"coordinates":[23.24333,58.99806],"type":"Point"}}