{"id":1360206143,"type":"Feature","properties":{"edtf:cessation":"uuuu","edtf:inception":"uuuu","geom:area":0,"geom:area_square_m":0,"geom:bbox":"23.83333,58.62111,23.83333,58.62111","geom:latitude":58.62111,"geom:longitude":23.83333,"gn:admin1_code":"11.0","gn:admin2_code":"430.0","gn:admin3_code":"3616.0","gn:asciiname":"Kunila","gn:cc2":"EE","gn:country_code":"EE","gn:dem":17,"gn:feature_class":"P","gn:feature_code":"PPL","gn:geonameid":590965,"gn:latitude":58.62111,"gn:longitude":23.83333,"gn:modification_date":"2017-11-25","gn:name":"Kunila","gn:population":0,"gn:timezone":"Europe/Tallinn","iso:country":"EE","lbl:bbox":"23.81333,58.60111,23.85333,58.64111","lbl:max_zoom":18,"lbl:min_zoom":13.5,"mz:hierarchy_label":1,"mz:is_current":1,"mz:min_zoom":12,"name:deu_x_preferred":["Kunila"],"name:est_x_preferred":["Kunila"],"name:hye_x_preferred":["Կունիլա"],"name:pol_x_preferred":["Kunila"],"name:spa_x_preferred":["Kunila"],"name:und_x_variant":["Kunila-Kalda"],"name:vol_x_preferred":["Kunila"],"src:geom":"geonames","wof:belongsto":[85683001,102191581,1713309617,85633135,1713305721],"wof:breaches":[],"wof:concordances":{"gn:id":590965,"wk:page":"Kunila"},"wof:coterminous":[1713309617],"wof:country":"EE","wof:geomhash":"7a3f513104144f1154bee5ee89c314d8","wof:hierarchy":[{"continent_id":102191581,"country_id":85633135,"county_id":1713305721,"localadmin_id":1713309617,"locality_id":1360206143,"region_id":85683001}],"wof:id":1360206143,"wof:lang_x_official":["est"],"wof:lang_x_spoken":["est"],"wof:lastmodified":1596661679,"wof:name":"Kunila","wof:parent_id":1713309617,"wof:placetype":"locality","wof:repo":"whosonfirst-data-admin-ee","wof:superseded_by":[],"wof:supersedes":[],"wof:tags":[]},"bbox":[23.83333,58.62111,23.83333,58.62111],"geometry":{"coordinates":[23.83333,58.62111],"type":"Point"}}