{"id":1259557617,"type":"Feature","properties":{"edtf:cessation":"uuuu","edtf:inception":"uuuu","geom:area":0,"geom:area_square_m":0,"geom:bbox":"27.04917,57.60083,27.04917,57.60083","geom:latitude":57.60083,"geom:longitude":27.04917,"gn:admin1_code":"21.0","gn:admin2_code":"698.0","gn:admin3_code":"7968.0","gn:asciiname":"Maeemurati","gn:country_code":"EE","gn:dem":206,"gn:feature_class":"P","gn:feature_code":"PPL","gn:geonameid":590404,"gn:latitude":57.60083,"gn:longitude":27.04917,"gn:modification_date":"2017-11-25","gn:name":"Mäemurati","gn:population":0,"gn:timezone":"Europe/Tallinn","iso:country":"EE","lbl:bbox":"27.02917,57.58083,27.06917,57.62083","lbl:max_zoom":18,"lbl:min_zoom":13.5,"mz:hierarchy_label":1,"mz:is_current":1,"mz:min_zoom":12,"name:est_x_preferred":["Mäe-Murati"],"name:und_x_variant":["Myaemurati","Mäemurati"],"src:geom":"geonames","wof:belongsto":[85682937,102191581,1713315047,85633135,1713305787],"wof:breaches":[],"wof:concordances":{"gn:id":590404,"wk:page":"M%C3%A4emurati"},"wof:country":"EE","wof:geomhash":"eb705d2106803b50435377b178cb396d","wof:hierarchy":[{"continent_id":102191581,"country_id":85633135,"county_id":1713305787,"localadmin_id":1713315047,"locality_id":1259557617,"region_id":85682937}],"wof:id":1259557617,"wof:lang_x_official":["est"],"wof:lang_x_spoken":["est"],"wof:lastmodified":1596676870,"wof:name":"Maeemurati","wof:parent_id":1713315047,"wof:placetype":"locality","wof:repo":"whosonfirst-data-admin-ee","wof:superseded_by":[],"wof:supersedes":[],"wof:tags":[]},"bbox":[27.04917,57.60083,27.04917,57.60083],"geometry":{"coordinates":[27.04917,57.60083],"type":"Point"}}