{"id":1293175271,"type":"Feature","properties":{"edtf:cessation":"uuuu","edtf:inception":"uuuu","geom:area":0,"geom:area_square_m":0,"geom:bbox":"25.39222,58.50472,25.39222,58.50472","geom:latitude":58.50472,"geom:longitude":25.39222,"gn:admin1_code":"20.0","gn:admin2_code":"615.0","gn:admin3_code":"1354.0","gn:asciiname":"Arjadi","gn:cc2":"EE","gn:country_code":"EE","gn:dem":57,"gn:feature_class":"P","gn:feature_code":"PPL","gn:geonameid":592426,"gn:latitude":58.50472,"gn:longitude":25.39222,"gn:modification_date":"2017-11-25","gn:name":"Arjadi","gn:population":0,"gn:timezone":"Europe/Tallinn","iso:country":"EE","lbl:bbox":"25.37222,58.48472,25.41222,58.52472","lbl:max_zoom":18,"lbl:min_zoom":13.5,"mz:hierarchy_label":1,"mz:is_current":1,"mz:min_zoom":12,"name:und_x_variant":["Ar’yadi","Arjadi"],"src:geom":"geonames","wof:belongsto":[85682985,102191581,1713311899,85633135,1713305735],"wof:breaches":[],"wof:concordances":{"gn:id":592426},"wof:coterminous":[1713311899],"wof:country":"EE","wof:geomhash":"44a117e66771a6d48a5a65c8e49765c4","wof:hierarchy":[{"continent_id":102191581,"country_id":85633135,"county_id":1713305735,"localadmin_id":1713311899,"locality_id":1293175271,"region_id":85682985}],"wof:id":1293175271,"wof:lang_x_official":["est"],"wof:lang_x_spoken":["est"],"wof:lastmodified":1596663456,"wof:name":"Arjadi","wof:parent_id":1713311899,"wof:placetype":"locality","wof:repo":"whosonfirst-data-admin-ee","wof:superseded_by":[],"wof:supersedes":[],"wof:tags":[]},"bbox":[25.39222,58.50472,25.39222,58.50472],"geometry":{"coordinates":[25.39222,58.50472],"type":"Point"}}