{"id":1259758387,"type":"Feature","properties":{"edtf:cessation":"uuuu","edtf:inception":"uuuu","geom:area":0,"geom:area_square_m":0,"geom:bbox":"26.03,57.95194,26.03,57.95194","geom:latitude":57.95194,"geom:longitude":26.03,"gn:admin1_code":"19.0","gn:admin2_code":"824.0","gn:admin3_code":"1171.0","gn:asciiname":"Alamoisa","gn:cc2":"EE","gn:country_code":"EE","gn:dem":54,"gn:feature_class":"P","gn:feature_code":"PPL","gn:geonameid":592572,"gn:latitude":57.95194,"gn:longitude":26.03,"gn:modification_date":"2017-11-25","gn:name":"Alamõisa","gn:population":0,"gn:timezone":"Europe/Tallinn","iso:country":"EE","lbl:bbox":"26.01,57.93194,26.05,57.97194","lbl:max_zoom":18,"lbl:min_zoom":13.5,"mz:hierarchy_label":1,"mz:is_current":1,"mz:min_zoom":12,"name:und_x_variant":["Myza Ala","Ala","Alamõisa"],"src:geom":"geonames","wof:belongsto":[85682941,102191581,1713310341,85633135,1713305687],"wof:breaches":[],"wof:concordances":{"gn:id":592572},"wof:coterminous":[1713310341],"wof:country":"EE","wof:geomhash":"d1b91b49815d8218685785d1be77cce4","wof:hierarchy":[{"continent_id":102191581,"country_id":85633135,"county_id":1713305687,"localadmin_id":1713310341,"locality_id":1259758387,"region_id":85682941}],"wof:id":1259758387,"wof:lang_x_official":["est"],"wof:lang_x_spoken":["est"],"wof:lastmodified":1596661437,"wof:name":"Alamoisa","wof:parent_id":1713310341,"wof:placetype":"locality","wof:repo":"whosonfirst-data-admin-ee","wof:superseded_by":[],"wof:supersedes":[],"wof:tags":[]},"bbox":[26.03,57.95194,26.03,57.95194],"geometry":{"coordinates":[26.03,57.95194],"type":"Point"}}