{"id":1309686173,"type":"Feature","properties":{"edtf:cessation":"uuuu","edtf:inception":"uuuu","geom:area":0,"geom:area_square_m":0,"geom:bbox":"27.14139,57.80083,27.14139,57.80083","geom:latitude":57.80083,"geom:longitude":27.14139,"gn:admin1_code":"21.0","gn:admin2_code":"917.0","gn:admin3_code":"7292.0","gn:asciiname":"Saaremaa","gn:country_code":"EE","gn:dem":143,"gn:feature_class":"P","gn:feature_code":"PPL","gn:geonameid":8620169,"gn:latitude":57.80083,"gn:longitude":27.14139,"gn:modification_date":"2017-11-25","gn:name":"Saaremaa","gn:population":0,"gn:timezone":"Europe/Tallinn","iso:country":"EE","lbl:bbox":"27.12139,57.78083,27.16139,57.82083","lbl:max_zoom":18,"lbl:min_zoom":13.5,"mz:hierarchy_label":1,"mz:is_current":1,"mz:min_zoom":12,"name:afr_x_preferred":["Saaremaa"],"name:ara_x_preferred":["ساريما"],"name:aze_x_preferred":["Saaremaa"],"name:bel_x_preferred":["Саарэмаа"],"name:ben_x_preferred":["সারেমা"],"name:bre_x_preferred":["Saaremaa"],"name:bul_x_preferred":["Сааремаа"],"name:cat_x_preferred":["Saaremaa"],"name:ceb_x_preferred":["Saaremaa"],"name:ces_x_preferred":["Saaremaa"],"name:dan_x_preferred":["Øsel"],"name:deu_x_preferred":["Saaremaa"],"name:dsb_x_preferred":["Saaremaa"],"name:ell_x_preferred":["Σάαρεμαα"],"name:epo_x_preferred":["Saaremaa"],"name:est_x_preferred":["Saaremaa"],"name:eus_x_preferred":["Saaremaa"],"name:fas_x_preferred":["سارما"],"name:fin_x_preferred":["Saarenmaa"],"name:fra_x_preferred":["Saaremaa"],"name:frr_x_preferred":["Saaremaa"],"name:fry_x_preferred":["Saaremaa"],"name:heb_x_preferred":["סארמאה"],"name:hrv_x_preferred":["Saaremaa"],"name:hsb_x_preferred":["Saaremaa"],"name:hun_x_preferred":["Saaremaa"],"name:hye_x_preferred":["Սաարեմաա"],"name:ind_x_preferred":["Saaremaa"],"name:isl_x_preferred":["Saaremaa"],"name:ita_x_preferred":["Saaremaa"],"name:jpn_x_preferred":["サーレマー島"],"name:kal_x_preferred":["Saaremaa"],"name:kat_x_preferred":["საარემაა"],"name:kaz_x_preferred":["Сааремаа"],"name:kor_x_preferred":["사레마섬"],"name:lav_x_preferred":["Sāmsala"],"name:lit_x_preferred":["Sarema"],"name:lmo_x_preferred":["Saaremaa"],"name:myv_x_preferred":["Сааремаа усия"],"name:nds_x_preferred":["Ösel"],"name:nld_x_preferred":["Saaremaa"],"name:nno_x_preferred":["Saaremaa"],"name:nor_x_preferred":["Saaremaa"],"name:oss_x_preferred":["Сааремаа"],"name:pol_x_preferred":["Sarema"],"name:por_x_preferred":["Saaremaa"],"name:ron_x_preferred":["Saaremaa"],"name:rus_x_preferred":["Сааремаа"],"name:sco_x_preferred":["Saaremaa"],"name:slk_x_preferred":["Saaremaa"],"name:slv_x_preferred":["Saaremaa"],"name:spa_x_preferred":["Saaremaa"],"name:sqi_x_preferred":["Saaremaa"],"name:srp_x_preferred":["Сарема"],"name:stq_x_preferred":["Saaremaa"],"name:swe_x_preferred":["Ösel"],"name:tha_x_preferred":["ซาเรมา"],"name:tur_x_preferred":["Saaremaa"],"name:ukr_x_preferred":["Сааремаа"],"name:und_x_variant":["Saarõmaa"],"name:vie_x_preferred":["Saaremaa"],"name:zho_x_preferred":["萨雷马岛"],"src:geom":"geonames","wof:belongsto":[85682937,102191581,1713316193,85633135,1713305633],"wof:breaches":[],"wof:concordances":{"gn:id":8620169},"wof:coterminous":[1713316193],"wof:country":"EE","wof:geomhash":"30d9db177e52cde6c33807ee36f4aa30","wof:hierarchy":[{"continent_id":102191581,"country_id":85633135,"county_id":1713305633,"localadmin_id":1713316193,"locality_id":1309686173,"region_id":85682937}],"wof:id":1309686173,"wof:lang_x_official":["est"],"wof:lang_x_spoken":["est"],"wof:lastmodified":1596660394,"wof:name":"Saaremaa","wof:parent_id":1713316193,"wof:placetype":"locality","wof:repo":"whosonfirst-data-admin-ee","wof:superseded_by":[],"wof:supersedes":[],"wof:tags":[]},"bbox":[27.14139,57.80083,27.14139,57.80083],"geometry":{"coordinates":[27.14139,57.80083],"type":"Point"}}