{"id":1310280779,"type":"Feature","properties":{"edtf:cessation":"uuuu","edtf:inception":"uuuu","geom:area":0,"geom:area_square_m":0,"geom:bbox":"26.91667,58.43333,26.91667,58.43333","geom:latitude":58.43333,"geom:longitude":26.91667,"gn:admin1_code":"18.0","gn:admin2_code":"796.0","gn:admin3_code":"8123.0","gn:asciiname":"Lombi","gn:country_code":"EE","gn:dem":59,"gn:feature_class":"P","gn:feature_code":"PPL","gn:geonameid":590544,"gn:latitude":58.43333,"gn:longitude":26.91667,"gn:modification_date":"2017-11-25","gn:name":"Lombi","gn:population":0,"gn:timezone":"Europe/Tallinn","iso:country":"EE","lbl:bbox":"26.89667,58.41333,26.93667,58.45333","lbl:max_zoom":18,"lbl:min_zoom":13.5,"mz:hierarchy_label":1,"mz:is_current":1,"mz:min_zoom":12,"name:ceb_x_preferred":["Lombi"],"name:nld_x_preferred":["Lombi"],"name:swe_x_preferred":["Lombi"],"src:geom":"geonames","wof:belongsto":[85683009,102191581,1713314507,85633135,1713305659],"wof:breaches":[],"wof:concordances":{"gn:id":590544},"wof:country":"EE","wof:geomhash":"1142afc62809bae8ee542d9e4ab6a286","wof:hierarchy":[{"continent_id":102191581,"country_id":85633135,"county_id":1713305659,"localadmin_id":1713314507,"locality_id":1310280779,"region_id":85683009}],"wof:id":1310280779,"wof:lang_x_official":["est"],"wof:lang_x_spoken":["est"],"wof:lastmodified":1596676475,"wof:name":"Lombi","wof:parent_id":1713314507,"wof:placetype":"locality","wof:repo":"whosonfirst-data-admin-ee","wof:superseded_by":[],"wof:supersedes":[],"wof:tags":[]},"bbox":[26.91667,58.43333,26.91667,58.43333],"geometry":{"coordinates":[26.91667,58.43333],"type":"Point"}}