{"id":1309980113,"type":"Feature","properties":{"edtf:cessation":"uuuu","edtf:inception":"uuuu","geom:area":0,"geom:area_square_m":0,"geom:bbox":"26.50861,57.76361,26.50861,57.76361","geom:latitude":57.76361,"geom:longitude":26.50861,"gn:admin1_code":"21.0","gn:admin2_code":"142.0","gn:admin3_code":"1678.0","gn:asciiname":"Haabsaare","gn:country_code":"EE","gn:dem":93,"gn:feature_class":"P","gn:feature_code":"PPL","gn:geonameid":794437,"gn:latitude":57.76361,"gn:longitude":26.50861,"gn:modification_date":"2017-11-25","gn:name":"Haabsaare","gn:population":0,"gn:timezone":"Europe/Tallinn","iso:country":"EE","lbl:bbox":"26.48861,57.74361,26.52861,57.78361","lbl:max_zoom":18,"lbl:min_zoom":13.5,"mz:hierarchy_label":1,"mz:is_current":1,"mz:min_zoom":12,"name:est_x_preferred":["Haabsaare"],"name:hye_x_preferred":["Հաաբսաառե"],"name:pol_x_preferred":["Haabsaare"],"name:sco_x_preferred":["Haabsaare"],"name:spa_x_preferred":["Haabsaare"],"name:ukr_x_preferred":["Хаабсааре"],"name:urd_x_preferred":["ہابسارے"],"name:vol_x_preferred":["Haabsaare"],"src:geom":"geonames","wof:belongsto":[85682937,102191581,1713314369,85633135,1713305795],"wof:breaches":[],"wof:concordances":{"gn:id":794437,"wk:page":"Haabsaare"},"wof:coterminous":[1713314369],"wof:country":"EE","wof:geomhash":"4acde66050bd3db8101c842d7e2464ea","wof:hierarchy":[{"continent_id":102191581,"country_id":85633135,"county_id":1713305795,"localadmin_id":1713314369,"locality_id":1309980113,"region_id":85682937}],"wof:id":1309980113,"wof:lang_x_official":["est"],"wof:lang_x_spoken":["est"],"wof:lastmodified":1596677023,"wof:name":"Haabsaare","wof:parent_id":1713314369,"wof:placetype":"locality","wof:repo":"whosonfirst-data-admin-ee","wof:superseded_by":[],"wof:supersedes":[],"wof:tags":[]},"bbox":[26.50861,57.76361,26.50861,57.76361],"geometry":{"coordinates":[26.50861,57.76361],"type":"Point"}}