{"id":1125890297,"type":"Feature","properties":{"edtf:cessation":"uuuu","edtf:inception":"uuuu","geom:area":0,"geom:area_square_m":0,"geom:bbox":"25.52722,59.45861,25.52722,59.45861","geom:latitude":59.45861,"geom:longitude":25.52722,"gn:country":"EE","gn:fcode":"PPL","gn:population":112,"iso:country":"EE","lbl:bbox":"25.50722,59.43861,25.54722,59.47861","lbl:latitude":59.45861,"lbl:longitude":25.52722,"lbl:max_zoom":18,"lbl:min_zoom":13,"mz:hierarchy_label":1,"mz:is_current":1,"mz:min_zoom":11,"mz:note":"Quattroshapes Point Gazetteer import 20170519","name:ceb_x_preferred":["Kahala"],"name:eng_x_preferred":["Kahala"],"name:est_x_preferred":["Kahala"],"name:fra_x_preferred":["Kahala"],"name:hye_x_preferred":["Կահալա"],"name:nld_x_preferred":["Kahala"],"name:pol_x_preferred":["Kahala"],"name:rus_x_preferred":["Кахала"],"name:spa_x_preferred":["Kahala"],"name:und_x_variant":["Kakhala"],"name:vol_x_preferred":["Kahala"],"qs_pg:aaroncc":"EE","qs_pg:gn_country":"EE","qs_pg:gn_fcode":"PPL","qs_pg:gn_id":591767,"qs_pg:gn_pop":112,"qs_pg:name":"Kahala","qs_pg:name_adm0":"Eesti","qs_pg:name_adm1":"Harjumaa","qs_pg:photos_9k":1,"qs_pg:photos_9r":1,"qs_pg:photos_all":6,"qs_pg:photos_sr":0,"qs_pg:pop_sr":1,"qs_pg:qs_id":915678,"qs_pg:qs_pg_placetype":"locality","qs_pg:qs_pg_placetype_gp":"Town","qs_pg:woe_adm0":23424805,"qs_pg:woe_id":842598,"src:geom":"qs_pg","src:lbl_centroid":"qs_pg","src:population":"geonames","woe:adm0_id":23424805,"woe:name_adm0":"Eesti","woe:name_adm1":"Harjumaa","woe:placetype":"Town","wof:belongsto":[85683055,102191581,1713306021,85633135,1713305725],"wof:breaches":[],"wof:concordances":{"gn:id":591767,"gp:id":842598,"qs_pg:id":915678,"wd:id":"Q2347306"},"wof:coterminous":[1713306021],"wof:country":"EE","wof:created":1497295284,"wof:geomhash":"408e5763a3e9f211eb6b016e9896e6ab","wof:hierarchy":[{"continent_id":102191581,"country_id":85633135,"county_id":1713305725,"localadmin_id":1713306021,"locality_id":1125890297,"region_id":85683055}],"wof:id":1125890297,"wof:lang_x_official":["est"],"wof:lang_x_spoken":["est"],"wof:lastmodified":1596661843,"wof:name":"Kahala","wof:parent_id":1713306021,"wof:placetype":"locality","wof:population":112,"wof:population_rank":1,"wof:repo":"whosonfirst-data-admin-ee","wof:superseded_by":[],"wof:supersedes":[],"wof:tags":[]},"bbox":[25.52722,59.45861,25.52722,59.45861],"geometry":{"coordinates":[25.52722,59.45861],"type":"Point"}}