{"id":1310475559,"type":"Feature","properties":{"edtf:cessation":"uuuu","edtf:inception":"uuuu","geom:area":0,"geom:area_square_m":0,"geom:bbox":"22.22694,58.10889,22.22694,58.10889","geom:latitude":58.10889,"geom:longitude":22.22694,"gn:admin1_code":"14.0","gn:admin2_code":"714.0","gn:admin3_code":"1297.0","gn:asciiname":"Easte","gn:country_code":"EE","gn:dem":13,"gn:feature_class":"P","gn:feature_code":"PPL","gn:geonameid":592318,"gn:latitude":58.10889,"gn:longitude":22.22694,"gn:modification_date":"2017-11-25","gn:name":"Easte","gn:population":0,"gn:timezone":"Europe/Tallinn","iso:country":"EE","lbl:bbox":"22.20694,58.08889,22.24694,58.12889","lbl:max_zoom":18,"lbl:min_zoom":13.5,"mz:hierarchy_label":1,"mz:is_current":1,"mz:min_zoom":12,"name:deu_x_preferred":["Easte"],"name:est_x_preferred":["Easte"],"name:fra_x_preferred":["Easte"],"name:hye_x_preferred":["Էաստե"],"name:pol_x_preferred":["Easte"],"name:spa_x_preferred":["Easte"],"name:ukr_x_preferred":["Еасте"],"name:und_x_variant":["Baste"],"name:vol_x_preferred":["Easte"],"src:geom":"geonames","wof:belongsto":[85682947,102191581,1713307499,85633135,1713305627],"wof:breaches":[],"wof:concordances":{"gn:id":592318,"wk:page":"Easte"},"wof:coterminous":[1713307577],"wof:country":"EE","wof:geomhash":"854b2cb9c81d0d912e1c83dc4f24d122","wof:hierarchy":[{"continent_id":102191581,"country_id":85633135,"county_id":1713305627,"localadmin_id":1713307499,"locality_id":1310475559,"region_id":85682947}],"wof:id":1310475559,"wof:lang_x_official":["est"],"wof:lang_x_spoken":["est"],"wof:lastmodified":1596674947,"wof:name":"Easte","wof:parent_id":1713307499,"wof:placetype":"locality","wof:repo":"whosonfirst-data-admin-ee","wof:superseded_by":[],"wof:supersedes":[],"wof:tags":[]},"bbox":[22.22694,58.10889,22.22694,58.10889],"geometry":{"coordinates":[22.22694,58.10889],"type":"Point"}}