{"id":1343549347,"type":"Feature","properties":{"edtf:cessation":"uuuu","edtf:inception":"uuuu","geom:area":0,"geom:area_square_m":0,"geom:bbox":"24.16667,58.36667,24.16667,58.36667","geom:latitude":58.36667,"geom:longitude":24.16667,"gn:admin1_code":"11.0","gn:admin2_code":"624.0","gn:admin3_code":"3746.0","gn:asciiname":"Ees-Soomra","gn:cc2":"EE","gn:country_code":"EE","gn:dem":34,"gn:feature_class":"P","gn:feature_code":"PPL","gn:geonameid":592308,"gn:latitude":58.36667,"gn:longitude":24.16667,"gn:modification_date":"2017-11-25","gn:name":"Ees-Soomra","gn:population":0,"gn:timezone":"Europe/Tallinn","iso:country":"EE","lbl:bbox":"24.14667,58.34667,24.18667,58.38667","lbl:max_zoom":18,"lbl:min_zoom":13.5,"mz:hierarchy_label":1,"mz:is_current":1,"mz:min_zoom":12,"name:und_x_variant":["Es-Somra","Ees-Soomra"],"src:geom":"geonames","wof:belongsto":[85682981,102191581,1713310473,85633135,1713305703],"wof:breaches":[],"wof:concordances":{"gn:id":592308},"wof:country":"EE","wof:geomhash":"f9bfc66bd7ff8202beb7778d5769ae52","wof:hierarchy":[{"continent_id":102191581,"country_id":85633135,"county_id":1713305703,"localadmin_id":1713310473,"locality_id":1343549347,"region_id":85682981}],"wof:id":1343549347,"wof:lang_x_official":["est"],"wof:lang_x_spoken":["est"],"wof:lastmodified":1596677703,"wof:name":"Ees-Soomra","wof:parent_id":1713310473,"wof:placetype":"locality","wof:repo":"whosonfirst-data-admin-ee","wof:superseded_by":[],"wof:supersedes":[],"wof:tags":[]},"bbox":[24.16667,58.36667,24.16667,58.36667],"geometry":{"coordinates":[24.16667,58.36667],"type":"Point"}}