{"id":1260184045,"type":"Feature","properties":{"edtf:cessation":"uuuu","edtf:inception":"uuuu","geom:area":0,"geom:area_square_m":0,"geom:bbox":"27.24056,59.35694,27.24056,59.35694","geom:latitude":59.35694,"geom:longitude":27.24056,"gn:admin1_code":"3.0","gn:admin2_code":"803.0","gn:admin3_code":"3269.0","gn:asciiname":"Kohtla-Vanakuela","gn:country_code":"EE","gn:dem":58,"gn:feature_class":"P","gn:feature_code":"PPL","gn:geonameid":8620082,"gn:latitude":59.35694,"gn:longitude":27.24056,"gn:modification_date":"2017-11-25","gn:name":"Kohtla-Vanaküla","gn:population":0,"gn:timezone":"Europe/Tallinn","iso:country":"EE","lbl:bbox":"27.22056,59.33694,27.26056,59.37694","lbl:max_zoom":18,"lbl:min_zoom":13.5,"mz:hierarchy_label":1,"mz:is_current":1,"mz:min_zoom":12,"name:und_x_variant":["Kohtla-Vanaküla","Vanaküla"],"src:geom":"geonames","wof:belongsto":[85683059,102191581,1713312997,85633135,1713305783],"wof:breaches":[],"wof:concordances":{"gn:id":8620082},"wof:country":"EE","wof:geomhash":"6579c95f338f9fd1785c02e508dcaa31","wof:hierarchy":[{"continent_id":102191581,"country_id":85633135,"county_id":1713305783,"localadmin_id":1713312997,"locality_id":1260184045,"region_id":85683059}],"wof:id":1260184045,"wof:lang_x_official":["est"],"wof:lang_x_spoken":["est"],"wof:lastmodified":1596676910,"wof:name":"Kohtla-Vanakuela","wof:parent_id":1713312997,"wof:placetype":"locality","wof:repo":"whosonfirst-data-admin-ee","wof:superseded_by":[],"wof:supersedes":[],"wof:tags":[]},"bbox":[27.24056,59.35694,27.24056,59.35694],"geometry":{"coordinates":[27.24056,59.35694],"type":"Point"}}