{"id":1326527203,"type":"Feature","properties":{"edtf:cessation":"uuuu","edtf:inception":"uuuu","geom:area":0,"geom:area_square_m":0,"geom:bbox":"25.88778,59.21056,25.88778,59.21056","geom:latitude":59.21056,"geom:longitude":25.88778,"gn:admin1_code":"8.0","gn:admin2_code":"792.0","gn:admin3_code":"7221.0","gn:asciiname":"Kuru","gn:country_code":"EE","gn:dem":99,"gn:feature_class":"P","gn:feature_code":"PPL","gn:geonameid":590906,"gn:latitude":59.21056,"gn:longitude":25.88778,"gn:modification_date":"2017-11-25","gn:name":"Kuru","gn:population":0,"gn:timezone":"Europe/Tallinn","iso:country":"EE","lbl:bbox":"25.86778,59.19056,25.90778,59.23056","lbl:max_zoom":18,"lbl:min_zoom":13.5,"mz:hierarchy_label":1,"mz:is_current":1,"mz:min_zoom":12,"name:bul_x_preferred":["Куру"],"name:cat_x_preferred":["Kuru"],"name:ceb_x_preferred":["Kuru"],"name:ces_x_preferred":["Kuru"],"name:che_x_preferred":["Куру"],"name:deu_x_preferred":["Kuru"],"name:est_x_preferred":["Kuru"],"name:fin_x_preferred":["Kuru"],"name:fra_x_preferred":["Kuru"],"name:heb_x_preferred":["קורו"],"name:hun_x_preferred":["Kuru"],"name:ind_x_preferred":["Kuru"],"name:ita_x_preferred":["Kuru"],"name:nld_x_preferred":["Kuru"],"name:rus_x_preferred":["Куру"],"name:slk_x_preferred":["Kuru"],"name:spa_x_preferred":["Kuru"],"name:srp_x_preferred":["Куру"],"name:swe_x_preferred":["Kuru"],"name:tgl_x_preferred":["Kuru"],"name:ukr_x_preferred":["Куру"],"name:vol_x_preferred":["Kuru"],"src:geom":"geonames","wof:belongsto":[85683049,102191581,1713315179,85633135,1713305761],"wof:breaches":[],"wof:concordances":{"gn:id":590906},"wof:coterminous":[1713308153],"wof:country":"EE","wof:geomhash":"14ddd8135bcebf4542f96f3c2467c64c","wof:hierarchy":[{"continent_id":102191581,"country_id":85633135,"county_id":1713305761,"localadmin_id":1713315179,"locality_id":1326527203,"region_id":85683049}],"wof:id":1326527203,"wof:lang_x_official":["est"],"wof:lang_x_spoken":["est"],"wof:lastmodified":1596676601,"wof:name":"Kuru","wof:parent_id":1713315179,"wof:placetype":"locality","wof:repo":"whosonfirst-data-admin-ee","wof:superseded_by":[],"wof:supersedes":[],"wof:tags":[]},"bbox":[25.88778,59.21056,25.88778,59.21056],"geometry":{"coordinates":[25.88778,59.21056],"type":"Point"}}