{"id":1243518799,"type":"Feature","properties":{"edtf:cessation":"uuuu","edtf:inception":"uuuu","geom:area":0,"geom:area_square_m":0,"geom:bbox":"26.59472,57.52139,26.59472,57.52139","geom:latitude":57.52139,"geom:longitude":26.59472,"gn:admin1_code":"21.0","gn:admin2_code":"698.0","gn:admin3_code":"2738.0","gn:asciiname":"Naha","gn:country_code":"EE","gn:dem":92,"gn:feature_class":"P","gn:feature_code":"PPL","gn:geonameid":590046,"gn:latitude":57.52139,"gn:longitude":26.59472,"gn:modification_date":"2017-11-25","gn:name":"Naha","gn:population":0,"gn:timezone":"Europe/Tallinn","iso:country":"EE","lbl:bbox":"26.57472,57.50139,26.61472,57.54139","lbl:max_zoom":18,"lbl:min_zoom":13.5,"mz:hierarchy_label":1,"mz:is_current":1,"mz:min_zoom":12,"name:ara_x_preferred":["ناها"],"name:ast_x_preferred":["Naha"],"name:aze_x_preferred":["Naha"],"name:bel_x_preferred":["Наха"],"name:bul_x_preferred":["Наха"],"name:cat_x_preferred":["Naha"],"name:cdo_x_preferred":["Naha-chê"],"name:ceb_x_preferred":["Naha Shi"],"name:ces_x_preferred":["Naha"],"name:deu_x_preferred":["Naha"],"name:epo_x_preferred":["Naha"],"name:est_x_preferred":["Naha"],"name:eus_x_preferred":["Naha"],"name:fas_x_preferred":["ناها"],"name:fin_x_preferred":["Naha"],"name:fra_x_preferred":["Naha"],"name:gle_x_preferred":["Naha"],"name:glg_x_preferred":["Naha"],"name:hak_x_preferred":["Naha-sṳ"],"name:heb_x_preferred":["נהה"],"name:hrv_x_preferred":["Naha"],"name:hun_x_preferred":["Naha"],"name:ind_x_preferred":["Naha"],"name:ita_x_preferred":["Naha"],"name:jpn_x_preferred":["那覇市"],"name:kat_x_preferred":["ნაჰა"],"name:kor_x_preferred":["나하시"],"name:lit_x_preferred":["Naha"],"name:mar_x_preferred":["नाहा"],"name:mlg_x_preferred":["Naha"],"name:msa_x_preferred":["Naha"],"name:myv_x_preferred":["Наха"],"name:mzn_x_preferred":["ناها"],"name:nld_x_preferred":["Naha"],"name:nor_x_preferred":["Naha"],"name:pol_x_preferred":["Naha"],"name:por_x_preferred":["Naha"],"name:que_x_preferred":["Naha"],"name:ron_x_preferred":["Naha"],"name:rus_x_preferred":["Наха"],"name:sco_x_preferred":["Naha"],"name:slk_x_preferred":["Naha"],"name:spa_x_preferred":["Naha"],"name:srp_x_preferred":["Наха"],"name:swa_x_preferred":["Naha"],"name:swe_x_preferred":["Naha"],"name:tgk_x_preferred":["Наҳа"],"name:tgl_x_preferred":["Naha"],"name:tha_x_preferred":["นาฮะ"],"name:tum_x_preferred":["Naha"],"name:tur_x_preferred":["Naha"],"name:ukr_x_preferred":["Наха"],"name:und_x_variant":["Nakha"],"name:urd_x_preferred":["ناہا"],"name:vie_x_preferred":["Naha"],"name:war_x_preferred":["Naha"],"name:zho_x_preferred":["那霸市"],"src:geom":"geonames","wof:belongsto":[85682937,102191581,1713315343,85633135,1713305787],"wof:breaches":[],"wof:concordances":{"gn:id":590046},"wof:country":"EE","wof:geomhash":"439efab3c17adcb438700fc40ad8513f","wof:hierarchy":[{"continent_id":102191581,"country_id":85633135,"county_id":1713305787,"localadmin_id":1713315343,"locality_id":1243518799,"region_id":85682937}],"wof:id":1243518799,"wof:lang_x_official":["est"],"wof:lang_x_spoken":["est"],"wof:lastmodified":1596676890,"wof:name":"Naha","wof:parent_id":1713315343,"wof:placetype":"locality","wof:repo":"whosonfirst-data-admin-ee","wof:superseded_by":[],"wof:supersedes":[],"wof:tags":[]},"bbox":[26.59472,57.52139,26.59472,57.52139],"geometry":{"coordinates":[26.59472,57.52139],"type":"Point"}}