{"id":1260292353,"type":"Feature","properties":{"edtf:cessation":"uuuu","edtf:inception":"uuuu","geom:area":0,"geom:area_square_m":0,"geom:bbox":"26.98556,59.25333,26.98556,59.25333","geom:latitude":59.25333,"geom:longitude":26.98556,"gn:admin1_code":"3.0","gn:admin2_code":"442.0","gn:admin3_code":"9200.0","gn:asciiname":"Luematu","gn:country_code":"EE","gn:dem":73,"gn:feature_class":"P","gn:feature_code":"PPL","gn:geonameid":590477,"gn:latitude":59.25333,"gn:longitude":26.98556,"gn:modification_date":"2017-11-25","gn:name":"Lümatu","gn:population":0,"gn:timezone":"Europe/Tallinn","iso:country":"EE","lbl:bbox":"26.96556,59.23333,27.00556,59.27333","lbl:max_zoom":18,"lbl:min_zoom":13.5,"mz:hierarchy_label":1,"mz:is_current":1,"mz:min_zoom":12,"name:deu_x_preferred":["Lümatu"],"name:est_x_preferred":["Lümatu"],"name:hye_x_preferred":["Լյումատու"],"name:pol_x_preferred":["Lümatu"],"name:spa_x_preferred":["Lümatu"],"name:und_x_variant":["Lyumatu"],"name:vol_x_preferred":["Lümatu"],"src:geom":"geonames","wof:belongsto":[85683059,102191581,1713311809,85633135,1713305695],"wof:breaches":[],"wof:concordances":{"gn:id":590477,"wk:page":"L%C3%BCmatu%2C_Ida-Viru_County"},"wof:coterminous":[1713313183],"wof:country":"EE","wof:geomhash":"aa68e65fd6e976d2c65e18e7ba9a23a6","wof:hierarchy":[{"continent_id":102191581,"country_id":85633135,"county_id":1713305695,"localadmin_id":1713311809,"locality_id":1260292353,"region_id":85683059}],"wof:id":1260292353,"wof:lang_x_official":["est"],"wof:lang_x_spoken":["est"],"wof:lastmodified":1596660797,"wof:name":"Luematu","wof:parent_id":1713311809,"wof:placetype":"locality","wof:repo":"whosonfirst-data-admin-ee","wof:superseded_by":[],"wof:supersedes":[],"wof:tags":[]},"bbox":[26.98556,59.25333,26.98556,59.25333],"geometry":{"coordinates":[26.98556,59.25333],"type":"Point"}}