{"id":1343335771,"type":"Feature","properties":{"edtf:cessation":"uuuu","edtf:inception":"uuuu","geom:area":0,"geom:area_square_m":0,"geom:bbox":"26.53639,57.79167,26.53639,57.79167","geom:latitude":57.79167,"geom:longitude":26.53639,"gn:admin1_code":"21.0","gn:admin2_code":"142.0","gn:admin3_code":"7714.0","gn:asciiname":"Soome","gn:country_code":"EE","gn:dem":91,"gn:feature_class":"P","gn:feature_code":"PPL","gn:geonameid":794433,"gn:latitude":57.79167,"gn:longitude":26.53639,"gn:modification_date":"2017-11-25","gn:name":"Soome","gn:population":0,"gn:timezone":"Europe/Tallinn","iso:country":"EE","lbl:bbox":"26.51639,57.77167,26.55639,57.81167","lbl:max_zoom":18,"lbl:min_zoom":13.5,"mz:hierarchy_label":1,"mz:is_current":1,"mz:min_zoom":12,"name:est_x_preferred":["Soome"],"name:hye_x_preferred":["Սոոմե"],"name:pol_x_preferred":["Soome"],"name:sco_x_preferred":["Soome"],"name:spa_x_preferred":["Soome"],"name:ukr_x_preferred":["Сооме"],"name:vol_x_preferred":["Soome"],"src:geom":"geonames","wof:belongsto":[85682937,102191581,1713310995,85633135,1713305795],"wof:breaches":[],"wof:concordances":{"gn:id":794433,"wk:page":"Soome%2C_Estonia"},"wof:coterminous":[1713310995],"wof:country":"EE","wof:geomhash":"a0e556bd24bfe3e99f3eed3062c58279","wof:hierarchy":[{"continent_id":102191581,"country_id":85633135,"county_id":1713305795,"localadmin_id":1713310995,"locality_id":1343335771,"region_id":85682937}],"wof:id":1343335771,"wof:lang_x_official":["est"],"wof:lang_x_spoken":["est"],"wof:lastmodified":1596677020,"wof:name":"Soome","wof:parent_id":1713310995,"wof:placetype":"locality","wof:repo":"whosonfirst-data-admin-ee","wof:superseded_by":[],"wof:supersedes":[],"wof:tags":[]},"bbox":[26.53639,57.79167,26.53639,57.79167],"geometry":{"coordinates":[26.53639,57.79167],"type":"Point"}}