{"id":1243032883,"type":"Feature","properties":{"edtf:cessation":"uuuu","edtf:inception":"uuuu","geom:area":0,"geom:area_square_m":0,"geom:bbox":"25.27722,58.56139,25.27722,58.56139","geom:latitude":58.56139,"geom:longitude":25.27722,"gn:admin1_code":"20.0","gn:admin2_code":"615.0","gn:admin3_code":"2754.0","gn:asciiname":"Karjasoo","gn:country_code":"EE","gn:dem":31,"gn:feature_class":"P","gn:feature_code":"PPL","gn:geonameid":793853,"gn:latitude":58.56139,"gn:longitude":25.27722,"gn:modification_date":"2017-11-25","gn:name":"Karjasoo","gn:population":0,"gn:timezone":"Europe/Tallinn","iso:country":"EE","lbl:bbox":"25.25722,58.54139,25.29722,58.58139","lbl:max_zoom":18,"lbl:min_zoom":13.5,"mz:hierarchy_label":1,"mz:is_current":1,"mz:min_zoom":12,"name:est_x_preferred":["Karjasoo"],"name:hye_x_preferred":["Կառյասոո"],"name:pol_x_preferred":["Karjasoo"],"name:spa_x_preferred":["Karjasoo"],"name:ukr_x_preferred":["Кар'ясоо"],"name:vol_x_preferred":["Karjasoo"],"src:geom":"geonames","wof:belongsto":[85682985,102191581,1713315229,85633135,1713305735],"wof:breaches":[],"wof:concordances":{"gn:id":793853,"wk:page":"Karjasoo"},"wof:coterminous":[1713315229],"wof:country":"EE","wof:geomhash":"393b49cb1792caf6bf3592b88ab26f06","wof:hierarchy":[{"continent_id":102191581,"country_id":85633135,"county_id":1713305735,"localadmin_id":1713315229,"locality_id":1243032883,"region_id":85682985}],"wof:id":1243032883,"wof:lang_x_official":["est"],"wof:lang_x_spoken":["est"],"wof:lastmodified":1596663463,"wof:name":"Karjasoo","wof:parent_id":1713315229,"wof:placetype":"locality","wof:repo":"whosonfirst-data-admin-ee","wof:superseded_by":[],"wof:supersedes":[],"wof:tags":[]},"bbox":[25.27722,58.56139,25.27722,58.56139],"geometry":{"coordinates":[25.27722,58.56139],"type":"Point"}}