{"id":1226205573,"type":"Feature","properties":{"edtf:cessation":"uuuu","edtf:inception":"uuuu","geom:area":0,"geom:area_square_m":0,"geom:bbox":"26.7075,58.20139,26.7075,58.20139","geom:latitude":58.20139,"geom:longitude":26.7075,"gn:admin1_code":"18.0","gn:admin2_code":"283.0","gn:admin3_code":"5784.0","gn:asciiname":"Paali","gn:cc2":"EE","gn:country_code":"EE","gn:dem":106,"gn:feature_class":"P","gn:feature_code":"PPL","gn:geonameid":589760,"gn:latitude":58.20139,"gn:longitude":26.7075,"gn:modification_date":"2017-11-25","gn:name":"Paali","gn:population":0,"gn:timezone":"Europe/Tallinn","iso:country":"EE","lbl:bbox":"26.6875,58.18139,26.7275,58.22139","lbl:max_zoom":18,"lbl:min_zoom":13.5,"mz:hierarchy_label":1,"mz:is_current":1,"mz:min_zoom":12,"name:est_x_preferred":["Paali"],"name:fra_x_preferred":["Paali"],"name:hye_x_preferred":["Պաալի"],"name:pol_x_preferred":["Paali"],"name:spa_x_preferred":["Paali"],"name:ukr_x_preferred":["Паалі"],"name:und_x_variant":["Pali"],"name:vol_x_preferred":["Paali"],"src:geom":"geonames","wof:belongsto":[85682995,102191581,1713308833,85633135,1713305717],"wof:breaches":[],"wof:concordances":{"gn:id":589760,"wk:page":"Paali"},"wof:coterminous":[1713308833],"wof:country":"EE","wof:geomhash":"b4c86ba592a38a30f7b7573eb16e0396","wof:hierarchy":[{"continent_id":102191581,"country_id":85633135,"county_id":1713305717,"localadmin_id":1713308833,"locality_id":1226205573,"region_id":85682995}],"wof:id":1226205573,"wof:lang_x_official":["est"],"wof:lang_x_spoken":["est"],"wof:lastmodified":1596676688,"wof:name":"Paali","wof:parent_id":1713308833,"wof:placetype":"locality","wof:repo":"whosonfirst-data-admin-ee","wof:superseded_by":[],"wof:supersedes":[],"wof:tags":[]},"bbox":[26.7075,58.20139,26.7075,58.20139],"geometry":{"coordinates":[26.7075,58.20139],"type":"Point"}}