{"id":1226521797,"type":"Feature","properties":{"edtf:cessation":"uuuu","edtf:inception":"uuuu","geom:area":0,"geom:area_square_m":0,"geom:bbox":"24.22111,58.84556,24.22111,58.84556","geom:latitude":58.84556,"geom:longitude":24.22111,"gn:admin1_code":"13.0","gn:admin2_code":"503.0","gn:admin3_code":"4554.0","gn:asciiname":"Luiste","gn:cc2":"EE","gn:country_code":"EE","gn:dem":22,"gn:feature_class":"P","gn:feature_code":"PPL","gn:geonameid":590490,"gn:latitude":58.84556,"gn:longitude":24.22111,"gn:modification_date":"2017-11-25","gn:name":"Luiste","gn:population":0,"gn:timezone":"Europe/Tallinn","iso:country":"EE","lbl:bbox":"24.20111,58.82556,24.24111,58.86556","lbl:max_zoom":18,"lbl:min_zoom":13.5,"mz:hierarchy_label":1,"mz:is_current":1,"mz:min_zoom":12,"name:est_x_preferred":["Luiste"],"name:fra_x_preferred":["Luiste"],"name:hye_x_preferred":["Լուիստե"],"name:pol_x_preferred":["Luiste"],"name:sco_x_preferred":["Luiste"],"name:spa_x_preferred":["Luiste"],"name:swe_x_preferred":["Luiste"],"name:und_x_variant":["Luyste"],"name:vol_x_preferred":["Luiste"],"src:geom":"geonames","wof:belongsto":[85683013,102191581,1713314999,85633135,1713305747],"wof:breaches":[],"wof:concordances":{"gn:id":590490,"wk:page":"Luiste"},"wof:coterminous":[1713314999],"wof:country":"EE","wof:geomhash":"d9bb7ee8040bd1f3ecd486f7d02df148","wof:hierarchy":[{"continent_id":102191581,"country_id":85633135,"county_id":1713305747,"localadmin_id":1713314999,"locality_id":1226521797,"region_id":85683013}],"wof:id":1226521797,"wof:lang_x_official":["est"],"wof:lang_x_spoken":["est"],"wof:lastmodified":1596662841,"wof:name":"Luiste","wof:parent_id":1713314999,"wof:placetype":"locality","wof:repo":"whosonfirst-data-admin-ee","wof:superseded_by":[],"wof:supersedes":[],"wof:tags":[]},"bbox":[24.22111,58.84556,24.22111,58.84556],"geometry":{"coordinates":[24.22111,58.84556],"type":"Point"}}