{"id":1243151429,"type":"Feature","properties":{"edtf:cessation":"uuuu","edtf:inception":"uuuu","geom:area":0,"geom:area_square_m":0,"geom:bbox":"24.5375,59.00944,24.5375,59.00944","geom:latitude":59.00944,"geom:longitude":24.5375,"gn:admin1_code":"13.0","gn:admin2_code":"503.0","gn:admin3_code":"7015.0","gn:asciiname":"Suurkuela","gn:country_code":"EE","gn:dem":65,"gn:feature_class":"P","gn:feature_code":"PPL","gn:geonameid":588501,"gn:latitude":59.00944,"gn:longitude":24.5375,"gn:modification_date":"2017-11-25","gn:name":"Suurküla","gn:population":0,"gn:timezone":"Europe/Tallinn","iso:country":"EE","lbl:bbox":"24.5175,58.98944,24.5575,59.02944","lbl:max_zoom":18,"lbl:min_zoom":13.5,"mz:hierarchy_label":1,"mz:is_current":1,"mz:min_zoom":12,"name:und_x_variant":["Surkyula","Suurküla"],"src:geom":"geonames","wof:belongsto":[85683013,102191581,1713311355,85633135,1713305747],"wof:breaches":[],"wof:concordances":{"gn:id":588501},"wof:country":"EE","wof:geomhash":"8087f76b228195a8662cb498e26c63c6","wof:hierarchy":[{"continent_id":102191581,"country_id":85633135,"county_id":1713305747,"localadmin_id":1713311355,"locality_id":1243151429,"region_id":85683013}],"wof:id":1243151429,"wof:lang_x_official":["est"],"wof:lang_x_spoken":["est"],"wof:lastmodified":1596662850,"wof:name":"Suurkuela","wof:parent_id":1713311355,"wof:placetype":"locality","wof:repo":"whosonfirst-data-admin-ee","wof:superseded_by":[],"wof:supersedes":[],"wof:tags":[]},"bbox":[24.5375,59.00944,24.5375,59.00944],"geometry":{"coordinates":[24.5375,59.00944],"type":"Point"}}