{"id":1226408561,"type":"Feature","properties":{"edtf:cessation":"uuuu","edtf:inception":"uuuu","geom:area":0,"geom:area_square_m":0,"geom:bbox":"26.78472,58.34028,26.78472,58.34028","geom:latitude":58.34028,"geom:longitude":26.78472,"gn:admin1_code":"18.0","gn:admin2_code":"432.0","gn:admin3_code":"9183.0","gn:asciiname":"Veibri","gn:country_code":"EE","gn:dem":36,"gn:feature_class":"P","gn:feature_code":"PPL","gn:geonameid":794111,"gn:latitude":58.34028,"gn:longitude":26.78472,"gn:modification_date":"2017-11-25","gn:name":"Veibri","gn:population":0,"gn:timezone":"Europe/Tallinn","iso:country":"EE","lbl:bbox":"26.76472,58.32028,26.80472,58.36028","lbl:max_zoom":18,"lbl:min_zoom":13.5,"mz:hierarchy_label":1,"mz:is_current":1,"mz:min_zoom":12,"name:est_x_preferred":["Veibri"],"name:fas_x_preferred":["ویبری"],"name:fra_x_preferred":["Veibri"],"name:hye_x_preferred":["Վեիբռի"],"name:nld_x_preferred":["Veibri"],"name:pol_x_preferred":["Veibri"],"name:spa_x_preferred":["Veibri"],"name:ukr_x_preferred":["Вейбрі"],"name:vol_x_preferred":["Veibri"],"src:geom":"geonames","wof:belongsto":[85682995,102191581,1713313765,85633135,1713305697],"wof:breaches":[],"wof:concordances":{"gn:id":794111,"wk:page":"Veibri"},"wof:coterminous":[1713313765],"wof:country":"EE","wof:geomhash":"315e49433e9c45763e3210edf199dacb","wof:hierarchy":[{"continent_id":102191581,"country_id":85633135,"county_id":1713305697,"localadmin_id":1713313765,"locality_id":1226408561,"region_id":85682995}],"wof:id":1226408561,"wof:lang_x_official":["est"],"wof:lang_x_spoken":["est"],"wof:lastmodified":1596660679,"wof:name":"Veibri","wof:parent_id":1713313765,"wof:placetype":"locality","wof:repo":"whosonfirst-data-admin-ee","wof:superseded_by":[],"wof:supersedes":[],"wof:tags":[]},"bbox":[26.78472,58.34028,26.78472,58.34028],"geometry":{"coordinates":[26.78472,58.34028],"type":"Point"}}