{"id":1293204615,"type":"Feature","properties":{"edtf:cessation":"uuuu","edtf:inception":"uuuu","geom:area":0,"geom:area_square_m":0,"geom:bbox":"24.39611,59.46917,24.39611,59.46917","geom:latitude":59.46917,"geom:longitude":24.39611,"gn:admin1_code":"1.0","gn:admin2_code":"198.0","gn:admin3_code":"7870.0","gn:asciiname":"Ranna","gn:country_code":"EE","gn:dem":14,"gn:feature_class":"P","gn:feature_code":"PPL","gn:geonameid":589137,"gn:latitude":59.46917,"gn:longitude":24.39611,"gn:modification_date":"2018-06-22","gn:name":"Ranna","gn:population":0,"gn:timezone":"Europe/Tallinn","iso:country":"EE","lbl:bbox":"24.37611,59.44917,24.41611,59.48917","lbl:max_zoom":18,"lbl:min_zoom":13.5,"mz:hierarchy_label":1,"mz:is_current":1,"mz:min_zoom":12,"name:ceb_x_preferred":["Ranna"],"name:deu_x_preferred":["Ranna"],"name:pol_x_preferred":["Ranna"],"name:swe_x_preferred":["Strandbyn"],"name:swe_x_variant":["Åsbyn","Ranna"],"name:und_x_variant":["Rannaküla"],"src:geom":"geonames","wof:belongsto":[85683055,102191581,1713312491,85633135,1713305681],"wof:breaches":[],"wof:concordances":{"gn:id":589137},"wof:country":"EE","wof:geomhash":"6b23fed422c42003d0b927f5a6066565","wof:hierarchy":[{"continent_id":102191581,"country_id":85633135,"county_id":1713305681,"localadmin_id":1713312491,"locality_id":1293204615,"region_id":85683055}],"wof:id":1293204615,"wof:lang_x_official":["est"],"wof:lang_x_spoken":["est"],"wof:lastmodified":1596661456,"wof:name":"Ranna","wof:parent_id":1713312491,"wof:placetype":"locality","wof:repo":"whosonfirst-data-admin-ee","wof:superseded_by":[],"wof:supersedes":[],"wof:tags":[]},"bbox":[24.39611,59.46917,24.39611,59.46917],"geometry":{"coordinates":[24.39611,59.46917],"type":"Point"}}