{"id":1242658783,"type":"Feature","properties":{"edtf:cessation":"uuuu","edtf:inception":"uuuu","geom:area":0,"geom:area_square_m":0,"geom:bbox":"23.95222,58.3475,23.95222,58.3475","geom:latitude":58.3475,"geom:longitude":23.95222,"gn:admin1_code":"11.0","gn:admin2_code":"624.0","gn:admin3_code":"6819.0","gn:asciiname":"Leetsaare","gn:country_code":"EE","gn:dem":20,"gn:feature_class":"P","gn:feature_code":"PPL","gn:geonameid":8620750,"gn:latitude":58.3475,"gn:longitude":23.95222,"gn:modification_date":"2017-11-25","gn:name":"Leetsaare","gn:population":0,"gn:timezone":"Europe/Tallinn","iso:country":"EE","lbl:bbox":"23.93222,58.3275,23.97222,58.3675","lbl:max_zoom":18,"lbl:min_zoom":13.5,"mz:hierarchy_label":1,"mz:is_current":1,"mz:min_zoom":12,"name:und_x_variant":["Läilaste"],"src:geom":"geonames","wof:belongsto":[85682981,102191581,1713310391,85633135,1713305703],"wof:breaches":[],"wof:concordances":{"gn:id":8620750},"wof:country":"EE","wof:geomhash":"17fdd05b4b471140adb510b44771df9e","wof:hierarchy":[{"continent_id":102191581,"country_id":85633135,"county_id":1713305703,"localadmin_id":1713310391,"locality_id":1242658783,"region_id":85682981}],"wof:id":1242658783,"wof:lang_x_official":["est"],"wof:lang_x_spoken":["est"],"wof:lastmodified":1596677702,"wof:name":"Leetsaare","wof:parent_id":1713310391,"wof:placetype":"locality","wof:repo":"whosonfirst-data-admin-ee","wof:superseded_by":[],"wof:supersedes":[],"wof:tags":[]},"bbox":[23.95222,58.3475,23.95222,58.3475],"geometry":{"coordinates":[23.95222,58.3475],"type":"Point"}}