{"id":1276958823,"type":"Feature","properties":{"edtf:cessation":"uuuu","edtf:inception":"uuuu","geom:area":0,"geom:area_square_m":0,"geom:bbox":"26.84889,57.97278,26.84889,57.97278","geom:latitude":57.97278,"geom:longitude":26.84889,"gn:admin1_code":"12.0","gn:admin2_code":"284.0","gn:admin3_code":"4730.0","gn:asciiname":"Magari","gn:country_code":"EE","gn:dem":126,"gn:feature_class":"P","gn:feature_code":"PPL","gn:geonameid":794582,"gn:latitude":57.97278,"gn:longitude":26.84889,"gn:modification_date":"2017-11-25","gn:name":"Magari","gn:population":0,"gn:timezone":"Europe/Tallinn","iso:country":"EE","lbl:bbox":"26.82889,57.95278,26.86889,57.99278","lbl:max_zoom":18,"lbl:min_zoom":13.5,"mz:hierarchy_label":1,"mz:is_current":1,"mz:min_zoom":12,"name:est_x_preferred":["Magari"],"name:hye_x_preferred":["Մագառի"],"name:pol_x_preferred":["Magari"],"name:spa_x_preferred":["Magari"],"name:ukr_x_preferred":["Магарі"],"name:vol_x_preferred":["Magari"],"src:geom":"geonames","wof:belongsto":[85682955,102191581,1713309911,85633135,1713305789],"wof:breaches":[],"wof:concordances":{"gn:id":794582,"wk:page":"Magari%2C_Estonia"},"wof:coterminous":[1713309911],"wof:country":"EE","wof:geomhash":"23802ed0397152046fd7fad2f6a4ae4b","wof:hierarchy":[{"continent_id":102191581,"country_id":85633135,"county_id":1713305789,"localadmin_id":1713309911,"locality_id":1276958823,"region_id":85682955}],"wof:id":1276958823,"wof:lang_x_official":["est"],"wof:lang_x_spoken":["est"],"wof:lastmodified":1596676794,"wof:name":"Magari","wof:parent_id":1713309911,"wof:placetype":"locality","wof:repo":"whosonfirst-data-admin-ee","wof:superseded_by":[],"wof:supersedes":[],"wof:tags":[]},"bbox":[26.84889,57.97278,26.84889,57.97278],"geometry":{"coordinates":[26.84889,57.97278],"type":"Point"}}