{"id":1309683185,"type":"Feature","properties":{"edtf:cessation":"uuuu","edtf:inception":"uuuu","geom:area":0,"geom:area_square_m":0,"geom:bbox":"23.36528,58.58694,23.36528,58.58694","geom:latitude":58.58694,"geom:longitude":23.36528,"gn:admin1_code":"14.0","gn:admin2_code":"478.0","gn:admin3_code":"3549.0","gn:asciiname":"Tusti","gn:country_code":"EE","gn:dem":16,"gn:feature_class":"P","gn:feature_code":"PPL","gn:geonameid":588136,"gn:latitude":58.58694,"gn:longitude":23.36528,"gn:modification_date":"2017-11-25","gn:name":"Tusti","gn:population":0,"gn:timezone":"Europe/Tallinn","iso:country":"EE","lbl:bbox":"23.34528,58.56694,23.38528,58.60694","lbl:max_zoom":18,"lbl:min_zoom":13.5,"mz:hierarchy_label":1,"mz:is_current":1,"mz:min_zoom":12,"name:deu_x_preferred":["Tusti"],"name:est_x_preferred":["Tusti"],"name:fas_x_preferred":["توستی"],"name:hye_x_preferred":["Տուստի"],"name:pol_x_preferred":["Tusti"],"name:spa_x_preferred":["Tusti"],"name:urd_x_preferred":["ٹسٹی"],"name:vol_x_preferred":["Tusti"],"src:geom":"geonames","wof:belongsto":[85682947,102191581,1713306203,85633135,1713305623],"wof:breaches":[],"wof:concordances":{"gn:id":588136,"wk:page":"Tusti%2C_Saare_County"},"wof:coterminous":[1713306183],"wof:country":"EE","wof:geomhash":"2761c4fe8fa0a5d5fd797491e6b244e8","wof:hierarchy":[{"continent_id":102191581,"country_id":85633135,"county_id":1713305623,"localadmin_id":1713306203,"locality_id":1309683185,"region_id":85682947}],"wof:id":1309683185,"wof:lang_x_official":["est"],"wof:lang_x_spoken":["est"],"wof:lastmodified":1596675297,"wof:name":"Tusti","wof:parent_id":1713306203,"wof:placetype":"locality","wof:repo":"whosonfirst-data-admin-ee","wof:superseded_by":[],"wof:supersedes":[],"wof:tags":[]},"bbox":[23.36528,58.58694,23.36528,58.58694],"geometry":{"coordinates":[23.36528,58.58694],"type":"Point"}}