{"id":1327236199,"type":"Feature","properties":{"edtf:cessation":"uuuu","edtf:inception":"uuuu","geom:area":0,"geom:area_square_m":0,"geom:bbox":"26.03667,58.75556,26.03667,58.75556","geom:latitude":58.75556,"geom:longitude":26.03667,"gn:admin1_code":"5.0","gn:admin2_code":"618.0","gn:admin3_code":"5462.0","gn:asciiname":"Uinvilja","gn:country_code":"EE","gn:dem":77,"gn:feature_class":"P","gn:feature_code":"PPL","gn:geonameid":8619500,"gn:latitude":58.75556,"gn:longitude":26.03667,"gn:modification_date":"2017-11-25","gn:name":"Uinvilja","gn:population":0,"gn:timezone":"Europe/Tallinn","iso:country":"EE","lbl:bbox":"26.01667,58.73556,26.05667,58.77556","lbl:max_zoom":18,"lbl:min_zoom":13.5,"mz:hierarchy_label":1,"mz:is_current":1,"mz:min_zoom":12,"name:und_x_variant":["Unvilla"],"src:geom":"geonames","wof:belongsto":[85683009,102191581,1713312183,85633135,1713305657],"wof:breaches":[],"wof:concordances":{"gn:id":8619500},"wof:country":"EE","wof:geomhash":"26f29d9312307cae6969c60e1db6c859","wof:hierarchy":[{"continent_id":102191581,"country_id":85633135,"county_id":1713305657,"localadmin_id":1713312183,"locality_id":1327236199,"region_id":85683009}],"wof:id":1327236199,"wof:lang_x_official":["est"],"wof:lang_x_spoken":["est"],"wof:lastmodified":1596676507,"wof:name":"Uinvilja","wof:parent_id":1713312183,"wof:placetype":"locality","wof:repo":"whosonfirst-data-admin-ee","wof:superseded_by":[],"wof:supersedes":[],"wof:tags":[]},"bbox":[26.03667,58.75556,26.03667,58.75556],"geometry":{"coordinates":[26.03667,58.75556],"type":"Point"}}