{"id":1343831981,"type":"Feature","properties":{"edtf:cessation":"uuuu","edtf:inception":"uuuu","geom:area":0,"geom:area_square_m":0,"geom:bbox":"27.06944,57.74361,27.06944,57.74361","geom:latitude":57.74361,"geom:longitude":27.06944,"gn:admin1_code":"21.0","gn:admin2_code":"698.0","gn:admin3_code":"5189.0","gn:asciiname":"Maee-Tilga","gn:country_code":"EE","gn:dem":243,"gn:feature_class":"P","gn:feature_code":"PPL","gn:geonameid":8620221,"gn:latitude":57.74361,"gn:longitude":27.06944,"gn:modification_date":"2017-11-25","gn:name":"Mäe-Tilga","gn:population":0,"gn:timezone":"Europe/Tallinn","iso:country":"EE","lbl:bbox":"27.04944,57.72361,27.08944,57.76361","lbl:max_zoom":18,"lbl:min_zoom":13.5,"mz:hierarchy_label":1,"mz:is_current":1,"mz:min_zoom":12,"name:und_x_variant":["Mäe-Tilga","Mäetilga"],"src:geom":"geonames","wof:belongsto":[85682937,102191581,1713315217,85633135,1713305787],"wof:breaches":[],"wof:concordances":{"gn:id":8620221},"wof:coterminous":[1713315217],"wof:country":"EE","wof:geomhash":"39795b20c472b25d5f6d3c2108e5c603","wof:hierarchy":[{"continent_id":102191581,"country_id":85633135,"county_id":1713305787,"localadmin_id":1713315217,"locality_id":1343831981,"region_id":85682937}],"wof:id":1343831981,"wof:lang_x_official":["est"],"wof:lang_x_spoken":["est"],"wof:lastmodified":1596676886,"wof:name":"Maee-Tilga","wof:parent_id":1713315217,"wof:placetype":"locality","wof:repo":"whosonfirst-data-admin-ee","wof:superseded_by":[],"wof:supersedes":[],"wof:tags":[]},"bbox":[27.06944,57.74361,27.06944,57.74361],"geometry":{"coordinates":[27.06944,57.74361],"type":"Point"}}