{"id":1226160701,"type":"Feature","properties":{"edtf:cessation":"uuuu","edtf:inception":"uuuu","geom:area":0,"geom:area_square_m":0,"geom:bbox":"24.44278,59.20806,24.44278,59.20806","geom:latitude":59.20806,"geom:longitude":24.44278,"gn:admin1_code":"1.0","gn:admin2_code":"726.0","gn:admin3_code":"5110.0","gn:asciiname":"Maarja","gn:country_code":"EE","gn:dem":41,"gn:feature_class":"P","gn:feature_code":"PPL","gn:geonameid":8619038,"gn:latitude":59.20806,"gn:longitude":24.44278,"gn:modification_date":"2017-11-25","gn:name":"Maarja","gn:population":0,"gn:timezone":"Europe/Tallinn","iso:country":"EE","lbl:bbox":"24.42278,59.18806,24.46278,59.22806","lbl:max_zoom":18,"lbl:min_zoom":13.5,"mz:hierarchy_label":1,"mz:is_current":1,"mz:min_zoom":12,"name:deu_x_preferred":["Maarja"],"name:est_x_preferred":["Maarja"],"name:fin_x_preferred":["Maarja"],"name:fra_x_preferred":["Maarja"],"name:lav_x_preferred":["Maarja"],"name:und_x_variant":["Kerkmaa"],"src:geom":"geonames","wof:belongsto":[85683055,102191581,1713307813,85633135,1713305739],"wof:breaches":[],"wof:concordances":{"gn:id":8619038},"wof:country":"EE","wof:geomhash":"a19342b6c01b1e2f0edfee815df94170","wof:hierarchy":[{"continent_id":102191581,"country_id":85633135,"county_id":1713305739,"localadmin_id":1713307813,"locality_id":1226160701,"region_id":85683055}],"wof:id":1226160701,"wof:lang_x_official":["est"],"wof:lang_x_spoken":["est"],"wof:lastmodified":1596663240,"wof:name":"Maarja","wof:parent_id":1713307813,"wof:placetype":"locality","wof:repo":"whosonfirst-data-admin-ee","wof:superseded_by":[],"wof:supersedes":[],"wof:tags":[]},"bbox":[24.44278,59.20806,24.44278,59.20806],"geometry":{"coordinates":[24.44278,59.20806],"type":"Point"}}