{"id":1327404791,"type":"Feature","properties":{"edtf:cessation":"uuuu","edtf:inception":"uuuu","geom:area":0,"geom:area_square_m":0,"geom:bbox":"22.80667,58.34306,22.80667,58.34306","geom:latitude":58.34306,"geom:longitude":22.80667,"gn:admin1_code":"14.0","gn:admin2_code":"714.0","gn:admin3_code":"4894.0","gn:asciiname":"Metsakuela","gn:country_code":"EE","gn:dem":12,"gn:feature_class":"P","gn:feature_code":"PPL","gn:geonameid":590256,"gn:latitude":58.34306,"gn:longitude":22.80667,"gn:modification_date":"2017-11-25","gn:name":"Metsaküla","gn:population":0,"gn:timezone":"Europe/Tallinn","iso:country":"EE","lbl:bbox":"22.78667,58.32306,22.82667,58.36306","lbl:max_zoom":18,"lbl:min_zoom":13.5,"mz:hierarchy_label":1,"mz:is_current":1,"mz:min_zoom":12,"name:und_x_variant":["Metsakyula","Metsa Asundus","Metsaküla"],"src:geom":"geonames","wof:belongsto":[85682947,102191581,1713306625,85633135,1713305627],"wof:breaches":[],"wof:concordances":{"gn:id":590256,"wk:page":"Metsak%C3%BCla%2C_Pihtla_Parish"},"wof:coterminous":[1713306625],"wof:country":"EE","wof:geomhash":"67c34359868f27b864e208be0a9dfdfc","wof:hierarchy":[{"continent_id":102191581,"country_id":85633135,"county_id":1713305627,"localadmin_id":1713306625,"locality_id":1327404791,"region_id":85682947}],"wof:id":1327404791,"wof:lang_x_official":["est"],"wof:lang_x_spoken":["est"],"wof:lastmodified":1596674957,"wof:name":"Metsakuela","wof:parent_id":1713306625,"wof:placetype":"locality","wof:repo":"whosonfirst-data-admin-ee","wof:superseded_by":[],"wof:supersedes":[],"wof:tags":[]},"bbox":[22.80667,58.34306,22.80667,58.34306],"geometry":{"coordinates":[22.80667,58.34306],"type":"Point"}}