{"id":1326811587,"type":"Feature","properties":{"edtf:cessation":"uuuu","edtf:inception":"uuuu","geom:area":0,"geom:area_square_m":0,"geom:bbox":"24.03944,58.61528,24.03944,58.61528","geom:latitude":58.61528,"geom:longitude":24.03944,"gn:admin1_code":"11.0","gn:admin2_code":"430.0","gn:admin3_code":"8157.0","gn:asciiname":"Tarva","gn:cc2":"EE","gn:country_code":"EE","gn:dem":28,"gn:feature_class":"P","gn:feature_code":"PPL","gn:geonameid":588328,"gn:latitude":58.61528,"gn:longitude":24.03944,"gn:modification_date":"2017-11-25","gn:name":"Tarva","gn:population":0,"gn:timezone":"Europe/Tallinn","iso:country":"EE","lbl:bbox":"24.01944,58.59528,24.05944,58.63528","lbl:max_zoom":18,"lbl:min_zoom":13.5,"mz:hierarchy_label":1,"mz:is_current":1,"mz:min_zoom":12,"name:und_x_variant":["Tõrva","Tyrva","Tarva"],"src:geom":"geonames","wof:belongsto":[85683001,102191581,1713309367,85633135,1713305721],"wof:breaches":[],"wof:concordances":{"gn:id":588328,"wk:page":"Tarva%2C_Koonga_Parish"},"wof:coterminous":[1713309367],"wof:country":"EE","wof:geomhash":"d55609d3c829df969d74d66522f4b471","wof:hierarchy":[{"continent_id":102191581,"country_id":85633135,"county_id":1713305721,"localadmin_id":1713309367,"locality_id":1326811587,"region_id":85683001}],"wof:id":1326811587,"wof:lang_x_official":["est"],"wof:lang_x_spoken":["est"],"wof:lastmodified":1596661678,"wof:name":"Tarva","wof:parent_id":1713309367,"wof:placetype":"locality","wof:repo":"whosonfirst-data-admin-ee","wof:superseded_by":[],"wof:supersedes":[],"wof:tags":[]},"bbox":[24.03944,58.61528,24.03944,58.61528],"geometry":{"coordinates":[24.03944,58.61528],"type":"Point"}}