{"id":1226218375,"type":"Feature","properties":{"edtf:cessation":"uuuu","edtf:inception":"uuuu","geom:area":0,"geom:area_square_m":0,"geom:bbox":"26.81361,58.43056,26.81361,58.43056","geom:latitude":58.43056,"geom:longitude":26.81361,"gn:admin1_code":"18.0","gn:admin2_code":"796.0","gn:admin3_code":"5310.0","gn:asciiname":"Moellatsi","gn:country_code":"EE","gn:dem":75,"gn:feature_class":"P","gn:feature_code":"PPL","gn:geonameid":590157,"gn:latitude":58.43056,"gn:longitude":26.81361,"gn:modification_date":"2017-11-25","gn:name":"Möllatsi","gn:population":0,"gn:timezone":"Europe/Tallinn","iso:country":"EE","lbl:bbox":"26.79361,58.41056,26.83361,58.45056","lbl:max_zoom":18,"lbl:min_zoom":13.5,"mz:hierarchy_label":1,"mz:is_current":1,"mz:min_zoom":12,"src:geom":"geonames","wof:belongsto":[85683009,102191581,1713313897,85633135,1713305659],"wof:breaches":[],"wof:concordances":{"gn:id":590157},"wof:coterminous":[1713313897],"wof:country":"EE","wof:geomhash":"60c1582c4f5f5644a9fee0c8c2411867","wof:hierarchy":[{"continent_id":102191581,"country_id":85633135,"county_id":1713305659,"localadmin_id":1713313897,"locality_id":1226218375,"region_id":85683009}],"wof:id":1226218375,"wof:lang_x_official":["est"],"wof:lang_x_spoken":["est"],"wof:lastmodified":1596676476,"wof:name":"Moellatsi","wof:parent_id":1713313897,"wof:placetype":"locality","wof:repo":"whosonfirst-data-admin-ee","wof:superseded_by":[],"wof:supersedes":[],"wof:tags":[]},"bbox":[26.81361,58.43056,26.81361,58.43056],"geometry":{"coordinates":[26.81361,58.43056],"type":"Point"}}