{"id":1126003971,"type":"Feature","properties":{"edtf:cessation":"uuuu","edtf:inception":"uuuu","geom:area":0,"geom:area_square_m":0,"geom:bbox":"25.98222,58.93917,25.98222,58.93917","geom:latitude":58.93917,"geom:longitude":25.98222,"gn:country":"EE","gn:fcode":"PPL","gn:population":223,"iso:country":"EE","lbl:bbox":"25.96222,58.91917,26.00222,58.95917","lbl:latitude":58.93917,"lbl:longitude":25.98222,"lbl:max_zoom":17,"lbl:min_zoom":12.5,"mz:hierarchy_label":1,"mz:is_current":1,"mz:min_zoom":11,"mz:note":"Quattroshapes Point Gazetteer import 20170519","name:ceb_x_preferred":["Vao"],"name:deu_x_preferred":["Vao"],"name:eng_x_preferred":["Vao"],"name:est_x_preferred":["Vao"],"name:fra_x_preferred":["Vao"],"name:glg_x_preferred":["Vao"],"name:pol_x_preferred":["Vao"],"name:rus_x_preferred":["Вао"],"name:swe_x_preferred":["Vao"],"name:und_x_variant":["Vao Asundus"],"qs_pg:aaroncc":"EE","qs_pg:gn_country":"EE","qs_pg:gn_fcode":"PPL","qs_pg:gn_id":587770,"qs_pg:gn_pop":223,"qs_pg:name":"Vao","qs_pg:name_adm0":"Eesti","qs_pg:name_adm1":"Järvamaa","qs_pg:photos_9k":1,"qs_pg:photos_9r":1,"qs_pg:photos_all":2,"qs_pg:photos_sr":0,"qs_pg:pop_sr":2,"qs_pg:qs_id":916023,"qs_pg:qs_pg_placetype":"locality","qs_pg:qs_pg_placetype_gp":"Town","qs_pg:woe_adm0":23424805,"qs_pg:woe_id":846307,"src:geom":"qs_pg","src:lbl_centroid":"qs_pg","src:population":"geonames","woe:adm0_id":23424805,"woe:name_adm0":"Eesti","woe:name_adm1":"Järvamaa","woe:placetype":"Town","wof:belongsto":[85683031,102191581,1713306829,85633135,1713305765],"wof:breaches":[],"wof:concordances":{"gn:id":587770,"gp:id":846307,"qs_pg:id":916023},"wof:coterminous":[1713306829],"wof:country":"EE","wof:created":1497299820,"wof:geomhash":"0a7cace15a4ce2ebc15fd0fafa58b3c1","wof:hierarchy":[{"continent_id":102191581,"country_id":85633135,"county_id":1713305765,"localadmin_id":1713306829,"locality_id":1126003971,"region_id":85683031}],"wof:id":1126003971,"wof:lang_x_official":["est"],"wof:lang_x_spoken":["est"],"wof:lastmodified":1596676652,"wof:name":"Vao","wof:parent_id":1713306829,"wof:placetype":"locality","wof:population":223,"wof:population_rank":2,"wof:repo":"whosonfirst-data-admin-ee","wof:superseded_by":[],"wof:supersedes":[],"wof:tags":[]},"bbox":[25.98222,58.93917,25.98222,58.93917],"geometry":{"coordinates":[25.98222,58.93917],"type":"Point"}}