{"id":1209509589,"type":"Feature","properties":{"edtf:cessation":"uuuu","edtf:inception":"uuuu","geom:area":0,"geom:area_square_m":0,"geom:bbox":"23.69861,58.65722,23.69861,58.65722","geom:latitude":58.65722,"geom:longitude":23.69861,"gn:admin1_code":"11.0","gn:admin2_code":"430.0","gn:admin3_code":"2323.0","gn:asciiname":"Vagivere","gn:country_code":"EE","gn:dem":21,"gn:feature_class":"P","gn:feature_code":"PPL","gn:geonameid":587959,"gn:latitude":58.65722,"gn:longitude":23.69861,"gn:modification_date":"2017-11-25","gn:name":"Vagivere","gn:population":0,"gn:timezone":"Europe/Tallinn","iso:country":"EE","lbl:bbox":"23.67861,58.63722,23.71861,58.67722","lbl:max_zoom":18,"lbl:min_zoom":13.5,"mz:hierarchy_label":1,"mz:is_current":1,"mz:min_zoom":12,"name:deu_x_preferred":["Vagivere"],"name:est_x_preferred":["Vagivere"],"name:hye_x_preferred":["Վագիվեռե"],"name:nld_x_preferred":["Vagivere"],"name:pol_x_preferred":["Vagivere"],"name:spa_x_preferred":["Vagivere"],"name:vol_x_preferred":["Vagivere"],"src:geom":"geonames","wof:belongsto":[85683001,102191581,1713309695,85633135,1713305721],"wof:breaches":[],"wof:concordances":{"gn:id":587959,"wk:page":"Vagivere"},"wof:coterminous":[1713308763],"wof:country":"EE","wof:geomhash":"3119b3da1209ec8a5caac1ffeb35f3f7","wof:hierarchy":[{"continent_id":102191581,"country_id":85633135,"county_id":1713305721,"localadmin_id":1713309695,"locality_id":1209509589,"region_id":85683001}],"wof:id":1209509589,"wof:lang_x_official":["est"],"wof:lang_x_spoken":["est"],"wof:lastmodified":1596661692,"wof:name":"Vagivere","wof:parent_id":1713309695,"wof:placetype":"locality","wof:repo":"whosonfirst-data-admin-ee","wof:superseded_by":[],"wof:supersedes":[],"wof:tags":[]},"bbox":[23.69861,58.65722,23.69861,58.65722],"geometry":{"coordinates":[23.69861,58.65722],"type":"Point"}}