{"id":1260139191,"type":"Feature","properties":{"edtf:cessation":"uuuu","edtf:inception":"uuuu","geom:area":0,"geom:area_square_m":0,"geom:bbox":"27.22472,57.665,27.22472,57.665","geom:latitude":57.665,"geom:longitude":27.22472,"gn:admin1_code":"21.0","gn:admin2_code":"698.0","gn:admin3_code":"7411.0","gn:asciiname":"Sandi","gn:country_code":"EE","gn:dem":195,"gn:feature_class":"P","gn:feature_code":"PPL","gn:geonameid":8619882,"gn:latitude":57.665,"gn:longitude":27.22472,"gn:modification_date":"2017-11-25","gn:name":"Sandi","gn:population":0,"gn:timezone":"Europe/Tallinn","iso:country":"EE","lbl:bbox":"27.20472,57.645,27.24472,57.685","lbl:max_zoom":18,"lbl:min_zoom":13.5,"mz:hierarchy_label":1,"mz:is_current":1,"mz:min_zoom":12,"name:ceb_x_preferred":["Sandi"],"name:ind_x_preferred":["Sandi"],"name:nld_x_preferred":["Sandi"],"name:swe_x_preferred":["Sandi"],"name:und_x_variant":["Vinnora"],"src:geom":"geonames","wof:belongsto":[85682937,102191581,1713316483,85633135,1713305787],"wof:breaches":[],"wof:concordances":{"gn:id":8619882},"wof:coterminous":[1713316483],"wof:country":"EE","wof:geomhash":"d061aa4f50eed6a4b285dc8309c2335c","wof:hierarchy":[{"continent_id":102191581,"country_id":85633135,"county_id":1713305787,"localadmin_id":1713316483,"locality_id":1260139191,"region_id":85682937}],"wof:id":1260139191,"wof:lang_x_official":["est"],"wof:lang_x_spoken":["est"],"wof:lastmodified":1596676876,"wof:name":"Sandi","wof:parent_id":1713316483,"wof:placetype":"locality","wof:repo":"whosonfirst-data-admin-ee","wof:superseded_by":[],"wof:supersedes":[],"wof:tags":[]},"bbox":[27.22472,57.665,27.22472,57.665],"geometry":{"coordinates":[27.22472,57.665],"type":"Point"}}