{"id":1344071173,"type":"Feature","properties":{"edtf:cessation":"uuuu","edtf:inception":"uuuu","geom:area":0,"geom:area_square_m":0,"geom:bbox":"24.45351,59.12547,24.45351,59.12547","geom:latitude":59.12547,"geom:longitude":24.45351,"gn:admin1_code":"1.0","gn:admin2_code":"726.0","gn:admin3_code":"1720.0","gn:asciiname":"Monuste","gn:cc2":"EE","gn:country_code":"EE","gn:dem":65,"gn:feature_class":"P","gn:feature_code":"PPL","gn:geonameid":590150,"gn:latitude":59.12547,"gn:longitude":24.45351,"gn:modification_date":"2017-11-25","gn:name":"Mõnuste","gn:population":0,"gn:timezone":"Europe/Tallinn","iso:country":"EE","lbl:bbox":"24.43351,59.10547,24.47351,59.14547","lbl:max_zoom":18,"lbl:min_zoom":13.5,"mz:hierarchy_label":1,"mz:is_current":1,"mz:min_zoom":12,"name:und_x_variant":["Mõnuste-Eest"],"src:geom":"geonames","wof:belongsto":[85683055,102191581,1713307859,85633135,1713305739],"wof:breaches":[],"wof:concordances":{"gn:id":590150},"wof:country":"EE","wof:geomhash":"f163b6b8ae07b62e81810f9c090cdcd8","wof:hierarchy":[{"continent_id":102191581,"country_id":85633135,"county_id":1713305739,"localadmin_id":1713307859,"locality_id":1344071173,"region_id":85683055}],"wof:id":1344071173,"wof:lang_x_official":["est"],"wof:lang_x_spoken":["est"],"wof:lastmodified":1596663246,"wof:name":"Monuste","wof:parent_id":1713307859,"wof:placetype":"locality","wof:repo":"whosonfirst-data-admin-ee","wof:superseded_by":[],"wof:supersedes":[],"wof:tags":[]},"bbox":[24.45351,59.12547,24.45351,59.12547],"geometry":{"coordinates":[24.45351,59.12547],"type":"Point"}}