{"id":1209687235,"type":"Feature","properties":{"edtf:cessation":"uuuu","edtf:inception":"uuuu","geom:area":0,"geom:area_square_m":0,"geom:bbox":"24.85528,58.94861,24.85528,58.94861","geom:latitude":58.94861,"geom:longitude":24.85528,"gn:admin1_code":"13.0","gn:admin2_code":"293.0","gn:admin3_code":"8970.0","gn:asciiname":"Valtu-Nurme","gn:country_code":"EE","gn:dem":66,"gn:feature_class":"P","gn:feature_code":"PPL","gn:geonameid":8618453,"gn:latitude":58.94861,"gn:longitude":24.85528,"gn:modification_date":"2017-11-25","gn:name":"Valtu-Nurme","gn:population":0,"gn:timezone":"Europe/Tallinn","iso:country":"EE","lbl:bbox":"24.83528,58.92861,24.87528,58.96861","lbl:max_zoom":18,"lbl:min_zoom":13.5,"mz:hierarchy_label":1,"mz:is_current":1,"mz:min_zoom":12,"name:ara_x_preferred":["فالتو نورم"],"name:est_x_preferred":["Valtu-Nurme"],"name:hye_x_preferred":["Վալտու-Նուռմե"],"name:pol_x_preferred":["Valtu-Nurme"],"name:sco_x_preferred":["Valtu-Nurme"],"name:spa_x_preferred":["Valtu-Nurme"],"name:und_x_variant":["Nurme"],"name:vol_x_preferred":["Valtu-Nurme"],"src:geom":"geonames","wof:belongsto":[85683013,102191581,1713311233,85633135,1713305713],"wof:breaches":[],"wof:concordances":{"gn:id":8618453,"wk:page":"Valtu-Nurme"},"wof:coterminous":[1713311233],"wof:country":"EE","wof:geomhash":"13c763f9fe3087eda5866042d5e83abe","wof:hierarchy":[{"continent_id":102191581,"country_id":85633135,"county_id":1713305713,"localadmin_id":1713311233,"locality_id":1209687235,"region_id":85683013}],"wof:id":1209687235,"wof:lang_x_official":["est"],"wof:lang_x_spoken":["est"],"wof:lastmodified":1596676746,"wof:name":"Valtu-Nurme","wof:parent_id":1713311233,"wof:placetype":"locality","wof:repo":"whosonfirst-data-admin-ee","wof:superseded_by":[],"wof:supersedes":[],"wof:tags":[]},"bbox":[24.85528,58.94861,24.85528,58.94861],"geometry":{"coordinates":[24.85528,58.94861],"type":"Point"}}