{"id":1259571351,"type":"Feature","properties":{"edtf:cessation":"uuuu","edtf:inception":"uuuu","geom:area":0,"geom:area_square_m":0,"geom:bbox":"24.87556,58.14278,24.87556,58.14278","geom:latitude":58.14278,"geom:longitude":24.87556,"gn:admin1_code":"11.0","gn:admin2_code":"712.0","gn:admin3_code":"4440.0","gn:asciiname":"Veski","gn:country_code":"EE","gn:dem":44,"gn:feature_class":"P","gn:feature_code":"PPL","gn:geonameid":8620616,"gn:latitude":58.14278,"gn:longitude":24.87556,"gn:modification_date":"2017-11-25","gn:name":"Veski","gn:population":0,"gn:timezone":"Europe/Tallinn","iso:country":"EE","lbl:bbox":"24.85556,58.12278,24.89556,58.16278","lbl:max_zoom":18,"lbl:min_zoom":13.5,"mz:hierarchy_label":1,"mz:is_current":1,"mz:min_zoom":12,"name:deu_x_preferred":["Veski"],"name:est_x_preferred":["Veski"],"name:pol_x_preferred":["Veski"],"name:rus_x_preferred":["Вески"],"name:sco_x_preferred":["Veski"],"name:und_x_variant":["Veske"],"src:geom":"geonames","wof:belongsto":[85682981,102191581,1713309667,85633135,1713305705],"wof:breaches":[],"wof:concordances":{"gn:id":8620616},"wof:country":"EE","wof:geomhash":"7104d0b94f18de7462858d889a39a7d1","wof:hierarchy":[{"continent_id":102191581,"country_id":85633135,"county_id":1713305705,"localadmin_id":1713309667,"locality_id":1259571351,"region_id":85682981}],"wof:id":1259571351,"wof:lang_x_official":["est"],"wof:lang_x_spoken":["est"],"wof:lastmodified":1596677731,"wof:name":"Veski","wof:parent_id":1713309667,"wof:placetype":"locality","wof:repo":"whosonfirst-data-admin-ee","wof:superseded_by":[],"wof:supersedes":[],"wof:tags":[]},"bbox":[24.87556,58.14278,24.87556,58.14278],"geometry":{"coordinates":[24.87556,58.14278],"type":"Point"}}