{"id":1243519275,"type":"Feature","properties":{"edtf:cessation":"uuuu","edtf:inception":"uuuu","geom:area":0,"geom:area_square_m":0,"geom:bbox":"25.24639,58.04472,25.24639,58.04472","geom:latitude":58.04472,"geom:longitude":25.24639,"gn:admin1_code":"20.0","gn:admin2_code":"480.0","gn:admin3_code":"4030.0","gn:asciiname":"Polde","gn:country_code":"EE","gn:dem":83,"gn:feature_class":"P","gn:feature_code":"PPL","gn:geonameid":8620777,"gn:latitude":58.04472,"gn:longitude":25.24639,"gn:modification_date":"2017-11-25","gn:name":"Põlde","gn:population":0,"gn:timezone":"Europe/Tallinn","iso:country":"EE","lbl:bbox":"25.22639,58.02472,25.26639,58.06472","lbl:max_zoom":18,"lbl:min_zoom":13.5,"mz:hierarchy_label":1,"mz:is_current":1,"mz:min_zoom":12,"src:geom":"geonames","wof:belongsto":[85682985,102191581,1713311573,85633135,1713305661],"wof:breaches":[],"wof:concordances":{"gn:id":8620777},"wof:country":"EE","wof:geomhash":"20aa98146bbd37f7632d93b147c7357a","wof:hierarchy":[{"continent_id":102191581,"country_id":85633135,"county_id":1713305661,"localadmin_id":1713311573,"locality_id":1243519275,"region_id":85682985}],"wof:id":1243519275,"wof:lang_x_official":["est"],"wof:lang_x_spoken":["est"],"wof:lastmodified":1596661306,"wof:name":"Polde","wof:parent_id":1713311573,"wof:placetype":"locality","wof:repo":"whosonfirst-data-admin-ee","wof:superseded_by":[],"wof:supersedes":[],"wof:tags":[]},"bbox":[25.24639,58.04472,25.24639,58.04472],"geometry":{"coordinates":[25.24639,58.04472],"type":"Point"}}