{"id":1225826293,"type":"Feature","properties":{"edtf:cessation":"uuuu","edtf:inception":"uuuu","geom:area":0,"geom:area_square_m":0,"geom:bbox":"24.89361,58.17639,24.89361,58.17639","geom:latitude":58.17639,"geom:longitude":24.89361,"gn:admin1_code":"11.0","gn:admin2_code":"712.0","gn:admin3_code":"7560.0","gn:asciiname":"Sigaste","gn:country_code":"EE","gn:dem":45,"gn:feature_class":"P","gn:feature_code":"PPL","gn:geonameid":588700,"gn:latitude":58.17639,"gn:longitude":24.89361,"gn:modification_date":"2017-11-25","gn:name":"Sigaste","gn:population":0,"gn:timezone":"Europe/Tallinn","iso:country":"EE","lbl:bbox":"24.87361,58.15639,24.91361,58.19639","lbl:max_zoom":18,"lbl:min_zoom":13.5,"mz:hierarchy_label":1,"mz:is_current":1,"mz:min_zoom":12,"name:eng_x_preferred":["Sigaste"],"name:est_x_preferred":["Sigaste"],"name:fra_x_preferred":["Sigaste"],"name:hye_x_preferred":["Սիգաստե"],"name:rus_x_preferred":["Сигасте"],"name:spa_x_preferred":["Sigaste"],"name:swe_x_preferred":["Sigaste"],"name:vol_x_preferred":["Sigaste"],"src:geom":"geonames","wof:belongsto":[85682981,102191581,1713309593,85633135,1713305705],"wof:breaches":[],"wof:concordances":{"gn:id":588700,"wk:page":"Sigaste"},"wof:coterminous":[1713309593],"wof:country":"EE","wof:geomhash":"c582afeadc02bd5fadae93f382e2a8b4","wof:hierarchy":[{"continent_id":102191581,"country_id":85633135,"county_id":1713305705,"localadmin_id":1713309593,"locality_id":1225826293,"region_id":85682981}],"wof:id":1225826293,"wof:lang_x_official":["est"],"wof:lang_x_spoken":["est"],"wof:lastmodified":1596677735,"wof:name":"Sigaste","wof:parent_id":1713309593,"wof:placetype":"locality","wof:repo":"whosonfirst-data-admin-ee","wof:superseded_by":[],"wof:supersedes":[],"wof:tags":[]},"bbox":[24.89361,58.17639,24.89361,58.17639],"geometry":{"coordinates":[24.89361,58.17639],"type":"Point"}}