{"id":1310574855,"type":"Feature","properties":{"edtf:cessation":"uuuu","edtf:inception":"uuuu","geom:area":0,"geom:area_square_m":0,"geom:bbox":"22.56746,58.24129,22.56746,58.24129","geom:latitude":58.24129,"geom:longitude":22.56746,"gn:admin1_code":"14.0","gn:admin2_code":"714.0","gn:admin3_code":"5044.0","gn:asciiname":"Sepama","gn:country_code":"EE","gn:dem":7,"gn:feature_class":"P","gn:feature_code":"PPL","gn:geonameid":8354602,"gn:latitude":58.24129,"gn:longitude":22.56746,"gn:modification_date":"2017-11-25","gn:name":"Sepama","gn:population":0,"gn:timezone":"Europe/Tallinn","iso:country":"EE","lbl:bbox":"22.54746,58.22129,22.58746,58.26129","lbl:max_zoom":18,"lbl:min_zoom":13.5,"mz:hierarchy_label":1,"mz:is_current":1,"mz:min_zoom":12,"src:geom":"geonames","wof:belongsto":[85682947,102191581,1713306545,85633135,1713305627],"wof:breaches":[],"wof:concordances":{"gn:id":8354602},"wof:country":"EE","wof:geomhash":"5701d6c83bce50da3b26a855468663e5","wof:hierarchy":[{"continent_id":102191581,"country_id":85633135,"county_id":1713305627,"localadmin_id":1713306545,"locality_id":1310574855,"region_id":85682947}],"wof:id":1310574855,"wof:lang_x_official":["est"],"wof:lang_x_spoken":["est"],"wof:lastmodified":1596674948,"wof:name":"Sepama","wof:parent_id":1713306545,"wof:placetype":"locality","wof:repo":"whosonfirst-data-admin-ee","wof:superseded_by":[],"wof:supersedes":[],"wof:tags":[]},"bbox":[22.56746,58.24129,22.56746,58.24129],"geometry":{"coordinates":[22.56746,58.24129],"type":"Point"}}