{"id":1126037555,"type":"Feature","properties":{"edtf:cessation":"uuuu","edtf:inception":"uuuu","geom:area":0,"geom:area_square_m":0,"geom:bbox":"25.81,58.145,25.81,58.145","geom:latitude":58.145,"geom:longitude":25.81,"gn:country":"EE","gn:fcode":"PPL","gn:population":300,"iso:country":"EE","lbl:bbox":"25.79,58.125,25.83,58.165","lbl:latitude":58.145,"lbl:longitude":25.81,"lbl:max_zoom":17,"lbl:min_zoom":12.5,"mz:hierarchy_label":1,"mz:is_current":1,"mz:min_zoom":11,"mz:note":"Quattroshapes Point Gazetteer import 20170519","name:ceb_x_preferred":["Kärstna"],"name:deu_x_preferred":["Kerstenhof"],"name:eng_x_preferred":["Kärstna"],"name:est_x_preferred":["Kärstna"],"name:fra_x_preferred":["Kärstna"],"name:hye_x_preferred":["Կեռստնա"],"name:nld_x_preferred":["Kärstna"],"name:pol_x_preferred":["Kärstna"],"name:rus_x_preferred":["Кярстна"],"name:spa_x_preferred":["Kärstna"],"name:swe_x_preferred":["Kärstna"],"name:ukr_x_preferred":["Миза Кярстна"],"name:ukr_x_variant":["Кярстна"],"name:und_x_variant":["Kyarstna"],"name:vol_x_preferred":["Kärstna"],"qs_pg:aaroncc":"EE","qs_pg:gn_country":"EE","qs_pg:gn_fcode":"PPL","qs_pg:gn_id":591572,"qs_pg:gn_pop":300,"qs_pg:name":"Kärstna","qs_pg:name_adm0":"Eesti","qs_pg:name_adm1":"Viljandimaa","qs_pg:photos_9k":1,"qs_pg:photos_9r":1,"qs_pg:photos_all":1,"qs_pg:photos_sr":0,"qs_pg:pop_sr":2,"qs_pg:qs_id":966744,"qs_pg:qs_pg_placetype":"locality","qs_pg:qs_pg_placetype_gp":"Town","qs_pg:woe_adm0":23424805,"qs_pg:woe_id":842778,"src:geom":"qs_pg","src:lbl_centroid":"qs_pg","src:population":"geonames","woe:adm0_id":23424805,"woe:name_adm0":"Eesti","woe:name_adm1":"Viljandimaa","woe:placetype":"Town","wof:belongsto":[85682985,102191581,1713309735,85633135,1713305669],"wof:breaches":[],"wof:concordances":{"gn:id":591572,"gp:id":842778,"qs_pg:id":966744,"wd:id":"Q3058498"},"wof:coterminous":[1713309735],"wof:country":"EE","wof:created":1497301891,"wof:geomhash":"2e442456635f1906c449f5c876dd1d7d","wof:hierarchy":[{"continent_id":102191581,"country_id":85633135,"county_id":1713305669,"localadmin_id":1713309735,"locality_id":1126037555,"region_id":85682985}],"wof:id":1126037555,"wof:lang_x_official":["est"],"wof:lang_x_spoken":["est"],"wof:lastmodified":1596661272,"wof:name":"Kärstna","wof:parent_id":1713309735,"wof:placetype":"locality","wof:population":300,"wof:population_rank":2,"wof:repo":"whosonfirst-data-admin-ee","wof:superseded_by":[],"wof:supersedes":[],"wof:tags":[]},"bbox":[25.81,58.145,25.81,58.145],"geometry":{"coordinates":[25.81,58.145],"type":"Point"}}