{"id":1193134259,"type":"Feature","properties":{"edtf:cessation":"uuuu","edtf:inception":"uuuu","geom:area":0,"geom:area_square_m":0,"geom:bbox":"26.33889,58.94056,26.33889,58.94056","geom:latitude":58.94056,"geom:longitude":26.33889,"gn:admin1_code":"8.0","gn:admin2_code":"928.0","gn:admin3_code":"4125.0","gn:asciiname":"Lasinurme","gn:cc2":"EE","gn:country_code":"EE","gn:dem":132,"gn:feature_class":"P","gn:feature_code":"PPL","gn:geonameid":590780,"gn:latitude":58.94056,"gn:longitude":26.33889,"gn:modification_date":"2017-11-25","gn:name":"Lasinurme","gn:population":0,"gn:timezone":"Europe/Tallinn","iso:country":"EE","lbl:bbox":"26.31889,58.92056,26.35889,58.96056","lbl:max_zoom":18,"lbl:min_zoom":13.5,"mz:hierarchy_label":1,"mz:is_current":1,"mz:min_zoom":12,"name:est_x_preferred":["Lasinurme"],"name:hye_x_preferred":["Լասինուռմե"],"name:pol_x_preferred":["Lasinurme"],"name:und_x_variant":["Lazinurme"],"name:urd_x_preferred":["لاسینورمی"],"name:vol_x_preferred":["Lasinurme"],"src:geom":"geonames","wof:belongsto":[85683049,102191581,1713311833,85633135,1713305769],"wof:breaches":[],"wof:concordances":{"gn:id":590780,"wk:page":"Lasinurme"},"wof:coterminous":[1713311833],"wof:country":"EE","wof:geomhash":"2fd89fb59e066962287a896aa4460fcb","wof:hierarchy":[{"continent_id":102191581,"country_id":85633135,"county_id":1713305769,"localadmin_id":1713311833,"locality_id":1193134259,"region_id":85683049}],"wof:id":1193134259,"wof:lang_x_official":["est"],"wof:lang_x_spoken":["est"],"wof:lastmodified":1596676542,"wof:name":"Lasinurme","wof:parent_id":1713311833,"wof:placetype":"locality","wof:repo":"whosonfirst-data-admin-ee","wof:superseded_by":[],"wof:supersedes":[],"wof:tags":[]},"bbox":[26.33889,58.94056,26.33889,58.94056],"geometry":{"coordinates":[26.33889,58.94056],"type":"Point"}}