{"id":1343685929,"type":"Feature","properties":{"edtf:cessation":"uuuu","edtf:inception":"uuuu","geom:area":0,"geom:area_square_m":0,"geom:bbox":"25.5725,59.03556,25.5725,59.03556","geom:latitude":59.03556,"geom:longitude":25.5725,"gn:admin1_code":"4.0","gn:admin2_code":"567.0","gn:admin3_code":"6405.0","gn:asciiname":"Puiatu","gn:cc2":"EE","gn:country_code":"EE","gn:dem":79,"gn:feature_class":"P","gn:feature_code":"PPL","gn:geonameid":589298,"gn:latitude":59.03556,"gn:longitude":25.5725,"gn:modification_date":"2017-11-25","gn:name":"Puiatu","gn:population":0,"gn:timezone":"Europe/Tallinn","iso:country":"EE","lbl:bbox":"25.5525,59.01556,25.5925,59.05556","lbl:max_zoom":18,"lbl:min_zoom":13.5,"mz:hierarchy_label":1,"mz:is_current":1,"mz:min_zoom":12,"name:est_x_preferred":["Puiatu"],"name:hye_x_preferred":["Պուիատու"],"name:pol_x_preferred":["Puiatu"],"name:ukr_x_preferred":["Пуйату"],"name:und_x_variant":["Puyatu","Puyatu-Aru","Puiatu-Aru"],"name:vol_x_preferred":["Puiatu"],"src:geom":"geonames","wof:belongsto":[85683031,102191581,1713308295,85633135,1713305663],"wof:breaches":[],"wof:concordances":{"gn:id":589298,"wk:page":"Puiatu%2C_Paide_Parish"},"wof:coterminous":[1713308295],"wof:country":"EE","wof:geomhash":"677f940b3c35753e0905f79d183701c7","wof:hierarchy":[{"continent_id":102191581,"country_id":85633135,"county_id":1713305663,"localadmin_id":1713308295,"locality_id":1343685929,"region_id":85683031}],"wof:id":1343685929,"wof:lang_x_official":["est"],"wof:lang_x_spoken":["est"],"wof:lastmodified":1596661327,"wof:name":"Puiatu","wof:parent_id":1713308295,"wof:placetype":"locality","wof:repo":"whosonfirst-data-admin-ee","wof:superseded_by":[],"wof:supersedes":[],"wof:tags":[]},"bbox":[25.5725,59.03556,25.5725,59.03556],"geometry":{"coordinates":[25.5725,59.03556],"type":"Point"}}