{"id":1126039043,"type":"Feature","properties":{"edtf:cessation":"uuuu","edtf:inception":"uuuu","geom:area":0,"geom:area_square_m":0,"geom:bbox":"27.18417,57.86278,27.18417,57.86278","geom:latitude":57.86278,"geom:longitude":27.18417,"gn:country":"EE","gn:fcode":"PPL","gn:population":309,"iso:country":"EE","lbl:bbox":"27.16417,57.84278,27.20417,57.88278","lbl:latitude":57.86278,"lbl:longitude":27.18417,"lbl:max_zoom":17,"lbl:min_zoom":12.5,"mz:hierarchy_label":1,"mz:is_current":1,"mz:min_zoom":11,"mz:note":"Quattroshapes Point Gazetteer import 20170519","name:ceb_x_preferred":["Lasva"],"name:ces_x_preferred":["Lasva"],"name:eng_x_preferred":["Lasva"],"name:est_x_preferred":["Lasva"],"name:hye_x_preferred":["Լասվա"],"name:rus_x_preferred":["Ласва"],"name:spa_x_preferred":["Lasva"],"name:ukr_x_preferred":["Ласва"],"name:und_x_variant":["Myza Lasva"],"name:urd_x_preferred":["لاسوا"],"name:vol_x_preferred":["Lasva"],"name:zho_x_preferred":["拉斯瓦"],"qs_pg:aaroncc":"EE","qs_pg:gn_country":"EE","qs_pg:gn_fcode":"PPL","qs_pg:gn_id":590770,"qs_pg:gn_pop":309,"qs_pg:name":"Lasva","qs_pg:name_adm0":"Eesti","qs_pg:name_adm1":"Võrumaa","qs_pg:photos_9k":1,"qs_pg:photos_9r":1,"qs_pg:photos_all":2,"qs_pg:photos_sr":0,"qs_pg:pop_sr":2,"qs_pg:qs_id":262019,"qs_pg:qs_pg_placetype":"locality","qs_pg:qs_pg_placetype_gp":"Town","qs_pg:woe_adm0":23424805,"qs_pg:woe_id":843530,"src:geom":"qs_pg","src:lbl_centroid":"qs_pg","src:population":"geonames","woe:adm0_id":23424805,"woe:name_adm0":"Eesti","woe:name_adm1":"Võrumaa","woe:placetype":"Town","wof:belongsto":[85682937,102191581,1713316255,85633135,1713305633],"wof:breaches":[],"wof:concordances":{"gn:id":590770,"gp:id":843530,"qs_pg:id":262019},"wof:coterminous":[1713316255],"wof:country":"EE","wof:created":1497302006,"wof:geomhash":"feaa7e7e0eb6e621b215b723c7113ff1","wof:hierarchy":[{"continent_id":102191581,"country_id":85633135,"county_id":1713305633,"localadmin_id":1713316255,"locality_id":1126039043,"region_id":85682937}],"wof:id":1126039043,"wof:lang_x_official":["est"],"wof:lang_x_spoken":["est"],"wof:lastmodified":1596660419,"wof:name":"Lasva","wof:parent_id":1713316255,"wof:placetype":"locality","wof:population":309,"wof:population_rank":2,"wof:repo":"whosonfirst-data-admin-ee","wof:superseded_by":[],"wof:supersedes":[],"wof:tags":[]},"bbox":[27.18417,57.86278,27.18417,57.86278],"geometry":{"coordinates":[27.18417,57.86278],"type":"Point"}}