{"id":1343879723,"type":"Feature","properties":{"edtf:cessation":"uuuu","edtf:inception":"uuuu","geom:area":0,"geom:area_square_m":0,"geom:bbox":"23.87194,58.79944,23.87194,58.79944","geom:latitude":58.79944,"geom:longitude":23.87194,"gn:admin1_code":"7.0","gn:admin2_code":"441.0","gn:admin3_code":"8106.0","gn:asciiname":"Kurevere","gn:cc2":"EE","gn:country_code":"EE","gn:dem":15,"gn:feature_class":"P","gn:feature_code":"PPL","gn:geonameid":590933,"gn:latitude":58.79944,"gn:longitude":23.87194,"gn:modification_date":"2018-05-02","gn:name":"Kurevere","gn:population":0,"gn:timezone":"Europe/Tallinn","iso:country":"EE","lbl:bbox":"23.85194,58.77944,23.89194,58.81944","lbl:max_zoom":18,"lbl:min_zoom":13.5,"mz:hierarchy_label":1,"mz:is_current":1,"mz:min_zoom":12,"name:deu_x_preferred":["Kurevere"],"name:est_x_preferred":["Kurevere"],"name:hye_x_preferred":["Կուռևեռե"],"name:pol_x_preferred":["Kurevere"],"name:spa_x_preferred":["Kurevere"],"name:ukr_x_preferred":["Куревере"],"name:und_x_variant":["Kureve"],"name:vol_x_preferred":["Kurevere"],"src:geom":"geonames","wof:belongsto":[85683001,102191581,1713312471,85633135,1713305701],"wof:breaches":[],"wof:concordances":{"gn:id":590933,"wk:page":"Kurevere%2C_L%C3%A4%C3%A4ne_County"},"wof:coterminous":[1713315167],"wof:country":"EE","wof:geomhash":"30df536e1f9e49d4d692a8d4aac23cec","wof:hierarchy":[{"continent_id":102191581,"country_id":85633135,"county_id":1713305701,"localadmin_id":1713312471,"locality_id":1343879723,"region_id":85683001}],"wof:id":1343879723,"wof:lang_x_official":["est"],"wof:lang_x_spoken":["est"],"wof:lastmodified":1596677439,"wof:name":"Kurevere","wof:parent_id":1713312471,"wof:placetype":"locality","wof:repo":"whosonfirst-data-admin-ee","wof:superseded_by":[],"wof:supersedes":[],"wof:tags":[]},"bbox":[23.87194,58.79944,23.87194,58.79944],"geometry":{"coordinates":[23.87194,58.79944],"type":"Point"}}