{"id":1276744359,"type":"Feature","properties":{"edtf:cessation":"uuuu","edtf:inception":"uuuu","geom:area":0,"geom:area_square_m":0,"geom:bbox":"24.31667,58.61667,24.31667,58.61667","geom:latitude":58.61667,"geom:longitude":24.31667,"gn:admin1_code":"11.0","gn:admin2_code":"638.0","gn:admin3_code":"5328.0","gn:asciiname":"Salukuela","gn:country_code":"EE","gn:dem":21,"gn:feature_class":"P","gn:feature_code":"PPL","gn:geonameid":588813,"gn:latitude":58.61667,"gn:longitude":24.31667,"gn:modification_date":"2017-11-25","gn:name":"Saluküla","gn:population":0,"gn:timezone":"Europe/Tallinn","iso:country":"EE","lbl:bbox":"24.29667,58.59667,24.33667,58.63667","lbl:max_zoom":18,"lbl:min_zoom":13.5,"mz:hierarchy_label":1,"mz:is_current":1,"mz:min_zoom":12,"src:geom":"geonames","wof:belongsto":[85682981,102191581,1713314391,85633135,1713305733],"wof:breaches":[],"wof:concordances":{"gn:id":588813},"wof:country":"EE","wof:geomhash":"52c36b3c8246e5ac4864d9d0779e78c8","wof:hierarchy":[{"continent_id":102191581,"country_id":85633135,"county_id":1713305733,"localadmin_id":1713314391,"locality_id":1276744359,"region_id":85682981}],"wof:id":1276744359,"wof:lang_x_official":["est"],"wof:lang_x_spoken":["est"],"wof:lastmodified":1596663427,"wof:name":"Salukuela","wof:parent_id":1713314391,"wof:placetype":"locality","wof:repo":"whosonfirst-data-admin-ee","wof:superseded_by":[],"wof:supersedes":[],"wof:tags":[]},"bbox":[24.31667,58.61667,24.31667,58.61667],"geometry":{"coordinates":[24.31667,58.61667],"type":"Point"}}