{"id":1259858769,"type":"Feature","properties":{"edtf:cessation":"uuuu","edtf:inception":"uuuu","geom:area":0,"geom:area_square_m":0,"geom:bbox":"24.79972,59.11111,24.79972,59.11111","geom:latitude":59.11111,"geom:longitude":24.79972,"gn:admin1_code":"13.0","gn:admin2_code":"317.0","gn:admin3_code":"5250.0","gn:asciiname":"Maelivere","gn:country_code":"EE","gn:dem":65,"gn:feature_class":"P","gn:feature_code":"PPL","gn:geonameid":590359,"gn:latitude":59.11111,"gn:longitude":24.79972,"gn:modification_date":"2017-11-25","gn:name":"Mälivere","gn:population":0,"gn:timezone":"Europe/Tallinn","iso:country":"EE","lbl:bbox":"24.77972,59.09111,24.81972,59.13111","lbl:max_zoom":18,"lbl:min_zoom":13.5,"mz:hierarchy_label":1,"mz:is_current":1,"mz:min_zoom":12,"name:est_x_preferred":["Mälivere"],"name:hye_x_preferred":["Մելիվեռե"],"name:pol_x_preferred":["Mälivere"],"name:rus_x_preferred":["Мяливере"],"name:sco_x_preferred":["Mälivere"],"name:spa_x_preferred":["Mälivere"],"name:und_x_variant":["Myalivere"],"name:vol_x_preferred":["Mälivere"],"src:geom":"geonames","wof:belongsto":[85683013,102191581,1713313313,85633135,1713305707],"wof:breaches":[],"wof:concordances":{"gn:id":590359,"wk:page":"M%C3%A4livere"},"wof:coterminous":[1713313313],"wof:country":"EE","wof:geomhash":"56fa787ba54e7a64aeabe0b2743e6747","wof:hierarchy":[{"continent_id":102191581,"country_id":85633135,"county_id":1713305707,"localadmin_id":1713313313,"locality_id":1259858769,"region_id":85683013}],"wof:id":1259858769,"wof:lang_x_official":["est"],"wof:lang_x_spoken":["est"],"wof:lastmodified":1596677036,"wof:name":"Maelivere","wof:parent_id":1713313313,"wof:placetype":"locality","wof:repo":"whosonfirst-data-admin-ee","wof:superseded_by":[],"wof:supersedes":[],"wof:tags":[]},"bbox":[24.79972,59.11111,24.79972,59.11111],"geometry":{"coordinates":[24.79972,59.11111],"type":"Point"}}