{"id":1276321655,"type":"Feature","properties":{"edtf:cessation":"uuuu","edtf:inception":"uuuu","geom:area":0,"geom:area_square_m":0,"geom:bbox":"24.69944,58.30889,24.69944,58.30889","geom:latitude":58.30889,"geom:longitude":24.69944,"gn:admin1_code":"11.0","gn:admin2_code":"624.0","gn:admin3_code":"9113.0","gn:asciiname":"Vaskryama","gn:country_code":"EE","gn:dem":15,"gn:feature_class":"P","gn:feature_code":"PPL","gn:geonameid":587723,"gn:latitude":58.30889,"gn:longitude":24.69944,"gn:modification_date":"2017-11-25","gn:name":"Vaskryama","gn:population":0,"gn:timezone":"Europe/Tallinn","iso:country":"EE","lbl:bbox":"24.67944,58.28889,24.71944,58.32889","lbl:max_zoom":18,"lbl:min_zoom":13.5,"mz:hierarchy_label":1,"mz:is_current":1,"mz:min_zoom":12,"name:und_x_variant":["Vaskrääma"],"src:geom":"geonames","wof:belongsto":[85682981,102191581,1713315055,85633135,1713305703],"wof:breaches":[],"wof:concordances":{"gn:id":587723},"wof:coterminous":[1713315055],"wof:country":"EE","wof:geomhash":"31609962a392b4110d72aa9533e17a12","wof:hierarchy":[{"continent_id":102191581,"country_id":85633135,"county_id":1713305703,"localadmin_id":1713315055,"locality_id":1276321655,"region_id":85682981}],"wof:id":1276321655,"wof:lang_x_official":["est"],"wof:lang_x_spoken":["est"],"wof:lastmodified":1596677705,"wof:name":"Vaskryama","wof:parent_id":1713315055,"wof:placetype":"locality","wof:repo":"whosonfirst-data-admin-ee","wof:superseded_by":[],"wof:supersedes":[],"wof:tags":[]},"bbox":[24.69944,58.30889,24.69944,58.30889],"geometry":{"coordinates":[24.69944,58.30889],"type":"Point"}}