{"id":1310184575,"type":"Feature","properties":{"edtf:cessation":"uuuu","edtf:inception":"uuuu","geom:area":0,"geom:area_square_m":0,"geom:bbox":"24.40111,58.76722,24.40111,58.76722","geom:latitude":58.76722,"geom:longitude":24.40111,"gn:admin1_code":"13.0","gn:admin2_code":"503.0","gn:admin3_code":"6629.0","gn:asciiname":"Paeaerdu-Moisakuela","gn:country_code":"EE","gn:dem":18,"gn:feature_class":"P","gn:feature_code":"PPL","gn:geonameid":8618172,"gn:latitude":58.76722,"gn:longitude":24.40111,"gn:modification_date":"2017-11-25","gn:name":"Päärdu-Mõisaküla","gn:population":0,"gn:timezone":"Europe/Tallinn","iso:country":"EE","lbl:bbox":"24.38111,58.74722,24.42111,58.78722","lbl:max_zoom":18,"lbl:min_zoom":13.5,"mz:hierarchy_label":1,"mz:is_current":1,"mz:min_zoom":12,"name:und_x_variant":["Päärdu-Mõisaküla","Päärdumõisa"],"src:geom":"geonames","wof:belongsto":[85683013,102191581,1713311095,85633135,1713305747],"wof:breaches":[],"wof:concordances":{"gn:id":8618172},"wof:country":"EE","wof:geomhash":"2131e42009d68daf4b3ebe5a688852bb","wof:hierarchy":[{"continent_id":102191581,"country_id":85633135,"county_id":1713305747,"localadmin_id":1713311095,"locality_id":1310184575,"region_id":85683013}],"wof:id":1310184575,"wof:lang_x_official":["est"],"wof:lang_x_spoken":["est"],"wof:lastmodified":1596662844,"wof:name":"Paeaerdu-Moisakuela","wof:parent_id":1713311095,"wof:placetype":"locality","wof:repo":"whosonfirst-data-admin-ee","wof:superseded_by":[],"wof:supersedes":[],"wof:tags":[]},"bbox":[24.40111,58.76722,24.40111,58.76722],"geometry":{"coordinates":[24.40111,58.76722],"type":"Point"}}