{"id":1210002063,"type":"Feature","properties":{"edtf:cessation":"uuuu","edtf:inception":"uuuu","geom:area":0,"geom:area_square_m":0,"geom:bbox":"25.99444,59.07167,25.99444,59.07167","geom:latitude":59.07167,"geom:longitude":25.99444,"gn:admin1_code":"8.0","gn:admin2_code":"792.0","gn:admin3_code":"2334.0","gn:asciiname":"Jaersi","gn:country_code":"EE","gn:dem":109,"gn:feature_class":"P","gn:feature_code":"PPL","gn:geonameid":591970,"gn:latitude":59.07167,"gn:longitude":25.99444,"gn:modification_date":"2017-11-25","gn:name":"Järsi","gn:population":0,"gn:timezone":"Europe/Tallinn","iso:country":"EE","lbl:bbox":"25.97444,59.05167,26.01444,59.09167","lbl:max_zoom":18,"lbl:min_zoom":13.5,"mz:hierarchy_label":1,"mz:is_current":1,"mz:min_zoom":12,"name:est_x_preferred":["Järsi"],"name:hye_x_preferred":["Եռսի"],"name:pol_x_preferred":["Järsi"],"name:ukr_x_preferred":["Ярсі"],"name:urd_x_preferred":["جارسی"],"name:vol_x_preferred":["Järsi"],"src:geom":"geonames","wof:belongsto":[85683049,102191581,1713314609,85633135,1713305761],"wof:breaches":[],"wof:concordances":{"gn:id":591970,"wk:page":"J%C3%A4rsi%2C_L%C3%A4%C3%A4ne-Viru_County"},"wof:coterminous":[1713314609],"wof:country":"EE","wof:geomhash":"82210fe30e0f2653beae6865eaefc4c0","wof:hierarchy":[{"continent_id":102191581,"country_id":85633135,"county_id":1713305761,"localadmin_id":1713314609,"locality_id":1210002063,"region_id":85683049}],"wof:id":1210002063,"wof:lang_x_official":["est"],"wof:lang_x_spoken":["est"],"wof:lastmodified":1596676605,"wof:name":"Jaersi","wof:parent_id":1713314609,"wof:placetype":"locality","wof:repo":"whosonfirst-data-admin-ee","wof:superseded_by":[],"wof:supersedes":[],"wof:tags":[]},"bbox":[25.99444,59.07167,25.99444,59.07167],"geometry":{"coordinates":[25.99444,59.07167],"type":"Point"}}