{"id":1277088425,"type":"Feature","properties":{"edtf:cessation":"uuuu","edtf:inception":"uuuu","geom:area":0,"geom:area_square_m":0,"geom:bbox":"24.07917,59.15667,24.07917,59.15667","geom:latitude":59.15667,"geom:longitude":24.07917,"gn:admin1_code":"1.0","gn:admin2_code":"431.0","gn:admin3_code":"4931.0","gn:asciiname":"Metslougu","gn:cc2":"EE","gn:country_code":"EE","gn:dem":24,"gn:feature_class":"P","gn:feature_code":"PPL","gn:geonameid":590216,"gn:latitude":59.15667,"gn:longitude":24.07917,"gn:modification_date":"2017-11-25","gn:name":"Metslõugu","gn:population":0,"gn:timezone":"Europe/Tallinn","iso:country":"EE","lbl:bbox":"24.05917,59.13667,24.09917,59.17667","lbl:max_zoom":18,"lbl:min_zoom":13.5,"mz:hierarchy_label":1,"mz:is_current":1,"mz:min_zoom":12,"name:est_x_preferred":["Metslõugu"],"name:fra_x_preferred":["Metslõugu"],"name:hye_x_preferred":["Մեցլիուգու"],"name:pol_x_preferred":["Metslõugu"],"name:spa_x_preferred":["Metslõugu"],"name:ukr_x_preferred":["Метслиуґу"],"name:und_x_variant":["Metslyugu"],"name:vol_x_preferred":["Metslõugu"],"src:geom":"geonames","wof:belongsto":[85683055,102191581,1713315335,85633135,1713305737],"wof:breaches":[],"wof:concordances":{"gn:id":590216,"wk:page":"Metsl%C3%B5ugu"},"wof:coterminous":[1713315335],"wof:country":"EE","wof:geomhash":"21e2f3e152e799574ed7feb440c5de01","wof:hierarchy":[{"continent_id":102191581,"country_id":85633135,"county_id":1713305737,"localadmin_id":1713315335,"locality_id":1277088425,"region_id":85683055}],"wof:id":1277088425,"wof:lang_x_official":["est"],"wof:lang_x_spoken":["est"],"wof:lastmodified":1596663327,"wof:name":"Metslougu","wof:parent_id":1713315335,"wof:placetype":"locality","wof:repo":"whosonfirst-data-admin-ee","wof:superseded_by":[],"wof:supersedes":[],"wof:tags":[]},"bbox":[24.07917,59.15667,24.07917,59.15667],"geometry":{"coordinates":[24.07917,59.15667],"type":"Point"}}