{"id":1260145997,"type":"Feature","properties":{"edtf:cessation":"uuuu","edtf:inception":"uuuu","geom:area":0,"geom:area_square_m":0,"geom:bbox":"26.31278,57.64028,26.31278,57.64028","geom:latitude":57.64028,"geom:longitude":26.31278,"gn:admin1_code":"19.0","gn:admin2_code":"855.0","gn:admin3_code":"4024.0","gn:asciiname":"Korkuna","gn:country_code":"EE","gn:dem":67,"gn:feature_class":"P","gn:feature_code":"PPL","gn:geonameid":794489,"gn:latitude":57.64028,"gn:longitude":26.31278,"gn:modification_date":"2017-11-25","gn:name":"Korkuna","gn:population":0,"gn:timezone":"Europe/Tallinn","iso:country":"EE","lbl:bbox":"26.29278,57.62028,26.33278,57.66028","lbl:max_zoom":18,"lbl:min_zoom":13.5,"mz:hierarchy_label":1,"mz:is_current":1,"mz:min_zoom":12,"name:est_x_preferred":["Korkuna"],"name:hye_x_preferred":["Կոռկունա"],"name:spa_x_preferred":["Korkuna"],"name:ukr_x_preferred":["Коркуна"],"name:vol_x_preferred":["Korkuna"],"src:geom":"geonames","wof:belongsto":[85682941,102191581,1713313401,85633135,1713305753],"wof:breaches":[],"wof:concordances":{"gn:id":794489,"wk:page":"Korkuna"},"wof:coterminous":[1713310187],"wof:country":"EE","wof:geomhash":"7082130b3f323736e2db8d6862fc9040","wof:hierarchy":[{"continent_id":102191581,"country_id":85633135,"county_id":1713305753,"localadmin_id":1713313401,"locality_id":1260145997,"region_id":85682941}],"wof:id":1260145997,"wof:lang_x_official":["est"],"wof:lang_x_spoken":["est"],"wof:lastmodified":1596661948,"wof:name":"Korkuna","wof:parent_id":1713313401,"wof:placetype":"locality","wof:repo":"whosonfirst-data-admin-ee","wof:superseded_by":[],"wof:supersedes":[],"wof:tags":[]},"bbox":[26.31278,57.64028,26.31278,57.64028],"geometry":{"coordinates":[26.31278,57.64028],"type":"Point"}}