{"id":1125873615,"type":"Feature","properties":{"edtf:cessation":"uuuu","edtf:inception":"uuuu","geom:area":0,"geom:area_square_m":0,"geom:bbox":"24.90639,59.34222,24.90639,59.34222","geom:latitude":59.34222,"geom:longitude":24.90639,"gn:country":"EE","gn:fcode":"PPL","gn:population":95,"iso:country":"EE","lbl:bbox":"24.88639,59.32222,24.92639,59.36222","lbl:latitude":59.34222,"lbl:longitude":24.90639,"lbl:max_zoom":18,"lbl:min_zoom":13,"mz:hierarchy_label":1,"mz:is_current":1,"mz:min_zoom":11,"mz:note":"Quattroshapes Point Gazetteer import 20170519","name:bul_x_preferred":["Авику"],"name:ceb_x_preferred":["Aaviku"],"name:deu_x_preferred":["Aaviku"],"name:eng_x_preferred":["Aaviku"],"name:est_x_preferred":["Aaviku"],"name:fas_x_preferred":["آویکو، بخش هارجو"],"name:fas_x_variant":["آویکو"],"name:fin_x_preferred":["Aaviku"],"name:fra_x_preferred":["Aaviku"],"name:hye_x_preferred":["Աավիկու"],"name:nld_x_preferred":["Aaviku"],"name:pol_x_preferred":["Aaviku"],"name:spa_x_preferred":["Aaviku"],"name:swe_x_preferred":["Aaviku"],"name:urd_x_preferred":["آویکو، حارجو کاؤنٹی"],"name:urd_x_variant":["آویکو"],"name:vol_x_preferred":["Aaviku"],"qs_pg:aaroncc":"EE","qs_pg:gn_country":"EE","qs_pg:gn_fcode":"PPL","qs_pg:gn_id":794979,"qs_pg:gn_pop":95,"qs_pg:name":"Aaviku","qs_pg:name_adm0":"Eesti","qs_pg:name_adm1":"Harjumaa","qs_pg:photos":524,"qs_pg:photos_1k":106,"qs_pg:photos_9k":2,"qs_pg:photos_9r":5,"qs_pg:photos_all":524,"qs_pg:photos_sr":7,"qs_pg:pop_sr":1,"qs_pg:qs_id":894603,"qs_pg:qs_pg_placetype":"locality","qs_pg:qs_pg_placetype_gp":"Town","qs_pg:woe_adm0":23424805,"qs_pg:woe_id":841813,"src:geom":"qs_pg","src:lbl_centroid":"qs_pg","src:population":"geonames","woe:adm0_id":23424805,"woe:name_adm0":"Eesti","woe:name_adm1":"Harjumaa","woe:placetype":"Town","wof:belongsto":[85683055,102191581,1713305887,85633135,1713305683],"wof:breaches":[],"wof:concordances":{"gn:id":794979,"gp:id":841813,"qs_pg:id":894603,"wd:id":"Q2569273"},"wof:coterminous":[1713305887],"wof:country":"EE","wof:created":1497294425,"wof:geomhash":"eae2b363faf9e9101bd9fdaea1a9a196","wof:hierarchy":[{"continent_id":102191581,"country_id":85633135,"county_id":1713305683,"localadmin_id":1713305887,"locality_id":1125873615,"region_id":85683055}],"wof:id":1125873615,"wof:lang_x_official":["est"],"wof:lang_x_spoken":["est"],"wof:lastmodified":1596661483,"wof:name":"Aaviku","wof:parent_id":1713305887,"wof:placetype":"locality","wof:population":95,"wof:population_rank":1,"wof:repo":"whosonfirst-data-admin-ee","wof:superseded_by":[],"wof:supersedes":[],"wof:tags":[]},"bbox":[24.90639,59.34222,24.90639,59.34222],"geometry":{"coordinates":[24.90639,59.34222],"type":"Point"}}