{"id":1192977473,"type":"Feature","properties":{"edtf:cessation":"uuuu","edtf:inception":"uuuu","geom:area":0,"geom:area_square_m":0,"geom:bbox":"27.11806,57.77583,27.11806,57.77583","geom:latitude":57.77583,"geom:longitude":27.11806,"gn:admin1_code":"21.0","gn:admin2_code":"917.0","gn:admin3_code":"8315.0","gn:asciiname":"Kallasto","gn:country_code":"EE","gn:dem":181,"gn:feature_class":"P","gn:feature_code":"PPL","gn:geonameid":8620192,"gn:latitude":57.77583,"gn:longitude":27.11806,"gn:modification_date":"2017-11-25","gn:name":"Kallastõ","gn:population":0,"gn:timezone":"Europe/Tallinn","iso:country":"EE","lbl:bbox":"27.09806,57.75583,27.13806,57.79583","lbl:max_zoom":18,"lbl:min_zoom":13.5,"mz:hierarchy_label":1,"mz:is_current":1,"mz:min_zoom":12,"name:und_x_variant":["Kallastõ","Kallaste"],"src:geom":"geonames","wof:belongsto":[85682937,102191581,1713315667,85633135,1713305633],"wof:breaches":[],"wof:concordances":{"gn:id":8620192},"wof:country":"EE","wof:geomhash":"afdb0c4029ec57af925edcbc2a661ef6","wof:hierarchy":[{"continent_id":102191581,"country_id":85633135,"county_id":1713305633,"localadmin_id":1713315667,"locality_id":1192977473,"region_id":85682937}],"wof:id":1192977473,"wof:lang_x_official":["est"],"wof:lang_x_spoken":["est"],"wof:lastmodified":1596660392,"wof:name":"Kallasto","wof:parent_id":1713315667,"wof:placetype":"locality","wof:repo":"whosonfirst-data-admin-ee","wof:superseded_by":[],"wof:supersedes":[],"wof:tags":[]},"bbox":[27.11806,57.77583,27.11806,57.77583],"geometry":{"coordinates":[27.11806,57.77583],"type":"Point"}}