{"id":1243247131,"type":"Feature","properties":{"edtf:cessation":"uuuu","edtf:inception":"uuuu","geom:area":0,"geom:area_square_m":0,"geom:bbox":"22.71667,58.51667,22.71667,58.51667","geom:latitude":58.51667,"geom:longitude":22.71667,"gn:admin1_code":"14.0","gn:admin2_code":"714.0","gn:admin3_code":"3437.0","gn:asciiname":"Kopli","gn:country_code":"EE","gn:dem":19,"gn:feature_class":"P","gn:feature_code":"PPL","gn:geonameid":591133,"gn:latitude":58.51667,"gn:longitude":22.71667,"gn:modification_date":"2017-11-25","gn:name":"Kopli","gn:population":0,"gn:timezone":"Europe/Tallinn","iso:country":"EE","lbl:bbox":"22.69667,58.49667,22.73667,58.53667","lbl:max_zoom":18,"lbl:min_zoom":13.5,"mz:hierarchy_label":1,"mz:is_current":1,"mz:min_zoom":12,"name:deu_x_preferred":["Kopli"],"name:est_x_preferred":["Kopli"],"name:hye_x_preferred":["Կոպլի"],"name:pol_x_preferred":["Kopli"],"name:spa_x_preferred":["Kopli"],"name:vol_x_preferred":["Kopli"],"src:geom":"geonames","wof:belongsto":[85682947,102191581,1713307535,85633135,1713305627],"wof:breaches":[],"wof:concordances":{"gn:id":591133,"wk:page":"Kopli%2C_Saare_County"},"wof:coterminous":[1713307535],"wof:country":"EE","wof:geomhash":"748e1b5eaed3949560d52b8ef16d1bf5","wof:hierarchy":[{"continent_id":102191581,"country_id":85633135,"county_id":1713305627,"localadmin_id":1713307535,"locality_id":1243247131,"region_id":85682947}],"wof:id":1243247131,"wof:lang_x_official":["est"],"wof:lang_x_spoken":["est"],"wof:lastmodified":1596674959,"wof:name":"Kopli","wof:parent_id":1713307535,"wof:placetype":"locality","wof:repo":"whosonfirst-data-admin-ee","wof:superseded_by":[],"wof:supersedes":[],"wof:tags":[]},"bbox":[22.71667,58.51667,22.71667,58.51667],"geometry":{"coordinates":[22.71667,58.51667],"type":"Point"}}