{"id":1326827023,"type":"Feature","properties":{"edtf:cessation":"uuuu","edtf:inception":"uuuu","geom:area":0,"geom:area_square_m":0,"geom:bbox":"26.63056,59.33944,26.63056,59.33944","geom:latitude":59.33944,"geom:longitude":26.63056,"gn:admin1_code":"8.0","gn:admin2_code":"901.0","gn:admin3_code":"5521.0","gn:asciiname":"Nommise","gn:cc2":"EE","gn:country_code":"EE","gn:dem":70,"gn:feature_class":"P","gn:feature_code":"PPL","gn:geonameid":589941,"gn:latitude":59.33944,"gn:longitude":26.63056,"gn:modification_date":"2017-11-25","gn:name":"Nõmmise","gn:population":0,"gn:timezone":"Europe/Tallinn","iso:country":"EE","lbl:bbox":"26.61056,59.31944,26.65056,59.35944","lbl:max_zoom":18,"lbl:min_zoom":13.5,"mz:hierarchy_label":1,"mz:is_current":1,"mz:min_zoom":12,"name:est_x_preferred":["Nõmmise"],"name:hye_x_preferred":["Նիմմիսե"],"name:pol_x_preferred":["Nõmmise"],"name:und_x_variant":["Nõmmiste","Nymmise"],"name:vol_x_preferred":["Nõmmise"],"src:geom":"geonames","wof:belongsto":[85683049,102191581,1713308063,85633135,1713305771],"wof:breaches":[],"wof:concordances":{"gn:id":589941,"wk:page":"N%C3%B5mmise"},"wof:coterminous":[1713308063],"wof:country":"EE","wof:geomhash":"20013ff00d08ca9444d35161e1a8925e","wof:hierarchy":[{"continent_id":102191581,"country_id":85633135,"county_id":1713305771,"localadmin_id":1713308063,"locality_id":1326827023,"region_id":85683049}],"wof:id":1326827023,"wof:lang_x_official":["est"],"wof:lang_x_spoken":["est"],"wof:lastmodified":1596677965,"wof:name":"Nommise","wof:parent_id":1713308063,"wof:placetype":"locality","wof:repo":"whosonfirst-data-admin-ee","wof:superseded_by":[],"wof:supersedes":[],"wof:tags":[]},"bbox":[26.63056,59.33944,26.63056,59.33944],"geometry":{"coordinates":[26.63056,59.33944],"type":"Point"}}