{"id":1276652353,"type":"Feature","properties":{"edtf:cessation":"uuuu","edtf:inception":"uuuu","geom:area":0,"geom:area_square_m":0,"geom:bbox":"26.37333,59.47111,26.37333,59.47111","geom:latitude":59.47111,"geom:longitude":26.37333,"gn:admin1_code":"8.0","gn:admin2_code":"191.0","gn:admin3_code":"6093.0","gn:asciiname":"Moislope","gn:country_code":"EE","gn:dem":62,"gn:feature_class":"P","gn:feature_code":"PPL","gn:geonameid":8618722,"gn:latitude":59.47111,"gn:longitude":26.37333,"gn:modification_date":"2017-11-25","gn:name":"Mõislõpe","gn:population":0,"gn:timezone":"Europe/Tallinn","iso:country":"EE","lbl:bbox":"26.35333,59.45111,26.39333,59.49111","lbl:max_zoom":18,"lbl:min_zoom":13.5,"mz:hierarchy_label":1,"mz:is_current":1,"mz:min_zoom":12,"src:geom":"geonames","wof:belongsto":[85683049,102191581,1713315297,85633135,1713305775],"wof:breaches":[],"wof:concordances":{"gn:id":8618722},"wof:country":"EE","wof:geomhash":"32a44ac2017903a30e6ad1465daf2e31","wof:hierarchy":[{"continent_id":102191581,"country_id":85633135,"county_id":1713305775,"localadmin_id":1713315297,"locality_id":1276652353,"region_id":85683049}],"wof:id":1276652353,"wof:lang_x_official":["est"],"wof:lang_x_spoken":["est"],"wof:lastmodified":1596678044,"wof:name":"Moislope","wof:parent_id":1713315297,"wof:placetype":"locality","wof:repo":"whosonfirst-data-admin-ee","wof:superseded_by":[],"wof:supersedes":[],"wof:tags":[]},"bbox":[26.37333,59.47111,26.37333,59.47111],"geometry":{"coordinates":[26.37333,59.47111],"type":"Point"}}