{"id":1210025949,"type":"Feature","properties":{"edtf:cessation":"uuuu","edtf:inception":"uuuu","geom:area":0,"geom:area_square_m":0,"geom:bbox":"25.29444,59.19667,25.29444,59.19667","geom:latitude":59.19667,"geom:longitude":25.29444,"gn:admin1_code":"1.0","gn:admin2_code":"338.0","gn:admin3_code":"9323.0","gn:asciiname":"Vilama","gn:country_code":"EE","gn:dem":83,"gn:feature_class":"P","gn:feature_code":"PPL","gn:geonameid":587599,"gn:latitude":59.19667,"gn:longitude":25.29444,"gn:modification_date":"2017-11-25","gn:name":"Vilama","gn:population":0,"gn:timezone":"Europe/Tallinn","iso:country":"EE","lbl:bbox":"25.27444,59.17667,25.31444,59.21667","lbl:max_zoom":18,"lbl:min_zoom":13.5,"mz:hierarchy_label":1,"mz:is_current":1,"mz:min_zoom":12,"name:est_x_preferred":["Vilama"],"name:fra_x_preferred":["Vilama"],"name:hye_x_preferred":["Վիլամա"],"name:nld_x_preferred":["Vilama"],"name:pol_x_preferred":["Vilama"],"name:spa_x_preferred":["Vilama"],"name:vol_x_preferred":["Vilama"],"src:geom":"geonames","wof:belongsto":[85683055,102191581,1713306439,85633135,1713305665],"wof:breaches":[],"wof:concordances":{"gn:id":587599,"wk:page":"Vilama"},"wof:coterminous":[1713306439],"wof:country":"EE","wof:geomhash":"7e52bf6a08ca02ecf2ad4d68d5998991","wof:hierarchy":[{"continent_id":102191581,"country_id":85633135,"county_id":1713305665,"localadmin_id":1713306439,"locality_id":1210025949,"region_id":85683055}],"wof:id":1210025949,"wof:lang_x_official":["est"],"wof:lang_x_spoken":["est"],"wof:lastmodified":1596661349,"wof:name":"Vilama","wof:parent_id":1713306439,"wof:placetype":"locality","wof:repo":"whosonfirst-data-admin-ee","wof:superseded_by":[],"wof:supersedes":[],"wof:tags":[]},"bbox":[25.29444,59.19667,25.29444,59.19667],"geometry":{"coordinates":[25.29444,59.19667],"type":"Point"}}