{"id":1360049881,"type":"Feature","properties":{"edtf:cessation":"uuuu","edtf:inception":"uuuu","geom:area":0,"geom:area_square_m":0,"geom:bbox":"27.06639,57.77389,27.06639,57.77389","geom:latitude":57.77389,"geom:longitude":27.06639,"gn:admin1_code":"21.0","gn:admin2_code":"917.0","gn:admin3_code":"3333.0","gn:asciiname":"Kolepi","gn:country_code":"EE","gn:dem":195,"gn:feature_class":"P","gn:feature_code":"PPL","gn:geonameid":794309,"gn:latitude":57.77389,"gn:longitude":27.06639,"gn:modification_date":"2017-11-25","gn:name":"Kolepi","gn:population":0,"gn:timezone":"Europe/Tallinn","iso:country":"EE","lbl:bbox":"27.04639,57.75389,27.08639,57.79389","lbl:max_zoom":18,"lbl:min_zoom":13.5,"mz:hierarchy_label":1,"mz:is_current":1,"mz:min_zoom":12,"name:est_x_preferred":["Kolepi"],"name:hye_x_preferred":["Կոլեպի"],"name:pol_x_preferred":["Kolepi"],"name:spa_x_preferred":["Kolepi"],"name:ukr_x_preferred":["Колепі"],"name:vol_x_preferred":["Kolepi"],"src:geom":"geonames","wof:belongsto":[85682937,102191581,1713316225,85633135,1713305633],"wof:breaches":[],"wof:concordances":{"gn:id":794309,"wk:page":"Kolepi"},"wof:coterminous":[1713316225],"wof:country":"EE","wof:geomhash":"d8df79ec77af4dea6d0f3959ce4e5ea2","wof:hierarchy":[{"continent_id":102191581,"country_id":85633135,"county_id":1713305633,"localadmin_id":1713316225,"locality_id":1360049881,"region_id":85682937}],"wof:id":1360049881,"wof:lang_x_official":["est"],"wof:lang_x_spoken":["est"],"wof:lastmodified":1596660393,"wof:name":"Kolepi","wof:parent_id":1713316225,"wof:placetype":"locality","wof:repo":"whosonfirst-data-admin-ee","wof:superseded_by":[],"wof:supersedes":[],"wof:tags":[]},"bbox":[27.06639,57.77389,27.06639,57.77389],"geometry":{"coordinates":[27.06639,57.77389],"type":"Point"}}