{"id":1310498213,"type":"Feature","properties":{"edtf:cessation":"uuuu","edtf:inception":"uuuu","geom:area":0,"geom:area_square_m":0,"geom:bbox":"23.85639,58.98444,23.85639,58.98444","geom:latitude":58.98444,"geom:longitude":23.85639,"gn:admin1_code":"7.0","gn:admin2_code":"441.0","gn:admin3_code":"9254.0","gn:asciiname":"Veski","gn:country_code":"EE","gn:dem":22,"gn:feature_class":"P","gn:feature_code":"PPL","gn:geonameid":587657,"gn:latitude":58.98444,"gn:longitude":23.85639,"gn:modification_date":"2017-11-25","gn:name":"Veski","gn:population":0,"gn:timezone":"Europe/Tallinn","iso:country":"EE","lbl:bbox":"23.83639,58.96444,23.87639,59.00444","lbl:max_zoom":18,"lbl:min_zoom":13.5,"mz:hierarchy_label":1,"mz:is_current":1,"mz:min_zoom":12,"name:deu_x_preferred":["Veski"],"name:est_x_preferred":["Veski"],"name:pol_x_preferred":["Veski"],"name:rus_x_preferred":["Вески"],"name:sco_x_preferred":["Veski"],"name:und_x_variant":["Veskiküla"],"src:geom":"geonames","wof:belongsto":[85683001,102191581,1713309045,85633135,1713305701],"wof:breaches":[],"wof:concordances":{"gn:id":587657},"wof:country":"EE","wof:geomhash":"cc6b8fb591362f6f20e788fd293eb7e9","wof:hierarchy":[{"continent_id":102191581,"country_id":85633135,"county_id":1713305701,"localadmin_id":1713309045,"locality_id":1310498213,"region_id":85683001}],"wof:id":1310498213,"wof:lang_x_official":["est"],"wof:lang_x_spoken":["est"],"wof:lastmodified":1596677432,"wof:name":"Veski","wof:parent_id":1713309045,"wof:placetype":"locality","wof:repo":"whosonfirst-data-admin-ee","wof:superseded_by":[],"wof:supersedes":[],"wof:tags":[]},"bbox":[23.85639,58.98444,23.85639,58.98444],"geometry":{"coordinates":[23.85639,58.98444],"type":"Point"}}