{"id":1344138029,"type":"Feature","properties":{"edtf:cessation":"uuuu","edtf:inception":"uuuu","geom:area":0,"geom:area_square_m":0,"geom:bbox":"23.76667,58.41667,23.76667,58.41667","geom:latitude":58.41667,"geom:longitude":23.76667,"gn:admin1_code":"11.0","gn:admin2_code":"430.0","gn:admin3_code":"1366.0","gn:asciiname":"Uue-Varbla","gn:cc2":"EE","gn:country_code":"EE","gn:dem":28,"gn:feature_class":"P","gn:feature_code":"PPL","gn:geonameid":588008,"gn:latitude":58.41667,"gn:longitude":23.76667,"gn:modification_date":"2017-11-25","gn:name":"Uue-Varbla","gn:population":0,"gn:timezone":"Europe/Tallinn","iso:country":"EE","lbl:bbox":"23.74667,58.39667,23.78667,58.43667","lbl:max_zoom":18,"lbl:min_zoom":13.5,"mz:hierarchy_label":1,"mz:is_current":1,"mz:min_zoom":12,"name:und_x_variant":["Myza Us Varbla","Varbla","Uue-Varbla"],"src:geom":"geonames","wof:belongsto":[85683001,102191581,1713309389,85633135,1713305721],"wof:breaches":[],"wof:concordances":{"gn:id":588008},"wof:country":"EE","wof:geomhash":"197349e92c5fb98042785b3a4203d7f9","wof:hierarchy":[{"continent_id":102191581,"country_id":85633135,"county_id":1713305721,"localadmin_id":1713309389,"locality_id":1344138029,"region_id":85683001}],"wof:id":1344138029,"wof:lang_x_official":["est"],"wof:lang_x_spoken":["est"],"wof:lastmodified":1596661700,"wof:name":"Uue-Varbla","wof:parent_id":1713309389,"wof:placetype":"locality","wof:repo":"whosonfirst-data-admin-ee","wof:superseded_by":[],"wof:supersedes":[],"wof:tags":[]},"bbox":[23.76667,58.41667,23.76667,58.41667],"geometry":{"coordinates":[23.76667,58.41667],"type":"Point"}}