{"id":1226724459,"type":"Feature","properties":{"edtf:cessation":"uuuu","edtf:inception":"uuuu","geom:area":0,"geom:area_square_m":0,"geom:bbox":"25.69083,58.64417,25.69083,58.64417","geom:latitude":58.64417,"geom:longitude":25.69083,"gn:admin1_code":"20.0","gn:admin2_code":"615.0","gn:admin3_code":"3142.0","gn:asciiname":"Arussaare","gn:country_code":"EE","gn:dem":53,"gn:feature_class":"P","gn:feature_code":"PPL","gn:geonameid":592385,"gn:latitude":58.64417,"gn:longitude":25.69083,"gn:modification_date":"2017-11-25","gn:name":"Arussaare","gn:population":0,"gn:timezone":"Europe/Tallinn","iso:country":"EE","lbl:bbox":"25.67083,58.62417,25.71083,58.66417","lbl:max_zoom":18,"lbl:min_zoom":13.5,"mz:hierarchy_label":1,"mz:is_current":1,"mz:min_zoom":12,"name:est_x_preferred":["Arussaare"],"name:hye_x_preferred":["Առուսաառե"],"name:nld_x_preferred":["Arussaare"],"name:pol_x_preferred":["Arussaare"],"name:spa_x_preferred":["Arussaare"],"name:ukr_x_preferred":["Аруссааре"],"name:vol_x_preferred":["Arussaare"],"src:geom":"geonames","wof:belongsto":[85682985,102191581,1713314131,85633135,1713305735],"wof:breaches":[],"wof:concordances":{"gn:id":592385,"wk:page":"Arussaare"},"wof:coterminous":[1713311717],"wof:country":"EE","wof:geomhash":"6c4cda1e36e15f34c482544ccfa64677","wof:hierarchy":[{"continent_id":102191581,"country_id":85633135,"county_id":1713305735,"localadmin_id":1713314131,"locality_id":1226724459,"region_id":85682985}],"wof:id":1226724459,"wof:lang_x_official":["est"],"wof:lang_x_spoken":["est"],"wof:lastmodified":1596663453,"wof:name":"Arussaare","wof:parent_id":1713314131,"wof:placetype":"locality","wof:repo":"whosonfirst-data-admin-ee","wof:superseded_by":[],"wof:supersedes":[],"wof:tags":[]},"bbox":[25.69083,58.64417,25.69083,58.64417],"geometry":{"coordinates":[25.69083,58.64417],"type":"Point"}}