{"id":1126037765,"type":"Feature","properties":{"edtf:cessation":"uuuu","edtf:inception":"uuuu","geom:area":0,"geom:area_square_m":0,"geom:bbox":"25.73167,58.6575,25.73167,58.6575","geom:latitude":58.6575,"geom:longitude":25.73167,"gn:country":"EE","gn:fcode":"PPL","gn:population":123,"iso:country":"EE","lbl:bbox":"25.71167,58.6375,25.75167,58.6775","lbl:latitude":58.6575,"lbl:longitude":25.73167,"lbl:max_zoom":18,"lbl:min_zoom":13,"mz:hierarchy_label":1,"mz:is_current":1,"mz:min_zoom":11,"mz:note":"Quattroshapes Point Gazetteer import 20170519","name:bul_x_preferred":["Пилиствере"],"name:ceb_x_preferred":["Pilistvere"],"name:deu_x_preferred":["Pilistvere"],"name:eng_x_preferred":["Pilistvere"],"name:est_x_preferred":["Pilistvere"],"name:fin_x_preferred":["Pilistvere"],"name:fra_x_preferred":["Pilistvere"],"name:hye_x_preferred":["Պիլիստվեռե"],"name:jpn_x_preferred":["ピリストヴェレ"],"name:nld_x_preferred":["Pilistvere"],"name:pol_x_preferred":["Pilistvere"],"name:rus_x_preferred":["Пилиствере"],"name:spa_x_preferred":["Pilistvere"],"name:swe_x_preferred":["Pilistvere"],"name:ukr_x_preferred":["Піліствере"],"name:und_x_variant":["Pillistfer"],"name:vol_x_preferred":["Pilistvere"],"qs_pg:aaroncc":"EE","qs_pg:gn_country":"EE","qs_pg:gn_fcode":"PPL","qs_pg:gn_id":589440,"qs_pg:gn_pop":123,"qs_pg:name":"Pilistvere","qs_pg:name_adm0":"Eesti","qs_pg:name_adm1":"Viljandimaa","qs_pg:photos_9k":1,"qs_pg:photos_9r":1,"qs_pg:photos_all":16,"qs_pg:photos_sr":0,"qs_pg:pop_sr":1,"qs_pg:qs_id":966867,"qs_pg:qs_pg_placetype":"locality","qs_pg:qs_pg_placetype_gp":"Town","qs_pg:woe_adm0":23424805,"qs_pg:woe_id":844761,"src:geom":"qs_pg","src:lbl_centroid":"qs_pg","src:population":"geonames","woe:adm0_id":23424805,"woe:name_adm0":"Eesti","woe:name_adm1":"Viljandimaa","woe:placetype":"Town","wof:belongsto":[85682985,102191581,1713311723,85633135,1713305735],"wof:breaches":[],"wof:concordances":{"gn:id":589440,"gp:id":844761,"qs_pg:id":966867,"wd:id":"Q646325"},"wof:coterminous":[1713311723],"wof:country":"EE","wof:created":1497301905,"wof:geomhash":"dd4057700a52178a78a8c73c539efed2","wof:hierarchy":[{"continent_id":102191581,"country_id":85633135,"county_id":1713305735,"localadmin_id":1713311723,"locality_id":1126037765,"region_id":85682985}],"wof:id":1126037765,"wof:lang_x_official":["est"],"wof:lang_x_spoken":["est"],"wof:lastmodified":1596663465,"wof:name":"Pilistvere","wof:parent_id":1713311723,"wof:placetype":"locality","wof:population":123,"wof:population_rank":1,"wof:repo":"whosonfirst-data-admin-ee","wof:superseded_by":[],"wof:supersedes":[],"wof:tags":[]},"bbox":[25.73167,58.6575,25.73167,58.6575],"geometry":{"coordinates":[25.73167,58.6575],"type":"Point"}}