{"id":1209792833,"type":"Feature","properties":{"edtf:cessation":"uuuu","edtf:inception":"uuuu","geom:area":0,"geom:area_square_m":0,"geom:bbox":"27.50472,58.07889,27.50472,58.07889","geom:latitude":58.07889,"geom:longitude":27.50472,"gn:admin1_code":"12.0","gn:admin2_code":"708.0","gn:admin3_code":"7016.0","gn:asciiname":"Lokuta","gn:country_code":"EE","gn:dem":33,"gn:feature_class":"P","gn:feature_code":"PPL","gn:geonameid":8620832,"gn:latitude":58.07889,"gn:longitude":27.50472,"gn:modification_date":"2017-11-25","gn:name":"Lokuta","gn:population":0,"gn:timezone":"Europe/Tallinn","iso:country":"EE","lbl:bbox":"27.48472,58.05889,27.52472,58.09889","lbl:max_zoom":18,"lbl:min_zoom":13.5,"mz:hierarchy_label":1,"mz:is_current":1,"mz:min_zoom":12,"name:ceb_x_preferred":["Lokuta"],"name:est_x_preferred":["Lokuta"],"name:fra_x_preferred":["Lokuta"],"name:hye_x_preferred":["Լոկուտա"],"name:pol_x_preferred":["Lokuta"],"name:sco_x_preferred":["Lokuta"],"name:swe_x_preferred":["Lokuta"],"name:ukr_x_preferred":["Локута"],"name:und_x_variant":["Lokota"],"name:vol_x_preferred":["Lokuta"],"src:geom":"geonames","wof:belongsto":[85682955,102191581,1713311035,85633135,1713305793],"wof:breaches":[],"wof:concordances":{"gn:id":8620832},"wof:country":"EE","wof:geomhash":"fc1b9e40914c535e372848c9dd25dc7f","wof:hierarchy":[{"continent_id":102191581,"country_id":85633135,"county_id":1713305793,"localadmin_id":1713311035,"locality_id":1209792833,"region_id":85682955}],"wof:id":1209792833,"wof:lang_x_official":["est"],"wof:lang_x_spoken":["est"],"wof:lastmodified":1596676999,"wof:name":"Lokuta","wof:parent_id":1713311035,"wof:placetype":"locality","wof:repo":"whosonfirst-data-admin-ee","wof:superseded_by":[],"wof:supersedes":[],"wof:tags":[]},"bbox":[27.50472,58.07889,27.50472,58.07889],"geometry":{"coordinates":[27.50472,58.07889],"type":"Point"}}