{"id":1343960949,"type":"Feature","properties":{"edtf:cessation":"uuuu","edtf:inception":"uuuu","geom:area":0,"geom:area_square_m":0,"geom:bbox":"22.90167,58.95641,22.90167,58.95641","geom:latitude":58.95641,"geom:longitude":22.90167,"gn:admin1_code":"2.0","gn:admin2_code":"205.0","gn:admin3_code":"6660.0","gn:asciiname":"Harju","gn:country_code":"EE","gn:dem":13,"gn:feature_class":"P","gn:feature_code":"PPL","gn:geonameid":592171,"gn:latitude":58.95641,"gn:longitude":22.90167,"gn:modification_date":"2017-11-25","gn:name":"Harju","gn:population":0,"gn:timezone":"Europe/Tallinn","iso:country":"EE","lbl:bbox":"22.88167,58.93641,22.92167,58.97641","lbl:max_zoom":18,"lbl:min_zoom":13.5,"mz:hierarchy_label":1,"mz:is_current":1,"mz:min_zoom":12,"name:und_x_variant":["Khar’yu","Harju"],"src:geom":"geonames","wof:belongsto":[85682989,102191581,1713310233,85633135,1713305629],"wof:breaches":[],"wof:concordances":{"gn:id":592171,"wk:page":"Harju%2C_P%C3%BChalepa_Parish"},"wof:country":"EE","wof:geomhash":"1e93feafb5de352a47fe830118c776fd","wof:hierarchy":[{"continent_id":102191581,"country_id":85633135,"county_id":1713305629,"localadmin_id":1713310233,"locality_id":1343960949,"region_id":85682989}],"wof:id":1343960949,"wof:lang_x_official":["est"],"wof:lang_x_spoken":["est"],"wof:lastmodified":1596670020,"wof:name":"Harju","wof:parent_id":1713310233,"wof:placetype":"locality","wof:repo":"whosonfirst-data-admin-ee","wof:superseded_by":[],"wof:supersedes":[],"wof:tags":[]},"bbox":[22.90167,58.95641,22.90167,58.95641],"geometry":{"coordinates":[22.90167,58.95641],"type":"Point"}}