{"id":1310662457,"type":"Feature","properties":{"edtf:cessation":"uuuu","edtf:inception":"uuuu","geom:area":0,"geom:area_square_m":0,"geom:bbox":"25.48056,58.32583,25.48056,58.32583","geom:latitude":58.32583,"geom:longitude":25.48056,"gn:admin1_code":"20.0","gn:admin2_code":"899.0","gn:admin3_code":"1794.0","gn:asciiname":"Kasekuela","gn:country_code":"EE","gn:dem":60,"gn:feature_class":"P","gn:feature_code":"PPL","gn:geonameid":8620425,"gn:latitude":58.32583,"gn:longitude":25.48056,"gn:modification_date":"2017-11-25","gn:name":"Kasek체la","gn:population":0,"gn:timezone":"Europe/Tallinn","iso:country":"EE","lbl:bbox":"25.46056,58.30583,25.50056,58.34583","lbl:max_zoom":18,"lbl:min_zoom":13.5,"mz:hierarchy_label":1,"mz:is_current":1,"mz:min_zoom":12,"name:und_x_variant":["Kasek체la","Kasek체l채"],"src:geom":"geonames","wof:belongsto":[85682985,102191581,1713309803,85633135,1713305669],"wof:breaches":[],"wof:concordances":{"gn:id":8620425},"wof:country":"EE","wof:geomhash":"971358aa113dec97b9c95d7d4bff9663","wof:hierarchy":[{"continent_id":102191581,"country_id":85633135,"county_id":1713305669,"localadmin_id":1713309803,"locality_id":1310662457,"region_id":85682985}],"wof:id":1310662457,"wof:lang_x_official":["est"],"wof:lang_x_spoken":["est"],"wof:lastmodified":1596661254,"wof:name":"Kasekuela","wof:parent_id":1713309803,"wof:placetype":"locality","wof:repo":"whosonfirst-data-admin-ee","wof:superseded_by":[],"wof:supersedes":[],"wof:tags":[]},"bbox":[25.48056,58.32583,25.48056,58.32583],"geometry":{"coordinates":[25.48056,58.32583],"type":"Point"}}