{"id":1260352281,"type":"Feature","properties":{"edtf:cessation":"uuuu","edtf:inception":"uuuu","geom:area":0,"geom:area_square_m":0,"geom:bbox":"26.88444,58.32194,26.88444,58.32194","geom:latitude":58.32194,"geom:longitude":26.88444,"gn:admin1_code":"18.0","gn:admin2_code":"291.0","gn:admin3_code":"3315.0","gn:asciiname":"Koke","gn:country_code":"EE","gn:dem":53,"gn:feature_class":"P","gn:feature_code":"PPL","gn:geonameid":794115,"gn:latitude":58.32194,"gn:longitude":26.88444,"gn:modification_date":"2017-11-25","gn:name":"Koke","gn:population":0,"gn:timezone":"Europe/Tallinn","iso:country":"EE","lbl:bbox":"26.86444,58.30194,26.90444,58.34194","lbl:max_zoom":18,"lbl:min_zoom":13.5,"mz:hierarchy_label":1,"mz:is_current":1,"mz:min_zoom":12,"name:est_x_preferred":["Koke"],"name:fra_x_preferred":["Koke"],"name:hye_x_preferred":["Կոկե"],"name:pol_x_preferred":["Koke"],"name:spa_x_preferred":["Koke"],"name:ukr_x_preferred":["Коке"],"name:vol_x_preferred":["Koke"],"src:geom":"geonames","wof:belongsto":[85682995,102191581,1713311417,85633135,1713305699],"wof:breaches":[],"wof:concordances":{"gn:id":794115,"wk:page":"Koke%2C_Estonia"},"wof:coterminous":[1713311417],"wof:country":"EE","wof:geomhash":"91e308c653e145b6f201be0db8a9d762","wof:hierarchy":[{"continent_id":102191581,"country_id":85633135,"county_id":1713305699,"localadmin_id":1713311417,"locality_id":1260352281,"region_id":85682995}],"wof:id":1260352281,"wof:lang_x_official":["est"],"wof:lang_x_spoken":["est"],"wof:lastmodified":1596660661,"wof:name":"Koke","wof:parent_id":1713311417,"wof:placetype":"locality","wof:repo":"whosonfirst-data-admin-ee","wof:superseded_by":[],"wof:supersedes":[],"wof:tags":[]},"bbox":[26.88444,58.32194,26.88444,58.32194],"geometry":{"coordinates":[26.88444,58.32194],"type":"Point"}}