{"id":1276562411,"type":"Feature","properties":{"edtf:cessation":"uuuu","edtf:inception":"uuuu","geom:area":0,"geom:area_square_m":0,"geom:bbox":"24.13667,59.25389,24.13667,59.25389","geom:latitude":59.25389,"geom:longitude":24.13667,"gn:admin1_code":"1.0","gn:admin2_code":"431.0","gn:admin3_code":"2731.0","gn:asciiname":"Karilepa","gn:country_code":"EE","gn:dem":11,"gn:feature_class":"P","gn:feature_code":"PPL","gn:geonameid":591611,"gn:latitude":59.25389,"gn:longitude":24.13667,"gn:modification_date":"2017-11-25","gn:name":"Karilepa","gn:population":0,"gn:timezone":"Europe/Tallinn","iso:country":"EE","lbl:bbox":"24.11667,59.23389,24.15667,59.27389","lbl:max_zoom":18,"lbl:min_zoom":13.5,"mz:hierarchy_label":1,"mz:is_current":1,"mz:min_zoom":12,"name:est_x_preferred":["Karilepa"],"name:fra_x_preferred":["Karilepa"],"name:hye_x_preferred":["Կառիլեպա"],"name:pol_x_preferred":["Karilepa"],"name:spa_x_preferred":["Karilepa"],"name:ukr_x_preferred":["Карілепа"],"name:vol_x_preferred":["Karilepa"],"src:geom":"geonames","wof:belongsto":[85683055,102191581,1713307771,85633135,1713305737],"wof:breaches":[],"wof:concordances":{"gn:id":591611,"wk:page":"Karilepa"},"wof:coterminous":[1713307771],"wof:country":"EE","wof:geomhash":"b3a8e3178da456186848a870d1f8592b","wof:hierarchy":[{"continent_id":102191581,"country_id":85633135,"county_id":1713305737,"localadmin_id":1713307771,"locality_id":1276562411,"region_id":85683055}],"wof:id":1276562411,"wof:lang_x_official":["est"],"wof:lang_x_spoken":["est"],"wof:lastmodified":1596663328,"wof:name":"Karilepa","wof:parent_id":1713307771,"wof:placetype":"locality","wof:repo":"whosonfirst-data-admin-ee","wof:superseded_by":[],"wof:supersedes":[],"wof:tags":[]},"bbox":[24.13667,59.25389,24.13667,59.25389],"geometry":{"coordinates":[24.13667,59.25389],"type":"Point"}}