{"id":1292910999,"type":"Feature","properties":{"edtf:cessation":"uuuu","edtf:inception":"uuuu","geom:area":0,"geom:area_square_m":0,"geom:bbox":"27.08333,58.95444,27.08333,58.95444","geom:latitude":58.95444,"geom:longitude":27.08333,"gn:admin1_code":"5.0","gn:admin2_code":"486.0","gn:admin3_code":"4459.0","gn:asciiname":"Lagedi","gn:country_code":"EE","gn:dem":36,"gn:feature_class":"P","gn:feature_code":"PPL","gn:geonameid":8618442,"gn:latitude":58.95444,"gn:longitude":27.08333,"gn:modification_date":"2017-11-25","gn:name":"Lagedi","gn:population":0,"gn:timezone":"Europe/Tallinn","iso:country":"EE","lbl:bbox":"27.06333,58.93444,27.10333,58.97444","lbl:max_zoom":18,"lbl:min_zoom":13.5,"mz:hierarchy_label":1,"mz:is_current":1,"mz:is_funky":1,"mz:min_zoom":12,"name:ceb_x_preferred":["Lagedi"],"name:deu_x_preferred":["Lagedi"],"name:est_x_preferred":["Lagedi"],"name:fra_x_preferred":["Lagedi"],"name:hye_x_preferred":["Լագեդի"],"name:lit_x_preferred":["Lagedi"],"name:nld_x_preferred":["Lagedi"],"name:pol_x_preferred":["Lagedi"],"name:sco_x_preferred":["Lagedi"],"name:spa_x_preferred":["Lagedi"],"name:swe_x_preferred":["Lagedi"],"name:und_x_variant":["Lageda"],"name:urd_x_preferred":["لاگیڈی"],"name:vol_x_preferred":["Lagedi"],"src:geom":"geonames","wof:belongsto":[85683059,102191581,1713312055,85633135,1713305677],"wof:breaches":[],"wof:concordances":{"gn:id":8618442},"wof:country":"EE","wof:geomhash":"5e58b177554e0a0db802fabe46fb4f1e","wof:hierarchy":[{"continent_id":102191581,"country_id":85633135,"county_id":1713305677,"localadmin_id":1713312055,"locality_id":1292910999,"region_id":85683059}],"wof:id":1292910999,"wof:lang_x_official":["est"],"wof:lang_x_spoken":["est"],"wof:lastmodified":1596661007,"wof:name":"Lagedi","wof:parent_id":1713312055,"wof:placetype":"locality","wof:repo":"whosonfirst-data-admin-ee","wof:superseded_by":[],"wof:supersedes":[],"wof:tags":[]},"bbox":[27.08333,58.95444,27.08333,58.95444],"geometry":{"coordinates":[27.08333,58.95444],"type":"Point"}}