{"id":1126003571,"type":"Feature","properties":{"edtf:cessation":"uuuu","edtf:inception":"uuuu","geom:area":0,"geom:area_square_m":0,"geom:bbox":"27.36778,59.36417,27.36778,59.36417","geom:latitude":59.36417,"geom:longitude":27.36778,"gn:country":"EE","gn:fcode":"PPL","gn:population":198,"iso:country":"EE","lbl:bbox":"27.34778,59.34417,27.38778,59.38417","lbl:latitude":59.36417,"lbl:longitude":27.36778,"lbl:max_zoom":18,"lbl:min_zoom":13,"mz:hierarchy_label":1,"mz:is_current":1,"mz:min_zoom":11,"mz:note":"Quattroshapes Point Gazetteer import 20170519","name:bul_x_preferred":["Едисе"],"name:ceb_x_preferred":["Edise"],"name:deu_x_preferred":["Edise"],"name:eng_x_preferred":["Edise"],"name:est_x_preferred":["Edise"],"name:fra_x_preferred":["Edise"],"name:hye_x_preferred":["Էդիսե"],"name:nld_x_preferred":["Edise"],"name:pol_x_preferred":["Edise"],"name:spa_x_preferred":["Edise"],"name:swe_x_preferred":["Edise"],"name:vol_x_preferred":["Edise"],"qs_pg:aaroncc":"EE","qs_pg:gn_country":"EE","qs_pg:gn_fcode":"PPL","qs_pg:gn_id":592316,"qs_pg:gn_pop":198,"qs_pg:name":"Edise","qs_pg:name_adm0":"Eesti","qs_pg:name_adm1":"Ida-Virumaa","qs_pg:photos_9k":1,"qs_pg:photos_9r":1,"qs_pg:photos_all":6,"qs_pg:photos_sr":0,"qs_pg:pop_sr":1,"qs_pg:qs_id":915629,"qs_pg:qs_pg_placetype":"locality","qs_pg:qs_pg_placetype_gp":"Town","qs_pg:woe_adm0":23424805,"qs_pg:woe_id":842092,"src:geom":"qs_pg","src:lbl_centroid":"qs_pg","src:population":"geonames","woe:adm0_id":23424805,"woe:name_adm0":"Eesti","woe:name_adm1":"Ida-Virumaa","woe:placetype":"Town","wof:belongsto":[85683059,102191581,1713306455,85633135,1713305651],"wof:breaches":[],"wof:concordances":{"gn:id":592316,"gp:id":842092,"qs_pg:id":915629,"wd:id":"Q1284822"},"wof:coterminous":[1713306455],"wof:country":"EE","wof:created":1497299797,"wof:geomhash":"146e4c099b4060555c4e4debb5f13754","wof:hierarchy":[{"continent_id":102191581,"country_id":85633135,"county_id":1713305651,"localadmin_id":1713306455,"locality_id":1126003571,"region_id":85683059}],"wof:id":1126003571,"wof:lang_x_official":["est"],"wof:lang_x_spoken":["est"],"wof:lastmodified":1596676516,"wof:name":"Edise","wof:parent_id":1713306455,"wof:placetype":"locality","wof:population":198,"wof:population_rank":1,"wof:repo":"whosonfirst-data-admin-ee","wof:superseded_by":[],"wof:supersedes":[],"wof:tags":[]},"bbox":[27.36778,59.36417,27.36778,59.36417],"geometry":{"coordinates":[27.36778,59.36417],"type":"Point"}}