{"id":1209920217,"type":"Feature","properties":{"edtf:cessation":"uuuu","edtf:inception":"uuuu","geom:area":0,"geom:area_square_m":0,"geom:bbox":"25.71222,58.78083,25.71222,58.78083","geom:latitude":58.78083,"geom:longitude":25.71222,"gn:admin1_code":"4.0","gn:admin2_code":"255.0","gn:admin3_code":"8097.0","gn:asciiname":"Tammekuela","gn:country_code":"EE","gn:dem":74,"gn:feature_class":"P","gn:feature_code":"PPL","gn:geonameid":588391,"gn:latitude":58.78083,"gn:longitude":25.71222,"gn:modification_date":"2017-11-25","gn:name":"Tammeküla","gn:population":0,"gn:timezone":"Europe/Tallinn","iso:country":"EE","lbl:bbox":"25.69222,58.76083,25.73222,58.80083","lbl:max_zoom":18,"lbl:min_zoom":13.5,"mz:hierarchy_label":1,"mz:is_current":1,"mz:min_zoom":12,"name:est_x_preferred":["Tammeküla"],"name:hye_x_preferred":["Տամեկյուլա"],"name:pol_x_preferred":["Tammeküla"],"name:spa_x_preferred":["Tammeküla"],"name:ukr_x_preferred":["Таммекюла"],"name:und_x_variant":["Tamme"],"name:vol_x_preferred":["Tammeküla"],"src:geom":"geonames","wof:belongsto":[85683031,102191581,1713306803,85633135,1713305765],"wof:breaches":[],"wof:concordances":{"gn:id":588391,"wk:page":"Tammek%C3%BCla"},"wof:coterminous":[1713306803],"wof:country":"EE","wof:geomhash":"808b017ee907a2853fa1f60aa4d4183f","wof:hierarchy":[{"continent_id":102191581,"country_id":85633135,"county_id":1713305765,"localadmin_id":1713306803,"locality_id":1209920217,"region_id":85683031}],"wof:id":1209920217,"wof:lang_x_official":["est"],"wof:lang_x_spoken":["est"],"wof:lastmodified":1596676639,"wof:name":"Tammekuela","wof:parent_id":1713306803,"wof:placetype":"locality","wof:repo":"whosonfirst-data-admin-ee","wof:superseded_by":[],"wof:supersedes":[],"wof:tags":[]},"bbox":[25.71222,58.78083,25.71222,58.78083],"geometry":{"coordinates":[25.71222,58.78083],"type":"Point"}}