{"id":1243368457,"type":"Feature","properties":{"edtf:cessation":"uuuu","edtf:inception":"uuuu","geom:area":0,"geom:area_square_m":0,"geom:bbox":"27.06667,58.71056,27.06667,58.71056","geom:latitude":58.71056,"geom:longitude":27.06667,"gn:admin1_code":"18.0","gn:admin2_code":"586.0","gn:admin3_code":"4685.0","gn:asciiname":"Luemati","gn:country_code":"EE","gn:dem":63,"gn:feature_class":"P","gn:feature_code":"PPL","gn:geonameid":590478,"gn:latitude":58.71056,"gn:longitude":27.06667,"gn:modification_date":"2017-11-25","gn:name":"Lümati","gn:population":0,"gn:timezone":"Europe/Tallinn","iso:country":"EE","lbl:bbox":"27.04667,58.69056,27.08667,58.73056","lbl:max_zoom":18,"lbl:min_zoom":13.5,"mz:hierarchy_label":1,"mz:is_current":1,"mz:min_zoom":12,"name:und_x_variant":["Lyumatu","Lümatu","Lümati"],"src:geom":"geonames","wof:belongsto":[85682995,102191581,1713313907,85633135,1713305679],"wof:breaches":[],"wof:concordances":{"gn:id":590478},"wof:coterminous":[1713313907],"wof:country":"EE","wof:geomhash":"d1edce8b698e601b389c8454436aa831","wof:hierarchy":[{"continent_id":102191581,"country_id":85633135,"county_id":1713305679,"localadmin_id":1713313907,"locality_id":1243368457,"region_id":85682995}],"wof:id":1243368457,"wof:lang_x_official":["est"],"wof:lang_x_spoken":["est"],"wof:lastmodified":1596660938,"wof:name":"Luemati","wof:parent_id":1713313907,"wof:placetype":"locality","wof:repo":"whosonfirst-data-admin-ee","wof:superseded_by":[],"wof:supersedes":[],"wof:tags":[]},"bbox":[27.06667,58.71056,27.06667,58.71056],"geometry":{"coordinates":[27.06667,58.71056],"type":"Point"}}