{"id":1293206567,"type":"Feature","properties":{"edtf:cessation":"uuuu","edtf:inception":"uuuu","geom:area":0,"geom:area_square_m":0,"geom:bbox":"25.61213,58.91196,25.61213,58.91196","geom:latitude":58.91196,"geom:longitude":25.61213,"gn:admin1_code":"4.0","gn:admin2_code":"567.0","gn:admin3_code":"5275.0","gn:asciiname":"Maeo","gn:country_code":"EE","gn:dem":78,"gn:feature_class":"P","gn:feature_code":"PPL","gn:geonameid":590333,"gn:latitude":58.91196,"gn:longitude":25.61213,"gn:modification_date":"2017-11-25","gn:name":"Mäo","gn:population":0,"gn:timezone":"Europe/Tallinn","iso:country":"EE","lbl:bbox":"25.59213,58.89196,25.63213,58.93196","lbl:max_zoom":18,"lbl:min_zoom":13.5,"mz:hierarchy_label":1,"mz:is_current":1,"mz:min_zoom":12,"name:deu_x_preferred":["Mäo"],"name:est_x_preferred":["Mäo"],"name:fra_x_preferred":["Mäo"],"name:hye_x_preferred":["Մյաո"],"name:pol_x_preferred":["Mäo"],"name:ukr_x_preferred":["Мяо"],"name:vol_x_preferred":["Mäo"],"src:geom":"geonames","wof:belongsto":[85683031,102191581,1713308329,85633135,1713305663],"wof:breaches":[],"wof:concordances":{"gn:id":590333,"wk:page":"M%C3%A4o%2C_J%C3%A4rva_County"},"wof:coterminous":[1713308329],"wof:country":"EE","wof:geomhash":"a9fe0793ae440db72ac3f14a9edc9cd7","wof:hierarchy":[{"continent_id":102191581,"country_id":85633135,"county_id":1713305663,"localadmin_id":1713308329,"locality_id":1293206567,"region_id":85683031}],"wof:id":1293206567,"wof:lang_x_official":["est"],"wof:lang_x_spoken":["est"],"wof:lastmodified":1596661328,"wof:name":"Maeo","wof:parent_id":1713308329,"wof:placetype":"locality","wof:repo":"whosonfirst-data-admin-ee","wof:superseded_by":[],"wof:supersedes":[],"wof:tags":[]},"bbox":[25.61213,58.91196,25.61213,58.91196],"geometry":{"coordinates":[25.61213,58.91196],"type":"Point"}}