{"id":1326806291,"type":"Feature","properties":{"edtf:cessation":"uuuu","edtf:inception":"uuuu","geom:area":0,"geom:area_square_m":0,"geom:bbox":"26.46806,58.22111,26.46806,58.22111","geom:latitude":58.22111,"geom:longitude":26.46806,"gn:admin1_code":"18.0","gn:admin2_code":"528.0","gn:admin3_code":"1223.0","gn:asciiname":"Altmaee","gn:country_code":"EE","gn:dem":82,"gn:feature_class":"P","gn:feature_code":"PPL","gn:geonameid":794027,"gn:latitude":58.22111,"gn:longitude":26.46806,"gn:modification_date":"2017-11-25","gn:name":"Altmäe","gn:population":0,"gn:timezone":"Europe/Tallinn","iso:country":"EE","lbl:bbox":"26.44806,58.20111,26.48806,58.24111","lbl:max_zoom":18,"lbl:min_zoom":13.5,"mz:hierarchy_label":1,"mz:is_current":1,"mz:min_zoom":12,"name:est_x_preferred":["Altmäe"],"name:fas_x_preferred":["التمای"],"name:hye_x_preferred":["Ալտմյաե"],"name:pol_x_preferred":["Altmäe"],"name:spa_x_preferred":["Altmäe"],"name:ukr_x_preferred":["Алтмяе"],"name:vol_x_preferred":["Altmäe"],"src:geom":"geonames","wof:belongsto":[85682995,102191581,1713314785,85633135,1713305715],"wof:breaches":[],"wof:concordances":{"gn:id":794027,"wk:page":"Altm%C3%A4e"},"wof:coterminous":[1713314785],"wof:country":"EE","wof:geomhash":"0aec937a0385e1724e50a23db008d52f","wof:hierarchy":[{"continent_id":102191581,"country_id":85633135,"county_id":1713305715,"localadmin_id":1713314785,"locality_id":1326806291,"region_id":85682995}],"wof:id":1326806291,"wof:lang_x_official":["est"],"wof:lang_x_spoken":["est"],"wof:lastmodified":1596676768,"wof:name":"Altmaee","wof:parent_id":1713314785,"wof:placetype":"locality","wof:repo":"whosonfirst-data-admin-ee","wof:superseded_by":[],"wof:supersedes":[],"wof:tags":[]},"bbox":[26.46806,58.22111,26.46806,58.22111],"geometry":{"coordinates":[26.46806,58.22111],"type":"Point"}}