{"id":1209038469,"type":"Feature","properties":{"edtf:cessation":"uuuu","edtf:inception":"uuuu","geom:area":0,"geom:area_square_m":0,"geom:bbox":"26.54389,58.79222,26.54389,58.79222","geom:latitude":58.79222,"geom:longitude":26.54389,"gn:admin1_code":"5.0","gn:admin2_code":"247.0","gn:admin3_code":"4080.0","gn:asciiname":"Rava","gn:country_code":"EE","gn:dem":90,"gn:feature_class":"P","gn:feature_code":"PPL","gn:geonameid":8619548,"gn:latitude":58.79222,"gn:longitude":26.54389,"gn:modification_date":"2017-11-25","gn:name":"Rava","gn:population":0,"gn:timezone":"Europe/Tallinn","iso:country":"EE","lbl:bbox":"26.52389,58.77222,26.56389,58.81222","lbl:max_zoom":18,"lbl:min_zoom":13.5,"mz:hierarchy_label":1,"mz:is_current":1,"mz:min_zoom":12,"name:ceb_x_preferred":["Rava"],"name:deu_x_preferred":["Rava"],"name:est_x_preferred":["Rava"],"name:hrv_x_preferred":["Rava"],"name:hun_x_preferred":["Rava"],"name:hye_x_preferred":["Ռավա"],"name:ita_x_preferred":["Rava"],"name:slv_x_preferred":["Rava"],"name:srp_x_preferred":["Рава"],"name:swe_x_preferred":["Rava"],"name:ukr_x_preferred":["Рава"],"name:und_x_variant":["Раба"],"name:vol_x_preferred":["Rava"],"src:geom":"geonames","wof:belongsto":[85683009,102191581,1713312035,85633135,1713305767],"wof:breaches":[],"wof:concordances":{"gn:id":8619548},"wof:country":"EE","wof:geomhash":"422591662334a47ee6aeb90d17529402","wof:hierarchy":[{"continent_id":102191581,"country_id":85633135,"county_id":1713305767,"localadmin_id":1713312035,"locality_id":1209038469,"region_id":85683009}],"wof:id":1209038469,"wof:lang_x_official":["est"],"wof:lang_x_spoken":["est"],"wof:lastmodified":1596676569,"wof:name":"Rava","wof:parent_id":1713312035,"wof:placetype":"locality","wof:repo":"whosonfirst-data-admin-ee","wof:superseded_by":[],"wof:supersedes":[],"wof:tags":[]},"bbox":[26.54389,58.79222,26.54389,58.79222],"geometry":{"coordinates":[26.54389,58.79222],"type":"Point"}}