{"id":1209981343,"type":"Feature","properties":{"edtf:cessation":"uuuu","edtf:inception":"uuuu","geom:area":0,"geom:area_square_m":0,"geom:bbox":"25.70222,58.26722,25.70222,58.26722","geom:latitude":58.26722,"geom:longitude":25.70222,"gn:admin1_code":"20.0","gn:admin2_code":"899.0","gn:admin3_code":"6423.0","gn:asciiname":"Lepiku","gn:country_code":"EE","gn:dem":100,"gn:feature_class":"P","gn:feature_code":"PPL","gn:geonameid":590677,"gn:latitude":58.26722,"gn:longitude":25.70222,"gn:modification_date":"2017-11-25","gn:name":"Lepiku","gn:population":0,"gn:timezone":"Europe/Tallinn","iso:country":"EE","lbl:bbox":"25.68222,58.24722,25.72222,58.28722","lbl:max_zoom":18,"lbl:min_zoom":13.5,"mz:hierarchy_label":1,"mz:is_current":1,"mz:min_zoom":12,"name:deu_x_preferred":["Lepiku"],"name:est_x_preferred":["Lepiku"],"name:pol_x_preferred":["Lepiku"],"name:swe_x_preferred":["Lepiku"],"name:ukr_x_preferred":["Лепіку"],"name:vol_x_preferred":["Lepiku"],"src:geom":"geonames","wof:belongsto":[85682985,102191581,1713309769,85633135,1713305669],"wof:breaches":[],"wof:concordances":{"gn:id":590677},"wof:country":"EE","wof:geomhash":"33ac2bd1fab938745386106e08a7d88c","wof:hierarchy":[{"continent_id":102191581,"country_id":85633135,"county_id":1713305669,"localadmin_id":1713309769,"locality_id":1209981343,"region_id":85682985}],"wof:id":1209981343,"wof:lang_x_official":["est"],"wof:lang_x_spoken":["est"],"wof:lastmodified":1596661264,"wof:name":"Lepiku","wof:parent_id":1713309769,"wof:placetype":"locality","wof:repo":"whosonfirst-data-admin-ee","wof:superseded_by":[],"wof:supersedes":[],"wof:tags":[]},"bbox":[25.70222,58.26722,25.70222,58.26722],"geometry":{"coordinates":[25.70222,58.26722],"type":"Point"}}