{"id":1259746367,"type":"Feature","properties":{"edtf:cessation":"uuuu","edtf:inception":"uuuu","geom:area":0,"geom:area_square_m":0,"geom:bbox":"26.98694,58.36917,26.98694,58.36917","geom:latitude":58.36917,"geom:longitude":26.98694,"gn:admin1_code":"18.0","gn:admin2_code":"291.0","gn:admin3_code":"5240.0","gn:asciiname":"Murulaane","gn:country_code":"EE","gn:dem":54,"gn:feature_class":"P","gn:feature_code":"PPL","gn:geonameid":8618395,"gn:latitude":58.36917,"gn:longitude":26.98694,"gn:modification_date":"2017-11-25","gn:name":"Murulaane","gn:population":0,"gn:timezone":"Europe/Tallinn","iso:country":"EE","lbl:bbox":"26.96694,58.34917,27.00694,58.38917","lbl:max_zoom":18,"lbl:min_zoom":13.5,"mz:hierarchy_label":1,"mz:is_current":1,"mz:min_zoom":12,"name:und_x_variant":["рабочихъ"],"src:geom":"geonames","wof:belongsto":[85682995,102191581,1713313709,85633135,1713305699],"wof:breaches":[],"wof:concordances":{"gn:id":8618395},"wof:country":"EE","wof:geomhash":"e6bf1893c1054f24525a31b85b63d27a","wof:hierarchy":[{"continent_id":102191581,"country_id":85633135,"county_id":1713305699,"localadmin_id":1713313709,"locality_id":1259746367,"region_id":85682995}],"wof:id":1259746367,"wof:lang_x_official":["est"],"wof:lang_x_spoken":["est"],"wof:lastmodified":1596660662,"wof:name":"Murulaane","wof:parent_id":1713313709,"wof:placetype":"locality","wof:repo":"whosonfirst-data-admin-ee","wof:superseded_by":[],"wof:supersedes":[],"wof:tags":[]},"bbox":[26.98694,58.36917,26.98694,58.36917],"geometry":{"coordinates":[26.98694,58.36917],"type":"Point"}}