{"id":1226134447,"type":"Feature","properties":{"edtf:cessation":"uuuu","edtf:inception":"uuuu","geom:area":0,"geom:area_square_m":0,"geom:bbox":"23.55,58.76667,23.55,58.76667","geom:latitude":58.76667,"geom:longitude":23.55,"gn:admin1_code":"7.0","gn:asciiname":"Kalakula","gn:cc2":"EE","gn:country_code":"EE","gn:dem":8,"gn:feature_class":"P","gn:feature_code":"PPL","gn:geonameid":591724,"gn:latitude":58.76667,"gn:longitude":23.55,"gn:modification_date":"2012-01-17","gn:name":"Kalaküla","gn:population":0,"gn:timezone":"Europe/Tallinn","iso:country":"EE","lbl:bbox":"23.53,58.74667,23.57,58.78667","lbl:max_zoom":18,"lbl:min_zoom":13.5,"mz:hierarchy_label":1,"mz:is_current":1,"mz:min_zoom":12,"name:und_x_variant":["Kívidepee","Kalakyula","Kidden","Kiidepää Küla","Kividepää","Kalaküla"],"src:geom":"geonames","wof:belongsto":[],"wof:breaches":[],"wof:concordances":{"gn:id":591724},"wof:country":"EE","wof:geomhash":"1356f78bb5914aecf6b46dcc43db55eb","wof:hierarchy":[{"continent_id":-1,"country_id":-1,"locality_id":1226134447,"region_id":-1}],"wof:id":1226134447,"wof:lang_x_official":["est"],"wof:lang_x_spoken":["est"],"wof:lastmodified":1596485169,"wof:name":"Kalakula","wof:parent_id":-1,"wof:placetype":"locality","wof:repo":"whosonfirst-data-admin-ee","wof:superseded_by":[],"wof:supersedes":[],"wof:tags":[]},"bbox":[23.55,58.76667,23.55,58.76667],"geometry":{"coordinates":[23.55,58.76667],"type":"Point"}}