{"id":1293942405,"type":"Feature","properties":{"edtf:cessation":"uuuu","edtf:inception":"uuuu","geom:area":0,"geom:area_square_m":0,"geom:bbox":"26.68278,57.88278,26.68278,57.88278","geom:latitude":57.88278,"geom:longitude":26.68278,"gn:admin1_code":"21.0","gn:admin2_code":"917.0","gn:admin3_code":"1894.0","gn:asciiname":"Horma","gn:country_code":"EE","gn:dem":128,"gn:feature_class":"P","gn:feature_code":"PPL","gn:geonameid":8619374,"gn:latitude":57.88278,"gn:longitude":26.68278,"gn:modification_date":"2017-11-25","gn:name":"Horma","gn:population":0,"gn:timezone":"Europe/Tallinn","iso:country":"EE","lbl:bbox":"26.66278,57.86278,26.70278,57.90278","lbl:max_zoom":18,"lbl:min_zoom":13.5,"mz:hierarchy_label":1,"mz:is_current":1,"mz:min_zoom":12,"src:geom":"geonames","wof:belongsto":[85682937,102191581,1713316103,85633135,1713305633],"wof:breaches":[],"wof:concordances":{"gn:id":8619374},"wof:coterminous":[1713316103],"wof:country":"EE","wof:geomhash":"429ed8934c084a3ba48d1aaa8c15c212","wof:hierarchy":[{"continent_id":102191581,"country_id":85633135,"county_id":1713305633,"localadmin_id":1713316103,"locality_id":1293942405,"region_id":85682937}],"wof:id":1293942405,"wof:lang_x_official":["est"],"wof:lang_x_spoken":["est"],"wof:lastmodified":1596660411,"wof:name":"Horma","wof:parent_id":1713316103,"wof:placetype":"locality","wof:repo":"whosonfirst-data-admin-ee","wof:superseded_by":[],"wof:supersedes":[],"wof:tags":[]},"bbox":[26.68278,57.88278,26.68278,57.88278],"geometry":{"coordinates":[26.68278,57.88278],"type":"Point"}}