{"id":1193272621,"type":"Feature","properties":{"edtf:cessation":"uuuu","edtf:inception":"uuuu","geom:area":0,"geom:area_square_m":0,"geom:bbox":"23.82444,58.81111,23.82444,58.81111","geom:latitude":58.81111,"geom:longitude":23.82444,"gn:admin1_code":"7.0","gn:admin2_code":"441.0","gn:admin3_code":"2977.0","gn:asciiname":"Aru","gn:country_code":"EE","gn:dem":14,"gn:feature_class":"P","gn:feature_code":"PPL","gn:geonameid":592402,"gn:latitude":58.81111,"gn:longitude":23.82444,"gn:modification_date":"2018-05-02","gn:name":"Aru","gn:population":0,"gn:timezone":"Europe/Tallinn","iso:country":"EE","lbl:bbox":"23.80444,58.79111,23.84444,58.83111","lbl:max_zoom":18,"lbl:min_zoom":13.5,"mz:hierarchy_label":1,"mz:is_current":1,"mz:min_zoom":12,"name:ast_x_preferred":["Aru"],"name:ceb_x_preferred":["Aru"],"name:est_x_preferred":["Aru"],"name:hye_x_preferred":["Առու"],"name:ind_x_preferred":["Aru"],"name:nld_x_preferred":["Aru"],"name:pol_x_preferred":["Aru"],"name:por_x_preferred":["Aru"],"name:rus_x_preferred":["Ару"],"name:srp_x_preferred":["Ару"],"name:swe_x_preferred":["Aru"],"name:und_x_variant":["Arokyula","Aruküla"],"name:vol_x_preferred":["Aru"],"src:geom":"geonames","wof:belongsto":[85683001,102191581,1713312485,85633135,1713305701],"wof:breaches":[],"wof:concordances":{"gn:id":592402},"wof:country":"EE","wof:geomhash":"24d35c70b3f8d220f7a649983cfa194b","wof:hierarchy":[{"continent_id":102191581,"country_id":85633135,"county_id":1713305701,"localadmin_id":1713312485,"locality_id":1193272621,"region_id":85683001}],"wof:id":1193272621,"wof:lang_x_official":["est"],"wof:lang_x_spoken":["est"],"wof:lastmodified":1596677425,"wof:name":"Aru","wof:parent_id":1713312485,"wof:placetype":"locality","wof:repo":"whosonfirst-data-admin-ee","wof:superseded_by":[],"wof:supersedes":[],"wof:tags":[]},"bbox":[23.82444,58.81111,23.82444,58.81111],"geometry":{"coordinates":[23.82444,58.81111],"type":"Point"}}