{"id":1225848359,"type":"Feature","properties":{"edtf:cessation":"uuuu","edtf:inception":"uuuu","geom:area":0,"geom:area_square_m":0,"geom:bbox":"22.577,58.71521,22.577,58.71521","geom:latitude":58.71521,"geom:longitude":22.577,"gn:admin1_code":"2.0","gn:admin2_code":"205.0","gn:admin3_code":"4898.0","gn:asciiname":"Metsalauka","gn:country_code":"EE","gn:dem":12,"gn:feature_class":"P","gn:feature_code":"PPL","gn:geonameid":590241,"gn:latitude":58.71521,"gn:longitude":22.577,"gn:modification_date":"2017-11-25","gn:name":"Metsalauka","gn:population":0,"gn:timezone":"Europe/Tallinn","iso:country":"EE","lbl:bbox":"22.557,58.69521,22.597,58.73521","lbl:max_zoom":18,"lbl:min_zoom":13.5,"mz:hierarchy_label":1,"mz:is_current":1,"mz:min_zoom":12,"name:deu_x_preferred":["Metsalauka"],"name:est_x_preferred":["Metsalauka"],"name:fra_x_preferred":["Metsalauka"],"name:hye_x_preferred":["Մեցալաուկա"],"name:pol_x_preferred":["Metsalauka"],"name:spa_x_preferred":["Metsalauka"],"name:vol_x_preferred":["Metsalauka"],"src:geom":"geonames","wof:belongsto":[85682989,102191581,1713310793,85633135,1713305629],"wof:breaches":[],"wof:concordances":{"gn:id":590241,"wk:page":"Metsalauka"},"wof:coterminous":[1713310793],"wof:country":"EE","wof:geomhash":"aee1aaab941f4c23f1bafc645f30481a","wof:hierarchy":[{"continent_id":102191581,"country_id":85633135,"county_id":1713305629,"localadmin_id":1713310793,"locality_id":1225848359,"region_id":85682989}],"wof:id":1225848359,"wof:lang_x_official":["est"],"wof:lang_x_spoken":["est"],"wof:lastmodified":1596670004,"wof:name":"Metsalauka","wof:parent_id":1713310793,"wof:placetype":"locality","wof:repo":"whosonfirst-data-admin-ee","wof:superseded_by":[],"wof:supersedes":[],"wof:tags":[]},"bbox":[22.577,58.71521,22.577,58.71521],"geometry":{"coordinates":[22.577,58.71521],"type":"Point"}}