{"id":1293353535,"type":"Feature","properties":{"edtf:cessation":"uuuu","edtf:inception":"uuuu","geom:area":0,"geom:area_square_m":0,"geom:bbox":"26.90194,58.60944,26.90194,58.60944","geom:latitude":58.60944,"geom:longitude":26.90194,"gn:admin1_code":"18.0","gn:admin2_code":"586.0","gn:admin3_code":"9644.0","gn:asciiname":"Vaelgi-Alajoe","gn:country_code":"EE","gn:dem":61,"gn:feature_class":"P","gn:feature_code":"PPL","gn:geonameid":8618815,"gn:latitude":58.60944,"gn:longitude":26.90194,"gn:modification_date":"2017-11-25","gn:name":"Välgi-Alajõe","gn:population":0,"gn:timezone":"Europe/Tallinn","iso:country":"EE","lbl:bbox":"26.88194,58.58944,26.92194,58.62944","lbl:max_zoom":18,"lbl:min_zoom":13.5,"mz:hierarchy_label":1,"mz:is_current":1,"mz:min_zoom":12,"name:und_x_variant":["Välgi-Alajõe","Alajõe"],"src:geom":"geonames","wof:belongsto":[85682995,102191581,1713312535,85633135,1713305679],"wof:breaches":[],"wof:concordances":{"gn:id":8618815},"wof:country":"EE","wof:geomhash":"7626cb73378ca8df15b5dd4ce684156d","wof:hierarchy":[{"continent_id":102191581,"country_id":85633135,"county_id":1713305679,"localadmin_id":1713312535,"locality_id":1293353535,"region_id":85682995}],"wof:id":1293353535,"wof:lang_x_official":["est"],"wof:lang_x_spoken":["est"],"wof:lastmodified":1596660927,"wof:name":"Vaelgi-Alajoe","wof:parent_id":1713312535,"wof:placetype":"locality","wof:repo":"whosonfirst-data-admin-ee","wof:superseded_by":[],"wof:supersedes":[],"wof:tags":[]},"bbox":[26.90194,58.60944,26.90194,58.60944],"geometry":{"coordinates":[26.90194,58.60944],"type":"Point"}}