{"id":1276293363,"type":"Feature","properties":{"edtf:cessation":"uuuu","edtf:inception":"uuuu","geom:area":0,"geom:area_square_m":0,"geom:bbox":"25.83972,58.38944,25.83972,58.38944","geom:latitude":58.38944,"geom:longitude":25.83972,"gn:admin1_code":"20.0","gn:admin2_code":"899.0","gn:admin3_code":"8569.0","gn:asciiname":"Taenassilma","gn:country_code":"EE","gn:dem":50,"gn:feature_class":"P","gn:feature_code":"PPL","gn:geonameid":793906,"gn:latitude":58.38944,"gn:longitude":25.83972,"gn:modification_date":"2017-11-25","gn:name":"Tänassilma","gn:population":0,"gn:timezone":"Europe/Tallinn","iso:country":"EE","lbl:bbox":"25.81972,58.36944,25.85972,58.40944","lbl:max_zoom":18,"lbl:min_zoom":13.5,"mz:hierarchy_label":1,"mz:is_current":1,"mz:min_zoom":12,"name:ceb_x_preferred":["Tänassilma"],"name:deu_x_preferred":["Tänassilma"],"name:eng_x_preferred":["Tänassilma"],"name:est_x_preferred":["Tänassilma"],"name:fas_x_preferred":["تاناسیلما"],"name:fra_x_preferred":["Tänassilma"],"name:hye_x_preferred":["Տենասիլմա"],"name:pol_x_preferred":["Tänassilma"],"name:rus_x_preferred":["Тянассилма"],"name:spa_x_preferred":["Tänassilma"],"name:swe_x_preferred":["Tänassilma"],"name:ukr_x_preferred":["Тянассілма"],"name:vol_x_preferred":["Tänassilma"],"src:geom":"geonames","wof:belongsto":[85682985,102191581,1713309879,85633135,1713305669],"wof:breaches":[],"wof:concordances":{"gn:id":793906,"wk:page":"T%C3%A4nassilma%2C_Viljandi_County"},"wof:country":"EE","wof:geomhash":"8c1a8936073a560ff8163f2d328b29af","wof:hierarchy":[{"continent_id":102191581,"country_id":85633135,"county_id":1713305669,"localadmin_id":1713309879,"locality_id":1276293363,"region_id":85682985}],"wof:id":1276293363,"wof:lang_x_official":["est"],"wof:lang_x_spoken":["est"],"wof:lastmodified":1596661248,"wof:name":"Taenassilma","wof:parent_id":1713309879,"wof:placetype":"locality","wof:repo":"whosonfirst-data-admin-ee","wof:superseded_by":[],"wof:supersedes":[],"wof:tags":[]},"bbox":[25.83972,58.38944,25.83972,58.38944],"geometry":{"coordinates":[25.83972,58.38944],"type":"Point"}}