{"id":1225965451,"type":"Feature","properties":{"edtf:cessation":"uuuu","edtf:inception":"uuuu","geom:area":0,"geom:area_square_m":0,"geom:bbox":"23.69361,58.59389,23.69361,58.59389","geom:latitude":58.59389,"geom:longitude":23.69361,"gn:admin1_code":"11.0","gn:admin2_code":"430.0","gn:admin3_code":"4607.0","gn:asciiname":"Loo","gn:cc2":"EE","gn:country_code":"EE","gn:dem":13,"gn:feature_class":"P","gn:feature_code":"PPL","gn:geonameid":590540,"gn:latitude":58.59389,"gn:longitude":23.69361,"gn:modification_date":"2017-11-25","gn:name":"Lõo","gn:population":0,"gn:timezone":"Europe/Tallinn","iso:country":"EE","lbl:bbox":"23.67361,58.57389,23.71361,58.61389","lbl:max_zoom":18,"lbl:min_zoom":13.5,"mz:hierarchy_label":1,"mz:is_current":1,"mz:min_zoom":12,"name:deu_x_preferred":["Lõo"],"name:est_x_preferred":["Lõo"],"name:hye_x_preferred":["Լիո"],"name:nld_x_preferred":["Lõo"],"name:pol_x_preferred":["Lõo"],"name:spa_x_preferred":["Lõo"],"name:ukr_x_preferred":["Лио"],"name:und_x_variant":["Lõoküla"],"name:vol_x_preferred":["Lõo"],"src:geom":"geonames","wof:belongsto":[85683001,102191581,1713309557,85633135,1713305721],"wof:breaches":[],"wof:concordances":{"gn:id":590540,"wk:page":"L%C3%B5o"},"wof:coterminous":[1713309557],"wof:country":"EE","wof:geomhash":"8afaecae08a3bd6bb0f5100e70b7dedf","wof:hierarchy":[{"continent_id":102191581,"country_id":85633135,"county_id":1713305721,"localadmin_id":1713309557,"locality_id":1225965451,"region_id":85683001}],"wof:id":1225965451,"wof:lang_x_official":["est"],"wof:lang_x_spoken":["est"],"wof:lastmodified":1596661678,"wof:name":"Loo","wof:parent_id":1713309557,"wof:placetype":"locality","wof:repo":"whosonfirst-data-admin-ee","wof:superseded_by":[],"wof:supersedes":[],"wof:tags":[]},"bbox":[23.69361,58.59389,23.69361,58.59389],"geometry":{"coordinates":[23.69361,58.59389],"type":"Point"}}