{"id":1209412245,"type":"Feature","properties":{"edtf:cessation":"uuuu","edtf:inception":"uuuu","geom:area":0,"geom:area_square_m":0,"geom:bbox":"26.25167,59.31889,26.25167,59.31889","geom:latitude":59.31889,"geom:longitude":26.25167,"gn:admin1_code":"8.0","gn:admin2_code":"661.0","gn:admin3_code":"5182.0","gn:asciiname":"Maedapea","gn:country_code":"EE","gn:dem":104,"gn:feature_class":"P","gn:feature_code":"PPL","gn:geonameid":793472,"gn:latitude":59.31889,"gn:longitude":26.25167,"gn:modification_date":"2017-11-25","gn:name":"Mädapea","gn:population":0,"gn:timezone":"Europe/Tallinn","iso:country":"EE","lbl:bbox":"26.23167,59.29889,26.27167,59.33889","lbl:max_zoom":18,"lbl:min_zoom":13.5,"mz:hierarchy_label":1,"mz:is_current":1,"mz:min_zoom":12,"name:est_x_preferred":["Mädapea"],"name:fra_x_preferred":["Mädapea"],"name:hye_x_preferred":["Մեդապեա"],"name:urd_x_preferred":["میڈاپیا"],"name:vol_x_preferred":["Mädapea"],"src:geom":"geonames","wof:belongsto":[85683049,102191581,1713308043,85633135,1713305719],"wof:breaches":[],"wof:concordances":{"gn:id":793472,"wk:page":"M%C3%A4dapea"},"wof:coterminous":[1713308043],"wof:country":"EE","wof:geomhash":"647f9893f144c3a74155c48554841dfa","wof:hierarchy":[{"continent_id":102191581,"country_id":85633135,"county_id":1713305719,"localadmin_id":1713308043,"locality_id":1209412245,"region_id":85683049}],"wof:id":1209412245,"wof:lang_x_official":["est"],"wof:lang_x_spoken":["est"],"wof:lastmodified":1596676670,"wof:name":"Maedapea","wof:parent_id":1713308043,"wof:placetype":"locality","wof:repo":"whosonfirst-data-admin-ee","wof:superseded_by":[],"wof:supersedes":[],"wof:tags":[]},"bbox":[26.25167,59.31889,26.25167,59.31889],"geometry":{"coordinates":[26.25167,59.31889],"type":"Point"}}