{"id":1344136289,"type":"Feature","properties":{"edtf:cessation":"uuuu","edtf:inception":"uuuu","geom:area":0,"geom:area_square_m":0,"geom:bbox":"24.75639,59.07278,24.75639,59.07278","geom:latitude":59.07278,"geom:longitude":24.75639,"gn:admin1_code":"13.0","gn:admin2_code":"668.0","gn:admin3_code":"3283.0","gn:asciiname":"Koigi","gn:cc2":"EE","gn:country_code":"EE","gn:dem":71,"gn:feature_class":"P","gn:feature_code":"PPL","gn:geonameid":591250,"gn:latitude":59.07278,"gn:longitude":24.75639,"gn:modification_date":"2017-11-25","gn:name":"Koigi","gn:population":0,"gn:timezone":"Europe/Tallinn","iso:country":"EE","lbl:bbox":"24.73639,59.05278,24.77639,59.09278","lbl:max_zoom":18,"lbl:min_zoom":13.5,"mz:hierarchy_label":1,"mz:is_current":1,"mz:min_zoom":12,"name:ceb_x_preferred":["Koigi"],"name:est_x_preferred":["Koigi"],"name:hye_x_preferred":["Կոիգի"],"name:nld_x_preferred":["Koigi"],"name:ron_x_preferred":["Koigi"],"name:sco_x_preferred":["Koigi"],"name:swe_x_preferred":["Koigi"],"name:ukr_x_preferred":["Койґі"],"name:und_x_variant":["Koygi"],"name:vol_x_preferred":["Koigi"],"src:geom":"geonames","wof:belongsto":[85683013,102191581,1713315435,85633135,1713305711],"wof:breaches":[],"wof:concordances":{"gn:id":591250},"wof:coterminous":[1713315435],"wof:country":"EE","wof:geomhash":"248ee5f5aa6dd941578b4ec6f9721670","wof:hierarchy":[{"continent_id":102191581,"country_id":85633135,"county_id":1713305711,"localadmin_id":1713315435,"locality_id":1344136289,"region_id":85683013}],"wof:id":1344136289,"wof:lang_x_official":["est"],"wof:lang_x_spoken":["est"],"wof:lastmodified":1596676730,"wof:name":"Koigi","wof:parent_id":1713315435,"wof:placetype":"locality","wof:repo":"whosonfirst-data-admin-ee","wof:superseded_by":[],"wof:supersedes":[],"wof:tags":[]},"bbox":[24.75639,59.07278,24.75639,59.07278],"geometry":{"coordinates":[24.75639,59.07278],"type":"Point"}}