{"id":1326693281,"type":"Feature","properties":{"edtf:cessation":"uuuu","edtf:inception":"uuuu","geom:area":0,"geom:area_square_m":0,"geom:bbox":"26.6975,58.50889,26.6975,58.50889","geom:latitude":58.50889,"geom:longitude":26.6975,"gn:admin1_code":"18.0","gn:admin2_code":"796.0","gn:admin3_code":"7745.0","gn:asciiname":"Alevi","gn:country_code":"EE","gn:dem":79,"gn:feature_class":"P","gn:feature_code":"PPL","gn:geonameid":8618167,"gn:latitude":58.50889,"gn:longitude":26.6975,"gn:modification_date":"2017-11-25","gn:name":"Alevi","gn:population":0,"gn:timezone":"Europe/Tallinn","iso:country":"EE","lbl:bbox":"26.6775,58.48889,26.7175,58.52889","lbl:max_zoom":18,"lbl:min_zoom":13.5,"mz:hierarchy_label":1,"mz:is_current":1,"mz:min_zoom":12,"name:und_x_variant":["Алеви"],"src:geom":"geonames","wof:belongsto":[85683009,102191581,1713309053,85633135,1713305659],"wof:breaches":[],"wof:concordances":{"gn:id":8618167},"wof:country":"EE","wof:geomhash":"18ab959e829bc9b00355d00c7d6d5202","wof:hierarchy":[{"continent_id":102191581,"country_id":85633135,"county_id":1713305659,"localadmin_id":1713309053,"locality_id":1326693281,"region_id":85683009}],"wof:id":1326693281,"wof:lang_x_official":["est"],"wof:lang_x_spoken":["est"],"wof:lastmodified":1596676473,"wof:name":"Alevi","wof:parent_id":1713309053,"wof:placetype":"locality","wof:repo":"whosonfirst-data-admin-ee","wof:superseded_by":[],"wof:supersedes":[],"wof:tags":[]},"bbox":[26.6975,58.50889,26.6975,58.50889],"geometry":{"coordinates":[26.6975,58.50889],"type":"Point"}}