{"id":1309806929,"type":"Feature","properties":{"edtf:cessation":"uuuu","edtf:inception":"uuuu","geom:area":0,"geom:area_square_m":0,"geom:bbox":"22.78116,58.84261,22.78116,58.84261","geom:latitude":58.84261,"geom:longitude":22.78116,"gn:admin1_code":"2.0","gn:admin2_code":"205.0","gn:admin3_code":"1200.0","gn:asciiname":"Allika","gn:country_code":"EE","gn:dem":15,"gn:feature_class":"P","gn:feature_code":"PPL","gn:geonameid":592537,"gn:latitude":58.84261,"gn:longitude":22.78116,"gn:modification_date":"2017-11-25","gn:name":"Allika","gn:population":0,"gn:timezone":"Europe/Tallinn","iso:country":"EE","lbl:bbox":"22.76116,58.82261,22.80116,58.86261","lbl:max_zoom":18,"lbl:min_zoom":13.5,"mz:hierarchy_label":1,"mz:is_current":1,"mz:min_zoom":12,"name:deu_x_preferred":["Allika"],"name:est_x_preferred":["Allika"],"name:fas_x_preferred":["الیکا"],"name:hye_x_preferred":["Ալլիկա"],"name:pol_x_preferred":["Allika"],"name:spa_x_preferred":["Allika"],"name:vol_x_preferred":["Allika"],"src:geom":"geonames","wof:belongsto":[85682989,102191581,1713309009,85633135,1713305629],"wof:breaches":[],"wof:concordances":{"gn:id":592537,"wk:page":"Allika%2C_Hiiu_County"},"wof:coterminous":[1713309009],"wof:country":"EE","wof:geomhash":"ced678215b4a86614be1105a51ee74fc","wof:hierarchy":[{"continent_id":102191581,"country_id":85633135,"county_id":1713305629,"localadmin_id":1713309009,"locality_id":1309806929,"region_id":85682989}],"wof:id":1309806929,"wof:lang_x_official":["est"],"wof:lang_x_spoken":["est"],"wof:lastmodified":1596670009,"wof:name":"Allika","wof:parent_id":1713309009,"wof:placetype":"locality","wof:repo":"whosonfirst-data-admin-ee","wof:superseded_by":[],"wof:supersedes":[],"wof:tags":[]},"bbox":[22.78116,58.84261,22.78116,58.84261],"geometry":{"coordinates":[22.78116,58.84261],"type":"Point"}}