{"id":1276662137,"type":"Feature","properties":{"edtf:cessation":"uuuu","edtf:inception":"uuuu","geom:area":0,"geom:area_square_m":0,"geom:bbox":"26.66917,58.78778,26.66917,58.78778","geom:latitude":58.78778,"geom:longitude":26.66917,"gn:admin1_code":"5.0","gn:admin2_code":"247.0","gn:admin3_code":"8480.0","gn:asciiname":"Konnakuela","gn:country_code":"EE","gn:dem":85,"gn:feature_class":"P","gn:feature_code":"PPL","gn:geonameid":8619535,"gn:latitude":58.78778,"gn:longitude":26.66917,"gn:modification_date":"2017-11-25","gn:name":"Konnaküla","gn:population":0,"gn:timezone":"Europe/Tallinn","iso:country":"EE","lbl:bbox":"26.64917,58.76778,26.68917,58.80778","lbl:max_zoom":18,"lbl:min_zoom":13.5,"mz:hierarchy_label":1,"mz:is_current":1,"mz:min_zoom":12,"name:und_x_variant":["Konnaküla","Konna"],"src:geom":"geonames","wof:belongsto":[85683009,102191581,1713312209,85633135,1713305767],"wof:breaches":[],"wof:concordances":{"gn:id":8619535},"wof:country":"EE","wof:geomhash":"fd7282ba4eec5e0a564b68b31311b921","wof:hierarchy":[{"continent_id":102191581,"country_id":85633135,"county_id":1713305767,"localadmin_id":1713312209,"locality_id":1276662137,"region_id":85683009}],"wof:id":1276662137,"wof:lang_x_official":["est"],"wof:lang_x_spoken":["est"],"wof:lastmodified":1596676580,"wof:name":"Konnakuela","wof:parent_id":1713312209,"wof:placetype":"locality","wof:repo":"whosonfirst-data-admin-ee","wof:superseded_by":[],"wof:supersedes":[],"wof:tags":[]},"bbox":[26.66917,58.78778,26.66917,58.78778],"geometry":{"coordinates":[26.66917,58.78778],"type":"Point"}}