{"id":1293845737,"type":"Feature","properties":{"edtf:cessation":"uuuu","edtf:inception":"uuuu","geom:area":0,"geom:area_square_m":0,"geom:bbox":"25.33639,58.4375,25.33639,58.4375","geom:latitude":58.4375,"geom:longitude":25.33639,"gn:admin1_code":"20.0","gn:admin2_code":"615.0","gn:admin3_code":"4261.0","gn:asciiname":"Murru","gn:country_code":"EE","gn:dem":52,"gn:feature_class":"P","gn:feature_code":"PPL","gn:geonameid":8620406,"gn:latitude":58.4375,"gn:longitude":25.33639,"gn:modification_date":"2017-11-25","gn:name":"Murru","gn:population":0,"gn:timezone":"Europe/Tallinn","iso:country":"EE","lbl:bbox":"25.31639,58.4175,25.35639,58.4575","lbl:max_zoom":18,"lbl:min_zoom":13.5,"mz:hierarchy_label":1,"mz:is_current":1,"mz:min_zoom":12,"name:est_x_preferred":["Murru"],"name:hye_x_preferred":["Մուռռու"],"name:pol_x_preferred":["Murru"],"name:spa_x_preferred":["Murru"],"name:und_x_variant":["Дв. Мурру"],"name:vol_x_preferred":["Murru"],"src:geom":"geonames","wof:belongsto":[85682985,102191581,1713311691,85633135,1713305735],"wof:breaches":[],"wof:concordances":{"gn:id":8620406},"wof:country":"EE","wof:geomhash":"c85a38efa7d0fcc054a9c729020b67a0","wof:hierarchy":[{"continent_id":102191581,"country_id":85633135,"county_id":1713305735,"localadmin_id":1713311691,"locality_id":1293845737,"region_id":85682985}],"wof:id":1293845737,"wof:lang_x_official":["est"],"wof:lang_x_spoken":["est"],"wof:lastmodified":1596663464,"wof:name":"Murru","wof:parent_id":1713311691,"wof:placetype":"locality","wof:repo":"whosonfirst-data-admin-ee","wof:superseded_by":[],"wof:supersedes":[],"wof:tags":[]},"bbox":[25.33639,58.4375,25.33639,58.4375],"geometry":{"coordinates":[25.33639,58.4375],"type":"Point"}}