{"id":1243143013,"type":"Feature","properties":{"edtf:cessation":"uuuu","edtf:inception":"uuuu","geom:area":0,"geom:area_square_m":0,"geom:bbox":"22.75,58.51667,22.75,58.51667","geom:latitude":58.51667,"geom:longitude":22.75,"gn:admin1_code":"14.0","gn:admin2_code":"714.0","gn:admin3_code":"5287.0","gn:asciiname":"Suella","gn:country_code":"EE","gn:dem":12,"gn:feature_class":"P","gn:feature_code":"PPL","gn:geonameid":588556,"gn:latitude":58.51667,"gn:longitude":22.75,"gn:modification_date":"2017-11-25","gn:name":"Sülla","gn:population":0,"gn:timezone":"Europe/Tallinn","iso:country":"EE","lbl:bbox":"22.73,58.49667,22.77,58.53667","lbl:max_zoom":18,"lbl:min_zoom":13.5,"mz:hierarchy_label":1,"mz:is_current":1,"mz:min_zoom":12,"name:und_x_variant":["Syulla","Sülla"],"src:geom":"geonames","wof:belongsto":[85682947,102191581,1713306919,85633135,1713305627],"wof:breaches":[],"wof:concordances":{"gn:id":588556},"wof:country":"EE","wof:geomhash":"0f29063baee4a82397a85593e9cd290c","wof:hierarchy":[{"continent_id":102191581,"country_id":85633135,"county_id":1713305627,"localadmin_id":1713306919,"locality_id":1243143013,"region_id":85682947}],"wof:id":1243143013,"wof:lang_x_official":["est"],"wof:lang_x_spoken":["est"],"wof:lastmodified":1596674964,"wof:name":"Suella","wof:parent_id":1713306919,"wof:placetype":"locality","wof:repo":"whosonfirst-data-admin-ee","wof:superseded_by":[],"wof:supersedes":[],"wof:tags":[]},"bbox":[22.75,58.51667,22.75,58.51667],"geometry":{"coordinates":[22.75,58.51667],"type":"Point"}}