{"id":1327129773,"type":"Feature","properties":{"edtf:cessation":"uuuu","edtf:inception":"uuuu","geom:area":0,"geom:area_square_m":0,"geom:bbox":"25.87083,59.51417,25.87083,59.51417","geom:latitude":59.51417,"geom:longitude":25.87083,"gn:admin1_code":"8.0","gn:admin2_code":"191.0","gn:admin3_code":"8787.0","gn:asciiname":"Uuskuela","gn:country_code":"EE","gn:dem":66,"gn:feature_class":"P","gn:feature_code":"PPL","gn:geonameid":587990,"gn:latitude":59.51417,"gn:longitude":25.87083,"gn:modification_date":"2017-11-25","gn:name":"Uusküla","gn:population":0,"gn:timezone":"Europe/Tallinn","iso:country":"EE","lbl:bbox":"25.85083,59.49417,25.89083,59.53417","lbl:max_zoom":18,"lbl:min_zoom":13.5,"mz:hierarchy_label":1,"mz:is_current":1,"mz:min_zoom":12,"name:und_x_variant":["Uekyula","Uueküla","Uzekyulya","Uusküla"],"src:geom":"geonames","wof:belongsto":[85683049,102191581,1713308269,85633135,1713305775],"wof:breaches":[],"wof:concordances":{"gn:id":587990},"wof:country":"EE","wof:geomhash":"12594469a820e4b858af4d217ec46167","wof:hierarchy":[{"continent_id":102191581,"country_id":85633135,"county_id":1713305775,"localadmin_id":1713308269,"locality_id":1327129773,"region_id":85683049}],"wof:id":1327129773,"wof:lang_x_official":["est"],"wof:lang_x_spoken":["est"],"wof:lastmodified":1596678048,"wof:name":"Uuskuela","wof:parent_id":1713308269,"wof:placetype":"locality","wof:repo":"whosonfirst-data-admin-ee","wof:superseded_by":[],"wof:supersedes":[],"wof:tags":[]},"bbox":[25.87083,59.51417,25.87083,59.51417],"geometry":{"coordinates":[25.87083,59.51417],"type":"Point"}}