{"id":1293683587,"type":"Feature","properties":{"edtf:cessation":"uuuu","edtf:inception":"uuuu","geom:area":0,"geom:area_square_m":0,"geom:bbox":"23.53333,58.78333,23.53333,58.78333","geom:latitude":58.78333,"geom:longitude":23.53333,"gn:admin1_code":"7.0","gn:admin2_code":"184.0","gn:admin3_code":"3027.0","gn:asciiname":"Lopi","gn:country_code":"EE","gn:dem":6,"gn:feature_class":"P","gn:feature_code":"PPL","gn:geonameid":590509,"gn:latitude":58.78333,"gn:longitude":23.53333,"gn:modification_date":"2017-11-25","gn:name":"Lopi","gn:population":0,"gn:timezone":"Europe/Tallinn","iso:country":"EE","lbl:bbox":"23.51333,58.76333,23.55333,58.80333","lbl:max_zoom":18,"lbl:min_zoom":13.5,"mz:hierarchy_label":1,"mz:is_current":1,"mz:min_zoom":12,"src:geom":"geonames","wof:belongsto":[85683001,102191581,1713308575,85633135,1713305755],"wof:breaches":[],"wof:concordances":{"gn:id":590509},"wof:country":"EE","wof:geomhash":"46af0fa7ae72a032efe6a52279450685","wof:hierarchy":[{"continent_id":102191581,"country_id":85633135,"county_id":1713305755,"localadmin_id":1713308575,"locality_id":1293683587,"region_id":85683001}],"wof:id":1293683587,"wof:lang_x_official":["est"],"wof:lang_x_spoken":["est"],"wof:lastmodified":1596662777,"wof:name":"Lopi","wof:parent_id":1713308575,"wof:placetype":"locality","wof:repo":"whosonfirst-data-admin-ee","wof:superseded_by":[],"wof:supersedes":[],"wof:tags":[]},"bbox":[23.53333,58.78333,23.53333,58.78333],"geometry":{"coordinates":[23.53333,58.78333],"type":"Point"}}