{"id":1243431557,"type":"Feature","properties":{"edtf:cessation":"uuuu","edtf:inception":"uuuu","geom:area":0,"geom:area_square_m":0,"geom:bbox":"26.71389,58.13806,26.71389,58.13806","geom:latitude":58.13806,"geom:longitude":26.71389,"gn:admin1_code":"12.0","gn:admin2_code":"284.0","gn:admin3_code":"4707.0","gn:asciiname":"Lutsu","gn:country_code":"EE","gn:dem":146,"gn:feature_class":"P","gn:feature_code":"PPL","gn:geonameid":8620609,"gn:latitude":58.13806,"gn:longitude":26.71389,"gn:modification_date":"2017-11-25","gn:name":"Lutsu","gn:population":0,"gn:timezone":"Europe/Tallinn","iso:country":"EE","lbl:bbox":"26.69389,58.11806,26.73389,58.15806","lbl:max_zoom":18,"lbl:min_zoom":13.5,"mz:hierarchy_label":1,"mz:is_current":1,"mz:min_zoom":12,"name:ceb_x_preferred":["Lutsu"],"name:est_x_preferred":["Lutsu"],"name:fra_x_preferred":["Lutsu"],"name:hye_x_preferred":["Լուցու"],"name:pol_x_preferred":["Lutsu"],"name:swe_x_preferred":["Lutsu"],"name:ukr_x_preferred":["Лутсу"],"name:und_x_variant":["Alaküla"],"name:vol_x_preferred":["Lutsu"],"src:geom":"geonames","wof:belongsto":[85682955,102191581,1713309941,85633135,1713305789],"wof:breaches":[],"wof:concordances":{"gn:id":8620609},"wof:country":"EE","wof:geomhash":"599e8c2a96ce59c00277ebc6196837f8","wof:hierarchy":[{"continent_id":102191581,"country_id":85633135,"county_id":1713305789,"localadmin_id":1713309941,"locality_id":1243431557,"region_id":85682955}],"wof:id":1243431557,"wof:lang_x_official":["est"],"wof:lang_x_spoken":["est"],"wof:lastmodified":1596676796,"wof:name":"Lutsu","wof:parent_id":1713309941,"wof:placetype":"locality","wof:repo":"whosonfirst-data-admin-ee","wof:superseded_by":[],"wof:supersedes":[],"wof:tags":[]},"bbox":[26.71389,58.13806,26.71389,58.13806],"geometry":{"coordinates":[26.71389,58.13806],"type":"Point"}}