{"id":1327428571,"type":"Feature","properties":{"edtf:cessation":"uuuu","edtf:inception":"uuuu","geom:area":0,"geom:area_square_m":0,"geom:bbox":"24.00972,58.84278,24.00972,58.84278","geom:latitude":58.84278,"geom:longitude":24.00972,"gn:admin1_code":"7.0","gn:admin2_code":"441.0","gn:admin3_code":"2266.0","gn:asciiname":"Madaste","gn:country_code":"EE","gn:dem":22,"gn:feature_class":"P","gn:feature_code":"PPL","gn:geonameid":590428,"gn:latitude":58.84278,"gn:longitude":24.00972,"gn:modification_date":"2017-11-25","gn:name":"Madaste","gn:population":0,"gn:timezone":"Europe/Tallinn","iso:country":"EE","lbl:bbox":"23.98972,58.82278,24.02972,58.86278","lbl:max_zoom":18,"lbl:min_zoom":13.5,"mz:hierarchy_label":1,"mz:is_current":1,"mz:min_zoom":12,"src:geom":"geonames","wof:belongsto":[85683001,102191581,1713309133,85633135,1713305701],"wof:breaches":[],"wof:concordances":{"gn:id":590428},"wof:country":"EE","wof:geomhash":"dd09a026ef8f7bf726612e48e98f597b","wof:hierarchy":[{"continent_id":102191581,"country_id":85633135,"county_id":1713305701,"localadmin_id":1713309133,"locality_id":1327428571,"region_id":85683001}],"wof:id":1327428571,"wof:lang_x_official":["est"],"wof:lang_x_spoken":["est"],"wof:lastmodified":1596677439,"wof:name":"Madaste","wof:parent_id":1713309133,"wof:placetype":"locality","wof:repo":"whosonfirst-data-admin-ee","wof:superseded_by":[],"wof:supersedes":[],"wof:tags":[]},"bbox":[24.00972,58.84278,24.00972,58.84278],"geometry":{"coordinates":[24.00972,58.84278],"type":"Point"}}