{"id":1259404013,"type":"Feature","properties":{"edtf:cessation":"uuuu","edtf:inception":"uuuu","geom:area":0,"geom:area_square_m":0,"geom:bbox":"23.49333,58.81222,23.49333,58.81222","geom:latitude":58.81222,"geom:longitude":23.49333,"gn:admin1_code":"7.0","gn:asciiname":"Pogari","gn:cc2":"EE","gn:country_code":"EE","gn:dem":1,"gn:feature_class":"P","gn:feature_code":"PPL","gn:geonameid":589724,"gn:latitude":58.81222,"gn:longitude":23.49333,"gn:modification_date":"2012-01-17","gn:name":"Põgari","gn:population":0,"gn:timezone":"Europe/Tallinn","iso:country":"EE","lbl:bbox":"23.47333,58.79222,23.51333,58.83222","lbl:max_zoom":18,"lbl:min_zoom":13.5,"mz:hierarchy_label":1,"mz:is_current":1,"mz:min_zoom":12,"name:und_x_variant":["Pagari","Peggari","Põgari"],"src:geom":"geonames","wof:belongsto":[],"wof:breaches":[],"wof:concordances":{"gn:id":589724},"wof:country":"EE","wof:geomhash":"28e14667a461ba133d055b2b7342060e","wof:hierarchy":[{"continent_id":-1,"country_id":-1,"locality_id":1259404013,"region_id":-1}],"wof:id":1259404013,"wof:lang_x_official":["est"],"wof:lang_x_spoken":["est"],"wof:lastmodified":1596485157,"wof:name":"Pogari","wof:parent_id":-1,"wof:placetype":"locality","wof:repo":"whosonfirst-data-admin-ee","wof:superseded_by":[],"wof:supersedes":[],"wof:tags":[]},"bbox":[23.49333,58.81222,23.49333,58.81222],"geometry":{"coordinates":[23.49333,58.81222],"type":"Point"}}