{"id":1343948659,"type":"Feature","properties":{"edtf:cessation":"uuuu","edtf:inception":"uuuu","geom:area":0,"geom:area_square_m":0,"geom:bbox":"26.31806,59.06639,26.31806,59.06639","geom:latitude":59.06639,"geom:longitude":26.31806,"gn:admin1_code":"8.0","gn:admin2_code":"928.0","gn:admin3_code":"3692.0","gn:asciiname":"Kurtna","gn:country_code":"EE","gn:dem":108,"gn:feature_class":"P","gn:feature_code":"PPL","gn:geonameid":590912,"gn:latitude":59.06639,"gn:longitude":26.31806,"gn:modification_date":"2017-11-25","gn:name":"Kurtna","gn:population":0,"gn:timezone":"Europe/Tallinn","iso:country":"EE","lbl:bbox":"26.29806,59.04639,26.33806,59.08639","lbl:max_zoom":18,"lbl:min_zoom":13.5,"mz:hierarchy_label":1,"mz:is_current":1,"mz:min_zoom":12,"name:est_x_preferred":["Kurtna"],"name:hye_x_preferred":["Կուռտնա"],"name:pol_x_preferred":["Kurtna"],"name:vol_x_preferred":["Kurtna"],"src:geom":"geonames","wof:belongsto":[85683049,102191581,1713312005,85633135,1713305769],"wof:breaches":[],"wof:concordances":{"gn:id":590912,"wk:page":"Kurtna%2C_L%C3%A4%C3%A4ne-Viru_County"},"wof:coterminous":[1713312005],"wof:country":"EE","wof:geomhash":"7562e9ed1dd725c9982a9309a0236fbe","wof:hierarchy":[{"continent_id":102191581,"country_id":85633135,"county_id":1713305769,"localadmin_id":1713312005,"locality_id":1343948659,"region_id":85683049}],"wof:id":1343948659,"wof:lang_x_official":["est"],"wof:lang_x_spoken":["est"],"wof:lastmodified":1596676545,"wof:name":"Kurtna","wof:parent_id":1713312005,"wof:placetype":"locality","wof:repo":"whosonfirst-data-admin-ee","wof:superseded_by":[],"wof:supersedes":[],"wof:tags":[]},"bbox":[26.31806,59.06639,26.31806,59.06639],"geometry":{"coordinates":[26.31806,59.06639],"type":"Point"}}