{"id":1276585625,"type":"Feature","properties":{"edtf:cessation":"uuuu","edtf:inception":"uuuu","geom:area":0,"geom:area_square_m":0,"geom:bbox":"25.52528,58.91389,25.52528,58.91389","geom:latitude":58.91389,"geom:longitude":25.52528,"gn:admin1_code":"4.0","gn:admin2_code":"567.0","gn:admin3_code":"9379.0","gn:asciiname":"Viraksaare","gn:country_code":"EE","gn:dem":73,"gn:feature_class":"P","gn:feature_code":"PPL","gn:geonameid":8618493,"gn:latitude":58.91389,"gn:longitude":25.52528,"gn:modification_date":"2017-11-25","gn:name":"Viraksaare","gn:population":0,"gn:timezone":"Europe/Tallinn","iso:country":"EE","lbl:bbox":"25.50528,58.89389,25.54528,58.93389","lbl:max_zoom":18,"lbl:min_zoom":13.5,"mz:hierarchy_label":1,"mz:is_current":1,"mz:min_zoom":12,"name:est_x_preferred":["Viraksaare"],"name:hye_x_preferred":["Վիռակսաառե"],"name:pol_x_preferred":["Viraksaare"],"name:ukr_x_preferred":["Віраксааре"],"name:vol_x_preferred":["Viraksaare"],"src:geom":"geonames","wof:belongsto":[85683031,102191581,1713308195,85633135,1713305663],"wof:breaches":[],"wof:concordances":{"gn:id":8618493,"wk:page":"Viraksaare"},"wof:coterminous":[1713308195],"wof:country":"EE","wof:geomhash":"004ee48236a510817ee2030325f54502","wof:hierarchy":[{"continent_id":102191581,"country_id":85633135,"county_id":1713305663,"localadmin_id":1713308195,"locality_id":1276585625,"region_id":85683031}],"wof:id":1276585625,"wof:lang_x_official":["est"],"wof:lang_x_spoken":["est"],"wof:lastmodified":1596661330,"wof:name":"Viraksaare","wof:parent_id":1713308195,"wof:placetype":"locality","wof:repo":"whosonfirst-data-admin-ee","wof:superseded_by":[],"wof:supersedes":[],"wof:tags":[]},"bbox":[25.52528,58.91389,25.52528,58.91389],"geometry":{"coordinates":[25.52528,58.91389],"type":"Point"}}