{"id":1326811541,"type":"Feature","properties":{"edtf:cessation":"uuuu","edtf:inception":"uuuu","geom:area":0,"geom:area_square_m":0,"geom:bbox":"24.87694,58.57361,24.87694,58.57361","geom:latitude":58.57361,"geom:longitude":24.87694,"gn:admin1_code":"11.0","gn:admin2_code":"809.0","gn:admin3_code":"4774.0","gn:asciiname":"Sikana","gn:country_code":"EE","gn:dem":35,"gn:feature_class":"P","gn:feature_code":"PPL","gn:geonameid":588692,"gn:latitude":58.57361,"gn:longitude":24.87694,"gn:modification_date":"2017-11-25","gn:name":"Sikana","gn:population":0,"gn:timezone":"Europe/Tallinn","iso:country":"EE","lbl:bbox":"24.85694,58.55361,24.89694,58.59361","lbl:max_zoom":18,"lbl:min_zoom":13.5,"mz:hierarchy_label":1,"mz:is_current":1,"mz:min_zoom":12,"name:est_x_preferred":["Sikana"],"name:hye_x_preferred":["Սիկանա"],"name:pol_x_preferred":["Sikana"],"name:spa_x_preferred":["Sikana"],"name:vol_x_preferred":["Sikana"],"src:geom":"geonames","wof:belongsto":[85682981,102191581,1713314555,85633135,1713305731],"wof:breaches":[],"wof:concordances":{"gn:id":588692,"wk:page":"Sikana"},"wof:coterminous":[1713314557],"wof:country":"EE","wof:geomhash":"fa354f9f0d2ad7eeb66f8c528db32281","wof:hierarchy":[{"continent_id":102191581,"country_id":85633135,"county_id":1713305731,"localadmin_id":1713314555,"locality_id":1326811541,"region_id":85682981}],"wof:id":1326811541,"wof:lang_x_official":["est"],"wof:lang_x_spoken":["est"],"wof:lastmodified":1596663382,"wof:name":"Sikana","wof:parent_id":1713314555,"wof:placetype":"locality","wof:repo":"whosonfirst-data-admin-ee","wof:superseded_by":[],"wof:supersedes":[],"wof:tags":[]},"bbox":[24.87694,58.57361,24.87694,58.57361],"geometry":{"coordinates":[24.87694,58.57361],"type":"Point"}}