{"id":1125913089,"type":"Feature","properties":{"edtf:cessation":"uuuu","edtf:inception":"uuuu","geom:area":0,"geom:area_square_m":0,"geom:bbox":"23.52667,59.22,23.52667,59.22","geom:latitude":59.22,"geom:longitude":23.52667,"gn:country":"EE","gn:fcode":"PPL","gn:population":0,"iso:country":"EE","lbl:bbox":"23.50667,59.2,23.54667,59.24","lbl:latitude":59.22,"lbl:longitude":23.52667,"lbl:max_zoom":18,"lbl:min_zoom":13.5,"mz:hierarchy_label":1,"mz:is_current":1,"mz:min_zoom":12,"mz:note":"Quattroshapes Point Gazetteer import 20170519","name:deu_x_preferred":["Spithami"],"name:eng_x_preferred":["Spithami"],"name:est_x_preferred":["Spithami"],"name:hye_x_preferred":["Սպիթամի"],"name:jpn_x_preferred":["スピットハミ"],"name:nld_x_preferred":["Spithami"],"name:pol_x_preferred":["Spithami"],"name:spa_x_preferred":["Spithami"],"name:swe_x_preferred":["Spithamn"],"name:ukr_x_preferred":["Спітгамі"],"name:vol_x_preferred":["Spithami"],"qs_pg:aaroncc":"EE","qs_pg:gn_country":"EE","qs_pg:gn_fcode":"PPL","qs_pg:gn_id":794915,"qs_pg:gn_pop":0,"qs_pg:name":"Spithami","qs_pg:name_adm0":"Eesti","qs_pg:name_adm1":"Läänemaa","qs_pg:photos":80,"qs_pg:photos_1k":16,"qs_pg:photos_9k":1,"qs_pg:photos_9r":3,"qs_pg:photos_all":80,"qs_pg:photos_sr":3,"qs_pg:pop_sr":0,"qs_pg:qs_id":478103,"qs_pg:qs_pg_placetype":"locality","qs_pg:qs_pg_placetype_gp":"Town","qs_pg:woe_adm0":23424805,"qs_pg:woe_id":845617,"src:geom":"qs_pg","src:lbl_centroid":"qs_pg","woe:adm0_id":23424805,"woe:name_adm0":"Eesti","woe:name_adm1":"Läänemaa","woe:placetype":"Town","wof:belongsto":[85683001,102191581,1713308705,85633135,1713305701],"wof:breaches":[],"wof:concordances":{"gn:id":794915,"gp:id":845617,"qs_pg:id":478103,"wd:id":"Q3451054"},"wof:coterminous":[1713308705],"wof:country":"EE","wof:created":1497296205,"wof:geomhash":"d2ea9014eef8fc2ce906278f9ff8413a","wof:hierarchy":[{"continent_id":102191581,"country_id":85633135,"county_id":1713305701,"localadmin_id":1713308705,"locality_id":1125913089,"region_id":85683001}],"wof:id":1125913089,"wof:lang_x_official":["est"],"wof:lang_x_spoken":["est"],"wof:lastmodified":1596677433,"wof:name":"Spithami","wof:parent_id":1713308705,"wof:placetype":"locality","wof:repo":"whosonfirst-data-admin-ee","wof:superseded_by":[],"wof:supersedes":[],"wof:tags":[]},"bbox":[23.52667,59.22,23.52667,59.22],"geometry":{"coordinates":[23.52667,59.22],"type":"Point"}}