{"id":1293667955,"type":"Feature","properties":{"edtf:cessation":"uuuu","edtf:inception":"uuuu","geom:area":0,"geom:area_square_m":0,"geom:bbox":"22.445,58.50278,22.445,58.50278","geom:latitude":58.50278,"geom:longitude":22.445,"gn:admin1_code":"14.0","gn:admin2_code":"714.0","gn:admin3_code":"2324.0","gn:asciiname":"Jaerise","gn:country_code":"EE","gn:dem":41,"gn:feature_class":"P","gn:feature_code":"PPL","gn:geonameid":591977,"gn:latitude":58.50278,"gn:longitude":22.445,"gn:modification_date":"2017-11-25","gn:name":"Järise","gn:population":0,"gn:timezone":"Europe/Tallinn","iso:country":"EE","lbl:bbox":"22.425,58.48278,22.465,58.52278","lbl:max_zoom":18,"lbl:min_zoom":13.5,"mz:hierarchy_label":1,"mz:is_current":1,"mz:min_zoom":12,"name:deu_x_preferred":["Järise"],"name:est_x_preferred":["Järise"],"name:hye_x_preferred":["Եռիսե"],"name:pol_x_preferred":["Järise"],"name:spa_x_preferred":["Järise"],"name:und_x_variant":["Yarise"],"name:urd_x_preferred":["جارسے"],"name:vol_x_preferred":["Järise"],"src:geom":"geonames","wof:belongsto":[85682947,102191581,1713307341,85633135,1713305627],"wof:breaches":[],"wof:concordances":{"gn:id":591977,"wk:page":"J%C3%A4rise%2C_Saare_County"},"wof:coterminous":[1713307341],"wof:country":"EE","wof:geomhash":"dee70e759a25a6319bc64cac3a7cd164","wof:hierarchy":[{"continent_id":102191581,"country_id":85633135,"county_id":1713305627,"localadmin_id":1713307341,"locality_id":1293667955,"region_id":85682947}],"wof:id":1293667955,"wof:lang_x_official":["est"],"wof:lang_x_spoken":["est"],"wof:lastmodified":1596674972,"wof:name":"Jaerise","wof:parent_id":1713307341,"wof:placetype":"locality","wof:repo":"whosonfirst-data-admin-ee","wof:superseded_by":[],"wof:supersedes":[],"wof:tags":[]},"bbox":[22.445,58.50278,22.445,58.50278],"geometry":{"coordinates":[22.445,58.50278],"type":"Point"}}