{"id":1293689711,"type":"Feature","properties":{"edtf:cessation":"uuuu","edtf:inception":"uuuu","geom:area":0,"geom:area_square_m":0,"geom:bbox":"22.59692,58.99621,22.59692,58.99621","geom:latitude":58.99621,"geom:longitude":22.59692,"gn:admin1_code":"2.0","gn:admin2_code":"205.0","gn:admin3_code":"3004.0","gn:asciiname":"Kidaste","gn:country_code":"EE","gn:dem":13,"gn:feature_class":"P","gn:feature_code":"PPL","gn:geonameid":591424,"gn:latitude":58.99621,"gn:longitude":22.59692,"gn:modification_date":"2017-11-25","gn:name":"Kidaste","gn:population":0,"gn:timezone":"Europe/Tallinn","iso:country":"EE","lbl:bbox":"22.57692,58.97621,22.61692,59.01621","lbl:max_zoom":18,"lbl:min_zoom":13.5,"mz:hierarchy_label":1,"mz:is_current":1,"mz:min_zoom":12,"name:deu_x_preferred":["Kidaste"],"name:est_x_preferred":["Kidaste"],"name:hye_x_preferred":["Կիդաստե"],"name:nld_x_preferred":["Kidaste"],"name:pol_x_preferred":["Kidaste"],"name:spa_x_preferred":["Kidaste"],"name:vol_x_preferred":["Kidaste"],"src:geom":"geonames","wof:belongsto":[85682989,102191581,1713310697,85633135,1713305629],"wof:breaches":[],"wof:concordances":{"gn:id":591424,"wk:page":"Kidaste"},"wof:coterminous":[1713310697],"wof:country":"EE","wof:geomhash":"21b9d4bbb05d1d432ce088a47b20fa5f","wof:hierarchy":[{"continent_id":102191581,"country_id":85633135,"county_id":1713305629,"localadmin_id":1713310697,"locality_id":1293689711,"region_id":85682989}],"wof:id":1293689711,"wof:lang_x_official":["est"],"wof:lang_x_spoken":["est"],"wof:lastmodified":1596670023,"wof:name":"Kidaste","wof:parent_id":1713310697,"wof:placetype":"locality","wof:repo":"whosonfirst-data-admin-ee","wof:superseded_by":[],"wof:supersedes":[],"wof:tags":[]},"bbox":[22.59692,58.99621,22.59692,58.99621],"geometry":{"coordinates":[22.59692,58.99621],"type":"Point"}}