{"id":1293279169,"type":"Feature","properties":{"edtf:cessation":"uuuu","edtf:inception":"uuuu","geom:area":0,"geom:area_square_m":0,"geom:bbox":"26.63556,58.03917,26.63556,58.03917","geom:latitude":58.03917,"geom:longitude":26.63556,"gn:admin1_code":"12.0","gn:admin2_code":"284.0","gn:admin3_code":"1785.0","gn:asciiname":"Oru-Taki","gn:country_code":"EE","gn:dem":186,"gn:feature_class":"P","gn:feature_code":"PPL","gn:geonameid":8620025,"gn:latitude":58.03917,"gn:longitude":26.63556,"gn:modification_date":"2017-11-25","gn:name":"Oru-Taki","gn:population":0,"gn:timezone":"Europe/Tallinn","iso:country":"EE","lbl:bbox":"26.61556,58.01917,26.65556,58.05917","lbl:max_zoom":18,"lbl:min_zoom":13.5,"mz:hierarchy_label":1,"mz:is_current":1,"mz:min_zoom":12,"name:und_x_variant":["Oru-Tani"],"src:geom":"geonames","wof:belongsto":[85682955,102191581,1713314269,85633135,1713305789],"wof:breaches":[],"wof:concordances":{"gn:id":8620025},"wof:country":"EE","wof:geomhash":"726864cd21bc34254f64eed5a74b6fc5","wof:hierarchy":[{"continent_id":102191581,"country_id":85633135,"county_id":1713305789,"localadmin_id":1713314269,"locality_id":1293279169,"region_id":85682955}],"wof:id":1293279169,"wof:lang_x_official":["est"],"wof:lang_x_spoken":["est"],"wof:lastmodified":1596676791,"wof:name":"Oru-Taki","wof:parent_id":1713314269,"wof:placetype":"locality","wof:repo":"whosonfirst-data-admin-ee","wof:superseded_by":[],"wof:supersedes":[],"wof:tags":[]},"bbox":[26.63556,58.03917,26.63556,58.03917],"geometry":{"coordinates":[26.63556,58.03917],"type":"Point"}}