{"id":1326611337,"type":"Feature","properties":{"edtf:cessation":"uuuu","edtf:inception":"uuuu","geom:area":0,"geom:area_square_m":0,"geom:bbox":"24.89806,58.46889,24.89806,58.46889","geom:latitude":58.46889,"geom:longitude":24.89806,"gn:admin1_code":"11.0","gn:admin2_code":"809.0","gn:admin3_code":"2251.0","gn:asciiname":"Puussaare","gn:country_code":"EE","gn:dem":23,"gn:feature_class":"P","gn:feature_code":"PPL","gn:geonameid":8620525,"gn:latitude":58.46889,"gn:longitude":24.89806,"gn:modification_date":"2017-11-25","gn:name":"Puussaare","gn:population":0,"gn:timezone":"Europe/Tallinn","iso:country":"EE","lbl:bbox":"24.87806,58.44889,24.91806,58.48889","lbl:max_zoom":18,"lbl:min_zoom":13.5,"mz:hierarchy_label":1,"mz:is_current":1,"mz:min_zoom":12,"name:und_x_variant":["Paista"],"src:geom":"geonames","wof:belongsto":[85682981,102191581,1713312415,85633135,1713305731],"wof:breaches":[],"wof:concordances":{"gn:id":8620525},"wof:country":"EE","wof:geomhash":"74f9f18650e455fc88a4fdb80e704a62","wof:hierarchy":[{"continent_id":102191581,"country_id":85633135,"county_id":1713305731,"localadmin_id":1713312415,"locality_id":1326611337,"region_id":85682981}],"wof:id":1326611337,"wof:lang_x_official":["est"],"wof:lang_x_spoken":["est"],"wof:lastmodified":1596663387,"wof:name":"Puussaare","wof:parent_id":1713312415,"wof:placetype":"locality","wof:repo":"whosonfirst-data-admin-ee","wof:superseded_by":[],"wof:supersedes":[],"wof:tags":[]},"bbox":[24.89806,58.46889,24.89806,58.46889],"geometry":{"coordinates":[24.89806,58.46889],"type":"Point"}}