{"id":1310665611,"type":"Feature","properties":{"edtf:cessation":"uuuu","edtf:inception":"uuuu","geom:area":0,"geom:area_square_m":0,"geom:bbox":"25.6475,58.50722,25.6475,58.50722","geom:latitude":58.50722,"geom:longitude":25.6475,"gn:admin1_code":"20.0","gn:admin2_code":"615.0","gn:admin3_code":"8586.0","gn:asciiname":"Onniste","gn:country_code":"EE","gn:dem":61,"gn:feature_class":"P","gn:feature_code":"PPL","gn:geonameid":589828,"gn:latitude":58.50722,"gn:longitude":25.6475,"gn:modification_date":"2017-11-25","gn:name":"Õnniste","gn:population":0,"gn:timezone":"Europe/Tallinn","iso:country":"EE","lbl:bbox":"25.6275,58.48722,25.6675,58.52722","lbl:max_zoom":18,"lbl:min_zoom":13.5,"mz:hierarchy_label":1,"mz:is_current":1,"mz:min_zoom":12,"name:und_x_variant":["Õniste","Õnniste"],"src:geom":"geonames","wof:belongsto":[85682985,102191581,1713311941,85633135,1713305735],"wof:breaches":[],"wof:concordances":{"gn:id":589828},"wof:country":"EE","wof:geomhash":"be6acd1cb5367d453112703815569f70","wof:hierarchy":[{"continent_id":102191581,"country_id":85633135,"county_id":1713305735,"localadmin_id":1713311941,"locality_id":1310665611,"region_id":85682985}],"wof:id":1310665611,"wof:lang_x_official":["est"],"wof:lang_x_spoken":["est"],"wof:lastmodified":1596663460,"wof:name":"Onniste","wof:parent_id":1713311941,"wof:placetype":"locality","wof:repo":"whosonfirst-data-admin-ee","wof:superseded_by":[],"wof:supersedes":[],"wof:tags":[]},"bbox":[25.6475,58.50722,25.6475,58.50722],"geometry":{"coordinates":[25.6475,58.50722],"type":"Point"}}