{"id":1309927019,"type":"Feature","properties":{"edtf:cessation":"uuuu","edtf:inception":"uuuu","geom:area":0,"geom:area_square_m":0,"geom:bbox":"23.60333,58.65861,23.60333,58.65861","geom:latitude":58.65861,"geom:longitude":23.60333,"gn:admin1_code":"11.0","gn:admin2_code":"430.0","gn:admin3_code":"4807.0","gn:asciiname":"Kokuta","gn:country_code":"EE","gn:dem":16,"gn:feature_class":"P","gn:feature_code":"PPL","gn:geonameid":591216,"gn:latitude":58.65861,"gn:longitude":23.60333,"gn:modification_date":"2017-11-25","gn:name":"Kokuta","gn:population":0,"gn:timezone":"Europe/Tallinn","iso:country":"EE","lbl:bbox":"23.58333,58.63861,23.62333,58.67861","lbl:max_zoom":18,"lbl:min_zoom":13.5,"mz:hierarchy_label":1,"mz:is_current":1,"mz:min_zoom":12,"name:deu_x_preferred":["Kokuta"],"name:est_x_preferred":["Kokuta"],"name:hye_x_preferred":["Կոկուտա"],"name:pol_x_preferred":["Kokuta"],"name:spa_x_preferred":["Kokuta"],"name:ukr_x_preferred":["Кокута"],"name:vol_x_preferred":["Kokuta"],"src:geom":"geonames","wof:belongsto":[85683001,102191581,1713309661,85633135,1713305721],"wof:breaches":[],"wof:concordances":{"gn:id":591216,"wk:page":"Kokuta"},"wof:coterminous":[1713309171],"wof:country":"EE","wof:geomhash":"df5a899ada637f8d33b517886be2101f","wof:hierarchy":[{"continent_id":102191581,"country_id":85633135,"county_id":1713305721,"localadmin_id":1713309661,"locality_id":1309927019,"region_id":85683001}],"wof:id":1309927019,"wof:lang_x_official":["est"],"wof:lang_x_spoken":["est"],"wof:lastmodified":1596661679,"wof:name":"Kokuta","wof:parent_id":1713309661,"wof:placetype":"locality","wof:repo":"whosonfirst-data-admin-ee","wof:superseded_by":[],"wof:supersedes":[],"wof:tags":[]},"bbox":[23.60333,58.65861,23.60333,58.65861],"geometry":{"coordinates":[23.60333,58.65861],"type":"Point"}}