{"id":1125935537,"type":"Feature","properties":{"edtf:cessation":"uuuu","edtf:inception":"uuuu","geom:area":0,"geom:area_square_m":0,"geom:bbox":"26.88,57.98028,26.88,57.98028","geom:latitude":57.98028,"geom:longitude":26.88,"gn:country":"EE","gn:fcode":"PPL","gn:population":372,"iso:country":"EE","lbl:bbox":"26.86,57.96028,26.9,58.00028","lbl:latitude":57.98028,"lbl:longitude":26.88,"lbl:max_zoom":17,"lbl:min_zoom":12.5,"mz:hierarchy_label":1,"mz:is_current":1,"mz:min_zoom":11,"mz:note":"Quattroshapes Point Gazetteer import 20170519","name:ceb_x_preferred":["Põlgaste"],"name:eng_x_preferred":["Põlgaste"],"name:est_x_preferred":["Põlgaste"],"name:hye_x_preferred":["Պիլգաստե"],"name:nld_x_preferred":["Põlgaste"],"name:pol_x_preferred":["Põlgaste"],"name:spa_x_preferred":["Põlgaste"],"name:swe_x_preferred":["Põlgaste"],"name:ukr_x_preferred":["Пилгасте"],"name:vol_x_preferred":["Põlgaste"],"name:vro_x_preferred":["Põlgastõ"],"qs_pg:aaroncc":"EE","qs_pg:gn_country":"EE","qs_pg:gn_fcode":"PPL","qs_pg:gn_id":794583,"qs_pg:gn_pop":372,"qs_pg:name":"Põlgaste","qs_pg:name_adm0":"Eesti","qs_pg:name_adm1":"Põlvamaa","qs_pg:photos_9r":0,"qs_pg:photos_sr":0,"qs_pg:pop_sr":2,"qs_pg:qs_id":1274360,"qs_pg:qs_pg_placetype":"locality","qs_pg:qs_pg_placetype_gp":"Town","qs_pg:woe_adm0":23424805,"qs_pg:woe_id":844819,"src:geom":"qs_pg","src:lbl_centroid":"qs_pg","src:population":"geonames","woe:adm0_id":23424805,"woe:name_adm0":"Eesti","woe:name_adm1":"Põlvamaa","woe:placetype":"Town","wof:belongsto":[85682955,102191581,1713312595,85633135,1713305789],"wof:breaches":[],"wof:concordances":{"gn:id":794583,"gp:id":844819,"qs_pg:id":1274360,"wd:id":"Q3464824"},"wof:coterminous":[1713312595],"wof:country":"EE","wof:created":1497296955,"wof:geomhash":"c91b30915e3026f88cd581b93764c46b","wof:hierarchy":[{"continent_id":102191581,"country_id":85633135,"county_id":1713305789,"localadmin_id":1713312595,"locality_id":1125935537,"region_id":85682955}],"wof:id":1125935537,"wof:lang_x_official":["est"],"wof:lang_x_spoken":["est"],"wof:lastmodified":1596676797,"wof:name":"Põlgaste","wof:parent_id":1713312595,"wof:placetype":"locality","wof:population":372,"wof:population_rank":2,"wof:repo":"whosonfirst-data-admin-ee","wof:superseded_by":[],"wof:supersedes":[],"wof:tags":[]},"bbox":[26.88,57.98028,26.88,57.98028],"geometry":{"coordinates":[26.88,57.98028],"type":"Point"}}