{"id":1277059957,"type":"Feature","properties":{"edtf:cessation":"uuuu","edtf:inception":"uuuu","geom:area":0,"geom:area_square_m":0,"geom:bbox":"22.91111,58.4125,22.91111,58.4125","geom:latitude":58.4125,"geom:longitude":22.91111,"gn:admin1_code":"14.0","gn:admin2_code":"714.0","gn:admin3_code":"8502.0","gn:asciiname":"Tonija","gn:cc2":"EE","gn:country_code":"EE","gn:dem":13,"gn:feature_class":"P","gn:feature_code":"PPL","gn:geonameid":588243,"gn:latitude":58.4125,"gn:longitude":22.91111,"gn:modification_date":"2017-11-25","gn:name":"Tõnija","gn:population":0,"gn:timezone":"Europe/Tallinn","iso:country":"EE","lbl:bbox":"22.89111,58.3925,22.93111,58.4325","lbl:max_zoom":18,"lbl:min_zoom":13.5,"mz:hierarchy_label":1,"mz:is_current":1,"mz:min_zoom":12,"name:deu_x_preferred":["Tõnija"],"name:est_x_preferred":["Tõnija"],"name:hye_x_preferred":["Տինիյա"],"name:nld_x_preferred":["Tõnija"],"name:pol_x_preferred":["Tõnija"],"name:spa_x_preferred":["Tõnija"],"name:und_x_variant":["Tyniya"],"name:vol_x_preferred":["Tõnija"],"src:geom":"geonames","wof:belongsto":[85682947,102191581,1713308359,85633135,1713305627],"wof:breaches":[],"wof:concordances":{"gn:id":588243,"wk:page":"T%C3%B5nija"},"wof:coterminous":[1713308359],"wof:country":"EE","wof:geomhash":"4d9d0afd65984bee6d372975b04a2bdb","wof:hierarchy":[{"continent_id":102191581,"country_id":85633135,"county_id":1713305627,"localadmin_id":1713308359,"locality_id":1277059957,"region_id":85682947}],"wof:id":1277059957,"wof:lang_x_official":["est"],"wof:lang_x_spoken":["est"],"wof:lastmodified":1596674970,"wof:name":"Tonija","wof:parent_id":1713308359,"wof:placetype":"locality","wof:repo":"whosonfirst-data-admin-ee","wof:superseded_by":[],"wof:supersedes":[],"wof:tags":[]},"bbox":[22.91111,58.4125,22.91111,58.4125],"geometry":{"coordinates":[22.91111,58.4125],"type":"Point"}}