{"id":1125890481,"type":"Feature","properties":{"edtf:cessation":"uuuu","edtf:inception":"uuuu","geom:area":0,"geom:area_square_m":0,"geom:bbox":"27.51444,59.30306,27.51444,59.30306","geom:latitude":59.30306,"geom:longitude":27.51444,"gn:country":"EE","gn:fcode":"PPL","gn:population":95,"iso:country":"EE","lbl:bbox":"27.49444,59.28306,27.53444,59.32306","lbl:latitude":59.30306,"lbl:longitude":27.51444,"lbl:max_zoom":18,"lbl:min_zoom":13,"mz:hierarchy_label":1,"mz:is_current":1,"mz:min_zoom":11,"mz:note":"Quattroshapes Point Gazetteer import 20170519","name:deu_x_preferred":["Vasavere"],"name:eng_x_preferred":["Vasavere"],"name:est_x_preferred":["Vasavere"],"name:fas_x_preferred":["وسور"],"name:fra_x_preferred":["Vasavere"],"name:hye_x_preferred":["Վասավեռե"],"name:nld_x_preferred":["Vasavere"],"name:pol_x_preferred":["Vasavere"],"name:spa_x_preferred":["Vasavere"],"name:swe_x_preferred":["Vasavere"],"name:und_x_variant":["Wasawere"],"name:vol_x_preferred":["Vasavere"],"qs_pg:aaroncc":"EE","qs_pg:gn_country":"EE","qs_pg:gn_fcode":"PPL","qs_pg:gn_id":587730,"qs_pg:gn_pop":95,"qs_pg:name":"Vasavere","qs_pg:name_adm0":"Eesti","qs_pg:name_adm1":"Ida-Virumaa","qs_pg:photos_9k":1,"qs_pg:photos_9r":1,"qs_pg:photos_all":13,"qs_pg:photos_sr":0,"qs_pg:pop_sr":1,"qs_pg:qs_id":916031,"qs_pg:qs_pg_placetype":"locality","qs_pg:qs_pg_placetype_gp":"Town","qs_pg:woe_adm0":23424805,"qs_pg:woe_id":846341,"src:geom":"qs_pg","src:lbl_centroid":"qs_pg","src:population":"geonames","woe:adm0_id":23424805,"woe:name_adm0":"Eesti","woe:name_adm1":"Ida-Virumaa","woe:placetype":"Town","wof:belongsto":[85683059,102191581,1713311961,85633135,1713305693],"wof:breaches":[],"wof:concordances":{"gn:id":587730,"gp:id":846341,"qs_pg:id":916031,"wd:id":"Q1024074"},"wof:coterminous":[1713311961],"wof:country":"EE","wof:created":1497295293,"wof:geomhash":"2798e5a9f656768eb60b5a02af57cb04","wof:hierarchy":[{"continent_id":102191581,"country_id":85633135,"county_id":1713305693,"localadmin_id":1713311961,"locality_id":1125890481,"region_id":85683059}],"wof:id":1125890481,"wof:lang_x_official":["est"],"wof:lang_x_spoken":["est"],"wof:lastmodified":1596660754,"wof:name":"Vasavere","wof:parent_id":1713311961,"wof:placetype":"locality","wof:population":95,"wof:population_rank":1,"wof:repo":"whosonfirst-data-admin-ee","wof:superseded_by":[],"wof:supersedes":[],"wof:tags":[]},"bbox":[27.51444,59.30306,27.51444,59.30306],"geometry":{"coordinates":[27.51444,59.30306],"type":"Point"}}