{"id":1309688039,"type":"Feature","properties":{"edtf:cessation":"uuuu","edtf:inception":"uuuu","geom:area":0,"geom:area_square_m":0,"geom:bbox":"27.11222,58.57194,27.11222,58.57194","geom:latitude":58.57194,"geom:longitude":27.11222,"gn:admin1_code":"18.0","gn:admin2_code":"586.0","gn:admin3_code":"7127.0","gn:asciiname":"Rupsi","gn:country_code":"EE","gn:dem":62,"gn:feature_class":"P","gn:feature_code":"PPL","gn:geonameid":794086,"gn:latitude":58.57194,"gn:longitude":27.11222,"gn:modification_date":"2017-11-25","gn:name":"Rupsi","gn:population":0,"gn:timezone":"Europe/Tallinn","iso:country":"EE","lbl:bbox":"27.09222,58.55194,27.13222,58.59194","lbl:max_zoom":18,"lbl:min_zoom":13.5,"mz:hierarchy_label":1,"mz:is_current":1,"mz:min_zoom":12,"name:est_x_preferred":["Rupsi"],"name:fra_x_preferred":["Rupsi"],"name:hye_x_preferred":["Ռուպսի"],"name:pol_x_preferred":["Rupsi"],"name:spa_x_preferred":["Rupsi"],"name:ukr_x_preferred":["Рупсі"],"name:vol_x_preferred":["Rupsi"],"src:geom":"geonames","wof:belongsto":[85682995,102191581,1713309317,85633135,1713305679],"wof:breaches":[],"wof:concordances":{"gn:id":794086,"wk:page":"Rupsi"},"wof:coterminous":[1713309317],"wof:country":"EE","wof:geomhash":"012e791a5f25395436d890b4c4d33d75","wof:hierarchy":[{"continent_id":102191581,"country_id":85633135,"county_id":1713305679,"localadmin_id":1713309317,"locality_id":1309688039,"region_id":85682995}],"wof:id":1309688039,"wof:lang_x_official":["est"],"wof:lang_x_spoken":["est"],"wof:lastmodified":1596660920,"wof:name":"Rupsi","wof:parent_id":1713309317,"wof:placetype":"locality","wof:repo":"whosonfirst-data-admin-ee","wof:superseded_by":[],"wof:supersedes":[],"wof:tags":[]},"bbox":[27.11222,58.57194,27.11222,58.57194],"geometry":{"coordinates":[27.11222,58.57194],"type":"Point"}}