{"id":1209177457,"type":"Feature","properties":{"edtf:cessation":"uuuu","edtf:inception":"uuuu","geom:area":0,"geom:area_square_m":0,"geom:bbox":"27.05056,58.36917,27.05056,58.36917","geom:latitude":58.36917,"geom:longitude":27.05056,"gn:admin1_code":"18.0","gn:admin2_code":"291.0","gn:admin3_code":"2411.0","gn:asciiname":"Kaarlimoisa","gn:country_code":"EE","gn:dem":45,"gn:feature_class":"P","gn:feature_code":"PPL","gn:geonameid":794093,"gn:latitude":58.36917,"gn:longitude":27.05056,"gn:modification_date":"2017-11-25","gn:name":"Kaarlimõisa","gn:population":0,"gn:timezone":"Europe/Tallinn","iso:country":"EE","lbl:bbox":"27.03056,58.34917,27.07056,58.38917","lbl:max_zoom":18,"lbl:min_zoom":13.5,"mz:hierarchy_label":1,"mz:is_current":1,"mz:min_zoom":12,"name:est_x_preferred":["Kaarlimõisa"],"name:hye_x_preferred":["Կաառլիմիիսա"],"name:pol_x_preferred":["Kaarlimõisa"],"name:spa_x_preferred":["Kaarlimõisa"],"name:ukr_x_preferred":["Каарлімийза"],"name:vol_x_preferred":["Kaarlimõisa"],"src:geom":"geonames","wof:belongsto":[85682995,102191581,1713311317,85633135,1713305699],"wof:breaches":[],"wof:concordances":{"gn:id":794093,"wk:page":"Kaarlim%C3%B5isa"},"wof:coterminous":[1713311317],"wof:country":"EE","wof:geomhash":"d0782c87d6ce1ce09e5702362d5cd29b","wof:hierarchy":[{"continent_id":102191581,"country_id":85633135,"county_id":1713305699,"localadmin_id":1713311317,"locality_id":1209177457,"region_id":85682995}],"wof:id":1209177457,"wof:lang_x_official":["est"],"wof:lang_x_spoken":["est"],"wof:lastmodified":1596660663,"wof:name":"Kaarlimoisa","wof:parent_id":1713311317,"wof:placetype":"locality","wof:repo":"whosonfirst-data-admin-ee","wof:superseded_by":[],"wof:supersedes":[],"wof:tags":[]},"bbox":[27.05056,58.36917,27.05056,58.36917],"geometry":{"coordinates":[27.05056,58.36917],"type":"Point"}}