{"id":1125896915,"type":"Feature","properties":{"edtf:cessation":"uuuu","edtf:inception":"uuuu","geom:area":0,"geom:area_square_m":0,"geom:bbox":"22.49056,58.31028,22.49056,58.31028","geom:latitude":58.31028,"geom:longitude":22.49056,"gn:country":"EE","gn:fcode":"PPL","gn:population":167,"iso:country":"EE","lbl:bbox":"22.47056,58.29028,22.51056,58.33028","lbl:latitude":58.31028,"lbl:longitude":22.49056,"lbl:max_zoom":18,"lbl:min_zoom":13,"mz:hierarchy_label":1,"mz:is_current":1,"mz:min_zoom":11,"mz:note":"Quattroshapes Point Gazetteer import 20170519","name:ceb_x_preferred":["Pähkla"],"name:deu_x_preferred":["Pähkla"],"name:eng_x_preferred":["Pähkla"],"name:est_x_preferred":["Pähkla"],"name:fra_x_preferred":["Pähkla"],"name:hye_x_preferred":["Պեհկլա"],"name:nld_x_preferred":["Pähkla"],"name:pol_x_preferred":["Pähkla"],"name:spa_x_preferred":["Pähkla"],"name:swe_x_preferred":["Pähkla"],"name:ukr_x_preferred":["Пягкла"],"name:und_x_variant":["Pyakhkla"],"name:vol_x_preferred":["Pähkla"],"qs_pg:aaroncc":"EE","qs_pg:gn_country":"EE","qs_pg:gn_fcode":"PPL","qs_pg:gn_id":589716,"qs_pg:gn_pop":167,"qs_pg:name":"Pähkla","qs_pg:name_adm0":"Eesti","qs_pg:name_adm1":"Saaremaa","qs_pg:photos_9k":1,"qs_pg:photos_9r":1,"qs_pg:photos_all":1,"qs_pg:photos_sr":0,"qs_pg:pop_sr":1,"qs_pg:qs_id":940414,"qs_pg:qs_pg_placetype":"locality","qs_pg:qs_pg_placetype_gp":"Town","qs_pg:woe_adm0":23424805,"qs_pg:woe_id":844509,"src:geom":"qs_pg","src:lbl_centroid":"qs_pg","src:population":"geonames","woe:adm0_id":23424805,"woe:name_adm0":"Eesti","woe:name_adm1":"Saaremaa","woe:placetype":"Town","wof:belongsto":[85682947,102191581,1713307163,85633135,1713305627],"wof:breaches":[],"wof:concordances":{"gn:id":589716,"gp:id":844509,"qs_pg:id":940414,"wd:id":"Q3470661"},"wof:coterminous":[1713307163],"wof:country":"EE","wof:created":1497295616,"wof:geomhash":"501d2dbbd958d3ddf94843ee623096bf","wof:hierarchy":[{"continent_id":102191581,"country_id":85633135,"county_id":1713305627,"localadmin_id":1713307163,"locality_id":1125896915,"region_id":85682947}],"wof:id":1125896915,"wof:lang_x_official":["est"],"wof:lang_x_spoken":["est"],"wof:lastmodified":1596674950,"wof:name":"Pähkla","wof:parent_id":1713307163,"wof:placetype":"locality","wof:population":167,"wof:population_rank":1,"wof:repo":"whosonfirst-data-admin-ee","wof:superseded_by":[],"wof:supersedes":[],"wof:tags":[]},"bbox":[22.49056,58.31028,22.49056,58.31028],"geometry":{"coordinates":[22.49056,58.31028],"type":"Point"}}