{"id":1343642613,"type":"Feature","properties":{"edtf:cessation":"uuuu","edtf:inception":"uuuu","geom:area":0,"geom:area_square_m":0,"geom:bbox":"25.08361,58.66694,25.08361,58.66694","geom:latitude":58.66694,"geom:longitude":25.08361,"gn:admin1_code":"11.0","gn:admin2_code":"638.0","gn:admin3_code":"2619.0","gn:asciiname":"Kalmaru","gn:country_code":"EE","gn:dem":44,"gn:feature_class":"P","gn:feature_code":"PPL","gn:geonameid":591693,"gn:latitude":58.66694,"gn:longitude":25.08361,"gn:modification_date":"2017-11-25","gn:name":"Kalmaru","gn:population":0,"gn:timezone":"Europe/Tallinn","iso:country":"EE","lbl:bbox":"25.06361,58.64694,25.10361,58.68694","lbl:max_zoom":18,"lbl:min_zoom":13.5,"mz:hierarchy_label":1,"mz:is_current":1,"mz:min_zoom":12,"name:est_x_preferred":["Kalmaru"],"name:hye_x_preferred":["Կալմառու"],"name:pol_x_preferred":["Kalmaru"],"name:spa_x_preferred":["Kalmaru"],"name:vol_x_preferred":["Kalmaru"],"src:geom":"geonames","wof:belongsto":[85682981,102191581,1713309305,85633135,1713305733],"wof:breaches":[],"wof:concordances":{"gn:id":591693,"wk:page":"Kalmaru"},"wof:coterminous":[1713309305],"wof:country":"EE","wof:geomhash":"6bd724850b3a378d5fd7d70b3ed48a5c","wof:hierarchy":[{"continent_id":102191581,"country_id":85633135,"county_id":1713305733,"localadmin_id":1713309305,"locality_id":1343642613,"region_id":85682981}],"wof:id":1343642613,"wof:lang_x_official":["est"],"wof:lang_x_spoken":["est"],"wof:lastmodified":1596663419,"wof:name":"Kalmaru","wof:parent_id":1713309305,"wof:placetype":"locality","wof:repo":"whosonfirst-data-admin-ee","wof:superseded_by":[],"wof:supersedes":[],"wof:tags":[]},"bbox":[25.08361,58.66694,25.08361,58.66694],"geometry":{"coordinates":[25.08361,58.66694],"type":"Point"}}