{"id":1276527269,"type":"Feature","properties":{"edtf:cessation":"uuuu","edtf:inception":"uuuu","geom:area":0,"geom:area_square_m":0,"geom:bbox":"24.50778,58.88111,24.50778,58.88111","geom:latitude":58.88111,"geom:longitude":24.50778,"gn:admin1_code":"13.0","gn:admin2_code":"503.0","gn:admin3_code":"4967.0","gn:asciiname":"Jaergkuela","gn:country_code":"EE","gn:dem":38,"gn:feature_class":"P","gn:feature_code":"PPL","gn:geonameid":8618516,"gn:latitude":58.88111,"gn:longitude":24.50778,"gn:modification_date":"2017-11-25","gn:name":"Järgküla","gn:population":0,"gn:timezone":"Europe/Tallinn","iso:country":"EE","lbl:bbox":"24.48778,58.86111,24.52778,58.90111","lbl:max_zoom":18,"lbl:min_zoom":13.5,"mz:hierarchy_label":1,"mz:is_current":1,"mz:min_zoom":12,"src:geom":"geonames","wof:belongsto":[85683013,102191581,1713311149,85633135,1713305747],"wof:breaches":[],"wof:concordances":{"gn:id":8618516},"wof:country":"EE","wof:geomhash":"194960e0ca449923b8dea5ecd93be437","wof:hierarchy":[{"continent_id":102191581,"country_id":85633135,"county_id":1713305747,"localadmin_id":1713311149,"locality_id":1276527269,"region_id":85683013}],"wof:id":1276527269,"wof:lang_x_official":["est"],"wof:lang_x_spoken":["est"],"wof:lastmodified":1596662847,"wof:name":"Jaergkuela","wof:parent_id":1713311149,"wof:placetype":"locality","wof:repo":"whosonfirst-data-admin-ee","wof:superseded_by":[],"wof:supersedes":[],"wof:tags":[]},"bbox":[24.50778,58.88111,24.50778,58.88111],"geometry":{"coordinates":[24.50778,58.88111],"type":"Point"}}