{"id":1193103335,"type":"Feature","properties":{"edtf:cessation":"uuuu","edtf:inception":"uuuu","geom:area":0,"geom:area_square_m":0,"geom:bbox":"27.04611,58.40944,27.04611,58.40944","geom:latitude":58.40944,"geom:longitude":27.04611,"gn:admin1_code":"18.0","gn:admin2_code":"432.0","gn:admin3_code":"9286.0","gn:asciiname":"Torvassoo","gn:country_code":"EE","gn:dem":53,"gn:feature_class":"P","gn:feature_code":"PPL","gn:geonameid":8618076,"gn:latitude":58.40944,"gn:longitude":27.04611,"gn:modification_date":"2017-11-25","gn:name":"Tõrvassoo","gn:population":0,"gn:timezone":"Europe/Tallinn","iso:country":"EE","lbl:bbox":"27.02611,58.38944,27.06611,58.42944","lbl:max_zoom":18,"lbl:min_zoom":13.5,"mz:hierarchy_label":1,"mz:is_current":1,"mz:min_zoom":12,"name:und_x_variant":["Tõrvassoo","Tõrvasoo"],"src:geom":"geonames","wof:belongsto":[85682995,102191581,1713313069,85633135,1713305697],"wof:breaches":[],"wof:concordances":{"gn:id":8618076},"wof:country":"EE","wof:geomhash":"497c1abefcefaf9ee900ccbf459a7f42","wof:hierarchy":[{"continent_id":102191581,"country_id":85633135,"county_id":1713305697,"localadmin_id":1713313069,"locality_id":1193103335,"region_id":85682995}],"wof:id":1193103335,"wof:lang_x_official":["est"],"wof:lang_x_spoken":["est"],"wof:lastmodified":1596660679,"wof:name":"Torvassoo","wof:parent_id":1713313069,"wof:placetype":"locality","wof:repo":"whosonfirst-data-admin-ee","wof:superseded_by":[],"wof:supersedes":[],"wof:tags":[]},"bbox":[27.04611,58.40944,27.04611,58.40944],"geometry":{"coordinates":[27.04611,58.40944],"type":"Point"}}