{"id":1125852487,"type":"Feature","properties":{"edtf:cessation":"uuuu","edtf:inception":"uuuu","geom:area":0,"geom:area_square_m":0,"geom:bbox":"24.58194,58.38861,24.58194,58.38861","geom:latitude":58.38861,"geom:longitude":24.58194,"gn:country":"EE","gn:fcode":"PPL","gn:population":354,"iso:country":"EE","lbl:bbox":"24.56194,58.36861,24.60194,58.40861","lbl:latitude":58.38861,"lbl:longitude":24.58194,"lbl:max_zoom":17,"lbl:min_zoom":12.5,"mz:hierarchy_label":1,"mz:is_current":1,"mz:min_zoom":11,"mz:note":"Quattroshapes Point Gazetteer import 20170519","name:ceb_x_preferred":["Tammiste"],"name:eng_x_preferred":["Tammiste"],"name:est_x_preferred":["Tammiste"],"name:fra_x_preferred":["Tammiste"],"name:hye_x_preferred":["Տամիստե"],"name:nld_x_preferred":["Tammiste"],"name:pol_x_preferred":["Tammiste"],"name:spa_x_preferred":["Tammiste"],"name:vol_x_preferred":["Tammiste"],"qs_pg:aaroncc":"EE","qs_pg:gn_country":"EE","qs_pg:gn_fcode":"PPL","qs_pg:gn_id":588378,"qs_pg:gn_pop":354,"qs_pg:name":"Tammiste","qs_pg:name_adm0":"Eesti","qs_pg:name_adm1":"Pärnumaa","qs_pg:photos_9k":1,"qs_pg:photos_9r":1,"qs_pg:photos_all":1,"qs_pg:photos_sr":0,"qs_pg:pop_sr":2,"qs_pg:qs_id":915976,"qs_pg:qs_pg_placetype":"locality","qs_pg:qs_pg_placetype_gp":"Town","qs_pg:woe_adm0":23424805,"qs_pg:woe_id":845769,"src:geom":"qs_pg","src:lbl_centroid":"qs_pg","src:population":"geonames","woe:adm0_id":23424805,"woe:name_adm0":"Eesti","woe:name_adm1":"Pärnumaa","woe:placetype":"Town","wof:belongsto":[85682981,102191581,1713312407,85633135,1713305731],"wof:breaches":[],"wof:concordances":{"gn:id":588378,"gp:id":845769,"qs_pg:id":915976,"wd:id":"Q2025564"},"wof:coterminous":[1713312407],"wof:country":"EE","wof:created":1497293477,"wof:geomhash":"14684a4fc23c1f1a26c723ea12575da8","wof:hierarchy":[{"continent_id":102191581,"country_id":85633135,"county_id":1713305731,"localadmin_id":1713312407,"locality_id":1125852487,"region_id":85682981}],"wof:id":1125852487,"wof:lang_x_official":["est"],"wof:lang_x_spoken":["est"],"wof:lastmodified":1596663383,"wof:name":"Tammiste","wof:parent_id":1713312407,"wof:placetype":"locality","wof:population":354,"wof:population_rank":2,"wof:repo":"whosonfirst-data-admin-ee","wof:superseded_by":[],"wof:supersedes":[],"wof:tags":[]},"bbox":[24.58194,58.38861,24.58194,58.38861],"geometry":{"coordinates":[24.58194,58.38861],"type":"Point"}}