{"id":1243249081,"type":"Feature","properties":{"edtf:cessation":"uuuu","edtf:inception":"uuuu","geom:area":0,"geom:area_square_m":0,"geom:bbox":"26.04472,59.44361,26.04472,59.44361","geom:latitude":59.44361,"geom:longitude":26.04472,"gn:admin1_code":"8.0","gn:admin2_code":"272.0","gn:admin3_code":"7164.0","gn:asciiname":"Romeda","gn:country_code":"EE","gn:dem":86,"gn:feature_class":"P","gn:feature_code":"PPL","gn:geonameid":588978,"gn:latitude":59.44361,"gn:longitude":26.04472,"gn:modification_date":"2017-11-25","gn:name":"Rõmeda","gn:population":0,"gn:timezone":"Europe/Tallinn","iso:country":"EE","lbl:bbox":"26.02472,59.42361,26.06472,59.46361","lbl:max_zoom":18,"lbl:min_zoom":13.5,"mz:hierarchy_label":1,"mz:is_current":1,"mz:min_zoom":12,"name:est_x_preferred":["Rõmeda"],"name:hye_x_preferred":["Ռիմեդա"],"name:pol_x_preferred":["Rõmeda"],"name:vol_x_preferred":["Rõmeda"],"src:geom":"geonames","wof:belongsto":[85683049,102191581,1713306715,85633135,1713305723],"wof:breaches":[],"wof:concordances":{"gn:id":588978,"wk:page":"R%C3%B5meda"},"wof:coterminous":[1713306715],"wof:country":"EE","wof:geomhash":"0e297d3c143502edd2b393a1bfdb3108","wof:hierarchy":[{"continent_id":102191581,"country_id":85633135,"county_id":1713305723,"localadmin_id":1713306715,"locality_id":1243249081,"region_id":85683049}],"wof:id":1243249081,"wof:lang_x_official":["est"],"wof:lang_x_spoken":["est"],"wof:lastmodified":1596661736,"wof:name":"Romeda","wof:parent_id":1713306715,"wof:placetype":"locality","wof:repo":"whosonfirst-data-admin-ee","wof:superseded_by":[],"wof:supersedes":[],"wof:tags":[]},"bbox":[26.04472,59.44361,26.04472,59.44361],"geometry":{"coordinates":[26.04472,59.44361],"type":"Point"}}