{"id":1125936683,"type":"Feature","properties":{"edtf:cessation":"uuuu","edtf:inception":"uuuu","geom:area":0,"geom:area_square_m":0,"geom:bbox":"26.73,58.27861,26.73,58.27861","geom:latitude":58.27861,"geom:longitude":26.73,"gn:country":"EE","gn:fcode":"PPL","gn:population":327,"iso:country":"EE","lbl:bbox":"26.71,58.25861,26.75,58.29861","lbl:latitude":58.27861,"lbl:longitude":26.73,"lbl:max_zoom":17,"lbl:min_zoom":12.5,"mz:hierarchy_label":1,"mz:is_current":1,"mz:min_zoom":11,"mz:note":"Quattroshapes Point Gazetteer import 20170519","name:bul_x_preferred":["Ухти"],"name:ceb_x_preferred":["Uhti"],"name:eng_x_preferred":["Uhti"],"name:est_x_preferred":["Uhti"],"name:fra_x_preferred":["Uhti"],"name:hye_x_preferred":["Ուհտի"],"name:nld_x_preferred":["Uhti"],"name:pol_x_preferred":["Uhti"],"name:spa_x_preferred":["Uhti"],"name:swe_x_preferred":["Uhti"],"name:ukr_x_preferred":["Угті"],"name:vol_x_preferred":["Uhti"],"qs_pg:aaroncc":"EE","qs_pg:gn_country":"EE","qs_pg:gn_fcode":"PPL","qs_pg:gn_id":794072,"qs_pg:gn_pop":327,"qs_pg:name":"Uhti","qs_pg:name_adm0":"Eesti","qs_pg:name_adm1":"Tartumaa","qs_pg:photos_9r":0,"qs_pg:photos_sr":0,"qs_pg:pop_sr":2,"qs_pg:qs_id":1274656,"qs_pg:qs_pg_placetype":"locality","qs_pg:qs_pg_placetype_gp":"Town","qs_pg:woe_adm0":23424805,"qs_pg:woe_id":846028,"src:geom":"qs_pg","src:lbl_centroid":"qs_pg","src:population":"geonames","woe:adm0_id":23424805,"woe:name_adm0":"Eesti","woe:name_adm1":"Tartumaa","woe:placetype":"Town","wof:belongsto":[85682995,102191581,1713314273,85633135,1713305717],"wof:breaches":[],"wof:concordances":{"gn:id":794072,"gp:id":846028,"qs_pg:id":1274656,"wd:id":"Q3453689"},"wof:coterminous":[1713314273],"wof:country":"EE","wof:created":1497296989,"wof:geomhash":"cc11af8bbeb3b5a3c7ed23ac6f9f8daa","wof:hierarchy":[{"continent_id":102191581,"country_id":85633135,"county_id":1713305717,"localadmin_id":1713314273,"locality_id":1125936683,"region_id":85682995}],"wof:id":1125936683,"wof:lang_x_official":["est"],"wof:lang_x_spoken":["est"],"wof:lastmodified":1596676692,"wof:name":"Uhti","wof:parent_id":1713314273,"wof:placetype":"locality","wof:population":327,"wof:population_rank":2,"wof:repo":"whosonfirst-data-admin-ee","wof:superseded_by":[],"wof:supersedes":[],"wof:tags":[]},"bbox":[26.73,58.27861,26.73,58.27861],"geometry":{"coordinates":[26.73,58.27861],"type":"Point"}}