{"id":1276678317,"type":"Feature","properties":{"edtf:cessation":"uuuu","edtf:inception":"uuuu","geom:area":0,"geom:area_square_m":0,"geom:bbox":"26.045,59.32111,26.045,59.32111","geom:latitude":59.32111,"geom:longitude":26.045,"gn:admin1_code":"8.0","gn:admin2_code":"272.0","gn:admin3_code":"4224.0","gn:asciiname":"Sorgi","gn:country_code":"EE","gn:dem":93,"gn:feature_class":"P","gn:feature_code":"PPL","gn:geonameid":8618838,"gn:latitude":59.32111,"gn:longitude":26.045,"gn:modification_date":"2018-05-02","gn:name":"Sorgi","gn:population":0,"gn:timezone":"Europe/Tallinn","iso:country":"EE","lbl:bbox":"26.025,59.30111,26.065,59.34111","lbl:max_zoom":18,"lbl:min_zoom":13.5,"mz:hierarchy_label":1,"mz:is_current":1,"mz:min_zoom":12,"name:und_x_variant":["Сорги"],"src:geom":"geonames","wof:belongsto":[85683049,102191581,1713312493,85633135,1713305723],"wof:breaches":[],"wof:concordances":{"gn:id":8618838},"wof:country":"EE","wof:geomhash":"ea2eae46cfd9253557d3dbfe8c136e3a","wof:hierarchy":[{"continent_id":102191581,"country_id":85633135,"county_id":1713305723,"localadmin_id":1713312493,"locality_id":1276678317,"region_id":85683049}],"wof:id":1276678317,"wof:lang_x_official":["est"],"wof:lang_x_spoken":["est"],"wof:lastmodified":1596661736,"wof:name":"Sorgi","wof:parent_id":1713312493,"wof:placetype":"locality","wof:repo":"whosonfirst-data-admin-ee","wof:superseded_by":[],"wof:supersedes":[],"wof:tags":[]},"bbox":[26.045,59.32111,26.045,59.32111],"geometry":{"coordinates":[26.045,59.32111],"type":"Point"}}