{"id":1242772279,"type":"Feature","properties":{"edtf:cessation":"uuuu","edtf:inception":"uuuu","geom:area":0,"geom:area_square_m":0,"geom:bbox":"23.65333,58.88056,23.65333,58.88056","geom:latitude":58.88056,"geom:longitude":23.65333,"gn:admin1_code":"7.0","gn:admin2_code":"184.0","gn:admin3_code":"8690.0","gn:asciiname":"Saanika","gn:cc2":"EE","gn:country_code":"EE","gn:dem":15,"gn:feature_class":"P","gn:feature_code":"PPL","gn:geonameid":588901,"gn:latitude":58.88056,"gn:longitude":23.65333,"gn:modification_date":"2017-11-25","gn:name":"Saanika","gn:population":0,"gn:timezone":"Europe/Tallinn","iso:country":"EE","lbl:bbox":"23.63333,58.86056,23.67333,58.90056","lbl:max_zoom":18,"lbl:min_zoom":13.5,"mz:hierarchy_label":1,"mz:is_current":1,"mz:min_zoom":12,"name:deu_x_preferred":["Saanika"],"name:est_x_preferred":["Saanika"],"name:hye_x_preferred":["Սաանիկա"],"name:pol_x_preferred":["Saanika"],"name:ukr_x_preferred":["Сааніка"],"name:und_x_variant":["Sanika"],"name:urd_x_preferred":["سانیکا"],"name:vol_x_preferred":["Saanika"],"src:geom":"geonames","wof:belongsto":[85683001,102191581,1713313813,85633135,1713305755],"wof:breaches":[],"wof:concordances":{"gn:id":588901,"wk:page":"Saanika"},"wof:coterminous":[1713308383],"wof:country":"EE","wof:geomhash":"b86641e2099f94a0200fc8be4b871ef1","wof:hierarchy":[{"continent_id":102191581,"country_id":85633135,"county_id":1713305755,"localadmin_id":1713313813,"locality_id":1242772279,"region_id":85683001}],"wof:id":1242772279,"wof:lang_x_official":["est"],"wof:lang_x_spoken":["est"],"wof:lastmodified":1596662774,"wof:name":"Saanika","wof:parent_id":1713313813,"wof:placetype":"locality","wof:repo":"whosonfirst-data-admin-ee","wof:superseded_by":[],"wof:supersedes":[],"wof:tags":[]},"bbox":[23.65333,58.88056,23.65333,58.88056],"geometry":{"coordinates":[23.65333,58.88056],"type":"Point"}}