{"id":1125935095,"type":"Feature","properties":{"edtf:cessation":"uuuu","edtf:inception":"uuuu","geom:area":0,"geom:area_square_m":0,"geom:bbox":"26.18917,57.90833,26.18917,57.90833","geom:latitude":57.90833,"geom:longitude":26.18917,"gn:country":"EE","gn:fcode":"PPL","gn:population":120,"iso:country":"EE","lbl:bbox":"26.16917,57.88833,26.20917,57.92833","lbl:latitude":57.90833,"lbl:longitude":26.18917,"lbl:max_zoom":18,"lbl:min_zoom":13,"mz:hierarchy_label":1,"mz:is_current":1,"mz:min_zoom":11,"mz:note":"Quattroshapes Point Gazetteer import 20170519","name:ceb_x_preferred":["Õruste"],"name:eng_x_preferred":["Õruste"],"name:est_x_preferred":["Õruste"],"name:fra_x_preferred":["Õruste"],"name:hye_x_preferred":["Իռուստե"],"name:nld_x_preferred":["Õruste"],"name:spa_x_preferred":["Õruste"],"name:swe_x_preferred":["Õruste"],"name:ukr_x_preferred":["Ирусте"],"name:vol_x_preferred":["Õruste"],"qs_pg:aaroncc":"EE","qs_pg:gn_country":"EE","qs_pg:gn_fcode":"PPL","qs_pg:gn_id":794531,"qs_pg:gn_pop":120,"qs_pg:name":"Õruste","qs_pg:name_adm0":"Eesti","qs_pg:name_adm1":"Valgamaa","qs_pg:photos_9r":0,"qs_pg:photos_sr":0,"qs_pg:pop_sr":1,"qs_pg:qs_id":1274252,"qs_pg:qs_pg_placetype":"locality","qs_pg:qs_pg_placetype_gp":"Town","qs_pg:woe_adm0":23424805,"qs_pg:woe_id":844437,"src:geom":"qs_pg","src:lbl_centroid":"qs_pg","src:population":"geonames","woe:adm0_id":23424805,"woe:name_adm0":"Eesti","woe:name_adm1":"Valgamaa","woe:placetype":"Town","wof:belongsto":[85682941,102191581,1713310721,85633135,1713305753],"wof:breaches":[],"wof:concordances":{"gn:id":794531,"gp:id":844437,"qs_pg:id":1274252,"wd:id":"Q3462633"},"wof:coterminous":[1713310721],"wof:country":"EE","wof:created":1497296941,"wof:geomhash":"3cd708c088527bc43fca2223fddca1db","wof:hierarchy":[{"continent_id":102191581,"country_id":85633135,"county_id":1713305753,"localadmin_id":1713310721,"locality_id":1125935095,"region_id":85682941}],"wof:id":1125935095,"wof:lang_x_official":["est"],"wof:lang_x_spoken":["est"],"wof:lastmodified":1596661955,"wof:name":"Õruste","wof:parent_id":1713310721,"wof:placetype":"locality","wof:population":120,"wof:population_rank":1,"wof:repo":"whosonfirst-data-admin-ee","wof:superseded_by":[],"wof:supersedes":[],"wof:tags":[]},"bbox":[26.18917,57.90833,26.18917,57.90833],"geometry":{"coordinates":[26.18917,57.90833],"type":"Point"}}