{"id":102551807,"type":"Feature","properties":{"edtf:cessation":"uuuu","edtf:inception":"uuuu","geom:area":0,"geom:area_square_m":0,"geom:bbox":"24.208333,59.26,24.208333,59.26","geom:latitude":59.26,"geom:longitude":24.208333,"iso:country":"EE","mz:hierarchy_label":1,"mz:is_current":1,"mz:min_zoom":13,"name:ceb_x_preferred":["Vasalemma"],"name:deu_x_preferred":["Flughafen Ämari"],"name:eng_x_preferred":["Ämari Air Base"],"name:eng_x_variant":["EEEI"],"name:est_x_preferred":["Ämari lennuväli"],"name:fas_x_preferred":["پایگاه هوایی آماری"],"name:fin_x_preferred":["Ämarin lentotukikohta"],"name:fra_x_preferred":["Base aérienne d'Ämari"],"name:hun_x_preferred":["Ämari légibázis"],"name:ita_x_preferred":["Aeroporto di Ämari"],"name:jpn_x_preferred":["アマリ空軍基地"],"name:lav_x_preferred":["Emari lidlauks"],"name:lit_x_preferred":["Amari aerodromas"],"name:msa_x_preferred":["Lapangan Terbang Amari"],"name:nld_x_preferred":["Ämari Air Base"],"name:pol_x_preferred":["Port lotniczy Ämari"],"name:rus_x_preferred":["Эмари"],"name:swe_x_preferred":["Ämari flygbas"],"name:tgk_x_preferred":["Пойгоҳи ҳавоӣ омор"],"oa:elevation_ft":"65","oa:type":"medium_airport","src:geom":"wikidata","src:geom_alt":[],"woe:hierarchy":{"country_id":23424805,"county_id":29389909,"planet_id":1,"state_id":2345276},"wof:belongsto":[102191581,1713307899,85633135,1243372973,1713305737,85683055],"wof:breaches":[],"wof:concordances":{"gp:id":12512747,"icao:code":"EEEI","oa:id":"2297","wd:id":"Q938047"},"wof:country":"EE","wof:geomhash":"ec7c66cf8de733147c1c7af4ec3a93ce","wof:hierarchy":[{"campus_id":102551807,"continent_id":102191581,"country_id":85633135,"county_id":1713305737,"localadmin_id":1713307899,"locality_id":1243372973,"neighbourhood_id":-1,"region_id":85683055}],"wof:id":102551807,"wof:lastmodified":1631751499,"wof:name":"Vasalemma Airport","wof:parent_id":1243372973,"wof:placetype":"campus","wof:repo":"whosonfirst-data-admin-ee","wof:superseded_by":[],"wof:supersedes":[],"wof:tags":["airport"]},"bbox":[24.208333,59.26,24.208333,59.26],"geometry":{"coordinates":[24.208333,59.26],"type":"Point"}}