{"id":1125875477,"type":"Feature","properties":{"edtf:cessation":"uuuu","edtf:inception":"uuuu","geom:area":0,"geom:area_square_m":0,"geom:bbox":"27.47611,58.08222,27.47611,58.08222","geom:latitude":58.08222,"geom:longitude":27.47611,"gn:country":"EE","gn:fcode":"PPL","gn:population":269,"iso:country":"EE","lbl:bbox":"27.45611,58.06222,27.49611,58.10222","lbl:latitude":58.08222,"lbl:longitude":27.47611,"lbl:max_zoom":17,"lbl:min_zoom":12.5,"mz:hierarchy_label":1,"mz:is_current":1,"mz:min_zoom":11,"mz:note":"Quattroshapes Point Gazetteer import 20170519","name:bul_x_preferred":["Ристипало"],"name:ceb_x_preferred":["Ristipalo"],"name:eng_x_preferred":["Ristipalo"],"name:est_x_preferred":["Ristipalo"],"name:hye_x_preferred":["Ռիստիպալո"],"name:nld_x_preferred":["Ristipalo"],"name:pol_x_preferred":["Ristipalo"],"name:spa_x_preferred":["Ristipalo"],"name:swe_x_preferred":["Ristipalo"],"name:ukr_x_preferred":["Рістіпало"],"name:vol_x_preferred":["Ristipalo"],"name:vro_x_preferred":["Ristipalo külä"],"qs_pg:aaroncc":"EE","qs_pg:gn_country":"EE","qs_pg:gn_fcode":"PPL","qs_pg:gn_id":794158,"qs_pg:gn_pop":269,"qs_pg:name":"Ristipalo","qs_pg:name_adm0":"Eesti","qs_pg:name_adm1":"Põlvamaa","qs_pg:photos_9r":0,"qs_pg:photos_sr":0,"qs_pg:pop_sr":2,"qs_pg:qs_id":406260,"qs_pg:qs_pg_placetype":"locality","qs_pg:qs_pg_placetype_gp":"Town","qs_pg:woe_adm0":23424805,"qs_pg:woe_id":845183,"src:geom":"qs_pg","src:lbl_centroid":"qs_pg","src:population":"geonames","woe:adm0_id":23424805,"woe:name_adm0":"Eesti","woe:name_adm1":"Põlvamaa","woe:placetype":"Town","wof:belongsto":[85682955,102191581,1713315947,85633135,1713305793],"wof:breaches":[],"wof:concordances":{"gn:id":794158,"gp:id":845183,"qs_pg:id":406260,"wd:id":"Q3466204"},"wof:coterminous":[1713311035],"wof:country":"EE","wof:created":1497294516,"wof:geomhash":"0074a9d0f8968d3cbe0bb22108349a68","wof:hierarchy":[{"continent_id":102191581,"country_id":85633135,"county_id":1713305793,"localadmin_id":1713315947,"locality_id":1125875477,"region_id":85682955}],"wof:id":1125875477,"wof:lang_x_official":["est"],"wof:lang_x_spoken":["est"],"wof:lastmodified":1596677001,"wof:name":"Ristipalo","wof:parent_id":1713315947,"wof:placetype":"locality","wof:population":269,"wof:population_rank":2,"wof:repo":"whosonfirst-data-admin-ee","wof:superseded_by":[],"wof:supersedes":[],"wof:tags":[]},"bbox":[27.47611,58.08222,27.47611,58.08222],"geometry":{"coordinates":[27.47611,58.08222],"type":"Point"}}