{"id":1343273401,"type":"Feature","properties":{"edtf:cessation":"uuuu","edtf:inception":"uuuu","geom:area":0,"geom:area_square_m":0,"geom:bbox":"27.28333,59.23333,27.28333,59.23333","geom:latitude":59.23333,"geom:longitude":27.28333,"gn:admin1_code":"3.0","gn:admin2_code":"130.0","gn:admin3_code":"5217.0","gn:asciiname":"Kopli","gn:country_code":"EE","gn:dem":67,"gn:feature_class":"P","gn:feature_code":"PPL","gn:geonameid":591132,"gn:latitude":59.23333,"gn:longitude":27.28333,"gn:modification_date":"2017-11-25","gn:name":"Kopli","gn:population":0,"gn:timezone":"Europe/Tallinn","iso:country":"EE","lbl:bbox":"27.26333,59.21333,27.30333,59.25333","lbl:max_zoom":18,"lbl:min_zoom":13.5,"mz:hierarchy_label":1,"mz:is_current":1,"mz:min_zoom":12,"name:ces_x_preferred":["Kopli"],"name:est_x_preferred":["Kopli"],"name:fas_x_preferred":["کوپلی"],"name:fin_x_preferred":["Kopli"],"name:fra_x_preferred":["Kopli"],"name:lit_x_preferred":["Kopli"],"name:nld_x_preferred":["Kopli"],"name:pol_x_preferred":["Kopli"],"name:rus_x_preferred":["Копли"],"name:spa_x_preferred":["Kopli"],"name:swe_x_preferred":["Kopli"],"src:geom":"geonames","wof:belongsto":[85683059,102191581,1713311887,85633135,1713305693],"wof:breaches":[],"wof:concordances":{"gn:id":591132},"wof:country":"EE","wof:geomhash":"2375b7f2cc4ab0b3164db325694b2dea","wof:hierarchy":[{"continent_id":102191581,"country_id":85633135,"county_id":1713305693,"localadmin_id":1713311887,"locality_id":1343273401,"region_id":85683059}],"wof:id":1343273401,"wof:lang_x_official":["est"],"wof:lang_x_spoken":["est"],"wof:lastmodified":1596660743,"wof:name":"Kopli","wof:parent_id":1713311887,"wof:placetype":"locality","wof:repo":"whosonfirst-data-admin-ee","wof:superseded_by":[],"wof:supersedes":[],"wof:tags":[]},"bbox":[27.28333,59.23333,27.28333,59.23333],"geometry":{"coordinates":[27.28333,59.23333],"type":"Point"}}