{"id":1225918229,"type":"Feature","properties":{"edtf:cessation":"uuuu","edtf:inception":"uuuu","geom:area":0,"geom:area_square_m":0,"geom:bbox":"27.45944,57.72278,27.45944,57.72278","geom:latitude":57.72278,"geom:longitude":27.45944,"gn:admin1_code":"21.0","gn:admin2_code":"732.0","gn:admin3_code":"5658.0","gn:asciiname":"Olehkova","gn:country_code":"EE","gn:dem":177,"gn:feature_class":"P","gn:feature_code":"PPL","gn:geonameid":8620128,"gn:latitude":57.72278,"gn:longitude":27.45944,"gn:modification_date":"2017-11-25","gn:name":"Olehkova","gn:population":0,"gn:timezone":"Europe/Tallinn","iso:country":"EE","lbl:bbox":"27.43944,57.70278,27.47944,57.74278","lbl:max_zoom":18,"lbl:min_zoom":13.5,"mz:hierarchy_label":1,"mz:is_current":1,"mz:min_zoom":12,"name:und_x_variant":["Olehnova"],"src:geom":"geonames","wof:belongsto":[85682955,102191581,1713316399,85633135,1713305631],"wof:breaches":[],"wof:concordances":{"gn:id":8620128},"wof:coterminous":[1713316399],"wof:country":"EE","wof:geomhash":"981bdb45f3120527f9f6558e7a619219","wof:hierarchy":[{"continent_id":102191581,"country_id":85633135,"county_id":1713305631,"localadmin_id":1713316399,"locality_id":1225918229,"region_id":85682955}],"wof:id":1225918229,"wof:lang_x_official":["est"],"wof:lang_x_spoken":["est"],"wof:lastmodified":1596663695,"wof:name":"Olehkova","wof:parent_id":1713316399,"wof:placetype":"locality","wof:repo":"whosonfirst-data-admin-ee","wof:superseded_by":[],"wof:supersedes":[],"wof:tags":[]},"bbox":[27.45944,57.72278,27.45944,57.72278],"geometry":{"coordinates":[27.45944,57.72278],"type":"Point"}}