{"id":1310698459,"type":"Feature","properties":{"edtf:cessation":"uuuu","edtf:inception":"uuuu","geom:area":0,"geom:area_square_m":0,"geom:bbox":"24.1425,58.8775,24.1425,58.8775","geom:latitude":58.8775,"geom:longitude":24.1425,"gn:admin1_code":"7.0","gn:admin2_code":"441.0","gn:admin3_code":"3590.0","gn:asciiname":"Kullametsa","gn:country_code":"EE","gn:dem":30,"gn:feature_class":"P","gn:feature_code":"PPL","gn:geonameid":795049,"gn:latitude":58.8775,"gn:longitude":24.1425,"gn:modification_date":"2017-11-25","gn:name":"Kullametsa","gn:population":0,"gn:timezone":"Europe/Tallinn","iso:country":"EE","lbl:bbox":"24.1225,58.8575,24.1625,58.8975","lbl:max_zoom":18,"lbl:min_zoom":13.5,"mz:hierarchy_label":1,"mz:is_current":1,"mz:min_zoom":12,"name:deu_x_preferred":["Kullametsa"],"name:est_x_preferred":["Kullametsa"],"name:hye_x_preferred":["Կուլլամեցա"],"name:nld_x_preferred":["Kullametsa"],"name:pol_x_preferred":["Kullametsa"],"name:spa_x_preferred":["Kullametsa"],"name:ukr_x_preferred":["Кулламетса"],"name:vol_x_preferred":["Kullametsa"],"src:geom":"geonames","wof:belongsto":[85683001,102191581,1713313205,85633135,1713305701],"wof:breaches":[],"wof:concordances":{"gn:id":795049,"wk:page":"Kullametsa"},"wof:coterminous":[1713313205],"wof:country":"EE","wof:geomhash":"e68cbe46b4558452c8d0e268d071ccc6","wof:hierarchy":[{"continent_id":102191581,"country_id":85633135,"county_id":1713305701,"localadmin_id":1713313205,"locality_id":1310698459,"region_id":85683001}],"wof:id":1310698459,"wof:lang_x_official":["est"],"wof:lang_x_spoken":["est"],"wof:lastmodified":1596677434,"wof:name":"Kullametsa","wof:parent_id":1713313205,"wof:placetype":"locality","wof:repo":"whosonfirst-data-admin-ee","wof:superseded_by":[],"wof:supersedes":[],"wof:tags":[]},"bbox":[24.1425,58.8775,24.1425,58.8775],"geometry":{"coordinates":[24.1425,58.8775],"type":"Point"}}