{"id":1259960901,"type":"Feature","properties":{"edtf:cessation":"uuuu","edtf:inception":"uuuu","geom:area":0,"geom:area_square_m":0,"geom:bbox":"24.80139,58.01333,24.80139,58.01333","geom:latitude":58.01333,"geom:longitude":24.80139,"gn:admin1_code":"11.0","gn:admin2_code":"712.0","gn:admin3_code":"4104.0","gn:asciiname":"Lanksaare","gn:cc2":"EE","gn:country_code":"EE","gn:dem":55,"gn:feature_class":"P","gn:feature_code":"PPL","gn:geonameid":590794,"gn:latitude":58.01333,"gn:longitude":24.80139,"gn:modification_date":"2017-11-25","gn:name":"Lanksaare","gn:population":0,"gn:timezone":"Europe/Tallinn","iso:country":"EE","lbl:bbox":"24.78139,57.99333,24.82139,58.03333","lbl:max_zoom":18,"lbl:min_zoom":13.5,"mz:hierarchy_label":1,"mz:is_current":1,"mz:min_zoom":12,"name:est_x_preferred":["Lanksaare"],"name:fra_x_preferred":["Lanksaare"],"name:hye_x_preferred":["Լանկսաառե"],"name:pol_x_preferred":["Lanksaare"],"name:spa_x_preferred":["Lanksaare"],"name:und_x_variant":["Lanksare"],"name:urd_x_preferred":["لانکساری"],"name:vol_x_preferred":["Lanksaare"],"src:geom":"geonames","wof:belongsto":[85682981,102191581,1713309529,85633135,1713305705],"wof:breaches":[],"wof:concordances":{"gn:id":590794,"wk:page":"Lanksaare"},"wof:coterminous":[1713309529],"wof:country":"EE","wof:geomhash":"c742b3dc8143cd95d4b2a096b350a4da","wof:hierarchy":[{"continent_id":102191581,"country_id":85633135,"county_id":1713305705,"localadmin_id":1713309529,"locality_id":1259960901,"region_id":85682981}],"wof:id":1259960901,"wof:lang_x_official":["est"],"wof:lang_x_spoken":["est"],"wof:lastmodified":1596677738,"wof:name":"Lanksaare","wof:parent_id":1713309529,"wof:placetype":"locality","wof:repo":"whosonfirst-data-admin-ee","wof:superseded_by":[],"wof:supersedes":[],"wof:tags":[]},"bbox":[24.80139,58.01333,24.80139,58.01333],"geometry":{"coordinates":[24.80139,58.01333],"type":"Point"}}