{"id":1242885581,"type":"Feature","properties":{"edtf:cessation":"uuuu","edtf:inception":"uuuu","geom:area":0,"geom:area_square_m":0,"geom:bbox":"26.84333,59.00639,26.84333,59.00639","geom:latitude":59.00639,"geom:longitude":26.84333,"gn:admin1_code":"5.0","gn:admin2_code":"486.0","gn:admin3_code":"5774.0","gn:asciiname":"Laurissaare","gn:country_code":"EE","gn:dem":60,"gn:feature_class":"P","gn:feature_code":"PPL","gn:geonameid":8618848,"gn:latitude":59.00639,"gn:longitude":26.84333,"gn:modification_date":"2017-11-25","gn:name":"Laurissaare","gn:population":0,"gn:timezone":"Europe/Tallinn","iso:country":"EE","lbl:bbox":"26.82333,58.98639,26.86333,59.02639","lbl:max_zoom":18,"lbl:min_zoom":13.5,"mz:hierarchy_label":1,"mz:is_current":1,"mz:min_zoom":12,"name:und_x_variant":["Laurisaare"],"src:geom":"geonames","wof:belongsto":[85683059,102191581,1713313621,85633135,1713305677],"wof:breaches":[],"wof:concordances":{"gn:id":8618848},"wof:country":"EE","wof:geomhash":"e8e898cf219a7c87897600d3751c0e6e","wof:hierarchy":[{"continent_id":102191581,"country_id":85633135,"county_id":1713305677,"localadmin_id":1713313621,"locality_id":1242885581,"region_id":85683059}],"wof:id":1242885581,"wof:lang_x_official":["est"],"wof:lang_x_spoken":["est"],"wof:lastmodified":1596661023,"wof:name":"Laurissaare","wof:parent_id":1713313621,"wof:placetype":"locality","wof:repo":"whosonfirst-data-admin-ee","wof:superseded_by":[],"wof:supersedes":[],"wof:tags":[]},"bbox":[26.84333,59.00639,26.84333,59.00639],"geometry":{"coordinates":[26.84333,59.00639],"type":"Point"}}