{"id":1259545361,"type":"Feature","properties":{"edtf:cessation":"uuuu","edtf:inception":"uuuu","geom:area":0,"geom:area_square_m":0,"geom:bbox":"25.19,58.33417,25.19,58.33417","geom:latitude":58.33417,"geom:longitude":25.19,"gn:admin1_code":"20.0","gn:admin2_code":"615.0","gn:admin3_code":"2013.0","gn:asciiname":"Iia","gn:cc2":"EE","gn:country_code":"EE","gn:dem":40,"gn:feature_class":"P","gn:feature_code":"PPL","gn:geonameid":795589,"gn:latitude":58.33417,"gn:longitude":25.19,"gn:modification_date":"2017-11-25","gn:name":"Iia","gn:population":0,"gn:timezone":"Europe/Tallinn","iso:country":"EE","lbl:bbox":"25.17,58.31417,25.21,58.35417","lbl:max_zoom":18,"lbl:min_zoom":13.5,"mz:hierarchy_label":1,"mz:is_current":1,"mz:min_zoom":12,"name:est_x_preferred":["Iia"],"name:hye_x_preferred":["Իիա"],"name:pol_x_preferred":["Iia"],"name:spa_x_preferred":["Iia"],"name:ukr_x_preferred":["Ійа"],"name:und_x_variant":["Ila"],"name:vol_x_preferred":["Iia"],"src:geom":"geonames","wof:belongsto":[85682985,102191581,1713312501,85633135,1713305735],"wof:breaches":[],"wof:concordances":{"gn:id":795589,"wk:page":"Iia%2C_Estonia"},"wof:coterminous":[1713312501],"wof:country":"EE","wof:geomhash":"38fea31f1775bb848008408345436b84","wof:hierarchy":[{"continent_id":102191581,"country_id":85633135,"county_id":1713305735,"localadmin_id":1713312501,"locality_id":1259545361,"region_id":85682985}],"wof:id":1259545361,"wof:lang_x_official":["est"],"wof:lang_x_spoken":["est"],"wof:lastmodified":1596663452,"wof:name":"Iia","wof:parent_id":1713312501,"wof:placetype":"locality","wof:repo":"whosonfirst-data-admin-ee","wof:superseded_by":[],"wof:supersedes":[],"wof:tags":[]},"bbox":[25.19,58.33417,25.19,58.33417],"geometry":{"coordinates":[25.19,58.33417],"type":"Point"}}