{"id":1225951657,"type":"Feature","properties":{"edtf:cessation":"uuuu","edtf:inception":"uuuu","geom:area":0,"geom:area_square_m":0,"geom:bbox":"27.36722,59.43889,27.36722,59.43889","geom:latitude":59.43889,"geom:longitude":27.36722,"gn:admin1_code":"3.0","gn:admin2_code":"803.0","gn:admin3_code":"8914.0","gn:asciiname":"Valaste","gn:cc2":"EE","gn:country_code":"EE","gn:dem":55,"gn:feature_class":"P","gn:feature_code":"PPL","gn:geonameid":587880,"gn:latitude":59.43889,"gn:longitude":27.36722,"gn:modification_date":"2017-11-25","gn:name":"Valaste","gn:population":0,"gn:timezone":"Europe/Tallinn","iso:country":"EE","lbl:bbox":"27.34722,59.41889,27.38722,59.45889","lbl:max_zoom":18,"lbl:min_zoom":13.5,"mz:hierarchy_label":1,"mz:is_current":1,"mz:min_zoom":12,"name:deu_x_preferred":["Valaste"],"name:est_x_preferred":["Valaste"],"name:hye_x_preferred":["Վալաստե"],"name:nld_x_preferred":["Valaste"],"name:pol_x_preferred":["Valaste"],"name:spa_x_preferred":["Valaste"],"name:und_x_variant":["Vallaste"],"name:vol_x_preferred":["Valaste"],"src:geom":"geonames","wof:belongsto":[85683059,102191581,1713306759,85633135,1713305783],"wof:breaches":[],"wof:concordances":{"gn:id":587880,"wk:page":"Valaste"},"wof:coterminous":[1713306759],"wof:country":"EE","wof:geomhash":"c2f563530f38148d387595ff0f634fe5","wof:hierarchy":[{"continent_id":102191581,"country_id":85633135,"county_id":1713305783,"localadmin_id":1713306759,"locality_id":1225951657,"region_id":85683059}],"wof:id":1225951657,"wof:lang_x_official":["est"],"wof:lang_x_spoken":["est"],"wof:lastmodified":1596676910,"wof:name":"Valaste","wof:parent_id":1713306759,"wof:placetype":"locality","wof:repo":"whosonfirst-data-admin-ee","wof:superseded_by":[],"wof:supersedes":[],"wof:tags":[]},"bbox":[27.36722,59.43889,27.36722,59.43889],"geometry":{"coordinates":[27.36722,59.43889],"type":"Point"}}