{"id":1209235831,"type":"Feature","properties":{"edtf:cessation":"uuuu","edtf:inception":"uuuu","geom:area":0,"geom:area_square_m":0,"geom:bbox":"24.05694,59.02333,24.05694,59.02333","geom:latitude":59.02333,"geom:longitude":24.05694,"gn:admin1_code":"7.0","gn:admin2_code":"441.0","gn:admin3_code":"6191.0","gn:asciiname":"Rouma","gn:country_code":"EE","gn:dem":43,"gn:feature_class":"P","gn:feature_code":"PPL","gn:geonameid":588942,"gn:latitude":59.02333,"gn:longitude":24.05694,"gn:modification_date":"2017-11-25","gn:name":"Rõuma","gn:population":0,"gn:timezone":"Europe/Tallinn","iso:country":"EE","lbl:bbox":"24.03694,59.00333,24.07694,59.04333","lbl:max_zoom":18,"lbl:min_zoom":13.5,"mz:hierarchy_label":1,"mz:is_current":1,"mz:min_zoom":12,"name:und_x_variant":["Ryuma","Rõuma"],"src:geom":"geonames","wof:belongsto":[85683001,102191581,1713315389,85633135,1713305701],"wof:breaches":[],"wof:concordances":{"gn:id":588942},"wof:coterminous":[1713312769],"wof:country":"EE","wof:geomhash":"68e9bbbe16f6e524d430c419039149dd","wof:hierarchy":[{"continent_id":102191581,"country_id":85633135,"county_id":1713305701,"localadmin_id":1713315389,"locality_id":1209235831,"region_id":85683001}],"wof:id":1209235831,"wof:lang_x_official":["est"],"wof:lang_x_spoken":["est"],"wof:lastmodified":1596677427,"wof:name":"Rouma","wof:parent_id":1713315389,"wof:placetype":"locality","wof:repo":"whosonfirst-data-admin-ee","wof:superseded_by":[],"wof:supersedes":[],"wof:tags":[]},"bbox":[24.05694,59.02333,24.05694,59.02333],"geometry":{"coordinates":[24.05694,59.02333],"type":"Point"}}