{"id":1327312747,"type":"Feature","properties":{"edtf:cessation":"uuuu","edtf:inception":"uuuu","geom:area":0,"geom:area_square_m":0,"geom:bbox":"22.97667,58.41556,22.97667,58.41556","geom:latitude":58.41556,"geom:longitude":22.97667,"gn:admin1_code":"14.0","gn:admin2_code":"714.0","gn:admin3_code":"2517.0","gn:asciiname":"Uyvere","gn:country_code":"EE","gn:dem":11,"gn:feature_class":"P","gn:feature_code":"PPL","gn:geonameid":587983,"gn:latitude":58.41556,"gn:longitude":22.97667,"gn:modification_date":"2017-11-25","gn:name":"Uyvere","gn:population":0,"gn:timezone":"Europe/Tallinn","iso:country":"EE","lbl:bbox":"22.95667,58.39556,22.99667,58.43556","lbl:max_zoom":18,"lbl:min_zoom":13.5,"mz:hierarchy_label":1,"mz:is_current":1,"mz:min_zoom":12,"name:deu_x_preferred":["Üüvere"],"name:est_x_preferred":["Üüvere"],"name:hye_x_preferred":["Յույուվեռե"],"name:pol_x_preferred":["Üüvere"],"name:spa_x_preferred":["Üüvere"],"name:und_x_variant":["Öövere","Uyvere"],"name:vol_x_preferred":["Üüvere"],"src:geom":"geonames","wof:belongsto":[85682947,102191581,1713307411,85633135,1713305627],"wof:breaches":[],"wof:concordances":{"gn:id":587983,"wk:page":"%C3%9C%C3%BCvere"},"wof:coterminous":[1713308077],"wof:country":"EE","wof:geomhash":"19cb88a4e5cfdaa7bc7e38a9616bf79e","wof:hierarchy":[{"continent_id":102191581,"country_id":85633135,"county_id":1713305627,"localadmin_id":1713307411,"locality_id":1327312747,"region_id":85682947}],"wof:id":1327312747,"wof:lang_x_official":["est"],"wof:lang_x_spoken":["est"],"wof:lastmodified":1596674955,"wof:name":"Uyvere","wof:parent_id":1713307411,"wof:placetype":"locality","wof:repo":"whosonfirst-data-admin-ee","wof:superseded_by":[],"wof:supersedes":[],"wof:tags":[]},"bbox":[22.97667,58.41556,22.97667,58.41556],"geometry":{"coordinates":[22.97667,58.41556],"type":"Point"}}