{"id":1343565957,"type":"Feature","properties":{"edtf:cessation":"uuuu","edtf:inception":"uuuu","geom:area":0,"geom:area_square_m":0,"geom:bbox":"26.71667,58.71667,26.71667,58.71667","geom:latitude":58.71667,"geom:longitude":26.71667,"gn:admin1_code":"5.0","gn:admin2_code":"486.0","gn:admin3_code":"2611.0","gn:asciiname":"Rohkuse","gn:country_code":"EE","gn:dem":97,"gn:feature_class":"P","gn:feature_code":"PPL","gn:geonameid":588991,"gn:latitude":58.71667,"gn:longitude":26.71667,"gn:modification_date":"2017-11-25","gn:name":"Rohkuse","gn:population":0,"gn:timezone":"Europe/Tallinn","iso:country":"EE","lbl:bbox":"26.69667,58.69667,26.73667,58.73667","lbl:max_zoom":18,"lbl:min_zoom":13.5,"mz:hierarchy_label":1,"mz:is_current":1,"mz:min_zoom":12,"name:und_x_variant":["Rokhkuze","Rohkuse"],"src:geom":"geonames","wof:belongsto":[85683059,102191581,1713312049,85633135,1713305677],"wof:breaches":[],"wof:concordances":{"gn:id":588991},"wof:country":"EE","wof:geomhash":"922208bfd48079034e90137da1e30a91","wof:hierarchy":[{"continent_id":102191581,"country_id":85633135,"county_id":1713305677,"localadmin_id":1713312049,"locality_id":1343565957,"region_id":85683059}],"wof:id":1343565957,"wof:lang_x_official":["est"],"wof:lang_x_spoken":["est"],"wof:lastmodified":1596661016,"wof:name":"Rohkuse","wof:parent_id":1713312049,"wof:placetype":"locality","wof:repo":"whosonfirst-data-admin-ee","wof:superseded_by":[],"wof:supersedes":[],"wof:tags":[]},"bbox":[26.71667,58.71667,26.71667,58.71667],"geometry":{"coordinates":[26.71667,58.71667],"type":"Point"}}