{"id":1226119749,"type":"Feature","properties":{"edtf:cessation":"uuuu","edtf:inception":"uuuu","geom:area":0,"geom:area_square_m":0,"geom:bbox":"26.71028,58.03917,26.71028,58.03917","geom:latitude":58.03917,"geom:longitude":26.71028,"gn:admin1_code":"12.0","gn:admin2_code":"284.0","gn:admin3_code":"7645.0","gn:asciiname":"Sirvaste","gn:country_code":"EE","gn:dem":147,"gn:feature_class":"P","gn:feature_code":"PPL","gn:geonameid":588657,"gn:latitude":58.03917,"gn:longitude":26.71028,"gn:modification_date":"2017-11-25","gn:name":"Sirvaste","gn:population":0,"gn:timezone":"Europe/Tallinn","iso:country":"EE","lbl:bbox":"26.69028,58.01917,26.73028,58.05917","lbl:max_zoom":18,"lbl:min_zoom":13.5,"mz:hierarchy_label":1,"mz:is_current":1,"mz:min_zoom":12,"name:est_x_preferred":["Sirvaste"],"name:hye_x_preferred":["Սիռվաստե"],"name:pol_x_preferred":["Sirvaste"],"name:spa_x_preferred":["Sirvaste"],"name:ukr_x_preferred":["Сірвасте"],"name:vol_x_preferred":["Sirvaste"],"src:geom":"geonames","wof:belongsto":[85682955,102191581,1713309781,85633135,1713305789],"wof:breaches":[],"wof:concordances":{"gn:id":588657,"wk:page":"Sirvaste"},"wof:coterminous":[1713309781],"wof:country":"EE","wof:geomhash":"f783dd7bdabdfa0c717894f9305a60c9","wof:hierarchy":[{"continent_id":102191581,"country_id":85633135,"county_id":1713305789,"localadmin_id":1713309781,"locality_id":1226119749,"region_id":85682955}],"wof:id":1226119749,"wof:lang_x_official":["est"],"wof:lang_x_spoken":["est"],"wof:lastmodified":1596676786,"wof:name":"Sirvaste","wof:parent_id":1713309781,"wof:placetype":"locality","wof:repo":"whosonfirst-data-admin-ee","wof:superseded_by":[],"wof:supersedes":[],"wof:tags":[]},"bbox":[26.71028,58.03917,26.71028,58.03917],"geometry":{"coordinates":[26.71028,58.03917],"type":"Point"}}