{"id":1309685893,"type":"Feature","properties":{"edtf:cessation":"uuuu","edtf:inception":"uuuu","geom:area":0,"geom:area_square_m":0,"geom:bbox":"22.74194,58.22778,22.74194,58.22778","geom:latitude":58.22778,"geom:longitude":22.74194,"gn:admin1_code":"14.0","gn:admin2_code":"714.0","gn:admin3_code":"7834.0","gn:asciiname":"Vaetta","gn:country_code":"EE","gn:dem":4,"gn:feature_class":"P","gn:feature_code":"PPL","gn:geonameid":794686,"gn:latitude":58.22778,"gn:longitude":22.74194,"gn:modification_date":"2017-11-25","gn:name":"Vätta","gn:population":0,"gn:timezone":"Europe/Tallinn","iso:country":"EE","lbl:bbox":"22.72194,58.20778,22.76194,58.24778","lbl:max_zoom":18,"lbl:min_zoom":13.5,"mz:hierarchy_label":1,"mz:is_current":1,"mz:min_zoom":12,"src:geom":"geonames","wof:belongsto":[85682947,102191581,1713306757,85633135,1713305627],"wof:breaches":[],"wof:concordances":{"gn:id":794686},"wof:country":"EE","wof:geomhash":"3ffd3d897823d8d67091d4e315f4382a","wof:hierarchy":[{"continent_id":102191581,"country_id":85633135,"county_id":1713305627,"localadmin_id":1713306757,"locality_id":1309685893,"region_id":85682947}],"wof:id":1309685893,"wof:lang_x_official":["est"],"wof:lang_x_spoken":["est"],"wof:lastmodified":1596674919,"wof:name":"Vaetta","wof:parent_id":1713306757,"wof:placetype":"locality","wof:repo":"whosonfirst-data-admin-ee","wof:superseded_by":[],"wof:supersedes":[],"wof:tags":[]},"bbox":[22.74194,58.22778,22.74194,58.22778],"geometry":{"coordinates":[22.74194,58.22778],"type":"Point"}}