{"id":1344127801,"type":"Feature","properties":{"edtf:cessation":"uuuu","edtf:inception":"uuuu","geom:area":0,"geom:area_square_m":0,"geom:bbox":"22.06667,58.18333,22.06667,58.18333","geom:latitude":58.18333,"geom:longitude":22.06667,"gn:admin1_code":"14.0","gn:admin2_code":"714.0","gn:admin3_code":"4057.0","gn:asciiname":"Metsalouka","gn:country_code":"EE","gn:dem":3,"gn:feature_class":"P","gn:feature_code":"PPL","gn:geonameid":796111,"gn:latitude":58.18333,"gn:longitude":22.06667,"gn:modification_date":"2017-11-25","gn:name":"Metsalõuka","gn:population":0,"gn:timezone":"Europe/Tallinn","iso:country":"EE","lbl:bbox":"22.04667,58.16333,22.08667,58.20333","lbl:max_zoom":18,"lbl:min_zoom":13.5,"mz:hierarchy_label":1,"mz:is_current":1,"mz:min_zoom":12,"name:und_x_variant":["Metsalõuka"],"src:geom":"geonames","wof:belongsto":[85682947,102191581,1713307333,85633135,1713305627],"wof:breaches":[],"wof:concordances":{"gn:id":796111},"wof:country":"EE","wof:geomhash":"b7a6664e4a4a622f8c2399cfa7513a63","wof:hierarchy":[{"continent_id":102191581,"country_id":85633135,"county_id":1713305627,"localadmin_id":1713307333,"locality_id":1344127801,"region_id":85682947}],"wof:id":1344127801,"wof:lang_x_official":["est"],"wof:lang_x_spoken":["est"],"wof:lastmodified":1596674960,"wof:name":"Metsalouka","wof:parent_id":1713307333,"wof:placetype":"locality","wof:repo":"whosonfirst-data-admin-ee","wof:superseded_by":[],"wof:supersedes":[],"wof:tags":[]},"bbox":[22.06667,58.18333,22.06667,58.18333],"geometry":{"coordinates":[22.06667,58.18333],"type":"Point"}}