{"id":1310128721,"type":"Feature","properties":{"edtf:cessation":"uuuu","edtf:inception":"uuuu","geom:area":0,"geom:area_square_m":0,"geom:bbox":"26.82528,58.80167,26.82528,58.80167","geom:latitude":58.80167,"geom:longitude":26.82528,"gn:admin1_code":"5.0","gn:admin2_code":"486.0","gn:admin3_code":"8149.0","gn:asciiname":"Jaskamurru","gn:country_code":"EE","gn:dem":49,"gn:feature_class":"P","gn:feature_code":"PPL","gn:geonameid":8618377,"gn:latitude":58.80167,"gn:longitude":26.82528,"gn:modification_date":"2017-11-25","gn:name":"Jaskamurru","gn:population":0,"gn:timezone":"Europe/Tallinn","iso:country":"EE","lbl:bbox":"26.80528,58.78167,26.84528,58.82167","lbl:max_zoom":18,"lbl:min_zoom":13.5,"mz:hierarchy_label":1,"mz:is_current":1,"mz:min_zoom":12,"name:und_x_variant":["Jaska-Murru"],"src:geom":"geonames","wof:belongsto":[85683059,102191581,1713312691,85633135,1713305677],"wof:breaches":[],"wof:concordances":{"gn:id":8618377},"wof:country":"EE","wof:geomhash":"ee7c420550b9a7965c006828c05d58e4","wof:hierarchy":[{"continent_id":102191581,"country_id":85633135,"county_id":1713305677,"localadmin_id":1713312691,"locality_id":1310128721,"region_id":85683059}],"wof:id":1310128721,"wof:lang_x_official":["est"],"wof:lang_x_spoken":["est"],"wof:lastmodified":1596661017,"wof:name":"Jaskamurru","wof:parent_id":1713312691,"wof:placetype":"locality","wof:repo":"whosonfirst-data-admin-ee","wof:superseded_by":[],"wof:supersedes":[],"wof:tags":[]},"bbox":[26.82528,58.80167,26.82528,58.80167],"geometry":{"coordinates":[26.82528,58.80167],"type":"Point"}}