{"id":1276672069,"type":"Feature","properties":{"edtf:cessation":"uuuu","edtf:inception":"uuuu","geom:area":0,"geom:area_square_m":0,"geom:bbox":"25.47,59.39611,25.47,59.39611","geom:latitude":59.39611,"geom:longitude":25.47,"gn:admin1_code":"1.0","gn:admin2_code":"141.0","gn:admin3_code":"1961.0","gn:asciiname":"Haermakosu","gn:country_code":"EE","gn:dem":71,"gn:feature_class":"P","gn:feature_code":"PPL","gn:geonameid":592162,"gn:latitude":59.39611,"gn:longitude":25.47,"gn:modification_date":"2017-11-25","gn:name":"Härmakosu","gn:population":0,"gn:timezone":"Europe/Tallinn","iso:country":"EE","lbl:bbox":"25.45,59.37611,25.49,59.41611","lbl:max_zoom":18,"lbl:min_zoom":13.5,"mz:hierarchy_label":1,"mz:is_current":1,"mz:min_zoom":12,"name:est_x_preferred":["Härmakosu"],"name:fra_x_preferred":["Härmakosu"],"name:hye_x_preferred":["Հեռմակոսու"],"name:nld_x_preferred":["Härmakosu"],"name:pol_x_preferred":["Härmakosu"],"name:sco_x_preferred":["Härmakosu"],"name:slk_x_preferred":["Härmakosu"],"name:spa_x_preferred":["Härmakosu"],"name:und_x_variant":["Yermakozu","Khyarmakosu"],"name:vol_x_preferred":["Härmakosu"],"src:geom":"geonames","wof:belongsto":[85683055,102191581,1713307197,85633135,1713305749],"wof:breaches":[],"wof:concordances":{"gn:id":592162,"wk:page":"H%C3%A4rmakosu"},"wof:coterminous":[1713307197],"wof:country":"EE","wof:geomhash":"2c9f160cdc03761146f97e3da6b4397f","wof:hierarchy":[{"continent_id":102191581,"country_id":85633135,"county_id":1713305749,"localadmin_id":1713307197,"locality_id":1276672069,"region_id":85683055}],"wof:id":1276672069,"wof:lang_x_official":["est"],"wof:lang_x_spoken":["est"],"wof:lastmodified":1596662802,"wof:name":"Haermakosu","wof:parent_id":1713307197,"wof:placetype":"locality","wof:repo":"whosonfirst-data-admin-ee","wof:superseded_by":[],"wof:supersedes":[],"wof:tags":[]},"bbox":[25.47,59.39611,25.47,59.39611],"geometry":{"coordinates":[25.47,59.39611],"type":"Point"}}