{"id":1243369461,"type":"Feature","properties":{"edtf:cessation":"uuuu","edtf:inception":"uuuu","geom:area":0,"geom:area_square_m":0,"geom:bbox":"25.78083,59.04889,25.78083,59.04889","geom:latitude":59.04889,"geom:longitude":25.78083,"gn:admin1_code":"4.0","gn:admin2_code":"567.0","gn:admin3_code":"8917.0","gn:asciiname":"Valasti","gn:country_code":"EE","gn:dem":92,"gn:feature_class":"P","gn:feature_code":"PPL","gn:geonameid":587879,"gn:latitude":59.04889,"gn:longitude":25.78083,"gn:modification_date":"2017-11-25","gn:name":"Valasti","gn:population":0,"gn:timezone":"Europe/Tallinn","iso:country":"EE","lbl:bbox":"25.76083,59.02889,25.80083,59.06889","lbl:max_zoom":18,"lbl:min_zoom":13.5,"mz:hierarchy_label":1,"mz:is_current":1,"mz:min_zoom":12,"name:est_x_preferred":["Valasti"],"name:hye_x_preferred":["Վալաստի"],"name:pol_x_preferred":["Valasti"],"name:ukr_x_preferred":["Валасті"],"name:vol_x_preferred":["Valasti"],"src:geom":"geonames","wof:belongsto":[85683031,102191581,1713308189,85633135,1713305663],"wof:breaches":[],"wof:concordances":{"gn:id":587879,"wk:page":"Valasti"},"wof:coterminous":[1713308189],"wof:country":"EE","wof:geomhash":"a7910d0362f093987d87ece759415f83","wof:hierarchy":[{"continent_id":102191581,"country_id":85633135,"county_id":1713305663,"localadmin_id":1713308189,"locality_id":1243369461,"region_id":85683031}],"wof:id":1243369461,"wof:lang_x_official":["est"],"wof:lang_x_spoken":["est"],"wof:lastmodified":1596661331,"wof:name":"Valasti","wof:parent_id":1713308189,"wof:placetype":"locality","wof:repo":"whosonfirst-data-admin-ee","wof:superseded_by":[],"wof:supersedes":[],"wof:tags":[]},"bbox":[25.78083,59.04889,25.78083,59.04889],"geometry":{"coordinates":[25.78083,59.04889],"type":"Point"}}