{"id":1344140417,"type":"Feature","properties":{"edtf:cessation":"uuuu","edtf:inception":"uuuu","geom:area":0,"geom:area_square_m":0,"geom:bbox":"22.78972,58.48694,22.78972,58.48694","geom:latitude":58.48694,"geom:longitude":22.78972,"gn:admin1_code":"14.0","gn:admin2_code":"714.0","gn:admin3_code":"4917.0","gn:asciiname":"Metsaere","gn:country_code":"EE","gn:dem":21,"gn:feature_class":"P","gn:feature_code":"PPL","gn:geonameid":590263,"gn:latitude":58.48694,"gn:longitude":22.78972,"gn:modification_date":"2017-11-25","gn:name":"Metsaere","gn:population":0,"gn:timezone":"Europe/Tallinn","iso:country":"EE","lbl:bbox":"22.76972,58.46694,22.80972,58.50694","lbl:max_zoom":18,"lbl:min_zoom":13.5,"mz:hierarchy_label":1,"mz:is_current":1,"mz:min_zoom":12,"name:und_x_variant":["Metsaare","Metsaere","Metsalõuka","Metsaääre"],"src:geom":"geonames","wof:belongsto":[85682947,102191581,1713306635,85633135,1713305627],"wof:breaches":[],"wof:concordances":{"gn:id":590263},"wof:coterminous":[1713306635],"wof:country":"EE","wof:geomhash":"ee89f34374487819eab3506f35ce9cc1","wof:hierarchy":[{"continent_id":102191581,"country_id":85633135,"county_id":1713305627,"localadmin_id":1713306635,"locality_id":1344140417,"region_id":85682947}],"wof:id":1344140417,"wof:lang_x_official":["est"],"wof:lang_x_spoken":["est"],"wof:lastmodified":1596674953,"wof:name":"Metsaere","wof:parent_id":1713306635,"wof:placetype":"locality","wof:repo":"whosonfirst-data-admin-ee","wof:superseded_by":[],"wof:supersedes":[],"wof:tags":[]},"bbox":[22.78972,58.48694,22.78972,58.48694],"geometry":{"coordinates":[22.78972,58.48694],"type":"Point"}}