{"id":1276767515,"type":"Feature","properties":{"edtf:cessation":"uuuu","edtf:inception":"uuuu","geom:area":0,"geom:area_square_m":0,"geom:bbox":"26.98444,58.65361,26.98444,58.65361","geom:latitude":58.65361,"geom:longitude":26.98444,"gn:admin1_code":"18.0","gn:admin2_code":"586.0","gn:admin3_code":"9150.0","gn:asciiname":"Ojakuela","gn:country_code":"EE","gn:dem":66,"gn:feature_class":"P","gn:feature_code":"PPL","gn:geonameid":8618314,"gn:latitude":58.65361,"gn:longitude":26.98444,"gn:modification_date":"2017-11-25","gn:name":"Ojaküla","gn:population":0,"gn:timezone":"Europe/Tallinn","iso:country":"EE","lbl:bbox":"26.96444,58.63361,27.00444,58.67361","lbl:max_zoom":18,"lbl:min_zoom":13.5,"mz:hierarchy_label":1,"mz:is_current":1,"mz:min_zoom":12,"src:geom":"geonames","wof:belongsto":[85682995,102191581,1713309707,85633135,1713305679],"wof:breaches":[],"wof:concordances":{"gn:id":8618314},"wof:country":"EE","wof:geomhash":"ea5b26f1329780924f346c363df4e578","wof:hierarchy":[{"continent_id":102191581,"country_id":85633135,"county_id":1713305679,"localadmin_id":1713309707,"locality_id":1276767515,"region_id":85682995}],"wof:id":1276767515,"wof:lang_x_official":["est"],"wof:lang_x_spoken":["est"],"wof:lastmodified":1596660932,"wof:name":"Ojakuela","wof:parent_id":1713309707,"wof:placetype":"locality","wof:repo":"whosonfirst-data-admin-ee","wof:superseded_by":[],"wof:supersedes":[],"wof:tags":[]},"bbox":[26.98444,58.65361,26.98444,58.65361],"geometry":{"coordinates":[26.98444,58.65361],"type":"Point"}}