{"id":1125831035,"type":"Feature","properties":{"edtf:cessation":"uuuu","edtf:inception":"uuuu","geom:area":0,"geom:area_square_m":0,"geom:bbox":"24.71833,59.23139,24.71833,59.23139","geom:latitude":59.23139,"geom:longitude":24.71833,"gn:country":"EE","gn:fcode":"PPL","gn:population":331,"iso:country":"EE","lbl:bbox":"24.69833,59.21139,24.73833,59.25139","lbl:latitude":59.23139,"lbl:longitude":24.71833,"lbl:max_zoom":17,"lbl:min_zoom":12.5,"mz:hierarchy_label":1,"mz:is_current":1,"mz:min_zoom":11,"mz:note":"Quattroshapes Point Gazetteer import 20170519","name:ceb_x_preferred":["Kurtna"],"name:deu_x_preferred":["Kurtna"],"name:eng_x_preferred":["Kurtna"],"name:est_x_preferred":["Kurtna"],"name:fra_x_preferred":["Kurtna"],"name:hye_x_preferred":["Կուռտնա"],"name:jpn_x_preferred":["クルトナ"],"name:nld_x_preferred":["Kurtna"],"name:pol_x_preferred":["Kurtna"],"name:rus_x_preferred":["Куртна"],"name:spa_x_preferred":["Kurtna"],"name:und_x_variant":["Myza Kurtna"],"name:vol_x_preferred":["Kurtna"],"qs_pg:aaroncc":"EE","qs_pg:gn_country":"EE","qs_pg:gn_fcode":"PPL","qs_pg:gn_id":590911,"qs_pg:gn_pop":331,"qs_pg:name":"Kurtna","qs_pg:photos_9r":0,"qs_pg:photos_sr":0,"qs_pg:pop_sr":2,"qs_pg:qs_id":81111,"qs_pg:qs_pg_placetype":"locality","src:geom":"qs_pg","src:lbl_centroid":"qs_pg","src:population":"geonames","wof:belongsto":[85683055,102191581,1713314659,85633135,1713305685],"wof:breaches":[],"wof:concordances":{"gn:id":590911,"qs_pg:id":81111,"wd:id":"Q1020190"},"wof:coterminous":[1713314659],"wof:country":"EE","wof:created":1497292499,"wof:geomhash":"8342d9669d8761f6fd070c50bce590f7","wof:hierarchy":[{"continent_id":102191581,"country_id":85633135,"county_id":1713305685,"localadmin_id":1713314659,"locality_id":1125831035,"region_id":85683055}],"wof:id":1125831035,"wof:lang_x_official":["est"],"wof:lang_x_spoken":["est"],"wof:lastmodified":1596661505,"wof:name":"Kurtna","wof:parent_id":1713314659,"wof:placetype":"locality","wof:population":331,"wof:population_rank":2,"wof:repo":"whosonfirst-data-admin-ee","wof:superseded_by":[],"wof:supersedes":[],"wof:tags":[]},"bbox":[24.71833,59.23139,24.71833,59.23139],"geometry":{"coordinates":[24.71833,59.23139],"type":"Point"}}