{"id":1293767107,"type":"Feature","properties":{"edtf:cessation":"uuuu","edtf:inception":"uuuu","geom:area":0,"geom:area_square_m":0,"geom:bbox":"23.26167,58.66167,23.26167,58.66167","geom:latitude":58.66167,"geom:longitude":23.26167,"gn:admin1_code":"14.0","gn:admin2_code":"478.0","gn:admin3_code":"2597.0","gn:asciiname":"Kallaste","gn:country_code":"EE","gn:dem":16,"gn:feature_class":"P","gn:feature_code":"PPL","gn:geonameid":591702,"gn:latitude":58.66167,"gn:longitude":23.26167,"gn:modification_date":"2017-11-25","gn:name":"Kallaste","gn:population":0,"gn:timezone":"Europe/Tallinn","iso:country":"EE","lbl:bbox":"23.24167,58.64167,23.28167,58.68167","lbl:max_zoom":18,"lbl:min_zoom":13.5,"mz:hierarchy_label":1,"mz:is_current":1,"mz:min_zoom":12,"name:deu_x_preferred":["Kallaste"],"name:est_x_preferred":["Kallaste"],"name:hye_x_preferred":["Կալլաստե"],"name:pol_x_preferred":["Kallaste"],"name:spa_x_preferred":["Kallaste"],"name:vol_x_preferred":["Kallaste"],"src:geom":"geonames","wof:belongsto":[85682947,102191581,1713306147,85633135,1713305623],"wof:breaches":[],"wof:concordances":{"gn:id":591702,"wk:page":"Kallaste%2C_Muhu_Parish"},"wof:coterminous":[1713306147],"wof:country":"EE","wof:geomhash":"dca5476473870e91669c86af7be274e0","wof:hierarchy":[{"continent_id":102191581,"country_id":85633135,"county_id":1713305623,"localadmin_id":1713306147,"locality_id":1293767107,"region_id":85682947}],"wof:id":1293767107,"wof:lang_x_official":["est"],"wof:lang_x_spoken":["est"],"wof:lastmodified":1596675302,"wof:name":"Kallaste","wof:parent_id":1713306147,"wof:placetype":"locality","wof:repo":"whosonfirst-data-admin-ee","wof:superseded_by":[],"wof:supersedes":[],"wof:tags":[]},"bbox":[23.26167,58.66167,23.26167,58.66167],"geometry":{"coordinates":[23.26167,58.66167],"type":"Point"}}