{"id":1276212151,"type":"Feature","properties":{"edtf:cessation":"uuuu","edtf:inception":"uuuu","geom:area":0,"geom:area_square_m":0,"geom:bbox":"26.19639,59.34389,26.19639,59.34389","geom:latitude":59.34389,"geom:longitude":26.19639,"gn:admin1_code":"8.0","gn:admin2_code":"272.0","gn:admin3_code":"8254.0","gn:asciiname":"Tirbiku","gn:country_code":"EE","gn:dem":89,"gn:feature_class":"P","gn:feature_code":"PPL","gn:geonameid":793474,"gn:latitude":59.34389,"gn:longitude":26.19639,"gn:modification_date":"2017-11-25","gn:name":"Tirbiku","gn:population":0,"gn:timezone":"Europe/Tallinn","iso:country":"EE","lbl:bbox":"26.17639,59.32389,26.21639,59.36389","lbl:max_zoom":18,"lbl:min_zoom":13.5,"mz:hierarchy_label":1,"mz:is_current":1,"mz:min_zoom":12,"name:est_x_preferred":["Tirbiku"],"name:hye_x_preferred":["Տիռբիկու"],"name:pol_x_preferred":["Tirbiku"],"name:vol_x_preferred":["Tirbiku"],"src:geom":"geonames","wof:belongsto":[85683049,102191581,1713313051,85633135,1713305723],"wof:breaches":[],"wof:concordances":{"gn:id":793474,"wk:page":"Tirbiku"},"wof:coterminous":[1713313051],"wof:country":"EE","wof:geomhash":"ecd2afac658ffe7eefa6e4f86ca858f7","wof:hierarchy":[{"continent_id":102191581,"country_id":85633135,"county_id":1713305723,"localadmin_id":1713313051,"locality_id":1276212151,"region_id":85683049}],"wof:id":1276212151,"wof:lang_x_official":["est"],"wof:lang_x_spoken":["est"],"wof:lastmodified":1596661730,"wof:name":"Tirbiku","wof:parent_id":1713313051,"wof:placetype":"locality","wof:repo":"whosonfirst-data-admin-ee","wof:superseded_by":[],"wof:supersedes":[],"wof:tags":[]},"bbox":[26.19639,59.34389,26.19639,59.34389],"geometry":{"coordinates":[26.19639,59.34389],"type":"Point"}}