{"id":1327432017,"type":"Feature","properties":{"edtf:cessation":"uuuu","edtf:inception":"uuuu","geom:area":0,"geom:area_square_m":0,"geom:bbox":"25.71917,58.86167,25.71917,58.86167","geom:latitude":58.86167,"geom:longitude":25.71917,"gn:admin1_code":"4.0","gn:admin2_code":"567.0","gn:admin3_code":"5474.0","gn:asciiname":"Nurmsi","gn:country_code":"EE","gn:dem":69,"gn:feature_class":"P","gn:feature_code":"PPL","gn:geonameid":589908,"gn:latitude":58.86167,"gn:longitude":25.71917,"gn:modification_date":"2017-11-25","gn:name":"Nurmsi","gn:population":0,"gn:timezone":"Europe/Tallinn","iso:country":"EE","lbl:bbox":"25.69917,58.84167,25.73917,58.88167","lbl:max_zoom":18,"lbl:min_zoom":13.5,"mz:hierarchy_label":1,"mz:is_current":1,"mz:min_zoom":12,"name:deu_x_preferred":["Nurmsi"],"name:est_x_preferred":["Nurmsi"],"name:fra_x_preferred":["Nurmsi"],"name:hye_x_preferred":["Նուռմսի"],"name:pol_x_preferred":["Nurmsi"],"name:ukr_x_preferred":["Нурмсі"],"name:vol_x_preferred":["Nurmsi"],"src:geom":"geonames","wof:belongsto":[85683031,102191581,1713312757,85633135,1713305663],"wof:breaches":[],"wof:concordances":{"gn:id":589908,"wk:page":"Nurmsi%2C_J%C3%A4rva_County"},"wof:coterminous":[1713312757],"wof:country":"EE","wof:geomhash":"a6e38a6256906e1846ae5e469d57de9f","wof:hierarchy":[{"continent_id":102191581,"country_id":85633135,"county_id":1713305663,"localadmin_id":1713312757,"locality_id":1327432017,"region_id":85683031}],"wof:id":1327432017,"wof:lang_x_official":["est"],"wof:lang_x_spoken":["est"],"wof:lastmodified":1596661331,"wof:name":"Nurmsi","wof:parent_id":1713312757,"wof:placetype":"locality","wof:repo":"whosonfirst-data-admin-ee","wof:superseded_by":[],"wof:supersedes":[],"wof:tags":[]},"bbox":[25.71917,58.86167,25.71917,58.86167],"geometry":{"coordinates":[25.71917,58.86167],"type":"Point"}}