{"id":1344115811,"type":"Feature","properties":{"edtf:cessation":"uuuu","edtf:inception":"uuuu","geom:area":0,"geom:area_square_m":0,"geom:bbox":"27.14333,57.75139,27.14333,57.75139","geom:latitude":57.75139,"geom:longitude":27.14333,"gn:admin1_code":"21.0","gn:admin2_code":"917.0","gn:admin3_code":"9458.0","gn:asciiname":"Hirmu","gn:country_code":"EE","gn:dem":191,"gn:feature_class":"P","gn:feature_code":"PPL","gn:geonameid":8619191,"gn:latitude":57.75139,"gn:longitude":27.14333,"gn:modification_date":"2017-11-25","gn:name":"Hirmu","gn:population":0,"gn:timezone":"Europe/Tallinn","iso:country":"EE","lbl:bbox":"27.12333,57.73139,27.16333,57.77139","lbl:max_zoom":18,"lbl:min_zoom":13.5,"mz:hierarchy_label":1,"mz:is_current":1,"mz:min_zoom":12,"name:und_x_variant":["Хирму"],"src:geom":"geonames","wof:belongsto":[85682937,102191581,1713315783,85633135,1713305633],"wof:breaches":[],"wof:concordances":{"gn:id":8619191},"wof:country":"EE","wof:geomhash":"d179fa84c4aa89ae1d7f0f3bb1649ba9","wof:hierarchy":[{"continent_id":102191581,"country_id":85633135,"county_id":1713305633,"localadmin_id":1713315783,"locality_id":1344115811,"region_id":85682937}],"wof:id":1344115811,"wof:lang_x_official":["est"],"wof:lang_x_spoken":["est"],"wof:lastmodified":1596660411,"wof:name":"Hirmu","wof:parent_id":1713315783,"wof:placetype":"locality","wof:repo":"whosonfirst-data-admin-ee","wof:superseded_by":[],"wof:supersedes":[],"wof:tags":[]},"bbox":[27.14333,57.75139,27.14333,57.75139],"geometry":{"coordinates":[27.14333,57.75139],"type":"Point"}}