{"id":1344171095,"type":"Feature","properties":{"edtf:cessation":"uuuu","edtf:inception":"uuuu","geom:area":0,"geom:area_square_m":0,"geom:bbox":"25.21611,59.38583,25.21611,59.38583","geom:latitude":59.38583,"geom:longitude":25.21611,"gn:admin1_code":"1.0","gn:admin2_code":"245.0","gn:admin3_code":"7405.0","gn:asciiname":"Sambu","gn:country_code":"EE","gn:dem":43,"gn:feature_class":"P","gn:feature_code":"PPL","gn:geonameid":793244,"gn:latitude":59.38583,"gn:longitude":25.21611,"gn:modification_date":"2017-11-25","gn:name":"Sambu","gn:population":0,"gn:timezone":"Europe/Tallinn","iso:country":"EE","lbl:bbox":"25.19611,59.36583,25.23611,59.40583","lbl:max_zoom":18,"lbl:min_zoom":13.5,"mz:hierarchy_label":1,"mz:is_current":1,"mz:min_zoom":12,"name:est_x_preferred":["Sambu"],"name:fra_x_preferred":["Sambu"],"name:hye_x_preferred":["Սամբու"],"name:nld_x_preferred":["Sambu"],"name:pol_x_preferred":["Sambu"],"name:spa_x_preferred":["Sambu"],"name:vol_x_preferred":["Sambu"],"src:geom":"geonames","wof:belongsto":[85683055,102191581,1713313137,85633135,1713305689],"wof:breaches":[],"wof:concordances":{"gn:id":793244,"wk:page":"Sambu%2C_Estonia"},"wof:coterminous":[1713313137],"wof:country":"EE","wof:geomhash":"abe9d2bae7f20f8cc8006d5790f88d3b","wof:hierarchy":[{"continent_id":102191581,"country_id":85633135,"county_id":1713305689,"localadmin_id":1713313137,"locality_id":1344171095,"region_id":85683055}],"wof:id":1344171095,"wof:lang_x_official":["est"],"wof:lang_x_spoken":["est"],"wof:lastmodified":1596661393,"wof:name":"Sambu","wof:parent_id":1713313137,"wof:placetype":"locality","wof:repo":"whosonfirst-data-admin-ee","wof:superseded_by":[],"wof:supersedes":[],"wof:tags":[]},"bbox":[25.21611,59.38583,25.21611,59.38583],"geometry":{"coordinates":[25.21611,59.38583],"type":"Point"}}