{"id":1343786033,"type":"Feature","properties":{"edtf:cessation":"uuuu","edtf:inception":"uuuu","geom:area":0,"geom:area_square_m":0,"geom:bbox":"25.76972,58.74722,25.76972,58.74722","geom:latitude":58.74722,"geom:longitude":25.76972,"gn:admin1_code":"4.0","gn:admin2_code":"255.0","gn:admin3_code":"2321.0","gn:asciiname":"Jaeravere","gn:country_code":"EE","gn:dem":68,"gn:feature_class":"P","gn:feature_code":"PPL","gn:geonameid":591978,"gn:latitude":58.74722,"gn:longitude":25.76972,"gn:modification_date":"2017-11-25","gn:name":"Järavere","gn:population":0,"gn:timezone":"Europe/Tallinn","iso:country":"EE","lbl:bbox":"25.74972,58.72722,25.78972,58.76722","lbl:max_zoom":18,"lbl:min_zoom":13.5,"mz:hierarchy_label":1,"mz:is_current":1,"mz:min_zoom":12,"name:eng_x_preferred":["Järavere"],"name:est_x_preferred":["Järavere"],"name:hye_x_preferred":["Եռավեռե"],"name:pol_x_preferred":["Järavere"],"name:rus_x_preferred":["Имавере"],"name:spa_x_preferred":["Järavere"],"name:ukr_x_preferred":["Яравере"],"name:und_x_variant":["Yaravere"],"name:urd_x_preferred":["جاروڑے"],"name:vol_x_preferred":["Järavere"],"src:geom":"geonames","wof:belongsto":[85683031,102191581,1713306905,85633135,1713305765],"wof:breaches":[],"wof:concordances":{"gn:id":591978,"wk:page":"J%C3%A4ravere"},"wof:coterminous":[1713306905],"wof:country":"EE","wof:geomhash":"b6c35adfb8608c80ecfc21be1fbfbc01","wof:hierarchy":[{"continent_id":102191581,"country_id":85633135,"county_id":1713305765,"localadmin_id":1713306905,"locality_id":1343786033,"region_id":85683031}],"wof:id":1343786033,"wof:lang_x_official":["est"],"wof:lang_x_spoken":["est"],"wof:lastmodified":1596676641,"wof:name":"Jaeravere","wof:parent_id":1713306905,"wof:placetype":"locality","wof:repo":"whosonfirst-data-admin-ee","wof:superseded_by":[],"wof:supersedes":[],"wof:tags":[]},"bbox":[25.76972,58.74722,25.76972,58.74722],"geometry":{"coordinates":[25.76972,58.74722],"type":"Point"}}