{"id":1309709183,"type":"Feature","properties":{"edtf:cessation":"uuuu","edtf:inception":"uuuu","geom:area":0,"geom:area_square_m":0,"geom:bbox":"23.55167,58.835,23.55167,58.835","geom:latitude":58.835,"geom:longitude":23.55167,"gn:admin1_code":"7.0","gn:admin2_code":"184.0","gn:admin3_code":"1201.0","gn:asciiname":"Allika","gn:country_code":"EE","gn:dem":8,"gn:feature_class":"P","gn:feature_code":"PPL","gn:geonameid":592527,"gn:latitude":58.835,"gn:longitude":23.55167,"gn:modification_date":"2017-11-25","gn:name":"Allika","gn:population":0,"gn:timezone":"Europe/Tallinn","iso:country":"EE","lbl:bbox":"23.53167,58.815,23.57167,58.855","lbl:max_zoom":18,"lbl:min_zoom":13.5,"mz:hierarchy_label":1,"mz:is_current":1,"mz:min_zoom":12,"name:deu_x_preferred":["Allika"],"name:est_x_preferred":["Allika"],"name:fas_x_preferred":["الیکا"],"name:hye_x_preferred":["Ալլիկա"],"name:pol_x_preferred":["Allika"],"name:ukr_x_preferred":["Алліка"],"name:und_x_variant":["Alliku"],"name:vol_x_preferred":["Allika"],"src:geom":"geonames","wof:belongsto":[85683001,102191581,1713308461,85633135,1713305755],"wof:breaches":[],"wof:concordances":{"gn:id":592527,"wk:page":"Allika%2C_L%C3%A4%C3%A4ne_County"},"wof:coterminous":[1713308461],"wof:country":"EE","wof:geomhash":"d4eaf551882d53201bcf7c1d5b4a4f46","wof:hierarchy":[{"continent_id":102191581,"country_id":85633135,"county_id":1713305755,"localadmin_id":1713308461,"locality_id":1309709183,"region_id":85683001}],"wof:id":1309709183,"wof:lang_x_official":["est"],"wof:lang_x_spoken":["est"],"wof:lastmodified":1596662770,"wof:name":"Allika","wof:parent_id":1713308461,"wof:placetype":"locality","wof:repo":"whosonfirst-data-admin-ee","wof:superseded_by":[],"wof:supersedes":[],"wof:tags":[]},"bbox":[23.55167,58.835,23.55167,58.835],"geometry":{"coordinates":[23.55167,58.835],"type":"Point"}}