{"id":1360268927,"type":"Feature","properties":{"edtf:cessation":"uuuu","edtf:inception":"uuuu","geom:area":0,"geom:area_square_m":0,"geom:bbox":"23.33222,58.56722,23.33222,58.56722","geom:latitude":58.56722,"geom:longitude":23.33222,"gn:admin1_code":"14.0","gn:admin2_code":"478.0","gn:admin3_code":"5639.0","gn:asciiname":"Oina","gn:country_code":"EE","gn:dem":15,"gn:feature_class":"P","gn:feature_code":"PPL","gn:geonameid":589868,"gn:latitude":58.56722,"gn:longitude":23.33222,"gn:modification_date":"2017-11-25","gn:name":"Oina","gn:population":0,"gn:timezone":"Europe/Tallinn","iso:country":"EE","lbl:bbox":"23.31222,58.54722,23.35222,58.58722","lbl:max_zoom":18,"lbl:min_zoom":13.5,"mz:hierarchy_label":1,"mz:is_current":1,"mz:min_zoom":12,"name:deu_x_preferred":["Oina"],"name:est_x_preferred":["Oina"],"name:hye_x_preferred":["Օինա"],"name:pol_x_preferred":["Oina"],"name:spa_x_preferred":["Oina"],"name:und_x_variant":["Oyna"],"name:vol_x_preferred":["Oina"],"src:geom":"geonames","wof:belongsto":[85682947,102191581,1713306209,85633135,1713305623],"wof:breaches":[],"wof:concordances":{"gn:id":589868,"wk:page":"Oina%2C_Estonia"},"wof:coterminous":[1713306209],"wof:country":"EE","wof:geomhash":"b1da36b1d679d01108512b272a82d6e4","wof:hierarchy":[{"continent_id":102191581,"country_id":85633135,"county_id":1713305623,"localadmin_id":1713306209,"locality_id":1360268927,"region_id":85682947}],"wof:id":1360268927,"wof:lang_x_official":["est"],"wof:lang_x_spoken":["est"],"wof:lastmodified":1596675299,"wof:name":"Oina","wof:parent_id":1713306209,"wof:placetype":"locality","wof:repo":"whosonfirst-data-admin-ee","wof:superseded_by":[],"wof:supersedes":[],"wof:tags":[]},"bbox":[23.33222,58.56722,23.33222,58.56722],"geometry":{"coordinates":[23.33222,58.56722],"type":"Point"}}