{"id":1293293325,"type":"Feature","properties":{"edtf:cessation":"uuuu","edtf:inception":"uuuu","geom:area":0,"geom:area_square_m":0,"geom:bbox":"25.6475,58.675,25.6475,58.675","geom:latitude":58.675,"geom:longitude":25.6475,"gn:admin1_code":"4.0","gn:admin2_code":"834.0","gn:admin3_code":"4873.0","gn:asciiname":"Meossaare","gn:cc2":"EE","gn:country_code":"EE","gn:dem":61,"gn:feature_class":"P","gn:feature_code":"PPL","gn:geonameid":590278,"gn:latitude":58.675,"gn:longitude":25.6475,"gn:modification_date":"2017-11-25","gn:name":"Meossaare","gn:population":0,"gn:timezone":"Europe/Tallinn","iso:country":"EE","lbl:bbox":"25.6275,58.655,25.6675,58.695","lbl:max_zoom":18,"lbl:min_zoom":13.5,"mz:hierarchy_label":1,"mz:is_current":1,"mz:min_zoom":12,"name:est_x_preferred":["Meossaare"],"name:fra_x_preferred":["Meossaare"],"name:hye_x_preferred":["Մեոսաառե"],"name:pol_x_preferred":["Meossaare"],"name:spa_x_preferred":["Meossaare"],"name:ukr_x_preferred":["Меоссааре"],"name:und_x_variant":["Meosare","Meosaare"],"name:vol_x_preferred":["Meossaare"],"src:geom":"geonames","wof:belongsto":[85683031,102191581,1713306693,85633135,1713305773],"wof:breaches":[],"wof:concordances":{"gn:id":590278,"wk:page":"Meossaare"},"wof:coterminous":[1713306693],"wof:country":"EE","wof:geomhash":"b0e613cd280c24ca641efb385ba6c8f1","wof:hierarchy":[{"continent_id":102191581,"country_id":85633135,"county_id":1713305773,"localadmin_id":1713306693,"locality_id":1293293325,"region_id":85683031}],"wof:id":1293293325,"wof:lang_x_official":["est"],"wof:lang_x_spoken":["est"],"wof:lastmodified":1596677993,"wof:name":"Meossaare","wof:parent_id":1713306693,"wof:placetype":"locality","wof:repo":"whosonfirst-data-admin-ee","wof:superseded_by":[],"wof:supersedes":[],"wof:tags":[]},"bbox":[25.6475,58.675,25.6475,58.675],"geometry":{"coordinates":[25.6475,58.675],"type":"Point"}}