{"id":1343233067,"type":"Feature","properties":{"edtf:cessation":"uuuu","edtf:inception":"uuuu","geom:area":0,"geom:area_square_m":0,"geom:bbox":"22.16167,58.17056,22.16167,58.17056","geom:latitude":58.17056,"geom:longitude":22.16167,"gn:admin1_code":"14.0","gn:admin2_code":"714.0","gn:admin3_code":"5308.0","gn:asciiname":"Moeldri","gn:country_code":"EE","gn:dem":17,"gn:feature_class":"P","gn:feature_code":"PPL","gn:geonameid":590159,"gn:latitude":58.17056,"gn:longitude":22.16167,"gn:modification_date":"2017-11-25","gn:name":"Möldri","gn:population":0,"gn:timezone":"Europe/Tallinn","iso:country":"EE","lbl:bbox":"22.14167,58.15056,22.18167,58.19056","lbl:max_zoom":18,"lbl:min_zoom":13.5,"mz:hierarchy_label":1,"mz:is_current":1,"mz:min_zoom":12,"name:deu_x_preferred":["Möldri"],"name:est_x_preferred":["Möldri"],"name:hye_x_preferred":["Մյոլդռի"],"name:nld_x_preferred":["Möldri"],"name:pol_x_preferred":["Möldri"],"name:ukr_x_preferred":["Мьолдрі"],"name:und_x_variant":["Möldri Küla","Mel’dri","Myl’dri"],"name:vol_x_preferred":["Möldri"],"src:geom":"geonames","wof:belongsto":[85682947,102191581,1713307061,85633135,1713305627],"wof:breaches":[],"wof:concordances":{"gn:id":590159,"wk:page":"M%C3%B6ldri%2C_Saare_County"},"wof:coterminous":[1713307061],"wof:country":"EE","wof:geomhash":"6813328b255ec9d0151440fc961ae429","wof:hierarchy":[{"continent_id":102191581,"country_id":85633135,"county_id":1713305627,"localadmin_id":1713307061,"locality_id":1343233067,"region_id":85682947}],"wof:id":1343233067,"wof:lang_x_official":["est"],"wof:lang_x_spoken":["est"],"wof:lastmodified":1596674914,"wof:name":"Moeldri","wof:parent_id":1713307061,"wof:placetype":"locality","wof:repo":"whosonfirst-data-admin-ee","wof:superseded_by":[],"wof:supersedes":[],"wof:tags":[]},"bbox":[22.16167,58.17056,22.16167,58.17056],"geometry":{"coordinates":[22.16167,58.17056],"type":"Point"}}