{"id":1310594465,"type":"Feature","properties":{"edtf:cessation":"uuuu","edtf:inception":"uuuu","geom:area":0,"geom:area_square_m":0,"geom:bbox":"25.95611,59.08,25.95611,59.08","geom:latitude":59.08,"geom:longitude":25.95611,"gn:admin1_code":"8.0","gn:admin2_code":"792.0","gn:admin3_code":"9506.0","gn:asciiname":"Vohmuta","gn:country_code":"EE","gn:dem":112,"gn:feature_class":"P","gn:feature_code":"PPL","gn:geonameid":587512,"gn:latitude":59.08,"gn:longitude":25.95611,"gn:modification_date":"2017-11-25","gn:name":"Võhmuta","gn:population":0,"gn:timezone":"Europe/Tallinn","iso:country":"EE","lbl:bbox":"25.93611,59.06,25.97611,59.1","lbl:max_zoom":18,"lbl:min_zoom":13.5,"mz:hierarchy_label":1,"mz:is_current":1,"mz:min_zoom":12,"name:est_x_preferred":["Võhmuta"],"name:hye_x_preferred":["Վիհմուտա"],"name:pol_x_preferred":["Võhmuta"],"name:ukr_x_preferred":["Вигмута"],"name:vol_x_preferred":["Võhmuta"],"src:geom":"geonames","wof:belongsto":[85683049,102191581,1713313831,85633135,1713305761],"wof:breaches":[],"wof:concordances":{"gn:id":587512,"wk:page":"V%C3%B5hmuta"},"wof:coterminous":[1713313831],"wof:country":"EE","wof:geomhash":"bdce7164c125068d4a4ae1528006814e","wof:hierarchy":[{"continent_id":102191581,"country_id":85633135,"county_id":1713305761,"localadmin_id":1713313831,"locality_id":1310594465,"region_id":85683049}],"wof:id":1310594465,"wof:lang_x_official":["est"],"wof:lang_x_spoken":["est"],"wof:lastmodified":1596676604,"wof:name":"Vohmuta","wof:parent_id":1713313831,"wof:placetype":"locality","wof:repo":"whosonfirst-data-admin-ee","wof:superseded_by":[],"wof:supersedes":[],"wof:tags":[]},"bbox":[25.95611,59.08,25.95611,59.08],"geometry":{"coordinates":[25.95611,59.08],"type":"Point"}}