{"id":1293480609,"type":"Feature","properties":{"edtf:cessation":"uuuu","edtf:inception":"uuuu","geom:area":0,"geom:area_square_m":0,"geom:bbox":"26.48444,58.95611,26.48444,58.95611","geom:latitude":58.95611,"geom:longitude":26.48444,"gn:admin1_code":"8.0","gn:admin2_code":"928.0","gn:admin3_code":"2080.0","gn:asciiname":"Korvekuela","gn:country_code":"EE","gn:dem":94,"gn:feature_class":"P","gn:feature_code":"PPL","gn:geonameid":8618828,"gn:latitude":58.95611,"gn:longitude":26.48444,"gn:modification_date":"2017-11-25","gn:name":"Kõrveküla","gn:population":0,"gn:timezone":"Europe/Tallinn","iso:country":"EE","lbl:bbox":"26.46444,58.93611,26.50444,58.97611","lbl:max_zoom":18,"lbl:min_zoom":13.5,"mz:hierarchy_label":1,"mz:is_current":1,"mz:min_zoom":12,"name:und_x_variant":["Kõrveküla","Kõrve"],"src:geom":"geonames","wof:belongsto":[85683049,102191581,1713315423,85633135,1713305769],"wof:breaches":[],"wof:concordances":{"gn:id":8618828},"wof:country":"EE","wof:geomhash":"0d0179026a7887208365e7590c71876b","wof:hierarchy":[{"continent_id":102191581,"country_id":85633135,"county_id":1713305769,"localadmin_id":1713315423,"locality_id":1293480609,"region_id":85683049}],"wof:id":1293480609,"wof:lang_x_official":["est"],"wof:lang_x_spoken":["est"],"wof:lastmodified":1596676545,"wof:name":"Korvekuela","wof:parent_id":1713315423,"wof:placetype":"locality","wof:repo":"whosonfirst-data-admin-ee","wof:superseded_by":[],"wof:supersedes":[],"wof:tags":[]},"bbox":[26.48444,58.95611,26.48444,58.95611],"geometry":{"coordinates":[26.48444,58.95611],"type":"Point"}}