{"id":1126036693,"type":"Feature","properties":{"edtf:cessation":"uuuu","edtf:inception":"uuuu","geom:area":0,"geom:area_square_m":0,"geom:bbox":"24.65222,58.43639,24.65222,58.43639","geom:latitude":58.43639,"geom:longitude":24.65222,"gn:country":"EE","gn:fcode":"PPL","gn:population":180,"iso:country":"EE","lbl:bbox":"24.63222,58.41639,24.67222,58.45639","lbl:latitude":58.43639,"lbl:longitude":24.65222,"lbl:max_zoom":18,"lbl:min_zoom":13,"mz:hierarchy_label":1,"mz:is_current":1,"mz:min_zoom":11,"mz:note":"Quattroshapes Point Gazetteer import 20170519","name:ceb_x_preferred":["Urge"],"name:eng_x_preferred":["Urge"],"name:est_x_preferred":["Urge"],"name:hye_x_preferred":["Ուռգե"],"name:nld_x_preferred":["Urge"],"name:pol_x_preferred":["Urge"],"name:spa_x_preferred":["Urge"],"name:swe_x_preferred":["Urge"],"name:vol_x_preferred":["Urge"],"qs_pg:aaroncc":"EE","qs_pg:gn_country":"EE","qs_pg:gn_fcode":"PPL","qs_pg:gn_id":588045,"qs_pg:gn_pop":180,"qs_pg:name":"Urge","qs_pg:name_adm0":"Eesti","qs_pg:name_adm1":"Pärnumaa","qs_pg:photos_9r":0,"qs_pg:photos_sr":0,"qs_pg:pop_sr":1,"qs_pg:qs_id":406441,"qs_pg:qs_pg_placetype":"locality","qs_pg:qs_pg_placetype_gp":"Town","qs_pg:woe_adm0":23424805,"qs_pg:woe_id":846084,"src:geom":"qs_pg","src:lbl_centroid":"qs_pg","src:population":"geonames","woe:adm0_id":23424805,"woe:name_adm0":"Eesti","woe:name_adm1":"Pärnumaa","woe:placetype":"Town","wof:belongsto":[85682981,102191581,1713312375,85633135,1713305731],"wof:breaches":[],"wof:concordances":{"gn:id":588045,"gp:id":846084,"qs_pg:id":406441,"wd:id":"Q11248314"},"wof:coterminous":[1713312375],"wof:country":"EE","wof:created":1497301831,"wof:geomhash":"e24a676d141e83334d93a6bc8dd75c8a","wof:hierarchy":[{"continent_id":102191581,"country_id":85633135,"county_id":1713305731,"localadmin_id":1713312375,"locality_id":1126036693,"region_id":85682981}],"wof:id":1126036693,"wof:lang_x_official":["est"],"wof:lang_x_spoken":["est"],"wof:lastmodified":1596663393,"wof:name":"Urge","wof:parent_id":1713312375,"wof:placetype":"locality","wof:population":180,"wof:population_rank":1,"wof:repo":"whosonfirst-data-admin-ee","wof:superseded_by":[],"wof:supersedes":[],"wof:tags":[]},"bbox":[24.65222,58.43639,24.65222,58.43639],"geometry":{"coordinates":[24.65222,58.43639],"type":"Point"}}