{"id":1226022995,"type":"Feature","properties":{"edtf:cessation":"uuuu","edtf:inception":"uuuu","geom:area":0,"geom:area_square_m":0,"geom:bbox":"24.33722,58.49722,24.33722,58.49722","geom:latitude":58.49722,"geom:longitude":24.33722,"gn:admin1_code":"11.0","gn:admin2_code":"624.0","gn:admin3_code":"2289.0","gn:asciiname":"Metsakuela","gn:country_code":"EE","gn:dem":13,"gn:feature_class":"P","gn:feature_code":"PPL","gn:geonameid":590252,"gn:latitude":58.49722,"gn:longitude":24.33722,"gn:modification_date":"2017-11-25","gn:name":"Metsaküla","gn:population":0,"gn:timezone":"Europe/Tallinn","iso:country":"EE","lbl:bbox":"24.31722,58.47722,24.35722,58.51722","lbl:max_zoom":18,"lbl:min_zoom":13.5,"mz:hierarchy_label":1,"mz:is_current":1,"mz:min_zoom":12,"name:und_x_variant":["Metskyula","Metsküla","Metsaküla"],"src:geom":"geonames","wof:belongsto":[85682981,102191581,1713314483,85633135,1713305703],"wof:breaches":[],"wof:concordances":{"gn:id":590252},"wof:country":"EE","wof:geomhash":"b304b96099c55c902d59c33db01415a2","wof:hierarchy":[{"continent_id":102191581,"country_id":85633135,"county_id":1713305703,"localadmin_id":1713314483,"locality_id":1226022995,"region_id":85682981}],"wof:id":1226022995,"wof:lang_x_official":["est"],"wof:lang_x_spoken":["est"],"wof:lastmodified":1596677700,"wof:name":"Metsakuela","wof:parent_id":1713314483,"wof:placetype":"locality","wof:repo":"whosonfirst-data-admin-ee","wof:superseded_by":[],"wof:supersedes":[],"wof:tags":[]},"bbox":[24.33722,58.49722,24.33722,58.49722],"geometry":{"coordinates":[24.33722,58.49722],"type":"Point"}}