{"id":1209821307,"type":"Feature","properties":{"edtf:cessation":"uuuu","edtf:inception":"uuuu","geom:area":0,"geom:area_square_m":0,"geom:bbox":"26.07806,58.92139,26.07806,58.92139","geom:latitude":58.92139,"geom:longitude":26.07806,"gn:admin1_code":"4.0","gn:admin2_code":"255.0","gn:admin3_code":"1640.0","gn:asciiname":"Rohu","gn:country_code":"EE","gn:dem":89,"gn:feature_class":"P","gn:feature_code":"PPL","gn:geonameid":793304,"gn:latitude":58.92139,"gn:longitude":26.07806,"gn:modification_date":"2017-11-25","gn:name":"Rõhu","gn:population":0,"gn:timezone":"Europe/Tallinn","iso:country":"EE","lbl:bbox":"26.05806,58.90139,26.09806,58.94139","lbl:max_zoom":18,"lbl:min_zoom":13.5,"mz:hierarchy_label":1,"mz:is_current":1,"mz:min_zoom":12,"name:ara_x_preferred":["رهيطة"],"name:asm_x_preferred":["ৰৌ মাছ"],"name:ben_x_preferred":["রুই"],"name:cat_x_preferred":["Labeo rohita"],"name:ceb_x_preferred":["Labeo rohita"],"name:deu_x_preferred":["Labeo rohita"],"name:eus_x_preferred":["Labeo rohita"],"name:fas_x_preferred":["روهو"],"name:fra_x_preferred":["Labeo rohita"],"name:guj_x_preferred":["રોહુ માછલી"],"name:hin_x_preferred":["रोहू मछली"],"name:isl_x_preferred":["Labeo Rohita"],"name:ita_x_preferred":["Labeo rohita"],"name:mal_x_preferred":["രോഹു"],"name:mya_x_preferred":["ငါးမြစ်ချင်း"],"name:nld_x_preferred":["Rohu"],"name:pnb_x_preferred":["رعو"],"name:snd_x_preferred":["پلو"],"name:spa_x_preferred":["Labeo rohita"],"name:swe_x_preferred":["Rohu"],"name:tam_x_preferred":["ரோகு மீன்"],"name:tha_x_preferred":["ปลายี่สกเทศ"],"name:war_x_preferred":["Labeo rohita"],"src:geom":"geonames","wof:belongsto":[85683031,102191581,1713307109,85633135,1713305765],"wof:breaches":[],"wof:concordances":{"gn:id":793304},"wof:coterminous":[1713307021],"wof:country":"EE","wof:geomhash":"87a3e8ff6c07968a5af46146ad68e2d5","wof:hierarchy":[{"continent_id":102191581,"country_id":85633135,"county_id":1713305765,"localadmin_id":1713307109,"locality_id":1209821307,"region_id":85683031}],"wof:id":1209821307,"wof:lang_x_official":["est"],"wof:lang_x_spoken":["est"],"wof:lastmodified":1596676643,"wof:name":"Rohu","wof:parent_id":1713307109,"wof:placetype":"locality","wof:repo":"whosonfirst-data-admin-ee","wof:superseded_by":[],"wof:supersedes":[],"wof:tags":[]},"bbox":[26.07806,58.92139,26.07806,58.92139],"geometry":{"coordinates":[26.07806,58.92139],"type":"Point"}}