{"id":1310076461,"type":"Feature","properties":{"edtf:cessation":"uuuu","edtf:inception":"uuuu","geom:area":0,"geom:area_square_m":0,"geom:bbox":"22.52083,58.36889,22.52083,58.36889","geom:latitude":58.36889,"geom:longitude":22.52083,"gn:admin1_code":"14.0","gn:admin2_code":"714.0","gn:admin3_code":"2412.0","gn:asciiname":"Joe","gn:country_code":"EE","gn:dem":27,"gn:feature_class":"P","gn:feature_code":"PPL","gn:geonameid":591932,"gn:latitude":58.36889,"gn:longitude":22.52083,"gn:modification_date":"2017-11-25","gn:name":"Jõe","gn:population":0,"gn:timezone":"Europe/Tallinn","iso:country":"EE","lbl:bbox":"22.50083,58.34889,22.54083,58.38889","lbl:max_zoom":18,"lbl:min_zoom":13.5,"mz:hierarchy_label":1,"mz:is_current":1,"mz:min_zoom":12,"name:und_x_variant":["Iyye","Jõe"],"src:geom":"geonames","wof:belongsto":[85682947,102191581,1713307323,85633135,1713305627],"wof:breaches":[],"wof:concordances":{"gn:id":591932,"wk:page":"J%C3%B5e%2C_L%C3%A4%C3%A4ne-Saare_Parish"},"wof:country":"EE","wof:geomhash":"9088dd2143e863aad064d375cd7012c1","wof:hierarchy":[{"continent_id":102191581,"country_id":85633135,"county_id":1713305627,"localadmin_id":1713307323,"locality_id":1310076461,"region_id":85682947}],"wof:id":1310076461,"wof:lang_x_official":["est"],"wof:lang_x_spoken":["est"],"wof:lastmodified":1596674934,"wof:name":"Joe","wof:parent_id":1713307323,"wof:placetype":"locality","wof:repo":"whosonfirst-data-admin-ee","wof:superseded_by":[],"wof:supersedes":[],"wof:tags":[]},"bbox":[22.52083,58.36889,22.52083,58.36889],"geometry":{"coordinates":[22.52083,58.36889],"type":"Point"}}