{"id":1310591867,"type":"Feature","properties":{"edtf:cessation":"uuuu","edtf:inception":"uuuu","geom:area":0,"geom:area_square_m":0,"geom:bbox":"26.48222,59.22833,26.48222,59.22833","geom:latitude":59.22833,"geom:longitude":26.48222,"gn:admin1_code":"8.0","gn:admin2_code":"901.0","gn:admin3_code":"2679.0","gn:asciiname":"Kannastiku","gn:country_code":"EE","gn:dem":127,"gn:feature_class":"P","gn:feature_code":"PPL","gn:geonameid":793427,"gn:latitude":59.22833,"gn:longitude":26.48222,"gn:modification_date":"2017-11-25","gn:name":"Kannastiku","gn:population":0,"gn:timezone":"Europe/Tallinn","iso:country":"EE","lbl:bbox":"26.46222,59.20833,26.50222,59.24833","lbl:max_zoom":18,"lbl:min_zoom":13.5,"mz:hierarchy_label":1,"mz:is_current":1,"mz:min_zoom":12,"name:est_x_preferred":["Kannastiku"],"name:hye_x_preferred":["Կաննաստիկու"],"name:vol_x_preferred":["Kannastiku"],"src:geom":"geonames","wof:belongsto":[85683049,102191581,1713307909,85633135,1713305771],"wof:breaches":[],"wof:concordances":{"gn:id":793427,"wk:page":"Kannastiku"},"wof:coterminous":[1713307909],"wof:country":"EE","wof:geomhash":"2f73febf05418089676ba66463444ef9","wof:hierarchy":[{"continent_id":102191581,"country_id":85633135,"county_id":1713305771,"localadmin_id":1713307909,"locality_id":1310591867,"region_id":85683049}],"wof:id":1310591867,"wof:lang_x_official":["est"],"wof:lang_x_spoken":["est"],"wof:lastmodified":1596677960,"wof:name":"Kannastiku","wof:parent_id":1713307909,"wof:placetype":"locality","wof:repo":"whosonfirst-data-admin-ee","wof:superseded_by":[],"wof:supersedes":[],"wof:tags":[]},"bbox":[26.48222,59.22833,26.48222,59.22833],"geometry":{"coordinates":[26.48222,59.22833],"type":"Point"}}