{
  "type": "Feature",
  "properties": {
    "iso:country":"FI",
    "wof:name":"Kaakkoinen",
    "wof:placetype":"neighbourhood"
},
  "geometry": {"coordinates":[25.04809934592073,60.1748252154514],"type":"Point"}
}