{"id":1344121723,"type":"Feature","properties":{"edtf:cessation":"uuuu","edtf:inception":"uuuu","geom:area":0,"geom:area_square_m":0,"geom:bbox":"25.24222,58.59361,25.24222,58.59361","geom:latitude":58.59361,"geom:longitude":25.24222,"gn:admin1_code":"20.0","gn:admin2_code":"615.0","gn:admin3_code":"3430.0","gn:asciiname":"Paerassaare","gn:country_code":"EE","gn:dem":42,"gn:feature_class":"P","gn:feature_code":"PPL","gn:geonameid":589609,"gn:latitude":58.59361,"gn:longitude":25.24222,"gn:modification_date":"2017-11-25","gn:name":"Pärassaare","gn:population":0,"gn:timezone":"Europe/Tallinn","iso:country":"EE","lbl:bbox":"25.22222,58.57361,25.26222,58.61361","lbl:max_zoom":18,"lbl:min_zoom":13.5,"mz:hierarchy_label":1,"mz:is_current":1,"mz:min_zoom":12,"name:und_x_variant":["Pärasaare","Pyarasare","Pärassaare"],"src:geom":"geonames","wof:belongsto":[85682985,102191581,1713314383,85633135,1713305735],"wof:breaches":[],"wof:concordances":{"gn:id":589609},"wof:country":"EE","wof:geomhash":"cb63fc1c674560979de18d7cff745ea6","wof:hierarchy":[{"continent_id":102191581,"country_id":85633135,"county_id":1713305735,"localadmin_id":1713314383,"locality_id":1344121723,"region_id":85682985}],"wof:id":1344121723,"wof:lang_x_official":["est"],"wof:lang_x_spoken":["est"],"wof:lastmodified":1596663461,"wof:name":"Paerassaare","wof:parent_id":1713314383,"wof:placetype":"locality","wof:repo":"whosonfirst-data-admin-ee","wof:superseded_by":[],"wof:supersedes":[],"wof:tags":[]},"bbox":[25.24222,58.59361,25.24222,58.59361],"geometry":{"coordinates":[25.24222,58.59361],"type":"Point"}}