{"id":1225845329,"type":"Feature","properties":{"edtf:cessation":"uuuu","edtf:inception":"uuuu","geom:area":0,"geom:area_square_m":0,"geom:bbox":"25.805,58.88167,25.805,58.88167","geom:latitude":58.88167,"geom:longitude":25.805,"gn:admin1_code":"4.0","gn:admin2_code":"255.0","gn:admin3_code":"9623.0","gn:asciiname":"Vaeike-Kareda","gn:country_code":"EE","gn:dem":73,"gn:feature_class":"P","gn:feature_code":"PPL","gn:geonameid":587932,"gn:latitude":58.88167,"gn:longitude":25.805,"gn:modification_date":"2017-11-25","gn:name":"Väike-Kareda","gn:population":0,"gn:timezone":"Europe/Tallinn","iso:country":"EE","lbl:bbox":"25.785,58.86167,25.825,58.90167","lbl:max_zoom":18,"lbl:min_zoom":13.5,"mz:hierarchy_label":1,"mz:is_current":1,"mz:min_zoom":12,"name:eng_x_preferred":["Väike-Kareda"],"name:est_x_preferred":["Väike-Kareda"],"name:fra_x_preferred":["Väike-Kareda"],"name:hye_x_preferred":["Վեիկե-Կառեդա"],"name:pol_x_preferred":["Väike-Kareda"],"name:rus_x_preferred":["Вяйке-Кяреда"],"name:spa_x_preferred":["Väike-Kareda"],"name:ukr_x_preferred":["Вяйке-Кареда"],"name:und_x_variant":["Kareda Väike","Väika-Kareda","Vyayke Kareda"],"name:vol_x_preferred":["Väike-Kareda"],"src:geom":"geonames","wof:belongsto":[85683031,102191581,1713312751,85633135,1713305765],"wof:breaches":[],"wof:concordances":{"gn:id":587932,"wk:page":"V%C3%A4ike-Kareda"},"wof:coterminous":[1713312751],"wof:country":"EE","wof:geomhash":"28c1bd91e36b45e3f24a127a6d1b3eb8","wof:hierarchy":[{"continent_id":102191581,"country_id":85633135,"county_id":1713305765,"localadmin_id":1713312751,"locality_id":1225845329,"region_id":85683031}],"wof:id":1225845329,"wof:lang_x_official":["est"],"wof:lang_x_spoken":["est"],"wof:lastmodified":1596676643,"wof:name":"Vaeike-Kareda","wof:parent_id":1713312751,"wof:placetype":"locality","wof:repo":"whosonfirst-data-admin-ee","wof:superseded_by":[],"wof:supersedes":[],"wof:tags":[]},"bbox":[25.805,58.88167,25.805,58.88167],"geometry":{"coordinates":[25.805,58.88167],"type":"Point"}}