{"id":1126034363,"type":"Feature","properties":{"edtf:cessation":"uuuu","edtf:inception":"uuuu","geom:area":0,"geom:area_square_m":0,"geom:bbox":"24.25444,59.34806,24.25444,59.34806","geom:latitude":59.34806,"geom:longitude":24.25444,"gn:country":"EE","gn:fcode":"PPL","gn:population":105,"iso:country":"EE","lbl:bbox":"24.23444,59.32806,24.27444,59.36806","lbl:latitude":59.34806,"lbl:longitude":24.25444,"lbl:max_zoom":18,"lbl:min_zoom":13,"mz:hierarchy_label":1,"mz:is_current":1,"mz:min_zoom":11,"mz:note":"Quattroshapes Point Gazetteer import 20170519","name:bul_x_preferred":["Клогарана"],"name:ceb_x_preferred":["Kloogaranna"],"name:eng_x_preferred":["Kloogaranna"],"name:est_x_preferred":["Kloogaranna"],"name:fin_x_preferred":["Kloogaranna"],"name:fra_x_preferred":["Kloogaranna"],"name:hye_x_preferred":["Կլոոգառաննա"],"name:nld_x_preferred":["Kloogaranna"],"name:pol_x_preferred":["Kloogaranna"],"name:rus_x_preferred":["Клоогаранна"],"name:spa_x_preferred":["Kloogaranna"],"name:swe_x_preferred":["Kloogaranna"],"name:ukr_x_preferred":["Клооґаранна"],"name:und_x_variant":["Kloga-Rand"],"name:vol_x_preferred":["Kloogaranna"],"qs_pg:aaroncc":"EE","qs_pg:gn_country":"EE","qs_pg:gn_fcode":"PPL","qs_pg:gn_id":591304,"qs_pg:gn_pop":105,"qs_pg:name":"Kloogaranna","qs_pg:name_adm0":"Eesti","qs_pg:name_adm1":"Harjumaa","qs_pg:photos":87,"qs_pg:photos_1k":18,"qs_pg:photos_9k":1,"qs_pg:photos_9r":3,"qs_pg:photos_all":87,"qs_pg:photos_sr":3,"qs_pg:pop_sr":1,"qs_pg:qs_id":1034200,"qs_pg:qs_pg_placetype":"locality","qs_pg:qs_pg_placetype_gp":"Town","qs_pg:woe_adm0":23424805,"qs_pg:woe_id":843030,"src:geom":"qs_pg","src:lbl_centroid":"qs_pg","src:population":"geonames","woe:adm0_id":23424805,"woe:name_adm0":"Eesti","woe:name_adm1":"Harjumaa","woe:placetype":"Town","wof:belongsto":[85683055,102191581,1713307719,85633135,1713305737],"wof:breaches":[],"wof:concordances":{"gn:id":591304,"gp:id":843030,"qs_pg:id":1034200,"wd:id":"Q3457833"},"wof:coterminous":[1713307719],"wof:country":"EE","wof:created":1497301686,"wof:geomhash":"1490ed075c79effb0db13a5f75c4b20d","wof:hierarchy":[{"continent_id":102191581,"country_id":85633135,"county_id":1713305737,"localadmin_id":1713307719,"locality_id":1126034363,"region_id":85683055}],"wof:id":1126034363,"wof:lang_x_official":["est"],"wof:lang_x_spoken":["est"],"wof:lastmodified":1596663329,"wof:name":"Kloogaranna","wof:parent_id":1713307719,"wof:placetype":"locality","wof:population":105,"wof:population_rank":1,"wof:repo":"whosonfirst-data-admin-ee","wof:superseded_by":[],"wof:supersedes":[],"wof:tags":[]},"bbox":[24.25444,59.34806,24.25444,59.34806],"geometry":{"coordinates":[24.25444,59.34806],"type":"Point"}}