{"id":1226007979,"type":"Feature","properties":{"edtf:cessation":"uuuu","edtf:inception":"uuuu","geom:area":0,"geom:area_square_m":0,"geom:bbox":"27.14722,58.62806,27.14722,58.62806","geom:latitude":58.62806,"geom:longitude":27.14722,"gn:admin1_code":"18.0","gn:admin2_code":"586.0","gn:admin3_code":"1176.0","gn:asciiname":"Virtsu","gn:country_code":"EE","gn:dem":55,"gn:feature_class":"P","gn:feature_code":"PPL","gn:geonameid":587558,"gn:latitude":58.62806,"gn:longitude":27.14722,"gn:modification_date":"2017-11-25","gn:name":"Virtsu","gn:population":0,"gn:timezone":"Europe/Tallinn","iso:country":"EE","lbl:bbox":"27.12722,58.60806,27.16722,58.64806","lbl:max_zoom":18,"lbl:min_zoom":13.5,"mz:hierarchy_label":1,"mz:is_current":1,"mz:min_zoom":12,"name:est_x_preferred":["Virtsu"],"name:fra_x_preferred":["Virtsu"],"name:hye_x_preferred":["Վիռցու"],"name:pol_x_preferred":["Virtsu"],"name:spa_x_preferred":["Virtsu"],"name:ukr_x_preferred":["Віртсу"],"name:vol_x_preferred":["Virtsu"],"src:geom":"geonames","wof:belongsto":[85682995,102191581,1713309289,85633135,1713305679],"wof:breaches":[],"wof:concordances":{"gn:id":587558,"wk:page":"Virtsu%2C_Tartu_County"},"wof:coterminous":[1713309709],"wof:country":"EE","wof:geomhash":"ee4be93f49cf8392578ce84a107dccb8","wof:hierarchy":[{"continent_id":102191581,"country_id":85633135,"county_id":1713305679,"localadmin_id":1713309289,"locality_id":1226007979,"region_id":85682995}],"wof:id":1226007979,"wof:lang_x_official":["est"],"wof:lang_x_spoken":["est"],"wof:lastmodified":1596660905,"wof:name":"Virtsu","wof:parent_id":1713309289,"wof:placetype":"locality","wof:repo":"whosonfirst-data-admin-ee","wof:superseded_by":[],"wof:supersedes":[],"wof:tags":[]},"bbox":[27.14722,58.62806,27.14722,58.62806],"geometry":{"coordinates":[27.14722,58.62806],"type":"Point"}}