{"id":1343941415,"type":"Feature","properties":{"edtf:cessation":"uuuu","edtf:inception":"uuuu","geom:area":0,"geom:area_square_m":0,"geom:bbox":"22.55806,58.49278,22.55806,58.49278","geom:latitude":58.49278,"geom:longitude":22.55806,"gn:admin1_code":"14.0","gn:admin2_code":"714.0","gn:admin3_code":"4409.0","gn:asciiname":"Purtsa","gn:country_code":"EE","gn:dem":23,"gn:feature_class":"P","gn:feature_code":"PPL","gn:geonameid":589263,"gn:latitude":58.49278,"gn:longitude":22.55806,"gn:modification_date":"2017-11-25","gn:name":"Purtsa","gn:population":0,"gn:timezone":"Europe/Tallinn","iso:country":"EE","lbl:bbox":"22.53806,58.47278,22.57806,58.51278","lbl:max_zoom":18,"lbl:min_zoom":13.5,"mz:hierarchy_label":1,"mz:is_current":1,"mz:min_zoom":12,"name:deu_x_preferred":["Purtsa"],"name:est_x_preferred":["Purtsa"],"name:hye_x_preferred":["Պուռցա"],"name:pol_x_preferred":["Purtsa"],"name:spa_x_preferred":["Purtsa"],"name:vol_x_preferred":["Purtsa"],"src:geom":"geonames","wof:belongsto":[85682947,102191581,1713306585,85633135,1713305627],"wof:breaches":[],"wof:concordances":{"gn:id":589263,"wk:page":"Purtsa"},"wof:coterminous":[1713308183],"wof:country":"EE","wof:geomhash":"2aa23c18097d185976ab45e129a2df52","wof:hierarchy":[{"continent_id":102191581,"country_id":85633135,"county_id":1713305627,"localadmin_id":1713306585,"locality_id":1343941415,"region_id":85682947}],"wof:id":1343941415,"wof:lang_x_official":["est"],"wof:lang_x_spoken":["est"],"wof:lastmodified":1596674950,"wof:name":"Purtsa","wof:parent_id":1713306585,"wof:placetype":"locality","wof:repo":"whosonfirst-data-admin-ee","wof:superseded_by":[],"wof:supersedes":[],"wof:tags":[]},"bbox":[22.55806,58.49278,22.55806,58.49278],"geometry":{"coordinates":[22.55806,58.49278],"type":"Point"}}