{"id":1309688113,"type":"Feature","properties":{"edtf:cessation":"uuuu","edtf:inception":"uuuu","geom:area":0,"geom:area_square_m":0,"geom:bbox":"26.99389,58.385,26.99389,58.385","geom:latitude":58.385,"geom:longitude":26.99389,"gn:admin1_code":"18.0","gn:admin2_code":"432.0","gn:admin3_code":"3059.0","gn:asciiname":"Saeveski","gn:country_code":"EE","gn:dem":42,"gn:feature_class":"P","gn:feature_code":"PPL","gn:geonameid":8618343,"gn:latitude":58.385,"gn:longitude":26.99389,"gn:modification_date":"2017-11-25","gn:name":"Saeveski","gn:population":0,"gn:timezone":"Europe/Tallinn","iso:country":"EE","lbl:bbox":"26.97389,58.365,27.01389,58.405","lbl:max_zoom":18,"lbl:min_zoom":13.5,"mz:hierarchy_label":1,"mz:is_current":1,"mz:min_zoom":12,"name:und_x_variant":["Saage"],"src:geom":"geonames","wof:belongsto":[85682995,102191581,1713313707,85633135,1713305697],"wof:breaches":[],"wof:concordances":{"gn:id":8618343},"wof:country":"EE","wof:geomhash":"30d32f1281213c74af5a6c845538418a","wof:hierarchy":[{"continent_id":102191581,"country_id":85633135,"county_id":1713305697,"localadmin_id":1713313707,"locality_id":1309688113,"region_id":85682995}],"wof:id":1309688113,"wof:lang_x_official":["est"],"wof:lang_x_spoken":["est"],"wof:lastmodified":1596660678,"wof:name":"Saeveski","wof:parent_id":1713313707,"wof:placetype":"locality","wof:repo":"whosonfirst-data-admin-ee","wof:superseded_by":[],"wof:supersedes":[],"wof:tags":[]},"bbox":[26.99389,58.385,26.99389,58.385],"geometry":{"coordinates":[26.99389,58.385],"type":"Point"}}