{"id":1259501177,"type":"Feature","properties":{"edtf:cessation":"uuuu","edtf:inception":"uuuu","geom:area":0,"geom:area_square_m":0,"geom:bbox":"24.76694,59.26528,24.76694,59.26528","geom:latitude":59.26528,"geom:longitude":24.76694,"gn:admin1_code":"1.0","gn:admin2_code":"718.0","gn:admin3_code":"7704.0","gn:asciiname":"Sookaera-Metsanurga","gn:country_code":"EE","gn:dem":60,"gn:feature_class":"P","gn:feature_code":"PPL","gn:geonameid":589943,"gn:latitude":59.26528,"gn:longitude":24.76694,"gn:modification_date":"2017-11-25","gn:name":"Sookaera-Metsanurga","gn:population":0,"gn:timezone":"Europe/Tallinn","iso:country":"EE","lbl:bbox":"24.74694,59.24528,24.78694,59.28528","lbl:max_zoom":18,"lbl:min_zoom":13.5,"mz:hierarchy_label":1,"mz:is_current":1,"mz:min_zoom":12,"name:est_x_preferred":["Sookaera-Metsanurga"],"name:fra_x_preferred":["Sookaera-Metsanurga"],"name:hye_x_preferred":["Սոոկաեռա-Մեցանուռգա"],"name:nld_x_preferred":["Sookaera-Metsanurga"],"name:pol_x_preferred":["Sookaera-Metsanurga"],"name:rus_x_preferred":["Соокаэра-Метсанурга"],"name:spa_x_preferred":["Sookaera-Metsanurga"],"name:und_x_variant":["Nymmekyula","Nabala-Nõmme","Nõmmeküla","Nõmmküla"],"name:vol_x_preferred":["Sookaera-Metsanurga"],"src:geom":"geonames","wof:belongsto":[85683055,102191581,1713312913,85633135,1713305685],"wof:breaches":[],"wof:concordances":{"gn:id":589943},"wof:coterminous":[1713312913],"wof:country":"EE","wof:geomhash":"c0b0eeb3d80ae6b63ecd166e17fdf988","wof:hierarchy":[{"continent_id":102191581,"country_id":85633135,"county_id":1713305685,"localadmin_id":1713312913,"locality_id":1259501177,"region_id":85683055}],"wof:id":1259501177,"wof:lang_x_official":["est"],"wof:lang_x_spoken":["est"],"wof:lastmodified":1596661505,"wof:name":"Sookaera-Metsanurga","wof:parent_id":1713312913,"wof:placetype":"locality","wof:repo":"whosonfirst-data-admin-ee","wof:superseded_by":[],"wof:supersedes":[],"wof:tags":[]},"bbox":[24.76694,59.26528,24.76694,59.26528],"geometry":{"coordinates":[24.76694,59.26528],"type":"Point"}}