{"id":1276553573,"type":"Feature","properties":{"edtf:cessation":"uuuu","edtf:inception":"uuuu","geom:area":0,"geom:area_square_m":0,"geom:bbox":"26.08556,58.99889,26.08556,58.99889","geom:latitude":58.99889,"geom:longitude":26.08556,"gn:admin1_code":"4.0","gn:admin2_code":"255.0","gn:admin3_code":"6398.0","gn:asciiname":"Puhmu","gn:cc2":"EE","gn:country_code":"EE","gn:dem":91,"gn:feature_class":"P","gn:feature_code":"PPL","gn:geonameid":589305,"gn:latitude":58.99889,"gn:longitude":26.08556,"gn:modification_date":"2017-11-25","gn:name":"Puhmu","gn:population":0,"gn:timezone":"Europe/Tallinn","iso:country":"EE","lbl:bbox":"26.06556,58.97889,26.10556,59.01889","lbl:max_zoom":18,"lbl:min_zoom":13.5,"mz:hierarchy_label":1,"mz:is_current":1,"mz:min_zoom":12,"name:est_x_preferred":["Puhmu"],"name:hye_x_preferred":["Պուհմու"],"name:pol_x_preferred":["Puhmu"],"name:spa_x_preferred":["Puhmu"],"name:ukr_x_preferred":["Пугму"],"name:und_x_variant":["Pukhmu"],"name:vol_x_preferred":["Puhmu"],"src:geom":"geonames","wof:belongsto":[85683031,102191581,1713306997,85633135,1713305765],"wof:breaches":[],"wof:concordances":{"gn:id":589305,"wk:page":"Puhmu"},"wof:coterminous":[1713306997],"wof:country":"EE","wof:geomhash":"2b24bf6b8d6e45af684657e6956e95e6","wof:hierarchy":[{"continent_id":102191581,"country_id":85633135,"county_id":1713305765,"localadmin_id":1713306997,"locality_id":1276553573,"region_id":85683031}],"wof:id":1276553573,"wof:lang_x_official":["est"],"wof:lang_x_spoken":["est"],"wof:lastmodified":1596676650,"wof:name":"Puhmu","wof:parent_id":1713306997,"wof:placetype":"locality","wof:repo":"whosonfirst-data-admin-ee","wof:superseded_by":[],"wof:supersedes":[],"wof:tags":[]},"bbox":[26.08556,58.99889,26.08556,58.99889],"geometry":{"coordinates":[26.08556,58.99889],"type":"Point"}}