{"id":1226527999,"type":"Feature","properties":{"edtf:cessation":"uuuu","edtf:inception":"uuuu","geom:area":0,"geom:area_square_m":0,"geom:bbox":"26.25444,59.3925,26.25444,59.3925","geom:latitude":59.3925,"geom:longitude":26.25444,"gn:admin1_code":"8.0","gn:admin2_code":"661.0","gn:admin3_code":"9196.0","gn:asciiname":"Arumetsa","gn:country_code":"EE","gn:dem":90,"gn:feature_class":"P","gn:feature_code":"PPL","gn:geonameid":8619597,"gn:latitude":59.3925,"gn:longitude":26.25444,"gn:modification_date":"2017-11-25","gn:name":"Arumetsa","gn:population":0,"gn:timezone":"Europe/Tallinn","iso:country":"EE","lbl:bbox":"26.23444,59.3725,26.27444,59.4125","lbl:max_zoom":18,"lbl:min_zoom":13.5,"mz:hierarchy_label":1,"mz:is_current":1,"mz:min_zoom":12,"name:ceb_x_preferred":["Arumetsa"],"name:est_x_preferred":["Arumetsa"],"name:fra_x_preferred":["Arumetsa"],"name:hye_x_preferred":["Առումեցա"],"name:pol_x_preferred":["Arumetsa"],"name:spa_x_preferred":["Arumetsa"],"name:swe_x_preferred":["Arumetsa"],"name:ukr_x_preferred":["Аруметса"],"name:und_x_variant":["Aru"],"name:vol_x_preferred":["Arumetsa"],"src:geom":"geonames","wof:belongsto":[85683049,102191581,1713314533,85633135,1713305719],"wof:breaches":[],"wof:concordances":{"gn:id":8619597},"wof:country":"EE","wof:geomhash":"0d53bc244efe81f7297e2c83f91929f2","wof:hierarchy":[{"continent_id":102191581,"country_id":85633135,"county_id":1713305719,"localadmin_id":1713314533,"locality_id":1226527999,"region_id":85683049}],"wof:id":1226527999,"wof:lang_x_official":["est"],"wof:lang_x_spoken":["est"],"wof:lastmodified":1596676670,"wof:name":"Arumetsa","wof:parent_id":1713314533,"wof:placetype":"locality","wof:repo":"whosonfirst-data-admin-ee","wof:superseded_by":[],"wof:supersedes":[],"wof:tags":[]},"bbox":[26.25444,59.3925,26.25444,59.3925],"geometry":{"coordinates":[26.25444,59.3925],"type":"Point"}}