{"id":1126037683,"type":"Feature","properties":{"edtf:cessation":"uuuu","edtf:inception":"uuuu","geom:area":0,"geom:area_square_m":0,"geom:bbox":"26.98694,57.88583,26.98694,57.88583","geom:latitude":57.88583,"geom:longitude":26.98694,"gn:country":"EE","gn:fcode":"PPL","gn:population":157,"iso:country":"EE","lbl:bbox":"26.96694,57.86583,27.00694,57.90583","lbl:latitude":57.88583,"lbl:longitude":26.98694,"lbl:max_zoom":18,"lbl:min_zoom":13,"mz:hierarchy_label":1,"mz:is_current":1,"mz:min_zoom":11,"mz:note":"Quattroshapes Point Gazetteer import 20170519","name:bul_x_preferred":["Лосу"],"name:ceb_x_preferred":["Loosu"],"name:eng_x_preferred":["Loosu"],"name:est_x_preferred":["Loosu"],"name:hye_x_preferred":["Լոոսու"],"name:nld_x_preferred":["Loosu"],"name:pol_x_preferred":["Loosu"],"name:spa_x_preferred":["Loosu"],"name:swe_x_preferred":["Loosu"],"name:ukr_x_preferred":["Лоосу"],"name:vol_x_preferred":["Loosu"],"name:vro_x_preferred":["Loosu"],"qs_pg:aaroncc":"EE","qs_pg:gn_country":"EE","qs_pg:gn_fcode":"PPL","qs_pg:gn_id":794314,"qs_pg:gn_pop":157,"qs_pg:name":"Loosu","qs_pg:name_adm0":"Eesti","qs_pg:name_adm1":"Võrumaa","qs_pg:photos_9k":1,"qs_pg:photos_9r":1,"qs_pg:photos_all":1,"qs_pg:photos_sr":0,"qs_pg:pop_sr":1,"qs_pg:qs_id":966801,"qs_pg:qs_pg_placetype":"locality","qs_pg:qs_pg_placetype_gp":"Town","qs_pg:woe_adm0":23424805,"qs_pg:woe_id":843765,"src:geom":"qs_pg","src:lbl_centroid":"qs_pg","src:population":"geonames","woe:adm0_id":23424805,"woe:name_adm0":"Eesti","woe:name_adm1":"Võrumaa","woe:placetype":"Town","wof:belongsto":[85682937,102191581,1713316475,85633135,1713305633],"wof:breaches":[],"wof:concordances":{"gn:id":794314,"gp:id":843765,"qs_pg:id":966801,"wd:id":"Q3453994"},"wof:coterminous":[1713316475],"wof:country":"EE","wof:created":1497301899,"wof:geomhash":"6d0f023183172b921bb0c0c564df5f6d","wof:hierarchy":[{"continent_id":102191581,"country_id":85633135,"county_id":1713305633,"localadmin_id":1713316475,"locality_id":1126037683,"region_id":85682937}],"wof:id":1126037683,"wof:lang_x_official":["est"],"wof:lang_x_spoken":["est"],"wof:lastmodified":1596660420,"wof:name":"Loosu","wof:parent_id":1713316475,"wof:placetype":"locality","wof:population":157,"wof:population_rank":1,"wof:repo":"whosonfirst-data-admin-ee","wof:superseded_by":[],"wof:supersedes":[],"wof:tags":[]},"bbox":[26.98694,57.88583,26.98694,57.88583],"geometry":{"coordinates":[26.98694,57.88583],"type":"Point"}}