{"id":1277163745,"type":"Feature","properties":{"edtf:cessation":"uuuu","edtf:inception":"uuuu","geom:area":0,"geom:area_square_m":0,"geom:bbox":"24.14889,58.93,24.14889,58.93","geom:latitude":58.93,"geom:longitude":24.14889,"gn:admin1_code":"13.0","gn:admin2_code":"503.0","gn:admin3_code":"8232.0","gn:asciiname":"Maidla","gn:country_code":"EE","gn:dem":40,"gn:feature_class":"P","gn:feature_code":"PPL","gn:geonameid":590375,"gn:latitude":58.93,"gn:longitude":24.14889,"gn:modification_date":"2017-11-25","gn:name":"Maidla","gn:population":0,"gn:timezone":"Europe/Tallinn","iso:country":"EE","lbl:bbox":"24.12889,58.91,24.16889,58.95","lbl:max_zoom":18,"lbl:min_zoom":13.5,"mz:hierarchy_label":1,"mz:is_current":1,"mz:min_zoom":12,"name:ceb_x_preferred":["Maidla"],"name:est_x_preferred":["Maidla"],"name:hye_x_preferred":["Մաիդլա"],"name:nld_x_preferred":["Maidla"],"name:pol_x_preferred":["Maidla"],"name:ron_x_preferred":["Maidla"],"name:rus_x_preferred":["Майдла"],"name:sco_x_preferred":["Maidla"],"name:swe_x_preferred":["Maidla"],"name:ukr_x_preferred":["Майдла"],"name:und_x_variant":["Maydla"],"name:vol_x_preferred":["Maidla"],"src:geom":"geonames","wof:belongsto":[85683013,102191581,1713313405,85633135,1713305747],"wof:breaches":[],"wof:concordances":{"gn:id":590375},"wof:coterminous":[1713313405],"wof:country":"EE","wof:geomhash":"dcc0438b50e3df6f95340796de1f625f","wof:hierarchy":[{"continent_id":102191581,"country_id":85633135,"county_id":1713305747,"localadmin_id":1713313405,"locality_id":1277163745,"region_id":85683013}],"wof:id":1277163745,"wof:lang_x_official":["est"],"wof:lang_x_spoken":["est"],"wof:lastmodified":1596662850,"wof:name":"Maidla","wof:parent_id":1713313405,"wof:placetype":"locality","wof:repo":"whosonfirst-data-admin-ee","wof:superseded_by":[],"wof:supersedes":[],"wof:tags":[]},"bbox":[24.14889,58.93,24.14889,58.93],"geometry":{"coordinates":[24.14889,58.93],"type":"Point"}}