{"id":1260253461,"type":"Feature","properties":{"edtf:cessation":"uuuu","edtf:inception":"uuuu","geom:area":0,"geom:area_square_m":0,"geom:bbox":"22.04778,58.34111,22.04778,58.34111","geom:latitude":58.34111,"geom:longitude":22.04778,"gn:admin1_code":"14.0","gn:admin2_code":"714.0","gn:admin3_code":"7088.0","gn:asciiname":"Rootsikuela","gn:country_code":"EE","gn:dem":14,"gn:feature_class":"P","gn:feature_code":"PPL","gn:geonameid":588956,"gn:latitude":58.34111,"gn:longitude":22.04778,"gn:modification_date":"2017-11-25","gn:name":"Rootsiküla","gn:population":0,"gn:timezone":"Europe/Tallinn","iso:country":"EE","lbl:bbox":"22.02778,58.32111,22.06778,58.36111","lbl:max_zoom":18,"lbl:min_zoom":13.5,"mz:hierarchy_label":1,"mz:is_current":1,"mz:min_zoom":12,"name:deu_x_preferred":["Rootsiküla"],"name:est_x_preferred":["Rootsiküla"],"name:hye_x_preferred":["Ռոոցիկյուլա"],"name:pol_x_preferred":["Rootsiküla"],"name:spa_x_preferred":["Rootsiküla"],"name:swe_x_preferred":["Rootsiküla"],"name:und_x_variant":["Myza Rotsikyula","Rootsiküla Asundus","Rotsikyula"],"name:vol_x_preferred":["Rootsiküla"],"src:geom":"geonames","wof:belongsto":[85682947,102191581,1713307065,85633135,1713305627],"wof:breaches":[],"wof:concordances":{"gn:id":588956,"wk:page":"Rootsik%C3%BCla%2C_Saare_County"},"wof:coterminous":[1713307065],"wof:country":"EE","wof:geomhash":"a8812517c42bca2cf4ea499aa2d13424","wof:hierarchy":[{"continent_id":102191581,"country_id":85633135,"county_id":1713305627,"localadmin_id":1713307065,"locality_id":1260253461,"region_id":85682947}],"wof:id":1260253461,"wof:lang_x_official":["est"],"wof:lang_x_spoken":["est"],"wof:lastmodified":1596674910,"wof:name":"Rootsikuela","wof:parent_id":1713307065,"wof:placetype":"locality","wof:repo":"whosonfirst-data-admin-ee","wof:superseded_by":[],"wof:supersedes":[],"wof:tags":[]},"bbox":[22.04778,58.34111,22.04778,58.34111],"geometry":{"coordinates":[22.04778,58.34111],"type":"Point"}}