{"id":1225958479,"type":"Feature","properties":{"edtf:cessation":"uuuu","edtf:inception":"uuuu","geom:area":0,"geom:area_square_m":0,"geom:bbox":"24.12778,59.28833,24.12778,59.28833","geom:latitude":59.28833,"geom:longitude":24.12778,"gn:admin1_code":"1.0","gn:admin2_code":"431.0","gn:admin3_code":"4722.0","gn:asciiname":"Madise","gn:country_code":"EE","gn:dem":17,"gn:feature_class":"P","gn:feature_code":"PPL","gn:geonameid":8618916,"gn:latitude":59.28833,"gn:longitude":24.12778,"gn:modification_date":"2017-11-25","gn:name":"Madise","gn:population":0,"gn:timezone":"Europe/Tallinn","iso:country":"EE","lbl:bbox":"24.10778,59.26833,24.14778,59.30833","lbl:max_zoom":18,"lbl:min_zoom":13.5,"mz:hierarchy_label":1,"mz:is_current":1,"mz:min_zoom":12,"name:est_x_preferred":["Madise"],"name:fra_x_preferred":["Madise"],"name:hye_x_preferred":["Մադիսե"],"name:pol_x_preferred":["Madise"],"name:spa_x_preferred":["Madise"],"name:swe_x_preferred":["Madise"],"name:ukr_x_preferred":["Мадізе"],"name:und_x_variant":["Rannaküla"],"name:urd_x_preferred":["میڈیسی"],"name:vol_x_preferred":["Madise"],"src:geom":"geonames","wof:belongsto":[85683055,102191581,1713307795,85633135,1713305737],"wof:breaches":[],"wof:concordances":{"gn:id":8618916,"wk:page":"Madise%2C_Harju_County"},"wof:coterminous":[1713307795],"wof:country":"EE","wof:geomhash":"97eb9d9d41ca996fc9d5dcf2ecdd2ac4","wof:hierarchy":[{"continent_id":102191581,"country_id":85633135,"county_id":1713305737,"localadmin_id":1713307795,"locality_id":1225958479,"region_id":85683055}],"wof:id":1225958479,"wof:lang_x_official":["est"],"wof:lang_x_spoken":["est"],"wof:lastmodified":1596663321,"wof:name":"Madise","wof:parent_id":1713307795,"wof:placetype":"locality","wof:repo":"whosonfirst-data-admin-ee","wof:superseded_by":[],"wof:supersedes":[],"wof:tags":[]},"bbox":[24.12778,59.28833,24.12778,59.28833],"geometry":{"coordinates":[24.12778,59.28833],"type":"Point"}}