{"id":1260269197,"type":"Feature","properties":{"edtf:cessation":"uuuu","edtf:inception":"uuuu","geom:area":0,"geom:area_square_m":0,"geom:bbox":"24.98194,59.1125,24.98194,59.1125","geom:latitude":59.1125,"geom:longitude":24.98194,"gn:admin1_code":"13.0","gn:admin2_code":"668.0","gn:admin3_code":"4733.0","gn:asciiname":"Mahtra-Saunakuela","gn:country_code":"EE","gn:dem":74,"gn:feature_class":"P","gn:feature_code":"PPL","gn:geonameid":8618356,"gn:latitude":59.1125,"gn:longitude":24.98194,"gn:modification_date":"2017-11-25","gn:name":"Mahtra-Saunak체la","gn:population":0,"gn:timezone":"Europe/Tallinn","iso:country":"EE","lbl:bbox":"24.96194,59.0925,25.00194,59.1325","lbl:max_zoom":18,"lbl:min_zoom":13.5,"mz:hierarchy_label":1,"mz:is_current":1,"mz:min_zoom":12,"name:und_x_variant":["Mahtra-Saunak체la","V채ikem천isa"],"src:geom":"geonames","wof:belongsto":[85683013,102191581,1713313661,85633135,1713305711],"wof:breaches":[],"wof:concordances":{"gn:id":8618356},"wof:country":"EE","wof:geomhash":"4b6ba77f16de9ea2a8ecd76ae827958c","wof:hierarchy":[{"continent_id":102191581,"country_id":85633135,"county_id":1713305711,"localadmin_id":1713313661,"locality_id":1260269197,"region_id":85683013}],"wof:id":1260269197,"wof:lang_x_official":["est"],"wof:lang_x_spoken":["est"],"wof:lastmodified":1596676719,"wof:name":"Mahtra-Saunakuela","wof:parent_id":1713313661,"wof:placetype":"locality","wof:repo":"whosonfirst-data-admin-ee","wof:superseded_by":[],"wof:supersedes":[],"wof:tags":[]},"bbox":[24.98194,59.1125,24.98194,59.1125],"geometry":{"coordinates":[24.98194,59.1125],"type":"Point"}}