{"id":1209379199,"type":"Feature","properties":{"edtf:cessation":"uuuu","edtf:inception":"uuuu","geom:area":0,"geom:area_square_m":0,"geom:bbox":"26.82417,57.89778,26.82417,57.89778","geom:latitude":57.89778,"geom:longitude":26.82417,"gn:admin1_code":"21.0","gn:admin2_code":"917.0","gn:admin3_code":"4373.0","gn:asciiname":"Lilli-Anne","gn:country_code":"EE","gn:dem":96,"gn:feature_class":"P","gn:feature_code":"PPL","gn:geonameid":794462,"gn:latitude":57.89778,"gn:longitude":26.82417,"gn:modification_date":"2017-11-25","gn:name":"Lilli-Anne","gn:population":0,"gn:timezone":"Europe/Tallinn","iso:country":"EE","lbl:bbox":"26.80417,57.87778,26.84417,57.91778","lbl:max_zoom":18,"lbl:min_zoom":13.5,"mz:hierarchy_label":1,"mz:is_current":1,"mz:min_zoom":12,"src:geom":"geonames","wof:belongsto":[85682937,102191581,1713316097,85633135,1713305633],"wof:breaches":[],"wof:concordances":{"gn:id":794462},"wof:coterminous":[1713316097],"wof:country":"EE","wof:geomhash":"bbd6c199b7dcafe26b26a2df4de0633b","wof:hierarchy":[{"continent_id":102191581,"country_id":85633135,"county_id":1713305633,"localadmin_id":1713316097,"locality_id":1209379199,"region_id":85682937}],"wof:id":1209379199,"wof:lang_x_official":["est"],"wof:lang_x_spoken":["est"],"wof:lastmodified":1596660401,"wof:name":"Lilli-Anne","wof:parent_id":1713316097,"wof:placetype":"locality","wof:repo":"whosonfirst-data-admin-ee","wof:superseded_by":[],"wof:supersedes":[],"wof:tags":[]},"bbox":[26.82417,57.89778,26.82417,57.89778],"geometry":{"coordinates":[26.82417,57.89778],"type":"Point"}}