{"id":1292980299,"type":"Feature","properties":{"edtf:cessation":"uuuu","edtf:inception":"uuuu","geom:area":0,"geom:area_square_m":0,"geom:bbox":"24.64083,59.10778,24.64083,59.10778","geom:latitude":59.10778,"geom:longitude":24.64083,"gn:admin1_code":"13.0","gn:admin2_code":"317.0","gn:admin3_code":"1079.0","gn:asciiname":"Adila","gn:cc2":"EE","gn:country_code":"EE","gn:dem":66,"gn:feature_class":"P","gn:feature_code":"PPL","gn:geonameid":592618,"gn:latitude":59.10778,"gn:longitude":24.64083,"gn:modification_date":"2017-11-25","gn:name":"Adila","gn:population":0,"gn:timezone":"Europe/Tallinn","iso:country":"EE","lbl:bbox":"24.62083,59.08778,24.66083,59.12778","lbl:max_zoom":18,"lbl:min_zoom":13.5,"mz:hierarchy_label":1,"mz:is_current":1,"mz:min_zoom":12,"name:est_x_preferred":["Adila"],"name:fas_x_preferred":["ادیلا"],"name:hye_x_preferred":["Ադիլա"],"name:pol_x_preferred":["Adila"],"name:rus_x_preferred":["Адила"],"name:sco_x_preferred":["Adila"],"name:spa_x_preferred":["Adila"],"name:und_x_variant":["Myza Adila"],"name:vol_x_preferred":["Adila"],"src:geom":"geonames","wof:belongsto":[85683013,102191581,1713314243,85633135,1713305707],"wof:breaches":[],"wof:concordances":{"gn:id":592618,"wk:page":"Adila"},"wof:coterminous":[1713314243],"wof:country":"EE","wof:geomhash":"10b7287726d9462f765dca5915e61341","wof:hierarchy":[{"continent_id":102191581,"country_id":85633135,"county_id":1713305707,"localadmin_id":1713314243,"locality_id":1292980299,"region_id":85683013}],"wof:id":1292980299,"wof:lang_x_official":["est"],"wof:lang_x_spoken":["est"],"wof:lastmodified":1596677034,"wof:name":"Adila","wof:parent_id":1713314243,"wof:placetype":"locality","wof:repo":"whosonfirst-data-admin-ee","wof:superseded_by":[],"wof:supersedes":[],"wof:tags":[]},"bbox":[24.64083,59.10778,24.64083,59.10778],"geometry":{"coordinates":[24.64083,59.10778],"type":"Point"}}