{"id":1293874329,"type":"Feature","properties":{"edtf:cessation":"uuuu","edtf:inception":"uuuu","geom:area":0,"geom:area_square_m":0,"geom:bbox":"26.41111,59.48972,26.41111,59.48972","geom:latitude":59.48972,"geom:longitude":26.41111,"gn:admin1_code":"8.0","gn:admin2_code":"903.0","gn:admin3_code":"7530.0","gn:asciiname":"Selja","gn:cc2":"EE","gn:country_code":"EE","gn:dem":61,"gn:feature_class":"P","gn:feature_code":"PPL","gn:geonameid":588725,"gn:latitude":59.48972,"gn:longitude":26.41111,"gn:modification_date":"2017-11-25","gn:name":"Selja","gn:population":0,"gn:timezone":"Europe/Tallinn","iso:country":"EE","lbl:bbox":"26.39111,59.46972,26.43111,59.50972","lbl:max_zoom":18,"lbl:min_zoom":13.5,"mz:hierarchy_label":1,"mz:is_current":1,"mz:min_zoom":12,"name:eng_x_preferred":["Selja"],"name:est_x_preferred":["Selja"],"name:hye_x_preferred":["Սելյա"],"name:pol_x_preferred":["Selja"],"name:rus_x_preferred":["Селья"],"name:und_x_variant":["Myza Sel’ya","Selja Asundus"],"name:vol_x_preferred":["Selja"],"src:geom":"geonames","wof:belongsto":[85683049,102191581,1713315237,85633135,1713305777],"wof:breaches":[],"wof:concordances":{"gn:id":588725,"wk:page":"Selja%2C_L%C3%A4%C3%A4ne-Viru_County"},"wof:coterminous":[1713315237],"wof:country":"EE","wof:geomhash":"0763bb587e2203a61262c5486ecd3854","wof:hierarchy":[{"continent_id":102191581,"country_id":85633135,"county_id":1713305777,"localadmin_id":1713315237,"locality_id":1293874329,"region_id":85683049}],"wof:id":1293874329,"wof:lang_x_official":["est"],"wof:lang_x_spoken":["est"],"wof:lastmodified":1596677938,"wof:name":"Selja","wof:parent_id":1713315237,"wof:placetype":"locality","wof:repo":"whosonfirst-data-admin-ee","wof:superseded_by":[],"wof:supersedes":[],"wof:tags":[]},"bbox":[26.41111,59.48972,26.41111,59.48972],"geometry":{"coordinates":[26.41111,59.48972],"type":"Point"}}