{"id":1259841259,"type":"Feature","properties":{"edtf:cessation":"uuuu","edtf:inception":"uuuu","geom:area":0,"geom:area_square_m":0,"geom:bbox":"25.74528,58.28639,25.74528,58.28639","geom:latitude":58.28639,"geom:longitude":25.74528,"gn:admin1_code":"20.0","gn:admin2_code":"899.0","gn:admin3_code":"4548.0","gn:asciiname":"Luiga","gn:country_code":"EE","gn:dem":101,"gn:feature_class":"P","gn:feature_code":"PPL","gn:geonameid":793937,"gn:latitude":58.28639,"gn:longitude":25.74528,"gn:modification_date":"2017-11-25","gn:name":"Luiga","gn:population":0,"gn:timezone":"Europe/Tallinn","iso:country":"EE","lbl:bbox":"25.72528,58.26639,25.76528,58.30639","lbl:max_zoom":18,"lbl:min_zoom":13.5,"mz:hierarchy_label":1,"mz:is_current":1,"mz:min_zoom":12,"src:geom":"geonames","wof:belongsto":[85682985,102191581,1713309763,85633135,1713305669],"wof:breaches":[],"wof:concordances":{"gn:id":793937},"wof:coterminous":[1713309763],"wof:country":"EE","wof:geomhash":"956b87934429e3436ddea8e163564f84","wof:hierarchy":[{"continent_id":102191581,"country_id":85633135,"county_id":1713305669,"localadmin_id":1713309763,"locality_id":1259841259,"region_id":85682985}],"wof:id":1259841259,"wof:lang_x_official":["est"],"wof:lang_x_spoken":["est"],"wof:lastmodified":1596661266,"wof:name":"Luiga","wof:parent_id":1713309763,"wof:placetype":"locality","wof:repo":"whosonfirst-data-admin-ee","wof:superseded_by":[],"wof:supersedes":[],"wof:tags":[]},"bbox":[25.74528,58.28639,25.74528,58.28639],"geometry":{"coordinates":[25.74528,58.28639],"type":"Point"}}