{"id":1343921267,"type":"Feature","properties":{"edtf:cessation":"uuuu","edtf:inception":"uuuu","geom:area":0,"geom:area_square_m":0,"geom:bbox":"26.78333,58.33333,26.78333,58.33333","geom:latitude":58.33333,"geom:longitude":26.78333,"gn:admin1_code":"18.0","gn:admin2_code":"283.0","gn:admin3_code":"7666.0","gn:asciiname":"Pataste","gn:country_code":"EE","gn:dem":32,"gn:feature_class":"P","gn:feature_code":"PPL","gn:geonameid":589560,"gn:latitude":58.33333,"gn:longitude":26.78333,"gn:modification_date":"2017-11-25","gn:name":"Pataste","gn:population":0,"gn:timezone":"Europe/Tallinn","iso:country":"EE","lbl:bbox":"26.76333,58.31333,26.80333,58.35333","lbl:max_zoom":18,"lbl:min_zoom":13.5,"mz:hierarchy_label":1,"mz:is_current":1,"mz:min_zoom":12,"src:geom":"geonames","wof:belongsto":[85682995,102191581,1713313891,85633135,1713305717],"wof:breaches":[],"wof:concordances":{"gn:id":589560},"wof:country":"EE","wof:geomhash":"5abf4fc9304311e8d8491cc5666709aa","wof:hierarchy":[{"continent_id":102191581,"country_id":85633135,"county_id":1713305717,"localadmin_id":1713313891,"locality_id":1343921267,"region_id":85682995}],"wof:id":1343921267,"wof:lang_x_official":["est"],"wof:lang_x_spoken":["est"],"wof:lastmodified":1596676692,"wof:name":"Pataste","wof:parent_id":1713313891,"wof:placetype":"locality","wof:repo":"whosonfirst-data-admin-ee","wof:superseded_by":[],"wof:supersedes":[],"wof:tags":[]},"bbox":[26.78333,58.33333,26.78333,58.33333],"geometry":{"coordinates":[26.78333,58.33333],"type":"Point"}}