{"id":1260385809,"type":"Feature","properties":{"edtf:cessation":"uuuu","edtf:inception":"uuuu","geom:area":0,"geom:area_square_m":0,"geom:bbox":"23.82806,59.02639,23.82806,59.02639","geom:latitude":59.02639,"geom:longitude":23.82806,"gn:admin1_code":"7.0","gn:admin2_code":"441.0","gn:admin3_code":"2906.0","gn:asciiname":"Keedika","gn:country_code":"EE","gn:dem":41,"gn:feature_class":"P","gn:feature_code":"PPL","gn:geonameid":794876,"gn:latitude":59.02639,"gn:longitude":23.82806,"gn:modification_date":"2017-11-25","gn:name":"Keedika","gn:population":0,"gn:timezone":"Europe/Tallinn","iso:country":"EE","lbl:bbox":"23.80806,59.00639,23.84806,59.04639","lbl:max_zoom":18,"lbl:min_zoom":13.5,"mz:hierarchy_label":1,"mz:is_current":1,"mz:min_zoom":12,"name:est_x_preferred":["Keedika"],"name:fra_x_preferred":["Keedika"],"name:hye_x_preferred":["Կեեդիկա"],"name:pol_x_preferred":["Keedika"],"name:spa_x_preferred":["Keedika"],"name:ukr_x_preferred":["Кеедіка"],"name:vol_x_preferred":["Keedika"],"src:geom":"geonames","wof:belongsto":[85683001,102191581,1713308875,85633135,1713305701],"wof:breaches":[],"wof:concordances":{"gn:id":794876,"wk:page":"Keedika"},"wof:coterminous":[1713308875],"wof:country":"EE","wof:geomhash":"495b30652bd1c7cae13235e2b71106bf","wof:hierarchy":[{"continent_id":102191581,"country_id":85633135,"county_id":1713305701,"localadmin_id":1713308875,"locality_id":1260385809,"region_id":85683001}],"wof:id":1260385809,"wof:lang_x_official":["est"],"wof:lang_x_spoken":["est"],"wof:lastmodified":1596677426,"wof:name":"Keedika","wof:parent_id":1713308875,"wof:placetype":"locality","wof:repo":"whosonfirst-data-admin-ee","wof:superseded_by":[],"wof:supersedes":[],"wof:tags":[]},"bbox":[23.82806,59.02639,23.82806,59.02639],"geometry":{"coordinates":[23.82806,59.02639],"type":"Point"}}