{"id":1259554515,"type":"Feature","properties":{"edtf:cessation":"uuuu","edtf:inception":"uuuu","geom:area":0,"geom:area_square_m":0,"geom:bbox":"22.46444,58.43139,22.46444,58.43139","geom:latitude":58.43139,"geom:longitude":22.46444,"gn:admin1_code":"14.0","gn:admin2_code":"714.0","gn:admin3_code":"8526.0","gn:asciiname":"Toru","gn:country_code":"EE","gn:dem":26,"gn:feature_class":"P","gn:feature_code":"PPL","gn:geonameid":588206,"gn:latitude":58.43139,"gn:longitude":22.46444,"gn:modification_date":"2017-11-25","gn:name":"Tõru","gn:population":0,"gn:timezone":"Europe/Tallinn","iso:country":"EE","lbl:bbox":"22.44444,58.41139,22.48444,58.45139","lbl:max_zoom":18,"lbl:min_zoom":13.5,"mz:hierarchy_label":1,"mz:is_current":1,"mz:min_zoom":12,"name:deu_x_preferred":["Tõru"],"name:est_x_preferred":["Tõru küla"],"name:fra_x_preferred":["Tõru"],"name:hye_x_preferred":["Տիռու"],"name:pol_x_preferred":["Tõru"],"name:spa_x_preferred":["Tõru"],"name:ukr_x_preferred":["Тиру"],"name:und_x_variant":["Tyru"],"name:vol_x_preferred":["Tõru küla"],"src:geom":"geonames","wof:belongsto":[85682947,102191581,1713308365,85633135,1713305627],"wof:breaches":[],"wof:concordances":{"gn:id":588206,"wk:page":"T%C3%B5ru"},"wof:coterminous":[1713308365],"wof:country":"EE","wof:geomhash":"c8437700881ac61d7c823a17cb7dff2a","wof:hierarchy":[{"continent_id":102191581,"country_id":85633135,"county_id":1713305627,"localadmin_id":1713308365,"locality_id":1259554515,"region_id":85682947}],"wof:id":1259554515,"wof:lang_x_official":["est"],"wof:lang_x_spoken":["est"],"wof:lastmodified":1596674914,"wof:name":"Toru","wof:parent_id":1713308365,"wof:placetype":"locality","wof:repo":"whosonfirst-data-admin-ee","wof:superseded_by":[],"wof:supersedes":[],"wof:tags":[]},"bbox":[22.46444,58.43139,22.46444,58.43139],"geometry":{"coordinates":[22.46444,58.43139],"type":"Point"}}