{"id":1276956767,"type":"Feature","properties":{"edtf:cessation":"uuuu","edtf:inception":"uuuu","geom:area":0,"geom:area_square_m":0,"geom:bbox":"24.80667,58.67278,24.80667,58.67278","geom:latitude":58.67278,"geom:longitude":24.80667,"gn:admin1_code":"11.0","gn:admin2_code":"638.0","gn:admin3_code":"7661.0","gn:asciiname":"Sohlu","gn:country_code":"EE","gn:dem":48,"gn:feature_class":"P","gn:feature_code":"PPL","gn:geonameid":591743,"gn:latitude":58.67278,"gn:longitude":24.80667,"gn:modification_date":"2017-11-25","gn:name":"Sohlu","gn:population":0,"gn:timezone":"Europe/Tallinn","iso:country":"EE","lbl:bbox":"24.78667,58.65278,24.82667,58.69278","lbl:max_zoom":18,"lbl:min_zoom":13.5,"mz:hierarchy_label":1,"mz:is_current":1,"mz:min_zoom":12,"name:est_x_preferred":["Sohlu"],"name:hye_x_preferred":["Սոհլու"],"name:pol_x_preferred":["Sohlu"],"name:spa_x_preferred":["Sohlu"],"name:und_x_variant":["Kaysma-Sokhlu","Kaisma-Sohlu"],"name:vol_x_preferred":["Sohlu"],"src:geom":"geonames","wof:belongsto":[85682981,102191581,1713309649,85633135,1713305733],"wof:breaches":[],"wof:concordances":{"gn:id":591743,"wk:page":"Sohlu"},"wof:coterminous":[1713309649],"wof:country":"EE","wof:geomhash":"fd714e68bb2e0b7dbf5f9496d0bc3ba5","wof:hierarchy":[{"continent_id":102191581,"country_id":85633135,"county_id":1713305733,"localadmin_id":1713309649,"locality_id":1276956767,"region_id":85682981}],"wof:id":1276956767,"wof:lang_x_official":["est"],"wof:lang_x_spoken":["est"],"wof:lastmodified":1596663430,"wof:name":"Sohlu","wof:parent_id":1713309649,"wof:placetype":"locality","wof:repo":"whosonfirst-data-admin-ee","wof:superseded_by":[],"wof:supersedes":[],"wof:tags":[]},"bbox":[24.80667,58.67278,24.80667,58.67278],"geometry":{"coordinates":[24.80667,58.67278],"type":"Point"}}