{"id":1260043231,"type":"Feature","properties":{"edtf:cessation":"uuuu","edtf:inception":"uuuu","geom:area":0,"geom:area_square_m":0,"geom:bbox":"26.80611,58.20917,26.80611,58.20917","geom:latitude":58.20917,"geom:longitude":26.80611,"gn:admin1_code":"18.0","gn:admin2_code":"283.0","gn:admin3_code":"7642.0","gn:asciiname":"Maidla","gn:country_code":"EE","gn:dem":73,"gn:feature_class":"P","gn:feature_code":"PPL","gn:geonameid":590376,"gn:latitude":58.20917,"gn:longitude":26.80611,"gn:modification_date":"2017-11-25","gn:name":"Maidla","gn:population":0,"gn:timezone":"Europe/Tallinn","iso:country":"EE","lbl:bbox":"26.78611,58.18917,26.82611,58.22917","lbl:max_zoom":18,"lbl:min_zoom":13.5,"mz:hierarchy_label":1,"mz:is_current":1,"mz:min_zoom":12,"name:ceb_x_preferred":["Maidla"],"name:est_x_preferred":["Maidla"],"name:hye_x_preferred":["Մաիդլա"],"name:nld_x_preferred":["Maidla"],"name:pol_x_preferred":["Maidla"],"name:ron_x_preferred":["Maidla"],"name:rus_x_preferred":["Майдла"],"name:sco_x_preferred":["Maidla"],"name:swe_x_preferred":["Maidla"],"name:ukr_x_preferred":["Майдла"],"name:und_x_variant":["Maidla Asundus"],"name:vol_x_preferred":["Maidla"],"src:geom":"geonames","wof:belongsto":[85682995,102191581,1713312381,85633135,1713305717],"wof:breaches":[],"wof:concordances":{"gn:id":590376},"wof:country":"EE","wof:geomhash":"d287623073da710bedb5e71d66f4cbb0","wof:hierarchy":[{"continent_id":102191581,"country_id":85633135,"county_id":1713305717,"localadmin_id":1713312381,"locality_id":1260043231,"region_id":85682995}],"wof:id":1260043231,"wof:lang_x_official":["est"],"wof:lang_x_spoken":["est"],"wof:lastmodified":1596676687,"wof:name":"Maidla","wof:parent_id":1713312381,"wof:placetype":"locality","wof:repo":"whosonfirst-data-admin-ee","wof:superseded_by":[],"wof:supersedes":[],"wof:tags":[]},"bbox":[26.80611,58.20917,26.80611,58.20917],"geometry":{"coordinates":[26.80611,58.20917],"type":"Point"}}