{"id":1344034865,"type":"Feature","properties":{"edtf:cessation":"uuuu","edtf:inception":"uuuu","geom:area":0,"geom:area_square_m":0,"geom:bbox":"27.23028,57.99778,27.23028,57.99778","geom:latitude":57.99778,"geom:longitude":27.23028,"gn:admin1_code":"12.0","gn:admin2_code":"708.0","gn:admin3_code":"7981.0","gn:asciiname":"Soohara","gn:cc2":"EE","gn:country_code":"EE","gn:dem":62,"gn:feature_class":"P","gn:feature_code":"PPL","gn:geonameid":588619,"gn:latitude":57.99778,"gn:longitude":27.23028,"gn:modification_date":"2017-11-25","gn:name":"Soohara","gn:population":0,"gn:timezone":"Europe/Tallinn","iso:country":"EE","lbl:bbox":"27.21028,57.97778,27.25028,58.01778","lbl:max_zoom":18,"lbl:min_zoom":13.5,"mz:hierarchy_label":1,"mz:is_current":1,"mz:min_zoom":12,"name:est_x_preferred":["Soohara"],"name:hye_x_preferred":["Սոոհառա"],"name:pol_x_preferred":["Soohara"],"name:spa_x_preferred":["Soohara"],"name:ukr_x_preferred":["Соохара"],"name:und_x_variant":["Sokhara"],"name:vol_x_preferred":["Soohara"],"src:geom":"geonames","wof:belongsto":[85682955,102191581,1713310937,85633135,1713305793],"wof:breaches":[],"wof:concordances":{"gn:id":588619,"wk:page":"Soohara"},"wof:coterminous":[1713310873],"wof:country":"EE","wof:geomhash":"000dffbe2ff9b74a73b3da6a9dcb1ae1","wof:hierarchy":[{"continent_id":102191581,"country_id":85633135,"county_id":1713305793,"localadmin_id":1713310937,"locality_id":1344034865,"region_id":85682955}],"wof:id":1344034865,"wof:lang_x_official":["est"],"wof:lang_x_spoken":["est"],"wof:lastmodified":1596677003,"wof:name":"Soohara","wof:parent_id":1713310937,"wof:placetype":"locality","wof:repo":"whosonfirst-data-admin-ee","wof:superseded_by":[],"wof:supersedes":[],"wof:tags":[]},"bbox":[27.23028,57.99778,27.23028,57.99778],"geometry":{"coordinates":[27.23028,57.99778],"type":"Point"}}