{"id":1327492399,"type":"Feature","properties":{"edtf:cessation":"uuuu","edtf:inception":"uuuu","geom:area":0,"geom:area_square_m":0,"geom:bbox":"27.26417,57.83583,27.26417,57.83583","geom:latitude":57.83583,"geom:longitude":27.26417,"gn:admin1_code":"21.0","gn:admin2_code":"917.0","gn:admin3_code":"5766.0","gn:asciiname":"Pille","gn:country_code":"EE","gn:dem":93,"gn:feature_class":"P","gn:feature_code":"PPL","gn:geonameid":8620162,"gn:latitude":57.83583,"gn:longitude":27.26417,"gn:modification_date":"2017-11-25","gn:name":"Pille","gn:population":0,"gn:timezone":"Europe/Tallinn","iso:country":"EE","lbl:bbox":"27.24417,57.81583,27.28417,57.85583","lbl:max_zoom":18,"lbl:min_zoom":13.5,"mz:hierarchy_label":1,"mz:is_current":1,"mz:min_zoom":12,"name:est_x_preferred":["Pille"],"name:hye_x_preferred":["Պիլլե"],"name:spa_x_preferred":["Pille"],"name:swe_x_preferred":["Pille"],"name:ukr_x_preferred":["Пілле"],"name:vol_x_preferred":["Pille"],"src:geom":"geonames","wof:belongsto":[85682937,102191581,1713315481,85633135,1713305633],"wof:breaches":[],"wof:concordances":{"gn:id":8620162},"wof:country":"EE","wof:geomhash":"7f16db24775b3b627326419ed8414e5a","wof:hierarchy":[{"continent_id":102191581,"country_id":85633135,"county_id":1713305633,"localadmin_id":1713315481,"locality_id":1327492399,"region_id":85682937}],"wof:id":1327492399,"wof:lang_x_official":["est"],"wof:lang_x_spoken":["est"],"wof:lastmodified":1596660418,"wof:name":"Pille","wof:parent_id":1713315481,"wof:placetype":"locality","wof:repo":"whosonfirst-data-admin-ee","wof:superseded_by":[],"wof:supersedes":[],"wof:tags":[]},"bbox":[27.26417,57.83583,27.26417,57.83583],"geometry":{"coordinates":[27.26417,57.83583],"type":"Point"}}