{"id":1309693463,"type":"Feature","properties":{"edtf:cessation":"uuuu","edtf:inception":"uuuu","geom:area":0,"geom:area_square_m":0,"geom:bbox":"24.4375,58.43361,24.4375,58.43361","geom:latitude":58.43361,"geom:longitude":24.4375,"gn:admin1_code":"11.0","gn:admin2_code":"624.0","gn:admin3_code":"4268.0","gn:asciiname":"Ullaste","gn:country_code":"EE","gn:dem":12,"gn:feature_class":"P","gn:feature_code":"PPL","gn:geonameid":588083,"gn:latitude":58.43361,"gn:longitude":24.4375,"gn:modification_date":"2017-11-25","gn:name":"Ullaste","gn:population":0,"gn:timezone":"Europe/Tallinn","iso:country":"EE","lbl:bbox":"24.4175,58.41361,24.4575,58.45361","lbl:max_zoom":18,"lbl:min_zoom":13.5,"mz:hierarchy_label":1,"mz:is_current":1,"mz:min_zoom":12,"name:deu_x_preferred":["Ullaste"],"name:est_x_preferred":["Ullaste"],"name:hye_x_preferred":["Ուլլաստե"],"name:nld_x_preferred":["Ullaste"],"name:pol_x_preferred":["Ullaste"],"name:spa_x_preferred":["Ullaste"],"name:ukr_x_preferred":["Улласте"],"name:und_x_variant":["Uliaste"],"name:vol_x_preferred":["Ullaste"],"src:geom":"geonames","wof:belongsto":[85682981,102191581,1713314217,85633135,1713305703],"wof:breaches":[],"wof:concordances":{"gn:id":588083},"wof:country":"EE","wof:geomhash":"483bae9fe6bbc0374f8fcc6e37f1657f","wof:hierarchy":[{"continent_id":102191581,"country_id":85633135,"county_id":1713305703,"localadmin_id":1713314217,"locality_id":1309693463,"region_id":85682981}],"wof:id":1309693463,"wof:lang_x_official":["est"],"wof:lang_x_spoken":["est"],"wof:lastmodified":1596677700,"wof:name":"Ullaste","wof:parent_id":1713314217,"wof:placetype":"locality","wof:repo":"whosonfirst-data-admin-ee","wof:superseded_by":[],"wof:supersedes":[],"wof:tags":[]},"bbox":[24.4375,58.43361,24.4375,58.43361],"geometry":{"coordinates":[24.4375,58.43361],"type":"Point"}}