{"id":1343427245,"type":"Feature","properties":{"edtf:cessation":"uuuu","edtf:inception":"uuuu","geom:area":0,"geom:area_square_m":0,"geom:bbox":"26.38611,58.36139,26.38611,58.36139","geom:latitude":58.36139,"geom:longitude":26.38611,"gn:admin1_code":"18.0","gn:admin2_code":"171.0","gn:admin3_code":"7208.0","gn:asciiname":"Teilma","gn:country_code":"EE","gn:dem":49,"gn:feature_class":"P","gn:feature_code":"PPL","gn:geonameid":793992,"gn:latitude":58.36139,"gn:longitude":26.38611,"gn:modification_date":"2017-11-25","gn:name":"Teilma","gn:population":0,"gn:timezone":"Europe/Tallinn","iso:country":"EE","lbl:bbox":"26.36611,58.34139,26.40611,58.38139","lbl:max_zoom":18,"lbl:min_zoom":13.5,"mz:hierarchy_label":1,"mz:is_current":1,"mz:min_zoom":12,"name:est_x_preferred":["Teilma"],"name:hye_x_preferred":["Տեիլմա"],"name:pol_x_preferred":["Teilma"],"name:spa_x_preferred":["Teilma"],"name:ukr_x_preferred":["Тейлма"],"name:vol_x_preferred":["Teilma"],"src:geom":"geonames","wof:belongsto":[85682995,102191581,1713310547,85633135,1713305757],"wof:breaches":[],"wof:concordances":{"gn:id":793992,"wk:page":"Teilma%2C_Tartu_County"},"wof:coterminous":[1713313865],"wof:country":"EE","wof:geomhash":"b9ccc7af78027a0ce5814c3209197134","wof:hierarchy":[{"continent_id":102191581,"country_id":85633135,"county_id":1713305757,"localadmin_id":1713310547,"locality_id":1343427245,"region_id":85682995}],"wof:id":1343427245,"wof:lang_x_official":["est"],"wof:lang_x_spoken":["est"],"wof:lastmodified":1596661914,"wof:name":"Teilma","wof:parent_id":1713310547,"wof:placetype":"locality","wof:repo":"whosonfirst-data-admin-ee","wof:superseded_by":[],"wof:supersedes":[],"wof:tags":[]},"bbox":[26.38611,58.36139,26.38611,58.36139],"geometry":{"coordinates":[26.38611,58.36139],"type":"Point"}}