{"id":1125768287,"type":"Feature","properties":{"edtf:cessation":"uuuu","edtf:inception":"uuuu","geom:area":0,"geom:area_square_m":0,"geom:bbox":"24.038085,59.383496,24.038085,59.383496","geom:latitude":59.383496,"geom:longitude":24.038085,"gn:country":null,"iso:country":"EE","lbl:bbox":"24.018085,59.363496,24.058085,59.403496","lbl:latitude":59.383496,"lbl:longitude":24.038085,"lbl:max_zoom":18,"lbl:min_zoom":13.5,"mz:hierarchy_label":1,"mz:is_current":1,"mz:is_funky":1,"mz:min_zoom":12,"mz:note":"Quattroshapes Point Gazetteer import 20170519","qs_pg:aaroncc":"EE","qs_pg:gn_country":null,"qs_pg:name":"V채ikek체la/Lillby","qs_pg:name_adm0":"Eesti","qs_pg:name_adm1":"Harjumaa","qs_pg:photos":24,"qs_pg:photos_1k":5,"qs_pg:photos_9k":1,"qs_pg:photos_9r":1,"qs_pg:photos_all":24,"qs_pg:photos_sr":1,"qs_pg:pop_sr":0,"qs_pg:qs_id":1258531,"qs_pg:qs_pg_placetype":"locality","qs_pg:qs_pg_placetype_gp":"Town","qs_pg:woe_adm0":23424805,"qs_pg:woe_id":29397810,"src:geom":"qs_pg","src:lbl_centroid":"qs_pg","woe:adm0_id":23424805,"woe:name_adm0":"Eesti","woe:name_adm1":"Harjumaa","woe:placetype":"Town","wof:belongsto":[85683055,102191581,1713307685,85633135,1713305737],"wof:breaches":[],"wof:concordances":{"gp:id":29397810,"qs_pg:id":1258531},"wof:country":"EE","wof:created":1497289974,"wof:geomhash":"3ea63873e7c2b7a09a1ea5a5382717e1","wof:hierarchy":[{"continent_id":102191581,"country_id":85633135,"county_id":1713305737,"localadmin_id":1713307685,"locality_id":1125768287,"region_id":85683055}],"wof:id":1125768287,"wof:lang_x_official":["est"],"wof:lang_x_spoken":["est"],"wof:lastmodified":1596663322,"wof:name":"V채ikek체la/Lillby","wof:parent_id":1713307685,"wof:placetype":"locality","wof:repo":"whosonfirst-data-admin-ee","wof:superseded_by":[],"wof:supersedes":[],"wof:tags":[]},"bbox":[24.038085,59.383496,24.038085,59.383496],"geometry":{"coordinates":[24.038085,59.383496],"type":"Point"}}