{"id":1326609349,"type":"Feature","properties":{"edtf:cessation":"uuuu","edtf:inception":"uuuu","geom:area":0,"geom:area_square_m":0,"geom:bbox":"24.82667,58.89389,24.82667,58.89389","geom:latitude":58.89389,"geom:longitude":24.82667,"gn:admin1_code":"13.0","gn:admin2_code":"293.0","gn:admin3_code":"4248.0","gn:asciiname":"Lellapere","gn:country_code":"EE","gn:dem":73,"gn:feature_class":"P","gn:feature_code":"PPL","gn:geonameid":795011,"gn:latitude":58.89389,"gn:longitude":24.82667,"gn:modification_date":"2017-11-25","gn:name":"Lellapere","gn:population":0,"gn:timezone":"Europe/Tallinn","iso:country":"EE","lbl:bbox":"24.80667,58.87389,24.84667,58.91389","lbl:max_zoom":18,"lbl:min_zoom":13.5,"mz:hierarchy_label":1,"mz:is_current":1,"mz:min_zoom":12,"name:est_x_preferred":["Lellapere"],"name:hye_x_preferred":["Լելապեռե"],"name:pol_x_preferred":["Lellapere"],"name:sco_x_preferred":["Lellapere"],"name:spa_x_preferred":["Lellapere"],"name:vol_x_preferred":["Lellapere"],"src:geom":"geonames","wof:belongsto":[85683013,102191581,1713314249,85633135,1713305713],"wof:breaches":[],"wof:concordances":{"gn:id":795011,"wk:page":"Lellapere"},"wof:coterminous":[1713314249],"wof:country":"EE","wof:geomhash":"333459a10db4b34b954cc69eaeed10f8","wof:hierarchy":[{"continent_id":102191581,"country_id":85633135,"county_id":1713305713,"localadmin_id":1713314249,"locality_id":1326609349,"region_id":85683013}],"wof:id":1326609349,"wof:lang_x_official":["est"],"wof:lang_x_spoken":["est"],"wof:lastmodified":1596676745,"wof:name":"Lellapere","wof:parent_id":1713314249,"wof:placetype":"locality","wof:repo":"whosonfirst-data-admin-ee","wof:superseded_by":[],"wof:supersedes":[],"wof:tags":[]},"bbox":[24.82667,58.89389,24.82667,58.89389],"geometry":{"coordinates":[24.82667,58.89389],"type":"Point"}}