{"id":1209626867,"type":"Feature","properties":{"edtf:cessation":"uuuu","edtf:inception":"uuuu","geom:area":0,"geom:area_square_m":0,"geom:bbox":"27.32444,59.12472,27.32444,59.12472","geom:latitude":59.12472,"geom:longitude":27.32444,"gn:admin1_code":"3.0","gn:admin2_code":"130.0","gn:admin3_code":"8578.0","gn:asciiname":"Kaleva","gn:country_code":"EE","gn:dem":63,"gn:feature_class":"P","gn:feature_code":"PPL","gn:geonameid":8619666,"gn:latitude":59.12472,"gn:longitude":27.32444,"gn:modification_date":"2017-11-25","gn:name":"Kaleva","gn:population":0,"gn:timezone":"Europe/Tallinn","iso:country":"EE","lbl:bbox":"27.30444,59.10472,27.34444,59.14472","lbl:max_zoom":18,"lbl:min_zoom":13.5,"mz:hierarchy_label":1,"mz:is_current":1,"mz:min_zoom":12,"name:ceb_x_preferred":["Kaleva"],"name:deu_x_preferred":["Kaleva"],"name:est_x_preferred":["Kaleva"],"name:fin_x_preferred":["Kaleva"],"name:fra_x_preferred":["Kaleva"],"name:nld_x_preferred":["Kaleva"],"name:por_x_preferred":["Kaleva"],"name:rus_x_preferred":["Калева"],"name:swe_x_preferred":["Kaleva"],"name:und_x_variant":["Terevere"],"src:geom":"geonames","wof:belongsto":[85683059,102191581,1713311995,85633135,1713305693],"wof:breaches":[],"wof:concordances":{"gn:id":8619666},"wof:country":"EE","wof:geomhash":"6718ceace6b4efe9d1872f3528c1497d","wof:hierarchy":[{"continent_id":102191581,"country_id":85633135,"county_id":1713305693,"localadmin_id":1713311995,"locality_id":1209626867,"region_id":85683059}],"wof:id":1209626867,"wof:lang_x_official":["est"],"wof:lang_x_spoken":["est"],"wof:lastmodified":1596660751,"wof:name":"Kaleva","wof:parent_id":1713311995,"wof:placetype":"locality","wof:repo":"whosonfirst-data-admin-ee","wof:superseded_by":[],"wof:supersedes":[],"wof:tags":[]},"bbox":[27.32444,59.12472,27.32444,59.12472],"geometry":{"coordinates":[27.32444,59.12472],"type":"Point"}}