{"id":1260087673,"type":"Feature","properties":{"edtf:cessation":"uuuu","edtf:inception":"uuuu","geom:area":0,"geom:area_square_m":0,"geom:bbox":"27.93333,59.36667,27.93333,59.36667","geom:latitude":59.36667,"geom:longitude":27.93333,"gn:admin1_code":"3.0","gn:admin2_code":"514.0","gn:admin3_code":"1833.0","gn:asciiname":"Repniku","gn:cc2":"EE","gn:country_code":"EE","gn:dem":34,"gn:feature_class":"P","gn:feature_code":"PPL","gn:geonameid":589050,"gn:latitude":59.36667,"gn:longitude":27.93333,"gn:modification_date":"2017-11-25","gn:name":"Repniku","gn:population":0,"gn:timezone":"Europe/Tallinn","iso:country":"EE","lbl:bbox":"27.91333,59.34667,27.95333,59.38667","lbl:max_zoom":18,"lbl:min_zoom":13.5,"mz:hierarchy_label":1,"mz:is_current":1,"mz:min_zoom":12,"name:und_x_variant":["Repniku Asundus","Repniku"],"src:geom":"geonames","wof:belongsto":[85683059,102191581,1713307631,85633135,1713305779],"wof:breaches":[],"wof:concordances":{"gn:id":589050},"wof:country":"EE","wof:geomhash":"3b1f6a5f4c3092fd1cf0e7f422dff33f","wof:hierarchy":[{"continent_id":102191581,"country_id":85633135,"county_id":1713305779,"localadmin_id":1713307631,"locality_id":1260087673,"region_id":85683059}],"wof:id":1260087673,"wof:lang_x_official":["est"],"wof:lang_x_spoken":["est"],"wof:lastmodified":1596677903,"wof:name":"Repniku","wof:parent_id":1713307631,"wof:placetype":"locality","wof:repo":"whosonfirst-data-admin-ee","wof:superseded_by":[],"wof:supersedes":[],"wof:tags":[]},"bbox":[27.93333,59.36667,27.93333,59.36667],"geometry":{"coordinates":[27.93333,59.36667],"type":"Point"}}