{
  "type": "Feature",
  "properties": {
    "iso:country":"FI",
    "name:fi_x_preferred_x_variant":[
        "\u00d6stersundom"
    ],
    "wof:name":"Ostersundom",
    "wof:placetype":"neighbourhood"
},
  "geometry": {"coordinates":[25.18844914612774,60.25659694519455],"type":"Point"}
}