{"id":1310117657,"type":"Feature","properties":{"edtf:cessation":"uuuu","edtf:inception":"uuuu","geom:area":0,"geom:area_square_m":0,"geom:bbox":"27.47472,59.19694,27.47472,59.19694","geom:latitude":59.19694,"geom:longitude":27.47472,"gn:admin1_code":"3.0","gn:admin2_code":"130.0","gn:admin3_code":"5677.0","gn:asciiname":"Ongassaare","gn:country_code":"EE","gn:dem":67,"gn:feature_class":"P","gn:feature_code":"PPL","gn:geonameid":793493,"gn:latitude":59.19694,"gn:longitude":27.47472,"gn:modification_date":"2017-11-25","gn:name":"Ongassaare","gn:population":0,"gn:timezone":"Europe/Tallinn","iso:country":"EE","lbl:bbox":"27.45472,59.17694,27.49472,59.21694","lbl:max_zoom":18,"lbl:min_zoom":13.5,"mz:hierarchy_label":1,"mz:is_current":1,"mz:min_zoom":12,"name:deu_x_preferred":["Ongassaare"],"name:est_x_preferred":["Ongassaare"],"name:fra_x_preferred":["Ongassaare"],"name:hye_x_preferred":["Օնգասաառե"],"name:nld_x_preferred":["Ongassaare"],"name:pol_x_preferred":["Ongassaare"],"name:spa_x_preferred":["Ongassaare"],"name:vol_x_preferred":["Ongassaare"],"name:zho_x_preferred":["翁加薩雷"],"src:geom":"geonames","wof:belongsto":[85683059,102191581,1713311647,85633135,1713305693],"wof:breaches":[],"wof:concordances":{"gn:id":793493,"wk:page":"Ongassaare"},"wof:coterminous":[1713311647],"wof:country":"EE","wof:geomhash":"ef603e43821e805aa987b1e541e4e97c","wof:hierarchy":[{"continent_id":102191581,"country_id":85633135,"county_id":1713305693,"localadmin_id":1713311647,"locality_id":1310117657,"region_id":85683059}],"wof:id":1310117657,"wof:lang_x_official":["est"],"wof:lang_x_spoken":["est"],"wof:lastmodified":1596660740,"wof:name":"Ongassaare","wof:parent_id":1713311647,"wof:placetype":"locality","wof:repo":"whosonfirst-data-admin-ee","wof:superseded_by":[],"wof:supersedes":[],"wof:tags":[]},"bbox":[27.47472,59.19694,27.47472,59.19694],"geometry":{"coordinates":[27.47472,59.19694],"type":"Point"}}