{"id":1293501715,"type":"Feature","properties":{"edtf:cessation":"uuuu","edtf:inception":"uuuu","geom:area":0,"geom:area_square_m":0,"geom:bbox":"25.68389,59.48361,25.68389,59.48361","geom:latitude":59.48361,"geom:longitude":25.68389,"gn:admin1_code":"1.0","gn:admin2_code":"353.0","gn:admin3_code":"2629.0","gn:asciiname":"Kalme","gn:country_code":"EE","gn:dem":65,"gn:feature_class":"P","gn:feature_code":"PPL","gn:geonameid":591692,"gn:latitude":59.48361,"gn:longitude":25.68389,"gn:modification_date":"2017-11-25","gn:name":"Kalme","gn:population":0,"gn:timezone":"Europe/Tallinn","iso:country":"EE","lbl:bbox":"25.66389,59.46361,25.70389,59.50361","lbl:max_zoom":18,"lbl:min_zoom":13.5,"mz:hierarchy_label":1,"mz:is_current":1,"mz:min_zoom":12,"name:est_x_preferred":["Kalme"],"name:fra_x_preferred":["Kalme"],"name:hye_x_preferred":["Կալմե"],"name:nld_x_preferred":["Kalme"],"name:pol_x_preferred":["Kalme"],"name:rus_x_preferred":["Кальме"],"name:spa_x_preferred":["Kalme"],"name:vol_x_preferred":["Kalme"],"src:geom":"geonames","wof:belongsto":[85683055,102191581,1713305921,85633135,1713305725],"wof:breaches":[],"wof:concordances":{"gn:id":591692,"wk:page":"Kalme%2C_Harju_County"},"wof:coterminous":[1713305921],"wof:country":"EE","wof:geomhash":"8d54662137efa0a8b469719924a4e643","wof:hierarchy":[{"continent_id":102191581,"country_id":85633135,"county_id":1713305725,"localadmin_id":1713305921,"locality_id":1293501715,"region_id":85683055}],"wof:id":1293501715,"wof:lang_x_official":["est"],"wof:lang_x_spoken":["est"],"wof:lastmodified":1596661846,"wof:name":"Kalme","wof:parent_id":1713305921,"wof:placetype":"locality","wof:repo":"whosonfirst-data-admin-ee","wof:superseded_by":[],"wof:supersedes":[],"wof:tags":[]},"bbox":[25.68389,59.48361,25.68389,59.48361],"geometry":{"coordinates":[25.68389,59.48361],"type":"Point"}}