{"id":1125957511,"type":"Feature","properties":{"edtf:cessation":"uuuu","edtf:inception":"uuuu","geom:area":0,"geom:area_square_m":0,"geom:bbox":"25.43306,58.44222,25.43306,58.44222","geom:latitude":58.44222,"geom:longitude":25.43306,"gn:country":"EE","gn:fcode":"PPL","gn:population":450,"iso:country":"EE","lbl:bbox":"25.41306,58.42222,25.45306,58.46222","lbl:latitude":58.44222,"lbl:longitude":25.43306,"lbl:max_zoom":17,"lbl:min_zoom":12.5,"mz:hierarchy_label":1,"mz:is_current":1,"mz:min_zoom":11,"mz:note":"Quattroshapes Point Gazetteer import 20170519","name:ceb_x_preferred":["Vastemõisa"],"name:deu_x_preferred":["Vastemõisa"],"name:eng_x_preferred":["Vastemõisa"],"name:est_x_preferred":["Vastemõisa"],"name:fas_x_preferred":["وستمیسا"],"name:fra_x_preferred":["Vastemõisa"],"name:hye_x_preferred":["Վաստեմիիսա"],"name:nld_x_preferred":["Vastemõisa"],"name:pol_x_preferred":["Vastemõisa"],"name:rus_x_preferred":["Вастеймыйза"],"name:spa_x_preferred":["Vastemõisa"],"name:ukr_x_preferred":["Вастемийза"],"name:und_x_variant":["Myza Vastemyyza"],"name:vol_x_preferred":["Vastemõisa"],"qs_pg:aaroncc":"EE","qs_pg:gn_country":"EE","qs_pg:gn_fcode":"PPL","qs_pg:gn_id":587715,"qs_pg:gn_pop":450,"qs_pg:name":"Vastemõisa","qs_pg:name_adm0":"Eesti","qs_pg:name_adm1":"Viljandimaa","qs_pg:photos_9r":0,"qs_pg:photos_sr":0,"qs_pg:pop_sr":2,"qs_pg:qs_id":406495,"qs_pg:qs_pg_placetype":"locality","qs_pg:qs_pg_placetype_gp":"Town","qs_pg:woe_adm0":23424805,"qs_pg:woe_id":846349,"src:geom":"qs_pg","src:lbl_centroid":"qs_pg","src:population":"geonames","woe:adm0_id":23424805,"woe:name_adm0":"Eesti","woe:name_adm1":"Viljandimaa","woe:placetype":"Town","wof:belongsto":[85682985,102191581,1713311881,85633135,1713305735],"wof:breaches":[],"wof:concordances":{"gn:id":587715,"gp:id":846349,"qs_pg:id":406495},"wof:coterminous":[1713311881],"wof:country":"EE","wof:created":1497297670,"wof:geomhash":"d0eacfc22f19011a40dfeae576ff2dc2","wof:hierarchy":[{"continent_id":102191581,"country_id":85633135,"county_id":1713305735,"localadmin_id":1713311881,"locality_id":1125957511,"region_id":85682985}],"wof:id":1125957511,"wof:lang_x_official":["est"],"wof:lang_x_spoken":["est"],"wof:lastmodified":1596663462,"wof:name":"Vastemõisa","wof:parent_id":1713311881,"wof:placetype":"locality","wof:population":450,"wof:population_rank":2,"wof:repo":"whosonfirst-data-admin-ee","wof:superseded_by":[],"wof:supersedes":[],"wof:tags":[]},"bbox":[25.43306,58.44222,25.43306,58.44222],"geometry":{"coordinates":[25.43306,58.44222],"type":"Point"}}