{"id":1327433359,"type":"Feature","properties":{"edtf:cessation":"uuuu","edtf:inception":"uuuu","geom:area":0,"geom:area_square_m":0,"geom:bbox":"27.39139,59.23028,27.39139,59.23028","geom:latitude":59.23028,"geom:longitude":27.39139,"gn:admin1_code":"3.0","gn:admin2_code":"130.0","gn:admin3_code":"1443.0","gn:asciiname":"Ridakuela","gn:country_code":"EE","gn:dem":81,"gn:feature_class":"P","gn:feature_code":"PPL","gn:geonameid":589041,"gn:latitude":59.23028,"gn:longitude":27.39139,"gn:modification_date":"2017-11-25","gn:name":"Ridaküla","gn:population":0,"gn:timezone":"Europe/Tallinn","iso:country":"EE","lbl:bbox":"27.37139,59.21028,27.41139,59.25028","lbl:max_zoom":18,"lbl:min_zoom":13.5,"mz:hierarchy_label":1,"mz:is_current":1,"mz:min_zoom":12,"name:und_x_variant":["Ridakyula","Ridaküla"],"src:geom":"geonames","wof:belongsto":[85683059,102191581,1713311771,85633135,1713305693],"wof:breaches":[],"wof:concordances":{"gn:id":589041},"wof:country":"EE","wof:geomhash":"2fb3ca6716db0a81508666dceddae4c1","wof:hierarchy":[{"continent_id":102191581,"country_id":85633135,"county_id":1713305693,"localadmin_id":1713311771,"locality_id":1327433359,"region_id":85683059}],"wof:id":1327433359,"wof:lang_x_official":["est"],"wof:lang_x_spoken":["est"],"wof:lastmodified":1596660756,"wof:name":"Ridakuela","wof:parent_id":1713311771,"wof:placetype":"locality","wof:repo":"whosonfirst-data-admin-ee","wof:superseded_by":[],"wof:supersedes":[],"wof:tags":[]},"bbox":[27.39139,59.23028,27.39139,59.23028],"geometry":{"coordinates":[27.39139,59.23028],"type":"Point"}}