{"id":1193141969,"type":"Feature","properties":{"edtf:cessation":"uuuu","edtf:inception":"uuuu","geom:area":0,"geom:area_square_m":0,"geom:bbox":"27.06944,58.75139,27.06944,58.75139","geom:latitude":58.75139,"geom:longitude":27.06944,"gn:admin1_code":"18.0","gn:admin2_code":"586.0","gn:admin3_code":"7953.0","gn:asciiname":"Syayeritsa","gn:country_code":"EE","gn:dem":37,"gn:feature_class":"P","gn:feature_code":"PPL","gn:geonameid":588869,"gn:latitude":58.75139,"gn:longitude":27.06944,"gn:modification_date":"2017-11-25","gn:name":"Syayeritsa","gn:population":0,"gn:timezone":"Europe/Tallinn","iso:country":"EE","lbl:bbox":"27.04944,58.73139,27.08944,58.77139","lbl:max_zoom":18,"lbl:min_zoom":13.5,"mz:hierarchy_label":1,"mz:is_current":1,"mz:min_zoom":12,"name:und_x_variant":["Sääritsa"],"src:geom":"geonames","wof:belongsto":[85682995,102191581,1713309159,85633135,1713305679],"wof:breaches":[],"wof:concordances":{"gn:id":588869},"wof:coterminous":[1713309159],"wof:country":"EE","wof:geomhash":"57b00b99df64acd47971ca5fc20830f4","wof:hierarchy":[{"continent_id":102191581,"country_id":85633135,"county_id":1713305679,"localadmin_id":1713309159,"locality_id":1193141969,"region_id":85682995}],"wof:id":1193141969,"wof:lang_x_official":["est"],"wof:lang_x_spoken":["est"],"wof:lastmodified":1596660904,"wof:name":"Syayeritsa","wof:parent_id":1713309159,"wof:placetype":"locality","wof:repo":"whosonfirst-data-admin-ee","wof:superseded_by":[],"wof:supersedes":[],"wof:tags":[]},"bbox":[27.06944,58.75139,27.06944,58.75139],"geometry":{"coordinates":[27.06944,58.75139],"type":"Point"}}