{"id":1343638667,"type":"Feature","properties":{"edtf:cessation":"uuuu","edtf:inception":"uuuu","geom:area":0,"geom:area_square_m":0,"geom:bbox":"27.47139,57.875,27.47139,57.875","geom:latitude":57.875,"geom:longitude":27.47139,"gn:admin1_code":"21.0","gn:admin2_code":"917.0","gn:admin3_code":"3446.0","gn:asciiname":"Korgomoisa","gn:country_code":"EE","gn:dem":88,"gn:feature_class":"P","gn:feature_code":"PPL","gn:geonameid":8620083,"gn:latitude":57.875,"gn:longitude":27.47139,"gn:modification_date":"2017-11-25","gn:name":"Korgõmõisa","gn:population":0,"gn:timezone":"Europe/Tallinn","iso:country":"EE","lbl:bbox":"27.45139,57.855,27.49139,57.895","lbl:max_zoom":18,"lbl:min_zoom":13.5,"mz:hierarchy_label":1,"mz:is_current":1,"mz:min_zoom":12,"name:deu_x_preferred":["Korgõmõisa"],"name:est_x_preferred":["Korgõmõisa"],"name:hye_x_preferred":["Կոռգիմիիսա"],"name:pol_x_preferred":["Korgõmõisa"],"name:spa_x_preferred":["Korgõmõisa"],"name:ukr_x_preferred":["Корґимийса"],"name:und_x_variant":["Kõrgemõisa"],"name:vol_x_preferred":["Korgõmõisa"],"src:geom":"geonames","wof:belongsto":[85682937,102191581,1713316355,85633135,1713305633],"wof:breaches":[],"wof:concordances":{"gn:id":8620083,"wk:page":"Korg%C3%B5m%C3%B5isa"},"wof:coterminous":[1713316355],"wof:country":"EE","wof:geomhash":"473cb0a4557cf75a0ce5909f6a0fef54","wof:hierarchy":[{"continent_id":102191581,"country_id":85633135,"county_id":1713305633,"localadmin_id":1713316355,"locality_id":1343638667,"region_id":85682937}],"wof:id":1343638667,"wof:lang_x_official":["est"],"wof:lang_x_spoken":["est"],"wof:lastmodified":1596660400,"wof:name":"Korgomoisa","wof:parent_id":1713316355,"wof:placetype":"locality","wof:repo":"whosonfirst-data-admin-ee","wof:superseded_by":[],"wof:supersedes":[],"wof:tags":[]},"bbox":[27.47139,57.875,27.47139,57.875],"geometry":{"coordinates":[27.47139,57.875],"type":"Point"}}