{"id":1276742069,"type":"Feature","properties":{"edtf:cessation":"uuuu","edtf:inception":"uuuu","geom:area":0,"geom:area_square_m":0,"geom:bbox":"22.18778,58.33861,22.18778,58.33861","geom:latitude":58.33861,"geom:longitude":22.18778,"gn:admin1_code":"14.0","gn:admin2_code":"714.0","gn:admin3_code":"3715.0","gn:asciiname":"Kuuse","gn:country_code":"EE","gn:dem":45,"gn:feature_class":"P","gn:feature_code":"PPL","gn:geonameid":590887,"gn:latitude":58.33861,"gn:longitude":22.18778,"gn:modification_date":"2017-11-25","gn:name":"Kuuse","gn:population":0,"gn:timezone":"Europe/Tallinn","iso:country":"EE","lbl:bbox":"22.16778,58.31861,22.20778,58.35861","lbl:max_zoom":18,"lbl:min_zoom":13.5,"mz:hierarchy_label":1,"mz:is_current":1,"mz:min_zoom":12,"name:deu_x_preferred":["Kuuse"],"name:est_x_preferred":["Kuuse"],"name:fra_x_preferred":["Kuuse"],"name:hye_x_preferred":["Կուուսե"],"name:pol_x_preferred":["Kuuse"],"name:spa_x_preferred":["Kuuse"],"name:ukr_x_preferred":["Куузе"],"name:und_x_variant":["Tavi"],"name:vol_x_preferred":["Kuuse"],"src:geom":"geonames","wof:belongsto":[85682947,102191581,1713307591,85633135,1713305627],"wof:breaches":[],"wof:concordances":{"gn:id":590887,"wk:page":"Kuuse"},"wof:coterminous":[1713307591],"wof:country":"EE","wof:geomhash":"20ce5d6897d306326a921e0b635deceb","wof:hierarchy":[{"continent_id":102191581,"country_id":85633135,"county_id":1713305627,"localadmin_id":1713307591,"locality_id":1276742069,"region_id":85682947}],"wof:id":1276742069,"wof:lang_x_official":["est"],"wof:lang_x_spoken":["est"],"wof:lastmodified":1596674952,"wof:name":"Kuuse","wof:parent_id":1713307591,"wof:placetype":"locality","wof:repo":"whosonfirst-data-admin-ee","wof:superseded_by":[],"wof:supersedes":[],"wof:tags":[]},"bbox":[22.18778,58.33861,22.18778,58.33861],"geometry":{"coordinates":[22.18778,58.33861],"type":"Point"}}