{"id":1276764395,"type":"Feature","properties":{"edtf:cessation":"uuuu","edtf:inception":"uuuu","geom:area":0,"geom:area_square_m":0,"geom:bbox":"27.13333,59.41667,27.13333,59.41667","geom:latitude":59.41667,"geom:longitude":27.13333,"gn:admin1_code":"3.0","gn:admin2_code":"442.0","gn:admin3_code":"9475.0","gn:asciiname":"Nehatu","gn:cc2":"EE","gn:country_code":"EE","gn:dem":52,"gn:feature_class":"P","gn:feature_code":"PPL","gn:geonameid":590005,"gn:latitude":59.41667,"gn:longitude":27.13333,"gn:modification_date":"2017-11-25","gn:name":"Nehatu","gn:population":0,"gn:timezone":"Europe/Tallinn","iso:country":"EE","lbl:bbox":"27.11333,59.39667,27.15333,59.43667","lbl:max_zoom":18,"lbl:min_zoom":13.5,"mz:hierarchy_label":1,"mz:is_current":1,"mz:min_zoom":12,"name:deu_x_preferred":["Nehatu"],"name:est_x_preferred":["Nehatu"],"name:nld_x_preferred":["Nehatu"],"name:pol_x_preferred":["Nehatu"],"name:und_x_variant":["Nekhatu"],"name:vol_x_preferred":["Nehatu"],"src:geom":"geonames","wof:belongsto":[85683059,102191581,1713311947,85633135,1713305695],"wof:breaches":[],"wof:concordances":{"gn:id":590005},"wof:country":"EE","wof:geomhash":"ebaf6dce06f55c817ce1c6c70586ac0e","wof:hierarchy":[{"continent_id":102191581,"country_id":85633135,"county_id":1713305695,"localadmin_id":1713311947,"locality_id":1276764395,"region_id":85683059}],"wof:id":1276764395,"wof:lang_x_official":["est"],"wof:lang_x_spoken":["est"],"wof:lastmodified":1596660809,"wof:name":"Nehatu","wof:parent_id":1713311947,"wof:placetype":"locality","wof:repo":"whosonfirst-data-admin-ee","wof:superseded_by":[],"wof:supersedes":[],"wof:tags":[]},"bbox":[27.13333,59.41667,27.13333,59.41667],"geometry":{"coordinates":[27.13333,59.41667],"type":"Point"}}