{"id":1276342607,"type":"Feature","properties":{"edtf:cessation":"uuuu","edtf:inception":"uuuu","geom:area":0,"geom:area_square_m":0,"geom:bbox":"26.87667,58.96944,26.87667,58.96944","geom:latitude":58.96944,"geom:longitude":26.87667,"gn:admin1_code":"5.0","gn:admin2_code":"486.0","gn:admin3_code":"7921.0","gn:asciiname":"Saelliksaare","gn:country_code":"EE","gn:dem":56,"gn:feature_class":"P","gn:feature_code":"PPL","gn:geonameid":793399,"gn:latitude":58.96944,"gn:longitude":26.87667,"gn:modification_date":"2017-11-25","gn:name":"Sälliksaare","gn:population":0,"gn:timezone":"Europe/Tallinn","iso:country":"EE","lbl:bbox":"26.85667,58.94944,26.89667,58.98944","lbl:max_zoom":18,"lbl:min_zoom":13.5,"mz:hierarchy_label":1,"mz:is_current":1,"mz:min_zoom":12,"name:deu_x_preferred":["Sälliksaare"],"name:est_x_preferred":["Sälliksaare"],"name:fra_x_preferred":["Sälliksaare"],"name:hye_x_preferred":["Սելիկսաառե"],"name:nld_x_preferred":["Sälliksaare"],"name:pol_x_preferred":["Sälliksaare"],"name:spa_x_preferred":["Sälliksaare"],"name:vol_x_preferred":["Sälliksaare"],"src:geom":"geonames","wof:belongsto":[85683059,102191581,1713312023,85633135,1713305677],"wof:breaches":[],"wof:concordances":{"gn:id":793399,"wk:page":"S%C3%A4lliksaare"},"wof:coterminous":[1713312023],"wof:country":"EE","wof:geomhash":"63f79297a01eab1eb98c86e9c9046048","wof:hierarchy":[{"continent_id":102191581,"country_id":85633135,"county_id":1713305677,"localadmin_id":1713312023,"locality_id":1276342607,"region_id":85683059}],"wof:id":1276342607,"wof:lang_x_official":["est"],"wof:lang_x_spoken":["est"],"wof:lastmodified":1596661011,"wof:name":"Saelliksaare","wof:parent_id":1713312023,"wof:placetype":"locality","wof:repo":"whosonfirst-data-admin-ee","wof:superseded_by":[],"wof:supersedes":[],"wof:tags":[]},"bbox":[26.87667,58.96944,26.87667,58.96944],"geometry":{"coordinates":[26.87667,58.96944],"type":"Point"}}