{"id":1243193741,"type":"Feature","properties":{"edtf:cessation":"uuuu","edtf:inception":"uuuu","geom:area":0,"geom:area_square_m":0,"geom:bbox":"23.50111,59.07139,23.50111,59.07139","geom:latitude":59.07139,"geom:longitude":23.50111,"gn:admin1_code":"7.0","gn:admin2_code":"441.0","gn:admin3_code":"3514.0","gn:asciiname":"Voeoela","gn:country_code":"EE","gn:dem":6,"gn:feature_class":"P","gn:feature_code":"PPL","gn:geonameid":587469,"gn:latitude":59.07139,"gn:longitude":23.50111,"gn:modification_date":"2017-11-25","gn:name":"Vööla","gn:population":0,"gn:timezone":"Europe/Tallinn","iso:country":"EE","lbl:bbox":"23.48111,59.05139,23.52111,59.09139","lbl:max_zoom":18,"lbl:min_zoom":13.5,"mz:hierarchy_label":1,"mz:is_current":1,"mz:min_zoom":12,"name:swe_x_preferred":["Bysholm"],"name:und_x_variant":["Vela","Vööla"],"src:geom":"geonames","wof:belongsto":[85683001,102191581,1713308909,85633135,1713305701],"wof:breaches":[],"wof:concordances":{"gn:id":587469},"wof:country":"EE","wof:geomhash":"62d96985a02057f850cb9982738be31c","wof:hierarchy":[{"continent_id":102191581,"country_id":85633135,"county_id":1713305701,"localadmin_id":1713308909,"locality_id":1243193741,"region_id":85683001}],"wof:id":1243193741,"wof:lang_x_official":["est"],"wof:lang_x_spoken":["est"],"wof:lastmodified":1596677441,"wof:name":"Voeoela","wof:parent_id":1713308909,"wof:placetype":"locality","wof:repo":"whosonfirst-data-admin-ee","wof:superseded_by":[],"wof:supersedes":[],"wof:tags":[]},"bbox":[23.50111,59.07139,23.50111,59.07139],"geometry":{"coordinates":[23.50111,59.07139],"type":"Point"}}