{"id":1343366529,"type":"Feature","properties":{"edtf:cessation":"uuuu","edtf:inception":"uuuu","geom:area":0,"geom:area_square_m":0,"geom:bbox":"27.51472,59.23611,27.51472,59.23611","geom:latitude":59.23611,"geom:longitude":27.51472,"gn:admin1_code":"3.0","gn:admin2_code":"130.0","gn:admin3_code":"1526.0","gn:asciiname":"Edivere","gn:country_code":"EE","gn:dem":65,"gn:feature_class":"P","gn:feature_code":"PPL","gn:geonameid":793494,"gn:latitude":59.23611,"gn:longitude":27.51472,"gn:modification_date":"2017-11-25","gn:name":"Edivere","gn:population":0,"gn:timezone":"Europe/Tallinn","iso:country":"EE","lbl:bbox":"27.49472,59.21611,27.53472,59.25611","lbl:max_zoom":18,"lbl:min_zoom":13.5,"mz:hierarchy_label":1,"mz:is_current":1,"mz:min_zoom":12,"name:deu_x_preferred":["Edivere"],"name:est_x_preferred":["Edivere"],"name:fra_x_preferred":["Edivere"],"name:hye_x_preferred":["Էդիվեռե"],"name:nld_x_preferred":["Edivere"],"name:pol_x_preferred":["Edivere"],"name:spa_x_preferred":["Edivere"],"name:vol_x_preferred":["Edivere"],"src:geom":"geonames","wof:belongsto":[85683059,102191581,1713311773,85633135,1713305693],"wof:breaches":[],"wof:concordances":{"gn:id":793494,"wk:page":"Edivere"},"wof:coterminous":[1713311773],"wof:country":"EE","wof:geomhash":"7f4ae2117564020dc2cd48313530a618","wof:hierarchy":[{"continent_id":102191581,"country_id":85633135,"county_id":1713305693,"localadmin_id":1713311773,"locality_id":1343366529,"region_id":85683059}],"wof:id":1343366529,"wof:lang_x_official":["est"],"wof:lang_x_spoken":["est"],"wof:lastmodified":1596660732,"wof:name":"Edivere","wof:parent_id":1713311773,"wof:placetype":"locality","wof:repo":"whosonfirst-data-admin-ee","wof:superseded_by":[],"wof:supersedes":[],"wof:tags":[]},"bbox":[27.51472,59.23611,27.51472,59.23611],"geometry":{"coordinates":[27.51472,59.23611],"type":"Point"}}