{"id":1293271501,"type":"Feature","properties":{"edtf:cessation":"uuuu","edtf:inception":"uuuu","geom:area":0,"geom:area_square_m":0,"geom:bbox":"24.76139,59.06889,24.76139,59.06889","geom:latitude":59.06889,"geom:longitude":24.76139,"gn:admin1_code":"13.0","gn:admin2_code":"668.0","gn:admin3_code":"3283.0","gn:asciiname":"Sootaguse","gn:country_code":"EE","gn:dem":69,"gn:feature_class":"P","gn:feature_code":"PPL","gn:geonameid":588583,"gn:latitude":59.06889,"gn:longitude":24.76139,"gn:modification_date":"2017-11-25","gn:name":"Sootaguse","gn:population":0,"gn:timezone":"Europe/Tallinn","iso:country":"EE","lbl:bbox":"24.74139,59.04889,24.78139,59.08889","lbl:max_zoom":18,"lbl:min_zoom":13.5,"mz:hierarchy_label":1,"mz:is_current":1,"mz:min_zoom":12,"name:und_x_variant":["Sotaguse","Sootaguse"],"src:geom":"geonames","wof:belongsto":[85683013,102191581,1713315435,85633135,1713305711],"wof:breaches":[],"wof:concordances":{"gn:id":588583},"wof:country":"EE","wof:geomhash":"f77a971833bb8b6ad1cd9f741e1bd53f","wof:hierarchy":[{"continent_id":102191581,"country_id":85633135,"county_id":1713305711,"localadmin_id":1713315435,"locality_id":1293271501,"region_id":85683013}],"wof:id":1293271501,"wof:lang_x_official":["est"],"wof:lang_x_spoken":["est"],"wof:lastmodified":1596676719,"wof:name":"Sootaguse","wof:parent_id":1713315435,"wof:placetype":"locality","wof:repo":"whosonfirst-data-admin-ee","wof:superseded_by":[],"wof:supersedes":[],"wof:tags":[]},"bbox":[24.76139,59.06889,24.76139,59.06889],"geometry":{"coordinates":[24.76139,59.06889],"type":"Point"}}