{"id":1259564411,"type":"Feature","properties":{"edtf:cessation":"uuuu","edtf:inception":"uuuu","geom:area":0,"geom:area_square_m":0,"geom:bbox":"24.41667,58.65,24.41667,58.65","geom:latitude":58.65,"geom:longitude":24.41667,"gn:admin1_code":"11.0","gn:admin2_code":"638.0","gn:admin3_code":"4101.0","gn:asciiname":"Vaeike-Langerma","gn:country_code":"EE","gn:dem":21,"gn:feature_class":"P","gn:feature_code":"PPL","gn:geonameid":587924,"gn:latitude":58.65,"gn:longitude":24.41667,"gn:modification_date":"2017-11-25","gn:name":"Väike-Langerma","gn:population":0,"gn:timezone":"Europe/Tallinn","iso:country":"EE","lbl:bbox":"24.39667,58.63,24.43667,58.67","lbl:max_zoom":18,"lbl:min_zoom":13.5,"mz:hierarchy_label":1,"mz:is_current":1,"mz:min_zoom":12,"src:geom":"geonames","wof:belongsto":[85682981,102191581,1713314123,85633135,1713305733],"wof:breaches":[],"wof:concordances":{"gn:id":587924},"wof:country":"EE","wof:geomhash":"09acd18d25227855a0ef2f99aef5f00c","wof:hierarchy":[{"continent_id":102191581,"country_id":85633135,"county_id":1713305733,"localadmin_id":1713314123,"locality_id":1259564411,"region_id":85682981}],"wof:id":1259564411,"wof:lang_x_official":["est"],"wof:lang_x_spoken":["est"],"wof:lastmodified":1596663417,"wof:name":"Vaeike-Langerma","wof:parent_id":1713314123,"wof:placetype":"locality","wof:repo":"whosonfirst-data-admin-ee","wof:superseded_by":[],"wof:supersedes":[],"wof:tags":[]},"bbox":[24.41667,58.65,24.41667,58.65],"geometry":{"coordinates":[24.41667,58.65],"type":"Point"}}