{"id":1243533379,"type":"Feature","properties":{"edtf:cessation":"uuuu","edtf:inception":"uuuu","geom:area":0,"geom:area_square_m":0,"geom:bbox":"22.27611,58.32833,22.27611,58.32833","geom:latitude":58.32833,"geom:longitude":22.27611,"gn:admin1_code":"14.0","gn:admin2_code":"714.0","gn:admin3_code":"5154.0","gn:asciiname":"Iyekyula","gn:country_code":"EE","gn:dem":9,"gn:feature_class":"P","gn:feature_code":"PPL","gn:geonameid":591922,"gn:latitude":58.32833,"gn:longitude":22.27611,"gn:modification_date":"2017-11-25","gn:name":"Iyekyula","gn:population":0,"gn:timezone":"Europe/Tallinn","iso:country":"EE","lbl:bbox":"22.25611,58.30833,22.29611,58.34833","lbl:max_zoom":18,"lbl:min_zoom":13.5,"mz:hierarchy_label":1,"mz:is_current":1,"mz:min_zoom":12,"name:und_x_variant":["Jõeküla"],"src:geom":"geonames","wof:belongsto":[85682947,102191581,1713306551,85633135,1713305627],"wof:breaches":[],"wof:concordances":{"gn:id":591922},"wof:country":"EE","wof:geomhash":"1846d4bf5762e65a3386c57246311032","wof:hierarchy":[{"continent_id":102191581,"country_id":85633135,"county_id":1713305627,"localadmin_id":1713306551,"locality_id":1243533379,"region_id":85682947}],"wof:id":1243533379,"wof:lang_x_official":["est"],"wof:lang_x_spoken":["est"],"wof:lastmodified":1596674966,"wof:name":"Iyekyula","wof:parent_id":1713306551,"wof:placetype":"locality","wof:repo":"whosonfirst-data-admin-ee","wof:superseded_by":[],"wof:supersedes":[],"wof:tags":[]},"bbox":[22.27611,58.32833,22.27611,58.32833],"geometry":{"coordinates":[22.27611,58.32833],"type":"Point"}}