{"id":1242943933,"type":"Feature","properties":{"edtf:cessation":"uuuu","edtf:inception":"uuuu","geom:area":0,"geom:area_square_m":0,"geom:bbox":"23.15306,58.4825,23.15306,58.4825","geom:latitude":58.4825,"geom:longitude":23.15306,"gn:admin1_code":"14.0","gn:admin2_code":"714.0","gn:admin3_code":"9658.0","gn:asciiname":"Vaelta","gn:country_code":"EE","gn:dem":6,"gn:feature_class":"P","gn:feature_code":"PPL","gn:geonameid":587831,"gn:latitude":58.4825,"gn:longitude":23.15306,"gn:modification_date":"2017-11-25","gn:name":"Välta","gn:population":0,"gn:timezone":"Europe/Tallinn","iso:country":"EE","lbl:bbox":"23.13306,58.4625,23.17306,58.5025","lbl:max_zoom":18,"lbl:min_zoom":13.5,"mz:hierarchy_label":1,"mz:is_current":1,"mz:min_zoom":12,"name:deu_x_preferred":["Välta"],"name:est_x_preferred":["Välta"],"name:hye_x_preferred":["Վելտա"],"name:pol_x_preferred":["Välta"],"name:rus_x_preferred":["Вялта"],"name:spa_x_preferred":["Välta"],"name:und_x_variant":["Vyal’ta"],"name:vol_x_preferred":["Välta"],"src:geom":"geonames","wof:belongsto":[85682947,102191581,1713308073,85633135,1713305627],"wof:breaches":[],"wof:concordances":{"gn:id":587831,"wk:page":"V%C3%A4lta"},"wof:coterminous":[1713308073],"wof:country":"EE","wof:geomhash":"973f6ddee8f3b0670af6dff7e5b63d4f","wof:hierarchy":[{"continent_id":102191581,"country_id":85633135,"county_id":1713305627,"localadmin_id":1713308073,"locality_id":1242943933,"region_id":85682947}],"wof:id":1242943933,"wof:lang_x_official":["est"],"wof:lang_x_spoken":["est"],"wof:lastmodified":1596674952,"wof:name":"Vaelta","wof:parent_id":1713308073,"wof:placetype":"locality","wof:repo":"whosonfirst-data-admin-ee","wof:superseded_by":[],"wof:supersedes":[],"wof:tags":[]},"bbox":[23.15306,58.4825,23.15306,58.4825],"geometry":{"coordinates":[23.15306,58.4825],"type":"Point"}}