{"id":1343833935,"type":"Feature","properties":{"edtf:cessation":"uuuu","edtf:inception":"uuuu","geom:area":0,"geom:area_square_m":0,"geom:bbox":"26.45056,58.16167,26.45056,58.16167","geom:latitude":58.16167,"geom:longitude":26.45056,"gn:admin1_code":"18.0","gn:admin2_code":"528.0","gn:admin3_code":"4046.0","gn:asciiname":"Laguja","gn:country_code":"EE","gn:dem":86,"gn:feature_class":"P","gn:feature_code":"PPL","gn:geonameid":590834,"gn:latitude":58.16167,"gn:longitude":26.45056,"gn:modification_date":"2017-11-25","gn:name":"Laguja","gn:population":0,"gn:timezone":"Europe/Tallinn","iso:country":"EE","lbl:bbox":"26.43056,58.14167,26.47056,58.18167","lbl:max_zoom":18,"lbl:min_zoom":13.5,"mz:hierarchy_label":1,"mz:is_current":1,"mz:min_zoom":12,"name:est_x_preferred":["Laguja"],"name:hye_x_preferred":["Լագույա"],"name:pol_x_preferred":["Laguja"],"name:spa_x_preferred":["Laguja"],"name:ukr_x_preferred":["Лаґуя"],"name:vol_x_preferred":["Laguja"],"src:geom":"geonames","wof:belongsto":[85682995,102191581,1713313803,85633135,1713305715],"wof:breaches":[],"wof:concordances":{"gn:id":590834,"wk:page":"Laguja"},"wof:coterminous":[1713313803],"wof:country":"EE","wof:geomhash":"de7b2f6e3b8dca2ca0779487cfcecc09","wof:hierarchy":[{"continent_id":102191581,"country_id":85633135,"county_id":1713305715,"localadmin_id":1713313803,"locality_id":1343833935,"region_id":85682995}],"wof:id":1343833935,"wof:lang_x_official":["est"],"wof:lang_x_spoken":["est"],"wof:lastmodified":1596676768,"wof:name":"Laguja","wof:parent_id":1713313803,"wof:placetype":"locality","wof:repo":"whosonfirst-data-admin-ee","wof:superseded_by":[],"wof:supersedes":[],"wof:tags":[]},"bbox":[26.45056,58.16167,26.45056,58.16167],"geometry":{"coordinates":[26.45056,58.16167],"type":"Point"}}