{"id":1309870541,"type":"Feature","properties":{"edtf:cessation":"uuuu","edtf:inception":"uuuu","geom:area":0,"geom:area_square_m":0,"geom:bbox":"25.26611,58.17833,25.26611,58.17833","geom:latitude":58.17833,"geom:longitude":25.26611,"gn:admin1_code":"20.0","gn:admin2_code":"480.0","gn:admin3_code":"8984.0","gn:asciiname":"Puka","gn:country_code":"EE","gn:dem":61,"gn:feature_class":"P","gn:feature_code":"PPL","gn:geonameid":8620453,"gn:latitude":58.17833,"gn:longitude":25.26611,"gn:modification_date":"2017-11-25","gn:name":"Puka","gn:population":0,"gn:timezone":"Europe/Tallinn","iso:country":"EE","lbl:bbox":"25.24611,58.15833,25.28611,58.19833","lbl:max_zoom":18,"lbl:min_zoom":13.5,"mz:hierarchy_label":1,"mz:is_current":1,"mz:min_zoom":12,"name:ceb_x_preferred":["Puka"],"name:deu_x_preferred":["Puka"],"name:est_x_preferred":["Puka"],"name:heb_x_preferred":["פוקה"],"name:hun_x_preferred":["Puka"],"name:hye_x_preferred":["Պուկա"],"name:mri_x_preferred":["Puka"],"name:nld_x_preferred":["Puka"],"name:por_x_preferred":["Puka"],"name:ron_x_preferred":["Puka"],"name:swe_x_preferred":["Puka"],"name:ukr_x_preferred":["Пука"],"name:und_x_variant":["Puju"],"name:vol_x_preferred":["Puka"],"src:geom":"geonames","wof:belongsto":[85682985,102191581,1713311743,85633135,1713305661],"wof:breaches":[],"wof:concordances":{"gn:id":8620453},"wof:country":"EE","wof:geomhash":"af821b35d407b0f389c6562fd3635cb6","wof:hierarchy":[{"continent_id":102191581,"country_id":85633135,"county_id":1713305661,"localadmin_id":1713311743,"locality_id":1309870541,"region_id":85682985}],"wof:id":1309870541,"wof:lang_x_official":["est"],"wof:lang_x_spoken":["est"],"wof:lastmodified":1596661299,"wof:name":"Puka","wof:parent_id":1713311743,"wof:placetype":"locality","wof:repo":"whosonfirst-data-admin-ee","wof:superseded_by":[],"wof:supersedes":[],"wof:tags":[]},"bbox":[25.26611,58.17833,25.26611,58.17833],"geometry":{"coordinates":[25.26611,58.17833],"type":"Point"}}