{"id":1260139173,"type":"Feature","properties":{"edtf:cessation":"uuuu","edtf:inception":"uuuu","geom:area":0,"geom:area_square_m":0,"geom:bbox":"26.5825,57.58583,26.5825,57.58583","geom:latitude":57.58583,"geom:longitude":26.5825,"gn:admin1_code":"21.0","gn:admin2_code":"698.0","gn:admin3_code":"3728.0","gn:asciiname":"Kilvagu","gn:country_code":"EE","gn:dem":99,"gn:feature_class":"P","gn:feature_code":"PPL","gn:geonameid":8619053,"gn:latitude":57.58583,"gn:longitude":26.5825,"gn:modification_date":"2017-11-25","gn:name":"Kilvagu","gn:population":0,"gn:timezone":"Europe/Tallinn","iso:country":"EE","lbl:bbox":"26.5625,57.56583,26.6025,57.60583","lbl:max_zoom":18,"lbl:min_zoom":13.5,"mz:hierarchy_label":1,"mz:is_current":1,"mz:min_zoom":12,"src:geom":"geonames","wof:belongsto":[85682937,102191581,1713314941,85633135,1713305787],"wof:breaches":[],"wof:concordances":{"gn:id":8619053},"wof:country":"EE","wof:geomhash":"53725c34c18782a3912e2341ca289298","wof:hierarchy":[{"continent_id":102191581,"country_id":85633135,"county_id":1713305787,"localadmin_id":1713314941,"locality_id":1260139173,"region_id":85682937}],"wof:id":1260139173,"wof:lang_x_official":["est"],"wof:lang_x_spoken":["est"],"wof:lastmodified":1596676876,"wof:name":"Kilvagu","wof:parent_id":1713314941,"wof:placetype":"locality","wof:repo":"whosonfirst-data-admin-ee","wof:superseded_by":[],"wof:supersedes":[],"wof:tags":[]},"bbox":[26.5825,57.58583,26.5825,57.58583],"geometry":{"coordinates":[26.5825,57.58583],"type":"Point"}}