{"id":1209390055,"type":"Feature","properties":{"edtf:cessation":"uuuu","edtf:inception":"uuuu","geom:area":0,"geom:area_square_m":0,"geom:bbox":"25.82222,58.02667,25.82222,58.02667","geom:latitude":58.02667,"geom:longitude":25.82222,"gn:admin1_code":"19.0","gn:admin2_code":"824.0","gn:admin3_code":"2757.0","gn:asciiname":"Koriste","gn:country_code":"EE","gn:dem":91,"gn:feature_class":"P","gn:feature_code":"PPL","gn:geonameid":8620617,"gn:latitude":58.02667,"gn:longitude":25.82222,"gn:modification_date":"2017-11-25","gn:name":"Koriste","gn:population":0,"gn:timezone":"Europe/Tallinn","iso:country":"EE","lbl:bbox":"25.80222,58.00667,25.84222,58.04667","lbl:max_zoom":18,"lbl:min_zoom":13.5,"mz:hierarchy_label":1,"mz:is_current":1,"mz:min_zoom":12,"name:und_x_variant":["Кароте"],"src:geom":"geonames","wof:belongsto":[85682941,102191581,1713312593,85633135,1713305687],"wof:breaches":[],"wof:concordances":{"gn:id":8620617},"wof:country":"EE","wof:geomhash":"6de2ee91cc1918e713de753b0034e655","wof:hierarchy":[{"continent_id":102191581,"country_id":85633135,"county_id":1713305687,"localadmin_id":1713312593,"locality_id":1209390055,"region_id":85682941}],"wof:id":1209390055,"wof:lang_x_official":["est"],"wof:lang_x_spoken":["est"],"wof:lastmodified":1596661435,"wof:name":"Koriste","wof:parent_id":1713312593,"wof:placetype":"locality","wof:repo":"whosonfirst-data-admin-ee","wof:superseded_by":[],"wof:supersedes":[],"wof:tags":[]},"bbox":[25.82222,58.02667,25.82222,58.02667],"geometry":{"coordinates":[25.82222,58.02667],"type":"Point"}}