{"id":1310665571,"type":"Feature","properties":{"edtf:cessation":"uuuu","edtf:inception":"uuuu","geom:area":0,"geom:area_square_m":0,"geom:bbox":"25.55139,58.155,25.55139,58.155","geom:latitude":58.155,"geom:longitude":25.55139,"gn:admin1_code":"20.0","gn:admin2_code":"480.0","gn:admin3_code":"6621.0","gn:asciiname":"Tiri","gn:country_code":"EE","gn:dem":77,"gn:feature_class":"P","gn:feature_code":"PPL","gn:geonameid":588278,"gn:latitude":58.155,"gn:longitude":25.55139,"gn:modification_date":"2017-11-25","gn:name":"Tiri","gn:population":0,"gn:timezone":"Europe/Tallinn","iso:country":"EE","lbl:bbox":"25.53139,58.135,25.57139,58.175","lbl:max_zoom":18,"lbl:min_zoom":13.5,"mz:hierarchy_label":1,"mz:is_current":1,"mz:min_zoom":12,"name:ceb_x_preferred":["Tiri"],"name:swe_x_preferred":["Tiri"],"src:geom":"geonames","wof:belongsto":[85682985,102191581,1713311677,85633135,1713305661],"wof:breaches":[],"wof:concordances":{"gn:id":588278},"wof:country":"EE","wof:geomhash":"36b00cf8d3ff119d5bab7f653bee4280","wof:hierarchy":[{"continent_id":102191581,"country_id":85633135,"county_id":1713305661,"localadmin_id":1713311677,"locality_id":1310665571,"region_id":85682985}],"wof:id":1310665571,"wof:lang_x_official":["est"],"wof:lang_x_spoken":["est"],"wof:lastmodified":1596661302,"wof:name":"Tiri","wof:parent_id":1713311677,"wof:placetype":"locality","wof:repo":"whosonfirst-data-admin-ee","wof:superseded_by":[],"wof:supersedes":[],"wof:tags":[]},"bbox":[25.55139,58.155,25.55139,58.155],"geometry":{"coordinates":[25.55139,58.155],"type":"Point"}}