{"id":1310266579,"type":"Feature","properties":{"edtf:cessation":"uuuu","edtf:inception":"uuuu","geom:area":0,"geom:area_square_m":0,"geom:bbox":"26.03444,58.45139,26.03444,58.45139","geom:latitude":58.45139,"geom:longitude":26.03444,"gn:admin1_code":"20.0","gn:admin2_code":"899.0","gn:admin3_code":"4650.0","gn:asciiname":"Laetkalu","gn:country_code":"EE","gn:dem":39,"gn:feature_class":"P","gn:feature_code":"PPL","gn:geonameid":590765,"gn:latitude":58.45139,"gn:longitude":26.03444,"gn:modification_date":"2017-11-25","gn:name":"Lätkalu","gn:population":0,"gn:timezone":"Europe/Tallinn","iso:country":"EE","lbl:bbox":"26.01444,58.43139,26.05444,58.47139","lbl:max_zoom":18,"lbl:min_zoom":13.5,"mz:hierarchy_label":1,"mz:is_current":1,"mz:min_zoom":12,"src:geom":"geonames","wof:belongsto":[85682985,102191581,1713309965,85633135,1713305669],"wof:breaches":[],"wof:concordances":{"gn:id":590765},"wof:coterminous":[1713309965],"wof:country":"EE","wof:geomhash":"7b342b6c47dfd966e0c8029781c0ae48","wof:hierarchy":[{"continent_id":102191581,"country_id":85633135,"county_id":1713305669,"localadmin_id":1713309965,"locality_id":1310266579,"region_id":85682985}],"wof:id":1310266579,"wof:lang_x_official":["est"],"wof:lang_x_spoken":["est"],"wof:lastmodified":1596661252,"wof:name":"Laetkalu","wof:parent_id":1713309965,"wof:placetype":"locality","wof:repo":"whosonfirst-data-admin-ee","wof:superseded_by":[],"wof:supersedes":[],"wof:tags":[]},"bbox":[26.03444,58.45139,26.03444,58.45139],"geometry":{"coordinates":[26.03444,58.45139],"type":"Point"}}