{"id":1126057007,"type":"Feature","properties":{"edtf:cessation":"uuuu","edtf:inception":"uuuu","geom:area":0,"geom:area_square_m":0,"geom:bbox":"24.60167,59.31917,24.60167,59.31917","geom:latitude":59.31917,"geom:longitude":24.60167,"gn:country":"EE","gn:fcode":"PPL","gn:population":198,"iso:country":"EE","lbl:bbox":"24.58167,59.29917,24.62167,59.33917","lbl:latitude":59.31917,"lbl:longitude":24.60167,"lbl:max_zoom":18,"lbl:min_zoom":13,"mz:hierarchy_label":1,"mz:is_current":1,"mz:min_zoom":11,"mz:note":"Quattroshapes Point Gazetteer import 20170519","name:ceb_x_preferred":["Jälgimäe"],"name:eng_x_preferred":["Jälgimäe"],"name:est_x_preferred":["Jälgimäe"],"name:fra_x_preferred":["Jälgimäe"],"name:hye_x_preferred":["Յելգիմեե"],"name:jpn_x_preferred":["イェルクメー"],"name:nld_x_preferred":["Jälgimäe"],"name:pol_x_preferred":["Jälgimäe"],"name:rus_x_preferred":["Яльгимяэ"],"name:spa_x_preferred":["Jälgimäe"],"name:swe_x_preferred":["Jälgimäe"],"name:urd_x_preferred":["جالگاما"],"name:vol_x_preferred":["Jälgimäe"],"qs_pg:aaroncc":"EE","qs_pg:gn_country":"EE","qs_pg:gn_fcode":"PPL","qs_pg:gn_id":591991,"qs_pg:gn_pop":198,"qs_pg:name":"Jälgimäe","qs_pg:name_adm0":"Eesti","qs_pg:name_adm1":"Harjumaa","qs_pg:photos_9k":1,"qs_pg:photos_9r":1,"qs_pg:photos_all":4,"qs_pg:photos_sr":0,"qs_pg:pop_sr":1,"qs_pg:qs_id":915661,"qs_pg:qs_pg_placetype":"locality","qs_pg:qs_pg_placetype_gp":"Town","qs_pg:woe_adm0":23424805,"qs_pg:woe_id":842390,"src:geom":"qs_pg","src:lbl_centroid":"qs_pg","src:population":"geonames","woe:adm0_id":23424805,"woe:name_adm0":"Eesti","woe:name_adm1":"Harjumaa","woe:placetype":"Town","wof:belongsto":[85683055,102191581,1713313163,85633135,1713305685],"wof:breaches":[],"wof:concordances":{"gn:id":591991,"gp:id":842390,"qs_pg:id":915661,"wd:id":"Q2327453"},"wof:coterminous":[1713313163],"wof:country":"EE","wof:created":1497303331,"wof:geomhash":"75808b194419b29630d85e1a0dbd652a","wof:hierarchy":[{"continent_id":102191581,"country_id":85633135,"county_id":1713305685,"localadmin_id":1713313163,"locality_id":1126057007,"region_id":85683055}],"wof:id":1126057007,"wof:lang_x_official":["est"],"wof:lang_x_spoken":["est"],"wof:lastmodified":1596661507,"wof:name":"Jälgimäe","wof:parent_id":1713313163,"wof:placetype":"locality","wof:population":198,"wof:population_rank":1,"wof:repo":"whosonfirst-data-admin-ee","wof:superseded_by":[],"wof:supersedes":[],"wof:tags":[]},"bbox":[24.60167,59.31917,24.60167,59.31917],"geometry":{"coordinates":[24.60167,59.31917],"type":"Point"}}