{"id":1343238529,"type":"Feature","properties":{"edtf:cessation":"uuuu","edtf:inception":"uuuu","geom:area":0,"geom:area_square_m":0,"geom:bbox":"24.86306,59.04472,24.86306,59.04472","geom:latitude":59.04472,"geom:longitude":24.86306,"gn:admin1_code":"13.0","gn:admin2_code":"668.0","gn:admin3_code":"5687.0","gn:asciiname":"Nomme","gn:country_code":"EE","gn:dem":79,"gn:feature_class":"P","gn:feature_code":"PPL","gn:geonameid":589953,"gn:latitude":59.04472,"gn:longitude":24.86306,"gn:modification_date":"2017-11-25","gn:name":"Nõmme","gn:population":0,"gn:timezone":"Europe/Tallinn","iso:country":"EE","lbl:bbox":"24.84306,59.02472,24.88306,59.06472","lbl:max_zoom":18,"lbl:min_zoom":13.5,"mz:hierarchy_label":1,"mz:is_current":1,"mz:min_zoom":12,"name:est_x_preferred":["Nõmme"],"name:hye_x_preferred":["Նիմե"],"name:pol_x_preferred":["Nõmme"],"name:sco_x_preferred":["Nõmme"],"name:spa_x_preferred":["Nõmme"],"name:und_x_variant":["Nymme"],"name:vol_x_preferred":["Nõmme"],"src:geom":"geonames","wof:belongsto":[85683013,102191581,1713314901,85633135,1713305711],"wof:breaches":[],"wof:concordances":{"gn:id":589953,"wk:page":"N%C3%B5mme%2C_Rapla_County"},"wof:coterminous":[1713311315],"wof:country":"EE","wof:geomhash":"865cd336eac65c2af3edffa49893e6d6","wof:hierarchy":[{"continent_id":102191581,"country_id":85633135,"county_id":1713305711,"localadmin_id":1713314901,"locality_id":1343238529,"region_id":85683013}],"wof:id":1343238529,"wof:lang_x_official":["est"],"wof:lang_x_spoken":["est"],"wof:lastmodified":1596676719,"wof:name":"Nomme","wof:parent_id":1713314901,"wof:placetype":"locality","wof:repo":"whosonfirst-data-admin-ee","wof:superseded_by":[],"wof:supersedes":[],"wof:tags":[]},"bbox":[24.86306,59.04472,24.86306,59.04472],"geometry":{"coordinates":[24.86306,59.04472],"type":"Point"}}