{"id":1209697165,"type":"Feature","properties":{"edtf:cessation":"uuuu","edtf:inception":"uuuu","geom:area":0,"geom:area_square_m":0,"geom:bbox":"24.97389,58.08778,24.97389,58.08778","geom:latitude":58.08778,"geom:longitude":24.97389,"gn:admin1_code":"11.0","gn:admin2_code":"712.0","gn:admin3_code":"2588.0","gn:asciiname":"Keskkuela","gn:country_code":"EE","gn:dem":67,"gn:feature_class":"P","gn:feature_code":"PPL","gn:geonameid":8620621,"gn:latitude":58.08778,"gn:longitude":24.97389,"gn:modification_date":"2017-11-25","gn:name":"Keskküla","gn:population":0,"gn:timezone":"Europe/Tallinn","iso:country":"EE","lbl:bbox":"24.95389,58.06778,24.99389,58.10778","lbl:max_zoom":18,"lbl:min_zoom":13.5,"mz:hierarchy_label":1,"mz:is_current":1,"mz:min_zoom":12,"name:und_x_variant":["Keskküla","Karu"],"src:geom":"geonames","wof:belongsto":[85682981,102191581,1713312545,85633135,1713305705],"wof:breaches":[],"wof:concordances":{"gn:id":8620621},"wof:country":"EE","wof:geomhash":"9b7128f2cfc7eb77fa9a3c0d5045e30b","wof:hierarchy":[{"continent_id":102191581,"country_id":85633135,"county_id":1713305705,"localadmin_id":1713312545,"locality_id":1209697165,"region_id":85682981}],"wof:id":1209697165,"wof:lang_x_official":["est"],"wof:lang_x_spoken":["est"],"wof:lastmodified":1596677738,"wof:name":"Keskkuela","wof:parent_id":1713312545,"wof:placetype":"locality","wof:repo":"whosonfirst-data-admin-ee","wof:superseded_by":[],"wof:supersedes":[],"wof:tags":[]},"bbox":[24.97389,58.08778,24.97389,58.08778],"geometry":{"coordinates":[24.97389,58.08778],"type":"Point"}}