{"id":1126008541,"type":"Feature","properties":{"edtf:cessation":"uuuu","edtf:inception":"uuuu","geom:area":0,"geom:area_square_m":0,"geom:bbox":"24.14056,59.23111,24.14056,59.23111","geom:latitude":59.23111,"geom:longitude":24.14056,"gn:country":"EE","gn:fcode":"PPL","gn:population":392,"iso:country":"EE","lbl:bbox":"24.12056,59.21111,24.16056,59.25111","lbl:latitude":59.23111,"lbl:longitude":24.14056,"lbl:max_zoom":17,"lbl:min_zoom":12.5,"mz:hierarchy_label":1,"mz:is_current":1,"mz:min_zoom":11,"mz:note":"Quattroshapes Point Gazetteer import 20170519","name:bul_x_preferred":["Падисе"],"name:ceb_x_preferred":["Padise"],"name:ces_x_preferred":["Padise"],"name:deu_x_preferred":["Padise"],"name:eng_x_preferred":["Padise"],"name:est_x_preferred":["Padise"],"name:fra_x_preferred":["Padise"],"name:hye_x_preferred":["Պադիսե"],"name:nld_x_preferred":["Padise"],"name:pol_x_preferred":["Padise"],"name:rus_x_preferred":["Падизе"],"name:sco_x_preferred":["Padise"],"name:swe_x_preferred":["Padise"],"name:ukr_x_preferred":["Монастир та миза Падізе"],"name:ukr_x_variant":["Падізе"],"name:vol_x_preferred":["Padise"],"qs_pg:aaroncc":"EE","qs_pg:gn_country":"EE","qs_pg:gn_fcode":"PPL","qs_pg:gn_id":589741,"qs_pg:gn_pop":392,"qs_pg:name":"Padise","qs_pg:name_adm0":"Eesti","qs_pg:name_adm1":"Harjumaa","qs_pg:photos_9k":1,"qs_pg:photos_9r":1,"qs_pg:photos_all":7,"qs_pg:photos_sr":0,"qs_pg:pop_sr":2,"qs_pg:qs_id":111114,"qs_pg:qs_pg_placetype":"locality","qs_pg:qs_pg_placetype_gp":"Town","qs_pg:woe_adm0":23424805,"qs_pg:woe_id":844486,"src:geom":"qs_pg","src:lbl_centroid":"qs_pg","src:population":"geonames","woe:adm0_id":23424805,"woe:name_adm0":"Eesti","woe:name_adm1":"Harjumaa","woe:placetype":"Town","wof:belongsto":[85683055,102191581,1713307691,85633135,1713305737],"wof:breaches":[],"wof:concordances":{"gn:id":589741,"gp:id":844486,"qs_pg:id":111114,"wd:id":"Q3044083"},"wof:coterminous":[1713307691],"wof:country":"EE","wof:created":1497300129,"wof:geomhash":"d35502b0943f7223753903e3f24feb3a","wof:hierarchy":[{"continent_id":102191581,"country_id":85633135,"county_id":1713305737,"localadmin_id":1713307691,"locality_id":1126008541,"region_id":85683055}],"wof:id":1126008541,"wof:lang_x_official":["est"],"wof:lang_x_spoken":["est"],"wof:lastmodified":1596663328,"wof:name":"Padise","wof:parent_id":1713307691,"wof:placetype":"locality","wof:population":392,"wof:population_rank":2,"wof:repo":"whosonfirst-data-admin-ee","wof:superseded_by":[],"wof:supersedes":[],"wof:tags":[]},"bbox":[24.14056,59.23111,24.14056,59.23111],"geometry":{"coordinates":[24.14056,59.23111],"type":"Point"}}