{"id":1225852473,"type":"Feature","properties":{"edtf:cessation":"uuuu","edtf:inception":"uuuu","geom:area":0,"geom:area_square_m":0,"geom:bbox":"27.10083,59.04028,27.10083,59.04028","geom:latitude":59.04028,"geom:longitude":27.10083,"gn:admin1_code":"3.0","gn:admin2_code":"130.0","gn:admin3_code":"7086.0","gn:asciiname":"Moisakuela","gn:country_code":"EE","gn:dem":44,"gn:feature_class":"P","gn:feature_code":"PPL","gn:geonameid":8619630,"gn:latitude":59.04028,"gn:longitude":27.10083,"gn:modification_date":"2017-11-25","gn:name":"Mõisaküla","gn:population":0,"gn:timezone":"Europe/Tallinn","iso:country":"EE","lbl:bbox":"27.08083,59.02028,27.12083,59.06028","lbl:max_zoom":18,"lbl:min_zoom":13.5,"mz:hierarchy_label":1,"mz:is_current":1,"mz:min_zoom":12,"src:geom":"geonames","wof:belongsto":[85683059,102191581,1713311813,85633135,1713305693],"wof:breaches":[],"wof:concordances":{"gn:id":8619630},"wof:country":"EE","wof:geomhash":"e3980ed20f3ca0abb5d0bd303cdccc86","wof:hierarchy":[{"continent_id":102191581,"country_id":85633135,"county_id":1713305693,"localadmin_id":1713311813,"locality_id":1225852473,"region_id":85683059}],"wof:id":1225852473,"wof:lang_x_official":["est"],"wof:lang_x_spoken":["est"],"wof:lastmodified":1596660736,"wof:name":"Moisakuela","wof:parent_id":1713311813,"wof:placetype":"locality","wof:repo":"whosonfirst-data-admin-ee","wof:superseded_by":[],"wof:supersedes":[],"wof:tags":[]},"bbox":[27.10083,59.04028,27.10083,59.04028],"geometry":{"coordinates":[27.10083,59.04028],"type":"Point"}}