{"id":1242859765,"type":"Feature","properties":{"edtf:cessation":"uuuu","edtf:inception":"uuuu","geom:area":0,"geom:area_square_m":0,"geom:bbox":"26.51917,59.22917,26.51917,59.22917","geom:latitude":59.22917,"geom:longitude":26.51917,"gn:admin1_code":"8.0","gn:admin2_code":"901.0","gn:admin3_code":"9467.0","gn:asciiname":"Vabatkuela","gn:country_code":"EE","gn:dem":104,"gn:feature_class":"P","gn:feature_code":"PPL","gn:geonameid":8619583,"gn:latitude":59.22917,"gn:longitude":26.51917,"gn:modification_date":"2017-11-25","gn:name":"Vabatküla","gn:population":0,"gn:timezone":"Europe/Tallinn","iso:country":"EE","lbl:bbox":"26.49917,59.20917,26.53917,59.24917","lbl:max_zoom":18,"lbl:min_zoom":13.5,"mz:hierarchy_label":1,"mz:is_current":1,"mz:min_zoom":12,"name:und_x_variant":["Vabatküla","Uus-Aru"],"src:geom":"geonames","wof:belongsto":[85683049,102191581,1713307711,85633135,1713305771],"wof:breaches":[],"wof:concordances":{"gn:id":8619583},"wof:country":"EE","wof:geomhash":"d75ceacfc672b8b16e6873239eca8c98","wof:hierarchy":[{"continent_id":102191581,"country_id":85633135,"county_id":1713305771,"localadmin_id":1713307711,"locality_id":1242859765,"region_id":85683049}],"wof:id":1242859765,"wof:lang_x_official":["est"],"wof:lang_x_spoken":["est"],"wof:lastmodified":1596677960,"wof:name":"Vabatkuela","wof:parent_id":1713307711,"wof:placetype":"locality","wof:repo":"whosonfirst-data-admin-ee","wof:superseded_by":[],"wof:supersedes":[],"wof:tags":[]},"bbox":[26.51917,59.22917,26.51917,59.22917],"geometry":{"coordinates":[26.51917,59.22917],"type":"Point"}}