{"id":1125933195,"type":"Feature","properties":{"edtf:cessation":"uuuu","edtf:inception":"uuuu","geom:area":0,"geom:area_square_m":0,"geom:bbox":"26.00472,59.26917,26.00472,59.26917","geom:latitude":59.26917,"geom:longitude":26.00472,"gn:country":"EE","gn:fcode":"PPL","gn:population":194,"iso:country":"EE","lbl:bbox":"25.98472,59.24917,26.02472,59.28917","lbl:latitude":59.26917,"lbl:longitude":26.00472,"lbl:max_zoom":18,"lbl:min_zoom":13,"mz:hierarchy_label":1,"mz:is_current":1,"mz:min_zoom":11,"mz:note":"Quattroshapes Point Gazetteer import 20170519","name:bul_x_preferred":["Имасту"],"name:ceb_x_preferred":["Imastu"],"name:eng_x_preferred":["Imastu"],"name:est_x_preferred":["Imastu"],"name:hye_x_preferred":["Իմաստու"],"name:nld_x_preferred":["Imastu"],"name:swe_x_preferred":["Imastu"],"name:ukr_x_preferred":["Імасту"],"name:und_x_variant":["Myza Ismastu"],"name:vol_x_preferred":["Imastu"],"qs_pg:aaroncc":"EE","qs_pg:gn_country":"EE","qs_pg:gn_fcode":"PPL","qs_pg:gn_id":592039,"qs_pg:gn_pop":194,"qs_pg:name":"Imastu","qs_pg:name_adm0":"Eesti","qs_pg:name_adm1":"Lääne-Virumaa","qs_pg:photos_9r":0,"qs_pg:photos_sr":0,"qs_pg:pop_sr":1,"qs_pg:qs_id":1273689,"qs_pg:qs_pg_placetype":"locality","qs_pg:qs_pg_placetype_gp":"Town","qs_pg:woe_adm0":23424805,"qs_pg:woe_id":842333,"src:geom":"qs_pg","src:lbl_centroid":"qs_pg","src:population":"geonames","woe:adm0_id":23424805,"woe:name_adm0":"Eesti","woe:name_adm1":"Lääne-Virumaa","woe:placetype":"Town","wof:belongsto":[85683049,102191581,1713314859,85633135,1713305761],"wof:breaches":[],"wof:concordances":{"gn:id":592039,"gp:id":842333,"qs_pg:id":1273689,"wd:id":"Q3468666"},"wof:coterminous":[1713314859],"wof:country":"EE","wof:created":1497296876,"wof:geomhash":"de3a6add05db90953475e97ca2c0e554","wof:hierarchy":[{"continent_id":102191581,"country_id":85633135,"county_id":1713305761,"localadmin_id":1713314859,"locality_id":1125933195,"region_id":85683049}],"wof:id":1125933195,"wof:lang_x_official":["est"],"wof:lang_x_spoken":["est"],"wof:lastmodified":1596676605,"wof:name":"Imastu","wof:parent_id":1713314859,"wof:placetype":"locality","wof:population":194,"wof:population_rank":1,"wof:repo":"whosonfirst-data-admin-ee","wof:superseded_by":[],"wof:supersedes":[],"wof:tags":[]},"bbox":[26.00472,59.26917,26.00472,59.26917],"geometry":{"coordinates":[26.00472,59.26917],"type":"Point"}}