{"id":1276941693,"type":"Feature","properties":{"edtf:cessation":"uuuu","edtf:inception":"uuuu","geom:area":0,"geom:area_square_m":0,"geom:bbox":"26.58444,57.57472,26.58444,57.57472","geom:latitude":57.57472,"geom:longitude":26.58444,"gn:admin1_code":"21.0","gn:admin2_code":"698.0","gn:admin3_code":"6076.0","gn:asciiname":"Peebu","gn:country_code":"EE","gn:dem":94,"gn:feature_class":"P","gn:feature_code":"PPL","gn:geonameid":794420,"gn:latitude":57.57472,"gn:longitude":26.58444,"gn:modification_date":"2017-11-25","gn:name":"Peebu","gn:population":0,"gn:timezone":"Europe/Tallinn","iso:country":"EE","lbl:bbox":"26.56444,57.55472,26.60444,57.59472","lbl:max_zoom":18,"lbl:min_zoom":13.5,"mz:hierarchy_label":1,"mz:is_current":1,"mz:min_zoom":12,"name:est_x_preferred":["Peebu"],"name:hye_x_preferred":["Պեեբու"],"name:pol_x_preferred":["Peebu"],"name:spa_x_preferred":["Peebu"],"name:swe_x_preferred":["Peebu"],"name:ukr_x_preferred":["Пеебу"],"name:vol_x_preferred":["Peebu"],"src:geom":"geonames","wof:belongsto":[85682937,102191581,1713315347,85633135,1713305787],"wof:breaches":[],"wof:concordances":{"gn:id":794420,"wk:page":"Peebu"},"wof:coterminous":[1713315347],"wof:country":"EE","wof:geomhash":"1932c9f5dec5a511dceccd77aebb24a2","wof:hierarchy":[{"continent_id":102191581,"country_id":85633135,"county_id":1713305787,"localadmin_id":1713315347,"locality_id":1276941693,"region_id":85682937}],"wof:id":1276941693,"wof:lang_x_official":["est"],"wof:lang_x_spoken":["est"],"wof:lastmodified":1596676896,"wof:name":"Peebu","wof:parent_id":1713315347,"wof:placetype":"locality","wof:repo":"whosonfirst-data-admin-ee","wof:superseded_by":[],"wof:supersedes":[],"wof:tags":[]},"bbox":[26.58444,57.57472,26.58444,57.57472],"geometry":{"coordinates":[26.58444,57.57472],"type":"Point"}}