{"id":1293870797,"type":"Feature","properties":{"edtf:cessation":"uuuu","edtf:inception":"uuuu","geom:area":0,"geom:area_square_m":0,"geom:bbox":"27.36583,58.16028,27.36583,58.16028","geom:latitude":58.16028,"geom:longitude":27.36583,"gn:admin1_code":"12.0","gn:admin2_code":"708.0","gn:admin3_code":"5221.0","gn:asciiname":"Maegiotsa","gn:country_code":"EE","gn:dem":51,"gn:feature_class":"P","gn:feature_code":"PPL","gn:geonameid":590387,"gn:latitude":58.16028,"gn:longitude":27.36583,"gn:modification_date":"2017-11-25","gn:name":"Mägiotsa","gn:population":0,"gn:timezone":"Europe/Tallinn","iso:country":"EE","lbl:bbox":"27.34583,58.14028,27.38583,58.18028","lbl:max_zoom":18,"lbl:min_zoom":13.5,"mz:hierarchy_label":1,"mz:is_current":1,"mz:min_zoom":12,"name:est_x_preferred":["Mägiotsa"],"name:hye_x_preferred":["Մեգիոցա"],"name:spa_x_preferred":["Mägiotsa"],"name:ukr_x_preferred":["Мягіотса"],"name:vol_x_preferred":["Mägiotsa"],"src:geom":"geonames","wof:belongsto":[85682955,102191581,1713313173,85633135,1713305793],"wof:breaches":[],"wof:concordances":{"gn:id":590387,"wk:page":"M%C3%A4giotsa"},"wof:coterminous":[1713313173],"wof:country":"EE","wof:geomhash":"e12152c9ae488eba2eebe56cd8faef56","wof:hierarchy":[{"continent_id":102191581,"country_id":85633135,"county_id":1713305793,"localadmin_id":1713313173,"locality_id":1293870797,"region_id":85682955}],"wof:id":1293870797,"wof:lang_x_official":["est"],"wof:lang_x_spoken":["est"],"wof:lastmodified":1596677001,"wof:name":"Maegiotsa","wof:parent_id":1713313173,"wof:placetype":"locality","wof:repo":"whosonfirst-data-admin-ee","wof:superseded_by":[],"wof:supersedes":[],"wof:tags":[]},"bbox":[27.36583,58.16028,27.36583,58.16028],"geometry":{"coordinates":[27.36583,58.16028],"type":"Point"}}