{"id":1126037661,"type":"Feature","properties":{"edtf:cessation":"uuuu","edtf:inception":"uuuu","geom:area":0,"geom:area_square_m":0,"geom:bbox":"27.45917,58.15528,27.45917,58.15528","geom:latitude":58.15528,"geom:longitude":27.45917,"gn:country":"EE","gn:fcode":"PPL","gn:population":286,"iso:country":"EE","lbl:bbox":"27.43917,58.13528,27.47917,58.17528","lbl:latitude":58.15528,"lbl:longitude":27.45917,"lbl:max_zoom":17,"lbl:min_zoom":12.5,"mz:hierarchy_label":1,"mz:is_current":1,"mz:min_zoom":11,"mz:note":"Quattroshapes Point Gazetteer import 20170519","name:bul_x_preferred":["Линте"],"name:ceb_x_preferred":["Linte"],"name:deu_x_preferred":["Linte"],"name:eng_x_preferred":["Linte"],"name:est_x_preferred":["Linte"],"name:fra_x_preferred":["Linte"],"name:hye_x_preferred":["Լինտե"],"name:nds_x_preferred":["Linte"],"name:nld_x_preferred":["Linte"],"name:pol_x_preferred":["Linte"],"name:ron_x_preferred":["retete linte"],"name:spa_x_preferred":["Linte"],"name:swe_x_preferred":["Linte"],"name:ukr_x_preferred":["Лінте"],"name:vol_x_preferred":["Linte"],"name:vro_x_preferred":["Linte"],"qs_pg:aaroncc":"EE","qs_pg:gn_country":"EE","qs_pg:gn_fcode":"PPL","qs_pg:gn_id":590596,"qs_pg:gn_pop":286,"qs_pg:name":"Linte","qs_pg:name_adm0":"Eesti","qs_pg:name_adm1":"Põlvamaa","qs_pg:photos_9k":1,"qs_pg:photos_9r":1,"qs_pg:photos_all":1,"qs_pg:photos_sr":0,"qs_pg:pop_sr":2,"qs_pg:qs_id":966797,"qs_pg:qs_pg_placetype":"locality","qs_pg:qs_pg_placetype_gp":"Town","qs_pg:woe_adm0":23424805,"qs_pg:woe_id":843699,"src:geom":"qs_pg","src:lbl_centroid":"qs_pg","src:population":"geonames","woe:adm0_id":23424805,"woe:name_adm0":"Eesti","woe:name_adm1":"Põlvamaa","woe:placetype":"Town","wof:belongsto":[85682955,102191581,1713310843,85633135,1713305793],"wof:breaches":[],"wof:concordances":{"gn:id":590596,"gp:id":843699,"qs_pg:id":966797,"wd:id":"Q3466844"},"wof:coterminous":[1713310843],"wof:country":"EE","wof:created":1497301898,"wof:geomhash":"d7c2a9f8e82f99ae95f353d9155be5f7","wof:hierarchy":[{"continent_id":102191581,"country_id":85633135,"county_id":1713305793,"localadmin_id":1713310843,"locality_id":1126037661,"region_id":85682955}],"wof:id":1126037661,"wof:lang_x_official":["est"],"wof:lang_x_spoken":["est"],"wof:lastmodified":1596677005,"wof:name":"Linte","wof:parent_id":1713310843,"wof:placetype":"locality","wof:population":286,"wof:population_rank":2,"wof:repo":"whosonfirst-data-admin-ee","wof:superseded_by":[],"wof:supersedes":[],"wof:tags":[]},"bbox":[27.45917,58.15528,27.45917,58.15528],"geometry":{"coordinates":[27.45917,58.15528],"type":"Point"}}