{"id":1209396075,"type":"Feature","properties":{"edtf:cessation":"uuuu","edtf:inception":"uuuu","geom:area":0,"geom:area_square_m":0,"geom:bbox":"24.68333,58.45,24.68333,58.45","geom:latitude":58.45,"geom:longitude":24.68333,"gn:admin1_code":"11.0","gn:admin2_code":"809.0","gn:admin3_code":"7265.0","gn:asciiname":"Metsakuela","gn:country_code":"EE","gn:dem":23,"gn:feature_class":"P","gn:feature_code":"PPL","gn:geonameid":590255,"gn:latitude":58.45,"gn:longitude":24.68333,"gn:modification_date":"2017-11-25","gn:name":"Metsaküla","gn:population":0,"gn:timezone":"Europe/Tallinn","iso:country":"EE","lbl:bbox":"24.66333,58.43,24.70333,58.47","lbl:max_zoom":18,"lbl:min_zoom":13.5,"mz:hierarchy_label":1,"mz:is_current":1,"mz:min_zoom":12,"name:und_x_variant":["Metsakyula","Metsaküla"],"src:geom":"geonames","wof:belongsto":[85682981,102191581,1713312403,85633135,1713305731],"wof:breaches":[],"wof:concordances":{"gn:id":590255},"wof:country":"EE","wof:geomhash":"011317a523f371c4b39565b69dbe6425","wof:hierarchy":[{"continent_id":102191581,"country_id":85633135,"county_id":1713305731,"localadmin_id":1713312403,"locality_id":1209396075,"region_id":85682981}],"wof:id":1209396075,"wof:lang_x_official":["est"],"wof:lang_x_spoken":["est"],"wof:lastmodified":1596663387,"wof:name":"Metsakuela","wof:parent_id":1713312403,"wof:placetype":"locality","wof:repo":"whosonfirst-data-admin-ee","wof:superseded_by":[],"wof:supersedes":[],"wof:tags":[]},"bbox":[24.68333,58.45,24.68333,58.45],"geometry":{"coordinates":[24.68333,58.45],"type":"Point"}}