{"id":1126063383,"type":"Feature","properties":{"edtf:cessation":"uuuu","edtf:inception":"uuuu","geom:area":0,"geom:area_square_m":0,"geom:bbox":"24.33222,59.30444,24.33222,59.30444","geom:latitude":59.30444,"geom:longitude":24.33222,"gn:country":"EE","gn:fcode":"PPLX","gn:population":0,"iso:country":"EE","lbl:bbox":"24.32722,59.29944,24.33722,59.30944","lbl:latitude":59.30444,"lbl:longitude":24.33222,"lbl:max_zoom":18,"mz:hierarchy_label":1,"mz:is_current":1,"mz:min_zoom":15,"mz:note":"Quattroshapes Point Gazetteer import 20170519","qs_pg:aaroncc":"EE","qs_pg:gn_country":"EE","qs_pg:gn_fcode":"PPLX","qs_pg:gn_id":588785,"qs_pg:gn_pop":0,"qs_pg:name":"Sassi","qs_pg:name_adm0":"Eesti","qs_pg:name_adm1":"Harjumaa","qs_pg:photos":7,"qs_pg:photos_1k":1,"qs_pg:photos_9k":1,"qs_pg:photos_9r":1,"qs_pg:photos_all":7,"qs_pg:photos_sr":1,"qs_pg:pop_sr":0,"qs_pg:qs_id":937073,"qs_pg:qs_pg_placetype":"neighbourhood","qs_pg:qs_pg_placetype_gp":"Suburb","qs_pg:woe_adm0":23424805,"qs_pg:woe_id":845396,"src:geom":"qs_pg","src:lbl_centroid":"qs_pg","woe:adm0_id":23424805,"woe:name_adm0":"Eesti","woe:name_adm1":"Harjumaa","woe:placetype":"Suburb","wof:belongsto":[102191581,1713307935,85633135,1713305737,85683055],"wof:breaches":[],"wof:concordances":{"gn:id":588785,"gp:id":845396,"qs_pg:id":937073},"wof:country":"EE","wof:created":1497308451,"wof:geomhash":"ee6cfcf6fa87254677f000caf26d7242","wof:hierarchy":[{"continent_id":102191581,"country_id":85633135,"county_id":1713305737,"localadmin_id":1713307935,"locality_id":-1,"neighbourhood_id":1126063383,"region_id":85683055}],"wof:id":1126063383,"wof:lastmodified":1596663332,"wof:name":"Sassi","wof:parent_id":-1,"wof:placetype":"neighbourhood","wof:repo":"whosonfirst-data-admin-ee","wof:superseded_by":[],"wof:supersedes":[],"wof:tags":[]},"bbox":[24.33222,59.30444,24.33222,59.30444],"geometry":{"coordinates":[24.33222,59.30444],"type":"Point"}}