{"id":1292974867,"type":"Feature","properties":{"edtf:cessation":"uuuu","edtf:inception":"uuuu","geom:area":0,"geom:area_square_m":0,"geom:bbox":"27.26667,57.78333,27.26667,57.78333","geom:latitude":57.78333,"geom:longitude":27.26667,"gn:admin1_code":"21.0","gn:admin2_code":"917.0","gn:admin3_code":"6484.0","gn:asciiname":"Kamara","gn:country_code":"EE","gn:dem":156,"gn:feature_class":"P","gn:feature_code":"PPL","gn:geonameid":591686,"gn:latitude":57.78333,"gn:longitude":27.26667,"gn:modification_date":"2017-11-25","gn:name":"Kamara","gn:population":0,"gn:timezone":"Europe/Tallinn","iso:country":"EE","lbl:bbox":"27.24667,57.76333,27.28667,57.80333","lbl:max_zoom":18,"lbl:min_zoom":13.5,"mz:hierarchy_label":1,"mz:is_current":1,"mz:min_zoom":12,"name:ceb_x_preferred":["Kamara"],"name:deu_x_preferred":["Kamara"],"name:ell_x_preferred":["Καμάρα"],"name:fin_x_preferred":["Kamara"],"name:fra_x_preferred":["Kamara"],"name:heb_x_preferred":["קמארה"],"name:ita_x_preferred":["Kamara"],"name:lav_x_preferred":["Kamara"],"name:que_x_preferred":["Kamara"],"name:rus_x_preferred":["Камара"],"name:swe_x_preferred":["Kamara"],"src:geom":"geonames","wof:belongsto":[85682937,102191581,1713316301,85633135,1713305633],"wof:breaches":[],"wof:concordances":{"gn:id":591686},"wof:country":"EE","wof:geomhash":"a4542bb4aacf392b9adb0bf7ed71a68c","wof:hierarchy":[{"continent_id":102191581,"country_id":85633135,"county_id":1713305633,"localadmin_id":1713316301,"locality_id":1292974867,"region_id":85682937}],"wof:id":1292974867,"wof:lang_x_official":["est"],"wof:lang_x_spoken":["est"],"wof:lastmodified":1596660392,"wof:name":"Kamara","wof:parent_id":1713316301,"wof:placetype":"locality","wof:repo":"whosonfirst-data-admin-ee","wof:superseded_by":[],"wof:supersedes":[],"wof:tags":[]},"bbox":[27.26667,57.78333,27.26667,57.78333],"geometry":{"coordinates":[27.26667,57.78333],"type":"Point"}}