{"id":1125957693,"type":"Feature","properties":{"edtf:cessation":"uuuu","edtf:inception":"uuuu","geom:area":0,"geom:area_square_m":0,"geom:bbox":"25.60833,58.48417,25.60833,58.48417","geom:latitude":58.48417,"geom:longitude":25.60833,"gn:country":"EE","gn:fcode":"PPL","gn:population":103,"iso:country":"EE","lbl:bbox":"25.58833,58.46417,25.62833,58.50417","lbl:latitude":58.48417,"lbl:longitude":25.60833,"lbl:max_zoom":18,"lbl:min_zoom":13,"mz:hierarchy_label":1,"mz:is_current":1,"mz:min_zoom":11,"mz:note":"Quattroshapes Point Gazetteer import 20170519","name:ceb_x_preferred":["Võivaku"],"name:eng_x_preferred":["Võivaku"],"name:est_x_preferred":["Võivaku"],"name:hye_x_preferred":["Վիիվակու"],"name:nld_x_preferred":["Võivaku"],"name:pol_x_preferred":["Võivaku"],"name:spa_x_preferred":["Võivaku"],"name:swe_x_preferred":["Võivaku"],"name:ukr_x_preferred":["Вийваку"],"name:vol_x_preferred":["Võivaku"],"qs_pg:aaroncc":"EE","qs_pg:gn_country":"EE","qs_pg:gn_fcode":"PPL","qs_pg:gn_id":794618,"qs_pg:gn_pop":103,"qs_pg:name":"Võivaku","qs_pg:name_adm0":"Eesti","qs_pg:name_adm1":"Viljandimaa","qs_pg:photos_9r":0,"qs_pg:photos_sr":0,"qs_pg:pop_sr":1,"qs_pg:qs_id":406527,"qs_pg:qs_pg_placetype":"locality","qs_pg:qs_pg_placetype_gp":"Town","qs_pg:woe_adm0":23424805,"qs_pg:woe_id":846558,"src:geom":"qs_pg","src:lbl_centroid":"qs_pg","src:population":"geonames","woe:adm0_id":23424805,"woe:name_adm0":"Eesti","woe:name_adm1":"Viljandimaa","woe:placetype":"Town","wof:belongsto":[85682985,102191581,1713312951,85633135,1713305735],"wof:breaches":[],"wof:concordances":{"gn:id":794618,"gp:id":846558,"qs_pg:id":406527,"wd:id":"Q11020021"},"wof:coterminous":[1713312951],"wof:country":"EE","wof:created":1497297676,"wof:geomhash":"5b43416e806620b7ec6e2f61872b75a4","wof:hierarchy":[{"continent_id":102191581,"country_id":85633135,"county_id":1713305735,"localadmin_id":1713312951,"locality_id":1125957693,"region_id":85682985}],"wof:id":1125957693,"wof:lang_x_official":["est"],"wof:lang_x_spoken":["est"],"wof:lastmodified":1596663462,"wof:name":"Võivaku","wof:parent_id":1713312951,"wof:placetype":"locality","wof:population":103,"wof:population_rank":1,"wof:repo":"whosonfirst-data-admin-ee","wof:superseded_by":[],"wof:supersedes":[],"wof:tags":[]},"bbox":[25.60833,58.48417,25.60833,58.48417],"geometry":{"coordinates":[25.60833,58.48417],"type":"Point"}}