{"id":1226039585,"type":"Feature","properties":{"edtf:cessation":"uuuu","edtf:inception":"uuuu","geom:area":0,"geom:area_square_m":0,"geom:bbox":"23.53333,58.56667,23.53333,58.56667","geom:latitude":58.56667,"geom:longitude":23.53333,"gn:admin1_code":"11.0","gn:admin2_code":"430.0","gn:admin3_code":"9388.0","gn:asciiname":"Vana-Virtsu","gn:cc2":"EE","gn:country_code":"EE","gn:dem":4,"gn:feature_class":"P","gn:feature_code":"PPL","gn:geonameid":587776,"gn:latitude":58.56667,"gn:longitude":23.53333,"gn:modification_date":"2017-11-25","gn:name":"Vana-Virtsu","gn:population":0,"gn:timezone":"Europe/Tallinn","iso:country":"EE","lbl:bbox":"23.51333,58.54667,23.55333,58.58667","lbl:max_zoom":18,"lbl:min_zoom":13.5,"mz:hierarchy_label":1,"mz:is_current":1,"mz:is_funky":1,"mz:min_zoom":12,"name:und_x_variant":["Myza Vana Virtsu","Vana-Virtsu"],"src:geom":"geonames","wof:belongsto":[85683001,102191581,1713308793,85633135,1713305721],"wof:breaches":[],"wof:concordances":{"gn:id":587776},"wof:country":"EE","wof:geomhash":"e287edfd369cdb6c6a2bc97f19ab00f1","wof:hierarchy":[{"continent_id":102191581,"country_id":85633135,"county_id":1713305721,"localadmin_id":1713308793,"locality_id":1226039585,"region_id":85683001}],"wof:id":1226039585,"wof:lang_x_official":["est"],"wof:lang_x_spoken":["est"],"wof:lastmodified":1596661686,"wof:name":"Vana-Virtsu","wof:parent_id":1713308793,"wof:placetype":"locality","wof:repo":"whosonfirst-data-admin-ee","wof:superseded_by":[],"wof:supersedes":[],"wof:tags":[]},"bbox":[23.53333,58.56667,23.53333,58.56667],"geometry":{"coordinates":[23.53333,58.56667],"type":"Point"}}