{"id":1126023589,"type":"Feature","properties":{"edtf:cessation":"uuuu","edtf:inception":"uuuu","geom:area":0,"geom:area_square_m":0,"geom:bbox":"26.3275,58.19722,26.3275,58.19722","geom:latitude":58.19722,"geom:longitude":26.3275,"gn:country":"EE","gn:fcode":"PPL","gn:population":127,"iso:country":"EE","lbl:bbox":"26.3075,58.17722,26.3475,58.21722","lbl:latitude":58.19722,"lbl:longitude":26.3275,"lbl:max_zoom":18,"lbl:min_zoom":13,"mz:hierarchy_label":1,"mz:is_current":1,"mz:min_zoom":11,"mz:note":"Quattroshapes Point Gazetteer import 20170519","name:ceb_x_preferred":["Tammiste"],"name:eng_x_preferred":["Tammiste"],"name:est_x_preferred":["Tammiste"],"name:fra_x_preferred":["Tammiste"],"name:hye_x_preferred":["Տամիստե"],"name:nld_x_preferred":["Tammiste"],"name:pol_x_preferred":["Tammiste"],"name:spa_x_preferred":["Tammiste"],"name:ukr_x_preferred":["Таммісте"],"name:vol_x_preferred":["Tammiste"],"qs_pg:aaroncc":"EE","qs_pg:gn_country":"EE","qs_pg:gn_fcode":"PPL","qs_pg:gn_id":794014,"qs_pg:gn_pop":127,"qs_pg:name":"Tammiste","qs_pg:name_adm0":"Eesti","qs_pg:name_adm1":"Tartumaa","qs_pg:photos_9k":1,"qs_pg:photos_9r":1,"qs_pg:photos_all":1,"qs_pg:photos_sr":0,"qs_pg:pop_sr":1,"qs_pg:qs_id":949748,"qs_pg:qs_pg_placetype":"locality","qs_pg:qs_pg_placetype_gp":"Town","qs_pg:woe_adm0":23424805,"qs_pg:woe_id":845768,"src:geom":"qs_pg","src:lbl_centroid":"qs_pg","src:population":"geonames","woe:adm0_id":23424805,"woe:name_adm0":"Eesti","woe:name_adm1":"Tartumaa","woe:placetype":"Town","wof:belongsto":[85682995,102191581,1713310593,85633135,1713305757],"wof:breaches":[],"wof:concordances":{"gn:id":794014,"gp:id":845768,"qs_pg:id":949748,"wd:id":"Q3454066"},"wof:coterminous":[1713310593],"wof:country":"EE","wof:created":1497300986,"wof:geomhash":"73fb1045752be50b4b6f0b56a7b8616a","wof:hierarchy":[{"continent_id":102191581,"country_id":85633135,"county_id":1713305757,"localadmin_id":1713310593,"locality_id":1126023589,"region_id":85682995}],"wof:id":1126023589,"wof:lang_x_official":["est"],"wof:lang_x_spoken":["est"],"wof:lastmodified":1596661921,"wof:name":"Tammiste","wof:parent_id":1713310593,"wof:placetype":"locality","wof:population":127,"wof:population_rank":1,"wof:repo":"whosonfirst-data-admin-ee","wof:superseded_by":[],"wof:supersedes":[],"wof:tags":[]},"bbox":[26.3275,58.19722,26.3275,58.19722],"geometry":{"coordinates":[26.3275,58.19722],"type":"Point"}}