{"id":1343821091,"type":"Feature","properties":{"edtf:cessation":"uuuu","edtf:inception":"uuuu","geom:area":0,"geom:area_square_m":0,"geom:bbox":"26.39833,58.51361,26.39833,58.51361","geom:latitude":58.51361,"geom:longitude":26.39833,"gn:admin1_code":"5.0","gn:admin2_code":"618.0","gn:admin3_code":"1226.0","gn:asciiname":"Vaeaenikvere","gn:cc2":"EE","gn:country_code":"EE","gn:dem":57,"gn:feature_class":"P","gn:feature_code":"PPL","gn:geonameid":587977,"gn:latitude":58.51361,"gn:longitude":26.39833,"gn:modification_date":"2017-11-25","gn:name":"Väänikvere","gn:population":0,"gn:timezone":"Europe/Tallinn","iso:country":"EE","lbl:bbox":"26.37833,58.49361,26.41833,58.53361","lbl:max_zoom":18,"lbl:min_zoom":13.5,"mz:hierarchy_label":1,"mz:is_current":1,"mz:min_zoom":12,"name:est_x_preferred":["Väänikvere"],"name:fra_x_preferred":["Väänikvere"],"name:hye_x_preferred":["Վեենիկվեռե"],"name:pol_x_preferred":["Väänikvere"],"name:spa_x_preferred":["Väänikvere"],"name:ukr_x_preferred":["Вяеніквере"],"name:und_x_variant":["Vyaanikvere"],"name:vol_x_preferred":["Väänikvere"],"src:geom":"geonames","wof:belongsto":[85683009,102191581,1713313007,85633135,1713305657],"wof:breaches":[],"wof:concordances":{"gn:id":587977,"wk:page":"V%C3%A4%C3%A4nikvere"},"wof:coterminous":[1713313411],"wof:country":"EE","wof:geomhash":"cd360e671b09bd3609cf665733e95be7","wof:hierarchy":[{"continent_id":102191581,"country_id":85633135,"county_id":1713305657,"localadmin_id":1713313007,"locality_id":1343821091,"region_id":85683009}],"wof:id":1343821091,"wof:lang_x_official":["est"],"wof:lang_x_spoken":["est"],"wof:lastmodified":1596676501,"wof:name":"Vaeaenikvere","wof:parent_id":1713313007,"wof:placetype":"locality","wof:repo":"whosonfirst-data-admin-ee","wof:superseded_by":[],"wof:supersedes":[],"wof:tags":[]},"bbox":[26.39833,58.51361,26.39833,58.51361],"geometry":{"coordinates":[26.39833,58.51361],"type":"Point"}}