{"id":1243534565,"type":"Feature","properties":{"edtf:cessation":"uuuu","edtf:inception":"uuuu","geom:area":0,"geom:area_square_m":0,"geom:bbox":"27.19139,58.22194,27.19139,58.22194","geom:latitude":58.22194,"geom:longitude":27.19139,"gn:admin1_code":"12.0","gn:admin2_code":"622.0","gn:admin3_code":"2471.0","gn:asciiname":"Laane","gn:country_code":"EE","gn:dem":47,"gn:feature_class":"P","gn:feature_code":"PPL","gn:geonameid":8620813,"gn:latitude":58.22194,"gn:longitude":27.19139,"gn:modification_date":"2017-11-25","gn:name":"Laane","gn:population":0,"gn:timezone":"Europe/Tallinn","iso:country":"EE","lbl:bbox":"27.17139,58.20194,27.21139,58.24194","lbl:max_zoom":18,"lbl:min_zoom":13.5,"mz:hierarchy_label":1,"mz:is_current":1,"mz:min_zoom":12,"name:est_x_preferred":["Laane"],"name:hye_x_preferred":["Լաանե"],"name:nld_x_preferred":["Laane"],"name:pol_x_preferred":["Laane"],"name:swe_x_preferred":["Laane"],"name:ukr_x_preferred":["Лаане"],"name:und_x_variant":["Лане"],"name:vol_x_preferred":["Laane"],"src:geom":"geonames","wof:belongsto":[85682955,102191581,1713314191,85633135,1713305791],"wof:breaches":[],"wof:concordances":{"gn:id":8620813},"wof:country":"EE","wof:geomhash":"cf17fbfe6ff5b1b7cb6a9ea15c33662c","wof:hierarchy":[{"continent_id":102191581,"country_id":85633135,"county_id":1713305791,"localadmin_id":1713314191,"locality_id":1243534565,"region_id":85682955}],"wof:id":1243534565,"wof:lang_x_official":["est"],"wof:lang_x_spoken":["est"],"wof:lastmodified":1596676970,"wof:name":"Laane","wof:parent_id":1713314191,"wof:placetype":"locality","wof:repo":"whosonfirst-data-admin-ee","wof:superseded_by":[],"wof:supersedes":[],"wof:tags":[]},"bbox":[27.19139,58.22194,27.19139,58.22194],"geometry":{"coordinates":[27.19139,58.22194],"type":"Point"}}