{"id":1125830965,"type":"Feature","properties":{"edtf:cessation":"uuuu","edtf:inception":"uuuu","geom:area":0,"geom:area_square_m":0,"geom:bbox":"24.86194,58.03306,24.86194,58.03306","geom:latitude":58.03306,"geom:longitude":24.86194,"gn:country":"EE","gn:fcode":"PPL","gn:population":141,"iso:country":"EE","lbl:bbox":"24.84194,58.01306,24.88194,58.05306","lbl:latitude":58.03306,"lbl:longitude":24.86194,"lbl:max_zoom":18,"lbl:min_zoom":13,"mz:hierarchy_label":1,"mz:is_current":1,"mz:min_zoom":11,"mz:note":"Quattroshapes Point Gazetteer import 20170519","name:ceb_x_preferred":["Veelikse"],"name:eng_x_preferred":["Veelikse"],"name:est_x_preferred":["Veelikse"],"name:fas_x_preferred":["ویلیکس، شهرستان پارنو"],"name:fas_x_variant":["ویلیکس"],"name:fra_x_preferred":["Veelikse"],"name:hye_x_preferred":["Վեելիկսե"],"name:nld_x_preferred":["Veelikse"],"name:spa_x_preferred":["Veelikse"],"name:swe_x_preferred":["Veelikse"],"name:und_x_variant":["Velikse"],"name:vol_x_preferred":["Veelikse"],"qs_pg:aaroncc":"EE","qs_pg:gn_country":"EE","qs_pg:gn_fcode":"PPL","qs_pg:gn_id":587692,"qs_pg:gn_pop":141,"qs_pg:name":"Veelikse","qs_pg:photos_9r":0,"qs_pg:photos_sr":0,"qs_pg:pop_sr":1,"qs_pg:qs_id":81097,"qs_pg:qs_pg_placetype":"locality","src:geom":"qs_pg","src:lbl_centroid":"qs_pg","src:population":"geonames","wof:belongsto":[85682981,102191581,1713309487,85633135,1713305705],"wof:breaches":[],"wof:concordances":{"gn:id":587692,"qs_pg:id":81097,"wd:id":"Q11020439"},"wof:coterminous":[1713309487],"wof:country":"EE","wof:created":1497292496,"wof:geomhash":"de694214c837b1ef42bab72cf23817b3","wof:hierarchy":[{"continent_id":102191581,"country_id":85633135,"county_id":1713305705,"localadmin_id":1713309487,"locality_id":1125830965,"region_id":85682981}],"wof:id":1125830965,"wof:lang_x_official":["est"],"wof:lang_x_spoken":["est"],"wof:lastmodified":1596677732,"wof:name":"Veelikse","wof:parent_id":1713309487,"wof:placetype":"locality","wof:population":141,"wof:population_rank":1,"wof:repo":"whosonfirst-data-admin-ee","wof:superseded_by":[],"wof:supersedes":[],"wof:tags":[]},"bbox":[24.86194,58.03306,24.86194,58.03306],"geometry":{"coordinates":[24.86194,58.03306],"type":"Point"}}