{"id":1310170267,"type":"Feature","properties":{"edtf:cessation":"uuuu","edtf:inception":"uuuu","geom:area":0,"geom:area_square_m":0,"geom:bbox":"25.42111,58.14889,25.42111,58.14889","geom:latitude":58.14889,"geom:longitude":25.42111,"gn:admin1_code":"20.0","gn:admin2_code":"480.0","gn:admin3_code":"3580.0","gn:asciiname":"Pornuse","gn:cc2":"EE","gn:country_code":"EE","gn:dem":72,"gn:feature_class":"P","gn:feature_code":"PPL","gn:geonameid":588011,"gn:latitude":58.14889,"gn:longitude":25.42111,"gn:modification_date":"2017-11-25","gn:name":"Pornuse","gn:population":0,"gn:timezone":"Europe/Tallinn","iso:country":"EE","lbl:bbox":"25.40111,58.12889,25.44111,58.16889","lbl:max_zoom":18,"lbl:min_zoom":13.5,"mz:hierarchy_label":1,"mz:is_current":1,"mz:min_zoom":12,"name:est_x_preferred":["Pornuse"],"name:hye_x_preferred":["Պոռնուսե"],"name:pol_x_preferred":["Pornuse"],"name:spa_x_preferred":["Pornuse"],"name:ukr_x_preferred":["Порнузе"],"name:und_x_variant":["Vana-Pornuse","Pornuse Asundus","Uue-Pomuse","Uue-Pornuse","Myza Vana-Pornuse"],"name:vol_x_preferred":["Pornuse"],"src:geom":"geonames","wof:belongsto":[85682985,102191581,1713311653,85633135,1713305661],"wof:breaches":[],"wof:concordances":{"gn:id":588011,"wk:page":"Pornuse"},"wof:coterminous":[1713311749],"wof:country":"EE","wof:geomhash":"80587f2e717211028353dd95ce2464fe","wof:hierarchy":[{"continent_id":102191581,"country_id":85633135,"county_id":1713305661,"localadmin_id":1713311653,"locality_id":1310170267,"region_id":85682985}],"wof:id":1310170267,"wof:lang_x_official":["est"],"wof:lang_x_spoken":["est"],"wof:lastmodified":1596661304,"wof:name":"Pornuse","wof:parent_id":1713311653,"wof:placetype":"locality","wof:repo":"whosonfirst-data-admin-ee","wof:superseded_by":[],"wof:supersedes":[],"wof:tags":[]},"bbox":[25.42111,58.14889,25.42111,58.14889],"geometry":{"coordinates":[25.42111,58.14889],"type":"Point"}}