{"id":1260068269,"type":"Feature","properties":{"edtf:cessation":"uuuu","edtf:inception":"uuuu","geom:area":0,"geom:area_square_m":0,"geom:bbox":"24.82944,58.15556,24.82944,58.15556","geom:latitude":58.15556,"geom:longitude":24.82944,"gn:admin1_code":"11.0","gn:admin2_code":"712.0","gn:admin3_code":"4440.0","gn:asciiname":"Napsu","gn:country_code":"EE","gn:dem":49,"gn:feature_class":"P","gn:feature_code":"PPL","gn:geonameid":590035,"gn:latitude":58.15556,"gn:longitude":24.82944,"gn:modification_date":"2017-11-25","gn:name":"Napsu","gn:population":0,"gn:timezone":"Europe/Tallinn","iso:country":"EE","lbl:bbox":"24.80944,58.13556,24.84944,58.17556","lbl:max_zoom":18,"lbl:min_zoom":13.5,"mz:hierarchy_label":1,"mz:is_current":1,"mz:min_zoom":12,"src:geom":"geonames","wof:belongsto":[85682981,102191581,1713309667,85633135,1713305705],"wof:breaches":[],"wof:concordances":{"gn:id":590035},"wof:country":"EE","wof:geomhash":"d9341aea3861981f53b3fc27b0a4cfae","wof:hierarchy":[{"continent_id":102191581,"country_id":85633135,"county_id":1713305705,"localadmin_id":1713309667,"locality_id":1260068269,"region_id":85682981}],"wof:id":1260068269,"wof:lang_x_official":["est"],"wof:lang_x_spoken":["est"],"wof:lastmodified":1596677731,"wof:name":"Napsu","wof:parent_id":1713309667,"wof:placetype":"locality","wof:repo":"whosonfirst-data-admin-ee","wof:superseded_by":[],"wof:supersedes":[],"wof:tags":[]},"bbox":[24.82944,58.15556,24.82944,58.15556],"geometry":{"coordinates":[24.82944,58.15556],"type":"Point"}}