{"id":1343673587,"type":"Feature","properties":{"edtf:cessation":"uuuu","edtf:inception":"uuuu","geom:area":0,"geom:area_square_m":0,"geom:bbox":"26.96806,58.99361,26.96806,58.99361","geom:latitude":58.99361,"geom:longitude":26.96806,"gn:admin1_code":"5.0","gn:admin2_code":"486.0","gn:admin3_code":"8819.0","gn:asciiname":"Vadi","gn:country_code":"EE","gn:dem":43,"gn:feature_class":"P","gn:feature_code":"PPL","gn:geonameid":587966,"gn:latitude":58.99361,"gn:longitude":26.96806,"gn:modification_date":"2017-11-25","gn:name":"Vadi","gn:population":0,"gn:timezone":"Europe/Tallinn","iso:country":"EE","lbl:bbox":"26.94806,58.97361,26.98806,59.01361","lbl:max_zoom":18,"lbl:min_zoom":13.5,"mz:hierarchy_label":1,"mz:is_current":1,"mz:min_zoom":12,"name:deu_x_preferred":["Vadi"],"name:est_x_preferred":["Vadi küla"],"name:fra_x_preferred":["Vadi"],"name:hye_x_preferred":["Վադի"],"name:pol_x_preferred":["Vadi"],"name:spa_x_preferred":["Vadi"],"name:vol_x_preferred":["Vadi küla"],"src:geom":"geonames","wof:belongsto":[85683059,102191581,1713312093,85633135,1713305677],"wof:breaches":[],"wof:concordances":{"gn:id":587966,"wk:page":"Vadi%2C_Estonia"},"wof:coterminous":[1713312093],"wof:country":"EE","wof:geomhash":"d2b47bf5c4703f2fa3e1718749d429cd","wof:hierarchy":[{"continent_id":102191581,"country_id":85633135,"county_id":1713305677,"localadmin_id":1713312093,"locality_id":1343673587,"region_id":85683059}],"wof:id":1343673587,"wof:lang_x_official":["est"],"wof:lang_x_spoken":["est"],"wof:lastmodified":1596661018,"wof:name":"Vadi","wof:parent_id":1713312093,"wof:placetype":"locality","wof:repo":"whosonfirst-data-admin-ee","wof:superseded_by":[],"wof:supersedes":[],"wof:tags":[]},"bbox":[26.96806,58.99361,26.96806,58.99361],"geometry":{"coordinates":[26.96806,58.99361],"type":"Point"}}