{"id":1326494575,"type":"Feature","properties":{"edtf:cessation":"uuuu","edtf:inception":"uuuu","geom:area":0,"geom:area_square_m":0,"geom:bbox":"26.96722,57.79472,26.96722,57.79472","geom:latitude":57.79472,"geom:longitude":26.96722,"gn:admin1_code":"21.0","gn:admin2_code":"917.0","gn:admin3_code":"3956.0","gn:asciiname":"Lalli","gn:country_code":"EE","gn:dem":101,"gn:feature_class":"P","gn:feature_code":"PPL","gn:geonameid":8620208,"gn:latitude":57.79472,"gn:longitude":26.96722,"gn:modification_date":"2017-11-25","gn:name":"Lalli","gn:population":0,"gn:timezone":"Europe/Tallinn","iso:country":"EE","lbl:bbox":"26.94722,57.77472,26.98722,57.81472","lbl:max_zoom":18,"lbl:min_zoom":13.5,"mz:hierarchy_label":1,"mz:is_current":1,"mz:min_zoom":12,"name:ara_x_preferred":["لالي"],"name:bel_x_preferred":["Лалі"],"name:deu_x_preferred":["Lalli"],"name:est_x_preferred":["Lalli"],"name:fin_x_preferred":["Lalli"],"name:fra_x_preferred":["Lalli"],"name:ita_x_preferred":["Lalli"],"name:rus_x_preferred":["Лалли"],"name:sco_x_preferred":["Lalli"],"name:spa_x_preferred":["Lalli"],"name:und_x_variant":["Lelli"],"src:geom":"geonames","wof:belongsto":[85682937,102191581,1713316469,85633135,1713305633],"wof:breaches":[],"wof:concordances":{"gn:id":8620208},"wof:country":"EE","wof:geomhash":"ea43a254b8a01e10fdaa3047793f0221","wof:hierarchy":[{"continent_id":102191581,"country_id":85633135,"county_id":1713305633,"localadmin_id":1713316469,"locality_id":1326494575,"region_id":85682937}],"wof:id":1326494575,"wof:lang_x_official":["est"],"wof:lang_x_spoken":["est"],"wof:lastmodified":1596660389,"wof:name":"Lalli","wof:parent_id":1713316469,"wof:placetype":"locality","wof:repo":"whosonfirst-data-admin-ee","wof:superseded_by":[],"wof:supersedes":[],"wof:tags":[]},"bbox":[26.96722,57.79472,26.96722,57.79472],"geometry":{"coordinates":[26.96722,57.79472],"type":"Point"}}