{"id":1126008727,"type":"Feature","properties":{"edtf:cessation":"uuuu","edtf:inception":"uuuu","geom:area":0,"geom:area_square_m":0,"geom:bbox":"26.04417,59.375,26.04417,59.375","geom:latitude":59.375,"geom:longitude":26.04417,"gn:country":"EE","gn:fcode":"PPL","gn:population":161,"iso:country":"EE","lbl:bbox":"26.02417,59.355,26.06417,59.395","lbl:latitude":59.375,"lbl:longitude":26.04417,"lbl:max_zoom":18,"lbl:min_zoom":13,"mz:hierarchy_label":1,"mz:is_current":1,"mz:min_zoom":11,"mz:note":"Quattroshapes Point Gazetteer import 20170519","name:ceb_x_preferred":["Vohnja"],"name:eng_x_preferred":["Vohnja"],"name:est_x_preferred":["Vohnja"],"name:hye_x_preferred":["Վոհնյա"],"name:nld_x_preferred":["Vohnja"],"name:swe_x_preferred":["Vohnja"],"name:vol_x_preferred":["Vohnja"],"qs_pg:aaroncc":"EE","qs_pg:gn_country":"EE","qs_pg:gn_fcode":"PPL","qs_pg:gn_id":587510,"qs_pg:gn_pop":161,"qs_pg:name":"Vohnja","qs_pg:name_adm0":"Eesti","qs_pg:name_adm1":"Lääne-Virumaa","qs_pg:photos_9k":1,"qs_pg:photos_9r":1,"qs_pg:photos_all":1,"qs_pg:photos_sr":0,"qs_pg:pop_sr":1,"qs_pg:qs_id":111216,"qs_pg:qs_pg_placetype":"locality","qs_pg:qs_pg_placetype_gp":"Town","qs_pg:woe_adm0":23424805,"qs_pg:woe_id":846540,"src:geom":"qs_pg","src:lbl_centroid":"qs_pg","src:population":"geonames","woe:adm0_id":23424805,"woe:name_adm0":"Eesti","woe:name_adm1":"Lääne-Virumaa","woe:placetype":"Town","wof:belongsto":[85683049,102191581,1713306107,85633135,1713305723],"wof:breaches":[],"wof:concordances":{"gn:id":587510,"gp:id":846540,"qs_pg:id":111216,"wd:id":"Q3462980"},"wof:coterminous":[1713306107],"wof:country":"EE","wof:created":1497300137,"wof:geomhash":"c2a05a1a5ae31bdc062a0c92b0fd8a42","wof:hierarchy":[{"continent_id":102191581,"country_id":85633135,"county_id":1713305723,"localadmin_id":1713306107,"locality_id":1126008727,"region_id":85683049}],"wof:id":1126008727,"wof:lang_x_official":["est"],"wof:lang_x_spoken":["est"],"wof:lastmodified":1596661738,"wof:name":"Vohnja","wof:parent_id":1713306107,"wof:placetype":"locality","wof:population":161,"wof:population_rank":1,"wof:repo":"whosonfirst-data-admin-ee","wof:superseded_by":[],"wof:supersedes":[],"wof:tags":[]},"bbox":[26.04417,59.375,26.04417,59.375],"geometry":{"coordinates":[26.04417,59.375],"type":"Point"}}