{"id":1243444999,"type":"Feature","properties":{"edtf:cessation":"uuuu","edtf:inception":"uuuu","geom:area":0,"geom:area_square_m":0,"geom:bbox":"26.15167,59.49028,26.15167,59.49028","geom:latitude":59.49028,"geom:longitude":26.15167,"gn:admin1_code":"8.0","gn:admin2_code":"191.0","gn:admin3_code":"4918.0","gn:asciiname":"Metsiku","gn:country_code":"EE","gn:dem":65,"gn:feature_class":"P","gn:feature_code":"PPL","gn:geonameid":590230,"gn:latitude":59.49028,"gn:longitude":26.15167,"gn:modification_date":"2017-11-25","gn:name":"Metsiku","gn:population":0,"gn:timezone":"Europe/Tallinn","iso:country":"EE","lbl:bbox":"26.13167,59.47028,26.17167,59.51028","lbl:max_zoom":18,"lbl:min_zoom":13.5,"mz:hierarchy_label":1,"mz:is_current":1,"mz:min_zoom":12,"name:eng_x_preferred":["Metsiku"],"name:est_x_preferred":["Metsiku"],"name:fra_x_preferred":["Metsiku"],"name:hye_x_preferred":["Մեցիկու"],"name:pol_x_preferred":["Metsiku"],"name:rus_x_preferred":["Метсику"],"name:vol_x_preferred":["Metsiku"],"src:geom":"geonames","wof:belongsto":[85683049,102191581,1713308127,85633135,1713305775],"wof:breaches":[],"wof:concordances":{"gn:id":590230,"wk:page":"Metsiku"},"wof:coterminous":[1713308127],"wof:country":"EE","wof:geomhash":"a44455d41fec1d72e84a54924b9460cd","wof:hierarchy":[{"continent_id":102191581,"country_id":85633135,"county_id":1713305775,"localadmin_id":1713308127,"locality_id":1243444999,"region_id":85683049}],"wof:id":1243444999,"wof:lang_x_official":["est"],"wof:lang_x_spoken":["est"],"wof:lastmodified":1596678048,"wof:name":"Metsiku","wof:parent_id":1713308127,"wof:placetype":"locality","wof:repo":"whosonfirst-data-admin-ee","wof:superseded_by":[],"wof:supersedes":[],"wof:tags":[]},"bbox":[26.15167,59.49028,26.15167,59.49028],"geometry":{"coordinates":[26.15167,59.49028],"type":"Point"}}