{"id":1243222665,"type":"Feature","properties":{"edtf:cessation":"uuuu","edtf:inception":"uuuu","geom:area":0,"geom:area_square_m":0,"geom:bbox":"26.88167,57.66583,26.88167,57.66583","geom:latitude":57.66583,"geom:longitude":26.88167,"gn:admin1_code":"21.0","gn:admin2_code":"698.0","gn:admin3_code":"4947.0","gn:asciiname":"Paerlijoe","gn:country_code":"EE","gn:dem":143,"gn:feature_class":"P","gn:feature_code":"PPL","gn:geonameid":794368,"gn:latitude":57.66583,"gn:longitude":26.88167,"gn:modification_date":"2017-11-25","gn:name":"Pärlijõe","gn:population":0,"gn:timezone":"Europe/Tallinn","iso:country":"EE","lbl:bbox":"26.86167,57.64583,26.90167,57.68583","lbl:max_zoom":18,"lbl:min_zoom":13.5,"mz:hierarchy_label":1,"mz:is_current":1,"mz:min_zoom":12,"name:est_x_preferred":["Pärlijõe"],"name:hye_x_preferred":["Պեռլիյիե"],"name:myv_x_preferred":["Пярлиыэ"],"name:pol_x_preferred":["Pärlijõe"],"name:spa_x_preferred":["Pärlijõe"],"name:ukr_x_preferred":["Пярлійие"],"name:vol_x_preferred":["Pärlijõe"],"src:geom":"geonames","wof:belongsto":[85682937,102191581,1713314813,85633135,1713305787],"wof:breaches":[],"wof:concordances":{"gn:id":794368,"wk:page":"P%C3%A4rlij%C3%B5e"},"wof:country":"EE","wof:geomhash":"1996e88c92bb3609506d45b598131a1d","wof:hierarchy":[{"continent_id":102191581,"country_id":85633135,"county_id":1713305787,"localadmin_id":1713314813,"locality_id":1243222665,"region_id":85682937}],"wof:id":1243222665,"wof:lang_x_official":["est"],"wof:lang_x_spoken":["est"],"wof:lastmodified":1596676897,"wof:name":"Paerlijoe","wof:parent_id":1713314813,"wof:placetype":"locality","wof:repo":"whosonfirst-data-admin-ee","wof:superseded_by":[],"wof:supersedes":[],"wof:tags":[]},"bbox":[26.88167,57.66583,26.88167,57.66583],"geometry":{"coordinates":[26.88167,57.66583],"type":"Point"}}