{"id":1326910573,"type":"Feature","properties":{"edtf:cessation":"uuuu","edtf:inception":"uuuu","geom:area":0,"geom:area_square_m":0,"geom:bbox":"27.25056,58.03806,27.25056,58.03806","geom:latitude":58.03806,"geom:longitude":27.25056,"gn:admin1_code":"12.0","gn:admin2_code":"708.0","gn:admin3_code":"9511.0","gn:asciiname":"Voiardi","gn:cc2":"EE","gn:country_code":"EE","gn:dem":63,"gn:feature_class":"P","gn:feature_code":"PPL","gn:geonameid":587507,"gn:latitude":58.03806,"gn:longitude":27.25056,"gn:modification_date":"2017-11-25","gn:name":"Võiardi","gn:population":0,"gn:timezone":"Europe/Tallinn","iso:country":"EE","lbl:bbox":"27.23056,58.01806,27.27056,58.05806","lbl:max_zoom":18,"lbl:min_zoom":13.5,"mz:hierarchy_label":1,"mz:is_current":1,"mz:min_zoom":12,"name:est_x_preferred":["Võiardi"],"name:hye_x_preferred":["Վիիառդի"],"name:spa_x_preferred":["Võiardi"],"name:ukr_x_preferred":["Виярді"],"name:und_x_variant":["Vyiardi","Võiardi Asundus"],"name:vol_x_preferred":["Võiardi"],"src:geom":"geonames","wof:belongsto":[85682955,102191581,1713310933,85633135,1713305793],"wof:breaches":[],"wof:concordances":{"gn:id":587507,"wk:page":"V%C3%B5iardi"},"wof:coterminous":[1713310933],"wof:country":"EE","wof:geomhash":"98cd8b81f7370f8178b2afd779b256b6","wof:hierarchy":[{"continent_id":102191581,"country_id":85633135,"county_id":1713305793,"localadmin_id":1713310933,"locality_id":1326910573,"region_id":85682955}],"wof:id":1326910573,"wof:lang_x_official":["est"],"wof:lang_x_spoken":["est"],"wof:lastmodified":1596677003,"wof:name":"Voiardi","wof:parent_id":1713310933,"wof:placetype":"locality","wof:repo":"whosonfirst-data-admin-ee","wof:superseded_by":[],"wof:supersedes":[],"wof:tags":[]},"bbox":[27.25056,58.03806,27.25056,58.03806],"geometry":{"coordinates":[27.25056,58.03806],"type":"Point"}}