{"id":1276852217,"type":"Feature","properties":{"edtf:cessation":"uuuu","edtf:inception":"uuuu","geom:area":0,"geom:area_square_m":0,"geom:bbox":"25.10944,58.66833,25.10944,58.66833","geom:latitude":58.66833,"geom:longitude":25.10944,"gn:admin1_code":"11.0","gn:admin2_code":"638.0","gn:admin3_code":"7186.0","gn:asciiname":"Rousa","gn:cc2":"EE","gn:country_code":"EE","gn:dem":40,"gn:feature_class":"P","gn:feature_code":"PPL","gn:geonameid":588940,"gn:latitude":58.66833,"gn:longitude":25.10944,"gn:modification_date":"2017-11-25","gn:name":"Rõusa","gn:population":0,"gn:timezone":"Europe/Tallinn","iso:country":"EE","lbl:bbox":"25.08944,58.64833,25.12944,58.68833","lbl:max_zoom":18,"lbl:min_zoom":13.5,"mz:hierarchy_label":1,"mz:is_current":1,"mz:min_zoom":12,"name:est_x_preferred":["Rõusa"],"name:hye_x_preferred":["Ռիուսա"],"name:pol_x_preferred":["Rõusa"],"name:spa_x_preferred":["Rõusa"],"name:und_x_variant":["Ryuza"],"name:vol_x_preferred":["Rõusa"],"src:geom":"geonames","wof:belongsto":[85682981,102191581,1713309229,85633135,1713305733],"wof:breaches":[],"wof:concordances":{"gn:id":588940,"wk:page":"R%C3%B5usa"},"wof:coterminous":[1713309229],"wof:country":"EE","wof:geomhash":"89312f5ddb21d92433344c175e42b064","wof:hierarchy":[{"continent_id":102191581,"country_id":85633135,"county_id":1713305733,"localadmin_id":1713309229,"locality_id":1276852217,"region_id":85682981}],"wof:id":1276852217,"wof:lang_x_official":["est"],"wof:lang_x_spoken":["est"],"wof:lastmodified":1596663429,"wof:name":"Rousa","wof:parent_id":1713309229,"wof:placetype":"locality","wof:repo":"whosonfirst-data-admin-ee","wof:superseded_by":[],"wof:supersedes":[],"wof:tags":[]},"bbox":[25.10944,58.66833,25.10944,58.66833],"geometry":{"coordinates":[25.10944,58.66833],"type":"Point"}}