{"id":1310164631,"type":"Feature","properties":{"edtf:cessation":"uuuu","edtf:inception":"uuuu","geom:area":0,"geom:area_square_m":0,"geom:bbox":"27.07583,57.59639,27.07583,57.59639","geom:latitude":57.59639,"geom:longitude":27.07583,"gn:admin1_code":"21.0","gn:admin2_code":"698.0","gn:admin3_code":"1262.0","gn:asciiname":"Andsumaee","gn:country_code":"EE","gn:dem":207,"gn:feature_class":"P","gn:feature_code":"PPL","gn:geonameid":8619712,"gn:latitude":57.59639,"gn:longitude":27.07583,"gn:modification_date":"2017-11-25","gn:name":"Andsumäe","gn:population":0,"gn:timezone":"Europe/Tallinn","iso:country":"EE","lbl:bbox":"27.05583,57.57639,27.09583,57.61639","lbl:max_zoom":18,"lbl:min_zoom":13.5,"mz:hierarchy_label":1,"mz:is_current":1,"mz:min_zoom":12,"name:und_x_variant":["Andsumäe","Antsumäe"],"src:geom":"geonames","wof:belongsto":[85682937,102191581,1713314743,85633135,1713305787],"wof:breaches":[],"wof:concordances":{"gn:id":8619712},"wof:coterminous":[1713314743],"wof:country":"EE","wof:geomhash":"efd2736fee62e4a0419a8eea9103c392","wof:hierarchy":[{"continent_id":102191581,"country_id":85633135,"county_id":1713305787,"localadmin_id":1713314743,"locality_id":1310164631,"region_id":85682937}],"wof:id":1310164631,"wof:lang_x_official":["est"],"wof:lang_x_spoken":["est"],"wof:lastmodified":1596676884,"wof:name":"Andsumaee","wof:parent_id":1713314743,"wof:placetype":"locality","wof:repo":"whosonfirst-data-admin-ee","wof:superseded_by":[],"wof:supersedes":[],"wof:tags":[]},"bbox":[27.07583,57.59639,27.07583,57.59639],"geometry":{"coordinates":[27.07583,57.59639],"type":"Point"}}