{"id":1259806397,"type":"Feature","properties":{"edtf:cessation":"uuuu","edtf:inception":"uuuu","geom:area":0,"geom:area_square_m":0,"geom:bbox":"26.62611,58.67667,26.62611,58.67667","geom:latitude":58.67667,"geom:longitude":26.62611,"gn:admin1_code":"5.0","gn:admin2_code":"247.0","gn:admin3_code":"1533.0","gn:asciiname":"Eerikvere","gn:country_code":"EE","gn:dem":98,"gn:feature_class":"P","gn:feature_code":"PPL","gn:geonameid":793333,"gn:latitude":58.67667,"gn:longitude":26.62611,"gn:modification_date":"2017-11-25","gn:name":"Eerikvere","gn:population":0,"gn:timezone":"Europe/Tallinn","iso:country":"EE","lbl:bbox":"26.60611,58.65667,26.64611,58.69667","lbl:max_zoom":18,"lbl:min_zoom":13.5,"mz:hierarchy_label":1,"mz:is_current":1,"mz:min_zoom":12,"name:est_x_preferred":["Eerikvere"],"name:hye_x_preferred":["Էեռիկվեռե"],"name:pol_x_preferred":["Eerikvere"],"name:spa_x_preferred":["Eerikvere"],"name:vol_x_preferred":["Eerikvere"],"src:geom":"geonames","wof:belongsto":[85683009,102191581,1713312287,85633135,1713305767],"wof:breaches":[],"wof:concordances":{"gn:id":793333,"wk:page":"Eerikvere"},"wof:coterminous":[1713312287],"wof:country":"EE","wof:geomhash":"49096d9846d02cf9ca4dbc9416f4323b","wof:hierarchy":[{"continent_id":102191581,"country_id":85633135,"county_id":1713305767,"localadmin_id":1713312287,"locality_id":1259806397,"region_id":85683009}],"wof:id":1259806397,"wof:lang_x_official":["est"],"wof:lang_x_spoken":["est"],"wof:lastmodified":1596676580,"wof:name":"Eerikvere","wof:parent_id":1713312287,"wof:placetype":"locality","wof:repo":"whosonfirst-data-admin-ee","wof:superseded_by":[],"wof:supersedes":[],"wof:tags":[]},"bbox":[26.62611,58.67667,26.62611,58.67667],"geometry":{"coordinates":[26.62611,58.67667],"type":"Point"}}