{"id":1293108297,"type":"Feature","properties":{"edtf:cessation":"uuuu","edtf:inception":"uuuu","geom:area":0,"geom:area_square_m":0,"geom:bbox":"25.59444,59.43111,25.59444,59.43111","geom:latitude":59.43111,"geom:longitude":25.59444,"gn:admin1_code":"1.0","gn:admin2_code":"353.0","gn:admin3_code":"7562.0","gn:asciiname":"Sigula","gn:country_code":"EE","gn:dem":73,"gn:feature_class":"P","gn:feature_code":"PPL","gn:geonameid":588698,"gn:latitude":59.43111,"gn:longitude":25.59444,"gn:modification_date":"2017-11-25","gn:name":"Sigula","gn:population":0,"gn:timezone":"Europe/Tallinn","iso:country":"EE","lbl:bbox":"25.57444,59.41111,25.61444,59.45111","lbl:max_zoom":18,"lbl:min_zoom":13.5,"mz:hierarchy_label":1,"mz:is_current":1,"mz:min_zoom":12,"name:est_x_preferred":["Sigula"],"name:fra_x_preferred":["Sigula"],"name:hye_x_preferred":["Սիգուլա"],"name:nld_x_preferred":["Sigula"],"name:pol_x_preferred":["Sigula"],"name:rus_x_preferred":["Сигула"],"name:spa_x_preferred":["Sigula"],"name:vol_x_preferred":["Sigula"],"src:geom":"geonames","wof:belongsto":[85683055,102191581,1713305993,85633135,1713305725],"wof:breaches":[],"wof:concordances":{"gn:id":588698,"wk:page":"Sigula"},"wof:coterminous":[1713305993],"wof:country":"EE","wof:geomhash":"726afc5147a99fd65795ff8a5704af06","wof:hierarchy":[{"continent_id":102191581,"country_id":85633135,"county_id":1713305725,"localadmin_id":1713305993,"locality_id":1293108297,"region_id":85683055}],"wof:id":1293108297,"wof:lang_x_official":["est"],"wof:lang_x_spoken":["est"],"wof:lastmodified":1596661846,"wof:name":"Sigula","wof:parent_id":1713305993,"wof:placetype":"locality","wof:repo":"whosonfirst-data-admin-ee","wof:superseded_by":[],"wof:supersedes":[],"wof:tags":[]},"bbox":[25.59444,59.43111,25.59444,59.43111],"geometry":{"coordinates":[25.59444,59.43111],"type":"Point"}}