{"id":1310485121,"type":"Feature","properties":{"edtf:cessation":"uuuu","edtf:inception":"uuuu","geom:area":0,"geom:area_square_m":0,"geom:bbox":"22.47833,58.33528,22.47833,58.33528","geom:latitude":58.33528,"geom:longitude":22.47833,"gn:admin1_code":"14.0","gn:admin2_code":"714.0","gn:admin3_code":"7543.0","gn:asciiname":"Sepa","gn:country_code":"EE","gn:dem":19,"gn:feature_class":"P","gn:feature_code":"PPL","gn:geonameid":588717,"gn:latitude":58.33528,"gn:longitude":22.47833,"gn:modification_date":"2017-11-25","gn:name":"Sepa","gn:population":0,"gn:timezone":"Europe/Tallinn","iso:country":"EE","lbl:bbox":"22.45833,58.31528,22.49833,58.35528","lbl:max_zoom":18,"lbl:min_zoom":13.5,"mz:hierarchy_label":1,"mz:is_current":1,"mz:min_zoom":12,"src:geom":"geonames","wof:belongsto":[85682947,102191581,1713306733,85633135,1713305627],"wof:breaches":[],"wof:concordances":{"gn:id":588717,"wk:page":"Sepa%2C_L%C3%A4%C3%A4ne-Saare_Parish"},"wof:coterminous":[1713306733],"wof:country":"EE","wof:geomhash":"51b0c41953bd908f48e3480e48096bf1","wof:hierarchy":[{"continent_id":102191581,"country_id":85633135,"county_id":1713305627,"localadmin_id":1713306733,"locality_id":1310485121,"region_id":85682947}],"wof:id":1310485121,"wof:lang_x_official":["est"],"wof:lang_x_spoken":["est"],"wof:lastmodified":1596674931,"wof:name":"Sepa","wof:parent_id":1713306733,"wof:placetype":"locality","wof:repo":"whosonfirst-data-admin-ee","wof:superseded_by":[],"wof:supersedes":[],"wof:tags":[]},"bbox":[22.47833,58.33528,22.47833,58.33528],"geometry":{"coordinates":[22.47833,58.33528],"type":"Point"}}