{"id":1259742155,"type":"Feature","properties":{"edtf:cessation":"uuuu","edtf:inception":"uuuu","geom:area":0,"geom:area_square_m":0,"geom:bbox":"26.56083,57.89194,26.56083,57.89194","geom:latitude":57.89194,"geom:longitude":26.56083,"gn:admin1_code":"21.0","gn:admin2_code":"142.0","gn:admin3_code":"8634.0","gn:asciiname":"Uhtjaerve","gn:country_code":"EE","gn:dem":115,"gn:feature_class":"P","gn:feature_code":"PPL","gn:geonameid":794451,"gn:latitude":57.89194,"gn:longitude":26.56083,"gn:modification_date":"2017-11-25","gn:name":"Uhtjärve","gn:population":0,"gn:timezone":"Europe/Tallinn","iso:country":"EE","lbl:bbox":"26.54083,57.87194,26.58083,57.91194","lbl:max_zoom":18,"lbl:min_zoom":13.5,"mz:hierarchy_label":1,"mz:is_current":1,"mz:min_zoom":12,"src:geom":"geonames","wof:belongsto":[85682937,102191581,1713310999,85633135,1713305795],"wof:breaches":[],"wof:concordances":{"gn:id":794451},"wof:coterminous":[1713310999],"wof:country":"EE","wof:geomhash":"4558968eea8abfc1e59c5380cab597ff","wof:hierarchy":[{"continent_id":102191581,"country_id":85633135,"county_id":1713305795,"localadmin_id":1713310999,"locality_id":1259742155,"region_id":85682937}],"wof:id":1259742155,"wof:lang_x_official":["est"],"wof:lang_x_spoken":["est"],"wof:lastmodified":1596677021,"wof:name":"Uhtjaerve","wof:parent_id":1713310999,"wof:placetype":"locality","wof:repo":"whosonfirst-data-admin-ee","wof:superseded_by":[],"wof:supersedes":[],"wof:tags":[]},"bbox":[26.56083,57.89194,26.56083,57.89194],"geometry":{"coordinates":[26.56083,57.89194],"type":"Point"}}