{"id":1292908173,"type":"Feature","properties":{"edtf:cessation":"uuuu","edtf:inception":"uuuu","geom:area":0,"geom:area_square_m":0,"geom:bbox":"26.1525,58.66056,26.1525,58.66056","geom:latitude":58.66056,"geom:longitude":26.1525,"gn:admin1_code":"5.0","gn:admin2_code":"618.0","gn:admin3_code":"6381.0","gn:asciiname":"Pudivere","gn:country_code":"EE","gn:dem":63,"gn:feature_class":"P","gn:feature_code":"PPL","gn:geonameid":794641,"gn:latitude":58.66056,"gn:longitude":26.1525,"gn:modification_date":"2017-11-25","gn:name":"Pudivere","gn:population":0,"gn:timezone":"Europe/Tallinn","iso:country":"EE","lbl:bbox":"26.1325,58.64056,26.1725,58.68056","lbl:max_zoom":18,"lbl:min_zoom":13.5,"mz:hierarchy_label":1,"mz:is_current":1,"mz:min_zoom":12,"name:est_x_preferred":["Pudivere"],"name:pol_x_preferred":["Pudivere"],"name:vol_x_preferred":["Pudivere"],"src:geom":"geonames","wof:belongsto":[85683009,102191581,1713312187,85633135,1713305657],"wof:breaches":[],"wof:concordances":{"gn:id":794641},"wof:country":"EE","wof:geomhash":"12be195662b438d7d2a1c35537e76d44","wof:hierarchy":[{"continent_id":102191581,"country_id":85633135,"county_id":1713305657,"localadmin_id":1713312187,"locality_id":1292908173,"region_id":85683009}],"wof:id":1292908173,"wof:lang_x_official":["est"],"wof:lang_x_spoken":["est"],"wof:lastmodified":1596676502,"wof:name":"Pudivere","wof:parent_id":1713312187,"wof:placetype":"locality","wof:repo":"whosonfirst-data-admin-ee","wof:superseded_by":[],"wof:supersedes":[],"wof:tags":[]},"bbox":[26.1525,58.66056,26.1525,58.66056],"geometry":{"coordinates":[26.1525,58.66056],"type":"Point"}}