{"id":1327309639,"type":"Feature","properties":{"edtf:cessation":"uuuu","edtf:inception":"uuuu","geom:area":0,"geom:area_square_m":0,"geom:bbox":"26.26722,58.14333,26.26722,58.14333","geom:latitude":58.14333,"geom:longitude":26.26722,"gn:admin1_code":"18.0","gn:admin2_code":"171.0","gn:admin3_code":"3738.0","gn:asciiname":"Mudsi","gn:country_code":"EE","gn:dem":95,"gn:feature_class":"P","gn:feature_code":"PPL","gn:geonameid":8620494,"gn:latitude":58.14333,"gn:longitude":26.26722,"gn:modification_date":"2017-11-25","gn:name":"Mudsi","gn:population":0,"gn:timezone":"Europe/Tallinn","iso:country":"EE","lbl:bbox":"26.24722,58.12333,26.28722,58.16333","lbl:max_zoom":18,"lbl:min_zoom":13.5,"mz:hierarchy_label":1,"mz:is_current":1,"mz:min_zoom":12,"src:geom":"geonames","wof:belongsto":[85682995,102191581,1713310241,85633135,1713305757],"wof:breaches":[],"wof:concordances":{"gn:id":8620494},"wof:country":"EE","wof:geomhash":"6c554a690bd4d842129bb4d26dfcff31","wof:hierarchy":[{"continent_id":102191581,"country_id":85633135,"county_id":1713305757,"localadmin_id":1713310241,"locality_id":1327309639,"region_id":85682995}],"wof:id":1327309639,"wof:lang_x_official":["est"],"wof:lang_x_spoken":["est"],"wof:lastmodified":1596661920,"wof:name":"Mudsi","wof:parent_id":1713310241,"wof:placetype":"locality","wof:repo":"whosonfirst-data-admin-ee","wof:superseded_by":[],"wof:supersedes":[],"wof:tags":[]},"bbox":[26.26722,58.14333,26.26722,58.14333],"geometry":{"coordinates":[26.26722,58.14333],"type":"Point"}}