{"id":1343626059,"type":"Feature","properties":{"edtf:cessation":"uuuu","edtf:inception":"uuuu","geom:area":0,"geom:area_square_m":0,"geom:bbox":"27.10556,57.92778,27.10556,57.92778","geom:latitude":57.92778,"geom:longitude":27.10556,"gn:admin1_code":"21.0","gn:admin2_code":"917.0","gn:admin3_code":"6255.0","gn:asciiname":"Pille","gn:country_code":"EE","gn:dem":86,"gn:feature_class":"P","gn:feature_code":"PPL","gn:geonameid":589436,"gn:latitude":57.92778,"gn:longitude":27.10556,"gn:modification_date":"2017-11-25","gn:name":"Pille","gn:population":0,"gn:timezone":"Europe/Tallinn","iso:country":"EE","lbl:bbox":"27.08556,57.90778,27.12556,57.94778","lbl:max_zoom":18,"lbl:min_zoom":13.5,"mz:hierarchy_label":1,"mz:is_current":1,"mz:min_zoom":12,"name:est_x_preferred":["Pille"],"name:hye_x_preferred":["Պիլլե"],"name:spa_x_preferred":["Pille"],"name:swe_x_preferred":["Pille"],"name:ukr_x_preferred":["Пілле"],"name:vol_x_preferred":["Pille"],"src:geom":"geonames","wof:belongsto":[85682937,102191581,1713315873,85633135,1713305633],"wof:breaches":[],"wof:concordances":{"gn:id":589436,"wk:page":"Pille"},"wof:coterminous":[1713315873],"wof:country":"EE","wof:geomhash":"873ee593862d9171a64476ac0ca27f1e","wof:hierarchy":[{"continent_id":102191581,"country_id":85633135,"county_id":1713305633,"localadmin_id":1713315873,"locality_id":1343626059,"region_id":85682937}],"wof:id":1343626059,"wof:lang_x_official":["est"],"wof:lang_x_spoken":["est"],"wof:lastmodified":1596660398,"wof:name":"Pille","wof:parent_id":1713315873,"wof:placetype":"locality","wof:repo":"whosonfirst-data-admin-ee","wof:superseded_by":[],"wof:supersedes":[],"wof:tags":[]},"bbox":[27.10556,57.92778,27.10556,57.92778],"geometry":{"coordinates":[27.10556,57.92778],"type":"Point"}}