{"id":1193257763,"type":"Feature","properties":{"edtf:cessation":"uuuu","edtf:inception":"uuuu","geom:area":0,"geom:area_square_m":0,"geom:bbox":"24.33028,58.73417,24.33028,58.73417","geom:latitude":58.73417,"geom:longitude":24.33028,"gn:admin1_code":"13.0","gn:admin2_code":"503.0","gn:admin3_code":"8834.0","gn:asciiname":"Vaguja","gn:country_code":"EE","gn:dem":16,"gn:feature_class":"P","gn:feature_code":"PPL","gn:geonameid":587958,"gn:latitude":58.73417,"gn:longitude":24.33028,"gn:modification_date":"2017-11-25","gn:name":"Vaguja","gn:population":0,"gn:timezone":"Europe/Tallinn","iso:country":"EE","lbl:bbox":"24.31028,58.71417,24.35028,58.75417","lbl:max_zoom":18,"lbl:min_zoom":13.5,"mz:hierarchy_label":1,"mz:is_current":1,"mz:min_zoom":12,"name:est_x_preferred":["Vaguja"],"name:fin_x_preferred":["Vaguja"],"name:hye_x_preferred":["Վագույա"],"name:pol_x_preferred":["Vaguja"],"name:sco_x_preferred":["Vaguja"],"name:spa_x_preferred":["Vaguja"],"name:und_x_variant":["Vaguya"],"name:vol_x_preferred":["Vaguja"],"src:geom":"geonames","wof:belongsto":[85683013,102191581,1713311151,85633135,1713305747],"wof:breaches":[],"wof:concordances":{"gn:id":587958,"wk:page":"Vaguja"},"wof:coterminous":[1713311151],"wof:country":"EE","wof:geomhash":"7e1cfbc5c8bb5725a112a1f3206be37f","wof:hierarchy":[{"continent_id":102191581,"country_id":85633135,"county_id":1713305747,"localadmin_id":1713311151,"locality_id":1193257763,"region_id":85683013}],"wof:id":1193257763,"wof:lang_x_official":["est"],"wof:lang_x_spoken":["est"],"wof:lastmodified":1596662845,"wof:name":"Vaguja","wof:parent_id":1713311151,"wof:placetype":"locality","wof:repo":"whosonfirst-data-admin-ee","wof:superseded_by":[],"wof:supersedes":[],"wof:tags":[]},"bbox":[24.33028,58.73417,24.33028,58.73417],"geometry":{"coordinates":[24.33028,58.73417],"type":"Point"}}