{"id":1243038809,"type":"Feature","properties":{"edtf:cessation":"uuuu","edtf:inception":"uuuu","geom:area":0,"geom:area_square_m":0,"geom:bbox":"22.93,58.57778,22.93,58.57778","geom:latitude":58.57778,"geom:longitude":22.93,"gn:admin1_code":"14.0","gn:admin2_code":"714.0","gn:admin3_code":"9804.0","gn:asciiname":"Moriku","gn:country_code":"EE","gn:dem":13,"gn:feature_class":"P","gn:feature_code":"PPL","gn:geonameid":589818,"gn:latitude":58.57778,"gn:longitude":22.93,"gn:modification_date":"2017-11-25","gn:name":"Moriku","gn:population":0,"gn:timezone":"Europe/Tallinn","iso:country":"EE","lbl:bbox":"22.91,58.55778,22.95,58.59778","lbl:max_zoom":18,"lbl:min_zoom":13.5,"mz:hierarchy_label":1,"mz:is_current":1,"mz:min_zoom":12,"name:ara_x_preferred":["إيريكو"],"name:deu_x_preferred":["Ööriku"],"name:est_x_preferred":["Ööriku"],"name:fra_x_preferred":["Ööriku"],"name:hye_x_preferred":["Օոռիկու"],"name:nld_x_preferred":["Ööriku"],"name:pol_x_preferred":["Ööriku"],"name:spa_x_preferred":["Ööriku"],"name:und_x_variant":["Eriku","Moriku"],"name:vol_x_preferred":["Ööriku"],"src:geom":"geonames","wof:belongsto":[85682947,102191581,1713308165,85633135,1713305627],"wof:breaches":[],"wof:concordances":{"gn:id":589818,"wk:page":"%C3%96%C3%B6riku"},"wof:coterminous":[1713308165],"wof:country":"EE","wof:geomhash":"c94705c4359495abfe0fe3f95082efe0","wof:hierarchy":[{"continent_id":102191581,"country_id":85633135,"county_id":1713305627,"localadmin_id":1713308165,"locality_id":1243038809,"region_id":85682947}],"wof:id":1243038809,"wof:lang_x_official":["est"],"wof:lang_x_spoken":["est"],"wof:lastmodified":1596674965,"wof:name":"Moriku","wof:parent_id":1713308165,"wof:placetype":"locality","wof:repo":"whosonfirst-data-admin-ee","wof:superseded_by":[],"wof:supersedes":[],"wof:tags":[]},"bbox":[22.93,58.57778,22.93,58.57778],"geometry":{"coordinates":[22.93,58.57778],"type":"Point"}}