{"id":1260363665,"type":"Feature","properties":{"edtf:cessation":"uuuu","edtf:inception":"uuuu","geom:area":0,"geom:area_square_m":0,"geom:bbox":"27.39889,57.76056,27.39889,57.76056","geom:latitude":57.76056,"geom:longitude":27.39889,"gn:admin1_code":"21.0","gn:admin2_code":"732.0","gn:admin3_code":"4571.0","gn:asciiname":"Lutja","gn:country_code":"EE","gn:dem":150,"gn:feature_class":"P","gn:feature_code":"PPL","gn:geonameid":8620134,"gn:latitude":57.76056,"gn:longitude":27.39889,"gn:modification_date":"2017-11-25","gn:name":"Lutja","gn:population":0,"gn:timezone":"Europe/Tallinn","iso:country":"EE","lbl:bbox":"27.37889,57.74056,27.41889,57.78056","lbl:max_zoom":18,"lbl:min_zoom":13.5,"mz:hierarchy_label":1,"mz:is_current":1,"mz:min_zoom":12,"src:geom":"geonames","wof:belongsto":[85682955,102191581,1713316133,85633135,1713305631],"wof:breaches":[],"wof:concordances":{"gn:id":8620134},"wof:coterminous":[1713316133],"wof:country":"EE","wof:geomhash":"7cd51f8294de4a790b2b4e791743e7ee","wof:hierarchy":[{"continent_id":102191581,"country_id":85633135,"county_id":1713305631,"localadmin_id":1713316133,"locality_id":1260363665,"region_id":85682955}],"wof:id":1260363665,"wof:lang_x_official":["est"],"wof:lang_x_spoken":["est"],"wof:lastmodified":1596663695,"wof:name":"Lutja","wof:parent_id":1713316133,"wof:placetype":"locality","wof:repo":"whosonfirst-data-admin-ee","wof:superseded_by":[],"wof:supersedes":[],"wof:tags":[]},"bbox":[27.39889,57.76056,27.39889,57.76056],"geometry":{"coordinates":[27.39889,57.76056],"type":"Point"}}