{"id":1260290881,"type":"Feature","properties":{"edtf:cessation":"uuuu","edtf:inception":"uuuu","geom:area":0,"geom:area_square_m":0,"geom:bbox":"25.43444,59.06083,25.43444,59.06083","geom:latitude":59.06083,"geom:longitude":25.43444,"gn:admin1_code":"4.0","gn:admin2_code":"567.0","gn:admin3_code":"5083.0","gn:asciiname":"Mustla","gn:country_code":"EE","gn:dem":84,"gn:feature_class":"P","gn:feature_code":"PPL","gn:geonameid":590075,"gn:latitude":59.06083,"gn:longitude":25.43444,"gn:modification_date":"2017-11-25","gn:name":"Mustla","gn:population":0,"gn:timezone":"Europe/Tallinn","iso:country":"EE","lbl:bbox":"25.41444,59.04083,25.45444,59.08083","lbl:max_zoom":18,"lbl:min_zoom":13.5,"mz:hierarchy_label":1,"mz:is_current":1,"mz:min_zoom":12,"name:ceb_x_preferred":["Mustla"],"name:ces_x_preferred":["Mustla"],"name:est_x_preferred":["Mustla"],"name:fra_x_preferred":["Mustla"],"name:hye_x_preferred":["Մուստլա"],"name:lit_x_preferred":["Mustla"],"name:rus_x_preferred":["Мустла"],"name:spa_x_preferred":["Mustla"],"name:swe_x_preferred":["Mustla"],"name:ukr_x_preferred":["Мустла"],"name:vol_x_preferred":["Mustla"],"name:zho_x_preferred":["穆斯特拉"],"src:geom":"geonames","wof:belongsto":[85683031,102191581,1713313261,85633135,1713305663],"wof:breaches":[],"wof:concordances":{"gn:id":590075},"wof:coterminous":[1713313261],"wof:country":"EE","wof:geomhash":"84cfcb24b1788466706e4673062af247","wof:hierarchy":[{"continent_id":102191581,"country_id":85633135,"county_id":1713305663,"localadmin_id":1713313261,"locality_id":1260290881,"region_id":85683031}],"wof:id":1260290881,"wof:lang_x_official":["est"],"wof:lang_x_spoken":["est"],"wof:lastmodified":1596661327,"wof:name":"Mustla","wof:parent_id":1713313261,"wof:placetype":"locality","wof:repo":"whosonfirst-data-admin-ee","wof:superseded_by":[],"wof:supersedes":[],"wof:tags":[]},"bbox":[25.43444,59.06083,25.43444,59.06083],"geometry":{"coordinates":[25.43444,59.06083],"type":"Point"}}