{"id":1126008421,"type":"Feature","properties":{"edtf:cessation":"uuuu","edtf:inception":"uuuu","geom:area":0,"geom:area_square_m":0,"geom:bbox":"22.26194,58.14611,22.26194,58.14611","geom:latitude":58.14611,"geom:longitude":22.26194,"gn:country":"EE","gn:fcode":"PPL","gn:population":109,"iso:country":"EE","lbl:bbox":"22.24194,58.12611,22.28194,58.16611","lbl:latitude":58.14611,"lbl:longitude":22.26194,"lbl:max_zoom":18,"lbl:min_zoom":13,"mz:hierarchy_label":1,"mz:is_current":1,"mz:min_zoom":11,"mz:note":"Quattroshapes Point Gazetteer import 20170519","name:ceb_x_preferred":["Läätsa"],"name:deu_x_preferred":["Läätsa"],"name:eng_x_preferred":["Läätsa"],"name:est_x_preferred":["Läätsa"],"name:hye_x_preferred":["Լեեցա"],"name:nld_x_preferred":["Läätsa"],"name:pol_x_preferred":["Läätsa"],"name:spa_x_preferred":["Läätsa"],"name:swe_x_preferred":["Läätsa"],"name:ukr_x_preferred":["Ляятса"],"name:urd_x_preferred":["لاٹسا"],"name:vol_x_preferred":["Läätsa"],"qs_pg:aaroncc":"EE","qs_pg:gn_country":"EE","qs_pg:gn_fcode":"PPL","qs_pg:gn_id":794656,"qs_pg:gn_pop":109,"qs_pg:name":"Läätsa","qs_pg:name_adm0":"Eesti","qs_pg:name_adm1":"Saaremaa","qs_pg:photos_9k":1,"qs_pg:photos_9r":1,"qs_pg:photos_all":2,"qs_pg:photos_sr":0,"qs_pg:pop_sr":1,"qs_pg:qs_id":111056,"qs_pg:qs_pg_placetype":"locality","qs_pg:qs_pg_placetype_gp":"Town","qs_pg:woe_adm0":23424805,"qs_pg:woe_id":843460,"src:geom":"qs_pg","src:lbl_centroid":"qs_pg","src:population":"geonames","woe:adm0_id":23424805,"woe:name_adm0":"Eesti","woe:name_adm1":"Saaremaa","woe:placetype":"Town","wof:belongsto":[102191581,85633135],"wof:breaches":[],"wof:concordances":{"gn:id":794656,"gp:id":843460,"qs_pg:id":111056,"wd:id":"Q2062084"},"wof:coterminous":[1713307123],"wof:country":"EE","wof:created":1497300120,"wof:geomhash":"080914b450198d3a1ac50b14984e5041","wof:hierarchy":[{"continent_id":102191581,"country_id":85633135,"locality_id":1126008421,"region_id":-1}],"wof:id":1126008421,"wof:lang_x_official":["est"],"wof:lang_x_spoken":["est"],"wof:lastmodified":1596130295,"wof:name":"Läätsa","wof:parent_id":-1,"wof:placetype":"locality","wof:population":109,"wof:population_rank":1,"wof:repo":"whosonfirst-data-admin-ee","wof:superseded_by":[],"wof:supersedes":[],"wof:tags":[]},"bbox":[22.26194,58.14611,22.26194,58.14611],"geometry":{"coordinates":[22.26194,58.14611],"type":"Point"}}