{"id":1209081351,"type":"Feature","properties":{"edtf:cessation":"uuuu","edtf:inception":"uuuu","geom:area":0,"geom:area_square_m":0,"geom:bbox":"25.90583,57.93389,25.90583,57.93389","geom:latitude":57.93389,"geom:longitude":25.90583,"gn:admin1_code":"19.0","gn:admin2_code":"824.0","gn:admin3_code":"2187.0","gn:asciiname":"Asu","gn:country_code":"EE","gn:dem":77,"gn:feature_class":"P","gn:feature_code":"PPL","gn:geonameid":592372,"gn:latitude":57.93389,"gn:longitude":25.90583,"gn:modification_date":"2017-11-25","gn:name":"Asu","gn:population":0,"gn:timezone":"Europe/Tallinn","iso:country":"EE","lbl:bbox":"25.88583,57.91389,25.92583,57.95389","lbl:max_zoom":18,"lbl:min_zoom":13.5,"mz:hierarchy_label":1,"mz:is_current":1,"mz:min_zoom":12,"name:und_x_variant":["Myza Azu","Asumaa","Asu"],"src:geom":"geonames","wof:belongsto":[85682941,102191581,1713310399,85633135,1713305687],"wof:breaches":[],"wof:concordances":{"gn:id":592372},"wof:country":"EE","wof:geomhash":"92f536344bd3435bf596436247afde65","wof:hierarchy":[{"continent_id":102191581,"country_id":85633135,"county_id":1713305687,"localadmin_id":1713310399,"locality_id":1209081351,"region_id":85682941}],"wof:id":1209081351,"wof:lang_x_official":["est"],"wof:lang_x_spoken":["est"],"wof:lastmodified":1596661435,"wof:name":"Asu","wof:parent_id":1713310399,"wof:placetype":"locality","wof:repo":"whosonfirst-data-admin-ee","wof:superseded_by":[],"wof:supersedes":[],"wof:tags":[]},"bbox":[25.90583,57.93389,25.90583,57.93389],"geometry":{"coordinates":[25.90583,57.93389],"type":"Point"}}