{"id":1242756733,"type":"Feature","properties":{"edtf:cessation":"uuuu","edtf:inception":"uuuu","geom:area":0,"geom:area_square_m":0,"geom:bbox":"22.43083,58.36611,22.43083,58.36611","geom:latitude":58.36611,"geom:longitude":22.43083,"gn:admin1_code":"14.0","gn:admin2_code":"714.0","gn:admin3_code":"9045.0","gn:asciiname":"Endla","gn:country_code":"EE","gn:dem":24,"gn:feature_class":"P","gn:feature_code":"PPL","gn:geonameid":592270,"gn:latitude":58.36611,"gn:longitude":22.43083,"gn:modification_date":"2017-11-25","gn:name":"Endla","gn:population":0,"gn:timezone":"Europe/Tallinn","iso:country":"EE","lbl:bbox":"22.41083,58.34611,22.45083,58.38611","lbl:max_zoom":18,"lbl:min_zoom":13.5,"mz:hierarchy_label":1,"mz:is_current":1,"mz:min_zoom":12,"name:deu_x_preferred":["Endla"],"name:est_x_preferred":["Endla"],"name:fra_x_preferred":["Endla"],"name:hye_x_preferred":["Էնդլա"],"name:nld_x_preferred":["Endla"],"name:pol_x_preferred":["Endla"],"name:spa_x_preferred":["Endla"],"name:ukr_x_preferred":["Ендла"],"name:vol_x_preferred":["Endla"],"src:geom":"geonames","wof:belongsto":[85682947,102191581,1713308491,85633135,1713305627],"wof:breaches":[],"wof:concordances":{"gn:id":592270,"wk:page":"Endla%2C_Saare_County"},"wof:coterminous":[1713307461],"wof:country":"EE","wof:geomhash":"f074b00937116697f619d8c4e317ff4e","wof:hierarchy":[{"continent_id":102191581,"country_id":85633135,"county_id":1713305627,"localadmin_id":1713308491,"locality_id":1242756733,"region_id":85682947}],"wof:id":1242756733,"wof:lang_x_official":["est"],"wof:lang_x_spoken":["est"],"wof:lastmodified":1596674921,"wof:name":"Endla","wof:parent_id":1713308491,"wof:placetype":"locality","wof:repo":"whosonfirst-data-admin-ee","wof:superseded_by":[],"wof:supersedes":[],"wof:tags":[]},"bbox":[22.43083,58.36611,22.43083,58.36611],"geometry":{"coordinates":[22.43083,58.36611],"type":"Point"}}