{"id":1326495055,"type":"Feature","properties":{"edtf:cessation":"uuuu","edtf:inception":"uuuu","geom:area":0,"geom:area_square_m":0,"geom:bbox":"25.93278,58.37333,25.93278,58.37333","geom:latitude":58.37333,"geom:longitude":25.93278,"gn:admin1_code":"20.0","gn:admin2_code":"899.0","gn:admin3_code":"6956.0","gn:asciiname":"Ridakuela","gn:country_code":"EE","gn:dem":47,"gn:feature_class":"P","gn:feature_code":"PPL","gn:geonameid":589043,"gn:latitude":58.37333,"gn:longitude":25.93278,"gn:modification_date":"2017-11-25","gn:name":"Ridaküla","gn:population":0,"gn:timezone":"Europe/Tallinn","iso:country":"EE","lbl:bbox":"25.91278,58.35333,25.95278,58.39333","lbl:max_zoom":18,"lbl:min_zoom":13.5,"mz:hierarchy_label":1,"mz:is_current":1,"mz:min_zoom":12,"name:und_x_variant":["Ridakyula","Ridaküla"],"src:geom":"geonames","wof:belongsto":[85682985,102191581,1713309817,85633135,1713305669],"wof:breaches":[],"wof:concordances":{"gn:id":589043},"wof:coterminous":[1713309817],"wof:country":"EE","wof:geomhash":"d91fe071561b0d6389cc114120e74ee7","wof:hierarchy":[{"continent_id":102191581,"country_id":85633135,"county_id":1713305669,"localadmin_id":1713309817,"locality_id":1326495055,"region_id":85682985}],"wof:id":1326495055,"wof:lang_x_official":["est"],"wof:lang_x_spoken":["est"],"wof:lastmodified":1596661250,"wof:name":"Ridakuela","wof:parent_id":1713309817,"wof:placetype":"locality","wof:repo":"whosonfirst-data-admin-ee","wof:superseded_by":[],"wof:supersedes":[],"wof:tags":[]},"bbox":[25.93278,58.37333,25.93278,58.37333],"geometry":{"coordinates":[25.93278,58.37333],"type":"Point"}}