{"id":1259959097,"type":"Feature","properties":{"edtf:cessation":"uuuu","edtf:inception":"uuuu","geom:area":0,"geom:area_square_m":0,"geom:bbox":"24.615,59.13833,24.615,59.13833","geom:latitude":59.13833,"geom:longitude":24.615,"gn:admin1_code":"13.0","gn:admin2_code":"317.0","gn:admin3_code":"6140.0","gn:asciiname":"Oru","gn:country_code":"EE","gn:dem":73,"gn:feature_class":"P","gn:feature_code":"PPL","gn:geonameid":589788,"gn:latitude":59.13833,"gn:longitude":24.615,"gn:modification_date":"2017-11-25","gn:name":"Oru","gn:population":0,"gn:timezone":"Europe/Tallinn","iso:country":"EE","lbl:bbox":"24.595,59.11833,24.635,59.15833","lbl:max_zoom":18,"lbl:min_zoom":13.5,"mz:hierarchy_label":1,"mz:is_current":1,"mz:min_zoom":12,"name:ceb_x_preferred":["Oru"],"name:ces_x_preferred":["Oru"],"name:est_x_preferred":["Oru"],"name:nld_x_preferred":["Oru"],"name:pol_x_preferred":["Oru"],"name:ron_x_preferred":["Oru"],"name:rus_x_preferred":["Ору"],"name:swe_x_preferred":["Oru"],"name:ukr_x_preferred":["Ору"],"name:vol_x_preferred":["Oru"],"src:geom":"geonames","wof:belongsto":[85683013,102191581,1713313541,85633135,1713305707],"wof:breaches":[],"wof:concordances":{"gn:id":589788},"wof:country":"EE","wof:geomhash":"7d42b9facddb160028901db97217fc4f","wof:hierarchy":[{"continent_id":102191581,"country_id":85633135,"county_id":1713305707,"localadmin_id":1713313541,"locality_id":1259959097,"region_id":85683013}],"wof:id":1259959097,"wof:lang_x_official":["est"],"wof:lang_x_spoken":["est"],"wof:lastmodified":1596677036,"wof:name":"Oru","wof:parent_id":1713313541,"wof:placetype":"locality","wof:repo":"whosonfirst-data-admin-ee","wof:superseded_by":[],"wof:supersedes":[],"wof:tags":[]},"bbox":[24.615,59.13833,24.615,59.13833],"geometry":{"coordinates":[24.615,59.13833],"type":"Point"}}