{"id":1260368351,"type":"Feature","properties":{"edtf:cessation":"uuuu","edtf:inception":"uuuu","geom:area":0,"geom:area_square_m":0,"geom:bbox":"24.41611,57.945,24.41611,57.945","geom:latitude":57.945,"geom:longitude":24.41611,"gn:admin1_code":"11.0","gn:admin2_code":"214.0","gn:admin3_code":"5706.0","gn:asciiname":"Moisakuela","gn:country_code":"EE","gn:dem":10,"gn:feature_class":"P","gn:feature_code":"PPL","gn:geonameid":590189,"gn:latitude":57.945,"gn:longitude":24.41611,"gn:modification_date":"2017-11-25","gn:name":"M천isak체la","gn:population":0,"gn:timezone":"Europe/Tallinn","iso:country":"EE","lbl:bbox":"24.39611,57.925,24.43611,57.965","lbl:max_zoom":18,"lbl:min_zoom":13.5,"mz:hierarchy_label":1,"mz:is_current":1,"mz:min_zoom":12,"name:und_x_variant":["Moisa","M천isak체la"],"src:geom":"geonames","wof:belongsto":[85682981,102191581,1713309245,85633135,1713305741],"wof:breaches":[],"wof:concordances":{"gn:id":590189},"wof:country":"EE","wof:geomhash":"99d437ee710c157176c03163c06fee62","wof:hierarchy":[{"continent_id":102191581,"country_id":85633135,"county_id":1713305741,"localadmin_id":1713309245,"locality_id":1260368351,"region_id":85682981}],"wof:id":1260368351,"wof:lang_x_official":["est"],"wof:lang_x_spoken":["est"],"wof:lastmodified":1596663208,"wof:name":"Moisakuela","wof:parent_id":1713309245,"wof:placetype":"locality","wof:repo":"whosonfirst-data-admin-ee","wof:superseded_by":[],"wof:supersedes":[],"wof:tags":[]},"bbox":[24.41611,57.945,24.41611,57.945],"geometry":{"coordinates":[24.41611,57.945],"type":"Point"}}