{"id":1293179797,"type":"Feature","properties":{"edtf:cessation":"uuuu","edtf:inception":"uuuu","geom:area":0,"geom:area_square_m":0,"geom:bbox":"22.79194,58.40861,22.79194,58.40861","geom:latitude":58.40861,"geom:longitude":22.79194,"gn:admin1_code":"14.0","gn:admin2_code":"714.0","gn:admin3_code":"8951.0","gn:asciiname":"Valayala","gn:cc2":"EE","gn:country_code":"EE","gn:dem":14,"gn:feature_class":"P","gn:feature_code":"PPL","gn:geonameid":607492,"gn:latitude":58.40861,"gn:longitude":22.79194,"gn:modification_date":"2017-11-25","gn:name":"Valayala","gn:population":0,"gn:timezone":"Europe/Tallinn","iso:country":"EE","lbl:bbox":"22.77194,58.38861,22.81194,58.42861","lbl:max_zoom":18,"lbl:min_zoom":13.5,"mz:hierarchy_label":1,"mz:is_current":1,"mz:is_funky":1,"mz:min_zoom":12,"name:ceb_x_preferred":["Valjala"],"name:ces_x_preferred":["Valjala"],"name:deu_x_preferred":["Valjala"],"name:est_x_preferred":["Valjala"],"name:fra_x_preferred":["Valjala"],"name:hye_x_preferred":["Վալյալա"],"name:pol_x_preferred":["Valjala"],"name:spa_x_preferred":["Valjala"],"name:srp_x_preferred":["Ваљала"],"name:swe_x_preferred":["Valjala"],"name:und_x_variant":["Valayala"],"name:vol_x_preferred":["Valjala"],"name:zho_x_preferred":["瓦利亞拉"],"src:geom":"geonames","wof:belongsto":[85682947,102191581,1713308483,85633135,1713305627],"wof:breaches":[],"wof:concordances":{"gn:id":607492,"wk:page":"Valjala"},"wof:country":"EE","wof:geomhash":"866ed928f5c46989b24ed6a3feaa0693","wof:hierarchy":[{"continent_id":102191581,"country_id":85633135,"county_id":1713305627,"localadmin_id":1713308483,"locality_id":1293179797,"region_id":85682947}],"wof:id":1293179797,"wof:lang_x_official":["est"],"wof:lang_x_spoken":["est"],"wof:lastmodified":1596674958,"wof:name":"Valayala","wof:parent_id":1713308483,"wof:placetype":"locality","wof:repo":"whosonfirst-data-admin-ee","wof:superseded_by":[],"wof:supersedes":[],"wof:tags":[]},"bbox":[22.79194,58.40861,22.79194,58.40861],"geometry":{"coordinates":[22.79194,58.40861],"type":"Point"}}