{"id":1126037725,"type":"Feature","properties":{"edtf:cessation":"uuuu","edtf:inception":"uuuu","geom:area":0,"geom:area_square_m":0,"geom:bbox":"24.98056,59.18778,24.98056,59.18778","geom:latitude":59.18778,"geom:longitude":24.98056,"gn:country":"EE","gn:fcode":"PPL","gn:population":394,"iso:country":"EE","lbl:bbox":"24.96056,59.16778,25.00056,59.20778","lbl:latitude":59.18778,"lbl:longitude":24.98056,"lbl:max_zoom":17,"lbl:min_zoom":12.5,"mz:hierarchy_label":1,"mz:is_current":1,"mz:min_zoom":11,"mz:note":"Quattroshapes Point Gazetteer import 20170519","name:ceb_x_preferred":["Oru"],"name:eng_x_preferred":["Oru"],"name:est_x_preferred":["Oru"],"name:fra_x_preferred":["Oru"],"name:hye_x_preferred":["Օռու"],"name:nld_x_preferred":["Oru"],"name:pol_x_preferred":["Oru"],"name:rus_x_preferred":["Ору"],"name:spa_x_preferred":["Oru"],"name:swe_x_preferred":["Oru"],"name:ukr_x_preferred":["Ору"],"name:vol_x_preferred":["Oru"],"qs_pg:aaroncc":"EE","qs_pg:gn_country":"EE","qs_pg:gn_fcode":"PPL","qs_pg:gn_id":589787,"qs_pg:gn_pop":394,"qs_pg:name":"Oru","qs_pg:name_adm0":"Eesti","qs_pg:name_adm1":"Harjumaa","qs_pg:photos_9k":1,"qs_pg:photos_9r":1,"qs_pg:photos_all":2,"qs_pg:photos_sr":0,"qs_pg:pop_sr":2,"qs_pg:qs_id":966839,"qs_pg:qs_pg_placetype":"locality","qs_pg:qs_pg_placetype_gp":"Town","qs_pg:woe_adm0":23424805,"qs_pg:woe_id":844431,"src:geom":"qs_pg","src:lbl_centroid":"qs_pg","src:population":"geonames","woe:adm0_id":23424805,"woe:name_adm0":"Eesti","woe:name_adm1":"Harjumaa","woe:placetype":"Town","wof:belongsto":[85683055,102191581,1713313297,85633135,1713305665],"wof:breaches":[],"wof:concordances":{"gn:id":589787,"gp:id":844431,"qs_pg:id":966839,"wd:id":"Q3455896"},"wof:coterminous":[1713313297],"wof:country":"EE","wof:created":1497301902,"wof:geomhash":"b74af09f18285b7bc655c12d001a8603","wof:hierarchy":[{"continent_id":102191581,"country_id":85633135,"county_id":1713305665,"localadmin_id":1713313297,"locality_id":1126037725,"region_id":85683055}],"wof:id":1126037725,"wof:lang_x_official":["est"],"wof:lang_x_spoken":["est"],"wof:lastmodified":1596661354,"wof:name":"Oru","wof:parent_id":1713313297,"wof:placetype":"locality","wof:population":394,"wof:population_rank":2,"wof:repo":"whosonfirst-data-admin-ee","wof:superseded_by":[],"wof:supersedes":[],"wof:tags":[]},"bbox":[24.98056,59.18778,24.98056,59.18778],"geometry":{"coordinates":[24.98056,59.18778],"type":"Point"}}