{"id":1226230403,"type":"Feature","properties":{"edtf:cessation":"uuuu","edtf:inception":"uuuu","geom:area":0,"geom:area_square_m":0,"geom:bbox":"25.25,58.21667,25.25,58.21667","geom:latitude":58.21667,"geom:longitude":25.25,"gn:admin1_code":"11.0","gn:admin2_code":"712.0","gn:admin3_code":"2631.0","gn:asciiname":"Pekre","gn:country_code":"EE","gn:dem":66,"gn:feature_class":"P","gn:feature_code":"PPL","gn:geonameid":589527,"gn:latitude":58.21667,"gn:longitude":25.25,"gn:modification_date":"2017-11-25","gn:name":"Pekre","gn:population":0,"gn:timezone":"Europe/Tallinn","iso:country":"EE","lbl:bbox":"25.23,58.19667,25.27,58.23667","lbl:max_zoom":18,"lbl:min_zoom":13.5,"mz:hierarchy_label":1,"mz:is_current":1,"mz:min_zoom":12,"name:bos_x_preferred":["Pekre"],"name:bul_x_preferred":["Пекре"],"name:ceb_x_preferred":["Pekre"],"name:nld_x_preferred":["Pekre"],"name:pol_x_preferred":["Pekre"],"name:ron_x_preferred":["Pekre"],"name:slv_x_preferred":["Pekre"],"name:ukr_x_preferred":["Пекре"],"src:geom":"geonames","wof:belongsto":[85682981,102191581,1713313987,85633135,1713305705],"wof:breaches":[],"wof:concordances":{"gn:id":589527},"wof:country":"EE","wof:geomhash":"d019f8b716318cdb64682c0533648a95","wof:hierarchy":[{"continent_id":102191581,"country_id":85633135,"county_id":1713305705,"localadmin_id":1713313987,"locality_id":1226230403,"region_id":85682981}],"wof:id":1226230403,"wof:lang_x_official":["est"],"wof:lang_x_spoken":["est"],"wof:lastmodified":1596677731,"wof:name":"Pekre","wof:parent_id":1713313987,"wof:placetype":"locality","wof:repo":"whosonfirst-data-admin-ee","wof:superseded_by":[],"wof:supersedes":[],"wof:tags":[]},"bbox":[25.25,58.21667,25.25,58.21667],"geometry":{"coordinates":[25.25,58.21667],"type":"Point"}}