{"id":1310706845,"type":"Feature","properties":{"edtf:cessation":"uuuu","edtf:inception":"uuuu","geom:area":0,"geom:area_square_m":0,"geom:bbox":"26.71139,58.67056,26.71139,58.67056","geom:latitude":58.67056,"geom:longitude":26.71139,"gn:admin1_code":"5.0","gn:admin2_code":"247.0","gn:admin3_code":"6727.0","gn:asciiname":"Rahivere","gn:country_code":"EE","gn:dem":67,"gn:feature_class":"P","gn:feature_code":"PPL","gn:geonameid":793343,"gn:latitude":58.67056,"gn:longitude":26.71139,"gn:modification_date":"2017-11-25","gn:name":"Rahivere","gn:population":0,"gn:timezone":"Europe/Tallinn","iso:country":"EE","lbl:bbox":"26.69139,58.65056,26.73139,58.69056","lbl:max_zoom":18,"lbl:min_zoom":13.5,"mz:hierarchy_label":1,"mz:is_current":1,"mz:min_zoom":12,"name:est_x_preferred":["Rahivere"],"name:hye_x_preferred":["Ռահիվեռե"],"name:pol_x_preferred":["Rahivere"],"name:spa_x_preferred":["Rahivere"],"name:vol_x_preferred":["Rahivere"],"src:geom":"geonames","wof:belongsto":[85683009,102191581,1713314055,85633135,1713305767],"wof:breaches":[],"wof:concordances":{"gn:id":793343,"wk:page":"Rahivere"},"wof:coterminous":[1713314551],"wof:country":"EE","wof:geomhash":"c9596e156ae72f15c0fbaf3853efecf8","wof:hierarchy":[{"continent_id":102191581,"country_id":85633135,"county_id":1713305767,"localadmin_id":1713314055,"locality_id":1310706845,"region_id":85683009}],"wof:id":1310706845,"wof:lang_x_official":["est"],"wof:lang_x_spoken":["est"],"wof:lastmodified":1596676578,"wof:name":"Rahivere","wof:parent_id":1713314055,"wof:placetype":"locality","wof:repo":"whosonfirst-data-admin-ee","wof:superseded_by":[],"wof:supersedes":[],"wof:tags":[]},"bbox":[26.71139,58.67056,26.71139,58.67056],"geometry":{"coordinates":[26.71139,58.67056],"type":"Point"}}