{"id":1276227811,"type":"Feature","properties":{"edtf:cessation":"uuuu","edtf:inception":"uuuu","geom:area":0,"geom:area_square_m":0,"geom:bbox":"25.38333,58.63333,25.38333,58.63333","geom:latitude":58.63333,"geom:longitude":25.38333,"gn:admin1_code":"4.0","gn:admin2_code":"834.0","gn:admin3_code":"6831.0","gn:asciiname":"Torvaaugu","gn:cc2":"EE","gn:country_code":"EE","gn:dem":53,"gn:feature_class":"P","gn:feature_code":"PPL","gn:geonameid":588203,"gn:latitude":58.63333,"gn:longitude":25.38333,"gn:modification_date":"2017-11-25","gn:name":"Tõrvaaugu","gn:population":0,"gn:timezone":"Europe/Tallinn","iso:country":"EE","lbl:bbox":"25.36333,58.61333,25.40333,58.65333","lbl:max_zoom":18,"lbl:min_zoom":13.5,"mz:hierarchy_label":1,"mz:is_current":1,"mz:min_zoom":12,"name:und_x_variant":["Tyrvaugu","Tõrvaaugu"],"src:geom":"geonames","wof:belongsto":[85683031,102191581,1713313817,85633135,1713305773],"wof:breaches":[],"wof:concordances":{"gn:id":588203},"wof:country":"EE","wof:geomhash":"0146d2e63b7d8607c9e2dcf6cec29072","wof:hierarchy":[{"continent_id":102191581,"country_id":85633135,"county_id":1713305773,"localadmin_id":1713313817,"locality_id":1276227811,"region_id":85683031}],"wof:id":1276227811,"wof:lang_x_official":["est"],"wof:lang_x_spoken":["est"],"wof:lastmodified":1596677984,"wof:name":"Torvaaugu","wof:parent_id":1713313817,"wof:placetype":"locality","wof:repo":"whosonfirst-data-admin-ee","wof:superseded_by":[],"wof:supersedes":[],"wof:tags":[]},"bbox":[25.38333,58.63333,25.38333,58.63333],"geometry":{"coordinates":[25.38333,58.63333],"type":"Point"}}