{"id":1209699269,"type":"Feature","properties":{"edtf:cessation":"uuuu","edtf:inception":"uuuu","geom:area":0,"geom:area_square_m":0,"geom:bbox":"22.80667,58.35583,22.80667,58.35583","geom:latitude":58.35583,"geom:longitude":22.80667,"gn:admin1_code":"14.0","gn:admin2_code":"714.0","gn:admin3_code":"2672.0","gn:asciiname":"Kangruselja","gn:cc2":"EE","gn:country_code":"EE","gn:dem":7,"gn:feature_class":"P","gn:feature_code":"PPL","gn:geonameid":591666,"gn:latitude":58.35583,"gn:longitude":22.80667,"gn:modification_date":"2017-11-25","gn:name":"Kangruselja","gn:population":0,"gn:timezone":"Europe/Tallinn","iso:country":"EE","lbl:bbox":"22.78667,58.33583,22.82667,58.37583","lbl:max_zoom":18,"lbl:min_zoom":13.5,"mz:hierarchy_label":1,"mz:is_current":1,"mz:min_zoom":12,"name:und_x_variant":["Kangrusel’ya","Kangruselja"],"src:geom":"geonames","wof:belongsto":[85682947,102191581,1713307321,85633135,1713305627],"wof:breaches":[],"wof:concordances":{"gn:id":591666},"wof:coterminous":[1713307321],"wof:country":"EE","wof:geomhash":"ce77ce62be9b23615efc10402546a9e8","wof:hierarchy":[{"continent_id":102191581,"country_id":85633135,"county_id":1713305627,"localadmin_id":1713307321,"locality_id":1209699269,"region_id":85682947}],"wof:id":1209699269,"wof:lang_x_official":["est"],"wof:lang_x_spoken":["est"],"wof:lastmodified":1596674945,"wof:name":"Kangruselja","wof:parent_id":1713307321,"wof:placetype":"locality","wof:repo":"whosonfirst-data-admin-ee","wof:superseded_by":[],"wof:supersedes":[],"wof:tags":[]},"bbox":[22.80667,58.35583,22.80667,58.35583],"geometry":{"coordinates":[22.80667,58.35583],"type":"Point"}}