{"id":1226736961,"type":"Feature","properties":{"edtf:cessation":"uuuu","edtf:inception":"uuuu","geom:area":0,"geom:area_square_m":0,"geom:bbox":"26.84222,57.93889,26.84222,57.93889","geom:latitude":57.93889,"geom:longitude":26.84222,"gn:admin1_code":"12.0","gn:admin2_code":"284.0","gn:admin3_code":"5557.0","gn:asciiname":"Naerapaeae","gn:country_code":"EE","gn:dem":114,"gn:feature_class":"P","gn:feature_code":"PPL","gn:geonameid":794470,"gn:latitude":57.93889,"gn:longitude":26.84222,"gn:modification_date":"2017-11-25","gn:name":"Närapää","gn:population":0,"gn:timezone":"Europe/Tallinn","iso:country":"EE","lbl:bbox":"26.82222,57.91889,26.86222,57.95889","lbl:max_zoom":18,"lbl:min_zoom":13.5,"mz:hierarchy_label":1,"mz:is_current":1,"mz:min_zoom":12,"name:est_x_preferred":["Närapää"],"name:hye_x_preferred":["Նեռապեե"],"name:pol_x_preferred":["Närapää"],"name:spa_x_preferred":["Närapää"],"name:ukr_x_preferred":["Нярапяя"],"name:vol_x_preferred":["Närapää"],"src:geom":"geonames","wof:belongsto":[85682955,102191581,1713312959,85633135,1713305789],"wof:breaches":[],"wof:concordances":{"gn:id":794470,"wk:page":"N%C3%A4rap%C3%A4%C3%A4"},"wof:country":"EE","wof:geomhash":"db63b2a8842467eac6d358588e8c39fb","wof:hierarchy":[{"continent_id":102191581,"country_id":85633135,"county_id":1713305789,"localadmin_id":1713312959,"locality_id":1226736961,"region_id":85682955}],"wof:id":1226736961,"wof:lang_x_official":["est"],"wof:lang_x_spoken":["est"],"wof:lastmodified":1596676793,"wof:name":"Naerapaeae","wof:parent_id":1713312959,"wof:placetype":"locality","wof:repo":"whosonfirst-data-admin-ee","wof:superseded_by":[],"wof:supersedes":[],"wof:tags":[]},"bbox":[26.84222,57.93889,26.84222,57.93889],"geometry":{"coordinates":[26.84222,57.93889],"type":"Point"}}