{"id":1343347149,"type":"Feature","properties":{"edtf:cessation":"uuuu","edtf:inception":"uuuu","geom:area":0,"geom:area_square_m":0,"geom:bbox":"26.31306,59.46611,26.31306,59.46611","geom:latitude":59.46611,"geom:longitude":26.31306,"gn:admin1_code":"8.0","gn:admin2_code":"191.0","gn:admin3_code":"2779.0","gn:asciiname":"Tougu","gn:country_code":"EE","gn:dem":67,"gn:feature_class":"P","gn:feature_code":"PPL","gn:geonameid":8618766,"gn:latitude":59.46611,"gn:longitude":26.31306,"gn:modification_date":"2017-11-25","gn:name":"Tõugu","gn:population":0,"gn:timezone":"Europe/Tallinn","iso:country":"EE","lbl:bbox":"26.29306,59.44611,26.33306,59.48611","lbl:max_zoom":18,"lbl:min_zoom":13.5,"mz:hierarchy_label":1,"mz:is_current":1,"mz:min_zoom":12,"src:geom":"geonames","wof:belongsto":[85683049,102191581,1713308627,85633135,1713305775],"wof:breaches":[],"wof:concordances":{"gn:id":8618766},"wof:country":"EE","wof:geomhash":"ac098fb3de8f86aa32cb6a8cf4bf33eb","wof:hierarchy":[{"continent_id":102191581,"country_id":85633135,"county_id":1713305775,"localadmin_id":1713308627,"locality_id":1343347149,"region_id":85683049}],"wof:id":1343347149,"wof:lang_x_official":["est"],"wof:lang_x_spoken":["est"],"wof:lastmodified":1596678041,"wof:name":"Tougu","wof:parent_id":1713308627,"wof:placetype":"locality","wof:repo":"whosonfirst-data-admin-ee","wof:superseded_by":[],"wof:supersedes":[],"wof:tags":[]},"bbox":[26.31306,59.46611,26.31306,59.46611],"geometry":{"coordinates":[26.31306,59.46611],"type":"Point"}}