{"id":1243468473,"type":"Feature","properties":{"edtf:cessation":"uuuu","edtf:inception":"uuuu","geom:area":0,"geom:area_square_m":0,"geom:bbox":"25.59611,59.31472,25.59611,59.31472","geom:latitude":59.31472,"geom:longitude":25.59611,"gn:admin1_code":"1.0","gn:admin2_code":"141.0","gn:admin3_code":"6254.0","gn:asciiname":"Rekka","gn:country_code":"EE","gn:dem":70,"gn:feature_class":"P","gn:feature_code":"PPL","gn:geonameid":589058,"gn:latitude":59.31472,"gn:longitude":25.59611,"gn:modification_date":"2017-11-25","gn:name":"Rekka","gn:population":0,"gn:timezone":"Europe/Tallinn","iso:country":"EE","lbl:bbox":"25.57611,59.29472,25.61611,59.33472","lbl:max_zoom":18,"lbl:min_zoom":13.5,"mz:hierarchy_label":1,"mz:is_current":1,"mz:min_zoom":12,"src:geom":"geonames","wof:belongsto":[85683055,102191581,1713314585,85633135,1713305749],"wof:breaches":[],"wof:concordances":{"gn:id":589058},"wof:country":"EE","wof:geomhash":"85e475658dc96550c6708430371a0f59","wof:hierarchy":[{"continent_id":102191581,"country_id":85633135,"county_id":1713305749,"localadmin_id":1713314585,"locality_id":1243468473,"region_id":85683055}],"wof:id":1243468473,"wof:lang_x_official":["est"],"wof:lang_x_spoken":["est"],"wof:lastmodified":1596662803,"wof:name":"Rekka","wof:parent_id":1713314585,"wof:placetype":"locality","wof:repo":"whosonfirst-data-admin-ee","wof:superseded_by":[],"wof:supersedes":[],"wof:tags":[]},"bbox":[25.59611,59.31472,25.59611,59.31472],"geometry":{"coordinates":[25.59611,59.31472],"type":"Point"}}