{"id":1243540785,"type":"Feature","properties":{"edtf:cessation":"uuuu","edtf:inception":"uuuu","geom:area":0,"geom:area_square_m":0,"geom:bbox":"24.53056,58.965,24.53056,58.965","geom:latitude":58.965,"geom:longitude":24.53056,"gn:admin1_code":"13.0","gn:admin2_code":"503.0","gn:admin3_code":"3831.0","gn:asciiname":"Korvetaguse","gn:cc2":"EE","gn:country_code":"EE","gn:dem":50,"gn:feature_class":"P","gn:feature_code":"PPL","gn:geonameid":591082,"gn:latitude":58.965,"gn:longitude":24.53056,"gn:modification_date":"2017-11-25","gn:name":"Kõrvetaguse","gn:population":0,"gn:timezone":"Europe/Tallinn","iso:country":"EE","lbl:bbox":"24.51056,58.945,24.55056,58.985","lbl:max_zoom":18,"lbl:min_zoom":13.5,"mz:hierarchy_label":1,"mz:is_current":1,"mz:min_zoom":12,"name:est_x_preferred":["Kõrvetaguse"],"name:hye_x_preferred":["Կիռվետագուսե"],"name:pol_x_preferred":["Kõrvetaguse"],"name:rus_x_preferred":["Кырветагузе"],"name:sco_x_preferred":["Kõrvetaguse"],"name:spa_x_preferred":["Kõrvetaguse"],"name:und_x_variant":["Kyrvetaguze"],"name:vol_x_preferred":["Kõrvetaguse"],"src:geom":"geonames","wof:belongsto":[85683013,102191581,1713313353,85633135,1713305747],"wof:breaches":[],"wof:concordances":{"gn:id":591082,"wk:page":"K%C3%B5rvetaguse"},"wof:coterminous":[1713313353],"wof:country":"EE","wof:geomhash":"b485f46439fea3e35b9075a5e77e2a33","wof:hierarchy":[{"continent_id":102191581,"country_id":85633135,"county_id":1713305747,"localadmin_id":1713313353,"locality_id":1243540785,"region_id":85683013}],"wof:id":1243540785,"wof:lang_x_official":["est"],"wof:lang_x_spoken":["est"],"wof:lastmodified":1596662847,"wof:name":"Korvetaguse","wof:parent_id":1713313353,"wof:placetype":"locality","wof:repo":"whosonfirst-data-admin-ee","wof:superseded_by":[],"wof:supersedes":[],"wof:tags":[]},"bbox":[24.53056,58.965,24.53056,58.965],"geometry":{"coordinates":[24.53056,58.965],"type":"Point"}}