{"id":1226123661,"type":"Feature","properties":{"edtf:cessation":"uuuu","edtf:inception":"uuuu","geom:area":0,"geom:area_square_m":0,"geom:bbox":"24.58333,58.25,24.58333,58.25","geom:latitude":58.25,"geom:longitude":24.58333,"gn:admin1_code":"11.0","gn:admin2_code":"214.0","gn:admin3_code":"4284.0","gn:asciiname":"Uulu-Leina","gn:cc2":"EE","gn:country_code":"EE","gn:dem":4,"gn:feature_class":"P","gn:feature_code":"PPL","gn:geonameid":588000,"gn:latitude":58.25,"gn:longitude":24.58333,"gn:modification_date":"2017-11-25","gn:name":"Uulu-Leina","gn:population":0,"gn:timezone":"Europe/Tallinn","iso:country":"EE","lbl:bbox":"24.56333,58.23,24.60333,58.27","lbl:max_zoom":18,"lbl:min_zoom":13.5,"mz:hierarchy_label":1,"mz:is_current":1,"mz:min_zoom":12,"name:und_x_variant":["Ulu-Leyna","Uulu-Leina"],"src:geom":"geonames","wof:belongsto":[85682981,102191581,1713312805,85633135,1713305741],"wof:breaches":[],"wof:concordances":{"gn:id":588000},"wof:country":"EE","wof:geomhash":"c5446106152a3649051297c79946d20d","wof:hierarchy":[{"continent_id":102191581,"country_id":85633135,"county_id":1713305741,"localadmin_id":1713312805,"locality_id":1226123661,"region_id":85682981}],"wof:id":1226123661,"wof:lang_x_official":["est"],"wof:lang_x_spoken":["est"],"wof:lastmodified":1596663208,"wof:name":"Uulu-Leina","wof:parent_id":1713312805,"wof:placetype":"locality","wof:repo":"whosonfirst-data-admin-ee","wof:superseded_by":[],"wof:supersedes":[],"wof:tags":[]},"bbox":[24.58333,58.25,24.58333,58.25],"geometry":{"coordinates":[24.58333,58.25],"type":"Point"}}