{"id":1259959163,"type":"Feature","properties":{"edtf:cessation":"uuuu","edtf:inception":"uuuu","geom:area":0,"geom:area_square_m":0,"geom:bbox":"24.93833,58.94083,24.93833,58.94083","geom:latitude":58.94083,"geom:longitude":24.93833,"gn:admin1_code":"13.0","gn:admin2_code":"293.0","gn:admin3_code":"4392.0","gn:asciiname":"Linnaaluste","gn:cc2":"EE","gn:country_code":"EE","gn:dem":77,"gn:feature_class":"P","gn:feature_code":"PPL","gn:geonameid":590612,"gn:latitude":58.94083,"gn:longitude":24.93833,"gn:modification_date":"2017-11-25","gn:name":"Linnaaluste","gn:population":0,"gn:timezone":"Europe/Tallinn","iso:country":"EE","lbl:bbox":"24.91833,58.92083,24.95833,58.96083","lbl:max_zoom":18,"lbl:min_zoom":13.5,"mz:hierarchy_label":1,"mz:is_current":1,"mz:min_zoom":12,"name:est_x_preferred":["Linnaaluste"],"name:hye_x_preferred":["Լիննաալուստե"],"name:pol_x_preferred":["Linnaaluste"],"name:sco_x_preferred":["Linnaaluste"],"name:spa_x_preferred":["Linnaaluste"],"name:und_x_variant":["Linnaluste"],"name:vol_x_preferred":["Linnaaluste"],"src:geom":"geonames","wof:belongsto":[85683013,102191581,1713309725,85633135,1713305713],"wof:breaches":[],"wof:concordances":{"gn:id":590612,"wk:page":"Linnaaluste"},"wof:coterminous":[1713309725],"wof:country":"EE","wof:geomhash":"beef6a70b0c7260afee665d89d292dbe","wof:hierarchy":[{"continent_id":102191581,"country_id":85633135,"county_id":1713305713,"localadmin_id":1713309725,"locality_id":1259959163,"region_id":85683013}],"wof:id":1259959163,"wof:lang_x_official":["est"],"wof:lang_x_spoken":["est"],"wof:lastmodified":1596676748,"wof:name":"Linnaaluste","wof:parent_id":1713309725,"wof:placetype":"locality","wof:repo":"whosonfirst-data-admin-ee","wof:superseded_by":[],"wof:supersedes":[],"wof:tags":[]},"bbox":[24.93833,58.94083,24.93833,58.94083],"geometry":{"coordinates":[24.93833,58.94083],"type":"Point"}}