{"id":1209948215,"type":"Feature","properties":{"edtf:cessation":"uuuu","edtf:inception":"uuuu","geom:area":0,"geom:area_square_m":0,"geom:bbox":"26.51389,58.56333,26.51389,58.56333","geom:latitude":58.56333,"geom:longitude":26.51389,"gn:admin1_code":"18.0","gn:admin2_code":"796.0","gn:admin3_code":"3737.0","gn:asciiname":"Kodukuela","gn:country_code":"EE","gn:dem":53,"gn:feature_class":"P","gn:feature_code":"PPL","gn:geonameid":793958,"gn:latitude":58.56333,"gn:longitude":26.51389,"gn:modification_date":"2017-11-25","gn:name":"Kõduküla","gn:population":0,"gn:timezone":"Europe/Tallinn","iso:country":"EE","lbl:bbox":"26.49389,58.54333,26.53389,58.58333","lbl:max_zoom":18,"lbl:min_zoom":13.5,"mz:hierarchy_label":1,"mz:is_current":1,"mz:min_zoom":12,"src:geom":"geonames","wof:belongsto":[85683009,102191581,1713308689,85633135,1713305659],"wof:breaches":[],"wof:concordances":{"gn:id":793958},"wof:coterminous":[1713308689],"wof:country":"EE","wof:geomhash":"ebd78c53b83a2567d51ffd2d0bd17a8f","wof:hierarchy":[{"continent_id":102191581,"country_id":85633135,"county_id":1713305659,"localadmin_id":1713308689,"locality_id":1209948215,"region_id":85683009}],"wof:id":1209948215,"wof:lang_x_official":["est"],"wof:lang_x_spoken":["est"],"wof:lastmodified":1596676477,"wof:name":"Kodukuela","wof:parent_id":1713308689,"wof:placetype":"locality","wof:repo":"whosonfirst-data-admin-ee","wof:superseded_by":[],"wof:supersedes":[],"wof:tags":[]},"bbox":[26.51389,58.56333,26.51389,58.56333],"geometry":{"coordinates":[26.51389,58.56333],"type":"Point"}}