{"id":1326792433,"type":"Feature","properties":{"edtf:cessation":"uuuu","edtf:inception":"uuuu","geom:area":0,"geom:area_square_m":0,"geom:bbox":"25.66667,58.45,25.66667,58.45","geom:latitude":58.45,"geom:longitude":25.66667,"gn:admin1_code":"20.0","gn:admin2_code":"899.0","gn:admin3_code":"9646.0","gn:asciiname":"Pupsi","gn:country_code":"EE","gn:dem":91,"gn:feature_class":"P","gn:feature_code":"PPL","gn:geonameid":589272,"gn:latitude":58.45,"gn:longitude":25.66667,"gn:modification_date":"2017-11-25","gn:name":"Pupsi","gn:population":0,"gn:timezone":"Europe/Tallinn","iso:country":"EE","lbl:bbox":"25.64667,58.43,25.68667,58.47","lbl:max_zoom":18,"lbl:min_zoom":13.5,"mz:hierarchy_label":1,"mz:is_current":1,"mz:min_zoom":12,"src:geom":"geonames","wof:belongsto":[85682985,102191581,1713313567,85633135,1713305669],"wof:breaches":[],"wof:concordances":{"gn:id":589272},"wof:country":"EE","wof:geomhash":"07ec08c743e594323d812f91e9c984f3","wof:hierarchy":[{"continent_id":102191581,"country_id":85633135,"county_id":1713305669,"localadmin_id":1713313567,"locality_id":1326792433,"region_id":85682985}],"wof:id":1326792433,"wof:lang_x_official":["est"],"wof:lang_x_spoken":["est"],"wof:lastmodified":1596661251,"wof:name":"Pupsi","wof:parent_id":1713313567,"wof:placetype":"locality","wof:repo":"whosonfirst-data-admin-ee","wof:superseded_by":[],"wof:supersedes":[],"wof:tags":[]},"bbox":[25.66667,58.45,25.66667,58.45],"geometry":{"coordinates":[25.66667,58.45],"type":"Point"}}