{"id":1126004793,"type":"Feature","properties":{"edtf:cessation":"uuuu","edtf:inception":"uuuu","geom:area":0,"geom:area_square_m":0,"geom:bbox":"25.86667,58.65,25.86667,58.65","geom:latitude":58.65,"geom:longitude":25.86667,"gn:country":"EE","gn:fcode":"PPL","gn:population":120,"iso:country":"EE","lbl:bbox":"25.84667,58.63,25.88667,58.67","lbl:latitude":58.65,"lbl:longitude":25.86667,"lbl:max_zoom":18,"lbl:min_zoom":13,"mz:hierarchy_label":1,"mz:is_current":1,"mz:min_zoom":11,"mz:note":"Quattroshapes Point Gazetteer import 20170519","name:ara_x_preferred":["آنا"],"name:aze_x_preferred":["Anna"],"name:cat_x_preferred":["Anna"],"name:ceb_x_preferred":["Anna"],"name:ces_x_preferred":["Anna"],"name:dan_x_preferred":["Anna"],"name:deu_x_preferred":["Anna"],"name:est_x_preferred":["Anna"],"name:fas_x_preferred":["آنا"],"name:fin_x_preferred":["Anna"],"name:fra_x_preferred":["Anna"],"name:glg_x_preferred":["Anna"],"name:heb_x_preferred":["אנה"],"name:ina_x_preferred":["Anna"],"name:ind_x_preferred":["Anna"],"name:ita_x_preferred":["Anna"],"name:jpn_x_preferred":["アンナ"],"name:lav_x_preferred":["Anna"],"name:nld_x_preferred":["Anna"],"name:pol_x_preferred":["Anna"],"name:por_x_preferred":["Anna"],"name:ron_x_preferred":["Anna"],"name:rus_x_preferred":["Анна"],"name:slk_x_preferred":["Anna"],"name:spa_x_preferred":["Anna"],"name:swe_x_preferred":["Anna"],"name:und_x_variant":["Annamõisa"],"name:vie_x_preferred":["Anna"],"name:vol_x_preferred":["Anna"],"name:zho_x_preferred":["安娜"],"qs_pg:aaroncc":"EE","qs_pg:gn_country":"EE","qs_pg:gn_fcode":"PPL","qs_pg:gn_id":592469,"qs_pg:gn_pop":120,"qs_pg:name":"Anna","qs_pg:name_adm0":"Eesti","qs_pg:name_adm1":"Järvamaa","qs_pg:photos_9k":1,"qs_pg:photos_9r":1,"qs_pg:photos_all":4,"qs_pg:photos_sr":0,"qs_pg:pop_sr":1,"qs_pg:qs_id":244106,"qs_pg:qs_pg_placetype":"locality","qs_pg:qs_pg_placetype_gp":"Town","qs_pg:woe_adm0":23424805,"qs_pg:woe_id":841955,"src:geom":"qs_pg","src:lbl_centroid":"qs_pg","src:population":"geonames","woe:adm0_id":23424805,"woe:name_adm0":"Eesti","woe:name_adm1":"Järvamaa","woe:placetype":"Town","wof:belongsto":[85683009,102191581,1713312157,85633135,1713305657],"wof:breaches":[],"wof:concordances":{"gn:id":592469,"gp:id":841955,"qs_pg:id":244106},"wof:country":"EE","wof:created":1497299874,"wof:geomhash":"ad7f3e63be76f4e1b730283621ccc9df","wof:hierarchy":[{"continent_id":102191581,"country_id":85633135,"county_id":1713305657,"localadmin_id":1713312157,"locality_id":1126004793,"region_id":85683009}],"wof:id":1126004793,"wof:lang_x_official":["est"],"wof:lang_x_spoken":["est"],"wof:lastmodified":1596676506,"wof:name":"Anna","wof:parent_id":1713312157,"wof:placetype":"locality","wof:population":120,"wof:population_rank":1,"wof:repo":"whosonfirst-data-admin-ee","wof:superseded_by":[],"wof:supersedes":[],"wof:tags":[]},"bbox":[25.86667,58.65,25.86667,58.65],"geometry":{"coordinates":[25.86667,58.65],"type":"Point"}}