{"id":1309708309,"type":"Feature","properties":{"edtf:cessation":"uuuu","edtf:inception":"uuuu","geom:area":0,"geom:area_square_m":0,"geom:bbox":"26.43917,59.47611,26.43917,59.47611","geom:latitude":59.47611,"geom:longitude":26.43917,"gn:admin1_code":"8.0","gn:admin2_code":"903.0","gn:admin3_code":"5791.0","gn:asciiname":"Paaskuela","gn:country_code":"EE","gn:dem":58,"gn:feature_class":"P","gn:feature_code":"PPL","gn:geonameid":793453,"gn:latitude":59.47611,"gn:longitude":26.43917,"gn:modification_date":"2017-11-25","gn:name":"Paasküla","gn:population":0,"gn:timezone":"Europe/Tallinn","iso:country":"EE","lbl:bbox":"26.41917,59.45611,26.45917,59.49611","lbl:max_zoom":18,"lbl:min_zoom":13.5,"mz:hierarchy_label":1,"mz:is_current":1,"mz:min_zoom":12,"name:est_x_preferred":["Paasküla"],"name:hye_x_preferred":["Պաասկյուլա"],"name:vol_x_preferred":["Paasküla"],"src:geom":"geonames","wof:belongsto":[85683049,102191581,1713315301,85633135,1713305777],"wof:breaches":[],"wof:concordances":{"gn:id":793453,"wk:page":"Paask%C3%BCla"},"wof:coterminous":[1713315301],"wof:country":"EE","wof:geomhash":"08a1ba43997dc69749bd468f5b222fd1","wof:hierarchy":[{"continent_id":102191581,"country_id":85633135,"county_id":1713305777,"localadmin_id":1713315301,"locality_id":1309708309,"region_id":85683049}],"wof:id":1309708309,"wof:lang_x_official":["est"],"wof:lang_x_spoken":["est"],"wof:lastmodified":1596677934,"wof:name":"Paaskuela","wof:parent_id":1713315301,"wof:placetype":"locality","wof:repo":"whosonfirst-data-admin-ee","wof:superseded_by":[],"wof:supersedes":[],"wof:tags":[]},"bbox":[26.43917,59.47611,26.43917,59.47611],"geometry":{"coordinates":[26.43917,59.47611],"type":"Point"}}