{"id":1276465025,"type":"Feature","properties":{"edtf:cessation":"uuuu","edtf:inception":"uuuu","geom:area":0,"geom:area_square_m":0,"geom:bbox":"23.50345,58.8504,23.50345,58.8504","geom:latitude":58.8504,"geom:longitude":23.50345,"gn:admin1_code":"7.0","gn:admin2_code":"184.0","gn:admin3_code":"3171.0","gn:asciiname":"Kivikuela","gn:country_code":"EE","gn:dem":7,"gn:feature_class":"P","gn:feature_code":"PPL","gn:geonameid":8224435,"gn:latitude":58.8504,"gn:longitude":23.50345,"gn:modification_date":"2017-11-25","gn:name":"Kiviküla","gn:population":0,"gn:timezone":"Europe/Tallinn","iso:country":"EE","lbl:bbox":"23.48345,58.8304,23.52345,58.8704","lbl:max_zoom":18,"lbl:min_zoom":13.5,"mz:hierarchy_label":1,"mz:is_current":1,"mz:min_zoom":12,"name:deu_x_preferred":["Kiviküla"],"name:est_x_preferred":["Kiviküla"],"name:hye_x_preferred":["Կիվիկյուլա"],"name:pol_x_preferred":["Kiviküla"],"name:ukr_x_preferred":["Ківікюла"],"name:vol_x_preferred":["Kiviküla"],"src:geom":"geonames","wof:belongsto":[85683001,102191581,1713308581,85633135,1713305755],"wof:breaches":[],"wof:concordances":{"gn:id":8224435,"wk:page":"Kivik%C3%BCla%2C_L%C3%A4%C3%A4ne_County"},"wof:coterminous":[1713308581],"wof:country":"EE","wof:geomhash":"02318bfb6b41b5d9ae8327eddd47a052","wof:hierarchy":[{"continent_id":102191581,"country_id":85633135,"county_id":1713305755,"localadmin_id":1713308581,"locality_id":1276465025,"region_id":85683001}],"wof:id":1276465025,"wof:lang_x_official":["est"],"wof:lang_x_spoken":["est"],"wof:lastmodified":1596662771,"wof:name":"Kivikuela","wof:parent_id":1713308581,"wof:placetype":"locality","wof:repo":"whosonfirst-data-admin-ee","wof:superseded_by":[],"wof:supersedes":[],"wof:tags":[]},"bbox":[23.50345,58.8504,23.50345,58.8504],"geometry":{"coordinates":[23.50345,58.8504],"type":"Point"}}