{"id":1243160189,"type":"Feature","properties":{"edtf:cessation":"uuuu","edtf:inception":"uuuu","geom:area":0,"geom:area_square_m":0,"geom:bbox":"25.02806,58.19389,25.02806,58.19389","geom:latitude":58.19389,"geom:longitude":25.02806,"gn:admin1_code":"11.0","gn:admin2_code":"712.0","gn:admin3_code":"9652.0","gn:asciiname":"Suitsukuela","gn:country_code":"EE","gn:dem":74,"gn:feature_class":"P","gn:feature_code":"PPL","gn:geonameid":588560,"gn:latitude":58.19389,"gn:longitude":25.02806,"gn:modification_date":"2017-11-25","gn:name":"Suitsuküla","gn:population":0,"gn:timezone":"Europe/Tallinn","iso:country":"EE","lbl:bbox":"25.00806,58.17389,25.04806,58.21389","lbl:max_zoom":18,"lbl:min_zoom":13.5,"mz:hierarchy_label":1,"mz:is_current":1,"mz:min_zoom":12,"name:und_x_variant":["Suytsukyula","Suitsuküla"],"src:geom":"geonames","wof:belongsto":[85682981,102191581,1713309531,85633135,1713305705],"wof:breaches":[],"wof:concordances":{"gn:id":588560},"wof:country":"EE","wof:geomhash":"16f4a74013bc209d8a10607d1e217b0f","wof:hierarchy":[{"continent_id":102191581,"country_id":85633135,"county_id":1713305705,"localadmin_id":1713309531,"locality_id":1243160189,"region_id":85682981}],"wof:id":1243160189,"wof:lang_x_official":["est"],"wof:lang_x_spoken":["est"],"wof:lastmodified":1596677737,"wof:name":"Suitsukuela","wof:parent_id":1713309531,"wof:placetype":"locality","wof:repo":"whosonfirst-data-admin-ee","wof:superseded_by":[],"wof:supersedes":[],"wof:tags":[]},"bbox":[25.02806,58.19389,25.02806,58.19389],"geometry":{"coordinates":[25.02806,58.19389],"type":"Point"}}