{"id":1242786469,"type":"Feature","properties":{"edtf:cessation":"uuuu","edtf:inception":"uuuu","geom:area":0,"geom:area_square_m":0,"geom:bbox":"22.18426,58.9242,22.18426,58.9242","geom:latitude":58.9242,"geom:longitude":22.18426,"gn:admin1_code":"2.0","gn:admin2_code":"205.0","gn:admin3_code":"7848.0","gn:asciiname":"Surepi","gn:country_code":"EE","gn:dem":43,"gn:feature_class":"P","gn:feature_code":"PPL","gn:geonameid":588523,"gn:latitude":58.9242,"gn:longitude":22.18426,"gn:modification_date":"2017-11-25","gn:name":"Surepi","gn:population":0,"gn:timezone":"Europe/Tallinn","iso:country":"EE","lbl:bbox":"22.16426,58.9042,22.20426,58.9442","lbl:max_zoom":18,"lbl:min_zoom":13.5,"mz:hierarchy_label":1,"mz:is_current":1,"mz:min_zoom":12,"name:deu_x_preferred":["Suurepsi"],"name:est_x_preferred":["Suurepsi"],"name:hye_x_preferred":["Սուուռեպսի"],"name:pol_x_preferred":["Suurepsi"],"name:spa_x_preferred":["Suurepsi"],"name:und_x_variant":["Surepi"],"name:vol_x_preferred":["Suurepsi"],"src:geom":"geonames","wof:belongsto":[85682989,102191581,1713310701,85633135,1713305629],"wof:breaches":[],"wof:concordances":{"gn:id":588523,"wk:page":"Suurepsi"},"wof:coterminous":[1713310701],"wof:country":"EE","wof:geomhash":"4695b8e10c947f884b25292f96098f1d","wof:hierarchy":[{"continent_id":102191581,"country_id":85633135,"county_id":1713305629,"localadmin_id":1713310701,"locality_id":1242786469,"region_id":85682989}],"wof:id":1242786469,"wof:lang_x_official":["est"],"wof:lang_x_spoken":["est"],"wof:lastmodified":1596670017,"wof:name":"Surepi","wof:parent_id":1713310701,"wof:placetype":"locality","wof:repo":"whosonfirst-data-admin-ee","wof:superseded_by":[],"wof:supersedes":[],"wof:tags":[]},"bbox":[22.18426,58.9242,22.18426,58.9242],"geometry":{"coordinates":[22.18426,58.9242],"type":"Point"}}