{"id":1209493393,"type":"Feature","properties":{"edtf:cessation":"uuuu","edtf:inception":"uuuu","geom:area":0,"geom:area_square_m":0,"geom:bbox":"24.48333,58.08333,24.48333,58.08333","geom:latitude":58.08333,"geom:longitude":24.48333,"gn:admin1_code":"11.0","gn:admin2_code":"214.0","gn:admin3_code":"1957.0","gn:asciiname":"Piiskopi","gn:country_code":"EE","gn:dem":1,"gn:feature_class":"P","gn:feature_code":"PPL","gn:geonameid":589474,"gn:latitude":58.08333,"gn:longitude":24.48333,"gn:modification_date":"2017-11-25","gn:name":"Piiskopi","gn:population":0,"gn:timezone":"Europe/Tallinn","iso:country":"EE","lbl:bbox":"24.46333,58.06333,24.50333,58.10333","lbl:max_zoom":18,"lbl:min_zoom":13.5,"mz:hierarchy_label":1,"mz:is_current":1,"mz:is_funky":1,"mz:min_zoom":12,"name:und_x_variant":["Piyskopi","Piiskopi"],"src:geom":"geonames","wof:belongsto":[85682981,102191581,1713309215,85633135,1713305741],"wof:breaches":[],"wof:concordances":{"gn:id":589474},"wof:country":"EE","wof:geomhash":"67b1c8c2a717ddf608b5531e01cf6e08","wof:hierarchy":[{"continent_id":102191581,"country_id":85633135,"county_id":1713305741,"localadmin_id":1713309215,"locality_id":1209493393,"region_id":85682981}],"wof:id":1209493393,"wof:lang_x_official":["est"],"wof:lang_x_spoken":["est"],"wof:lastmodified":1596663206,"wof:name":"Piiskopi","wof:parent_id":1713309215,"wof:placetype":"locality","wof:repo":"whosonfirst-data-admin-ee","wof:superseded_by":[],"wof:supersedes":[],"wof:tags":[]},"bbox":[24.48333,58.08333,24.48333,58.08333],"geometry":{"coordinates":[24.48333,58.08333],"type":"Point"}}