{"id":1260081235,"type":"Feature","properties":{"edtf:cessation":"uuuu","edtf:inception":"uuuu","geom:area":0,"geom:area_square_m":0,"geom:bbox":"25.92944,58.98528,25.92944,58.98528","geom:latitude":58.98528,"geom:longitude":25.92944,"gn:admin1_code":"4.0","gn:admin2_code":"255.0","gn:admin3_code":"8388.0","gn:asciiname":"Salutaguse","gn:country_code":"EE","gn:dem":96,"gn:feature_class":"P","gn:feature_code":"PPL","gn:geonameid":588810,"gn:latitude":58.98528,"gn:longitude":25.92944,"gn:modification_date":"2017-11-25","gn:name":"Salutaguse","gn:population":0,"gn:timezone":"Europe/Tallinn","iso:country":"EE","lbl:bbox":"25.90944,58.96528,25.94944,59.00528","lbl:max_zoom":18,"lbl:min_zoom":13.5,"mz:hierarchy_label":1,"mz:is_current":1,"mz:min_zoom":12,"name:est_x_preferred":["Salutaguse"],"name:pol_x_preferred":["Salutaguse"],"name:sco_x_preferred":["Salutaguse"],"name:ukr_x_preferred":["Салутаґузе"],"name:und_x_variant":["Salutaguze"],"name:vol_x_preferred":["Salutaguse"],"src:geom":"geonames","wof:belongsto":[85683031,102191581,1713306805,85633135,1713305765],"wof:breaches":[],"wof:concordances":{"gn:id":588810},"wof:coterminous":[1713306815],"wof:country":"EE","wof:geomhash":"119faeb2495403ac8a30400a4d418428","wof:hierarchy":[{"continent_id":102191581,"country_id":85633135,"county_id":1713305765,"localadmin_id":1713306805,"locality_id":1260081235,"region_id":85683031}],"wof:id":1260081235,"wof:lang_x_official":["est"],"wof:lang_x_spoken":["est"],"wof:lastmodified":1596676636,"wof:name":"Salutaguse","wof:parent_id":1713306805,"wof:placetype":"locality","wof:repo":"whosonfirst-data-admin-ee","wof:superseded_by":[],"wof:supersedes":[],"wof:tags":[]},"bbox":[25.92944,58.98528,25.92944,58.98528],"geometry":{"coordinates":[25.92944,58.98528],"type":"Point"}}