{"id":1310076511,"type":"Feature","properties":{"edtf:cessation":"uuuu","edtf:inception":"uuuu","geom:area":0,"geom:area_square_m":0,"geom:bbox":"22.09194,58.19833,22.09194,58.19833","geom:latitude":58.19833,"geom:longitude":22.09194,"gn:admin1_code":"14.0","gn:admin2_code":"714.0","gn:admin3_code":"6997.0","gn:asciiname":"Riksu","gn:country_code":"EE","gn:dem":5,"gn:feature_class":"P","gn:feature_code":"PPL","gn:geonameid":589020,"gn:latitude":58.19833,"gn:longitude":22.09194,"gn:modification_date":"2017-11-25","gn:name":"Riksu","gn:population":0,"gn:timezone":"Europe/Tallinn","iso:country":"EE","lbl:bbox":"22.07194,58.17833,22.11194,58.21833","lbl:max_zoom":18,"lbl:min_zoom":13.5,"mz:hierarchy_label":1,"mz:is_current":1,"mz:min_zoom":12,"name:deu_x_preferred":["Riksu"],"name:est_x_preferred":["Riksu"],"name:fra_x_preferred":["Riksu"],"name:hye_x_preferred":["Ռիկսու"],"name:pol_x_preferred":["Riksu"],"name:spa_x_preferred":["Riksu"],"name:ukr_x_preferred":["Ріксу"],"name:vol_x_preferred":["Riksu"],"src:geom":"geonames","wof:belongsto":[85682947,102191581,1713307063,85633135,1713305627],"wof:breaches":[],"wof:concordances":{"gn:id":589020,"wk:page":"Riksu"},"wof:coterminous":[1713307063],"wof:country":"EE","wof:geomhash":"cc413dc3a718015361d57b2242325bcf","wof:hierarchy":[{"continent_id":102191581,"country_id":85633135,"county_id":1713305627,"localadmin_id":1713307063,"locality_id":1310076511,"region_id":85682947}],"wof:id":1310076511,"wof:lang_x_official":["est"],"wof:lang_x_spoken":["est"],"wof:lastmodified":1596674911,"wof:name":"Riksu","wof:parent_id":1713307063,"wof:placetype":"locality","wof:repo":"whosonfirst-data-admin-ee","wof:superseded_by":[],"wof:supersedes":[],"wof:tags":[]},"bbox":[22.09194,58.19833,22.09194,58.19833],"geometry":{"coordinates":[22.09194,58.19833],"type":"Point"}}