{"id":1343441171,"type":"Feature","properties":{"edtf:cessation":"uuuu","edtf:inception":"uuuu","geom:area":0,"geom:area_square_m":0,"geom:bbox":"27.04028,58.19472,27.04028,58.19472","geom:latitude":58.19472,"geom:longitude":27.04028,"gn:admin1_code":"12.0","gn:admin2_code":"622.0","gn:admin3_code":"4468.0","gn:asciiname":"Loko","gn:country_code":"EE","gn:dem":76,"gn:feature_class":"P","gn:feature_code":"PPL","gn:geonameid":794602,"gn:latitude":58.19472,"gn:longitude":27.04028,"gn:modification_date":"2017-11-25","gn:name":"Loko","gn:population":0,"gn:timezone":"Europe/Tallinn","iso:country":"EE","lbl:bbox":"27.02028,58.17472,27.06028,58.21472","lbl:max_zoom":18,"lbl:min_zoom":13.5,"mz:hierarchy_label":1,"mz:is_current":1,"mz:min_zoom":12,"name:deu_x_preferred":["Loko"],"name:est_x_preferred":["Loko"],"name:hye_x_preferred":["Լոկո"],"name:pol_x_preferred":["Loko"],"name:spa_x_preferred":["Loko"],"name:ukr_x_preferred":["Локо"],"name:vol_x_preferred":["Loko"],"src:geom":"geonames","wof:belongsto":[85682955,102191581,1713310961,85633135,1713305791],"wof:breaches":[],"wof:concordances":{"gn:id":794602,"wk:page":"Loko%2C_Estonia"},"wof:coterminous":[1713310961],"wof:country":"EE","wof:geomhash":"1879a4bfc006adcd90571b56ef0b1ddd","wof:hierarchy":[{"continent_id":102191581,"country_id":85633135,"county_id":1713305791,"localadmin_id":1713310961,"locality_id":1343441171,"region_id":85682955}],"wof:id":1343441171,"wof:lang_x_official":["est"],"wof:lang_x_spoken":["est"],"wof:lastmodified":1596676965,"wof:name":"Loko","wof:parent_id":1713310961,"wof:placetype":"locality","wof:repo":"whosonfirst-data-admin-ee","wof:superseded_by":[],"wof:supersedes":[],"wof:tags":[]},"bbox":[27.04028,58.19472,27.04028,58.19472],"geometry":{"coordinates":[27.04028,58.19472],"type":"Point"}}