{"id":1125974765,"type":"Feature","properties":{"edtf:cessation":"uuuu","edtf:inception":"uuuu","geom:area":0,"geom:area_square_m":0,"geom:bbox":"26.27167,58.16917,26.27167,58.16917","geom:latitude":58.16917,"geom:longitude":26.27167,"gn:country":"EE","gn:fcode":"PPL","gn:population":97,"iso:country":"EE","lbl:bbox":"26.25167,58.14917,26.29167,58.18917","lbl:latitude":58.16917,"lbl:longitude":26.27167,"lbl:max_zoom":18,"lbl:min_zoom":13,"mz:hierarchy_label":1,"mz:is_current":1,"mz:min_zoom":11,"mz:note":"Quattroshapes Point Gazetteer import 20170519","name:ceb_x_preferred":["Tilga"],"name:eng_x_preferred":["Tilga"],"name:est_x_preferred":["Tilga"],"name:fra_x_preferred":["Tilga"],"name:hye_x_preferred":["Տիլգա"],"name:nld_x_preferred":["Tilga"],"name:pol_x_preferred":["Tilga"],"name:spa_x_preferred":["Tilga"],"name:ukr_x_preferred":["Тілґа"],"name:vol_x_preferred":["Tilga"],"qs_pg:aaroncc":"EE","qs_pg:gn_country":"EE","qs_pg:gn_fcode":"PPL","qs_pg:gn_id":794012,"qs_pg:gn_pop":97,"qs_pg:name":"Tilgu","qs_pg:name_adm0":"Eesti","qs_pg:name_adm1":"Võrumaa","qs_pg:photos_9r":0,"qs_pg:photos_sr":0,"qs_pg:pop_sr":1,"qs_pg:qs_id":528658,"qs_pg:qs_pg_placetype":"locality","qs_pg:qs_pg_placetype_gp":"Town","qs_pg:woe_adm0":23424805,"qs_pg:woe_id":29399216,"src:geom":"qs_pg","src:lbl_centroid":"qs_pg","src:population":"geonames","woe:adm0_id":23424805,"woe:name_adm0":"Eesti","woe:name_adm1":"Võrumaa","woe:placetype":"Town","wof:belongsto":[85682995,102191581,1713310441,85633135,1713305757],"wof:breaches":[],"wof:concordances":{"gn:id":794012,"gp:id":29399216,"qs_pg:id":528658,"wd:id":"Q3453855"},"wof:coterminous":[1713310441],"wof:country":"EE","wof:created":1497298302,"wof:geomhash":"b6398ef1b07900f2cc8f321973483f05","wof:hierarchy":[{"continent_id":102191581,"country_id":85633135,"county_id":1713305757,"localadmin_id":1713310441,"locality_id":1125974765,"region_id":85682995}],"wof:id":1125974765,"wof:lang_x_official":["est"],"wof:lang_x_spoken":["est"],"wof:lastmodified":1596661921,"wof:name":"Tilgu","wof:parent_id":1713310441,"wof:placetype":"locality","wof:population":97,"wof:population_rank":1,"wof:repo":"whosonfirst-data-admin-ee","wof:superseded_by":[],"wof:supersedes":[],"wof:tags":[]},"bbox":[26.27167,58.16917,26.27167,58.16917],"geometry":{"coordinates":[26.27167,58.16917],"type":"Point"}}