{"id":1226442833,"type":"Feature","properties":{"edtf:cessation":"uuuu","edtf:inception":"uuuu","geom:area":0,"geom:area_square_m":0,"geom:bbox":"25.43333,59.01667,25.43333,59.01667","geom:latitude":59.01667,"geom:longitude":25.43333,"gn:admin1_code":"4.0","gn:admin2_code":"567.0","gn:admin3_code":"5083.0","gn:asciiname":"Poeiatu","gn:country_code":"EE","gn:dem":78,"gn:feature_class":"P","gn:feature_code":"PPL","gn:geonameid":589399,"gn:latitude":59.01667,"gn:longitude":25.43333,"gn:modification_date":"2017-11-25","gn:name":"Pöiatu","gn:population":0,"gn:timezone":"Europe/Tallinn","iso:country":"EE","lbl:bbox":"25.41333,58.99667,25.45333,59.03667","lbl:max_zoom":18,"lbl:min_zoom":13.5,"mz:hierarchy_label":1,"mz:is_current":1,"mz:min_zoom":12,"name:und_x_variant":["Peiatu","Pöiatu"],"src:geom":"geonames","wof:belongsto":[85683031,102191581,1713313261,85633135,1713305663],"wof:breaches":[],"wof:concordances":{"gn:id":589399},"wof:country":"EE","wof:geomhash":"ee49d5e5b3906509e3baba9b9bdea757","wof:hierarchy":[{"continent_id":102191581,"country_id":85633135,"county_id":1713305663,"localadmin_id":1713313261,"locality_id":1226442833,"region_id":85683031}],"wof:id":1226442833,"wof:lang_x_official":["est"],"wof:lang_x_spoken":["est"],"wof:lastmodified":1596661326,"wof:name":"Poeiatu","wof:parent_id":1713313261,"wof:placetype":"locality","wof:repo":"whosonfirst-data-admin-ee","wof:superseded_by":[],"wof:supersedes":[],"wof:tags":[]},"bbox":[25.43333,59.01667,25.43333,59.01667],"geometry":{"coordinates":[25.43333,59.01667],"type":"Point"}}