{"id":1259859649,"type":"Feature","properties":{"edtf:cessation":"uuuu","edtf:inception":"uuuu","geom:area":0,"geom:area_square_m":0,"geom:bbox":"27.18722,57.99278,27.18722,57.99278","geom:latitude":57.99278,"geom:longitude":27.18722,"gn:admin1_code":"12.0","gn:admin2_code":"708.0","gn:admin3_code":"9294.0","gn:asciiname":"Viira","gn:country_code":"EE","gn:dem":65,"gn:feature_class":"P","gn:feature_code":"PPL","gn:geonameid":8619980,"gn:latitude":57.99278,"gn:longitude":27.18722,"gn:modification_date":"2017-11-25","gn:name":"Viira","gn:population":0,"gn:timezone":"Europe/Tallinn","iso:country":"EE","lbl:bbox":"27.16722,57.97278,27.20722,58.01278","lbl:max_zoom":18,"lbl:min_zoom":13.5,"mz:hierarchy_label":1,"mz:is_current":1,"mz:min_zoom":12,"name:deu_x_preferred":["Viira"],"name:est_x_preferred":["Viira"],"name:fin_x_preferred":["Viira"],"name:nld_x_preferred":["Viira"],"name:ukr_x_preferred":["Війра"],"src:geom":"geonames","wof:belongsto":[85682955,102191581,1713313365,85633135,1713305793],"wof:breaches":[],"wof:concordances":{"gn:id":8619980},"wof:coterminous":[1713313365],"wof:country":"EE","wof:geomhash":"5ad8d8c13dd14af24e86dba528d4d856","wof:hierarchy":[{"continent_id":102191581,"country_id":85633135,"county_id":1713305793,"localadmin_id":1713313365,"locality_id":1259859649,"region_id":85682955}],"wof:id":1259859649,"wof:lang_x_official":["est"],"wof:lang_x_spoken":["est"],"wof:lastmodified":1596677002,"wof:name":"Viira","wof:parent_id":1713313365,"wof:placetype":"locality","wof:repo":"whosonfirst-data-admin-ee","wof:superseded_by":[],"wof:supersedes":[],"wof:tags":[]},"bbox":[27.18722,57.99278,27.18722,57.99278],"geometry":{"coordinates":[27.18722,57.99278],"type":"Point"}}