{"id":1259654647,"type":"Feature","properties":{"edtf:cessation":"uuuu","edtf:inception":"uuuu","geom:area":0,"geom:area_square_m":0,"geom:bbox":"22.19139,58.08806,22.19139,58.08806","geom:latitude":58.08806,"geom:longitude":22.19139,"gn:admin1_code":"14.0","gn:admin2_code":"714.0","gn:admin3_code":"4608.0","gn:asciiname":"Lou","gn:cc2":"EE","gn:country_code":"EE","gn:dem":10,"gn:feature_class":"P","gn:feature_code":"PPL","gn:geonameid":590507,"gn:latitude":58.08806,"gn:longitude":22.19139,"gn:modification_date":"2017-11-25","gn:name":"Lõu","gn:population":0,"gn:timezone":"Europe/Tallinn","iso:country":"EE","lbl:bbox":"22.17139,58.06806,22.21139,58.10806","lbl:max_zoom":18,"lbl:min_zoom":13.5,"mz:hierarchy_label":1,"mz:is_current":1,"mz:min_zoom":12,"name:deu_x_preferred":["Lõu"],"name:est_x_preferred":["Lõu"],"name:hye_x_preferred":["Լիու"],"name:pol_x_preferred":["Lõu"],"name:spa_x_preferred":["Lõu"],"name:ukr_x_preferred":["Лиу"],"name:und_x_variant":["Lyo"],"name:vol_x_preferred":["Lõu"],"src:geom":"geonames","wof:belongsto":[85682947,102191581,1713306557,85633135,1713305627],"wof:breaches":[],"wof:concordances":{"gn:id":590507,"wk:page":"L%C3%B5u"},"wof:coterminous":[1713306557],"wof:country":"EE","wof:geomhash":"e3938667767d2a35964a6c89d8604722","wof:hierarchy":[{"continent_id":102191581,"country_id":85633135,"county_id":1713305627,"localadmin_id":1713306557,"locality_id":1259654647,"region_id":85682947}],"wof:id":1259654647,"wof:lang_x_official":["est"],"wof:lang_x_spoken":["est"],"wof:lastmodified":1596674914,"wof:name":"Lou","wof:parent_id":1713306557,"wof:placetype":"locality","wof:repo":"whosonfirst-data-admin-ee","wof:superseded_by":[],"wof:supersedes":[],"wof:tags":[]},"bbox":[22.19139,58.08806,22.19139,58.08806],"geometry":{"coordinates":[22.19139,58.08806],"type":"Point"}}