{"id":1125956523,"type":"Feature","properties":{"edtf:cessation":"uuuu","edtf:inception":"uuuu","geom:area":0,"geom:area_square_m":0,"geom:bbox":"26.35278,59.415,26.35278,59.415","geom:latitude":59.415,"geom:longitude":26.35278,"gn:country":"EE","gn:fcode":"PPL","gn:population":151,"iso:country":"EE","lbl:bbox":"26.33278,59.395,26.37278,59.435","lbl:latitude":59.415,"lbl:longitude":26.35278,"lbl:max_zoom":18,"lbl:min_zoom":13,"mz:hierarchy_label":1,"mz:is_current":1,"mz:min_zoom":11,"mz:note":"Quattroshapes Point Gazetteer import 20170519","name:ceb_x_preferred":["Põdruse"],"name:eng_x_preferred":["Põdruse"],"name:est_x_preferred":["Põdruse"],"name:fra_x_preferred":["Põdruse"],"name:hye_x_preferred":["Պիդռուսե"],"name:nld_x_preferred":["Põdruse"],"name:pol_x_preferred":["Põdruse"],"name:swe_x_preferred":["Põdruse"],"name:und_x_variant":["Põdruse Asundus"],"name:vol_x_preferred":["Põdruse"],"qs_pg:aaroncc":"EE","qs_pg:gn_country":"EE","qs_pg:gn_fcode":"PPL","qs_pg:gn_id":589410,"qs_pg:gn_pop":151,"qs_pg:name":"Põdruse","qs_pg:name_adm0":"Eesti","qs_pg:name_adm1":"Lääne-Virumaa","qs_pg:photos_9r":0,"qs_pg:photos_sr":0,"qs_pg:pop_sr":1,"qs_pg:qs_id":406169,"qs_pg:qs_pg_placetype":"locality","qs_pg:qs_pg_placetype_gp":"Town","qs_pg:woe_adm0":23424805,"qs_pg:woe_id":844797,"src:geom":"qs_pg","src:lbl_centroid":"qs_pg","src:population":"geonames","woe:adm0_id":23424805,"woe:name_adm0":"Eesti","woe:name_adm1":"Lääne-Virumaa","woe:placetype":"Town","wof:belongsto":[85683049,102191581,1713308263,85633135,1713305775],"wof:breaches":[],"wof:concordances":{"gn:id":589410,"gp:id":844797,"qs_pg:id":406169,"wd:id":"Q3464756"},"wof:coterminous":[1713308263],"wof:country":"EE","wof:created":1497297636,"wof:geomhash":"c300fde3d08e5c070c2c664204828c3c","wof:hierarchy":[{"continent_id":102191581,"country_id":85633135,"county_id":1713305775,"localadmin_id":1713308263,"locality_id":1125956523,"region_id":85683049}],"wof:id":1125956523,"wof:lang_x_official":["est"],"wof:lang_x_spoken":["est"],"wof:lastmodified":1596678046,"wof:name":"Põdruse","wof:parent_id":1713308263,"wof:placetype":"locality","wof:population":151,"wof:population_rank":1,"wof:repo":"whosonfirst-data-admin-ee","wof:superseded_by":[],"wof:supersedes":[],"wof:tags":[]},"bbox":[26.35278,59.415,26.35278,59.415],"geometry":{"coordinates":[26.35278,59.415],"type":"Point"}}