{"id":1259659641,"type":"Feature","properties":{"edtf:cessation":"uuuu","edtf:inception":"uuuu","geom:area":0,"geom:area_square_m":0,"geom:bbox":"26.48583,58.18889,26.48583,58.18889","geom:latitude":58.18889,"geom:longitude":26.48583,"gn:admin1_code":"18.0","gn:admin2_code":"528.0","gn:admin3_code":"1665.0","gn:asciiname":"Etsaste","gn:country_code":"EE","gn:dem":86,"gn:feature_class":"P","gn:feature_code":"PPL","gn:geonameid":592239,"gn:latitude":58.18889,"gn:longitude":26.48583,"gn:modification_date":"2017-11-25","gn:name":"Etsaste","gn:population":0,"gn:timezone":"Europe/Tallinn","iso:country":"EE","lbl:bbox":"26.46583,58.16889,26.50583,58.20889","lbl:max_zoom":18,"lbl:min_zoom":13.5,"mz:hierarchy_label":1,"mz:is_current":1,"mz:min_zoom":12,"name:est_x_preferred":["Etsaste"],"name:hye_x_preferred":["Էցաստե"],"name:pol_x_preferred":["Etsaste"],"name:spa_x_preferred":["Etsaste"],"name:ukr_x_preferred":["Етсасте"],"name:vol_x_preferred":["Etsaste"],"src:geom":"geonames","wof:belongsto":[85682995,102191581,1713313373,85633135,1713305715],"wof:breaches":[],"wof:concordances":{"gn:id":592239,"wk:page":"Etsaste"},"wof:coterminous":[1713313373],"wof:country":"EE","wof:geomhash":"010730212bacf14ffa7bac171c0b6435","wof:hierarchy":[{"continent_id":102191581,"country_id":85633135,"county_id":1713305715,"localadmin_id":1713313373,"locality_id":1259659641,"region_id":85682995}],"wof:id":1259659641,"wof:lang_x_official":["est"],"wof:lang_x_spoken":["est"],"wof:lastmodified":1596676767,"wof:name":"Etsaste","wof:parent_id":1713313373,"wof:placetype":"locality","wof:repo":"whosonfirst-data-admin-ee","wof:superseded_by":[],"wof:supersedes":[],"wof:tags":[]},"bbox":[26.48583,58.18889,26.48583,58.18889],"geometry":{"coordinates":[26.48583,58.18889],"type":"Point"}}