{"id":1343937151,"type":"Feature","properties":{"edtf:cessation":"uuuu","edtf:inception":"uuuu","geom:area":0,"geom:area_square_m":0,"geom:bbox":"24.77639,58.91472,24.77639,58.91472","geom:latitude":58.91472,"geom:longitude":24.77639,"gn:admin1_code":"13.0","gn:admin2_code":"668.0","gn:admin3_code":"6533.0","gn:asciiname":"Hiienurme","gn:country_code":"EE","gn:dem":58,"gn:feature_class":"P","gn:feature_code":"PPL","gn:geonameid":592134,"gn:latitude":58.91472,"gn:longitude":24.77639,"gn:modification_date":"2017-11-25","gn:name":"Hiienurme","gn:population":0,"gn:timezone":"Europe/Tallinn","iso:country":"EE","lbl:bbox":"24.75639,58.89472,24.79639,58.93472","lbl:max_zoom":18,"lbl:min_zoom":13.5,"mz:hierarchy_label":1,"mz:is_current":1,"mz:min_zoom":12,"name:und_x_variant":["Hiinurme","Khiynurme","Hiienurme"],"src:geom":"geonames","wof:belongsto":[85683013,102191581,1713314065,85633135,1713305711],"wof:breaches":[],"wof:concordances":{"gn:id":592134},"wof:country":"EE","wof:geomhash":"b8f443ff36a8e3c50100687b921f9d9f","wof:hierarchy":[{"continent_id":102191581,"country_id":85633135,"county_id":1713305711,"localadmin_id":1713314065,"locality_id":1343937151,"region_id":85683013}],"wof:id":1343937151,"wof:lang_x_official":["est"],"wof:lang_x_spoken":["est"],"wof:lastmodified":1596676728,"wof:name":"Hiienurme","wof:parent_id":1713314065,"wof:placetype":"locality","wof:repo":"whosonfirst-data-admin-ee","wof:superseded_by":[],"wof:supersedes":[],"wof:tags":[]},"bbox":[24.77639,58.91472,24.77639,58.91472],"geometry":{"coordinates":[24.77639,58.91472],"type":"Point"}}