{"id":1343435379,"type":"Feature","properties":{"edtf:cessation":"uuuu","edtf:inception":"uuuu","geom:area":0,"geom:area_square_m":0,"geom:bbox":"25.92417,58.23667,25.92417,58.23667","geom:latitude":58.23667,"geom:longitude":25.92417,"gn:admin1_code":"20.0","gn:admin2_code":"899.0","gn:admin3_code":"8159.0","gn:asciiname":"Saegae","gn:country_code":"EE","gn:dem":43,"gn:feature_class":"P","gn:feature_code":"PPL","gn:geonameid":8620719,"gn:latitude":58.23667,"gn:longitude":25.92417,"gn:modification_date":"2017-11-25","gn:name":"Sägä","gn:population":0,"gn:timezone":"Europe/Tallinn","iso:country":"EE","lbl:bbox":"25.90417,58.21667,25.94417,58.25667","lbl:max_zoom":18,"lbl:min_zoom":13.5,"mz:hierarchy_label":1,"mz:is_current":1,"mz:min_zoom":12,"name:und_x_variant":["Sägä","Sägaküla"],"src:geom":"geonames","wof:belongsto":[85682985,102191581,1713310085,85633135,1713305669],"wof:breaches":[],"wof:concordances":{"gn:id":8620719},"wof:country":"EE","wof:geomhash":"0314bc5baf53fc70a183f0967cad6fdb","wof:hierarchy":[{"continent_id":102191581,"country_id":85633135,"county_id":1713305669,"localadmin_id":1713310085,"locality_id":1343435379,"region_id":85682985}],"wof:id":1343435379,"wof:lang_x_official":["est"],"wof:lang_x_spoken":["est"],"wof:lastmodified":1596661250,"wof:name":"Saegae","wof:parent_id":1713310085,"wof:placetype":"locality","wof:repo":"whosonfirst-data-admin-ee","wof:superseded_by":[],"wof:supersedes":[],"wof:tags":[]},"bbox":[25.92417,58.23667,25.92417,58.23667],"geometry":{"coordinates":[25.92417,58.23667],"type":"Point"}}