{"id":1209978563,"type":"Feature","properties":{"edtf:cessation":"uuuu","edtf:inception":"uuuu","geom:area":0,"geom:area_square_m":0,"geom:bbox":"25.41667,58.55,25.41667,58.55","geom:latitude":58.55,"geom:longitude":25.41667,"gn:admin1_code":"20.0","gn:admin2_code":"615.0","gn:admin3_code":"9765.0","gn:asciiname":"Sassi","gn:cc2":"EE","gn:country_code":"EE","gn:dem":68,"gn:feature_class":"P","gn:feature_code":"PPL","gn:geonameid":588787,"gn:latitude":58.55,"gn:longitude":25.41667,"gn:modification_date":"2017-11-25","gn:name":"Sassi","gn:population":0,"gn:timezone":"Europe/Tallinn","iso:country":"EE","lbl:bbox":"25.39667,58.53,25.43667,58.57","lbl:max_zoom":18,"lbl:min_zoom":13.5,"mz:hierarchy_label":1,"mz:is_current":1,"mz:min_zoom":12,"name:und_x_variant":["Sass","Sassi"],"src:geom":"geonames","wof:belongsto":[85682985,102191581,1713311725,85633135,1713305735],"wof:breaches":[],"wof:concordances":{"gn:id":588787},"wof:country":"EE","wof:geomhash":"f86ea9d638fab3563484429dfa3eaabf","wof:hierarchy":[{"continent_id":102191581,"country_id":85633135,"county_id":1713305735,"localadmin_id":1713311725,"locality_id":1209978563,"region_id":85682985}],"wof:id":1209978563,"wof:lang_x_official":["est"],"wof:lang_x_spoken":["est"],"wof:lastmodified":1596663461,"wof:name":"Sassi","wof:parent_id":1713311725,"wof:placetype":"locality","wof:repo":"whosonfirst-data-admin-ee","wof:superseded_by":[],"wof:supersedes":[],"wof:tags":[]},"bbox":[25.41667,58.55,25.41667,58.55],"geometry":{"coordinates":[25.41667,58.55],"type":"Point"}}