{"id":1344231095,"type":"Feature","properties":{"edtf:cessation":"uuuu","edtf:inception":"uuuu","geom:area":0,"geom:area_square_m":0,"geom:bbox":"27.10722,57.72139,27.10722,57.72139","geom:latitude":57.72139,"geom:longitude":27.10722,"gn:admin1_code":"21.0","gn:admin2_code":"698.0","gn:admin3_code":"2008.0","gn:asciiname":"Ihatsi","gn:country_code":"EE","gn:dem":237,"gn:feature_class":"P","gn:feature_code":"PPL","gn:geonameid":8620186,"gn:latitude":57.72139,"gn:longitude":27.10722,"gn:modification_date":"2017-11-25","gn:name":"Ihatsi","gn:population":0,"gn:timezone":"Europe/Tallinn","iso:country":"EE","lbl:bbox":"27.08722,57.70139,27.12722,57.74139","lbl:max_zoom":18,"lbl:min_zoom":13.5,"mz:hierarchy_label":1,"mz:is_current":1,"mz:min_zoom":12,"src:geom":"geonames","wof:belongsto":[85682937,102191581,1713315273,85633135,1713305787],"wof:breaches":[],"wof:concordances":{"gn:id":8620186},"wof:coterminous":[1713315273],"wof:country":"EE","wof:geomhash":"de128ec84b8985ada6a8c0fdf5cac373","wof:hierarchy":[{"continent_id":102191581,"country_id":85633135,"county_id":1713305787,"localadmin_id":1713315273,"locality_id":1344231095,"region_id":85682937}],"wof:id":1344231095,"wof:lang_x_official":["est"],"wof:lang_x_spoken":["est"],"wof:lastmodified":1596676891,"wof:name":"Ihatsi","wof:parent_id":1713315273,"wof:placetype":"locality","wof:repo":"whosonfirst-data-admin-ee","wof:superseded_by":[],"wof:supersedes":[],"wof:tags":[]},"bbox":[27.10722,57.72139,27.10722,57.72139],"geometry":{"coordinates":[27.10722,57.72139],"type":"Point"}}