{"id":1293791387,"type":"Feature","properties":{"edtf:cessation":"uuuu","edtf:inception":"uuuu","geom:area":0,"geom:area_square_m":0,"geom:bbox":"27.74083,59.055,27.74083,59.055","geom:latitude":59.055,"geom:longitude":27.74083,"gn:admin1_code":"3.0","gn:admin2_code":"130.0","gn:admin3_code":"2767.0","gn:asciiname":"Karoli","gn:country_code":"EE","gn:dem":37,"gn:feature_class":"P","gn:feature_code":"PPL","gn:geonameid":591579,"gn:latitude":59.055,"gn:longitude":27.74083,"gn:modification_date":"2017-11-25","gn:name":"Karoli","gn:population":0,"gn:timezone":"Europe/Tallinn","iso:country":"EE","lbl:bbox":"27.72083,59.035,27.76083,59.075","lbl:max_zoom":18,"lbl:min_zoom":13.5,"mz:hierarchy_label":1,"mz:is_current":1,"mz:min_zoom":12,"name:deu_x_preferred":["Karoli"],"name:est_x_preferred":["Karoli"],"name:fra_x_preferred":["Karoli"],"name:hye_x_preferred":["Կառոլի"],"name:pol_x_preferred":["Karoli"],"name:spa_x_preferred":["Karoli"],"name:vol_x_preferred":["Karoli"],"src:geom":"geonames","wof:belongsto":[85683059,102191581,1713311593,85633135,1713305693],"wof:breaches":[],"wof:concordances":{"gn:id":591579,"wk:page":"Karoli%2C_Estonia"},"wof:coterminous":[1713311593],"wof:country":"EE","wof:geomhash":"752bf84bfbf79c6a36bc68f764152f31","wof:hierarchy":[{"continent_id":102191581,"country_id":85633135,"county_id":1713305693,"localadmin_id":1713311593,"locality_id":1293791387,"region_id":85683059}],"wof:id":1293791387,"wof:lang_x_official":["est"],"wof:lang_x_spoken":["est"],"wof:lastmodified":1596660755,"wof:name":"Karoli","wof:parent_id":1713311593,"wof:placetype":"locality","wof:repo":"whosonfirst-data-admin-ee","wof:superseded_by":[],"wof:supersedes":[],"wof:tags":[]},"bbox":[27.74083,59.055,27.74083,59.055],"geometry":{"coordinates":[27.74083,59.055],"type":"Point"}}