{"id":1226325917,"type":"Feature","properties":{"edtf:cessation":"uuuu","edtf:inception":"uuuu","geom:area":0,"geom:area_square_m":0,"geom:bbox":"23.20417,58.64083,23.20417,58.64083","geom:latitude":58.64083,"geom:longitude":23.20417,"gn:admin1_code":"14.0","gn:admin2_code":"478.0","gn:admin3_code":"6638.0","gn:asciiname":"Poeitse","gn:country_code":"EE","gn:dem":23,"gn:feature_class":"P","gn:feature_code":"PPL","gn:geonameid":589395,"gn:latitude":58.64083,"gn:longitude":23.20417,"gn:modification_date":"2017-11-25","gn:name":"Pöitse","gn:population":0,"gn:timezone":"Europe/Tallinn","iso:country":"EE","lbl:bbox":"23.18417,58.62083,23.22417,58.66083","lbl:max_zoom":18,"lbl:min_zoom":13.5,"mz:hierarchy_label":1,"mz:is_current":1,"mz:min_zoom":12,"name:deu_x_preferred":["Põitse"],"name:est_x_preferred":["Põitse"],"name:hye_x_preferred":["Պիիցե"],"name:pol_x_preferred":["Põitse"],"name:spa_x_preferred":["Põitse"],"name:und_x_variant":["Pyytsi","Pöitse"],"name:vol_x_preferred":["Põitse"],"src:geom":"geonames","wof:belongsto":[85682947,102191581,1713306245,85633135,1713305623],"wof:breaches":[],"wof:concordances":{"gn:id":589395,"wk:page":"P%C3%B5itse"},"wof:coterminous":[1713306245],"wof:country":"EE","wof:geomhash":"6ffe75f14c682c03fd920da28eb0f4e9","wof:hierarchy":[{"continent_id":102191581,"country_id":85633135,"county_id":1713305623,"localadmin_id":1713306245,"locality_id":1226325917,"region_id":85682947}],"wof:id":1226325917,"wof:lang_x_official":["est"],"wof:lang_x_spoken":["est"],"wof:lastmodified":1596675297,"wof:name":"Poeitse","wof:parent_id":1713306245,"wof:placetype":"locality","wof:repo":"whosonfirst-data-admin-ee","wof:superseded_by":[],"wof:supersedes":[],"wof:tags":[]},"bbox":[23.20417,58.64083,23.20417,58.64083],"geometry":{"coordinates":[23.20417,58.64083],"type":"Point"}}