{"id":1343864549,"type":"Feature","properties":{"edtf:cessation":"uuuu","edtf:inception":"uuuu","geom:area":0,"geom:area_square_m":0,"geom:bbox":"25.60278,58.87778,25.60278,58.87778","geom:latitude":58.87778,"geom:longitude":25.60278,"gn:admin1_code":"4.0","gn:admin2_code":"567.0","gn:admin3_code":"5317.0","gn:asciiname":"Kriilevaelja","gn:country_code":"EE","gn:dem":70,"gn:feature_class":"P","gn:feature_code":"PPL","gn:geonameid":793308,"gn:latitude":58.87778,"gn:longitude":25.60278,"gn:modification_date":"2017-11-25","gn:name":"Kriilevälja","gn:population":0,"gn:timezone":"Europe/Tallinn","iso:country":"EE","lbl:bbox":"25.58278,58.85778,25.62278,58.89778","lbl:max_zoom":18,"lbl:min_zoom":13.5,"mz:hierarchy_label":1,"mz:is_current":1,"mz:min_zoom":12,"name:est_x_preferred":["Kriilevälja"],"name:hye_x_preferred":["Կռիիլևելյա"],"name:pol_x_preferred":["Kriilevälja"],"name:ukr_x_preferred":["Крійлевялья"],"name:vol_x_preferred":["Kriilevälja"],"src:geom":"geonames","wof:belongsto":[85683031,102191581,1713308297,85633135,1713305663],"wof:breaches":[],"wof:concordances":{"gn:id":793308,"wk:page":"Kriilev%C3%A4lja"},"wof:coterminous":[1713308253],"wof:country":"EE","wof:geomhash":"1667e08a641dbef186c7ef531b16335a","wof:hierarchy":[{"continent_id":102191581,"country_id":85633135,"county_id":1713305663,"localadmin_id":1713308297,"locality_id":1343864549,"region_id":85683031}],"wof:id":1343864549,"wof:lang_x_official":["est"],"wof:lang_x_spoken":["est"],"wof:lastmodified":1596661327,"wof:name":"Kriilevaelja","wof:parent_id":1713308297,"wof:placetype":"locality","wof:repo":"whosonfirst-data-admin-ee","wof:superseded_by":[],"wof:supersedes":[],"wof:tags":[]},"bbox":[25.60278,58.87778,25.60278,58.87778],"geometry":{"coordinates":[25.60278,58.87778],"type":"Point"}}