{"id":1209786749,"type":"Feature","properties":{"edtf:cessation":"uuuu","edtf:inception":"uuuu","geom:area":0,"geom:area_square_m":0,"geom:bbox":"22.73556,58.30417,22.73556,58.30417","geom:latitude":58.30417,"geom:longitude":22.73556,"gn:admin1_code":"14.0","gn:admin2_code":"714.0","gn:admin3_code":"6653.0","gn:asciiname":"Lasnamaa","gn:country_code":"EE","gn:dem":18,"gn:feature_class":"P","gn:feature_code":"PPL","gn:geonameid":590776,"gn:latitude":58.30417,"gn:longitude":22.73556,"gn:modification_date":"2017-11-25","gn:name":"Lasnamaa","gn:population":0,"gn:timezone":"Europe/Tallinn","iso:country":"EE","lbl:bbox":"22.71556,58.28417,22.75556,58.32417","lbl:max_zoom":18,"lbl:min_zoom":13.5,"mz:hierarchy_label":1,"mz:is_current":1,"mz:min_zoom":12,"name:und_x_variant":["Lakhnamakh","Lasnamaa"],"src:geom":"geonames","wof:belongsto":[85682947,102191581,1713307183,85633135,1713305627],"wof:breaches":[],"wof:concordances":{"gn:id":590776},"wof:country":"EE","wof:geomhash":"8817f2793f76a3636041a37394e187b9","wof:hierarchy":[{"continent_id":102191581,"country_id":85633135,"county_id":1713305627,"localadmin_id":1713307183,"locality_id":1209786749,"region_id":85682947}],"wof:id":1209786749,"wof:lang_x_official":["est"],"wof:lang_x_spoken":["est"],"wof:lastmodified":1596674951,"wof:name":"Lasnamaa","wof:parent_id":1713307183,"wof:placetype":"locality","wof:repo":"whosonfirst-data-admin-ee","wof:superseded_by":[],"wof:supersedes":[],"wof:tags":[]},"bbox":[22.73556,58.30417,22.73556,58.30417],"geometry":{"coordinates":[22.73556,58.30417],"type":"Point"}}