{"id":1260067415,"type":"Feature","properties":{"edtf:cessation":"uuuu","edtf:inception":"uuuu","geom:area":0,"geom:area_square_m":0,"geom:bbox":"27.05528,57.98361,27.05528,57.98361","geom:latitude":57.98361,"geom:longitude":27.05528,"gn:admin1_code":"12.0","gn:admin2_code":"622.0","gn:admin3_code":"1844.0","gn:asciiname":"Koiola","gn:country_code":"EE","gn:dem":91,"gn:feature_class":"P","gn:feature_code":"PPL","gn:geonameid":591228,"gn:latitude":57.98361,"gn:longitude":27.05528,"gn:modification_date":"2017-11-25","gn:name":"Koiola","gn:population":0,"gn:timezone":"Europe/Tallinn","iso:country":"EE","lbl:bbox":"27.03528,57.96361,27.07528,58.00361","lbl:max_zoom":18,"lbl:min_zoom":13.5,"mz:hierarchy_label":1,"mz:is_current":1,"mz:min_zoom":12,"src:geom":"geonames","wof:belongsto":[85682955,102191581,1713310957,85633135,1713305791],"wof:breaches":[],"wof:concordances":{"gn:id":591228},"wof:country":"EE","wof:geomhash":"3fd4bf3aec2d6465106216e2fa2e49c1","wof:hierarchy":[{"continent_id":102191581,"country_id":85633135,"county_id":1713305791,"localadmin_id":1713310957,"locality_id":1260067415,"region_id":85682955}],"wof:id":1260067415,"wof:lang_x_official":["est"],"wof:lang_x_spoken":["est"],"wof:lastmodified":1596676965,"wof:name":"Koiola","wof:parent_id":1713310957,"wof:placetype":"locality","wof:repo":"whosonfirst-data-admin-ee","wof:superseded_by":[],"wof:supersedes":[],"wof:tags":[]},"bbox":[27.05528,57.98361,27.05528,57.98361],"geometry":{"coordinates":[27.05528,57.98361],"type":"Point"}}