{"id":1125890363,"type":"Feature","properties":{"edtf:cessation":"uuuu","edtf:inception":"uuuu","geom:area":0,"geom:area_square_m":0,"geom:bbox":"24.08167,58.87889,24.08167,58.87889","geom:latitude":58.87889,"geom:longitude":24.08167,"gn:country":"EE","gn:fcode":"PPL","gn:population":332,"iso:country":"EE","lbl:bbox":"24.06167,58.85889,24.10167,58.89889","lbl:latitude":58.87889,"lbl:longitude":24.08167,"lbl:max_zoom":17,"lbl:min_zoom":12.5,"mz:hierarchy_label":1,"mz:is_current":1,"mz:min_zoom":11,"mz:note":"Quattroshapes Point Gazetteer import 20170519","name:ceb_x_preferred":["Kullamaa"],"name:ces_x_preferred":["Kullamaa"],"name:deu_x_preferred":["Kullamaa"],"name:eng_x_preferred":["Kullamaa"],"name:est_x_preferred":["Kullamaa"],"name:hye_x_preferred":["Կուլլամաա"],"name:pol_x_preferred":["Kullamaa"],"name:rus_x_preferred":["Кулламаа"],"name:srp_x_preferred":["Кулама"],"name:swe_x_preferred":["Kullamaa"],"name:ukr_x_preferred":["Кулламаа"],"name:und_x_variant":["Gol’denbek"],"name:vol_x_preferred":["Kullamaa"],"name:zho_x_preferred":["庫拉馬"],"qs_pg:aaroncc":"EE","qs_pg:gn_country":"EE","qs_pg:gn_fcode":"PPL","qs_pg:gn_id":590996,"qs_pg:gn_pop":332,"qs_pg:name":"Kullamaa","qs_pg:name_adm0":"Eesti","qs_pg:name_adm1":"Läänemaa","qs_pg:photos_9k":1,"qs_pg:photos_9r":1,"qs_pg:photos_all":1,"qs_pg:photos_sr":0,"qs_pg:pop_sr":2,"qs_pg:qs_id":915763,"qs_pg:qs_pg_placetype":"locality","qs_pg:qs_pg_placetype_gp":"Town","qs_pg:woe_adm0":23424805,"qs_pg:woe_id":843331,"src:geom":"qs_pg","src:lbl_centroid":"qs_pg","src:population":"geonames","woe:adm0_id":23424805,"woe:name_adm0":"Eesti","woe:name_adm1":"Läänemaa","woe:placetype":"Town","wof:belongsto":[85683001,102191581,1713308911,85633135,1713305701],"wof:breaches":[],"wof:concordances":{"gn:id":590996,"gp:id":843331,"qs_pg:id":915763},"wof:coterminous":[1713308911],"wof:country":"EE","wof:created":1497295286,"wof:geomhash":"25a3d9c90205c720851be16860b31506","wof:hierarchy":[{"continent_id":102191581,"country_id":85633135,"county_id":1713305701,"localadmin_id":1713308911,"locality_id":1125890363,"region_id":85683001}],"wof:id":1125890363,"wof:lang_x_official":["est"],"wof:lang_x_spoken":["est"],"wof:lastmodified":1596677433,"wof:name":"Kullamaa","wof:parent_id":1713308911,"wof:placetype":"locality","wof:population":332,"wof:population_rank":2,"wof:repo":"whosonfirst-data-admin-ee","wof:superseded_by":[],"wof:supersedes":[],"wof:tags":[]},"bbox":[24.08167,58.87889,24.08167,58.87889],"geometry":{"coordinates":[24.08167,58.87889],"type":"Point"}}