{"id":1343358217,"type":"Feature","properties":{"edtf:cessation":"uuuu","edtf:inception":"uuuu","geom:area":0,"geom:area_square_m":0,"geom:bbox":"26.60389,58.89444,26.60389,58.89444","geom:latitude":58.89444,"geom:longitude":26.60389,"gn:admin1_code":"5.0","gn:admin2_code":"247.0","gn:admin3_code":"8404.0","gn:asciiname":"Tuimoisa","gn:cc2":"EE","gn:country_code":"EE","gn:dem":102,"gn:feature_class":"P","gn:feature_code":"PPL","gn:geonameid":588164,"gn:latitude":58.89444,"gn:longitude":26.60389,"gn:modification_date":"2017-11-25","gn:name":"Tuimõisa","gn:population":0,"gn:timezone":"Europe/Tallinn","iso:country":"EE","lbl:bbox":"26.58389,58.87444,26.62389,58.91444","lbl:max_zoom":18,"lbl:min_zoom":13.5,"mz:hierarchy_label":1,"mz:is_current":1,"mz:min_zoom":12,"name:und_x_variant":["Tuymyyza","Tuimõisa"],"src:geom":"geonames","wof:belongsto":[85683009,102191581,1713315425,85633135,1713305767],"wof:breaches":[],"wof:concordances":{"gn:id":588164},"wof:coterminous":[1713315425],"wof:country":"EE","wof:geomhash":"b10d0c996df6936feeedb6b6908710a5","wof:hierarchy":[{"continent_id":102191581,"country_id":85633135,"county_id":1713305767,"localadmin_id":1713315425,"locality_id":1343358217,"region_id":85683009}],"wof:id":1343358217,"wof:lang_x_official":["est"],"wof:lang_x_spoken":["est"],"wof:lastmodified":1596676571,"wof:name":"Tuimoisa","wof:parent_id":1713315425,"wof:placetype":"locality","wof:repo":"whosonfirst-data-admin-ee","wof:superseded_by":[],"wof:supersedes":[],"wof:tags":[]},"bbox":[26.60389,58.89444,26.60389,58.89444],"geometry":{"coordinates":[26.60389,58.89444],"type":"Point"}}