{"id":1126003895,"type":"Feature","properties":{"edtf:cessation":"uuuu","edtf:inception":"uuuu","geom:area":0,"geom:area_square_m":0,"geom:bbox":"27.16028,58.02056,27.16028,58.02056","geom:latitude":58.02056,"geom:longitude":27.16028,"gn:country":"EE","gn:fcode":"PPL","gn:population":123,"iso:country":"EE","lbl:bbox":"27.14028,58.00056,27.18028,58.04056","lbl:latitude":58.02056,"lbl:longitude":27.16028,"lbl:max_zoom":18,"lbl:min_zoom":13,"mz:hierarchy_label":1,"mz:is_current":1,"mz:min_zoom":11,"mz:note":"Quattroshapes Point Gazetteer import 20170519","name:bul_x_preferred":["Парци"],"name:ceb_x_preferred":["Partsi"],"name:eng_x_preferred":["Partsi"],"name:est_x_preferred":["Partsi"],"name:hye_x_preferred":["Պառցի"],"name:nld_x_preferred":["Partsi"],"name:pol_x_preferred":["Partsi"],"name:spa_x_preferred":["Partsi"],"name:swe_x_preferred":["Partsi"],"name:ukr_x_preferred":["Партсі"],"name:vol_x_preferred":["Partsi"],"name:vro_x_preferred":["Pardsi"],"qs_pg:aaroncc":"EE","qs_pg:gn_country":"EE","qs_pg:gn_fcode":"PPL","qs_pg:gn_id":589568,"qs_pg:gn_pop":123,"qs_pg:name":"Partsi","qs_pg:name_adm0":"Eesti","qs_pg:name_adm1":"Põlvamaa","qs_pg:photos_9k":1,"qs_pg:photos_9r":1,"qs_pg:photos_all":2,"qs_pg:photos_sr":0,"qs_pg:pop_sr":1,"qs_pg:qs_id":915895,"qs_pg:qs_pg_placetype":"locality","qs_pg:qs_pg_placetype_gp":"Town","qs_pg:woe_adm0":23424805,"qs_pg:woe_id":844641,"src:geom":"qs_pg","src:lbl_centroid":"qs_pg","src:population":"geonames","woe:adm0_id":23424805,"woe:name_adm0":"Eesti","woe:name_adm1":"Põlvamaa","woe:placetype":"Town","wof:belongsto":[85682955,102191581,1713313407,85633135,1713305791],"wof:breaches":[],"wof:concordances":{"gn:id":589568,"gp:id":844641,"qs_pg:id":915895,"wd:id":"Q3457468"},"wof:coterminous":[1713313407],"wof:country":"EE","wof:created":1497299813,"wof:geomhash":"2f94de8ecee27cb0942cb950133ba129","wof:hierarchy":[{"continent_id":102191581,"country_id":85633135,"county_id":1713305791,"localadmin_id":1713313407,"locality_id":1126003895,"region_id":85682955}],"wof:id":1126003895,"wof:lang_x_official":["est"],"wof:lang_x_spoken":["est"],"wof:lastmodified":1596676973,"wof:name":"Partsi","wof:parent_id":1713313407,"wof:placetype":"locality","wof:population":123,"wof:population_rank":1,"wof:repo":"whosonfirst-data-admin-ee","wof:superseded_by":[],"wof:supersedes":[],"wof:tags":[]},"bbox":[27.16028,58.02056,27.16028,58.02056],"geometry":{"coordinates":[27.16028,58.02056],"type":"Point"}}