{"id":1226032895,"type":"Feature","properties":{"edtf:cessation":"uuuu","edtf:inception":"uuuu","geom:area":0,"geom:area_square_m":0,"geom:bbox":"24.42083,58.56417,24.42083,58.56417","geom:latitude":58.56417,"geom:longitude":24.42083,"gn:admin1_code":"11.0","gn:admin2_code":"638.0","gn:admin3_code":"6278.0","gn:asciiname":"Pitsalu","gn:country_code":"EE","gn:dem":23,"gn:feature_class":"P","gn:feature_code":"PPL","gn:geonameid":589420,"gn:latitude":58.56417,"gn:longitude":24.42083,"gn:modification_date":"2017-11-25","gn:name":"Pitsalu","gn:population":0,"gn:timezone":"Europe/Tallinn","iso:country":"EE","lbl:bbox":"24.40083,58.54417,24.44083,58.58417","lbl:max_zoom":18,"lbl:min_zoom":13.5,"mz:hierarchy_label":1,"mz:is_current":1,"mz:min_zoom":12,"name:est_x_preferred":["Pitsalu"],"name:hye_x_preferred":["Պիցալու"],"name:pol_x_preferred":["Pitsalu"],"name:spa_x_preferred":["Pitsalu"],"name:vol_x_preferred":["Pitsalu"],"src:geom":"geonames","wof:belongsto":[85682981,102191581,1713314419,85633135,1713305733],"wof:breaches":[],"wof:concordances":{"gn:id":589420,"wk:page":"Pitsalu"},"wof:coterminous":[1713314419],"wof:country":"EE","wof:geomhash":"c1239613bb817cef2dcf44ae27863473","wof:hierarchy":[{"continent_id":102191581,"country_id":85633135,"county_id":1713305733,"localadmin_id":1713314419,"locality_id":1226032895,"region_id":85682981}],"wof:id":1226032895,"wof:lang_x_official":["est"],"wof:lang_x_spoken":["est"],"wof:lastmodified":1596663420,"wof:name":"Pitsalu","wof:parent_id":1713314419,"wof:placetype":"locality","wof:repo":"whosonfirst-data-admin-ee","wof:superseded_by":[],"wof:supersedes":[],"wof:tags":[]},"bbox":[24.42083,58.56417,24.42083,58.56417],"geometry":{"coordinates":[24.42083,58.56417],"type":"Point"}}