{"id":1326893015,"type":"Feature","properties":{"edtf:cessation":"uuuu","edtf:inception":"uuuu","geom:area":0,"geom:area_square_m":0,"geom:bbox":"26.15917,58.03028,26.15917,58.03028","geom:latitude":58.03028,"geom:longitude":26.15917,"gn:admin1_code":"19.0","gn:admin2_code":"557.0","gn:admin3_code":"6549.0","gn:asciiname":"Poru","gn:country_code":"EE","gn:dem":88,"gn:feature_class":"P","gn:feature_code":"PPL","gn:geonameid":794555,"gn:latitude":58.03028,"gn:longitude":26.15917,"gn:modification_date":"2017-11-25","gn:name":"Põru","gn:population":0,"gn:timezone":"Europe/Tallinn","iso:country":"EE","lbl:bbox":"26.13917,58.01028,26.17917,58.05028","lbl:max_zoom":18,"lbl:min_zoom":13.5,"mz:hierarchy_label":1,"mz:is_current":1,"mz:min_zoom":12,"src:geom":"geonames","wof:belongsto":[85682941,102191581,1713314087,85633135,1713305759],"wof:breaches":[],"wof:concordances":{"gn:id":794555},"wof:coterminous":[1713314087],"wof:country":"EE","wof:geomhash":"fddf5852bf98e5f38ffc35fb2f1789aa","wof:hierarchy":[{"continent_id":102191581,"country_id":85633135,"county_id":1713305759,"localadmin_id":1713314087,"locality_id":1326893015,"region_id":85682941}],"wof:id":1326893015,"wof:lang_x_official":["est"],"wof:lang_x_spoken":["est"],"wof:lastmodified":1596661876,"wof:name":"Poru","wof:parent_id":1713314087,"wof:placetype":"locality","wof:repo":"whosonfirst-data-admin-ee","wof:superseded_by":[],"wof:supersedes":[],"wof:tags":[]},"bbox":[26.15917,58.03028,26.15917,58.03028],"geometry":{"coordinates":[26.15917,58.03028],"type":"Point"}}