{"id":1310164601,"type":"Feature","properties":{"edtf:cessation":"uuuu","edtf:inception":"uuuu","geom:area":0,"geom:area_square_m":0,"geom:bbox":"27.12667,57.69278,27.12667,57.69278","geom:latitude":57.69278,"geom:longitude":27.12667,"gn:admin1_code":"21.0","gn:admin2_code":"698.0","gn:admin3_code":"6362.0","gn:asciiname":"Peraemotsa","gn:country_code":"EE","gn:dem":222,"gn:feature_class":"P","gn:feature_code":"PPL","gn:geonameid":8620285,"gn:latitude":57.69278,"gn:longitude":27.12667,"gn:modification_date":"2017-11-25","gn:name":"Per채m천tsa","gn:population":0,"gn:timezone":"Europe/Tallinn","iso:country":"EE","lbl:bbox":"27.10667,57.67278,27.14667,57.71278","lbl:max_zoom":18,"lbl:min_zoom":13.5,"mz:hierarchy_label":1,"mz:is_current":1,"mz:min_zoom":12,"name:und_x_variant":["Per채m천tsa","Perametsa"],"src:geom":"geonames","wof:belongsto":[85682937,102191581,1713316339,85633135,1713305787],"wof:breaches":[],"wof:concordances":{"gn:id":8620285},"wof:country":"EE","wof:geomhash":"96621ad9b57a76b8c5fc7bab20a06c7f","wof:hierarchy":[{"continent_id":102191581,"country_id":85633135,"county_id":1713305787,"localadmin_id":1713316339,"locality_id":1310164601,"region_id":85682937}],"wof:id":1310164601,"wof:lang_x_official":["est"],"wof:lang_x_spoken":["est"],"wof:lastmodified":1596676876,"wof:name":"Peraemotsa","wof:parent_id":1713316339,"wof:placetype":"locality","wof:repo":"whosonfirst-data-admin-ee","wof:superseded_by":[],"wof:supersedes":[],"wof:tags":[]},"bbox":[27.12667,57.69278,27.12667,57.69278],"geometry":{"coordinates":[27.12667,57.69278],"type":"Point"}}