{"id":1310186165,"type":"Feature","properties":{"edtf:cessation":"uuuu","edtf:inception":"uuuu","geom:area":0,"geom:area_square_m":0,"geom:bbox":"24.46667,58.38333,24.46667,58.38333","geom:latitude":58.38333,"geom:longitude":24.46667,"gn:admin1_code":"11.0","gn:admin2_code":"624.0","gn:admin3_code":"6619.0","gn:asciiname":"Vana-Paernu","gn:country_code":"EE","gn:dem":0,"gn:feature_class":"P","gn:feature_code":"PPL","gn:geonameid":592325,"gn:latitude":58.38333,"gn:longitude":24.46667,"gn:modification_date":"2017-11-25","gn:name":"Vana-Pärnu","gn:population":0,"gn:timezone":"Europe/Tallinn","iso:country":"EE","lbl:bbox":"24.44667,58.36333,24.48667,58.40333","lbl:max_zoom":18,"lbl:min_zoom":13.5,"mz:hierarchy_label":1,"mz:is_current":1,"mz:is_funky":1,"mz:min_zoom":12,"src:geom":"geonames","wof:belongsto":[85682981,102191581,1713312479,85633135,1713305703],"wof:breaches":[],"wof:concordances":{"gn:id":592325},"wof:country":"EE","wof:geomhash":"0e0cc065eaaf20c70232513c7b84bace","wof:hierarchy":[{"continent_id":102191581,"country_id":85633135,"county_id":1713305703,"localadmin_id":1713312479,"locality_id":1310186165,"region_id":85682981}],"wof:id":1310186165,"wof:lang_x_official":["est"],"wof:lang_x_spoken":["est"],"wof:lastmodified":1596677704,"wof:name":"Vana-Paernu","wof:parent_id":1713312479,"wof:placetype":"locality","wof:repo":"whosonfirst-data-admin-ee","wof:superseded_by":[],"wof:supersedes":[],"wof:tags":[]},"bbox":[24.46667,58.38333,24.46667,58.38333],"geometry":{"coordinates":[24.46667,58.38333],"type":"Point"}}