{"id":1259795195,"type":"Feature","properties":{"edtf:cessation":"uuuu","edtf:inception":"uuuu","geom:area":0,"geom:area_square_m":0,"geom:bbox":"27.59056,59.38611,27.59056,59.38611","geom:latitude":59.38611,"geom:longitude":27.59056,"gn:admin1_code":"3.0","gn:admin2_code":"803.0","gn:admin3_code":"3375.0","gn:asciiname":"Moonakuela","gn:country_code":"EE","gn:dem":52,"gn:feature_class":"P","gn:feature_code":"PPL","gn:geonameid":8619123,"gn:latitude":59.38611,"gn:longitude":27.59056,"gn:modification_date":"2017-11-25","gn:name":"Moonaküla","gn:population":0,"gn:timezone":"Europe/Tallinn","iso:country":"EE","lbl:bbox":"27.57056,59.36611,27.61056,59.40611","lbl:max_zoom":18,"lbl:min_zoom":13.5,"mz:hierarchy_label":1,"mz:is_current":1,"mz:min_zoom":12,"name:und_x_variant":["Moonaküla","Metsa-Mägara"],"src:geom":"geonames","wof:belongsto":[85683059,102191581,1713312987,85633135,1713305783],"wof:breaches":[],"wof:concordances":{"gn:id":8619123},"wof:country":"EE","wof:geomhash":"ebd0f31fb3a815203692cc64ff2538b5","wof:hierarchy":[{"continent_id":102191581,"country_id":85633135,"county_id":1713305783,"localadmin_id":1713312987,"locality_id":1259795195,"region_id":85683059}],"wof:id":1259795195,"wof:lang_x_official":["est"],"wof:lang_x_spoken":["est"],"wof:lastmodified":1596676912,"wof:name":"Moonakuela","wof:parent_id":1713312987,"wof:placetype":"locality","wof:repo":"whosonfirst-data-admin-ee","wof:superseded_by":[],"wof:supersedes":[],"wof:tags":[]},"bbox":[27.59056,59.38611,27.59056,59.38611],"geometry":{"coordinates":[27.59056,59.38611],"type":"Point"}}