{"id":1259902607,"type":"Feature","properties":{"edtf:cessation":"uuuu","edtf:inception":"uuuu","geom:area":0,"geom:area_square_m":0,"geom:bbox":"27.09667,58.72694,27.09667,58.72694","geom:latitude":58.72694,"geom:longitude":27.09667,"gn:admin1_code":"18.0","gn:admin2_code":"586.0","gn:admin3_code":"9787.0","gn:asciiname":"Ranna","gn:cc2":"EE","gn:country_code":"EE","gn:dem":45,"gn:feature_class":"P","gn:feature_code":"PPL","gn:geonameid":589138,"gn:latitude":58.72694,"gn:longitude":27.09667,"gn:modification_date":"2017-11-25","gn:name":"Ranna","gn:population":0,"gn:timezone":"Europe/Tallinn","iso:country":"EE","lbl:bbox":"27.07667,58.70694,27.11667,58.74694","lbl:max_zoom":18,"lbl:min_zoom":13.5,"mz:hierarchy_label":1,"mz:is_current":1,"mz:min_zoom":12,"name:ceb_x_preferred":["Ranna"],"name:deu_x_preferred":["Ranna"],"name:eng_x_preferred":["Ranna"],"name:pol_x_preferred":["Ranna"],"name:rus_x_preferred":["Ранна"],"name:swe_x_preferred":["Ranna"],"name:und_x_variant":["Myza Ranna"],"src:geom":"geonames","wof:belongsto":[85682995,102191581,1713309713,85633135,1713305679],"wof:breaches":[],"wof:concordances":{"gn:id":589138},"wof:coterminous":[1713309149],"wof:country":"EE","wof:geomhash":"9424794a59f651556f4fa02e741fc5f3","wof:hierarchy":[{"continent_id":102191581,"country_id":85633135,"county_id":1713305679,"localadmin_id":1713309713,"locality_id":1259902607,"region_id":85682995}],"wof:id":1259902607,"wof:lang_x_official":["est"],"wof:lang_x_spoken":["est"],"wof:lastmodified":1596660922,"wof:name":"Ranna","wof:parent_id":1713309713,"wof:placetype":"locality","wof:repo":"whosonfirst-data-admin-ee","wof:superseded_by":[],"wof:supersedes":[],"wof:tags":[]},"bbox":[27.09667,58.72694,27.09667,58.72694],"geometry":{"coordinates":[27.09667,58.72694],"type":"Point"}}