{"id":1125936199,"type":"Feature","properties":{"edtf:cessation":"uuuu","edtf:inception":"uuuu","geom:area":0,"geom:area_square_m":0,"geom:bbox":"24.31556,58.92278,24.31556,58.92278","geom:latitude":58.92278,"geom:longitude":24.31556,"gn:country":"EE","gn:fcode":"PPL","gn:population":338,"iso:country":"EE","lbl:bbox":"24.29556,58.90278,24.33556,58.94278","lbl:latitude":58.92278,"lbl:longitude":24.31556,"lbl:max_zoom":17,"lbl:min_zoom":12.5,"mz:hierarchy_label":1,"mz:is_current":1,"mz:min_zoom":11,"mz:note":"Quattroshapes Point Gazetteer import 20170519","name:ceb_x_preferred":["Sipa"],"name:eng_x_preferred":["Sipa"],"name:est_x_preferred":["Sipa"],"name:fra_x_preferred":["Sipa"],"name:hye_x_preferred":["Սիպա"],"name:nld_x_preferred":["Sipa"],"name:pol_x_preferred":["Sipa"],"name:rus_x_preferred":["Сипа"],"name:sco_x_preferred":["Sipa"],"name:spa_x_preferred":["Sipa"],"name:vol_x_preferred":["Sipa"],"qs_pg:aaroncc":"EE","qs_pg:gn_country":"EE","qs_pg:gn_fcode":"PPL","qs_pg:gn_id":588668,"qs_pg:gn_pop":338,"qs_pg:name":"Sipa","qs_pg:name_adm0":"Eesti","qs_pg:name_adm1":"Läänemaa","qs_pg:photos_9r":0,"qs_pg:photos_sr":0,"qs_pg:pop_sr":2,"qs_pg:qs_id":1274511,"qs_pg:qs_pg_placetype":"locality","qs_pg:qs_pg_placetype_gp":"Town","qs_pg:woe_adm0":23424805,"qs_pg:woe_id":845511,"src:geom":"qs_pg","src:lbl_centroid":"qs_pg","src:population":"geonames","woe:adm0_id":23424805,"woe:name_adm0":"Eesti","woe:name_adm1":"Läänemaa","woe:placetype":"Town","wof:belongsto":[85683013,102191581,1713311375,85633135,1713305747],"wof:breaches":[],"wof:concordances":{"gn:id":588668,"gp:id":845511,"qs_pg:id":1274511,"wd:id":"Q2647214"},"wof:coterminous":[1713311375],"wof:country":"EE","wof:created":1497296976,"wof:geomhash":"070c7c6bd268dfd22845a247c60ecbbe","wof:hierarchy":[{"continent_id":102191581,"country_id":85633135,"county_id":1713305747,"localadmin_id":1713311375,"locality_id":1125936199,"region_id":85683013}],"wof:id":1125936199,"wof:lang_x_official":["est"],"wof:lang_x_spoken":["est"],"wof:lastmodified":1596662853,"wof:name":"Sipa","wof:parent_id":1713311375,"wof:placetype":"locality","wof:population":338,"wof:population_rank":2,"wof:repo":"whosonfirst-data-admin-ee","wof:superseded_by":[],"wof:supersedes":[],"wof:tags":[]},"bbox":[24.31556,58.92278,24.31556,58.92278],"geometry":{"coordinates":[24.31556,58.92278],"type":"Point"}}