{"id":1193020919,"type":"Feature","properties":{"edtf:cessation":"uuuu","edtf:inception":"uuuu","geom:area":0,"geom:area_square_m":0,"geom:bbox":"26.91528,58.64278,26.91528,58.64278","geom:latitude":58.64278,"geom:longitude":26.91528,"gn:admin1_code":"18.0","gn:admin2_code":"586.0","gn:admin3_code":"7913.0","gn:asciiname":"Sooru","gn:country_code":"EE","gn:dem":76,"gn:feature_class":"P","gn:feature_code":"PPL","gn:geonameid":794634,"gn:latitude":58.64278,"gn:longitude":26.91528,"gn:modification_date":"2017-11-25","gn:name":"Sõõru","gn:population":0,"gn:timezone":"Europe/Tallinn","iso:country":"EE","lbl:bbox":"26.89528,58.62278,26.93528,58.66278","lbl:max_zoom":18,"lbl:min_zoom":13.5,"mz:hierarchy_label":1,"mz:is_current":1,"mz:min_zoom":12,"name:ceb_x_preferred":["Sooru"],"name:est_x_preferred":["Sooru"],"name:hye_x_preferred":["Սոոռու"],"name:pol_x_preferred":["Sooru"],"name:spa_x_preferred":["Sooru"],"name:swe_x_preferred":["Sooru"],"name:ukr_x_preferred":["Соору"],"name:vol_x_preferred":["Sooru"],"src:geom":"geonames","wof:belongsto":[85682995,102191581,1713309641,85633135,1713305679],"wof:breaches":[],"wof:concordances":{"gn:id":794634},"wof:coterminous":[1713309641],"wof:country":"EE","wof:geomhash":"1548ae091cbd03d20cc759096f3f2ef2","wof:hierarchy":[{"continent_id":102191581,"country_id":85633135,"county_id":1713305679,"localadmin_id":1713309641,"locality_id":1193020919,"region_id":85682995}],"wof:id":1193020919,"wof:lang_x_official":["est"],"wof:lang_x_spoken":["est"],"wof:lastmodified":1596660907,"wof:name":"Sooru","wof:parent_id":1713309641,"wof:placetype":"locality","wof:repo":"whosonfirst-data-admin-ee","wof:superseded_by":[],"wof:supersedes":[],"wof:tags":[]},"bbox":[26.91528,58.64278,26.91528,58.64278],"geometry":{"coordinates":[26.91528,58.64278],"type":"Point"}}