{"id":1344266621,"type":"Feature","properties":{"edtf:cessation":"uuuu","edtf:inception":"uuuu","geom:area":0,"geom:area_square_m":0,"geom:bbox":"25.65056,59.335,25.65056,59.335","geom:latitude":59.335,"geom:longitude":25.65056,"gn:admin1_code":"1.0","gn:admin2_code":"141.0","gn:admin3_code":"6254.0","gn:asciiname":"Apuparra","gn:country_code":"EE","gn:dem":80,"gn:feature_class":"P","gn:feature_code":"PPL","gn:geonameid":592452,"gn:latitude":59.335,"gn:longitude":25.65056,"gn:modification_date":"2017-11-25","gn:name":"Apuparra","gn:population":0,"gn:timezone":"Europe/Tallinn","iso:country":"EE","lbl:bbox":"25.63056,59.315,25.67056,59.355","lbl:max_zoom":18,"lbl:min_zoom":13.5,"mz:hierarchy_label":1,"mz:is_current":1,"mz:min_zoom":12,"name:und_x_variant":["Apupara","Apuparra"],"src:geom":"geonames","wof:belongsto":[85683055,102191581,1713314585,85633135,1713305749],"wof:breaches":[],"wof:concordances":{"gn:id":592452},"wof:country":"EE","wof:geomhash":"4f7e6155dcbaf6a009e901cee526430c","wof:hierarchy":[{"continent_id":102191581,"country_id":85633135,"county_id":1713305749,"localadmin_id":1713314585,"locality_id":1344266621,"region_id":85683055}],"wof:id":1344266621,"wof:lang_x_official":["est"],"wof:lang_x_spoken":["est"],"wof:lastmodified":1596662803,"wof:name":"Apuparra","wof:parent_id":1713314585,"wof:placetype":"locality","wof:repo":"whosonfirst-data-admin-ee","wof:superseded_by":[],"wof:supersedes":[],"wof:tags":[]},"bbox":[25.65056,59.335,25.65056,59.335],"geometry":{"coordinates":[25.65056,59.335],"type":"Point"}}