{"id":1210025957,"type":"Feature","properties":{"edtf:cessation":"uuuu","edtf:inception":"uuuu","geom:area":0,"geom:area_square_m":0,"geom:bbox":"24.21889,59.32833,24.21889,59.32833","geom:latitude":59.32833,"geom:longitude":24.21889,"gn:admin1_code":"1.0","gn:admin2_code":"431.0","gn:admin3_code":"3205.0","gn:asciiname":"Klooga Aedlinn","gn:country_code":"EE","gn:dem":21,"gn:feature_class":"P","gn:feature_code":"PPL","gn:geonameid":794935,"gn:latitude":59.32833,"gn:longitude":24.21889,"gn:modification_date":"2017-11-25","gn:name":"Klooga Aedlinn","gn:population":0,"gn:timezone":"Europe/Tallinn","iso:country":"EE","lbl:bbox":"24.19889,59.30833,24.23889,59.34833","lbl:max_zoom":18,"lbl:min_zoom":13.5,"mz:hierarchy_label":1,"mz:is_current":1,"mz:is_funky":1,"mz:min_zoom":12,"src:geom":"geonames","wof:belongsto":[85683055,102191581,1713307825,85633135,1713305737],"wof:breaches":[],"wof:concordances":{"gn:id":794935},"wof:country":"EE","wof:geomhash":"ae95ba42148a8d01bf9a556345bc468f","wof:hierarchy":[{"continent_id":102191581,"country_id":85633135,"county_id":1713305737,"localadmin_id":1713307825,"locality_id":1210025957,"region_id":85683055}],"wof:id":1210025957,"wof:lang_x_official":["est"],"wof:lang_x_spoken":["est"],"wof:lastmodified":1596663321,"wof:name":"Klooga Aedlinn","wof:parent_id":1713307825,"wof:placetype":"locality","wof:repo":"whosonfirst-data-admin-ee","wof:superseded_by":[],"wof:supersedes":[],"wof:tags":[]},"bbox":[24.21889,59.32833,24.21889,59.32833],"geometry":{"coordinates":[24.21889,59.32833],"type":"Point"}}