{"id":1226823149,"type":"Feature","properties":{"edtf:cessation":"uuuu","edtf:inception":"uuuu","geom:area":0,"geom:area_square_m":0,"geom:bbox":"26.76972,57.84167,26.76972,57.84167","geom:latitude":57.84167,"geom:longitude":26.76972,"gn:admin1_code":"21.0","gn:admin2_code":"917.0","gn:admin3_code":"1942.0","gn:asciiname":"Haenike","gn:country_code":"EE","gn:dem":79,"gn:feature_class":"P","gn:feature_code":"PPL","gn:geonameid":592188,"gn:latitude":57.84167,"gn:longitude":26.76972,"gn:modification_date":"2017-11-25","gn:name":"Hänike","gn:population":0,"gn:timezone":"Europe/Tallinn","iso:country":"EE","lbl:bbox":"26.74972,57.82167,26.78972,57.86167","lbl:max_zoom":18,"lbl:min_zoom":13.5,"mz:hierarchy_label":1,"mz:is_current":1,"mz:min_zoom":12,"name:und_x_variant":["Khyanike","Hanike Asundus","Hänike"],"src:geom":"geonames","wof:belongsto":[85682937,102191581,1713316367,85633135,1713305633],"wof:breaches":[],"wof:concordances":{"gn:id":592188},"wof:coterminous":[1713316367],"wof:country":"EE","wof:geomhash":"bb3806e4a3d731dccd291b0255307ce2","wof:hierarchy":[{"continent_id":102191581,"country_id":85633135,"county_id":1713305633,"localadmin_id":1713316367,"locality_id":1226823149,"region_id":85682937}],"wof:id":1226823149,"wof:lang_x_official":["est"],"wof:lang_x_spoken":["est"],"wof:lastmodified":1596660418,"wof:name":"Haenike","wof:parent_id":1713316367,"wof:placetype":"locality","wof:repo":"whosonfirst-data-admin-ee","wof:superseded_by":[],"wof:supersedes":[],"wof:tags":[]},"bbox":[26.76972,57.84167,26.76972,57.84167],"geometry":{"coordinates":[26.76972,57.84167],"type":"Point"}}