{"id":1276232691,"type":"Feature","properties":{"edtf:cessation":"uuuu","edtf:inception":"uuuu","geom:area":0,"geom:area_square_m":0,"geom:bbox":"26.68833,58.83389,26.68833,58.83389","geom:latitude":58.83389,"geom:longitude":26.68833,"gn:admin1_code":"5.0","gn:admin2_code":"247.0","gn:admin3_code":"9519.0","gn:asciiname":"Voidivere","gn:country_code":"EE","gn:dem":98,"gn:feature_class":"P","gn:feature_code":"PPL","gn:geonameid":793381,"gn:latitude":58.83389,"gn:longitude":26.68833,"gn:modification_date":"2017-11-25","gn:name":"Võidivere","gn:population":0,"gn:timezone":"Europe/Tallinn","iso:country":"EE","lbl:bbox":"26.66833,58.81389,26.70833,58.85389","lbl:max_zoom":18,"lbl:min_zoom":13.5,"mz:hierarchy_label":1,"mz:is_current":1,"mz:min_zoom":12,"src:geom":"geonames","wof:belongsto":[85683009,102191581,1713312231,85633135,1713305767],"wof:breaches":[],"wof:concordances":{"gn:id":793381},"wof:coterminous":[1713312231],"wof:country":"EE","wof:geomhash":"c60bb94e5dfbf6e3d3dace47e5c2c72d","wof:hierarchy":[{"continent_id":102191581,"country_id":85633135,"county_id":1713305767,"localadmin_id":1713312231,"locality_id":1276232691,"region_id":85683009}],"wof:id":1276232691,"wof:lang_x_official":["est"],"wof:lang_x_spoken":["est"],"wof:lastmodified":1596676577,"wof:name":"Voidivere","wof:parent_id":1713312231,"wof:placetype":"locality","wof:repo":"whosonfirst-data-admin-ee","wof:superseded_by":[],"wof:supersedes":[],"wof:tags":[]},"bbox":[26.68833,58.83389,26.68833,58.83389],"geometry":{"coordinates":[26.68833,58.83389],"type":"Point"}}