{"id":1125830989,"type":"Feature","properties":{"edtf:cessation":"uuuu","edtf:inception":"uuuu","geom:area":0,"geom:area_square_m":0,"geom:bbox":"23.70694,58.99611,23.70694,58.99611","geom:latitude":58.99611,"geom:longitude":23.70694,"gn:country":"EE","gn:fcode":"PPL","gn:population":460,"iso:country":"EE","lbl:bbox":"23.68694,58.97611,23.72694,59.01611","lbl:latitude":58.99611,"lbl:longitude":23.70694,"lbl:max_zoom":17,"lbl:min_zoom":12.5,"mz:hierarchy_label":1,"mz:is_current":1,"mz:min_zoom":11,"mz:note":"Quattroshapes Point Gazetteer import 20170519","name:ceb_x_preferred":["Linnamäe"],"name:eng_x_preferred":["Linnamäe"],"name:est_x_preferred":["Linnamäe"],"name:fra_x_preferred":["Linnamäe"],"name:hye_x_preferred":["Լիննամյաե"],"name:nld_x_preferred":["Linnamäe"],"name:pol_x_preferred":["Linnamäe"],"name:spa_x_preferred":["Linnamäe"],"name:swe_x_preferred":["Linnamäe"],"name:ukr_x_preferred":["Ліннамяе"],"name:und_x_variant":["Linnamyae"],"name:vol_x_preferred":["Linnamäe"],"qs_pg:aaroncc":"EE","qs_pg:gn_country":"EE","qs_pg:gn_fcode":"PPL","qs_pg:gn_id":590607,"qs_pg:gn_pop":460,"qs_pg:name":"Linnamäe","qs_pg:photos_9r":0,"qs_pg:photos_sr":0,"qs_pg:pop_sr":2,"qs_pg:qs_id":81105,"qs_pg:qs_pg_placetype":"locality","src:geom":"qs_pg","src:lbl_centroid":"qs_pg","src:population":"geonames","wof:belongsto":[85683001,102191581,1713308997,85633135,1713305701],"wof:breaches":[],"wof:concordances":{"gn:id":590607,"qs_pg:id":81105,"wd:id":"Q611559"},"wof:coterminous":[1713308997],"wof:country":"EE","wof:created":1497292498,"wof:geomhash":"a980e33926e1b5805011caee23efbd0c","wof:hierarchy":[{"continent_id":102191581,"country_id":85633135,"county_id":1713305701,"localadmin_id":1713308997,"locality_id":1125830989,"region_id":85683001}],"wof:id":1125830989,"wof:lang_x_official":["est"],"wof:lang_x_spoken":["est"],"wof:lastmodified":1596677429,"wof:name":"Linnamäe","wof:parent_id":1713308997,"wof:placetype":"locality","wof:population":460,"wof:population_rank":2,"wof:repo":"whosonfirst-data-admin-ee","wof:superseded_by":[],"wof:supersedes":[],"wof:tags":[]},"bbox":[23.70694,58.99611,23.70694,58.99611],"geometry":{"coordinates":[23.70694,58.99611],"type":"Point"}}