{"id":1242982419,"type":"Feature","properties":{"edtf:cessation":"uuuu","edtf:inception":"uuuu","geom:area":0,"geom:area_square_m":0,"geom:bbox":"26.91694,59.27028,26.91694,59.27028","geom:latitude":59.27028,"geom:longitude":26.91694,"gn:admin1_code":"3.0","gn:admin2_code":"442.0","gn:admin3_code":"7640.0","gn:asciiname":"Sirtsi","gn:country_code":"EE","gn:dem":70,"gn:feature_class":"P","gn:feature_code":"PPL","gn:geonameid":588660,"gn:latitude":59.27028,"gn:longitude":26.91694,"gn:modification_date":"2017-11-25","gn:name":"Sirtsi","gn:population":0,"gn:timezone":"Europe/Tallinn","iso:country":"EE","lbl:bbox":"26.89694,59.25028,26.93694,59.29028","lbl:max_zoom":18,"lbl:min_zoom":13.5,"mz:hierarchy_label":1,"mz:is_current":1,"mz:min_zoom":12,"name:deu_x_preferred":["Sirtsi"],"name:est_x_preferred":["Sirtsi"],"name:hye_x_preferred":["Սիռցի"],"name:pol_x_preferred":["Sirtsi"],"name:spa_x_preferred":["Sirtsi"],"name:vol_x_preferred":["Sirtsi"],"src:geom":"geonames","wof:belongsto":[85683059,102191581,1713313445,85633135,1713305695],"wof:breaches":[],"wof:concordances":{"gn:id":588660,"wk:page":"Sirtsi"},"wof:coterminous":[1713313445],"wof:country":"EE","wof:geomhash":"8d970f2454aaa4996fb17dd071fd7e7d","wof:hierarchy":[{"continent_id":102191581,"country_id":85633135,"county_id":1713305695,"localadmin_id":1713313445,"locality_id":1242982419,"region_id":85683059}],"wof:id":1242982419,"wof:lang_x_official":["est"],"wof:lang_x_spoken":["est"],"wof:lastmodified":1596660811,"wof:name":"Sirtsi","wof:parent_id":1713313445,"wof:placetype":"locality","wof:repo":"whosonfirst-data-admin-ee","wof:superseded_by":[],"wof:supersedes":[],"wof:tags":[]},"bbox":[26.91694,59.27028,26.91694,59.27028],"geometry":{"coordinates":[26.91694,59.27028],"type":"Point"}}