{"id":1225953861,"type":"Feature","properties":{"edtf:cessation":"uuuu","edtf:inception":"uuuu","geom:area":0,"geom:area_square_m":0,"geom:bbox":"25.31028,59.44583,25.31028,59.44583","geom:latitude":59.44583,"geom:longitude":25.31028,"gn:admin1_code":"1.0","gn:admin2_code":"353.0","gn:admin3_code":"7122.0","gn:asciiname":"Rummu","gn:country_code":"EE","gn:dem":44,"gn:feature_class":"P","gn:feature_code":"PPL","gn:geonameid":8618663,"gn:latitude":59.44583,"gn:longitude":25.31028,"gn:modification_date":"2017-11-25","gn:name":"Rummu","gn:population":0,"gn:timezone":"Europe/Tallinn","iso:country":"EE","lbl:bbox":"25.29028,59.42583,25.33028,59.46583","lbl:max_zoom":18,"lbl:min_zoom":13.5,"mz:hierarchy_label":1,"mz:is_current":1,"mz:min_zoom":12,"name:ceb_x_preferred":["Rummu"],"name:deu_x_preferred":["Rummu"],"name:est_x_preferred":["Rummu"],"name:fra_x_preferred":["Rummu"],"name:hye_x_preferred":["Ռումմու"],"name:nld_x_preferred":["Rummu"],"name:pol_x_preferred":["Rummu"],"name:rus_x_preferred":["Румму"],"name:swe_x_preferred":["Rummu"],"name:ukr_x_preferred":["Румму"],"name:vol_x_preferred":["Rummu"],"src:geom":"geonames","wof:belongsto":[85683055,102191581,1713306061,85633135,1713305725],"wof:breaches":[],"wof:concordances":{"gn:id":8618663},"wof:coterminous":[1713306061],"wof:country":"EE","wof:geomhash":"d258c0eb7b5817ce3af76c4987b4003b","wof:hierarchy":[{"continent_id":102191581,"country_id":85633135,"county_id":1713305725,"localadmin_id":1713306061,"locality_id":1225953861,"region_id":85683055}],"wof:id":1225953861,"wof:lang_x_official":["est"],"wof:lang_x_spoken":["est"],"wof:lastmodified":1596661841,"wof:name":"Rummu","wof:parent_id":1713306061,"wof:placetype":"locality","wof:repo":"whosonfirst-data-admin-ee","wof:superseded_by":[],"wof:supersedes":[],"wof:tags":[]},"bbox":[25.31028,59.44583,25.31028,59.44583],"geometry":{"coordinates":[25.31028,59.44583],"type":"Point"}}