{"id":1125829553,"type":"Feature","properties":{"edtf:cessation":"uuuu","edtf:inception":"uuuu","geom:area":0,"geom:area_square_m":0,"geom:bbox":"25.50333,58.34528,25.50333,58.34528","geom:latitude":58.34528,"geom:longitude":25.50333,"gn:country":"EE","gn:fcode":"PPL","gn:population":475,"iso:country":"EE","lbl:bbox":"25.48333,58.32528,25.52333,58.36528","lbl:latitude":58.34528,"lbl:longitude":25.50333,"lbl:max_zoom":17,"lbl:min_zoom":12.5,"mz:hierarchy_label":1,"mz:is_current":1,"mz:min_zoom":11,"mz:note":"Quattroshapes Point Gazetteer import 20170519","name:bul_x_preferred":["Пяри"],"name:ceb_x_preferred":["Pyari"],"name:eng_x_preferred":["Päri"],"name:est_x_preferred":["Päri"],"name:fra_x_preferred":["Päri"],"name:hye_x_preferred":["Պեռի"],"name:nld_x_preferred":["Päri"],"name:pol_x_preferred":["Päri"],"name:rus_x_preferred":["Пяри"],"name:spa_x_preferred":["Päri"],"name:swe_x_preferred":["Päri"],"name:ukr_x_preferred":["Пярі"],"name:vol_x_preferred":["Päri"],"qs_pg:aaroncc":"EE","qs_pg:gn_country":"EE","qs_pg:gn_fcode":"PPL","qs_pg:gn_id":589604,"qs_pg:gn_pop":475,"qs_pg:name":"Päri","qs_pg:name_adm0":"Eesti","qs_pg:name_adm1":"Viljandimaa","qs_pg:photos_9k":1,"qs_pg:photos_9r":1,"qs_pg:photos_all":3,"qs_pg:photos_sr":0,"qs_pg:pop_sr":2,"qs_pg:qs_id":890016,"qs_pg:qs_pg_placetype":"locality","qs_pg:qs_pg_placetype_gp":"Town","qs_pg:woe_adm0":23424805,"qs_pg:woe_id":844613,"src:geom":"qs_pg","src:lbl_centroid":"qs_pg","src:population":"geonames","woe:adm0_id":23424805,"woe:name_adm0":"Eesti","woe:name_adm1":"Viljandimaa","woe:placetype":"Town","wof:belongsto":[85682985,102191581,1713309927,85633135,1713305669],"wof:breaches":[],"wof:concordances":{"gn:id":589604,"gp:id":844613,"qs_pg:id":890016,"wd:id":"Q23888039"},"wof:coterminous":[1713309927],"wof:country":"EE","wof:created":1497292431,"wof:geomhash":"a4041af523288164af34e6b9127589dc","wof:hierarchy":[{"continent_id":102191581,"country_id":85633135,"county_id":1713305669,"localadmin_id":1713309927,"locality_id":1125829553,"region_id":85682985}],"wof:id":1125829553,"wof:lang_x_official":["est"],"wof:lang_x_spoken":["est"],"wof:lastmodified":1596661258,"wof:name":"Päri","wof:parent_id":1713309927,"wof:placetype":"locality","wof:population":475,"wof:population_rank":2,"wof:repo":"whosonfirst-data-admin-ee","wof:superseded_by":[],"wof:supersedes":[],"wof:tags":[]},"bbox":[25.50333,58.34528,25.50333,58.34528],"geometry":{"coordinates":[25.50333,58.34528],"type":"Point"}}