{"id":1259580945,"type":"Feature","properties":{"edtf:cessation":"uuuu","edtf:inception":"uuuu","geom:area":0,"geom:area_square_m":0,"geom:bbox":"26.39694,59.28944,26.39694,59.28944","geom:latitude":59.28944,"geom:longitude":26.39694,"gn:admin1_code":"8.0","gn:admin2_code":"901.0","gn:admin3_code":"9009.0","gn:asciiname":"Vana-Vinni","gn:country_code":"EE","gn:dem":99,"gn:feature_class":"P","gn:feature_code":"PPL","gn:geonameid":587572,"gn:latitude":59.28944,"gn:longitude":26.39694,"gn:modification_date":"2017-11-25","gn:name":"Vana-Vinni","gn:population":0,"gn:timezone":"Europe/Tallinn","iso:country":"EE","lbl:bbox":"26.37694,59.26944,26.41694,59.30944","lbl:max_zoom":18,"lbl:min_zoom":13.5,"mz:hierarchy_label":1,"mz:is_current":1,"mz:min_zoom":12,"name:ara_x_preferred":["فانا فيني"],"name:est_x_preferred":["Vana-Vinni"],"name:fas_x_preferred":["وانا وینی"],"name:hye_x_preferred":["Վանա-Վիննի"],"name:und_x_variant":["Vinni"],"name:vol_x_preferred":["Vana-Vinni"],"src:geom":"geonames","wof:belongsto":[85683049,102191581,1713314863,85633135,1713305771],"wof:breaches":[],"wof:concordances":{"gn:id":587572,"wk:page":"Vana-Vinni"},"wof:coterminous":[1713314863],"wof:country":"EE","wof:geomhash":"aa3753464917bb5f7f2b488e5c0c5779","wof:hierarchy":[{"continent_id":102191581,"country_id":85633135,"county_id":1713305771,"localadmin_id":1713314863,"locality_id":1259580945,"region_id":85683049}],"wof:id":1259580945,"wof:lang_x_official":["est"],"wof:lang_x_spoken":["est"],"wof:lastmodified":1596677961,"wof:name":"Vana-Vinni","wof:parent_id":1713314863,"wof:placetype":"locality","wof:repo":"whosonfirst-data-admin-ee","wof:superseded_by":[],"wof:supersedes":[],"wof:tags":[]},"bbox":[26.39694,59.28944,26.39694,59.28944],"geometry":{"coordinates":[26.39694,59.28944],"type":"Point"}}