{"id":1242869637,"type":"Feature","properties":{"edtf:cessation":"uuuu","edtf:inception":"uuuu","geom:area":0,"geom:area_square_m":0,"geom:bbox":"26.71667,59.13333,26.71667,59.13333","geom:latitude":59.13333,"geom:longitude":26.71667,"gn:admin1_code":"8.0","gn:admin2_code":"901.0","gn:admin3_code":"6829.0","gn:asciiname":"AEdara","gn:country_code":"EE","gn:dem":91,"gn:feature_class":"P","gn:feature_code":"PPL","gn:geonameid":592621,"gn:latitude":59.13333,"gn:longitude":26.71667,"gn:modification_date":"2017-11-25","gn:name":"Ädara","gn:population":0,"gn:timezone":"Europe/Tallinn","iso:country":"EE","lbl:bbox":"26.69667,59.11333,26.73667,59.15333","lbl:max_zoom":18,"lbl:min_zoom":13.5,"mz:hierarchy_label":1,"mz:is_current":1,"mz:min_zoom":12,"name:und_x_variant":["Ädara Asundus","Ädara"],"src:geom":"geonames","wof:belongsto":[85683049,102191581,1713307621,85633135,1713305771],"wof:breaches":[],"wof:concordances":{"gn:id":592621},"wof:country":"EE","wof:geomhash":"fe9926128568b98af4ccf351d1bd9ce2","wof:hierarchy":[{"continent_id":102191581,"country_id":85633135,"county_id":1713305771,"localadmin_id":1713307621,"locality_id":1242869637,"region_id":85683049}],"wof:id":1242869637,"wof:lang_x_official":["est"],"wof:lang_x_spoken":["est"],"wof:lastmodified":1596677964,"wof:name":"AEdara","wof:parent_id":1713307621,"wof:placetype":"locality","wof:repo":"whosonfirst-data-admin-ee","wof:superseded_by":[],"wof:supersedes":[],"wof:tags":[]},"bbox":[26.71667,59.13333,26.71667,59.13333],"geometry":{"coordinates":[26.71667,59.13333],"type":"Point"}}