{"id":1126037983,"type":"Feature","properties":{"edtf:cessation":"uuuu","edtf:inception":"uuuu","geom:area":0,"geom:area_square_m":0,"geom:bbox":"26.67556,59.35306,26.67556,59.35306","geom:latitude":59.35306,"geom:longitude":26.67556,"gn:country":"EE","gn:fcode":"PPL","gn:population":186,"iso:country":"EE","lbl:bbox":"26.65556,59.33306,26.69556,59.37306","lbl:latitude":59.35306,"lbl:longitude":26.67556,"lbl:max_zoom":18,"lbl:min_zoom":13,"mz:hierarchy_label":1,"mz:is_current":1,"mz:min_zoom":11,"mz:note":"Quattroshapes Point Gazetteer import 20170519","name:ceb_x_preferred":["Viru-Kabala"],"name:eng_x_preferred":["Viru-Kabala"],"name:est_x_preferred":["Viru-Kabala"],"name:hye_x_preferred":["Վիռու-Կաբալա"],"name:nld_x_preferred":["Viru-Kabala"],"name:pol_x_preferred":["Viru-Kabala"],"name:swe_x_preferred":["Viru-Kabala"],"name:vol_x_preferred":["Viru-Kabala"],"qs_pg:aaroncc":"EE","qs_pg:gn_country":"EE","qs_pg:gn_fcode":"PPL","qs_pg:gn_id":587556,"qs_pg:gn_pop":186,"qs_pg:name":"Viru-Kabala","qs_pg:name_adm0":"Eesti","qs_pg:name_adm1":"Lääne-Virumaa","qs_pg:photos_9k":1,"qs_pg:photos_9r":1,"qs_pg:photos_all":1,"qs_pg:photos_sr":0,"qs_pg:pop_sr":1,"qs_pg:qs_id":966954,"qs_pg:qs_pg_placetype":"locality","qs_pg:qs_pg_placetype_gp":"Town","qs_pg:woe_adm0":23424805,"qs_pg:woe_id":846497,"src:geom":"qs_pg","src:lbl_centroid":"qs_pg","src:population":"geonames","woe:adm0_id":23424805,"woe:name_adm0":"Eesti","woe:name_adm1":"Lääne-Virumaa","woe:placetype":"Town","wof:belongsto":[85683049,102191581,1713307709,85633135,1713305771],"wof:breaches":[],"wof:concordances":{"gn:id":587556,"gp:id":846497,"qs_pg:id":966954,"wd:id":"Q3463055"},"wof:coterminous":[1713307709],"wof:country":"EE","wof:created":1497301920,"wof:geomhash":"c4c0ef9592a655d5e0d12b4b606581ab","wof:hierarchy":[{"continent_id":102191581,"country_id":85633135,"county_id":1713305771,"localadmin_id":1713307709,"locality_id":1126037983,"region_id":85683049}],"wof:id":1126037983,"wof:lang_x_official":["est"],"wof:lang_x_spoken":["est"],"wof:lastmodified":1596677970,"wof:name":"Viru-Kabala","wof:parent_id":1713307709,"wof:placetype":"locality","wof:population":186,"wof:population_rank":1,"wof:repo":"whosonfirst-data-admin-ee","wof:superseded_by":[],"wof:supersedes":[],"wof:tags":[]},"bbox":[26.67556,59.35306,26.67556,59.35306],"geometry":{"coordinates":[26.67556,59.35306],"type":"Point"}}