{"id":1225964237,"type":"Feature","properties":{"edtf:cessation":"uuuu","edtf:inception":"uuuu","geom:area":0,"geom:area_square_m":0,"geom:bbox":"26.40972,59.47778,26.40972,59.47778","geom:latitude":59.47778,"geom:longitude":26.40972,"gn:admin1_code":"8.0","gn:admin2_code":"903.0","gn:admin3_code":"4786.0","gn:asciiname":"Marinu","gn:country_code":"EE","gn:dem":61,"gn:feature_class":"P","gn:feature_code":"PPL","gn:geonameid":8618658,"gn:latitude":59.47778,"gn:longitude":26.40972,"gn:modification_date":"2017-11-25","gn:name":"Marinu","gn:population":0,"gn:timezone":"Europe/Tallinn","iso:country":"EE","lbl:bbox":"26.38972,59.45778,26.42972,59.49778","lbl:max_zoom":18,"lbl:min_zoom":13.5,"mz:hierarchy_label":1,"mz:is_current":1,"mz:min_zoom":12,"name:est_x_preferred":["Marinu"],"name:hye_x_preferred":["Մառինու"],"name:und_x_variant":["Marino"],"name:vol_x_preferred":["Marinu"],"src:geom":"geonames","wof:belongsto":[85683049,102191581,1713315235,85633135,1713305777],"wof:breaches":[],"wof:concordances":{"gn:id":8618658,"wk:page":"Marinu"},"wof:coterminous":[1713315235],"wof:country":"EE","wof:geomhash":"7d6d196239a03043235a13bc5e590c46","wof:hierarchy":[{"continent_id":102191581,"country_id":85633135,"county_id":1713305777,"localadmin_id":1713315235,"locality_id":1225964237,"region_id":85683049}],"wof:id":1225964237,"wof:lang_x_official":["est"],"wof:lang_x_spoken":["est"],"wof:lastmodified":1596677932,"wof:name":"Marinu","wof:parent_id":1713315235,"wof:placetype":"locality","wof:repo":"whosonfirst-data-admin-ee","wof:superseded_by":[],"wof:supersedes":[],"wof:tags":[]},"bbox":[26.40972,59.47778,26.40972,59.47778],"geometry":{"coordinates":[26.40972,59.47778],"type":"Point"}}