{
  "type": "Feature",
  "properties": {
    "iso:country":"FI",
    "wof:name":"Eira",
    "wof:placetype":"neighbourhood"
},
  "geometry": {"coordinates":[24.9387962720872,60.15595012182582],"type":"Point"}
}