{"id":1293857947,"type":"Feature","properties":{"edtf:cessation":"uuuu","edtf:inception":"uuuu","geom:area":0,"geom:area_square_m":0,"geom:bbox":"27.23556,57.83167,27.23556,57.83167","geom:latitude":57.83167,"geom:longitude":27.23556,"gn:admin1_code":"21.0","gn:admin2_code":"917.0","gn:admin3_code":"8252.0","gn:asciiname":"Tiri","gn:country_code":"EE","gn:dem":96,"gn:feature_class":"P","gn:feature_code":"PPL","gn:geonameid":8619915,"gn:latitude":57.83167,"gn:longitude":27.23556,"gn:modification_date":"2017-11-25","gn:name":"Tiri","gn:population":0,"gn:timezone":"Europe/Tallinn","iso:country":"EE","lbl:bbox":"27.21556,57.81167,27.25556,57.85167","lbl:max_zoom":18,"lbl:min_zoom":13.5,"mz:hierarchy_label":1,"mz:is_current":1,"mz:min_zoom":12,"name:ceb_x_preferred":["Tiri"],"name:swe_x_preferred":["Tiri"],"name:und_x_variant":["Тири"],"src:geom":"geonames","wof:belongsto":[85682937,102191581,1713315487,85633135,1713305633],"wof:breaches":[],"wof:concordances":{"gn:id":8619915},"wof:coterminous":[1713315487],"wof:country":"EE","wof:geomhash":"42a09ae20d4d8ddcf7a6ecdee4886471","wof:hierarchy":[{"continent_id":102191581,"country_id":85633135,"county_id":1713305633,"localadmin_id":1713315487,"locality_id":1293857947,"region_id":85682937}],"wof:id":1293857947,"wof:lang_x_official":["est"],"wof:lang_x_spoken":["est"],"wof:lastmodified":1596660415,"wof:name":"Tiri","wof:parent_id":1713315487,"wof:placetype":"locality","wof:repo":"whosonfirst-data-admin-ee","wof:superseded_by":[],"wof:supersedes":[],"wof:tags":[]},"bbox":[27.23556,57.83167,27.23556,57.83167],"geometry":{"coordinates":[27.23556,57.83167],"type":"Point"}}