{"id":1209313785,"type":"Feature","properties":{"edtf:cessation":"uuuu","edtf:inception":"uuuu","geom:area":0,"geom:area_square_m":0,"geom:bbox":"27.05583,58.74028,27.05583,58.74028","geom:latitude":58.74028,"geom:longitude":27.05583,"gn:admin1_code":"18.0","gn:admin2_code":"586.0","gn:admin3_code":"6699.0","gn:asciiname":"Raatvere","gn:country_code":"EE","gn:dem":45,"gn:feature_class":"P","gn:feature_code":"PPL","gn:geonameid":589219,"gn:latitude":58.74028,"gn:longitude":27.05583,"gn:modification_date":"2017-11-25","gn:name":"Raatvere","gn:population":0,"gn:timezone":"Europe/Tallinn","iso:country":"EE","lbl:bbox":"27.03583,58.72028,27.07583,58.76028","lbl:max_zoom":18,"lbl:min_zoom":13.5,"mz:hierarchy_label":1,"mz:is_current":1,"mz:min_zoom":12,"src:geom":"geonames","wof:belongsto":[85682995,102191581,1713309565,85633135,1713305679],"wof:breaches":[],"wof:concordances":{"gn:id":589219},"wof:coterminous":[1713309565],"wof:country":"EE","wof:geomhash":"d53685e97f1ef5da51ed3612dcd2b881","wof:hierarchy":[{"continent_id":102191581,"country_id":85633135,"county_id":1713305679,"localadmin_id":1713309565,"locality_id":1209313785,"region_id":85682995}],"wof:id":1209313785,"wof:lang_x_official":["est"],"wof:lang_x_spoken":["est"],"wof:lastmodified":1596660905,"wof:name":"Raatvere","wof:parent_id":1713309565,"wof:placetype":"locality","wof:repo":"whosonfirst-data-admin-ee","wof:superseded_by":[],"wof:supersedes":[],"wof:tags":[]},"bbox":[27.05583,58.74028,27.05583,58.74028],"geometry":{"coordinates":[27.05583,58.74028],"type":"Point"}}