{"id":1343971873,"type":"Feature","properties":{"edtf:cessation":"uuuu","edtf:inception":"uuuu","geom:area":0,"geom:area_square_m":0,"geom:bbox":"24.13472,59.26528,24.13472,59.26528","geom:latitude":59.26528,"geom:longitude":24.13472,"gn:admin1_code":"1.0","gn:admin2_code":"431.0","gn:admin3_code":"2731.0","gn:asciiname":"Vaeemla","gn:country_code":"EE","gn:dem":17,"gn:feature_class":"P","gn:feature_code":"PPL","gn:geonameid":587961,"gn:latitude":59.26528,"gn:longitude":24.13472,"gn:modification_date":"2017-11-25","gn:name":"Väemla","gn:population":0,"gn:timezone":"Europe/Tallinn","iso:country":"EE","lbl:bbox":"24.11472,59.24528,24.15472,59.28528","lbl:max_zoom":18,"lbl:min_zoom":13.5,"mz:hierarchy_label":1,"mz:is_current":1,"mz:min_zoom":12,"src:geom":"geonames","wof:belongsto":[85683055,102191581,1713307771,85633135,1713305737],"wof:breaches":[],"wof:concordances":{"gn:id":587961},"wof:country":"EE","wof:geomhash":"1fcb19ca8b47d8619858e24351cfc291","wof:hierarchy":[{"continent_id":102191581,"country_id":85633135,"county_id":1713305737,"localadmin_id":1713307771,"locality_id":1343971873,"region_id":85683055}],"wof:id":1343971873,"wof:lang_x_official":["est"],"wof:lang_x_spoken":["est"],"wof:lastmodified":1596663326,"wof:name":"Vaeemla","wof:parent_id":1713307771,"wof:placetype":"locality","wof:repo":"whosonfirst-data-admin-ee","wof:superseded_by":[],"wof:supersedes":[],"wof:tags":[]},"bbox":[24.13472,59.26528,24.13472,59.26528],"geometry":{"coordinates":[24.13472,59.26528],"type":"Point"}}