{"id":1242673251,"type":"Feature","properties":{"edtf:cessation":"uuuu","edtf:inception":"uuuu","geom:area":0,"geom:area_square_m":0,"geom:bbox":"26.27917,59.24167,26.27917,59.24167","geom:latitude":59.24167,"geom:longitude":26.27917,"gn:admin1_code":"8.0","gn:admin2_code":"792.0","gn:admin3_code":"3438.0","gn:asciiname":"Koplitaguse","gn:country_code":"EE","gn:dem":121,"gn:feature_class":"P","gn:feature_code":"PPL","gn:geonameid":8618858,"gn:latitude":59.24167,"gn:longitude":26.27917,"gn:modification_date":"2017-11-25","gn:name":"Koplitaguse","gn:population":0,"gn:timezone":"Europe/Tallinn","iso:country":"EE","lbl:bbox":"26.25917,59.22167,26.29917,59.26167","lbl:max_zoom":18,"lbl:min_zoom":13.5,"mz:hierarchy_label":1,"mz:is_current":1,"mz:min_zoom":12,"name:est_x_preferred":["Koplitaguse"],"name:hye_x_preferred":["Կոպլիտագուսե"],"name:ukr_x_preferred":["Коплітаґузе"],"name:und_x_variant":["Koonu"],"name:vol_x_preferred":["Koplitaguse"],"src:geom":"geonames","wof:belongsto":[85683049,102191581,1713314021,85633135,1713305761],"wof:breaches":[],"wof:concordances":{"gn:id":8618858,"wk:page":"Koplitaguse"},"wof:coterminous":[1713314021],"wof:country":"EE","wof:geomhash":"60709b9b2c3cff5367c1e987f8ad1c82","wof:hierarchy":[{"continent_id":102191581,"country_id":85633135,"county_id":1713305761,"localadmin_id":1713314021,"locality_id":1242673251,"region_id":85683049}],"wof:id":1242673251,"wof:lang_x_official":["est"],"wof:lang_x_spoken":["est"],"wof:lastmodified":1596676601,"wof:name":"Koplitaguse","wof:parent_id":1713314021,"wof:placetype":"locality","wof:repo":"whosonfirst-data-admin-ee","wof:superseded_by":[],"wof:supersedes":[],"wof:tags":[]},"bbox":[26.27917,59.24167,26.27917,59.24167],"geometry":{"coordinates":[26.27917,59.24167],"type":"Point"}}