{"id":1293676159,"type":"Feature","properties":{"edtf:cessation":"uuuu","edtf:inception":"uuuu","geom:area":0,"geom:area_square_m":0,"geom:bbox":"26.75417,57.93361,26.75417,57.93361","geom:latitude":57.93361,"geom:longitude":26.75417,"gn:admin1_code":"12.0","gn:admin2_code":"284.0","gn:admin3_code":"3280.0","gn:asciiname":"Koigera","gn:country_code":"EE","gn:dem":121,"gn:feature_class":"P","gn:feature_code":"PPL","gn:geonameid":794472,"gn:latitude":57.93361,"gn:longitude":26.75417,"gn:modification_date":"2017-11-25","gn:name":"Koigera","gn:population":0,"gn:timezone":"Europe/Tallinn","iso:country":"EE","lbl:bbox":"26.73417,57.91361,26.77417,57.95361","lbl:max_zoom":18,"lbl:min_zoom":13.5,"mz:hierarchy_label":1,"mz:is_current":1,"mz:min_zoom":12,"name:est_x_preferred":["Koigera"],"name:hye_x_preferred":["Կոիգեռա"],"name:pol_x_preferred":["Koigera"],"name:spa_x_preferred":["Koigera"],"name:ukr_x_preferred":["Коїгера"],"name:vol_x_preferred":["Koigera"],"src:geom":"geonames","wof:belongsto":[85682955,102191581,1713316081,85633135,1713305789],"wof:breaches":[],"wof:concordances":{"gn:id":794472,"wk:page":"Koigera"},"wof:coterminous":[1713316081],"wof:country":"EE","wof:geomhash":"1f0d309984de0d83e077405fa0e907d6","wof:hierarchy":[{"continent_id":102191581,"country_id":85633135,"county_id":1713305789,"localadmin_id":1713316081,"locality_id":1293676159,"region_id":85682955}],"wof:id":1293676159,"wof:lang_x_official":["est"],"wof:lang_x_spoken":["est"],"wof:lastmodified":1596676795,"wof:name":"Koigera","wof:parent_id":1713316081,"wof:placetype":"locality","wof:repo":"whosonfirst-data-admin-ee","wof:superseded_by":[],"wof:supersedes":[],"wof:tags":[]},"bbox":[26.75417,57.93361,26.75417,57.93361],"geometry":{"coordinates":[26.75417,57.93361],"type":"Point"}}