{"id":1344076935,"type":"Feature","properties":{"edtf:cessation":"uuuu","edtf:inception":"uuuu","geom:area":0,"geom:area_square_m":0,"geom:bbox":"26.27167,59.40944,26.27167,59.40944","geom:latitude":59.40944,"geom:longitude":26.27167,"gn:admin1_code":"8.0","gn:admin2_code":"191.0","gn:admin3_code":"3161.0","gn:asciiname":"Veskimaee","gn:country_code":"EE","gn:dem":84,"gn:feature_class":"P","gn:feature_code":"PPL","gn:geonameid":8619598,"gn:latitude":59.40944,"gn:longitude":26.27167,"gn:modification_date":"2017-11-25","gn:name":"Veskimäe","gn:population":0,"gn:timezone":"Europe/Tallinn","iso:country":"EE","lbl:bbox":"26.25167,59.38944,26.29167,59.42944","lbl:max_zoom":18,"lbl:min_zoom":13.5,"mz:hierarchy_label":1,"mz:is_current":1,"mz:min_zoom":12,"src:geom":"geonames","wof:belongsto":[85683049,102191581,1713313943,85633135,1713305775],"wof:breaches":[],"wof:concordances":{"gn:id":8619598},"wof:country":"EE","wof:geomhash":"b1167c75a422808bf44f8c8b242281f9","wof:hierarchy":[{"continent_id":102191581,"country_id":85633135,"county_id":1713305775,"localadmin_id":1713313943,"locality_id":1344076935,"region_id":85683049}],"wof:id":1344076935,"wof:lang_x_official":["est"],"wof:lang_x_spoken":["est"],"wof:lastmodified":1596678047,"wof:name":"Veskimaee","wof:parent_id":1713313943,"wof:placetype":"locality","wof:repo":"whosonfirst-data-admin-ee","wof:superseded_by":[],"wof:supersedes":[],"wof:tags":[]},"bbox":[26.27167,59.40944,26.27167,59.40944],"geometry":{"coordinates":[26.27167,59.40944],"type":"Point"}}