{"id":1343943511,"type":"Feature","properties":{"edtf:cessation":"uuuu","edtf:inception":"uuuu","geom:area":0,"geom:area_square_m":0,"geom:bbox":"26.3075,59.47694,26.3075,59.47694","geom:latitude":59.47694,"geom:longitude":26.3075,"gn:admin1_code":"8.0","gn:admin2_code":"191.0","gn:admin3_code":"2779.0","gn:asciiname":"Varangu-Raja","gn:country_code":"EE","gn:dem":69,"gn:feature_class":"P","gn:feature_code":"PPL","gn:geonameid":8618767,"gn:latitude":59.47694,"gn:longitude":26.3075,"gn:modification_date":"2017-11-25","gn:name":"Varangu-Raja","gn:population":0,"gn:timezone":"Europe/Tallinn","iso:country":"EE","lbl:bbox":"26.2875,59.45694,26.3275,59.49694","lbl:max_zoom":18,"lbl:min_zoom":13.5,"mz:hierarchy_label":1,"mz:is_current":1,"mz:min_zoom":12,"name:und_x_variant":["Warangu"],"src:geom":"geonames","wof:belongsto":[85683049,102191581,1713308627,85633135,1713305775],"wof:breaches":[],"wof:concordances":{"gn:id":8618767},"wof:country":"EE","wof:geomhash":"c1e5d9d01996f1fdfe421e10628daa13","wof:hierarchy":[{"continent_id":102191581,"country_id":85633135,"county_id":1713305775,"localadmin_id":1713308627,"locality_id":1343943511,"region_id":85683049}],"wof:id":1343943511,"wof:lang_x_official":["est"],"wof:lang_x_spoken":["est"],"wof:lastmodified":1596678046,"wof:name":"Varangu-Raja","wof:parent_id":1713308627,"wof:placetype":"locality","wof:repo":"whosonfirst-data-admin-ee","wof:superseded_by":[],"wof:supersedes":[],"wof:tags":[]},"bbox":[26.3075,59.47694,26.3075,59.47694],"geometry":{"coordinates":[26.3075,59.47694],"type":"Point"}}