{"id":1293613417,"type":"Feature","properties":{"edtf:cessation":"uuuu","edtf:inception":"uuuu","geom:area":0,"geom:area_square_m":0,"geom:bbox":"25.65,59.05,25.65,59.05","geom:latitude":59.05,"geom:longitude":25.65,"gn:admin1_code":"4.0","gn:admin2_code":"567.0","gn:admin3_code":"5609.0","gn:asciiname":"Kiigumoisa","gn:cc2":"EE","gn:country_code":"EE","gn:dem":80,"gn:feature_class":"P","gn:feature_code":"PPL","gn:geonameid":591407,"gn:latitude":59.05,"gn:longitude":25.65,"gn:modification_date":"2017-11-25","gn:name":"Kiigumõisa","gn:population":0,"gn:timezone":"Europe/Tallinn","iso:country":"EE","lbl:bbox":"25.63,59.03,25.67,59.07","lbl:max_zoom":18,"lbl:min_zoom":13.5,"mz:hierarchy_label":1,"mz:is_current":1,"mz:min_zoom":12,"name:und_x_variant":["Kiygumyiza","Kiigumõisa"],"src:geom":"geonames","wof:belongsto":[85683031,102191581,1713313437,85633135,1713305663],"wof:breaches":[],"wof:concordances":{"gn:id":591407},"wof:country":"EE","wof:geomhash":"2052d79af179baa9a8dde876aa698d1e","wof:hierarchy":[{"continent_id":102191581,"country_id":85633135,"county_id":1713305663,"localadmin_id":1713313437,"locality_id":1293613417,"region_id":85683031}],"wof:id":1293613417,"wof:lang_x_official":["est"],"wof:lang_x_spoken":["est"],"wof:lastmodified":1596661330,"wof:name":"Kiigumoisa","wof:parent_id":1713313437,"wof:placetype":"locality","wof:repo":"whosonfirst-data-admin-ee","wof:superseded_by":[],"wof:supersedes":[],"wof:tags":[]},"bbox":[25.65,59.05,25.65,59.05],"geometry":{"coordinates":[25.65,59.05],"type":"Point"}}