{"id":1343266459,"type":"Feature","properties":{"edtf:cessation":"uuuu","edtf:inception":"uuuu","geom:area":0,"geom:area_square_m":0,"geom:bbox":"26.02861,58.67583,26.02861,58.67583","geom:latitude":58.67583,"geom:longitude":26.02861,"gn:admin1_code":"5.0","gn:admin2_code":"618.0","gn:admin3_code":"6048.0","gn:asciiname":"Arukse","gn:country_code":"EE","gn:dem":66,"gn:feature_class":"P","gn:feature_code":"PPL","gn:geonameid":8618404,"gn:latitude":58.67583,"gn:longitude":26.02861,"gn:modification_date":"2017-11-25","gn:name":"Arukse","gn:population":0,"gn:timezone":"Europe/Tallinn","iso:country":"EE","lbl:bbox":"26.00861,58.65583,26.04861,58.69583","lbl:max_zoom":18,"lbl:min_zoom":13.5,"mz:hierarchy_label":1,"mz:is_current":1,"mz:min_zoom":12,"name:est_x_preferred":["Arukse"],"name:hye_x_preferred":["Առուկսե"],"name:pol_x_preferred":["Arukse"],"name:und_x_variant":["Arukese"],"name:vol_x_preferred":["Arukse"],"src:geom":"geonames","wof:belongsto":[85683009,102191581,1713312543,85633135,1713305657],"wof:breaches":[],"wof:concordances":{"gn:id":8618404},"wof:country":"EE","wof:geomhash":"5588564b6efc5cbb97ac4aa5b7cb51b0","wof:hierarchy":[{"continent_id":102191581,"country_id":85633135,"county_id":1713305657,"localadmin_id":1713312543,"locality_id":1343266459,"region_id":85683009}],"wof:id":1343266459,"wof:lang_x_official":["est"],"wof:lang_x_spoken":["est"],"wof:lastmodified":1596676500,"wof:name":"Arukse","wof:parent_id":1713312543,"wof:placetype":"locality","wof:repo":"whosonfirst-data-admin-ee","wof:superseded_by":[],"wof:supersedes":[],"wof:tags":[]},"bbox":[26.02861,58.67583,26.02861,58.67583],"geometry":{"coordinates":[26.02861,58.67583],"type":"Point"}}