{"id":1343442201,"type":"Feature","properties":{"edtf:cessation":"uuuu","edtf:inception":"uuuu","geom:area":0,"geom:area_square_m":0,"geom:bbox":"24.43611,58.62,24.43611,58.62","geom:latitude":58.62,"geom:longitude":24.43611,"gn:admin1_code":"11.0","gn:admin2_code":"638.0","gn:admin3_code":"7061.0","gn:asciiname":"Roodi","gn:cc2":"EE","gn:country_code":"EE","gn:dem":29,"gn:feature_class":"P","gn:feature_code":"PPL","gn:geonameid":588971,"gn:latitude":58.62,"gn:longitude":24.43611,"gn:modification_date":"2017-11-25","gn:name":"Roodi","gn:population":0,"gn:timezone":"Europe/Tallinn","iso:country":"EE","lbl:bbox":"24.41611,58.6,24.45611,58.64","lbl:max_zoom":18,"lbl:min_zoom":13.5,"mz:hierarchy_label":1,"mz:is_current":1,"mz:min_zoom":12,"name:est_x_preferred":["Roodi"],"name:hye_x_preferred":["Ռոոդի"],"name:pol_x_preferred":["Roodi"],"name:spa_x_preferred":["Roodi"],"name:und_x_variant":["Myza Rodi"],"name:vol_x_preferred":["Roodi"],"src:geom":"geonames","wof:belongsto":[85682981,102191581,1713309351,85633135,1713305733],"wof:breaches":[],"wof:concordances":{"gn:id":588971,"wk:page":"Roodi"},"wof:coterminous":[1713309351],"wof:country":"EE","wof:geomhash":"9da9082c92926c481e9d2ddc30f0c556","wof:hierarchy":[{"continent_id":102191581,"country_id":85633135,"county_id":1713305733,"localadmin_id":1713309351,"locality_id":1343442201,"region_id":85682981}],"wof:id":1343442201,"wof:lang_x_official":["est"],"wof:lang_x_spoken":["est"],"wof:lastmodified":1596663419,"wof:name":"Roodi","wof:parent_id":1713309351,"wof:placetype":"locality","wof:repo":"whosonfirst-data-admin-ee","wof:superseded_by":[],"wof:supersedes":[],"wof:tags":[]},"bbox":[24.43611,58.62,24.43611,58.62],"geometry":{"coordinates":[24.43611,58.62],"type":"Point"}}