{"id":1209079969,"type":"Feature","properties":{"edtf:cessation":"uuuu","edtf:inception":"uuuu","geom:area":0,"geom:area_square_m":0,"geom:bbox":"22.19306,58.18083,22.19306,58.18083","geom:latitude":58.18083,"geom:longitude":22.19306,"gn:admin1_code":"14.0","gn:admin2_code":"714.0","gn:admin3_code":"8227.0","gn:asciiname":"Uuskuela","gn:country_code":"EE","gn:dem":19,"gn:feature_class":"P","gn:feature_code":"PPL","gn:geonameid":8619279,"gn:latitude":58.18083,"gn:longitude":22.19306,"gn:modification_date":"2017-11-25","gn:name":"Uusküla","gn:population":0,"gn:timezone":"Europe/Tallinn","iso:country":"EE","lbl:bbox":"22.17306,58.16083,22.21306,58.20083","lbl:max_zoom":18,"lbl:min_zoom":13.5,"mz:hierarchy_label":1,"mz:is_current":1,"mz:min_zoom":12,"name:und_x_variant":["Uusküla","Kristuse Sündimiseirik"],"src:geom":"geonames","wof:belongsto":[85682947,102191581,1713308279,85633135,1713305627],"wof:breaches":[],"wof:concordances":{"gn:id":8619279},"wof:country":"EE","wof:geomhash":"4c6d7563b1821e304ad99ebe8e83a109","wof:hierarchy":[{"continent_id":102191581,"country_id":85633135,"county_id":1713305627,"localadmin_id":1713308279,"locality_id":1209079969,"region_id":85682947}],"wof:id":1209079969,"wof:lang_x_official":["est"],"wof:lang_x_spoken":["est"],"wof:lastmodified":1596674918,"wof:name":"Uuskuela","wof:parent_id":1713308279,"wof:placetype":"locality","wof:repo":"whosonfirst-data-admin-ee","wof:superseded_by":[],"wof:supersedes":[],"wof:tags":[]},"bbox":[22.19306,58.18083,22.19306,58.18083],"geometry":{"coordinates":[22.19306,58.18083],"type":"Point"}}