{"id":1225839433,"type":"Feature","properties":{"edtf:cessation":"uuuu","edtf:inception":"uuuu","geom:area":0,"geom:area_square_m":0,"geom:bbox":"23.57944,59.13278,23.57944,59.13278","geom:latitude":59.13278,"geom:longitude":23.57944,"gn:admin1_code":"7.0","gn:admin2_code":"441.0","gn:admin3_code":"1964.0","gn:asciiname":"Hoebringi","gn:country_code":"EE","gn:dem":25,"gn:feature_class":"P","gn:feature_code":"PPL","gn:geonameid":592107,"gn:latitude":59.13278,"gn:longitude":23.57944,"gn:modification_date":"2017-11-25","gn:name":"Höbringi","gn:population":0,"gn:timezone":"Europe/Tallinn","iso:country":"EE","lbl:bbox":"23.55944,59.11278,23.59944,59.15278","lbl:max_zoom":18,"lbl:min_zoom":13.5,"mz:hierarchy_label":1,"mz:is_current":1,"mz:min_zoom":12,"name:deu_x_preferred":["Höbringi"],"name:est_x_preferred":["Höbringi"],"name:hye_x_preferred":["Հոոբռինգի"],"name:nld_x_preferred":["Höbringi"],"name:pol_x_preferred":["Höbringi"],"name:spa_x_preferred":["Höbringi"],"name:swe_x_preferred":["Höbring"],"name:ukr_x_preferred":["Гєбрінґі"],"name:und_x_variant":["Khyubringi"],"name:vol_x_preferred":["Höbringi"],"src:geom":"geonames","wof:belongsto":[85683001,102191581,1713308743,85633135,1713305701],"wof:breaches":[],"wof:concordances":{"gn:id":592107,"wk:page":"H%C3%B6bringi"},"wof:coterminous":[1713308743],"wof:country":"EE","wof:geomhash":"44085c7d34b1eae886a3b10ffa54bfdc","wof:hierarchy":[{"continent_id":102191581,"country_id":85633135,"county_id":1713305701,"localadmin_id":1713308743,"locality_id":1225839433,"region_id":85683001}],"wof:id":1225839433,"wof:lang_x_official":["est"],"wof:lang_x_spoken":["est"],"wof:lastmodified":1596677427,"wof:name":"Hoebringi","wof:parent_id":1713308743,"wof:placetype":"locality","wof:repo":"whosonfirst-data-admin-ee","wof:superseded_by":[],"wof:supersedes":[],"wof:tags":[]},"bbox":[23.57944,59.13278,23.57944,59.13278],"geometry":{"coordinates":[23.57944,59.13278],"type":"Point"}}