{"id":1260288569,"type":"Feature","properties":{"edtf:cessation":"uuuu","edtf:inception":"uuuu","geom:area":0,"geom:area_square_m":0,"geom:bbox":"24.4875,59.12333,24.4875,59.12333","geom:latitude":59.12333,"geom:longitude":24.4875,"gn:admin1_code":"1.0","gn:admin2_code":"726.0","gn:admin3_code":"2976.0","gn:asciiname":"Niine","gn:country_code":"EE","gn:dem":58,"gn:feature_class":"P","gn:feature_code":"PPL","gn:geonameid":8618439,"gn:latitude":59.12333,"gn:longitude":24.4875,"gn:modification_date":"2017-11-25","gn:name":"Niine","gn:population":0,"gn:timezone":"Europe/Tallinn","iso:country":"EE","lbl:bbox":"24.4675,59.10333,24.5075,59.14333","lbl:max_zoom":18,"lbl:min_zoom":13.5,"mz:hierarchy_label":1,"mz:is_current":1,"mz:min_zoom":12,"name:und_x_variant":["Jaani"],"src:geom":"geonames","wof:belongsto":[85683055,102191581,1713307891,85633135,1713305739],"wof:breaches":[],"wof:concordances":{"gn:id":8618439},"wof:country":"EE","wof:geomhash":"72ff0919e555bf004d959aca92ee5de9","wof:hierarchy":[{"continent_id":102191581,"country_id":85633135,"county_id":1713305739,"localadmin_id":1713307891,"locality_id":1260288569,"region_id":85683055}],"wof:id":1260288569,"wof:lang_x_official":["est"],"wof:lang_x_spoken":["est"],"wof:lastmodified":1596663244,"wof:name":"Niine","wof:parent_id":1713307891,"wof:placetype":"locality","wof:repo":"whosonfirst-data-admin-ee","wof:superseded_by":[],"wof:supersedes":[],"wof:tags":[]},"bbox":[24.4875,59.12333,24.4875,59.12333],"geometry":{"coordinates":[24.4875,59.12333],"type":"Point"}}