{"id":1125858383,"type":"Feature","properties":{"edtf:cessation":"uuuu","edtf:inception":"uuuu","geom:area":0,"geom:area_square_m":0,"geom:bbox":"26.68972,58.33889,26.68972,58.33889","geom:latitude":58.33889,"geom:longitude":26.68972,"gn:country":"EE","gn:fcode":"PPL","gn:population":336,"iso:country":"EE","lbl:bbox":"26.66972,58.31889,26.70972,58.35889","lbl:latitude":58.33889,"lbl:longitude":26.68972,"lbl:max_zoom":17,"lbl:min_zoom":12.5,"mz:hierarchy_label":1,"mz:is_current":1,"mz:min_zoom":11,"mz:note":"Quattroshapes Point Gazetteer import 20170519","name:bul_x_preferred":["Соинасте"],"name:ceb_x_preferred":["Soinaste"],"name:eng_x_preferred":["Soinaste"],"name:est_x_preferred":["Soinaste"],"name:fra_x_preferred":["Soinaste"],"name:hye_x_preferred":["Սոինաստե"],"name:nld_x_preferred":["Soinaste"],"name:pol_x_preferred":["Soinaste"],"name:spa_x_preferred":["Soinaste"],"name:swe_x_preferred":["Soinaste"],"name:ukr_x_preferred":["Сойнасте"],"name:vol_x_preferred":["Soinaste"],"qs_pg:aaroncc":"EE","qs_pg:gn_country":"EE","qs_pg:gn_fcode":"PPL","qs_pg:gn_id":794040,"qs_pg:gn_pop":336,"qs_pg:name":"Soinaste","qs_pg:name_adm0":"Eesti","qs_pg:name_adm1":"Tartumaa","qs_pg:photos_9r":0,"qs_pg:photos_sr":0,"qs_pg:pop_sr":2,"qs_pg:qs_id":1274521,"qs_pg:qs_pg_placetype":"locality","qs_pg:qs_pg_placetype_gp":"Town","qs_pg:woe_adm0":23424805,"qs_pg:woe_id":845543,"src:geom":"qs_pg","src:lbl_centroid":"qs_pg","src:population":"geonames","woe:adm0_id":23424805,"woe:name_adm0":"Eesti","woe:name_adm1":"Tartumaa","woe:placetype":"Town","wof:belongsto":[85682995,102191581,1713313891,85633135,1713305717],"wof:breaches":[],"wof:concordances":{"gn:id":794040,"gp:id":845543,"qs_pg:id":1274521,"wd:id":"Q671025"},"wof:coterminous":[1713313891],"wof:country":"EE","wof:created":1497293719,"wof:geomhash":"4952c8cad76542a305d866a225a59ae9","wof:hierarchy":[{"continent_id":102191581,"country_id":85633135,"county_id":1713305717,"localadmin_id":1713313891,"locality_id":1125858383,"region_id":85682995}],"wof:id":1125858383,"wof:lang_x_official":["est"],"wof:lang_x_spoken":["est"],"wof:lastmodified":1596676688,"wof:name":"Soinaste","wof:parent_id":1713313891,"wof:placetype":"locality","wof:population":336,"wof:population_rank":2,"wof:repo":"whosonfirst-data-admin-ee","wof:superseded_by":[],"wof:supersedes":[],"wof:tags":[]},"bbox":[26.68972,58.33889,26.68972,58.33889],"geometry":{"coordinates":[26.68972,58.33889],"type":"Point"}}