{"id":1276534029,"type":"Feature","properties":{"edtf:cessation":"uuuu","edtf:inception":"uuuu","geom:area":0,"geom:area_square_m":0,"geom:bbox":"26.08583,59.23472,26.08583,59.23472","geom:latitude":59.23472,"geom:longitude":26.08583,"gn:admin1_code":"8.0","gn:admin2_code":"792.0","gn:admin3_code":"7343.0","gn:asciiname":"Kalle","gn:country_code":"EE","gn:dem":101,"gn:feature_class":"P","gn:feature_code":"PPL","gn:geonameid":8618491,"gn:latitude":59.23472,"gn:longitude":26.08583,"gn:modification_date":"2017-11-25","gn:name":"Kalle","gn:population":0,"gn:timezone":"Europe/Tallinn","iso:country":"EE","lbl:bbox":"26.06583,59.21472,26.10583,59.25472","lbl:max_zoom":18,"lbl:min_zoom":13.5,"mz:hierarchy_label":1,"mz:is_current":1,"mz:min_zoom":12,"name:deu_x_preferred":["Kalle"],"name:fin_x_preferred":["Kalle"],"name:nld_x_preferred":["Kalle"],"name:swe_x_preferred":["Karl"],"name:und_x_variant":["Kalle-Trilli"],"src:geom":"geonames","wof:belongsto":[85683049,102191581,1713308257,85633135,1713305761],"wof:breaches":[],"wof:concordances":{"gn:id":8618491},"wof:country":"EE","wof:geomhash":"d4170c112b3b170297dd556d6c387a6a","wof:hierarchy":[{"continent_id":102191581,"country_id":85633135,"county_id":1713305761,"localadmin_id":1713308257,"locality_id":1276534029,"region_id":85683049}],"wof:id":1276534029,"wof:lang_x_official":["est"],"wof:lang_x_spoken":["est"],"wof:lastmodified":1596676605,"wof:name":"Kalle","wof:parent_id":1713308257,"wof:placetype":"locality","wof:repo":"whosonfirst-data-admin-ee","wof:superseded_by":[],"wof:supersedes":[],"wof:tags":[]},"bbox":[26.08583,59.23472,26.08583,59.23472],"geometry":{"coordinates":[26.08583,59.23472],"type":"Point"}}