{"id":1242893819,"type":"Feature","properties":{"edtf:cessation":"uuuu","edtf:inception":"uuuu","geom:area":0,"geom:area_square_m":0,"geom:bbox":"25.84611,59.56278,25.84611,59.56278","geom:latitude":59.56278,"geom:longitude":25.84611,"gn:admin1_code":"8.0","gn:admin2_code":"191.0","gn:admin3_code":"1637.0","gn:asciiname":"Eru","gn:cc2":"EE","gn:country_code":"EE","gn:dem":40,"gn:feature_class":"P","gn:feature_code":"PPL","gn:geonameid":592249,"gn:latitude":59.56278,"gn:longitude":25.84611,"gn:modification_date":"2017-11-25","gn:name":"Eru","gn:population":0,"gn:timezone":"Europe/Tallinn","iso:country":"EE","lbl:bbox":"25.82611,59.54278,25.86611,59.58278","lbl:max_zoom":18,"lbl:min_zoom":13.5,"mz:hierarchy_label":1,"mz:is_current":1,"mz:min_zoom":12,"name:est_x_preferred":["Eru"],"name:fra_x_preferred":["Eru"],"name:hye_x_preferred":["Էռու"],"name:pol_x_preferred":["Eru"],"name:und_x_variant":["Eru Küla"],"name:vol_x_preferred":["Eru"],"src:geom":"geonames","wof:belongsto":[85683049,102191581,1713308471,85633135,1713305775],"wof:breaches":[],"wof:concordances":{"gn:id":592249,"wk:page":"Eru%2C_Estonia"},"wof:coterminous":[1713308471],"wof:country":"EE","wof:geomhash":"5371c98d3ee867ad986a2b3c0043faf1","wof:hierarchy":[{"continent_id":102191581,"country_id":85633135,"county_id":1713305775,"localadmin_id":1713308471,"locality_id":1242893819,"region_id":85683049}],"wof:id":1242893819,"wof:lang_x_official":["est"],"wof:lang_x_spoken":["est"],"wof:lastmodified":1596678039,"wof:name":"Eru","wof:parent_id":1713308471,"wof:placetype":"locality","wof:repo":"whosonfirst-data-admin-ee","wof:superseded_by":[],"wof:supersedes":[],"wof:tags":[]},"bbox":[25.84611,59.56278,25.84611,59.56278],"geometry":{"coordinates":[25.84611,59.56278],"type":"Point"}}