{"id":1310371583,"type":"Feature","properties":{"edtf:cessation":"uuuu","edtf:inception":"uuuu","geom:area":0,"geom:area_square_m":0,"geom:bbox":"26.32694,58.27083,26.32694,58.27083","geom:latitude":58.27083,"geom:longitude":26.32694,"gn:admin1_code":"18.0","gn:admin2_code":"171.0","gn:admin3_code":"6322.0","gn:asciiname":"Poole","gn:cc2":"EE","gn:country_code":"EE","gn:dem":83,"gn:feature_class":"P","gn:feature_code":"PPL","gn:geonameid":589369,"gn:latitude":58.27083,"gn:longitude":26.32694,"gn:modification_date":"2017-11-25","gn:name":"Poole","gn:population":0,"gn:timezone":"Europe/Tallinn","iso:country":"EE","lbl:bbox":"26.30694,58.25083,26.34694,58.29083","lbl:max_zoom":18,"lbl:min_zoom":13.5,"mz:hierarchy_label":1,"mz:is_current":1,"mz:min_zoom":12,"name:ell_x_preferred":["Πουλ"],"name:est_x_preferred":["Poole"],"name:fra_x_preferred":["Poole"],"name:hin_x_preferred":["पूल"],"name:hye_x_preferred":["Պոոլե"],"name:ind_x_preferred":["Poole"],"name:pol_x_preferred":["Poole"],"name:spa_x_preferred":["Poole"],"name:tur_x_preferred":["Poole"],"name:ukr_x_preferred":["Пооле"],"name:und_x_variant":["Poolemõisa","Pote"],"name:vie_x_preferred":["Poole"],"name:vol_x_preferred":["Poole"],"src:geom":"geonames","wof:belongsto":[85682995,102191581,1713310725,85633135,1713305757],"wof:breaches":[],"wof:concordances":{"gn:id":589369,"wk:page":"Poole%2C_Estonia"},"wof:coterminous":[1713310725],"wof:country":"EE","wof:geomhash":"59f57ec8aa44ee9aa4c978f3029f8c93","wof:hierarchy":[{"continent_id":102191581,"country_id":85633135,"county_id":1713305757,"localadmin_id":1713310725,"locality_id":1310371583,"region_id":85682995}],"wof:id":1310371583,"wof:lang_x_official":["est"],"wof:lang_x_spoken":["est"],"wof:lastmodified":1636502241,"wof:name":"Poole","wof:parent_id":1713310725,"wof:placetype":"locality","wof:repo":"whosonfirst-data-admin-ee","wof:superseded_by":[],"wof:supersedes":[],"wof:tags":[]},"bbox":[26.32694,58.27083,26.32694,58.27083],"geometry":{"coordinates":[26.32694,58.27083],"type":"Point"}}