{"id":1310102377,"type":"Feature","properties":{"edtf:cessation":"uuuu","edtf:inception":"uuuu","geom:area":0,"geom:area_square_m":0,"geom:bbox":"23.64194,58.63722,23.64194,58.63722","geom:latitude":58.63722,"geom:longitude":23.64194,"gn:admin1_code":"11.0","gn:admin2_code":"430.0","gn:admin3_code":"3765.0","gn:asciiname":"Uue-Virtsu","gn:country_code":"EE","gn:dem":15,"gn:feature_class":"P","gn:feature_code":"PPL","gn:geonameid":588006,"gn:latitude":58.63722,"gn:longitude":23.64194,"gn:modification_date":"2017-11-25","gn:name":"Uue-Virtsu","gn:population":0,"gn:timezone":"Europe/Tallinn","iso:country":"EE","lbl:bbox":"23.62194,58.61722,23.66194,58.65722","lbl:max_zoom":18,"lbl:min_zoom":13.5,"mz:hierarchy_label":1,"mz:is_current":1,"mz:min_zoom":12,"name:und_x_variant":["Polumyza Us Virtsu","Neu-Werder","Us Virtsu","Uue-Vistsu","Uue Wirtsu","Virtsu","Uue-Virtsu"],"src:geom":"geonames","wof:belongsto":[85683001,102191581,1713309619,85633135,1713305721],"wof:breaches":[],"wof:concordances":{"gn:id":588006},"wof:country":"EE","wof:geomhash":"99d41798168ffab30294f8ab3df72b8f","wof:hierarchy":[{"continent_id":102191581,"country_id":85633135,"county_id":1713305721,"localadmin_id":1713309619,"locality_id":1310102377,"region_id":85683001}],"wof:id":1310102377,"wof:lang_x_official":["est"],"wof:lang_x_spoken":["est"],"wof:lastmodified":1596661684,"wof:name":"Uue-Virtsu","wof:parent_id":1713309619,"wof:placetype":"locality","wof:repo":"whosonfirst-data-admin-ee","wof:superseded_by":[],"wof:supersedes":[],"wof:tags":[]},"bbox":[23.64194,58.63722,23.64194,58.63722],"geometry":{"coordinates":[23.64194,58.63722],"type":"Point"}}