{"id":1193264645,"type":"Feature","properties":{"edtf:cessation":"uuuu","edtf:inception":"uuuu","geom:area":0,"geom:area_square_m":0,"geom:bbox":"24.89222,59.10361,24.89222,59.10361","geom:latitude":59.10361,"geom:longitude":24.89222,"gn:admin1_code":"13.0","gn:admin2_code":"668.0","gn:admin3_code":"1944.0","gn:asciiname":"Haergla","gn:country_code":"EE","gn:dem":71,"gn:feature_class":"P","gn:feature_code":"PPL","gn:geonameid":795002,"gn:latitude":59.10361,"gn:longitude":24.89222,"gn:modification_date":"2017-11-25","gn:name":"Härgla","gn:population":0,"gn:timezone":"Europe/Tallinn","iso:country":"EE","lbl:bbox":"24.87222,59.08361,24.91222,59.12361","lbl:max_zoom":18,"lbl:min_zoom":13.5,"mz:hierarchy_label":1,"mz:is_current":1,"mz:min_zoom":12,"name:est_x_preferred":["Härgla"],"name:fra_x_preferred":["Härgla"],"name:hye_x_preferred":["Հեռգլա"],"name:pol_x_preferred":["Härgla"],"name:sco_x_preferred":["Härgla"],"name:spa_x_preferred":["Härgla"],"name:vol_x_preferred":["Härgla"],"src:geom":"geonames","wof:belongsto":[85683013,102191581,1713313949,85633135,1713305711],"wof:breaches":[],"wof:concordances":{"gn:id":795002,"wk:page":"H%C3%A4rgla"},"wof:coterminous":[1713313949],"wof:country":"EE","wof:geomhash":"68980ca5fe583e497404885ace587fd6","wof:hierarchy":[{"continent_id":102191581,"country_id":85633135,"county_id":1713305711,"localadmin_id":1713313949,"locality_id":1193264645,"region_id":85683013}],"wof:id":1193264645,"wof:lang_x_official":["est"],"wof:lang_x_spoken":["est"],"wof:lastmodified":1596676722,"wof:name":"Haergla","wof:parent_id":1713313949,"wof:placetype":"locality","wof:repo":"whosonfirst-data-admin-ee","wof:superseded_by":[],"wof:supersedes":[],"wof:tags":[]},"bbox":[24.89222,59.10361,24.89222,59.10361],"geometry":{"coordinates":[24.89222,59.10361],"type":"Point"}}