{"id":1126008551,"type":"Feature","properties":{"edtf:cessation":"uuuu","edtf:inception":"uuuu","geom:area":0,"geom:area_square_m":0,"geom:bbox":"26.34444,58.11917,26.34444,58.11917","geom:latitude":58.11917,"geom:longitude":26.34444,"gn:country":"EE","gn:fcode":"PPL","gn:population":187,"iso:country":"EE","lbl:bbox":"26.32444,58.09917,26.36444,58.13917","lbl:latitude":58.11917,"lbl:longitude":26.34444,"lbl:max_zoom":18,"lbl:min_zoom":13,"mz:hierarchy_label":1,"mz:is_current":1,"mz:min_zoom":11,"mz:note":"Quattroshapes Point Gazetteer import 20170519","name:ceb_x_preferred":["Palupera"],"name:eng_x_preferred":["Palupera Parish"],"name:est_x_preferred":["Palupera vald"],"name:est_x_variant":["Palupera"],"name:fas_x_preferred":["دهستان پالوپرا"],"name:fra_x_preferred":["Commune de Palupera"],"name:hye_x_preferred":["Պալուպեռա"],"name:kat_x_preferred":["პალუპერის მუნიციპალიტეტი"],"name:nld_x_preferred":["Palupera"],"name:nor_x_preferred":["Palupera kommune"],"name:pol_x_preferred":["Gmina Palupera"],"name:pol_x_variant":["Palupera"],"name:ron_x_preferred":["Comuna Palupera"],"name:rus_x_preferred":["Палупера"],"name:spa_x_preferred":["Palupera"],"name:swe_x_preferred":["Palupera"],"name:ukr_x_preferred":["Палупера"],"name:und_x_variant":["Palupera Asundus"],"name:vol_x_preferred":["Palupera"],"qs_pg:aaroncc":"EE","qs_pg:gn_country":"EE","qs_pg:gn_fcode":"PPL","qs_pg:gn_id":589638,"qs_pg:gn_pop":187,"qs_pg:name":"Palupera","qs_pg:name_adm0":"Eesti","qs_pg:name_adm1":"Valgamaa","qs_pg:photos_9k":1,"qs_pg:photos_9r":1,"qs_pg:photos_all":3,"qs_pg:photos_sr":0,"qs_pg:pop_sr":1,"qs_pg:qs_id":111121,"qs_pg:qs_pg_placetype":"locality","qs_pg:qs_pg_placetype_gp":"Town","qs_pg:woe_adm0":23424805,"qs_pg:woe_id":844585,"src:geom":"qs_pg","src:lbl_centroid":"qs_pg","src:population":"geonames","woe:adm0_id":23424805,"woe:name_adm0":"Eesti","woe:name_adm1":"Valgamaa","woe:placetype":"Town","wof:belongsto":[85682995,102191581,1713313495,85633135,1713305757],"wof:breaches":[],"wof:concordances":{"gn:id":589638,"gp:id":844585,"qs_pg:id":111121},"wof:coterminous":[1713313495],"wof:country":"EE","wof:created":1497300129,"wof:geomhash":"a9fec8ca31975b4e9f535600f816135d","wof:hierarchy":[{"continent_id":102191581,"country_id":85633135,"county_id":1713305757,"localadmin_id":1713313495,"locality_id":1126008551,"region_id":85682995}],"wof:id":1126008551,"wof:lang_x_official":["est"],"wof:lang_x_spoken":["est"],"wof:lastmodified":1596661922,"wof:name":"Palupera","wof:parent_id":1713313495,"wof:placetype":"locality","wof:population":187,"wof:population_rank":1,"wof:repo":"whosonfirst-data-admin-ee","wof:superseded_by":[],"wof:supersedes":[],"wof:tags":[]},"bbox":[26.34444,58.11917,26.34444,58.11917],"geometry":{"coordinates":[26.34444,58.11917],"type":"Point"}}