{"id":1293609203,"type":"Feature","properties":{"edtf:cessation":"uuuu","edtf:inception":"uuuu","geom:area":0,"geom:area_square_m":0,"geom:bbox":"26.27667,59.35639,26.27667,59.35639","geom:latitude":59.35639,"geom:longitude":26.27667,"gn:admin1_code":"8.0","gn:admin2_code":"661.0","gn:admin3_code":"2744.0","gn:asciiname":"Arupealse","gn:country_code":"EE","gn:dem":86,"gn:feature_class":"P","gn:feature_code":"PPL","gn:geonameid":8619686,"gn:latitude":59.35639,"gn:longitude":26.27667,"gn:modification_date":"2017-11-25","gn:name":"Arupealse","gn:population":0,"gn:timezone":"Europe/Tallinn","iso:country":"EE","lbl:bbox":"26.25667,59.33639,26.29667,59.37639","lbl:max_zoom":18,"lbl:min_zoom":13.5,"mz:hierarchy_label":1,"mz:is_current":1,"mz:min_zoom":12,"name:und_x_variant":["Aru"],"src:geom":"geonames","wof:belongsto":[85683049,102191581,1713313049,85633135,1713305719],"wof:breaches":[],"wof:concordances":{"gn:id":8619686},"wof:country":"EE","wof:geomhash":"d0e8e26ee89a49d3a27104a73279afa6","wof:hierarchy":[{"continent_id":102191581,"country_id":85633135,"county_id":1713305719,"localadmin_id":1713313049,"locality_id":1293609203,"region_id":85683049}],"wof:id":1293609203,"wof:lang_x_official":["est"],"wof:lang_x_spoken":["est"],"wof:lastmodified":1596676674,"wof:name":"Arupealse","wof:parent_id":1713313049,"wof:placetype":"locality","wof:repo":"whosonfirst-data-admin-ee","wof:superseded_by":[],"wof:supersedes":[],"wof:tags":[]},"bbox":[26.27667,59.35639,26.27667,59.35639],"geometry":{"coordinates":[26.27667,59.35639],"type":"Point"}}