{"id":1126003925,"type":"Feature","properties":{"edtf:cessation":"uuuu","edtf:inception":"uuuu","geom:area":0,"geom:area_square_m":0,"geom:bbox":"27.515,58.10611,27.515,58.10611","geom:latitude":58.10611,"geom:longitude":27.515,"gn:country":"EE","gn:fcode":"PPL","gn:population":160,"iso:country":"EE","lbl:bbox":"27.495,58.08611,27.535,58.12611","lbl:latitude":58.10611,"lbl:longitude":27.515,"lbl:max_zoom":18,"lbl:min_zoom":13,"mz:hierarchy_label":1,"mz:is_current":1,"mz:min_zoom":11,"mz:note":"Quattroshapes Point Gazetteer import 20170519","name:bul_x_preferred":["Раигла"],"name:ceb_x_preferred":["Raigla"],"name:eng_x_preferred":["Raigla"],"name:est_x_preferred":["Raigla"],"name:hye_x_preferred":["Ռաիգլա"],"name:nld_x_preferred":["Raigla"],"name:spa_x_preferred":["Raigla"],"name:swe_x_preferred":["Raigla"],"name:ukr_x_preferred":["Раїгла"],"name:und_x_variant":["Myza Raygla"],"name:vol_x_preferred":["Raigla"],"name:vro_x_preferred":["Raigla"],"qs_pg:aaroncc":"EE","qs_pg:gn_country":"EE","qs_pg:gn_fcode":"PPL","qs_pg:gn_id":589180,"qs_pg:gn_pop":160,"qs_pg:name":"Raigla","qs_pg:name_adm0":"Eesti","qs_pg:name_adm1":"Põlvamaa","qs_pg:photos_9k":1,"qs_pg:photos_9r":1,"qs_pg:photos_all":9,"qs_pg:photos_sr":0,"qs_pg:pop_sr":1,"qs_pg:qs_id":915934,"qs_pg:qs_pg_placetype":"locality","qs_pg:qs_pg_placetype_gp":"Town","qs_pg:woe_adm0":23424805,"qs_pg:woe_id":845012,"src:geom":"qs_pg","src:lbl_centroid":"qs_pg","src:population":"geonames","woe:adm0_id":23424805,"woe:name_adm0":"Eesti","woe:name_adm1":"Põlvamaa","woe:placetype":"Town","wof:belongsto":[85682955,102191581,1713312961,85633135,1713305793],"wof:breaches":[],"wof:concordances":{"gn:id":589180,"gp:id":845012,"qs_pg:id":915934,"wd:id":"Q3466571"},"wof:coterminous":[1713312961],"wof:country":"EE","wof:created":1497299817,"wof:geomhash":"29f0358bb77795d0e2473f0ca9bc14db","wof:hierarchy":[{"continent_id":102191581,"country_id":85633135,"county_id":1713305793,"localadmin_id":1713312961,"locality_id":1126003925,"region_id":85682955}],"wof:id":1126003925,"wof:lang_x_official":["est"],"wof:lang_x_spoken":["est"],"wof:lastmodified":1596677005,"wof:name":"Raigla","wof:parent_id":1713312961,"wof:placetype":"locality","wof:population":160,"wof:population_rank":1,"wof:repo":"whosonfirst-data-admin-ee","wof:superseded_by":[],"wof:supersedes":[],"wof:tags":[]},"bbox":[27.515,58.10611,27.515,58.10611],"geometry":{"coordinates":[27.515,58.10611],"type":"Point"}}