{"id":1293762603,"type":"Feature","properties":{"edtf:cessation":"uuuu","edtf:inception":"uuuu","geom:area":0,"geom:area_square_m":0,"geom:bbox":"21.96917,58.47417,21.96917,58.47417","geom:latitude":58.47417,"geom:longitude":21.96917,"gn:admin1_code":"14.0","gn:admin2_code":"714.0","gn:admin3_code":"8270.0","gn:asciiname":"Kuralase","gn:cc2":"EE","gn:country_code":"EE","gn:dem":16,"gn:feature_class":"P","gn:feature_code":"PPL","gn:geonameid":590953,"gn:latitude":58.47417,"gn:longitude":21.96917,"gn:modification_date":"2017-11-25","gn:name":"Kuralase","gn:population":0,"gn:timezone":"Europe/Tallinn","iso:country":"EE","lbl:bbox":"21.94917,58.45417,21.98917,58.49417","lbl:max_zoom":18,"lbl:min_zoom":13.5,"mz:hierarchy_label":1,"mz:is_current":1,"mz:min_zoom":12,"name:deu_x_preferred":["Kuralase"],"name:est_x_preferred":["Kuralase"],"name:fra_x_preferred":["Kuralase"],"name:hye_x_preferred":["Կուռալասե"],"name:pol_x_preferred":["Kuralase"],"name:spa_x_preferred":["Kuralase"],"name:und_x_variant":["Kuralese"],"name:vol_x_preferred":["Kuralase"],"src:geom":"geonames","wof:belongsto":[85682947,102191581,1713308317,85633135,1713305627],"wof:breaches":[],"wof:concordances":{"gn:id":590953,"wk:page":"Kuralase"},"wof:coterminous":[1713307585],"wof:country":"EE","wof:geomhash":"962f8ee54801413410c686993c3221df","wof:hierarchy":[{"continent_id":102191581,"country_id":85633135,"county_id":1713305627,"localadmin_id":1713308317,"locality_id":1293762603,"region_id":85682947}],"wof:id":1293762603,"wof:lang_x_official":["est"],"wof:lang_x_spoken":["est"],"wof:lastmodified":1596674968,"wof:name":"Kuralase","wof:parent_id":1713308317,"wof:placetype":"locality","wof:repo":"whosonfirst-data-admin-ee","wof:superseded_by":[],"wof:supersedes":[],"wof:tags":[]},"bbox":[21.96917,58.47417,21.96917,58.47417],"geometry":{"coordinates":[21.96917,58.47417],"type":"Point"}}