{"id":1327220069,"type":"Feature","properties":{"edtf:cessation":"uuuu","edtf:inception":"uuuu","geom:area":0,"geom:area_square_m":0,"geom:bbox":"24.90083,58.91556,24.90083,58.91556","geom:latitude":58.91556,"geom:longitude":24.90083,"gn:admin1_code":"13.0","gn:admin2_code":"293.0","gn:admin3_code":"2900.0","gn:asciiname":"Nadalama","gn:country_code":"EE","gn:dem":68,"gn:feature_class":"P","gn:feature_code":"PPL","gn:geonameid":795012,"gn:latitude":58.91556,"gn:longitude":24.90083,"gn:modification_date":"2017-11-25","gn:name":"Nadalama","gn:population":0,"gn:timezone":"Europe/Tallinn","iso:country":"EE","lbl:bbox":"24.88083,58.89556,24.92083,58.93556","lbl:max_zoom":18,"lbl:min_zoom":13.5,"mz:hierarchy_label":1,"mz:is_current":1,"mz:min_zoom":12,"src:geom":"geonames","wof:belongsto":[85683013,102191581,1713309717,85633135,1713305713],"wof:breaches":[],"wof:concordances":{"gn:id":795012},"wof:coterminous":[1713311275],"wof:country":"EE","wof:geomhash":"3eb361ae00b93479258068f550a484bf","wof:hierarchy":[{"continent_id":102191581,"country_id":85633135,"county_id":1713305713,"localadmin_id":1713309717,"locality_id":1327220069,"region_id":85683013}],"wof:id":1327220069,"wof:lang_x_official":["est"],"wof:lang_x_spoken":["est"],"wof:lastmodified":1596676747,"wof:name":"Nadalama","wof:parent_id":1713309717,"wof:placetype":"locality","wof:repo":"whosonfirst-data-admin-ee","wof:superseded_by":[],"wof:supersedes":[],"wof:tags":[]},"bbox":[24.90083,58.91556,24.90083,58.91556],"geometry":{"coordinates":[24.90083,58.91556],"type":"Point"}}