{"id":1125957059,"type":"Feature","properties":{"edtf:cessation":"uuuu","edtf:inception":"uuuu","geom:area":0,"geom:area_square_m":0,"geom:bbox":"24.37778,58.89556,24.37778,58.89556","geom:latitude":58.89556,"geom:longitude":24.37778,"gn:country":"EE","gn:fcode":"PPL","gn:population":123,"iso:country":"EE","lbl:bbox":"24.35778,58.87556,24.39778,58.91556","lbl:latitude":58.89556,"lbl:longitude":24.37778,"lbl:max_zoom":18,"lbl:min_zoom":13,"mz:hierarchy_label":1,"mz:is_current":1,"mz:min_zoom":11,"mz:note":"Quattroshapes Point Gazetteer import 20170519","name:ceb_x_preferred":["Sõtke"],"name:eng_x_preferred":["Sõtke"],"name:est_x_preferred":["Sõtke"],"name:fra_x_preferred":["Sõtke"],"name:hye_x_preferred":["Սիտկե"],"name:nld_x_preferred":["Sõtke"],"name:pol_x_preferred":["Sõtke"],"name:sco_x_preferred":["Sõtke"],"name:spa_x_preferred":["Sõtke"],"name:und_x_variant":["Sotküla Asundus"],"name:vol_x_preferred":["Sõtke"],"qs_pg:aaroncc":"EE","qs_pg:gn_country":"EE","qs_pg:gn_fcode":"PPL","qs_pg:gn_id":588568,"qs_pg:gn_pop":123,"qs_pg:name":"Sõtke","qs_pg:name_adm0":"Eesti","qs_pg:name_adm1":"Raplamaa","qs_pg:photos_9r":0,"qs_pg:photos_sr":0,"qs_pg:pop_sr":1,"qs_pg:qs_id":406360,"qs_pg:qs_pg_placetype":"locality","qs_pg:qs_pg_placetype_gp":"Town","qs_pg:woe_adm0":23424805,"qs_pg:woe_id":845615,"src:geom":"qs_pg","src:lbl_centroid":"qs_pg","src:population":"geonames","woe:adm0_id":23424805,"woe:name_adm0":"Eesti","woe:name_adm1":"Raplamaa","woe:placetype":"Town","wof:belongsto":[85683013,102191581,1713311403,85633135,1713305747],"wof:breaches":[],"wof:concordances":{"gn:id":588568,"gp:id":845615,"qs_pg:id":406360,"wd:id":"Q2647162"},"wof:coterminous":[1713311403],"wof:country":"EE","wof:created":1497297653,"wof:geomhash":"94a33e5a9545e7db9c6696bc9b1663e0","wof:hierarchy":[{"continent_id":102191581,"country_id":85633135,"county_id":1713305747,"localadmin_id":1713311403,"locality_id":1125957059,"region_id":85683013}],"wof:id":1125957059,"wof:lang_x_official":["est"],"wof:lang_x_spoken":["est"],"wof:lastmodified":1596662849,"wof:name":"Sõtke","wof:parent_id":1713311403,"wof:placetype":"locality","wof:population":123,"wof:population_rank":1,"wof:repo":"whosonfirst-data-admin-ee","wof:superseded_by":[],"wof:supersedes":[],"wof:tags":[]},"bbox":[24.37778,58.89556,24.37778,58.89556],"geometry":{"coordinates":[24.37778,58.89556],"type":"Point"}}