{"id":1226653341,"type":"Feature","properties":{"edtf:cessation":"uuuu","edtf:inception":"uuuu","geom:area":0,"geom:area_square_m":0,"geom:bbox":"27.24639,59.43389,27.24639,59.43389","geom:latitude":59.43389,"geom:longitude":27.24639,"gn:admin1_code":"3.0","gn:admin2_code":"803.0","gn:admin3_code":"7348.0","gn:asciiname":"Ontika-Saka","gn:country_code":"EE","gn:dem":58,"gn:feature_class":"P","gn:feature_code":"PPL","gn:geonameid":588841,"gn:latitude":59.43389,"gn:longitude":27.24639,"gn:modification_date":"2017-11-25","gn:name":"Ontika-Saka","gn:population":0,"gn:timezone":"Europe/Tallinn","iso:country":"EE","lbl:bbox":"27.22639,59.41389,27.26639,59.45389","lbl:max_zoom":18,"lbl:min_zoom":13.5,"mz:hierarchy_label":1,"mz:is_current":1,"mz:min_zoom":12,"name:und_x_variant":["Saka-Ontika","Ontika-Saka"],"src:geom":"geonames","wof:belongsto":[85683059,102191581,1713306779,85633135,1713305783],"wof:breaches":[],"wof:concordances":{"gn:id":588841},"wof:country":"EE","wof:geomhash":"16c8fb024637863855e01c0914e58424","wof:hierarchy":[{"continent_id":102191581,"country_id":85633135,"county_id":1713305783,"localadmin_id":1713306779,"locality_id":1226653341,"region_id":85683059}],"wof:id":1226653341,"wof:lang_x_official":["est"],"wof:lang_x_spoken":["est"],"wof:lastmodified":1596676911,"wof:name":"Ontika-Saka","wof:parent_id":1713306779,"wof:placetype":"locality","wof:repo":"whosonfirst-data-admin-ee","wof:superseded_by":[],"wof:supersedes":[],"wof:tags":[]},"bbox":[27.24639,59.43389,27.24639,59.43389],"geometry":{"coordinates":[27.24639,59.43389],"type":"Point"}}