{"id":1276137071,"type":"Feature","properties":{"edtf:cessation":"uuuu","edtf:inception":"uuuu","geom:area":0,"geom:area_square_m":0,"geom:bbox":"24.58311,59.43952,24.58311,59.43952","geom:latitude":59.43952,"geom:longitude":24.58311,"gn:admin1_code":"1.0","gn:admin2_code":"784.0","gn:admin3_code":"176.0","gn:asciiname":"Iye","gn:country_code":"EE","gn:dem":10,"gn:feature_class":"P","gn:feature_code":"PPL","gn:geonameid":591928,"gn:latitude":59.43952,"gn:longitude":24.58311,"gn:modification_date":"2017-11-25","gn:name":"Iye","gn:population":0,"gn:timezone":"Europe/Tallinn","iso:country":"EE","lbl:bbox":"24.56311,59.41952,24.60311,59.45952","lbl:max_zoom":18,"lbl:min_zoom":13.5,"mz:hierarchy_label":1,"mz:is_current":1,"mz:is_funky":1,"mz:min_zoom":12,"name:und_x_variant":["Jõe","Jõeküla"],"src:geom":"geonames","wof:belongsto":[85683055,102191581,1713313501,85633135,1713305645],"wof:breaches":[],"wof:concordances":{"gn:id":591928},"wof:country":"EE","wof:geomhash":"1d6cc854bf79d61756a9941797f08adf","wof:hierarchy":[{"continent_id":102191581,"country_id":85633135,"county_id":1713305645,"localadmin_id":1713313501,"locality_id":1276137071,"region_id":85683055}],"wof:id":1276137071,"wof:lang_x_official":["est"],"wof:lang_x_spoken":["est"],"wof:lastmodified":1596663516,"wof:name":"Iye","wof:parent_id":1713313501,"wof:placetype":"locality","wof:repo":"whosonfirst-data-admin-ee","wof:superseded_by":[],"wof:supersedes":[],"wof:tags":[]},"bbox":[24.58311,59.43952,24.58311,59.43952],"geometry":{"coordinates":[24.58311,59.43952],"type":"Point"}}