{"id":1343764139,"type":"Feature","properties":{"edtf:cessation":"uuuu","edtf:inception":"uuuu","geom:area":0,"geom:area_square_m":0,"geom:bbox":"27.39056,59.11222,27.39056,59.11222","geom:latitude":59.11222,"geom:longitude":27.39056,"gn:admin1_code":"3.0","gn:admin2_code":"130.0","gn:admin3_code":"9075.0","gn:asciiname":"Varesmetsa","gn:cc2":"EE","gn:country_code":"EE","gn:dem":58,"gn:feature_class":"P","gn:feature_code":"PPL","gn:geonameid":587751,"gn:latitude":59.11222,"gn:longitude":27.39056,"gn:modification_date":"2017-11-25","gn:name":"Varesmetsa","gn:population":0,"gn:timezone":"Europe/Tallinn","iso:country":"EE","lbl:bbox":"27.37056,59.09222,27.41056,59.13222","lbl:max_zoom":18,"lbl:min_zoom":13.5,"mz:hierarchy_label":1,"mz:is_current":1,"mz:min_zoom":12,"name:deu_x_preferred":["Varesmetsa"],"name:est_x_preferred":["Varesmetsa"],"name:fas_x_preferred":["ورسمتسا"],"name:fra_x_preferred":["Varesmetsa"],"name:hye_x_preferred":["Վառեսմեցա"],"name:nld_x_preferred":["Varesmetsa"],"name:pol_x_preferred":["Varesmetsa"],"name:spa_x_preferred":["Varesmetsa"],"name:und_x_variant":["Taga-Varesmetsa"],"name:vol_x_preferred":["Varesmetsa"],"src:geom":"geonames","wof:belongsto":[85683059,102191581,1713311863,85633135,1713305693],"wof:breaches":[],"wof:concordances":{"gn:id":587751,"wk:page":"Varesmetsa"},"wof:coterminous":[1713311863],"wof:country":"EE","wof:geomhash":"0ed1c043a2aa5af40a73355fc7b5ca9f","wof:hierarchy":[{"continent_id":102191581,"country_id":85633135,"county_id":1713305693,"localadmin_id":1713311863,"locality_id":1343764139,"region_id":85683059}],"wof:id":1343764139,"wof:lang_x_official":["est"],"wof:lang_x_spoken":["est"],"wof:lastmodified":1596660736,"wof:name":"Varesmetsa","wof:parent_id":1713311863,"wof:placetype":"locality","wof:repo":"whosonfirst-data-admin-ee","wof:superseded_by":[],"wof:supersedes":[],"wof:tags":[]},"bbox":[27.39056,59.11222,27.39056,59.11222],"geometry":{"coordinates":[27.39056,59.11222],"type":"Point"}}