{"id":1327414987,"type":"Feature","properties":{"edtf:cessation":"uuuu","edtf:inception":"uuuu","geom:area":0,"geom:area_square_m":0,"geom:bbox":"24.91861,58.50528,24.91861,58.50528","geom:latitude":58.50528,"geom:longitude":24.91861,"gn:admin1_code":"11.0","gn:admin2_code":"809.0","gn:admin3_code":"8269.0","gn:asciiname":"Tohkuse","gn:country_code":"EE","gn:dem":28,"gn:feature_class":"P","gn:feature_code":"PPL","gn:geonameid":588417,"gn:latitude":58.50528,"gn:longitude":24.91861,"gn:modification_date":"2017-11-25","gn:name":"Tohkuse","gn:population":0,"gn:timezone":"Europe/Tallinn","iso:country":"EE","lbl:bbox":"24.89861,58.48528,24.93861,58.52528","lbl:max_zoom":18,"lbl:min_zoom":13.5,"mz:hierarchy_label":1,"mz:is_current":1,"mz:min_zoom":12,"name:und_x_variant":["Tahkuse","Takhkuse","Tohkuse"],"src:geom":"geonames","wof:belongsto":[85682981,102191581,1713313499,85633135,1713305731],"wof:breaches":[],"wof:concordances":{"gn:id":588417},"wof:country":"EE","wof:geomhash":"19e31fd43c3380ef204b4e14ef3ff759","wof:hierarchy":[{"continent_id":102191581,"country_id":85633135,"county_id":1713305731,"localadmin_id":1713313499,"locality_id":1327414987,"region_id":85682981}],"wof:id":1327414987,"wof:lang_x_official":["est"],"wof:lang_x_spoken":["est"],"wof:lastmodified":1596663391,"wof:name":"Tohkuse","wof:parent_id":1713313499,"wof:placetype":"locality","wof:repo":"whosonfirst-data-admin-ee","wof:superseded_by":[],"wof:supersedes":[],"wof:tags":[]},"bbox":[24.91861,58.50528,24.91861,58.50528],"geometry":{"coordinates":[24.91861,58.50528],"type":"Point"}}