{"id":1125872391,"type":"Feature","properties":{"edtf:cessation":"uuuu","edtf:inception":"uuuu","geom:area":0,"geom:area_square_m":0,"geom:bbox":"24.79278,59.37667,24.79278,59.37667","geom:latitude":59.37667,"geom:longitude":24.79278,"gn:country":"EE","gn:fcode":"PPL","gn:population":190,"iso:country":"EE","lbl:bbox":"24.77278,59.35667,24.81278,59.39667","lbl:latitude":59.37667,"lbl:longitude":24.79278,"lbl:max_zoom":18,"lbl:min_zoom":13,"mz:hierarchy_label":1,"mz:is_current":1,"mz:min_zoom":11,"mz:note":"Quattroshapes Point Gazetteer import 20170519","name:ceb_x_preferred":["Järveküla"],"name:eng_x_preferred":["Järveküla"],"name:est_x_preferred":["Järveküla"],"name:fra_x_preferred":["Järveküla"],"name:hye_x_preferred":["Յեռվեկյուլա"],"name:nld_x_preferred":["Järveküla"],"name:pol_x_preferred":["Järveküla"],"name:spa_x_preferred":["Järveküla"],"name:swe_x_preferred":["Järveküla"],"name:und_x_variant":["Yarvekyulya"],"name:urd_x_preferred":["جاروکولا، حرجو کاؤنٹی"],"name:urd_x_variant":["جاروکولا"],"name:vol_x_preferred":["Järveküla"],"qs_pg:aaroncc":"EE","qs_pg:gn_country":"EE","qs_pg:gn_fcode":"PPL","qs_pg:gn_id":591951,"qs_pg:gn_pop":190,"qs_pg:name":"Järveküla","qs_pg:name_adm0":"Eesti","qs_pg:name_adm1":"Harjumaa","qs_pg:photos_9k":1,"qs_pg:photos_9r":2,"qs_pg:photos_all":34,"qs_pg:photos_sr":0,"qs_pg:pop_sr":1,"qs_pg:qs_id":110965,"qs_pg:qs_pg_placetype":"locality","qs_pg:qs_pg_placetype_gp":"Town","qs_pg:woe_adm0":23424805,"qs_pg:woe_id":842420,"src:geom":"qs_pg","src:lbl_centroid":"qs_pg","src:population":"geonames","woe:adm0_id":23424805,"woe:name_adm0":"Eesti","woe:name_adm1":"Harjumaa","woe:placetype":"Town","wof:belongsto":[85683055,102191581,1713306345,85633135,1713305683],"wof:breaches":[],"wof:concordances":{"gn:id":591951,"gp:id":842420,"qs_pg:id":110965,"wd:id":"Q2113694"},"wof:coterminous":[1713306345],"wof:country":"EE","wof:created":1497294365,"wof:geomhash":"fef005bb8c94491b7769b7225f437035","wof:hierarchy":[{"continent_id":102191581,"country_id":85633135,"county_id":1713305683,"localadmin_id":1713306345,"locality_id":1125872391,"region_id":85683055}],"wof:id":1125872391,"wof:lang_x_official":["est"],"wof:lang_x_spoken":["est"],"wof:lastmodified":1596661482,"wof:name":"Järveküla","wof:parent_id":1713306345,"wof:placetype":"locality","wof:population":190,"wof:population_rank":1,"wof:repo":"whosonfirst-data-admin-ee","wof:superseded_by":[],"wof:supersedes":[],"wof:tags":[]},"bbox":[24.79278,59.37667,24.79278,59.37667],"geometry":{"coordinates":[24.79278,59.37667],"type":"Point"}}