{"id":1310181031,"type":"Feature","properties":{"edtf:cessation":"uuuu","edtf:inception":"uuuu","geom:area":0,"geom:area_square_m":0,"geom:bbox":"26.96833,58.45472,26.96833,58.45472","geom:latitude":58.45472,"geom:longitude":26.96833,"gn:admin1_code":"18.0","gn:admin2_code":"796.0","gn:admin3_code":"7988.0","gn:asciiname":"Vilussaare","gn:country_code":"EE","gn:dem":57,"gn:feature_class":"P","gn:feature_code":"PPL","gn:geonameid":794085,"gn:latitude":58.45472,"gn:longitude":26.96833,"gn:modification_date":"2017-11-25","gn:name":"Vilussaare","gn:population":0,"gn:timezone":"Europe/Tallinn","iso:country":"EE","lbl:bbox":"26.94833,58.43472,26.98833,58.47472","lbl:max_zoom":18,"lbl:min_zoom":13.5,"mz:hierarchy_label":1,"mz:is_current":1,"mz:min_zoom":12,"src:geom":"geonames","wof:belongsto":[85683009,102191581,1713314567,85633135,1713305659],"wof:breaches":[],"wof:concordances":{"gn:id":794085},"wof:coterminous":[1713314157],"wof:country":"EE","wof:geomhash":"0f3dc05f1f3417201f24e69da5ebab1b","wof:hierarchy":[{"continent_id":102191581,"country_id":85633135,"county_id":1713305659,"localadmin_id":1713314567,"locality_id":1310181031,"region_id":85683009}],"wof:id":1310181031,"wof:lang_x_official":["est"],"wof:lang_x_spoken":["est"],"wof:lastmodified":1596676472,"wof:name":"Vilussaare","wof:parent_id":1713314567,"wof:placetype":"locality","wof:repo":"whosonfirst-data-admin-ee","wof:superseded_by":[],"wof:supersedes":[],"wof:tags":[]},"bbox":[26.96833,58.45472,26.96833,58.45472],"geometry":{"coordinates":[26.96833,58.45472],"type":"Point"}}