{"id":1276154995,"type":"Feature","properties":{"edtf:cessation":"uuuu","edtf:inception":"uuuu","geom:area":0,"geom:area_square_m":0,"geom:bbox":"26.6075,58.53778,26.6075,58.53778","geom:latitude":58.53778,"geom:longitude":26.6075,"gn:admin1_code":"18.0","gn:admin2_code":"796.0","gn:admin3_code":"9461.0","gn:asciiname":"Kaste","gn:country_code":"EE","gn:dem":52,"gn:feature_class":"P","gn:feature_code":"PPL","gn:geonameid":8618803,"gn:latitude":58.53778,"gn:longitude":26.6075,"gn:modification_date":"2017-11-25","gn:name":"Kaste","gn:population":0,"gn:timezone":"Europe/Tallinn","iso:country":"EE","lbl:bbox":"26.5875,58.51778,26.6275,58.55778","lbl:max_zoom":18,"lbl:min_zoom":13.5,"mz:hierarchy_label":1,"mz:is_current":1,"mz:min_zoom":12,"name:und_x_variant":["Voldi"],"src:geom":"geonames","wof:belongsto":[85683009,102191581,1713313673,85633135,1713305659],"wof:breaches":[],"wof:concordances":{"gn:id":8618803},"wof:country":"EE","wof:geomhash":"23553245f8e7f64b7706318a5fa44c55","wof:hierarchy":[{"continent_id":102191581,"country_id":85633135,"county_id":1713305659,"localadmin_id":1713313673,"locality_id":1276154995,"region_id":85683009}],"wof:id":1276154995,"wof:lang_x_official":["est"],"wof:lang_x_spoken":["est"],"wof:lastmodified":1596676468,"wof:name":"Kaste","wof:parent_id":1713313673,"wof:placetype":"locality","wof:repo":"whosonfirst-data-admin-ee","wof:superseded_by":[],"wof:supersedes":[],"wof:tags":[]},"bbox":[26.6075,58.53778,26.6075,58.53778],"geometry":{"coordinates":[26.6075,58.53778],"type":"Point"}}