{"id":1360079691,"type":"Feature","properties":{"edtf:cessation":"uuuu","edtf:inception":"uuuu","geom:area":0,"geom:area_square_m":0,"geom:bbox":"23.5325,59.07944,23.5325,59.07944","geom:latitude":59.07944,"geom:longitude":23.5325,"gn:admin1_code":"7.0","gn:admin2_code":"441.0","gn:admin3_code":"1760.0","gn:asciiname":"Hara","gn:cc2":"EE","gn:country_code":"EE","gn:dem":9,"gn:feature_class":"P","gn:feature_code":"PPL","gn:geonameid":592185,"gn:latitude":59.07944,"gn:longitude":23.5325,"gn:modification_date":"2017-11-25","gn:name":"Hara","gn:population":0,"gn:timezone":"Europe/Tallinn","iso:country":"EE","lbl:bbox":"23.5125,59.05944,23.5525,59.09944","lbl:max_zoom":18,"lbl:min_zoom":13.5,"mz:hierarchy_label":1,"mz:is_current":1,"mz:min_zoom":12,"name:deu_x_preferred":["Hara"],"name:est_x_preferred":["Hara"],"name:hye_x_preferred":["Հառա"],"name:nld_x_preferred":["Hara"],"name:pol_x_preferred":["Hara"],"name:spa_x_preferred":["Hara"],"name:swe_x_preferred":["Harga"],"name:ukr_x_preferred":["Гара"],"name:und_x_variant":["Khar’ya","Kharga","Khara","Harja"],"name:vol_x_preferred":["Hara"],"src:geom":"geonames","wof:belongsto":[85683001,102191581,1713308727,85633135,1713305701],"wof:breaches":[],"wof:concordances":{"gn:id":592185,"wk:page":"Hara%2C_L%C3%A4%C3%A4ne_County"},"wof:coterminous":[1713308727],"wof:country":"EE","wof:geomhash":"791d8e8463e830f4e42bdcb4a399bd2d","wof:hierarchy":[{"continent_id":102191581,"country_id":85633135,"county_id":1713305701,"localadmin_id":1713308727,"locality_id":1360079691,"region_id":85683001}],"wof:id":1360079691,"wof:lang_x_official":["est"],"wof:lang_x_spoken":["est"],"wof:lastmodified":1596677428,"wof:name":"Hara","wof:parent_id":1713308727,"wof:placetype":"locality","wof:repo":"whosonfirst-data-admin-ee","wof:superseded_by":[],"wof:supersedes":[],"wof:tags":[]},"bbox":[23.5325,59.07944,23.5325,59.07944],"geometry":{"coordinates":[23.5325,59.07944],"type":"Point"}}