{"id":1259488079,"type":"Feature","properties":{"edtf:cessation":"uuuu","edtf:inception":"uuuu","geom:area":0,"geom:area_square_m":0,"geom:bbox":"26.57611,58.79611,26.57611,58.79611","geom:latitude":58.79611,"geom:longitude":26.57611,"gn:admin1_code":"5.0","gn:admin2_code":"247.0","gn:admin3_code":"5954.0","gn:asciiname":"Palupere","gn:country_code":"EE","gn:dem":94,"gn:feature_class":"P","gn:feature_code":"PPL","gn:geonameid":589636,"gn:latitude":58.79611,"gn:longitude":26.57611,"gn:modification_date":"2017-11-25","gn:name":"Palupere","gn:population":0,"gn:timezone":"Europe/Tallinn","iso:country":"EE","lbl:bbox":"26.55611,58.77611,26.59611,58.81611","lbl:max_zoom":18,"lbl:min_zoom":13.5,"mz:hierarchy_label":1,"mz:is_current":1,"mz:min_zoom":12,"name:est_x_preferred":["Palupere"],"name:fra_x_preferred":["Palupere"],"name:hye_x_preferred":["Պալուպեռե"],"name:spa_x_preferred":["Palupere"],"name:ukr_x_preferred":["Палупере"],"name:vol_x_preferred":["Palupere"],"src:geom":"geonames","wof:belongsto":[85683009,102191581,1713312253,85633135,1713305767],"wof:breaches":[],"wof:concordances":{"gn:id":589636,"wk:page":"Palupere"},"wof:coterminous":[1713312253],"wof:country":"EE","wof:geomhash":"ffa3b9fa5a31124d3b7bbdba0c3d9b6f","wof:hierarchy":[{"continent_id":102191581,"country_id":85633135,"county_id":1713305767,"localadmin_id":1713312253,"locality_id":1259488079,"region_id":85683009}],"wof:id":1259488079,"wof:lang_x_official":["est"],"wof:lang_x_spoken":["est"],"wof:lastmodified":1596676570,"wof:name":"Palupere","wof:parent_id":1713312253,"wof:placetype":"locality","wof:repo":"whosonfirst-data-admin-ee","wof:superseded_by":[],"wof:supersedes":[],"wof:tags":[]},"bbox":[26.57611,58.79611,26.57611,58.79611],"geometry":{"coordinates":[26.57611,58.79611],"type":"Point"}}