{"id":1276982171,"type":"Feature","properties":{"edtf:cessation":"uuuu","edtf:inception":"uuuu","geom:area":0,"geom:area_square_m":0,"geom:bbox":"27.01056,59.26417,27.01056,59.26417","geom:latitude":59.26417,"geom:longitude":27.01056,"gn:admin1_code":"3.0","gn:admin2_code":"442.0","gn:admin3_code":"5574.0","gn:asciiname":"Oandu","gn:country_code":"EE","gn:dem":66,"gn:feature_class":"P","gn:feature_code":"PPL","gn:geonameid":793433,"gn:latitude":59.26417,"gn:longitude":27.01056,"gn:modification_date":"2017-11-25","gn:name":"Oandu","gn:population":0,"gn:timezone":"Europe/Tallinn","iso:country":"EE","lbl:bbox":"26.99056,59.24417,27.03056,59.28417","lbl:max_zoom":18,"lbl:min_zoom":13.5,"mz:hierarchy_label":1,"mz:is_current":1,"mz:min_zoom":12,"name:deu_x_preferred":["Oandu"],"name:est_x_preferred":["Oandu"],"name:hye_x_preferred":["Օանդու"],"name:pol_x_preferred":["Oandu"],"name:spa_x_preferred":["Oandu"],"name:vol_x_preferred":["Oandu"],"src:geom":"geonames","wof:belongsto":[85683059,102191581,1713311807,85633135,1713305695],"wof:breaches":[],"wof:concordances":{"gn:id":793433,"wk:page":"Oandu%2C_Ida-Viru_County"},"wof:coterminous":[1713311807],"wof:country":"EE","wof:geomhash":"7e5491100898a8c72f7dd0d9ffecafce","wof:hierarchy":[{"continent_id":102191581,"country_id":85633135,"county_id":1713305695,"localadmin_id":1713311807,"locality_id":1276982171,"region_id":85683059}],"wof:id":1276982171,"wof:lang_x_official":["est"],"wof:lang_x_spoken":["est"],"wof:lastmodified":1596660810,"wof:name":"Oandu","wof:parent_id":1713311807,"wof:placetype":"locality","wof:repo":"whosonfirst-data-admin-ee","wof:superseded_by":[],"wof:supersedes":[],"wof:tags":[]},"bbox":[27.01056,59.26417,27.01056,59.26417],"geometry":{"coordinates":[27.01056,59.26417],"type":"Point"}}