{"id":1293179251,"type":"Feature","properties":{"edtf:cessation":"uuuu","edtf:inception":"uuuu","geom:area":0,"geom:area_square_m":0,"geom:bbox":"24.76667,58.68333,24.76667,58.68333","geom:latitude":58.68333,"geom:longitude":24.76667,"gn:admin1_code":"11.0","gn:admin2_code":"638.0","gn:admin3_code":"2545.0","gn:asciiname":"Allika","gn:country_code":"EE","gn:dem":51,"gn:feature_class":"P","gn:feature_code":"PPL","gn:geonameid":592539,"gn:latitude":58.68333,"gn:longitude":24.76667,"gn:modification_date":"2017-11-25","gn:name":"Allika","gn:population":0,"gn:timezone":"Europe/Tallinn","iso:country":"EE","lbl:bbox":"24.74667,58.66333,24.78667,58.70333","lbl:max_zoom":18,"lbl:min_zoom":13.5,"mz:hierarchy_label":1,"mz:is_current":1,"mz:min_zoom":12,"name:deu_x_preferred":["Allika"],"name:est_x_preferred":["Allika"],"name:hye_x_preferred":["Ալլիկա"],"name:nld_x_preferred":["Allika"],"name:pol_x_preferred":["Allika"],"name:sco_x_preferred":["Allika"],"name:ukr_x_preferred":["Алліка"],"name:vol_x_preferred":["Allika"],"src:geom":"geonames","wof:belongsto":[85682981,102191581,1713312613,85633135,1713305733],"wof:breaches":[],"wof:concordances":{"gn:id":592539},"wof:country":"EE","wof:geomhash":"2dd4ef2d43c6277a80ab195baf1170ac","wof:hierarchy":[{"continent_id":102191581,"country_id":85633135,"county_id":1713305733,"localadmin_id":1713312613,"locality_id":1293179251,"region_id":85682981}],"wof:id":1293179251,"wof:lang_x_official":["est"],"wof:lang_x_spoken":["est"],"wof:lastmodified":1596663426,"wof:name":"Allika","wof:parent_id":1713312613,"wof:placetype":"locality","wof:repo":"whosonfirst-data-admin-ee","wof:superseded_by":[],"wof:supersedes":[],"wof:tags":[]},"bbox":[24.76667,58.68333,24.76667,58.68333],"geometry":{"coordinates":[24.76667,58.68333],"type":"Point"}}