{"id":1226756455,"type":"Feature","properties":{"edtf:cessation":"uuuu","edtf:inception":"uuuu","geom:area":0,"geom:area_square_m":0,"geom:bbox":"22.92258,58.93299,22.92258,58.93299","geom:latitude":58.93299,"geom:longitude":22.92258,"gn:admin1_code":"2.0","gn:admin2_code":"205.0","gn:admin3_code":"1807.0","gn:asciiname":"Tempa","gn:country_code":"EE","gn:dem":13,"gn:feature_class":"P","gn:feature_code":"PPL","gn:geonameid":588306,"gn:latitude":58.93299,"gn:longitude":22.92258,"gn:modification_date":"2018-03-06","gn:name":"Tempa","gn:population":0,"gn:timezone":"Europe/Tallinn","iso:country":"EE","lbl:bbox":"22.90258,58.91299,22.94258,58.95299","lbl:max_zoom":18,"lbl:min_zoom":13.5,"mz:hierarchy_label":1,"mz:is_current":1,"mz:min_zoom":12,"name:ces_x_preferred":["Tempa"],"name:deu_x_preferred":["Tempa"],"name:est_x_preferred":["Tempa"],"name:hye_x_preferred":["Տեմպա"],"name:pol_x_preferred":["Tempa"],"name:spa_x_preferred":["Tempa"],"name:srp_x_preferred":["Темпа"],"name:swe_x_preferred":["Tempa"],"name:vol_x_preferred":["Tempa"],"name:zho_x_preferred":["滕帕"],"src:geom":"geonames","wof:belongsto":[85682989,102191581,1713310647,85633135,1713305629],"wof:breaches":[],"wof:concordances":{"gn:id":588306,"wk:page":"Tempa%2C_Estonia"},"wof:coterminous":[1713310763],"wof:country":"EE","wof:geomhash":"151c7a8170e25db3546102736b30a153","wof:hierarchy":[{"continent_id":102191581,"country_id":85633135,"county_id":1713305629,"localadmin_id":1713310647,"locality_id":1226756455,"region_id":85682989}],"wof:id":1226756455,"wof:lang_x_official":["est"],"wof:lang_x_spoken":["est"],"wof:lastmodified":1596670020,"wof:name":"Tempa","wof:parent_id":1713310647,"wof:placetype":"locality","wof:repo":"whosonfirst-data-admin-ee","wof:superseded_by":[],"wof:supersedes":[],"wof:tags":[]},"bbox":[22.92258,58.93299,22.92258,58.93299],"geometry":{"coordinates":[22.92258,58.93299],"type":"Point"}}