{"id":1276547683,"type":"Feature","properties":{"edtf:cessation":"uuuu","edtf:inception":"uuuu","geom:area":0,"geom:area_square_m":0,"geom:bbox":"25.37333,58.97667,25.37333,58.97667","geom:latitude":58.97667,"geom:longitude":25.37333,"gn:admin1_code":"4.0","gn:admin2_code":"834.0","gn:admin3_code":"7452.0","gn:asciiname":"Saueaugu","gn:country_code":"EE","gn:dem":83,"gn:feature_class":"P","gn:feature_code":"PPL","gn:geonameid":793309,"gn:latitude":58.97667,"gn:longitude":25.37333,"gn:modification_date":"2017-11-25","gn:name":"Saueaugu","gn:population":0,"gn:timezone":"Europe/Tallinn","iso:country":"EE","lbl:bbox":"25.35333,58.95667,25.39333,58.99667","lbl:max_zoom":18,"lbl:min_zoom":13.5,"mz:hierarchy_label":1,"mz:is_current":1,"mz:min_zoom":12,"name:est_x_preferred":["Saueaugu"],"name:hye_x_preferred":["Սաուեաուգու"],"name:pol_x_preferred":["Saueaugu"],"name:spa_x_preferred":["Saueaugu"],"name:ukr_x_preferred":["Сауеауґу"],"name:vol_x_preferred":["Saueaugu"],"src:geom":"geonames","wof:belongsto":[85683031,102191581,1713313425,85633135,1713305773],"wof:breaches":[],"wof:concordances":{"gn:id":793309,"wk:page":"Saueaugu"},"wof:coterminous":[1713313425],"wof:country":"EE","wof:geomhash":"9f0c5ef48b787761df2aebed1b4d5019","wof:hierarchy":[{"continent_id":102191581,"country_id":85633135,"county_id":1713305773,"localadmin_id":1713313425,"locality_id":1276547683,"region_id":85683031}],"wof:id":1276547683,"wof:lang_x_official":["est"],"wof:lang_x_spoken":["est"],"wof:lastmodified":1596677993,"wof:name":"Saueaugu","wof:parent_id":1713313425,"wof:placetype":"locality","wof:repo":"whosonfirst-data-admin-ee","wof:superseded_by":[],"wof:supersedes":[],"wof:tags":[]},"bbox":[25.37333,58.97667,25.37333,58.97667],"geometry":{"coordinates":[25.37333,58.97667],"type":"Point"}}