{"id":1360249305,"type":"Feature","properties":{"edtf:cessation":"uuuu","edtf:inception":"uuuu","geom:area":0,"geom:area_square_m":0,"geom:bbox":"27.00444,57.88,27.00444,57.88","geom:latitude":57.88,"geom:longitude":27.00444,"gn:admin1_code":"21.0","gn:admin2_code":"917.0","gn:admin3_code":"4519.0","gn:asciiname":"Korgomaee","gn:country_code":"EE","gn:dem":80,"gn:feature_class":"P","gn:feature_code":"PPL","gn:geonameid":8620232,"gn:latitude":57.88,"gn:longitude":27.00444,"gn:modification_date":"2017-11-25","gn:name":"Korgõmäe","gn:population":0,"gn:timezone":"Europe/Tallinn","iso:country":"EE","lbl:bbox":"26.98444,57.86,27.02444,57.9","lbl:max_zoom":18,"lbl:min_zoom":13.5,"mz:hierarchy_label":1,"mz:is_current":1,"mz:min_zoom":12,"name:und_x_variant":["Korgõmäe","Kõrgemäe"],"src:geom":"geonames","wof:belongsto":[85682937,102191581,1713316475,85633135,1713305633],"wof:breaches":[],"wof:concordances":{"gn:id":8620232},"wof:country":"EE","wof:geomhash":"332abe0c3cd2b5aa64dfd028640fe3cc","wof:hierarchy":[{"continent_id":102191581,"country_id":85633135,"county_id":1713305633,"localadmin_id":1713316475,"locality_id":1360249305,"region_id":85682937}],"wof:id":1360249305,"wof:lang_x_official":["est"],"wof:lang_x_spoken":["est"],"wof:lastmodified":1596660396,"wof:name":"Korgomaee","wof:parent_id":1713316475,"wof:placetype":"locality","wof:repo":"whosonfirst-data-admin-ee","wof:superseded_by":[],"wof:supersedes":[],"wof:tags":[]},"bbox":[27.00444,57.88,27.00444,57.88],"geometry":{"coordinates":[27.00444,57.88],"type":"Point"}}