{"id":1293758821,"type":"Feature","properties":{"edtf:cessation":"uuuu","edtf:inception":"uuuu","geom:area":0,"geom:area_square_m":0,"geom:bbox":"26.44417,58.08139,26.44417,58.08139","geom:latitude":58.08139,"geom:longitude":26.44417,"gn:admin1_code":"19.0","gn:admin2_code":"557.0","gn:admin3_code":"6060.0","gn:asciiname":"Kirikukuela","gn:country_code":"EE","gn:dem":113,"gn:feature_class":"P","gn:feature_code":"PPL","gn:geonameid":591359,"gn:latitude":58.08139,"gn:longitude":26.44417,"gn:modification_date":"2017-11-25","gn:name":"Kirikuküla","gn:population":0,"gn:timezone":"Europe/Tallinn","iso:country":"EE","lbl:bbox":"26.42417,58.06139,26.46417,58.10139","lbl:max_zoom":18,"lbl:min_zoom":13.5,"mz:hierarchy_label":1,"mz:is_current":1,"mz:min_zoom":12,"name:und_x_variant":["Kiriku","Kirikuküla"],"src:geom":"geonames","wof:belongsto":[85682941,102191581,1713309833,85633135,1713305759],"wof:breaches":[],"wof:concordances":{"gn:id":591359},"wof:country":"EE","wof:geomhash":"f442ab2aea4d6ed60760686e2672f60f","wof:hierarchy":[{"continent_id":102191581,"country_id":85633135,"county_id":1713305759,"localadmin_id":1713309833,"locality_id":1293758821,"region_id":85682941}],"wof:id":1293758821,"wof:lang_x_official":["est"],"wof:lang_x_spoken":["est"],"wof:lastmodified":1596661880,"wof:name":"Kirikukuela","wof:parent_id":1713309833,"wof:placetype":"locality","wof:repo":"whosonfirst-data-admin-ee","wof:superseded_by":[],"wof:supersedes":[],"wof:tags":[]},"bbox":[26.44417,58.08139,26.44417,58.08139],"geometry":{"coordinates":[26.44417,58.08139],"type":"Point"}}