{"id":1209473879,"type":"Feature","properties":{"edtf:cessation":"uuuu","edtf:inception":"uuuu","geom:area":0,"geom:area_square_m":0,"geom:bbox":"26.53111,57.69639,26.53111,57.69639","geom:latitude":57.69639,"geom:longitude":26.53111,"gn:admin1_code":"21.0","gn:admin2_code":"142.0","gn:admin3_code":"9737.0","gn:asciiname":"Saera","gn:country_code":"EE","gn:dem":85,"gn:feature_class":"P","gn:feature_code":"PPL","gn:geonameid":8618719,"gn:latitude":57.69639,"gn:longitude":26.53111,"gn:modification_date":"2017-11-25","gn:name":"Saera","gn:population":0,"gn:timezone":"Europe/Tallinn","iso:country":"EE","lbl:bbox":"26.51111,57.67639,26.55111,57.71639","lbl:max_zoom":18,"lbl:min_zoom":13.5,"mz:hierarchy_label":1,"mz:is_current":1,"mz:min_zoom":12,"name:und_x_variant":["Soe"],"src:geom":"geonames","wof:belongsto":[85682937,102191581,1713313331,85633135,1713305795],"wof:breaches":[],"wof:concordances":{"gn:id":8618719},"wof:country":"EE","wof:geomhash":"2ff8d87da22ab80dc49cfab2d45c05e5","wof:hierarchy":[{"continent_id":102191581,"country_id":85633135,"county_id":1713305795,"localadmin_id":1713313331,"locality_id":1209473879,"region_id":85682937}],"wof:id":1209473879,"wof:lang_x_official":["est"],"wof:lang_x_spoken":["est"],"wof:lastmodified":1596677024,"wof:name":"Saera","wof:parent_id":1713313331,"wof:placetype":"locality","wof:repo":"whosonfirst-data-admin-ee","wof:superseded_by":[],"wof:supersedes":[],"wof:tags":[]},"bbox":[26.53111,57.69639,26.53111,57.69639],"geometry":{"coordinates":[26.53111,57.69639],"type":"Point"}}