{"id":1293511981,"type":"Feature","properties":{"edtf:cessation":"uuuu","edtf:inception":"uuuu","geom:area":0,"geom:area_square_m":0,"geom:bbox":"26.56361,59.19194,26.56361,59.19194","geom:latitude":59.19194,"geom:longitude":26.56361,"gn:admin1_code":"8.0","gn:admin2_code":"901.0","gn:admin3_code":"7012.0","gn:asciiname":"Laehtse","gn:country_code":"EE","gn:dem":111,"gn:feature_class":"P","gn:feature_code":"PPL","gn:geonameid":793413,"gn:latitude":59.19194,"gn:longitude":26.56361,"gn:modification_date":"2017-11-25","gn:name":"Lähtse","gn:population":0,"gn:timezone":"Europe/Tallinn","iso:country":"EE","lbl:bbox":"26.54361,59.17194,26.58361,59.21194","lbl:max_zoom":18,"lbl:min_zoom":13.5,"mz:hierarchy_label":1,"mz:is_current":1,"mz:min_zoom":12,"src:geom":"geonames","wof:belongsto":[85683049,102191581,1713307623,85633135,1713305771],"wof:breaches":[],"wof:concordances":{"gn:id":793413},"wof:coterminous":[1713308009],"wof:country":"EE","wof:geomhash":"f84a379af6f6339bea413ece70171f2a","wof:hierarchy":[{"continent_id":102191581,"country_id":85633135,"county_id":1713305771,"localadmin_id":1713307623,"locality_id":1293511981,"region_id":85683049}],"wof:id":1293511981,"wof:lang_x_official":["est"],"wof:lang_x_spoken":["est"],"wof:lastmodified":1596677966,"wof:name":"Laehtse","wof:parent_id":1713307623,"wof:placetype":"locality","wof:repo":"whosonfirst-data-admin-ee","wof:superseded_by":[],"wof:supersedes":[],"wof:tags":[]},"bbox":[26.56361,59.19194,26.56361,59.19194],"geometry":{"coordinates":[26.56361,59.19194],"type":"Point"}}