{"id":1259554471,"type":"Feature","properties":{"edtf:cessation":"uuuu","edtf:inception":"uuuu","geom:area":0,"geom:area_square_m":0,"geom:bbox":"23.2175,58.48083,23.2175,58.48083","geom:latitude":58.48083,"geom:longitude":23.2175,"gn:admin1_code":"14.0","gn:admin2_code":"714.0","gn:admin3_code":"4238.0","gn:asciiname":"Leisi","gn:country_code":"EE","gn:dem":8,"gn:feature_class":"P","gn:feature_code":"PPL","gn:geonameid":590705,"gn:latitude":58.48083,"gn:longitude":23.2175,"gn:modification_date":"2017-11-25","gn:name":"Leisi","gn:population":0,"gn:timezone":"Europe/Tallinn","iso:country":"EE","lbl:bbox":"23.1975,58.46083,23.2375,58.50083","lbl:max_zoom":18,"lbl:min_zoom":13.5,"mz:hierarchy_label":1,"mz:is_current":1,"mz:min_zoom":12,"name:und_x_variant":["Leyzi","Leisi"],"src:geom":"geonames","wof:belongsto":[85682947,102191581,1713306499,85633135,1713305627],"wof:breaches":[],"wof:concordances":{"gn:id":590705,"wk:page":"Leisi%2C_P%C3%B6ide_Parish"},"wof:coterminous":[1713306499],"wof:country":"EE","wof:geomhash":"302e63a6fc8eaa1f3b7e425b7ef37893","wof:hierarchy":[{"continent_id":102191581,"country_id":85633135,"county_id":1713305627,"localadmin_id":1713306499,"locality_id":1259554471,"region_id":85682947}],"wof:id":1259554471,"wof:lang_x_official":["est"],"wof:lang_x_spoken":["est"],"wof:lastmodified":1596674913,"wof:name":"Leisi","wof:parent_id":1713306499,"wof:placetype":"locality","wof:repo":"whosonfirst-data-admin-ee","wof:superseded_by":[],"wof:supersedes":[],"wof:tags":[]},"bbox":[23.2175,58.48083,23.2175,58.48083],"geometry":{"coordinates":[23.2175,58.48083],"type":"Point"}}