{"id":1125868081,"type":"Feature","properties":{"edtf:cessation":"uuuu","edtf:inception":"uuuu","geom:area":0,"geom:area_square_m":0,"geom:bbox":"25.13028,59.34306,25.13028,59.34306","geom:latitude":59.34306,"geom:longitude":25.13028,"gn:country":"EE","gn:fcode":"PPL","gn:population":176,"iso:country":"EE","lbl:bbox":"25.11028,59.32306,25.15028,59.36306","lbl:latitude":59.34306,"lbl:longitude":25.13028,"lbl:max_zoom":18,"lbl:min_zoom":13,"mz:hierarchy_label":1,"mz:is_current":1,"mz:min_zoom":11,"mz:note":"Quattroshapes Point Gazetteer import 20170519","name:bul_x_preferred":["Калеси"],"name:ceb_x_preferred":["Kalesi"],"name:eng_x_preferred":["Kalesi"],"name:est_x_preferred":["Kalesi"],"name:fra_x_preferred":["Kalesi"],"name:hye_x_preferred":["Կալեսի"],"name:nld_x_preferred":["Kalesi"],"name:pol_x_preferred":["Kalesi"],"name:spa_x_preferred":["Kalesi"],"name:swe_x_preferred":["Kalesi"],"name:und_x_variant":["Kalesi-Saunaküla"],"name:vol_x_preferred":["Kalesi"],"qs_pg:aaroncc":"EE","qs_pg:gn_country":"EE","qs_pg:gn_fcode":"PPL","qs_pg:gn_id":591719,"qs_pg:gn_pop":176,"qs_pg:name":"Kalesi","qs_pg:name_adm0":"Eesti","qs_pg:name_adm1":"Harjumaa","qs_pg:photos_9k":1,"qs_pg:photos_9r":1,"qs_pg:photos_all":7,"qs_pg:photos_sr":0,"qs_pg:pop_sr":1,"qs_pg:qs_id":423122,"qs_pg:qs_pg_placetype":"locality","qs_pg:qs_pg_placetype_gp":"Town","qs_pg:woe_adm0":23424805,"qs_pg:woe_id":842637,"src:geom":"qs_pg","src:lbl_centroid":"qs_pg","src:population":"geonames","woe:adm0_id":23424805,"woe:name_adm0":"Eesti","woe:name_adm1":"Harjumaa","woe:placetype":"Town","wof:belongsto":[85683055,102191581,1713305991,85633135,1713305751],"wof:breaches":[],"wof:concordances":{"gn:id":591719,"gp:id":842637,"qs_pg:id":423122,"wd:id":"Q2316558"},"wof:coterminous":[1713305991],"wof:country":"EE","wof:created":1497294147,"wof:geomhash":"69b4a35c1986510c8bb5930fbbe31ef1","wof:hierarchy":[{"continent_id":102191581,"country_id":85633135,"county_id":1713305751,"localadmin_id":1713305991,"locality_id":1125868081,"region_id":85683055}],"wof:id":1125868081,"wof:lang_x_official":["est"],"wof:lang_x_spoken":["est"],"wof:lastmodified":1596661931,"wof:name":"Kalesi","wof:parent_id":1713305991,"wof:placetype":"locality","wof:population":176,"wof:population_rank":1,"wof:repo":"whosonfirst-data-admin-ee","wof:superseded_by":[],"wof:supersedes":[],"wof:tags":[]},"bbox":[25.13028,59.34306,25.13028,59.34306],"geometry":{"coordinates":[25.13028,59.34306],"type":"Point"}}