{"id":1326463179,"type":"Feature","properties":{"edtf:cessation":"uuuu","edtf:inception":"uuuu","geom:area":0,"geom:area_square_m":0,"geom:bbox":"25.93722,59.13389,25.93722,59.13389","geom:latitude":59.13389,"geom:longitude":25.93722,"gn:admin1_code":"4.0","gn:admin2_code":"255.0","gn:admin3_code":"7081.0","gn:asciiname":"Kaarevere","gn:country_code":"EE","gn:dem":120,"gn:feature_class":"P","gn:feature_code":"PPL","gn:geonameid":591850,"gn:latitude":59.13389,"gn:longitude":25.93722,"gn:modification_date":"2017-11-25","gn:name":"Kaarevere","gn:population":0,"gn:timezone":"Europe/Tallinn","iso:country":"EE","lbl:bbox":"25.91722,59.11389,25.95722,59.15389","lbl:max_zoom":18,"lbl:min_zoom":13.5,"mz:hierarchy_label":1,"mz:is_current":1,"mz:min_zoom":12,"name:und_x_variant":["Karevere","Kaarevere"],"src:geom":"geonames","wof:belongsto":[85683031,102191581,1713306841,85633135,1713305765],"wof:breaches":[],"wof:concordances":{"gn:id":591850},"wof:country":"EE","wof:geomhash":"29cb0df5d1d3507c111600594cb5d8ea","wof:hierarchy":[{"continent_id":102191581,"country_id":85633135,"county_id":1713305765,"localadmin_id":1713306841,"locality_id":1326463179,"region_id":85683031}],"wof:id":1326463179,"wof:lang_x_official":["est"],"wof:lang_x_spoken":["est"],"wof:lastmodified":1596676636,"wof:name":"Kaarevere","wof:parent_id":1713306841,"wof:placetype":"locality","wof:repo":"whosonfirst-data-admin-ee","wof:superseded_by":[],"wof:supersedes":[],"wof:tags":[]},"bbox":[25.93722,59.13389,25.93722,59.13389],"geometry":{"coordinates":[25.93722,59.13389],"type":"Point"}}