{"id":1226725843,"type":"Feature","properties":{"edtf:cessation":"uuuu","edtf:inception":"uuuu","geom:area":0,"geom:area_square_m":0,"geom:bbox":"26.97611,58.35583,26.97611,58.35583","geom:latitude":58.35583,"geom:longitude":26.97611,"gn:admin1_code":"18.0","gn:admin2_code":"291.0","gn:admin3_code":"8211.0","gn:asciiname":"Tigase","gn:country_code":"EE","gn:dem":46,"gn:feature_class":"P","gn:feature_code":"PPL","gn:geonameid":794133,"gn:latitude":58.35583,"gn:longitude":26.97611,"gn:modification_date":"2017-11-25","gn:name":"Tigase","gn:population":0,"gn:timezone":"Europe/Tallinn","iso:country":"EE","lbl:bbox":"26.95611,58.33583,26.99611,58.37583","lbl:max_zoom":18,"lbl:min_zoom":13.5,"mz:hierarchy_label":1,"mz:is_current":1,"mz:min_zoom":12,"name:fra_x_preferred":["Tigase"],"name:nld_x_preferred":["Tigase"],"src:geom":"geonames","wof:belongsto":[85682995,102191581,1713311115,85633135,1713305699],"wof:breaches":[],"wof:concordances":{"gn:id":794133,"wk:page":"Tigase"},"wof:coterminous":[1713311115],"wof:country":"EE","wof:geomhash":"753c1ab695e8e0304eea0102dcf5e0a4","wof:hierarchy":[{"continent_id":102191581,"country_id":85633135,"county_id":1713305699,"localadmin_id":1713311115,"locality_id":1226725843,"region_id":85682995}],"wof:id":1226725843,"wof:lang_x_official":["est"],"wof:lang_x_spoken":["est"],"wof:lastmodified":1596660663,"wof:name":"Tigase","wof:parent_id":1713311115,"wof:placetype":"locality","wof:repo":"whosonfirst-data-admin-ee","wof:superseded_by":[],"wof:supersedes":[],"wof:tags":[]},"bbox":[26.97611,58.35583,26.97611,58.35583],"geometry":{"coordinates":[26.97611,58.35583],"type":"Point"}}