{"id":1226356535,"type":"Feature","properties":{"edtf:cessation":"uuuu","edtf:inception":"uuuu","geom:area":0,"geom:area_square_m":0,"geom:bbox":"24.31417,59.1875,24.31417,59.1875","geom:latitude":59.1875,"geom:longitude":24.31417,"gn:admin1_code":"1.0","gn:admin2_code":"726.0","gn:admin3_code":"3001.0","gn:asciiname":"Metsakuela","gn:country_code":"EE","gn:dem":41,"gn:feature_class":"P","gn:feature_code":"PPL","gn:geonameid":8619560,"gn:latitude":59.1875,"gn:longitude":24.31417,"gn:modification_date":"2017-11-25","gn:name":"Metsaküla","gn:population":0,"gn:timezone":"Europe/Tallinn","iso:country":"EE","lbl:bbox":"24.29417,59.1675,24.33417,59.2075","lbl:max_zoom":18,"lbl:min_zoom":13.5,"mz:hierarchy_label":1,"mz:is_current":1,"mz:min_zoom":12,"name:und_x_variant":["Metsaküla","Metsküla"],"src:geom":"geonames","wof:belongsto":[85683055,102191581,1713315259,85633135,1713305739],"wof:breaches":[],"wof:concordances":{"gn:id":8619560},"wof:country":"EE","wof:geomhash":"bb823665c46186241a4051b7851e3bcf","wof:hierarchy":[{"continent_id":102191581,"country_id":85633135,"county_id":1713305739,"localadmin_id":1713315259,"locality_id":1226356535,"region_id":85683055}],"wof:id":1226356535,"wof:lang_x_official":["est"],"wof:lang_x_spoken":["est"],"wof:lastmodified":1596663241,"wof:name":"Metsakuela","wof:parent_id":1713315259,"wof:placetype":"locality","wof:repo":"whosonfirst-data-admin-ee","wof:superseded_by":[],"wof:supersedes":[],"wof:tags":[]},"bbox":[24.31417,59.1875,24.31417,59.1875],"geometry":{"coordinates":[24.31417,59.1875],"type":"Point"}}