{"id":1226637751,"type":"Feature","properties":{"edtf:cessation":"uuuu","edtf:inception":"uuuu","geom:area":0,"geom:area_square_m":0,"geom:bbox":"23.85417,59.01389,23.85417,59.01389","geom:latitude":59.01389,"geom:longitude":23.85417,"gn:admin1_code":"7.0","gn:admin2_code":"441.0","gn:admin3_code":"9254.0","gn:asciiname":"Hardu","gn:country_code":"EE","gn:dem":41,"gn:feature_class":"P","gn:feature_code":"PPL","gn:geonameid":592180,"gn:latitude":59.01389,"gn:longitude":23.85417,"gn:modification_date":"2017-11-25","gn:name":"Hardu","gn:population":0,"gn:timezone":"Europe/Tallinn","iso:country":"EE","lbl:bbox":"23.83417,58.99389,23.87417,59.03389","lbl:max_zoom":18,"lbl:min_zoom":13.5,"mz:hierarchy_label":1,"mz:is_current":1,"mz:min_zoom":12,"src:geom":"geonames","wof:belongsto":[85683001,102191581,1713309045,85633135,1713305701],"wof:breaches":[],"wof:concordances":{"gn:id":592180},"wof:country":"EE","wof:geomhash":"32dd119afc9170ba70fe2cc338136feb","wof:hierarchy":[{"continent_id":102191581,"country_id":85633135,"county_id":1713305701,"localadmin_id":1713309045,"locality_id":1226637751,"region_id":85683001}],"wof:id":1226637751,"wof:lang_x_official":["est"],"wof:lang_x_spoken":["est"],"wof:lastmodified":1596677430,"wof:name":"Hardu","wof:parent_id":1713309045,"wof:placetype":"locality","wof:repo":"whosonfirst-data-admin-ee","wof:superseded_by":[],"wof:supersedes":[],"wof:tags":[]},"bbox":[23.85417,59.01389,23.85417,59.01389],"geometry":{"coordinates":[23.85417,59.01389],"type":"Point"}}