{"id":1226406777,"type":"Feature","properties":{"edtf:cessation":"uuuu","edtf:inception":"uuuu","geom:area":0,"geom:area_square_m":0,"geom:bbox":"27.1925,57.70167,27.1925,57.70167","geom:latitude":57.70167,"geom:longitude":27.1925,"gn:admin1_code":"21.0","gn:admin2_code":"917.0","gn:admin3_code":"3991.0","gn:asciiname":"Kuendja","gn:country_code":"EE","gn:dem":193,"gn:feature_class":"P","gn:feature_code":"PPL","gn:geonameid":794349,"gn:latitude":57.70167,"gn:longitude":27.1925,"gn:modification_date":"2017-11-25","gn:name":"Kündja","gn:population":0,"gn:timezone":"Europe/Tallinn","iso:country":"EE","lbl:bbox":"27.1725,57.68167,27.2125,57.72167","lbl:max_zoom":18,"lbl:min_zoom":13.5,"mz:hierarchy_label":1,"mz:is_current":1,"mz:min_zoom":12,"name:est_x_preferred":["Kündja"],"name:hye_x_preferred":["Կյունդյա"],"name:nld_x_preferred":["Kündja"],"name:pol_x_preferred":["Kündja"],"name:spa_x_preferred":["Kündja"],"name:ukr_x_preferred":["Кюндя"],"name:vol_x_preferred":["Kündja"],"src:geom":"geonames","wof:belongsto":[85682937,102191581,1713316331,85633135,1713305633],"wof:breaches":[],"wof:concordances":{"gn:id":794349,"wk:page":"K%C3%BCndja"},"wof:coterminous":[1713316331],"wof:country":"EE","wof:geomhash":"5d8e5f959a046c2e2e36d13ec664f766","wof:hierarchy":[{"continent_id":102191581,"country_id":85633135,"county_id":1713305633,"localadmin_id":1713316331,"locality_id":1226406777,"region_id":85682937}],"wof:id":1226406777,"wof:lang_x_official":["est"],"wof:lang_x_spoken":["est"],"wof:lastmodified":1596660407,"wof:name":"Kuendja","wof:parent_id":1713316331,"wof:placetype":"locality","wof:repo":"whosonfirst-data-admin-ee","wof:superseded_by":[],"wof:supersedes":[],"wof:tags":[]},"bbox":[27.1925,57.70167,27.1925,57.70167],"geometry":{"coordinates":[27.1925,57.70167],"type":"Point"}}