{"id":1310700723,"type":"Feature","properties":{"edtf:cessation":"uuuu","edtf:inception":"uuuu","geom:area":0,"geom:area_square_m":0,"geom:bbox":"26.5225,58.71472,26.5225,58.71472","geom:latitude":58.71472,"geom:longitude":26.5225,"gn:admin1_code":"5.0","gn:admin2_code":"247.0","gn:admin3_code":"9037.0","gn:asciiname":"Vanavaelja","gn:country_code":"EE","gn:dem":91,"gn:feature_class":"P","gn:feature_code":"PPL","gn:geonameid":8618302,"gn:latitude":58.71472,"gn:longitude":26.5225,"gn:modification_date":"2017-11-25","gn:name":"Vanavälja","gn:population":0,"gn:timezone":"Europe/Tallinn","iso:country":"EE","lbl:bbox":"26.5025,58.69472,26.5425,58.73472","lbl:max_zoom":18,"lbl:min_zoom":13.5,"mz:hierarchy_label":1,"mz:is_current":1,"mz:min_zoom":12,"name:und_x_variant":["Vanavälja","Valma soo"],"src:geom":"geonames","wof:belongsto":[85683009,102191581,1713312365,85633135,1713305767],"wof:breaches":[],"wof:concordances":{"gn:id":8618302},"wof:coterminous":[1713312365],"wof:country":"EE","wof:geomhash":"172f93b9fc80e69bed333c9c81f43165","wof:hierarchy":[{"continent_id":102191581,"country_id":85633135,"county_id":1713305767,"localadmin_id":1713312365,"locality_id":1310700723,"region_id":85683009}],"wof:id":1310700723,"wof:lang_x_official":["est"],"wof:lang_x_spoken":["est"],"wof:lastmodified":1596676574,"wof:name":"Vanavaelja","wof:parent_id":1713312365,"wof:placetype":"locality","wof:repo":"whosonfirst-data-admin-ee","wof:superseded_by":[],"wof:supersedes":[],"wof:tags":[]},"bbox":[26.5225,58.71472,26.5225,58.71472],"geometry":{"coordinates":[26.5225,58.71472],"type":"Point"}}