{"id":1225830787,"type":"Feature","properties":{"edtf:cessation":"uuuu","edtf:inception":"uuuu","geom:area":0,"geom:area_square_m":0,"geom:bbox":"26.29,59.37972,26.29,59.37972","geom:latitude":59.37972,"geom:longitude":26.29,"gn:admin1_code":"8.0","gn:admin2_code":"661.0","gn:admin3_code":"3202.0","gn:asciiname":"Kloodi","gn:country_code":"EE","gn:dem":81,"gn:feature_class":"P","gn:feature_code":"PPL","gn:geonameid":793461,"gn:latitude":59.37972,"gn:longitude":26.29,"gn:modification_date":"2017-11-25","gn:name":"Kloodi","gn:population":0,"gn:timezone":"Europe/Tallinn","iso:country":"EE","lbl:bbox":"26.27,59.35972,26.31,59.39972","lbl:max_zoom":18,"lbl:min_zoom":13.5,"mz:hierarchy_label":1,"mz:is_current":1,"mz:min_zoom":12,"name:est_x_preferred":["Kloodi"],"name:fra_x_preferred":["Kloodi"],"name:hye_x_preferred":["Կլոոդի"],"name:vol_x_preferred":["Kloodi"],"src:geom":"geonames","wof:belongsto":[85683049,102191581,1713313947,85633135,1713305719],"wof:breaches":[],"wof:concordances":{"gn:id":793461,"wk:page":"Kloodi"},"wof:coterminous":[1713313947],"wof:country":"EE","wof:geomhash":"e35bddac52038b1e1ae23f35fec7fd55","wof:hierarchy":[{"continent_id":102191581,"country_id":85633135,"county_id":1713305719,"localadmin_id":1713313947,"locality_id":1225830787,"region_id":85683049}],"wof:id":1225830787,"wof:lang_x_official":["est"],"wof:lang_x_spoken":["est"],"wof:lastmodified":1596676669,"wof:name":"Kloodi","wof:parent_id":1713313947,"wof:placetype":"locality","wof:repo":"whosonfirst-data-admin-ee","wof:superseded_by":[],"wof:supersedes":[],"wof:tags":[]},"bbox":[26.29,59.37972,26.29,59.37972],"geometry":{"coordinates":[26.29,59.37972],"type":"Point"}}