{"id":1226234191,"type":"Feature","properties":{"edtf:cessation":"uuuu","edtf:inception":"uuuu","geom:area":0,"geom:area_square_m":0,"geom:bbox":"23.51212,58.99334,23.51212,58.99334","geom:latitude":58.99334,"geom:longitude":23.51212,"gn:admin1_code":"7.0","gn:admin2_code":"441.0","gn:admin3_code":"9803.0","gn:asciiname":"OEsterbi","gn:country_code":"EE","gn:dem":7,"gn:feature_class":"P","gn:feature_code":"PPL","gn:geonameid":592295,"gn:latitude":58.99334,"gn:longitude":23.51212,"gn:modification_date":"2017-11-25","gn:name":"Österbi","gn:population":0,"gn:timezone":"Europe/Tallinn","iso:country":"EE","lbl:bbox":"23.49212,58.97334,23.53212,59.01334","lbl:max_zoom":18,"lbl:min_zoom":13.5,"mz:hierarchy_label":1,"mz:is_current":1,"mz:min_zoom":12,"name:deu_x_preferred":["Österby"],"name:est_x_preferred":["Österby"],"name:hye_x_preferred":["Օոստեռբու"],"name:pol_x_preferred":["Österby"],"name:spa_x_preferred":["Österby"],"name:swe_x_historical":["Österbi"],"name:swe_x_preferred":["Österby"],"name:swe_x_variant":["Österbi"],"name:ukr_x_preferred":["Естербю"],"name:und_x_variant":["Eisterby","Öesterby","Esterbyu","Eistrepa","Eisterbi","Eisterpa"],"name:vol_x_preferred":["Österby"],"src:geom":"geonames","wof:belongsto":[85683001,102191581,1713309047,85633135,1713305701],"wof:breaches":[],"wof:concordances":{"gn:id":592295,"wk:page":"%C3%96sterby"},"wof:country":"EE","wof:geomhash":"be0f053bade2f74dda85677934011484","wof:hierarchy":[{"continent_id":102191581,"country_id":85633135,"county_id":1713305701,"localadmin_id":1713309047,"locality_id":1226234191,"region_id":85683001}],"wof:id":1226234191,"wof:lang_x_official":["est"],"wof:lang_x_spoken":["est"],"wof:lastmodified":1596677436,"wof:name":"OEsterbi","wof:parent_id":1713309047,"wof:placetype":"locality","wof:repo":"whosonfirst-data-admin-ee","wof:superseded_by":[],"wof:supersedes":[],"wof:tags":[]},"bbox":[23.51212,58.99334,23.51212,58.99334],"geometry":{"coordinates":[23.51212,58.99334],"type":"Point"}}