{"id":1327210993,"type":"Feature","properties":{"edtf:cessation":"uuuu","edtf:inception":"uuuu","geom:area":0,"geom:area_square_m":0,"geom:bbox":"27.45194,58.10333,27.45194,58.10333","geom:latitude":58.10333,"geom:longitude":27.45194,"gn:admin1_code":"12.0","gn:admin2_code":"708.0","gn:admin3_code":"7216.0","gn:asciiname":"Jaama","gn:country_code":"EE","gn:dem":44,"gn:feature_class":"P","gn:feature_code":"PPL","gn:geonameid":8620504,"gn:latitude":58.10333,"gn:longitude":27.45194,"gn:modification_date":"2017-11-25","gn:name":"Jaama","gn:population":0,"gn:timezone":"Europe/Tallinn","iso:country":"EE","lbl:bbox":"27.43194,58.08333,27.47194,58.12333","lbl:max_zoom":18,"lbl:min_zoom":13.5,"mz:hierarchy_label":1,"mz:is_current":1,"mz:is_funky":1,"mz:min_zoom":12,"name:ceb_x_preferred":["Jaama"],"name:deu_x_preferred":["Jaama"],"name:est_x_preferred":["Jaama"],"name:nds_x_preferred":["Jaama"],"name:nld_x_preferred":["Jaama"],"name:pol_x_preferred":["Jaama"],"name:swe_x_preferred":["Jaama"],"name:und_x_variant":["Beresje"],"name:vol_x_preferred":["Jaama"],"src:geom":"geonames","wof:belongsto":[85682955,102191581,1713310869,85633135,1713305793],"wof:breaches":[],"wof:concordances":{"gn:id":8620504},"wof:country":"EE","wof:geomhash":"0424a592416fced7218dbad638fe8720","wof:hierarchy":[{"continent_id":102191581,"country_id":85633135,"county_id":1713305793,"localadmin_id":1713310869,"locality_id":1327210993,"region_id":85682955}],"wof:id":1327210993,"wof:lang_x_official":["est"],"wof:lang_x_spoken":["est"],"wof:lastmodified":1596677003,"wof:name":"Jaama","wof:parent_id":1713310869,"wof:placetype":"locality","wof:repo":"whosonfirst-data-admin-ee","wof:superseded_by":[],"wof:supersedes":[],"wof:tags":[]},"bbox":[27.45194,58.10333,27.45194,58.10333],"geometry":{"coordinates":[27.45194,58.10333],"type":"Point"}}