{"id":1125955815,"type":"Feature","properties":{"edtf:cessation":"uuuu","edtf:inception":"uuuu","geom:area":0,"geom:area_square_m":0,"geom:bbox":"25.37361,58.81361,25.37361,58.81361","geom:latitude":58.81361,"geom:longitude":25.37361,"gn:country":"EE","gn:fcode":"PPL","gn:population":185,"iso:country":"EE","lbl:bbox":"25.35361,58.79361,25.39361,58.83361","lbl:latitude":58.81361,"lbl:longitude":25.37361,"lbl:max_zoom":18,"lbl:min_zoom":13,"mz:hierarchy_label":1,"mz:is_current":1,"mz:min_zoom":11,"mz:note":"Quattroshapes Point Gazetteer import 20170519","name:ceb_x_preferred":["Lokuta"],"name:est_x_preferred":["Lokuta"],"name:fra_x_preferred":["Lokuta"],"name:hye_x_preferred":["Լոկուտա"],"name:pol_x_preferred":["Lokuta"],"name:sco_x_preferred":["Lokuta"],"name:swe_x_preferred":["Lokuta"],"name:ukr_x_preferred":["Локута"],"name:vol_x_preferred":["Lokuta"],"qs_pg:aaroncc":"EE","qs_pg:gn_country":"EE","qs_pg:gn_fcode":"PPL","qs_pg:gn_id":590548,"qs_pg:gn_pop":185,"qs_pg:name":"Lokuta","qs_pg:name_adm0":"Eesti","qs_pg:name_adm1":"Järvamaa","qs_pg:photos_9r":0,"qs_pg:photos_sr":0,"qs_pg:pop_sr":1,"qs_pg:qs_id":405961,"qs_pg:qs_pg_placetype":"locality","qs_pg:qs_pg_placetype_gp":"Town","qs_pg:woe_adm0":23424805,"qs_pg:woe_id":843734,"src:geom":"qs_pg","src:lbl_centroid":"qs_pg","src:population":"geonames","woe:adm0_id":23424805,"woe:name_adm0":"Eesti","woe:name_adm1":"Järvamaa","woe:placetype":"Town","wof:belongsto":[85683031,102191581,1713315927,85633135,1713305773],"wof:breaches":[],"wof:concordances":{"gn:id":590548,"gp:id":843734,"qs_pg:id":405961},"wof:coterminous":[1713315927],"wof:country":"EE","wof:created":1497297616,"wof:geomhash":"834a6afe815e1159ecb48a153eec4596","wof:hierarchy":[{"continent_id":102191581,"country_id":85633135,"county_id":1713305773,"localadmin_id":1713315927,"locality_id":1125955815,"region_id":85683031}],"wof:id":1125955815,"wof:lang_x_official":["est"],"wof:lang_x_spoken":["est"],"wof:lastmodified":1596677991,"wof:name":"Lokuta","wof:parent_id":1713315927,"wof:placetype":"locality","wof:population":185,"wof:population_rank":1,"wof:repo":"whosonfirst-data-admin-ee","wof:superseded_by":[],"wof:supersedes":[],"wof:tags":[]},"bbox":[25.37361,58.81361,25.37361,58.81361],"geometry":{"coordinates":[25.37361,58.81361],"type":"Point"}}