{"id":1344245123,"type":"Feature","properties":{"edtf:cessation":"uuuu","edtf:inception":"uuuu","geom:area":0,"geom:area_square_m":0,"geom:bbox":"24.17639,58.46556,24.17639,58.46556","geom:latitude":58.46556,"geom:longitude":24.17639,"gn:admin1_code":"11.0","gn:admin2_code":"624.0","gn:admin3_code":"1394.0","gn:asciiname":"Volla","gn:country_code":"EE","gn:dem":38,"gn:feature_class":"P","gn:feature_code":"PPL","gn:geonameid":587486,"gn:latitude":58.46556,"gn:longitude":24.17639,"gn:modification_date":"2017-11-25","gn:name":"Võlla","gn:population":0,"gn:timezone":"Europe/Tallinn","iso:country":"EE","lbl:bbox":"24.15639,58.44556,24.19639,58.48556","lbl:max_zoom":18,"lbl:min_zoom":13.5,"mz:hierarchy_label":1,"mz:is_current":1,"mz:min_zoom":12,"name:ceb_x_preferred":["Volla"],"name:srp_x_preferred":["Vola"],"name:swe_x_preferred":["Volla"],"name:und_x_variant":["Myza Vylla","Võlla"],"src:geom":"geonames","wof:belongsto":[85682981,102191581,1713310433,85633135,1713305703],"wof:breaches":[],"wof:concordances":{"gn:id":587486},"wof:country":"EE","wof:geomhash":"044e684e6606694285890de93a09ae91","wof:hierarchy":[{"continent_id":102191581,"country_id":85633135,"county_id":1713305703,"localadmin_id":1713310433,"locality_id":1344245123,"region_id":85682981}],"wof:id":1344245123,"wof:lang_x_official":["est"],"wof:lang_x_spoken":["est"],"wof:lastmodified":1596677711,"wof:name":"Volla","wof:parent_id":1713310433,"wof:placetype":"locality","wof:repo":"whosonfirst-data-admin-ee","wof:superseded_by":[],"wof:supersedes":[],"wof:tags":[]},"bbox":[24.17639,58.46556,24.17639,58.46556],"geometry":{"coordinates":[24.17639,58.46556],"type":"Point"}}