{"id":1343542301,"type":"Feature","properties":{"edtf:cessation":"uuuu","edtf:inception":"uuuu","geom:area":0,"geom:area_square_m":0,"geom:bbox":"24.01306,58.44583,24.01306,58.44583","geom:latitude":58.44583,"geom:longitude":24.01306,"gn:admin1_code":"11.0","gn:admin2_code":"624.0","gn:admin3_code":"8475.0","gn:asciiname":"Tohela","gn:cc2":"EE","gn:country_code":"EE","gn:dem":25,"gn:feature_class":"P","gn:feature_code":"PPL","gn:geonameid":588273,"gn:latitude":58.44583,"gn:longitude":24.01306,"gn:modification_date":"2017-11-25","gn:name":"Tõhela","gn:population":0,"gn:timezone":"Europe/Tallinn","iso:country":"EE","lbl:bbox":"23.99306,58.42583,24.03306,58.46583","lbl:max_zoom":18,"lbl:min_zoom":13.5,"mz:hierarchy_label":1,"mz:is_current":1,"mz:min_zoom":12,"name:eng_x_preferred":["Tõhela"],"name:est_x_preferred":["Tõhela"],"name:fas_x_preferred":["توهلا"],"name:hye_x_preferred":["Տիհելա"],"name:pol_x_preferred":["Tõhela"],"name:rus_x_preferred":["Тыхела"],"name:ukr_x_preferred":["Тигела"],"name:und_x_variant":["Tykhela"],"name:vol_x_preferred":["Tõhela"],"src:geom":"geonames","wof:belongsto":[85682981,102191581,1713310429,85633135,1713305703],"wof:breaches":[],"wof:concordances":{"gn:id":588273,"wk:page":"T%C3%B5hela"},"wof:coterminous":[1713310429],"wof:country":"EE","wof:geomhash":"587b42807d81c04adbd186d6608634d8","wof:hierarchy":[{"continent_id":102191581,"country_id":85633135,"county_id":1713305703,"localadmin_id":1713310429,"locality_id":1343542301,"region_id":85682981}],"wof:id":1343542301,"wof:lang_x_official":["est"],"wof:lang_x_spoken":["est"],"wof:lastmodified":1596677702,"wof:name":"Tohela","wof:parent_id":1713310429,"wof:placetype":"locality","wof:repo":"whosonfirst-data-admin-ee","wof:superseded_by":[],"wof:supersedes":[],"wof:tags":[]},"bbox":[24.01306,58.44583,24.01306,58.44583],"geometry":{"coordinates":[24.01306,58.44583],"type":"Point"}}