{"id":1343247487,"type":"Feature","properties":{"edtf:cessation":"uuuu","edtf:inception":"uuuu","geom:area":0,"geom:area_square_m":0,"geom:bbox":"26.18583,59.56528,26.18583,59.56528","geom:latitude":59.56528,"geom:longitude":26.18583,"gn:admin1_code":"8.0","gn:admin2_code":"191.0","gn:admin3_code":"1723.0","gn:asciiname":"Haili","gn:country_code":"EE","gn:dem":56,"gn:feature_class":"P","gn:feature_code":"PPL","gn:geonameid":793481,"gn:latitude":59.56528,"gn:longitude":26.18583,"gn:modification_date":"2017-11-25","gn:name":"Haili","gn:population":0,"gn:timezone":"Europe/Tallinn","iso:country":"EE","lbl:bbox":"26.16583,59.54528,26.20583,59.58528","lbl:max_zoom":18,"lbl:min_zoom":13.5,"mz:hierarchy_label":1,"mz:is_current":1,"mz:min_zoom":12,"name:est_x_preferred":["Haili"],"name:fra_x_preferred":["Haili"],"name:hye_x_preferred":["Հաիլի"],"name:vol_x_preferred":["Haili"],"src:geom":"geonames","wof:belongsto":[85683049,102191581,1713308437,85633135,1713305775],"wof:breaches":[],"wof:concordances":{"gn:id":793481,"wk:page":"Haili"},"wof:coterminous":[1713308437],"wof:country":"EE","wof:geomhash":"adc927cb1a4f4a852679e17c0d84cdd8","wof:hierarchy":[{"continent_id":102191581,"country_id":85633135,"county_id":1713305775,"localadmin_id":1713308437,"locality_id":1343247487,"region_id":85683049}],"wof:id":1343247487,"wof:lang_x_official":["est"],"wof:lang_x_spoken":["est"],"wof:lastmodified":1596678040,"wof:name":"Haili","wof:parent_id":1713308437,"wof:placetype":"locality","wof:repo":"whosonfirst-data-admin-ee","wof:superseded_by":[],"wof:supersedes":[],"wof:tags":[]},"bbox":[26.18583,59.56528,26.18583,59.56528],"geometry":{"coordinates":[26.18583,59.56528],"type":"Point"}}