{"id":1226140043,"type":"Feature","properties":{"edtf:cessation":"uuuu","edtf:inception":"uuuu","geom:area":0,"geom:area_square_m":0,"geom:bbox":"26.38278,59.12806,26.38278,59.12806","geom:latitude":59.12806,"geom:longitude":26.38278,"gn:admin1_code":"8.0","gn:admin2_code":"928.0","gn:admin3_code":"1484.0","gn:asciiname":"Avispea-Tagakuela","gn:country_code":"EE","gn:dem":132,"gn:feature_class":"P","gn:feature_code":"PPL","gn:geonameid":8618763,"gn:latitude":59.12806,"gn:longitude":26.38278,"gn:modification_date":"2017-11-25","gn:name":"Avispea-Tagaküla","gn:population":0,"gn:timezone":"Europe/Tallinn","iso:country":"EE","lbl:bbox":"26.36278,59.10806,26.40278,59.14806","lbl:max_zoom":18,"lbl:min_zoom":13.5,"mz:hierarchy_label":1,"mz:is_current":1,"mz:min_zoom":12,"src:geom":"geonames","wof:belongsto":[85683049,102191581,1713313363,85633135,1713305769],"wof:breaches":[],"wof:concordances":{"gn:id":8618763},"wof:country":"EE","wof:geomhash":"11207b73faa0900b6a7d58680736155b","wof:hierarchy":[{"continent_id":102191581,"country_id":85633135,"county_id":1713305769,"localadmin_id":1713313363,"locality_id":1226140043,"region_id":85683049}],"wof:id":1226140043,"wof:lang_x_official":["est"],"wof:lang_x_spoken":["est"],"wof:lastmodified":1596676539,"wof:name":"Avispea-Tagakuela","wof:parent_id":1713313363,"wof:placetype":"locality","wof:repo":"whosonfirst-data-admin-ee","wof:superseded_by":[],"wof:supersedes":[],"wof:tags":[]},"bbox":[26.38278,59.12806,26.38278,59.12806],"geometry":{"coordinates":[26.38278,59.12806],"type":"Point"}}