{"id":1309817353,"type":"Feature","properties":{"edtf:cessation":"uuuu","edtf:inception":"uuuu","geom:area":0,"geom:area_square_m":0,"geom:bbox":"25.36667,59.41667,25.36667,59.41667","geom:latitude":59.41667,"geom:longitude":25.36667,"gn:admin1_code":"1.0","gn:admin2_code":"353.0","gn:admin3_code":"3993.0","gn:asciiname":"Kuelmaallika","gn:country_code":"EE","gn:dem":68,"gn:feature_class":"P","gn:feature_code":"PPL","gn:geonameid":590986,"gn:latitude":59.41667,"gn:longitude":25.36667,"gn:modification_date":"2017-11-25","gn:name":"Külmaallika","gn:population":0,"gn:timezone":"Europe/Tallinn","iso:country":"EE","lbl:bbox":"25.34667,59.39667,25.38667,59.43667","lbl:max_zoom":18,"lbl:min_zoom":13.5,"mz:hierarchy_label":1,"mz:is_current":1,"mz:min_zoom":12,"name:est_x_preferred":["Külmaallika"],"name:fra_x_preferred":["Külmaallika"],"name:hye_x_preferred":["Կյուլմաալլիկա"],"name:pol_x_preferred":["Külmaallika"],"name:rus_x_preferred":["Кюльмааллика"],"name:spa_x_preferred":["Külmaallika"],"name:und_x_variant":["Külmalliku","Kyul’mallika"],"name:vol_x_preferred":["Külmaallika"],"src:geom":"geonames","wof:belongsto":[85683055,102191581,1713305977,85633135,1713305725],"wof:breaches":[],"wof:concordances":{"gn:id":590986,"wk:page":"K%C3%BClmaallika"},"wof:coterminous":[1713305977],"wof:country":"EE","wof:geomhash":"baec39b54a65a195cf696ae305d512f0","wof:hierarchy":[{"continent_id":102191581,"country_id":85633135,"county_id":1713305725,"localadmin_id":1713305977,"locality_id":1309817353,"region_id":85683055}],"wof:id":1309817353,"wof:lang_x_official":["est"],"wof:lang_x_spoken":["est"],"wof:lastmodified":1596661845,"wof:name":"Kuelmaallika","wof:parent_id":1713305977,"wof:placetype":"locality","wof:repo":"whosonfirst-data-admin-ee","wof:superseded_by":[],"wof:supersedes":[],"wof:tags":[]},"bbox":[25.36667,59.41667,25.36667,59.41667],"geometry":{"coordinates":[25.36667,59.41667],"type":"Point"}}