{"id":1226349791,"type":"Feature","properties":{"edtf:cessation":"uuuu","edtf:inception":"uuuu","geom:area":0,"geom:area_square_m":0,"geom:bbox":"27.34611,59.21139,27.34611,59.21139","geom:latitude":59.21139,"geom:longitude":27.34611,"gn:admin1_code":"3.0","gn:admin2_code":"130.0","gn:admin3_code":"8624.0","gn:asciiname":"Uhe","gn:country_code":"EE","gn:dem":64,"gn:feature_class":"P","gn:feature_code":"PPL","gn:geonameid":8618698,"gn:latitude":59.21139,"gn:longitude":27.34611,"gn:modification_date":"2017-11-25","gn:name":"Uhe","gn:population":0,"gn:timezone":"Europe/Tallinn","iso:country":"EE","lbl:bbox":"27.32611,59.19139,27.36611,59.23139","lbl:max_zoom":18,"lbl:min_zoom":13.5,"mz:hierarchy_label":1,"mz:is_current":1,"mz:min_zoom":12,"name:deu_x_preferred":["Uhe"],"name:est_x_preferred":["Uhe"],"name:hye_x_preferred":["Ուհե"],"name:nld_x_preferred":["Uhe"],"name:pol_x_preferred":["Uhe"],"name:spa_x_preferred":["Uhe"],"name:und_x_variant":["Uhhe"],"name:vol_x_preferred":["Uhe"],"src:geom":"geonames","wof:belongsto":[85683059,102191581,1713311699,85633135,1713305693],"wof:breaches":[],"wof:concordances":{"gn:id":8618698,"wk:page":"Uhe"},"wof:coterminous":[1713311699],"wof:country":"EE","wof:geomhash":"c33f179bbc1fc3c296fad0f1fd3fa0da","wof:hierarchy":[{"continent_id":102191581,"country_id":85633135,"county_id":1713305693,"localadmin_id":1713311699,"locality_id":1226349791,"region_id":85683059}],"wof:id":1226349791,"wof:lang_x_official":["est"],"wof:lang_x_spoken":["est"],"wof:lastmodified":1596660738,"wof:name":"Uhe","wof:parent_id":1713311699,"wof:placetype":"locality","wof:repo":"whosonfirst-data-admin-ee","wof:superseded_by":[],"wof:supersedes":[],"wof:tags":[]},"bbox":[27.34611,59.21139,27.34611,59.21139],"geometry":{"coordinates":[27.34611,59.21139],"type":"Point"}}