{"id":1125936019,"type":"Feature","properties":{"edtf:cessation":"uuuu","edtf:inception":"uuuu","geom:area":0,"geom:area_square_m":0,"geom:bbox":"25.69056,58.43056,25.69056,58.43056","geom:latitude":58.43056,"geom:longitude":25.69056,"gn:country":"EE","gn:fcode":"PPL","gn:population":330,"iso:country":"EE","lbl:bbox":"25.67056,58.41056,25.71056,58.45056","lbl:latitude":58.43056,"lbl:longitude":25.69056,"lbl:max_zoom":17,"lbl:min_zoom":12.5,"mz:hierarchy_label":1,"mz:is_current":1,"mz:min_zoom":11,"mz:note":"Quattroshapes Point Gazetteer import 20170519","name:ceb_x_preferred":["Saarepeedi"],"name:ces_x_preferred":["Saarepeedi"],"name:eng_x_preferred":["Saarepeedi"],"name:est_x_preferred":["Saarepeedi"],"name:fra_x_preferred":["Saarepeedi"],"name:hye_x_preferred":["Սաառեպեեդի"],"name:nld_x_preferred":["Saarepeedi"],"name:pol_x_preferred":["Saarepeedi"],"name:rus_x_preferred":["Саарепе"],"name:spa_x_preferred":["Saarepeedi"],"name:swe_x_preferred":["Saarepeedi"],"name:ukr_x_preferred":["Саарепееді"],"name:urd_x_preferred":["سارےپیدی"],"name:vol_x_preferred":["Saarepeedi"],"qs_pg:aaroncc":"EE","qs_pg:gn_country":"EE","qs_pg:gn_fcode":"PPL","qs_pg:gn_id":588873,"qs_pg:gn_pop":330,"qs_pg:name":"Saarepeedi","qs_pg:name_adm0":"Eesti","qs_pg:name_adm1":"Viljandimaa","qs_pg:photos_9r":0,"qs_pg:photos_sr":0,"qs_pg:pop_sr":2,"qs_pg:qs_id":1274466,"qs_pg:qs_pg_placetype":"locality","qs_pg:qs_pg_placetype_gp":"Town","qs_pg:woe_adm0":23424805,"qs_pg:woe_id":845302,"src:geom":"qs_pg","src:lbl_centroid":"qs_pg","src:population":"geonames","woe:adm0_id":23424805,"woe:name_adm0":"Eesti","woe:name_adm1":"Viljandimaa","woe:placetype":"Town","wof:belongsto":[85682985,102191581,1713313481,85633135,1713305669],"wof:breaches":[],"wof:concordances":{"gn:id":588873,"gp:id":845302,"qs_pg:id":1274466},"wof:coterminous":[1713313481],"wof:country":"EE","wof:created":1497296971,"wof:geomhash":"5c45ad87e6d3f3a3f4dde0dde8e652dc","wof:hierarchy":[{"continent_id":102191581,"country_id":85633135,"county_id":1713305669,"localadmin_id":1713313481,"locality_id":1125936019,"region_id":85682985}],"wof:id":1125936019,"wof:lang_x_official":["est"],"wof:lang_x_spoken":["est"],"wof:lastmodified":1596661271,"wof:name":"Saarepeedi","wof:parent_id":1713313481,"wof:placetype":"locality","wof:population":330,"wof:population_rank":2,"wof:repo":"whosonfirst-data-admin-ee","wof:superseded_by":[],"wof:supersedes":[],"wof:tags":[]},"bbox":[25.69056,58.43056,25.69056,58.43056],"geometry":{"coordinates":[25.69056,58.43056],"type":"Point"}}