{"id":1209235813,"type":"Feature","properties":{"edtf:cessation":"uuuu","edtf:inception":"uuuu","geom:area":0,"geom:area_square_m":0,"geom:bbox":"23.59361,59.07306,23.59361,59.07306","geom:latitude":59.07306,"geom:longitude":23.59361,"gn:admin1_code":"7.0","gn:admin2_code":"441.0","gn:admin3_code":"1469.0","gn:asciiname":"Aulepa","gn:cc2":"EE","gn:country_code":"EE","gn:dem":14,"gn:feature_class":"P","gn:feature_code":"PPL","gn:geonameid":592344,"gn:latitude":59.07306,"gn:longitude":23.59361,"gn:modification_date":"2017-11-25","gn:name":"Aulepa","gn:population":0,"gn:timezone":"Europe/Tallinn","iso:country":"EE","lbl:bbox":"23.57361,59.05306,23.61361,59.09306","lbl:max_zoom":18,"lbl:min_zoom":13.5,"mz:hierarchy_label":1,"mz:is_current":1,"mz:min_zoom":12,"name:deu_x_preferred":["Aulepa"],"name:est_x_preferred":["Aulepa"],"name:hye_x_preferred":["Աուլեպա"],"name:nld_x_preferred":["Aulepa"],"name:pol_x_preferred":["Aulepa"],"name:spa_x_preferred":["Aulepa"],"name:swe_x_preferred":["Dirslätt"],"name:ukr_x_preferred":["Аулепа"],"name:und_x_variant":["Auglepa"],"name:vol_x_preferred":["Aulepa"],"src:geom":"geonames","wof:belongsto":[85683001,102191581,1713309137,85633135,1713305701],"wof:breaches":[],"wof:concordances":{"gn:id":592344,"wk:page":"Aulepa"},"wof:coterminous":[1713309137],"wof:country":"EE","wof:geomhash":"a1339472f700e9f01f398680aedea0db","wof:hierarchy":[{"continent_id":102191581,"country_id":85633135,"county_id":1713305701,"localadmin_id":1713309137,"locality_id":1209235813,"region_id":85683001}],"wof:id":1209235813,"wof:lang_x_official":["est"],"wof:lang_x_spoken":["est"],"wof:lastmodified":1596677426,"wof:name":"Aulepa","wof:parent_id":1713309137,"wof:placetype":"locality","wof:repo":"whosonfirst-data-admin-ee","wof:superseded_by":[],"wof:supersedes":[],"wof:tags":[]},"bbox":[23.59361,59.07306,23.59361,59.07306],"geometry":{"coordinates":[23.59361,59.07306],"type":"Point"}}