{"id":1310275921,"type":"Feature","properties":{"edtf:cessation":"uuuu","edtf:inception":"uuuu","geom:area":0,"geom:area_square_m":0,"geom:bbox":"22.7025,58.47417,22.7025,58.47417","geom:latitude":58.47417,"geom:longitude":22.7025,"gn:admin1_code":"14.0","gn:admin2_code":"714.0","gn:admin3_code":"7537.0","gn:asciiname":"Kaisa","gn:cc2":"EE","gn:country_code":"EE","gn:dem":22,"gn:feature_class":"P","gn:feature_code":"PPL","gn:geonameid":591745,"gn:latitude":58.47417,"gn:longitude":22.7025,"gn:modification_date":"2017-11-25","gn:name":"Kaisa","gn:population":0,"gn:timezone":"Europe/Tallinn","iso:country":"EE","lbl:bbox":"22.6825,58.45417,22.7225,58.49417","lbl:max_zoom":18,"lbl:min_zoom":13.5,"mz:hierarchy_label":1,"mz:is_current":1,"mz:min_zoom":12,"name:deu_x_preferred":["Kaisa"],"name:est_x_preferred":["Kaisa"],"name:hye_x_preferred":["Կաիսա"],"name:pol_x_preferred":["Kaisa"],"name:spa_x_preferred":["Kaisa"],"name:und_x_variant":["Kayza"],"name:vol_x_preferred":["Kaisa"],"src:geom":"geonames","wof:belongsto":[85682947,102191581,1713306743,85633135,1713305627],"wof:breaches":[],"wof:concordances":{"gn:id":591745,"wk:page":"Kaisa%2C_Estonia"},"wof:coterminous":[1713307415],"wof:country":"EE","wof:geomhash":"2f7bc4747a017edca70698e1d3200afb","wof:hierarchy":[{"continent_id":102191581,"country_id":85633135,"county_id":1713305627,"localadmin_id":1713306743,"locality_id":1310275921,"region_id":85682947}],"wof:id":1310275921,"wof:lang_x_official":["est"],"wof:lang_x_spoken":["est"],"wof:lastmodified":1596674934,"wof:name":"Kaisa","wof:parent_id":1713306743,"wof:placetype":"locality","wof:repo":"whosonfirst-data-admin-ee","wof:superseded_by":[],"wof:supersedes":[],"wof:tags":[]},"bbox":[22.7025,58.47417,22.7025,58.47417],"geometry":{"coordinates":[22.7025,58.47417],"type":"Point"}}