{"id":1209223519,"type":"Feature","properties":{"edtf:cessation":"uuuu","edtf:inception":"uuuu","geom:area":0,"geom:area_square_m":0,"geom:bbox":"22.78886,58.99852,22.78886,58.99852","geom:latitude":58.99852,"geom:longitude":22.78886,"gn:admin1_code":"2.0","gn:admin2_code":"205.0","gn:admin3_code":"1787.0","gn:asciiname":"Hausma","gn:country_code":"EE","gn:dem":6,"gn:feature_class":"P","gn:feature_code":"PPL","gn:geonameid":794853,"gn:latitude":58.99852,"gn:longitude":22.78886,"gn:modification_date":"2017-11-25","gn:name":"Hausma","gn:population":0,"gn:timezone":"Europe/Tallinn","iso:country":"EE","lbl:bbox":"22.76886,58.97852,22.80886,59.01852","lbl:max_zoom":18,"lbl:min_zoom":13.5,"mz:hierarchy_label":1,"mz:is_current":1,"mz:min_zoom":12,"name:deu_x_preferred":["Hausma"],"name:est_x_preferred":["Hausma"],"name:hye_x_preferred":["Հաուսմա"],"name:pol_x_preferred":["Hausma"],"name:spa_x_preferred":["Hausma"],"name:vol_x_preferred":["Hausma"],"src:geom":"geonames","wof:belongsto":[85682989,102191581,1713310637,85633135,1713305629],"wof:breaches":[],"wof:concordances":{"gn:id":794853,"wk:page":"Hausma"},"wof:coterminous":[1713310637],"wof:country":"EE","wof:geomhash":"73ff2f13cc5fa4d7b6f92c47b6423081","wof:hierarchy":[{"continent_id":102191581,"country_id":85633135,"county_id":1713305629,"localadmin_id":1713310637,"locality_id":1209223519,"region_id":85682989}],"wof:id":1209223519,"wof:lang_x_official":["est"],"wof:lang_x_spoken":["est"],"wof:lastmodified":1596670013,"wof:name":"Hausma","wof:parent_id":1713310637,"wof:placetype":"locality","wof:repo":"whosonfirst-data-admin-ee","wof:superseded_by":[],"wof:supersedes":[],"wof:tags":[]},"bbox":[22.78886,58.99852,22.78886,58.99852],"geometry":{"coordinates":[22.78886,58.99852],"type":"Point"}}