{"id":1360171085,"type":"Feature","properties":{"edtf:cessation":"uuuu","edtf:inception":"uuuu","geom:area":0,"geom:area_square_m":0,"geom:bbox":"24.45139,59.04917,24.45139,59.04917","geom:latitude":59.04917,"geom:longitude":24.45139,"gn:admin1_code":"13.0","gn:admin2_code":"503.0","gn:admin3_code":"9063.0","gn:asciiname":"Sirgu","gn:country_code":"EE","gn:dem":48,"gn:feature_class":"P","gn:feature_code":"PPL","gn:geonameid":588661,"gn:latitude":59.04917,"gn:longitude":24.45139,"gn:modification_date":"2017-11-25","gn:name":"Sirgu","gn:population":0,"gn:timezone":"Europe/Tallinn","iso:country":"EE","lbl:bbox":"24.43139,59.02917,24.47139,59.06917","lbl:max_zoom":18,"lbl:min_zoom":13.5,"mz:hierarchy_label":1,"mz:is_current":1,"mz:min_zoom":12,"name:est_x_preferred":["Sirgu"],"name:fra_x_preferred":["Sirgu"],"name:hye_x_preferred":["Սիռգու"],"name:nld_x_preferred":["Sirgu"],"name:pol_x_preferred":["Sirgu"],"name:spa_x_preferred":["Sirgu"],"name:ukr_x_preferred":["Сірґу"],"name:vol_x_preferred":["Sirgu"],"src:geom":"geonames","wof:belongsto":[85683013,102191581,1713311427,85633135,1713305747],"wof:breaches":[],"wof:concordances":{"gn:id":588661},"wof:country":"EE","wof:geomhash":"d35940b841713c1dca7b20489adc2f21","wof:hierarchy":[{"continent_id":102191581,"country_id":85633135,"county_id":1713305747,"localadmin_id":1713311427,"locality_id":1360171085,"region_id":85683013}],"wof:id":1360171085,"wof:lang_x_official":["est"],"wof:lang_x_spoken":["est"],"wof:lastmodified":1596662837,"wof:name":"Sirgu","wof:parent_id":1713311427,"wof:placetype":"locality","wof:repo":"whosonfirst-data-admin-ee","wof:superseded_by":[],"wof:supersedes":[],"wof:tags":[]},"bbox":[24.45139,59.04917,24.45139,59.04917],"geometry":{"coordinates":[24.45139,59.04917],"type":"Point"}}