{"id":1210030603,"type":"Feature","properties":{"edtf:cessation":"uuuu","edtf:inception":"uuuu","geom:area":0,"geom:area_square_m":0,"geom:bbox":"25.49111,59.44389,25.49111,59.44389","geom:latitude":59.44389,"geom:longitude":25.49111,"gn:admin1_code":"1.0","gn:admin2_code":"353.0","gn:admin3_code":"2046.0","gn:asciiname":"Ilmastalu","gn:country_code":"EE","gn:dem":54,"gn:feature_class":"P","gn:feature_code":"PPL","gn:geonameid":8618906,"gn:latitude":59.44389,"gn:longitude":25.49111,"gn:modification_date":"2017-11-25","gn:name":"Ilmastalu","gn:population":0,"gn:timezone":"Europe/Tallinn","iso:country":"EE","lbl:bbox":"25.47111,59.42389,25.51111,59.46389","lbl:max_zoom":18,"lbl:min_zoom":13.5,"mz:hierarchy_label":1,"mz:is_current":1,"mz:min_zoom":12,"name:est_x_preferred":["Ilmastalu"],"name:fra_x_preferred":["Ilmastalu"],"name:hye_x_preferred":["Իլմաստալու"],"name:nld_x_preferred":["Ilmastalu"],"name:pol_x_preferred":["Ilmastalu"],"name:rus_x_preferred":["Ильмасталу"],"name:spa_x_preferred":["Ilmastalu"],"name:und_x_variant":["Ilmatsalu"],"name:vol_x_preferred":["Ilmastalu"],"src:geom":"geonames","wof:belongsto":[85683055,102191581,1713305939,85633135,1713305725],"wof:breaches":[],"wof:concordances":{"gn:id":8618906,"wk:page":"Ilmastalu"},"wof:coterminous":[1713305939],"wof:country":"EE","wof:geomhash":"114bbd2eebf22f9a1a781bc3237926fd","wof:hierarchy":[{"continent_id":102191581,"country_id":85633135,"county_id":1713305725,"localadmin_id":1713305939,"locality_id":1210030603,"region_id":85683055}],"wof:id":1210030603,"wof:lang_x_official":["est"],"wof:lang_x_spoken":["est"],"wof:lastmodified":1596661841,"wof:name":"Ilmastalu","wof:parent_id":1713305939,"wof:placetype":"locality","wof:repo":"whosonfirst-data-admin-ee","wof:superseded_by":[],"wof:supersedes":[],"wof:tags":[]},"bbox":[25.49111,59.44389,25.49111,59.44389],"geometry":{"coordinates":[25.49111,59.44389],"type":"Point"}}