{"id":1344045359,"type":"Feature","properties":{"edtf:cessation":"uuuu","edtf:inception":"uuuu","geom:area":0,"geom:area_square_m":0,"geom:bbox":"23.78222,58.43444,23.78222,58.43444","geom:latitude":58.43444,"geom:longitude":23.78222,"gn:admin1_code":"11.0","gn:admin2_code":"430.0","gn:admin3_code":"6135.0","gn:asciiname":"Piha","gn:country_code":"EE","gn:dem":16,"gn:feature_class":"P","gn:feature_code":"PPL","gn:geonameid":589502,"gn:latitude":58.43444,"gn:longitude":23.78222,"gn:modification_date":"2017-11-25","gn:name":"Piha","gn:population":0,"gn:timezone":"Europe/Tallinn","iso:country":"EE","lbl:bbox":"23.76222,58.41444,23.80222,58.45444","lbl:max_zoom":18,"lbl:min_zoom":13.5,"mz:hierarchy_label":1,"mz:is_current":1,"mz:min_zoom":12,"name:est_x_preferred":["Piha"],"name:hye_x_preferred":["Պիհա"],"name:pol_x_preferred":["Piha"],"name:spa_x_preferred":["Piha"],"name:und_x_variant":["Pikha"],"name:vol_x_preferred":["Piha"],"src:geom":"geonames","wof:belongsto":[85683001,102191581,1713309029,85633135,1713305721],"wof:breaches":[],"wof:concordances":{"gn:id":589502,"wk:page":"Piha%2C_Estonia"},"wof:coterminous":[1713309029],"wof:country":"EE","wof:geomhash":"641ac19b2ec3d1f7984444a99d027bc8","wof:hierarchy":[{"continent_id":102191581,"country_id":85633135,"county_id":1713305721,"localadmin_id":1713309029,"locality_id":1344045359,"region_id":85683001}],"wof:id":1344045359,"wof:lang_x_official":["est"],"wof:lang_x_spoken":["est"],"wof:lastmodified":1596661699,"wof:name":"Piha","wof:parent_id":1713309029,"wof:placetype":"locality","wof:repo":"whosonfirst-data-admin-ee","wof:superseded_by":[],"wof:supersedes":[],"wof:tags":[]},"bbox":[23.78222,58.43444,23.78222,58.43444],"geometry":{"coordinates":[23.78222,58.43444],"type":"Point"}}