{
  "type": "Feature",
  "properties": {
    "iso:country":"FI",
    "wof:name":"Kallio",
    "wof:placetype":"neighbourhood"
},
  "geometry": {"coordinates":[24.95351624256735,60.18195909961933],"type":"Point"}
}