{"id":1310280857,"type":"Feature","properties":{"edtf:cessation":"uuuu","edtf:inception":"uuuu","geom:area":0,"geom:area_square_m":0,"geom:bbox":"26.54361,58.46472,26.54361,58.46472","geom:latitude":58.46472,"geom:longitude":26.54361,"gn:admin1_code":"18.0","gn:admin2_code":"796.0","gn:admin3_code":"9728.0","gn:asciiname":"Ovi","gn:cc2":"EE","gn:country_code":"EE","gn:dem":38,"gn:feature_class":"P","gn:feature_code":"PPL","gn:geonameid":589771,"gn:latitude":58.46472,"gn:longitude":26.54361,"gn:modification_date":"2017-11-25","gn:name":"Õvi","gn:population":0,"gn:timezone":"Europe/Tallinn","iso:country":"EE","lbl:bbox":"26.52361,58.44472,26.56361,58.48472","lbl:max_zoom":18,"lbl:min_zoom":13.5,"mz:hierarchy_label":1,"mz:is_current":1,"mz:min_zoom":12,"name:eng_x_preferred":["Õvi"],"name:rus_x_preferred":["Ыви"],"name:und_x_variant":["Yvi Pervyye","Õvi Üks"],"src:geom":"geonames","wof:belongsto":[85683009,102191581,1713308971,85633135,1713305659],"wof:breaches":[],"wof:concordances":{"gn:id":589771},"wof:coterminous":[1713308971],"wof:country":"EE","wof:geomhash":"5f7c7e4e2f33a3844092747c3269b399","wof:hierarchy":[{"continent_id":102191581,"country_id":85633135,"county_id":1713305659,"localadmin_id":1713308971,"locality_id":1310280857,"region_id":85683009}],"wof:id":1310280857,"wof:lang_x_official":["est"],"wof:lang_x_spoken":["est"],"wof:lastmodified":1596676471,"wof:name":"Ovi","wof:parent_id":1713308971,"wof:placetype":"locality","wof:repo":"whosonfirst-data-admin-ee","wof:superseded_by":[],"wof:supersedes":[],"wof:tags":[]},"bbox":[26.54361,58.46472,26.54361,58.46472],"geometry":{"coordinates":[26.54361,58.46472],"type":"Point"}}