{"id":1260369193,"type":"Feature","properties":{"edtf:cessation":"uuuu","edtf:inception":"uuuu","geom:area":0,"geom:area_square_m":0,"geom:bbox":"22.17083,58.18167,22.17083,58.18167","geom:latitude":58.18167,"geom:longitude":22.17083,"gn:admin1_code":"14.0","gn:admin2_code":"714.0","gn:admin3_code":"4899.0","gn:asciiname":"Metsalouka","gn:country_code":"EE","gn:dem":19,"gn:feature_class":"P","gn:feature_code":"PPL","gn:geonameid":8619797,"gn:latitude":58.18167,"gn:longitude":22.17083,"gn:modification_date":"2017-11-25","gn:name":"Metsalõuka","gn:population":0,"gn:timezone":"Europe/Tallinn","iso:country":"EE","lbl:bbox":"22.15083,58.16167,22.19083,58.20167","lbl:max_zoom":18,"lbl:min_zoom":13.5,"mz:hierarchy_label":1,"mz:is_current":1,"mz:min_zoom":12,"name:deu_x_preferred":["Metsalõuka"],"name:est_x_preferred":["Metsalõuka"],"name:fra_x_preferred":["Metsalõuka"],"name:hye_x_preferred":["Մեցալիուկա"],"name:nld_x_preferred":["Metsalõuka"],"name:pol_x_preferred":["Metsalõuka"],"name:spa_x_preferred":["Metsalõuka"],"name:ukr_x_preferred":["Метсалиука"],"name:und_x_variant":["Metsalauka"],"name:vol_x_preferred":["Metsalõuka"],"src:geom":"geonames","wof:belongsto":[85682947,102191581,1713306629,85633135,1713305627],"wof:breaches":[],"wof:concordances":{"gn:id":8619797,"wk:page":"Metsal%C3%B5uka"},"wof:coterminous":[1713306629],"wof:country":"EE","wof:geomhash":"092dcc3b46f09eed9dfa15e7d463fe97","wof:hierarchy":[{"continent_id":102191581,"country_id":85633135,"county_id":1713305627,"localadmin_id":1713306629,"locality_id":1260369193,"region_id":85682947}],"wof:id":1260369193,"wof:lang_x_official":["est"],"wof:lang_x_spoken":["est"],"wof:lastmodified":1596674928,"wof:name":"Metsalouka","wof:parent_id":1713306629,"wof:placetype":"locality","wof:repo":"whosonfirst-data-admin-ee","wof:superseded_by":[],"wof:supersedes":[],"wof:tags":[]},"bbox":[22.17083,58.18167,22.17083,58.18167],"geometry":{"coordinates":[22.17083,58.18167],"type":"Point"}}