{"id":1209206181,"type":"Feature","properties":{"edtf:cessation":"uuuu","edtf:inception":"uuuu","geom:area":0,"geom:area_square_m":0,"geom:bbox":"23.45778,58.94,23.45778,58.94","geom:latitude":58.94,"geom:longitude":23.45778,"gn:admin1_code":"7.0","gn:admin2_code":"184.0","gn:admin3_code":"5527.0","gn:asciiname":"Nomme","gn:country_code":"EE","gn:dem":2,"gn:feature_class":"P","gn:feature_code":"PPL","gn:geonameid":589957,"gn:latitude":58.94,"gn:longitude":23.45778,"gn:modification_date":"2017-11-25","gn:name":"Nõmme","gn:population":0,"gn:timezone":"Europe/Tallinn","iso:country":"EE","lbl:bbox":"23.43778,58.92,23.47778,58.96","lbl:max_zoom":18,"lbl:min_zoom":13.5,"mz:hierarchy_label":1,"mz:is_current":1,"mz:min_zoom":12,"name:deu_x_preferred":["Nõmme"],"name:est_x_preferred":["Nõmme"],"name:hye_x_preferred":["Նիմե"],"name:pol_x_preferred":["Nõmme"],"name:ukr_x_preferred":["Нимме"],"name:und_x_variant":["Nymme"],"name:vol_x_preferred":["Nõmme"],"src:geom":"geonames","wof:belongsto":[85683001,102191581,1713308497,85633135,1713305755],"wof:breaches":[],"wof:concordances":{"gn:id":589957,"wk:page":"N%C3%B5mme%2C_Ridala_Parish"},"wof:coterminous":[1713308497],"wof:country":"EE","wof:geomhash":"8d339ee25900961560adab2980573e8f","wof:hierarchy":[{"continent_id":102191581,"country_id":85633135,"county_id":1713305755,"localadmin_id":1713308497,"locality_id":1209206181,"region_id":85683001}],"wof:id":1209206181,"wof:lang_x_official":["est"],"wof:lang_x_spoken":["est"],"wof:lastmodified":1596662770,"wof:name":"Nomme","wof:parent_id":1713308497,"wof:placetype":"locality","wof:repo":"whosonfirst-data-admin-ee","wof:superseded_by":[],"wof:supersedes":[],"wof:tags":[]},"bbox":[23.45778,58.94,23.45778,58.94],"geometry":{"coordinates":[23.45778,58.94],"type":"Point"}}