{"id":1260157379,"type":"Feature","properties":{"edtf:cessation":"uuuu","edtf:inception":"uuuu","geom:area":0,"geom:area_square_m":0,"geom:bbox":"24.33222,58.70889,24.33222,58.70889","geom:latitude":58.70889,"geom:longitude":24.33222,"gn:admin1_code":"13.0","gn:admin2_code":"503.0","gn:admin3_code":"7946.0","gn:asciiname":"Jaedivere-Tagakuela","gn:country_code":"EE","gn:dem":15,"gn:feature_class":"P","gn:feature_code":"PPL","gn:geonameid":8618145,"gn:latitude":58.70889,"gn:longitude":24.33222,"gn:modification_date":"2017-11-25","gn:name":"Jädivere-Tagaküla","gn:population":0,"gn:timezone":"Europe/Tallinn","iso:country":"EE","lbl:bbox":"24.31222,58.68889,24.35222,58.72889","lbl:max_zoom":18,"lbl:min_zoom":13.5,"mz:hierarchy_label":1,"mz:is_current":1,"mz:min_zoom":12,"name:und_x_variant":["Jädivere-Tagaküla","Jädivere"],"src:geom":"geonames","wof:belongsto":[85683013,102191581,1713315641,85633135,1713305747],"wof:breaches":[],"wof:concordances":{"gn:id":8618145},"wof:country":"EE","wof:geomhash":"21888105768e4d2968139a733732dcda","wof:hierarchy":[{"continent_id":102191581,"country_id":85633135,"county_id":1713305747,"localadmin_id":1713315641,"locality_id":1260157379,"region_id":85683013}],"wof:id":1260157379,"wof:lang_x_official":["est"],"wof:lang_x_spoken":["est"],"wof:lastmodified":1596662841,"wof:name":"Jaedivere-Tagakuela","wof:parent_id":1713315641,"wof:placetype":"locality","wof:repo":"whosonfirst-data-admin-ee","wof:superseded_by":[],"wof:supersedes":[],"wof:tags":[]},"bbox":[24.33222,58.70889,24.33222,58.70889],"geometry":{"coordinates":[24.33222,58.70889],"type":"Point"}}