{"id":1276401859,"type":"Feature","properties":{"edtf:cessation":"uuuu","edtf:inception":"uuuu","geom:area":0,"geom:area_square_m":0,"geom:bbox":"26.29056,57.67056,26.29056,57.67056","geom:latitude":57.67056,"geom:longitude":26.29056,"gn:admin1_code":"19.0","gn:admin2_code":"855.0","gn:admin3_code":"3289.0","gn:asciiname":"Puegeri","gn:country_code":"EE","gn:dem":76,"gn:feature_class":"P","gn:feature_code":"PPL","gn:geonameid":589483,"gn:latitude":57.67056,"gn:longitude":26.29056,"gn:modification_date":"2017-11-25","gn:name":"Pügeri","gn:population":0,"gn:timezone":"Europe/Tallinn","iso:country":"EE","lbl:bbox":"26.27056,57.65056,26.31056,57.69056","lbl:max_zoom":18,"lbl:min_zoom":13.5,"mz:hierarchy_label":1,"mz:is_current":1,"mz:min_zoom":12,"name:und_x_variant":["Piiri","Pügeri"],"src:geom":"geonames","wof:belongsto":[85682941,102191581,1713313383,85633135,1713305753],"wof:breaches":[],"wof:concordances":{"gn:id":589483},"wof:country":"EE","wof:geomhash":"ae049f570b3d80234e1397c311b3d9d8","wof:hierarchy":[{"continent_id":102191581,"country_id":85633135,"county_id":1713305753,"localadmin_id":1713313383,"locality_id":1276401859,"region_id":85682941}],"wof:id":1276401859,"wof:lang_x_official":["est"],"wof:lang_x_spoken":["est"],"wof:lastmodified":1596661949,"wof:name":"Puegeri","wof:parent_id":1713313383,"wof:placetype":"locality","wof:repo":"whosonfirst-data-admin-ee","wof:superseded_by":[],"wof:supersedes":[],"wof:tags":[]},"bbox":[26.29056,57.67056,26.29056,57.67056],"geometry":{"coordinates":[26.29056,57.67056],"type":"Point"}}