{"id":1259685931,"type":"Feature","properties":{"edtf:cessation":"uuuu","edtf:inception":"uuuu","geom:area":0,"geom:area_square_m":0,"geom:bbox":"27.56167,59.24111,27.56167,59.24111","geom:latitude":59.24111,"geom:longitude":27.56167,"gn:admin1_code":"3.0","gn:admin2_code":"130.0","gn:admin3_code":"3377.0","gn:asciiname":"Konsu","gn:country_code":"EE","gn:dem":56,"gn:feature_class":"P","gn:feature_code":"PPL","gn:geonameid":591171,"gn:latitude":59.24111,"gn:longitude":27.56167,"gn:modification_date":"2017-11-25","gn:name":"Konsu","gn:population":0,"gn:timezone":"Europe/Tallinn","iso:country":"EE","lbl:bbox":"27.54167,59.22111,27.58167,59.26111","lbl:max_zoom":18,"lbl:min_zoom":13.5,"mz:hierarchy_label":1,"mz:is_current":1,"mz:min_zoom":12,"name:deu_x_preferred":["Konsu"],"name:est_x_preferred":["Konsu"],"name:fra_x_preferred":["Konsu"],"name:hye_x_preferred":["Կոնսու"],"name:pol_x_preferred":["Konsu"],"name:spa_x_preferred":["Konsu"],"name:vol_x_preferred":["Konsu"],"src:geom":"geonames","wof:belongsto":[85683059,102191581,1713313321,85633135,1713305693],"wof:breaches":[],"wof:concordances":{"gn:id":591171,"wk:page":"Konsu"},"wof:coterminous":[1713313321],"wof:country":"EE","wof:geomhash":"05e72f9109ebe5be8dafc2fd9fb4c716","wof:hierarchy":[{"continent_id":102191581,"country_id":85633135,"county_id":1713305693,"localadmin_id":1713313321,"locality_id":1259685931,"region_id":85683059}],"wof:id":1259685931,"wof:lang_x_official":["est"],"wof:lang_x_spoken":["est"],"wof:lastmodified":1596660733,"wof:name":"Konsu","wof:parent_id":1713313321,"wof:placetype":"locality","wof:repo":"whosonfirst-data-admin-ee","wof:superseded_by":[],"wof:supersedes":[],"wof:tags":[]},"bbox":[27.56167,59.24111,27.56167,59.24111],"geometry":{"coordinates":[27.56167,59.24111],"type":"Point"}}