{"id":1343471731,"type":"Feature","properties":{"edtf:cessation":"uuuu","edtf:inception":"uuuu","geom:area":0,"geom:area_square_m":0,"geom:bbox":"22.64139,58.76194,22.64139,58.76194","geom:latitude":58.76194,"geom:longitude":22.64139,"gn:admin1_code":"2.0","gn:admin2_code":"205.0","gn:admin3_code":"8656.0","gn:asciiname":"Ulja","gn:country_code":"EE","gn:dem":20,"gn:feature_class":"P","gn:feature_code":"PPL","gn:geonameid":588087,"gn:latitude":58.76194,"gn:longitude":22.64139,"gn:modification_date":"2017-11-25","gn:name":"Ulja","gn:population":0,"gn:timezone":"Europe/Tallinn","iso:country":"EE","lbl:bbox":"22.62139,58.74194,22.66139,58.78194","lbl:max_zoom":18,"lbl:min_zoom":13.5,"mz:hierarchy_label":1,"mz:is_current":1,"mz:min_zoom":12,"name:deu_x_preferred":["Ulja"],"name:est_x_preferred":["Ulja"],"name:fra_x_preferred":["Ulja"],"name:hye_x_preferred":["Ուլյա"],"name:pol_x_preferred":["Ulja"],"name:spa_x_preferred":["Ulja"],"name:und_x_variant":["Ul’ya"],"name:vol_x_preferred":["Ulja"],"src:geom":"geonames","wof:belongsto":[85682989,102191581,1713310801,85633135,1713305629],"wof:breaches":[],"wof:concordances":{"gn:id":588087,"wk:page":"Ulja"},"wof:coterminous":[1713310801],"wof:country":"EE","wof:geomhash":"8c1d1b994b70df96f4d665f2ff3e7e05","wof:hierarchy":[{"continent_id":102191581,"country_id":85633135,"county_id":1713305629,"localadmin_id":1713310801,"locality_id":1343471731,"region_id":85682989}],"wof:id":1343471731,"wof:lang_x_official":["est"],"wof:lang_x_spoken":["est"],"wof:lastmodified":1596670018,"wof:name":"Ulja","wof:parent_id":1713310801,"wof:placetype":"locality","wof:repo":"whosonfirst-data-admin-ee","wof:superseded_by":[],"wof:supersedes":[],"wof:tags":[]},"bbox":[22.64139,58.76194,22.64139,58.76194],"geometry":{"coordinates":[22.64139,58.76194],"type":"Point"}}