{"id":1293352285,"type":"Feature","properties":{"edtf:cessation":"uuuu","edtf:inception":"uuuu","geom:area":0,"geom:area_square_m":0,"geom:bbox":"25.59472,58.12972,25.59472,58.12972","geom:latitude":58.12972,"geom:longitude":25.59472,"gn:admin1_code":"20.0","gn:admin2_code":"480.0","gn:admin3_code":"5758.0","gn:asciiname":"Kadrina","gn:country_code":"EE","gn:dem":94,"gn:feature_class":"P","gn:feature_code":"PPL","gn:geonameid":591785,"gn:latitude":58.12972,"gn:longitude":25.59472,"gn:modification_date":"2017-11-25","gn:name":"Kadrina","gn:population":0,"gn:timezone":"Europe/Tallinn","iso:country":"EE","lbl:bbox":"25.57472,58.10972,25.61472,58.14972","lbl:max_zoom":18,"lbl:min_zoom":13.5,"mz:hierarchy_label":1,"mz:is_current":1,"mz:min_zoom":12,"name:ceb_x_preferred":["Kadrina"],"name:ces_x_preferred":["Kadrina"],"name:est_x_preferred":["Kadrina"],"name:fra_x_preferred":["Kadrina"],"name:hye_x_preferred":["Կադռինա"],"name:lit_x_preferred":["Kadrina"],"name:nld_x_preferred":["Kadrina"],"name:ron_x_preferred":["Kadrina"],"name:rus_x_preferred":["Кадрина"],"name:swe_x_preferred":["Kadrina"],"name:vol_x_preferred":["Kadrina"],"name:zho_x_preferred":["卡德里納"],"src:geom":"geonames","wof:belongsto":[85682985,102191581,1713311611,85633135,1713305661],"wof:breaches":[],"wof:concordances":{"gn:id":591785},"wof:country":"EE","wof:geomhash":"463b59dd5e0836c89e41cbb9236ab962","wof:hierarchy":[{"continent_id":102191581,"country_id":85633135,"county_id":1713305661,"localadmin_id":1713311611,"locality_id":1293352285,"region_id":85682985}],"wof:id":1293352285,"wof:lang_x_official":["est"],"wof:lang_x_spoken":["est"],"wof:lastmodified":1596661305,"wof:name":"Kadrina","wof:parent_id":1713311611,"wof:placetype":"locality","wof:repo":"whosonfirst-data-admin-ee","wof:superseded_by":[],"wof:supersedes":[],"wof:tags":[]},"bbox":[25.59472,58.12972,25.59472,58.12972],"geometry":{"coordinates":[25.59472,58.12972],"type":"Point"}}