{"id":1293275697,"type":"Feature","properties":{"edtf:cessation":"uuuu","edtf:inception":"uuuu","geom:area":0,"geom:area_square_m":0,"geom:bbox":"23.43722,58.63444,23.43722,58.63444","geom:latitude":58.63444,"geom:longitude":23.43722,"gn:admin1_code":"14.0","gn:admin2_code":"478.0","gn:admin3_code":"2987.0","gn:asciiname":"Kesse","gn:country_code":"EE","gn:dem":10,"gn:feature_class":"P","gn:feature_code":"PPL","gn:geonameid":8618414,"gn:latitude":58.63444,"gn:longitude":23.43722,"gn:modification_date":"2017-11-25","gn:name":"Kesse","gn:population":0,"gn:timezone":"Europe/Tallinn","iso:country":"EE","lbl:bbox":"23.41722,58.61444,23.45722,58.65444","lbl:max_zoom":18,"lbl:min_zoom":13.5,"mz:hierarchy_label":1,"mz:is_current":1,"mz:min_zoom":12,"name:und_x_variant":["Kesselaiu"],"src:geom":"geonames","wof:belongsto":[85682947,102191581,1713306257,85633135,1713305623],"wof:breaches":[],"wof:concordances":{"gn:id":8618414},"wof:coterminous":[1713306257],"wof:country":"EE","wof:geomhash":"c3ad6a9537c13d9a813e59452e456be1","wof:hierarchy":[{"continent_id":102191581,"country_id":85633135,"county_id":1713305623,"localadmin_id":1713306257,"locality_id":1293275697,"region_id":85682947}],"wof:id":1293275697,"wof:lang_x_official":["est"],"wof:lang_x_spoken":["est"],"wof:lastmodified":1596675301,"wof:name":"Kesse","wof:parent_id":1713306257,"wof:placetype":"locality","wof:repo":"whosonfirst-data-admin-ee","wof:superseded_by":[],"wof:supersedes":[],"wof:tags":[]},"bbox":[23.43722,58.63444,23.43722,58.63444],"geometry":{"coordinates":[23.43722,58.63444],"type":"Point"}}