{"id":1226667433,"type":"Feature","properties":{"edtf:cessation":"uuuu","edtf:inception":"uuuu","geom:area":0,"geom:area_square_m":0,"geom:bbox":"24.14778,58.73778,24.14778,58.73778","geom:latitude":58.73778,"geom:longitude":24.14778,"gn:admin1_code":"11.0","gn:admin2_code":"430.0","gn:admin3_code":"7117.0","gn:asciiname":"Rumba","gn:country_code":"EE","gn:dem":9,"gn:feature_class":"P","gn:feature_code":"PPL","gn:geonameid":588927,"gn:latitude":58.73778,"gn:longitude":24.14778,"gn:modification_date":"2017-11-25","gn:name":"Rumba","gn:population":0,"gn:timezone":"Europe/Tallinn","iso:country":"EE","lbl:bbox":"24.12778,58.71778,24.16778,58.75778","lbl:max_zoom":18,"lbl:min_zoom":13.5,"mz:hierarchy_label":1,"mz:is_current":1,"mz:min_zoom":12,"name:fas_x_preferred":["رومبا"],"name:spa_x_preferred":["Rumba criolla"],"src:geom":"geonames","wof:belongsto":[85683001,102191581,1713314211,85633135,1713305721],"wof:breaches":[],"wof:concordances":{"gn:id":588927},"wof:coterminous":[1713314211],"wof:country":"EE","wof:geomhash":"f3a14f119feaa113d431bd832035a363","wof:hierarchy":[{"continent_id":102191581,"country_id":85633135,"county_id":1713305721,"localadmin_id":1713314211,"locality_id":1226667433,"region_id":85683001}],"wof:id":1226667433,"wof:lang_x_official":["est"],"wof:lang_x_spoken":["est"],"wof:lastmodified":1596661692,"wof:name":"Rumba","wof:parent_id":1713314211,"wof:placetype":"locality","wof:repo":"whosonfirst-data-admin-ee","wof:superseded_by":[],"wof:supersedes":[],"wof:tags":[]},"bbox":[24.14778,58.73778,24.14778,58.73778],"geometry":{"coordinates":[24.14778,58.73778],"type":"Point"}}