{"id":1293863173,"type":"Feature","properties":{"edtf:cessation":"uuuu","edtf:inception":"uuuu","geom:area":0,"geom:area_square_m":0,"geom:bbox":"25.08889,59.02083,25.08889,59.02083","geom:latitude":59.02083,"geom:longitude":25.08889,"gn:admin1_code":"13.0","gn:admin2_code":"668.0","gn:admin3_code":"8305.0","gn:asciiname":"Toomja","gn:country_code":"EE","gn:dem":80,"gn:feature_class":"P","gn:feature_code":"PPL","gn:geonameid":588230,"gn:latitude":59.02083,"gn:longitude":25.08889,"gn:modification_date":"2017-11-25","gn:name":"Toomja","gn:population":0,"gn:timezone":"Europe/Tallinn","iso:country":"EE","lbl:bbox":"25.06889,59.00083,25.10889,59.04083","lbl:max_zoom":18,"lbl:min_zoom":13.5,"mz:hierarchy_label":1,"mz:is_current":1,"mz:min_zoom":12,"name:est_x_preferred":["Toomja"],"name:hye_x_preferred":["Տոոմյա"],"name:pol_x_preferred":["Toomja"],"name:sco_x_preferred":["Toomja"],"name:spa_x_preferred":["Toomja"],"name:vol_x_preferred":["Toomja"],"src:geom":"geonames","wof:belongsto":[85683013,102191581,1713311107,85633135,1713305711],"wof:breaches":[],"wof:concordances":{"gn:id":588230,"wk:page":"Toomja"},"wof:coterminous":[1713311107],"wof:country":"EE","wof:geomhash":"308e3bb17d2e9ebfd56d222a68b8bf66","wof:hierarchy":[{"continent_id":102191581,"country_id":85633135,"county_id":1713305711,"localadmin_id":1713311107,"locality_id":1293863173,"region_id":85683013}],"wof:id":1293863173,"wof:lang_x_official":["est"],"wof:lang_x_spoken":["est"],"wof:lastmodified":1596676730,"wof:name":"Toomja","wof:parent_id":1713311107,"wof:placetype":"locality","wof:repo":"whosonfirst-data-admin-ee","wof:superseded_by":[],"wof:supersedes":[],"wof:tags":[]},"bbox":[25.08889,59.02083,25.08889,59.02083],"geometry":{"coordinates":[25.08889,59.02083],"type":"Point"}}