{"id":1310104733,"type":"Feature","properties":{"edtf:cessation":"uuuu","edtf:inception":"uuuu","geom:area":0,"geom:area_square_m":0,"geom:bbox":"26.96194,58.73528,26.96194,58.73528","geom:latitude":58.73528,"geom:longitude":26.96194,"gn:admin1_code":"18.0","gn:admin2_code":"586.0","gn:admin3_code":"6111.0","gn:asciiname":"Perametsa","gn:country_code":"EE","gn:dem":49,"gn:feature_class":"P","gn:feature_code":"PPL","gn:geonameid":589514,"gn:latitude":58.73528,"gn:longitude":26.96194,"gn:modification_date":"2017-11-25","gn:name":"Perametsa","gn:population":0,"gn:timezone":"Europe/Tallinn","iso:country":"EE","lbl:bbox":"26.94194,58.71528,26.98194,58.75528","lbl:max_zoom":18,"lbl:min_zoom":13.5,"mz:hierarchy_label":1,"mz:is_current":1,"mz:min_zoom":12,"name:est_x_preferred":["Perametsa"],"name:nld_x_preferred":["Perametsa"],"name:pol_x_preferred":["Perametsa"],"name:vol_x_preferred":["Perametsa"],"src:geom":"geonames","wof:belongsto":[85682995,102191581,1713313911,85633135,1713305679],"wof:breaches":[],"wof:concordances":{"gn:id":589514},"wof:coterminous":[1713313911],"wof:country":"EE","wof:geomhash":"4e306236cff507c82d8f1c47d88885af","wof:hierarchy":[{"continent_id":102191581,"country_id":85633135,"county_id":1713305679,"localadmin_id":1713313911,"locality_id":1310104733,"region_id":85682995}],"wof:id":1310104733,"wof:lang_x_official":["est"],"wof:lang_x_spoken":["est"],"wof:lastmodified":1596660913,"wof:name":"Perametsa","wof:parent_id":1713313911,"wof:placetype":"locality","wof:repo":"whosonfirst-data-admin-ee","wof:superseded_by":[],"wof:supersedes":[],"wof:tags":[]},"bbox":[26.96194,58.73528,26.96194,58.73528],"geometry":{"coordinates":[26.96194,58.73528],"type":"Point"}}