{"id":1260191495,"type":"Feature","properties":{"edtf:cessation":"uuuu","edtf:inception":"uuuu","geom:area":0,"geom:area_square_m":0,"geom:bbox":"22.22927,58.88804,22.22927,58.88804","geom:latitude":58.88804,"geom:longitude":22.22927,"gn:admin1_code":"2.0","gn:admin2_code":"205.0","gn:admin3_code":"8209.0","gn:asciiname":"Tiharu","gn:country_code":"EE","gn:dem":17,"gn:feature_class":"P","gn:feature_code":"PPL","gn:geonameid":588302,"gn:latitude":58.88804,"gn:longitude":22.22927,"gn:modification_date":"2017-11-25","gn:name":"Tiharu","gn:population":0,"gn:timezone":"Europe/Tallinn","iso:country":"EE","lbl:bbox":"22.20927,58.86804,22.24927,58.90804","lbl:max_zoom":18,"lbl:min_zoom":13.5,"mz:hierarchy_label":1,"mz:is_current":1,"mz:min_zoom":12,"name:deu_x_preferred":["Tiharu"],"name:est_x_preferred":["Tiharu"],"name:hye_x_preferred":["Տիհառու"],"name:pol_x_preferred":["Tiharu"],"name:und_x_variant":["Tikharu"],"name:vol_x_preferred":["Tiharu"],"src:geom":"geonames","wof:belongsto":[85682989,102191581,1713310765,85633135,1713305629],"wof:breaches":[],"wof:concordances":{"gn:id":588302,"wk:page":"Tiharu"},"wof:coterminous":[1713310765],"wof:country":"EE","wof:geomhash":"2bdce46a87cb6c018117eec5c9baa333","wof:hierarchy":[{"continent_id":102191581,"country_id":85633135,"county_id":1713305629,"localadmin_id":1713310765,"locality_id":1260191495,"region_id":85682989}],"wof:id":1260191495,"wof:lang_x_official":["est"],"wof:lang_x_spoken":["est"],"wof:lastmodified":1596670004,"wof:name":"Tiharu","wof:parent_id":1713310765,"wof:placetype":"locality","wof:repo":"whosonfirst-data-admin-ee","wof:superseded_by":[],"wof:supersedes":[],"wof:tags":[]},"bbox":[22.22927,58.88804,22.22927,58.88804],"geometry":{"coordinates":[22.22927,58.88804],"type":"Point"}}