{"id":1326896719,"type":"Feature","properties":{"edtf:cessation":"uuuu","edtf:inception":"uuuu","geom:area":0,"geom:area_square_m":0,"geom:bbox":"27.07472,58.26694,27.07472,58.26694","geom:latitude":58.26694,"geom:longitude":27.07472,"gn:admin1_code":"18.0","gn:admin2_code":"291.0","gn:admin3_code":"2076.0","gn:asciiname":"Imste","gn:country_code":"EE","gn:dem":48,"gn:feature_class":"P","gn:feature_code":"PPL","gn:geonameid":794132,"gn:latitude":58.26694,"gn:longitude":27.07472,"gn:modification_date":"2017-11-25","gn:name":"Imste","gn:population":0,"gn:timezone":"Europe/Tallinn","iso:country":"EE","lbl:bbox":"27.05472,58.24694,27.09472,58.28694","lbl:max_zoom":18,"lbl:min_zoom":13.5,"mz:hierarchy_label":1,"mz:is_current":1,"mz:min_zoom":12,"src:geom":"geonames","wof:belongsto":[85682995,102191581,1713311291,85633135,1713305699],"wof:breaches":[],"wof:concordances":{"gn:id":794132},"wof:coterminous":[1713311291],"wof:country":"EE","wof:geomhash":"e44de8afc48ddd014febb62671ce84ff","wof:hierarchy":[{"continent_id":102191581,"country_id":85633135,"county_id":1713305699,"localadmin_id":1713311291,"locality_id":1326896719,"region_id":85682995}],"wof:id":1326896719,"wof:lang_x_official":["est"],"wof:lang_x_spoken":["est"],"wof:lastmodified":1596660666,"wof:name":"Imste","wof:parent_id":1713311291,"wof:placetype":"locality","wof:repo":"whosonfirst-data-admin-ee","wof:superseded_by":[],"wof:supersedes":[],"wof:tags":[]},"bbox":[27.07472,58.26694,27.07472,58.26694],"geometry":{"coordinates":[27.07472,58.26694],"type":"Point"}}