{
  "type": "Feature",
  "properties": {
    "iso:country":"FI",
    "wof:name":"Puistola",
    "wof:placetype":"neighbourhood"
},
  "geometry": {"coordinates":[25.04615621227508,60.27174669323062],"type":"Point"}
}