{"id":1243425355,"type":"Feature","properties":{"edtf:cessation":"uuuu","edtf:inception":"uuuu","geom:area":0,"geom:area_square_m":0,"geom:bbox":"22.92389,58.61,22.92389,58.61","geom:latitude":58.61,"geom:longitude":22.92389,"gn:admin1_code":"14.0","gn:admin2_code":"714.0","gn:admin3_code":"1695.0","gn:asciiname":"Jaani","gn:country_code":"EE","gn:dem":9,"gn:feature_class":"P","gn:feature_code":"PPL","gn:geonameid":794724,"gn:latitude":58.61,"gn:longitude":22.92389,"gn:modification_date":"2017-11-25","gn:name":"Jaani","gn:population":0,"gn:timezone":"Europe/Tallinn","iso:country":"EE","lbl:bbox":"22.90389,58.59,22.94389,58.63","lbl:max_zoom":18,"lbl:min_zoom":13.5,"mz:hierarchy_label":1,"mz:is_current":1,"mz:min_zoom":12,"name:deu_x_preferred":["Jaani"],"name:nds_x_preferred":["Jaani"],"src:geom":"geonames","wof:belongsto":[85682947,102191581,1713307265,85633135,1713305627],"wof:breaches":[],"wof:concordances":{"gn:id":794724,"wk:page":"Jaani"},"wof:coterminous":[1713307521],"wof:country":"EE","wof:geomhash":"97bac4a4451f1603d2ae64f47d2776d8","wof:hierarchy":[{"continent_id":102191581,"country_id":85633135,"county_id":1713305627,"localadmin_id":1713307265,"locality_id":1243425355,"region_id":85682947}],"wof:id":1243425355,"wof:lang_x_official":["est"],"wof:lang_x_spoken":["est"],"wof:lastmodified":1596674966,"wof:name":"Jaani","wof:parent_id":1713307265,"wof:placetype":"locality","wof:repo":"whosonfirst-data-admin-ee","wof:superseded_by":[],"wof:supersedes":[],"wof:tags":[]},"bbox":[22.92389,58.61,22.92389,58.61],"geometry":{"coordinates":[22.92389,58.61],"type":"Point"}}