{"id":1360205993,"type":"Feature","properties":{"edtf:cessation":"uuuu","edtf:inception":"uuuu","geom:area":0,"geom:area_square_m":0,"geom:bbox":"23.67667,58.64278,23.67667,58.64278","geom:latitude":58.64278,"geom:longitude":23.67667,"gn:admin1_code":"11.0","gn:admin2_code":"430.0","gn:admin3_code":"9478.0","gn:asciiname":"Voose","gn:country_code":"EE","gn:dem":22,"gn:feature_class":"P","gn:feature_code":"PPL","gn:geonameid":587461,"gn:latitude":58.64278,"gn:longitude":23.67667,"gn:modification_date":"2017-11-25","gn:name":"Voose","gn:population":0,"gn:timezone":"Europe/Tallinn","iso:country":"EE","lbl:bbox":"23.65667,58.62278,23.69667,58.66278","lbl:max_zoom":18,"lbl:min_zoom":13.5,"mz:hierarchy_label":1,"mz:is_current":1,"mz:min_zoom":12,"name:und_x_variant":["Myza Voze","Voose"],"src:geom":"geonames","wof:belongsto":[85683001,102191581,1713308795,85633135,1713305721],"wof:breaches":[],"wof:concordances":{"gn:id":587461,"wk:page":"Voose%2C_L%C3%A4%C3%A4ne_County"},"wof:coterminous":[1713308795],"wof:country":"EE","wof:geomhash":"2269eb22fd8402851af0fab6168c63a1","wof:hierarchy":[{"continent_id":102191581,"country_id":85633135,"county_id":1713305721,"localadmin_id":1713308795,"locality_id":1360205993,"region_id":85683001}],"wof:id":1360205993,"wof:lang_x_official":["est"],"wof:lang_x_spoken":["est"],"wof:lastmodified":1596661677,"wof:name":"Voose","wof:parent_id":1713308795,"wof:placetype":"locality","wof:repo":"whosonfirst-data-admin-ee","wof:superseded_by":[],"wof:supersedes":[],"wof:tags":[]},"bbox":[23.67667,58.64278,23.67667,58.64278],"geometry":{"coordinates":[23.67667,58.64278],"type":"Point"}}