{"id":1125936709,"type":"Feature","properties":{"edtf:cessation":"uuuu","edtf:inception":"uuuu","geom:area":0,"geom:area_square_m":0,"geom:bbox":"25.66056,58.52278,25.66056,58.52278","geom:latitude":58.52278,"geom:longitude":25.66056,"gn:country":"EE","gn:fcode":"PPL","gn:population":236,"iso:country":"EE","lbl:bbox":"25.64056,58.50278,25.68056,58.54278","lbl:latitude":58.52278,"lbl:longitude":25.66056,"lbl:max_zoom":17,"lbl:min_zoom":12.5,"mz:hierarchy_label":1,"mz:is_current":1,"mz:min_zoom":11,"mz:note":"Quattroshapes Point Gazetteer import 20170519","name:und_x_variant":["Yul’de"],"qs_pg:aaroncc":"EE","qs_pg:gn_country":"EE","qs_pg:gn_fcode":"PPL","qs_pg:gn_id":588099,"qs_pg:gn_pop":236,"qs_pg:name":"Ülde","qs_pg:name_adm0":"Eesti","qs_pg:name_adm1":"Viljandimaa","qs_pg:photos_9r":0,"qs_pg:photos_sr":0,"qs_pg:pop_sr":2,"qs_pg:qs_id":1274663,"qs_pg:qs_pg_placetype":"locality","qs_pg:qs_pg_placetype_gp":"Town","qs_pg:woe_adm0":23424805,"qs_pg:woe_id":846037,"src:geom":"qs_pg","src:lbl_centroid":"qs_pg","src:population":"geonames","woe:adm0_id":23424805,"woe:name_adm0":"Eesti","woe:name_adm1":"Viljandimaa","woe:placetype":"Town","wof:belongsto":[85682985,102191581,1713311639,85633135,1713305735],"wof:breaches":[],"wof:concordances":{"gn:id":588099,"gp:id":846037,"qs_pg:id":1274663},"wof:coterminous":[1713311639],"wof:country":"EE","wof:created":1497296990,"wof:geomhash":"29d8a1c000a34d7d61e8ba06bdfc7af0","wof:hierarchy":[{"continent_id":102191581,"country_id":85633135,"county_id":1713305735,"localadmin_id":1713311639,"locality_id":1125936709,"region_id":85682985}],"wof:id":1125936709,"wof:lang_x_official":["est"],"wof:lang_x_spoken":["est"],"wof:lastmodified":1596663464,"wof:name":"Ülde","wof:parent_id":1713311639,"wof:placetype":"locality","wof:population":236,"wof:population_rank":2,"wof:repo":"whosonfirst-data-admin-ee","wof:superseded_by":[],"wof:supersedes":[],"wof:tags":[]},"bbox":[25.66056,58.52278,25.66056,58.52278],"geometry":{"coordinates":[25.66056,58.52278],"type":"Point"}}