{"id":1276629515,"type":"Feature","properties":{"edtf:cessation":"uuuu","edtf:inception":"uuuu","geom:area":0,"geom:area_square_m":0,"geom:bbox":"25.58139,58.50583,25.58139,58.50583","geom:latitude":58.50583,"geom:longitude":25.58139,"gn:admin1_code":"20.0","gn:admin2_code":"615.0","gn:admin3_code":"4998.0","gn:asciiname":"Mudiste","gn:country_code":"EE","gn:dem":85,"gn:feature_class":"P","gn:feature_code":"PPL","gn:geonameid":590131,"gn:latitude":58.50583,"gn:longitude":25.58139,"gn:modification_date":"2017-11-25","gn:name":"Mudiste","gn:population":0,"gn:timezone":"Europe/Tallinn","iso:country":"EE","lbl:bbox":"25.56139,58.48583,25.60139,58.52583","lbl:max_zoom":18,"lbl:min_zoom":13.5,"mz:hierarchy_label":1,"mz:is_current":1,"mz:min_zoom":12,"src:geom":"geonames","wof:belongsto":[85682985,102191581,1713312277,85633135,1713305735],"wof:breaches":[],"wof:concordances":{"gn:id":590131},"wof:coterminous":[1713312277],"wof:country":"EE","wof:geomhash":"8ab955e8d6d8a16c1dfbbf3eef67e0c8","wof:hierarchy":[{"continent_id":102191581,"country_id":85633135,"county_id":1713305735,"localadmin_id":1713312277,"locality_id":1276629515,"region_id":85682985}],"wof:id":1276629515,"wof:lang_x_official":["est"],"wof:lang_x_spoken":["est"],"wof:lastmodified":1596663460,"wof:name":"Mudiste","wof:parent_id":1713312277,"wof:placetype":"locality","wof:repo":"whosonfirst-data-admin-ee","wof:superseded_by":[],"wof:supersedes":[],"wof:tags":[]},"bbox":[25.58139,58.50583,25.58139,58.50583],"geometry":{"coordinates":[25.58139,58.50583],"type":"Point"}}