{"id":1226326057,"type":"Feature","properties":{"edtf:cessation":"uuuu","edtf:inception":"uuuu","geom:area":0,"geom:area_square_m":0,"geom:bbox":"22.44389,58.39111,22.44389,58.39111","geom:latitude":58.39111,"geom:longitude":22.44389,"gn:admin1_code":"14.0","gn:admin2_code":"714.0","gn:admin3_code":"1731.0","gn:asciiname":"Hakjala","gn:cc2":"EE","gn:country_code":"EE","gn:dem":28,"gn:feature_class":"P","gn:feature_code":"PPL","gn:geonameid":592204,"gn:latitude":58.39111,"gn:longitude":22.44389,"gn:modification_date":"2017-11-25","gn:name":"Hakjala","gn:population":0,"gn:timezone":"Europe/Tallinn","iso:country":"EE","lbl:bbox":"22.42389,58.37111,22.46389,58.41111","lbl:max_zoom":18,"lbl:min_zoom":13.5,"mz:hierarchy_label":1,"mz:is_current":1,"mz:min_zoom":12,"name:deu_x_preferred":["Hakjala"],"name:est_x_preferred":["Hakjala"],"name:fra_x_preferred":["Hakjala"],"name:hye_x_preferred":["Հակյալա"],"name:nld_x_preferred":["Hakjala"],"name:pol_x_preferred":["Hakjala"],"name:spa_x_preferred":["Hakjala"],"name:ukr_x_preferred":["Гак'яла"],"name:und_x_variant":["Khak’yala"],"name:vol_x_preferred":["Hakjala"],"src:geom":"geonames","wof:belongsto":[85682947,102191581,1713307595,85633135,1713305627],"wof:breaches":[],"wof:concordances":{"gn:id":592204,"wk:page":"Hakjala"},"wof:coterminous":[1713307595],"wof:country":"EE","wof:geomhash":"e9e15a39c6b91ccb108634797c6c7a44","wof:hierarchy":[{"continent_id":102191581,"country_id":85633135,"county_id":1713305627,"localadmin_id":1713307595,"locality_id":1226326057,"region_id":85682947}],"wof:id":1226326057,"wof:lang_x_official":["est"],"wof:lang_x_spoken":["est"],"wof:lastmodified":1596674944,"wof:name":"Hakjala","wof:parent_id":1713307595,"wof:placetype":"locality","wof:repo":"whosonfirst-data-admin-ee","wof:superseded_by":[],"wof:supersedes":[],"wof:tags":[]},"bbox":[22.44389,58.39111,22.44389,58.39111],"geometry":{"coordinates":[22.44389,58.39111],"type":"Point"}}