{"id":1293553771,"type":"Feature","properties":{"edtf:cessation":"uuuu","edtf:inception":"uuuu","geom:area":0,"geom:area_square_m":0,"geom:bbox":"26.8725,57.725,26.8725,57.725","geom:latitude":57.725,"geom:longitude":26.8725,"gn:admin1_code":"21.0","gn:admin2_code":"698.0","gn:admin3_code":"1861.0","gn:asciiname":"Hinu","gn:country_code":"EE","gn:dem":123,"gn:feature_class":"P","gn:feature_code":"PPL","gn:geonameid":8619707,"gn:latitude":57.725,"gn:longitude":26.8725,"gn:modification_date":"2017-11-25","gn:name":"Hinu","gn:population":0,"gn:timezone":"Europe/Tallinn","iso:country":"EE","lbl:bbox":"26.8525,57.705,26.8925,57.745","lbl:max_zoom":18,"lbl:min_zoom":13.5,"mz:hierarchy_label":1,"mz:is_current":1,"mz:min_zoom":12,"name:und_x_variant":["Hino"],"src:geom":"geonames","wof:belongsto":[85682937,102191581,1713315039,85633135,1713305787],"wof:breaches":[],"wof:concordances":{"gn:id":8619707},"wof:coterminous":[1713315039],"wof:country":"EE","wof:geomhash":"ad2a6f2a49a7c8935b6f9d448e3a1ddf","wof:hierarchy":[{"continent_id":102191581,"country_id":85633135,"county_id":1713305787,"localadmin_id":1713315039,"locality_id":1293553771,"region_id":85682937}],"wof:id":1293553771,"wof:lang_x_official":["est"],"wof:lang_x_spoken":["est"],"wof:lastmodified":1596676900,"wof:name":"Hinu","wof:parent_id":1713315039,"wof:placetype":"locality","wof:repo":"whosonfirst-data-admin-ee","wof:superseded_by":[],"wof:supersedes":[],"wof:tags":[]},"bbox":[26.8725,57.725,26.8725,57.725],"geometry":{"coordinates":[26.8725,57.725],"type":"Point"}}