{"id":1360098893,"type":"Feature","properties":{"edtf:cessation":"uuuu","edtf:inception":"uuuu","geom:area":0,"geom:area_square_m":0,"geom:bbox":"25.26194,59.17389,25.26194,59.17389","geom:latitude":59.17389,"geom:longitude":25.26194,"gn:admin1_code":"1.0","gn:admin2_code":"338.0","gn:admin3_code":"6872.0","gn:asciiname":"Raveliku","gn:country_code":"EE","gn:dem":65,"gn:feature_class":"P","gn:feature_code":"PPL","gn:geonameid":793275,"gn:latitude":59.17389,"gn:longitude":25.26194,"gn:modification_date":"2017-11-25","gn:name":"Raveliku","gn:population":0,"gn:timezone":"Europe/Tallinn","iso:country":"EE","lbl:bbox":"25.24194,59.15389,25.28194,59.19389","lbl:max_zoom":18,"lbl:min_zoom":13.5,"mz:hierarchy_label":1,"mz:is_current":1,"mz:min_zoom":12,"name:est_x_preferred":["Raveliku"],"name:fra_x_preferred":["Raveliku"],"name:hye_x_preferred":["Ռավելիկու"],"name:pol_x_preferred":["Raveliku"],"name:spa_x_preferred":["Raveliku"],"name:vol_x_preferred":["Raveliku"],"src:geom":"geonames","wof:belongsto":[85683055,102191581,1713306297,85633135,1713305665],"wof:breaches":[],"wof:concordances":{"gn:id":793275,"wk:page":"Raveliku"},"wof:coterminous":[1713306297],"wof:country":"EE","wof:geomhash":"87ed9deff9c2e3f874404de1fe40bb66","wof:hierarchy":[{"continent_id":102191581,"country_id":85633135,"county_id":1713305665,"localadmin_id":1713306297,"locality_id":1360098893,"region_id":85683055}],"wof:id":1360098893,"wof:lang_x_official":["est"],"wof:lang_x_spoken":["est"],"wof:lastmodified":1596661347,"wof:name":"Raveliku","wof:parent_id":1713306297,"wof:placetype":"locality","wof:repo":"whosonfirst-data-admin-ee","wof:superseded_by":[],"wof:supersedes":[],"wof:tags":[]},"bbox":[25.26194,59.17389,25.26194,59.17389],"geometry":{"coordinates":[25.26194,59.17389],"type":"Point"}}