{"id":1243542943,"type":"Feature","properties":{"edtf:cessation":"uuuu","edtf:inception":"uuuu","geom:area":0,"geom:area_square_m":0,"geom:bbox":"25.01667,58.11667,25.01667,58.11667","geom:latitude":58.11667,"geom:longitude":25.01667,"gn:admin1_code":"11.0","gn:admin2_code":"712.0","gn:admin3_code":"4235.0","gn:asciiname":"Pati","gn:country_code":"EE","gn:dem":82,"gn:feature_class":"P","gn:feature_code":"PPL","gn:geonameid":589559,"gn:latitude":58.11667,"gn:longitude":25.01667,"gn:modification_date":"2017-11-25","gn:name":"Pati","gn:population":0,"gn:timezone":"Europe/Tallinn","iso:country":"EE","lbl:bbox":"24.99667,58.09667,25.03667,58.13667","lbl:max_zoom":18,"lbl:min_zoom":13.5,"mz:hierarchy_label":1,"mz:is_current":1,"mz:min_zoom":12,"name:ceb_x_preferred":["Pati"],"name:deu_x_preferred":["Pati"],"name:fas_x_preferred":["پاتی"],"name:fas_x_variant":["پتی"],"name:fra_x_preferred":["Pati"],"name:heb_x_preferred":["פטי"],"name:hin_x_preferred":["पाटी"],"name:hun_x_preferred":["Pati"],"name:ind_x_preferred":["Pati"],"name:ita_x_preferred":["Pati"],"name:kor_x_preferred":["파티"],"name:mlg_x_preferred":["Pati"],"name:nld_x_preferred":["Pati"],"name:pol_x_preferred":["Pati"],"name:por_x_preferred":["Pati"],"name:rus_x_preferred":["Пати"],"name:swe_x_preferred":["Pati"],"name:tur_x_preferred":["Pati"],"name:ukr_x_preferred":["Паті"],"name:und_x_variant":["Myza Pati"],"name:urd_x_preferred":["پاتی"],"name:vie_x_preferred":["Pati"],"name:zho_cn_x_preferred":["巴蒂"],"name:zho_tw_x_preferred":["帕蒂"],"src:geom":"geonames","wof:belongsto":[85682981,102191581,1713313019,85633135,1713305705],"wof:breaches":[],"wof:concordances":{"gn:id":589559},"wof:country":"EE","wof:geomhash":"14cb699f69279811f49eeb227e563028","wof:hierarchy":[{"continent_id":102191581,"country_id":85633135,"county_id":1713305705,"localadmin_id":1713313019,"locality_id":1243542943,"region_id":85682981}],"wof:id":1243542943,"wof:lang_x_official":["est"],"wof:lang_x_spoken":["est"],"wof:lastmodified":1636502245,"wof:name":"Pati","wof:parent_id":1713313019,"wof:placetype":"locality","wof:repo":"whosonfirst-data-admin-ee","wof:superseded_by":[],"wof:supersedes":[],"wof:tags":[]},"bbox":[25.01667,58.11667,25.01667,58.11667],"geometry":{"coordinates":[25.01667,58.11667],"type":"Point"}}