{"id":1209432593,"type":"Feature","properties":{"edtf:cessation":"uuuu","edtf:inception":"uuuu","geom:area":0,"geom:area_square_m":0,"geom:bbox":"24.12028,59.23306,24.12028,59.23306","geom:latitude":59.23306,"geom:longitude":24.12028,"gn:admin1_code":"1.0","gn:admin2_code":"431.0","gn:admin3_code":"4019.0","gn:asciiname":"Kloostri","gn:country_code":"EE","gn:dem":8,"gn:feature_class":"P","gn:feature_code":"PPL","gn:geonameid":591302,"gn:latitude":59.23306,"gn:longitude":24.12028,"gn:modification_date":"2017-11-25","gn:name":"Kloostri","gn:population":0,"gn:timezone":"Europe/Tallinn","iso:country":"EE","lbl:bbox":"24.10028,59.21306,24.14028,59.25306","lbl:max_zoom":18,"lbl:min_zoom":13.5,"mz:hierarchy_label":1,"mz:is_current":1,"mz:min_zoom":12,"name:deu_x_preferred":["Kloostri"],"name:est_x_preferred":["Kloostri"],"name:hye_x_preferred":["Կլոոստռի"],"name:nld_x_preferred":["Kloostri"],"name:pol_x_preferred":["Kloostri"],"name:spa_x_preferred":["Kloostri"],"name:ukr_x_preferred":["Клоострі"],"name:und_x_variant":["Klostri","Kloostri Asundus","Kloostri-Metslõugu"],"name:vol_x_preferred":["Kloostri"],"src:geom":"geonames","wof:belongsto":[85683055,102191581,1713307861,85633135,1713305737],"wof:breaches":[],"wof:concordances":{"gn:id":591302},"wof:country":"EE","wof:geomhash":"6f6e64e4028f3295099d99dec6a58a06","wof:hierarchy":[{"continent_id":102191581,"country_id":85633135,"county_id":1713305737,"localadmin_id":1713307861,"locality_id":1209432593,"region_id":85683055}],"wof:id":1209432593,"wof:lang_x_official":["est"],"wof:lang_x_spoken":["est"],"wof:lastmodified":1596663322,"wof:name":"Kloostri","wof:parent_id":1713307861,"wof:placetype":"locality","wof:repo":"whosonfirst-data-admin-ee","wof:superseded_by":[],"wof:supersedes":[],"wof:tags":[]},"bbox":[24.12028,59.23306,24.12028,59.23306],"geometry":{"coordinates":[24.12028,59.23306],"type":"Point"}}