{"id":1276521713,"type":"Feature","properties":{"edtf:cessation":"uuuu","edtf:inception":"uuuu","geom:area":0,"geom:area_square_m":0,"geom:bbox":"27.31722,57.61111,27.31722,57.61111","geom:latitude":57.61111,"geom:longitude":27.31722,"gn:admin1_code":"21.0","gn:admin2_code":"698.0","gn:admin3_code":"7272.0","gn:asciiname":"Saagrimaee","gn:country_code":"EE","gn:dem":188,"gn:feature_class":"P","gn:feature_code":"PPL","gn:geonameid":8619841,"gn:latitude":57.61111,"gn:longitude":27.31722,"gn:modification_date":"2017-11-25","gn:name":"Saagrimäe","gn:population":0,"gn:timezone":"Europe/Tallinn","iso:country":"EE","lbl:bbox":"27.29722,57.59111,27.33722,57.63111","lbl:max_zoom":18,"lbl:min_zoom":13.5,"mz:hierarchy_label":1,"mz:is_current":1,"mz:min_zoom":12,"name:und_x_variant":["Saagrimäe","Sagrimäe"],"src:geom":"geonames","wof:belongsto":[85682937,102191581,1713316055,85633135,1713305787],"wof:breaches":[],"wof:concordances":{"gn:id":8619841},"wof:coterminous":[1713316055],"wof:country":"EE","wof:geomhash":"5a048036bc60b876ec3adbd53813587c","wof:hierarchy":[{"continent_id":102191581,"country_id":85633135,"county_id":1713305787,"localadmin_id":1713316055,"locality_id":1276521713,"region_id":85682937}],"wof:id":1276521713,"wof:lang_x_official":["est"],"wof:lang_x_spoken":["est"],"wof:lastmodified":1596676894,"wof:name":"Saagrimaee","wof:parent_id":1713316055,"wof:placetype":"locality","wof:repo":"whosonfirst-data-admin-ee","wof:superseded_by":[],"wof:supersedes":[],"wof:tags":[]},"bbox":[27.31722,57.61111,27.31722,57.61111],"geometry":{"coordinates":[27.31722,57.61111],"type":"Point"}}