{"id":1226741403,"type":"Feature","properties":{"edtf:cessation":"uuuu","edtf:inception":"uuuu","geom:area":0,"geom:area_square_m":0,"geom:bbox":"23.49028,58.86944,23.49028,58.86944","geom:latitude":58.86944,"geom:longitude":23.49028,"gn:admin1_code":"7.0","gn:admin2_code":"184.0","gn:admin3_code":"8321.0","gn:asciiname":"Tanska","gn:country_code":"EE","gn:dem":12,"gn:feature_class":"P","gn:feature_code":"PPL","gn:geonameid":588351,"gn:latitude":58.86944,"gn:longitude":23.49028,"gn:modification_date":"2017-11-25","gn:name":"Tanska","gn:population":0,"gn:timezone":"Europe/Tallinn","iso:country":"EE","lbl:bbox":"23.47028,58.84944,23.51028,58.88944","lbl:max_zoom":18,"lbl:min_zoom":13.5,"mz:hierarchy_label":1,"mz:is_current":1,"mz:min_zoom":12,"name:deu_x_preferred":["Tanska"],"name:est_x_preferred":["Tanska"],"name:hye_x_preferred":["Տանսկա"],"name:pol_x_preferred":["Tanska"],"name:ukr_x_preferred":["Танска"],"name:vol_x_preferred":["Tanska"],"src:geom":"geonames","wof:belongsto":[85683001,102191581,1713308387,85633135,1713305755],"wof:breaches":[],"wof:concordances":{"gn:id":588351,"wk:page":"Tanska%2C_Estonia"},"wof:coterminous":[1713308387],"wof:country":"EE","wof:geomhash":"d0f8f19157db78ca28d286b293f7712e","wof:hierarchy":[{"continent_id":102191581,"country_id":85633135,"county_id":1713305755,"localadmin_id":1713308387,"locality_id":1226741403,"region_id":85683001}],"wof:id":1226741403,"wof:lang_x_official":["est"],"wof:lang_x_spoken":["est"],"wof:lastmodified":1596662773,"wof:name":"Tanska","wof:parent_id":1713308387,"wof:placetype":"locality","wof:repo":"whosonfirst-data-admin-ee","wof:superseded_by":[],"wof:supersedes":[],"wof:tags":[]},"bbox":[23.49028,58.86944,23.49028,58.86944],"geometry":{"coordinates":[23.49028,58.86944],"type":"Point"}}