{"id":1209217623,"type":"Feature","properties":{"edtf:cessation":"uuuu","edtf:inception":"uuuu","geom:area":0,"geom:area_square_m":0,"geom:bbox":"22.47626,58.78486,22.47626,58.78486","geom:latitude":58.78486,"geom:longitude":22.47626,"gn:admin1_code":"2.0","gn:admin2_code":"205.0","gn:admin3_code":"3160.0","gn:asciiname":"Kitsa","gn:country_code":"EE","gn:dem":10,"gn:feature_class":"P","gn:feature_code":"PPL","gn:geonameid":591332,"gn:latitude":58.78486,"gn:longitude":22.47626,"gn:modification_date":"2017-11-25","gn:name":"Kitsa","gn:population":0,"gn:timezone":"Europe/Tallinn","iso:country":"EE","lbl:bbox":"22.45626,58.76486,22.49626,58.80486","lbl:max_zoom":18,"lbl:min_zoom":13.5,"mz:hierarchy_label":1,"mz:is_current":1,"mz:min_zoom":12,"name:deu_x_preferred":["Kitsa"],"name:est_x_preferred":["Kitsa"],"name:fra_x_preferred":["Kitsa"],"name:hye_x_preferred":["Կիցա"],"name:pol_x_preferred":["Kitsa"],"name:spa_x_preferred":["Kitsa"],"name:vol_x_preferred":["Kitsa"],"src:geom":"geonames","wof:belongsto":[85682989,102191581,1713310253,85633135,1713305629],"wof:breaches":[],"wof:concordances":{"gn:id":591332,"wk:page":"Kitsa%2C_Estonia"},"wof:coterminous":[1713310253],"wof:country":"EE","wof:geomhash":"ffb3ae6dd084243fb62f04928df60598","wof:hierarchy":[{"continent_id":102191581,"country_id":85633135,"county_id":1713305629,"localadmin_id":1713310253,"locality_id":1209217623,"region_id":85682989}],"wof:id":1209217623,"wof:lang_x_official":["est"],"wof:lang_x_spoken":["est"],"wof:lastmodified":1596670012,"wof:name":"Kitsa","wof:parent_id":1713310253,"wof:placetype":"locality","wof:repo":"whosonfirst-data-admin-ee","wof:superseded_by":[],"wof:supersedes":[],"wof:tags":[]},"bbox":[22.47626,58.78486,22.47626,58.78486],"geometry":{"coordinates":[22.47626,58.78486],"type":"Point"}}