{"id":1343848827,"type":"Feature","properties":{"edtf:cessation":"uuuu","edtf:inception":"uuuu","geom:area":0,"geom:area_square_m":0,"geom:bbox":"25.95194,59.36556,25.95194,59.36556","geom:latitude":59.36556,"geom:longitude":25.95194,"gn:admin1_code":"8.0","gn:admin2_code":"272.0","gn:admin3_code":"3823.0","gn:asciiname":"Korvekuela","gn:country_code":"EE","gn:dem":98,"gn:feature_class":"P","gn:feature_code":"PPL","gn:geonameid":591088,"gn:latitude":59.36556,"gn:longitude":25.95194,"gn:modification_date":"2017-11-25","gn:name":"Kõrveküla","gn:population":0,"gn:timezone":"Europe/Tallinn","iso:country":"EE","lbl:bbox":"25.93194,59.34556,25.97194,59.38556","lbl:max_zoom":18,"lbl:min_zoom":13.5,"mz:hierarchy_label":1,"mz:is_current":1,"mz:min_zoom":12,"name:und_x_variant":["Kyrve","Kõrve","Kõrveküla"],"src:geom":"geonames","wof:belongsto":[85683049,102191581,1713312507,85633135,1713305723],"wof:breaches":[],"wof:concordances":{"gn:id":591088},"wof:coterminous":[1713312507],"wof:country":"EE","wof:geomhash":"6e7429332add6f974465cc36e547b4e8","wof:hierarchy":[{"continent_id":102191581,"country_id":85633135,"county_id":1713305723,"localadmin_id":1713312507,"locality_id":1343848827,"region_id":85683049}],"wof:id":1343848827,"wof:lang_x_official":["est"],"wof:lang_x_spoken":["est"],"wof:lastmodified":1596661731,"wof:name":"Korvekuela","wof:parent_id":1713312507,"wof:placetype":"locality","wof:repo":"whosonfirst-data-admin-ee","wof:superseded_by":[],"wof:supersedes":[],"wof:tags":[]},"bbox":[25.95194,59.36556,25.95194,59.36556],"geometry":{"coordinates":[25.95194,59.36556],"type":"Point"}}