{"id":1126017661,"type":"Feature","properties":{"edtf:cessation":"uuuu","edtf:inception":"uuuu","geom:area":0,"geom:area_square_m":0,"geom:bbox":"25.12528,59.04333,25.12528,59.04333","geom:latitude":59.04333,"geom:longitude":25.12528,"gn:country":"EE","gn:fcode":"PPL","gn:population":385,"iso:country":"EE","lbl:bbox":"25.10528,59.02333,25.14528,59.06333","lbl:latitude":59.04333,"lbl:longitude":25.12528,"lbl:max_zoom":17,"lbl:min_zoom":12.5,"mz:hierarchy_label":1,"mz:is_current":1,"mz:min_zoom":11,"mz:note":"Quattroshapes Point Gazetteer import 20170519","name:bul_x_preferred":["Куимеца"],"name:ceb_x_preferred":["Kuimetsa"],"name:eng_x_preferred":["Kuimetsa"],"name:est_x_preferred":["Kuimetsa"],"name:hye_x_preferred":["Կուիմեցա"],"name:nld_x_preferred":["Kuimetsa"],"name:pol_x_preferred":["Kuimetsa"],"name:rus_x_preferred":["Куйметса"],"name:sco_x_preferred":["Kuimetsa"],"name:spa_x_preferred":["Kuimetsa"],"name:swe_x_preferred":["Kuimetsa"],"name:und_x_variant":["Kuymetsa"],"name:vol_x_preferred":["Kuimetsa"],"qs_pg:aaroncc":"EE","qs_pg:gn_country":"EE","qs_pg:gn_fcode":"PPL","qs_pg:gn_id":591026,"qs_pg:gn_pop":385,"qs_pg:name":"Kuimetsa","qs_pg:name_adm0":"Eesti","qs_pg:name_adm1":"Raplamaa","qs_pg:photos_9k":1,"qs_pg:photos_9r":1,"qs_pg:photos_all":1,"qs_pg:photos_sr":0,"qs_pg:pop_sr":2,"qs_pg:qs_id":940387,"qs_pg:qs_pg_placetype":"locality","qs_pg:qs_pg_placetype_gp":"Town","qs_pg:woe_adm0":23424805,"qs_pg:woe_id":843297,"src:geom":"qs_pg","src:lbl_centroid":"qs_pg","src:population":"geonames","woe:adm0_id":23424805,"woe:name_adm0":"Eesti","woe:name_adm1":"Raplamaa","woe:placetype":"Town","wof:belongsto":[85683013,102191581,1713313367,85633135,1713305711],"wof:breaches":[],"wof:concordances":{"gn:id":591026,"gp:id":843297,"qs_pg:id":940387,"wd:id":"Q3467369"},"wof:coterminous":[1713313367],"wof:country":"EE","wof:created":1497300648,"wof:geomhash":"2c469fd573e0ec666b54608a1cca5941","wof:hierarchy":[{"continent_id":102191581,"country_id":85633135,"county_id":1713305711,"localadmin_id":1713313367,"locality_id":1126017661,"region_id":85683013}],"wof:id":1126017661,"wof:lang_x_official":["est"],"wof:lang_x_spoken":["est"],"wof:lastmodified":1596676725,"wof:name":"Kuimetsa","wof:parent_id":1713313367,"wof:placetype":"locality","wof:population":385,"wof:population_rank":2,"wof:repo":"whosonfirst-data-admin-ee","wof:superseded_by":[],"wof:supersedes":[],"wof:tags":[]},"bbox":[25.12528,59.04333,25.12528,59.04333],"geometry":{"coordinates":[25.12528,59.04333],"type":"Point"}}