{"id":1276405135,"type":"Feature","properties":{"edtf:cessation":"uuuu","edtf:inception":"uuuu","geom:area":0,"geom:area_square_m":0,"geom:bbox":"26.55389,58.05611,26.55389,58.05611","geom:latitude":58.05611,"geom:longitude":26.55389,"gn:admin1_code":"19.0","gn:admin2_code":"557.0","gn:admin3_code":"6252.0","gn:asciiname":"Maeekuela","gn:country_code":"EE","gn:dem":150,"gn:feature_class":"P","gn:feature_code":"PPL","gn:geonameid":8620550,"gn:latitude":58.05611,"gn:longitude":26.55389,"gn:modification_date":"2017-11-25","gn:name":"Mäeküla","gn:population":0,"gn:timezone":"Europe/Tallinn","iso:country":"EE","lbl:bbox":"26.53389,58.03611,26.57389,58.07611","lbl:max_zoom":18,"lbl:min_zoom":13.5,"mz:hierarchy_label":1,"mz:is_current":1,"mz:min_zoom":12,"src:geom":"geonames","wof:belongsto":[85682941,102191581,1713314177,85633135,1713305759],"wof:breaches":[],"wof:concordances":{"gn:id":8620550},"wof:country":"EE","wof:geomhash":"11c85ec718403050a54e4b7d6dc0ed70","wof:hierarchy":[{"continent_id":102191581,"country_id":85633135,"county_id":1713305759,"localadmin_id":1713314177,"locality_id":1276405135,"region_id":85682941}],"wof:id":1276405135,"wof:lang_x_official":["est"],"wof:lang_x_spoken":["est"],"wof:lastmodified":1596661876,"wof:name":"Maeekuela","wof:parent_id":1713314177,"wof:placetype":"locality","wof:repo":"whosonfirst-data-admin-ee","wof:superseded_by":[],"wof:supersedes":[],"wof:tags":[]},"bbox":[26.55389,58.05611,26.55389,58.05611],"geometry":{"coordinates":[26.55389,58.05611],"type":"Point"}}