{"id":1125819289,"type":"Feature","properties":{"edtf:cessation":"uuuu","edtf:inception":"uuuu","geom:area":0,"geom:area_square_m":0,"geom:bbox":"27.01278,58.13056,27.01278,58.13056","geom:latitude":58.13056,"geom:longitude":27.01278,"gn:country":"EE","gn:fcode":"PPL","gn:population":127,"iso:country":"EE","lbl:bbox":"26.99278,58.11056,27.03278,58.15056","lbl:latitude":58.13056,"lbl:longitude":27.01278,"lbl:max_zoom":18,"lbl:min_zoom":13,"mz:hierarchy_label":1,"mz:is_current":1,"mz:min_zoom":11,"mz:note":"Quattroshapes Point Gazetteer import 20170519","name:ceb_x_preferred":["Kiidjärve"],"name:eng_x_preferred":["Kiidjärve"],"name:est_x_preferred":["Kiidjärve"],"name:hye_x_preferred":["Կիիդյեռվե"],"name:nld_x_preferred":["Kiidjärve"],"name:pol_x_preferred":["Kiidjärve"],"name:rus_x_preferred":["Кийдъярве"],"name:spa_x_preferred":["Kiidjärve"],"name:swe_x_preferred":["Kiidjärve"],"name:ukr_x_preferred":["Кіїд'ярве"],"name:und_x_variant":["Kid’yarve"],"name:vol_x_preferred":["Kiidjärve"],"qs_pg:aaroncc":"EE","qs_pg:gn_country":"EE","qs_pg:gn_fcode":"PPL","qs_pg:gn_id":591411,"qs_pg:gn_pop":127,"qs_pg:name":"Kiidjärve","qs_pg:name_adm0":"Eesti","qs_pg:name_adm1":"Põlvamaa","qs_pg:photos":16,"qs_pg:photos_1k":3,"qs_pg:photos_9k":1,"qs_pg:photos_9r":1,"qs_pg:photos_all":16,"qs_pg:photos_sr":1,"qs_pg:pop_sr":1,"qs_pg:qs_id":506319,"qs_pg:qs_pg_placetype":"locality","qs_pg:qs_pg_placetype_gp":"Town","qs_pg:woe_adm0":23424805,"qs_pg:woe_id":842927,"src:geom":"qs_pg","src:lbl_centroid":"qs_pg","src:population":"geonames","woe:adm0_id":23424805,"woe:name_adm0":"Eesti","woe:name_adm1":"Põlvamaa","woe:placetype":"Town","wof:belongsto":[85682955,102191581,1713313055,85633135,1713305791],"wof:breaches":[],"wof:concordances":{"gn:id":591411,"gp:id":842927,"qs_pg:id":506319,"wd:id":"Q3470184"},"wof:coterminous":[1713313055],"wof:country":"EE","wof:created":1497291979,"wof:geomhash":"6c05f5a9a2a089eea3e3ee7534149839","wof:hierarchy":[{"continent_id":102191581,"country_id":85633135,"county_id":1713305791,"localadmin_id":1713313055,"locality_id":1125819289,"region_id":85682955}],"wof:id":1125819289,"wof:lang_x_official":["est"],"wof:lang_x_spoken":["est"],"wof:lastmodified":1596676959,"wof:name":"Kiidjärve","wof:parent_id":1713313055,"wof:placetype":"locality","wof:population":127,"wof:population_rank":1,"wof:repo":"whosonfirst-data-admin-ee","wof:superseded_by":[],"wof:supersedes":[],"wof:tags":[]},"bbox":[27.01278,58.13056,27.01278,58.13056],"geometry":{"coordinates":[27.01278,58.13056],"type":"Point"}}