{"id":1293407801,"type":"Feature","properties":{"edtf:cessation":"uuuu","edtf:inception":"uuuu","geom:area":0,"geom:area_square_m":0,"geom:bbox":"24.53917,59.31083,24.53917,59.31083","geom:latitude":59.31083,"geom:longitude":24.53917,"gn:admin1_code":"1.0","gn:admin2_code":"726.0","gn:admin3_code":"2267.0","gn:asciiname":"Vanamyyza-Myaekyula","gn:country_code":"EE","gn:dem":46,"gn:feature_class":"P","gn:feature_code":"PPL","gn:geonameid":587798,"gn:latitude":59.31083,"gn:longitude":24.53917,"gn:modification_date":"2017-11-25","gn:name":"Vanamyyza-Myaekyula","gn:population":0,"gn:timezone":"Europe/Tallinn","iso:country":"EE","lbl:bbox":"24.51917,59.29083,24.55917,59.33083","lbl:max_zoom":18,"lbl:min_zoom":13.5,"mz:hierarchy_label":1,"mz:is_current":1,"mz:min_zoom":12,"name:und_x_variant":["Vanamõisa-Mäeküla","Mäeküla"],"src:geom":"geonames","wof:belongsto":[85683055,102191581,1713307915,85633135,1713305739],"wof:breaches":[],"wof:concordances":{"gn:id":587798},"wof:country":"EE","wof:geomhash":"48646b562406dd9b294354ef6eecd679","wof:hierarchy":[{"continent_id":102191581,"country_id":85633135,"county_id":1713305739,"localadmin_id":1713307915,"locality_id":1293407801,"region_id":85683055}],"wof:id":1293407801,"wof:lang_x_official":["est"],"wof:lang_x_spoken":["est"],"wof:lastmodified":1596663248,"wof:name":"Vanamyyza-Myaekyula","wof:parent_id":1713307915,"wof:placetype":"locality","wof:repo":"whosonfirst-data-admin-ee","wof:superseded_by":[],"wof:supersedes":[],"wof:tags":[]},"bbox":[24.53917,59.31083,24.53917,59.31083],"geometry":{"coordinates":[24.53917,59.31083],"type":"Point"}}