{"id":1209495281,"type":"Feature","properties":{"edtf:cessation":"uuuu","edtf:inception":"uuuu","geom:area":0,"geom:area_square_m":0,"geom:bbox":"27.11639,58.11944,27.11639,58.11944","geom:latitude":58.11944,"geom:longitude":27.11639,"gn:admin1_code":"12.0","gn:admin2_code":"622.0","gn:admin3_code":"1609.0","gn:asciiname":"Kitsoruusuu","gn:country_code":"EE","gn:dem":58,"gn:feature_class":"P","gn:feature_code":"PPL","gn:geonameid":8620730,"gn:latitude":58.11944,"gn:longitude":27.11639,"gn:modification_date":"2017-11-25","gn:name":"Kitsõruusuu","gn:population":0,"gn:timezone":"Europe/Tallinn","iso:country":"EE","lbl:bbox":"27.09639,58.09944,27.13639,58.13944","lbl:max_zoom":18,"lbl:min_zoom":13.5,"mz:hierarchy_label":1,"mz:is_current":1,"mz:min_zoom":12,"name:und_x_variant":["Kitsõruusuu","Kitseroosoo"],"src:geom":"geonames","wof:belongsto":[85682955,102191581,1713310861,85633135,1713305791],"wof:breaches":[],"wof:concordances":{"gn:id":8620730},"wof:country":"EE","wof:geomhash":"c5bb4c1511d731a193d0a0d06be8d831","wof:hierarchy":[{"continent_id":102191581,"country_id":85633135,"county_id":1713305791,"localadmin_id":1713310861,"locality_id":1209495281,"region_id":85682955}],"wof:id":1209495281,"wof:lang_x_official":["est"],"wof:lang_x_spoken":["est"],"wof:lastmodified":1596676967,"wof:name":"Kitsoruusuu","wof:parent_id":1713310861,"wof:placetype":"locality","wof:repo":"whosonfirst-data-admin-ee","wof:superseded_by":[],"wof:supersedes":[],"wof:tags":[]},"bbox":[27.11639,58.11944,27.11639,58.11944],"geometry":{"coordinates":[27.11639,58.11944],"type":"Point"}}