{"id":1125887327,"type":"Feature","properties":{"edtf:cessation":"uuuu","edtf:inception":"uuuu","geom:area":0,"geom:area_square_m":0,"geom:bbox":"24.22972,59.38639,24.22972,59.38639","geom:latitude":59.38639,"geom:longitude":24.22972,"gn:country":"EE","gn:fcode":"PPL","gn:population":277,"iso:country":"EE","lbl:bbox":"24.20972,59.36639,24.24972,59.40639","lbl:latitude":59.38639,"lbl:longitude":24.22972,"lbl:max_zoom":17,"lbl:min_zoom":12.5,"mz:hierarchy_label":1,"mz:is_current":1,"mz:min_zoom":11,"mz:note":"Quattroshapes Point Gazetteer import 20170519","name:bul_x_preferred":["Лауласма"],"name:ceb_x_preferred":["Laulasmaa"],"name:eng_x_preferred":["Laulasmaa"],"name:est_x_preferred":["Laulasmaa"],"name:fra_x_preferred":["Laulasmaa"],"name:hye_x_preferred":["Լաուլասմաա"],"name:nld_x_preferred":["Laulasmaa"],"name:pol_x_preferred":["Laulasmaa"],"name:rus_x_preferred":["Мыза Лауласмаа"],"name:spa_x_preferred":["Laulasmaa"],"name:swe_x_preferred":["Laulasmaa"],"name:ukr_x_preferred":["Лауласмаа"],"name:und_x_variant":["Myza Laulasma"],"name:vol_x_preferred":["Laulasmaa"],"qs_pg:aaroncc":"EE","qs_pg:gn_country":"EE","qs_pg:gn_fcode":"PPL","qs_pg:gn_id":590753,"qs_pg:gn_pop":277,"qs_pg:name":"Laulasmaa","qs_pg:name_adm0":"Eesti","qs_pg:name_adm1":"Harjumaa","qs_pg:photos":34,"qs_pg:photos_1k":7,"qs_pg:photos_9k":1,"qs_pg:photos_9r":2,"qs_pg:photos_all":34,"qs_pg:photos_sr":2,"qs_pg:pop_sr":2,"qs_pg:qs_id":1219159,"qs_pg:qs_pg_placetype":"locality","qs_pg:qs_pg_placetype_gp":"Town","qs_pg:woe_adm0":23424805,"qs_pg:woe_id":843544,"src:geom":"qs_pg","src:lbl_centroid":"qs_pg","src:population":"geonames","woe:adm0_id":23424805,"woe:name_adm0":"Eesti","woe:name_adm1":"Harjumaa","woe:placetype":"Town","wof:belongsto":[85683055,102191581,1713307801,85633135,1713305737],"wof:breaches":[],"wof:concordances":{"gn:id":590753,"gp:id":843544,"qs_pg:id":1219159,"wd:id":"Q2672540"},"wof:coterminous":[1713307801],"wof:country":"EE","wof:created":1497295143,"wof:geomhash":"2fa3100b2d38b7eac0918136402d9d96","wof:hierarchy":[{"continent_id":102191581,"country_id":85633135,"county_id":1713305737,"localadmin_id":1713307801,"locality_id":1125887327,"region_id":85683055}],"wof:id":1125887327,"wof:lang_x_official":["est"],"wof:lang_x_spoken":["est"],"wof:lastmodified":1596663326,"wof:name":"Laulasmaa","wof:parent_id":1713307801,"wof:placetype":"locality","wof:population":277,"wof:population_rank":2,"wof:repo":"whosonfirst-data-admin-ee","wof:superseded_by":[],"wof:supersedes":[],"wof:tags":[]},"bbox":[24.22972,59.38639,24.22972,59.38639],"geometry":{"coordinates":[24.22972,59.38639],"type":"Point"}}