{"id":1125862977,"type":"Feature","properties":{"edtf:cessation":"uuuu","edtf:inception":"uuuu","geom:area":0,"geom:area_square_m":0,"geom:bbox":"26.2375,59.11722,26.2375,59.11722","geom:latitude":59.11722,"geom:longitude":26.2375,"gn:country":"EE","gn:fcode":"PPL","gn:population":156,"iso:country":"EE","lbl:bbox":"26.2175,59.09722,26.2575,59.13722","lbl:latitude":59.11722,"lbl:longitude":26.2375,"lbl:max_zoom":18,"lbl:min_zoom":13,"mz:hierarchy_label":1,"mz:is_current":1,"mz:min_zoom":11,"mz:note":"Quattroshapes Point Gazetteer import 20170519","name:bul_x_preferred":["Ебавере"],"name:ceb_x_preferred":["Ebavere"],"name:eng_x_preferred":["Ebavere"],"name:est_x_preferred":["Ebavere"],"name:fra_x_preferred":["Ebavere"],"name:hye_x_preferred":["Էբավեռե"],"name:nld_x_preferred":["Ebavere"],"name:pol_x_preferred":["Ebavere"],"name:swe_x_preferred":["Ebavere"],"name:vol_x_preferred":["Ebavere"],"qs_pg:aaroncc":"EE","qs_pg:gn_country":"EE","qs_pg:gn_fcode":"PPL","qs_pg:gn_id":793417,"qs_pg:gn_pop":156,"qs_pg:name":"Ebavere","qs_pg:name_adm0":"Eesti","qs_pg:name_adm1":"Lääne-Virumaa","qs_pg:photos_9k":1,"qs_pg:photos_9r":1,"qs_pg:photos_all":2,"qs_pg:photos_sr":0,"qs_pg:pop_sr":1,"qs_pg:qs_id":255641,"qs_pg:qs_pg_placetype":"locality","qs_pg:qs_pg_placetype_gp":"Town","qs_pg:woe_adm0":23424805,"qs_pg:woe_id":842091,"src:geom":"qs_pg","src:lbl_centroid":"qs_pg","src:population":"geonames","woe:adm0_id":23424805,"woe:name_adm0":"Eesti","woe:name_adm1":"Lääne-Virumaa","woe:placetype":"Town","wof:belongsto":[85683049,102191581,1713311789,85633135,1713305769],"wof:breaches":[],"wof:concordances":{"gn:id":793417,"gp:id":842091,"qs_pg:id":255641,"wd:id":"Q3470023"},"wof:coterminous":[1713311789],"wof:country":"EE","wof:created":1497293912,"wof:geomhash":"43f11c5c817e06ea20bd57d4ad41d72f","wof:hierarchy":[{"continent_id":102191581,"country_id":85633135,"county_id":1713305769,"localadmin_id":1713311789,"locality_id":1125862977,"region_id":85683049}],"wof:id":1125862977,"wof:lang_x_official":["est"],"wof:lang_x_spoken":["est"],"wof:lastmodified":1596676539,"wof:name":"Ebavere","wof:parent_id":1713311789,"wof:placetype":"locality","wof:population":156,"wof:population_rank":1,"wof:repo":"whosonfirst-data-admin-ee","wof:superseded_by":[],"wof:supersedes":[],"wof:tags":[]},"bbox":[26.2375,59.11722,26.2375,59.11722],"geometry":{"coordinates":[26.2375,59.11722],"type":"Point"}}