{"id":1125835761,"type":"Feature","properties":{"edtf:cessation":"uuuu","edtf:inception":"uuuu","geom:area":0,"geom:area_square_m":0,"geom:bbox":"27.01861,58.05056,27.01861,58.05056","geom:latitude":58.05056,"geom:longitude":27.01861,"gn:country":"EE","gn:fcode":"PPL","gn:population":129,"iso:country":"EE","lbl:bbox":"26.99861,58.03056,27.03861,58.07056","lbl:latitude":58.05056,"lbl:longitude":27.01861,"lbl:max_zoom":18,"lbl:min_zoom":13,"mz:hierarchy_label":1,"mz:is_current":1,"mz:min_zoom":11,"mz:note":"Quattroshapes Point Gazetteer import 20170519","name:bul_x_preferred":["Пури"],"name:ceb_x_preferred":["Puuri"],"name:eng_x_preferred":["Puuri"],"name:est_x_preferred":["Puuri"],"name:hye_x_preferred":["Պուուռի"],"name:nld_x_preferred":["Puuri"],"name:spa_x_preferred":["Puuri"],"name:swe_x_preferred":["Puuri"],"name:ukr_x_preferred":["Пуурі"],"name:vol_x_preferred":["Puuri"],"name:vro_x_preferred":["Puuri"],"qs_pg:aaroncc":"EE","qs_pg:gn_country":"EE","qs_pg:gn_fcode":"PPL","qs_pg:gn_id":794165,"qs_pg:gn_pop":129,"qs_pg:name":"Puuri","qs_pg:name_adm0":"Eesti","qs_pg:name_adm1":"Põlvamaa","qs_pg:photos_9r":0,"qs_pg:photos_sr":0,"qs_pg:pop_sr":1,"qs_pg:qs_id":1274391,"qs_pg:qs_pg_placetype":"locality","qs_pg:qs_pg_placetype_gp":"Town","qs_pg:woe_adm0":23424805,"qs_pg:woe_id":844946,"src:geom":"qs_pg","src:lbl_centroid":"qs_pg","src:population":"geonames","woe:adm0_id":23424805,"woe:name_adm0":"Eesti","woe:name_adm1":"Põlvamaa","woe:placetype":"Town","wof:belongsto":[85682955,102191581,1713310865,85633135,1713305791],"wof:breaches":[],"wof:concordances":{"gn:id":794165,"gp:id":844946,"qs_pg:id":1274391,"wd:id":"Q3457513"},"wof:coterminous":[1713310865],"wof:country":"EE","wof:created":1497292709,"wof:geomhash":"5c87cc730dc7ef8678e0164f9b0c217c","wof:hierarchy":[{"continent_id":102191581,"country_id":85633135,"county_id":1713305791,"localadmin_id":1713310865,"locality_id":1125835761,"region_id":85682955}],"wof:id":1125835761,"wof:lang_x_official":["est"],"wof:lang_x_spoken":["est"],"wof:lastmodified":1596676964,"wof:name":"Puuri","wof:parent_id":1713310865,"wof:placetype":"locality","wof:population":129,"wof:population_rank":1,"wof:repo":"whosonfirst-data-admin-ee","wof:superseded_by":[],"wof:supersedes":[],"wof:tags":[]},"bbox":[27.01861,58.05056,27.01861,58.05056],"geometry":{"coordinates":[27.01861,58.05056],"type":"Point"}}