{"id":1209778953,"type":"Feature","properties":{"edtf:cessation":"uuuu","edtf:inception":"uuuu","geom:area":0,"geom:area_square_m":0,"geom:bbox":"26.92167,58.42194,26.92167,58.42194","geom:latitude":58.42194,"geom:longitude":26.92167,"gn:admin1_code":"18.0","gn:admin2_code":"796.0","gn:admin3_code":"3970.0","gn:asciiname":"Korbi","gn:country_code":"EE","gn:dem":56,"gn:feature_class":"P","gn:feature_code":"PPL","gn:geonameid":8619454,"gn:latitude":58.42194,"gn:longitude":26.92167,"gn:modification_date":"2017-11-25","gn:name":"Korbi","gn:population":0,"gn:timezone":"Europe/Tallinn","iso:country":"EE","lbl:bbox":"26.90167,58.40194,26.94167,58.44194","lbl:max_zoom":18,"lbl:min_zoom":13.5,"mz:hierarchy_label":1,"mz:is_current":1,"mz:min_zoom":12,"name:und_x_variant":["Karbi"],"src:geom":"geonames","wof:belongsto":[85683009,102191581,1713314643,85633135,1713305659],"wof:breaches":[],"wof:concordances":{"gn:id":8619454},"wof:country":"EE","wof:geomhash":"fe4e72b2cafb8b6d8fc1734c75977ab6","wof:hierarchy":[{"continent_id":102191581,"country_id":85633135,"county_id":1713305659,"localadmin_id":1713314643,"locality_id":1209778953,"region_id":85683009}],"wof:id":1209778953,"wof:lang_x_official":["est"],"wof:lang_x_spoken":["est"],"wof:lastmodified":1596676476,"wof:name":"Korbi","wof:parent_id":1713314643,"wof:placetype":"locality","wof:repo":"whosonfirst-data-admin-ee","wof:superseded_by":[],"wof:supersedes":[],"wof:tags":[]},"bbox":[26.92167,58.42194,26.92167,58.42194],"geometry":{"coordinates":[26.92167,58.42194],"type":"Point"}}