{"id":1226413437,"type":"Feature","properties":{"edtf:cessation":"uuuu","edtf:inception":"uuuu","geom:area":0,"geom:area_square_m":0,"geom:bbox":"22.86028,58.41778,22.86028,58.41778","geom:latitude":58.41778,"geom:longitude":22.86028,"gn:admin1_code":"14.0","gn:admin2_code":"714.0","gn:admin3_code":"8952.0","gn:asciiname":"Veeriku","gn:country_code":"EE","gn:dem":17,"gn:feature_class":"P","gn:feature_code":"PPL","gn:geonameid":794708,"gn:latitude":58.41778,"gn:longitude":22.86028,"gn:modification_date":"2017-11-25","gn:name":"Veeriku","gn:population":0,"gn:timezone":"Europe/Tallinn","iso:country":"EE","lbl:bbox":"22.84028,58.39778,22.88028,58.43778","lbl:max_zoom":18,"lbl:min_zoom":13.5,"mz:hierarchy_label":1,"mz:is_current":1,"mz:min_zoom":12,"name:deu_x_preferred":["Veeriku"],"name:est_x_preferred":["Veeriku küla"],"name:pol_x_preferred":["Veeriku"],"name:vol_x_preferred":["Veeriku küla"],"src:geom":"geonames","wof:belongsto":[85682947,102191581,1713308455,85633135,1713305627],"wof:breaches":[],"wof:concordances":{"gn:id":794708,"wk:page":"Veeriku%2C_Saare_County"},"wof:coterminous":[1713308557],"wof:country":"EE","wof:geomhash":"6f8b09d5e75040fb808688f7944718ed","wof:hierarchy":[{"continent_id":102191581,"country_id":85633135,"county_id":1713305627,"localadmin_id":1713308455,"locality_id":1226413437,"region_id":85682947}],"wof:id":1226413437,"wof:lang_x_official":["est"],"wof:lang_x_spoken":["est"],"wof:lastmodified":1596674940,"wof:name":"Veeriku","wof:parent_id":1713308455,"wof:placetype":"locality","wof:repo":"whosonfirst-data-admin-ee","wof:superseded_by":[],"wof:supersedes":[],"wof:tags":[]},"bbox":[22.86028,58.41778,22.86028,58.41778],"geometry":{"coordinates":[22.86028,58.41778],"type":"Point"}}