{"id":1326792385,"type":"Feature","properties":{"edtf:cessation":"uuuu","edtf:inception":"uuuu","geom:area":0,"geom:area_square_m":0,"geom:bbox":"25.815,58.12278,25.815,58.12278","geom:latitude":58.12278,"geom:longitude":25.815,"gn:admin1_code":"20.0","gn:admin2_code":"899.0","gn:admin3_code":"6541.0","gn:asciiname":"Porga","gn:cc2":"EE","gn:country_code":"EE","gn:dem":105,"gn:feature_class":"P","gn:feature_code":"PPL","gn:geonameid":589361,"gn:latitude":58.12278,"gn:longitude":25.815,"gn:modification_date":"2017-11-25","gn:name":"Põrga","gn:population":0,"gn:timezone":"Europe/Tallinn","iso:country":"EE","lbl:bbox":"25.795,58.10278,25.835,58.14278","lbl:max_zoom":18,"lbl:min_zoom":13.5,"mz:hierarchy_label":1,"mz:is_current":1,"mz:min_zoom":12,"name:chv_x_preferred":["Порга"],"name:ron_x_preferred":["Porga"],"name:und_x_variant":["Pyrga","Põrga"],"src:geom":"geonames","wof:belongsto":[85682985,102191581,1713314377,85633135,1713305669],"wof:breaches":[],"wof:concordances":{"gn:id":589361},"wof:coterminous":[1713314377],"wof:country":"EE","wof:geomhash":"6c4fee7ba9808d484a3d0570411ca48d","wof:hierarchy":[{"continent_id":102191581,"country_id":85633135,"county_id":1713305669,"localadmin_id":1713314377,"locality_id":1326792385,"region_id":85682985}],"wof:id":1326792385,"wof:lang_x_official":["est"],"wof:lang_x_spoken":["est"],"wof:lastmodified":1596661254,"wof:name":"Porga","wof:parent_id":1713314377,"wof:placetype":"locality","wof:repo":"whosonfirst-data-admin-ee","wof:superseded_by":[],"wof:supersedes":[],"wof:tags":[]},"bbox":[25.815,58.12278,25.815,58.12278],"geometry":{"coordinates":[25.815,58.12278],"type":"Point"}}