{"id":1243540831,"type":"Feature","properties":{"edtf:cessation":"uuuu","edtf:inception":"uuuu","geom:area":0,"geom:area_square_m":0,"geom:bbox":"25.2275,58.81556,25.2275,58.81556","geom:latitude":58.81556,"geom:longitude":25.2275,"gn:admin1_code":"4.0","gn:admin2_code":"834.0","gn:admin3_code":"3735.0","gn:asciiname":"Kodu","gn:cc2":"EE","gn:country_code":"EE","gn:dem":70,"gn:feature_class":"P","gn:feature_code":"PPL","gn:geonameid":591281,"gn:latitude":58.81556,"gn:longitude":25.2275,"gn:modification_date":"2017-11-25","gn:name":"Kõdu","gn:population":0,"gn:timezone":"Europe/Tallinn","iso:country":"EE","lbl:bbox":"25.2075,58.79556,25.2475,58.83556","lbl:max_zoom":18,"lbl:min_zoom":13.5,"mz:hierarchy_label":1,"mz:is_current":1,"mz:min_zoom":12,"name:est_x_preferred":["Kõdu küla"],"name:hye_x_preferred":["Կիդու"],"name:pol_x_preferred":["Kõdu"],"name:sco_x_preferred":["Kõdu"],"name:spa_x_preferred":["Kõdu"],"name:ukr_x_preferred":["Киду"],"name:und_x_variant":["Kõduküla","Kydukyula"],"name:vol_x_preferred":["Kõdu"],"src:geom":"geonames","wof:belongsto":[85683031,102191581,1713306487,85633135,1713305773],"wof:breaches":[],"wof:concordances":{"gn:id":591281,"wk:page":"K%C3%B5du"},"wof:coterminous":[1713306487],"wof:country":"EE","wof:geomhash":"d7a7e3a54ee2454fdfaf413a99e6d21d","wof:hierarchy":[{"continent_id":102191581,"country_id":85633135,"county_id":1713305773,"localadmin_id":1713306487,"locality_id":1243540831,"region_id":85683031}],"wof:id":1243540831,"wof:lang_x_official":["est"],"wof:lang_x_spoken":["est"],"wof:lastmodified":1596677996,"wof:name":"Kodu","wof:parent_id":1713306487,"wof:placetype":"locality","wof:repo":"whosonfirst-data-admin-ee","wof:superseded_by":[],"wof:supersedes":[],"wof:tags":[]},"bbox":[25.2275,58.81556,25.2275,58.81556],"geometry":{"coordinates":[25.2275,58.81556],"type":"Point"}}