{"id":1209994629,"type":"Feature","properties":{"edtf:cessation":"uuuu","edtf:inception":"uuuu","geom:area":0,"geom:area_square_m":0,"geom:bbox":"23.99944,58.47833,23.99944,58.47833","geom:latitude":58.47833,"geom:longitude":23.99944,"gn:admin1_code":"11.0","gn:admin2_code":"624.0","gn:admin3_code":"3109.0","gn:asciiname":"Viruna-Teoste","gn:country_code":"EE","gn:dem":20,"gn:feature_class":"P","gn:feature_code":"PPL","gn:geonameid":8620004,"gn:latitude":58.47833,"gn:longitude":23.99944,"gn:modification_date":"2017-11-25","gn:name":"Viruna-Teoste","gn:population":0,"gn:timezone":"Europe/Tallinn","iso:country":"EE","lbl:bbox":"23.97944,58.45833,24.01944,58.49833","lbl:max_zoom":18,"lbl:min_zoom":13.5,"mz:hierarchy_label":1,"mz:is_current":1,"mz:min_zoom":12,"name:und_x_variant":["Viruna"],"src:geom":"geonames","wof:belongsto":[85682981,102191581,1713313675,85633135,1713305703],"wof:breaches":[],"wof:concordances":{"gn:id":8620004},"wof:country":"EE","wof:geomhash":"3a120f756f53501ef7bd0b33f1726b84","wof:hierarchy":[{"continent_id":102191581,"country_id":85633135,"county_id":1713305703,"localadmin_id":1713313675,"locality_id":1209994629,"region_id":85682981}],"wof:id":1209994629,"wof:lang_x_official":["est"],"wof:lang_x_spoken":["est"],"wof:lastmodified":1596677707,"wof:name":"Viruna-Teoste","wof:parent_id":1713313675,"wof:placetype":"locality","wof:repo":"whosonfirst-data-admin-ee","wof:superseded_by":[],"wof:supersedes":[],"wof:tags":[]},"bbox":[23.99944,58.47833,23.99944,58.47833],"geometry":{"coordinates":[23.99944,58.47833],"type":"Point"}}