{"id":1310109985,"type":"Feature","properties":{"edtf:cessation":"uuuu","edtf:inception":"uuuu","geom:area":0,"geom:area_square_m":0,"geom:bbox":"23.90528,59.18694,23.90528,59.18694","geom:latitude":59.18694,"geom:longitude":23.90528,"gn:admin1_code":"1.0","gn:admin2_code":"431.0","gn:admin3_code":"1782.0","gn:asciiname":"Soo-otsa","gn:country_code":"EE","gn:dem":16,"gn:feature_class":"P","gn:feature_code":"PPL","gn:geonameid":588580,"gn:latitude":59.18694,"gn:longitude":23.90528,"gn:modification_date":"2017-11-25","gn:name":"Soo-otsa","gn:population":0,"gn:timezone":"Europe/Tallinn","iso:country":"EE","lbl:bbox":"23.88528,59.16694,23.92528,59.20694","lbl:max_zoom":18,"lbl:min_zoom":13.5,"mz:hierarchy_label":1,"mz:is_current":1,"mz:min_zoom":12,"name:deu_x_preferred":["Soo-otsa"],"name:est_x_preferred":["Soo-otsa"],"name:hye_x_preferred":["Սոո-Ոցա"],"name:pol_x_preferred":["Soo-otsa"],"name:spa_x_preferred":["Soo-otsa"],"name:ukr_x_preferred":["Соо-отса"],"name:und_x_variant":["Sooltse","Sootse","Sol’tsa"],"name:vol_x_preferred":["Soo-otsa"],"src:geom":"geonames","wof:belongsto":[85683055,102191581,1713315313,85633135,1713305737],"wof:breaches":[],"wof:concordances":{"gn:id":588580},"wof:country":"EE","wof:geomhash":"e004fafb25ccc3c47503df47d866b00c","wof:hierarchy":[{"continent_id":102191581,"country_id":85633135,"county_id":1713305737,"localadmin_id":1713315313,"locality_id":1310109985,"region_id":85683055}],"wof:id":1310109985,"wof:lang_x_official":["est"],"wof:lang_x_spoken":["est"],"wof:lastmodified":1596663319,"wof:name":"Soo-otsa","wof:parent_id":1713315313,"wof:placetype":"locality","wof:repo":"whosonfirst-data-admin-ee","wof:superseded_by":[],"wof:supersedes":[],"wof:tags":[]},"bbox":[23.90528,59.18694,23.90528,59.18694],"geometry":{"coordinates":[23.90528,59.18694],"type":"Point"}}