{"id":1260363649,"type":"Feature","properties":{"edtf:cessation":"uuuu","edtf:inception":"uuuu","geom:area":0,"geom:area_square_m":0,"geom:bbox":"27.40639,57.76889,27.40639,57.76889","geom:latitude":57.76889,"geom:longitude":27.40639,"gn:admin1_code":"21.0","gn:admin2_code":"732.0","gn:admin3_code":"2665.0","gn:asciiname":"Kaernae","gn:country_code":"EE","gn:dem":130,"gn:feature_class":"P","gn:feature_code":"PPL","gn:geonameid":8619783,"gn:latitude":57.76889,"gn:longitude":27.40639,"gn:modification_date":"2017-11-25","gn:name":"Kärnä","gn:population":0,"gn:timezone":"Europe/Tallinn","iso:country":"EE","lbl:bbox":"27.38639,57.74889,27.42639,57.78889","lbl:max_zoom":18,"lbl:min_zoom":13.5,"mz:hierarchy_label":1,"mz:is_current":1,"mz:min_zoom":12,"name:und_x_variant":["Kärnä","Kärna"],"src:geom":"geonames","wof:belongsto":[85682955,102191581,1713316157,85633135,1713305631],"wof:breaches":[],"wof:concordances":{"gn:id":8619783},"wof:country":"EE","wof:geomhash":"6e77f9f7e6973c992813f8448c01e79a","wof:hierarchy":[{"continent_id":102191581,"country_id":85633135,"county_id":1713305631,"localadmin_id":1713316157,"locality_id":1260363649,"region_id":85682955}],"wof:id":1260363649,"wof:lang_x_official":["est"],"wof:lang_x_spoken":["est"],"wof:lastmodified":1596663694,"wof:name":"Kaernae","wof:parent_id":1713316157,"wof:placetype":"locality","wof:repo":"whosonfirst-data-admin-ee","wof:superseded_by":[],"wof:supersedes":[],"wof:tags":[]},"bbox":[27.40639,57.76889,27.40639,57.76889],"geometry":{"coordinates":[27.40639,57.76889],"type":"Point"}}