{"id":1293595483,"type":"Feature","properties":{"edtf:cessation":"uuuu","edtf:inception":"uuuu","geom:area":0,"geom:area_square_m":0,"geom:bbox":"25.69194,59.17583,25.69194,59.17583","geom:latitude":59.17583,"geom:longitude":25.69194,"gn:admin1_code":"4.0","gn:admin2_code":"255.0","gn:admin3_code":"7961.0","gn:asciiname":"Aniste","gn:country_code":"EE","gn:dem":88,"gn:feature_class":"P","gn:feature_code":"PPL","gn:geonameid":8618457,"gn:latitude":59.17583,"gn:longitude":25.69194,"gn:modification_date":"2017-11-25","gn:name":"Aniste","gn:population":0,"gn:timezone":"Europe/Tallinn","iso:country":"EE","lbl:bbox":"25.67194,59.15583,25.71194,59.19583","lbl:max_zoom":18,"lbl:min_zoom":13.5,"mz:hierarchy_label":1,"mz:is_current":1,"mz:min_zoom":12,"src:geom":"geonames","wof:belongsto":[85683031,102191581,1713306793,85633135,1713305765],"wof:breaches":[],"wof:concordances":{"gn:id":8618457},"wof:country":"EE","wof:geomhash":"0a6c5d6a6272a7344d904b9f1a93cbe0","wof:hierarchy":[{"continent_id":102191581,"country_id":85633135,"county_id":1713305765,"localadmin_id":1713306793,"locality_id":1293595483,"region_id":85683031}],"wof:id":1293595483,"wof:lang_x_official":["est"],"wof:lang_x_spoken":["est"],"wof:lastmodified":1596676651,"wof:name":"Aniste","wof:parent_id":1713306793,"wof:placetype":"locality","wof:repo":"whosonfirst-data-admin-ee","wof:superseded_by":[],"wof:supersedes":[],"wof:tags":[]},"bbox":[25.69194,59.17583,25.69194,59.17583],"geometry":{"coordinates":[25.69194,59.17583],"type":"Point"}}