{"id":1260000839,"type":"Feature","properties":{"edtf:cessation":"uuuu","edtf:inception":"uuuu","geom:area":0,"geom:area_square_m":0,"geom:bbox":"23.43611,58.90778,23.43611,58.90778","geom:latitude":58.90778,"geom:longitude":23.43611,"gn:admin1_code":"7.0","gn:admin2_code":"184.0","gn:admin3_code":"7036.0","gn:asciiname":"Rohukuela","gn:country_code":"EE","gn:dem":8,"gn:feature_class":"P","gn:feature_code":"PPL","gn:geonameid":588987,"gn:latitude":58.90778,"gn:longitude":23.43611,"gn:modification_date":"2017-11-25","gn:name":"Rohuküla","gn:population":0,"gn:timezone":"Europe/Tallinn","iso:country":"EE","lbl:bbox":"23.41611,58.88778,23.45611,58.92778","lbl:max_zoom":18,"lbl:min_zoom":13.5,"mz:hierarchy_label":1,"mz:is_current":1,"mz:min_zoom":12,"name:deu_x_preferred":["Rohuküla"],"name:est_x_preferred":["Rohuküla"],"name:fra_x_preferred":["Rohuküla"],"name:hye_x_preferred":["Ռոհուկյուլա"],"name:pol_x_preferred":["Rohuküla"],"name:swe_x_preferred":["Rus"],"name:ukr_x_preferred":["Рогукюла"],"name:und_x_variant":["Rokhyukyula","Rokhukyula","Rohukola"],"name:vol_x_preferred":["Rohuküla"],"src:geom":"geonames","wof:belongsto":[85683001,102191581,1713308537,85633135,1713305755],"wof:breaches":[],"wof:concordances":{"gn:id":588987,"wk:page":"Rohuk%C3%BCla"},"wof:coterminous":[1713308537],"wof:country":"EE","wof:geomhash":"77f36d36154ef0789816242dd1e54d1c","wof:hierarchy":[{"continent_id":102191581,"country_id":85633135,"county_id":1713305755,"localadmin_id":1713308537,"locality_id":1260000839,"region_id":85683001}],"wof:id":1260000839,"wof:lang_x_official":["est"],"wof:lang_x_spoken":["est"],"wof:lastmodified":1596662768,"wof:name":"Rohukuela","wof:parent_id":1713308537,"wof:placetype":"locality","wof:repo":"whosonfirst-data-admin-ee","wof:superseded_by":[],"wof:supersedes":[],"wof:tags":[]},"bbox":[23.43611,58.90778,23.43611,58.90778],"geometry":{"coordinates":[23.43611,58.90778],"type":"Point"}}