{"id":1343846321,"type":"Feature","properties":{"edtf:cessation":"uuuu","edtf:inception":"uuuu","geom:area":0,"geom:area_square_m":0,"geom:bbox":"23.9675,58.55111,23.9675,58.55111","geom:latitude":58.55111,"geom:longitude":23.9675,"gn:admin1_code":"11.0","gn:admin2_code":"430.0","gn:admin3_code":"6054.0","gn:asciiname":"Peantse","gn:country_code":"EE","gn:dem":27,"gn:feature_class":"P","gn:feature_code":"PPL","gn:geonameid":589549,"gn:latitude":58.55111,"gn:longitude":23.9675,"gn:modification_date":"2017-11-25","gn:name":"Peantse","gn:population":0,"gn:timezone":"Europe/Tallinn","iso:country":"EE","lbl:bbox":"23.9475,58.53111,23.9875,58.57111","lbl:max_zoom":18,"lbl:min_zoom":13.5,"mz:hierarchy_label":1,"mz:is_current":1,"mz:min_zoom":12,"name:est_x_preferred":["Peantse"],"name:hye_x_preferred":["Պեանցե"],"name:pol_x_preferred":["Peantse"],"name:spa_x_preferred":["Peantse"],"name:und_x_variant":["Piantse"],"name:vol_x_preferred":["Peantse"],"src:geom":"geonames","wof:belongsto":[85683001,102191581,1713309275,85633135,1713305721],"wof:breaches":[],"wof:concordances":{"gn:id":589549,"wk:page":"Peantse"},"wof:coterminous":[1713309275],"wof:country":"EE","wof:geomhash":"078f63ac796b1c646e42cbbe17867cbd","wof:hierarchy":[{"continent_id":102191581,"country_id":85633135,"county_id":1713305721,"localadmin_id":1713309275,"locality_id":1343846321,"region_id":85683001}],"wof:id":1343846321,"wof:lang_x_official":["est"],"wof:lang_x_spoken":["est"],"wof:lastmodified":1596661680,"wof:name":"Peantse","wof:parent_id":1713309275,"wof:placetype":"locality","wof:repo":"whosonfirst-data-admin-ee","wof:superseded_by":[],"wof:supersedes":[],"wof:tags":[]},"bbox":[23.9675,58.55111,23.9675,58.55111],"geometry":{"coordinates":[23.9675,58.55111],"type":"Point"}}