{"id":1343723781,"type":"Feature","properties":{"edtf:cessation":"uuuu","edtf:inception":"uuuu","geom:area":0,"geom:area_square_m":0,"geom:bbox":"25.48222,57.98667,25.48222,57.98667","geom:latitude":57.98667,"geom:longitude":25.48222,"gn:admin1_code":"20.0","gn:admin2_code":"480.0","gn:admin3_code":"4370.0","gn:asciiname":"Masa","gn:country_code":"EE","gn:dem":92,"gn:feature_class":"P","gn:feature_code":"PPL","gn:geonameid":8620035,"gn:latitude":57.98667,"gn:longitude":25.48222,"gn:modification_date":"2017-11-25","gn:name":"Masa","gn:population":0,"gn:timezone":"Europe/Tallinn","iso:country":"EE","lbl:bbox":"25.46222,57.96667,25.50222,58.00667","lbl:max_zoom":18,"lbl:min_zoom":13.5,"mz:hierarchy_label":1,"mz:is_current":1,"mz:min_zoom":12,"name:fra_x_preferred":["Masa"],"name:kor_x_preferred":["마사"],"name:msa_x_preferred":["Masa"],"name:ukr_x_preferred":["Маса"],"name:und_x_variant":["Дв. Масса"],"name:zho_x_preferred":["马萨"],"src:geom":"geonames","wof:belongsto":[85682985,102191581,1713313775,85633135,1713305661],"wof:breaches":[],"wof:concordances":{"gn:id":8620035},"wof:country":"EE","wof:geomhash":"b9a483d1e482db2ef7e77bcaff8857db","wof:hierarchy":[{"continent_id":102191581,"country_id":85633135,"county_id":1713305661,"localadmin_id":1713313775,"locality_id":1343723781,"region_id":85682985}],"wof:id":1343723781,"wof:lang_x_official":["est"],"wof:lang_x_spoken":["est"],"wof:lastmodified":1596661299,"wof:name":"Masa","wof:parent_id":1713313775,"wof:placetype":"locality","wof:repo":"whosonfirst-data-admin-ee","wof:superseded_by":[],"wof:supersedes":[],"wof:tags":[]},"bbox":[25.48222,57.98667,25.48222,57.98667],"geometry":{"coordinates":[25.48222,57.98667],"type":"Point"}}