{"id":1126003809,"type":"Feature","properties":{"edtf:cessation":"uuuu","edtf:inception":"uuuu","geom:area":0,"geom:area_square_m":0,"geom:bbox":"27.13528,58.26222,27.13528,58.26222","geom:latitude":58.26222,"geom:longitude":27.13528,"gn:country":"EE","gn:fcode":"PPL","gn:population":125,"iso:country":"EE","lbl:bbox":"27.11528,58.24222,27.15528,58.28222","lbl:latitude":58.26222,"lbl:longitude":27.13528,"lbl:max_zoom":18,"lbl:min_zoom":13,"mz:hierarchy_label":1,"mz:is_current":1,"mz:min_zoom":11,"mz:note":"Quattroshapes Point Gazetteer import 20170519","name:bul_x_preferred":["Ляенисте"],"name:ceb_x_preferred":["Lyaeniste"],"name:eng_x_preferred":["Lääniste"],"name:est_x_preferred":["Lääniste"],"name:fra_x_preferred":["Lääniste"],"name:hye_x_preferred":["Լեենիստե"],"name:nld_x_preferred":["Lääniste"],"name:pol_x_preferred":["Lääniste"],"name:rus_x_preferred":["Ляэнисте"],"name:spa_x_preferred":["Lääniste"],"name:swe_x_preferred":["Lääniste"],"name:ukr_x_preferred":["Ляеністе"],"name:und_x_variant":["Lyaaniste"],"name:urd_x_preferred":["لانیسٹی"],"name:vol_x_preferred":["Lääniste"],"qs_pg:aaroncc":"EE","qs_pg:gn_country":"EE","qs_pg:gn_fcode":"PPL","qs_pg:gn_id":590853,"qs_pg:gn_pop":125,"qs_pg:name":"Lääniste","qs_pg:name_adm0":"Eesti","qs_pg:name_adm1":"Tartumaa","qs_pg:photos_9k":1,"qs_pg:photos_9r":1,"qs_pg:photos_all":2,"qs_pg:photos_sr":0,"qs_pg:pop_sr":1,"qs_pg:qs_id":915780,"qs_pg:qs_pg_placetype":"locality","qs_pg:qs_pg_placetype_gp":"Town","qs_pg:woe_adm0":23424805,"qs_pg:woe_id":843456,"src:geom":"qs_pg","src:lbl_centroid":"qs_pg","src:population":"geonames","woe:adm0_id":23424805,"woe:name_adm0":"Eesti","woe:name_adm1":"Tartumaa","woe:placetype":"Town","wof:belongsto":[85682955,102191581,1713314191,85633135,1713305791],"wof:breaches":[],"wof:concordances":{"gn:id":590853,"gp:id":843456,"qs_pg:id":915780,"wd:id":"Q3457655"},"wof:coterminous":[1713314015],"wof:country":"EE","wof:created":1497299809,"wof:geomhash":"9b8c7a21b0bf2502d714899e0789859d","wof:hierarchy":[{"continent_id":102191581,"country_id":85633135,"county_id":1713305791,"localadmin_id":1713314191,"locality_id":1126003809,"region_id":85682955}],"wof:id":1126003809,"wof:lang_x_official":["est"],"wof:lang_x_spoken":["est"],"wof:lastmodified":1596676973,"wof:name":"Lääniste","wof:parent_id":1713314191,"wof:placetype":"locality","wof:population":125,"wof:population_rank":1,"wof:repo":"whosonfirst-data-admin-ee","wof:superseded_by":[],"wof:supersedes":[],"wof:tags":[]},"bbox":[27.13528,58.26222,27.13528,58.26222],"geometry":{"coordinates":[27.13528,58.26222],"type":"Point"}}