{"id":1343547611,"type":"Feature","properties":{"edtf:cessation":"uuuu","edtf:inception":"uuuu","geom:area":0,"geom:area_square_m":0,"geom:bbox":"24.82889,59.09528,24.82889,59.09528","geom:latitude":59.09528,"geom:longitude":24.82889,"gn:admin1_code":"13.0","gn:admin2_code":"668.0","gn:admin3_code":"7518.0","gn:asciiname":"Seli","gn:cc2":"EE","gn:country_code":"EE","gn:dem":68,"gn:feature_class":"P","gn:feature_code":"PPL","gn:geonameid":588738,"gn:latitude":59.09528,"gn:longitude":24.82889,"gn:modification_date":"2017-11-25","gn:name":"Seli","gn:population":0,"gn:timezone":"Europe/Tallinn","iso:country":"EE","lbl:bbox":"24.80889,59.07528,24.84889,59.11528","lbl:max_zoom":18,"lbl:min_zoom":13.5,"mz:hierarchy_label":1,"mz:is_current":1,"mz:min_zoom":12,"name:eng_x_preferred":["Seli"],"name:est_x_preferred":["Seli"],"name:hye_x_preferred":["Սելի"],"name:pol_x_preferred":["Seli"],"name:rus_x_preferred":["Сели"],"name:sco_x_preferred":["Seli"],"name:spa_x_preferred":["Seli"],"name:und_x_variant":["Myza Seli","Seli Asundus"],"name:vol_x_preferred":["Seli"],"src:geom":"geonames","wof:belongsto":[85683013,102191581,1713311135,85633135,1713305711],"wof:breaches":[],"wof:concordances":{"gn:id":588738,"wk:page":"Seli%2C_Rapla_County"},"wof:coterminous":[1713311135],"wof:country":"EE","wof:geomhash":"dd7704ab7c9d87800b69e03ea794ab0a","wof:hierarchy":[{"continent_id":102191581,"country_id":85633135,"county_id":1713305711,"localadmin_id":1713311135,"locality_id":1343547611,"region_id":85683013}],"wof:id":1343547611,"wof:lang_x_official":["est"],"wof:lang_x_spoken":["est"],"wof:lastmodified":1596676720,"wof:name":"Seli","wof:parent_id":1713311135,"wof:placetype":"locality","wof:repo":"whosonfirst-data-admin-ee","wof:superseded_by":[],"wof:supersedes":[],"wof:tags":[]},"bbox":[24.82889,59.09528,24.82889,59.09528],"geometry":{"coordinates":[24.82889,59.09528],"type":"Point"}}