{"id":1125971299,"type":"Feature","properties":{"edtf:cessation":"uuuu","edtf:inception":"uuuu","geom:area":0,"geom:area_square_m":0,"geom:bbox":"26.33444,59.13083,26.33444,59.13083","geom:latitude":59.13083,"geom:longitude":26.33444,"gn:country":"EE","gn:fcode":"PPL","gn:population":128,"iso:country":"EE","lbl:bbox":"26.31444,59.11083,26.35444,59.15083","lbl:latitude":59.13083,"lbl:longitude":26.33444,"lbl:max_zoom":18,"lbl:min_zoom":13,"mz:hierarchy_label":1,"mz:is_current":1,"mz:min_zoom":11,"mz:note":"Quattroshapes Point Gazetteer import 20170519","name:bul_x_preferred":["Еипри"],"name:ceb_x_preferred":["Eipri"],"name:eng_x_preferred":["Eipri"],"name:est_x_preferred":["Eipri"],"name:hye_x_preferred":["Էիպռի"],"name:nld_x_preferred":["Eipri"],"name:pol_x_preferred":["Eipri"],"name:swe_x_preferred":["Eipri"],"name:und_x_variant":["Yeypri"],"name:vol_x_preferred":["Eipri"],"qs_pg:aaroncc":"EE","qs_pg:gn_country":"EE","qs_pg:gn_fcode":"PPL","qs_pg:gn_id":592297,"qs_pg:gn_pop":128,"qs_pg:name":"Eipri","qs_pg:name_adm0":"Eesti","qs_pg:name_adm1":"Lääne-Virumaa","qs_pg:photos_9r":0,"qs_pg:photos_sr":0,"qs_pg:pop_sr":1,"qs_pg:qs_id":405705,"qs_pg:qs_pg_placetype":"locality","qs_pg:qs_pg_placetype_gp":"Town","qs_pg:woe_adm0":23424805,"qs_pg:woe_id":842108,"src:geom":"qs_pg","src:lbl_centroid":"qs_pg","src:population":"geonames","woe:adm0_id":23424805,"woe:name_adm0":"Eesti","woe:name_adm1":"Lääne-Virumaa","woe:placetype":"Town","wof:belongsto":[85683049,102191581,1713311893,85633135,1713305769],"wof:breaches":[],"wof:concordances":{"gn:id":592297,"gp:id":842108,"qs_pg:id":405705,"wd:id":"Q3468829"},"wof:coterminous":[1713311893],"wof:country":"EE","wof:created":1497298175,"wof:geomhash":"4fdaa9f1c53439aa0ad39096c61fd5a1","wof:hierarchy":[{"continent_id":102191581,"country_id":85633135,"county_id":1713305769,"localadmin_id":1713311893,"locality_id":1125971299,"region_id":85683049}],"wof:id":1125971299,"wof:lang_x_official":["est"],"wof:lang_x_spoken":["est"],"wof:lastmodified":1596676546,"wof:name":"Eipri","wof:parent_id":1713311893,"wof:placetype":"locality","wof:population":128,"wof:population_rank":1,"wof:repo":"whosonfirst-data-admin-ee","wof:superseded_by":[],"wof:supersedes":[],"wof:tags":[]},"bbox":[26.33444,59.13083,26.33444,59.13083],"geometry":{"coordinates":[26.33444,59.13083],"type":"Point"}}