{"id":1193100209,"type":"Feature","properties":{"edtf:cessation":"uuuu","edtf:inception":"uuuu","geom:area":0,"geom:area_square_m":0,"geom:bbox":"27.15611,58.51083,27.15611,58.51083","geom:latitude":58.51083,"geom:longitude":27.15611,"gn:admin1_code":"18.0","gn:admin2_code":"586.0","gn:admin3_code":"9031.0","gn:asciiname":"Vanaussaia","gn:country_code":"EE","gn:dem":42,"gn:feature_class":"P","gn:feature_code":"PPL","gn:geonameid":794089,"gn:latitude":58.51083,"gn:longitude":27.15611,"gn:modification_date":"2017-11-25","gn:name":"Vanaussaia","gn:population":0,"gn:timezone":"Europe/Tallinn","iso:country":"EE","lbl:bbox":"27.13611,58.49083,27.17611,58.53083","lbl:max_zoom":18,"lbl:min_zoom":13.5,"mz:hierarchy_label":1,"mz:is_current":1,"mz:min_zoom":12,"src:geom":"geonames","wof:belongsto":[85682995,102191581,1713309703,85633135,1713305679],"wof:breaches":[],"wof:concordances":{"gn:id":794089},"wof:coterminous":[1713309703],"wof:country":"EE","wof:geomhash":"71bc741c3e88a1dcfa7c40a757c50720","wof:hierarchy":[{"continent_id":102191581,"country_id":85633135,"county_id":1713305679,"localadmin_id":1713309703,"locality_id":1193100209,"region_id":85682995}],"wof:id":1193100209,"wof:lang_x_official":["est"],"wof:lang_x_spoken":["est"],"wof:lastmodified":1596660921,"wof:name":"Vanaussaia","wof:parent_id":1713309703,"wof:placetype":"locality","wof:repo":"whosonfirst-data-admin-ee","wof:superseded_by":[],"wof:supersedes":[],"wof:tags":[]},"bbox":[27.15611,58.51083,27.15611,58.51083],"geometry":{"coordinates":[27.15611,58.51083],"type":"Point"}}