{"id":1360161943,"type":"Feature","properties":{"edtf:cessation":"uuuu","edtf:inception":"uuuu","geom:area":0,"geom:area_square_m":0,"geom:bbox":"27.50917,58.02833,27.50917,58.02833","geom:latitude":58.02833,"geom:longitude":27.50917,"gn:admin1_code":"21.0","gn:admin2_code":"732.0","gn:admin3_code":"8300.0","gn:asciiname":"Padosaaro","gn:country_code":"EE","gn:dem":36,"gn:feature_class":"P","gn:feature_code":"PPL","gn:geonameid":8620606,"gn:latitude":58.02833,"gn:longitude":27.50917,"gn:modification_date":"2017-11-25","gn:name":"Padosaarõ","gn:population":0,"gn:timezone":"Europe/Tallinn","iso:country":"EE","lbl:bbox":"27.48917,58.00833,27.52917,58.04833","lbl:max_zoom":18,"lbl:min_zoom":13.5,"mz:hierarchy_label":1,"mz:is_current":1,"mz:min_zoom":12,"name:und_x_variant":["Padosaarõ","Padosaare"],"src:geom":"geonames","wof:belongsto":[85682955,102191581,1713316153,85633135,1713305631],"wof:breaches":[],"wof:concordances":{"gn:id":8620606},"wof:country":"EE","wof:geomhash":"7347a036d24dc4fb31d565b420224ce6","wof:hierarchy":[{"continent_id":102191581,"country_id":85633135,"county_id":1713305631,"localadmin_id":1713316153,"locality_id":1360161943,"region_id":85682955}],"wof:id":1360161943,"wof:lang_x_official":["est"],"wof:lang_x_spoken":["est"],"wof:lastmodified":1596663695,"wof:name":"Padosaaro","wof:parent_id":1713316153,"wof:placetype":"locality","wof:repo":"whosonfirst-data-admin-ee","wof:superseded_by":[],"wof:supersedes":[],"wof:tags":[]},"bbox":[27.50917,58.02833,27.50917,58.02833],"geometry":{"coordinates":[27.50917,58.02833],"type":"Point"}}