{"id":1309692383,"type":"Feature","properties":{"edtf:cessation":"uuuu","edtf:inception":"uuuu","geom:area":0,"geom:area_square_m":0,"geom:bbox":"27.26111,58.12833,27.26111,58.12833","geom:latitude":58.12833,"geom:longitude":27.26111,"gn:admin1_code":"12.0","gn:admin2_code":"622.0","gn:admin3_code":"7858.0","gn:asciiname":"Suurmetsa","gn:country_code":"EE","gn:dem":50,"gn:feature_class":"P","gn:feature_code":"PPL","gn:geonameid":794159,"gn:latitude":58.12833,"gn:longitude":27.26111,"gn:modification_date":"2017-11-25","gn:name":"Suurmetsa","gn:population":0,"gn:timezone":"Europe/Tallinn","iso:country":"EE","lbl:bbox":"27.24111,58.10833,27.28111,58.14833","lbl:max_zoom":18,"lbl:min_zoom":13.5,"mz:hierarchy_label":1,"mz:is_current":1,"mz:min_zoom":12,"name:deu_x_preferred":["Suurmetsa"],"name:est_x_preferred":["Suurmetsa"],"name:hye_x_preferred":["Սուուռմեցա"],"name:pol_x_preferred":["Suurmetsa"],"name:spa_x_preferred":["Suurmetsa"],"name:ukr_x_preferred":["Суурметса"],"name:vol_x_preferred":["Suurmetsa"],"src:geom":"geonames","wof:belongsto":[85682955,102191581,1713310945,85633135,1713305791],"wof:breaches":[],"wof:concordances":{"gn:id":794159,"wk:page":"Suurmetsa"},"wof:coterminous":[1713310945],"wof:country":"EE","wof:geomhash":"add7b72a33e68d8114248ecf31ce4106","wof:hierarchy":[{"continent_id":102191581,"country_id":85633135,"county_id":1713305791,"localadmin_id":1713310945,"locality_id":1309692383,"region_id":85682955}],"wof:id":1309692383,"wof:lang_x_official":["est"],"wof:lang_x_spoken":["est"],"wof:lastmodified":1596676965,"wof:name":"Suurmetsa","wof:parent_id":1713310945,"wof:placetype":"locality","wof:repo":"whosonfirst-data-admin-ee","wof:superseded_by":[],"wof:supersedes":[],"wof:tags":[]},"bbox":[27.26111,58.12833,27.26111,58.12833],"geometry":{"coordinates":[27.26111,58.12833],"type":"Point"}}