{"id":1293364733,"type":"Feature","properties":{"edtf:cessation":"uuuu","edtf:inception":"uuuu","geom:area":0,"geom:area_square_m":0,"geom:bbox":"25.29889,58.24389,25.29889,58.24389","geom:latitude":58.24389,"geom:longitude":25.29889,"gn:admin1_code":"20.0","gn:admin2_code":"480.0","gn:admin3_code":"8240.0","gn:asciiname":"Undi","gn:country_code":"EE","gn:dem":61,"gn:feature_class":"P","gn:feature_code":"PPL","gn:geonameid":592085,"gn:latitude":58.24389,"gn:longitude":25.29889,"gn:modification_date":"2017-11-25","gn:name":"Undi","gn:population":0,"gn:timezone":"Europe/Tallinn","iso:country":"EE","lbl:bbox":"25.27889,58.22389,25.31889,58.26389","lbl:max_zoom":18,"lbl:min_zoom":13.5,"mz:hierarchy_label":1,"mz:is_current":1,"mz:min_zoom":12,"name:new_x_preferred":["उंडि मण्डल"],"name:tam_x_preferred":["உண்டி"],"name:tel_x_preferred":["ఉండి"],"name:und_x_variant":["Hundimaa","Khundima","Undi"],"name:urd_x_preferred":["اونڈی"],"src:geom":"geonames","wof:belongsto":[85682985,102191581,1713314139,85633135,1713305661],"wof:breaches":[],"wof:concordances":{"gn:id":592085},"wof:country":"EE","wof:geomhash":"ea60927057a99362c32724a092672f21","wof:hierarchy":[{"continent_id":102191581,"country_id":85633135,"county_id":1713305661,"localadmin_id":1713314139,"locality_id":1293364733,"region_id":85682985}],"wof:id":1293364733,"wof:lang_x_official":["est"],"wof:lang_x_spoken":["est"],"wof:lastmodified":1596661298,"wof:name":"Undi","wof:parent_id":1713314139,"wof:placetype":"locality","wof:repo":"whosonfirst-data-admin-ee","wof:superseded_by":[],"wof:supersedes":[],"wof:tags":[]},"bbox":[25.29889,58.24389,25.29889,58.24389],"geometry":{"coordinates":[25.29889,58.24389],"type":"Point"}}