{"id":1309805491,"type":"Feature","properties":{"edtf:cessation":"uuuu","edtf:inception":"uuuu","geom:area":0,"geom:area_square_m":0,"geom:bbox":"26.99639,59.25389,26.99639,59.25389","geom:latitude":59.25389,"geom:longitude":26.99639,"gn:admin1_code":"3.0","gn:admin2_code":"442.0","gn:admin3_code":"9200.0","gn:asciiname":"Veneoja","gn:country_code":"EE","gn:dem":62,"gn:feature_class":"P","gn:feature_code":"PPL","gn:geonameid":8618883,"gn:latitude":59.25389,"gn:longitude":26.99639,"gn:modification_date":"2017-11-25","gn:name":"Veneoja","gn:population":0,"gn:timezone":"Europe/Tallinn","iso:country":"EE","lbl:bbox":"26.97639,59.23389,27.01639,59.27389","lbl:max_zoom":18,"lbl:min_zoom":13.5,"mz:hierarchy_label":1,"mz:is_current":1,"mz:min_zoom":12,"name:deu_x_preferred":["Veneoja"],"name:est_x_preferred":["Veneoja"],"name:fas_x_preferred":["ونئوجا"],"name:hye_x_preferred":["Վենեոյա"],"name:pol_x_preferred":["Veneoja"],"name:spa_x_preferred":["Veneoja"],"name:und_x_variant":["Сел. Венеоя"],"name:vol_x_preferred":["Veneoja"],"src:geom":"geonames","wof:belongsto":[85683059,102191581,1713311809,85633135,1713305695],"wof:breaches":[],"wof:concordances":{"gn:id":8618883,"wk:page":"Veneoja"},"wof:coterminous":[1713311809],"wof:country":"EE","wof:geomhash":"f703861ae8bc39e7556aae0b57fd5c5d","wof:hierarchy":[{"continent_id":102191581,"country_id":85633135,"county_id":1713305695,"localadmin_id":1713311809,"locality_id":1309805491,"region_id":85683059}],"wof:id":1309805491,"wof:lang_x_official":["est"],"wof:lang_x_spoken":["est"],"wof:lastmodified":1596660799,"wof:name":"Veneoja","wof:parent_id":1713311809,"wof:placetype":"locality","wof:repo":"whosonfirst-data-admin-ee","wof:superseded_by":[],"wof:supersedes":[],"wof:tags":[]},"bbox":[26.99639,59.25389,26.99639,59.25389],"geometry":{"coordinates":[26.99639,59.25389],"type":"Point"}}