{"id":1108979963,"type":"Feature","properties":{"edtf:cessation":"uuuu","edtf:inception":"uuuu","geom:area":0,"geom:area_square_m":0,"geom:bbox":"26.96861,58.78611,26.96861,58.78611","geom:latitude":58.78611,"geom:longitude":26.96861,"gn:country":"EE","gn:fcode":"PPLX","gn:population":161,"iso:country":"EE","lbl:bbox":"26.94861,58.76611,26.98861,58.80611","lbl:latitude":58.78611,"lbl:longitude":26.96861,"lbl:max_zoom":18,"lbl:min_zoom":13,"mz:hierarchy_label":1,"mz:is_current":1,"mz:min_zoom":11,"mz:note":"Quattroshapes Point Gazetteer import 20170519","name:ceb_x_preferred":["Kasepya"],"name:est_x_preferred":["Kasepää"],"name:fra_x_preferred":["Kasepää"],"name:hye_x_preferred":["Կասեպեե"],"name:nld_x_preferred":["Kasepää"],"name:spa_x_preferred":["Kasepää"],"name:swe_x_preferred":["Kasepää"],"name:ukr_x_preferred":["Казепяе"],"name:vol_x_preferred":["Kasepää"],"qs_pg:aaroncc":"EE","qs_pg:gn_country":"EE","qs_pg:gn_fcode":"PPLX","qs_pg:gn_id":591542,"qs_pg:gn_pop":161,"qs_pg:name":"Kasepää","qs_pg:name_adm0":"Eesti","qs_pg:name_adm1":"Jõgevamaa","qs_pg:photos_9k":1,"qs_pg:photos_9r":1,"qs_pg:photos_all":3,"qs_pg:photos_sr":0,"qs_pg:pop_sr":1,"qs_pg:qs_id":966750,"qs_pg:qs_pg_placetype":"locality_gp_neighbourhood_gn","qs_pg:qs_pg_placetype_gp":"Town","qs_pg:woe_adm0":23424805,"qs_pg:woe_id":842799,"src:geom":"qs_pg","src:lbl_centroid":"qs_pg","src:population":"geonames","woe:adm0_id":23424805,"woe:name_adm0":"Eesti","woe:name_adm1":"Jõgevamaa","woe:placetype":"Town","wof:belongsto":[85683059,102191581,1713312053,85633135,1713305677],"wof:breaches":[],"wof:concordances":{"gn:id":591542,"qs_pg:id":966750,"woe:id":842799},"wof:coterminous":[1713312053],"wof:country":"EE","wof:created":1496793242,"wof:geomhash":"718fa208cdfc0ac478a08cff927d13b3","wof:hierarchy":[{"continent_id":102191581,"country_id":85633135,"county_id":1713305677,"localadmin_id":1713312053,"locality_id":1108979963,"region_id":85683059}],"wof:id":1108979963,"wof:lang_x_official":["est"],"wof:lang_x_spoken":["est"],"wof:lastmodified":1596661016,"wof:name":"Kasepää","wof:parent_id":1713312053,"wof:placetype":"locality","wof:population":161,"wof:population_rank":1,"wof:repo":"whosonfirst-data-admin-ee","wof:superseded_by":[],"wof:supersedes":[],"wof:tags":[]},"bbox":[26.96861,58.78611,26.96861,58.78611],"geometry":{"coordinates":[26.96861,58.78611],"type":"Point"}}