{"id":1226540639,"type":"Feature","properties":{"edtf:cessation":"uuuu","edtf:inception":"uuuu","geom:area":0,"geom:area_square_m":0,"geom:bbox":"25.97722,59.0175,25.97722,59.0175","geom:latitude":59.0175,"geom:longitude":25.97722,"gn:admin1_code":"4.0","gn:admin2_code":"255.0","gn:admin3_code":"4927.0","gn:asciiname":"Metsla","gn:country_code":"EE","gn:dem":100,"gn:feature_class":"P","gn:feature_code":"PPL","gn:geonameid":590217,"gn:latitude":59.0175,"gn:longitude":25.97722,"gn:modification_date":"2017-11-25","gn:name":"Metsla","gn:population":0,"gn:timezone":"Europe/Tallinn","iso:country":"EE","lbl:bbox":"25.95722,58.9975,25.99722,59.0375","lbl:max_zoom":18,"lbl:min_zoom":13.5,"mz:hierarchy_label":1,"mz:is_current":1,"mz:min_zoom":12,"name:vol_x_preferred":["Metsla"],"src:geom":"geonames","wof:belongsto":[85683031,102191581,1713306867,85633135,1713305765],"wof:breaches":[],"wof:concordances":{"gn:id":590217,"wk:page":"Metsla"},"wof:coterminous":[1713306867],"wof:country":"EE","wof:geomhash":"d9aa4ec0ab31d6343126af7d5f7f6857","wof:hierarchy":[{"continent_id":102191581,"country_id":85633135,"county_id":1713305765,"localadmin_id":1713306867,"locality_id":1226540639,"region_id":85683031}],"wof:id":1226540639,"wof:lang_x_official":["est"],"wof:lang_x_spoken":["est"],"wof:lastmodified":1596676647,"wof:name":"Metsla","wof:parent_id":1713306867,"wof:placetype":"locality","wof:repo":"whosonfirst-data-admin-ee","wof:superseded_by":[],"wof:supersedes":[],"wof:tags":[]},"bbox":[25.97722,59.0175,25.97722,59.0175],"geometry":{"coordinates":[25.97722,59.0175],"type":"Point"}}