{"id":1125934809,"type":"Feature","properties":{"edtf:cessation":"uuuu","edtf:inception":"uuuu","geom:area":0,"geom:area_square_m":0,"geom:bbox":"25.64917,58.34,25.64917,58.34","geom:latitude":58.34,"geom:longitude":25.64917,"gn:country":"EE","gn:fcode":"PPL","gn:population":107,"iso:country":"EE","lbl:bbox":"25.62917,58.32,25.66917,58.36","lbl:latitude":58.34,"lbl:longitude":25.64917,"lbl:max_zoom":18,"lbl:min_zoom":13,"mz:hierarchy_label":1,"mz:is_current":1,"mz:min_zoom":11,"mz:note":"Quattroshapes Point Gazetteer import 20170519","name:ceb_x_preferred":["Mäeltküla"],"name:est_x_preferred":["Mäeltküla"],"name:fra_x_preferred":["Mäeltküla"],"name:hye_x_preferred":["Մյաելտկյուլա"],"name:pol_x_preferred":["Mäeltküla"],"name:spa_x_preferred":["Mäeltküla"],"name:swe_x_preferred":["Mäeltküla"],"name:ukr_x_preferred":["Мяелткюла"],"name:und_x_variant":["Mäeküla"],"name:vol_x_preferred":["Mäeltküla"],"qs_pg:aaroncc":"EE","qs_pg:gn_country":"EE","qs_pg:gn_fcode":"PPL","qs_pg:gn_id":590407,"qs_pg:gn_pop":107,"qs_pg:name":"Mäeltküla","qs_pg:name_adm0":"Eesti","qs_pg:name_adm1":"Viljandimaa","qs_pg:photos_9r":0,"qs_pg:photos_sr":0,"qs_pg:pop_sr":1,"qs_pg:qs_id":1274121,"qs_pg:qs_pg_placetype":"locality","qs_pg:qs_pg_placetype_gp":"Town","qs_pg:woe_adm0":23424805,"qs_pg:woe_id":843865,"src:geom":"qs_pg","src:lbl_centroid":"qs_pg","src:population":"geonames","woe:adm0_id":23424805,"woe:name_adm0":"Eesti","woe:name_adm1":"Viljandimaa","woe:placetype":"Town","wof:belongsto":[85682985,102191581,1713310115,85633135,1713305669],"wof:breaches":[],"wof:concordances":{"gn:id":590407,"gp:id":843865,"qs_pg:id":1274121},"wof:coterminous":[1713310115],"wof:country":"EE","wof:created":1497296928,"wof:geomhash":"b0855d2c08e6a2c1c7af2c08a42d2622","wof:hierarchy":[{"continent_id":102191581,"country_id":85633135,"county_id":1713305669,"localadmin_id":1713310115,"locality_id":1125934809,"region_id":85682985}],"wof:id":1125934809,"wof:lang_x_official":["est"],"wof:lang_x_spoken":["est"],"wof:lastmodified":1596661263,"wof:name":"Mäeltküla","wof:parent_id":1713310115,"wof:placetype":"locality","wof:population":107,"wof:population_rank":1,"wof:repo":"whosonfirst-data-admin-ee","wof:superseded_by":[],"wof:supersedes":[],"wof:tags":[]},"bbox":[25.64917,58.34,25.64917,58.34],"geometry":{"coordinates":[25.64917,58.34],"type":"Point"}}