{
  "type": "Feature",
  "properties": {
    "iso:country":"FI",
    "wof:name":"Pasila",
    "wof:placetype":"neighbourhood"
},
  "geometry": {"coordinates":[24.92742370014196,60.20545263645963],"type":"Point"}
}