{"id":1209704097,"type":"Feature","properties":{"edtf:cessation":"uuuu","edtf:inception":"uuuu","geom:area":0,"geom:area_square_m":0,"geom:bbox":"23.90944,58.51667,23.90944,58.51667","geom:latitude":58.51667,"geom:longitude":23.90944,"gn:admin1_code":"11.0","gn:admin2_code":"430.0","gn:admin3_code":"8220.0","gn:asciiname":"Tiilima","gn:country_code":"EE","gn:dem":18,"gn:feature_class":"P","gn:feature_code":"PPL","gn:geonameid":8618215,"gn:latitude":58.51667,"gn:longitude":23.90944,"gn:modification_date":"2017-11-25","gn:name":"Tiilima","gn:population":0,"gn:timezone":"Europe/Tallinn","iso:country":"EE","lbl:bbox":"23.88944,58.49667,23.92944,58.53667","lbl:max_zoom":18,"lbl:min_zoom":13.5,"mz:hierarchy_label":1,"mz:is_current":1,"mz:min_zoom":12,"name:est_x_preferred":["Tiilima"],"name:hye_x_preferred":["Տիիլիմա"],"name:pol_x_preferred":["Tiilima"],"name:spa_x_preferred":["Tiilima"],"name:und_x_variant":["Tiilemaa"],"name:vol_x_preferred":["Tiilima"],"src:geom":"geonames","wof:belongsto":[85683001,102191581,1713313705,85633135,1713305721],"wof:breaches":[],"wof:concordances":{"gn:id":8618215,"wk:page":"Tiilima"},"wof:country":"EE","wof:geomhash":"7f43cfe9b858a62cb76a77966dacbf54","wof:hierarchy":[{"continent_id":102191581,"country_id":85633135,"county_id":1713305721,"localadmin_id":1713313705,"locality_id":1209704097,"region_id":85683001}],"wof:id":1209704097,"wof:lang_x_official":["est"],"wof:lang_x_spoken":["est"],"wof:lastmodified":1596661689,"wof:name":"Tiilima","wof:parent_id":1713313705,"wof:placetype":"locality","wof:repo":"whosonfirst-data-admin-ee","wof:superseded_by":[],"wof:supersedes":[],"wof:tags":[]},"bbox":[23.90944,58.51667,23.90944,58.51667],"geometry":{"coordinates":[23.90944,58.51667],"type":"Point"}}