{"id":1326691937,"type":"Feature","properties":{"edtf:cessation":"uuuu","edtf:inception":"uuuu","geom:area":0,"geom:area_square_m":0,"geom:bbox":"25.47778,58.18556,25.47778,58.18556","geom:latitude":58.18556,"geom:longitude":25.47778,"gn:admin1_code":"20.0","gn:admin2_code":"480.0","gn:admin3_code":"1625.0","gn:asciiname":"Kaarli","gn:cc2":"EE","gn:country_code":"EE","gn:dem":65,"gn:feature_class":"P","gn:feature_code":"PPL","gn:geonameid":591848,"gn:latitude":58.18556,"gn:longitude":25.47778,"gn:modification_date":"2017-11-25","gn:name":"Kaarli","gn:population":0,"gn:timezone":"Europe/Tallinn","iso:country":"EE","lbl:bbox":"25.45778,58.16556,25.49778,58.20556","lbl:max_zoom":18,"lbl:min_zoom":13.5,"mz:hierarchy_label":1,"mz:is_current":1,"mz:min_zoom":12,"name:eng_x_preferred":["Kaarli"],"name:rus_x_preferred":["Каарли"],"name:und_x_variant":["Karli"],"src:geom":"geonames","wof:belongsto":[85682985,102191581,1713314305,85633135,1713305661],"wof:breaches":[],"wof:concordances":{"gn:id":591848},"wof:coterminous":[1713311659],"wof:country":"EE","wof:geomhash":"d3486c0bef495ea68e00b52fd2cbc58c","wof:hierarchy":[{"continent_id":102191581,"country_id":85633135,"county_id":1713305661,"localadmin_id":1713314305,"locality_id":1326691937,"region_id":85682985}],"wof:id":1326691937,"wof:lang_x_official":["est"],"wof:lang_x_spoken":["est"],"wof:lastmodified":1596661302,"wof:name":"Kaarli","wof:parent_id":1713314305,"wof:placetype":"locality","wof:repo":"whosonfirst-data-admin-ee","wof:superseded_by":[],"wof:supersedes":[],"wof:tags":[]},"bbox":[25.47778,58.18556,25.47778,58.18556],"geometry":{"coordinates":[25.47778,58.18556],"type":"Point"}}