{"id":1242854609,"type":"Feature","properties":{"edtf:cessation":"uuuu","edtf:inception":"uuuu","geom:area":0,"geom:area_square_m":0,"geom:bbox":"27.14111,58.12333,27.14111,58.12333","geom:latitude":58.12333,"geom:longitude":27.14111,"gn:admin1_code":"12.0","gn:admin2_code":"622.0","gn:admin3_code":"1081.0","gn:asciiname":"Kooskora","gn:country_code":"EE","gn:dem":46,"gn:feature_class":"P","gn:feature_code":"PPL","gn:geonameid":8620762,"gn:latitude":58.12333,"gn:longitude":27.14111,"gn:modification_date":"2017-11-25","gn:name":"Kooskora","gn:population":0,"gn:timezone":"Europe/Tallinn","iso:country":"EE","lbl:bbox":"27.12111,58.10333,27.16111,58.14333","lbl:max_zoom":18,"lbl:min_zoom":13.5,"mz:hierarchy_label":1,"mz:is_current":1,"mz:min_zoom":12,"src:geom":"geonames","wof:belongsto":[85682955,102191581,1713311137,85633135,1713305791],"wof:breaches":[],"wof:concordances":{"gn:id":8620762},"wof:country":"EE","wof:geomhash":"8fbbe746f3ff0158f2a70f5aab40a121","wof:hierarchy":[{"continent_id":102191581,"country_id":85633135,"county_id":1713305791,"localadmin_id":1713311137,"locality_id":1242854609,"region_id":85682955}],"wof:id":1242854609,"wof:lang_x_official":["est"],"wof:lang_x_spoken":["est"],"wof:lastmodified":1596676965,"wof:name":"Kooskora","wof:parent_id":1713311137,"wof:placetype":"locality","wof:repo":"whosonfirst-data-admin-ee","wof:superseded_by":[],"wof:supersedes":[],"wof:tags":[]},"bbox":[27.14111,58.12333,27.14111,58.12333],"geometry":{"coordinates":[27.14111,58.12333],"type":"Point"}}