{"id":1125881997,"type":"Feature","properties":{"edtf:cessation":"uuuu","edtf:inception":"uuuu","geom:area":0,"geom:area_square_m":0,"geom:bbox":"23.76972,58.97056,23.76972,58.97056","geom:latitude":58.97056,"geom:longitude":23.76972,"gn:country":"EE","gn:fcode":"PPL","gn:population":225,"iso:country":"EE","lbl:bbox":"23.74972,58.95056,23.78972,58.99056","lbl:latitude":58.97056,"lbl:longitude":23.76972,"lbl:max_zoom":17,"lbl:min_zoom":12.5,"mz:hierarchy_label":1,"mz:is_current":1,"mz:min_zoom":11,"mz:note":"Quattroshapes Point Gazetteer import 20170519","name:ceb_x_preferred":["Nigula"],"name:deu_x_preferred":["Nigula"],"name:eng_x_preferred":["Nigula"],"name:est_x_preferred":["Nigula"],"name:fra_x_preferred":["Nigula"],"name:hye_x_preferred":["Նիգուլա"],"name:nld_x_preferred":["Nigula"],"name:pol_x_preferred":["Nigula"],"name:spa_x_preferred":["Nigula"],"name:ukr_x_preferred":["Ніґула"],"name:vol_x_preferred":["Nigula"],"qs_pg:aaroncc":"EE","qs_pg:gn_country":"EE","qs_pg:gn_fcode":"PPL","qs_pg:gn_id":794878,"qs_pg:gn_pop":225,"qs_pg:name":"Nigula","qs_pg:name_adm0":"Eesti","qs_pg:name_adm1":"Läänemaa","qs_pg:photos_9k":1,"qs_pg:photos_9r":1,"qs_pg:photos_all":16,"qs_pg:photos_sr":0,"qs_pg:pop_sr":2,"qs_pg:qs_id":889999,"qs_pg:qs_pg_placetype":"locality","qs_pg:qs_pg_placetype_gp":"Town","qs_pg:woe_adm0":23424805,"qs_pg:woe_id":844243,"src:geom":"qs_pg","src:lbl_centroid":"qs_pg","src:population":"geonames","woe:adm0_id":23424805,"woe:name_adm0":"Eesti","woe:name_adm1":"Läänemaa","woe:placetype":"Town","wof:belongsto":[85683001,102191581,1713309033,85633135,1713305701],"wof:breaches":[],"wof:concordances":{"gn:id":794878,"gp:id":844243,"qs_pg:id":889999,"wd:id":"Q1023652"},"wof:coterminous":[1713309033],"wof:country":"EE","wof:created":1497294860,"wof:geomhash":"bd19203a5f38a58eaeb4f10bb95766dd","wof:hierarchy":[{"continent_id":102191581,"country_id":85633135,"county_id":1713305701,"localadmin_id":1713309033,"locality_id":1125881997,"region_id":85683001}],"wof:id":1125881997,"wof:lang_x_official":["est"],"wof:lang_x_spoken":["est"],"wof:lastmodified":1596677427,"wof:name":"Nigula","wof:parent_id":1713309033,"wof:placetype":"locality","wof:population":225,"wof:population_rank":2,"wof:repo":"whosonfirst-data-admin-ee","wof:superseded_by":[],"wof:supersedes":[],"wof:tags":[]},"bbox":[23.76972,58.97056,23.76972,58.97056],"geometry":{"coordinates":[23.76972,58.97056],"type":"Point"}}