{"id":1225920133,"type":"Feature","properties":{"edtf:cessation":"uuuu","edtf:inception":"uuuu","geom:area":0,"geom:area_square_m":0,"geom:bbox":"26.90889,58.35694,26.90889,58.35694","geom:latitude":58.35694,"geom:longitude":26.90889,"gn:admin1_code":"18.0","gn:admin2_code":"291.0","gn:admin3_code":"8987.0","gn:asciiname":"Vana-Kastre","gn:country_code":"EE","gn:dem":39,"gn:feature_class":"P","gn:feature_code":"PPL","gn:geonameid":587820,"gn:latitude":58.35694,"gn:longitude":26.90889,"gn:modification_date":"2017-11-25","gn:name":"Vana-Kastre","gn:population":0,"gn:timezone":"Europe/Tallinn","iso:country":"EE","lbl:bbox":"26.88889,58.33694,26.92889,58.37694","lbl:max_zoom":18,"lbl:min_zoom":13.5,"mz:hierarchy_label":1,"mz:is_current":1,"mz:min_zoom":12,"name:ara_x_preferred":["فانا كستر"],"name:est_x_preferred":["Vana-Kastre"],"name:fas_x_preferred":["وانا کستر"],"name:hye_x_preferred":["Վանա-Կաստռե"],"name:nld_x_preferred":["Vana-Kastre"],"name:pol_x_preferred":["Vana-Kastre"],"name:spa_x_preferred":["Vana-Kastre"],"name:ukr_x_preferred":["Вана-Кастре"],"name:vol_x_preferred":["Vana-Kastre"],"src:geom":"geonames","wof:belongsto":[85682995,102191581,1713313883,85633135,1713305699],"wof:breaches":[],"wof:concordances":{"gn:id":587820,"wk:page":"Vana-Kastre"},"wof:coterminous":[1713313883],"wof:country":"EE","wof:geomhash":"a521e1b003adad5e96ae859f54632e8d","wof:hierarchy":[{"continent_id":102191581,"country_id":85633135,"county_id":1713305699,"localadmin_id":1713313883,"locality_id":1225920133,"region_id":85682995}],"wof:id":1225920133,"wof:lang_x_official":["est"],"wof:lang_x_spoken":["est"],"wof:lastmodified":1596660662,"wof:name":"Vana-Kastre","wof:parent_id":1713313883,"wof:placetype":"locality","wof:repo":"whosonfirst-data-admin-ee","wof:superseded_by":[],"wof:supersedes":[],"wof:tags":[]},"bbox":[26.90889,58.35694,26.90889,58.35694],"geometry":{"coordinates":[26.90889,58.35694],"type":"Point"}}