{"id":1360159885,"type":"Feature","properties":{"edtf:cessation":"uuuu","edtf:inception":"uuuu","geom:area":0,"geom:area_square_m":0,"geom:bbox":"26.42,57.73194,26.42,57.73194","geom:latitude":57.73194,"geom:longitude":26.42,"gn:admin1_code":"19.0","gn:admin2_code":"855.0","gn:admin3_code":"6887.0","gn:asciiname":"Madsa","gn:country_code":"EE","gn:dem":90,"gn:feature_class":"P","gn:feature_code":"PPL","gn:geonameid":8619087,"gn:latitude":57.73194,"gn:longitude":26.42,"gn:modification_date":"2017-11-25","gn:name":"Madsa","gn:population":0,"gn:timezone":"Europe/Tallinn","iso:country":"EE","lbl:bbox":"26.4,57.71194,26.44,57.75194","lbl:max_zoom":18,"lbl:min_zoom":13.5,"mz:hierarchy_label":1,"mz:is_current":1,"mz:min_zoom":12,"src:geom":"geonames","wof:belongsto":[85682941,102191581,1713314739,85633135,1713305753],"wof:breaches":[],"wof:concordances":{"gn:id":8619087},"wof:country":"EE","wof:geomhash":"63f4218986727593c3d3c24c95a1e312","wof:hierarchy":[{"continent_id":102191581,"country_id":85633135,"county_id":1713305753,"localadmin_id":1713314739,"locality_id":1360159885,"region_id":85682941}],"wof:id":1360159885,"wof:lang_x_official":["est"],"wof:lang_x_spoken":["est"],"wof:lastmodified":1596661949,"wof:name":"Madsa","wof:parent_id":1713314739,"wof:placetype":"locality","wof:repo":"whosonfirst-data-admin-ee","wof:superseded_by":[],"wof:supersedes":[],"wof:tags":[]},"bbox":[26.42,57.73194,26.42,57.73194],"geometry":{"coordinates":[26.42,57.73194],"type":"Point"}}