{"id":1125936849,"type":"Feature","properties":{"edtf:cessation":"uuuu","edtf:inception":"uuuu","geom:area":0,"geom:area_square_m":0,"geom:bbox":"25.98417,58.61111,25.98417,58.61111","geom:latitude":58.61111,"geom:longitude":25.98417,"gn:country":"EE","gn:fcode":"PPL","gn:population":489,"iso:country":"EE","lbl:bbox":"25.96417,58.59111,26.00417,58.63111","lbl:latitude":58.61111,"lbl:longitude":25.98417,"lbl:max_zoom":17,"lbl:min_zoom":12.5,"mz:hierarchy_label":1,"mz:is_current":1,"mz:min_zoom":11,"mz:note":"Quattroshapes Point Gazetteer import 20170519","name:ceb_x_preferred":["Väike-Kamari"],"name:eng_x_preferred":["Väike-Kamari"],"name:est_x_preferred":["Väike-Kamari"],"name:hye_x_preferred":["Վեիկե-Կամառի"],"name:nld_x_preferred":["Väike-Kamari"],"name:pol_x_preferred":["Väike-Kamari"],"name:spa_x_preferred":["Väike-Kamari"],"name:swe_x_preferred":["Väike-Kamari"],"name:vol_x_preferred":["Väike-Kamari"],"qs_pg:aaroncc":"EE","qs_pg:gn_country":"EE","qs_pg:gn_fcode":"PPL","qs_pg:gn_id":793911,"qs_pg:gn_pop":489,"qs_pg:name":"Väike-Kamari","qs_pg:name_adm0":"Eesti","qs_pg:name_adm1":"Jõgevamaa","qs_pg:photos_9r":0,"qs_pg:photos_sr":0,"qs_pg:pop_sr":2,"qs_pg:qs_id":1274698,"qs_pg:qs_pg_placetype":"locality","qs_pg:qs_pg_placetype_gp":"Town","qs_pg:woe_adm0":23424805,"qs_pg:woe_id":846185,"src:geom":"qs_pg","src:lbl_centroid":"qs_pg","src:population":"geonames","woe:adm0_id":23424805,"woe:name_adm0":"Eesti","woe:name_adm1":"Jõgevamaa","woe:placetype":"Town","wof:belongsto":[85683009,102191581,1713314293,85633135,1713305657],"wof:breaches":[],"wof:concordances":{"gn:id":793911,"gp:id":846185,"qs_pg:id":1274698,"wd:id":"Q7944308"},"wof:coterminous":[1713314293],"wof:country":"EE","wof:created":1497296993,"wof:geomhash":"7b0d0df8913aedc04dbfcbd158c0c99e","wof:hierarchy":[{"continent_id":102191581,"country_id":85633135,"county_id":1713305657,"localadmin_id":1713314293,"locality_id":1125936849,"region_id":85683009}],"wof:id":1125936849,"wof:lang_x_official":["est"],"wof:lang_x_spoken":["est"],"wof:lastmodified":1596676507,"wof:name":"Väike-Kamari","wof:parent_id":1713314293,"wof:placetype":"locality","wof:population":489,"wof:population_rank":2,"wof:repo":"whosonfirst-data-admin-ee","wof:superseded_by":[],"wof:supersedes":[],"wof:tags":[]},"bbox":[25.98417,58.61111,25.98417,58.61111],"geometry":{"coordinates":[25.98417,58.61111],"type":"Point"}}