{"id":1126065403,"type":"Feature","properties":{"edtf:cessation":"uuuu","edtf:inception":"uuuu","geom:area":0,"geom:area_square_m":0,"geom:bbox":"23.83528,58.51139,23.83528,58.51139","geom:latitude":58.51139,"geom:longitude":23.83528,"gn:country":"EE","gn:fcode":"PPLX","gn:population":129,"iso:country":"EE","lbl:bbox":"23.83028,58.50639,23.84028,58.51639","lbl:latitude":58.51139,"lbl:longitude":23.83528,"lbl:max_zoom":18,"mz:hierarchy_label":1,"mz:is_current":1,"mz:min_zoom":15,"mz:note":"Quattroshapes Point Gazetteer import 20170519","name:ceb_x_preferred":["Tõusi"],"name:est_x_preferred":["Tõusi"],"name:fas_x_preferred":["توئوسی"],"name:hye_x_preferred":["Տիուսի"],"name:pol_x_preferred":["Tõusi"],"name:spa_x_preferred":["Tõusi"],"name:swe_x_preferred":["Tõusi"],"name:und_x_variant":["Khallivanni"],"name:vol_x_preferred":["Tõusi"],"qs_pg:aaroncc":"EE","qs_pg:gn_country":"EE","qs_pg:gn_fcode":"PPLX","qs_pg:gn_id":588199,"qs_pg:gn_pop":129,"qs_pg:name":"Tõusi","qs_pg:photos_9r":0,"qs_pg:photos_sr":0,"qs_pg:pop_sr":1,"qs_pg:qs_id":81101,"qs_pg:qs_pg_placetype":"neighbourhood","src:geom":"qs_pg","src:lbl_centroid":"qs_pg","src:population":"geonames","wof:belongsto":[102191581,1713309439,85633135,1713305721,85683001],"wof:breaches":[],"wof:concordances":{"gn:id":588199,"qs_pg:id":81101},"wof:country":"EE","wof:created":1497308797,"wof:geomhash":"dd51d23abc753d7e7320000e7f87e57b","wof:hierarchy":[{"continent_id":102191581,"country_id":85633135,"county_id":1713305721,"localadmin_id":1713309439,"locality_id":-1,"neighbourhood_id":1126065403,"region_id":85683001}],"wof:id":1126065403,"wof:lastmodified":1596661705,"wof:name":"Tõusi","wof:parent_id":-1,"wof:placetype":"neighbourhood","wof:population":129,"wof:population_rank":1,"wof:repo":"whosonfirst-data-admin-ee","wof:superseded_by":[],"wof:supersedes":[],"wof:tags":[]},"bbox":[23.83528,58.51139,23.83528,58.51139],"geometry":{"coordinates":[23.83528,58.51139],"type":"Point"}}