{"id":1126045095,"type":"Feature","properties":{"edtf:cessation":"uuuu","edtf:inception":"uuuu","geom:area":0,"geom:area_square_m":0,"geom:bbox":"24.79722,59.55694,24.79722,59.55694","geom:latitude":59.55694,"geom:longitude":24.79722,"gn:country":"EE","gn:fcode":"PPL","gn:population":316,"iso:country":"EE","lbl:bbox":"24.77722,59.53694,24.81722,59.57694","lbl:latitude":59.55694,"lbl:longitude":24.79722,"lbl:max_zoom":17,"lbl:min_zoom":12.5,"mz:hierarchy_label":1,"mz:is_current":1,"mz:min_zoom":11,"mz:note":"Quattroshapes Point Gazetteer import 20170519","name:bul_x_preferred":["Рохунеме"],"name:ceb_x_preferred":["Rohuneeme"],"name:eng_x_preferred":["Rohuneeme"],"name:est_x_preferred":["Rohuneeme"],"name:fra_x_preferred":["Rohuneeme"],"name:hye_x_preferred":["Ռոհունեեմե"],"name:nld_x_preferred":["Rohuneeme"],"name:pol_x_preferred":["Rohuneeme"],"name:rus_x_preferred":["Рохунеэме"],"name:spa_x_preferred":["Rohuneeme"],"name:swe_x_preferred":["Rohuneeme"],"name:und_x_variant":["Rokhuneme"],"name:vol_x_preferred":["Rohuneeme"],"qs_pg:aaroncc":"EE","qs_pg:gn_country":"EE","qs_pg:gn_fcode":"PPL","qs_pg:gn_id":588984,"qs_pg:gn_pop":316,"qs_pg:name":"Rohuneeme","qs_pg:photos_9r":0,"qs_pg:photos_sr":0,"qs_pg:pop_sr":2,"qs_pg:qs_id":550129,"qs_pg:qs_pg_placetype":"locality","src:geom":"qs_pg","src:lbl_centroid":"qs_pg","src:population":"geonames","wof:belongsto":[85683055,102191581,1713306067,85633135,1713305625],"wof:breaches":[],"wof:concordances":{"gn:id":588984,"qs_pg:id":550129,"wd:id":"Q2417795"},"wof:coterminous":[1713306067],"wof:country":"EE","wof:created":1497302386,"wof:geomhash":"2c0bfedd4bc78264e424b7b04f2373d6","wof:hierarchy":[{"continent_id":102191581,"country_id":85633135,"county_id":1713305625,"localadmin_id":1713306067,"locality_id":1126045095,"region_id":85683055}],"wof:id":1126045095,"wof:lang_x_official":["est"],"wof:lang_x_spoken":["est"],"wof:lastmodified":1596676119,"wof:name":"Rohuneeme","wof:parent_id":1713306067,"wof:placetype":"locality","wof:population":316,"wof:population_rank":2,"wof:repo":"whosonfirst-data-admin-ee","wof:superseded_by":[],"wof:supersedes":[],"wof:tags":[]},"bbox":[24.79722,59.55694,24.79722,59.55694],"geometry":{"coordinates":[24.79722,59.55694],"type":"Point"}}