{"id":1259667173,"type":"Feature","properties":{"edtf:cessation":"uuuu","edtf:inception":"uuuu","geom:area":0,"geom:area_square_m":0,"geom:bbox":"21.92472,58.2925,21.92472,58.2925","geom:latitude":58.2925,"geom:longitude":21.92472,"gn:admin1_code":"14.0","gn:admin2_code":"714.0","gn:admin3_code":"1436.0","gn:asciiname":"Atla","gn:cc2":"EE","gn:country_code":"EE","gn:dem":13,"gn:feature_class":"P","gn:feature_code":"PPL","gn:geonameid":592361,"gn:latitude":58.2925,"gn:longitude":21.92472,"gn:modification_date":"2017-11-25","gn:name":"Atla","gn:population":0,"gn:timezone":"Europe/Tallinn","iso:country":"EE","lbl:bbox":"21.90472,58.2725,21.94472,58.3125","lbl:max_zoom":18,"lbl:min_zoom":13.5,"mz:hierarchy_label":1,"mz:is_current":1,"mz:min_zoom":12,"name:deu_x_preferred":["Atla"],"name:est_x_preferred":["Atla"],"name:fra_x_preferred":["Atla"],"name:hye_x_preferred":["Ատլա"],"name:pol_x_preferred":["Atla"],"name:spa_x_preferred":["Atla"],"name:ukr_x_preferred":["Атла"],"name:und_x_variant":["Myza Atla","Atla Asundus"],"name:vol_x_preferred":["Atla"],"src:geom":"geonames","wof:belongsto":[85682947,102191581,1713307557,85633135,1713305627],"wof:breaches":[],"wof:concordances":{"gn:id":592361,"wk:page":"Atla%2C_Saare_County"},"wof:coterminous":[1713307557],"wof:country":"EE","wof:geomhash":"5061d14d0c8072cff13a786fa3bbbb38","wof:hierarchy":[{"continent_id":102191581,"country_id":85633135,"county_id":1713305627,"localadmin_id":1713307557,"locality_id":1259667173,"region_id":85682947}],"wof:id":1259667173,"wof:lang_x_official":["est"],"wof:lang_x_spoken":["est"],"wof:lastmodified":1596674945,"wof:name":"Atla","wof:parent_id":1713307557,"wof:placetype":"locality","wof:repo":"whosonfirst-data-admin-ee","wof:superseded_by":[],"wof:supersedes":[],"wof:tags":[]},"bbox":[21.92472,58.2925,21.92472,58.2925],"geometry":{"coordinates":[21.92472,58.2925],"type":"Point"}}