{"id":1193257221,"type":"Feature","properties":{"edtf:cessation":"uuuu","edtf:inception":"uuuu","geom:area":0,"geom:area_square_m":0,"geom:bbox":"23.24528,58.63528,23.24528,58.63528","geom:latitude":58.63528,"geom:longitude":23.24528,"gn:admin1_code":"14.0","gn:admin2_code":"478.0","gn:admin3_code":"4292.0","gn:asciiname":"Kapi","gn:country_code":"EE","gn:dem":16,"gn:feature_class":"P","gn:feature_code":"PPL","gn:geonameid":591648,"gn:latitude":58.63528,"gn:longitude":23.24528,"gn:modification_date":"2017-11-25","gn:name":"Kapi","gn:population":0,"gn:timezone":"Europe/Tallinn","iso:country":"EE","lbl:bbox":"23.22528,58.61528,23.26528,58.65528","lbl:max_zoom":18,"lbl:min_zoom":13.5,"mz:hierarchy_label":1,"mz:is_current":1,"mz:min_zoom":12,"name:deu_x_preferred":["Kapi"],"name:est_x_preferred":["Kapi"],"name:hye_x_preferred":["Կապի"],"name:pol_x_preferred":["Kapi"],"name:spa_x_preferred":["Kapi"],"name:vol_x_preferred":["Kapi"],"src:geom":"geonames","wof:belongsto":[85682947,102191581,1713306167,85633135,1713305623],"wof:breaches":[],"wof:concordances":{"gn:id":591648,"wk:page":"Kapi%2C_Estonia"},"wof:coterminous":[1713306145],"wof:country":"EE","wof:geomhash":"12a15dad9c2de2e73f466b702f141923","wof:hierarchy":[{"continent_id":102191581,"country_id":85633135,"county_id":1713305623,"localadmin_id":1713306167,"locality_id":1193257221,"region_id":85682947}],"wof:id":1193257221,"wof:lang_x_official":["est"],"wof:lang_x_spoken":["est"],"wof:lastmodified":1596675298,"wof:name":"Kapi","wof:parent_id":1713306167,"wof:placetype":"locality","wof:repo":"whosonfirst-data-admin-ee","wof:superseded_by":[],"wof:supersedes":[],"wof:tags":[]},"bbox":[23.24528,58.63528,23.24528,58.63528],"geometry":{"coordinates":[23.24528,58.63528],"type":"Point"}}