{"id":1209211697,"type":"Feature","properties":{"edtf:cessation":"uuuu","edtf:inception":"uuuu","geom:area":0,"geom:area_square_m":0,"geom:bbox":"23.66667,58.78333,23.66667,58.78333","geom:latitude":58.78333,"geom:longitude":23.66667,"gn:admin1_code":"7.0","gn:admin2_code":"184.0","gn:admin3_code":"1711.0","gn:asciiname":"Haeska","gn:cc2":"EE","gn:country_code":"EE","gn:dem":3,"gn:feature_class":"P","gn:feature_code":"PPL","gn:geonameid":592212,"gn:latitude":58.78333,"gn:longitude":23.66667,"gn:modification_date":"2017-11-25","gn:name":"Haeska","gn:population":0,"gn:timezone":"Europe/Tallinn","iso:country":"EE","lbl:bbox":"23.64667,58.76333,23.68667,58.80333","lbl:max_zoom":18,"lbl:min_zoom":13.5,"mz:hierarchy_label":1,"mz:is_current":1,"mz:min_zoom":12,"name:deu_x_preferred":["Haeska"],"name:est_x_preferred":["Haeska"],"name:nld_x_preferred":["Haeska"],"name:pol_x_preferred":["Haeska"],"name:und_x_variant":["Myza Khaeska","Haeska Asundus"],"name:vol_x_preferred":["Haeska"],"src:geom":"geonames","wof:belongsto":[85683001,102191581,1713314681,85633135,1713305755],"wof:breaches":[],"wof:concordances":{"gn:id":592212},"wof:country":"EE","wof:geomhash":"884158a0ba14292f784d0a7055315dfd","wof:hierarchy":[{"continent_id":102191581,"country_id":85633135,"county_id":1713305755,"localadmin_id":1713314681,"locality_id":1209211697,"region_id":85683001}],"wof:id":1209211697,"wof:lang_x_official":["est"],"wof:lang_x_spoken":["est"],"wof:lastmodified":1596662771,"wof:name":"Haeska","wof:parent_id":1713314681,"wof:placetype":"locality","wof:repo":"whosonfirst-data-admin-ee","wof:superseded_by":[],"wof:supersedes":[],"wof:tags":[]},"bbox":[23.66667,58.78333,23.66667,58.78333],"geometry":{"coordinates":[23.66667,58.78333],"type":"Point"}}