{"id":1243533785,"type":"Feature","properties":{"edtf:cessation":"uuuu","edtf:inception":"uuuu","geom:area":0,"geom:area_square_m":0,"geom:bbox":"24.77417,59.18583,24.77417,59.18583","geom:latitude":59.18583,"geom:longitude":24.77417,"gn:admin1_code":"13.0","gn:admin2_code":"317.0","gn:admin3_code":"8721.0","gn:asciiname":"Urge","gn:country_code":"EE","gn:dem":74,"gn:feature_class":"P","gn:feature_code":"PPL","gn:geonameid":588044,"gn:latitude":59.18583,"gn:longitude":24.77417,"gn:modification_date":"2017-11-25","gn:name":"Urge","gn:population":0,"gn:timezone":"Europe/Tallinn","iso:country":"EE","lbl:bbox":"24.75417,59.16583,24.79417,59.20583","lbl:max_zoom":18,"lbl:min_zoom":13.5,"mz:hierarchy_label":1,"mz:is_current":1,"mz:min_zoom":12,"name:est_x_preferred":["Urge"],"name:hye_x_preferred":["Ուռգե"],"name:pol_x_preferred":["Urge"],"name:rus_x_preferred":["Урге"],"name:sco_x_preferred":["Urge"],"name:spa_x_preferred":["Urge"],"name:vol_x_preferred":["Urge"],"src:geom":"geonames","wof:belongsto":[85683013,102191581,1713313249,85633135,1713305707],"wof:breaches":[],"wof:concordances":{"gn:id":588044,"wk:page":"Urge%2C_Rapla_County"},"wof:coterminous":[1713313249],"wof:country":"EE","wof:geomhash":"90b7ab86544b52c34144caaa8d387513","wof:hierarchy":[{"continent_id":102191581,"country_id":85633135,"county_id":1713305707,"localadmin_id":1713313249,"locality_id":1243533785,"region_id":85683013}],"wof:id":1243533785,"wof:lang_x_official":["est"],"wof:lang_x_spoken":["est"],"wof:lastmodified":1596677037,"wof:name":"Urge","wof:parent_id":1713313249,"wof:placetype":"locality","wof:repo":"whosonfirst-data-admin-ee","wof:superseded_by":[],"wof:supersedes":[],"wof:tags":[]},"bbox":[24.77417,59.18583,24.77417,59.18583],"geometry":{"coordinates":[24.77417,59.18583],"type":"Point"}}