{"id":1276958139,"type":"Feature","properties":{"edtf:cessation":"uuuu","edtf:inception":"uuuu","geom:area":0,"geom:area_square_m":0,"geom:bbox":"24.83333,59.18333,24.83333,59.18333","geom:latitude":59.18333,"geom:longitude":24.83333,"gn:admin1_code":"13.0","gn:admin2_code":"317.0","gn:admin3_code":"1270.0","gn:asciiname":"Angerja-UElejoe","gn:country_code":"EE","gn:dem":66,"gn:feature_class":"P","gn:feature_code":"PPL","gn:geonameid":592484,"gn:latitude":59.18333,"gn:longitude":24.83333,"gn:modification_date":"2017-11-25","gn:name":"Angerja-Ülejõe","gn:population":0,"gn:timezone":"Europe/Tallinn","iso:country":"EE","lbl:bbox":"24.81333,59.16333,24.85333,59.20333","lbl:max_zoom":18,"lbl:min_zoom":13.5,"mz:hierarchy_label":1,"mz:is_current":1,"mz:min_zoom":12,"name:und_x_variant":["Angerja","Anger’ya-Yuleyye","Angerja-Ülejõe"],"src:geom":"geonames","wof:belongsto":[85683013,102191581,1713314247,85633135,1713305707],"wof:breaches":[],"wof:concordances":{"gn:id":592484},"wof:country":"EE","wof:geomhash":"22af431447e4423a8210237151922460","wof:hierarchy":[{"continent_id":102191581,"country_id":85633135,"county_id":1713305707,"localadmin_id":1713314247,"locality_id":1276958139,"region_id":85683013}],"wof:id":1276958139,"wof:lang_x_official":["est"],"wof:lang_x_spoken":["est"],"wof:lastmodified":1596677037,"wof:name":"Angerja-UElejoe","wof:parent_id":1713314247,"wof:placetype":"locality","wof:repo":"whosonfirst-data-admin-ee","wof:superseded_by":[],"wof:supersedes":[],"wof:tags":[]},"bbox":[24.83333,59.18333,24.83333,59.18333],"geometry":{"coordinates":[24.83333,59.18333],"type":"Point"}}