{"id":1243041711,"type":"Feature","properties":{"edtf:cessation":"uuuu","edtf:inception":"uuuu","geom:area":0,"geom:area_square_m":0,"geom:bbox":"23.01889,58.54139,23.01889,58.54139","geom:latitude":58.54139,"geom:longitude":23.01889,"gn:admin1_code":"14.0","gn:admin2_code":"714.0","gn:admin3_code":"4363.0","gn:asciiname":"Suur-Rahula","gn:country_code":"EE","gn:dem":13,"gn:feature_class":"P","gn:feature_code":"PPL","gn:geonameid":588482,"gn:latitude":58.54139,"gn:longitude":23.01889,"gn:modification_date":"2017-11-25","gn:name":"Suur-Rahula","gn:population":0,"gn:timezone":"Europe/Tallinn","iso:country":"EE","lbl:bbox":"22.99889,58.52139,23.03889,58.56139","lbl:max_zoom":18,"lbl:min_zoom":13.5,"mz:hierarchy_label":1,"mz:is_current":1,"mz:min_zoom":12,"name:deu_x_preferred":["Suur-Rahula"],"name:est_x_preferred":["Suur-Rahula"],"name:fra_x_preferred":["Suur-Rahula"],"name:hye_x_preferred":["Սուուռ-Ռահուլա"],"name:nld_x_preferred":["Suur-Rahula"],"name:pol_x_preferred":["Suur-Rahula"],"name:spa_x_preferred":["Suur-Rahula"],"name:und_x_variant":["Rahula","Sur Rakhula"],"name:vol_x_preferred":["Suur-Rahula"],"src:geom":"geonames","wof:belongsto":[85682947,102191581,1713306671,85633135,1713305627],"wof:breaches":[],"wof:concordances":{"gn:id":588482,"wk:page":"Suur-Rahula"},"wof:coterminous":[1713308129],"wof:country":"EE","wof:geomhash":"2b63aaf63998fca9c781819f93802463","wof:hierarchy":[{"continent_id":102191581,"country_id":85633135,"county_id":1713305627,"localadmin_id":1713306671,"locality_id":1243041711,"region_id":85682947}],"wof:id":1243041711,"wof:lang_x_official":["est"],"wof:lang_x_spoken":["est"],"wof:lastmodified":1596674963,"wof:name":"Suur-Rahula","wof:parent_id":1713306671,"wof:placetype":"locality","wof:repo":"whosonfirst-data-admin-ee","wof:superseded_by":[],"wof:supersedes":[],"wof:tags":[]},"bbox":[23.01889,58.54139,23.01889,58.54139],"geometry":{"coordinates":[23.01889,58.54139],"type":"Point"}}