{"id":1125935941,"type":"Feature","properties":{"edtf:cessation":"uuuu","edtf:inception":"uuuu","geom:area":0,"geom:area_square_m":0,"geom:bbox":"26.60389,57.77889,26.60389,57.77889","geom:latitude":57.77889,"geom:longitude":26.60389,"gn:country":"EE","gn:fcode":"PPL","gn:population":108,"iso:country":"EE","lbl:bbox":"26.58389,57.75889,26.62389,57.79889","lbl:latitude":57.77889,"lbl:longitude":26.60389,"lbl:max_zoom":18,"lbl:min_zoom":13,"mz:hierarchy_label":1,"mz:is_current":1,"mz:min_zoom":11,"mz:note":"Quattroshapes Point Gazetteer import 20170519","name:bul_x_preferred":["Рими"],"name:ceb_x_preferred":["Rimmi"],"name:eng_x_preferred":["Rimmi"],"name:est_x_preferred":["Rimmi"],"name:hye_x_preferred":["Ռիմմի"],"name:nld_x_preferred":["Rimmi"],"name:pol_x_preferred":["Rimmi"],"name:sco_x_preferred":["Rimmi"],"name:spa_x_preferred":["Rimmi"],"name:swe_x_preferred":["Rimmi"],"name:ukr_x_preferred":["Ріммі"],"name:vol_x_preferred":["Rimmi"],"qs_pg:aaroncc":"EE","qs_pg:gn_country":"EE","qs_pg:gn_fcode":"PPL","qs_pg:gn_id":794394,"qs_pg:gn_pop":108,"qs_pg:name":"Rimmi","qs_pg:name_adm0":"Eesti","qs_pg:name_adm1":"Võrumaa","qs_pg:photos_9r":0,"qs_pg:photos_sr":0,"qs_pg:pop_sr":1,"qs_pg:qs_id":1274445,"qs_pg:qs_pg_placetype":"locality","qs_pg:qs_pg_placetype_gp":"Town","qs_pg:woe_adm0":23424805,"qs_pg:woe_id":845174,"src:geom":"qs_pg","src:lbl_centroid":"qs_pg","src:population":"geonames","woe:adm0_id":23424805,"woe:name_adm0":"Eesti","woe:name_adm1":"Võrumaa","woe:placetype":"Town","wof:belongsto":[85682937,102191581,1713316229,85633135,1713305795],"wof:breaches":[],"wof:concordances":{"gn:id":794394,"gp:id":845174,"qs_pg:id":1274445,"wd:id":"Q3455665"},"wof:coterminous":[1713316229],"wof:country":"EE","wof:created":1497296968,"wof:geomhash":"f597ea0146989838ef2c79b73815f7fe","wof:hierarchy":[{"continent_id":102191581,"country_id":85633135,"county_id":1713305795,"localadmin_id":1713316229,"locality_id":1125935941,"region_id":85682937}],"wof:id":1125935941,"wof:lang_x_official":["est"],"wof:lang_x_spoken":["est"],"wof:lastmodified":1596677026,"wof:name":"Rimmi","wof:parent_id":1713316229,"wof:placetype":"locality","wof:population":108,"wof:population_rank":1,"wof:repo":"whosonfirst-data-admin-ee","wof:superseded_by":[],"wof:supersedes":[],"wof:tags":[]},"bbox":[26.60389,57.77889,26.60389,57.77889],"geometry":{"coordinates":[26.60389,57.77889],"type":"Point"}}