{"id":1276505637,"type":"Feature","properties":{"edtf:cessation":"uuuu","edtf:inception":"uuuu","geom:area":0,"geom:area_square_m":0,"geom:bbox":"26.65694,57.87917,26.65694,57.87917","geom:latitude":57.87917,"geom:longitude":26.65694,"gn:admin1_code":"21.0","gn:admin2_code":"917.0","gn:admin3_code":"1764.0","gn:asciiname":"Maeepodra","gn:country_code":"EE","gn:dem":136,"gn:feature_class":"P","gn:feature_code":"PPL","gn:geonameid":8619372,"gn:latitude":57.87917,"gn:longitude":26.65694,"gn:modification_date":"2017-11-25","gn:name":"Mäepõdra","gn:population":0,"gn:timezone":"Europe/Tallinn","iso:country":"EE","lbl:bbox":"26.63694,57.85917,26.67694,57.89917","lbl:max_zoom":18,"lbl:min_zoom":13.5,"mz:hierarchy_label":1,"mz:is_current":1,"mz:min_zoom":12,"src:geom":"geonames","wof:belongsto":[85682937,102191581,1713316101,85633135,1713305633],"wof:breaches":[],"wof:concordances":{"gn:id":8619372},"wof:country":"EE","wof:geomhash":"13fb5125242141c32a65c61f2e50114f","wof:hierarchy":[{"continent_id":102191581,"country_id":85633135,"county_id":1713305633,"localadmin_id":1713316101,"locality_id":1276505637,"region_id":85682937}],"wof:id":1276505637,"wof:lang_x_official":["est"],"wof:lang_x_spoken":["est"],"wof:lastmodified":1596660389,"wof:name":"Maeepodra","wof:parent_id":1713316101,"wof:placetype":"locality","wof:repo":"whosonfirst-data-admin-ee","wof:superseded_by":[],"wof:supersedes":[],"wof:tags":[]},"bbox":[26.65694,57.87917,26.65694,57.87917],"geometry":{"coordinates":[26.65694,57.87917],"type":"Point"}}