{"id":1293364129,"type":"Feature","properties":{"edtf:cessation":"uuuu","edtf:inception":"uuuu","geom:area":0,"geom:area_square_m":0,"geom:bbox":"23.02944,58.44111,23.02944,58.44111","geom:latitude":58.44111,"geom:longitude":23.02944,"gn:admin1_code":"14.0","gn:admin2_code":"714.0","gn:admin3_code":"5849.0","gn:asciiname":"Pahavalla","gn:cc2":"EE","gn:country_code":"EE","gn:dem":9,"gn:feature_class":"P","gn:feature_code":"PPL","gn:geonameid":589719,"gn:latitude":58.44111,"gn:longitude":23.02944,"gn:modification_date":"2017-11-25","gn:name":"Pahavalla","gn:population":0,"gn:timezone":"Europe/Tallinn","iso:country":"EE","lbl:bbox":"23.00944,58.42111,23.04944,58.46111","lbl:max_zoom":18,"lbl:min_zoom":13.5,"mz:hierarchy_label":1,"mz:is_current":1,"mz:min_zoom":12,"name:deu_x_preferred":["Pahavalla"],"name:est_x_preferred":["Pahavalla"],"name:hye_x_preferred":["Պահավալլա"],"name:pol_x_preferred":["Pahavalla"],"name:spa_x_preferred":["Pahavalla"],"name:und_x_variant":["Pakhavalla"],"name:vol_x_preferred":["Pahavalla"],"src:geom":"geonames","wof:belongsto":[85682947,102191581,1713306975,85633135,1713305627],"wof:breaches":[],"wof:concordances":{"gn:id":589719,"wk:page":"Pahavalla"},"wof:coterminous":[1713306975],"wof:country":"EE","wof:geomhash":"593acc4a3f641229b6f07bf35da632d1","wof:hierarchy":[{"continent_id":102191581,"country_id":85633135,"county_id":1713305627,"localadmin_id":1713306975,"locality_id":1293364129,"region_id":85682947}],"wof:id":1293364129,"wof:lang_x_official":["est"],"wof:lang_x_spoken":["est"],"wof:lastmodified":1596674917,"wof:name":"Pahavalla","wof:parent_id":1713306975,"wof:placetype":"locality","wof:repo":"whosonfirst-data-admin-ee","wof:superseded_by":[],"wof:supersedes":[],"wof:tags":[]},"bbox":[23.02944,58.44111,23.02944,58.44111],"geometry":{"coordinates":[23.02944,58.44111],"type":"Point"}}