{"id":1293060157,"type":"Feature","properties":{"edtf:cessation":"uuuu","edtf:inception":"uuuu","geom:area":0,"geom:area_square_m":0,"geom:bbox":"27.315,57.69583,27.315,57.69583","geom:latitude":57.69583,"geom:longitude":27.315,"gn:admin1_code":"21.0","gn:admin2_code":"917.0","gn:admin3_code":"9144.0","gn:asciiname":"Vatsa","gn:country_code":"EE","gn:dem":184,"gn:feature_class":"P","gn:feature_code":"PPL","gn:geonameid":794252,"gn:latitude":57.69583,"gn:longitude":27.315,"gn:modification_date":"2017-11-25","gn:name":"Vatsa","gn:population":0,"gn:timezone":"Europe/Tallinn","iso:country":"EE","lbl:bbox":"27.295,57.67583,27.335,57.71583","lbl:max_zoom":18,"lbl:min_zoom":13.5,"mz:hierarchy_label":1,"mz:is_current":1,"mz:min_zoom":12,"name:est_x_preferred":["Vatsa"],"name:hye_x_preferred":["Վացա"],"name:nld_x_preferred":["Vatsa"],"name:pol_x_preferred":["Vatsa"],"name:spa_x_preferred":["Vatsa"],"name:ukr_x_preferred":["Ватса"],"name:vol_x_preferred":["Vatsa"],"src:geom":"geonames","wof:belongsto":[85682937,102191581,1713316345,85633135,1713305633],"wof:breaches":[],"wof:concordances":{"gn:id":794252,"wk:page":"Vatsa%2C_Estonia"},"wof:coterminous":[1713316345],"wof:country":"EE","wof:geomhash":"bfc344c1707e29f72edca97df179d826","wof:hierarchy":[{"continent_id":102191581,"country_id":85633135,"county_id":1713305633,"localadmin_id":1713316345,"locality_id":1293060157,"region_id":85682937}],"wof:id":1293060157,"wof:lang_x_official":["est"],"wof:lang_x_spoken":["est"],"wof:lastmodified":1596660398,"wof:name":"Vatsa","wof:parent_id":1713316345,"wof:placetype":"locality","wof:repo":"whosonfirst-data-admin-ee","wof:superseded_by":[],"wof:supersedes":[],"wof:tags":[]},"bbox":[27.315,57.69583,27.315,57.69583],"geometry":{"coordinates":[27.315,57.69583],"type":"Point"}}