{"id":1125956077,"type":"Feature","properties":{"edtf:cessation":"uuuu","edtf:inception":"uuuu","geom:area":0,"geom:area_square_m":0,"geom:bbox":"27.04528,58.06667,27.04528,58.06667","geom:latitude":58.06667,"geom:longitude":27.04528,"gn:country":"EE","gn:fcode":"PPL","gn:population":616,"iso:country":"EE","lbl:bbox":"27.02528,58.04667,27.06528,58.08667","lbl:latitude":58.06667,"lbl:longitude":27.04528,"lbl:max_zoom":17,"lbl:min_zoom":12.5,"mz:hierarchy_label":1,"mz:is_current":1,"mz:min_zoom":11,"mz:note":"Quattroshapes Point Gazetteer import 20170519","name:bul_x_preferred":["Мамасте"],"name:ceb_x_preferred":["Mammaste"],"name:eng_x_preferred":["Mammaste"],"name:est_x_preferred":["Mammaste"],"name:hye_x_preferred":["Մամաստե"],"name:jpn_x_preferred":["マンマステ"],"name:nld_x_preferred":["Mammaste"],"name:spa_x_preferred":["Mammaste"],"name:swe_x_preferred":["Mammaste"],"name:ukr_x_preferred":["Маммасте"],"name:vol_x_preferred":["Mammaste"],"name:vro_x_preferred":["Mamastõ"],"qs_pg:aaroncc":"EE","qs_pg:gn_country":"EE","qs_pg:gn_fcode":"PPL","qs_pg:gn_id":590354,"qs_pg:gn_pop":616,"qs_pg:name":"Mammaste","qs_pg:name_adm0":"Eesti","qs_pg:name_adm1":"Põlvamaa","qs_pg:photos_9r":0,"qs_pg:photos_sr":0,"qs_pg:pop_sr":2,"qs_pg:qs_id":405994,"qs_pg:qs_pg_placetype":"locality","qs_pg:qs_pg_placetype_gp":"Town","qs_pg:woe_adm0":23424805,"qs_pg:woe_id":843919,"src:geom":"qs_pg","src:lbl_centroid":"qs_pg","src:population":"geonames","woe:adm0_id":23424805,"woe:name_adm0":"Eesti","woe:name_adm1":"Põlvamaa","woe:placetype":"Town","wof:belongsto":[85682955,102191581,1713311023,85633135,1713305791],"wof:breaches":[],"wof:concordances":{"gn:id":590354,"gp:id":843919,"qs_pg:id":405994,"wd:id":"Q3457369"},"wof:coterminous":[1713311023],"wof:country":"EE","wof:created":1497297623,"wof:geomhash":"fed52fe259eac9efa3f1f848a216ffa0","wof:hierarchy":[{"continent_id":102191581,"country_id":85633135,"county_id":1713305791,"localadmin_id":1713311023,"locality_id":1125956077,"region_id":85682955}],"wof:id":1125956077,"wof:lang_x_official":["est"],"wof:lang_x_spoken":["est"],"wof:lastmodified":1596676968,"wof:name":"Mammaste","wof:parent_id":1713311023,"wof:placetype":"locality","wof:population":616,"wof:population_rank":2,"wof:repo":"whosonfirst-data-admin-ee","wof:superseded_by":[],"wof:supersedes":[],"wof:tags":[]},"bbox":[27.04528,58.06667,27.04528,58.06667],"geometry":{"coordinates":[27.04528,58.06667],"type":"Point"}}