{"id":1293759389,"type":"Feature","properties":{"edtf:cessation":"uuuu","edtf:inception":"uuuu","geom:area":0,"geom:area_square_m":0,"geom:bbox":"27.23333,58.27639,27.23333,58.27639","geom:latitude":58.27639,"geom:longitude":27.23333,"gn:admin1_code":"18.0","gn:admin2_code":"291.0","gn:admin3_code":"3772.0","gn:asciiname":"Liispollu","gn:cc2":"EE","gn:country_code":"EE","gn:dem":38,"gn:feature_class":"P","gn:feature_code":"PPL","gn:geonameid":590646,"gn:latitude":58.27639,"gn:longitude":27.23333,"gn:modification_date":"2017-11-25","gn:name":"Liispõllu","gn:population":0,"gn:timezone":"Europe/Tallinn","iso:country":"EE","lbl:bbox":"27.21333,58.25639,27.25333,58.29639","lbl:max_zoom":18,"lbl:min_zoom":13.5,"mz:hierarchy_label":1,"mz:is_current":1,"mz:min_zoom":12,"name:est_x_preferred":["Liispõllu"],"name:fra_x_preferred":["Liispõllu"],"name:hye_x_preferred":["Լիիսպիլլու"],"name:pol_x_preferred":["Liispõllu"],"name:spa_x_preferred":["Liispõllu"],"name:ukr_x_preferred":["Лійспиллу"],"name:und_x_variant":["Liispyllu","Lispyllu"],"name:vol_x_preferred":["Liispõllu"],"src:geom":"geonames","wof:belongsto":[85682995,102191581,1713313343,85633135,1713305699],"wof:breaches":[],"wof:concordances":{"gn:id":590646,"wk:page":"Liisp%C3%B5llu"},"wof:coterminous":[1713313517],"wof:country":"EE","wof:geomhash":"39a85d4e83f336b935e0fbcdc3036f39","wof:hierarchy":[{"continent_id":102191581,"country_id":85633135,"county_id":1713305699,"localadmin_id":1713313343,"locality_id":1293759389,"region_id":85682995}],"wof:id":1293759389,"wof:lang_x_official":["est"],"wof:lang_x_spoken":["est"],"wof:lastmodified":1596660666,"wof:name":"Liispollu","wof:parent_id":1713313343,"wof:placetype":"locality","wof:repo":"whosonfirst-data-admin-ee","wof:superseded_by":[],"wof:supersedes":[],"wof:tags":[]},"bbox":[27.23333,58.27639,27.23333,58.27639],"geometry":{"coordinates":[27.23333,58.27639],"type":"Point"}}