{"id":1243155685,"type":"Feature","properties":{"edtf:cessation":"uuuu","edtf:inception":"uuuu","geom:area":0,"geom:area_square_m":0,"geom:bbox":"22.08556,58.18556,22.08556,58.18556","geom:latitude":58.18556,"geom:longitude":22.08556,"gn:admin1_code":"14.0","gn:admin2_code":"714.0","gn:admin3_code":"4057.0","gn:asciiname":"Lahetaguse","gn:cc2":"EE","gn:country_code":"EE","gn:dem":7,"gn:feature_class":"P","gn:feature_code":"PPL","gn:geonameid":590824,"gn:latitude":58.18556,"gn:longitude":22.08556,"gn:modification_date":"2017-11-25","gn:name":"Lahetaguse","gn:population":0,"gn:timezone":"Europe/Tallinn","iso:country":"EE","lbl:bbox":"22.06556,58.16556,22.10556,58.20556","lbl:max_zoom":18,"lbl:min_zoom":13.5,"mz:hierarchy_label":1,"mz:is_current":1,"mz:min_zoom":12,"name:deu_x_preferred":["Lahetaguse"],"name:est_x_preferred":["Lahetaguse"],"name:fra_x_preferred":["Lahetaguse"],"name:hye_x_preferred":["Լահետագուսե"],"name:nld_x_preferred":["Lahetaguse"],"name:pol_x_preferred":["Lahetaguse"],"name:spa_x_preferred":["Lahetaguse"],"name:ukr_x_preferred":["Лахетагусе"],"name:und_x_variant":["Myza Lakhetaguze","Lakhetaguze"],"name:urd_x_preferred":["لاہیٹاگوسی"],"name:vol_x_preferred":["Lahetaguse"],"src:geom":"geonames","wof:belongsto":[85682947,102191581,1713307333,85633135,1713305627],"wof:breaches":[],"wof:concordances":{"gn:id":590824,"wk:page":"Lahetaguse"},"wof:coterminous":[1713307333],"wof:country":"EE","wof:geomhash":"e7a025e903f091945b11b2da6c29c247","wof:hierarchy":[{"continent_id":102191581,"country_id":85633135,"county_id":1713305627,"localadmin_id":1713307333,"locality_id":1243155685,"region_id":85682947}],"wof:id":1243155685,"wof:lang_x_official":["est"],"wof:lang_x_spoken":["est"],"wof:lastmodified":1596674957,"wof:name":"Lahetaguse","wof:parent_id":1713307333,"wof:placetype":"locality","wof:repo":"whosonfirst-data-admin-ee","wof:superseded_by":[],"wof:supersedes":[],"wof:tags":[]},"bbox":[22.08556,58.18556,22.08556,58.18556],"geometry":{"coordinates":[22.08556,58.18556],"type":"Point"}}