{"id":1277162959,"type":"Feature","properties":{"edtf:cessation":"uuuu","edtf:inception":"uuuu","geom:area":0,"geom:area_square_m":0,"geom:bbox":"26.50306,59.24917,26.50306,59.24917","geom:latitude":59.24917,"geom:longitude":26.50306,"gn:admin1_code":"8.0","gn:admin2_code":"901.0","gn:admin3_code":"9467.0","gn:asciiname":"Variku","gn:country_code":"EE","gn:dem":103,"gn:feature_class":"P","gn:feature_code":"PPL","gn:geonameid":8619584,"gn:latitude":59.24917,"gn:longitude":26.50306,"gn:modification_date":"2017-11-25","gn:name":"Variku","gn:population":0,"gn:timezone":"Europe/Tallinn","iso:country":"EE","lbl:bbox":"26.48306,59.22917,26.52306,59.26917","lbl:max_zoom":18,"lbl:min_zoom":13.5,"mz:hierarchy_label":1,"mz:is_current":1,"mz:min_zoom":12,"name:deu_x_preferred":["Variku"],"name:est_x_preferred":["Variku"],"name:fas_x_preferred":["وریکو"],"name:hye_x_preferred":["Վառիկու"],"name:nld_x_preferred":["Variku"],"name:pol_x_preferred":["Variku"],"name:spa_x_preferred":["Variku"],"name:ukr_x_preferred":["Варіку"],"name:und_x_variant":["Varika"],"name:vol_x_preferred":["Variku"],"src:geom":"geonames","wof:belongsto":[85683049,102191581,1713307711,85633135,1713305771],"wof:breaches":[],"wof:concordances":{"gn:id":8619584},"wof:country":"EE","wof:geomhash":"72b761770c04eb2e9be5e36397d61060","wof:hierarchy":[{"continent_id":102191581,"country_id":85633135,"county_id":1713305771,"localadmin_id":1713307711,"locality_id":1277162959,"region_id":85683049}],"wof:id":1277162959,"wof:lang_x_official":["est"],"wof:lang_x_spoken":["est"],"wof:lastmodified":1596677966,"wof:name":"Variku","wof:parent_id":1713307711,"wof:placetype":"locality","wof:repo":"whosonfirst-data-admin-ee","wof:superseded_by":[],"wof:supersedes":[],"wof:tags":[]},"bbox":[26.50306,59.24917,26.50306,59.24917],"geometry":{"coordinates":[26.50306,59.24917],"type":"Point"}}