{"id":1209699295,"type":"Feature","properties":{"edtf:cessation":"uuuu","edtf:inception":"uuuu","geom:area":0,"geom:area_square_m":0,"geom:bbox":"22.30861,58.29389,22.30861,58.29389","geom:latitude":58.29389,"geom:longitude":22.30861,"gn:admin1_code":"14.0","gn:admin2_code":"714.0","gn:admin3_code":"5836.0","gn:asciiname":"Paevere","gn:country_code":"EE","gn:dem":7,"gn:feature_class":"P","gn:feature_code":"PPL","gn:geonameid":589726,"gn:latitude":58.29389,"gn:longitude":22.30861,"gn:modification_date":"2017-11-25","gn:name":"Paevere","gn:population":0,"gn:timezone":"Europe/Tallinn","iso:country":"EE","lbl:bbox":"22.28861,58.27389,22.32861,58.31389","lbl:max_zoom":18,"lbl:min_zoom":13.5,"mz:hierarchy_label":1,"mz:is_current":1,"mz:min_zoom":12,"name:deu_x_preferred":["Paevere"],"name:est_x_preferred":["Paevere"],"name:fra_x_preferred":["Paevere"],"name:hye_x_preferred":["Պաևեռե"],"name:nld_x_preferred":["Paevere"],"name:pol_x_preferred":["Paevere"],"name:spa_x_preferred":["Paevere"],"name:ukr_x_preferred":["Паевере"],"name:vol_x_preferred":["Paevere"],"src:geom":"geonames","wof:belongsto":[85682947,102191581,1713306973,85633135,1713305627],"wof:breaches":[],"wof:concordances":{"gn:id":589726,"wk:page":"Paevere"},"wof:coterminous":[1713306973],"wof:country":"EE","wof:geomhash":"5205588bc8afdb0b9da4cb26667ae5a3","wof:hierarchy":[{"continent_id":102191581,"country_id":85633135,"county_id":1713305627,"localadmin_id":1713306973,"locality_id":1209699295,"region_id":85682947}],"wof:id":1209699295,"wof:lang_x_official":["est"],"wof:lang_x_spoken":["est"],"wof:lastmodified":1596674953,"wof:name":"Paevere","wof:parent_id":1713306973,"wof:placetype":"locality","wof:repo":"whosonfirst-data-admin-ee","wof:superseded_by":[],"wof:supersedes":[],"wof:tags":[]},"bbox":[22.30861,58.29389,22.30861,58.29389],"geometry":{"coordinates":[22.30861,58.29389],"type":"Point"}}