{"id":1125870223,"type":"Feature","properties":{"edtf:cessation":"uuuu","edtf:inception":"uuuu","geom:area":0,"geom:area_square_m":0,"geom:bbox":"26.65056,58.38556,26.65056,58.38556","geom:latitude":58.38556,"geom:longitude":26.65056,"gn:country":"EE","gn:fcode":"PPL","gn:population":135,"iso:country":"EE","lbl:bbox":"26.63056,58.36556,26.67056,58.40556","lbl:latitude":58.38556,"lbl:longitude":26.65056,"lbl:max_zoom":18,"lbl:min_zoom":13,"mz:hierarchy_label":1,"mz:is_current":1,"mz:min_zoom":11,"mz:note":"Quattroshapes Point Gazetteer import 20170519","name:ceb_x_preferred":["Kandiküla"],"name:eng_x_preferred":["Kandiküla"],"name:est_x_preferred":["Kandiküla"],"name:fra_x_preferred":["Kandiküla"],"name:hye_x_preferred":["Կանդիկյուլա"],"name:nld_x_preferred":["Kandiküla"],"name:pol_x_preferred":["Kandiküla"],"name:swe_x_preferred":["Kandiküla"],"name:ukr_x_preferred":["Кандікюла"],"name:vol_x_preferred":["Kandiküla"],"qs_pg:aaroncc":"EE","qs_pg:gn_country":"EE","qs_pg:gn_fcode":"PPL","qs_pg:gn_id":794042,"qs_pg:gn_pop":135,"qs_pg:name":"Kandiküla","qs_pg:name_adm0":"Eesti","qs_pg:name_adm1":"Tartumaa","qs_pg:photos_9k":1,"qs_pg:photos_9r":1,"qs_pg:photos_all":2,"qs_pg:photos_sr":0,"qs_pg:pop_sr":1,"qs_pg:qs_id":179653,"qs_pg:qs_pg_placetype":"locality","qs_pg:qs_pg_placetype_gp":"Town","qs_pg:woe_adm0":23424805,"qs_pg:woe_id":842683,"src:geom":"qs_pg","src:lbl_centroid":"qs_pg","src:population":"geonames","woe:adm0_id":23424805,"woe:name_adm0":"Eesti","woe:name_adm1":"Tartumaa","woe:placetype":"Town","wof:belongsto":[85682995,102191581,1713313871,85633135,1713305675],"wof:breaches":[],"wof:concordances":{"gn:id":794042,"gp:id":842683,"qs_pg:id":179653,"wd:id":"Q3459470"},"wof:coterminous":[1713313871],"wof:country":"EE","wof:created":1497294254,"wof:geomhash":"41de05da0af92c122a6506343f3182f3","wof:hierarchy":[{"continent_id":102191581,"country_id":85633135,"county_id":1713305675,"localadmin_id":1713313871,"locality_id":1125870223,"region_id":85682995}],"wof:id":1125870223,"wof:lang_x_official":["est"],"wof:lang_x_spoken":["est"],"wof:lastmodified":1596661174,"wof:name":"Kandiküla","wof:parent_id":1713313871,"wof:placetype":"locality","wof:population":135,"wof:population_rank":1,"wof:repo":"whosonfirst-data-admin-ee","wof:superseded_by":[],"wof:supersedes":[],"wof:tags":[]},"bbox":[26.65056,58.38556,26.65056,58.38556],"geometry":{"coordinates":[26.65056,58.38556],"type":"Point"}}