{"id":1326915887,"type":"Feature","properties":{"edtf:cessation":"uuuu","edtf:inception":"uuuu","geom:area":0,"geom:area_square_m":0,"geom:bbox":"26.29056,59.42722,26.29056,59.42722","geom:latitude":59.42722,"geom:longitude":26.29056,"gn:admin1_code":"8.0","gn:admin2_code":"191.0","gn:admin3_code":"1986.0","gn:asciiname":"Haljala-Raja","gn:country_code":"EE","gn:dem":76,"gn:feature_class":"P","gn:feature_code":"PPL","gn:geonameid":8619692,"gn:latitude":59.42722,"gn:longitude":26.29056,"gn:modification_date":"2018-07-05","gn:name":"Haljala-Raja","gn:population":0,"gn:timezone":"Europe/Tallinn","iso:country":"EE","lbl:bbox":"26.27056,59.40722,26.31056,59.44722","lbl:max_zoom":18,"lbl:min_zoom":13.5,"mz:hierarchy_label":1,"mz:is_current":1,"mz:min_zoom":12,"src:geom":"geonames","wof:belongsto":[85683049,102191581,1713308591,85633135,1713305775],"wof:breaches":[],"wof:concordances":{"gn:id":8619692},"wof:country":"EE","wof:geomhash":"9593d0b6e9cf311bf9b66610a0db6d80","wof:hierarchy":[{"continent_id":102191581,"country_id":85633135,"county_id":1713305775,"localadmin_id":1713308591,"locality_id":1326915887,"region_id":85683049}],"wof:id":1326915887,"wof:lang_x_official":["est"],"wof:lang_x_spoken":["est"],"wof:lastmodified":1596678048,"wof:name":"Haljala-Raja","wof:parent_id":1713308591,"wof:placetype":"locality","wof:repo":"whosonfirst-data-admin-ee","wof:superseded_by":[],"wof:supersedes":[],"wof:tags":[]},"bbox":[26.29056,59.42722,26.29056,59.42722],"geometry":{"coordinates":[26.29056,59.42722],"type":"Point"}}