{"id":1292966909,"type":"Feature","properties":{"edtf:cessation":"uuuu","edtf:inception":"uuuu","geom:area":0,"geom:area_square_m":0,"geom:bbox":"26.59861,58.22139,26.59861,58.22139","geom:latitude":58.22139,"geom:longitude":26.59861,"gn:admin1_code":"18.0","gn:admin2_code":"283.0","gn:admin3_code":"9419.0","gn:asciiname":"Visnapuu","gn:country_code":"EE","gn:dem":129,"gn:feature_class":"P","gn:feature_code":"PPL","gn:geonameid":794055,"gn:latitude":58.22139,"gn:longitude":26.59861,"gn:modification_date":"2017-11-25","gn:name":"Visnapuu","gn:population":0,"gn:timezone":"Europe/Tallinn","iso:country":"EE","lbl:bbox":"26.57861,58.20139,26.61861,58.24139","lbl:max_zoom":18,"lbl:min_zoom":13.5,"mz:hierarchy_label":1,"mz:is_current":1,"mz:min_zoom":12,"name:est_x_preferred":["Visnapuu"],"name:fra_x_preferred":["Visnapuu"],"name:hye_x_preferred":["Վիսնապուու"],"name:pol_x_preferred":["Visnapuu"],"name:spa_x_preferred":["Visnapuu"],"name:ukr_x_preferred":["Віснапуу"],"name:vol_x_preferred":["Visnapuu"],"src:geom":"geonames","wof:belongsto":[85682995,102191581,1713314221,85633135,1713305717],"wof:breaches":[],"wof:concordances":{"gn:id":794055,"wk:page":"Visnapuu"},"wof:coterminous":[1713314221],"wof:country":"EE","wof:geomhash":"ed3e0aebbaf3b04990301bcf41aa10dd","wof:hierarchy":[{"continent_id":102191581,"country_id":85633135,"county_id":1713305717,"localadmin_id":1713314221,"locality_id":1292966909,"region_id":85682995}],"wof:id":1292966909,"wof:lang_x_official":["est"],"wof:lang_x_spoken":["est"],"wof:lastmodified":1596676690,"wof:name":"Visnapuu","wof:parent_id":1713314221,"wof:placetype":"locality","wof:repo":"whosonfirst-data-admin-ee","wof:superseded_by":[],"wof:supersedes":[],"wof:tags":[]},"bbox":[26.59861,58.22139,26.59861,58.22139],"geometry":{"coordinates":[26.59861,58.22139],"type":"Point"}}