{"id":1226425971,"type":"Feature","properties":{"edtf:cessation":"uuuu","edtf:inception":"uuuu","geom:area":0,"geom:area_square_m":0,"geom:bbox":"22.5025,58.25806,22.5025,58.25806","geom:latitude":58.25806,"geom:longitude":22.5025,"gn:admin1_code":"14.0","gn:admin2_code":"714.0","gn:admin3_code":"3655.0","gn:asciiname":"Ida-Niidu","gn:country_code":"EE","gn:dem":9,"gn:feature_class":"P","gn:feature_code":"PPL","gn:geonameid":8620644,"gn:latitude":58.25806,"gn:longitude":22.5025,"gn:modification_date":"2017-11-25","gn:name":"Ida-Niidu","gn:population":0,"gn:timezone":"Europe/Tallinn","iso:country":"EE","lbl:bbox":"22.4825,58.23806,22.5225,58.27806","lbl:max_zoom":18,"lbl:min_zoom":13.5,"mz:hierarchy_label":1,"mz:is_current":1,"mz:is_funky":1,"mz:min_zoom":12,"src:geom":"geonames","wof:belongsto":[85682947,102191581,1713307339,85633135,1713305627],"wof:breaches":[],"wof:concordances":{"gn:id":8620644},"wof:country":"EE","wof:geomhash":"27f034f3362c2bc187b8efea50512645","wof:hierarchy":[{"continent_id":102191581,"country_id":85633135,"county_id":1713305627,"localadmin_id":1713307339,"locality_id":1226425971,"region_id":85682947}],"wof:id":1226425971,"wof:lang_x_official":["est"],"wof:lang_x_spoken":["est"],"wof:lastmodified":1596674945,"wof:name":"Ida-Niidu","wof:parent_id":1713307339,"wof:placetype":"locality","wof:repo":"whosonfirst-data-admin-ee","wof:superseded_by":[],"wof:supersedes":[],"wof:tags":[]},"bbox":[22.5025,58.25806,22.5025,58.25806],"geometry":{"coordinates":[22.5025,58.25806],"type":"Point"}}