{"id":1226829101,"type":"Feature","properties":{"edtf:cessation":"uuuu","edtf:inception":"uuuu","geom:area":0,"geom:area_square_m":0,"geom:bbox":"27.38139,58.00583,27.38139,58.00583","geom:latitude":58.00583,"geom:longitude":27.38139,"gn:admin1_code":"12.0","gn:admin2_code":"708.0","gn:admin3_code":"3589.0","gn:asciiname":"Kullamaee","gn:country_code":"EE","gn:dem":49,"gn:feature_class":"P","gn:feature_code":"PPL","gn:geonameid":8620574,"gn:latitude":58.00583,"gn:longitude":27.38139,"gn:modification_date":"2017-11-25","gn:name":"Kullamäe","gn:population":0,"gn:timezone":"Europe/Tallinn","iso:country":"EE","lbl:bbox":"27.36139,57.98583,27.40139,58.02583","lbl:max_zoom":18,"lbl:min_zoom":13.5,"mz:hierarchy_label":1,"mz:is_current":1,"mz:min_zoom":12,"name:und_x_variant":["Kullamäe","Куламяги"],"src:geom":"geonames","wof:belongsto":[85682955,102191581,1713311045,85633135,1713305793],"wof:breaches":[],"wof:concordances":{"gn:id":8620574},"wof:coterminous":[1713311045],"wof:country":"EE","wof:geomhash":"af7cb678df5e2ade14619663cd662a3b","wof:hierarchy":[{"continent_id":102191581,"country_id":85633135,"county_id":1713305793,"localadmin_id":1713311045,"locality_id":1226829101,"region_id":85682955}],"wof:id":1226829101,"wof:lang_x_official":["est"],"wof:lang_x_spoken":["est"],"wof:lastmodified":1596677004,"wof:name":"Kullamaee","wof:parent_id":1713311045,"wof:placetype":"locality","wof:repo":"whosonfirst-data-admin-ee","wof:superseded_by":[],"wof:supersedes":[],"wof:tags":[]},"bbox":[27.38139,58.00583,27.38139,58.00583],"geometry":{"coordinates":[27.38139,58.00583],"type":"Point"}}