{"id":1343852607,"type":"Feature","properties":{"edtf:cessation":"uuuu","edtf:inception":"uuuu","geom:area":0,"geom:area_square_m":0,"geom:bbox":"23.19391,58.99144,23.19391,58.99144","geom:latitude":58.99144,"geom:longitude":23.19391,"gn:admin1_code":"7.0","gn:admin2_code":"907.0","gn:admin3_code":"7845.0","gn:asciiname":"Suuremoisa","gn:country_code":"EE","gn:dem":14,"gn:feature_class":"P","gn:feature_code":"PPL","gn:geonameid":588524,"gn:latitude":58.99144,"gn:longitude":23.19391,"gn:modification_date":"2018-06-22","gn:name":"Suuremõisa","gn:population":0,"gn:timezone":"Europe/Tallinn","iso:country":"EE","lbl:bbox":"23.17391,58.97144,23.21391,59.01144","lbl:max_zoom":18,"lbl:min_zoom":13.5,"mz:hierarchy_label":1,"mz:is_current":1,"mz:min_zoom":12,"name:deu_x_preferred":["Suuremõisa"],"name:est_x_preferred":["Suuremõisa"],"name:hye_x_preferred":["Սուուռեմիիսա"],"name:pol_x_preferred":["Suuremõisa"],"name:spa_x_preferred":["Suuremõisa"],"name:swe_x_preferred":["Storhovet"],"name:swe_x_variant":["Magnushov"],"name:ukr_x_preferred":["Сууремийза"],"name:und_x_variant":["Suremyyza"],"name:vol_x_preferred":["Suuremõisa"],"src:geom":"geonames","wof:belongsto":[85683001,102191581,1713306763,85633135,1713305639],"wof:breaches":[],"wof:concordances":{"gn:id":588524,"wk:page":"Suurem%C3%B5isa%2C_L%C3%A4%C3%A4ne_County"},"wof:coterminous":[1713306763],"wof:country":"EE","wof:geomhash":"aabf43bedfbc0eec5e2a32728480ed46","wof:hierarchy":[{"continent_id":102191581,"country_id":85633135,"county_id":1713305639,"localadmin_id":1713306763,"locality_id":1343852607,"region_id":85683001}],"wof:id":1343852607,"wof:lang_x_official":["est"],"wof:lang_x_spoken":["est"],"wof:lastmodified":1596663600,"wof:name":"Suuremoisa","wof:parent_id":1713306763,"wof:placetype":"locality","wof:repo":"whosonfirst-data-admin-ee","wof:superseded_by":[],"wof:supersedes":[],"wof:tags":[]},"bbox":[23.19391,58.99144,23.19391,58.99144],"geometry":{"coordinates":[23.19391,58.99144],"type":"Point"}}