{"id":1326650131,"type":"Feature","properties":{"edtf:cessation":"uuuu","edtf:inception":"uuuu","geom:area":0,"geom:area_square_m":0,"geom:bbox":"26.60167,59.54056,26.60167,59.54056","geom:latitude":59.54056,"geom:longitude":26.60167,"gn:admin1_code":"8.0","gn:admin2_code":"903.0","gn:admin3_code":"4305.0","gn:asciiname":"Letipea","gn:country_code":"EE","gn:dem":21,"gn:feature_class":"P","gn:feature_code":"PPL","gn:geonameid":793451,"gn:latitude":59.54056,"gn:longitude":26.60167,"gn:modification_date":"2017-11-25","gn:name":"Letipea","gn:population":0,"gn:timezone":"Europe/Tallinn","iso:country":"EE","lbl:bbox":"26.58167,59.52056,26.62167,59.56056","lbl:max_zoom":18,"lbl:min_zoom":13.5,"mz:hierarchy_label":1,"mz:is_current":1,"mz:min_zoom":12,"name:eng_x_preferred":["Letipea"],"name:est_x_preferred":["Letipea"],"name:hye_x_preferred":["Լետիպեա"],"name:pol_x_preferred":["Letipea"],"name:rus_x_preferred":["Летипеа"],"name:vol_x_preferred":["Letipea"],"src:geom":"geonames","wof:belongsto":[85683049,102191581,1713307651,85633135,1713305777],"wof:breaches":[],"wof:concordances":{"gn:id":793451,"wk:page":"Letipea"},"wof:coterminous":[1713307651],"wof:country":"EE","wof:geomhash":"4cc1fc0fb98c86335deaab2f61448edd","wof:hierarchy":[{"continent_id":102191581,"country_id":85633135,"county_id":1713305777,"localadmin_id":1713307651,"locality_id":1326650131,"region_id":85683049}],"wof:id":1326650131,"wof:lang_x_official":["est"],"wof:lang_x_spoken":["est"],"wof:lastmodified":1596677932,"wof:name":"Letipea","wof:parent_id":1713307651,"wof:placetype":"locality","wof:repo":"whosonfirst-data-admin-ee","wof:superseded_by":[],"wof:supersedes":[],"wof:tags":[]},"bbox":[26.60167,59.54056,26.60167,59.54056],"geometry":{"coordinates":[26.60167,59.54056],"type":"Point"}}