{"id":1326605259,"type":"Feature","properties":{"edtf:cessation":"uuuu","edtf:inception":"uuuu","geom:area":0,"geom:area_square_m":0,"geom:bbox":"25.91667,58.06667,25.91667,58.06667","geom:latitude":58.06667,"geom:longitude":25.91667,"gn:admin1_code":"19.0","gn:admin2_code":"824.0","gn:admin3_code":"9025.0","gn:asciiname":"Vana Leebiku","gn:cc2":"EE","gn:country_code":"EE","gn:dem":82,"gn:feature_class":"P","gn:feature_code":"PPL","gn:geonameid":587811,"gn:latitude":58.06667,"gn:longitude":25.91667,"gn:modification_date":"2017-11-25","gn:name":"Vana Leebiku","gn:population":0,"gn:timezone":"Europe/Tallinn","iso:country":"EE","lbl:bbox":"25.89667,58.04667,25.93667,58.08667","lbl:max_zoom":18,"lbl:min_zoom":13.5,"mz:hierarchy_label":1,"mz:is_current":1,"mz:min_zoom":12,"name:und_x_variant":["Leebiku Vana Mõisad","Vana-Lebiku","Leebiku Asundus","Vanaküla","Vana Leebiku"],"src:geom":"geonames","wof:belongsto":[85682941,102191581,1713310397,85633135,1713305687],"wof:breaches":[],"wof:concordances":{"gn:id":587811},"wof:country":"EE","wof:geomhash":"39edcff87d45bbdae925bf6ee8aa9e95","wof:hierarchy":[{"continent_id":102191581,"country_id":85633135,"county_id":1713305687,"localadmin_id":1713310397,"locality_id":1326605259,"region_id":85682941}],"wof:id":1326605259,"wof:lang_x_official":["est"],"wof:lang_x_spoken":["est"],"wof:lastmodified":1596661436,"wof:name":"Vana Leebiku","wof:parent_id":1713310397,"wof:placetype":"locality","wof:repo":"whosonfirst-data-admin-ee","wof:superseded_by":[],"wof:supersedes":[],"wof:tags":[]},"bbox":[25.91667,58.06667,25.91667,58.06667],"geometry":{"coordinates":[25.91667,58.06667],"type":"Point"}}