{"id":1326807609,"type":"Feature","properties":{"edtf:cessation":"uuuu","edtf:inception":"uuuu","geom:area":0,"geom:area_square_m":0,"geom:bbox":"27.47139,58.1375,27.47139,58.1375","geom:latitude":58.1375,"geom:longitude":27.47139,"gn:admin1_code":"12.0","gn:admin2_code":"708.0","gn:admin3_code":"8313.0","gn:asciiname":"Tooste","gn:country_code":"EE","gn:dem":38,"gn:feature_class":"P","gn:feature_code":"PPL","gn:geonameid":588225,"gn:latitude":58.1375,"gn:longitude":27.47139,"gn:modification_date":"2017-11-25","gn:name":"Tooste","gn:population":0,"gn:timezone":"Europe/Tallinn","iso:country":"EE","lbl:bbox":"27.45139,58.1175,27.49139,58.1575","lbl:max_zoom":18,"lbl:min_zoom":13.5,"mz:hierarchy_label":1,"mz:is_current":1,"mz:min_zoom":12,"name:eng_x_preferred":["Tooste"],"name:est_x_preferred":["Tooste"],"name:hye_x_preferred":["Տոոստե"],"name:rus_x_preferred":["Тоосте"],"name:spa_x_preferred":["Tooste"],"name:ukr_x_preferred":["Тоосте"],"name:vol_x_preferred":["Tooste"],"src:geom":"geonames","wof:belongsto":[85682955,102191581,1713310895,85633135,1713305793],"wof:breaches":[],"wof:concordances":{"gn:id":588225,"wk:page":"Tooste"},"wof:coterminous":[1713310895],"wof:country":"EE","wof:geomhash":"afae1999f59e240260b1ebc417575e19","wof:hierarchy":[{"continent_id":102191581,"country_id":85633135,"county_id":1713305793,"localadmin_id":1713310895,"locality_id":1326807609,"region_id":85682955}],"wof:id":1326807609,"wof:lang_x_official":["est"],"wof:lang_x_spoken":["est"],"wof:lastmodified":1596676999,"wof:name":"Tooste","wof:parent_id":1713310895,"wof:placetype":"locality","wof:repo":"whosonfirst-data-admin-ee","wof:superseded_by":[],"wof:supersedes":[],"wof:tags":[]},"bbox":[27.47139,58.1375,27.47139,58.1375],"geometry":{"coordinates":[27.47139,58.1375],"type":"Point"}}