{"id":1125992603,"type":"Feature","properties":{"edtf:cessation":"uuuu","edtf:inception":"uuuu","geom:area":0,"geom:area_square_m":0,"geom:bbox":"23.21306,58.675,23.21306,58.675","geom:latitude":58.675,"geom:longitude":23.21306,"gn:country":"EE","gn:fcode":"PPL","gn:population":106,"iso:country":"EE","lbl:bbox":"23.19306,58.655,23.23306,58.695","lbl:latitude":58.675,"lbl:longitude":23.21306,"lbl:max_zoom":18,"lbl:min_zoom":13,"mz:hierarchy_label":1,"mz:is_current":1,"mz:min_zoom":11,"mz:note":"Quattroshapes Point Gazetteer import 20170519","name:ceb_x_preferred":["Nõmmküla"],"name:deu_x_preferred":["Nõmmküla"],"name:eng_x_preferred":["Nõmmküla"],"name:est_x_preferred":["Nõmmküla"],"name:hye_x_preferred":["Նիմմկյուլա"],"name:nld_x_preferred":["Nõmmküla"],"name:pol_x_preferred":["Nõmmküla"],"name:spa_x_preferred":["Nõmmküla"],"name:swe_x_preferred":["Nõmmküla"],"name:und_x_variant":["Nýmkyulya"],"name:vol_x_preferred":["Nõmmküla"],"qs_pg:aaroncc":"EE","qs_pg:gn_country":"EE","qs_pg:gn_fcode":"PPL","qs_pg:gn_id":589940,"qs_pg:gn_pop":106,"qs_pg:name":"Nõmmküla","qs_pg:name_adm0":"Eesti","qs_pg:name_adm1":"Saaremaa","qs_pg:photos_9k":1,"qs_pg:photos_9r":1,"qs_pg:photos_all":7,"qs_pg:photos_sr":0,"qs_pg:pop_sr":1,"qs_pg:qs_id":998355,"qs_pg:qs_pg_placetype":"locality","qs_pg:qs_pg_placetype_gp":"Town","qs_pg:woe_adm0":23424805,"qs_pg:woe_id":844291,"src:geom":"qs_pg","src:lbl_centroid":"qs_pg","src:population":"geonames","woe:adm0_id":23424805,"woe:name_adm0":"Eesti","woe:name_adm1":"Saaremaa","woe:placetype":"Town","wof:belongsto":[85682947,102191581,1713306153,85633135,1713305623],"wof:breaches":[],"wof:concordances":{"gn:id":589940,"gp:id":844291,"qs_pg:id":998355,"wd:id":"Q1896137"},"wof:coterminous":[1713306153],"wof:country":"EE","wof:created":1497299132,"wof:geomhash":"51044bd0b9b95657114812af0678e6fd","wof:hierarchy":[{"continent_id":102191581,"country_id":85633135,"county_id":1713305623,"localadmin_id":1713306153,"locality_id":1125992603,"region_id":85682947}],"wof:id":1125992603,"wof:lang_x_official":["est"],"wof:lang_x_spoken":["est"],"wof:lastmodified":1596675301,"wof:name":"Nõmmküla","wof:parent_id":1713306153,"wof:placetype":"locality","wof:population":106,"wof:population_rank":1,"wof:repo":"whosonfirst-data-admin-ee","wof:superseded_by":[],"wof:supersedes":[],"wof:tags":[]},"bbox":[23.21306,58.675,23.21306,58.675],"geometry":{"coordinates":[23.21306,58.675],"type":"Point"}}