{"id":1293704539,"type":"Feature","properties":{"edtf:cessation":"uuuu","edtf:inception":"uuuu","geom:area":0,"geom:area_square_m":0,"geom:bbox":"24.80222,59.34944,24.80222,59.34944","geom:latitude":59.34944,"geom:longitude":24.80222,"gn:admin1_code":"1.0","gn:admin2_code":"304.0","gn:admin3_code":"2671.0","gn:asciiname":"Saire","gn:country_code":"EE","gn:dem":56,"gn:feature_class":"P","gn:feature_code":"PPL","gn:geonameid":588843,"gn:latitude":59.34944,"gn:longitude":24.80222,"gn:modification_date":"2017-11-25","gn:name":"Saire","gn:population":0,"gn:timezone":"Europe/Tallinn","iso:country":"EE","lbl:bbox":"24.78222,59.32944,24.82222,59.36944","lbl:max_zoom":18,"lbl:min_zoom":13.5,"mz:hierarchy_label":1,"mz:is_current":1,"mz:is_funky":1,"mz:min_zoom":12,"name:und_x_variant":["Sayre","Saire"],"src:geom":"geonames","wof:belongsto":[85683055,102191581,1713313099,85633135,1713305643],"wof:breaches":[],"wof:concordances":{"gn:id":588843},"wof:country":"EE","wof:geomhash":"b76d4591cbf7d417545989e1b04669d8","wof:hierarchy":[{"continent_id":102191581,"country_id":85633135,"county_id":1713305643,"localadmin_id":1713313099,"locality_id":1293704539,"region_id":85683055}],"wof:id":1293704539,"wof:lang_x_official":["est"],"wof:lang_x_spoken":["est"],"wof:lastmodified":1596663502,"wof:name":"Saire","wof:parent_id":1713313099,"wof:placetype":"locality","wof:repo":"whosonfirst-data-admin-ee","wof:superseded_by":[],"wof:supersedes":[],"wof:tags":[]},"bbox":[24.80222,59.34944,24.80222,59.34944],"geometry":{"coordinates":[24.80222,59.34944],"type":"Point"}}