{"id":1226429621,"type":"Feature","properties":{"edtf:cessation":"uuuu","edtf:inception":"uuuu","geom:area":0,"geom:area_square_m":0,"geom:bbox":"27.67028,57.98861,27.67028,57.98861","geom:latitude":57.98861,"geom:longitude":27.67028,"gn:admin1_code":"21.0","gn:admin2_code":"732.0","gn:admin3_code":"9194.0","gn:asciiname":"Saaropaeae","gn:country_code":"EE","gn:dem":36,"gn:feature_class":"P","gn:feature_code":"PPL","gn:geonameid":8620088,"gn:latitude":57.98861,"gn:longitude":27.67028,"gn:modification_date":"2017-11-25","gn:name":"Saarõpää","gn:population":0,"gn:timezone":"Europe/Tallinn","iso:country":"EE","lbl:bbox":"27.65028,57.96861,27.69028,58.00861","lbl:max_zoom":18,"lbl:min_zoom":13.5,"mz:hierarchy_label":1,"mz:is_current":1,"mz:min_zoom":12,"name:und_x_variant":["Saarõpää","Saarepää"],"src:geom":"geonames","wof:belongsto":[85682955,102191581,1713316415,85633135,1713305631],"wof:breaches":[],"wof:concordances":{"gn:id":8620088},"wof:country":"EE","wof:geomhash":"820843b5b3d4433860e36d580b524e61","wof:hierarchy":[{"continent_id":102191581,"country_id":85633135,"county_id":1713305631,"localadmin_id":1713316415,"locality_id":1226429621,"region_id":85682955}],"wof:id":1226429621,"wof:lang_x_official":["est"],"wof:lang_x_spoken":["est"],"wof:lastmodified":1596663700,"wof:name":"Saaropaeae","wof:parent_id":1713316415,"wof:placetype":"locality","wof:repo":"whosonfirst-data-admin-ee","wof:superseded_by":[],"wof:supersedes":[],"wof:tags":[]},"bbox":[27.67028,57.98861,27.67028,57.98861],"geometry":{"coordinates":[27.67028,57.98861],"type":"Point"}}