{"id":1292981205,"type":"Feature","properties":{"edtf:cessation":"uuuu","edtf:inception":"uuuu","geom:area":0,"geom:area_square_m":0,"geom:bbox":"27.535,58.0275,27.535,58.0275","geom:latitude":58.0275,"geom:longitude":27.535,"gn:admin1_code":"21.0","gn:admin2_code":"732.0","gn:admin3_code":"8300.0","gn:asciiname":"Toomasmaee","gn:country_code":"EE","gn:dem":33,"gn:feature_class":"P","gn:feature_code":"PPL","gn:geonameid":588232,"gn:latitude":58.0275,"gn:longitude":27.535,"gn:modification_date":"2017-11-25","gn:name":"Toomasmäe","gn:population":0,"gn:timezone":"Europe/Tallinn","iso:country":"EE","lbl:bbox":"27.515,58.0075,27.555,58.0475","lbl:max_zoom":18,"lbl:min_zoom":13.5,"mz:hierarchy_label":1,"mz:is_current":1,"mz:min_zoom":12,"name:deu_x_preferred":["Toomasmäe"],"name:est_x_preferred":["Toomasmäe"],"name:fra_x_preferred":["Toomasmäe"],"name:hye_x_preferred":["Տոոմասմյաե"],"name:pol_x_preferred":["Toomasmäe"],"name:spa_x_preferred":["Toomasmäe"],"name:ukr_x_preferred":["Тоомасмяе"],"name:und_x_variant":["Tomasmyae","Toomasmyae"],"name:vol_x_preferred":["Toomasmäe"],"src:geom":"geonames","wof:belongsto":[85682955,102191581,1713316153,85633135,1713305631],"wof:breaches":[],"wof:concordances":{"gn:id":588232,"wk:page":"Toomasm%C3%A4e"},"wof:coterminous":[1713316153],"wof:country":"EE","wof:geomhash":"2b665e8f46bd9c3139b387185bca414f","wof:hierarchy":[{"continent_id":102191581,"country_id":85633135,"county_id":1713305631,"localadmin_id":1713316153,"locality_id":1292981205,"region_id":85682955}],"wof:id":1292981205,"wof:lang_x_official":["est"],"wof:lang_x_spoken":["est"],"wof:lastmodified":1596663695,"wof:name":"Toomasmaee","wof:parent_id":1713316153,"wof:placetype":"locality","wof:repo":"whosonfirst-data-admin-ee","wof:superseded_by":[],"wof:supersedes":[],"wof:tags":[]},"bbox":[27.535,58.0275,27.535,58.0275],"geometry":{"coordinates":[27.535,58.0275],"type":"Point"}}