{"id":1193006233,"type":"Feature","properties":{"edtf:cessation":"uuuu","edtf:inception":"uuuu","geom:area":0,"geom:area_square_m":0,"geom:bbox":"24.95,58.56667,24.95,58.56667","geom:latitude":58.56667,"geom:longitude":24.95,"gn:admin1_code":"11.0","gn:admin2_code":"638.0","gn:admin3_code":"3599.0","gn:asciiname":"Alt-Massu","gn:cc2":"EE","gn:country_code":"EE","gn:dem":26,"gn:feature_class":"P","gn:feature_code":"PPL","gn:geonameid":592514,"gn:latitude":58.56667,"gn:longitude":24.95,"gn:modification_date":"2017-11-25","gn:name":"Alt-Massu","gn:population":0,"gn:timezone":"Europe/Tallinn","iso:country":"EE","lbl:bbox":"24.93,58.54667,24.97,58.58667","lbl:max_zoom":18,"lbl:min_zoom":13.5,"mz:hierarchy_label":1,"mz:is_current":1,"mz:min_zoom":12,"name:und_x_variant":["Massu","Alt-Massu"],"src:geom":"geonames","wof:belongsto":[85682981,102191581,1713309195,85633135,1713305733],"wof:breaches":[],"wof:concordances":{"gn:id":592514},"wof:country":"EE","wof:geomhash":"5b52842c396ccf4c7abc95bf8a76e864","wof:hierarchy":[{"continent_id":102191581,"country_id":85633135,"county_id":1713305733,"localadmin_id":1713309195,"locality_id":1193006233,"region_id":85682981}],"wof:id":1193006233,"wof:lang_x_official":["est"],"wof:lang_x_spoken":["est"],"wof:lastmodified":1596663418,"wof:name":"Alt-Massu","wof:parent_id":1713309195,"wof:placetype":"locality","wof:repo":"whosonfirst-data-admin-ee","wof:superseded_by":[],"wof:supersedes":[],"wof:tags":[]},"bbox":[24.95,58.56667,24.95,58.56667],"geometry":{"coordinates":[24.95,58.56667],"type":"Point"}}