{"id":1242937477,"type":"Feature","properties":{"edtf:cessation":"uuuu","edtf:inception":"uuuu","geom:area":0,"geom:area_square_m":0,"geom:bbox":"26.95833,57.87694,26.95833,57.87694","geom:latitude":57.87694,"geom:longitude":26.95833,"gn:admin1_code":"21.0","gn:admin2_code":"917.0","gn:admin3_code":"5378.0","gn:asciiname":"Tsopa","gn:country_code":"EE","gn:dem":81,"gn:feature_class":"P","gn:feature_code":"PPL","gn:geonameid":8619935,"gn:latitude":57.87694,"gn:longitude":26.95833,"gn:modification_date":"2017-11-25","gn:name":"Tsopa","gn:population":0,"gn:timezone":"Europe/Tallinn","iso:country":"EE","lbl:bbox":"26.93833,57.85694,26.97833,57.89694","lbl:max_zoom":18,"lbl:min_zoom":13.5,"mz:hierarchy_label":1,"mz:is_current":1,"mz:min_zoom":12,"name:und_x_variant":["Tsopakülä","Tsopa"],"src:geom":"geonames","wof:belongsto":[85682937,102191581,1713315921,85633135,1713305633],"wof:breaches":[],"wof:concordances":{"gn:id":8619935},"wof:country":"EE","wof:geomhash":"3a94bc2b7d1065dc9adfad7266d7f8ca","wof:hierarchy":[{"continent_id":102191581,"country_id":85633135,"county_id":1713305633,"localadmin_id":1713315921,"locality_id":1242937477,"region_id":85682937}],"wof:id":1242937477,"wof:lang_x_official":["est"],"wof:lang_x_spoken":["est"],"wof:lastmodified":1596660403,"wof:name":"Tsopa","wof:parent_id":1713315921,"wof:placetype":"locality","wof:repo":"whosonfirst-data-admin-ee","wof:superseded_by":[],"wof:supersedes":[],"wof:tags":[]},"bbox":[26.95833,57.87694,26.95833,57.87694],"geometry":{"coordinates":[26.95833,57.87694],"type":"Point"}}