{"id":1259654707,"type":"Feature","properties":{"edtf:cessation":"uuuu","edtf:inception":"uuuu","geom:area":0,"geom:area_square_m":0,"geom:bbox":"22.11111,58.20667,22.11111,58.20667","geom:latitude":58.20667,"geom:longitude":22.11111,"gn:admin1_code":"14.0","gn:admin2_code":"714.0","gn:admin3_code":"8158.0","gn:asciiname":"Taritu","gn:country_code":"EE","gn:dem":13,"gn:feature_class":"P","gn:feature_code":"PPL","gn:geonameid":588339,"gn:latitude":58.20667,"gn:longitude":22.11111,"gn:modification_date":"2018-05-02","gn:name":"Taritu","gn:population":0,"gn:timezone":"Europe/Tallinn","iso:country":"EE","lbl:bbox":"22.09111,58.18667,22.13111,58.22667","lbl:max_zoom":18,"lbl:min_zoom":13.5,"mz:hierarchy_label":1,"mz:is_current":1,"mz:min_zoom":12,"name:deu_x_preferred":["Taritu"],"name:est_x_preferred":["Taritu"],"name:fra_x_preferred":["Taritu"],"name:hye_x_preferred":["Տառիտու"],"name:pol_x_preferred":["Taritu"],"name:rus_x_preferred":["Тариту"],"name:spa_x_preferred":["Taritu"],"name:ukr_x_preferred":["Таріту"],"name:vol_x_preferred":["Taritu"],"src:geom":"geonames","wof:belongsto":[85682947,102191581,1713312553,85633135,1713305627],"wof:breaches":[],"wof:concordances":{"gn:id":588339,"wk:page":"Taritu"},"wof:coterminous":[1713312553],"wof:country":"EE","wof:geomhash":"612b569dee496f7c6a1f7017d8f69a44","wof:hierarchy":[{"continent_id":102191581,"country_id":85633135,"county_id":1713305627,"localadmin_id":1713312553,"locality_id":1259654707,"region_id":85682947}],"wof:id":1259654707,"wof:lang_x_official":["est"],"wof:lang_x_spoken":["est"],"wof:lastmodified":1596674916,"wof:name":"Taritu","wof:parent_id":1713312553,"wof:placetype":"locality","wof:repo":"whosonfirst-data-admin-ee","wof:superseded_by":[],"wof:supersedes":[],"wof:tags":[]},"bbox":[22.11111,58.20667,22.11111,58.20667],"geometry":{"coordinates":[22.11111,58.20667],"type":"Point"}}