{"id":1309719531,"type":"Feature","properties":{"edtf:cessation":"uuuu","edtf:inception":"uuuu","geom:area":0,"geom:area_square_m":0,"geom:bbox":"27.59806,59.01194,27.59806,59.01194","geom:latitude":59.01194,"geom:longitude":27.59806,"gn:admin1_code":"3.0","gn:admin2_code":"130.0","gn:admin3_code":"7649.0","gn:asciiname":"Smolnitsa","gn:country_code":"EE","gn:dem":35,"gn:feature_class":"P","gn:feature_code":"PPL","gn:geonameid":588655,"gn:latitude":59.01194,"gn:longitude":27.59806,"gn:modification_date":"2017-11-25","gn:name":"Smolnitsa","gn:population":0,"gn:timezone":"Europe/Tallinn","iso:country":"EE","lbl:bbox":"27.57806,58.99194,27.61806,59.03194","lbl:max_zoom":18,"lbl:min_zoom":13.5,"mz:hierarchy_label":1,"mz:is_current":1,"mz:min_zoom":12,"name:deu_x_preferred":["Smolnitsa"],"name:est_x_preferred":["Smolnitsa"],"name:hye_x_preferred":["Սմոլնիցա"],"name:nld_x_preferred":["Smolnitsa"],"name:pol_x_preferred":["Smolnitsa"],"name:rus_x_preferred":["Смольница"],"name:spa_x_preferred":["Smolnitsa"],"name:vol_x_preferred":["Smolnitsa"],"src:geom":"geonames","wof:belongsto":[85683059,102191581,1713311731,85633135,1713305693],"wof:breaches":[],"wof:concordances":{"gn:id":588655,"wk:page":"Smolnitsa%2C_Estonia"},"wof:coterminous":[1713311731],"wof:country":"EE","wof:geomhash":"88cd9e4fa0ba9bf1a7e5e1b654054a74","wof:hierarchy":[{"continent_id":102191581,"country_id":85633135,"county_id":1713305693,"localadmin_id":1713311731,"locality_id":1309719531,"region_id":85683059}],"wof:id":1309719531,"wof:lang_x_official":["est"],"wof:lang_x_spoken":["est"],"wof:lastmodified":1596660747,"wof:name":"Smolnitsa","wof:parent_id":1713311731,"wof:placetype":"locality","wof:repo":"whosonfirst-data-admin-ee","wof:superseded_by":[],"wof:supersedes":[],"wof:tags":[]},"bbox":[27.59806,59.01194,27.59806,59.01194],"geometry":{"coordinates":[27.59806,59.01194],"type":"Point"}}