{"id":1209278839,"type":"Feature","properties":{"edtf:cessation":"uuuu","edtf:inception":"uuuu","geom:area":0,"geom:area_square_m":0,"geom:bbox":"27.34056,57.61111,27.34056,57.61111","geom:latitude":57.61111,"geom:longitude":27.34056,"gn:admin1_code":"21.0","gn:admin2_code":"732.0","gn:admin3_code":"3502.0","gn:asciiname":"Kriiva","gn:country_code":"EE","gn:dem":187,"gn:feature_class":"P","gn:feature_code":"PPL","gn:geonameid":591051,"gn:latitude":57.61111,"gn:longitude":27.34056,"gn:modification_date":"2017-11-25","gn:name":"Kriiva","gn:population":0,"gn:timezone":"Europe/Tallinn","iso:country":"EE","lbl:bbox":"27.32056,57.59111,27.36056,57.63111","lbl:max_zoom":18,"lbl:min_zoom":13.5,"mz:hierarchy_label":1,"mz:is_current":1,"mz:min_zoom":12,"name:est_x_preferred":["Kriiva"],"name:hye_x_preferred":["Կռիիվա"],"name:pol_x_preferred":["Kriiva"],"name:spa_x_preferred":["Kriiva"],"name:ukr_x_preferred":["Кріїва"],"name:vol_x_preferred":["Kriiva"],"src:geom":"geonames","wof:belongsto":[85682955,102191581,1713316177,85633135,1713305631],"wof:breaches":[],"wof:concordances":{"gn:id":591051,"wk:page":"Kriiva"},"wof:coterminous":[1713316177],"wof:country":"EE","wof:geomhash":"0d1f4f4c35e43dcc3147ed778521d66c","wof:hierarchy":[{"continent_id":102191581,"country_id":85633135,"county_id":1713305631,"localadmin_id":1713316177,"locality_id":1209278839,"region_id":85682955}],"wof:id":1209278839,"wof:lang_x_official":["est"],"wof:lang_x_spoken":["est"],"wof:lastmodified":1596663694,"wof:name":"Kriiva","wof:parent_id":1713316177,"wof:placetype":"locality","wof:repo":"whosonfirst-data-admin-ee","wof:superseded_by":[],"wof:supersedes":[],"wof:tags":[]},"bbox":[27.34056,57.61111,27.34056,57.61111],"geometry":{"coordinates":[27.34056,57.61111],"type":"Point"}}