{"id":1310009277,"type":"Feature","properties":{"edtf:cessation":"uuuu","edtf:inception":"uuuu","geom:area":0,"geom:area_square_m":0,"geom:bbox":"22.46528,58.97583,22.46528,58.97583","geom:latitude":58.97583,"geom:longitude":22.46528,"gn:admin1_code":"2.0","gn:admin2_code":"205.0","gn:admin3_code":"3795.0","gn:asciiname":"Ninametsa","gn:country_code":"EE","gn:dem":8,"gn:feature_class":"P","gn:feature_code":"PPL","gn:geonameid":8618190,"gn:latitude":58.97583,"gn:longitude":22.46528,"gn:modification_date":"2017-11-25","gn:name":"Ninametsa","gn:population":0,"gn:timezone":"Europe/Tallinn","iso:country":"EE","lbl:bbox":"22.44528,58.95583,22.48528,58.99583","lbl:max_zoom":18,"lbl:min_zoom":13.5,"mz:hierarchy_label":1,"mz:is_current":1,"mz:is_funky":1,"mz:min_zoom":12,"name:und_x_variant":["Ninarahu"],"src:geom":"geonames","wof:belongsto":[85682989,102191581,1713310369,85633135,1713305629],"wof:breaches":[],"wof:concordances":{"gn:id":8618190},"wof:country":"EE","wof:geomhash":"12152c5272409248aa6500f4077fc8af","wof:hierarchy":[{"continent_id":102191581,"country_id":85633135,"county_id":1713305629,"localadmin_id":1713310369,"locality_id":1310009277,"region_id":85682989}],"wof:id":1310009277,"wof:lang_x_official":["est"],"wof:lang_x_spoken":["est"],"wof:lastmodified":1596670016,"wof:name":"Ninametsa","wof:parent_id":1713310369,"wof:placetype":"locality","wof:repo":"whosonfirst-data-admin-ee","wof:superseded_by":[],"wof:supersedes":[],"wof:tags":[]},"bbox":[22.46528,58.97583,22.46528,58.97583],"geometry":{"coordinates":[22.46528,58.97583],"type":"Point"}}