{"id":1125882929,"type":"Feature","properties":{"edtf:cessation":"uuuu","edtf:inception":"uuuu","geom:area":0,"geom:area_square_m":0,"geom:bbox":"22.78194,58.79222,22.78194,58.79222","geom:latitude":58.79222,"geom:longitude":22.78194,"gn:country":"EE","gn:fcode":"PPL","gn:population":0,"iso:country":"EE","lbl:bbox":"22.76194,58.77222,22.80194,58.81222","lbl:latitude":58.79222,"lbl:longitude":22.78194,"lbl:max_zoom":18,"lbl:min_zoom":13.5,"mz:hierarchy_label":1,"mz:is_current":1,"mz:min_zoom":12,"mz:note":"Quattroshapes Point Gazetteer import 20170519","name:deu_x_preferred":["Orjaku"],"name:eng_x_preferred":["Orjaku"],"name:est_x_preferred":["Orjaku"],"name:hye_x_preferred":["Օռյակու"],"name:nld_x_preferred":["Orjaku"],"name:pol_x_preferred":["Orjaku"],"name:spa_x_preferred":["Orjaku"],"name:und_x_variant":["Or’yaku"],"name:vol_x_preferred":["Orjaku"],"qs_pg:aaroncc":"EE","qs_pg:gn_country":"EE","qs_pg:gn_fcode":"PPL","qs_pg:gn_id":589795,"qs_pg:gn_pop":0,"qs_pg:name":"Orjaku","qs_pg:name_adm0":"Eesti","qs_pg:name_adm1":"Hiiumaa","qs_pg:photos":108,"qs_pg:photos_1k":22,"qs_pg:photos_9k":1,"qs_pg:photos_9r":3,"qs_pg:photos_all":108,"qs_pg:photos_sr":3,"qs_pg:pop_sr":0,"qs_pg:qs_id":894611,"qs_pg:qs_pg_placetype":"locality","qs_pg:qs_pg_placetype_gp":"Town","qs_pg:woe_adm0":23424805,"qs_pg:woe_id":844426,"src:geom":"qs_pg","src:lbl_centroid":"qs_pg","woe:adm0_id":23424805,"woe:name_adm0":"Eesti","woe:name_adm1":"Hiiumaa","woe:placetype":"Town","wof:belongsto":[102191581,85633135,85682989],"wof:breaches":[],"wof:concordances":{"gn:id":589795,"gp:id":844426,"qs_pg:id":894611,"wd:id":"Q3454627"},"wof:coterminous":[1713310499],"wof:country":"EE","wof:created":1497294910,"wof:geomhash":"28db3b20c44f3e87787ada09a407c379","wof:hierarchy":[{"continent_id":102191581,"country_id":85633135,"locality_id":1125882929,"region_id":85682989}],"wof:id":1125882929,"wof:lang_x_official":["est"],"wof:lang_x_spoken":["est"],"wof:lastmodified":1596130365,"wof:name":"Orjaku","wof:parent_id":85682989,"wof:placetype":"locality","wof:repo":"whosonfirst-data-admin-ee","wof:superseded_by":[],"wof:supersedes":[],"wof:tags":[]},"bbox":[22.78194,58.79222,22.78194,58.79222],"geometry":{"coordinates":[22.78194,58.79222],"type":"Point"}}