{"id":1310390885,"type":"Feature","properties":{"edtf:cessation":"uuuu","edtf:inception":"uuuu","geom:area":0,"geom:area_square_m":0,"geom:bbox":"26.15389,59.35972,26.15389,59.35972","geom:latitude":59.35972,"geom:longitude":26.15389,"gn:admin1_code":"8.0","gn:admin2_code":"272.0","gn:admin3_code":"4106.0","gn:asciiname":"Lante","gn:country_code":"EE","gn:dem":87,"gn:feature_class":"P","gn:feature_code":"PPL","gn:geonameid":590791,"gn:latitude":59.35972,"gn:longitude":26.15389,"gn:modification_date":"2017-11-25","gn:name":"Lante","gn:population":0,"gn:timezone":"Europe/Tallinn","iso:country":"EE","lbl:bbox":"26.13389,59.33972,26.17389,59.37972","lbl:max_zoom":18,"lbl:min_zoom":13.5,"mz:hierarchy_label":1,"mz:is_current":1,"mz:min_zoom":12,"name:est_x_preferred":["Lante"],"name:hye_x_preferred":["Լանտե"],"name:pol_x_preferred":["Lante"],"name:urd_x_preferred":["لانٹی"],"name:vol_x_preferred":["Lante"],"src:geom":"geonames","wof:belongsto":[85683049,102191581,1713306099,85633135,1713305723],"wof:breaches":[],"wof:concordances":{"gn:id":590791,"wk:page":"Lante"},"wof:coterminous":[1713306099],"wof:country":"EE","wof:geomhash":"1bc8d96a106b30601b9e3c066cd37b27","wof:hierarchy":[{"continent_id":102191581,"country_id":85633135,"county_id":1713305723,"localadmin_id":1713306099,"locality_id":1310390885,"region_id":85683049}],"wof:id":1310390885,"wof:lang_x_official":["est"],"wof:lang_x_spoken":["est"],"wof:lastmodified":1596661732,"wof:name":"Lante","wof:parent_id":1713306099,"wof:placetype":"locality","wof:repo":"whosonfirst-data-admin-ee","wof:superseded_by":[],"wof:supersedes":[],"wof:tags":[]},"bbox":[26.15389,59.35972,26.15389,59.35972],"geometry":{"coordinates":[26.15389,59.35972],"type":"Point"}}