{"id":1259970459,"type":"Feature","properties":{"edtf:cessation":"uuuu","edtf:inception":"uuuu","geom:area":0,"geom:area_square_m":0,"geom:bbox":"25.89583,59.40861,25.89583,59.40861","geom:latitude":59.40861,"geom:longitude":25.89583,"gn:admin1_code":"8.0","gn:admin2_code":"272.0","gn:admin3_code":"5147.0","gn:asciiname":"Soomukse","gn:country_code":"EE","gn:dem":93,"gn:feature_class":"P","gn:feature_code":"PPL","gn:geonameid":588607,"gn:latitude":59.40861,"gn:longitude":25.89583,"gn:modification_date":"2017-11-25","gn:name":"Soomukse","gn:population":0,"gn:timezone":"Europe/Tallinn","iso:country":"EE","lbl:bbox":"25.87583,59.38861,25.91583,59.42861","lbl:max_zoom":18,"lbl:min_zoom":13.5,"mz:hierarchy_label":1,"mz:is_current":1,"mz:min_zoom":12,"name:und_x_variant":["Somukse","Soomukse"],"src:geom":"geonames","wof:belongsto":[85683049,102191581,1713314513,85633135,1713305723],"wof:breaches":[],"wof:concordances":{"gn:id":588607},"wof:country":"EE","wof:geomhash":"dcf4d16569068919fd0cef52ee45caf8","wof:hierarchy":[{"continent_id":102191581,"country_id":85633135,"county_id":1713305723,"localadmin_id":1713314513,"locality_id":1259970459,"region_id":85683049}],"wof:id":1259970459,"wof:lang_x_official":["est"],"wof:lang_x_spoken":["est"],"wof:lastmodified":1596661736,"wof:name":"Soomukse","wof:parent_id":1713314513,"wof:placetype":"locality","wof:repo":"whosonfirst-data-admin-ee","wof:superseded_by":[],"wof:supersedes":[],"wof:tags":[]},"bbox":[25.89583,59.40861,25.89583,59.40861],"geometry":{"coordinates":[25.89583,59.40861],"type":"Point"}}