{"id":1243377299,"type":"Feature","properties":{"edtf:cessation":"uuuu","edtf:inception":"uuuu","geom:area":0,"geom:area_square_m":0,"geom:bbox":"24.45722,59.24194,24.45722,59.24194","geom:latitude":59.24194,"geom:longitude":24.45722,"gn:admin1_code":"1.0","gn:admin2_code":"726.0","gn:admin3_code":"8450.0","gn:asciiname":"Paellu","gn:country_code":"EE","gn:dem":44,"gn:feature_class":"P","gn:feature_code":"PPL","gn:geonameid":589649,"gn:latitude":59.24194,"gn:longitude":24.45722,"gn:modification_date":"2017-11-25","gn:name":"Pällu","gn:population":0,"gn:timezone":"Europe/Tallinn","iso:country":"EE","lbl:bbox":"24.43722,59.22194,24.47722,59.26194","lbl:max_zoom":18,"lbl:min_zoom":13.5,"mz:hierarchy_label":1,"mz:is_current":1,"mz:min_zoom":12,"src:geom":"geonames","wof:belongsto":[85683055,102191581,1713313451,85633135,1713305739],"wof:breaches":[],"wof:concordances":{"gn:id":589649},"wof:coterminous":[1713307913],"wof:country":"EE","wof:geomhash":"d8e42ae4636ff3fa0a5282ed9beca1cb","wof:hierarchy":[{"continent_id":102191581,"country_id":85633135,"county_id":1713305739,"localadmin_id":1713313451,"locality_id":1243377299,"region_id":85683055}],"wof:id":1243377299,"wof:lang_x_official":["est"],"wof:lang_x_spoken":["est"],"wof:lastmodified":1596663249,"wof:name":"Paellu","wof:parent_id":1713313451,"wof:placetype":"locality","wof:repo":"whosonfirst-data-admin-ee","wof:superseded_by":[],"wof:supersedes":[],"wof:tags":[]},"bbox":[24.45722,59.24194,24.45722,59.24194],"geometry":{"coordinates":[24.45722,59.24194],"type":"Point"}}