{"id":1125858427,"type":"Feature","properties":{"edtf:cessation":"uuuu","edtf:inception":"uuuu","geom:area":0,"geom:area_square_m":0,"geom:bbox":"27.09528,59.40056,27.09528,59.40056","geom:latitude":59.40056,"geom:longitude":27.09528,"gn:country":"EE","gn:fcode":"PPL","gn:population":121,"iso:country":"EE","lbl:bbox":"27.07528,59.38056,27.11528,59.42056","lbl:latitude":59.40056,"lbl:longitude":27.09528,"lbl:max_zoom":18,"lbl:min_zoom":13,"mz:hierarchy_label":1,"mz:is_current":1,"mz:min_zoom":11,"mz:note":"Quattroshapes Point Gazetteer import 20170519","name:ceb_x_preferred":["Varja"],"name:deu_x_preferred":["Varja"],"name:eng_x_preferred":["Varja"],"name:est_x_preferred":["Varja"],"name:fra_x_preferred":["Varja"],"name:hye_x_preferred":["Վառյա"],"name:nld_x_preferred":["Varja"],"name:pol_x_preferred":["Varja"],"name:spa_x_preferred":["Varja"],"name:und_x_variant":["Varia"],"name:vol_x_preferred":["Varja"],"qs_pg:aaroncc":"EE","qs_pg:gn_country":"EE","qs_pg:gn_fcode":"PPL","qs_pg:gn_id":587746,"qs_pg:gn_pop":121,"qs_pg:name":"Varja","qs_pg:name_adm0":"Eesti","qs_pg:name_adm1":"Ida-Virumaa","qs_pg:photos_9r":0,"qs_pg:photos_sr":0,"qs_pg:pop_sr":1,"qs_pg:qs_id":1274738,"qs_pg:qs_pg_placetype":"locality","qs_pg:qs_pg_placetype_gp":"Town","qs_pg:woe_adm0":23424805,"qs_pg:woe_id":846331,"src:geom":"qs_pg","src:lbl_centroid":"qs_pg","src:population":"geonames","woe:adm0_id":23424805,"woe:name_adm0":"Eesti","woe:name_adm1":"Ida-Virumaa","woe:placetype":"Town","wof:belongsto":[85683059,102191581,1713311855,85633135,1713305695],"wof:breaches":[],"wof:concordances":{"gn:id":587746,"gp:id":846331,"qs_pg:id":1274738,"wd:id":"Q984313"},"wof:coterminous":[1713311855],"wof:country":"EE","wof:created":1497293721,"wof:geomhash":"020eb432f0385288f292f67afe269eb3","wof:hierarchy":[{"continent_id":102191581,"country_id":85633135,"county_id":1713305695,"localadmin_id":1713311855,"locality_id":1125858427,"region_id":85683059}],"wof:id":1125858427,"wof:lang_x_official":["est"],"wof:lang_x_spoken":["est"],"wof:lastmodified":1596660802,"wof:name":"Varja","wof:parent_id":1713311855,"wof:placetype":"locality","wof:population":121,"wof:population_rank":1,"wof:repo":"whosonfirst-data-admin-ee","wof:superseded_by":[],"wof:supersedes":[],"wof:tags":[]},"bbox":[27.09528,59.40056,27.09528,59.40056],"geometry":{"coordinates":[27.09528,59.40056],"type":"Point"}}