{"id":1209378155,"type":"Feature","properties":{"edtf:cessation":"uuuu","edtf:inception":"uuuu","geom:area":0,"geom:area_square_m":0,"geom:bbox":"26.52472,58.20083,26.52472,58.20083","geom:latitude":58.20083,"geom:longitude":26.52472,"gn:admin1_code":"18.0","gn:admin2_code":"283.0","gn:admin3_code":"5690.0","gn:asciiname":"Oomiste","gn:country_code":"EE","gn:dem":113,"gn:feature_class":"P","gn:feature_code":"PPL","gn:geonameid":794025,"gn:latitude":58.20083,"gn:longitude":26.52472,"gn:modification_date":"2017-11-25","gn:name":"Oomiste","gn:population":0,"gn:timezone":"Europe/Tallinn","iso:country":"EE","lbl:bbox":"26.50472,58.18083,26.54472,58.22083","lbl:max_zoom":18,"lbl:min_zoom":13.5,"mz:hierarchy_label":1,"mz:is_current":1,"mz:min_zoom":12,"name:est_x_preferred":["Oomiste"],"name:fra_x_preferred":["Oomiste"],"name:hye_x_preferred":["Օոմիստե"],"name:pol_x_preferred":["Oomiste"],"name:spa_x_preferred":["Oomiste"],"name:ukr_x_preferred":["Оомісте"],"name:vol_x_preferred":["Oomiste"],"src:geom":"geonames","wof:belongsto":[85682995,102191581,1713314783,85633135,1713305717],"wof:breaches":[],"wof:concordances":{"gn:id":794025,"wk:page":"Oomiste"},"wof:coterminous":[1713314783],"wof:country":"EE","wof:geomhash":"5aa62cae806cf559e6a4182cf303b4fc","wof:hierarchy":[{"continent_id":102191581,"country_id":85633135,"county_id":1713305717,"localadmin_id":1713314783,"locality_id":1209378155,"region_id":85682995}],"wof:id":1209378155,"wof:lang_x_official":["est"],"wof:lang_x_spoken":["est"],"wof:lastmodified":1596676689,"wof:name":"Oomiste","wof:parent_id":1713314783,"wof:placetype":"locality","wof:repo":"whosonfirst-data-admin-ee","wof:superseded_by":[],"wof:supersedes":[],"wof:tags":[]},"bbox":[26.52472,58.20083,26.52472,58.20083],"geometry":{"coordinates":[26.52472,58.20083],"type":"Point"}}