{"id":1293653623,"type":"Feature","properties":{"edtf:cessation":"uuuu","edtf:inception":"uuuu","geom:area":0,"geom:area_square_m":0,"geom:bbox":"27.2375,57.88222,27.2375,57.88222","geom:latitude":57.88222,"geom:longitude":27.2375,"gn:admin1_code":"21.0","gn:admin2_code":"917.0","gn:admin3_code":"6212.0","gn:asciiname":"Virve","gn:country_code":"EE","gn:dem":84,"gn:feature_class":"P","gn:feature_code":"PPL","gn:geonameid":587546,"gn:latitude":57.88222,"gn:longitude":27.2375,"gn:modification_date":"2017-11-25","gn:name":"Virve","gn:population":0,"gn:timezone":"Europe/Tallinn","iso:country":"EE","lbl:bbox":"27.2175,57.86222,27.2575,57.90222","lbl:max_zoom":18,"lbl:min_zoom":13.5,"mz:hierarchy_label":1,"mz:is_current":1,"mz:min_zoom":12,"name:fin_x_preferred":["Virve"],"src:geom":"geonames","wof:belongsto":[85682937,102191581,1713316343,85633135,1713305633],"wof:breaches":[],"wof:concordances":{"gn:id":587546},"wof:country":"EE","wof:geomhash":"443919383dfa444d3334b170888cb361","wof:hierarchy":[{"continent_id":102191581,"country_id":85633135,"county_id":1713305633,"localadmin_id":1713316343,"locality_id":1293653623,"region_id":85682937}],"wof:id":1293653623,"wof:lang_x_official":["est"],"wof:lang_x_spoken":["est"],"wof:lastmodified":1596660414,"wof:name":"Virve","wof:parent_id":1713316343,"wof:placetype":"locality","wof:repo":"whosonfirst-data-admin-ee","wof:superseded_by":[],"wof:supersedes":[],"wof:tags":[]},"bbox":[27.2375,57.88222,27.2375,57.88222],"geometry":{"coordinates":[27.2375,57.88222],"type":"Point"}}