{"id":1226008051,"type":"Feature","properties":{"edtf:cessation":"uuuu","edtf:inception":"uuuu","geom:area":0,"geom:area_square_m":0,"geom:bbox":"26.17833,58.18444,26.17833,58.18444","geom:latitude":58.18444,"geom:longitude":26.17833,"gn:admin1_code":"18.0","gn:admin2_code":"171.0","gn:admin3_code":"6164.0","gn:asciiname":"Piigandi","gn:country_code":"EE","gn:dem":59,"gn:feature_class":"P","gn:feature_code":"PPL","gn:geonameid":794010,"gn:latitude":58.18444,"gn:longitude":26.17833,"gn:modification_date":"2017-11-25","gn:name":"Piigandi","gn:population":0,"gn:timezone":"Europe/Tallinn","iso:country":"EE","lbl:bbox":"26.15833,58.16444,26.19833,58.20444","lbl:max_zoom":18,"lbl:min_zoom":13.5,"mz:hierarchy_label":1,"mz:is_current":1,"mz:min_zoom":12,"name:est_x_preferred":["Piigandi"],"name:fra_x_preferred":["Piigandi"],"name:hye_x_preferred":["Պիիգանդի"],"name:pol_x_preferred":["Piigandi"],"name:spa_x_preferred":["Piigandi"],"name:ukr_x_preferred":["Пійґанді"],"name:vol_x_preferred":["Piigandi"],"src:geom":"geonames","wof:belongsto":[85682995,102191581,1713310673,85633135,1713305757],"wof:breaches":[],"wof:concordances":{"gn:id":794010,"wk:page":"Piigandi%2C_Tartu_County"},"wof:coterminous":[1713310673],"wof:country":"EE","wof:geomhash":"c6b69e8c8dbb04cd749676c2edcb9955","wof:hierarchy":[{"continent_id":102191581,"country_id":85633135,"county_id":1713305757,"localadmin_id":1713310673,"locality_id":1226008051,"region_id":85682995}],"wof:id":1226008051,"wof:lang_x_official":["est"],"wof:lang_x_spoken":["est"],"wof:lastmodified":1596661909,"wof:name":"Piigandi","wof:parent_id":1713310673,"wof:placetype":"locality","wof:repo":"whosonfirst-data-admin-ee","wof:superseded_by":[],"wof:supersedes":[],"wof:tags":[]},"bbox":[26.17833,58.18444,26.17833,58.18444],"geometry":{"coordinates":[26.17833,58.18444],"type":"Point"}}