{"id":1277046501,"type":"Feature","properties":{"edtf:cessation":"uuuu","edtf:inception":"uuuu","geom:area":0,"geom:area_square_m":0,"geom:bbox":"22.88333,58.36667,22.88333,58.36667","geom:latitude":58.36667,"geom:longitude":22.88333,"gn:admin1_code":"14.0","gn:admin2_code":"714.0","gn:admin3_code":"2603.0","gn:asciiname":"Uue-Love","gn:cc2":"EE","gn:country_code":"EE","gn:dem":14,"gn:feature_class":"P","gn:feature_code":"PPL","gn:geonameid":588016,"gn:latitude":58.36667,"gn:longitude":22.88333,"gn:modification_date":"2017-11-25","gn:name":"Uue-Lõve","gn:population":0,"gn:timezone":"Europe/Tallinn","iso:country":"EE","lbl:bbox":"22.86333,58.34667,22.90333,58.38667","lbl:max_zoom":18,"lbl:min_zoom":13.5,"mz:hierarchy_label":1,"mz:is_current":1,"mz:min_zoom":12,"name:und_x_variant":["Myza Ue-Lyve","Uue-Lõve"],"src:geom":"geonames","wof:belongsto":[85682947,102191581,1713307393,85633135,1713305627],"wof:breaches":[],"wof:concordances":{"gn:id":588016},"wof:country":"EE","wof:geomhash":"dc4fecd21d6f52d46f9bc54dafee8745","wof:hierarchy":[{"continent_id":102191581,"country_id":85633135,"county_id":1713305627,"localadmin_id":1713307393,"locality_id":1277046501,"region_id":85682947}],"wof:id":1277046501,"wof:lang_x_official":["est"],"wof:lang_x_spoken":["est"],"wof:lastmodified":1596674960,"wof:name":"Uue-Love","wof:parent_id":1713307393,"wof:placetype":"locality","wof:repo":"whosonfirst-data-admin-ee","wof:superseded_by":[],"wof:supersedes":[],"wof:tags":[]},"bbox":[22.88333,58.36667,22.88333,58.36667],"geometry":{"coordinates":[22.88333,58.36667],"type":"Point"}}