{"id":1226221711,"type":"Feature","properties":{"edtf:cessation":"uuuu","edtf:inception":"uuuu","geom:area":0,"geom:area_square_m":0,"geom:bbox":"24.30194,58.78778,24.30194,58.78778","geom:latitude":58.78778,"geom:longitude":24.30194,"gn:admin1_code":"13.0","gn:admin2_code":"503.0","gn:admin3_code":"8208.0","gn:asciiname":"Tiduvere","gn:country_code":"EE","gn:dem":17,"gn:feature_class":"P","gn:feature_code":"PPL","gn:geonameid":588303,"gn:latitude":58.78778,"gn:longitude":24.30194,"gn:modification_date":"2017-11-25","gn:name":"Tiduvere","gn:population":0,"gn:timezone":"Europe/Tallinn","iso:country":"EE","lbl:bbox":"24.28194,58.76778,24.32194,58.80778","lbl:max_zoom":18,"lbl:min_zoom":13.5,"mz:hierarchy_label":1,"mz:is_current":1,"mz:min_zoom":12,"name:est_x_preferred":["Tiduvere"],"name:hye_x_preferred":["Տիդուվեռե"],"name:pol_x_preferred":["Tiduvere"],"name:sco_x_preferred":["Tiduvere"],"name:spa_x_preferred":["Tiduvere"],"name:vol_x_preferred":["Tiduvere"],"src:geom":"geonames","wof:belongsto":[85683013,102191581,1713311097,85633135,1713305747],"wof:breaches":[],"wof:concordances":{"gn:id":588303,"wk:page":"Tiduvere"},"wof:coterminous":[1713311097],"wof:country":"EE","wof:geomhash":"00708699d17c683bb8b1e6ca76acdbbb","wof:hierarchy":[{"continent_id":102191581,"country_id":85633135,"county_id":1713305747,"localadmin_id":1713311097,"locality_id":1226221711,"region_id":85683013}],"wof:id":1226221711,"wof:lang_x_official":["est"],"wof:lang_x_spoken":["est"],"wof:lastmodified":1596662838,"wof:name":"Tiduvere","wof:parent_id":1713311097,"wof:placetype":"locality","wof:repo":"whosonfirst-data-admin-ee","wof:superseded_by":[],"wof:supersedes":[],"wof:tags":[]},"bbox":[24.30194,58.78778,24.30194,58.78778],"geometry":{"coordinates":[24.30194,58.78778],"type":"Point"}}