{"id":1344245093,"type":"Feature","properties":{"edtf:cessation":"uuuu","edtf:inception":"uuuu","geom:area":0,"geom:area_square_m":0,"geom:bbox":"25.02611,58.63889,25.02611,58.63889","geom:latitude":58.63889,"geom:longitude":25.02611,"gn:admin1_code":"11.0","gn:admin2_code":"638.0","gn:admin3_code":"7229.0","gn:asciiname":"Raetsepa","gn:country_code":"EE","gn:dem":36,"gn:feature_class":"P","gn:feature_code":"PPL","gn:geonameid":793840,"gn:latitude":58.63889,"gn:longitude":25.02611,"gn:modification_date":"2017-11-25","gn:name":"Rätsepa","gn:population":0,"gn:timezone":"Europe/Tallinn","iso:country":"EE","lbl:bbox":"25.00611,58.61889,25.04611,58.65889","lbl:max_zoom":18,"lbl:min_zoom":13.5,"mz:hierarchy_label":1,"mz:is_current":1,"mz:min_zoom":12,"src:geom":"geonames","wof:belongsto":[85682981,102191581,1713309611,85633135,1713305733],"wof:breaches":[],"wof:concordances":{"gn:id":793840},"wof:coterminous":[1713309611],"wof:country":"EE","wof:geomhash":"09ad826296f1282f43a2021536f5ada6","wof:hierarchy":[{"continent_id":102191581,"country_id":85633135,"county_id":1713305733,"localadmin_id":1713309611,"locality_id":1344245093,"region_id":85682981}],"wof:id":1344245093,"wof:lang_x_official":["est"],"wof:lang_x_spoken":["est"],"wof:lastmodified":1596663430,"wof:name":"Raetsepa","wof:parent_id":1713309611,"wof:placetype":"locality","wof:repo":"whosonfirst-data-admin-ee","wof:superseded_by":[],"wof:supersedes":[],"wof:tags":[]},"bbox":[25.02611,58.63889,25.02611,58.63889],"geometry":{"coordinates":[25.02611,58.63889],"type":"Point"}}