{"id":1293263115,"type":"Feature","properties":{"edtf:cessation":"uuuu","edtf:inception":"uuuu","geom:area":0,"geom:area_square_m":0,"geom:bbox":"22.62417,58.36556,22.62417,58.36556","geom:latitude":58.36556,"geom:longitude":22.62417,"gn:admin1_code":"14.0","gn:admin2_code":"714.0","gn:admin3_code":"7451.0","gn:asciiname":"Saue-Putla","gn:country_code":"EE","gn:dem":27,"gn:feature_class":"P","gn:feature_code":"PPL","gn:geonameid":588776,"gn:latitude":58.36556,"gn:longitude":22.62417,"gn:modification_date":"2017-11-25","gn:name":"Saue-Putla","gn:population":0,"gn:timezone":"Europe/Tallinn","iso:country":"EE","lbl:bbox":"22.60417,58.34556,22.64417,58.38556","lbl:max_zoom":18,"lbl:min_zoom":13.5,"mz:hierarchy_label":1,"mz:is_current":1,"mz:min_zoom":12,"name:deu_x_preferred":["Saue-Putla"],"name:est_x_preferred":["Saue-Putla"],"name:hye_x_preferred":["Սաուե-Պուտլա"],"name:pol_x_preferred":["Saue-Putla"],"name:spa_x_preferred":["Saue-Putla"],"name:vol_x_preferred":["Saue-Putla"],"src:geom":"geonames","wof:belongsto":[85682947,102191581,1713306729,85633135,1713305627],"wof:breaches":[],"wof:concordances":{"gn:id":588776,"wk:page":"Saue-Putla"},"wof:coterminous":[1713306729],"wof:country":"EE","wof:geomhash":"447ae3ef0d6936fbdbca53e12959a843","wof:hierarchy":[{"continent_id":102191581,"country_id":85633135,"county_id":1713305627,"localadmin_id":1713306729,"locality_id":1293263115,"region_id":85682947}],"wof:id":1293263115,"wof:lang_x_official":["est"],"wof:lang_x_spoken":["est"],"wof:lastmodified":1596674935,"wof:name":"Saue-Putla","wof:parent_id":1713306729,"wof:placetype":"locality","wof:repo":"whosonfirst-data-admin-ee","wof:superseded_by":[],"wof:supersedes":[],"wof:tags":[]},"bbox":[22.62417,58.36556,22.62417,58.36556],"geometry":{"coordinates":[22.62417,58.36556],"type":"Point"}}