{"id":1209990543,"type":"Feature","properties":{"edtf:cessation":"uuuu","edtf:inception":"uuuu","geom:area":0,"geom:area_square_m":0,"geom:bbox":"27.45944,57.715,27.45944,57.715","geom:latitude":57.715,"geom:longitude":27.45944,"gn:admin1_code":"21.0","gn:admin2_code":"732.0","gn:admin3_code":"7628.0","gn:asciiname":"Sirgova","gn:country_code":"EE","gn:dem":185,"gn:feature_class":"P","gn:feature_code":"PPL","gn:geonameid":8620042,"gn:latitude":57.715,"gn:longitude":27.45944,"gn:modification_date":"2017-11-25","gn:name":"Sirgova","gn:population":0,"gn:timezone":"Europe/Tallinn","iso:country":"EE","lbl:bbox":"27.43944,57.695,27.47944,57.735","lbl:max_zoom":18,"lbl:min_zoom":13.5,"mz:hierarchy_label":1,"mz:is_current":1,"mz:min_zoom":12,"name:und_x_variant":["Sirkova"],"src:geom":"geonames","wof:belongsto":[85682955,102191581,1713316405,85633135,1713305631],"wof:breaches":[],"wof:concordances":{"gn:id":8620042},"wof:coterminous":[1713316405],"wof:country":"EE","wof:geomhash":"4cf16f5cf424709cbe1d7d891d121995","wof:hierarchy":[{"continent_id":102191581,"country_id":85633135,"county_id":1713305631,"localadmin_id":1713316405,"locality_id":1209990543,"region_id":85682955}],"wof:id":1209990543,"wof:lang_x_official":["est"],"wof:lang_x_spoken":["est"],"wof:lastmodified":1596663703,"wof:name":"Sirgova","wof:parent_id":1713316405,"wof:placetype":"locality","wof:repo":"whosonfirst-data-admin-ee","wof:superseded_by":[],"wof:supersedes":[],"wof:tags":[]},"bbox":[27.45944,57.715,27.45944,57.715],"geometry":{"coordinates":[27.45944,57.715],"type":"Point"}}