{"id":1125912949,"type":"Feature","properties":{"edtf:cessation":"uuuu","edtf:inception":"uuuu","geom:area":0,"geom:area_square_m":0,"geom:bbox":"26.11333,59.58083,26.11333,59.58083","geom:latitude":59.58083,"geom:longitude":26.11333,"gn:country":"EE","gn:fcode":"PPL","gn:population":0,"iso:country":"EE","lbl:bbox":"26.09333,59.56083,26.13333,59.60083","lbl:latitude":59.58083,"lbl:longitude":26.11333,"lbl:max_zoom":18,"lbl:min_zoom":13.5,"mz:hierarchy_label":1,"mz:is_current":1,"mz:min_zoom":12,"mz:note":"Quattroshapes Point Gazetteer import 20170519","name:bul_x_preferred":["Алтя"],"name:deu_x_preferred":["Altja"],"name:eng_x_preferred":["Altja"],"name:est_x_preferred":["Altja"],"name:fas_x_preferred":["التجا"],"name:fra_x_preferred":["Altja"],"name:hye_x_preferred":["Ալտյա"],"name:nld_x_preferred":["Altja"],"name:pol_x_preferred":["Altja"],"name:rus_x_preferred":["Алтья"],"name:swe_x_preferred":["Altja"],"name:ukr_x_preferred":["Алтья"],"name:und_x_variant":["Al’t’ya"],"name:vol_x_preferred":["Altja"],"qs_pg:aaroncc":"EE","qs_pg:gn_country":"EE","qs_pg:gn_fcode":"PPL","qs_pg:gn_id":592521,"qs_pg:gn_pop":0,"qs_pg:name":"Altja","qs_pg:name_adm0":"Eesti","qs_pg:name_adm1":"Lääne-Virumaa","qs_pg:photos":59,"qs_pg:photos_1k":12,"qs_pg:photos_9k":1,"qs_pg:photos_9r":2,"qs_pg:photos_all":59,"qs_pg:photos_sr":2,"qs_pg:pop_sr":0,"qs_pg:qs_id":478035,"qs_pg:qs_pg_placetype":"locality","qs_pg:qs_pg_placetype_gp":"Town","qs_pg:woe_adm0":23424805,"qs_pg:woe_id":841911,"src:geom":"qs_pg","src:lbl_centroid":"qs_pg","woe:adm0_id":23424805,"woe:name_adm0":"Eesti","woe:name_adm1":"Lääne-Virumaa","woe:placetype":"Town","wof:belongsto":[85683049,102191581,1713308309,85633135,1713305775],"wof:breaches":[],"wof:concordances":{"gn:id":592521,"gp:id":841911,"qs_pg:id":478035,"wd:id":"Q441823"},"wof:coterminous":[1713308309],"wof:country":"EE","wof:created":1497296201,"wof:geomhash":"6204d7d88d5192f58901cd8b43746b1f","wof:hierarchy":[{"continent_id":102191581,"country_id":85633135,"county_id":1713305775,"localadmin_id":1713308309,"locality_id":1125912949,"region_id":85683049}],"wof:id":1125912949,"wof:lang_x_official":["est"],"wof:lang_x_spoken":["est"],"wof:lastmodified":1596678042,"wof:name":"Altja","wof:parent_id":1713308309,"wof:placetype":"locality","wof:repo":"whosonfirst-data-admin-ee","wof:superseded_by":[],"wof:supersedes":[],"wof:tags":[]},"bbox":[26.11333,59.58083,26.11333,59.58083],"geometry":{"coordinates":[26.11333,59.58083],"type":"Point"}}