{"id":1226551499,"type":"Feature","properties":{"edtf:cessation":"uuuu","edtf:inception":"uuuu","geom:area":0,"geom:area_square_m":0,"geom:bbox":"27.83262,59.30721,27.83262,59.30721","geom:latitude":59.30721,"geom:longitude":27.83262,"gn:admin1_code":"3.0","gn:admin2_code":"514.0","gn:admin3_code":"5067.0","gn:asciiname":"Metskuela","gn:country_code":"EE","gn:dem":32,"gn:feature_class":"P","gn:feature_code":"PPL","gn:geonameid":590220,"gn:latitude":59.30721,"gn:longitude":27.83262,"gn:modification_date":"2017-11-25","gn:name":"Metsküla","gn:population":0,"gn:timezone":"Europe/Tallinn","iso:country":"EE","lbl:bbox":"27.81262,59.28721,27.85262,59.32721","lbl:max_zoom":18,"lbl:min_zoom":13.5,"mz:hierarchy_label":1,"mz:is_current":1,"mz:min_zoom":12,"name:und_x_variant":["Metskyula","Metsküla"],"src:geom":"geonames","wof:belongsto":[85683059,102191581,1713313271,85633135,1713305779],"wof:breaches":[],"wof:concordances":{"gn:id":590220},"wof:country":"EE","wof:geomhash":"3a3f30aa103259b57f2bfeca0bc8f713","wof:hierarchy":[{"continent_id":102191581,"country_id":85633135,"county_id":1713305779,"localadmin_id":1713313271,"locality_id":1226551499,"region_id":85683059}],"wof:id":1226551499,"wof:lang_x_official":["est"],"wof:lang_x_spoken":["est"],"wof:lastmodified":1596677904,"wof:name":"Metskuela","wof:parent_id":1713313271,"wof:placetype":"locality","wof:repo":"whosonfirst-data-admin-ee","wof:superseded_by":[],"wof:supersedes":[],"wof:tags":[]},"bbox":[27.83262,59.30721,27.83262,59.30721],"geometry":{"coordinates":[27.83262,59.30721],"type":"Point"}}