{"id":1243240789,"type":"Feature","properties":{"edtf:cessation":"uuuu","edtf:inception":"uuuu","geom:area":0,"geom:area_square_m":0,"geom:bbox":"27.48306,57.98694,27.48306,57.98694","geom:latitude":57.98694,"geom:longitude":27.48306,"gn:admin1_code":"21.0","gn:admin2_code":"732.0","gn:admin3_code":"6474.0","gn:asciiname":"Puugnitsa","gn:country_code":"EE","gn:dem":38,"gn:feature_class":"P","gn:feature_code":"PPL","gn:geonameid":794199,"gn:latitude":57.98694,"gn:longitude":27.48306,"gn:modification_date":"2017-11-25","gn:name":"Puugnitsa","gn:population":0,"gn:timezone":"Europe/Tallinn","iso:country":"EE","lbl:bbox":"27.46306,57.96694,27.50306,58.00694","lbl:max_zoom":18,"lbl:min_zoom":13.5,"mz:hierarchy_label":1,"mz:is_current":1,"mz:min_zoom":12,"name:deu_x_preferred":["Puugnitsa"],"name:est_x_preferred":["Puugnitsa"],"name:fra_x_preferred":["Puugnitsa"],"name:hye_x_preferred":["Պուուգնիցա"],"name:pol_x_preferred":["Puugnitsa"],"name:spa_x_preferred":["Puugnitsa"],"name:ukr_x_preferred":["Пуугніца"],"name:vol_x_preferred":["Puugnitsa"],"src:geom":"geonames","wof:belongsto":[85682955,102191581,1713315949,85633135,1713305631],"wof:breaches":[],"wof:concordances":{"gn:id":794199,"wk:page":"Puugnitsa"},"wof:coterminous":[1713315949],"wof:country":"EE","wof:geomhash":"99823891613053c51afb5a1f058bd82b","wof:hierarchy":[{"continent_id":102191581,"country_id":85633135,"county_id":1713305631,"localadmin_id":1713315949,"locality_id":1243240789,"region_id":85682955}],"wof:id":1243240789,"wof:lang_x_official":["est"],"wof:lang_x_spoken":["est"],"wof:lastmodified":1596663706,"wof:name":"Puugnitsa","wof:parent_id":1713315949,"wof:placetype":"locality","wof:repo":"whosonfirst-data-admin-ee","wof:superseded_by":[],"wof:supersedes":[],"wof:tags":[]},"bbox":[27.48306,57.98694,27.48306,57.98694],"geometry":{"coordinates":[27.48306,57.98694],"type":"Point"}}