{"id":1225943205,"type":"Feature","properties":{"edtf:cessation":"uuuu","edtf:inception":"uuuu","geom:area":0,"geom:area_square_m":0,"geom:bbox":"26.07917,58.80333,26.07917,58.80333","geom:latitude":58.80333,"geom:longitude":26.07917,"gn:admin1_code":"5.0","gn:admin2_code":"618.0","gn:admin3_code":"8483.0","gn:asciiname":"Toivere","gn:cc2":"EE","gn:country_code":"EE","gn:dem":78,"gn:feature_class":"P","gn:feature_code":"PPL","gn:geonameid":588259,"gn:latitude":58.80333,"gn:longitude":26.07917,"gn:modification_date":"2017-11-25","gn:name":"Tõivere","gn:population":0,"gn:timezone":"Europe/Tallinn","iso:country":"EE","lbl:bbox":"26.05917,58.78333,26.09917,58.82333","lbl:max_zoom":18,"lbl:min_zoom":13.5,"mz:hierarchy_label":1,"mz:is_current":1,"mz:min_zoom":12,"name:est_x_preferred":["Tõivere"],"name:fas_x_preferred":["تویور"],"name:hye_x_preferred":["Տիիվեռե"],"name:pol_x_preferred":["Tõivere"],"name:spa_x_preferred":["Tõivere"],"name:ukr_x_preferred":["Тийвере"],"name:und_x_variant":["Toyvere","Toivere"],"name:vol_x_preferred":["Tõivere"],"src:geom":"geonames","wof:belongsto":[85683009,102191581,1713314521,85633135,1713305657],"wof:breaches":[],"wof:concordances":{"gn:id":588259,"wk:page":"T%C3%B5ivere"},"wof:coterminous":[1713314521],"wof:country":"EE","wof:geomhash":"6e58c99dc67a4b8162f0d7979d689612","wof:hierarchy":[{"continent_id":102191581,"country_id":85633135,"county_id":1713305657,"localadmin_id":1713314521,"locality_id":1225943205,"region_id":85683009}],"wof:id":1225943205,"wof:lang_x_official":["est"],"wof:lang_x_spoken":["est"],"wof:lastmodified":1596676498,"wof:name":"Toivere","wof:parent_id":1713314521,"wof:placetype":"locality","wof:repo":"whosonfirst-data-admin-ee","wof:superseded_by":[],"wof:supersedes":[],"wof:tags":[]},"bbox":[26.07917,58.80333,26.07917,58.80333],"geometry":{"coordinates":[26.07917,58.80333],"type":"Point"}}