{"id":1259360201,"type":"Feature","properties":{"edtf:cessation":"uuuu","edtf:inception":"uuuu","geom:area":0,"geom:area_square_m":0,"geom:bbox":"27.33389,57.82917,27.33389,57.82917","geom:latitude":57.82917,"geom:longitude":27.33389,"gn:admin1_code":"21.0","gn:admin2_code":"917.0","gn:admin3_code":"6345.0","gn:asciiname":"Praakmani","gn:country_code":"EE","gn:dem":99,"gn:feature_class":"P","gn:feature_code":"PPL","gn:geonameid":8620163,"gn:latitude":57.82917,"gn:longitude":27.33389,"gn:modification_date":"2017-11-25","gn:name":"Praakmani","gn:population":0,"gn:timezone":"Europe/Tallinn","iso:country":"EE","lbl:bbox":"27.31389,57.80917,27.35389,57.84917","lbl:max_zoom":18,"lbl:min_zoom":13.5,"mz:hierarchy_label":1,"mz:is_current":1,"mz:min_zoom":12,"name:est_x_preferred":["Praakmani"],"name:hye_x_preferred":["Պռաակմանի"],"name:pol_x_preferred":["Praakmani"],"name:spa_x_preferred":["Praakmani"],"name:ukr_x_preferred":["Праакмані"],"name:vol_x_preferred":["Praakmani"],"src:geom":"geonames","wof:belongsto":[85682937,102191581,1713315973,85633135,1713305633],"wof:breaches":[],"wof:concordances":{"gn:id":8620163,"wk:page":"Praakmani"},"wof:coterminous":[1713315973],"wof:country":"EE","wof:geomhash":"fa0477f67c61131a30fc74c7905a0433","wof:hierarchy":[{"continent_id":102191581,"country_id":85633135,"county_id":1713305633,"localadmin_id":1713315973,"locality_id":1259360201,"region_id":85682937}],"wof:id":1259360201,"wof:lang_x_official":["est"],"wof:lang_x_spoken":["est"],"wof:lastmodified":1596660403,"wof:name":"Praakmani","wof:parent_id":1713315973,"wof:placetype":"locality","wof:repo":"whosonfirst-data-admin-ee","wof:superseded_by":[],"wof:supersedes":[],"wof:tags":[]},"bbox":[27.33389,57.82917,27.33389,57.82917],"geometry":{"coordinates":[27.33389,57.82917],"type":"Point"}}