{"id":1360047167,"type":"Feature","properties":{"edtf:cessation":"uuuu","edtf:inception":"uuuu","geom:area":0,"geom:area_square_m":0,"geom:bbox":"25.37694,58.42583,25.37694,58.42583","geom:latitude":58.42583,"geom:longitude":25.37694,"gn:admin1_code":"20.0","gn:admin2_code":"615.0","gn:admin3_code":"2116.0","gn:asciiname":"Ivaski","gn:country_code":"EE","gn:dem":60,"gn:feature_class":"P","gn:feature_code":"PPL","gn:geonameid":793860,"gn:latitude":58.42583,"gn:longitude":25.37694,"gn:modification_date":"2017-11-25","gn:name":"Ivaski","gn:population":0,"gn:timezone":"Europe/Tallinn","iso:country":"EE","lbl:bbox":"25.35694,58.40583,25.39694,58.44583","lbl:max_zoom":18,"lbl:min_zoom":13.5,"mz:hierarchy_label":1,"mz:is_current":1,"mz:min_zoom":12,"name:est_x_preferred":["Ivaski"],"name:hye_x_preferred":["Իվասկի"],"name:pol_x_preferred":["Ivaski"],"name:spa_x_preferred":["Ivaski"],"name:ukr_x_preferred":["Іваскі"],"name:vol_x_preferred":["Ivaski"],"src:geom":"geonames","wof:belongsto":[85682985,102191581,1713311719,85633135,1713305735],"wof:breaches":[],"wof:concordances":{"gn:id":793860,"wk:page":"Ivaski"},"wof:coterminous":[1713311719],"wof:country":"EE","wof:geomhash":"1b005c2d26bed91c5c926c4ed5128560","wof:hierarchy":[{"continent_id":102191581,"country_id":85633135,"county_id":1713305735,"localadmin_id":1713311719,"locality_id":1360047167,"region_id":85682985}],"wof:id":1360047167,"wof:lang_x_official":["est"],"wof:lang_x_spoken":["est"],"wof:lastmodified":1596663452,"wof:name":"Ivaski","wof:parent_id":1713311719,"wof:placetype":"locality","wof:repo":"whosonfirst-data-admin-ee","wof:superseded_by":[],"wof:supersedes":[],"wof:tags":[]},"bbox":[25.37694,58.42583,25.37694,58.42583],"geometry":{"coordinates":[25.37694,58.42583],"type":"Point"}}