{"id":1125830069,"type":"Feature","properties":{"edtf:cessation":"uuuu","edtf:inception":"uuuu","geom:area":0,"geom:area_square_m":0,"geom:bbox":"24.79318,59.26402,24.79318,59.26402","geom:latitude":59.26402,"geom:longitude":24.79318,"gn:country":"EE","gn:fcode":"PPLF","gn:population":4,"iso:country":"EE","lbl:bbox":"24.77318,59.24402,24.81318,59.28402","lbl:latitude":59.26402,"lbl:longitude":24.79318,"lbl:max_zoom":18,"lbl:min_zoom":13,"mz:hierarchy_label":1,"mz:is_current":1,"mz:min_zoom":11,"mz:note":"Quattroshapes Point Gazetteer import 20170519","qs_pg:aaroncc":"EE","qs_pg:gn_country":"EE","qs_pg:gn_fcode":"PPLF","qs_pg:gn_id":7576714,"qs_pg:gn_pop":4,"qs_pg:name":"aaviku talu","qs_pg:photos_9r":0,"qs_pg:photos_sr":0,"qs_pg:pop_sr":1,"qs_pg:qs_id":693271,"qs_pg:qs_pg_placetype":"locality","src:geom":"qs_pg","src:lbl_centroid":"qs_pg","src:population":"geonames","wof:belongsto":[85683055,102191581,1713312911,85633135,1713305643],"wof:breaches":[],"wof:concordances":{"gn:id":7576714,"qs_pg:id":693271},"wof:country":"EE","wof:created":1497292459,"wof:geomhash":"4a1d7ed2137e8e2437a8e2796f12c98b","wof:hierarchy":[{"continent_id":102191581,"country_id":85633135,"county_id":1713305643,"localadmin_id":1713312911,"locality_id":1125830069,"region_id":85683055}],"wof:id":1125830069,"wof:lang_x_official":["est"],"wof:lang_x_spoken":["est"],"wof:lastmodified":1596663500,"wof:name":"aaviku talu","wof:parent_id":1713312911,"wof:placetype":"locality","wof:population":4,"wof:population_rank":1,"wof:repo":"whosonfirst-data-admin-ee","wof:superseded_by":[],"wof:supersedes":[],"wof:tags":[]},"bbox":[24.79318,59.26402,24.79318,59.26402],"geometry":{"coordinates":[24.79318,59.26402],"type":"Point"}}