{"id":1343546899,"type":"Feature","properties":{"edtf:cessation":"uuuu","edtf:inception":"uuuu","geom:area":0,"geom:area_square_m":0,"geom:bbox":"26.58194,59.18722,26.58194,59.18722","geom:latitude":59.18722,"geom:longitude":26.58194,"gn:admin1_code":"8.0","gn:admin2_code":"901.0","gn:admin3_code":"7012.0","gn:asciiname":"Puka","gn:country_code":"EE","gn:dem":101,"gn:feature_class":"P","gn:feature_code":"PPL","gn:geonameid":589290,"gn:latitude":59.18722,"gn:longitude":26.58194,"gn:modification_date":"2017-11-25","gn:name":"Puka","gn:population":0,"gn:timezone":"Europe/Tallinn","iso:country":"EE","lbl:bbox":"26.56194,59.16722,26.60194,59.20722","lbl:max_zoom":18,"lbl:min_zoom":13.5,"mz:hierarchy_label":1,"mz:is_current":1,"mz:min_zoom":12,"name:ceb_x_preferred":["Puka"],"name:deu_x_preferred":["Puka"],"name:est_x_preferred":["Puka"],"name:heb_x_preferred":["פוקה"],"name:hun_x_preferred":["Puka"],"name:hye_x_preferred":["Պուկա"],"name:mri_x_preferred":["Puka"],"name:nld_x_preferred":["Puka"],"name:por_x_preferred":["Puka"],"name:ron_x_preferred":["Puka"],"name:swe_x_preferred":["Puka"],"name:ukr_x_preferred":["Пука"],"name:vol_x_preferred":["Puka"],"src:geom":"geonames","wof:belongsto":[85683049,102191581,1713307623,85633135,1713305771],"wof:breaches":[],"wof:concordances":{"gn:id":589290},"wof:coterminous":[1713307875],"wof:country":"EE","wof:geomhash":"5d5c4c7b96f7ea36cb9838969267f6f1","wof:hierarchy":[{"continent_id":102191581,"country_id":85633135,"county_id":1713305771,"localadmin_id":1713307623,"locality_id":1343546899,"region_id":85683049}],"wof:id":1343546899,"wof:lang_x_official":["est"],"wof:lang_x_spoken":["est"],"wof:lastmodified":1596677963,"wof:name":"Puka","wof:parent_id":1713307623,"wof:placetype":"locality","wof:repo":"whosonfirst-data-admin-ee","wof:superseded_by":[],"wof:supersedes":[],"wof:tags":[]},"bbox":[26.58194,59.18722,26.58194,59.18722],"geometry":{"coordinates":[26.58194,59.18722],"type":"Point"}}