{"id":1310026891,"type":"Feature","properties":{"edtf:cessation":"uuuu","edtf:inception":"uuuu","geom:area":0,"geom:area_square_m":0,"geom:bbox":"24.06833,58.91306,24.06833,58.91306","geom:latitude":58.91306,"geom:longitude":24.06833,"gn:admin1_code":"7.0","gn:admin2_code":"441.0","gn:admin3_code":"2593.0","gn:asciiname":"Kalju","gn:cc2":"EE","gn:country_code":"EE","gn:dem":32,"gn:feature_class":"P","gn:feature_code":"PPL","gn:geonameid":591705,"gn:latitude":58.91306,"gn:longitude":24.06833,"gn:modification_date":"2017-11-25","gn:name":"Kalju","gn:population":0,"gn:timezone":"Europe/Tallinn","iso:country":"EE","lbl:bbox":"24.04833,58.89306,24.08833,58.93306","lbl:max_zoom":18,"lbl:min_zoom":13.5,"mz:hierarchy_label":1,"mz:is_current":1,"mz:min_zoom":12,"name:deu_x_preferred":["Kalju"],"name:est_x_preferred":["Kalju"],"name:hye_x_preferred":["Կալյու"],"name:nld_x_preferred":["Kalju"],"name:pol_x_preferred":["Kalju"],"name:spa_x_preferred":["Kalju"],"name:ukr_x_preferred":["Калью"],"name:und_x_variant":["Kal’yu"],"name:vol_x_preferred":["Kalju"],"src:geom":"geonames","wof:belongsto":[85683001,102191581,1713308849,85633135,1713305701],"wof:breaches":[],"wof:concordances":{"gn:id":591705,"wk:page":"Kalju%2C_L%C3%A4%C3%A4ne_County"},"wof:coterminous":[1713308849],"wof:country":"EE","wof:geomhash":"d5c605dc685d4ecca136fb5928046e54","wof:hierarchy":[{"continent_id":102191581,"country_id":85633135,"county_id":1713305701,"localadmin_id":1713308849,"locality_id":1310026891,"region_id":85683001}],"wof:id":1310026891,"wof:lang_x_official":["est"],"wof:lang_x_spoken":["est"],"wof:lastmodified":1596677438,"wof:name":"Kalju","wof:parent_id":1713308849,"wof:placetype":"locality","wof:repo":"whosonfirst-data-admin-ee","wof:superseded_by":[],"wof:supersedes":[],"wof:tags":[]},"bbox":[24.06833,58.91306,24.06833,58.91306],"geometry":{"coordinates":[24.06833,58.91306],"type":"Point"}}