{"id":1193272635,"type":"Feature","properties":{"edtf:cessation":"uuuu","edtf:inception":"uuuu","geom:area":0,"geom:area_square_m":0,"geom:bbox":"23.50583,59.18417,23.50583,59.18417","geom:latitude":59.18417,"geom:longitude":23.50583,"gn:admin1_code":"7.0","gn:admin2_code":"441.0","gn:admin3_code":"7077.0","gn:asciiname":"Rooslepa","gn:cc2":"EE","gn:country_code":"EE","gn:dem":7,"gn:feature_class":"P","gn:feature_code":"PPL","gn:geonameid":796116,"gn:latitude":59.18417,"gn:longitude":23.50583,"gn:modification_date":"2017-11-25","gn:name":"Rooslepa","gn:population":0,"gn:timezone":"Europe/Tallinn","iso:country":"EE","lbl:bbox":"23.48583,59.16417,23.52583,59.20417","lbl:max_zoom":18,"lbl:min_zoom":13.5,"mz:hierarchy_label":1,"mz:is_current":1,"mz:min_zoom":12,"name:deu_x_preferred":["Rooslepa"],"name:est_x_preferred":["Rooslepa"],"name:hye_x_preferred":["Ռոոսլեպա"],"name:pol_x_preferred":["Rooslepa"],"name:spa_x_preferred":["Rooslepa"],"name:swe_x_preferred":["Roslep"],"name:ukr_x_preferred":["Роослепа"],"name:und_x_variant":["Kirka Rooslepa","Rooslepa Kabel","Rooslepa Surnuaed","Roslep Chapel","Reslepa","Rozlepa"],"name:vol_x_preferred":["Rooslepa"],"src:geom":"geonames","wof:belongsto":[85683001,102191581,1713309077,85633135,1713305701],"wof:breaches":[],"wof:concordances":{"gn:id":796116,"wk:page":"Rooslepa"},"wof:coterminous":[1713309077],"wof:country":"EE","wof:geomhash":"17eee0569b7109c62e22b19f73737862","wof:hierarchy":[{"continent_id":102191581,"country_id":85633135,"county_id":1713305701,"localadmin_id":1713309077,"locality_id":1193272635,"region_id":85683001}],"wof:id":1193272635,"wof:lang_x_official":["est"],"wof:lang_x_spoken":["est"],"wof:lastmodified":1596677426,"wof:name":"Rooslepa","wof:parent_id":1713309077,"wof:placetype":"locality","wof:repo":"whosonfirst-data-admin-ee","wof:superseded_by":[],"wof:supersedes":[],"wof:tags":[]},"bbox":[23.50583,59.18417,23.50583,59.18417],"geometry":{"coordinates":[23.50583,59.18417],"type":"Point"}}