{"id":1326501113,"type":"Feature","properties":{"edtf:cessation":"uuuu","edtf:inception":"uuuu","geom:area":0,"geom:area_square_m":0,"geom:bbox":"22.67583,58.29639,22.67583,58.29639","geom:latitude":58.29639,"geom:longitude":22.67583,"gn:admin1_code":"14.0","gn:admin2_code":"714.0","gn:admin3_code":"3719.0","gn:asciiname":"Kuusiku","gn:cc2":"EE","gn:country_code":"EE","gn:dem":16,"gn:feature_class":"P","gn:feature_code":"PPL","gn:geonameid":590884,"gn:latitude":58.29639,"gn:longitude":22.67583,"gn:modification_date":"2017-11-25","gn:name":"Kuusiku","gn:population":0,"gn:timezone":"Europe/Tallinn","iso:country":"EE","lbl:bbox":"22.65583,58.27639,22.69583,58.31639","lbl:max_zoom":18,"lbl:min_zoom":13.5,"mz:hierarchy_label":1,"mz:is_current":1,"mz:min_zoom":12,"name:und_x_variant":["Kusiku-Il’pla","Kuusiku"],"src:geom":"geonames","wof:belongsto":[85682947,102191581,1713307593,85633135,1713305627],"wof:breaches":[],"wof:concordances":{"gn:id":590884,"wk:page":"Kuusiku%2C_Pihtla_Parish"},"wof:coterminous":[1713307593],"wof:country":"EE","wof:geomhash":"e0eaa16c614d566d567b2c48eb685db5","wof:hierarchy":[{"continent_id":102191581,"country_id":85633135,"county_id":1713305627,"localadmin_id":1713307593,"locality_id":1326501113,"region_id":85682947}],"wof:id":1326501113,"wof:lang_x_official":["est"],"wof:lang_x_spoken":["est"],"wof:lastmodified":1596674929,"wof:name":"Kuusiku","wof:parent_id":1713307593,"wof:placetype":"locality","wof:repo":"whosonfirst-data-admin-ee","wof:superseded_by":[],"wof:supersedes":[],"wof:tags":[]},"bbox":[22.67583,58.29639,22.67583,58.29639],"geometry":{"coordinates":[22.67583,58.29639],"type":"Point"}}