{"id":1293385633,"type":"Feature","properties":{"edtf:cessation":"uuuu","edtf:inception":"uuuu","geom:area":0,"geom:area_square_m":0,"geom:bbox":"26.64861,59.45056,26.64861,59.45056","geom:latitude":59.45056,"geom:longitude":26.64861,"gn:admin1_code":"8.0","gn:admin2_code":"903.0","gn:admin3_code":"5456.0","gn:asciiname":"Nugeri","gn:country_code":"EE","gn:dem":54,"gn:feature_class":"P","gn:feature_code":"PPL","gn:geonameid":589923,"gn:latitude":59.45056,"gn:longitude":26.64861,"gn:modification_date":"2017-11-25","gn:name":"Nugeri","gn:population":0,"gn:timezone":"Europe/Tallinn","iso:country":"EE","lbl:bbox":"26.62861,59.43056,26.66861,59.47056","lbl:max_zoom":18,"lbl:min_zoom":13.5,"mz:hierarchy_label":1,"mz:is_current":1,"mz:min_zoom":12,"name:est_x_preferred":["Nugeri"],"name:hye_x_preferred":["Նուգեռի"],"name:vol_x_preferred":["Nugeri"],"src:geom":"geonames","wof:belongsto":[85683049,102191581,1713307705,85633135,1713305777],"wof:breaches":[],"wof:concordances":{"gn:id":589923,"wk:page":"Nugeri"},"wof:coterminous":[1713307705],"wof:country":"EE","wof:geomhash":"8e9c884d3adb5b5f31e8cd1529c06718","wof:hierarchy":[{"continent_id":102191581,"country_id":85633135,"county_id":1713305777,"localadmin_id":1713307705,"locality_id":1293385633,"region_id":85683049}],"wof:id":1293385633,"wof:lang_x_official":["est"],"wof:lang_x_spoken":["est"],"wof:lastmodified":1596677938,"wof:name":"Nugeri","wof:parent_id":1713307705,"wof:placetype":"locality","wof:repo":"whosonfirst-data-admin-ee","wof:superseded_by":[],"wof:supersedes":[],"wof:tags":[]},"bbox":[26.64861,59.45056,26.64861,59.45056],"geometry":{"coordinates":[26.64861,59.45056],"type":"Point"}}