{
  "type": "Feature",
  "properties": {
    "iso:country":"FI",
    "name:sw_x_variant":[
        "\u00c5s"
    ],
    "wof:name":"Harju",
    "wof:placetype":"neighbourhood"
},
  "geometry": {"coordinates":[24.95282959671406,60.18844567533608],"type":"Point"}
}