{"id":1226755333,"type":"Feature","properties":{"edtf:cessation":"uuuu","edtf:inception":"uuuu","geom:area":0,"geom:area_square_m":0,"geom:bbox":"27.13111,59.40583,27.13111,59.40583","geom:latitude":59.40583,"geom:longitude":27.13111,"gn:admin1_code":"3.0","gn:admin2_code":"442.0","gn:admin3_code":"9475.0","gn:asciiname":"Voorepera","gn:cc2":"EE","gn:country_code":"EE","gn:dem":49,"gn:feature_class":"P","gn:feature_code":"PPL","gn:geonameid":587464,"gn:latitude":59.40583,"gn:longitude":27.13111,"gn:modification_date":"2017-11-25","gn:name":"Voorepera","gn:population":0,"gn:timezone":"Europe/Tallinn","iso:country":"EE","lbl:bbox":"27.11111,59.38583,27.15111,59.42583","lbl:max_zoom":18,"lbl:min_zoom":13.5,"mz:hierarchy_label":1,"mz:is_current":1,"mz:min_zoom":12,"name:deu_x_preferred":["Voorepera"],"name:est_x_preferred":["Voorepera"],"name:hye_x_preferred":["Վոոռեպեռա"],"name:nld_x_preferred":["Voorepera"],"name:pol_x_preferred":["Voorepera"],"name:spa_x_preferred":["Voorepera"],"name:und_x_variant":["Vooreperu"],"name:vol_x_preferred":["Voorepera"],"src:geom":"geonames","wof:belongsto":[85683059,102191581,1713311947,85633135,1713305695],"wof:breaches":[],"wof:concordances":{"gn:id":587464,"wk:page":"Voorepera"},"wof:coterminous":[1713311947],"wof:country":"EE","wof:geomhash":"a40cd516e5938ff45a04b7cc5e5b5b2e","wof:hierarchy":[{"continent_id":102191581,"country_id":85633135,"county_id":1713305695,"localadmin_id":1713311947,"locality_id":1226755333,"region_id":85683059}],"wof:id":1226755333,"wof:lang_x_official":["est"],"wof:lang_x_spoken":["est"],"wof:lastmodified":1596660812,"wof:name":"Voorepera","wof:parent_id":1713311947,"wof:placetype":"locality","wof:repo":"whosonfirst-data-admin-ee","wof:superseded_by":[],"wof:supersedes":[],"wof:tags":[]},"bbox":[27.13111,59.40583,27.13111,59.40583],"geometry":{"coordinates":[27.13111,59.40583],"type":"Point"}}