{"id":1292986535,"type":"Feature","properties":{"edtf:cessation":"uuuu","edtf:inception":"uuuu","geom:area":0,"geom:area_square_m":0,"geom:bbox":"25.98083,59.21972,25.98083,59.21972","geom:latitude":59.21972,"geom:longitude":25.98083,"gn:admin1_code":"8.0","gn:admin2_code":"792.0","gn:admin3_code":"5551.0","gn:asciiname":"Nyao","gn:country_code":"EE","gn:dem":109,"gn:feature_class":"P","gn:feature_code":"PPL","gn:geonameid":590038,"gn:latitude":59.21972,"gn:longitude":25.98083,"gn:modification_date":"2017-11-25","gn:name":"Nyao","gn:population":0,"gn:timezone":"Europe/Tallinn","iso:country":"EE","lbl:bbox":"25.96083,59.19972,26.00083,59.23972","lbl:max_zoom":18,"lbl:min_zoom":13.5,"mz:hierarchy_label":1,"mz:is_current":1,"mz:min_zoom":12,"name:est_x_preferred":["Näo"],"name:hye_x_preferred":["Նեո"],"name:ukr_x_preferred":["Няо"],"name:und_x_variant":["Näoküla","Nyao"],"name:vol_x_preferred":["Näo"],"src:geom":"geonames","wof:belongsto":[85683049,102191581,1713308159,85633135,1713305761],"wof:breaches":[],"wof:concordances":{"gn:id":590038,"wk:page":"N%C3%A4o"},"wof:coterminous":[1713308159],"wof:country":"EE","wof:geomhash":"bbb8148c950df2fb99ed8be8d25896ea","wof:hierarchy":[{"continent_id":102191581,"country_id":85633135,"county_id":1713305761,"localadmin_id":1713308159,"locality_id":1292986535,"region_id":85683049}],"wof:id":1292986535,"wof:lang_x_official":["est"],"wof:lang_x_spoken":["est"],"wof:lastmodified":1596676601,"wof:name":"Nyao","wof:parent_id":1713308159,"wof:placetype":"locality","wof:repo":"whosonfirst-data-admin-ee","wof:superseded_by":[],"wof:supersedes":[],"wof:tags":[]},"bbox":[25.98083,59.21972,25.98083,59.21972],"geometry":{"coordinates":[25.98083,59.21972],"type":"Point"}}