{"id":1125983845,"type":"Feature","properties":{"edtf:cessation":"uuuu","edtf:inception":"uuuu","geom:area":0,"geom:area_square_m":0,"geom:bbox":"23.24694,58.60194,23.24694,58.60194","geom:latitude":58.60194,"geom:longitude":23.24694,"gn:country":"EE","gn:fcode":"PPL","gn:population":0,"iso:country":"EE","lbl:bbox":"23.22694,58.58194,23.26694,58.62194","lbl:latitude":58.60194,"lbl:longitude":23.24694,"lbl:max_zoom":18,"lbl:min_zoom":13.5,"mz:hierarchy_label":1,"mz:is_current":1,"mz:min_zoom":12,"mz:note":"Quattroshapes Point Gazetteer import 20170519","name:ceb_x_preferred":["Liiva"],"name:ces_x_preferred":["Liiva"],"name:deu_x_preferred":["Liiva"],"name:est_x_preferred":["Liiva"],"name:fin_x_preferred":["Liiva"],"name:nld_x_preferred":["Liiva"],"name:pol_x_preferred":["Liiva"],"name:swe_x_preferred":["Moon"],"name:swe_x_variant":["Liiva"],"name:und_x_variant":["Muhu"],"name:vol_x_preferred":["Liiva"],"qs_pg:aaroncc":"EE","qs_pg:gn_country":"EE","qs_pg:gn_fcode":"PPL","qs_pg:gn_id":590637,"qs_pg:gn_pop":0,"qs_pg:name":"Liiva","qs_pg:name_adm0":"Eesti","qs_pg:name_adm1":"Saaremaa","qs_pg:photos":43,"qs_pg:photos_1k":9,"qs_pg:photos_9k":1,"qs_pg:photos_9r":2,"qs_pg:photos_all":43,"qs_pg:photos_sr":2,"qs_pg:pop_sr":0,"qs_pg:qs_id":994387,"qs_pg:qs_pg_placetype":"locality","qs_pg:qs_pg_placetype_gp":"Town","qs_pg:woe_adm0":23424805,"qs_pg:woe_id":843653,"src:geom":"qs_pg","src:lbl_centroid":"qs_pg","woe:adm0_id":23424805,"woe:name_adm0":"Eesti","woe:name_adm1":"Saaremaa","woe:placetype":"Town","wof:belongsto":[85682947,102191581,1713306227,85633135,1713305623],"wof:breaches":[],"wof:concordances":{"gn:id":590637,"gp:id":843653,"qs_pg:id":994387},"wof:coterminous":[1713306227],"wof:country":"EE","wof:created":1497298702,"wof:geomhash":"3568d9cb326841b40aaef1491a9ba159","wof:hierarchy":[{"continent_id":102191581,"country_id":85633135,"county_id":1713305623,"localadmin_id":1713306227,"locality_id":1125983845,"region_id":85682947}],"wof:id":1125983845,"wof:lang_x_official":["est"],"wof:lang_x_spoken":["est"],"wof:lastmodified":1596675301,"wof:name":"Liiva","wof:parent_id":1713306227,"wof:placetype":"locality","wof:repo":"whosonfirst-data-admin-ee","wof:superseded_by":[],"wof:supersedes":[],"wof:tags":[]},"bbox":[23.24694,58.60194,23.24694,58.60194],"geometry":{"coordinates":[23.24694,58.60194],"type":"Point"}}