{"id":1225927319,"type":"Feature","properties":{"edtf:cessation":"uuuu","edtf:inception":"uuuu","geom:area":0,"geom:area_square_m":0,"geom:bbox":"23.33167,58.62056,23.33167,58.62056","geom:latitude":58.62056,"geom:longitude":23.33167,"gn:admin1_code":"14.0","gn:admin2_code":"478.0","gn:admin3_code":"4215.0","gn:asciiname":"Lehtmetsa","gn:country_code":"EE","gn:dem":7,"gn:feature_class":"P","gn:feature_code":"PPL","gn:geonameid":590719,"gn:latitude":58.62056,"gn:longitude":23.33167,"gn:modification_date":"2017-11-25","gn:name":"Lehtmetsa","gn:population":0,"gn:timezone":"Europe/Tallinn","iso:country":"EE","lbl:bbox":"23.31167,58.60056,23.35167,58.64056","lbl:max_zoom":18,"lbl:min_zoom":13.5,"mz:hierarchy_label":1,"mz:is_current":1,"mz:min_zoom":12,"name:deu_x_preferred":["Lehtmetsa"],"name:est_x_preferred":["Lehtmetsa"],"name:hye_x_preferred":["Լեհտմեցա"],"name:pol_x_preferred":["Lehtmetsa"],"name:spa_x_preferred":["Lehtmetsa"],"name:und_x_variant":["Lekhtmetsa"],"name:vol_x_preferred":["Lehtmetsa"],"src:geom":"geonames","wof:belongsto":[85682947,102191581,1713306163,85633135,1713305623],"wof:breaches":[],"wof:concordances":{"gn:id":590719,"wk:page":"Lehtmetsa%2C_Saare_County"},"wof:coterminous":[1713306163],"wof:country":"EE","wof:geomhash":"c8fa351934644230e07d26c048d92b49","wof:hierarchy":[{"continent_id":102191581,"country_id":85633135,"county_id":1713305623,"localadmin_id":1713306163,"locality_id":1225927319,"region_id":85682947}],"wof:id":1225927319,"wof:lang_x_official":["est"],"wof:lang_x_spoken":["est"],"wof:lastmodified":1596675299,"wof:name":"Lehtmetsa","wof:parent_id":1713306163,"wof:placetype":"locality","wof:repo":"whosonfirst-data-admin-ee","wof:superseded_by":[],"wof:supersedes":[],"wof:tags":[]},"bbox":[23.33167,58.62056,23.33167,58.62056],"geometry":{"coordinates":[23.33167,58.62056],"type":"Point"}}