{"id":1243029961,"type":"Feature","properties":{"edtf:cessation":"uuuu","edtf:inception":"uuuu","geom:area":0,"geom:area_square_m":0,"geom:bbox":"25.41389,58.60139,25.41389,58.60139","geom:latitude":58.60139,"geom:longitude":25.41389,"gn:admin1_code":"20.0","gn:admin2_code":"615.0","gn:admin3_code":"2304.0","gn:asciiname":"Jaelevere","gn:country_code":"EE","gn:dem":47,"gn:feature_class":"P","gn:feature_code":"PPL","gn:geonameid":591992,"gn:latitude":58.60139,"gn:longitude":25.41389,"gn:modification_date":"2017-11-25","gn:name":"Jälevere","gn:population":0,"gn:timezone":"Europe/Tallinn","iso:country":"EE","lbl:bbox":"25.39389,58.58139,25.43389,58.62139","lbl:max_zoom":18,"lbl:min_zoom":13.5,"mz:hierarchy_label":1,"mz:is_current":1,"mz:min_zoom":12,"name:und_x_variant":["Yalevere","Jätevere","Jälevere"],"src:geom":"geonames","wof:belongsto":[85682985,102191581,1713314387,85633135,1713305735],"wof:breaches":[],"wof:concordances":{"gn:id":591992},"wof:coterminous":[1713314387],"wof:country":"EE","wof:geomhash":"0e424d9427af65b3f74758044820bc55","wof:hierarchy":[{"continent_id":102191581,"country_id":85633135,"county_id":1713305735,"localadmin_id":1713314387,"locality_id":1243029961,"region_id":85682985}],"wof:id":1243029961,"wof:lang_x_official":["est"],"wof:lang_x_spoken":["est"],"wof:lastmodified":1596663461,"wof:name":"Jaelevere","wof:parent_id":1713314387,"wof:placetype":"locality","wof:repo":"whosonfirst-data-admin-ee","wof:superseded_by":[],"wof:supersedes":[],"wof:tags":[]},"bbox":[25.41389,58.60139,25.41389,58.60139],"geometry":{"coordinates":[25.41389,58.60139],"type":"Point"}}