{"id":1125941369,"type":"Feature","properties":{"edtf:cessation":"uuuu","edtf:inception":"uuuu","geom:area":0,"geom:area_square_m":0,"geom:bbox":"25.66694,59.15056,25.66694,59.15056","geom:latitude":59.15056,"geom:longitude":25.66694,"gn:country":"EE","gn:fcode":"PPL","gn:population":349,"iso:country":"EE","lbl:bbox":"25.64694,59.13056,25.68694,59.17056","lbl:latitude":59.15056,"lbl:longitude":25.66694,"lbl:max_zoom":17,"lbl:min_zoom":12.5,"mz:hierarchy_label":1,"mz:is_current":1,"mz:min_zoom":11,"mz:note":"Quattroshapes Point Gazetteer import 20170519","name:bul_x_preferred":["Албу"],"name:ceb_x_preferred":["Albu"],"name:eng_x_preferred":["Albu"],"name:est_x_preferred":["Albu"],"name:fas_x_preferred":["البو، استونیا"],"name:fas_x_variant":["البو"],"name:fra_x_preferred":["Albu"],"name:hye_x_preferred":["Ալբու"],"name:nld_x_preferred":["Albu"],"name:pol_x_preferred":["Albu"],"name:spa_x_preferred":["Albu"],"name:swe_x_preferred":["Albu"],"name:ukr_x_preferred":["Албу"],"name:vol_x_preferred":["Albu"],"qs_pg:aaroncc":"EE","qs_pg:gn_country":"EE","qs_pg:gn_fcode":"PPL","qs_pg:gn_id":592551,"qs_pg:gn_pop":349,"qs_pg:name":"Albu","qs_pg:name_adm0":"Eesti","qs_pg:name_adm1":"Järvamaa","qs_pg:photos_9k":1,"qs_pg:photos_9r":1,"qs_pg:photos_all":3,"qs_pg:photos_sr":0,"qs_pg:pop_sr":2,"qs_pg:qs_id":1140450,"qs_pg:qs_pg_placetype":"locality","qs_pg:qs_pg_placetype_gp":"Town","qs_pg:woe_adm0":23424805,"qs_pg:woe_id":841886,"src:geom":"qs_pg","src:lbl_centroid":"qs_pg","src:population":"geonames","woe:adm0_id":23424805,"woe:name_adm0":"Eesti","woe:name_adm1":"Järvamaa","woe:placetype":"Town","wof:belongsto":[85683031,102191581,1713306895,85633135,1713305765],"wof:breaches":[],"wof:concordances":{"gn:id":592551,"gp:id":841886,"qs_pg:id":1140450,"wd:id":"Q2831968"},"wof:coterminous":[1713306895],"wof:country":"EE","wof:created":1497297129,"wof:geomhash":"d424058013575b52861bbeec7c8181c6","wof:hierarchy":[{"continent_id":102191581,"country_id":85633135,"county_id":1713305765,"localadmin_id":1713306895,"locality_id":1125941369,"region_id":85683031}],"wof:id":1125941369,"wof:lang_x_official":["est"],"wof:lang_x_spoken":["est"],"wof:lastmodified":1596676646,"wof:name":"Albu","wof:parent_id":1713306895,"wof:placetype":"locality","wof:population":349,"wof:population_rank":2,"wof:repo":"whosonfirst-data-admin-ee","wof:superseded_by":[],"wof:supersedes":[],"wof:tags":[]},"bbox":[25.66694,59.15056,25.66694,59.15056],"geometry":{"coordinates":[25.66694,59.15056],"type":"Point"}}