{"id":1209893259,"type":"Feature","properties":{"edtf:cessation":"uuuu","edtf:inception":"uuuu","geom:area":0,"geom:area_square_m":0,"geom:bbox":"27.04806,57.93083,27.04806,57.93083","geom:latitude":57.93083,"geom:longitude":27.04806,"gn:admin1_code":"12.0","gn:admin2_code":"622.0","gn:admin3_code":"2197.0","gn:asciiname":"Joosu","gn:country_code":"EE","gn:dem":88,"gn:feature_class":"P","gn:feature_code":"PPL","gn:geonameid":591885,"gn:latitude":57.93083,"gn:longitude":27.04806,"gn:modification_date":"2017-11-25","gn:name":"Joosu","gn:population":0,"gn:timezone":"Europe/Tallinn","iso:country":"EE","lbl:bbox":"27.02806,57.91083,27.06806,57.95083","lbl:max_zoom":18,"lbl:min_zoom":13.5,"mz:hierarchy_label":1,"mz:is_current":1,"mz:min_zoom":12,"name:deu_x_preferred":["Joosu"],"name:est_x_preferred":["Joosu"],"name:fra_x_preferred":["Joosu"],"name:hye_x_preferred":["Յոոսու"],"name:nld_x_preferred":["Joosu"],"name:pol_x_preferred":["Joosu"],"name:sco_x_preferred":["Joosu"],"name:spa_x_preferred":["Joosu"],"name:ukr_x_preferred":["Йоосу"],"name:vol_x_preferred":["Joosu"],"src:geom":"geonames","wof:belongsto":[85682955,102191581,1713312763,85633135,1713305791],"wof:breaches":[],"wof:concordances":{"gn:id":591885,"wk:page":"Joosu"},"wof:coterminous":[1713312763],"wof:country":"EE","wof:geomhash":"2518fa3572437e82e2c8113d63e73436","wof:hierarchy":[{"continent_id":102191581,"country_id":85633135,"county_id":1713305791,"localadmin_id":1713312763,"locality_id":1209893259,"region_id":85682955}],"wof:id":1209893259,"wof:lang_x_official":["est"],"wof:lang_x_spoken":["est"],"wof:lastmodified":1596676967,"wof:name":"Joosu","wof:parent_id":1713312763,"wof:placetype":"locality","wof:repo":"whosonfirst-data-admin-ee","wof:superseded_by":[],"wof:supersedes":[],"wof:tags":[]},"bbox":[27.04806,57.93083,27.04806,57.93083],"geometry":{"coordinates":[27.04806,57.93083],"type":"Point"}}