{"id":1327017011,"type":"Feature","properties":{"edtf:cessation":"uuuu","edtf:inception":"uuuu","geom:area":0,"geom:area_square_m":0,"geom:bbox":"27.48806,57.85722,27.48806,57.85722","geom:latitude":57.85722,"geom:longitude":27.48806,"gn:admin1_code":"21.0","gn:admin2_code":"917.0","gn:admin3_code":"3755.0","gn:asciiname":"Kolikuela","gn:country_code":"EE","gn:dem":83,"gn:feature_class":"P","gn:feature_code":"PPL","gn:geonameid":8620084,"gn:latitude":57.85722,"gn:longitude":27.48806,"gn:modification_date":"2017-11-25","gn:name":"Kõliküla","gn:population":0,"gn:timezone":"Europe/Tallinn","iso:country":"EE","lbl:bbox":"27.46806,57.83722,27.50806,57.87722","lbl:max_zoom":18,"lbl:min_zoom":13.5,"mz:hierarchy_label":1,"mz:is_current":1,"mz:min_zoom":12,"name:deu_x_preferred":["Kõliküla"],"name:est_x_preferred":["Kõliküla"],"name:hye_x_preferred":["Կիլիկյուլա"],"name:pol_x_preferred":["Kõliküla"],"name:spa_x_preferred":["Kõliküla"],"name:ukr_x_preferred":["Килікюла"],"name:und_x_variant":["Kõlli"],"name:vol_x_preferred":["Kõliküla"],"src:geom":"geonames","wof:belongsto":[85682937,102191581,1713316019,85633135,1713305633],"wof:breaches":[],"wof:concordances":{"gn:id":8620084,"wk:page":"K%C3%B5lik%C3%BCla"},"wof:coterminous":[1713316019],"wof:country":"EE","wof:geomhash":"6a3929f62f01cda8d51088cee7e68067","wof:hierarchy":[{"continent_id":102191581,"country_id":85633135,"county_id":1713305633,"localadmin_id":1713316019,"locality_id":1327017011,"region_id":85682937}],"wof:id":1327017011,"wof:lang_x_official":["est"],"wof:lang_x_spoken":["est"],"wof:lastmodified":1596660420,"wof:name":"Kolikuela","wof:parent_id":1713316019,"wof:placetype":"locality","wof:repo":"whosonfirst-data-admin-ee","wof:superseded_by":[],"wof:supersedes":[],"wof:tags":[]},"bbox":[27.48806,57.85722,27.48806,57.85722],"geometry":{"coordinates":[27.48806,57.85722],"type":"Point"}}