{"id":1243519295,"type":"Feature","properties":{"edtf:cessation":"uuuu","edtf:inception":"uuuu","geom:area":0,"geom:area_square_m":0,"geom:bbox":"25.85333,58.28194,25.85333,58.28194","geom:latitude":58.28194,"geom:longitude":25.85333,"gn:admin1_code":"20.0","gn:admin2_code":"899.0","gn:admin3_code":"2570.0","gn:asciiname":"Saarevalla","gn:country_code":"EE","gn:dem":54,"gn:feature_class":"P","gn:feature_code":"PPL","gn:geonameid":8620436,"gn:latitude":58.28194,"gn:longitude":25.85333,"gn:modification_date":"2017-11-25","gn:name":"Saarevalla","gn:population":0,"gn:timezone":"Europe/Tallinn","iso:country":"EE","lbl:bbox":"25.83333,58.26194,25.87333,58.30194","lbl:max_zoom":18,"lbl:min_zoom":13.5,"mz:hierarchy_label":1,"mz:is_current":1,"mz:min_zoom":12,"src:geom":"geonames","wof:belongsto":[85682985,102191581,1713309919,85633135,1713305669],"wof:breaches":[],"wof:concordances":{"gn:id":8620436},"wof:country":"EE","wof:geomhash":"8cc17c34f47c8cb66631f24c31b1bd7e","wof:hierarchy":[{"continent_id":102191581,"country_id":85633135,"county_id":1713305669,"localadmin_id":1713309919,"locality_id":1243519295,"region_id":85682985}],"wof:id":1243519295,"wof:lang_x_official":["est"],"wof:lang_x_spoken":["est"],"wof:lastmodified":1596661267,"wof:name":"Saarevalla","wof:parent_id":1713309919,"wof:placetype":"locality","wof:repo":"whosonfirst-data-admin-ee","wof:superseded_by":[],"wof:supersedes":[],"wof:tags":[]},"bbox":[25.85333,58.28194,25.85333,58.28194],"geometry":{"coordinates":[25.85333,58.28194],"type":"Point"}}