{"id":1209836967,"type":"Feature","properties":{"edtf:cessation":"uuuu","edtf:inception":"uuuu","geom:area":0,"geom:area_square_m":0,"geom:bbox":"23.52861,58.63333,23.52861,58.63333","geom:latitude":58.63333,"geom:longitude":23.52861,"gn:admin1_code":"11.0","gn:admin2_code":"430.0","gn:admin3_code":"1649.0","gn:asciiname":"Sepamaa","gn:country_code":"EE","gn:dem":17,"gn:feature_class":"P","gn:feature_code":"PPL","gn:geonameid":588713,"gn:latitude":58.63333,"gn:longitude":23.52861,"gn:modification_date":"2017-11-25","gn:name":"Sepamaa","gn:population":0,"gn:timezone":"Europe/Tallinn","iso:country":"EE","lbl:bbox":"23.50861,58.61333,23.54861,58.65333","lbl:max_zoom":18,"lbl:min_zoom":13.5,"mz:hierarchy_label":1,"mz:is_current":1,"mz:min_zoom":12,"name:und_x_variant":["Seppama","Sepamaa"],"src:geom":"geonames","wof:belongsto":[85683001,102191581,1713309395,85633135,1713305721],"wof:breaches":[],"wof:concordances":{"gn:id":588713},"wof:country":"EE","wof:geomhash":"d82d9ab5badcd2695fec6a8489832b0c","wof:hierarchy":[{"continent_id":102191581,"country_id":85633135,"county_id":1713305721,"localadmin_id":1713309395,"locality_id":1209836967,"region_id":85683001}],"wof:id":1209836967,"wof:lang_x_official":["est"],"wof:lang_x_spoken":["est"],"wof:lastmodified":1596661686,"wof:name":"Sepamaa","wof:parent_id":1713309395,"wof:placetype":"locality","wof:repo":"whosonfirst-data-admin-ee","wof:superseded_by":[],"wof:supersedes":[],"wof:tags":[]},"bbox":[23.52861,58.63333,23.52861,58.63333],"geometry":{"coordinates":[23.52861,58.63333],"type":"Point"}}