{"id":1226241733,"type":"Feature","properties":{"edtf:cessation":"uuuu","edtf:inception":"uuuu","geom:area":0,"geom:area_square_m":0,"geom:bbox":"26.27083,58.86806,26.27083,58.86806","geom:latitude":58.86806,"geom:longitude":26.27083,"gn:admin1_code":"5.0","gn:admin2_code":"247.0","gn:admin3_code":"8295.0","gn:asciiname":"Tooma","gn:country_code":"EE","gn:dem":82,"gn:feature_class":"P","gn:feature_code":"PPL","gn:geonameid":588235,"gn:latitude":58.86806,"gn:longitude":26.27083,"gn:modification_date":"2017-11-25","gn:name":"Tooma","gn:population":0,"gn:timezone":"Europe/Tallinn","iso:country":"EE","lbl:bbox":"26.25083,58.84806,26.29083,58.88806","lbl:max_zoom":18,"lbl:min_zoom":13.5,"mz:hierarchy_label":1,"mz:is_current":1,"mz:min_zoom":12,"name:deu_x_preferred":["Tooma"],"src:geom":"geonames","wof:belongsto":[85683009,102191581,1713312205,85633135,1713305767],"wof:breaches":[],"wof:concordances":{"gn:id":588235},"wof:coterminous":[1713312205],"wof:country":"EE","wof:geomhash":"f8b15aa80e612b36a70cdf7b2dfabea2","wof:hierarchy":[{"continent_id":102191581,"country_id":85633135,"county_id":1713305767,"localadmin_id":1713312205,"locality_id":1226241733,"region_id":85683009}],"wof:id":1226241733,"wof:lang_x_official":["est"],"wof:lang_x_spoken":["est"],"wof:lastmodified":1596676575,"wof:name":"Tooma","wof:parent_id":1713312205,"wof:placetype":"locality","wof:repo":"whosonfirst-data-admin-ee","wof:superseded_by":[],"wof:supersedes":[],"wof:tags":[]},"bbox":[26.27083,58.86806,26.27083,58.86806],"geometry":{"coordinates":[26.27083,58.86806],"type":"Point"}}