{"id":1125809329,"type":"Feature","properties":{"edtf:cessation":"uuuu","edtf:inception":"uuuu","geom:area":0,"geom:area_square_m":0,"geom:bbox":"23.08917,58.595,23.08917,58.595","geom:latitude":58.595,"geom:longitude":23.08917,"gn:country":"EE","gn:fcode":"PPL","gn:population":0,"iso:country":"EE","lbl:bbox":"23.06917,58.575,23.10917,58.615","lbl:latitude":58.595,"lbl:longitude":23.08917,"lbl:max_zoom":18,"lbl:min_zoom":13,"mz:hierarchy_label":1,"mz:is_current":1,"mz:min_zoom":11,"mz:note":"Quattroshapes Point Gazetteer import 20170519","name:deu_x_preferred":["Koguva"],"name:eng_x_preferred":["Koguva"],"name:est_x_preferred":["Koguva"],"name:fra_x_preferred":["Koguva"],"name:hye_x_preferred":["Կոգուվա"],"name:nld_x_preferred":["Koguva"],"name:pol_x_preferred":["Koguva"],"name:spa_x_preferred":["Koguva"],"name:vol_x_preferred":["Koguva"],"qs_pg:aaroncc":"EE","qs_pg:gn_country":"EE","qs_pg:gn_fcode":"PPL","qs_pg:gn_id":591271,"qs_pg:gn_pop":0,"qs_pg:name":"Koguva","qs_pg:name_adm0":"Eesti","qs_pg:name_adm1":"Saaremaa","qs_pg:photos":62,"qs_pg:photos_1k":13,"qs_pg:photos_9k":1,"qs_pg:photos_9r":2,"qs_pg:photos_all":62,"qs_pg:photos_sr":2,"qs_pg:pop_sr":0,"qs_pg:qs_id":1083343,"qs_pg:qs_pg_placetype":"locality","qs_pg:qs_pg_placetype_gp":"Town","qs_pg:woe_adm0":23424805,"qs_pg:woe_id":843070,"src:geom":"qs_pg","src:lbl_centroid":"qs_pg","src:population":"geonames","woe:adm0_id":23424805,"woe:name_adm0":"Eesti","woe:name_adm1":"Saaremaa","woe:placetype":"Town","wof:belongsto":[85682947,102191581,1713306201,85633135,1713305623],"wof:breaches":[],"wof:concordances":{"gn:id":591271,"gp:id":843070,"qs_pg:id":1083343,"wd:id":"Q744397"},"wof:coterminous":[1713306201],"wof:country":"EE","wof:created":1497291591,"wof:geomhash":"e6ffacfe3ae629dcf867b79d725a71a1","wof:hierarchy":[{"continent_id":102191581,"country_id":85633135,"county_id":1713305623,"localadmin_id":1713306201,"locality_id":1125809329,"region_id":85682947}],"wof:id":1125809329,"wof:lang_x_official":["est"],"wof:lang_x_spoken":["est"],"wof:lastmodified":1596675297,"wof:name":"Koguva","wof:parent_id":1713306201,"wof:placetype":"locality","wof:population":30,"wof:population_rank":1,"wof:repo":"whosonfirst-data-admin-ee","wof:superseded_by":[],"wof:supersedes":[],"wof:tags":[]},"bbox":[23.08917,58.595,23.08917,58.595],"geometry":{"coordinates":[23.08917,58.595],"type":"Point"}}