{"id":1259939009,"type":"Feature","properties":{"edtf:cessation":"uuuu","edtf:inception":"uuuu","geom:area":0,"geom:area_square_m":0,"geom:bbox":"26.91194,57.73806,26.91194,57.73806","geom:latitude":57.73806,"geom:longitude":26.91194,"gn:admin1_code":"21.0","gn:admin2_code":"698.0","gn:admin3_code":"5306.0","gn:asciiname":"Moeldri","gn:country_code":"EE","gn:dem":141,"gn:feature_class":"P","gn:feature_code":"PPL","gn:geonameid":8618682,"gn:latitude":57.73806,"gn:longitude":26.91194,"gn:modification_date":"2017-11-25","gn:name":"Möldri","gn:population":0,"gn:timezone":"Europe/Tallinn","iso:country":"EE","lbl:bbox":"26.89194,57.71806,26.93194,57.75806","lbl:max_zoom":18,"lbl:min_zoom":13.5,"mz:hierarchy_label":1,"mz:is_current":1,"mz:min_zoom":12,"src:geom":"geonames","wof:belongsto":[85682937,102191581,1713314723,85633135,1713305787],"wof:breaches":[],"wof:concordances":{"gn:id":8618682},"wof:coterminous":[1713314723],"wof:country":"EE","wof:geomhash":"985c0dfeaa17909de453e050adfbe8ec","wof:hierarchy":[{"continent_id":102191581,"country_id":85633135,"county_id":1713305787,"localadmin_id":1713314723,"locality_id":1259939009,"region_id":85682937}],"wof:id":1259939009,"wof:lang_x_official":["est"],"wof:lang_x_spoken":["est"],"wof:lastmodified":1596676896,"wof:name":"Moeldri","wof:parent_id":1713314723,"wof:placetype":"locality","wof:repo":"whosonfirst-data-admin-ee","wof:superseded_by":[],"wof:supersedes":[],"wof:tags":[]},"bbox":[26.91194,57.73806,26.91194,57.73806],"geometry":{"coordinates":[26.91194,57.73806],"type":"Point"}}