{"id":1259459933,"type":"Feature","properties":{"edtf:cessation":"uuuu","edtf:inception":"uuuu","geom:area":0,"geom:area_square_m":0,"geom:bbox":"27.36222,58.08972,27.36222,58.08972","geom:latitude":58.08972,"geom:longitude":27.36222,"gn:admin1_code":"12.0","gn:admin2_code":"708.0","gn:admin3_code":"2140.0","gn:asciiname":"Punni","gn:country_code":"EE","gn:dem":47,"gn:feature_class":"P","gn:feature_code":"PPL","gn:geonameid":8620829,"gn:latitude":58.08972,"gn:longitude":27.36222,"gn:modification_date":"2017-11-25","gn:name":"Punni","gn:population":0,"gn:timezone":"Europe/Tallinn","iso:country":"EE","lbl:bbox":"27.34222,58.06972,27.38222,58.10972","lbl:max_zoom":18,"lbl:min_zoom":13.5,"mz:hierarchy_label":1,"mz:is_current":1,"mz:min_zoom":12,"src:geom":"geonames","wof:belongsto":[85682955,102191581,1713310967,85633135,1713305793],"wof:breaches":[],"wof:concordances":{"gn:id":8620829},"wof:country":"EE","wof:geomhash":"324616ae426ad68e9ee25c4d11e18c8a","wof:hierarchy":[{"continent_id":102191581,"country_id":85633135,"county_id":1713305793,"localadmin_id":1713310967,"locality_id":1259459933,"region_id":85682955}],"wof:id":1259459933,"wof:lang_x_official":["est"],"wof:lang_x_spoken":["est"],"wof:lastmodified":1596676994,"wof:name":"Punni","wof:parent_id":1713310967,"wof:placetype":"locality","wof:repo":"whosonfirst-data-admin-ee","wof:superseded_by":[],"wof:supersedes":[],"wof:tags":[]},"bbox":[27.36222,58.08972,27.36222,58.08972],"geometry":{"coordinates":[27.36222,58.08972],"type":"Point"}}