{"id":1326804905,"type":"Feature","properties":{"edtf:cessation":"uuuu","edtf:inception":"uuuu","geom:area":0,"geom:area_square_m":0,"geom:bbox":"25.35611,58.59056,25.35611,58.59056","geom:latitude":58.59056,"geom:longitude":25.35611,"gn:admin1_code":"20.0","gn:admin2_code":"615.0","gn:admin3_code":"9262.0","gn:asciiname":"Tamme","gn:country_code":"EE","gn:dem":42,"gn:feature_class":"P","gn:feature_code":"PPL","gn:geonameid":588394,"gn:latitude":58.59056,"gn:longitude":25.35611,"gn:modification_date":"2017-11-25","gn:name":"Tamme","gn:population":0,"gn:timezone":"Europe/Tallinn","iso:country":"EE","lbl:bbox":"25.33611,58.57056,25.37611,58.61056","lbl:max_zoom":18,"lbl:min_zoom":13.5,"mz:hierarchy_label":1,"mz:is_current":1,"mz:min_zoom":12,"name:ceb_x_preferred":["Tamme"],"name:ces_x_preferred":["Tamme"],"name:deu_x_preferred":["Tamme"],"name:est_x_preferred":["Tamme"],"name:hye_x_preferred":["Տամմե"],"name:rus_x_preferred":["Тамме"],"name:sco_x_preferred":["Tamme"],"name:swe_x_preferred":["Tamme"],"name:ukr_x_preferred":["Тамме"],"name:vol_x_preferred":["Tamme"],"src:geom":"geonames","wof:belongsto":[85682985,102191581,1713313153,85633135,1713305735],"wof:breaches":[],"wof:concordances":{"gn:id":588394},"wof:country":"EE","wof:geomhash":"b2acbb0dfd0f1576b417e1e5dd7ab35a","wof:hierarchy":[{"continent_id":102191581,"country_id":85633135,"county_id":1713305735,"localadmin_id":1713313153,"locality_id":1326804905,"region_id":85682985}],"wof:id":1326804905,"wof:lang_x_official":["est"],"wof:lang_x_spoken":["est"],"wof:lastmodified":1596663459,"wof:name":"Tamme","wof:parent_id":1713313153,"wof:placetype":"locality","wof:repo":"whosonfirst-data-admin-ee","wof:superseded_by":[],"wof:supersedes":[],"wof:tags":[]},"bbox":[25.35611,58.59056,25.35611,58.59056],"geometry":{"coordinates":[25.35611,58.59056],"type":"Point"}}