{"id":1243146197,"type":"Feature","properties":{"edtf:cessation":"uuuu","edtf:inception":"uuuu","geom:area":0,"geom:area_square_m":0,"geom:bbox":"27.04444,57.76111,27.04444,57.76111","geom:latitude":57.76111,"geom:longitude":27.04444,"gn:admin1_code":"21.0","gn:admin2_code":"917.0","gn:admin3_code":"5141.0","gn:asciiname":"Vaestolasto","gn:country_code":"EE","gn:dem":204,"gn:feature_class":"P","gn:feature_code":"PPL","gn:geonameid":8620222,"gn:latitude":57.76111,"gn:longitude":27.04444,"gn:modification_date":"2017-11-25","gn:name":"Vaest천last천","gn:population":0,"gn:timezone":"Europe/Tallinn","iso:country":"EE","lbl:bbox":"27.02444,57.74111,27.06444,57.78111","lbl:max_zoom":18,"lbl:min_zoom":13.5,"mz:hierarchy_label":1,"mz:is_current":1,"mz:min_zoom":12,"name:und_x_variant":["Vaest천last천","Vaestelaste"],"src:geom":"geonames","wof:belongsto":[85682937,102191581,1713315559,85633135,1713305633],"wof:breaches":[],"wof:concordances":{"gn:id":8620222},"wof:country":"EE","wof:geomhash":"d47ae811935d67cb7d57e3884fc6deee","wof:hierarchy":[{"continent_id":102191581,"country_id":85633135,"county_id":1713305633,"localadmin_id":1713315559,"locality_id":1243146197,"region_id":85682937}],"wof:id":1243146197,"wof:lang_x_official":["est"],"wof:lang_x_spoken":["est"],"wof:lastmodified":1596660416,"wof:name":"Vaestolasto","wof:parent_id":1713315559,"wof:placetype":"locality","wof:repo":"whosonfirst-data-admin-ee","wof:superseded_by":[],"wof:supersedes":[],"wof:tags":[]},"bbox":[27.04444,57.76111,27.04444,57.76111],"geometry":{"coordinates":[27.04444,57.76111],"type":"Point"}}