{"id":1125934903,"type":"Feature","properties":{"edtf:cessation":"uuuu","edtf:inception":"uuuu","geom:area":0,"geom:area_square_m":0,"geom:bbox":"26.98139,58.32889,26.98139,58.32889","geom:latitude":58.32889,"geom:longitude":26.98139,"gn:country":"EE","gn:fcode":"PPL","gn:population":484,"iso:country":"EE","lbl:bbox":"26.96139,58.30889,27.00139,58.34889","lbl:latitude":58.32889,"lbl:longitude":26.98139,"lbl:max_zoom":17,"lbl:min_zoom":12.5,"mz:hierarchy_label":1,"mz:is_current":1,"mz:min_zoom":11,"mz:note":"Quattroshapes Point Gazetteer import 20170519","name:bul_x_preferred":["Мелисте"],"name:ceb_x_preferred":["Melliste"],"name:eng_x_preferred":["Melliste"],"name:est_x_preferred":["Melliste"],"name:hye_x_preferred":["Մելլիստե"],"name:nld_x_preferred":["Melliste"],"name:pol_x_preferred":["Melliste"],"name:spa_x_preferred":["Melliste"],"name:swe_x_preferred":["Melliste"],"name:ukr_x_preferred":["Меллісте"],"name:und_x_variant":["Meliste"],"name:vol_x_preferred":["Melliste"],"name:zho_x_preferred":["梅利斯泰"],"qs_pg:aaroncc":"EE","qs_pg:gn_country":"EE","qs_pg:gn_fcode":"PPL","qs_pg:gn_id":590280,"qs_pg:gn_pop":484,"qs_pg:name":"Melliste","qs_pg:name_adm0":"Eesti","qs_pg:name_adm1":"Tartumaa","qs_pg:photos_9r":0,"qs_pg:photos_sr":0,"qs_pg:pop_sr":2,"qs_pg:qs_id":1274153,"qs_pg:qs_pg_placetype":"locality","qs_pg:qs_pg_placetype_gp":"Town","qs_pg:woe_adm0":23424805,"qs_pg:woe_id":843982,"src:geom":"qs_pg","src:lbl_centroid":"qs_pg","src:population":"geonames","woe:adm0_id":23424805,"woe:name_adm0":"Eesti","woe:name_adm1":"Tartumaa","woe:placetype":"Town","wof:belongsto":[85682995,102191581,1713311335,85633135,1713305699],"wof:breaches":[],"wof:concordances":{"gn:id":590280,"gp:id":843982,"qs_pg:id":1274153,"wd:id":"Q3455876"},"wof:coterminous":[1713311335],"wof:country":"EE","wof:created":1497296934,"wof:geomhash":"d6196763bfce4d481b5ba95d4feefcd2","wof:hierarchy":[{"continent_id":102191581,"country_id":85633135,"county_id":1713305699,"localadmin_id":1713311335,"locality_id":1125934903,"region_id":85682995}],"wof:id":1125934903,"wof:lang_x_official":["est"],"wof:lang_x_spoken":["est"],"wof:lastmodified":1596660665,"wof:name":"Melliste","wof:parent_id":1713311335,"wof:placetype":"locality","wof:population":484,"wof:population_rank":2,"wof:repo":"whosonfirst-data-admin-ee","wof:superseded_by":[],"wof:supersedes":[],"wof:tags":[]},"bbox":[26.98139,58.32889,26.98139,58.32889],"geometry":{"coordinates":[26.98139,58.32889],"type":"Point"}}