{"id":1259494895,"type":"Feature","properties":{"edtf:cessation":"uuuu","edtf:inception":"uuuu","geom:area":0,"geom:area_square_m":0,"geom:bbox":"26.86,59.43833,26.86,59.43833","geom:latitude":59.43833,"geom:longitude":26.86,"gn:admin1_code":"8.0","gn:admin2_code":"903.0","gn:admin3_code":"3814.0","gn:asciiname":"Kortsialuse","gn:country_code":"EE","gn:dem":54,"gn:feature_class":"P","gn:feature_code":"PPL","gn:geonameid":793444,"gn:latitude":59.43833,"gn:longitude":26.86,"gn:modification_date":"2017-11-25","gn:name":"Kõrtsialuse","gn:population":0,"gn:timezone":"Europe/Tallinn","iso:country":"EE","lbl:bbox":"26.84,59.41833,26.88,59.45833","lbl:max_zoom":18,"lbl:min_zoom":13.5,"mz:hierarchy_label":1,"mz:is_current":1,"mz:min_zoom":12,"name:deu_x_preferred":["Kõrtsialuse"],"name:est_x_preferred":["Kõrtsialuse"],"name:fra_x_preferred":["Kõrtsialuse"],"name:hye_x_preferred":["Կիռցիալուսե"],"name:nld_x_preferred":["Kõrtsialuse"],"name:pol_x_preferred":["Kõrtsialuse"],"name:vol_x_preferred":["Kõrtsialuse"],"src:geom":"geonames","wof:belongsto":[85683049,102191581,1713307997,85633135,1713305777],"wof:breaches":[],"wof:concordances":{"gn:id":793444,"wk:page":"K%C3%B5rtsialuse"},"wof:coterminous":[1713307997],"wof:country":"EE","wof:geomhash":"7a0ecb20b9b1e5a0d932071c88b61d6e","wof:hierarchy":[{"continent_id":102191581,"country_id":85633135,"county_id":1713305777,"localadmin_id":1713307997,"locality_id":1259494895,"region_id":85683049}],"wof:id":1259494895,"wof:lang_x_official":["est"],"wof:lang_x_spoken":["est"],"wof:lastmodified":1596677932,"wof:name":"Kortsialuse","wof:parent_id":1713307997,"wof:placetype":"locality","wof:repo":"whosonfirst-data-admin-ee","wof:superseded_by":[],"wof:supersedes":[],"wof:tags":[]},"bbox":[26.86,59.43833,26.86,59.43833],"geometry":{"coordinates":[26.86,59.43833],"type":"Point"}}