{"id":1243143095,"type":"Feature","properties":{"edtf:cessation":"uuuu","edtf:inception":"uuuu","geom:area":0,"geom:area_square_m":0,"geom:bbox":"23.30139,58.56222,23.30139,58.56222","geom:latitude":58.56222,"geom:longitude":23.30139,"gn:admin1_code":"14.0","gn:admin2_code":"478.0","gn:admin3_code":"6715.0","gn:asciiname":"Raeegma","gn:country_code":"EE","gn:dem":13,"gn:feature_class":"P","gn:feature_code":"PPL","gn:geonameid":589204,"gn:latitude":58.56222,"gn:longitude":23.30139,"gn:modification_date":"2017-11-25","gn:name":"Räegma","gn:population":0,"gn:timezone":"Europe/Tallinn","iso:country":"EE","lbl:bbox":"23.28139,58.54222,23.32139,58.58222","lbl:max_zoom":18,"lbl:min_zoom":13.5,"mz:hierarchy_label":1,"mz:is_current":1,"mz:min_zoom":12,"name:deu_x_preferred":["Raegma"],"name:est_x_preferred":["Raegma"],"name:hye_x_preferred":["Ռաեգմա"],"name:pol_x_preferred":["Raegma"],"name:spa_x_preferred":["Raegma"],"name:und_x_variant":["Räegmaa","Räegma"],"name:vol_x_preferred":["Raegma"],"src:geom":"geonames","wof:belongsto":[85682947,102191581,1713306239,85633135,1713305623],"wof:breaches":[],"wof:concordances":{"gn:id":589204,"wk:page":"Raegma"},"wof:coterminous":[1713306239],"wof:country":"EE","wof:geomhash":"e64d4ff8238e008d05f2943a2eed75f8","wof:hierarchy":[{"continent_id":102191581,"country_id":85633135,"county_id":1713305623,"localadmin_id":1713306239,"locality_id":1243143095,"region_id":85682947}],"wof:id":1243143095,"wof:lang_x_official":["est"],"wof:lang_x_spoken":["est"],"wof:lastmodified":1596675301,"wof:name":"Raeegma","wof:parent_id":1713306239,"wof:placetype":"locality","wof:repo":"whosonfirst-data-admin-ee","wof:superseded_by":[],"wof:supersedes":[],"wof:tags":[]},"bbox":[23.30139,58.56222,23.30139,58.56222],"geometry":{"coordinates":[23.30139,58.56222],"type":"Point"}}