{"id":1243243693,"type":"Feature","properties":{"edtf:cessation":"uuuu","edtf:inception":"uuuu","geom:area":0,"geom:area_square_m":0,"geom:bbox":"26.95,57.95,26.95,57.95","geom:latitude":57.95,"geom:longitude":26.95,"gn:admin1_code":"12.0","gn:admin2_code":"622.0","gn:admin3_code":"4051.0","gn:asciiname":"Ojasaare","gn:cc2":"EE","gn:country_code":"EE","gn:dem":94,"gn:feature_class":"P","gn:feature_code":"PPL","gn:geonameid":589848,"gn:latitude":57.95,"gn:longitude":26.95,"gn:modification_date":"2017-11-25","gn:name":"Ojasaare","gn:population":0,"gn:timezone":"Europe/Tallinn","iso:country":"EE","lbl:bbox":"26.93,57.93,26.97,57.97","lbl:max_zoom":18,"lbl:min_zoom":13.5,"mz:hierarchy_label":1,"mz:is_current":1,"mz:min_zoom":12,"name:und_x_variant":["Voru/Ojasaare","Oyasare","Ojasaare"],"src:geom":"geonames","wof:belongsto":[85682955,102191581,1713316477,85633135,1713305791],"wof:breaches":[],"wof:concordances":{"gn:id":589848},"wof:country":"EE","wof:geomhash":"6d66306be8b52ced7bf0ca477d24b6d2","wof:hierarchy":[{"continent_id":102191581,"country_id":85633135,"county_id":1713305791,"localadmin_id":1713316477,"locality_id":1243243693,"region_id":85682955}],"wof:id":1243243693,"wof:lang_x_official":["est"],"wof:lang_x_spoken":["est"],"wof:lastmodified":1596676970,"wof:name":"Ojasaare","wof:parent_id":1713316477,"wof:placetype":"locality","wof:repo":"whosonfirst-data-admin-ee","wof:superseded_by":[],"wof:supersedes":[],"wof:tags":[]},"bbox":[26.95,57.95,26.95,57.95],"geometry":{"coordinates":[26.95,57.95],"type":"Point"}}