{"id":1242563059,"type":"Feature","properties":{"edtf:cessation":"uuuu","edtf:inception":"uuuu","geom:area":0,"geom:area_square_m":0,"geom:bbox":"26.38222,58.94028,26.38222,58.94028","geom:latitude":58.94028,"geom:longitude":26.38222,"gn:admin1_code":"8.0","gn:admin2_code":"928.0","gn:admin3_code":"1594.0","gn:asciiname":"Emumaee","gn:country_code":"EE","gn:dem":150,"gn:feature_class":"P","gn:feature_code":"PPL","gn:geonameid":793391,"gn:latitude":58.94028,"gn:longitude":26.38222,"gn:modification_date":"2017-11-25","gn:name":"Emumäe","gn:population":0,"gn:timezone":"Europe/Tallinn","iso:country":"EE","lbl:bbox":"26.36222,58.92028,26.40222,58.96028","lbl:max_zoom":18,"lbl:min_zoom":13.5,"mz:hierarchy_label":1,"mz:is_current":1,"mz:min_zoom":12,"name:und_x_variant":["Emumägi","Emumäe"],"src:geom":"geonames","wof:belongsto":[85683049,102191581,1713312695,85633135,1713305769],"wof:breaches":[],"wof:concordances":{"gn:id":793391},"wof:coterminous":[1713312695],"wof:country":"EE","wof:geomhash":"aa557d03f22cfd6741902e30260987c0","wof:hierarchy":[{"continent_id":102191581,"country_id":85633135,"county_id":1713305769,"localadmin_id":1713312695,"locality_id":1242563059,"region_id":85683049}],"wof:id":1242563059,"wof:lang_x_official":["est"],"wof:lang_x_spoken":["est"],"wof:lastmodified":1596676539,"wof:name":"Emumaee","wof:parent_id":1713312695,"wof:placetype":"locality","wof:repo":"whosonfirst-data-admin-ee","wof:superseded_by":[],"wof:supersedes":[],"wof:tags":[]},"bbox":[26.38222,58.94028,26.38222,58.94028],"geometry":{"coordinates":[26.38222,58.94028],"type":"Point"}}