{"id":1126037783,"type":"Feature","properties":{"edtf:cessation":"uuuu","edtf:inception":"uuuu","geom:area":0,"geom:area_square_m":0,"geom:bbox":"26.78167,58.16472,26.78167,58.16472","geom:latitude":58.16472,"geom:longitude":26.78167,"gn:country":"EE","gn:fcode":"PPL","gn:population":100,"iso:country":"EE","lbl:bbox":"26.76167,58.14472,26.80167,58.18472","lbl:latitude":58.16472,"lbl:longitude":26.78167,"lbl:max_zoom":18,"lbl:min_zoom":13,"mz:hierarchy_label":1,"mz:is_current":1,"mz:min_zoom":11,"mz:note":"Quattroshapes Point Gazetteer import 20170519","name:deu_x_preferred":["Prangli"],"name:eng_x_preferred":["Prangli"],"name:est_x_preferred":["Prangli küla"],"name:est_x_variant":["Prangli"],"name:hye_x_preferred":["Պռանգլի"],"name:nld_x_preferred":["Prangli"],"name:pol_x_preferred":["Prangli"],"name:rus_x_preferred":["Прангли"],"name:sco_x_preferred":["Prangli"],"name:spa_x_preferred":["Prangli"],"name:ukr_x_preferred":["Пранглі"],"name:und_x_variant":["Myza Vana-Prangli"],"name:vol_x_preferred":["Prangli küla"],"qs_pg:aaroncc":"EE","qs_pg:gn_country":"EE","qs_pg:gn_fcode":"PPL","qs_pg:gn_id":589344,"qs_pg:gn_pop":100,"qs_pg:name":"Prangli","qs_pg:name_adm0":"Eesti","qs_pg:name_adm1":"Põlvamaa","qs_pg:photos_9k":1,"qs_pg:photos_9r":1,"qs_pg:photos_all":2,"qs_pg:photos_sr":0,"qs_pg:pop_sr":1,"qs_pg:qs_id":966872,"qs_pg:qs_pg_placetype":"locality","qs_pg:qs_pg_placetype_gp":"Town","qs_pg:woe_adm0":23424805,"qs_pg:woe_id":844862,"src:geom":"qs_pg","src:lbl_centroid":"qs_pg","src:population":"geonames","woe:adm0_id":23424805,"woe:name_adm0":"Eesti","woe:name_adm1":"Põlvamaa","woe:placetype":"Town","wof:belongsto":[85682955,102191581,1713312707,85633135,1713305789],"wof:breaches":[],"wof:concordances":{"gn:id":589344,"gp:id":844862,"qs_pg:id":966872,"wd:id":"Q3464761"},"wof:coterminous":[1713312707],"wof:country":"EE","wof:created":1497301906,"wof:geomhash":"29f928aa0ffd76898259d6f923138dde","wof:hierarchy":[{"continent_id":102191581,"country_id":85633135,"county_id":1713305789,"localadmin_id":1713312707,"locality_id":1126037783,"region_id":85682955}],"wof:id":1126037783,"wof:lang_x_official":["est"],"wof:lang_x_spoken":["est"],"wof:lastmodified":1596676798,"wof:name":"Prangli","wof:parent_id":1713312707,"wof:placetype":"locality","wof:population":100,"wof:population_rank":1,"wof:repo":"whosonfirst-data-admin-ee","wof:superseded_by":[],"wof:supersedes":[],"wof:tags":[]},"bbox":[26.78167,58.16472,26.78167,58.16472],"geometry":{"coordinates":[26.78167,58.16472],"type":"Point"}}