{"id":1226730959,"type":"Feature","properties":{"edtf:cessation":"uuuu","edtf:inception":"uuuu","geom:area":0,"geom:area_square_m":0,"geom:bbox":"24.90556,58.1525,24.90556,58.1525","geom:latitude":58.1525,"geom:longitude":24.90556,"gn:admin1_code":"11.0","gn:admin2_code":"712.0","gn:admin3_code":"4440.0","gn:asciiname":"Surtsi","gn:country_code":"EE","gn:dem":61,"gn:feature_class":"P","gn:feature_code":"PPL","gn:geonameid":588542,"gn:latitude":58.1525,"gn:longitude":24.90556,"gn:modification_date":"2017-11-25","gn:name":"Surtsi","gn:population":0,"gn:timezone":"Europe/Tallinn","iso:country":"EE","lbl:bbox":"24.88556,58.1325,24.92556,58.1725","lbl:max_zoom":18,"lbl:min_zoom":13.5,"mz:hierarchy_label":1,"mz:is_current":1,"mz:min_zoom":12,"src:geom":"geonames","wof:belongsto":[85682981,102191581,1713309667,85633135,1713305705],"wof:breaches":[],"wof:concordances":{"gn:id":588542},"wof:country":"EE","wof:geomhash":"394cc4cb2f83043d1c881f80460585f1","wof:hierarchy":[{"continent_id":102191581,"country_id":85633135,"county_id":1713305705,"localadmin_id":1713309667,"locality_id":1226730959,"region_id":85682981}],"wof:id":1226730959,"wof:lang_x_official":["est"],"wof:lang_x_spoken":["est"],"wof:lastmodified":1596677737,"wof:name":"Surtsi","wof:parent_id":1713309667,"wof:placetype":"locality","wof:repo":"whosonfirst-data-admin-ee","wof:superseded_by":[],"wof:supersedes":[],"wof:tags":[]},"bbox":[24.90556,58.1525,24.90556,58.1525],"geometry":{"coordinates":[24.90556,58.1525],"type":"Point"}}