{"id":1276416839,"type":"Feature","properties":{"edtf:cessation":"uuuu","edtf:inception":"uuuu","geom:area":0,"geom:area_square_m":0,"geom:bbox":"24.65083,58.87083,24.65083,58.87083","geom:latitude":58.87083,"geom:longitude":24.65083,"gn:admin1_code":"13.0","gn:admin2_code":"668.0","gn:admin3_code":"4924.0","gn:asciiname":"Metskuela","gn:country_code":"EE","gn:dem":51,"gn:feature_class":"P","gn:feature_code":"PPL","gn:geonameid":590223,"gn:latitude":58.87083,"gn:longitude":24.65083,"gn:modification_date":"2017-11-25","gn:name":"Metsküla","gn:population":0,"gn:timezone":"Europe/Tallinn","iso:country":"EE","lbl:bbox":"24.63083,58.85083,24.67083,58.89083","lbl:max_zoom":18,"lbl:min_zoom":13.5,"mz:hierarchy_label":1,"mz:is_current":1,"mz:min_zoom":12,"name:und_x_variant":["Metskyula","Metsküla"],"src:geom":"geonames","wof:belongsto":[85683013,102191581,1713311409,85633135,1713305711],"wof:breaches":[],"wof:concordances":{"gn:id":590223,"wk:page":"Metsk%C3%BCla%2C_Raikk%C3%BCla_Parish"},"wof:coterminous":[1713311409],"wof:country":"EE","wof:geomhash":"223d89710c0945cd9c9f996b52f2208f","wof:hierarchy":[{"continent_id":102191581,"country_id":85633135,"county_id":1713305711,"localadmin_id":1713311409,"locality_id":1276416839,"region_id":85683013}],"wof:id":1276416839,"wof:lang_x_official":["est"],"wof:lang_x_spoken":["est"],"wof:lastmodified":1596676726,"wof:name":"Metskuela","wof:parent_id":1713311409,"wof:placetype":"locality","wof:repo":"whosonfirst-data-admin-ee","wof:superseded_by":[],"wof:supersedes":[],"wof:tags":[]},"bbox":[24.65083,58.87083,24.65083,58.87083],"geometry":{"coordinates":[24.65083,58.87083],"type":"Point"}}