{"id":1125992077,"type":"Feature","properties":{"edtf:cessation":"uuuu","edtf:inception":"uuuu","geom:area":0,"geom:area_square_m":0,"geom:bbox":"26.43472,58.01944,26.43472,58.01944","geom:latitude":58.01944,"geom:longitude":26.43472,"gn:country":"EE","gn:fcode":"PPL","gn:population":362,"iso:country":"EE","lbl:bbox":"26.41472,57.99944,26.45472,58.03944","lbl:latitude":58.01944,"lbl:longitude":26.43472,"lbl:max_zoom":17,"lbl:min_zoom":12.5,"mz:hierarchy_label":1,"mz:is_current":1,"mz:min_zoom":11,"mz:note":"Quattroshapes Point Gazetteer import 20170519","qs_pg:aaroncc":"EE","qs_pg:gn_country":"EE","qs_pg:gn_fcode":"PPL","qs_pg:gn_id":794564,"qs_pg:gn_pop":362,"qs_pg:name":"Sihva","qs_pg:name_adm0":"Eesti","qs_pg:name_adm1":"Valgamaa","qs_pg:photos":15,"qs_pg:photos_1k":3,"qs_pg:photos_9k":1,"qs_pg:photos_9r":1,"qs_pg:photos_all":15,"qs_pg:photos_sr":1,"qs_pg:pop_sr":2,"qs_pg:qs_id":1353615,"qs_pg:qs_pg_placetype":"locality","qs_pg:qs_pg_placetype_gp":"Town","qs_pg:woe_adm0":23424805,"qs_pg:woe_id":845483,"src:geom":"qs_pg","src:lbl_centroid":"qs_pg","src:population":"geonames","woe:adm0_id":23424805,"woe:name_adm0":"Eesti","woe:name_adm1":"Valgamaa","woe:placetype":"Town","wof:belongsto":[85682941,102191581,1713309835,85633135,1713305759],"wof:breaches":[],"wof:concordances":{"gn:id":794564,"gp:id":845483,"qs_pg:id":1353615},"wof:coterminous":[1713309835],"wof:country":"EE","wof:created":1497299109,"wof:geomhash":"b9d09298990e4e049a709c34e77bd557","wof:hierarchy":[{"continent_id":102191581,"country_id":85633135,"county_id":1713305759,"localadmin_id":1713309835,"locality_id":1125992077,"region_id":85682941}],"wof:id":1125992077,"wof:lang_x_official":["est"],"wof:lang_x_spoken":["est"],"wof:lastmodified":1596661878,"wof:name":"Sihva","wof:parent_id":1713309835,"wof:placetype":"locality","wof:population":362,"wof:population_rank":2,"wof:repo":"whosonfirst-data-admin-ee","wof:superseded_by":[],"wof:supersedes":[],"wof:tags":[]},"bbox":[26.43472,58.01944,26.43472,58.01944],"geometry":{"coordinates":[26.43472,58.01944],"type":"Point"}}