{"id":1310184485,"type":"Feature","properties":{"edtf:cessation":"uuuu","edtf:inception":"uuuu","geom:area":0,"geom:area_square_m":0,"geom:bbox":"24.56222,58.86778,24.56222,58.86778","geom:latitude":58.86778,"geom:longitude":24.56222,"gn:admin1_code":"13.0","gn:admin2_code":"503.0","gn:admin3_code":"4919.0","gn:asciiname":"Jaaniveski","gn:country_code":"EE","gn:dem":36,"gn:feature_class":"P","gn:feature_code":"PPL","gn:geonameid":795028,"gn:latitude":58.86778,"gn:longitude":24.56222,"gn:modification_date":"2017-11-25","gn:name":"Jaaniveski","gn:population":0,"gn:timezone":"Europe/Tallinn","iso:country":"EE","lbl:bbox":"24.54222,58.84778,24.58222,58.88778","lbl:max_zoom":18,"lbl:min_zoom":13.5,"mz:hierarchy_label":1,"mz:is_current":1,"mz:min_zoom":12,"name:est_x_preferred":["Jaaniveski"],"name:fra_x_preferred":["Jaaniveski"],"name:hye_x_preferred":["Յաանիվեսկի"],"name:pol_x_preferred":["Jaaniveski"],"name:sco_x_preferred":["Jaaniveski"],"name:spa_x_preferred":["Jaaniveski"],"name:urd_x_preferred":["جانوسکی"],"name:vol_x_preferred":["Jaaniveski"],"src:geom":"geonames","wof:belongsto":[85683013,102191581,1713311193,85633135,1713305747],"wof:breaches":[],"wof:concordances":{"gn:id":795028,"wk:page":"Jaaniveski"},"wof:coterminous":[1713311345],"wof:country":"EE","wof:geomhash":"3a8a7db2d8f0e7fdac440cd17b27046c","wof:hierarchy":[{"continent_id":102191581,"country_id":85633135,"county_id":1713305747,"localadmin_id":1713311193,"locality_id":1310184485,"region_id":85683013}],"wof:id":1310184485,"wof:lang_x_official":["est"],"wof:lang_x_spoken":["est"],"wof:lastmodified":1596662840,"wof:name":"Jaaniveski","wof:parent_id":1713311193,"wof:placetype":"locality","wof:repo":"whosonfirst-data-admin-ee","wof:superseded_by":[],"wof:supersedes":[],"wof:tags":[]},"bbox":[24.56222,58.86778,24.56222,58.86778],"geometry":{"coordinates":[24.56222,58.86778],"type":"Point"}}