{"id":1225809645,"type":"Feature","properties":{"edtf:cessation":"uuuu","edtf:inception":"uuuu","geom:area":0,"geom:area_square_m":0,"geom:bbox":"26.96722,57.77889,26.96722,57.77889","geom:latitude":57.77889,"geom:longitude":26.96722,"gn:admin1_code":"21.0","gn:admin2_code":"917.0","gn:admin3_code":"5450.0","gn:asciiname":"Liinamaee","gn:country_code":"EE","gn:dem":133,"gn:feature_class":"P","gn:feature_code":"PPL","gn:geonameid":8620209,"gn:latitude":57.77889,"gn:longitude":26.96722,"gn:modification_date":"2017-11-25","gn:name":"Liinamäe","gn:population":0,"gn:timezone":"Europe/Tallinn","iso:country":"EE","lbl:bbox":"26.94722,57.75889,26.98722,57.79889","lbl:max_zoom":18,"lbl:min_zoom":13.5,"mz:hierarchy_label":1,"mz:is_current":1,"mz:min_zoom":12,"name:und_x_variant":["Liinamäe","Linnamäe"],"src:geom":"geonames","wof:belongsto":[85682937,102191581,1713316139,85633135,1713305633],"wof:breaches":[],"wof:concordances":{"gn:id":8620209},"wof:country":"EE","wof:geomhash":"71ea29a2df312b8db99ade8039b72d97","wof:hierarchy":[{"continent_id":102191581,"country_id":85633135,"county_id":1713305633,"localadmin_id":1713316139,"locality_id":1225809645,"region_id":85682937}],"wof:id":1225809645,"wof:lang_x_official":["est"],"wof:lang_x_spoken":["est"],"wof:lastmodified":1596660406,"wof:name":"Liinamaee","wof:parent_id":1713316139,"wof:placetype":"locality","wof:repo":"whosonfirst-data-admin-ee","wof:superseded_by":[],"wof:supersedes":[],"wof:tags":[]},"bbox":[26.96722,57.77889,26.96722,57.77889],"geometry":{"coordinates":[26.96722,57.77889],"type":"Point"}}