{"id":1126105595,"type":"Feature","properties":{"edtf:cessation":"uuuu","edtf:inception":"uuuu","geom:area":0,"geom:area_square_m":0,"geom:bbox":"23.83556,58.36333,23.83556,58.36333","geom:latitude":58.36333,"geom:longitude":23.83556,"gn:country":"EE","gn:fcode":"PPLX","gn:population":134,"iso:country":"EE","lbl:bbox":"23.83056,58.35833,23.84056,58.36833","lbl:latitude":58.36333,"lbl:longitude":23.83556,"lbl:max_zoom":18,"mz:hierarchy_label":1,"mz:is_current":1,"mz:min_zoom":15,"mz:note":"Quattroshapes Point Gazetteer import 20170519","name:ben_x_preferred":["সারে"],"name:ceb_x_preferred":["Saare"],"name:deu_x_preferred":["Saare"],"name:est_x_preferred":["Saare"],"name:hin_x_preferred":["सारे"],"name:hye_x_preferred":["Սաառե"],"name:nld_x_preferred":["Saare"],"name:pol_x_preferred":["Saare"],"name:por_x_preferred":["Saare"],"name:ron_x_preferred":["Saare"],"name:rus_x_preferred":["Сааре"],"name:swe_x_preferred":["Saare"],"name:ukr_x_preferred":["Сааре"],"name:und_x_variant":["Sare"],"name:vol_x_preferred":["Saare"],"qs_pg:aaroncc":"EE","qs_pg:gn_country":"EE","qs_pg:gn_fcode":"PPLX","qs_pg:gn_id":588891,"qs_pg:gn_pop":134,"qs_pg:name":"Saare","qs_pg:photos_9r":0,"qs_pg:photos_sr":0,"qs_pg:pop_sr":1,"qs_pg:qs_id":550127,"qs_pg:qs_pg_placetype":"neighbourhood","src:geom":"qs_pg","src:lbl_centroid":"qs_pg","src:population":"geonames","wof:belongsto":[102191581,1713308955,85633135,1713305721,85683001],"wof:breaches":[],"wof:concordances":{"gn:id":588891,"qs_pg:id":550127},"wof:country":"EE","wof:created":1497316870,"wof:geomhash":"27c1eead9c77d42d96aa1fe2a39bd9a4","wof:hierarchy":[{"continent_id":102191581,"country_id":85633135,"county_id":1713305721,"localadmin_id":1713308955,"locality_id":-1,"neighbourhood_id":1126105595,"region_id":85683001}],"wof:id":1126105595,"wof:lastmodified":1636502244,"wof:name":"Saare","wof:parent_id":-1,"wof:placetype":"neighbourhood","wof:population":134,"wof:population_rank":1,"wof:repo":"whosonfirst-data-admin-ee","wof:superseded_by":[],"wof:supersedes":[],"wof:tags":[]},"bbox":[23.83556,58.36333,23.83556,58.36333],"geometry":{"coordinates":[23.83556,58.36333],"type":"Point"}}