{"id":1242848449,"type":"Feature","properties":{"edtf:cessation":"uuuu","edtf:inception":"uuuu","geom:area":0,"geom:area_square_m":0,"geom:bbox":"26.78417,57.74222,26.78417,57.74222","geom:latitude":57.74222,"geom:longitude":26.78417,"gn:admin1_code":"21.0","gn:admin2_code":"698.0","gn:admin3_code":"7930.0","gn:asciiname":"Saenna","gn:country_code":"EE","gn:dem":78,"gn:feature_class":"P","gn:feature_code":"PPL","gn:geonameid":588796,"gn:latitude":57.74222,"gn:longitude":26.78417,"gn:modification_date":"2017-11-25","gn:name":"Sänna","gn:population":0,"gn:timezone":"Europe/Tallinn","iso:country":"EE","lbl:bbox":"26.76417,57.72222,26.80417,57.76222","lbl:max_zoom":18,"lbl:min_zoom":13.5,"mz:hierarchy_label":1,"mz:is_current":1,"mz:min_zoom":12,"name:eng_x_preferred":["Sänna"],"name:est_x_preferred":["Sänna"],"name:hye_x_preferred":["Սեննա"],"name:myv_x_preferred":["Сянна"],"name:pol_x_preferred":["Sänna"],"name:rus_x_preferred":["Сянна"],"name:spa_x_preferred":["Sänna"],"name:ukr_x_preferred":["Сянна"],"name:und_x_variant":["Syanna","Sänna Asundus","Myza Syanna"],"name:vol_x_preferred":["Sänna"],"src:geom":"geonames","wof:belongsto":[85682937,102191581,1713314761,85633135,1713305787],"wof:breaches":[],"wof:concordances":{"gn:id":588796,"wk:page":"S%C3%A4nna"},"wof:coterminous":[1713314761],"wof:country":"EE","wof:geomhash":"9f68ddd468460290aabd96e6eb10a48c","wof:hierarchy":[{"continent_id":102191581,"country_id":85633135,"county_id":1713305787,"localadmin_id":1713314761,"locality_id":1242848449,"region_id":85682937}],"wof:id":1242848449,"wof:lang_x_official":["est"],"wof:lang_x_spoken":["est"],"wof:lastmodified":1596676869,"wof:name":"Saenna","wof:parent_id":1713314761,"wof:placetype":"locality","wof:repo":"whosonfirst-data-admin-ee","wof:superseded_by":[],"wof:supersedes":[],"wof:tags":[]},"bbox":[26.78417,57.74222,26.78417,57.74222],"geometry":{"coordinates":[26.78417,57.74222],"type":"Point"}}