{"id":1242742267,"type":"Feature","properties":{"edtf:cessation":"uuuu","edtf:inception":"uuuu","geom:area":0,"geom:area_square_m":0,"geom:bbox":"26.91778,57.69917,26.91778,57.69917","geom:latitude":57.69917,"geom:longitude":26.91778,"gn:admin1_code":"21.0","gn:admin2_code":"698.0","gn:admin3_code":"1791.0","gn:asciiname":"Heibri","gn:country_code":"EE","gn:dem":144,"gn:feature_class":"P","gn:feature_code":"PPL","gn:geonameid":794337,"gn:latitude":57.69917,"gn:longitude":26.91778,"gn:modification_date":"2017-11-25","gn:name":"Heibri","gn:population":0,"gn:timezone":"Europe/Tallinn","iso:country":"EE","lbl:bbox":"26.89778,57.67917,26.93778,57.71917","lbl:max_zoom":18,"lbl:min_zoom":13.5,"mz:hierarchy_label":1,"mz:is_current":1,"mz:min_zoom":12,"name:est_x_preferred":["Heibri"],"name:hye_x_preferred":["Հեիբռի"],"name:myv_x_preferred":["Хейбри"],"name:pol_x_preferred":["Heibri"],"name:spa_x_preferred":["Heibri"],"name:ukr_x_preferred":["Хейбрі"],"name:vol_x_preferred":["Heibri"],"src:geom":"geonames","wof:belongsto":[85682937,102191581,1713315253,85633135,1713305787],"wof:breaches":[],"wof:concordances":{"gn:id":794337,"wk:page":"Heibri"},"wof:coterminous":[1713315253],"wof:country":"EE","wof:geomhash":"378534a00094347454919281574f4686","wof:hierarchy":[{"continent_id":102191581,"country_id":85633135,"county_id":1713305787,"localadmin_id":1713315253,"locality_id":1242742267,"region_id":85682937}],"wof:id":1242742267,"wof:lang_x_official":["est"],"wof:lang_x_spoken":["est"],"wof:lastmodified":1596676882,"wof:name":"Heibri","wof:parent_id":1713315253,"wof:placetype":"locality","wof:repo":"whosonfirst-data-admin-ee","wof:superseded_by":[],"wof:supersedes":[],"wof:tags":[]},"bbox":[26.91778,57.69917,26.91778,57.69917],"geometry":{"coordinates":[26.91778,57.69917],"type":"Point"}}