{"id":1293870041,"type":"Feature","properties":{"edtf:cessation":"uuuu","edtf:inception":"uuuu","geom:area":0,"geom:area_square_m":0,"geom:bbox":"24.87167,58.94694,24.87167,58.94694","geom:latitude":58.94694,"geom:longitude":24.87167,"gn:admin1_code":"13.0","gn:admin2_code":"293.0","gn:admin3_code":"7353.0","gn:asciiname":"Saksa","gn:country_code":"EE","gn:dem":68,"gn:feature_class":"P","gn:feature_code":"PPL","gn:geonameid":588834,"gn:latitude":58.94694,"gn:longitude":24.87167,"gn:modification_date":"2017-11-25","gn:name":"Saksa","gn:population":0,"gn:timezone":"Europe/Tallinn","iso:country":"EE","lbl:bbox":"24.85167,58.92694,24.89167,58.96694","lbl:max_zoom":18,"lbl:min_zoom":13.5,"mz:hierarchy_label":1,"mz:is_current":1,"mz:min_zoom":12,"name:est_x_preferred":["Saksa küla"],"name:hye_x_preferred":["Սակսա"],"name:pol_x_preferred":["Saksa"],"name:sco_x_preferred":["Saksa"],"name:spa_x_preferred":["Saksa"],"name:vol_x_preferred":["Saksa küla"],"src:geom":"geonames","wof:belongsto":[85683013,102191581,1713311261,85633135,1713305713],"wof:breaches":[],"wof:concordances":{"gn:id":588834,"wk:page":"Saksa"},"wof:coterminous":[1713311261],"wof:country":"EE","wof:geomhash":"ad5917d237e4f29b3ef9f8494113981c","wof:hierarchy":[{"continent_id":102191581,"country_id":85633135,"county_id":1713305713,"localadmin_id":1713311261,"locality_id":1293870041,"region_id":85683013}],"wof:id":1293870041,"wof:lang_x_official":["est"],"wof:lang_x_spoken":["est"],"wof:lastmodified":1596676747,"wof:name":"Saksa","wof:parent_id":1713311261,"wof:placetype":"locality","wof:repo":"whosonfirst-data-admin-ee","wof:superseded_by":[],"wof:supersedes":[],"wof:tags":[]},"bbox":[24.87167,58.94694,24.87167,58.94694],"geometry":{"coordinates":[24.87167,58.94694],"type":"Point"}}