{"id":1276887963,"type":"Feature","properties":{"edtf:cessation":"uuuu","edtf:inception":"uuuu","geom:area":0,"geom:area_square_m":0,"geom:bbox":"25.27944,59.27167,25.27944,59.27167","geom:latitude":59.27167,"geom:longitude":25.27944,"gn:admin1_code":"1.0","gn:admin2_code":"141.0","gn:admin3_code":"4672.0","gn:asciiname":"Luekati","gn:country_code":"EE","gn:dem":59,"gn:feature_class":"P","gn:feature_code":"PPL","gn:geonameid":590487,"gn:latitude":59.27167,"gn:longitude":25.27944,"gn:modification_date":"2017-11-25","gn:name":"Lükati","gn:population":0,"gn:timezone":"Europe/Tallinn","iso:country":"EE","lbl:bbox":"25.25944,59.25167,25.29944,59.29167","lbl:max_zoom":18,"lbl:min_zoom":13.5,"mz:hierarchy_label":1,"mz:is_current":1,"mz:min_zoom":12,"name:est_x_preferred":["Lükati"],"name:fra_x_preferred":["Lükati"],"name:hye_x_preferred":["Լյուկատի"],"name:nld_x_preferred":["Lükati"],"name:pol_x_preferred":["Lükati"],"name:sco_x_preferred":["Lükati"],"name:slk_x_preferred":["Lükati"],"name:spa_x_preferred":["Lükati"],"name:und_x_variant":["Lyukati"],"name:vol_x_preferred":["Lükati"],"src:geom":"geonames","wof:belongsto":[85683055,102191581,1713315185,85633135,1713305749],"wof:breaches":[],"wof:concordances":{"gn:id":590487,"wk:page":"L%C3%BCkati"},"wof:coterminous":[1713315185],"wof:country":"EE","wof:geomhash":"2a8c3971f3ff2a9c9cce483f1b911b2c","wof:hierarchy":[{"continent_id":102191581,"country_id":85633135,"county_id":1713305749,"localadmin_id":1713315185,"locality_id":1276887963,"region_id":85683055}],"wof:id":1276887963,"wof:lang_x_official":["est"],"wof:lang_x_spoken":["est"],"wof:lastmodified":1596662803,"wof:name":"Luekati","wof:parent_id":1713315185,"wof:placetype":"locality","wof:repo":"whosonfirst-data-admin-ee","wof:superseded_by":[],"wof:supersedes":[],"wof:tags":[]},"bbox":[25.27944,59.27167,25.27944,59.27167],"geometry":{"coordinates":[25.27944,59.27167],"type":"Point"}}