{"id":1327231915,"type":"Feature","properties":{"edtf:cessation":"uuuu","edtf:inception":"uuuu","geom:area":0,"geom:area_square_m":0,"geom:bbox":"26.08639,58.94861,26.08639,58.94861","geom:latitude":58.94861,"geom:longitude":26.08639,"gn:admin1_code":"4.0","gn:admin2_code":"255.0","gn:admin3_code":"9638.0","gn:asciiname":"Vaeinjaerve","gn:country_code":"EE","gn:dem":89,"gn:feature_class":"P","gn:feature_code":"PPL","gn:geonameid":793302,"gn:latitude":58.94861,"gn:longitude":26.08639,"gn:modification_date":"2017-11-25","gn:name":"Väinjärve","gn:population":0,"gn:timezone":"Europe/Tallinn","iso:country":"EE","lbl:bbox":"26.06639,58.92861,26.10639,58.96861","lbl:max_zoom":18,"lbl:min_zoom":13.5,"mz:hierarchy_label":1,"mz:is_current":1,"mz:min_zoom":12,"name:est_x_preferred":["Väinjärve"],"name:hye_x_preferred":["Վեինյեռվե"],"name:pol_x_preferred":["Väinjärve"],"name:spa_x_preferred":["Väinjärve"],"name:ukr_x_preferred":["Вяйньярве"],"name:vol_x_preferred":["Väinjärve"],"src:geom":"geonames","wof:belongsto":[85683031,102191581,1713307105,85633135,1713305765],"wof:breaches":[],"wof:concordances":{"gn:id":793302,"wk:page":"V%C3%A4inj%C3%A4rve"},"wof:coterminous":[1713307105],"wof:country":"EE","wof:geomhash":"a7c8575bdf973837c8dfcec3bfeb18b0","wof:hierarchy":[{"continent_id":102191581,"country_id":85633135,"county_id":1713305765,"localadmin_id":1713307105,"locality_id":1327231915,"region_id":85683031}],"wof:id":1327231915,"wof:lang_x_official":["est"],"wof:lang_x_spoken":["est"],"wof:lastmodified":1596676651,"wof:name":"Vaeinjaerve","wof:parent_id":1713307105,"wof:placetype":"locality","wof:repo":"whosonfirst-data-admin-ee","wof:superseded_by":[],"wof:supersedes":[],"wof:tags":[]},"bbox":[26.08639,58.94861,26.08639,58.94861],"geometry":{"coordinates":[26.08639,58.94861],"type":"Point"}}