{"id":1293364743,"type":"Feature","properties":{"edtf:cessation":"uuuu","edtf:inception":"uuuu","geom:area":0,"geom:area_square_m":0,"geom:bbox":"25.87528,58.15111,25.87528,58.15111","geom:latitude":58.15111,"geom:longitude":25.87528,"gn:admin1_code":"20.0","gn:admin2_code":"899.0","gn:admin3_code":"7076.0","gn:asciiname":"Laanekuru","gn:country_code":"EE","gn:dem":71,"gn:feature_class":"P","gn:feature_code":"PPL","gn:geonameid":8620459,"gn:latitude":58.15111,"gn:longitude":25.87528,"gn:modification_date":"2017-11-25","gn:name":"Laanekuru","gn:population":0,"gn:timezone":"Europe/Tallinn","iso:country":"EE","lbl:bbox":"25.85528,58.13111,25.89528,58.17111","lbl:max_zoom":18,"lbl:min_zoom":13.5,"mz:hierarchy_label":1,"mz:is_current":1,"mz:min_zoom":12,"name:und_x_variant":["Räägi"],"src:geom":"geonames","wof:belongsto":[85682985,102191581,1713313925,85633135,1713305669],"wof:breaches":[],"wof:concordances":{"gn:id":8620459},"wof:country":"EE","wof:geomhash":"cee046fe7090a5c01d07f13311a68144","wof:hierarchy":[{"continent_id":102191581,"country_id":85633135,"county_id":1713305669,"localadmin_id":1713313925,"locality_id":1293364743,"region_id":85682985}],"wof:id":1293364743,"wof:lang_x_official":["est"],"wof:lang_x_spoken":["est"],"wof:lastmodified":1596661260,"wof:name":"Laanekuru","wof:parent_id":1713313925,"wof:placetype":"locality","wof:repo":"whosonfirst-data-admin-ee","wof:superseded_by":[],"wof:supersedes":[],"wof:tags":[]},"bbox":[25.87528,58.15111,25.87528,58.15111],"geometry":{"coordinates":[25.87528,58.15111],"type":"Point"}}