{"id":1209729649,"type":"Feature","properties":{"edtf:cessation":"uuuu","edtf:inception":"uuuu","geom:area":0,"geom:area_square_m":0,"geom:bbox":"23.94139,59.20194,23.94139,59.20194","geom:latitude":59.20194,"geom:longitude":23.94139,"gn:admin1_code":"1.0","gn:admin2_code":"431.0","gn:admin3_code":"1782.0","gn:asciiname":"Hatu","gn:cc2":"EE","gn:country_code":"EE","gn:dem":16,"gn:feature_class":"P","gn:feature_code":"PPL","gn:geonameid":592160,"gn:latitude":59.20194,"gn:longitude":23.94139,"gn:modification_date":"2017-11-25","gn:name":"Hatu","gn:population":0,"gn:timezone":"Europe/Tallinn","iso:country":"EE","lbl:bbox":"23.92139,59.18194,23.96139,59.22194","lbl:max_zoom":18,"lbl:min_zoom":13.5,"mz:hierarchy_label":1,"mz:is_current":1,"mz:min_zoom":12,"name:est_x_preferred":["Hatu"],"name:fra_x_preferred":["Hatu"],"name:hye_x_preferred":["Հատու"],"name:pol_x_preferred":["Hatu"],"name:spa_x_preferred":["Hatu"],"name:ukr_x_preferred":["Гату"],"name:und_x_variant":["Khatukyula"],"name:vol_x_preferred":["Hatu"],"src:geom":"geonames","wof:belongsto":[85683055,102191581,1713315313,85633135,1713305737],"wof:breaches":[],"wof:concordances":{"gn:id":592160,"wk:page":"Hatu"},"wof:coterminous":[1713315313],"wof:country":"EE","wof:geomhash":"24d482154e281a120d55fcaafe04f75b","wof:hierarchy":[{"continent_id":102191581,"country_id":85633135,"county_id":1713305737,"localadmin_id":1713315313,"locality_id":1209729649,"region_id":85683055}],"wof:id":1209729649,"wof:lang_x_official":["est"],"wof:lang_x_spoken":["est"],"wof:lastmodified":1596663325,"wof:name":"Hatu","wof:parent_id":1713315313,"wof:placetype":"locality","wof:repo":"whosonfirst-data-admin-ee","wof:superseded_by":[],"wof:supersedes":[],"wof:tags":[]},"bbox":[23.94139,59.20194,23.94139,59.20194],"geometry":{"coordinates":[23.94139,59.20194],"type":"Point"}}