{"id":1326594215,"type":"Feature","properties":{"edtf:cessation":"uuuu","edtf:inception":"uuuu","geom:area":0,"geom:area_square_m":0,"geom:bbox":"27.36139,57.625,27.36139,57.625","geom:latitude":57.625,"geom:longitude":27.36139,"gn:admin1_code":"21.0","gn:admin2_code":"732.0","gn:admin3_code":"6375.0","gn:asciiname":"Luhamaa","gn:country_code":"EE","gn:dem":189,"gn:feature_class":"P","gn:feature_code":"PPL","gn:geonameid":794248,"gn:latitude":57.625,"gn:longitude":27.36139,"gn:modification_date":"2017-11-25","gn:name":"Luhamaa","gn:population":0,"gn:timezone":"Europe/Tallinn","iso:country":"EE","lbl:bbox":"27.34139,57.605,27.38139,57.645","lbl:max_zoom":18,"lbl:min_zoom":13.5,"mz:hierarchy_label":1,"mz:is_current":1,"mz:min_zoom":12,"name:ces_x_preferred":["Luhamaa"],"name:deu_x_preferred":["Luhamaa"],"name:est_x_preferred":["Luhamaa"],"name:fra_x_preferred":["Luhamaa"],"name:swe_x_preferred":["Luhamaa"],"src:geom":"geonames","wof:belongsto":[85682955,102191581,1713315623,85633135,1713305631],"wof:breaches":[],"wof:concordances":{"gn:id":794248,"wk:page":"Luhamaa"},"wof:country":"EE","wof:geomhash":"6392df737516a83e3a2235940fa9304d","wof:hierarchy":[{"continent_id":102191581,"country_id":85633135,"county_id":1713305631,"localadmin_id":1713315623,"locality_id":1326594215,"region_id":85682955}],"wof:id":1326594215,"wof:lang_x_official":["est"],"wof:lang_x_spoken":["est"],"wof:lastmodified":1596663698,"wof:name":"Luhamaa","wof:parent_id":1713315623,"wof:placetype":"locality","wof:repo":"whosonfirst-data-admin-ee","wof:superseded_by":[],"wof:supersedes":[],"wof:tags":[]},"bbox":[27.36139,57.625,27.36139,57.625],"geometry":{"coordinates":[27.36139,57.625],"type":"Point"}}