{"id":1260053799,"type":"Feature","properties":{"edtf:cessation":"uuuu","edtf:inception":"uuuu","geom:area":0,"geom:area_square_m":0,"geom:bbox":"23.19639,58.59278,23.19639,58.59278","geom:latitude":58.59278,"geom:longitude":23.19639,"gn:admin1_code":"14.0","gn:admin2_code":"478.0","gn:admin3_code":"9027.0","gn:asciiname":"Vanamoisa","gn:country_code":"EE","gn:dem":14,"gn:feature_class":"P","gn:feature_code":"PPL","gn:geonameid":587806,"gn:latitude":58.59278,"gn:longitude":23.19639,"gn:modification_date":"2017-11-25","gn:name":"Vanamõisa","gn:population":0,"gn:timezone":"Europe/Tallinn","iso:country":"EE","lbl:bbox":"23.17639,58.57278,23.21639,58.61278","lbl:max_zoom":18,"lbl:min_zoom":13.5,"mz:hierarchy_label":1,"mz:is_current":1,"mz:min_zoom":12,"name:ara_x_preferred":["فانامويسا"],"name:deu_x_preferred":["Vanamõisa"],"name:est_x_preferred":["Vanamõisa"],"name:fas_x_preferred":["ونمیسا"],"name:hye_x_preferred":["Վանամիիսա"],"name:pol_x_preferred":["Vanamõisa"],"name:spa_x_preferred":["Vanamõisa"],"name:und_x_variant":["Vanamyyza"],"name:vol_x_preferred":["Vanamõisa"],"src:geom":"geonames","wof:belongsto":[85682947,102191581,1713306157,85633135,1713305623],"wof:breaches":[],"wof:concordances":{"gn:id":587806,"wk:page":"Vanam%C3%B5isa%2C_Muhu_Parish"},"wof:coterminous":[1713306157],"wof:country":"EE","wof:geomhash":"18e70498e1410a77811062f3dade5b84","wof:hierarchy":[{"continent_id":102191581,"country_id":85633135,"county_id":1713305623,"localadmin_id":1713306157,"locality_id":1260053799,"region_id":85682947}],"wof:id":1260053799,"wof:lang_x_official":["est"],"wof:lang_x_spoken":["est"],"wof:lastmodified":1596675299,"wof:name":"Vanamoisa","wof:parent_id":1713306157,"wof:placetype":"locality","wof:repo":"whosonfirst-data-admin-ee","wof:superseded_by":[],"wof:supersedes":[],"wof:tags":[]},"bbox":[23.19639,58.59278,23.19639,58.59278],"geometry":{"coordinates":[23.19639,58.59278],"type":"Point"}}