{"id":1125809223,"type":"Feature","properties":{"edtf:cessation":"uuuu","edtf:inception":"uuuu","geom:area":0,"geom:area_square_m":0,"geom:bbox":"24.40694,58.40472,24.40694,58.40472","geom:latitude":58.40472,"geom:longitude":24.40694,"gn:country":"EE","gn:fcode":"PPL","gn:population":497,"iso:country":"EE","lbl:bbox":"24.38694,58.38472,24.42694,58.42472","lbl:latitude":58.40472,"lbl:longitude":24.40694,"lbl:max_zoom":17,"lbl:min_zoom":12.5,"mz:hierarchy_label":1,"mz:is_current":1,"mz:min_zoom":11,"mz:note":"Quattroshapes Point Gazetteer import 20170519","name:bul_x_preferred":["Папсаре"],"name:ceb_x_preferred":["Papsaare"],"name:eng_x_preferred":["Papsaare"],"name:est_x_preferred":["Papsaare"],"name:hye_x_preferred":["Պապսաառե"],"name:nld_x_preferred":["Papsaare"],"name:pol_x_preferred":["Papsaare"],"name:swe_x_preferred":["Papsaare"],"name:und_x_variant":["Pappsare"],"name:vol_x_preferred":["Papsaare"],"qs_pg:aaroncc":"EE","qs_pg:gn_country":"EE","qs_pg:gn_fcode":"PPL","qs_pg:gn_id":589614,"qs_pg:gn_pop":497,"qs_pg:name":"Papsaare","qs_pg:name_adm0":"Eesti","qs_pg:name_adm1":"Pärnumaa","qs_pg:photos":1613,"qs_pg:photos_1k":327,"qs_pg:photos_9k":7,"qs_pg:photos_9r":8,"qs_pg:photos_all":1613,"qs_pg:photos_sr":13,"qs_pg:pop_sr":2,"qs_pg:qs_id":1083341,"qs_pg:qs_pg_placetype":"locality","qs_pg:qs_pg_placetype_gp":"Town","qs_pg:woe_adm0":23424805,"qs_pg:woe_id":844601,"src:geom":"qs_pg","src:lbl_centroid":"qs_pg","src:population":"geonames","woe:adm0_id":23424805,"woe:name_adm0":"Eesti","woe:name_adm1":"Pärnumaa","woe:placetype":"Town","wof:belongsto":[85682981,102191581,1713313149,85633135,1713305703],"wof:breaches":[],"wof:concordances":{"gn:id":589614,"gp:id":844601,"qs_pg:id":1083341,"wd:id":"Q1954271"},"wof:coterminous":[1713313149],"wof:country":"EE","wof:created":1497291587,"wof:geomhash":"f07233afb1a492bd79c264f2070a5a95","wof:hierarchy":[{"continent_id":102191581,"country_id":85633135,"county_id":1713305703,"localadmin_id":1713313149,"locality_id":1125809223,"region_id":85682981}],"wof:id":1125809223,"wof:lang_x_official":["est"],"wof:lang_x_spoken":["est"],"wof:lastmodified":1596677701,"wof:name":"Papsaare","wof:parent_id":1713313149,"wof:placetype":"locality","wof:population":497,"wof:population_rank":2,"wof:repo":"whosonfirst-data-admin-ee","wof:superseded_by":[],"wof:supersedes":[],"wof:tags":[]},"bbox":[24.40694,58.40472,24.40694,58.40472],"geometry":{"coordinates":[24.40694,58.40472],"type":"Point"}}