{"id":1225804035,"type":"Feature","properties":{"edtf:cessation":"uuuu","edtf:inception":"uuuu","geom:area":0,"geom:area_square_m":0,"geom:bbox":"27.31306,57.81333,27.31306,57.81333","geom:latitude":57.81333,"geom:longitude":27.31306,"gn:admin1_code":"21.0","gn:admin2_code":"917.0","gn:admin3_code":"8014.0","gn:asciiname":"Tabina","gn:country_code":"EE","gn:dem":74,"gn:feature_class":"P","gn:feature_code":"PPL","gn:geonameid":588453,"gn:latitude":57.81333,"gn:longitude":27.31306,"gn:modification_date":"2017-11-25","gn:name":"Tabina","gn:population":0,"gn:timezone":"Europe/Tallinn","iso:country":"EE","lbl:bbox":"27.29306,57.79333,27.33306,57.83333","lbl:max_zoom":18,"lbl:min_zoom":13.5,"mz:hierarchy_label":1,"mz:is_current":1,"mz:min_zoom":12,"name:est_x_preferred":["Tabina"],"name:hye_x_preferred":["Տաբինա"],"name:pol_x_preferred":["Tabina"],"name:spa_x_preferred":["Tabina"],"name:ukr_x_preferred":["Табіна"],"name:vol_x_preferred":["Tabina"],"src:geom":"geonames","wof:belongsto":[85682937,102191581,1713315965,85633135,1713305633],"wof:breaches":[],"wof:concordances":{"gn:id":588453,"wk:page":"Tabina%2C_Estonia"},"wof:coterminous":[1713315965],"wof:country":"EE","wof:geomhash":"580e7d0d351f6b92625d80dfbd58dd9e","wof:hierarchy":[{"continent_id":102191581,"country_id":85633135,"county_id":1713305633,"localadmin_id":1713315965,"locality_id":1225804035,"region_id":85682937}],"wof:id":1225804035,"wof:lang_x_official":["est"],"wof:lang_x_spoken":["est"],"wof:lastmodified":1596660390,"wof:name":"Tabina","wof:parent_id":1713315965,"wof:placetype":"locality","wof:repo":"whosonfirst-data-admin-ee","wof:superseded_by":[],"wof:supersedes":[],"wof:tags":[]},"bbox":[27.31306,57.81333,27.31306,57.81333],"geometry":{"coordinates":[27.31306,57.81333],"type":"Point"}}