{"id":1125936647,"type":"Feature","properties":{"edtf:cessation":"uuuu","edtf:inception":"uuuu","geom:area":0,"geom:area_square_m":0,"geom:bbox":"25.45389,58.81583,25.45389,58.81583","geom:latitude":58.81583,"geom:longitude":25.45389,"gn:country":"EE","gn:fcode":"PPL","gn:population":507,"iso:country":"EE","lbl:bbox":"25.43389,58.79583,25.47389,58.83583","lbl:latitude":58.81583,"lbl:longitude":25.45389,"lbl:max_zoom":17,"lbl:min_zoom":12.5,"mz:hierarchy_label":1,"mz:is_current":1,"mz:min_zoom":11,"mz:note":"Quattroshapes Point Gazetteer import 20170519","name:ceb_x_preferred":["Türi-Alliku"],"name:eng_x_preferred":["Türi-Alliku"],"name:est_x_preferred":["Türi-Alliku"],"name:fas_x_preferred":["توری آلیکو"],"name:fra_x_preferred":["Türi-Alliku"],"name:hye_x_preferred":["Տյուռի-Ալիկու"],"name:nld_x_preferred":["Türi-Alliku"],"name:pol_x_preferred":["Türi-Alliku"],"name:spa_x_preferred":["Türi-Alliku"],"name:swe_x_preferred":["Türi-Alliku"],"name:ukr_x_preferred":["Тюрі-Алліку"],"name:und_x_variant":["Alliku"],"name:vol_x_preferred":["Türi-Alliku"],"qs_pg:aaroncc":"EE","qs_pg:gn_country":"EE","qs_pg:gn_fcode":"PPL","qs_pg:gn_id":588152,"qs_pg:gn_pop":507,"qs_pg:name":"Türi-Alliku","qs_pg:name_adm0":"Eesti","qs_pg:name_adm1":"Järvamaa","qs_pg:photos_9r":0,"qs_pg:photos_sr":0,"qs_pg:pop_sr":2,"qs_pg:qs_id":1274639,"qs_pg:qs_pg_placetype":"locality","qs_pg:qs_pg_placetype_gp":"Town","qs_pg:woe_adm0":23424805,"qs_pg:woe_id":845985,"src:geom":"qs_pg","src:lbl_centroid":"qs_pg","src:population":"geonames","woe:adm0_id":23424805,"woe:name_adm0":"Eesti","woe:name_adm1":"Järvamaa","woe:placetype":"Town","wof:belongsto":[85683031,102191581,1713315925,85633135,1713305773],"wof:breaches":[],"wof:concordances":{"gn:id":588152,"gp:id":845985,"qs_pg:id":1274639,"wd:id":"Q3463636"},"wof:coterminous":[1713315925],"wof:country":"EE","wof:created":1497296988,"wof:geomhash":"749a581403d474999c30ca50456431de","wof:hierarchy":[{"continent_id":102191581,"country_id":85633135,"county_id":1713305773,"localadmin_id":1713315925,"locality_id":1125936647,"region_id":85683031}],"wof:id":1125936647,"wof:lang_x_official":["est"],"wof:lang_x_spoken":["est"],"wof:lastmodified":1596677997,"wof:name":"Türi-Alliku","wof:parent_id":1713315925,"wof:placetype":"locality","wof:population":507,"wof:population_rank":2,"wof:repo":"whosonfirst-data-admin-ee","wof:superseded_by":[],"wof:supersedes":[],"wof:tags":[]},"bbox":[25.45389,58.81583,25.45389,58.81583],"geometry":{"coordinates":[25.45389,58.81583],"type":"Point"}}