{"id":1260363351,"type":"Feature","properties":{"edtf:cessation":"uuuu","edtf:inception":"uuuu","geom:area":0,"geom:area_square_m":0,"geom:bbox":"22.18639,57.98694,22.18639,57.98694","geom:latitude":57.98694,"geom:longitude":22.18639,"gn:admin1_code":"14.0","gn:admin2_code":"714.0","gn:admin3_code":"2442.0","gn:asciiname":"Kaavi","gn:cc2":"EE","gn:country_code":"EE","gn:dem":9,"gn:feature_class":"P","gn:feature_code":"PPL","gn:geonameid":591826,"gn:latitude":57.98694,"gn:longitude":22.18639,"gn:modification_date":"2017-11-25","gn:name":"Kaavi","gn:population":0,"gn:timezone":"Europe/Tallinn","iso:country":"EE","lbl:bbox":"22.16639,57.96694,22.20639,58.00694","lbl:max_zoom":18,"lbl:min_zoom":13.5,"mz:hierarchy_label":1,"mz:is_current":1,"mz:min_zoom":12,"name:deu_x_preferred":["Kaavi"],"name:est_x_preferred":["Kaavi"],"name:fin_x_preferred":["Kaavi"],"name:fra_x_preferred":["Kaavi"],"name:hye_x_preferred":["Կաավի"],"name:pol_x_preferred":["Kaavi"],"name:spa_x_preferred":["Kaavi"],"name:ukr_x_preferred":["Кааві"],"name:und_x_variant":["Kavi"],"name:vol_x_preferred":["Kaavi"],"src:geom":"geonames","wof:belongsto":[85682947,102191581,1713307409,85633135,1713305627],"wof:breaches":[],"wof:concordances":{"gn:id":591826,"wk:page":"Kaavi%2C_Estonia"},"wof:coterminous":[1713307409],"wof:country":"EE","wof:geomhash":"e76f8ee8be5cbeb8fdbb3c8b794b11ed","wof:hierarchy":[{"continent_id":102191581,"country_id":85633135,"county_id":1713305627,"localadmin_id":1713307409,"locality_id":1260363351,"region_id":85682947}],"wof:id":1260363351,"wof:lang_x_official":["est"],"wof:lang_x_spoken":["est"],"wof:lastmodified":1596674915,"wof:name":"Kaavi","wof:parent_id":1713307409,"wof:placetype":"locality","wof:repo":"whosonfirst-data-admin-ee","wof:superseded_by":[],"wof:supersedes":[],"wof:tags":[]},"bbox":[22.18639,57.98694,22.18639,57.98694],"geometry":{"coordinates":[22.18639,57.98694],"type":"Point"}}