{"id":1209579987,"type":"Feature","properties":{"edtf:cessation":"uuuu","edtf:inception":"uuuu","geom:area":0,"geom:area_square_m":0,"geom:bbox":"27.13722,57.75111,27.13722,57.75111","geom:latitude":57.75111,"geom:longitude":27.13722,"gn:admin1_code":"21.0","gn:admin2_code":"917.0","gn:admin3_code":"9458.0","gn:asciiname":"Ihaerde","gn:country_code":"EE","gn:dem":189,"gn:feature_class":"P","gn:feature_code":"PPL","gn:geonameid":8619192,"gn:latitude":57.75111,"gn:longitude":27.13722,"gn:modification_date":"2017-11-25","gn:name":"Ihärde","gn:population":0,"gn:timezone":"Europe/Tallinn","iso:country":"EE","lbl:bbox":"27.11722,57.73111,27.15722,57.77111","lbl:max_zoom":18,"lbl:min_zoom":13.5,"mz:hierarchy_label":1,"mz:is_current":1,"mz:min_zoom":12,"name:und_x_variant":["Ihärde","Iharde"],"src:geom":"geonames","wof:belongsto":[85682937,102191581,1713315783,85633135,1713305633],"wof:breaches":[],"wof:concordances":{"gn:id":8619192},"wof:country":"EE","wof:geomhash":"d1a2253e3adb86438536e917c4c00389","wof:hierarchy":[{"continent_id":102191581,"country_id":85633135,"county_id":1713305633,"localadmin_id":1713315783,"locality_id":1209579987,"region_id":85682937}],"wof:id":1209579987,"wof:lang_x_official":["est"],"wof:lang_x_spoken":["est"],"wof:lastmodified":1596660409,"wof:name":"Ihaerde","wof:parent_id":1713315783,"wof:placetype":"locality","wof:repo":"whosonfirst-data-admin-ee","wof:superseded_by":[],"wof:supersedes":[],"wof:tags":[]},"bbox":[27.13722,57.75111,27.13722,57.75111],"geometry":{"coordinates":[27.13722,57.75111],"type":"Point"}}