{"id":1360299235,"type":"Feature","properties":{"edtf:cessation":"uuuu","edtf:inception":"uuuu","geom:area":0,"geom:area_square_m":0,"geom:bbox":"24.31139,59.06528,24.31139,59.06528","geom:latitude":59.06528,"geom:longitude":24.31139,"gn:admin1_code":"1.0","gn:admin2_code":"726.0","gn:admin3_code":"5467.0","gn:asciiname":"Varese","gn:country_code":"EE","gn:dem":49,"gn:feature_class":"P","gn:feature_code":"PPL","gn:geonameid":587754,"gn:latitude":59.06528,"gn:longitude":24.31139,"gn:modification_date":"2017-11-25","gn:name":"Varese","gn:population":0,"gn:timezone":"Europe/Tallinn","iso:country":"EE","lbl:bbox":"24.29139,59.04528,24.33139,59.08528","lbl:max_zoom":18,"lbl:min_zoom":13.5,"mz:hierarchy_label":1,"mz:is_current":1,"mz:min_zoom":12,"name:ara_x_preferred":["فاريزي"],"name:azb_x_preferred":["وارزه"],"name:bre_x_preferred":["Varese"],"name:bul_x_preferred":["Варезе"],"name:cat_x_preferred":["Varese"],"name:ceb_x_preferred":["Varese"],"name:ces_x_preferred":["Varese"],"name:cos_x_preferred":["Varese"],"name:dan_x_preferred":["Varese"],"name:deu_x_preferred":["Varese"],"name:ell_x_preferred":["Βαρέζε"],"name:eml_x_preferred":["Varais"],"name:epo_x_preferred":["Varese"],"name:est_x_preferred":["Varese"],"name:eus_x_preferred":["Varese"],"name:fas_x_preferred":["وارزه"],"name:fin_x_preferred":["Varese"],"name:fra_x_preferred":["Varèse"],"name:gle_x_preferred":["Varese"],"name:glg_x_preferred":["Varese"],"name:heb_x_preferred":["וארזה"],"name:hrv_x_preferred":["Varese"],"name:hun_x_preferred":["Varese"],"name:hye_x_preferred":["Վարեզե"],"name:ind_x_preferred":["Varese"],"name:ita_x_preferred":["Varese"],"name:jpn_x_preferred":["ヴァレーゼ"],"name:kat_x_preferred":["ვარეზე"],"name:kaz_x_preferred":["Варезе"],"name:kor_x_preferred":["바레세"],"name:lat_x_preferred":["Baretium"],"name:lav_x_preferred":["Varēze"],"name:lit_x_preferred":["Varezė"],"name:lmo_x_preferred":["Vares"],"name:ltz_x_preferred":["Varese"],"name:msa_x_preferred":["Varese"],"name:nap_x_preferred":["Varese"],"name:nld_x_preferred":["Varese"],"name:nno_x_preferred":["Varese"],"name:nor_x_preferred":["Varese"],"name:oci_x_preferred":["Varese"],"name:pms_x_preferred":["Varèis"],"name:pnb_x_preferred":["واریسی"],"name:pol_x_preferred":["Varese"],"name:por_x_preferred":["Varese"],"name:que_x_preferred":["Varese"],"name:ron_x_preferred":["Varese"],"name:rus_x_preferred":["Варесе"],"name:san_x_preferred":["वारेसे"],"name:scn_x_preferred":["Varesi"],"name:sco_x_preferred":["Varese"],"name:slk_x_preferred":["Varese"],"name:spa_x_preferred":["Varese"],"name:sqi_x_preferred":["Varese"],"name:srd_x_preferred":["Varese"],"name:srp_x_preferred":["Варезе"],"name:swe_x_preferred":["Varese"],"name:szl_x_preferred":["Varese"],"name:tat_x_preferred":["Варезе"],"name:tha_x_preferred":["วาเรซี"],"name:tur_x_preferred":["Varese"],"name:twi_x_preferred":["Varese"],"name:ukr_x_preferred":["Варезе"],"name:und_x_variant":["Vareze"],"name:urd_x_preferred":["واریزے"],"name:vec_x_preferred":["Varexe"],"name:vie_x_preferred":["Varese"],"name:vol_x_preferred":["Varese"],"name:war_x_preferred":["Varese"],"name:zho_x_preferred":["瓦雷澤"],"src:geom":"geonames","wof:belongsto":[85683055,102191581,1713313519,85633135,1713305739],"wof:breaches":[],"wof:concordances":{"gn:id":587754},"wof:country":"EE","wof:geomhash":"2c1d82c81b6f96ce65f13a9e122986dd","wof:hierarchy":[{"continent_id":102191581,"country_id":85633135,"county_id":1713305739,"localadmin_id":1713313519,"locality_id":1360299235,"region_id":85683055}],"wof:id":1360299235,"wof:lang_x_official":["est"],"wof:lang_x_spoken":["est"],"wof:lastmodified":1596663241,"wof:name":"Varese","wof:parent_id":1713313519,"wof:placetype":"locality","wof:repo":"whosonfirst-data-admin-ee","wof:superseded_by":[],"wof:supersedes":[],"wof:tags":[]},"bbox":[24.31139,59.06528,24.31139,59.06528],"geometry":{"coordinates":[24.31139,59.06528],"type":"Point"}}