{"id":1326850341,"type":"Feature","properties":{"edtf:cessation":"uuuu","edtf:inception":"uuuu","geom:area":0,"geom:area_square_m":0,"geom:bbox":"26.10139,59.55389,26.10139,59.55389","geom:latitude":59.55389,"geom:longitude":26.10139,"gn:admin1_code":"8.0","gn:admin2_code":"191.0","gn:admin3_code":"4151.0","gn:asciiname":"Tepelvaelja","gn:country_code":"EE","gn:dem":58,"gn:feature_class":"P","gn:feature_code":"PPL","gn:geonameid":793260,"gn:latitude":59.55389,"gn:longitude":26.10139,"gn:modification_date":"2017-11-25","gn:name":"Tepelvälja","gn:population":0,"gn:timezone":"Europe/Tallinn","iso:country":"EE","lbl:bbox":"26.08139,59.53389,26.12139,59.57389","lbl:max_zoom":18,"lbl:min_zoom":13.5,"mz:hierarchy_label":1,"mz:is_current":1,"mz:min_zoom":12,"name:est_x_preferred":["Tepelvälja"],"name:fra_x_preferred":["Tepelvälja"],"name:hye_x_preferred":["Տեպելվելյա"],"name:pol_x_preferred":["Tepelvälja"],"name:vol_x_preferred":["Tepelvälja"],"src:geom":"geonames","wof:belongsto":[85683049,102191581,1713308515,85633135,1713305775],"wof:breaches":[],"wof:concordances":{"gn:id":793260,"wk:page":"Tepelv%C3%A4lja"},"wof:coterminous":[1713308549],"wof:country":"EE","wof:geomhash":"2aa9e4048efc404cf7083f8d9104e783","wof:hierarchy":[{"continent_id":102191581,"country_id":85633135,"county_id":1713305775,"localadmin_id":1713308515,"locality_id":1326850341,"region_id":85683049}],"wof:id":1326850341,"wof:lang_x_official":["est"],"wof:lang_x_spoken":["est"],"wof:lastmodified":1596678042,"wof:name":"Tepelvaelja","wof:parent_id":1713308515,"wof:placetype":"locality","wof:repo":"whosonfirst-data-admin-ee","wof:superseded_by":[],"wof:supersedes":[],"wof:tags":[]},"bbox":[26.10139,59.55389,26.10139,59.55389],"geometry":{"coordinates":[26.10139,59.55389],"type":"Point"}}