{"id":1343627089,"type":"Feature","properties":{"edtf:cessation":"uuuu","edtf:inception":"uuuu","geom:area":0,"geom:area_square_m":0,"geom:bbox":"26.18472,58.01833,26.18472,58.01833","geom:latitude":58.01833,"geom:longitude":26.18472,"gn:admin1_code":"19.0","gn:admin2_code":"557.0","gn:admin3_code":"3534.0","gn:asciiname":"Viki","gn:country_code":"EE","gn:dem":100,"gn:feature_class":"P","gn:feature_code":"PPL","gn:geonameid":8620310,"gn:latitude":58.01833,"gn:longitude":26.18472,"gn:modification_date":"2017-11-25","gn:name":"Viki","gn:population":0,"gn:timezone":"Europe/Tallinn","iso:country":"EE","lbl:bbox":"26.16472,57.99833,26.20472,58.03833","lbl:max_zoom":18,"lbl:min_zoom":13.5,"mz:hierarchy_label":1,"mz:is_current":1,"mz:min_zoom":12,"name:ceb_x_preferred":["Viki"],"name:ces_x_preferred":["Viki"],"name:est_x_preferred":["Viki"],"name:fra_x_preferred":["Viki"],"name:swe_x_preferred":["Viki"],"name:tur_x_preferred":["Viki"],"name:zho_x_preferred":["Viki"],"src:geom":"geonames","wof:belongsto":[85682941,102191581,1713309893,85633135,1713305759],"wof:breaches":[],"wof:concordances":{"gn:id":8620310},"wof:country":"EE","wof:geomhash":"9ffae11e41a9f35c146de6cc4f9ba7bd","wof:hierarchy":[{"continent_id":102191581,"country_id":85633135,"county_id":1713305759,"localadmin_id":1713309893,"locality_id":1343627089,"region_id":85682941}],"wof:id":1343627089,"wof:lang_x_official":["est"],"wof:lang_x_spoken":["est"],"wof:lastmodified":1596661875,"wof:name":"Viki","wof:parent_id":1713309893,"wof:placetype":"locality","wof:repo":"whosonfirst-data-admin-ee","wof:superseded_by":[],"wof:supersedes":[],"wof:tags":[]},"bbox":[26.18472,58.01833,26.18472,58.01833],"geometry":{"coordinates":[26.18472,58.01833],"type":"Point"}}