{"id":1327213909,"type":"Feature","properties":{"edtf:cessation":"uuuu","edtf:inception":"uuuu","geom:area":0,"geom:area_square_m":0,"geom:bbox":"27.14083,58.08028,27.14083,58.08028","geom:latitude":58.08028,"geom:longitude":27.14083,"gn:admin1_code":"12.0","gn:admin2_code":"622.0","gn:admin3_code":"1081.0","gn:asciiname":"Viiraperae","gn:country_code":"EE","gn:dem":65,"gn:feature_class":"P","gn:feature_code":"PPL","gn:geonameid":8620767,"gn:latitude":58.08028,"gn:longitude":27.14083,"gn:modification_date":"2017-11-25","gn:name":"Viiraperä","gn:population":0,"gn:timezone":"Europe/Tallinn","iso:country":"EE","lbl:bbox":"27.12083,58.06028,27.16083,58.10028","lbl:max_zoom":18,"lbl:min_zoom":13.5,"mz:hierarchy_label":1,"mz:is_current":1,"mz:min_zoom":12,"src:geom":"geonames","wof:belongsto":[85682955,102191581,1713311137,85633135,1713305791],"wof:breaches":[],"wof:concordances":{"gn:id":8620767},"wof:country":"EE","wof:geomhash":"88b5eee9db7119e06ad94855d89979ed","wof:hierarchy":[{"continent_id":102191581,"country_id":85633135,"county_id":1713305791,"localadmin_id":1713311137,"locality_id":1327213909,"region_id":85682955}],"wof:id":1327213909,"wof:lang_x_official":["est"],"wof:lang_x_spoken":["est"],"wof:lastmodified":1596676972,"wof:name":"Viiraperae","wof:parent_id":1713311137,"wof:placetype":"locality","wof:repo":"whosonfirst-data-admin-ee","wof:superseded_by":[],"wof:supersedes":[],"wof:tags":[]},"bbox":[27.14083,58.08028,27.14083,58.08028],"geometry":{"coordinates":[27.14083,58.08028],"type":"Point"}}