{"id":1277140085,"type":"Feature","properties":{"edtf:cessation":"uuuu","edtf:inception":"uuuu","geom:area":0,"geom:area_square_m":0,"geom:bbox":"26.96389,58.50389,26.96389,58.50389","geom:latitude":58.50389,"geom:longitude":26.96389,"gn:admin1_code":"18.0","gn:admin2_code":"586.0","gn:admin3_code":"3703.0","gn:asciiname":"Porikuela","gn:country_code":"EE","gn:dem":61,"gn:feature_class":"P","gn:feature_code":"PPL","gn:geonameid":8619472,"gn:latitude":58.50389,"gn:longitude":26.96389,"gn:modification_date":"2017-11-25","gn:name":"Poriküla","gn:population":0,"gn:timezone":"Europe/Tallinn","iso:country":"EE","lbl:bbox":"26.94389,58.48389,26.98389,58.52389","lbl:max_zoom":18,"lbl:min_zoom":13.5,"mz:hierarchy_label":1,"mz:is_current":1,"mz:min_zoom":12,"name:und_x_variant":["Poriküla","Pori"],"src:geom":"geonames","wof:belongsto":[85682995,102191581,1713309475,85633135,1713305679],"wof:breaches":[],"wof:concordances":{"gn:id":8619472},"wof:country":"EE","wof:geomhash":"10bf4056cb2108b3b70c0ca5abd725cd","wof:hierarchy":[{"continent_id":102191581,"country_id":85633135,"county_id":1713305679,"localadmin_id":1713309475,"locality_id":1277140085,"region_id":85682995}],"wof:id":1277140085,"wof:lang_x_official":["est"],"wof:lang_x_spoken":["est"],"wof:lastmodified":1596660939,"wof:name":"Porikuela","wof:parent_id":1713309475,"wof:placetype":"locality","wof:repo":"whosonfirst-data-admin-ee","wof:superseded_by":[],"wof:supersedes":[],"wof:tags":[]},"bbox":[26.96389,58.50389,26.96389,58.50389],"geometry":{"coordinates":[26.96389,58.50389],"type":"Point"}}