{"id":1226128747,"type":"Feature","properties":{"edtf:cessation":"uuuu","edtf:inception":"uuuu","geom:area":0,"geom:area_square_m":0,"geom:bbox":"24.33111,58.84833,24.33111,58.84833","geom:latitude":58.84833,"geom:longitude":24.33111,"gn:admin1_code":"13.0","gn:admin2_code":"503.0","gn:admin3_code":"8283.0","gn:asciiname":"Tolli","gn:country_code":"EE","gn:dem":27,"gn:feature_class":"P","gn:feature_code":"PPL","gn:geonameid":795039,"gn:latitude":58.84833,"gn:longitude":24.33111,"gn:modification_date":"2017-11-25","gn:name":"Tolli","gn:population":0,"gn:timezone":"Europe/Tallinn","iso:country":"EE","lbl:bbox":"24.31111,58.82833,24.35111,58.86833","lbl:max_zoom":18,"lbl:min_zoom":13.5,"mz:hierarchy_label":1,"mz:is_current":1,"mz:min_zoom":12,"name:est_x_preferred":["Tolli"],"name:fra_x_preferred":["Tolli"],"name:hye_x_preferred":["Տոլլի"],"name:pol_x_preferred":["Tolli"],"name:sco_x_preferred":["Tolli"],"name:spa_x_preferred":["Tolli"],"name:vol_x_preferred":["Tolli"],"src:geom":"geonames","wof:belongsto":[85683013,102191581,1713311465,85633135,1713305747],"wof:breaches":[],"wof:concordances":{"gn:id":795039,"wk:page":"Tolli"},"wof:coterminous":[1713311465],"wof:country":"EE","wof:geomhash":"895d23919ecfa1a2857d2d20b4ad9209","wof:hierarchy":[{"continent_id":102191581,"country_id":85633135,"county_id":1713305747,"localadmin_id":1713311465,"locality_id":1226128747,"region_id":85683013}],"wof:id":1226128747,"wof:lang_x_official":["est"],"wof:lang_x_spoken":["est"],"wof:lastmodified":1596662844,"wof:name":"Tolli","wof:parent_id":1713311465,"wof:placetype":"locality","wof:repo":"whosonfirst-data-admin-ee","wof:superseded_by":[],"wof:supersedes":[],"wof:tags":[]},"bbox":[24.33111,58.84833,24.33111,58.84833],"geometry":{"coordinates":[24.33111,58.84833],"type":"Point"}}