{"id":1259757645,"type":"Feature","properties":{"edtf:cessation":"uuuu","edtf:inception":"uuuu","geom:area":0,"geom:area_square_m":0,"geom:bbox":"25.65833,58.31306,25.65833,58.31306","geom:latitude":58.31306,"geom:longitude":25.65833,"gn:admin1_code":"20.0","gn:admin2_code":"899.0","gn:admin3_code":"4484.0","gn:asciiname":"Lolu","gn:country_code":"EE","gn:dem":83,"gn:feature_class":"P","gn:feature_code":"PPL","gn:geonameid":793914,"gn:latitude":58.31306,"gn:longitude":25.65833,"gn:modification_date":"2017-11-25","gn:name":"Lolu","gn:population":0,"gn:timezone":"Europe/Tallinn","iso:country":"EE","lbl:bbox":"25.63833,58.29306,25.67833,58.33306","lbl:max_zoom":18,"lbl:min_zoom":13.5,"mz:hierarchy_label":1,"mz:is_current":1,"mz:min_zoom":12,"src:geom":"geonames","wof:belongsto":[85682985,102191581,1713309963,85633135,1713305669],"wof:breaches":[],"wof:concordances":{"gn:id":793914},"wof:coterminous":[1713309963],"wof:country":"EE","wof:geomhash":"34e15461706f04b44f686cd2dc0c7706","wof:hierarchy":[{"continent_id":102191581,"country_id":85633135,"county_id":1713305669,"localadmin_id":1713309963,"locality_id":1259757645,"region_id":85682985}],"wof:id":1259757645,"wof:lang_x_official":["est"],"wof:lang_x_spoken":["est"],"wof:lastmodified":1596661255,"wof:name":"Lolu","wof:parent_id":1713309963,"wof:placetype":"locality","wof:repo":"whosonfirst-data-admin-ee","wof:superseded_by":[],"wof:supersedes":[],"wof:tags":[]},"bbox":[25.65833,58.31306,25.65833,58.31306],"geometry":{"coordinates":[25.65833,58.31306],"type":"Point"}}