{"id":1126018199,"type":"Feature","properties":{"edtf:cessation":"uuuu","edtf:inception":"uuuu","geom:area":0,"geom:area_square_m":0,"geom:bbox":"26.48194,59.31861,26.48194,59.31861","geom:latitude":59.31861,"geom:longitude":26.48194,"gn:country":"EE","gn:fcode":"PPL","gn:population":0,"iso:country":"EE","lbl:bbox":"26.46194,59.29861,26.50194,59.33861","lbl:latitude":59.31861,"lbl:longitude":26.48194,"lbl:max_zoom":18,"lbl:min_zoom":13.5,"mz:hierarchy_label":1,"mz:is_current":1,"mz:min_zoom":12,"mz:note":"Quattroshapes Point Gazetteer import 20170519","name:und_x_variant":["Myza Ryagavere"],"qs_pg:aaroncc":"EE","qs_pg:gn_country":"EE","qs_pg:gn_fcode":"PPL","qs_pg:gn_id":589197,"qs_pg:gn_pop":0,"qs_pg:name":"Rägavere","qs_pg:name_adm0":"Eesti","qs_pg:name_adm1":"Lääne-Virumaa","qs_pg:photos":2,"qs_pg:photos_1k":1,"qs_pg:photos_9k":1,"qs_pg:photos_9r":1,"qs_pg:photos_all":2,"qs_pg:photos_sr":1,"qs_pg:pop_sr":0,"qs_pg:qs_id":1015215,"qs_pg:qs_pg_placetype":"locality","qs_pg:qs_pg_placetype_gp":"Town","qs_pg:woe_adm0":23424805,"qs_pg:woe_id":844994,"src:geom":"qs_pg","src:lbl_centroid":"qs_pg","woe:adm0_id":23424805,"woe:name_adm0":"Eesti","woe:name_adm1":"Lääne-Virumaa","woe:placetype":"Town","wof:belongsto":[85683049,102191581,1713307957,85633135,1713305771],"wof:breaches":[],"wof:concordances":{"gn:id":589197,"gp:id":844994,"qs_pg:id":1015215},"wof:coterminous":[1713312661],"wof:country":"EE","wof:created":1497300677,"wof:geomhash":"0f8c3dee3a67f655a2c1d3a8288d9a45","wof:hierarchy":[{"continent_id":102191581,"country_id":85633135,"county_id":1713305771,"localadmin_id":1713307957,"locality_id":1126018199,"region_id":85683049}],"wof:id":1126018199,"wof:lang_x_official":["est"],"wof:lang_x_spoken":["est"],"wof:lastmodified":1596677970,"wof:name":"Rägavere","wof:parent_id":1713307957,"wof:placetype":"locality","wof:repo":"whosonfirst-data-admin-ee","wof:superseded_by":[],"wof:supersedes":[],"wof:tags":[]},"bbox":[26.48194,59.31861,26.48194,59.31861],"geometry":{"coordinates":[26.48194,59.31861],"type":"Point"}}