{"id":1259654659,"type":"Feature","properties":{"edtf:cessation":"uuuu","edtf:inception":"uuuu","geom:area":0,"geom:area_square_m":0,"geom:bbox":"21.84944,58.37583,21.84944,58.37583","geom:latitude":58.37583,"geom:longitude":21.84944,"gn:admin1_code":"14.0","gn:admin2_code":"714.0","gn:admin3_code":"9357.0","gn:asciiname":"Vilsandi","gn:country_code":"EE","gn:dem":5,"gn:feature_class":"P","gn:feature_code":"PPL","gn:geonameid":587583,"gn:latitude":58.37583,"gn:longitude":21.84944,"gn:modification_date":"2017-11-25","gn:name":"Vilsandi","gn:population":0,"gn:timezone":"Europe/Tallinn","iso:country":"EE","lbl:bbox":"21.82944,58.35583,21.86944,58.39583","lbl:max_zoom":18,"lbl:min_zoom":13.5,"mz:hierarchy_label":1,"mz:is_current":1,"mz:min_zoom":12,"name:ceb_x_preferred":["Vilsandi"],"name:ces_x_preferred":["Vilsandi"],"name:deu_x_preferred":["Vilsandi"],"name:est_x_preferred":["Vilsandi"],"name:fin_x_preferred":["Vilsandi"],"name:fra_x_preferred":["Vilsandi"],"name:heb_x_preferred":["וילסאנדי"],"name:hrv_x_preferred":["Vilsandi"],"name:hye_x_preferred":["Վիլսանդի"],"name:lav_x_preferred":["Vilsandi"],"name:lit_x_preferred":["Vilsandis"],"name:nld_x_preferred":["Vilsandi"],"name:nno_x_preferred":["Vilsandi"],"name:nor_x_preferred":["Vilsandi"],"name:pol_x_preferred":["Vilsandi"],"name:rus_x_preferred":["Вильсанди"],"name:spa_x_preferred":["Vilsandi"],"name:srp_x_preferred":["Вилсанди"],"name:swe_x_preferred":["Vilsandi"],"name:tur_x_preferred":["Vilsandi"],"name:ukr_x_preferred":["Вільсанді"],"src:geom":"geonames","wof:belongsto":[85682947,102191581,1713308599,85633135,1713305627],"wof:breaches":[],"wof:concordances":{"gn:id":587583},"wof:coterminous":[1713308599],"wof:country":"EE","wof:geomhash":"9e1498c5f0a45195f2e48633f1d354d5","wof:hierarchy":[{"continent_id":102191581,"country_id":85633135,"county_id":1713305627,"localadmin_id":1713308599,"locality_id":1259654659,"region_id":85682947}],"wof:id":1259654659,"wof:lang_x_official":["est"],"wof:lang_x_spoken":["est"],"wof:lastmodified":1596674939,"wof:name":"Vilsandi","wof:parent_id":1713308599,"wof:placetype":"locality","wof:repo":"whosonfirst-data-admin-ee","wof:superseded_by":[],"wof:supersedes":[],"wof:tags":[]},"bbox":[21.84944,58.37583,21.84944,58.37583],"geometry":{"coordinates":[21.84944,58.37583],"type":"Point"}}