{"id":1243370937,"type":"Feature","properties":{"edtf:cessation":"uuuu","edtf:inception":"uuuu","geom:area":0,"geom:area_square_m":0,"geom:bbox":"27.0525,58.95667,27.0525,58.95667","geom:latitude":58.95667,"geom:longitude":27.0525,"gn:admin1_code":"5.0","gn:admin2_code":"486.0","gn:admin3_code":"4459.0","gn:asciiname":"UElejoe","gn:country_code":"EE","gn:dem":39,"gn:feature_class":"P","gn:feature_code":"PPL","gn:geonameid":8618555,"gn:latitude":58.95667,"gn:longitude":27.0525,"gn:modification_date":"2017-11-25","gn:name":"Ülejõe","gn:population":0,"gn:timezone":"Europe/Tallinn","iso:country":"EE","lbl:bbox":"27.0325,58.93667,27.0725,58.97667","lbl:max_zoom":18,"lbl:min_zoom":13.5,"mz:hierarchy_label":1,"mz:is_current":1,"mz:is_funky":1,"mz:min_zoom":12,"name:und_x_variant":["Ülejõe","Ülejõe-Lohusuu"],"src:geom":"geonames","wof:belongsto":[85683059,102191581,1713312055,85633135,1713305677],"wof:breaches":[],"wof:concordances":{"gn:id":8618555},"wof:country":"EE","wof:geomhash":"a4f4488586947d065462f6e390866b61","wof:hierarchy":[{"continent_id":102191581,"country_id":85633135,"county_id":1713305677,"localadmin_id":1713312055,"locality_id":1243370937,"region_id":85683059}],"wof:id":1243370937,"wof:lang_x_official":["est"],"wof:lang_x_spoken":["est"],"wof:lastmodified":1596661029,"wof:name":"UElejoe","wof:parent_id":1713312055,"wof:placetype":"locality","wof:repo":"whosonfirst-data-admin-ee","wof:superseded_by":[],"wof:supersedes":[],"wof:tags":[]},"bbox":[27.0525,58.95667,27.0525,58.95667],"geometry":{"coordinates":[27.0525,58.95667],"type":"Point"}}