{"id":1327234843,"type":"Feature","properties":{"edtf:cessation":"uuuu","edtf:inception":"uuuu","geom:area":0,"geom:area_square_m":0,"geom:bbox":"22.32769,58.89523,22.32769,58.89523","geom:latitude":58.89523,"geom:longitude":22.32769,"gn:admin1_code":"2.0","gn:admin2_code":"205.0","gn:admin3_code":"4023.0","gn:asciiname":"Laasi","gn:country_code":"EE","gn:dem":10,"gn:feature_class":"P","gn:feature_code":"PPL","gn:geonameid":8618245,"gn:latitude":58.89523,"gn:longitude":22.32769,"gn:modification_date":"2017-11-25","gn:name":"Laasi","gn:population":0,"gn:timezone":"Europe/Tallinn","iso:country":"EE","lbl:bbox":"22.30769,58.87523,22.34769,58.91523","lbl:max_zoom":18,"lbl:min_zoom":13.5,"mz:hierarchy_label":1,"mz:is_current":1,"mz:min_zoom":12,"name:deu_x_preferred":["Laasi"],"name:est_x_preferred":["Laasi"],"name:hye_x_preferred":["Լաասի"],"name:pol_x_preferred":["Laasi"],"name:und_x_variant":["Lassi"],"name:vol_x_preferred":["Laasi"],"src:geom":"geonames","wof:belongsto":[85682989,102191581,1713310373,85633135,1713305629],"wof:breaches":[],"wof:concordances":{"gn:id":8618245,"wk:page":"Laasi"},"wof:coterminous":[1713310373],"wof:country":"EE","wof:geomhash":"7dbe7f098f6991245d57ea5a904790d3","wof:hierarchy":[{"continent_id":102191581,"country_id":85633135,"county_id":1713305629,"localadmin_id":1713310373,"locality_id":1327234843,"region_id":85682989}],"wof:id":1327234843,"wof:lang_x_official":["est"],"wof:lang_x_spoken":["est"],"wof:lastmodified":1596670025,"wof:name":"Laasi","wof:parent_id":1713310373,"wof:placetype":"locality","wof:repo":"whosonfirst-data-admin-ee","wof:superseded_by":[],"wof:supersedes":[],"wof:tags":[]},"bbox":[22.32769,58.89523,22.32769,58.89523],"geometry":{"coordinates":[22.32769,58.89523],"type":"Point"}}