{"id":1226747901,"type":"Feature","properties":{"edtf:cessation":"uuuu","edtf:inception":"uuuu","geom:area":0,"geom:area_square_m":0,"geom:bbox":"25.51222,58.92667,25.51222,58.92667","geom:latitude":58.92667,"geom:longitude":25.51222,"gn:admin1_code":"4.0","gn:admin2_code":"834.0","gn:admin3_code":"7254.0","gn:asciiname":"Palivere","gn:country_code":"EE","gn:dem":75,"gn:feature_class":"P","gn:feature_code":"PPL","gn:geonameid":8618486,"gn:latitude":58.92667,"gn:longitude":25.51222,"gn:modification_date":"2017-11-25","gn:name":"Palivere","gn:population":0,"gn:timezone":"Europe/Tallinn","iso:country":"EE","lbl:bbox":"25.49222,58.90667,25.53222,58.94667","lbl:max_zoom":18,"lbl:min_zoom":13.5,"mz:hierarchy_label":1,"mz:is_current":1,"mz:min_zoom":12,"name:ceb_x_preferred":["Palivere"],"name:deu_x_preferred":["Palivere"],"name:est_x_preferred":["Palivere"],"name:fra_x_preferred":["Palivere"],"name:hye_x_preferred":["Պալիվեռե"],"name:pol_x_preferred":["Palivere"],"name:spa_x_preferred":["Palivere"],"name:swe_x_preferred":["Palivere"],"name:ukr_x_preferred":["Палівере"],"name:und_x_variant":["Pallifer"],"name:vol_x_preferred":["Palivere"],"src:geom":"geonames","wof:belongsto":[85683031,102191581,1713306691,85633135,1713305773],"wof:breaches":[],"wof:concordances":{"gn:id":8618486},"wof:country":"EE","wof:geomhash":"ba177d2151e0910fe8b1b4d304b66e4e","wof:hierarchy":[{"continent_id":102191581,"country_id":85633135,"county_id":1713305773,"localadmin_id":1713306691,"locality_id":1226747901,"region_id":85683031}],"wof:id":1226747901,"wof:lang_x_official":["est"],"wof:lang_x_spoken":["est"],"wof:lastmodified":1596677992,"wof:name":"Palivere","wof:parent_id":1713306691,"wof:placetype":"locality","wof:repo":"whosonfirst-data-admin-ee","wof:superseded_by":[],"wof:supersedes":[],"wof:tags":[]},"bbox":[25.51222,58.92667,25.51222,58.92667],"geometry":{"coordinates":[25.51222,58.92667],"type":"Point"}}