{"id":1225907471,"type":"Feature","properties":{"edtf:cessation":"uuuu","edtf:inception":"uuuu","geom:area":0,"geom:area_square_m":0,"geom:bbox":"27.09889,58.61556,27.09889,58.61556","geom:latitude":58.61556,"geom:longitude":27.09889,"gn:admin1_code":"18.0","gn:admin2_code":"586.0","gn:admin3_code":"5709.0","gn:asciiname":"Orgemaee","gn:country_code":"EE","gn:dem":64,"gn:feature_class":"P","gn:feature_code":"PPL","gn:geonameid":8618408,"gn:latitude":58.61556,"gn:longitude":27.09889,"gn:modification_date":"2017-11-25","gn:name":"Orgemäe","gn:population":0,"gn:timezone":"Europe/Tallinn","iso:country":"EE","lbl:bbox":"27.07889,58.59556,27.11889,58.63556","lbl:max_zoom":18,"lbl:min_zoom":13.5,"mz:hierarchy_label":1,"mz:is_current":1,"mz:min_zoom":12,"name:est_x_preferred":["Orgemäe"],"name:fra_x_preferred":["Orgemäe"],"name:hye_x_preferred":["Օռգեմյաե"],"name:pol_x_preferred":["Orgemäe"],"name:spa_x_preferred":["Orgemäe"],"name:ukr_x_preferred":["Орґемяе"],"name:und_x_variant":["Orgmäe"],"name:vol_x_preferred":["Orgemäe"],"src:geom":"geonames","wof:belongsto":[85682995,102191581,1713309505,85633135,1713305679],"wof:breaches":[],"wof:concordances":{"gn:id":8618408,"wk:page":"Orgem%C3%A4e"},"wof:coterminous":[1713309505],"wof:country":"EE","wof:geomhash":"0caa99308af20ca2c1acbd3022b790a6","wof:hierarchy":[{"continent_id":102191581,"country_id":85633135,"county_id":1713305679,"localadmin_id":1713309505,"locality_id":1225907471,"region_id":85682995}],"wof:id":1225907471,"wof:lang_x_official":["est"],"wof:lang_x_spoken":["est"],"wof:lastmodified":1596660910,"wof:name":"Orgemaee","wof:parent_id":1713309505,"wof:placetype":"locality","wof:repo":"whosonfirst-data-admin-ee","wof:superseded_by":[],"wof:supersedes":[],"wof:tags":[]},"bbox":[27.09889,58.61556,27.09889,58.61556],"geometry":{"coordinates":[27.09889,58.61556],"type":"Point"}}