{"id":1226428773,"type":"Feature","properties":{"edtf:cessation":"uuuu","edtf:inception":"uuuu","geom:area":0,"geom:area_square_m":0,"geom:bbox":"25.13639,59.0025,25.13639,59.0025","geom:latitude":59.0025,"geom:longitude":25.13639,"gn:admin1_code":"13.0","gn:admin2_code":"668.0","gn:admin3_code":"8279.0","gn:asciiname":"Viirika","gn:country_code":"EE","gn:dem":80,"gn:feature_class":"P","gn:feature_code":"PPL","gn:geonameid":587616,"gn:latitude":59.0025,"gn:longitude":25.13639,"gn:modification_date":"2017-11-25","gn:name":"Viirika","gn:population":0,"gn:timezone":"Europe/Tallinn","iso:country":"EE","lbl:bbox":"25.11639,58.9825,25.15639,59.0225","lbl:max_zoom":18,"lbl:min_zoom":13.5,"mz:hierarchy_label":1,"mz:is_current":1,"mz:min_zoom":12,"src:geom":"geonames","wof:belongsto":[85683013,102191581,1713311189,85633135,1713305711],"wof:breaches":[],"wof:concordances":{"gn:id":587616},"wof:country":"EE","wof:geomhash":"2053b11c522b4ab3e3b157a990f7300c","wof:hierarchy":[{"continent_id":102191581,"country_id":85633135,"county_id":1713305711,"localadmin_id":1713311189,"locality_id":1226428773,"region_id":85683013}],"wof:id":1226428773,"wof:lang_x_official":["est"],"wof:lang_x_spoken":["est"],"wof:lastmodified":1596676724,"wof:name":"Viirika","wof:parent_id":1713311189,"wof:placetype":"locality","wof:repo":"whosonfirst-data-admin-ee","wof:superseded_by":[],"wof:supersedes":[],"wof:tags":[]},"bbox":[25.13639,59.0025,25.13639,59.0025],"geometry":{"coordinates":[25.13639,59.0025],"type":"Point"}}