{"id":1276358563,"type":"Feature","properties":{"edtf:cessation":"uuuu","edtf:inception":"uuuu","geom:area":0,"geom:area_square_m":0,"geom:bbox":"26.23722,59.4125,26.23722,59.4125","geom:latitude":59.4125,"geom:longitude":26.23722,"gn:admin1_code":"8.0","gn:admin2_code":"191.0","gn:admin3_code":"4331.0","gn:asciiname":"Lihulope","gn:country_code":"EE","gn:dem":87,"gn:feature_class":"P","gn:feature_code":"PPL","gn:geonameid":793476,"gn:latitude":59.4125,"gn:longitude":26.23722,"gn:modification_date":"2017-11-25","gn:name":"Lihulõpe","gn:population":0,"gn:timezone":"Europe/Tallinn","iso:country":"EE","lbl:bbox":"26.21722,59.3925,26.25722,59.4325","lbl:max_zoom":18,"lbl:min_zoom":13.5,"mz:hierarchy_label":1,"mz:is_current":1,"mz:min_zoom":12,"name:est_x_preferred":["Lihulõpe"],"name:hye_x_preferred":["Լիհուլիպե"],"name:pol_x_preferred":["Lihulõpe"],"name:vol_x_preferred":["Lihulõpe"],"src:geom":"geonames","wof:belongsto":[85683049,102191581,1713314531,85633135,1713305775],"wof:breaches":[],"wof:concordances":{"gn:id":793476,"wk:page":"Lihul%C3%B5pe"},"wof:coterminous":[1713314531],"wof:country":"EE","wof:geomhash":"ca42bdd0e91c8a7fa50820110db74bd6","wof:hierarchy":[{"continent_id":102191581,"country_id":85633135,"county_id":1713305775,"localadmin_id":1713314531,"locality_id":1276358563,"region_id":85683049}],"wof:id":1276358563,"wof:lang_x_official":["est"],"wof:lang_x_spoken":["est"],"wof:lastmodified":1596678040,"wof:name":"Lihulope","wof:parent_id":1713314531,"wof:placetype":"locality","wof:repo":"whosonfirst-data-admin-ee","wof:superseded_by":[],"wof:supersedes":[],"wof:tags":[]},"bbox":[26.23722,59.4125,26.23722,59.4125],"geometry":{"coordinates":[26.23722,59.4125],"type":"Point"}}