{"id":1309715131,"type":"Feature","properties":{"edtf:cessation":"uuuu","edtf:inception":"uuuu","geom:area":0,"geom:area_square_m":0,"geom:bbox":"22.52351,58.99888,22.52351,58.99888","geom:latitude":58.99888,"geom:longitude":22.52351,"gn:admin1_code":"2.0","gn:admin2_code":"205.0","gn:admin3_code":"6908.0","gn:asciiname":"Reigi","gn:country_code":"EE","gn:dem":8,"gn:feature_class":"P","gn:feature_code":"PPL","gn:geonameid":589067,"gn:latitude":58.99888,"gn:longitude":22.52351,"gn:modification_date":"2017-11-25","gn:name":"Reigi","gn:population":0,"gn:timezone":"Europe/Tallinn","iso:country":"EE","lbl:bbox":"22.50351,58.97888,22.54351,59.01888","lbl:max_zoom":18,"lbl:min_zoom":13.5,"mz:hierarchy_label":1,"mz:is_current":1,"mz:min_zoom":12,"name:deu_x_preferred":["Reigi"],"name:est_x_preferred":["Reigi"],"name:hye_x_preferred":["Ռեիգի"],"name:nld_x_preferred":["Reigi"],"name:pol_x_preferred":["Reigi"],"name:spa_x_preferred":["Reigi"],"name:swe_x_preferred":["Röicks"],"name:swe_x_variant":["Dagö#Byar"],"name:und_x_variant":["Reyzhi","Roigi","Reygi"],"name:vol_x_preferred":["Reigi"],"src:geom":"geonames","wof:belongsto":[85682989,102191581,1713310603,85633135,1713305629],"wof:breaches":[],"wof:concordances":{"gn:id":589067,"wk:page":"Reigi"},"wof:coterminous":[1713310603],"wof:country":"EE","wof:geomhash":"f0ecf07a0466cb9105259242e6939c81","wof:hierarchy":[{"continent_id":102191581,"country_id":85633135,"county_id":1713305629,"localadmin_id":1713310603,"locality_id":1309715131,"region_id":85682989}],"wof:id":1309715131,"wof:lang_x_official":["est"],"wof:lang_x_spoken":["est"],"wof:lastmodified":1596670003,"wof:name":"Reigi","wof:parent_id":1713310603,"wof:placetype":"locality","wof:repo":"whosonfirst-data-admin-ee","wof:superseded_by":[],"wof:supersedes":[],"wof:tags":[]},"bbox":[22.52351,58.99888,22.52351,58.99888],"geometry":{"coordinates":[22.52351,58.99888],"type":"Point"}}