{"id":1209200929,"type":"Feature","properties":{"edtf:cessation":"uuuu","edtf:inception":"uuuu","geom:area":0,"geom:area_square_m":0,"geom:bbox":"25.08917,58.765,25.08917,58.765","geom:latitude":58.765,"geom:longitude":25.08917,"gn:admin1_code":"4.0","gn:admin2_code":"834.0","gn:admin3_code":"3600.0","gn:asciiname":"Maidemaa","gn:country_code":"EE","gn:dem":56,"gn:feature_class":"P","gn:feature_code":"PPL","gn:geonameid":8618181,"gn:latitude":58.765,"gn:longitude":25.08917,"gn:modification_date":"2017-11-25","gn:name":"Maidemaa","gn:population":0,"gn:timezone":"Europe/Tallinn","iso:country":"EE","lbl:bbox":"25.06917,58.745,25.10917,58.785","lbl:max_zoom":18,"lbl:min_zoom":13.5,"mz:hierarchy_label":1,"mz:is_current":1,"mz:min_zoom":12,"name:und_x_variant":["Kaseniidi"],"src:geom":"geonames","wof:belongsto":[85683031,102191581,1713313469,85633135,1713305773],"wof:breaches":[],"wof:concordances":{"gn:id":8618181},"wof:country":"EE","wof:geomhash":"42541c08937a0920378241c4615d2657","wof:hierarchy":[{"continent_id":102191581,"country_id":85633135,"county_id":1713305773,"localadmin_id":1713313469,"locality_id":1209200929,"region_id":85683031}],"wof:id":1209200929,"wof:lang_x_official":["est"],"wof:lang_x_spoken":["est"],"wof:lastmodified":1596677985,"wof:name":"Maidemaa","wof:parent_id":1713313469,"wof:placetype":"locality","wof:repo":"whosonfirst-data-admin-ee","wof:superseded_by":[],"wof:supersedes":[],"wof:tags":[]},"bbox":[25.08917,58.765,25.08917,58.765],"geometry":{"coordinates":[25.08917,58.765],"type":"Point"}}