{"id":1209928223,"type":"Feature","properties":{"edtf:cessation":"uuuu","edtf:inception":"uuuu","geom:area":0,"geom:area_square_m":0,"geom:bbox":"24.58138,59.25745,24.58138,59.25745","geom:latitude":59.25745,"geom:longitude":24.58138,"gn:admin1_code":"1.0","gn:admin2_code":"726.0","gn:admin3_code":"3439.0","gn:asciiname":"Voore","gn:country_code":"EE","gn:dem":47,"gn:feature_class":"P","gn:feature_code":"PPL","gn:geonameid":587466,"gn:latitude":59.25745,"gn:longitude":24.58138,"gn:modification_date":"2017-11-25","gn:name":"Voore","gn:population":0,"gn:timezone":"Europe/Tallinn","iso:country":"EE","lbl:bbox":"24.56138,59.23745,24.60138,59.27745","lbl:max_zoom":18,"lbl:min_zoom":13.5,"mz:hierarchy_label":1,"mz:is_current":1,"mz:min_zoom":12,"name:ceb_x_preferred":["Voore"],"name:est_x_preferred":["Voore"],"name:kat_x_preferred":["ვოორე"],"name:pol_x_preferred":["Voore"],"name:swe_x_preferred":["Voore"],"name:und_x_variant":["Myza Vore","Voore Asundus"],"src:geom":"geonames","wof:belongsto":[85683055,102191581,1713307973,85633135,1713305739],"wof:breaches":[],"wof:concordances":{"gn:id":587466},"wof:country":"EE","wof:geomhash":"e9e2dbec3b5e8b695f6a2e04d835660f","wof:hierarchy":[{"continent_id":102191581,"country_id":85633135,"county_id":1713305739,"localadmin_id":1713307973,"locality_id":1209928223,"region_id":85683055}],"wof:id":1209928223,"wof:lang_x_official":["est"],"wof:lang_x_spoken":["est"],"wof:lastmodified":1596663241,"wof:name":"Voore","wof:parent_id":1713307973,"wof:placetype":"locality","wof:repo":"whosonfirst-data-admin-ee","wof:superseded_by":[],"wof:supersedes":[],"wof:tags":[]},"bbox":[24.58138,59.25745,24.58138,59.25745],"geometry":{"coordinates":[24.58138,59.25745],"type":"Point"}}