{"id":1293097961,"type":"Feature","properties":{"edtf:cessation":"uuuu","edtf:inception":"uuuu","geom:area":0,"geom:area_square_m":0,"geom:bbox":"26.42444,58.745,26.42444,58.745","geom:latitude":58.745,"geom:longitude":26.42444,"gn:admin1_code":"5.0","gn:admin2_code":"247.0","gn:admin3_code":"1582.0","gn:asciiname":"Ellakvere","gn:country_code":"EE","gn:dem":73,"gn:feature_class":"P","gn:feature_code":"PPL","gn:geonameid":793326,"gn:latitude":58.745,"gn:longitude":26.42444,"gn:modification_date":"2017-11-25","gn:name":"Ellakvere","gn:population":0,"gn:timezone":"Europe/Tallinn","iso:country":"EE","lbl:bbox":"26.40444,58.725,26.44444,58.765","lbl:max_zoom":18,"lbl:min_zoom":13.5,"mz:hierarchy_label":1,"mz:is_current":1,"mz:min_zoom":12,"name:est_x_preferred":["Ellakvere"],"name:fra_x_preferred":["Ellakvere"],"name:hye_x_preferred":["Էլլակվեռե"],"name:spa_x_preferred":["Ellakvere"],"name:ukr_x_preferred":["Еллаквере"],"name:vol_x_preferred":["Ellakvere"],"src:geom":"geonames","wof:belongsto":[85683009,102191581,1713312237,85633135,1713305767],"wof:breaches":[],"wof:concordances":{"gn:id":793326,"wk:page":"Ellakvere"},"wof:coterminous":[1713312237],"wof:country":"EE","wof:geomhash":"7e9b225ecaa10f0768581236778a4e23","wof:hierarchy":[{"continent_id":102191581,"country_id":85633135,"county_id":1713305767,"localadmin_id":1713312237,"locality_id":1293097961,"region_id":85683009}],"wof:id":1293097961,"wof:lang_x_official":["est"],"wof:lang_x_spoken":["est"],"wof:lastmodified":1596676573,"wof:name":"Ellakvere","wof:parent_id":1713312237,"wof:placetype":"locality","wof:repo":"whosonfirst-data-admin-ee","wof:superseded_by":[],"wof:supersedes":[],"wof:tags":[]},"bbox":[26.42444,58.745,26.42444,58.745],"geometry":{"coordinates":[26.42444,58.745],"type":"Point"}}