{"id":1327339459,"type":"Feature","properties":{"edtf:cessation":"uuuu","edtf:inception":"uuuu","geom:area":0,"geom:area_square_m":0,"geom:bbox":"25.855,58.95861,25.855,58.95861","geom:latitude":58.95861,"geom:longitude":25.855,"gn:admin1_code":"4.0","gn:admin2_code":"255.0","gn:admin3_code":"3992.0","gn:asciiname":"Kueti","gn:country_code":"EE","gn:dem":87,"gn:feature_class":"P","gn:feature_code":"PPL","gn:geonameid":8618617,"gn:latitude":58.95861,"gn:longitude":25.855,"gn:modification_date":"2017-11-25","gn:name":"Küti","gn:population":0,"gn:timezone":"Europe/Tallinn","iso:country":"EE","lbl:bbox":"25.835,58.93861,25.875,58.97861","lbl:max_zoom":18,"lbl:min_zoom":13.5,"mz:hierarchy_label":1,"mz:is_current":1,"mz:min_zoom":12,"src:geom":"geonames","wof:belongsto":[85683031,102191581,1713306971,85633135,1713305765],"wof:breaches":[],"wof:concordances":{"gn:id":8618617},"wof:coterminous":[1713306971],"wof:country":"EE","wof:geomhash":"7185827314ff05e5c6f22962307dc61f","wof:hierarchy":[{"continent_id":102191581,"country_id":85633135,"county_id":1713305765,"localadmin_id":1713306971,"locality_id":1327339459,"region_id":85683031}],"wof:id":1327339459,"wof:lang_x_official":["est"],"wof:lang_x_spoken":["est"],"wof:lastmodified":1596676650,"wof:name":"Kueti","wof:parent_id":1713306971,"wof:placetype":"locality","wof:repo":"whosonfirst-data-admin-ee","wof:superseded_by":[],"wof:supersedes":[],"wof:tags":[]},"bbox":[25.855,58.95861,25.855,58.95861],"geometry":{"coordinates":[25.855,58.95861],"type":"Point"}}