{"id":1343785799,"type":"Feature","properties":{"edtf:cessation":"uuuu","edtf:inception":"uuuu","geom:area":0,"geom:area_square_m":0,"geom:bbox":"25.58972,58.86889,25.58972,58.86889","geom:latitude":58.86889,"geom:longitude":25.58972,"gn:admin1_code":"4.0","gn:admin2_code":"567.0","gn:admin3_code":"5317.0","gn:asciiname":"Muendi","gn:country_code":"EE","gn:dem":67,"gn:feature_class":"P","gn:feature_code":"PPL","gn:geonameid":590119,"gn:latitude":58.86889,"gn:longitude":25.58972,"gn:modification_date":"2017-11-25","gn:name":"Mündi","gn:population":0,"gn:timezone":"Europe/Tallinn","iso:country":"EE","lbl:bbox":"25.56972,58.84889,25.60972,58.88889","lbl:max_zoom":18,"lbl:min_zoom":13.5,"mz:hierarchy_label":1,"mz:is_current":1,"mz:min_zoom":12,"name:est_x_preferred":["Mündi"],"name:hye_x_preferred":["Մյունդի"],"name:pol_x_preferred":["Mündi"],"name:ukr_x_preferred":["Мюнді"],"name:und_x_variant":["Myza Mundi"],"name:vol_x_preferred":["Mündi"],"src:geom":"geonames","wof:belongsto":[85683031,102191581,1713308297,85633135,1713305663],"wof:breaches":[],"wof:concordances":{"gn:id":590119,"wk:page":"M%C3%BCndi"},"wof:coterminous":[1713308297],"wof:country":"EE","wof:geomhash":"52b837a086725ed046193c0aeae28191","wof:hierarchy":[{"continent_id":102191581,"country_id":85633135,"county_id":1713305663,"localadmin_id":1713308297,"locality_id":1343785799,"region_id":85683031}],"wof:id":1343785799,"wof:lang_x_official":["est"],"wof:lang_x_spoken":["est"],"wof:lastmodified":1596661326,"wof:name":"Muendi","wof:parent_id":1713308297,"wof:placetype":"locality","wof:repo":"whosonfirst-data-admin-ee","wof:superseded_by":[],"wof:supersedes":[],"wof:tags":[]},"bbox":[25.58972,58.86889,25.58972,58.86889],"geometry":{"coordinates":[25.58972,58.86889],"type":"Point"}}