{"id":1226663773,"type":"Feature","properties":{"edtf:cessation":"uuuu","edtf:inception":"uuuu","geom:area":0,"geom:area_square_m":0,"geom:bbox":"25.25333,59.19472,25.25333,59.19472","geom:latitude":59.19472,"geom:longitude":25.25333,"gn:admin1_code":"1.0","gn:admin2_code":"338.0","gn:admin3_code":"5962.0","gn:asciiname":"Maardu","gn:country_code":"EE","gn:dem":78,"gn:feature_class":"P","gn:feature_code":"PPL","gn:geonameid":590449,"gn:latitude":59.19472,"gn:longitude":25.25333,"gn:modification_date":"2017-11-25","gn:name":"Maardu","gn:population":0,"gn:timezone":"Europe/Tallinn","iso:country":"EE","lbl:bbox":"25.23333,59.17472,25.27333,59.21472","lbl:max_zoom":18,"lbl:min_zoom":13.5,"mz:hierarchy_label":1,"mz:is_current":1,"mz:min_zoom":12,"name:aze_x_preferred":["Maardu"],"name:bel_x_preferred":["Маарду"],"name:bul_x_preferred":["Маарду"],"name:ceb_x_preferred":["Maardu"],"name:ces_x_preferred":["Maardu"],"name:dan_x_preferred":["Maardu"],"name:deu_x_preferred":["Maardu"],"name:epo_x_preferred":["Maardu"],"name:est_x_preferred":["Maardu"],"name:fas_x_preferred":["ماردو"],"name:fin_x_preferred":["Maardu"],"name:fra_x_preferred":["Maardu"],"name:haw_x_preferred":["Maardu"],"name:hrv_x_preferred":["Maardu"],"name:hsb_x_preferred":["Maardu"],"name:hun_x_preferred":["Maardu"],"name:hye_x_preferred":["Մաառդու"],"name:ita_x_preferred":["Maardu"],"name:jpn_x_preferred":["マールドゥ"],"name:kat_x_preferred":["მაარდუ"],"name:kor_x_preferred":["마르두"],"name:lav_x_preferred":["Mārdu"],"name:lit_x_preferred":["Mardu"],"name:mkd_x_preferred":["Марду"],"name:mrj_x_preferred":["Маарду"],"name:msa_x_preferred":["Maardu"],"name:myv_x_preferred":["Маарду ош"],"name:nld_x_preferred":["Maardu"],"name:nno_x_preferred":["Maardu"],"name:nor_x_preferred":["Maardu"],"name:pol_x_preferred":["Maardu"],"name:por_x_preferred":["Maardu"],"name:ron_x_preferred":["Maardu"],"name:rus_x_preferred":["Маарду"],"name:slk_x_preferred":["Maardu"],"name:spa_x_preferred":["Maardu"],"name:srp_x_preferred":["Марду"],"name:swe_x_preferred":["Maardu"],"name:tat_x_preferred":["Маарду"],"name:tur_x_preferred":["Maardu"],"name:ukr_x_preferred":["Маарду"],"name:urd_x_preferred":["مارڈو"],"name:vep_x_preferred":["Maardu"],"name:vol_x_preferred":["Maardu"],"name:zho_x_preferred":["馬爾杜"],"src:geom":"geonames","wof:belongsto":[85683055,102191581,1713306301,85633135,1713305665],"wof:breaches":[],"wof:concordances":{"gn:id":590449},"wof:country":"EE","wof:geomhash":"eb8975e8cdad160886b9ad2f4e7cba26","wof:hierarchy":[{"continent_id":102191581,"country_id":85633135,"county_id":1713305665,"localadmin_id":1713306301,"locality_id":1226663773,"region_id":85683055}],"wof:id":1226663773,"wof:lang_x_official":["est"],"wof:lang_x_spoken":["est"],"wof:lastmodified":1596661349,"wof:name":"Maardu","wof:parent_id":1713306301,"wof:placetype":"locality","wof:repo":"whosonfirst-data-admin-ee","wof:superseded_by":[],"wof:supersedes":[],"wof:tags":[]},"bbox":[25.25333,59.19472,25.25333,59.19472],"geometry":{"coordinates":[25.25333,59.19472],"type":"Point"}}