{"id":1209902441,"type":"Feature","properties":{"edtf:cessation":"uuuu","edtf:inception":"uuuu","geom:area":0,"geom:area_square_m":0,"geom:bbox":"24.19278,58.98972,24.19278,58.98972","geom:latitude":58.98972,"geom:longitude":24.19278,"gn:admin1_code":"13.0","gn:admin2_code":"503.0","gn:admin3_code":"4200.0","gn:asciiname":"Leevre","gn:cc2":"EE","gn:country_code":"EE","gn:dem":49,"gn:feature_class":"P","gn:feature_code":"PPL","gn:geonameid":590729,"gn:latitude":58.98972,"gn:longitude":24.19278,"gn:modification_date":"2017-11-25","gn:name":"Leevre","gn:population":0,"gn:timezone":"Europe/Tallinn","iso:country":"EE","lbl:bbox":"24.17278,58.96972,24.21278,59.00972","lbl:max_zoom":18,"lbl:min_zoom":13.5,"mz:hierarchy_label":1,"mz:is_current":1,"mz:min_zoom":12,"name:est_x_preferred":["Leevre"],"name:fra_x_preferred":["Leevre"],"name:hye_x_preferred":["Լեևռե"],"name:pol_x_preferred":["Leevre"],"name:sco_x_preferred":["Leevre"],"name:spa_x_preferred":["Leevre"],"name:und_x_variant":["Leevri","Levre"],"name:vol_x_preferred":["Leevre"],"src:geom":"geonames","wof:belongsto":[85683013,102191581,1713314829,85633135,1713305747],"wof:breaches":[],"wof:concordances":{"gn:id":590729,"wk:page":"Leevre"},"wof:coterminous":[1713314829],"wof:country":"EE","wof:geomhash":"e4d5521b7d09ac752563bb7136e2e1d9","wof:hierarchy":[{"continent_id":102191581,"country_id":85633135,"county_id":1713305747,"localadmin_id":1713314829,"locality_id":1209902441,"region_id":85683013}],"wof:id":1209902441,"wof:lang_x_official":["est"],"wof:lang_x_spoken":["est"],"wof:lastmodified":1596662836,"wof:name":"Leevre","wof:parent_id":1713314829,"wof:placetype":"locality","wof:repo":"whosonfirst-data-admin-ee","wof:superseded_by":[],"wof:supersedes":[],"wof:tags":[]},"bbox":[24.19278,58.98972,24.19278,58.98972],"geometry":{"coordinates":[24.19278,58.98972],"type":"Point"}}