{"id":1293213215,"type":"Feature","properties":{"edtf:cessation":"uuuu","edtf:inception":"uuuu","geom:area":0,"geom:area_square_m":0,"geom:bbox":"22.52361,58.73167,22.52361,58.73167","geom:latitude":58.73167,"geom:longitude":22.52361,"gn:admin1_code":"2.0","gn:admin2_code":"205.0","gn:admin3_code":"3978.0","gn:asciiname":"Kabuna","gn:country_code":"EE","gn:dem":11,"gn:feature_class":"P","gn:feature_code":"PPL","gn:geonameid":591801,"gn:latitude":58.73167,"gn:longitude":22.52361,"gn:modification_date":"2017-11-25","gn:name":"Kabuna","gn:population":0,"gn:timezone":"Europe/Tallinn","iso:country":"EE","lbl:bbox":"22.50361,58.71167,22.54361,58.75167","lbl:max_zoom":18,"lbl:min_zoom":13.5,"mz:hierarchy_label":1,"mz:is_current":1,"mz:min_zoom":12,"name:deu_x_preferred":["Kabuna"],"name:est_x_preferred":["Kabuna"],"name:fra_x_preferred":["Kabuna"],"name:hye_x_preferred":["Կաբունա"],"name:pol_x_preferred":["Kabuna"],"name:spa_x_preferred":["Kabuna"],"name:vol_x_preferred":["Kabuna"],"src:geom":"geonames","wof:belongsto":[85682989,102191581,1713310743,85633135,1713305629],"wof:breaches":[],"wof:concordances":{"gn:id":591801,"wk:page":"Kabuna"},"wof:coterminous":[1713310251],"wof:country":"EE","wof:geomhash":"a7985228fe3d368ddfa1901227211ded","wof:hierarchy":[{"continent_id":102191581,"country_id":85633135,"county_id":1713305629,"localadmin_id":1713310743,"locality_id":1293213215,"region_id":85682989}],"wof:id":1293213215,"wof:lang_x_official":["est"],"wof:lang_x_spoken":["est"],"wof:lastmodified":1596670014,"wof:name":"Kabuna","wof:parent_id":1713310743,"wof:placetype":"locality","wof:repo":"whosonfirst-data-admin-ee","wof:superseded_by":[],"wof:supersedes":[],"wof:tags":[]},"bbox":[22.52361,58.73167,22.52361,58.73167],"geometry":{"coordinates":[22.52361,58.73167],"type":"Point"}}