{"id":1259558759,"type":"Feature","properties":{"edtf:cessation":"uuuu","edtf:inception":"uuuu","geom:area":0,"geom:area_square_m":0,"geom:bbox":"26.55028,57.9725,26.55028,57.9725","geom:latitude":57.9725,"geom:longitude":26.55028,"gn:admin1_code":"19.0","gn:admin2_code":"557.0","gn:admin3_code":"3286.0","gn:asciiname":"Koigu","gn:cc2":"EE","gn:country_code":"EE","gn:dem":143,"gn:feature_class":"P","gn:feature_code":"PPL","gn:geonameid":591244,"gn:latitude":57.9725,"gn:longitude":26.55028,"gn:modification_date":"2017-11-25","gn:name":"Koigu","gn:population":0,"gn:timezone":"Europe/Tallinn","iso:country":"EE","lbl:bbox":"26.53028,57.9525,26.57028,57.9925","lbl:max_zoom":18,"lbl:min_zoom":13.5,"mz:hierarchy_label":1,"mz:is_current":1,"mz:min_zoom":12,"name:est_x_preferred":["Koigu"],"name:hye_x_preferred":["Կոիգու"],"name:pol_x_preferred":["Koigu"],"name:spa_x_preferred":["Koigu"],"name:ukr_x_preferred":["Койґу"],"name:und_x_variant":["Koygu","Koigu Asundus"],"name:vol_x_preferred":["Koigu"],"src:geom":"geonames","wof:belongsto":[85682941,102191581,1713312993,85633135,1713305759],"wof:breaches":[],"wof:concordances":{"gn:id":591244,"wk:page":"Koigu%2C_Valga_County"},"wof:coterminous":[1713312993],"wof:country":"EE","wof:geomhash":"3e81453c7593f890a6dbe33b3cee2068","wof:hierarchy":[{"continent_id":102191581,"country_id":85633135,"county_id":1713305759,"localadmin_id":1713312993,"locality_id":1259558759,"region_id":85682941}],"wof:id":1259558759,"wof:lang_x_official":["est"],"wof:lang_x_spoken":["est"],"wof:lastmodified":1596661873,"wof:name":"Koigu","wof:parent_id":1713312993,"wof:placetype":"locality","wof:repo":"whosonfirst-data-admin-ee","wof:superseded_by":[],"wof:supersedes":[],"wof:tags":[]},"bbox":[26.55028,57.9725,26.55028,57.9725],"geometry":{"coordinates":[26.55028,57.9725],"type":"Point"}}