{"id":1243568669,"type":"Feature","properties":{"edtf:cessation":"uuuu","edtf:inception":"uuuu","geom:area":0,"geom:area_square_m":0,"geom:bbox":"24.04306,59.21556,24.04306,59.21556","geom:latitude":59.21556,"geom:longitude":24.04306,"gn:admin1_code":"1.0","gn:admin2_code":"431.0","gn:admin3_code":"3762.0","gn:asciiname":"Kommaste","gn:cc2":"EE","gn:country_code":"EE","gn:dem":23,"gn:feature_class":"P","gn:feature_code":"PPL","gn:geonameid":591191,"gn:latitude":59.21556,"gn:longitude":24.04306,"gn:modification_date":"2017-11-25","gn:name":"Kõmmaste","gn:population":0,"gn:timezone":"Europe/Tallinn","iso:country":"EE","lbl:bbox":"24.02306,59.19556,24.06306,59.23556","lbl:max_zoom":18,"lbl:min_zoom":13.5,"mz:hierarchy_label":1,"mz:is_current":1,"mz:min_zoom":12,"name:est_x_preferred":["Kõmmaste"],"name:fra_x_preferred":["Kõmmaste"],"name:hye_x_preferred":["Կիմմաստե"],"name:pol_x_preferred":["Kõmmaste"],"name:spa_x_preferred":["Kõmmaste"],"name:ukr_x_preferred":["Киммасте"],"name:und_x_variant":["Kymaste","Kõmaste"],"name:vol_x_preferred":["Kõmmaste"],"src:geom":"geonames","wof:belongsto":[85683055,102191581,1713307767,85633135,1713305737],"wof:breaches":[],"wof:concordances":{"gn:id":591191,"wk:page":"K%C3%B5mmaste"},"wof:coterminous":[1713307767],"wof:country":"EE","wof:geomhash":"6cf2a4836c81786e0afd05fede198e44","wof:hierarchy":[{"continent_id":102191581,"country_id":85633135,"county_id":1713305737,"localadmin_id":1713307767,"locality_id":1243568669,"region_id":85683055}],"wof:id":1243568669,"wof:lang_x_official":["est"],"wof:lang_x_spoken":["est"],"wof:lastmodified":1596663328,"wof:name":"Kommaste","wof:parent_id":1713307767,"wof:placetype":"locality","wof:repo":"whosonfirst-data-admin-ee","wof:superseded_by":[],"wof:supersedes":[],"wof:tags":[]},"bbox":[24.04306,59.21556,24.04306,59.21556],"geometry":{"coordinates":[24.04306,59.21556],"type":"Point"}}