{"id":1327495911,"type":"Feature","properties":{"edtf:cessation":"uuuu","edtf:inception":"uuuu","geom:area":0,"geom:area_square_m":0,"geom:bbox":"25.97278,58.0375,25.97278,58.0375","geom:latitude":58.0375,"geom:longitude":25.97278,"gn:admin1_code":"19.0","gn:admin2_code":"824.0","gn:admin3_code":"7113.0","gn:asciiname":"Rulli","gn:country_code":"EE","gn:dem":42,"gn:feature_class":"P","gn:feature_code":"PPL","gn:geonameid":588929,"gn:latitude":58.0375,"gn:longitude":25.97278,"gn:modification_date":"2017-11-25","gn:name":"Rulli","gn:population":0,"gn:timezone":"Europe/Tallinn","iso:country":"EE","lbl:bbox":"25.95278,58.0175,25.99278,58.0575","lbl:max_zoom":18,"lbl:min_zoom":13.5,"mz:hierarchy_label":1,"mz:is_current":1,"mz:min_zoom":12,"name:est_x_preferred":["Rulli"],"name:hye_x_preferred":["Ռուլլի"],"name:pol_x_preferred":["Rulli"],"name:spa_x_preferred":["Rulli"],"name:ukr_x_preferred":["Руллі"],"name:vol_x_preferred":["Rulli"],"src:geom":"geonames","wof:belongsto":[85682941,102191581,1713310403,85633135,1713305687],"wof:breaches":[],"wof:concordances":{"gn:id":588929,"wk:page":"Rulli"},"wof:coterminous":[1713310403],"wof:country":"EE","wof:geomhash":"8af042dbfeb0a552c08f4117ae4a9bbd","wof:hierarchy":[{"continent_id":102191581,"country_id":85633135,"county_id":1713305687,"localadmin_id":1713310403,"locality_id":1327495911,"region_id":85682941}],"wof:id":1327495911,"wof:lang_x_official":["est"],"wof:lang_x_spoken":["est"],"wof:lastmodified":1596661439,"wof:name":"Rulli","wof:parent_id":1713310403,"wof:placetype":"locality","wof:repo":"whosonfirst-data-admin-ee","wof:superseded_by":[],"wof:supersedes":[],"wof:tags":[]},"bbox":[25.97278,58.0375,25.97278,58.0375],"geometry":{"coordinates":[25.97278,58.0375],"type":"Point"}}