{"id":1344263279,"type":"Feature","properties":{"edtf:cessation":"uuuu","edtf:inception":"uuuu","geom:area":0,"geom:area_square_m":0,"geom:bbox":"25.60694,59.02417,25.60694,59.02417","geom:latitude":59.02417,"geom:longitude":25.60694,"gn:admin1_code":"4.0","gn:admin2_code":"567.0","gn:admin3_code":"7889.0","gn:asciiname":"Someru","gn:country_code":"EE","gn:dem":79,"gn:feature_class":"P","gn:feature_code":"PPL","gn:geonameid":588633,"gn:latitude":59.02417,"gn:longitude":25.60694,"gn:modification_date":"2017-11-25","gn:name":"Sõmeru","gn:population":0,"gn:timezone":"Europe/Tallinn","iso:country":"EE","lbl:bbox":"25.58694,59.00417,25.62694,59.04417","lbl:max_zoom":18,"lbl:min_zoom":13.5,"mz:hierarchy_label":1,"mz:is_current":1,"mz:min_zoom":12,"name:und_x_variant":["Symeru","Sõmeru"],"src:geom":"geonames","wof:belongsto":[85683031,102191581,1713308149,85633135,1713305663],"wof:breaches":[],"wof:concordances":{"gn:id":588633},"wof:coterminous":[1713308149],"wof:country":"EE","wof:geomhash":"3fd9b7b412a3c7b79253b0687a0f9958","wof:hierarchy":[{"continent_id":102191581,"country_id":85633135,"county_id":1713305663,"localadmin_id":1713308149,"locality_id":1344263279,"region_id":85683031}],"wof:id":1344263279,"wof:lang_x_official":["est"],"wof:lang_x_spoken":["est"],"wof:lastmodified":1596661330,"wof:name":"Someru","wof:parent_id":1713308149,"wof:placetype":"locality","wof:repo":"whosonfirst-data-admin-ee","wof:superseded_by":[],"wof:supersedes":[],"wof:tags":[]},"bbox":[25.60694,59.02417,25.60694,59.02417],"geometry":{"coordinates":[25.60694,59.02417],"type":"Point"}}