{"id":1225908651,"type":"Feature","properties":{"edtf:cessation":"uuuu","edtf:inception":"uuuu","geom:area":0,"geom:area_square_m":0,"geom:bbox":"26.9225,57.78278,26.9225,57.78278","geom:latitude":57.78278,"geom:longitude":26.9225,"gn:admin1_code":"21.0","gn:admin2_code":"917.0","gn:admin3_code":"8994.0","gn:asciiname":"Lompka","gn:country_code":"EE","gn:dem":111,"gn:feature_class":"P","gn:feature_code":"PPL","gn:geonameid":794329,"gn:latitude":57.78278,"gn:longitude":26.9225,"gn:modification_date":"2017-11-25","gn:name":"Lompka","gn:population":0,"gn:timezone":"Europe/Tallinn","iso:country":"EE","lbl:bbox":"26.9025,57.76278,26.9425,57.80278","lbl:max_zoom":18,"lbl:min_zoom":13.5,"mz:hierarchy_label":1,"mz:is_current":1,"mz:min_zoom":12,"name:est_x_preferred":["Lompka"],"name:hye_x_preferred":["Լոմպկա"],"name:pol_x_preferred":["Lompka"],"name:spa_x_preferred":["Lompka"],"name:ukr_x_preferred":["Ломпка"],"name:vol_x_preferred":["Lompka"],"src:geom":"geonames","wof:belongsto":[85682937,102191581,1713315635,85633135,1713305633],"wof:breaches":[],"wof:concordances":{"gn:id":794329,"wk:page":"Lompka"},"wof:coterminous":[1713316471],"wof:country":"EE","wof:geomhash":"832687d77e36bca9eb28d1b1e4a15a5b","wof:hierarchy":[{"continent_id":102191581,"country_id":85633135,"county_id":1713305633,"localadmin_id":1713315635,"locality_id":1225908651,"region_id":85682937}],"wof:id":1225908651,"wof:lang_x_official":["est"],"wof:lang_x_spoken":["est"],"wof:lastmodified":1596660404,"wof:name":"Lompka","wof:parent_id":1713315635,"wof:placetype":"locality","wof:repo":"whosonfirst-data-admin-ee","wof:superseded_by":[],"wof:supersedes":[],"wof:tags":[]},"bbox":[26.9225,57.78278,26.9225,57.78278],"geometry":{"coordinates":[26.9225,57.78278],"type":"Point"}}