{"id":1293293101,"type":"Feature","properties":{"edtf:cessation":"uuuu","edtf:inception":"uuuu","geom:area":0,"geom:area_square_m":0,"geom:bbox":"26.13639,58.93167,26.13639,58.93167","geom:latitude":58.93167,"geom:longitude":26.13639,"gn:admin1_code":"4.0","gn:admin2_code":"255.0","gn:admin3_code":"6360.0","gn:asciiname":"Preedi","gn:country_code":"EE","gn:dem":92,"gn:feature_class":"P","gn:feature_code":"PPL","gn:geonameid":793303,"gn:latitude":58.93167,"gn:longitude":26.13639,"gn:modification_date":"2017-11-25","gn:name":"Preedi","gn:population":0,"gn:timezone":"Europe/Tallinn","iso:country":"EE","lbl:bbox":"26.11639,58.91167,26.15639,58.95167","lbl:max_zoom":18,"lbl:min_zoom":13.5,"mz:hierarchy_label":1,"mz:is_current":1,"mz:min_zoom":12,"name:est_x_preferred":["Preedi"],"name:hye_x_preferred":["Պռեեդի"],"name:pol_x_preferred":["Preedi"],"name:spa_x_preferred":["Preedi"],"name:ukr_x_preferred":["Прееді"],"name:vol_x_preferred":["Preedi"],"src:geom":"geonames","wof:belongsto":[85683031,102191581,1713313357,85633135,1713305765],"wof:breaches":[],"wof:concordances":{"gn:id":793303,"wk:page":"Preedi"},"wof:coterminous":[1713313357],"wof:country":"EE","wof:geomhash":"645ea7d0e5df8b813c1525aa8f35904a","wof:hierarchy":[{"continent_id":102191581,"country_id":85633135,"county_id":1713305765,"localadmin_id":1713313357,"locality_id":1293293101,"region_id":85683031}],"wof:id":1293293101,"wof:lang_x_official":["est"],"wof:lang_x_spoken":["est"],"wof:lastmodified":1596676648,"wof:name":"Preedi","wof:parent_id":1713313357,"wof:placetype":"locality","wof:repo":"whosonfirst-data-admin-ee","wof:superseded_by":[],"wof:supersedes":[],"wof:tags":[]},"bbox":[26.13639,58.93167,26.13639,58.93167],"geometry":{"coordinates":[26.13639,58.93167],"type":"Point"}}