{"id":1276527403,"type":"Feature","properties":{"edtf:cessation":"uuuu","edtf:inception":"uuuu","geom:area":0,"geom:area_square_m":0,"geom:bbox":"25.03917,58.86472,25.03917,58.86472","geom:latitude":58.86472,"geom:longitude":25.03917,"gn:admin1_code":"13.0","gn:admin2_code":"293.0","gn:admin3_code":"2835.0","gn:asciiname":"Asunduse","gn:country_code":"EE","gn:dem":68,"gn:feature_class":"P","gn:feature_code":"PPL","gn:geonameid":8619465,"gn:latitude":58.86472,"gn:longitude":25.03917,"gn:modification_date":"2017-11-25","gn:name":"Asunduse","gn:population":0,"gn:timezone":"Europe/Tallinn","iso:country":"EE","lbl:bbox":"25.01917,58.84472,25.05917,58.88472","lbl:max_zoom":18,"lbl:min_zoom":13.5,"mz:hierarchy_label":1,"mz:is_current":1,"mz:min_zoom":12,"src:geom":"geonames","wof:belongsto":[85683013,102191581,1713313429,85633135,1713305713],"wof:breaches":[],"wof:concordances":{"gn:id":8619465},"wof:country":"EE","wof:geomhash":"5383760a2559832e3e46a24aae98b38e","wof:hierarchy":[{"continent_id":102191581,"country_id":85633135,"county_id":1713305713,"localadmin_id":1713313429,"locality_id":1276527403,"region_id":85683013}],"wof:id":1276527403,"wof:lang_x_official":["est"],"wof:lang_x_spoken":["est"],"wof:lastmodified":1596676747,"wof:name":"Asunduse","wof:parent_id":1713313429,"wof:placetype":"locality","wof:repo":"whosonfirst-data-admin-ee","wof:superseded_by":[],"wof:supersedes":[],"wof:tags":[]},"bbox":[25.03917,58.86472,25.03917,58.86472],"geometry":{"coordinates":[25.03917,58.86472],"type":"Point"}}