{"id":1125935023,"type":"Feature","properties":{"edtf:cessation":"uuuu","edtf:inception":"uuuu","geom:area":0,"geom:area_square_m":0,"geom:bbox":"25.52333,58.58194,25.52333,58.58194","geom:latitude":58.58194,"geom:longitude":25.52333,"gn:country":"EE","gn:fcode":"PPL","gn:population":120,"iso:country":"EE","lbl:bbox":"25.50333,58.56194,25.54333,58.60194","lbl:latitude":58.58194,"lbl:longitude":25.52333,"lbl:max_zoom":18,"lbl:min_zoom":13,"mz:hierarchy_label":1,"mz:is_current":1,"mz:min_zoom":11,"mz:note":"Quattroshapes Point Gazetteer import 20170519","name:ceb_x_preferred":["Navesti"],"name:eng_x_preferred":["Navesti"],"name:est_x_preferred":["Navesti"],"name:hye_x_preferred":["Նավեստի"],"name:nld_x_preferred":["Navesti"],"name:pol_x_preferred":["Navesti"],"name:spa_x_preferred":["Navesti"],"name:swe_x_preferred":["Navesti"],"name:ukr_x_preferred":["Навесті"],"name:und_x_variant":["Navesti Asundus"],"name:vol_x_preferred":["Navesti"],"qs_pg:aaroncc":"EE","qs_pg:gn_country":"EE","qs_pg:gn_fcode":"PPL","qs_pg:gn_id":590017,"qs_pg:gn_pop":120,"qs_pg:name":"Navesti","qs_pg:name_adm0":"Eesti","qs_pg:name_adm1":"Viljandimaa","qs_pg:photos_9r":0,"qs_pg:photos_sr":0,"qs_pg:pop_sr":1,"qs_pg:qs_id":1274203,"qs_pg:qs_pg_placetype":"locality","qs_pg:qs_pg_placetype_gp":"Town","qs_pg:woe_adm0":23424805,"qs_pg:woe_id":844224,"src:geom":"qs_pg","src:lbl_centroid":"qs_pg","src:population":"geonames","woe:adm0_id":23424805,"woe:name_adm0":"Eesti","woe:name_adm1":"Viljandimaa","woe:placetype":"Town","wof:belongsto":[85682985,102191581,1713311801,85633135,1713305735],"wof:breaches":[],"wof:concordances":{"gn:id":590017,"gp:id":844224,"qs_pg:id":1274203,"wd:id":"Q3465779"},"wof:coterminous":[1713311801],"wof:country":"EE","wof:created":1497296938,"wof:geomhash":"25cd668942eab2bed4f2d6d40fd08763","wof:hierarchy":[{"continent_id":102191581,"country_id":85633135,"county_id":1713305735,"localadmin_id":1713311801,"locality_id":1125935023,"region_id":85682985}],"wof:id":1125935023,"wof:lang_x_official":["est"],"wof:lang_x_spoken":["est"],"wof:lastmodified":1596663460,"wof:name":"Navesti","wof:parent_id":1713311801,"wof:placetype":"locality","wof:population":120,"wof:population_rank":1,"wof:repo":"whosonfirst-data-admin-ee","wof:superseded_by":[],"wof:supersedes":[],"wof:tags":[]},"bbox":[25.52333,58.58194,25.52333,58.58194],"geometry":{"coordinates":[25.52333,58.58194],"type":"Point"}}