{"id":1327400177,"type":"Feature","properties":{"edtf:cessation":"uuuu","edtf:inception":"uuuu","geom:area":0,"geom:area_square_m":0,"geom:bbox":"26.39806,58.20417,26.39806,58.20417","geom:latitude":58.20417,"geom:longitude":26.39806,"gn:admin1_code":"18.0","gn:admin2_code":"171.0","gn:admin3_code":"2622.0","gn:asciiname":"Leivaste","gn:country_code":"EE","gn:dem":65,"gn:feature_class":"P","gn:feature_code":"PPL","gn:geonameid":8620801,"gn:latitude":58.20417,"gn:longitude":26.39806,"gn:modification_date":"2017-11-25","gn:name":"Leivaste","gn:population":0,"gn:timezone":"Europe/Tallinn","iso:country":"EE","lbl:bbox":"26.37806,58.18417,26.41806,58.22417","lbl:max_zoom":18,"lbl:min_zoom":13.5,"mz:hierarchy_label":1,"mz:is_current":1,"mz:min_zoom":12,"name:und_x_variant":["Lapetukma"],"src:geom":"geonames","wof:belongsto":[85682995,102191581,1713310627,85633135,1713305757],"wof:breaches":[],"wof:concordances":{"gn:id":8620801},"wof:country":"EE","wof:geomhash":"df1129eac3b0d6d94d9aec91e20d389c","wof:hierarchy":[{"continent_id":102191581,"country_id":85633135,"county_id":1713305757,"localadmin_id":1713310627,"locality_id":1327400177,"region_id":85682995}],"wof:id":1327400177,"wof:lang_x_official":["est"],"wof:lang_x_spoken":["est"],"wof:lastmodified":1596661920,"wof:name":"Leivaste","wof:parent_id":1713310627,"wof:placetype":"locality","wof:repo":"whosonfirst-data-admin-ee","wof:superseded_by":[],"wof:supersedes":[],"wof:tags":[]},"bbox":[26.39806,58.20417,26.39806,58.20417],"geometry":{"coordinates":[26.39806,58.20417],"type":"Point"}}