{"id":1210012067,"type":"Feature","properties":{"edtf:cessation":"uuuu","edtf:inception":"uuuu","geom:area":0,"geom:area_square_m":0,"geom:bbox":"25.82639,59.50889,25.82639,59.50889","geom:latitude":59.50889,"geom:longitude":25.82639,"gn:admin1_code":"1.0","gn:admin2_code":"353.0","gn:admin3_code":"2194.0","gn:asciiname":"Joaveski","gn:country_code":"EE","gn:dem":58,"gn:feature_class":"P","gn:feature_code":"PPL","gn:geonameid":591934,"gn:latitude":59.50889,"gn:longitude":25.82639,"gn:modification_date":"2017-11-25","gn:name":"Joaveski","gn:population":0,"gn:timezone":"Europe/Tallinn","iso:country":"EE","lbl:bbox":"25.80639,59.48889,25.84639,59.52889","lbl:max_zoom":18,"lbl:min_zoom":13.5,"mz:hierarchy_label":1,"mz:is_current":1,"mz:min_zoom":12,"name:est_x_preferred":["Joaveski"],"name:fra_x_preferred":["Joaveski"],"name:hye_x_preferred":["Յոավեսկի"],"name:nld_x_preferred":["Joaveski"],"name:pol_x_preferred":["Joaveski"],"name:rus_x_preferred":["Йоавески"],"name:spa_x_preferred":["Joaveski"],"name:vol_x_preferred":["Joaveski"],"src:geom":"geonames","wof:belongsto":[85683055,102191581,1713313799,85633135,1713305725],"wof:breaches":[],"wof:concordances":{"gn:id":591934,"wk:page":"Joaveski"},"wof:coterminous":[1713313799],"wof:country":"EE","wof:geomhash":"5ddacb36c507fe17b0d471bb9903f627","wof:hierarchy":[{"continent_id":102191581,"country_id":85633135,"county_id":1713305725,"localadmin_id":1713313799,"locality_id":1210012067,"region_id":85683055}],"wof:id":1210012067,"wof:lang_x_official":["est"],"wof:lang_x_spoken":["est"],"wof:lastmodified":1596661841,"wof:name":"Joaveski","wof:parent_id":1713313799,"wof:placetype":"locality","wof:repo":"whosonfirst-data-admin-ee","wof:superseded_by":[],"wof:supersedes":[],"wof:tags":[]},"bbox":[25.82639,59.50889,25.82639,59.50889],"geometry":{"coordinates":[25.82639,59.50889],"type":"Point"}}