{"id":1259497435,"type":"Feature","properties":{"edtf:cessation":"uuuu","edtf:inception":"uuuu","geom:area":0,"geom:area_square_m":0,"geom:bbox":"25.76306,59.30306,25.76306,59.30306","geom:latitude":59.30306,"geom:longitude":25.76306,"gn:admin1_code":"1.0","gn:admin2_code":"141.0","gn:admin3_code":"6254.0","gn:asciiname":"Pruunakorve","gn:country_code":"EE","gn:dem":89,"gn:feature_class":"P","gn:feature_code":"PPL","gn:geonameid":589331,"gn:latitude":59.30306,"gn:longitude":25.76306,"gn:modification_date":"2017-11-25","gn:name":"Pruunakõrve","gn:population":0,"gn:timezone":"Europe/Tallinn","iso:country":"EE","lbl:bbox":"25.74306,59.28306,25.78306,59.32306","lbl:max_zoom":18,"lbl:min_zoom":13.5,"mz:hierarchy_label":1,"mz:is_current":1,"mz:min_zoom":12,"name:und_x_variant":["Prunakyrve","Pruunakõrve"],"src:geom":"geonames","wof:belongsto":[85683055,102191581,1713314585,85633135,1713305749],"wof:breaches":[],"wof:concordances":{"gn:id":589331},"wof:country":"EE","wof:geomhash":"b3e00ec2c17c8adfa2e900bfc93c32c8","wof:hierarchy":[{"continent_id":102191581,"country_id":85633135,"county_id":1713305749,"localadmin_id":1713314585,"locality_id":1259497435,"region_id":85683055}],"wof:id":1259497435,"wof:lang_x_official":["est"],"wof:lang_x_spoken":["est"],"wof:lastmodified":1596662797,"wof:name":"Pruunakorve","wof:parent_id":1713314585,"wof:placetype":"locality","wof:repo":"whosonfirst-data-admin-ee","wof:superseded_by":[],"wof:supersedes":[],"wof:tags":[]},"bbox":[25.76306,59.30306,25.76306,59.30306],"geometry":{"coordinates":[25.76306,59.30306],"type":"Point"}}