{"id":1259507485,"type":"Feature","properties":{"edtf:cessation":"uuuu","edtf:inception":"uuuu","geom:area":0,"geom:area_square_m":0,"geom:bbox":"25.47472,58.91889,25.47472,58.91889","geom:latitude":58.91889,"geom:longitude":25.47472,"gn:admin1_code":"4.0","gn:admin2_code":"834.0","gn:admin3_code":"7254.0","gn:asciiname":"Venevere","gn:country_code":"EE","gn:dem":69,"gn:feature_class":"P","gn:feature_code":"PPL","gn:geonameid":587674,"gn:latitude":58.91889,"gn:longitude":25.47472,"gn:modification_date":"2017-11-25","gn:name":"Venevere","gn:population":0,"gn:timezone":"Europe/Tallinn","iso:country":"EE","lbl:bbox":"25.45472,58.89889,25.49472,58.93889","lbl:max_zoom":18,"lbl:min_zoom":13.5,"mz:hierarchy_label":1,"mz:is_current":1,"mz:min_zoom":12,"src:geom":"geonames","wof:belongsto":[85683031,102191581,1713306691,85633135,1713305773],"wof:breaches":[],"wof:concordances":{"gn:id":587674},"wof:country":"EE","wof:geomhash":"913fd7fc23d5f07242a4ad83c982df77","wof:hierarchy":[{"continent_id":102191581,"country_id":85633135,"county_id":1713305773,"localadmin_id":1713306691,"locality_id":1259507485,"region_id":85683031}],"wof:id":1259507485,"wof:lang_x_official":["est"],"wof:lang_x_spoken":["est"],"wof:lastmodified":1596677986,"wof:name":"Venevere","wof:parent_id":1713306691,"wof:placetype":"locality","wof:repo":"whosonfirst-data-admin-ee","wof:superseded_by":[],"wof:supersedes":[],"wof:tags":[]},"bbox":[25.47472,58.91889,25.47472,58.91889],"geometry":{"coordinates":[25.47472,58.91889],"type":"Point"}}