{"id":1243163789,"type":"Feature","properties":{"edtf:cessation":"uuuu","edtf:inception":"uuuu","geom:area":0,"geom:area_square_m":0,"geom:bbox":"23.73472,58.97556,23.73472,58.97556","geom:latitude":58.97556,"geom:longitude":23.73472,"gn:admin1_code":"7.0","gn:admin2_code":"441.0","gn:admin3_code":"3247.0","gn:asciiname":"Kopli","gn:country_code":"EE","gn:dem":18,"gn:feature_class":"P","gn:feature_code":"PPL","gn:geonameid":8619400,"gn:latitude":58.97556,"gn:longitude":23.73472,"gn:modification_date":"2017-11-25","gn:name":"Kopli","gn:population":0,"gn:timezone":"Europe/Tallinn","iso:country":"EE","lbl:bbox":"23.71472,58.95556,23.75472,58.99556","lbl:max_zoom":18,"lbl:min_zoom":13.5,"mz:hierarchy_label":1,"mz:is_current":1,"mz:min_zoom":12,"name:ces_x_preferred":["Kopli"],"name:est_x_preferred":["Kopli"],"name:fas_x_preferred":["کوپلی"],"name:fin_x_preferred":["Kopli"],"name:fra_x_preferred":["Kopli"],"name:lit_x_preferred":["Kopli"],"name:nld_x_preferred":["Kopli"],"name:pol_x_preferred":["Kopli"],"name:rus_x_preferred":["Копли"],"name:spa_x_preferred":["Kopli"],"name:swe_x_preferred":["Kopli"],"src:geom":"geonames","wof:belongsto":[85683001,102191581,1713308777,85633135,1713305701],"wof:breaches":[],"wof:concordances":{"gn:id":8619400},"wof:country":"EE","wof:geomhash":"60af2882cc466cd3c57bce8321d0bfcd","wof:hierarchy":[{"continent_id":102191581,"country_id":85633135,"county_id":1713305701,"localadmin_id":1713308777,"locality_id":1243163789,"region_id":85683001}],"wof:id":1243163789,"wof:lang_x_official":["est"],"wof:lang_x_spoken":["est"],"wof:lastmodified":1596677440,"wof:name":"Kopli","wof:parent_id":1713308777,"wof:placetype":"locality","wof:repo":"whosonfirst-data-admin-ee","wof:superseded_by":[],"wof:supersedes":[],"wof:tags":[]},"bbox":[23.73472,58.97556,23.73472,58.97556],"geometry":{"coordinates":[23.73472,58.97556],"type":"Point"}}