{"id":1310466693,"type":"Feature","properties":{"edtf:cessation":"uuuu","edtf:inception":"uuuu","geom:area":0,"geom:area_square_m":0,"geom:bbox":"25.62806,58.53222,25.62806,58.53222","geom:latitude":58.53222,"geom:longitude":25.62806,"gn:admin1_code":"20.0","gn:admin2_code":"615.0","gn:admin3_code":"3690.0","gn:asciiname":"Kurnuvere","gn:country_code":"EE","gn:dem":50,"gn:feature_class":"P","gn:feature_code":"PPL","gn:geonameid":590916,"gn:latitude":58.53222,"gn:longitude":25.62806,"gn:modification_date":"2017-11-25","gn:name":"Kurnuvere","gn:population":0,"gn:timezone":"Europe/Tallinn","iso:country":"EE","lbl:bbox":"25.60806,58.51222,25.64806,58.55222","lbl:max_zoom":18,"lbl:min_zoom":13.5,"mz:hierarchy_label":1,"mz:is_current":1,"mz:min_zoom":12,"src:geom":"geonames","wof:belongsto":[85682985,102191581,1713311945,85633135,1713305735],"wof:breaches":[],"wof:concordances":{"gn:id":590916},"wof:coterminous":[1713311945],"wof:country":"EE","wof:geomhash":"76b9e1ef756099ccccdf0fb1a8444ce5","wof:hierarchy":[{"continent_id":102191581,"country_id":85633135,"county_id":1713305735,"localadmin_id":1713311945,"locality_id":1310466693,"region_id":85682985}],"wof:id":1310466693,"wof:lang_x_official":["est"],"wof:lang_x_spoken":["est"],"wof:lastmodified":1596663457,"wof:name":"Kurnuvere","wof:parent_id":1713311945,"wof:placetype":"locality","wof:repo":"whosonfirst-data-admin-ee","wof:superseded_by":[],"wof:supersedes":[],"wof:tags":[]},"bbox":[25.62806,58.53222,25.62806,58.53222],"geometry":{"coordinates":[25.62806,58.53222],"type":"Point"}}