{"id":1310120143,"type":"Feature","properties":{"edtf:cessation":"uuuu","edtf:inception":"uuuu","geom:area":0,"geom:area_square_m":0,"geom:bbox":"24.02667,59.28278,24.02667,59.28278","geom:latitude":59.28278,"geom:longitude":24.02667,"gn:admin1_code":"1.0","gn:admin2_code":"431.0","gn:admin3_code":"3682.0","gn:asciiname":"Kurkse","gn:cc2":"EE","gn:country_code":"EE","gn:dem":7,"gn:feature_class":"P","gn:feature_code":"PPL","gn:geonameid":590920,"gn:latitude":59.28278,"gn:longitude":24.02667,"gn:modification_date":"2018-06-22","gn:name":"Kurkse","gn:population":0,"gn:timezone":"Europe/Tallinn","iso:country":"EE","lbl:bbox":"24.00667,59.26278,24.04667,59.30278","lbl:max_zoom":18,"lbl:min_zoom":13.5,"mz:hierarchy_label":1,"mz:is_current":1,"mz:min_zoom":12,"name:eng_x_preferred":["Kurkse"],"name:est_x_preferred":["Kurkse"],"name:fra_x_preferred":["Kurkse"],"name:hye_x_preferred":["Կուռկսե"],"name:pol_x_preferred":["Kurkse"],"name:rus_x_preferred":["Курксе"],"name:spa_x_preferred":["Kurkse"],"name:swe_x_preferred":["Korkis"],"name:swe_x_variant":["Padis#Byar"],"name:ukr_x_preferred":["Курксе"],"name:und_x_variant":["Kurks","Kurksi"],"name:vol_x_preferred":["Kurkse"],"src:geom":"geonames","wof:belongsto":[85683055,102191581,1713307827,85633135,1713305737],"wof:breaches":[],"wof:concordances":{"gn:id":590920,"wk:page":"Kurkse"},"wof:coterminous":[1713307827],"wof:country":"EE","wof:geomhash":"d4655542c4bdfd4a2548d1c47b2e4db7","wof:hierarchy":[{"continent_id":102191581,"country_id":85633135,"county_id":1713305737,"localadmin_id":1713307827,"locality_id":1310120143,"region_id":85683055}],"wof:id":1310120143,"wof:lang_x_official":["est"],"wof:lang_x_spoken":["est"],"wof:lastmodified":1596663322,"wof:name":"Kurkse","wof:parent_id":1713307827,"wof:placetype":"locality","wof:repo":"whosonfirst-data-admin-ee","wof:superseded_by":[],"wof:supersedes":[],"wof:tags":[]},"bbox":[24.02667,59.28278,24.02667,59.28278],"geometry":{"coordinates":[24.02667,59.28278],"type":"Point"}}