{"id":1343878231,"type":"Feature","properties":{"edtf:cessation":"uuuu","edtf:inception":"uuuu","geom:area":0,"geom:area_square_m":0,"geom:bbox":"25.72139,59.22583,25.72139,59.22583","geom:latitude":59.22583,"geom:longitude":25.72139,"gn:admin1_code":"8.0","gn:admin2_code":"792.0","gn:admin3_code":"6847.0","gn:asciiname":"Raudla","gn:country_code":"EE","gn:dem":83,"gn:feature_class":"P","gn:feature_code":"PPL","gn:geonameid":589097,"gn:latitude":59.22583,"gn:longitude":25.72139,"gn:modification_date":"2017-11-25","gn:name":"Raudla","gn:population":0,"gn:timezone":"Europe/Tallinn","iso:country":"EE","lbl:bbox":"25.70139,59.20583,25.74139,59.24583","lbl:max_zoom":18,"lbl:min_zoom":13.5,"mz:hierarchy_label":1,"mz:is_current":1,"mz:min_zoom":12,"name:est_x_preferred":["Raudla"],"name:hye_x_preferred":["Ռաուդլա"],"name:ukr_x_preferred":["Раудла"],"name:vol_x_preferred":["Raudla"],"src:geom":"geonames","wof:belongsto":[85683049,102191581,1713308231,85633135,1713305761],"wof:breaches":[],"wof:concordances":{"gn:id":589097,"wk:page":"Raudla"},"wof:coterminous":[1713308231],"wof:country":"EE","wof:geomhash":"f19ef088164f9efebd5f5e644e5ba0a7","wof:hierarchy":[{"continent_id":102191581,"country_id":85633135,"county_id":1713305761,"localadmin_id":1713308231,"locality_id":1343878231,"region_id":85683049}],"wof:id":1343878231,"wof:lang_x_official":["est"],"wof:lang_x_spoken":["est"],"wof:lastmodified":1596676606,"wof:name":"Raudla","wof:parent_id":1713308231,"wof:placetype":"locality","wof:repo":"whosonfirst-data-admin-ee","wof:superseded_by":[],"wof:supersedes":[],"wof:tags":[]},"bbox":[25.72139,59.22583,25.72139,59.22583],"geometry":{"coordinates":[25.72139,59.22583],"type":"Point"}}