{"id":1344236989,"type":"Feature","properties":{"edtf:cessation":"uuuu","edtf:inception":"uuuu","geom:area":0,"geom:area_square_m":0,"geom:bbox":"27.75528,57.87722,27.75528,57.87722","geom:latitude":57.87722,"geom:longitude":27.75528,"gn:admin1_code":"21.0","gn:admin2_code":"732.0","gn:admin3_code":"3609.0","gn:asciiname":"Saabolda","gn:cc2":"EE","gn:country_code":"EE","gn:dem":54,"gn:feature_class":"P","gn:feature_code":"PPL","gn:geonameid":588859,"gn:latitude":57.87722,"gn:longitude":27.75528,"gn:modification_date":"2017-11-25","gn:name":"Saabolda","gn:population":0,"gn:timezone":"Europe/Tallinn","iso:country":"EE","lbl:bbox":"27.73528,57.85722,27.77528,57.89722","lbl:max_zoom":18,"lbl:min_zoom":13.5,"mz:hierarchy_label":1,"mz:is_current":1,"mz:min_zoom":12,"name:eng_x_preferred":["Saabolda"],"name:est_x_preferred":["Saabolda"],"name:hye_x_preferred":["Սաաբոլդա"],"name:pol_x_preferred":["Saabolda"],"name:rus_x_preferred":["Саоболда"],"name:sco_x_preferred":["Saabolda"],"name:spa_x_preferred":["Saabolda"],"name:ukr_x_preferred":["Сааболда"],"name:und_x_variant":["Zabolda","Sabolda"],"name:urd_x_preferred":["سابولڈا"],"name:vol_x_preferred":["Saabolda"],"src:geom":"geonames","wof:belongsto":[85682955,102191581,1713315995,85633135,1713305631],"wof:breaches":[],"wof:concordances":{"gn:id":588859,"wk:page":"Saabolda"},"wof:coterminous":[1713315971],"wof:country":"EE","wof:geomhash":"6a17dad608f49cae01f6c8cd8b2dbd8a","wof:hierarchy":[{"continent_id":102191581,"country_id":85633135,"county_id":1713305631,"localadmin_id":1713315995,"locality_id":1344236989,"region_id":85682955}],"wof:id":1344236989,"wof:lang_x_official":["est"],"wof:lang_x_spoken":["est"],"wof:lastmodified":1596663709,"wof:name":"Saabolda","wof:parent_id":1713315995,"wof:placetype":"locality","wof:repo":"whosonfirst-data-admin-ee","wof:superseded_by":[],"wof:supersedes":[],"wof:tags":[]},"bbox":[27.75528,57.87722,27.75528,57.87722],"geometry":{"coordinates":[27.75528,57.87722],"type":"Point"}}