{"id":1326894881,"type":"Feature","properties":{"edtf:cessation":"uuuu","edtf:inception":"uuuu","geom:area":0,"geom:area_square_m":0,"geom:bbox":"26.49778,57.93139,26.49778,57.93139","geom:latitude":57.93139,"geom:longitude":26.49778,"gn:admin1_code":"21.0","gn:admin2_code":"142.0","gn:admin3_code":"9414.0","gn:asciiname":"Visela","gn:country_code":"EE","gn:dem":90,"gn:feature_class":"P","gn:feature_code":"PPL","gn:geonameid":8619971,"gn:latitude":57.93139,"gn:longitude":26.49778,"gn:modification_date":"2017-11-25","gn:name":"Visela","gn:population":0,"gn:timezone":"Europe/Tallinn","iso:country":"EE","lbl:bbox":"26.47778,57.91139,26.51778,57.95139","lbl:max_zoom":18,"lbl:min_zoom":13.5,"mz:hierarchy_label":1,"mz:is_current":1,"mz:min_zoom":12,"name:und_x_variant":["Viselä"],"src:geom":"geonames","wof:belongsto":[85682937,102191581,1713313619,85633135,1713305795],"wof:breaches":[],"wof:concordances":{"gn:id":8619971},"wof:coterminous":[1713313619],"wof:country":"EE","wof:geomhash":"100ffb01c78a0e021e17edc3d354b6aa","wof:hierarchy":[{"continent_id":102191581,"country_id":85633135,"county_id":1713305795,"localadmin_id":1713313619,"locality_id":1326894881,"region_id":85682937}],"wof:id":1326894881,"wof:lang_x_official":["est"],"wof:lang_x_spoken":["est"],"wof:lastmodified":1596677024,"wof:name":"Visela","wof:parent_id":1713313619,"wof:placetype":"locality","wof:repo":"whosonfirst-data-admin-ee","wof:superseded_by":[],"wof:supersedes":[],"wof:tags":[]},"bbox":[26.49778,57.93139,26.49778,57.93139],"geometry":{"coordinates":[26.49778,57.93139],"type":"Point"}}