{"id":1292921241,"type":"Feature","properties":{"edtf:cessation":"uuuu","edtf:inception":"uuuu","geom:area":0,"geom:area_square_m":0,"geom:bbox":"24.15778,59.16972,24.15778,59.16972","geom:latitude":59.16972,"geom:longitude":24.15778,"gn:admin1_code":"1.0","gn:admin2_code":"431.0","gn:admin3_code":"3224.0","gn:asciiname":"Kobru","gn:country_code":"EE","gn:dem":39,"gn:feature_class":"P","gn:feature_code":"PPL","gn:geonameid":591295,"gn:latitude":59.16972,"gn:longitude":24.15778,"gn:modification_date":"2017-11-25","gn:name":"Kobru","gn:population":0,"gn:timezone":"Europe/Tallinn","iso:country":"EE","lbl:bbox":"24.13778,59.14972,24.17778,59.18972","lbl:max_zoom":18,"lbl:min_zoom":13.5,"mz:hierarchy_label":1,"mz:is_current":1,"mz:min_zoom":12,"name:est_x_preferred":["Kobru"],"name:fra_x_preferred":["Kobru"],"name:hye_x_preferred":["Կոբռու"],"name:pol_x_preferred":["Kobru"],"name:spa_x_preferred":["Kobru"],"name:ukr_x_preferred":["Кобру"],"name:vol_x_preferred":["Kobru"],"src:geom":"geonames","wof:belongsto":[85683055,102191581,1713314707,85633135,1713305737],"wof:breaches":[],"wof:concordances":{"gn:id":591295,"wk:page":"Kobru"},"wof:coterminous":[1713314707],"wof:country":"EE","wof:geomhash":"bebf49902c224d9a0a1f03ce76eadd82","wof:hierarchy":[{"continent_id":102191581,"country_id":85633135,"county_id":1713305737,"localadmin_id":1713314707,"locality_id":1292921241,"region_id":85683055}],"wof:id":1292921241,"wof:lang_x_official":["est"],"wof:lang_x_spoken":["est"],"wof:lastmodified":1596663324,"wof:name":"Kobru","wof:parent_id":1713314707,"wof:placetype":"locality","wof:repo":"whosonfirst-data-admin-ee","wof:superseded_by":[],"wof:supersedes":[],"wof:tags":[]},"bbox":[24.15778,59.16972,24.15778,59.16972],"geometry":{"coordinates":[24.15778,59.16972],"type":"Point"}}