{"id":1125957301,"type":"Feature","properties":{"edtf:cessation":"uuuu","edtf:inception":"uuuu","geom:area":0,"geom:area_square_m":0,"geom:bbox":"26.03333,59.0975,26.03333,59.0975","geom:latitude":59.0975,"geom:longitude":26.03333,"gn:country":"EE","gn:fcode":"PPL","gn:population":401,"iso:country":"EE","lbl:bbox":"26.01333,59.0775,26.05333,59.1175","lbl:latitude":59.0975,"lbl:longitude":26.03333,"lbl:max_zoom":17,"lbl:min_zoom":12.5,"mz:hierarchy_label":1,"mz:is_current":1,"mz:min_zoom":11,"mz:note":"Quattroshapes Point Gazetteer import 20170519","name:ceb_x_preferred":["Vajangu"],"name:eng_x_preferred":["Vajangu"],"name:est_x_preferred":["Vajangu"],"name:hye_x_preferred":["Վայանգու"],"name:nld_x_preferred":["Vajangu"],"name:swe_x_preferred":["Vajangu"],"name:ukr_x_preferred":["Ваянґу"],"name:und_x_variant":["Vayangu"],"name:vol_x_preferred":["Vajangu"],"qs_pg:aaroncc":"EE","qs_pg:gn_country":"EE","qs_pg:gn_fcode":"PPL","qs_pg:gn_id":587887,"qs_pg:gn_pop":401,"qs_pg:name":"Vajangu","qs_pg:name_adm0":"Eesti","qs_pg:name_adm1":"Lääne-Virumaa","qs_pg:photos_9r":0,"qs_pg:photos_sr":0,"qs_pg:pop_sr":2,"qs_pg:qs_id":406467,"qs_pg:qs_pg_placetype":"locality","qs_pg:qs_pg_placetype_gp":"Town","qs_pg:woe_adm0":23424805,"qs_pg:woe_id":846210,"src:geom":"qs_pg","src:lbl_centroid":"qs_pg","src:population":"geonames","woe:adm0_id":23424805,"woe:name_adm0":"Eesti","woe:name_adm1":"Lääne-Virumaa","woe:placetype":"Town","wof:belongsto":[85683049,102191581,1713314651,85633135,1713305761],"wof:breaches":[],"wof:concordances":{"gn:id":587887,"gp:id":846210,"qs_pg:id":406467,"wd:id":"Q3462691"},"wof:coterminous":[1713308335],"wof:country":"EE","wof:created":1497297662,"wof:geomhash":"684d0b3473059aa0f79f0e76fac5785d","wof:hierarchy":[{"continent_id":102191581,"country_id":85633135,"county_id":1713305761,"localadmin_id":1713314651,"locality_id":1125957301,"region_id":85683049}],"wof:id":1125957301,"wof:lang_x_official":["est"],"wof:lang_x_spoken":["est"],"wof:lastmodified":1596676606,"wof:name":"Vajangu","wof:parent_id":1713314651,"wof:placetype":"locality","wof:population":401,"wof:population_rank":2,"wof:repo":"whosonfirst-data-admin-ee","wof:superseded_by":[],"wof:supersedes":[],"wof:tags":[]},"bbox":[26.03333,59.0975,26.03333,59.0975],"geometry":{"coordinates":[26.03333,59.0975],"type":"Point"}}