{"id":1326650083,"type":"Feature","properties":{"edtf:cessation":"uuuu","edtf:inception":"uuuu","geom:area":0,"geom:area_square_m":0,"geom:bbox":"26.21056,59.42972,26.21056,59.42972","geom:latitude":59.42972,"geom:longitude":26.21056,"gn:admin1_code":"8.0","gn:admin2_code":"191.0","gn:admin3_code":"4331.0","gn:asciiname":"Arukuela","gn:country_code":"EE","gn:dem":87,"gn:feature_class":"P","gn:feature_code":"PPL","gn:geonameid":8619615,"gn:latitude":59.42972,"gn:longitude":26.21056,"gn:modification_date":"2017-11-25","gn:name":"Aruküla","gn:population":0,"gn:timezone":"Europe/Tallinn","iso:country":"EE","lbl:bbox":"26.19056,59.40972,26.23056,59.44972","lbl:max_zoom":18,"lbl:min_zoom":13.5,"mz:hierarchy_label":1,"mz:is_current":1,"mz:min_zoom":12,"src:geom":"geonames","wof:belongsto":[85683049,102191581,1713314531,85633135,1713305775],"wof:breaches":[],"wof:concordances":{"gn:id":8619615},"wof:country":"EE","wof:geomhash":"5c0e6ad85608470e37a08c79bc5480f9","wof:hierarchy":[{"continent_id":102191581,"country_id":85633135,"county_id":1713305775,"localadmin_id":1713314531,"locality_id":1326650083,"region_id":85683049}],"wof:id":1326650083,"wof:lang_x_official":["est"],"wof:lang_x_spoken":["est"],"wof:lastmodified":1596678042,"wof:name":"Arukuela","wof:parent_id":1713314531,"wof:placetype":"locality","wof:repo":"whosonfirst-data-admin-ee","wof:superseded_by":[],"wof:supersedes":[],"wof:tags":[]},"bbox":[26.21056,59.42972,26.21056,59.42972],"geometry":{"coordinates":[26.21056,59.42972],"type":"Point"}}